Compiled from "BuildDependencyGenerator.java"
public class org.antlr.v4.tool.BuildDependencyGenerator {
  protected org.antlr.v4.Tool tool;

  protected org.antlr.v4.tool.Grammar g;

  protected org.antlr.v4.codegen.CodeGenerator generator;

  protected org.stringtemplate.v4.STGroup templates;

  public org.antlr.v4.tool.BuildDependencyGenerator(org.antlr.v4.Tool, org.antlr.v4.tool.Grammar);
    Code:
       0: aload_0
       1: invokespecial #1                  // Method java/lang/Object."<init>":()V
       4: aload_0
       5: aload_1
       6: putfield      #2                  // Field tool:Lorg/antlr/v4/Tool;
       9: aload_0
      10: aload_2
      11: putfield      #3                  // Field g:Lorg/antlr/v4/tool/Grammar;
      14: aload_2
      15: ldc           #4                  // String language
      17: invokevirtual #5                  // Method org/antlr/v4/tool/Grammar.getOptionString:(Ljava/lang/String;)Ljava/lang/String;
      20: astore_3
      21: aload_0
      22: new           #6                  // class org/antlr/v4/codegen/CodeGenerator
      25: dup
      26: aload_1
      27: aload_2
      28: aload_3
      29: invokespecial #7                  // Method org/antlr/v4/codegen/CodeGenerator."<init>":(Lorg/antlr/v4/Tool;Lorg/antlr/v4/tool/Grammar;Ljava/lang/String;)V
      32: putfield      #8                  // Field generator:Lorg/antlr/v4/codegen/CodeGenerator;
      35: return

  public java.util.List<java.io.File> getGeneratedFileList();
    Code:
       0: new           #9                  // class java/util/ArrayList
       3: dup
       4: invokespecial #10                 // Method java/util/ArrayList."<init>":()V
       7: astore_1
       8: aload_0
       9: getfield      #8                  // Field generator:Lorg/antlr/v4/codegen/CodeGenerator;
      12: invokevirtual #11                 // Method org/antlr/v4/codegen/CodeGenerator.getTarget:()Lorg/antlr/v4/codegen/Target;
      15: invokevirtual #12                 // Method org/antlr/v4/codegen/Target.needsHeader:()Z
      18: ifeq          40
      21: aload_1
      22: aload_0
      23: aload_0
      24: getfield      #8                  // Field generator:Lorg/antlr/v4/codegen/CodeGenerator;
      27: iconst_1
      28: invokevirtual #13                 // Method org/antlr/v4/codegen/CodeGenerator.getRecognizerFileName:(Z)Ljava/lang/String;
      31: invokevirtual #14                 // Method getOutputFile:(Ljava/lang/String;)Ljava/io/File;
      34: invokeinterface #15,  2           // InterfaceMethod java/util/List.add:(Ljava/lang/Object;)Z
      39: pop
      40: aload_1
      41: aload_0
      42: aload_0
      43: getfield      #8                  // Field generator:Lorg/antlr/v4/codegen/CodeGenerator;
      46: iconst_0
      47: invokevirtual #13                 // Method org/antlr/v4/codegen/CodeGenerator.getRecognizerFileName:(Z)Ljava/lang/String;
      50: invokevirtual #14                 // Method getOutputFile:(Ljava/lang/String;)Ljava/io/File;
      53: invokeinterface #15,  2           // InterfaceMethod java/util/List.add:(Ljava/lang/Object;)Z
      58: pop
      59: aload_1
      60: aload_0
      61: aload_0
      62: getfield      #8                  // Field generator:Lorg/antlr/v4/codegen/CodeGenerator;
      65: invokevirtual #16                 // Method org/antlr/v4/codegen/CodeGenerator.getVocabFileName:()Ljava/lang/String;
      68: invokevirtual #14                 // Method getOutputFile:(Ljava/lang/String;)Ljava/io/File;
      71: invokeinterface #15,  2           // InterfaceMethod java/util/List.add:(Ljava/lang/Object;)Z
      76: pop
      77: aconst_null
      78: astore_2
      79: aload_0
      80: getfield      #8                  // Field generator:Lorg/antlr/v4/codegen/CodeGenerator;
      83: invokevirtual #17                 // Method org/antlr/v4/codegen/CodeGenerator.getTemplates:()Lorg/stringtemplate/v4/STGroup;
      86: ldc           #18                 // String codeFileExtension
      88: invokevirtual #19                 // Method org/stringtemplate/v4/STGroup.getInstanceOf:(Ljava/lang/String;)Lorg/stringtemplate/v4/ST;
      91: astore_3
      92: aload_0
      93: getfield      #8                  // Field generator:Lorg/antlr/v4/codegen/CodeGenerator;
      96: invokevirtual #17                 // Method org/antlr/v4/codegen/CodeGenerator.getTemplates:()Lorg/stringtemplate/v4/STGroup;
      99: ldc           #20                 // String headerFile
     101: invokevirtual #21                 // Method org/stringtemplate/v4/STGroup.isDefined:(Ljava/lang/String;)Z
     104: ifeq          179
     107: aload_0
     108: getfield      #8                  // Field generator:Lorg/antlr/v4/codegen/CodeGenerator;
     111: invokevirtual #17                 // Method org/antlr/v4/codegen/CodeGenerator.getTemplates:()Lorg/stringtemplate/v4/STGroup;
     114: ldc           #22                 // String headerFileExtension
     116: invokevirtual #19                 // Method org/stringtemplate/v4/STGroup.getInstanceOf:(Ljava/lang/String;)Lorg/stringtemplate/v4/ST;
     119: astore_2
     120: aload_0
     121: getfield      #3                  // Field g:Lorg/antlr/v4/tool/Grammar;
     124: invokevirtual #23                 // Method org/antlr/v4/tool/Grammar.getType:()I
     127: invokestatic  #24                 // Method org/antlr/v4/tool/Grammar.getGrammarTypeToFileNameSuffix:(I)Ljava/lang/String;
     130: astore        4
     132: new           #25                 // class java/lang/StringBuilder
     135: dup
     136: invokespecial #26                 // Method java/lang/StringBuilder."<init>":()V
     139: aload_0
     140: getfield      #3                  // Field g:Lorg/antlr/v4/tool/Grammar;
     143: getfield      #27                 // Field org/antlr/v4/tool/Grammar.name:Ljava/lang/String;
     146: invokevirtual #28                 // Method java/lang/StringBuilder.append:(Ljava/lang/String;)Ljava/lang/StringBuilder;
     149: aload         4
     151: invokevirtual #28                 // Method java/lang/StringBuilder.append:(Ljava/lang/String;)Ljava/lang/StringBuilder;
     154: aload_2
     155: invokevirtual #29                 // Method org/stringtemplate/v4/ST.render:()Ljava/lang/String;
     158: invokevirtual #28                 // Method java/lang/StringBuilder.append:(Ljava/lang/String;)Ljava/lang/StringBuilder;
     161: invokevirtual #30                 // Method java/lang/StringBuilder.toString:()Ljava/lang/String;
     164: astore        5
     166: aload_1
     167: aload_0
     168: aload         5
     170: invokevirtual #14                 // Method getOutputFile:(Ljava/lang/String;)Ljava/io/File;
     173: invokeinterface #15,  2           // InterfaceMethod java/util/List.add:(Ljava/lang/Object;)Z
     178: pop
     179: aload_0
     180: getfield      #3                  // Field g:Lorg/antlr/v4/tool/Grammar;
     183: invokevirtual #31                 // Method org/antlr/v4/tool/Grammar.isCombined:()Z
     186: ifeq          339
     189: bipush        31
     191: invokestatic  #24                 // Method org/antlr/v4/tool/Grammar.getGrammarTypeToFileNameSuffix:(I)Ljava/lang/String;
     194: astore        4
     196: new           #25                 // class java/lang/StringBuilder
     199: dup
     200: invokespecial #26                 // Method java/lang/StringBuilder."<init>":()V
     203: aload_0
     204: getfield      #3                  // Field g:Lorg/antlr/v4/tool/Grammar;
     207: getfield      #27                 // Field org/antlr/v4/tool/Grammar.name:Ljava/lang/String;
     210: invokevirtual #28                 // Method java/lang/StringBuilder.append:(Ljava/lang/String;)Ljava/lang/StringBuilder;
     213: aload         4
     215: invokevirtual #28                 // Method java/lang/StringBuilder.append:(Ljava/lang/String;)Ljava/lang/StringBuilder;
     218: aload_3
     219: invokevirtual #29                 // Method org/stringtemplate/v4/ST.render:()Ljava/lang/String;
     222: invokevirtual #28                 // Method java/lang/StringBuilder.append:(Ljava/lang/String;)Ljava/lang/StringBuilder;
     225: invokevirtual #30                 // Method java/lang/StringBuilder.toString:()Ljava/lang/String;
     228: astore        5
     230: aload_1
     231: aload_0
     232: aload         5
     234: invokevirtual #14                 // Method getOutputFile:(Ljava/lang/String;)Ljava/io/File;
     237: invokeinterface #15,  2           // InterfaceMethod java/util/List.add:(Ljava/lang/Object;)Z
     242: pop
     243: new           #25                 // class java/lang/StringBuilder
     246: dup
     247: invokespecial #26                 // Method java/lang/StringBuilder."<init>":()V
     250: aload_0
     251: getfield      #3                  // Field g:Lorg/antlr/v4/tool/Grammar;
     254: getfield      #27                 // Field org/antlr/v4/tool/Grammar.name:Ljava/lang/String;
     257: invokevirtual #28                 // Method java/lang/StringBuilder.append:(Ljava/lang/String;)Ljava/lang/StringBuilder;
     260: aload         4
     262: invokevirtual #28                 // Method java/lang/StringBuilder.append:(Ljava/lang/String;)Ljava/lang/StringBuilder;
     265: ldc           #32                 // String .tokens
     267: invokevirtual #28                 // Method java/lang/StringBuilder.append:(Ljava/lang/String;)Ljava/lang/StringBuilder;
     270: invokevirtual #30                 // Method java/lang/StringBuilder.toString:()Ljava/lang/String;
     273: astore        6
     275: aload_1
     276: aload_0
     277: aload         6
     279: invokevirtual #14                 // Method getOutputFile:(Ljava/lang/String;)Ljava/io/File;
     282: invokeinterface #15,  2           // InterfaceMethod java/util/List.add:(Ljava/lang/Object;)Z
     287: pop
     288: aload_2
     289: ifnull        339
     292: new           #25                 // class java/lang/StringBuilder
     295: dup
     296: invokespecial #26                 // Method java/lang/StringBuilder."<init>":()V
     299: aload_0
     300: getfield      #3                  // Field g:Lorg/antlr/v4/tool/Grammar;
     303: getfield      #27                 // Field org/antlr/v4/tool/Grammar.name:Ljava/lang/String;
     306: invokevirtual #28                 // Method java/lang/StringBuilder.append:(Ljava/lang/String;)Ljava/lang/StringBuilder;
     309: aload         4
     311: invokevirtual #28                 // Method java/lang/StringBuilder.append:(Ljava/lang/String;)Ljava/lang/StringBuilder;
     314: aload_2
     315: invokevirtual #29                 // Method org/stringtemplate/v4/ST.render:()Ljava/lang/String;
     318: invokevirtual #28                 // Method java/lang/StringBuilder.append:(Ljava/lang/String;)Ljava/lang/StringBuilder;
     321: invokevirtual #30                 // Method java/lang/StringBuilder.toString:()Ljava/lang/String;
     324: astore        7
     326: aload_1
     327: aload_0
     328: aload         7
     330: invokevirtual #14                 // Method getOutputFile:(Ljava/lang/String;)Ljava/io/File;
     333: invokeinterface #15,  2           // InterfaceMethod java/util/List.add:(Ljava/lang/Object;)Z
     338: pop
     339: aload_0
     340: getfield      #3                  // Field g:Lorg/antlr/v4/tool/Grammar;
     343: getfield      #33                 // Field org/antlr/v4/tool/Grammar.tool:Lorg/antlr/v4/Tool;
     346: getfield      #34                 // Field org/antlr/v4/Tool.gen_listener:Z
     349: ifeq          454
     352: aload_0
     353: getfield      #8                  // Field generator:Lorg/antlr/v4/codegen/CodeGenerator;
     356: invokevirtual #11                 // Method org/antlr/v4/codegen/CodeGenerator.getTarget:()Lorg/antlr/v4/codegen/Target;
     359: invokevirtual #12                 // Method org/antlr/v4/codegen/Target.needsHeader:()Z
     362: ifeq          384
     365: aload_1
     366: aload_0
     367: aload_0
     368: getfield      #8                  // Field generator:Lorg/antlr/v4/codegen/CodeGenerator;
     371: iconst_1
     372: invokevirtual #35                 // Method org/antlr/v4/codegen/CodeGenerator.getListenerFileName:(Z)Ljava/lang/String;
     375: invokevirtual #14                 // Method getOutputFile:(Ljava/lang/String;)Ljava/io/File;
     378: invokeinterface #15,  2           // InterfaceMethod java/util/List.add:(Ljava/lang/Object;)Z
     383: pop
     384: aload_1
     385: aload_0
     386: aload_0
     387: getfield      #8                  // Field generator:Lorg/antlr/v4/codegen/CodeGenerator;
     390: iconst_0
     391: invokevirtual #35                 // Method org/antlr/v4/codegen/CodeGenerator.getListenerFileName:(Z)Ljava/lang/String;
     394: invokevirtual #14                 // Method getOutputFile:(Ljava/lang/String;)Ljava/io/File;
     397: invokeinterface #15,  2           // InterfaceMethod java/util/List.add:(Ljava/lang/Object;)Z
     402: pop
     403: aload_0
     404: getfield      #8                  // Field generator:Lorg/antlr/v4/codegen/CodeGenerator;
     407: invokevirtual #11                 // Method org/antlr/v4/codegen/CodeGenerator.getTarget:()Lorg/antlr/v4/codegen/Target;
     410: invokevirtual #12                 // Method org/antlr/v4/codegen/Target.needsHeader:()Z
     413: ifeq          435
     416: aload_1
     417: aload_0
     418: aload_0
     419: getfield      #8                  // Field generator:Lorg/antlr/v4/codegen/CodeGenerator;
     422: iconst_1
     423: invokevirtual #36                 // Method org/antlr/v4/codegen/CodeGenerator.getBaseListenerFileName:(Z)Ljava/lang/String;
     426: invokevirtual #14                 // Method getOutputFile:(Ljava/lang/String;)Ljava/io/File;
     429: invokeinterface #15,  2           // InterfaceMethod java/util/List.add:(Ljava/lang/Object;)Z
     434: pop
     435: aload_1
     436: aload_0
     437: aload_0
     438: getfield      #8                  // Field generator:Lorg/antlr/v4/codegen/CodeGenerator;
     441: iconst_0
     442: invokevirtual #36                 // Method org/antlr/v4/codegen/CodeGenerator.getBaseListenerFileName:(Z)Ljava/lang/String;
     445: invokevirtual #14                 // Method getOutputFile:(Ljava/lang/String;)Ljava/io/File;
     448: invokeinterface #15,  2           // InterfaceMethod java/util/List.add:(Ljava/lang/Object;)Z
     453: pop
     454: aload_0
     455: getfield      #3                  // Field g:Lorg/antlr/v4/tool/Grammar;
     458: getfield      #33                 // Field org/antlr/v4/tool/Grammar.tool:Lorg/antlr/v4/Tool;
     461: getfield      #37                 // Field org/antlr/v4/Tool.gen_visitor:Z
     464: ifeq          569
     467: aload_0
     468: getfield      #8                  // Field generator:Lorg/antlr/v4/codegen/CodeGenerator;
     471: invokevirtual #11                 // Method org/antlr/v4/codegen/CodeGenerator.getTarget:()Lorg/antlr/v4/codegen/Target;
     474: invokevirtual #12                 // Method org/antlr/v4/codegen/Target.needsHeader:()Z
     477: ifeq          499
     480: aload_1
     481: aload_0
     482: aload_0
     483: getfield      #8                  // Field generator:Lorg/antlr/v4/codegen/CodeGenerator;
     486: iconst_1
     487: invokevirtual #38                 // Method org/antlr/v4/codegen/CodeGenerator.getVisitorFileName:(Z)Ljava/lang/String;
     490: invokevirtual #14                 // Method getOutputFile:(Ljava/lang/String;)Ljava/io/File;
     493: invokeinterface #15,  2           // InterfaceMethod java/util/List.add:(Ljava/lang/Object;)Z
     498: pop
     499: aload_1
     500: aload_0
     501: aload_0
     502: getfield      #8                  // Field generator:Lorg/antlr/v4/codegen/CodeGenerator;
     505: iconst_0
     506: invokevirtual #38                 // Method org/antlr/v4/codegen/CodeGenerator.getVisitorFileName:(Z)Ljava/lang/String;
     509: invokevirtual #14                 // Method getOutputFile:(Ljava/lang/String;)Ljava/io/File;
     512: invokeinterface #15,  2           // InterfaceMethod java/util/List.add:(Ljava/lang/Object;)Z
     517: pop
     518: aload_0
     519: getfield      #8                  // Field generator:Lorg/antlr/v4/codegen/CodeGenerator;
     522: invokevirtual #11                 // Method org/antlr/v4/codegen/CodeGenerator.getTarget:()Lorg/antlr/v4/codegen/Target;
     525: invokevirtual #12                 // Method org/antlr/v4/codegen/Target.needsHeader:()Z
     528: ifeq          550
     531: aload_1
     532: aload_0
     533: aload_0
     534: getfield      #8                  // Field generator:Lorg/antlr/v4/codegen/CodeGenerator;
     537: iconst_1
     538: invokevirtual #39                 // Method org/antlr/v4/codegen/CodeGenerator.getBaseVisitorFileName:(Z)Ljava/lang/String;
     541: invokevirtual #14                 // Method getOutputFile:(Ljava/lang/String;)Ljava/io/File;
     544: invokeinterface #15,  2           // InterfaceMethod java/util/List.add:(Ljava/lang/Object;)Z
     549: pop
     550: aload_1
     551: aload_0
     552: aload_0
     553: getfield      #8                  // Field generator:Lorg/antlr/v4/codegen/CodeGenerator;
     556: iconst_0
     557: invokevirtual #39                 // Method org/antlr/v4/codegen/CodeGenerator.getBaseVisitorFileName:(Z)Ljava/lang/String;
     560: invokevirtual #14                 // Method getOutputFile:(Ljava/lang/String;)Ljava/io/File;
     563: invokeinterface #15,  2           // InterfaceMethod java/util/List.add:(Ljava/lang/Object;)Z
     568: pop
     569: aload_0
     570: getfield      #3                  // Field g:Lorg/antlr/v4/tool/Grammar;
     573: invokevirtual #40                 // Method org/antlr/v4/tool/Grammar.getAllImportedGrammars:()Ljava/util/List;
     576: astore        4
     578: aload         4
     580: ifnull        633
     583: aload         4
     585: invokeinterface #41,  1           // InterfaceMethod java/util/List.iterator:()Ljava/util/Iterator;
     590: astore        5
     592: aload         5
     594: invokeinterface #42,  1           // InterfaceMethod java/util/Iterator.hasNext:()Z
     599: ifeq          633
     602: aload         5
     604: invokeinterface #43,  1           // InterfaceMethod java/util/Iterator.next:()Ljava/lang/Object;
     609: checkcast     #44                 // class org/antlr/v4/tool/Grammar
     612: astore        6
     614: aload_1
     615: aload_0
     616: aload         6
     618: getfield      #45                 // Field org/antlr/v4/tool/Grammar.fileName:Ljava/lang/String;
     621: invokevirtual #14                 // Method getOutputFile:(Ljava/lang/String;)Ljava/io/File;
     624: invokeinterface #15,  2           // InterfaceMethod java/util/List.add:(Ljava/lang/Object;)Z
     629: pop
     630: goto          592
     633: aload_1
     634: invokeinterface #46,  1           // InterfaceMethod java/util/List.isEmpty:()Z
     639: ifeq          644
     642: aconst_null
     643: areturn
     644: aload_1
     645: areturn

  public java.io.File getOutputFile(java.lang.String);
    Code:
       0: aload_0
       1: getfield      #2                  // Field tool:Lorg/antlr/v4/Tool;
       4: aload_0
       5: getfield      #3                  // Field g:Lorg/antlr/v4/tool/Grammar;
       8: getfield      #45                 // Field org/antlr/v4/tool/Grammar.fileName:Ljava/lang/String;
      11: invokevirtual #47                 // Method org/antlr/v4/Tool.getOutputDirectory:(Ljava/lang/String;)Ljava/io/File;
      14: astore_2
      15: aload_2
      16: invokevirtual #48                 // Method java/io/File.toString:()Ljava/lang/String;
      19: ldc           #49                 // String .
      21: invokevirtual #50                 // Method java/lang/String.equals:(Ljava/lang/Object;)Z
      24: ifeq          36
      27: aload_0
      28: getfield      #2                  // Field tool:Lorg/antlr/v4/Tool;
      31: aload_1
      32: invokevirtual #47                 // Method org/antlr/v4/Tool.getOutputDirectory:(Ljava/lang/String;)Ljava/io/File;
      35: astore_2
      36: aload_2
      37: invokevirtual #48                 // Method java/io/File.toString:()Ljava/lang/String;
      40: ldc           #49                 // String .
      42: invokevirtual #50                 // Method java/lang/String.equals:(Ljava/lang/Object;)Z
      45: ifeq          57
      48: new           #51                 // class java/io/File
      51: dup
      52: aload_1
      53: invokespecial #52                 // Method java/io/File."<init>":(Ljava/lang/String;)V
      56: areturn
      57: aload_2
      58: invokevirtual #53                 // Method java/io/File.getName:()Ljava/lang/String;
      61: ldc           #49                 // String .
      63: invokevirtual #50                 // Method java/lang/String.equals:(Ljava/lang/Object;)Z
      66: ifeq          100
      69: aload_2
      70: invokevirtual #48                 // Method java/io/File.toString:()Ljava/lang/String;
      73: astore_3
      74: aload_3
      75: bipush        46
      77: invokevirtual #54                 // Method java/lang/String.lastIndexOf:(I)I
      80: istore        4
      82: new           #51                 // class java/io/File
      85: dup
      86: aload_2
      87: invokevirtual #48                 // Method java/io/File.toString:()Ljava/lang/String;
      90: iconst_0
      91: iload         4
      93: invokevirtual #55                 // Method java/lang/String.substring:(II)Ljava/lang/String;
      96: invokespecial #52                 // Method java/io/File."<init>":(Ljava/lang/String;)V
      99: astore_2
     100: aload_2
     101: invokevirtual #53                 // Method java/io/File.getName:()Ljava/lang/String;
     104: bipush        32
     106: invokevirtual #56                 // Method java/lang/String.indexOf:(I)I
     109: iflt          133
     112: aload_2
     113: invokevirtual #48                 // Method java/io/File.toString:()Ljava/lang/String;
     116: ldc           #57                 // String
     118: ldc           #58                 // String \\
     120: invokevirtual #59                 // Method java/lang/String.replace:(Ljava/lang/CharSequence;Ljava/lang/CharSequence;)Ljava/lang/String;
     123: astore_3
     124: new           #51                 // class java/io/File
     127: dup
     128: aload_3
     129: invokespecial #52                 // Method java/io/File."<init>":(Ljava/lang/String;)V
     132: astore_2
     133: new           #51                 // class java/io/File
     136: dup
     137: aload_2
     138: aload_1
     139: invokespecial #60                 // Method java/io/File."<init>":(Ljava/io/File;Ljava/lang/String;)V
     142: areturn

  public java.util.List<java.io.File> getDependenciesFileList();
    Code:
       0: aload_0
       1: invokevirtual #61                 // Method getNonImportDependenciesFileList:()Ljava/util/List;
       4: astore_1
       5: aload_0
       6: getfield      #3                  // Field g:Lorg/antlr/v4/tool/Grammar;
       9: invokevirtual #40                 // Method org/antlr/v4/tool/Grammar.getAllImportedGrammars:()Ljava/util/List;
      12: astore_2
      13: aload_2
      14: ifnull        85
      17: aload_2
      18: invokeinterface #41,  1           // InterfaceMethod java/util/List.iterator:()Ljava/util/Iterator;
      23: astore_3
      24: aload_3
      25: invokeinterface #42,  1           // InterfaceMethod java/util/Iterator.hasNext:()Z
      30: ifeq          85
      33: aload_3
      34: invokeinterface #43,  1           // InterfaceMethod java/util/Iterator.next:()Ljava/lang/Object;
      39: checkcast     #44                 // class org/antlr/v4/tool/Grammar
      42: astore        4
      44: aload_0
      45: getfield      #2                  // Field tool:Lorg/antlr/v4/Tool;
      48: getfield      #62                 // Field org/antlr/v4/Tool.libDirectory:Ljava/lang/String;
      51: astore        5
      53: aload_0
      54: aload         5
      56: aload         4
      58: getfield      #45                 // Field org/antlr/v4/tool/Grammar.fileName:Ljava/lang/String;
      61: invokevirtual #63                 // Method groomQualifiedFileName:(Ljava/lang/String;Ljava/lang/String;)Ljava/lang/String;
      64: astore        6
      66: aload_1
      67: new           #51                 // class java/io/File
      70: dup
      71: aload         6
      73: invokespecial #52                 // Method java/io/File."<init>":(Ljava/lang/String;)V
      76: invokeinterface #15,  2           // InterfaceMethod java/util/List.add:(Ljava/lang/Object;)Z
      81: pop
      82: goto          24
      85: aload_1
      86: invokeinterface #46,  1           // InterfaceMethod java/util/List.isEmpty:()Z
      91: ifeq          96
      94: aconst_null
      95: areturn
      96: aload_1
      97: areturn

  public java.util.List<java.io.File> getNonImportDependenciesFileList();
    Code:
       0: new           #9                  // class java/util/ArrayList
       3: dup
       4: invokespecial #10                 // Method java/util/ArrayList."<init>":()V
       7: astore_1
       8: aload_0
       9: getfield      #3                  // Field g:Lorg/antlr/v4/tool/Grammar;
      12: ldc           #64                 // String tokenVocab
      14: invokevirtual #5                  // Method org/antlr/v4/tool/Grammar.getOptionString:(Ljava/lang/String;)Ljava/lang/String;
      17: astore_2
      18: aload_2
      19: ifnull        96
      22: new           #25                 // class java/lang/StringBuilder
      25: dup
      26: invokespecial #26                 // Method java/lang/StringBuilder."<init>":()V
      29: aload_2
      30: invokevirtual #28                 // Method java/lang/StringBuilder.append:(Ljava/lang/String;)Ljava/lang/StringBuilder;
      33: ldc           #32                 // String .tokens
      35: invokevirtual #28                 // Method java/lang/StringBuilder.append:(Ljava/lang/String;)Ljava/lang/StringBuilder;
      38: invokevirtual #30                 // Method java/lang/StringBuilder.toString:()Ljava/lang/String;
      41: astore_3
      42: aload_0
      43: getfield      #2                  // Field tool:Lorg/antlr/v4/Tool;
      46: getfield      #62                 // Field org/antlr/v4/Tool.libDirectory:Ljava/lang/String;
      49: ldc           #49                 // String .
      51: invokevirtual #50                 // Method java/lang/String.equals:(Ljava/lang/Object;)Z
      54: ifeq          70
      57: new           #51                 // class java/io/File
      60: dup
      61: aload_3
      62: invokespecial #52                 // Method java/io/File."<init>":(Ljava/lang/String;)V
      65: astore        4
      67: goto          87
      70: new           #51                 // class java/io/File
      73: dup
      74: aload_0
      75: getfield      #2                  // Field tool:Lorg/antlr/v4/Tool;
      78: getfield      #62                 // Field org/antlr/v4/Tool.libDirectory:Ljava/lang/String;
      81: aload_3
      82: invokespecial #65                 // Method java/io/File."<init>":(Ljava/lang/String;Ljava/lang/String;)V
      85: astore        4
      87: aload_1
      88: aload         4
      90: invokeinterface #15,  2           // InterfaceMethod java/util/List.add:(Ljava/lang/Object;)Z
      95: pop
      96: aload_1
      97: areturn

  public org.stringtemplate.v4.ST getDependencies();
    Code:
       0: aload_0
       1: invokevirtual #66                 // Method loadDependencyTemplates:()V
       4: aload_0
       5: getfield      #67                 // Field templates:Lorg/stringtemplate/v4/STGroup;
       8: ldc           #68                 // String dependencies
      10: invokevirtual #19                 // Method org/stringtemplate/v4/STGroup.getInstanceOf:(Ljava/lang/String;)Lorg/stringtemplate/v4/ST;
      13: astore_1
      14: aload_1
      15: ldc           #69                 // String in
      17: aload_0
      18: invokevirtual #70                 // Method getDependenciesFileList:()Ljava/util/List;
      21: invokevirtual #71                 // Method org/stringtemplate/v4/ST.add:(Ljava/lang/String;Ljava/lang/Object;)Lorg/stringtemplate/v4/ST;
      24: pop
      25: aload_1
      26: ldc           #72                 // String out
      28: aload_0
      29: invokevirtual #73                 // Method getGeneratedFileList:()Ljava/util/List;
      32: invokevirtual #71                 // Method org/stringtemplate/v4/ST.add:(Ljava/lang/String;Ljava/lang/Object;)Lorg/stringtemplate/v4/ST;
      35: pop
      36: aload_1
      37: ldc           #74                 // String grammarFileName
      39: aload_0
      40: getfield      #3                  // Field g:Lorg/antlr/v4/tool/Grammar;
      43: getfield      #45                 // Field org/antlr/v4/tool/Grammar.fileName:Ljava/lang/String;
      46: invokevirtual #71                 // Method org/stringtemplate/v4/ST.add:(Ljava/lang/String;Ljava/lang/Object;)Lorg/stringtemplate/v4/ST;
      49: pop
      50: aload_1
      51: areturn

  public void loadDependencyTemplates();
    Code:
       0: aload_0
       1: getfield      #67                 // Field templates:Lorg/stringtemplate/v4/STGroup;
       4: ifnull        8
       7: return
       8: ldc           #75                 // String org/antlr/v4/tool/templates/depend.stg
      10: astore_1
      11: aload_0
      12: new           #76                 // class org/stringtemplate/v4/STGroupFile
      15: dup
      16: aload_1
      17: ldc           #77                 // String UTF-8
      19: invokespecial #78                 // Method org/stringtemplate/v4/STGroupFile."<init>":(Ljava/lang/String;Ljava/lang/String;)V
      22: putfield      #67                 // Field templates:Lorg/stringtemplate/v4/STGroup;
      25: return

  public org.antlr.v4.codegen.CodeGenerator getGenerator();
    Code:
       0: aload_0
       1: getfield      #8                  // Field generator:Lorg/antlr/v4/codegen/CodeGenerator;
       4: areturn

  public java.lang.String groomQualifiedFileName(java.lang.String, java.lang.String);
    Code:
       0: aload_1
       1: ldc           #49                 // String .
       3: invokevirtual #50                 // Method java/lang/String.equals:(Ljava/lang/Object;)Z
       6: ifeq          11
       9: aload_2
      10: areturn
      11: aload_1
      12: bipush        32
      14: invokevirtual #56                 // Method java/lang/String.indexOf:(I)I
      17: iflt          54
      20: aload_1
      21: ldc           #57                 // String
      23: ldc           #58                 // String \\
      25: invokevirtual #59                 // Method java/lang/String.replace:(Ljava/lang/CharSequence;Ljava/lang/CharSequence;)Ljava/lang/String;
      28: astore_3
      29: new           #25                 // class java/lang/StringBuilder
      32: dup
      33: invokespecial #26                 // Method java/lang/StringBuilder."<init>":()V
      36: aload_3
      37: invokevirtual #28                 // Method java/lang/StringBuilder.append:(Ljava/lang/String;)Ljava/lang/StringBuilder;
      40: getstatic     #79                 // Field java/io/File.separator:Ljava/lang/String;
      43: invokevirtual #28                 // Method java/lang/StringBuilder.append:(Ljava/lang/String;)Ljava/lang/StringBuilder;
      46: aload_2
      47: invokevirtual #28                 // Method java/lang/StringBuilder.append:(Ljava/lang/String;)Ljava/lang/StringBuilder;
      50: invokevirtual #30                 // Method java/lang/StringBuilder.toString:()Ljava/lang/String;
      53: areturn
      54: new           #25                 // class java/lang/StringBuilder
      57: dup
      58: invokespecial #26                 // Method java/lang/StringBuilder."<init>":()V
      61: aload_1
      62: invokevirtual #28                 // Method java/lang/StringBuilder.append:(Ljava/lang/String;)Ljava/lang/StringBuilder;
      65: getstatic     #79                 // Field java/io/File.separator:Ljava/lang/String;
      68: invokevirtual #28                 // Method java/lang/StringBuilder.append:(Ljava/lang/String;)Ljava/lang/StringBuilder;
      71: aload_2
      72: invokevirtual #28                 // Method java/lang/StringBuilder.append:(Ljava/lang/String;)Ljava/lang/StringBuilder;
      75: invokevirtual #30                 // Method java/lang/StringBuilder.toString:()Ljava/lang/String;
      78: areturn
}
