Compiled from "NewRuleParam.java"
public class org.sonar.api.batch.rule.internal.NewRuleParam {
  final java.lang.String key;

  java.lang.String description;

  org.sonar.api.batch.rule.internal.NewRuleParam(java.lang.String);
    Code:
       0: aload_0
       1: invokespecial #13                 // Method java/lang/Object."<init>":()V
       4: aload_0
       5: aload_1
       6: putfield      #15                 // Field key:Ljava/lang/String;
       9: return

  public org.sonar.api.batch.rule.internal.NewRuleParam setDescription(java.lang.String);
    Code:
       0: aload_0
       1: aload_1
       2: putfield      #22                 // Field description:Ljava/lang/String;
       5: aload_0
       6: areturn
}
