Compiled from "SubjectAttributeDesignatorTypeImplBuilder.java"
public class org.opensaml.xacml.policy.impl.SubjectAttributeDesignatorTypeImplBuilder extends org.opensaml.xacml.impl.AbstractXACMLObjectBuilder<org.opensaml.xacml.policy.SubjectAttributeDesignatorType> {
  public org.opensaml.xacml.policy.impl.SubjectAttributeDesignatorTypeImplBuilder();
    Code:
       0: aload_0
       1: invokespecial #1                  // Method org/opensaml/xacml/impl/AbstractXACMLObjectBuilder."<init>":()V
       4: return

  public org.opensaml.xacml.policy.SubjectAttributeDesignatorType buildObject(java.lang.String, java.lang.String, java.lang.String);
    Code:
       0: new           #2                  // class org/opensaml/xacml/policy/impl/SubjectAttributeDesignatorTypeImpl
       3: dup
       4: aload_1
       5: aload_2
       6: aload_3
       7: invokespecial #3                  // Method org/opensaml/xacml/policy/impl/SubjectAttributeDesignatorTypeImpl."<init>":(Ljava/lang/String;Ljava/lang/String;Ljava/lang/String;)V
      10: areturn

  public org.opensaml.xacml.policy.SubjectAttributeDesignatorType buildObject();
    Code:
       0: aload_0
       1: getstatic     #4                  // Field org/opensaml/xacml/policy/SubjectAttributeDesignatorType.DEFAULT_ELEMENT_QNAME:Ljavax/xml/namespace/QName;
       4: invokevirtual #5                  // Method buildObject:(Ljavax/xml/namespace/QName;)Lorg/opensaml/core/xml/XMLObject;
       7: checkcast     #6                  // class org/opensaml/xacml/policy/SubjectAttributeDesignatorType
      10: areturn

  public org.opensaml.xacml.XACMLObject buildObject();
    Code:
       0: aload_0
       1: invokevirtual #7                  // Method buildObject:()Lorg/opensaml/xacml/policy/SubjectAttributeDesignatorType;
       4: areturn

  public org.opensaml.core.xml.XMLObject buildObject(java.lang.String, java.lang.String, java.lang.String);
    Code:
       0: aload_0
       1: aload_1
       2: aload_2
       3: aload_3
       4: invokevirtual #8                  // Method buildObject:(Ljava/lang/String;Ljava/lang/String;Ljava/lang/String;)Lorg/opensaml/xacml/policy/SubjectAttributeDesignatorType;
       7: areturn
}
