Compiled from "RegexMatcher.java"
class io.grpc.xds.shaded.io.envoyproxy.envoy.type.matcher.v3.RegexMatcher$2 {
  static final int[] $SwitchMap$io$envoyproxy$envoy$type$matcher$v3$RegexMatcher$EngineTypeCase;

  static {};
    Code:
       0: invokestatic  #20                 // Method io/grpc/xds/shaded/io/envoyproxy/envoy/type/matcher/v3/RegexMatcher$EngineTypeCase.values:()[Lio/grpc/xds/shaded/io/envoyproxy/envoy/type/matcher/v3/RegexMatcher$EngineTypeCase;
       3: arraylength
       4: newarray       int
       6: putstatic     #22                 // Field $SwitchMap$io$envoyproxy$envoy$type$matcher$v3$RegexMatcher$EngineTypeCase:[I
       9: getstatic     #22                 // Field $SwitchMap$io$envoyproxy$envoy$type$matcher$v3$RegexMatcher$EngineTypeCase:[I
      12: getstatic     #26                 // Field io/grpc/xds/shaded/io/envoyproxy/envoy/type/matcher/v3/RegexMatcher$EngineTypeCase.GOOGLE_RE2:Lio/grpc/xds/shaded/io/envoyproxy/envoy/type/matcher/v3/RegexMatcher$EngineTypeCase;
      15: invokevirtual #30                 // Method io/grpc/xds/shaded/io/envoyproxy/envoy/type/matcher/v3/RegexMatcher$EngineTypeCase.ordinal:()I
      18: iconst_1
      19: iastore
      20: goto          24
      23: astore_0
      24: getstatic     #22                 // Field $SwitchMap$io$envoyproxy$envoy$type$matcher$v3$RegexMatcher$EngineTypeCase:[I
      27: getstatic     #33                 // Field io/grpc/xds/shaded/io/envoyproxy/envoy/type/matcher/v3/RegexMatcher$EngineTypeCase.ENGINETYPE_NOT_SET:Lio/grpc/xds/shaded/io/envoyproxy/envoy/type/matcher/v3/RegexMatcher$EngineTypeCase;
      30: invokevirtual #30                 // Method io/grpc/xds/shaded/io/envoyproxy/envoy/type/matcher/v3/RegexMatcher$EngineTypeCase.ordinal:()I
      33: iconst_2
      34: iastore
      35: goto          39
      38: astore_0
      39: return
    Exception table:
       from    to  target type
           9    20    23   Class java/lang/NoSuchFieldError
          24    35    38   Class java/lang/NoSuchFieldError
}
