Compiled from "MonthDayKeyDeserializer.java"
public class io.dekorate.deps.jackson.datatype.jsr310.deser.key.MonthDayKeyDeserializer extends io.dekorate.deps.jackson.datatype.jsr310.deser.key.Jsr310KeyDeserializer {
  public static final io.dekorate.deps.jackson.datatype.jsr310.deser.key.MonthDayKeyDeserializer INSTANCE;

  private static final java.time.format.DateTimeFormatter PARSER;

  private io.dekorate.deps.jackson.datatype.jsr310.deser.key.MonthDayKeyDeserializer();
    Code:
       0: aload_0
       1: invokespecial #13                 // Method io/dekorate/deps/jackson/datatype/jsr310/deser/key/Jsr310KeyDeserializer."<init>":()V
       4: return

  protected java.time.MonthDay deserialize(java.lang.String, io.dekorate.deps.jackson.databind.DeserializationContext) throws java.io.IOException;
    Code:
       0: aload_1
       1: getstatic     #22                 // Field PARSER:Ljava/time/format/DateTimeFormatter;
       4: invokestatic  #28                 // Method java/time/MonthDay.parse:(Ljava/lang/CharSequence;Ljava/time/format/DateTimeFormatter;)Ljava/time/MonthDay;
       7: areturn
       8: astore_3
       9: aload_0
      10: aload_2
      11: ldc           #24                 // class java/time/MonthDay
      13: aload_3
      14: aload_1
      15: invokevirtual #32                 // Method _handleDateTimeException:(Lio/dekorate/deps/jackson/databind/DeserializationContext;Ljava/lang/Class;Ljava/time/DateTimeException;Ljava/lang/String;)Ljava/lang/Object;
      18: checkcast     #24                 // class java/time/MonthDay
      21: areturn
    Exception table:
       from    to  target type
           0     7     8   Class java/time/DateTimeException

  protected java.lang.Object deserialize(java.lang.String, io.dekorate.deps.jackson.databind.DeserializationContext) throws java.io.IOException;
    Code:
       0: aload_0
       1: aload_1
       2: aload_2
       3: invokevirtual #41                 // Method deserialize:(Ljava/lang/String;Lio/dekorate/deps/jackson/databind/DeserializationContext;)Ljava/time/MonthDay;
       6: areturn

  static {};
    Code:
       0: new           #2                  // class io/dekorate/deps/jackson/datatype/jsr310/deser/key/MonthDayKeyDeserializer
       3: dup
       4: invokespecial #43                 // Method "<init>":()V
       7: putstatic     #45                 // Field INSTANCE:Lio/dekorate/deps/jackson/datatype/jsr310/deser/key/MonthDayKeyDeserializer;
      10: new           #47                 // class java/time/format/DateTimeFormatterBuilder
      13: dup
      14: invokespecial #48                 // Method java/time/format/DateTimeFormatterBuilder."<init>":()V
      17: ldc           #50                 // String --
      19: invokevirtual #54                 // Method java/time/format/DateTimeFormatterBuilder.appendLiteral:(Ljava/lang/String;)Ljava/time/format/DateTimeFormatterBuilder;
      22: getstatic     #60                 // Field java/time/temporal/ChronoField.MONTH_OF_YEAR:Ljava/time/temporal/ChronoField;
      25: iconst_2
      26: invokevirtual #64                 // Method java/time/format/DateTimeFormatterBuilder.appendValue:(Ljava/time/temporal/TemporalField;I)Ljava/time/format/DateTimeFormatterBuilder;
      29: bipush        45
      31: invokevirtual #67                 // Method java/time/format/DateTimeFormatterBuilder.appendLiteral:(C)Ljava/time/format/DateTimeFormatterBuilder;
      34: getstatic     #70                 // Field java/time/temporal/ChronoField.DAY_OF_MONTH:Ljava/time/temporal/ChronoField;
      37: iconst_2
      38: invokevirtual #64                 // Method java/time/format/DateTimeFormatterBuilder.appendValue:(Ljava/time/temporal/TemporalField;I)Ljava/time/format/DateTimeFormatterBuilder;
      41: invokevirtual #74                 // Method java/time/format/DateTimeFormatterBuilder.toFormatter:()Ljava/time/format/DateTimeFormatter;
      44: putstatic     #22                 // Field PARSER:Ljava/time/format/DateTimeFormatter;
      47: return
}
