Compiled from "CompileTaskSupport.java"
class org.codehaus.groovy.ant.CompileTaskSupport$1 implements java.security.PrivilegedAction<groovy.lang.GroovyClassLoader> {
  final org.codehaus.groovy.ant.CompileTaskSupport this$0;

  org.codehaus.groovy.ant.CompileTaskSupport$1(org.codehaus.groovy.ant.CompileTaskSupport);
    Code:
       0: aload_0
       1: aload_1
       2: putfield      #19                 // Field this$0:Lorg/codehaus/groovy/ant/CompileTaskSupport;
       5: aload_0
       6: invokespecial #22                 // Method java/lang/Object."<init>":()V
       9: return

  public groovy.lang.GroovyClassLoader run();
    Code:
       0: new           #27                 // class groovy/lang/GroovyClassLoader
       3: dup
       4: invokestatic  #33                 // Method java/lang/ClassLoader.getSystemClassLoader:()Ljava/lang/ClassLoader;
       7: aload_0
       8: getfield      #19                 // Field this$0:Lorg/codehaus/groovy/ant/CompileTaskSupport;
      11: getfield      #37                 // Field org/codehaus/groovy/ant/CompileTaskSupport.config:Lorg/codehaus/groovy/control/CompilerConfiguration;
      14: invokespecial #40                 // Method groovy/lang/GroovyClassLoader."<init>":(Ljava/lang/ClassLoader;Lorg/codehaus/groovy/control/CompilerConfiguration;)V
      17: areturn

  public java.lang.Object run();
    Code:
       0: aload_0
       1: invokevirtual #43                 // Method run:()Lgroovy/lang/GroovyClassLoader;
       4: areturn
}
