Compiled from "SpringBootContextLoader.java"
class org.springframework.boot.test.context.SpringBootContextLoader$ReactiveWebConfigurer {
  private static final java.lang.Class<org.springframework.boot.web.reactive.context.GenericReactiveWebApplicationContext> WEB_CONTEXT_CLASS;

  private org.springframework.boot.test.context.SpringBootContextLoader$ReactiveWebConfigurer();
    Code:
       0: aload_0
       1: invokespecial #2                  // Method java/lang/Object."<init>":()V
       4: return

  void configure(org.springframework.boot.SpringApplication);
    Code:
       0: aload_1
       1: getstatic     #3                  // Field WEB_CONTEXT_CLASS:Ljava/lang/Class;
       4: invokevirtual #4                  // Method org/springframework/boot/SpringApplication.setApplicationContextClass:(Ljava/lang/Class;)V
       7: return

  org.springframework.boot.test.context.SpringBootContextLoader$ReactiveWebConfigurer(org.springframework.boot.test.context.SpringBootContextLoader$1);
    Code:
       0: aload_0
       1: invokespecial #1                  // Method "<init>":()V
       4: return

  static {};
    Code:
       0: ldc           #5                  // class org/springframework/boot/web/reactive/context/GenericReactiveWebApplicationContext
       2: putstatic     #3                  // Field WEB_CONTEXT_CLASS:Ljava/lang/Class;
       5: return
}
