Compiled from "DebugUtil.java"
public final class org.jboss.netty.util.DebugUtil {
  private static final boolean DEBUG_ENABLED;

  public static boolean isDebugEnabled();
    Code:
       0: getstatic     #1                  // Field DEBUG_ENABLED:Z
       3: ireturn

  private org.jboss.netty.util.DebugUtil();
    Code:
       0: aload_0
       1: invokespecial #2                  // Method java/lang/Object."<init>":()V
       4: return

  static {};
    Code:
       0: ldc           #3                  // String org.jboss.netty.debug
       2: iconst_0
       3: invokestatic  #4                  // Method org/jboss/netty/util/internal/SystemPropertyUtil.getBoolean:(Ljava/lang/String;Z)Z
       6: putstatic     #1                  // Field DEBUG_ENABLED:Z
       9: return
}
