Compiled from "ExternalResourceUtil.java"
public final class org.jboss.netty.util.ExternalResourceUtil {
  public static void release(org.jboss.netty.util.ExternalResourceReleasable...);
    Code:
       0: aload_0
       1: arraylength
       2: anewarray     #1                  // class org/jboss/netty/util/ExternalResourceReleasable
       5: astore_1
       6: iconst_0
       7: istore_2
       8: iload_2
       9: aload_0
      10: arraylength
      11: if_icmpge     64
      14: aload_0
      15: iload_2
      16: aaload
      17: ifnonnull     52
      20: new           #2                  // class java/lang/NullPointerException
      23: dup
      24: new           #3                  // class java/lang/StringBuilder
      27: dup
      28: invokespecial #4                  // Method java/lang/StringBuilder."<init>":()V
      31: ldc           #5                  // String releasables[
      33: invokevirtual #6                  // Method java/lang/StringBuilder.append:(Ljava/lang/String;)Ljava/lang/StringBuilder;
      36: iload_2
      37: invokevirtual #7                  // Method java/lang/StringBuilder.append:(I)Ljava/lang/StringBuilder;
      40: bipush        93
      42: invokevirtual #8                  // Method java/lang/StringBuilder.append:(C)Ljava/lang/StringBuilder;
      45: invokevirtual #9                  // Method java/lang/StringBuilder.toString:()Ljava/lang/String;
      48: invokespecial #10                 // Method java/lang/NullPointerException."<init>":(Ljava/lang/String;)V
      51: athrow
      52: aload_1
      53: iload_2
      54: aload_0
      55: iload_2
      56: aaload
      57: aastore
      58: iinc          2, 1
      61: goto          8
      64: aload_1
      65: astore_2
      66: aload_2
      67: arraylength
      68: istore_3
      69: iconst_0
      70: istore        4
      72: iload         4
      74: iload_3
      75: if_icmpge     97
      78: aload_2
      79: iload         4
      81: aaload
      82: astore        5
      84: aload         5
      86: invokeinterface #11,  1           // InterfaceMethod org/jboss/netty/util/ExternalResourceReleasable.releaseExternalResources:()V
      91: iinc          4, 1
      94: goto          72
      97: return

  private org.jboss.netty.util.ExternalResourceUtil();
    Code:
       0: aload_0
       1: invokespecial #12                 // Method java/lang/Object."<init>":()V
       4: return
}
