Compiled from "ScriptingDefaultsParser.java"
class org.springframework.scripting.config.ScriptingDefaultsParser implements org.springframework.beans.factory.xml.BeanDefinitionParser {
  private static final java.lang.String REFRESH_CHECK_DELAY_ATTRIBUTE;

  private static final java.lang.String PROXY_TARGET_CLASS_ATTRIBUTE;

  org.springframework.scripting.config.ScriptingDefaultsParser();
    Code:
       0: aload_0
       1: invokespecial #1                  // Method java/lang/Object."<init>":()V
       4: return

  public org.springframework.beans.factory.config.BeanDefinition parse(org.w3c.dom.Element, org.springframework.beans.factory.xml.ParserContext);
    Code:
       0: aload_2
       1: invokevirtual #2                  // Method org/springframework/beans/factory/xml/ParserContext.getRegistry:()Lorg/springframework/beans/factory/support/BeanDefinitionRegistry;
       4: invokestatic  #3                  // Method org/springframework/scripting/config/LangNamespaceUtils.registerScriptFactoryPostProcessorIfNecessary:(Lorg/springframework/beans/factory/support/BeanDefinitionRegistry;)Lorg/springframework/beans/factory/config/BeanDefinition;
       7: astore_3
       8: aload_1
       9: ldc           #5                  // String refresh-check-delay
      11: invokeinterface #6,  2            // InterfaceMethod org/w3c/dom/Element.getAttribute:(Ljava/lang/String;)Ljava/lang/String;
      16: astore        4
      18: aload         4
      20: invokestatic  #7                  // Method org/springframework/util/StringUtils.hasText:(Ljava/lang/String;)Z
      23: ifeq          43
      26: aload_3
      27: invokeinterface #8,  1            // InterfaceMethod org/springframework/beans/factory/config/BeanDefinition.getPropertyValues:()Lorg/springframework/beans/MutablePropertyValues;
      32: ldc           #9                  // String defaultRefreshCheckDelay
      34: aload         4
      36: invokestatic  #10                 // Method java/lang/Long.valueOf:(Ljava/lang/String;)Ljava/lang/Long;
      39: invokevirtual #11                 // Method org/springframework/beans/MutablePropertyValues.add:(Ljava/lang/String;Ljava/lang/Object;)Lorg/springframework/beans/MutablePropertyValues;
      42: pop
      43: aload_1
      44: ldc           #12                 // String proxy-target-class
      46: invokeinterface #6,  2            // InterfaceMethod org/w3c/dom/Element.getAttribute:(Ljava/lang/String;)Ljava/lang/String;
      51: astore        5
      53: aload         5
      55: invokestatic  #7                  // Method org/springframework/util/StringUtils.hasText:(Ljava/lang/String;)Z
      58: ifeq          84
      61: aload_3
      62: invokeinterface #8,  1            // InterfaceMethod org/springframework/beans/factory/config/BeanDefinition.getPropertyValues:()Lorg/springframework/beans/MutablePropertyValues;
      67: ldc           #13                 // String defaultProxyTargetClass
      69: new           #14                 // class org/springframework/beans/factory/config/TypedStringValue
      72: dup
      73: aload         5
      75: ldc           #15                 // class java/lang/Boolean
      77: invokespecial #16                 // Method org/springframework/beans/factory/config/TypedStringValue."<init>":(Ljava/lang/String;Ljava/lang/Class;)V
      80: invokevirtual #11                 // Method org/springframework/beans/MutablePropertyValues.add:(Ljava/lang/String;Ljava/lang/Object;)Lorg/springframework/beans/MutablePropertyValues;
      83: pop
      84: aconst_null
      85: areturn
}
