Compiled from "Future.scala"
public final class scala.concurrent.Future$$anonfun$recover$1 extends scala.runtime.AbstractFunction1<scala.util.Try<T>, scala.concurrent.Promise<U>> implements scala.Serializable {
  public static final long serialVersionUID;

  private final scala.concurrent.Promise p$5;

  private final scala.PartialFunction pf$4;

  public final scala.concurrent.Promise<U> apply(scala.util.Try<T>);
    Code:
       0: aload_0
       1: getfield      #25                 // Field p$5:Lscala/concurrent/Promise;
       4: aload_1
       5: aload_0
       6: getfield      #27                 // Field pf$4:Lscala/PartialFunction;
       9: invokevirtual #32                 // Method scala/util/Try.recover:(Lscala/PartialFunction;)Lscala/util/Try;
      12: invokeinterface #37,  2           // InterfaceMethod scala/concurrent/Promise.complete:(Lscala/util/Try;)Lscala/concurrent/Promise;
      17: areturn

  public final java.lang.Object apply(java.lang.Object);
    Code:
       0: aload_0
       1: aload_1
       2: checkcast     #29                 // class scala/util/Try
       5: invokevirtual #44                 // Method apply:(Lscala/util/Try;)Lscala/concurrent/Promise;
       8: areturn

  public scala.concurrent.Future$$anonfun$recover$1(scala.concurrent.Future<T>);
    Code:
       0: aload_0
       1: aload_2
       2: putfield      #25                 // Field p$5:Lscala/concurrent/Promise;
       5: aload_0
       6: aload_3
       7: putfield      #27                 // Field pf$4:Lscala/PartialFunction;
      10: aload_0
      11: invokespecial #51                 // Method scala/runtime/AbstractFunction1."<init>":()V
      14: return
}
