Compiled from "Future.scala"
public final class scala.concurrent.Future$$anonfun$failed$1 extends scala.runtime.AbstractFunction1<scala.util.Try<T>, scala.concurrent.Promise<java.lang.Throwable>> implements scala.Serializable {
  public static final long serialVersionUID;

  private final scala.concurrent.Promise p$1;

  public final scala.concurrent.Promise<java.lang.Throwable> apply(scala.util.Try<T>);
    Code:
       0: aload_1
       1: instanceof    #23                 // class scala/util/Failure
       4: ifeq          29
       7: aload_1
       8: checkcast     #23                 // class scala/util/Failure
      11: astore_2
      12: aload_0
      13: getfield      #25                 // Field p$1:Lscala/concurrent/Promise;
      16: aload_2
      17: invokevirtual #29                 // Method scala/util/Failure.exception:()Ljava/lang/Throwable;
      20: invokeinterface #35,  2           // InterfaceMethod scala/concurrent/Promise.success:(Ljava/lang/Object;)Lscala/concurrent/Promise;
      25: astore_3
      26: goto          55
      29: aload_1
      30: instanceof    #37                 // class scala/util/Success
      33: ifeq          57
      36: aload_0
      37: getfield      #25                 // Field p$1:Lscala/concurrent/Promise;
      40: new           #39                 // class java/util/NoSuchElementException
      43: dup
      44: ldc           #41                 // String Future.failed not completed with a throwable.
      46: invokespecial #45                 // Method java/util/NoSuchElementException."<init>":(Ljava/lang/String;)V
      49: invokeinterface #49,  2           // InterfaceMethod scala/concurrent/Promise.failure:(Ljava/lang/Throwable;)Lscala/concurrent/Promise;
      54: astore_3
      55: aload_3
      56: areturn
      57: new           #51                 // class scala/MatchError
      60: dup
      61: aload_1
      62: invokespecial #54                 // Method scala/MatchError."<init>":(Ljava/lang/Object;)V
      65: athrow

  public final java.lang.Object apply(java.lang.Object);
    Code:
       0: aload_0
       1: aload_1
       2: checkcast     #61                 // class scala/util/Try
       5: invokevirtual #63                 // Method apply:(Lscala/util/Try;)Lscala/concurrent/Promise;
       8: areturn

  public scala.concurrent.Future$$anonfun$failed$1(scala.concurrent.Future<T>);
    Code:
       0: aload_0
       1: aload_2
       2: putfield      #25                 // Field p$1:Lscala/concurrent/Promise;
       5: aload_0
       6: invokespecial #69                 // Method scala/runtime/AbstractFunction1."<init>":()V
       9: return
}
