Compiled from "Authorization.kt"
public final class net.mamoe.mirai.api.http.adapter.http.feature.auth.Authorization implements io.ktor.application.ApplicationFeature<io.ktor.application.Application, kotlin.Unit, net.mamoe.mirai.api.http.adapter.http.feature.auth.Authorization> {
  public static final net.mamoe.mirai.api.http.adapter.http.feature.auth.Authorization INSTANCE;

  private static final io.ktor.util.AttributeKey<net.mamoe.mirai.api.http.adapter.http.feature.auth.Authorization> key;

  public static final io.ktor.util.AttributeKey<net.mamoe.mirai.api.http.context.session.Session> sessionAttr;

  private net.mamoe.mirai.api.http.adapter.http.feature.auth.Authorization();
    Code:
       0: aload_0
       1: invokespecial #11                 // Method java/lang/Object."<init>":()V
       4: return

  public net.mamoe.mirai.api.http.adapter.http.feature.auth.Authorization install(io.ktor.application.Application, kotlin.jvm.functions.Function1<? super kotlin.Unit, kotlin.Unit>);
    Code:
       0: aload_1
       1: ldc           #19                 // String pipeline
       3: invokestatic  #25                 // Method kotlin/jvm/internal/Intrinsics.checkNotNullParameter:(Ljava/lang/Object;Ljava/lang/String;)V
       6: aload_2
       7: ldc           #27                 // String configure
       9: invokestatic  #25                 // Method kotlin/jvm/internal/Intrinsics.checkNotNullParameter:(Ljava/lang/Object;Ljava/lang/String;)V
      12: aload_1
      13: getstatic     #33                 // Field io/ktor/application/ApplicationCallPipeline.ApplicationPhase:Lio/ktor/application/ApplicationCallPipeline$ApplicationPhase;
      16: invokevirtual #39                 // Method io/ktor/application/ApplicationCallPipeline$ApplicationPhase.getFeatures:()Lio/ktor/util/pipeline/PipelinePhase;
      19: new           #41                 // class net/mamoe/mirai/api/http/adapter/http/feature/auth/Authorization$install$1
      22: dup
      23: aconst_null
      24: invokespecial #44                 // Method net/mamoe/mirai/api/http/adapter/http/feature/auth/Authorization$install$1."<init>":(Lkotlin/coroutines/Continuation;)V
      27: checkcast     #46                 // class kotlin/jvm/functions/Function3
      30: invokevirtual #52                 // Method io/ktor/application/Application.intercept:(Lio/ktor/util/pipeline/PipelinePhase;Lkotlin/jvm/functions/Function3;)V
      33: aload_0
      34: areturn

  private final java.lang.String sessionKeyFromHeader(io.ktor.util.pipeline.PipelineContext<?, io.ktor.application.ApplicationCall>);
    Code:
       0: aload_1
       1: astore_2
       2: iconst_0
       3: istore_3
       4: aload_2
       5: invokeinterface #63,  1           // InterfaceMethod io/ktor/util/pipeline/PipelineContext.getContext:()Ljava/lang/Object;
      10: checkcast     #65                 // class io/ktor/application/ApplicationCall
      13: invokeinterface #69,  1           // InterfaceMethod io/ktor/application/ApplicationCall.getRequest:()Lio/ktor/request/ApplicationRequest;
      18: ldc           #71                 // String sessionKey
      20: invokestatic  #77                 // Method io/ktor/request/ApplicationRequestPropertiesKt.header:(Lio/ktor/request/ApplicationRequest;Ljava/lang/String;)Ljava/lang/String;
      23: areturn

  private final java.lang.String sessionKeyFromAuthorization(io.ktor.util.pipeline.PipelineContext<?, io.ktor.application.ApplicationCall>);
    Code:
       0: aload_1
       1: astore_2
       2: iconst_0
       3: istore_3
       4: aload_2
       5: invokeinterface #63,  1           // InterfaceMethod io/ktor/util/pipeline/PipelineContext.getContext:()Ljava/lang/Object;
      10: checkcast     #65                 // class io/ktor/application/ApplicationCall
      13: invokeinterface #69,  1           // InterfaceMethod io/ktor/application/ApplicationCall.getRequest:()Lio/ktor/request/ApplicationRequest;
      18: ldc           #85                 // String Authorization
      20: invokestatic  #77                 // Method io/ktor/request/ApplicationRequestPropertiesKt.header:(Lio/ktor/request/ApplicationRequest;Ljava/lang/String;)Ljava/lang/String;
      23: dup
      24: ifnonnull     32
      27: pop
      28: aconst_null
      29: goto          120
      32: astore_3
      33: iconst_0
      34: istore        4
      36: aload_3
      37: checkcast     #87                 // class java/lang/CharSequence
      40: iconst_1
      41: newarray       char
      43: astore        5
      45: aload         5
      47: iconst_0
      48: bipush        32
      50: castore
      51: aload         5
      53: iconst_0
      54: iconst_2
      55: iconst_2
      56: aconst_null
      57: invokestatic  #93                 // Method kotlin/text/StringsKt.split$default:(Ljava/lang/CharSequence;[CZIILjava/lang/Object;)Ljava/util/List;
      60: astore        6
      62: aload         6
      64: iconst_0
      65: invokeinterface #99,  2           // InterfaceMethod java/util/List.get:(I)Ljava/lang/Object;
      70: checkcast     #101                // class java/lang/String
      73: astore        5
      75: aload         6
      77: iconst_1
      78: invokeinterface #99,  2           // InterfaceMethod java/util/List.get:(I)Ljava/lang/Object;
      83: checkcast     #101                // class java/lang/String
      86: astore        7
      88: aload         5
      90: ldc           #103                // String session
      92: iconst_1
      93: invokestatic  #107                // Method kotlin/text/StringsKt.equals:(Ljava/lang/String;Ljava/lang/String;Z)Z
      96: ifne          110
      99: aload         5
     101: ldc           #71                 // String sessionKey
     103: iconst_1
     104: invokestatic  #107                // Method kotlin/text/StringsKt.equals:(Ljava/lang/String;Ljava/lang/String;Z)Z
     107: ifeq          115
     110: aload         7
     112: goto          119
     115: aconst_null
     116: checkcast     #101                // class java/lang/String
     119: areturn
     120: checkcast     #101                // class java/lang/String
     123: areturn

  public io.ktor.util.AttributeKey<net.mamoe.mirai.api.http.adapter.http.feature.auth.Authorization> getKey();
    Code:
       0: getstatic     #120                // Field key:Lio/ktor/util/AttributeKey;
       3: areturn

  public final net.mamoe.mirai.api.http.context.session.Session getHeaderSession(io.ktor.util.pipeline.PipelineContext<?, io.ktor.application.ApplicationCall>);
    Code:
       0: aload_1
       1: ldc           #126                // String <this>
       3: invokestatic  #25                 // Method kotlin/jvm/internal/Intrinsics.checkNotNullParameter:(Ljava/lang/Object;Ljava/lang/String;)V
       6: aload_1
       7: astore_2
       8: iconst_0
       9: istore_3
      10: aload_2
      11: invokeinterface #63,  1           // InterfaceMethod io/ktor/util/pipeline/PipelineContext.getContext:()Ljava/lang/Object;
      16: checkcast     #65                 // class io/ktor/application/ApplicationCall
      19: invokeinterface #130,  1          // InterfaceMethod io/ktor/application/ApplicationCall.getAttributes:()Lio/ktor/util/Attributes;
      24: getstatic     #133                // Field sessionAttr:Lio/ktor/util/AttributeKey;
      27: invokeinterface #139,  2          // InterfaceMethod io/ktor/util/Attributes.getOrNull:(Lio/ktor/util/AttributeKey;)Ljava/lang/Object;
      32: checkcast     #141                // class net/mamoe/mirai/api/http/context/session/Session
      35: areturn

  public java.lang.Object install(io.ktor.util.pipeline.Pipeline, kotlin.jvm.functions.Function1);
    Code:
       0: aload_0
       1: aload_1
       2: checkcast     #48                 // class io/ktor/application/Application
       5: aload_2
       6: invokevirtual #145                // Method install:(Lio/ktor/application/Application;Lkotlin/jvm/functions/Function1;)Lnet/mamoe/mirai/api/http/adapter/http/feature/auth/Authorization;
       9: areturn

  public static final java.lang.String access$sessionKeyFromHeader(net.mamoe.mirai.api.http.adapter.http.feature.auth.Authorization, io.ktor.util.pipeline.PipelineContext);
    Code:
       0: aload_0
       1: aload_1
       2: invokespecial #150                // Method sessionKeyFromHeader:(Lio/ktor/util/pipeline/PipelineContext;)Ljava/lang/String;
       5: areturn

  public static final java.lang.String access$sessionKeyFromAuthorization(net.mamoe.mirai.api.http.adapter.http.feature.auth.Authorization, io.ktor.util.pipeline.PipelineContext);
    Code:
       0: aload_0
       1: aload_1
       2: invokespecial #155                // Method sessionKeyFromAuthorization:(Lio/ktor/util/pipeline/PipelineContext;)Ljava/lang/String;
       5: areturn

  static {};
    Code:
       0: new           #2                  // class net/mamoe/mirai/api/http/adapter/http/feature/auth/Authorization
       3: dup
       4: invokespecial #157                // Method "<init>":()V
       7: putstatic     #160                // Field INSTANCE:Lnet/mamoe/mirai/api/http/adapter/http/feature/auth/Authorization;
      10: new           #162                // class io/ktor/util/AttributeKey
      13: dup
      14: ldc           #85                 // String Authorization
      16: invokespecial #165                // Method io/ktor/util/AttributeKey."<init>":(Ljava/lang/String;)V
      19: putstatic     #120                // Field key:Lio/ktor/util/AttributeKey;
      22: new           #162                // class io/ktor/util/AttributeKey
      25: dup
      26: ldc           #167                // String Session
      28: invokespecial #165                // Method io/ktor/util/AttributeKey."<init>":(Ljava/lang/String;)V
      31: putstatic     #133                // Field sessionAttr:Lio/ktor/util/AttributeKey;
      34: return
}
