Compiled from "ReadResourceHandler.java"
public class org.jboss.as.controller.operations.global.ReadResourceHandler extends org.jboss.as.controller.operations.global.GlobalOperationHandlers$AbstractMultiTargetHandler {
  private static final org.jboss.as.controller.SimpleAttributeDefinition ATTRIBUTES_ONLY;

  public static final org.jboss.as.controller.OperationDefinition DEFINITION;

  public static final org.jboss.as.controller.OperationStepHandler INSTANCE;

  private static final org.jboss.as.controller.SimpleAttributeDefinition RESOLVE;

  public static final org.jboss.as.controller.OperationDefinition RESOLVE_DEFINITION;

  public static final org.jboss.as.controller.OperationStepHandler RESOLVE_INSTANCE;

  private final org.jboss.as.controller.operations.validation.ParametersValidator validator;

  private final org.jboss.as.controller.OperationStepHandler overrideHandler;

  private final boolean resolvable;

  public org.jboss.as.controller.operations.global.ReadResourceHandler();
    Code:
       0: aload_0
       1: aconst_null
       2: aconst_null
       3: iconst_0
       4: iconst_0
       5: invokespecial #3                  // Method "<init>":(Lorg/jboss/as/controller/operations/global/FilteredData;Lorg/jboss/as/controller/OperationStepHandler;ZZ)V
       8: return

  public org.jboss.as.controller.operations.global.ReadResourceHandler(boolean);
    Code:
       0: aload_0
       1: aconst_null
       2: aconst_null
       3: iload_1
       4: iconst_0
       5: invokespecial #3                  // Method "<init>":(Lorg/jboss/as/controller/operations/global/FilteredData;Lorg/jboss/as/controller/OperationStepHandler;ZZ)V
       8: return

  org.jboss.as.controller.operations.global.ReadResourceHandler(org.jboss.as.controller.operations.global.FilteredData, org.jboss.as.controller.OperationStepHandler, boolean);
    Code:
       0: aload_0
       1: aload_1
       2: aload_2
       3: iload_3
       4: iconst_1
       5: invokespecial #3                  // Method "<init>":(Lorg/jboss/as/controller/operations/global/FilteredData;Lorg/jboss/as/controller/OperationStepHandler;ZZ)V
       8: return

  private org.jboss.as.controller.operations.global.ReadResourceHandler(org.jboss.as.controller.operations.global.FilteredData, org.jboss.as.controller.OperationStepHandler, boolean, boolean);
    Code:
       0: aload_0
       1: aload_1
       2: iload         4
       4: invokespecial #4                  // Method org/jboss/as/controller/operations/global/GlobalOperationHandlers$AbstractMultiTargetHandler."<init>":(Lorg/jboss/as/controller/operations/global/FilteredData;Z)V
       7: aload_0
       8: new           #5                  // class org/jboss/as/controller/operations/global/ReadResourceHandler$1
      11: dup
      12: aload_0
      13: invokespecial #6                  // Method org/jboss/as/controller/operations/global/ReadResourceHandler$1."<init>":(Lorg/jboss/as/controller/operations/global/ReadResourceHandler;)V
      16: putfield      #7                  // Field validator:Lorg/jboss/as/controller/operations/validation/ParametersValidator;
      19: aload_0
      20: aload_2
      21: putfield      #8                  // Field overrideHandler:Lorg/jboss/as/controller/OperationStepHandler;
      24: aload_0
      25: iload_3
      26: putfield      #2                  // Field resolvable:Z
      29: return

  void doExecute(org.jboss.as.controller.OperationContext, org.jboss.dmr.ModelNode, org.jboss.as.controller.operations.global.FilteredData, boolean) throws org.jboss.as.controller.OperationFailedException;
    Code:
       0: aload_3
       1: ifnonnull     15
       4: aload_0
       5: aload_1
       6: aload_2
       7: iload         4
       9: invokespecial #9                  // Method doExecuteInternal:(Lorg/jboss/as/controller/OperationContext;Lorg/jboss/dmr/ModelNode;Z)V
      12: goto          179
      15: aload_0
      16: getfield      #8                  // Field overrideHandler:Lorg/jboss/as/controller/OperationStepHandler;
      19: ifnonnull     33
      22: aload_0
      23: aload_1
      24: aload_2
      25: iload         4
      27: invokespecial #9                  // Method doExecuteInternal:(Lorg/jboss/as/controller/OperationContext;Lorg/jboss/dmr/ModelNode;Z)V
      30: goto          44
      33: aload_0
      34: getfield      #8                  // Field overrideHandler:Lorg/jboss/as/controller/OperationStepHandler;
      37: aload_1
      38: aload_2
      39: invokeinterface #10,  3           // InterfaceMethod org/jboss/as/controller/OperationStepHandler.execute:(Lorg/jboss/as/controller/OperationContext;Lorg/jboss/dmr/ModelNode;)V
      44: goto          179
      47: astore        5
      49: aload_0
      50: aload_1
      51: aload_2
      52: aload_3
      53: invokespecial #12                 // Method reportInaccesible:(Lorg/jboss/as/controller/OperationContext;Lorg/jboss/dmr/ModelNode;Lorg/jboss/as/controller/operations/global/FilteredData;)V
      56: getstatic     #13                 // Field org/jboss/as/controller/logging/ControllerLogger.MGMT_OP_LOGGER:Lorg/jboss/as/controller/logging/ControllerLogger;
      59: ldc           #14                 // String Caught ResourceNotAddressableException in %s
      61: aload_0
      62: invokeinterface #15,  3           // InterfaceMethod org/jboss/as/controller/logging/ControllerLogger.tracef:(Ljava/lang/String;Ljava/lang/Object;)V
      67: goto          179
      70: astore        5
      72: aload_1
      73: aload_2
      74: getstatic     #17                 // Field org/jboss/as/controller/access/Action$ActionEffect.ADDRESS:Lorg/jboss/as/controller/access/Action$ActionEffect;
      77: invokestatic  #18                 // Method java/util/EnumSet.of:(Ljava/lang/Enum;)Ljava/util/EnumSet;
      80: invokeinterface #19,  3           // InterfaceMethod org/jboss/as/controller/OperationContext.authorize:(Lorg/jboss/dmr/ModelNode;Ljava/util/Set;)Lorg/jboss/as/controller/access/AuthorizationResult;
      85: invokevirtual #20                 // Method org/jboss/as/controller/access/AuthorizationResult.getDecision:()Lorg/jboss/as/controller/access/AuthorizationResult$Decision;
      88: astore        6
      90: getstatic     #13                 // Field org/jboss/as/controller/logging/ControllerLogger.MGMT_OP_LOGGER:Lorg/jboss/as/controller/logging/ControllerLogger;
      93: ldc           #21                 // String Caught NoSuchResourceException in %s. Authorization decision is %s
      95: aload_0
      96: aload         6
      98: invokeinterface #22,  4           // InterfaceMethod org/jboss/as/controller/logging/ControllerLogger.tracef:(Ljava/lang/String;Ljava/lang/Object;Ljava/lang/Object;)V
     103: aload         6
     105: getstatic     #23                 // Field org/jboss/as/controller/access/AuthorizationResult$Decision.DENY:Lorg/jboss/as/controller/access/AuthorizationResult$Decision;
     108: if_acmpne     121
     111: aload_0
     112: aload_1
     113: aload_2
     114: aload_3
     115: invokespecial #12                 // Method reportInaccesible:(Lorg/jboss/as/controller/OperationContext;Lorg/jboss/dmr/ModelNode;Lorg/jboss/as/controller/operations/global/FilteredData;)V
     118: goto          129
     121: iload         4
     123: ifne          129
     126: aload         5
     128: athrow
     129: goto          179
     132: astore        5
     134: aload_2
     135: ldc           #25                 // String address
     137: invokevirtual #26                 // Method org/jboss/dmr/ModelNode.get:(Ljava/lang/String;)Lorg/jboss/dmr/ModelNode;
     140: invokestatic  #27                 // Method org/jboss/as/controller/PathAddress.pathAddress:(Lorg/jboss/dmr/ModelNode;)Lorg/jboss/as/controller/PathAddress;
     143: astore        6
     145: aload_3
     146: aload         6
     148: invokevirtual #28                 // Method org/jboss/as/controller/operations/global/FilteredData.addReadRestrictedResource:(Lorg/jboss/as/controller/PathAddress;)V
     151: aload_1
     152: invokeinterface #29,  1           // InterfaceMethod org/jboss/as/controller/OperationContext.getResult:()Lorg/jboss/dmr/ModelNode;
     157: new           #30                 // class org/jboss/dmr/ModelNode
     160: dup
     161: invokespecial #31                 // Method org/jboss/dmr/ModelNode."<init>":()V
     164: invokevirtual #32                 // Method org/jboss/dmr/ModelNode.set:(Lorg/jboss/dmr/ModelNode;)Lorg/jboss/dmr/ModelNode;
     167: pop
     168: getstatic     #13                 // Field org/jboss/as/controller/logging/ControllerLogger.MGMT_OP_LOGGER:Lorg/jboss/as/controller/logging/ControllerLogger;
     171: ldc           #33                 // String Caught UnauthorizedException in %s
     173: aload_0
     174: invokeinterface #15,  3           // InterfaceMethod org/jboss/as/controller/logging/ControllerLogger.tracef:(Ljava/lang/String;Ljava/lang/Object;)V
     179: return
    Exception table:
       from    to  target type
          15    44    47   Class org/jboss/as/controller/access/ResourceNotAddressableException
          15    44    70   Class org/jboss/as/controller/registry/Resource$NoSuchResourceException
          15    44   132   Class org/jboss/as/controller/UnauthorizedException

  private void reportInaccesible(org.jboss.as.controller.OperationContext, org.jboss.dmr.ModelNode, org.jboss.as.controller.operations.global.FilteredData);
    Code:
       0: aload_2
       1: ldc           #25                 // String address
       3: invokevirtual #26                 // Method org/jboss/dmr/ModelNode.get:(Ljava/lang/String;)Lorg/jboss/dmr/ModelNode;
       6: invokestatic  #27                 // Method org/jboss/as/controller/PathAddress.pathAddress:(Lorg/jboss/dmr/ModelNode;)Lorg/jboss/as/controller/PathAddress;
       9: astore        4
      11: aload_3
      12: aload         4
      14: invokevirtual #34                 // Method org/jboss/as/controller/operations/global/FilteredData.addAccessRestrictedResource:(Lorg/jboss/as/controller/PathAddress;)V
      17: aload_1
      18: invokeinterface #29,  1           // InterfaceMethod org/jboss/as/controller/OperationContext.getResult:()Lorg/jboss/dmr/ModelNode;
      23: new           #30                 // class org/jboss/dmr/ModelNode
      26: dup
      27: invokespecial #31                 // Method org/jboss/dmr/ModelNode."<init>":()V
      30: invokevirtual #32                 // Method org/jboss/dmr/ModelNode.set:(Lorg/jboss/dmr/ModelNode;)Lorg/jboss/dmr/ModelNode;
      33: pop
      34: return

  private void doExecuteInternal(org.jboss.as.controller.OperationContext, org.jboss.dmr.ModelNode, boolean) throws org.jboss.as.controller.OperationFailedException;
    Code:
       0: aload_0
       1: getfield      #7                  // Field validator:Lorg/jboss/as/controller/operations/validation/ParametersValidator;
       4: aload_2
       5: invokevirtual #35                 // Method org/jboss/as/controller/operations/validation/ParametersValidator.validate:(Lorg/jboss/dmr/ModelNode;)V
       8: aload_2
       9: ldc           #36                 // String operation
      11: invokevirtual #37                 // Method org/jboss/dmr/ModelNode.require:(Ljava/lang/String;)Lorg/jboss/dmr/ModelNode;
      14: invokevirtual #38                 // Method org/jboss/dmr/ModelNode.asString:()Ljava/lang/String;
      17: astore        4
      19: aload_1
      20: invokeinterface #39,  1           // InterfaceMethod org/jboss/as/controller/OperationContext.getCurrentAddress:()Lorg/jboss/as/controller/PathAddress;
      25: astore        5
      27: aload_1
      28: aload_2
      29: invokestatic  #40                 // Method org/jboss/as/controller/operations/global/GlobalOperationHandlers.getRecursive:(Lorg/jboss/as/controller/OperationContext;Lorg/jboss/dmr/ModelNode;)Z
      32: istore        6
      34: aload_2
      35: ldc           #41                 // String include-runtime
      37: invokevirtual #26                 // Method org/jboss/dmr/ModelNode.get:(Ljava/lang/String;)Lorg/jboss/dmr/ModelNode;
      40: iconst_0
      41: invokevirtual #42                 // Method org/jboss/dmr/ModelNode.asBoolean:(Z)Z
      44: istore        7
      46: aload_2
      47: ldc           #43                 // String proxies
      49: invokevirtual #26                 // Method org/jboss/dmr/ModelNode.get:(Ljava/lang/String;)Lorg/jboss/dmr/ModelNode;
      52: iconst_0
      53: invokevirtual #42                 // Method org/jboss/dmr/ModelNode.asBoolean:(Z)Z
      56: istore        8
      58: aload_2
      59: ldc           #44                 // String include-aliases
      61: invokevirtual #26                 // Method org/jboss/dmr/ModelNode.get:(Ljava/lang/String;)Lorg/jboss/dmr/ModelNode;
      64: iconst_0
      65: invokevirtual #42                 // Method org/jboss/dmr/ModelNode.asBoolean:(Z)Z
      68: istore        9
      70: aload_2
      71: ldc           #45                 // String include-defaults
      73: invokevirtual #26                 // Method org/jboss/dmr/ModelNode.get:(Ljava/lang/String;)Lorg/jboss/dmr/ModelNode;
      76: iconst_1
      77: invokevirtual #42                 // Method org/jboss/dmr/ModelNode.asBoolean:(Z)Z
      80: istore        10
      82: aload_2
      83: ldc           #46                 // String attributes-only
      85: invokevirtual #26                 // Method org/jboss/dmr/ModelNode.get:(Ljava/lang/String;)Lorg/jboss/dmr/ModelNode;
      88: iconst_0
      89: invokevirtual #42                 // Method org/jboss/dmr/ModelNode.asBoolean:(Z)Z
      92: istore        11
      94: getstatic     #47                 // Field RESOLVE:Lorg/jboss/as/controller/SimpleAttributeDefinition;
      97: aload_1
      98: aload_2
      99: invokevirtual #48                 // Method org/jboss/as/controller/SimpleAttributeDefinition.resolveModelAttribute:(Lorg/jboss/as/controller/OperationContext;Lorg/jboss/dmr/ModelNode;)Lorg/jboss/dmr/ModelNode;
     102: invokevirtual #49                 // Method org/jboss/dmr/ModelNode.asBoolean:()Z
     105: istore        12
     107: new           #50                 // class java/util/HashSet
     110: dup
     111: invokespecial #51                 // Method java/util/HashSet."<init>":()V
     114: astore        13
     116: new           #52                 // class java/util/HashMap
     119: dup
     120: invokespecial #53                 // Method java/util/HashMap."<init>":()V
     123: astore        14
     125: iload         7
     127: ifeq          140
     130: new           #52                 // class java/util/HashMap
     133: dup
     134: invokespecial #53                 // Method java/util/HashMap."<init>":()V
     137: goto          143
     140: invokestatic  #54                 // Method java/util/Collections.emptyMap:()Ljava/util/Map;
     143: astore        15
     145: new           #52                 // class java/util/HashMap
     148: dup
     149: invokespecial #53                 // Method java/util/HashMap."<init>":()V
     152: astore        16
     154: iload         6
     156: ifeq          169
     159: new           #55                 // class java/util/LinkedHashMap
     162: dup
     163: invokespecial #56                 // Method java/util/LinkedHashMap."<init>":()V
     166: goto          172
     169: invokestatic  #54                 // Method java/util/Collections.emptyMap:()Ljava/util/Map;
     172: astore        17
     174: aload_0
     175: invokevirtual #57                 // Method getFilteredData:()Lorg/jboss/as/controller/operations/global/FilteredData;
     178: astore        18
     180: aload         18
     182: ifnonnull     197
     185: new           #58                 // class org/jboss/as/controller/operations/global/FilteredData
     188: dup
     189: aload         5
     191: invokespecial #59                 // Method org/jboss/as/controller/operations/global/FilteredData."<init>":(Lorg/jboss/as/controller/PathAddress;)V
     194: goto          199
     197: aload         18
     199: astore        19
     201: new           #60                 // class org/jboss/as/controller/operations/global/ReadResourceHandler$ReadResourceAssemblyHandler
     204: dup
     205: aload         5
     207: aload         15
     209: aload         16
     211: aload         14
     213: aload         17
     215: aload         13
     217: aload         19
     219: iload_3
     220: aconst_null
     221: invokespecial #61                 // Method org/jboss/as/controller/operations/global/ReadResourceHandler$ReadResourceAssemblyHandler."<init>":(Lorg/jboss/as/controller/PathAddress;Ljava/util/Map;Ljava/util/Map;Ljava/util/Map;Ljava/util/Map;Ljava/util/Set;Lorg/jboss/as/controller/operations/global/FilteredData;ZLorg/jboss/as/controller/operations/global/ReadResourceHandler$1;)V
     224: astore        20
     226: aload_1
     227: aload         20
     229: iload         7
     231: ifeq          240
     234: getstatic     #62                 // Field org/jboss/as/controller/OperationContext$Stage.VERIFY:Lorg/jboss/as/controller/OperationContext$Stage;
     237: goto          243
     240: getstatic     #63                 // Field org/jboss/as/controller/OperationContext$Stage.MODEL:Lorg/jboss/as/controller/OperationContext$Stage;
     243: iconst_1
     244: invokeinterface #64,  4           // InterfaceMethod org/jboss/as/controller/OperationContext.addStep:(Lorg/jboss/as/controller/OperationStepHandler;Lorg/jboss/as/controller/OperationContext$Stage;Z)V
     249: aload_1
     250: invokeinterface #65,  1           // InterfaceMethod org/jboss/as/controller/OperationContext.getResourceRegistration:()Lorg/jboss/as/controller/registry/ImmutableManagementResourceRegistration;
     255: astore        21
     257: aload_1
     258: aload         21
     260: invokestatic  #66                 // Method nullSafeReadResource:(Lorg/jboss/as/controller/OperationContext;Lorg/jboss/as/controller/registry/ImmutableManagementResourceRegistration;)Lorg/jboss/as/controller/registry/Resource;
     263: astore        22
     265: aload         21
     267: ifnull        284
     270: aload_1
     271: aload         5
     273: aload         21
     275: aload         22
     277: aconst_null
     278: invokestatic  #67                 // Method org/jboss/as/controller/operations/global/GlobalOperationHandlers.getChildAddresses:(Lorg/jboss/as/controller/OperationContext;Lorg/jboss/as/controller/PathAddress;Lorg/jboss/as/controller/registry/ImmutableManagementResourceRegistration;Lorg/jboss/as/controller/registry/Resource;Ljava/lang/String;)Ljava/util/Map;
     281: goto          287
     284: invokestatic  #54                 // Method java/util/Collections.emptyMap:()Ljava/util/Map;
     287: astore        23
     289: iload         11
     291: ifne          884
     294: aload         23
     296: invokeinterface #68,  1           // InterfaceMethod java/util/Map.entrySet:()Ljava/util/Set;
     301: invokeinterface #69,  1           // InterfaceMethod java/util/Set.iterator:()Ljava/util/Iterator;
     306: astore        24
     308: aload         24
     310: invokeinterface #70,  1           // InterfaceMethod java/util/Iterator.hasNext:()Z
     315: ifeq          884
     318: aload         24
     320: invokeinterface #71,  1           // InterfaceMethod java/util/Iterator.next:()Ljava/lang/Object;
     325: checkcast     #72                 // class java/util/Map$Entry
     328: astore        25
     330: aload         25
     332: invokeinterface #73,  1           // InterfaceMethod java/util/Map$Entry.getKey:()Ljava/lang/Object;
     337: checkcast     #74                 // class java/lang/String
     340: astore        26
     342: aload         13
     344: aload         26
     346: invokeinterface #75,  2           // InterfaceMethod java/util/Set.add:(Ljava/lang/Object;)Z
     351: pop
     352: iload         9
     354: ifne          406
     357: aload         25
     359: invokeinterface #76,  1           // InterfaceMethod java/util/Map$Entry.getValue:()Ljava/lang/Object;
     364: ifnull        385
     367: aload         25
     369: invokeinterface #76,  1           // InterfaceMethod java/util/Map$Entry.getValue:()Ljava/lang/Object;
     374: checkcast     #77                 // class java/util/Set
     377: invokeinterface #78,  1           // InterfaceMethod java/util/Set.isEmpty:()Z
     382: ifeq          406
     385: aload_0
     386: aload         21
     388: aload         26
     390: invokespecial #79                 // Method isGlobalAlias:(Lorg/jboss/as/controller/registry/ImmutableManagementResourceRegistration;Ljava/lang/String;)Z
     393: ifeq          406
     396: aload         13
     398: aload         26
     400: invokeinterface #80,  2           // InterfaceMethod java/util/Set.remove:(Ljava/lang/Object;)Z
     405: pop
     406: aload         25
     408: invokeinterface #76,  1           // InterfaceMethod java/util/Map$Entry.getValue:()Ljava/lang/Object;
     413: checkcast     #77                 // class java/util/Set
     416: invokeinterface #69,  1           // InterfaceMethod java/util/Set.iterator:()Ljava/util/Iterator;
     421: astore        27
     423: aload         27
     425: invokeinterface #70,  1           // InterfaceMethod java/util/Iterator.hasNext:()Z
     430: ifeq          881
     433: aload         27
     435: invokeinterface #71,  1           // InterfaceMethod java/util/Iterator.next:()Ljava/lang/Object;
     440: checkcast     #74                 // class java/lang/String
     443: astore        28
     445: aload         26
     447: aload         28
     449: invokestatic  #81                 // Method org/jboss/as/controller/PathElement.pathElement:(Ljava/lang/String;Ljava/lang/String;)Lorg/jboss/as/controller/PathElement;
     452: astore        29
     454: aload         5
     456: iconst_1
     457: anewarray     #82                 // class org/jboss/as/controller/PathElement
     460: dup
     461: iconst_0
     462: aload         29
     464: aastore
     465: invokevirtual #83                 // Method org/jboss/as/controller/PathAddress.append:([Lorg/jboss/as/controller/PathElement;)Lorg/jboss/as/controller/PathAddress;
     468: astore        30
     470: ldc           #84                 // String read-resource
     472: aload         30
     474: invokestatic  #85                 // Method org/jboss/as/controller/operations/common/Util.createEmptyOperation:(Ljava/lang/String;Lorg/jboss/as/controller/PathAddress;)Lorg/jboss/dmr/ModelNode;
     477: astore        31
     479: iconst_1
     480: anewarray     #82                 // class org/jboss/as/controller/PathElement
     483: dup
     484: iconst_0
     485: aload         29
     487: aastore
     488: invokestatic  #86                 // Method org/jboss/as/controller/PathAddress.pathAddress:([Lorg/jboss/as/controller/PathElement;)Lorg/jboss/as/controller/PathAddress;
     491: astore        32
     493: iload         6
     495: ifeq          777
     498: aload         21
     500: aload         32
     502: invokeinterface #87,  2           // InterfaceMethod org/jboss/as/controller/registry/ImmutableManagementResourceRegistration.getSubModel:(Lorg/jboss/as/controller/PathAddress;)Lorg/jboss/as/controller/registry/ImmutableManagementResourceRegistration;
     507: astore        33
     509: aload         33
     511: ifnonnull     534
     514: new           #88                 // class org/jboss/as/controller/OperationFailedException
     517: dup
     518: getstatic     #89                 // Field org/jboss/as/controller/logging/ControllerLogger.ROOT_LOGGER:Lorg/jboss/as/controller/logging/ControllerLogger;
     521: aload         26
     523: aload         28
     525: invokeinterface #90,  3           // InterfaceMethod org/jboss/as/controller/logging/ControllerLogger.noChildRegistry:(Ljava/lang/String;Ljava/lang/String;)Ljava/lang/String;
     530: invokespecial #91                 // Method org/jboss/as/controller/OperationFailedException."<init>":(Ljava/lang/String;)V
     533: athrow
     534: aload         33
     536: invokeinterface #92,  1           // InterfaceMethod org/jboss/as/controller/registry/ImmutableManagementResourceRegistration.isRemote:()Z
     541: istore        34
     543: aload         33
     545: invokeinterface #93,  1           // InterfaceMethod org/jboss/as/controller/registry/ImmutableManagementResourceRegistration.isRuntimeOnly:()Z
     550: istore        35
     552: iload         35
     554: ifeq          577
     557: iload         7
     559: ifeq          567
     562: iload         34
     564: ifeq          577
     567: iload         8
     569: ifeq          581
     572: iload         34
     574: ifeq          581
     577: iconst_1
     578: goto          582
     581: iconst_0
     582: istore        36
     584: iload         9
     586: ifne          612
     589: aload         33
     591: invokeinterface #94,  1           // InterfaceMethod org/jboss/as/controller/registry/ImmutableManagementResourceRegistration.isAlias:()Z
     596: ifeq          612
     599: aload         13
     601: aload         26
     603: invokeinterface #80,  2           // InterfaceMethod java/util/Set.remove:(Ljava/lang/Object;)Z
     608: pop
     609: iconst_0
     610: istore        36
     612: iload         36
     614: ifeq          774
     617: aload         13
     619: aload         26
     621: invokeinterface #80,  2           // InterfaceMethod java/util/Set.remove:(Ljava/lang/Object;)Z
     626: pop
     627: aload_1
     628: aload_2
     629: aload         31
     631: invokestatic  #95                 // Method org/jboss/as/controller/operations/global/GlobalOperationHandlers.setNextRecursive:(Lorg/jboss/as/controller/OperationContext;Lorg/jboss/dmr/ModelNode;Lorg/jboss/dmr/ModelNode;)V
     634: aload         31
     636: ldc           #43                 // String proxies
     638: invokevirtual #26                 // Method org/jboss/dmr/ModelNode.get:(Ljava/lang/String;)Lorg/jboss/dmr/ModelNode;
     641: iload         8
     643: invokevirtual #96                 // Method org/jboss/dmr/ModelNode.set:(Z)Lorg/jboss/dmr/ModelNode;
     646: pop
     647: aload         31
     649: ldc           #41                 // String include-runtime
     651: invokevirtual #26                 // Method org/jboss/dmr/ModelNode.get:(Ljava/lang/String;)Lorg/jboss/dmr/ModelNode;
     654: iload         7
     656: invokevirtual #96                 // Method org/jboss/dmr/ModelNode.set:(Z)Lorg/jboss/dmr/ModelNode;
     659: pop
     660: aload         31
     662: ldc           #44                 // String include-aliases
     664: invokevirtual #26                 // Method org/jboss/dmr/ModelNode.get:(Ljava/lang/String;)Lorg/jboss/dmr/ModelNode;
     667: iload         9
     669: invokevirtual #96                 // Method org/jboss/dmr/ModelNode.set:(Z)Lorg/jboss/dmr/ModelNode;
     672: pop
     673: aload         31
     675: ldc           #45                 // String include-defaults
     677: invokevirtual #26                 // Method org/jboss/dmr/ModelNode.get:(Ljava/lang/String;)Lorg/jboss/dmr/ModelNode;
     680: iload         10
     682: invokevirtual #96                 // Method org/jboss/dmr/ModelNode.set:(Z)Lorg/jboss/dmr/ModelNode;
     685: pop
     686: new           #30                 // class org/jboss/dmr/ModelNode
     689: dup
     690: invokespecial #31                 // Method org/jboss/dmr/ModelNode."<init>":()V
     693: astore        37
     695: aload         17
     697: aload         29
     699: aload         37
     701: invokeinterface #97,  3           // InterfaceMethod java/util/Map.put:(Ljava/lang/Object;Ljava/lang/Object;)Ljava/lang/Object;
     706: pop
     707: aload         33
     709: getstatic     #98                 // Field org/jboss/as/controller/PathAddress.EMPTY_ADDRESS:Lorg/jboss/as/controller/PathAddress;
     712: aload         4
     714: invokeinterface #99,  3           // InterfaceMethod org/jboss/as/controller/registry/ImmutableManagementResourceRegistration.getOperationHandler:(Lorg/jboss/as/controller/PathAddress;Ljava/lang/String;)Lorg/jboss/as/controller/OperationStepHandler;
     719: astore        38
     721: aload         38
     723: ifnull        741
     726: aload         38
     728: invokevirtual #100                // Method java/lang/Object.getClass:()Ljava/lang/Class;
     731: aload_0
     732: invokevirtual #100                // Method java/lang/Object.getClass:()Ljava/lang/Class;
     735: if_acmpne     741
     738: aconst_null
     739: astore        38
     741: new           #101                // class org/jboss/as/controller/operations/global/ReadResourceHandler
     744: dup
     745: aload         19
     747: aload         38
     749: aload_0
     750: getfield      #2                  // Field resolvable:Z
     753: invokespecial #102                // Method "<init>":(Lorg/jboss/as/controller/operations/global/FilteredData;Lorg/jboss/as/controller/OperationStepHandler;Z)V
     756: astore        39
     758: aload_1
     759: aload         37
     761: aload         31
     763: aload         39
     765: getstatic     #63                 // Field org/jboss/as/controller/OperationContext$Stage.MODEL:Lorg/jboss/as/controller/OperationContext$Stage;
     768: iconst_1
     769: invokeinterface #103,  6          // InterfaceMethod org/jboss/as/controller/OperationContext.addStep:(Lorg/jboss/dmr/ModelNode;Lorg/jboss/dmr/ModelNode;Lorg/jboss/as/controller/OperationStepHandler;Lorg/jboss/as/controller/OperationContext$Stage;Z)V
     774: goto          878
     777: aload_1
     778: aload         31
     780: getstatic     #17                 // Field org/jboss/as/controller/access/Action$ActionEffect.ADDRESS:Lorg/jboss/as/controller/access/Action$ActionEffect;
     783: invokestatic  #18                 // Method java/util/EnumSet.of:(Ljava/lang/Enum;)Ljava/util/EnumSet;
     786: invokeinterface #19,  3           // InterfaceMethod org/jboss/as/controller/OperationContext.authorize:(Lorg/jboss/dmr/ModelNode;Ljava/util/Set;)Lorg/jboss/as/controller/access/AuthorizationResult;
     791: astore        33
     793: aload         33
     795: invokevirtual #20                 // Method org/jboss/as/controller/access/AuthorizationResult.getDecision:()Lorg/jboss/as/controller/access/AuthorizationResult$Decision;
     798: getstatic     #23                 // Field org/jboss/as/controller/access/AuthorizationResult$Decision.DENY:Lorg/jboss/as/controller/access/AuthorizationResult$Decision;
     801: if_acmpne     814
     804: aload         19
     806: aload         30
     808: invokevirtual #34                 // Method org/jboss/as/controller/operations/global/FilteredData.addAccessRestrictedResource:(Lorg/jboss/as/controller/PathAddress;)V
     811: goto          878
     814: aload         14
     816: aload         26
     818: invokeinterface #104,  2          // InterfaceMethod java/util/Map.get:(Ljava/lang/Object;)Ljava/lang/Object;
     823: checkcast     #30                 // class org/jboss/dmr/ModelNode
     826: astore        34
     828: aload         34
     830: ifnonnull     870
     833: aload         13
     835: aload         26
     837: invokeinterface #80,  2           // InterfaceMethod java/util/Set.remove:(Ljava/lang/Object;)Z
     842: pop
     843: new           #30                 // class org/jboss/dmr/ModelNode
     846: dup
     847: invokespecial #31                 // Method org/jboss/dmr/ModelNode."<init>":()V
     850: astore        34
     852: aload         34
     854: invokevirtual #105                // Method org/jboss/dmr/ModelNode.setEmptyObject:()Lorg/jboss/dmr/ModelNode;
     857: pop
     858: aload         14
     860: aload         26
     862: aload         34
     864: invokeinterface #97,  3           // InterfaceMethod java/util/Map.put:(Ljava/lang/Object;Ljava/lang/Object;)Ljava/lang/Object;
     869: pop
     870: aload         34
     872: aload         28
     874: invokevirtual #26                 // Method org/jboss/dmr/ModelNode.get:(Ljava/lang/String;)Lorg/jboss/dmr/ModelNode;
     877: pop
     878: goto          423
     881: goto          308
     884: aload         21
     886: ifnull        902
     889: aload         21
     891: getstatic     #98                 // Field org/jboss/as/controller/PathAddress.EMPTY_ADDRESS:Lorg/jboss/as/controller/PathAddress;
     894: invokeinterface #106,  2          // InterfaceMethod org/jboss/as/controller/registry/ImmutableManagementResourceRegistration.getAttributeNames:(Lorg/jboss/as/controller/PathAddress;)Ljava/util/Set;
     899: goto          905
     902: invokestatic  #107                // Method java/util/Collections.emptySet:()Ljava/util/Set;
     905: astore        24
     907: aload         24
     909: invokeinterface #69,  1           // InterfaceMethod java/util/Set.iterator:()Ljava/util/Iterator;
     914: astore        25
     916: aload         25
     918: invokeinterface #70,  1           // InterfaceMethod java/util/Iterator.hasNext:()Z
     923: ifeq          1066
     926: aload         25
     928: invokeinterface #71,  1           // InterfaceMethod java/util/Iterator.next:()Ljava/lang/Object;
     933: checkcast     #74                 // class java/lang/String
     936: astore        26
     938: aload         21
     940: getstatic     #98                 // Field org/jboss/as/controller/PathAddress.EMPTY_ADDRESS:Lorg/jboss/as/controller/PathAddress;
     943: aload         26
     945: invokeinterface #108,  3          // InterfaceMethod org/jboss/as/controller/registry/ImmutableManagementResourceRegistration.getAttributeAccess:(Lorg/jboss/as/controller/PathAddress;Ljava/lang/String;)Lorg/jboss/as/controller/registry/AttributeAccess;
     950: astore        27
     952: iload         9
     954: ifne          973
     957: aload         27
     959: invokevirtual #109                // Method org/jboss/as/controller/registry/AttributeAccess.getFlags:()Ljava/util/Set;
     962: getstatic     #110                // Field org/jboss/as/controller/registry/AttributeAccess$Flag.ALIAS:Lorg/jboss/as/controller/registry/AttributeAccess$Flag;
     965: invokeinterface #111,  2          // InterfaceMethod java/util/Set.contains:(Ljava/lang/Object;)Z
     970: ifne          1063
     973: iload         7
     975: ifne          989
     978: aload         27
     980: invokevirtual #112                // Method org/jboss/as/controller/registry/AttributeAccess.getStorageType:()Lorg/jboss/as/controller/registry/AttributeAccess$Storage;
     983: getstatic     #113                // Field org/jboss/as/controller/registry/AttributeAccess$Storage.CONFIGURATION:Lorg/jboss/as/controller/registry/AttributeAccess$Storage;
     986: if_acmpne     1063
     989: aload         27
     991: invokevirtual #114                // Method org/jboss/as/controller/registry/AttributeAccess.getAccessType:()Lorg/jboss/as/controller/registry/AttributeAccess$AccessType;
     994: getstatic     #115                // Field org/jboss/as/controller/registry/AttributeAccess$AccessType.METRIC:Lorg/jboss/as/controller/registry/AttributeAccess$AccessType;
     997: if_acmpne     1005
    1000: aload         15
    1002: goto          1007
    1005: aload         16
    1007: astore        28
    1009: aload         27
    1011: invokevirtual #116                // Method org/jboss/as/controller/registry/AttributeAccess.getAttributeDefinition:()Lorg/jboss/as/controller/AttributeDefinition;
    1014: astore        29
    1016: aload         29
    1018: ifnonnull     1033
    1021: new           #117                // class org/jboss/as/controller/AttributeDefinition$NameAndGroup
    1024: dup
    1025: aload         26
    1027: invokespecial #118                // Method org/jboss/as/controller/AttributeDefinition$NameAndGroup."<init>":(Ljava/lang/String;)V
    1030: goto          1042
    1033: new           #117                // class org/jboss/as/controller/AttributeDefinition$NameAndGroup
    1036: dup
    1037: aload         29
    1039: invokespecial #119                // Method org/jboss/as/controller/AttributeDefinition$NameAndGroup."<init>":(Lorg/jboss/as/controller/AttributeDefinition;)V
    1042: astore        30
    1044: aload_0
    1045: aload_1
    1046: aload         5
    1048: iload         10
    1050: iload         12
    1052: aload         19
    1054: aload         21
    1056: aload         30
    1058: aload         28
    1060: invokespecial #120                // Method addReadAttributeStep:(Lorg/jboss/as/controller/OperationContext;Lorg/jboss/as/controller/PathAddress;ZZLorg/jboss/as/controller/operations/global/FilteredData;Lorg/jboss/as/controller/registry/ImmutableManagementResourceRegistration;Lorg/jboss/as/controller/AttributeDefinition$NameAndGroup;Ljava/util/Map;)V
    1063: goto          916
    1066: aload         22
    1068: invokeinterface #121,  1          // InterfaceMethod org/jboss/as/controller/registry/Resource.getModel:()Lorg/jboss/dmr/ModelNode;
    1073: astore        25
    1075: aload         25
    1077: invokevirtual #122                // Method org/jboss/dmr/ModelNode.isDefined:()Z
    1080: ifeq          1186
    1083: aload         25
    1085: invokevirtual #123                // Method org/jboss/dmr/ModelNode.keys:()Ljava/util/Set;
    1088: invokeinterface #69,  1           // InterfaceMethod java/util/Set.iterator:()Ljava/util/Iterator;
    1093: astore        26
    1095: aload         26
    1097: invokeinterface #70,  1           // InterfaceMethod java/util/Iterator.hasNext:()Z
    1102: ifeq          1186
    1105: aload         26
    1107: invokeinterface #71,  1           // InterfaceMethod java/util/Iterator.next:()Ljava/lang/Object;
    1112: checkcast     #74                 // class java/lang/String
    1115: astore        27
    1117: new           #117                // class org/jboss/as/controller/AttributeDefinition$NameAndGroup
    1120: dup
    1121: aload         27
    1123: invokespecial #118                // Method org/jboss/as/controller/AttributeDefinition$NameAndGroup."<init>":(Ljava/lang/String;)V
    1126: astore        28
    1128: aload         16
    1130: aload         28
    1132: invokeinterface #124,  2          // InterfaceMethod java/util/Map.containsKey:(Ljava/lang/Object;)Z
    1137: ifne          1183
    1140: aload         23
    1142: aload         27
    1144: invokeinterface #124,  2          // InterfaceMethod java/util/Map.containsKey:(Ljava/lang/Object;)Z
    1149: ifne          1183
    1152: aload         15
    1154: aload         28
    1156: invokeinterface #124,  2          // InterfaceMethod java/util/Map.containsKey:(Ljava/lang/Object;)Z
    1161: ifne          1183
    1164: aload_0
    1165: aload_1
    1166: aload         5
    1168: iload         10
    1170: iload         12
    1172: aload         19
    1174: aload         21
    1176: aload         28
    1178: aload         16
    1180: invokespecial #120                // Method addReadAttributeStep:(Lorg/jboss/as/controller/OperationContext;Lorg/jboss/as/controller/PathAddress;ZZLorg/jboss/as/controller/operations/global/FilteredData;Lorg/jboss/as/controller/registry/ImmutableManagementResourceRegistration;Lorg/jboss/as/controller/AttributeDefinition$NameAndGroup;Ljava/util/Map;)V
    1183: goto          1095
    1186: iload         10
    1188: ifeq          1389
    1191: aload         21
    1193: getstatic     #98                 // Field org/jboss/as/controller/PathAddress.EMPTY_ADDRESS:Lorg/jboss/as/controller/PathAddress;
    1196: invokeinterface #125,  2          // InterfaceMethod org/jboss/as/controller/registry/ImmutableManagementResourceRegistration.getModelDescription:(Lorg/jboss/as/controller/PathAddress;)Lorg/jboss/as/controller/descriptions/DescriptionProvider;
    1201: astore        26
    1203: aload_1
    1204: aload_2
    1205: invokestatic  #126                // Method org/jboss/as/controller/operations/global/GlobalOperationHandlers.getLocale:(Lorg/jboss/as/controller/OperationContext;Lorg/jboss/dmr/ModelNode;)Ljava/util/Locale;
    1208: astore        27
    1210: aload         26
    1212: aload         27
    1214: invokeinterface #127,  2          // InterfaceMethod org/jboss/as/controller/descriptions/DescriptionProvider.getModelDescription:(Ljava/util/Locale;)Lorg/jboss/dmr/ModelNode;
    1219: astore        28
    1221: aload         28
    1223: invokevirtual #122                // Method org/jboss/dmr/ModelNode.isDefined:()Z
    1226: ifeq          1389
    1229: aload         28
    1231: ldc           #128                // String attributes
    1233: invokevirtual #129                // Method org/jboss/dmr/ModelNode.hasDefined:(Ljava/lang/String;)Z
    1236: ifeq          1389
    1239: aload         28
    1241: ldc           #128                // String attributes
    1243: invokevirtual #26                 // Method org/jboss/dmr/ModelNode.get:(Ljava/lang/String;)Lorg/jboss/dmr/ModelNode;
    1246: invokevirtual #123                // Method org/jboss/dmr/ModelNode.keys:()Ljava/util/Set;
    1249: invokeinterface #69,  1           // InterfaceMethod java/util/Set.iterator:()Ljava/util/Iterator;
    1254: astore        29
    1256: aload         29
    1258: invokeinterface #70,  1           // InterfaceMethod java/util/Iterator.hasNext:()Z
    1263: ifeq          1389
    1266: aload         29
    1268: invokeinterface #71,  1           // InterfaceMethod java/util/Iterator.next:()Ljava/lang/Object;
    1273: checkcast     #74                 // class java/lang/String
    1276: astore        30
    1278: new           #117                // class org/jboss/as/controller/AttributeDefinition$NameAndGroup
    1281: dup
    1282: aload         30
    1284: invokespecial #118                // Method org/jboss/as/controller/AttributeDefinition$NameAndGroup."<init>":(Ljava/lang/String;)V
    1287: astore        31
    1289: aload         23
    1291: aload         30
    1293: invokeinterface #124,  2          // InterfaceMethod java/util/Map.containsKey:(Ljava/lang/Object;)Z
    1298: ifne          1386
    1301: aload         16
    1303: aload         31
    1305: invokeinterface #124,  2          // InterfaceMethod java/util/Map.containsKey:(Ljava/lang/Object;)Z
    1310: ifne          1386
    1313: aload         15
    1315: aload         31
    1317: invokeinterface #124,  2          // InterfaceMethod java/util/Map.containsKey:(Ljava/lang/Object;)Z
    1322: ifne          1386
    1325: aload         28
    1327: ldc           #128                // String attributes
    1329: invokevirtual #26                 // Method org/jboss/dmr/ModelNode.get:(Ljava/lang/String;)Lorg/jboss/dmr/ModelNode;
    1332: aload         30
    1334: invokevirtual #129                // Method org/jboss/dmr/ModelNode.hasDefined:(Ljava/lang/String;)Z
    1337: ifeq          1386
    1340: aload         28
    1342: iconst_2
    1343: anewarray     #74                 // class java/lang/String
    1346: dup
    1347: iconst_0
    1348: ldc           #128                // String attributes
    1350: aastore
    1351: dup
    1352: iconst_1
    1353: aload         30
    1355: aastore
    1356: invokevirtual #130                // Method org/jboss/dmr/ModelNode.get:([Ljava/lang/String;)Lorg/jboss/dmr/ModelNode;
    1359: ldc           #131                // String default
    1361: invokevirtual #129                // Method org/jboss/dmr/ModelNode.hasDefined:(Ljava/lang/String;)Z
    1364: ifeq          1386
    1367: aload_0
    1368: aload_1
    1369: aload         5
    1371: iload         10
    1373: iload         12
    1375: aload         19
    1377: aload         21
    1379: aload         31
    1381: aload         16
    1383: invokespecial #120                // Method addReadAttributeStep:(Lorg/jboss/as/controller/OperationContext;Lorg/jboss/as/controller/PathAddress;ZZLorg/jboss/as/controller/operations/global/FilteredData;Lorg/jboss/as/controller/registry/ImmutableManagementResourceRegistration;Lorg/jboss/as/controller/AttributeDefinition$NameAndGroup;Ljava/util/Map;)V
    1386: goto          1256
    1389: return

  private boolean isSingletonResource(org.jboss.as.controller.registry.ImmutableManagementResourceRegistration, java.lang.String);
    Code:
       0: aload_1
       1: iconst_1
       2: anewarray     #82                 // class org/jboss/as/controller/PathElement
       5: dup
       6: iconst_0
       7: aload_2
       8: invokestatic  #132                // Method org/jboss/as/controller/PathElement.pathElement:(Ljava/lang/String;)Lorg/jboss/as/controller/PathElement;
      11: aastore
      12: invokestatic  #86                 // Method org/jboss/as/controller/PathAddress.pathAddress:([Lorg/jboss/as/controller/PathElement;)Lorg/jboss/as/controller/PathAddress;
      15: invokeinterface #87,  2           // InterfaceMethod org/jboss/as/controller/registry/ImmutableManagementResourceRegistration.getSubModel:(Lorg/jboss/as/controller/PathAddress;)Lorg/jboss/as/controller/registry/ImmutableManagementResourceRegistration;
      20: ifnonnull     27
      23: iconst_1
      24: goto          28
      27: iconst_0
      28: ireturn

  private boolean isGlobalAlias(org.jboss.as.controller.registry.ImmutableManagementResourceRegistration, java.lang.String);
    Code:
       0: aload_0
       1: aload_1
       2: aload_2
       3: invokespecial #133                // Method isSingletonResource:(Lorg/jboss/as/controller/registry/ImmutableManagementResourceRegistration;Ljava/lang/String;)Z
       6: ifeq          136
       9: aload_1
      10: getstatic     #98                 // Field org/jboss/as/controller/PathAddress.EMPTY_ADDRESS:Lorg/jboss/as/controller/PathAddress;
      13: invokeinterface #134,  2          // InterfaceMethod org/jboss/as/controller/registry/ImmutableManagementResourceRegistration.getChildAddresses:(Lorg/jboss/as/controller/PathAddress;)Ljava/util/Set;
      18: astore_3
      19: iconst_0
      20: istore        4
      22: iconst_1
      23: istore        5
      25: aload_3
      26: invokeinterface #69,  1           // InterfaceMethod java/util/Set.iterator:()Ljava/util/Iterator;
      31: astore        6
      33: aload         6
      35: invokeinterface #70,  1           // InterfaceMethod java/util/Iterator.hasNext:()Z
      40: ifeq          120
      43: aload         6
      45: invokeinterface #71,  1           // InterfaceMethod java/util/Iterator.next:()Ljava/lang/Object;
      50: checkcast     #82                 // class org/jboss/as/controller/PathElement
      53: astore        7
      55: aload         7
      57: invokevirtual #135                // Method org/jboss/as/controller/PathElement.getKey:()Ljava/lang/String;
      60: aload_2
      61: invokevirtual #136                // Method java/lang/String.equals:(Ljava/lang/Object;)Z
      64: ifeq          117
      67: iconst_1
      68: istore        4
      70: aload_1
      71: iconst_1
      72: anewarray     #82                 // class org/jboss/as/controller/PathElement
      75: dup
      76: iconst_0
      77: aload         7
      79: aastore
      80: invokestatic  #86                 // Method org/jboss/as/controller/PathAddress.pathAddress:([Lorg/jboss/as/controller/PathElement;)Lorg/jboss/as/controller/PathAddress;
      83: invokeinterface #87,  2           // InterfaceMethod org/jboss/as/controller/registry/ImmutableManagementResourceRegistration.getSubModel:(Lorg/jboss/as/controller/PathAddress;)Lorg/jboss/as/controller/registry/ImmutableManagementResourceRegistration;
      88: astore        8
      90: iload         5
      92: ifeq          114
      95: aload         8
      97: ifnull        114
     100: aload         8
     102: invokeinterface #94,  1           // InterfaceMethod org/jboss/as/controller/registry/ImmutableManagementResourceRegistration.isAlias:()Z
     107: ifeq          114
     110: iconst_1
     111: goto          115
     114: iconst_0
     115: istore        5
     117: goto          33
     120: iload         4
     122: ifeq          134
     125: iload         5
     127: ifeq          134
     130: iconst_1
     131: goto          135
     134: iconst_0
     135: ireturn
     136: aload_1
     137: iconst_1
     138: anewarray     #82                 // class org/jboss/as/controller/PathElement
     141: dup
     142: iconst_0
     143: aload_2
     144: invokestatic  #132                // Method org/jboss/as/controller/PathElement.pathElement:(Ljava/lang/String;)Lorg/jboss/as/controller/PathElement;
     147: aastore
     148: invokestatic  #86                 // Method org/jboss/as/controller/PathAddress.pathAddress:([Lorg/jboss/as/controller/PathElement;)Lorg/jboss/as/controller/PathAddress;
     151: invokeinterface #87,  2           // InterfaceMethod org/jboss/as/controller/registry/ImmutableManagementResourceRegistration.getSubModel:(Lorg/jboss/as/controller/PathAddress;)Lorg/jboss/as/controller/registry/ImmutableManagementResourceRegistration;
     156: invokeinterface #94,  1           // InterfaceMethod org/jboss/as/controller/registry/ImmutableManagementResourceRegistration.isAlias:()Z
     161: ireturn

  private void addReadAttributeStep(org.jboss.as.controller.OperationContext, org.jboss.as.controller.PathAddress, boolean, boolean, org.jboss.as.controller.operations.global.FilteredData, org.jboss.as.controller.registry.ImmutableManagementResourceRegistration, org.jboss.as.controller.AttributeDefinition$NameAndGroup, java.util.Map<org.jboss.as.controller.AttributeDefinition$NameAndGroup, org.jboss.as.controller.operations.global.GlobalOperationHandlers$AvailableResponse>);
    Code:
       0: aload         6
       2: getstatic     #98                 // Field org/jboss/as/controller/PathAddress.EMPTY_ADDRESS:Lorg/jboss/as/controller/PathAddress;
       5: ldc           #137                // String read-attribute
       7: invokeinterface #99,  3           // InterfaceMethod org/jboss/as/controller/registry/ImmutableManagementResourceRegistration.getOperationHandler:(Lorg/jboss/as/controller/PathAddress;Ljava/lang/String;)Lorg/jboss/as/controller/OperationStepHandler;
      12: astore        9
      14: aload         9
      16: ifnull        38
      19: aload         9
      21: getstatic     #138                // Field org/jboss/as/controller/operations/global/ReadAttributeHandler.INSTANCE:Lorg/jboss/as/controller/OperationStepHandler;
      24: if_acmpeq     35
      27: aload         9
      29: getstatic     #139                // Field org/jboss/as/controller/operations/global/ReadAttributeHandler.RESOLVE_INSTANCE:Lorg/jboss/as/controller/OperationStepHandler;
      32: if_acmpne     38
      35: aconst_null
      36: astore        9
      38: new           #140                // class org/jboss/as/controller/operations/global/ReadAttributeHandler
      41: dup
      42: aload         5
      44: aload         9
      46: iload         4
      48: ifeq          62
      51: aload_0
      52: getfield      #2                  // Field resolvable:Z
      55: ifeq          62
      58: iconst_1
      59: goto          63
      62: iconst_0
      63: invokespecial #141                // Method org/jboss/as/controller/operations/global/ReadAttributeHandler."<init>":(Lorg/jboss/as/controller/operations/global/FilteredData;Lorg/jboss/as/controller/OperationStepHandler;Z)V
      66: astore        10
      68: aload_2
      69: aload         7
      71: invokevirtual #142                // Method org/jboss/as/controller/AttributeDefinition$NameAndGroup.getName:()Ljava/lang/String;
      74: invokestatic  #143                // Method org/jboss/as/controller/operations/common/Util.getReadAttributeOperation:(Lorg/jboss/as/controller/PathAddress;Ljava/lang/String;)Lorg/jboss/dmr/ModelNode;
      77: astore        11
      79: aload         11
      81: ldc           #45                 // String include-defaults
      83: invokevirtual #26                 // Method org/jboss/dmr/ModelNode.get:(Ljava/lang/String;)Lorg/jboss/dmr/ModelNode;
      86: iload_3
      87: invokevirtual #96                 // Method org/jboss/dmr/ModelNode.set:(Z)Lorg/jboss/dmr/ModelNode;
      90: pop
      91: aload         11
      93: ldc           #144                // String resolve-expressions
      95: invokevirtual #26                 // Method org/jboss/dmr/ModelNode.get:(Ljava/lang/String;)Lorg/jboss/dmr/ModelNode;
      98: iload         4
     100: invokevirtual #96                 // Method org/jboss/dmr/ModelNode.set:(Z)Lorg/jboss/dmr/ModelNode;
     103: pop
     104: new           #30                 // class org/jboss/dmr/ModelNode
     107: dup
     108: invokespecial #31                 // Method org/jboss/dmr/ModelNode."<init>":()V
     111: astore        12
     113: new           #145                // class org/jboss/as/controller/operations/global/GlobalOperationHandlers$AvailableResponse
     116: dup
     117: aload         12
     119: invokespecial #146                // Method org/jboss/as/controller/operations/global/GlobalOperationHandlers$AvailableResponse."<init>":(Lorg/jboss/dmr/ModelNode;)V
     122: astore        13
     124: aload         8
     126: aload         7
     128: aload         13
     130: invokeinterface #97,  3           // InterfaceMethod java/util/Map.put:(Ljava/lang/Object;Ljava/lang/Object;)Ljava/lang/Object;
     135: pop
     136: new           #147                // class org/jboss/as/controller/operations/global/GlobalOperationHandlers$AvailableResponseWrapper
     139: dup
     140: aload         10
     142: aload         13
     144: invokespecial #148                // Method org/jboss/as/controller/operations/global/GlobalOperationHandlers$AvailableResponseWrapper."<init>":(Lorg/jboss/as/controller/OperationStepHandler;Lorg/jboss/as/controller/operations/global/GlobalOperationHandlers$AvailableResponse;)V
     147: astore        14
     149: aload_1
     150: aload         12
     152: aload         11
     154: aload         14
     156: getstatic     #63                 // Field org/jboss/as/controller/OperationContext$Stage.MODEL:Lorg/jboss/as/controller/OperationContext$Stage;
     159: iconst_1
     160: invokeinterface #103,  6          // InterfaceMethod org/jboss/as/controller/OperationContext.addStep:(Lorg/jboss/dmr/ModelNode;Lorg/jboss/dmr/ModelNode;Lorg/jboss/as/controller/OperationStepHandler;Lorg/jboss/as/controller/OperationContext$Stage;Z)V
     165: return

  private static org.jboss.as.controller.registry.Resource nullSafeReadResource(org.jboss.as.controller.OperationContext, org.jboss.as.controller.registry.ImmutableManagementResourceRegistration);
    Code:
       0: aload_1
       1: ifnull        35
       4: aload_1
       5: invokeinterface #92,  1           // InterfaceMethod org/jboss/as/controller/registry/ImmutableManagementResourceRegistration.isRemote:()Z
      10: ifeq          35
      13: aload_0
      14: getstatic     #98                 // Field org/jboss/as/controller/PathAddress.EMPTY_ADDRESS:Lorg/jboss/as/controller/PathAddress;
      17: iconst_0
      18: invokeinterface #149,  3          // InterfaceMethod org/jboss/as/controller/OperationContext.readResource:(Lorg/jboss/as/controller/PathAddress;Z)Lorg/jboss/as/controller/registry/Resource;
      23: astore_2
      24: goto          46
      27: astore_3
      28: getstatic     #151                // Field org/jboss/as/controller/registry/PlaceholderResource.INSTANCE:Lorg/jboss/as/controller/registry/PlaceholderResource;
      31: astore_2
      32: goto          46
      35: aload_0
      36: getstatic     #98                 // Field org/jboss/as/controller/PathAddress.EMPTY_ADDRESS:Lorg/jboss/as/controller/PathAddress;
      39: iconst_0
      40: invokeinterface #149,  3          // InterfaceMethod org/jboss/as/controller/OperationContext.readResource:(Lorg/jboss/as/controller/PathAddress;Z)Lorg/jboss/as/controller/registry/Resource;
      45: astore_2
      46: aload_2
      47: areturn
    Exception table:
       from    to  target type
          13    24    27   Class java/lang/RuntimeException

  static boolean access$000(org.jboss.as.controller.operations.global.ReadResourceHandler);
    Code:
       0: aload_0
       1: getfield      #2                  // Field resolvable:Z
       4: ireturn

  static {};
    Code:
       0: new           #152                // class org/jboss/as/controller/SimpleAttributeDefinitionBuilder
       3: dup
       4: ldc           #46                 // String attributes-only
       6: getstatic     #153                // Field org/jboss/dmr/ModelType.BOOLEAN:Lorg/jboss/dmr/ModelType;
       9: invokespecial #154                // Method org/jboss/as/controller/SimpleAttributeDefinitionBuilder."<init>":(Ljava/lang/String;Lorg/jboss/dmr/ModelType;)V
      12: iconst_1
      13: invokevirtual #155                // Method org/jboss/as/controller/SimpleAttributeDefinitionBuilder.setAllowNull:(Z)Lorg/jboss/as/controller/AbstractAttributeDefinitionBuilder;
      16: checkcast     #152                // class org/jboss/as/controller/SimpleAttributeDefinitionBuilder
      19: new           #30                 // class org/jboss/dmr/ModelNode
      22: dup
      23: iconst_0
      24: invokespecial #156                // Method org/jboss/dmr/ModelNode."<init>":(Z)V
      27: invokevirtual #157                // Method org/jboss/as/controller/SimpleAttributeDefinitionBuilder.setDefaultValue:(Lorg/jboss/dmr/ModelNode;)Lorg/jboss/as/controller/AbstractAttributeDefinitionBuilder;
      30: checkcast     #152                // class org/jboss/as/controller/SimpleAttributeDefinitionBuilder
      33: invokevirtual #158                // Method org/jboss/as/controller/SimpleAttributeDefinitionBuilder.build:()Lorg/jboss/as/controller/SimpleAttributeDefinition;
      36: putstatic     #159                // Field ATTRIBUTES_ONLY:Lorg/jboss/as/controller/SimpleAttributeDefinition;
      39: new           #160                // class org/jboss/as/controller/SimpleOperationDefinitionBuilder
      42: dup
      43: ldc           #84                 // String read-resource
      45: iconst_1
      46: anewarray     #74                 // class java/lang/String
      49: dup
      50: iconst_0
      51: ldc           #161                // String global
      53: aastore
      54: invokestatic  #162                // Method org/jboss/as/controller/descriptions/common/ControllerResolver.getResolver:([Ljava/lang/String;)Lorg/jboss/as/controller/descriptions/ResourceDescriptionResolver;
      57: invokespecial #163                // Method org/jboss/as/controller/SimpleOperationDefinitionBuilder."<init>":(Ljava/lang/String;Lorg/jboss/as/controller/descriptions/ResourceDescriptionResolver;)V
      60: bipush        7
      62: anewarray     #164                // class org/jboss/as/controller/AttributeDefinition
      65: dup
      66: iconst_0
      67: getstatic     #165                // Field org/jboss/as/controller/operations/global/GlobalOperationAttributes.RECURSIVE:Lorg/jboss/as/controller/SimpleAttributeDefinition;
      70: aastore
      71: dup
      72: iconst_1
      73: getstatic     #166                // Field org/jboss/as/controller/operations/global/GlobalOperationAttributes.RECURSIVE_DEPTH:Lorg/jboss/as/controller/SimpleAttributeDefinition;
      76: aastore
      77: dup
      78: iconst_2
      79: getstatic     #167                // Field org/jboss/as/controller/operations/global/GlobalOperationAttributes.PROXIES:Lorg/jboss/as/controller/SimpleAttributeDefinition;
      82: aastore
      83: dup
      84: iconst_3
      85: getstatic     #168                // Field org/jboss/as/controller/operations/global/GlobalOperationAttributes.INCLUDE_RUNTIME:Lorg/jboss/as/controller/SimpleAttributeDefinition;
      88: aastore
      89: dup
      90: iconst_4
      91: getstatic     #169                // Field org/jboss/as/controller/operations/global/GlobalOperationAttributes.INCLUDE_DEFAULTS:Lorg/jboss/as/controller/SimpleAttributeDefinition;
      94: aastore
      95: dup
      96: iconst_5
      97: getstatic     #159                // Field ATTRIBUTES_ONLY:Lorg/jboss/as/controller/SimpleAttributeDefinition;
     100: aastore
     101: dup
     102: bipush        6
     104: getstatic     #170                // Field org/jboss/as/controller/operations/global/GlobalOperationAttributes.INCLUDE_ALIASES:Lorg/jboss/as/controller/SimpleAttributeDefinition;
     107: aastore
     108: invokevirtual #171                // Method org/jboss/as/controller/SimpleOperationDefinitionBuilder.setParameters:([Lorg/jboss/as/controller/AttributeDefinition;)Lorg/jboss/as/controller/SimpleOperationDefinitionBuilder;
     111: invokevirtual #172                // Method org/jboss/as/controller/SimpleOperationDefinitionBuilder.setReadOnly:()Lorg/jboss/as/controller/SimpleOperationDefinitionBuilder;
     114: invokevirtual #173                // Method org/jboss/as/controller/SimpleOperationDefinitionBuilder.setRuntimeOnly:()Lorg/jboss/as/controller/SimpleOperationDefinitionBuilder;
     117: getstatic     #174                // Field org/jboss/dmr/ModelType.OBJECT:Lorg/jboss/dmr/ModelType;
     120: invokevirtual #175                // Method org/jboss/as/controller/SimpleOperationDefinitionBuilder.setReplyType:(Lorg/jboss/dmr/ModelType;)Lorg/jboss/as/controller/SimpleOperationDefinitionBuilder;
     123: invokevirtual #176                // Method org/jboss/as/controller/SimpleOperationDefinitionBuilder.build:()Lorg/jboss/as/controller/SimpleOperationDefinition;
     126: putstatic     #177                // Field DEFINITION:Lorg/jboss/as/controller/OperationDefinition;
     129: new           #101                // class org/jboss/as/controller/operations/global/ReadResourceHandler
     132: dup
     133: invokespecial #178                // Method "<init>":()V
     136: putstatic     #179                // Field INSTANCE:Lorg/jboss/as/controller/OperationStepHandler;
     139: new           #152                // class org/jboss/as/controller/SimpleAttributeDefinitionBuilder
     142: dup
     143: ldc           #144                // String resolve-expressions
     145: getstatic     #153                // Field org/jboss/dmr/ModelType.BOOLEAN:Lorg/jboss/dmr/ModelType;
     148: invokespecial #154                // Method org/jboss/as/controller/SimpleAttributeDefinitionBuilder."<init>":(Ljava/lang/String;Lorg/jboss/dmr/ModelType;)V
     151: iconst_1
     152: invokevirtual #155                // Method org/jboss/as/controller/SimpleAttributeDefinitionBuilder.setAllowNull:(Z)Lorg/jboss/as/controller/AbstractAttributeDefinitionBuilder;
     155: checkcast     #152                // class org/jboss/as/controller/SimpleAttributeDefinitionBuilder
     158: new           #30                 // class org/jboss/dmr/ModelNode
     161: dup
     162: iconst_0
     163: invokespecial #156                // Method org/jboss/dmr/ModelNode."<init>":(Z)V
     166: invokevirtual #157                // Method org/jboss/as/controller/SimpleAttributeDefinitionBuilder.setDefaultValue:(Lorg/jboss/dmr/ModelNode;)Lorg/jboss/as/controller/AbstractAttributeDefinitionBuilder;
     169: checkcast     #152                // class org/jboss/as/controller/SimpleAttributeDefinitionBuilder
     172: invokevirtual #158                // Method org/jboss/as/controller/SimpleAttributeDefinitionBuilder.build:()Lorg/jboss/as/controller/SimpleAttributeDefinition;
     175: putstatic     #47                 // Field RESOLVE:Lorg/jboss/as/controller/SimpleAttributeDefinition;
     178: new           #160                // class org/jboss/as/controller/SimpleOperationDefinitionBuilder
     181: dup
     182: ldc           #84                 // String read-resource
     184: iconst_1
     185: anewarray     #74                 // class java/lang/String
     188: dup
     189: iconst_0
     190: ldc           #161                // String global
     192: aastore
     193: invokestatic  #162                // Method org/jboss/as/controller/descriptions/common/ControllerResolver.getResolver:([Ljava/lang/String;)Lorg/jboss/as/controller/descriptions/ResourceDescriptionResolver;
     196: invokespecial #163                // Method org/jboss/as/controller/SimpleOperationDefinitionBuilder."<init>":(Ljava/lang/String;Lorg/jboss/as/controller/descriptions/ResourceDescriptionResolver;)V
     199: bipush        8
     201: anewarray     #164                // class org/jboss/as/controller/AttributeDefinition
     204: dup
     205: iconst_0
     206: getstatic     #47                 // Field RESOLVE:Lorg/jboss/as/controller/SimpleAttributeDefinition;
     209: aastore
     210: dup
     211: iconst_1
     212: getstatic     #165                // Field org/jboss/as/controller/operations/global/GlobalOperationAttributes.RECURSIVE:Lorg/jboss/as/controller/SimpleAttributeDefinition;
     215: aastore
     216: dup
     217: iconst_2
     218: getstatic     #166                // Field org/jboss/as/controller/operations/global/GlobalOperationAttributes.RECURSIVE_DEPTH:Lorg/jboss/as/controller/SimpleAttributeDefinition;
     221: aastore
     222: dup
     223: iconst_3
     224: getstatic     #167                // Field org/jboss/as/controller/operations/global/GlobalOperationAttributes.PROXIES:Lorg/jboss/as/controller/SimpleAttributeDefinition;
     227: aastore
     228: dup
     229: iconst_4
     230: getstatic     #168                // Field org/jboss/as/controller/operations/global/GlobalOperationAttributes.INCLUDE_RUNTIME:Lorg/jboss/as/controller/SimpleAttributeDefinition;
     233: aastore
     234: dup
     235: iconst_5
     236: getstatic     #169                // Field org/jboss/as/controller/operations/global/GlobalOperationAttributes.INCLUDE_DEFAULTS:Lorg/jboss/as/controller/SimpleAttributeDefinition;
     239: aastore
     240: dup
     241: bipush        6
     243: getstatic     #159                // Field ATTRIBUTES_ONLY:Lorg/jboss/as/controller/SimpleAttributeDefinition;
     246: aastore
     247: dup
     248: bipush        7
     250: getstatic     #170                // Field org/jboss/as/controller/operations/global/GlobalOperationAttributes.INCLUDE_ALIASES:Lorg/jboss/as/controller/SimpleAttributeDefinition;
     253: aastore
     254: invokevirtual #171                // Method org/jboss/as/controller/SimpleOperationDefinitionBuilder.setParameters:([Lorg/jboss/as/controller/AttributeDefinition;)Lorg/jboss/as/controller/SimpleOperationDefinitionBuilder;
     257: invokevirtual #172                // Method org/jboss/as/controller/SimpleOperationDefinitionBuilder.setReadOnly:()Lorg/jboss/as/controller/SimpleOperationDefinitionBuilder;
     260: invokevirtual #173                // Method org/jboss/as/controller/SimpleOperationDefinitionBuilder.setRuntimeOnly:()Lorg/jboss/as/controller/SimpleOperationDefinitionBuilder;
     263: getstatic     #174                // Field org/jboss/dmr/ModelType.OBJECT:Lorg/jboss/dmr/ModelType;
     266: invokevirtual #175                // Method org/jboss/as/controller/SimpleOperationDefinitionBuilder.setReplyType:(Lorg/jboss/dmr/ModelType;)Lorg/jboss/as/controller/SimpleOperationDefinitionBuilder;
     269: invokevirtual #176                // Method org/jboss/as/controller/SimpleOperationDefinitionBuilder.build:()Lorg/jboss/as/controller/SimpleOperationDefinition;
     272: putstatic     #180                // Field RESOLVE_DEFINITION:Lorg/jboss/as/controller/OperationDefinition;
     275: new           #101                // class org/jboss/as/controller/operations/global/ReadResourceHandler
     278: dup
     279: iconst_1
     280: invokespecial #181                // Method "<init>":(Z)V
     283: putstatic     #182                // Field RESOLVE_INSTANCE:Lorg/jboss/as/controller/OperationStepHandler;
     286: return
}
