Compiled from "TransformCallToStatic.java"
public class javassist.convert.TransformCallToStatic extends javassist.convert.TransformCall {
  public javassist.convert.TransformCallToStatic(javassist.convert.Transformer, javassist.CtMethod, javassist.CtMethod);
    Code:
       0: aload_0
       1: aload_1
       2: aload_2
       3: aload_3
       4: invokespecial #1                  // Method javassist/convert/TransformCall."<init>":(Ljavassist/convert/Transformer;Ljavassist/CtMethod;Ljavassist/CtMethod;)V
       7: aload_0
       8: aload_2
       9: invokevirtual #2                  // Method javassist/CtMethod.getMethodInfo2:()Ljavassist/bytecode/MethodInfo;
      12: invokevirtual #3                  // Method javassist/bytecode/MethodInfo.getDescriptor:()Ljava/lang/String;
      15: putfield      #4                  // Field methodDescriptor:Ljava/lang/String;
      18: return

  protected int match(int, int, javassist.bytecode.CodeIterator, int, javassist.bytecode.ConstPool);
    Code:
       0: aload_0
       1: getfield      #5                  // Field newIndex:I
       4: ifne          63
       7: aload_0
       8: getfield      #6                  // Field classname:Ljava/lang/String;
      11: aload_0
      12: getfield      #4                  // Field methodDescriptor:Ljava/lang/String;
      15: invokestatic  #7                  // Method javassist/bytecode/Descriptor.insertParameter:(Ljava/lang/String;Ljava/lang/String;)Ljava/lang/String;
      18: astore        6
      20: aload         5
      22: aload_0
      23: getfield      #8                  // Field newMethodname:Ljava/lang/String;
      26: aload         6
      28: invokevirtual #9                  // Method javassist/bytecode/ConstPool.addNameAndTypeInfo:(Ljava/lang/String;Ljava/lang/String;)I
      31: istore        7
      33: aload         5
      35: aload_0
      36: getfield      #10                 // Field newClassname:Ljava/lang/String;
      39: invokevirtual #11                 // Method javassist/bytecode/ConstPool.addClassInfo:(Ljava/lang/String;)I
      42: istore        8
      44: aload_0
      45: aload         5
      47: iload         8
      49: iload         7
      51: invokevirtual #12                 // Method javassist/bytecode/ConstPool.addMethodrefInfo:(II)I
      54: putfield      #5                  // Field newIndex:I
      57: aload_0
      58: aload         5
      60: putfield      #13                 // Field constPool:Ljavassist/bytecode/ConstPool;
      63: aload_3
      64: sipush        184
      67: iload_2
      68: invokevirtual #15                 // Method javassist/bytecode/CodeIterator.writeByte:(II)V
      71: aload_3
      72: aload_0
      73: getfield      #5                  // Field newIndex:I
      76: iload_2
      77: iconst_1
      78: iadd
      79: invokevirtual #16                 // Method javassist/bytecode/CodeIterator.write16bit:(II)V
      82: iload_2
      83: ireturn
}
