Compiled from "CalculateHashStrategy.java"
public class org.sonatype.spice.zapper.fs.CalculateHashStrategy implements org.sonatype.spice.zapper.fs.HashStrategy {
  private final org.sonatype.spice.zapper.hash.HashAlgorithm hashAlgorithm;

  public org.sonatype.spice.zapper.fs.CalculateHashStrategy(org.sonatype.spice.zapper.hash.HashAlgorithm);
    Code:
       0: aload_0
       1: invokespecial #1                  // Method java/lang/Object."<init>":()V
       4: aload_0
       5: aload_1
       6: ldc_w         #2                  // class org/sonatype/spice/zapper/hash/HashAlgorithm
       9: invokestatic  #3                  // Method org/sonatype/spice/zapper/internal/Check.notNull:(Ljava/lang/Object;Ljava/lang/Class;)Ljava/lang/Object;
      12: checkcast     #2                  // class org/sonatype/spice/zapper/hash/HashAlgorithm
      15: putfield      #4                  // Field hashAlgorithm:Lorg/sonatype/spice/zapper/hash/HashAlgorithm;
      18: return

  public org.sonatype.spice.zapper.hash.HashAlgorithm getHashAlgorithm();
    Code:
       0: aload_0
       1: getfield      #4                  // Field hashAlgorithm:Lorg/sonatype/spice/zapper/hash/HashAlgorithm;
       4: areturn

  public org.sonatype.spice.zapper.hash.Hash getHashFor(java.io.File) throws java.io.IOException;
    Code:
       0: aload_0
       1: getfield      #4                  // Field hashAlgorithm:Lorg/sonatype/spice/zapper/hash/HashAlgorithm;
       4: ldc_w         #2                  // class org/sonatype/spice/zapper/hash/HashAlgorithm
       7: invokestatic  #3                  // Method org/sonatype/spice/zapper/internal/Check.notNull:(Ljava/lang/Object;Ljava/lang/Class;)Ljava/lang/Object;
      10: checkcast     #2                  // class org/sonatype/spice/zapper/hash/HashAlgorithm
      13: aload_1
      14: ldc_w         #5                  // class java/io/File
      17: invokestatic  #3                  // Method org/sonatype/spice/zapper/internal/Check.notNull:(Ljava/lang/Object;Ljava/lang/Class;)Ljava/lang/Object;
      20: checkcast     #5                  // class java/io/File
      23: invokestatic  #6                  // Method org/sonatype/spice/zapper/hash/HashUtils.getDigest:(Lorg/sonatype/spice/zapper/hash/HashAlgorithm;Ljava/io/File;)Lorg/sonatype/spice/zapper/hash/Hash;
      26: areturn
}
