Compiled from "ParseConfiguration.java"
public final class org.attoparser.config.ParseConfiguration$ElementBalancing extends java.lang.Enum<org.attoparser.config.ParseConfiguration$ElementBalancing> {
  public static final org.attoparser.config.ParseConfiguration$ElementBalancing NO_BALANCING;

  public static final org.attoparser.config.ParseConfiguration$ElementBalancing REQUIRE_BALANCED;

  public static final org.attoparser.config.ParseConfiguration$ElementBalancing AUTO_OPEN_CLOSE;

  public static final org.attoparser.config.ParseConfiguration$ElementBalancing AUTO_CLOSE;

  private static final org.attoparser.config.ParseConfiguration$ElementBalancing[] $VALUES;

  public static org.attoparser.config.ParseConfiguration$ElementBalancing[] values();
    Code:
       0: getstatic     #1                  // Field $VALUES:[Lorg/attoparser/config/ParseConfiguration$ElementBalancing;
       3: invokevirtual #2                  // Method "[Lorg/attoparser/config/ParseConfiguration$ElementBalancing;".clone:()Ljava/lang/Object;
       6: checkcast     #3                  // class "[Lorg/attoparser/config/ParseConfiguration$ElementBalancing;"
       9: areturn

  public static org.attoparser.config.ParseConfiguration$ElementBalancing valueOf(java.lang.String);
    Code:
       0: ldc           #4                  // class org/attoparser/config/ParseConfiguration$ElementBalancing
       2: aload_0
       3: invokestatic  #5                  // Method java/lang/Enum.valueOf:(Ljava/lang/Class;Ljava/lang/String;)Ljava/lang/Enum;
       6: checkcast     #4                  // class org/attoparser/config/ParseConfiguration$ElementBalancing
       9: areturn

  private org.attoparser.config.ParseConfiguration$ElementBalancing();
    Code:
       0: aload_0
       1: aload_1
       2: iload_2
       3: invokespecial #6                  // Method java/lang/Enum."<init>":(Ljava/lang/String;I)V
       6: return

  static {};
    Code:
       0: new           #4                  // class org/attoparser/config/ParseConfiguration$ElementBalancing
       3: dup
       4: ldc           #7                  // String NO_BALANCING
       6: iconst_0
       7: invokespecial #8                  // Method "<init>":(Ljava/lang/String;I)V
      10: putstatic     #9                  // Field NO_BALANCING:Lorg/attoparser/config/ParseConfiguration$ElementBalancing;
      13: new           #4                  // class org/attoparser/config/ParseConfiguration$ElementBalancing
      16: dup
      17: ldc           #10                 // String REQUIRE_BALANCED
      19: iconst_1
      20: invokespecial #8                  // Method "<init>":(Ljava/lang/String;I)V
      23: putstatic     #11                 // Field REQUIRE_BALANCED:Lorg/attoparser/config/ParseConfiguration$ElementBalancing;
      26: new           #4                  // class org/attoparser/config/ParseConfiguration$ElementBalancing
      29: dup
      30: ldc           #12                 // String AUTO_OPEN_CLOSE
      32: iconst_2
      33: invokespecial #8                  // Method "<init>":(Ljava/lang/String;I)V
      36: putstatic     #13                 // Field AUTO_OPEN_CLOSE:Lorg/attoparser/config/ParseConfiguration$ElementBalancing;
      39: new           #4                  // class org/attoparser/config/ParseConfiguration$ElementBalancing
      42: dup
      43: ldc           #14                 // String AUTO_CLOSE
      45: iconst_3
      46: invokespecial #8                  // Method "<init>":(Ljava/lang/String;I)V
      49: putstatic     #15                 // Field AUTO_CLOSE:Lorg/attoparser/config/ParseConfiguration$ElementBalancing;
      52: iconst_4
      53: anewarray     #4                  // class org/attoparser/config/ParseConfiguration$ElementBalancing
      56: dup
      57: iconst_0
      58: getstatic     #9                  // Field NO_BALANCING:Lorg/attoparser/config/ParseConfiguration$ElementBalancing;
      61: aastore
      62: dup
      63: iconst_1
      64: getstatic     #11                 // Field REQUIRE_BALANCED:Lorg/attoparser/config/ParseConfiguration$ElementBalancing;
      67: aastore
      68: dup
      69: iconst_2
      70: getstatic     #13                 // Field AUTO_OPEN_CLOSE:Lorg/attoparser/config/ParseConfiguration$ElementBalancing;
      73: aastore
      74: dup
      75: iconst_3
      76: getstatic     #15                 // Field AUTO_CLOSE:Lorg/attoparser/config/ParseConfiguration$ElementBalancing;
      79: aastore
      80: putstatic     #1                  // Field $VALUES:[Lorg/attoparser/config/ParseConfiguration$ElementBalancing;
      83: return
}
