Compiled from "DefaultFieldBuilder.java"
public class org.apache.james.mime4j.stream.DefaultFieldBuilder implements org.apache.james.mime4j.stream.FieldBuilder {
  private static final java.util.BitSet FIELD_CHARS;

  private final org.apache.james.mime4j.util.ByteArrayBuffer buf;

  private final int maxlen;

  public org.apache.james.mime4j.stream.DefaultFieldBuilder(int);
    Code:
       0: aload_0
       1: invokespecial #1                  // Method java/lang/Object."<init>":()V
       4: aload_0
       5: new           #2                  // class org/apache/james/mime4j/util/ByteArrayBuffer
       8: dup
       9: sipush        1024
      12: invokespecial #3                  // Method org/apache/james/mime4j/util/ByteArrayBuffer."<init>":(I)V
      15: putfield      #4                  // Field buf:Lorg/apache/james/mime4j/util/ByteArrayBuffer;
      18: aload_0
      19: iload_1
      20: putfield      #5                  // Field maxlen:I
      23: return

  public void reset();
    Code:
       0: aload_0
       1: getfield      #4                  // Field buf:Lorg/apache/james/mime4j/util/ByteArrayBuffer;
       4: invokevirtual #6                  // Method org/apache/james/mime4j/util/ByteArrayBuffer.clear:()V
       7: return

  public void append(org.apache.james.mime4j.util.ByteArrayBuffer) throws org.apache.james.mime4j.io.MaxHeaderLengthLimitException;
    Code:
       0: aload_1
       1: ifnonnull     5
       4: return
       5: aload_1
       6: invokevirtual #7                  // Method org/apache/james/mime4j/util/ByteArrayBuffer.length:()I
       9: istore_2
      10: aload_0
      11: getfield      #5                  // Field maxlen:I
      14: ifle          43
      17: aload_0
      18: getfield      #4                  // Field buf:Lorg/apache/james/mime4j/util/ByteArrayBuffer;
      21: invokevirtual #7                  // Method org/apache/james/mime4j/util/ByteArrayBuffer.length:()I
      24: iload_2
      25: iadd
      26: aload_0
      27: getfield      #5                  // Field maxlen:I
      30: if_icmplt     43
      33: new           #8                  // class org/apache/james/mime4j/io/MaxHeaderLengthLimitException
      36: dup
      37: ldc           #9                  // String Maximum header length limit exceeded
      39: invokespecial #10                 // Method org/apache/james/mime4j/io/MaxHeaderLengthLimitException."<init>":(Ljava/lang/String;)V
      42: athrow
      43: aload_0
      44: getfield      #4                  // Field buf:Lorg/apache/james/mime4j/util/ByteArrayBuffer;
      47: aload_1
      48: invokevirtual #11                 // Method org/apache/james/mime4j/util/ByteArrayBuffer.buffer:()[B
      51: iconst_0
      52: aload_1
      53: invokevirtual #7                  // Method org/apache/james/mime4j/util/ByteArrayBuffer.length:()I
      56: invokevirtual #12                 // Method org/apache/james/mime4j/util/ByteArrayBuffer.append:([BII)V
      59: return

  public org.apache.james.mime4j.stream.RawField build() throws org.apache.james.mime4j.MimeException;
    Code:
       0: aload_0
       1: getfield      #4                  // Field buf:Lorg/apache/james/mime4j/util/ByteArrayBuffer;
       4: invokevirtual #7                  // Method org/apache/james/mime4j/util/ByteArrayBuffer.length:()I
       7: istore_1
       8: iload_1
       9: ifle          48
      12: aload_0
      13: getfield      #4                  // Field buf:Lorg/apache/james/mime4j/util/ByteArrayBuffer;
      16: iload_1
      17: iconst_1
      18: isub
      19: invokevirtual #13                 // Method org/apache/james/mime4j/util/ByteArrayBuffer.byteAt:(I)B
      22: bipush        10
      24: if_icmpne     30
      27: iinc          1, -1
      30: aload_0
      31: getfield      #4                  // Field buf:Lorg/apache/james/mime4j/util/ByteArrayBuffer;
      34: iload_1
      35: iconst_1
      36: isub
      37: invokevirtual #13                 // Method org/apache/james/mime4j/util/ByteArrayBuffer.byteAt:(I)B
      40: bipush        13
      42: if_icmpne     48
      45: iinc          1, -1
      48: new           #2                  // class org/apache/james/mime4j/util/ByteArrayBuffer
      51: dup
      52: aload_0
      53: getfield      #4                  // Field buf:Lorg/apache/james/mime4j/util/ByteArrayBuffer;
      56: invokevirtual #11                 // Method org/apache/james/mime4j/util/ByteArrayBuffer.buffer:()[B
      59: iload_1
      60: iconst_0
      61: invokespecial #14                 // Method org/apache/james/mime4j/util/ByteArrayBuffer."<init>":([BIZ)V
      64: astore_2
      65: getstatic     #15                 // Field org/apache/james/mime4j/stream/RawFieldParser.DEFAULT:Lorg/apache/james/mime4j/stream/RawFieldParser;
      68: aload_2
      69: invokevirtual #16                 // Method org/apache/james/mime4j/stream/RawFieldParser.parseField:(Lorg/apache/james/mime4j/util/ByteSequence;)Lorg/apache/james/mime4j/stream/RawField;
      72: astore_3
      73: aload_3
      74: invokevirtual #17                 // Method org/apache/james/mime4j/stream/RawField.getName:()Ljava/lang/String;
      77: astore        4
      79: iconst_0
      80: istore        5
      82: iload         5
      84: aload         4
      86: invokevirtual #18                 // Method java/lang/String.length:()I
      89: if_icmpge     148
      92: aload         4
      94: iload         5
      96: invokevirtual #19                 // Method java/lang/String.charAt:(I)C
      99: istore        6
     101: getstatic     #20                 // Field FIELD_CHARS:Ljava/util/BitSet;
     104: iload         6
     106: invokevirtual #21                 // Method java/util/BitSet.get:(I)Z
     109: ifne          142
     112: new           #22                 // class org/apache/james/mime4j/MimeException
     115: dup
     116: new           #23                 // class java/lang/StringBuilder
     119: dup
     120: invokespecial #24                 // Method java/lang/StringBuilder."<init>":()V
     123: ldc           #25                 // String MIME field name contains illegal characters:
     125: invokevirtual #26                 // Method java/lang/StringBuilder.append:(Ljava/lang/String;)Ljava/lang/StringBuilder;
     128: aload_3
     129: invokevirtual #17                 // Method org/apache/james/mime4j/stream/RawField.getName:()Ljava/lang/String;
     132: invokevirtual #26                 // Method java/lang/StringBuilder.append:(Ljava/lang/String;)Ljava/lang/StringBuilder;
     135: invokevirtual #27                 // Method java/lang/StringBuilder.toString:()Ljava/lang/String;
     138: invokespecial #28                 // Method org/apache/james/mime4j/MimeException."<init>":(Ljava/lang/String;)V
     141: athrow
     142: iinc          5, 1
     145: goto          82
     148: aload_3
     149: areturn

  public org.apache.james.mime4j.util.ByteArrayBuffer getRaw();
    Code:
       0: aload_0
       1: getfield      #4                  // Field buf:Lorg/apache/james/mime4j/util/ByteArrayBuffer;
       4: areturn

  static {};
    Code:
       0: new           #29                 // class java/util/BitSet
       3: dup
       4: invokespecial #30                 // Method java/util/BitSet."<init>":()V
       7: putstatic     #20                 // Field FIELD_CHARS:Ljava/util/BitSet;
      10: bipush        33
      12: istore_0
      13: iload_0
      14: bipush        57
      16: if_icmpgt     32
      19: getstatic     #20                 // Field FIELD_CHARS:Ljava/util/BitSet;
      22: iload_0
      23: invokevirtual #31                 // Method java/util/BitSet.set:(I)V
      26: iinc          0, 1
      29: goto          13
      32: bipush        59
      34: istore_0
      35: iload_0
      36: bipush        126
      38: if_icmpgt     54
      41: getstatic     #20                 // Field FIELD_CHARS:Ljava/util/BitSet;
      44: iload_0
      45: invokevirtual #31                 // Method java/util/BitSet.set:(I)V
      48: iinc          0, 1
      51: goto          35
      54: return
}
