Compiled from "MigrationType.java"
public final class org.flywaydb.core.api.MigrationType extends java.lang.Enum<org.flywaydb.core.api.MigrationType> {
  public static final org.flywaydb.core.api.MigrationType SCHEMA;

  public static final org.flywaydb.core.api.MigrationType BASELINE;

  public static final org.flywaydb.core.api.MigrationType SQL;

  public static final org.flywaydb.core.api.MigrationType JDBC;

  public static final org.flywaydb.core.api.MigrationType SPRING_JDBC;

  public static final org.flywaydb.core.api.MigrationType CUSTOM;

  private static final org.flywaydb.core.api.MigrationType[] $VALUES;

  public static org.flywaydb.core.api.MigrationType[] values();
    Code:
       0: getstatic     #1                  // Field $VALUES:[Lorg/flywaydb/core/api/MigrationType;
       3: invokevirtual #2                  // Method "[Lorg/flywaydb/core/api/MigrationType;".clone:()Ljava/lang/Object;
       6: checkcast     #3                  // class "[Lorg/flywaydb/core/api/MigrationType;"
       9: areturn

  public static org.flywaydb.core.api.MigrationType valueOf(java.lang.String);
    Code:
       0: ldc           #4                  // class org/flywaydb/core/api/MigrationType
       2: aload_0
       3: invokestatic  #5                  // Method java/lang/Enum.valueOf:(Ljava/lang/Class;Ljava/lang/String;)Ljava/lang/Enum;
       6: checkcast     #4                  // class org/flywaydb/core/api/MigrationType
       9: areturn

  private org.flywaydb.core.api.MigrationType();
    Code:
       0: aload_0
       1: aload_1
       2: iload_2
       3: invokespecial #6                  // Method java/lang/Enum."<init>":(Ljava/lang/String;I)V
       6: return

  static {};
    Code:
       0: new           #4                  // class org/flywaydb/core/api/MigrationType
       3: dup
       4: ldc           #7                  // String SCHEMA
       6: iconst_0
       7: invokespecial #8                  // Method "<init>":(Ljava/lang/String;I)V
      10: putstatic     #9                  // Field SCHEMA:Lorg/flywaydb/core/api/MigrationType;
      13: new           #4                  // class org/flywaydb/core/api/MigrationType
      16: dup
      17: ldc           #10                 // String BASELINE
      19: iconst_1
      20: invokespecial #8                  // Method "<init>":(Ljava/lang/String;I)V
      23: putstatic     #11                 // Field BASELINE:Lorg/flywaydb/core/api/MigrationType;
      26: new           #4                  // class org/flywaydb/core/api/MigrationType
      29: dup
      30: ldc           #12                 // String SQL
      32: iconst_2
      33: invokespecial #8                  // Method "<init>":(Ljava/lang/String;I)V
      36: putstatic     #13                 // Field SQL:Lorg/flywaydb/core/api/MigrationType;
      39: new           #4                  // class org/flywaydb/core/api/MigrationType
      42: dup
      43: ldc           #14                 // String JDBC
      45: iconst_3
      46: invokespecial #8                  // Method "<init>":(Ljava/lang/String;I)V
      49: putstatic     #15                 // Field JDBC:Lorg/flywaydb/core/api/MigrationType;
      52: new           #4                  // class org/flywaydb/core/api/MigrationType
      55: dup
      56: ldc           #16                 // String SPRING_JDBC
      58: iconst_4
      59: invokespecial #8                  // Method "<init>":(Ljava/lang/String;I)V
      62: putstatic     #17                 // Field SPRING_JDBC:Lorg/flywaydb/core/api/MigrationType;
      65: new           #4                  // class org/flywaydb/core/api/MigrationType
      68: dup
      69: ldc           #18                 // String CUSTOM
      71: iconst_5
      72: invokespecial #8                  // Method "<init>":(Ljava/lang/String;I)V
      75: putstatic     #19                 // Field CUSTOM:Lorg/flywaydb/core/api/MigrationType;
      78: bipush        6
      80: anewarray     #4                  // class org/flywaydb/core/api/MigrationType
      83: dup
      84: iconst_0
      85: getstatic     #9                  // Field SCHEMA:Lorg/flywaydb/core/api/MigrationType;
      88: aastore
      89: dup
      90: iconst_1
      91: getstatic     #11                 // Field BASELINE:Lorg/flywaydb/core/api/MigrationType;
      94: aastore
      95: dup
      96: iconst_2
      97: getstatic     #13                 // Field SQL:Lorg/flywaydb/core/api/MigrationType;
     100: aastore
     101: dup
     102: iconst_3
     103: getstatic     #15                 // Field JDBC:Lorg/flywaydb/core/api/MigrationType;
     106: aastore
     107: dup
     108: iconst_4
     109: getstatic     #17                 // Field SPRING_JDBC:Lorg/flywaydb/core/api/MigrationType;
     112: aastore
     113: dup
     114: iconst_5
     115: getstatic     #19                 // Field CUSTOM:Lorg/flywaydb/core/api/MigrationType;
     118: aastore
     119: putstatic     #1                  // Field $VALUES:[Lorg/flywaydb/core/api/MigrationType;
     122: return
}
