Compiled from "MigrationVersion.java"
public final class org.flywaydb.core.api.MigrationVersion implements java.lang.Comparable<org.flywaydb.core.api.MigrationVersion> {
  public static final org.flywaydb.core.api.MigrationVersion EMPTY;

  public static final org.flywaydb.core.api.MigrationVersion LATEST;

  public static final org.flywaydb.core.api.MigrationVersion CURRENT;

  private static java.util.regex.Pattern splitPattern;

  private final java.util.List<java.math.BigInteger> versionParts;

  private final java.lang.String displayText;

  public static org.flywaydb.core.api.MigrationVersion fromVersion(java.lang.String);
    Code:
       0: ldc           #1                  // String current
       2: aload_0
       3: invokevirtual #2                  // Method java/lang/String.equalsIgnoreCase:(Ljava/lang/String;)Z
       6: ifeq          13
       9: getstatic     #3                  // Field CURRENT:Lorg/flywaydb/core/api/MigrationVersion;
      12: areturn
      13: getstatic     #4                  // Field LATEST:Lorg/flywaydb/core/api/MigrationVersion;
      16: invokevirtual #5                  // Method getVersion:()Ljava/lang/String;
      19: aload_0
      20: invokevirtual #6                  // Method java/lang/String.equals:(Ljava/lang/Object;)Z
      23: ifeq          30
      26: getstatic     #4                  // Field LATEST:Lorg/flywaydb/core/api/MigrationVersion;
      29: areturn
      30: aload_0
      31: ifnonnull     38
      34: getstatic     #7                  // Field EMPTY:Lorg/flywaydb/core/api/MigrationVersion;
      37: areturn
      38: new           #8                  // class org/flywaydb/core/api/MigrationVersion
      41: dup
      42: aload_0
      43: invokespecial #9                  // Method "<init>":(Ljava/lang/String;)V
      46: areturn

  private org.flywaydb.core.api.MigrationVersion(java.lang.String);
    Code:
       0: aload_0
       1: invokespecial #10                 // Method java/lang/Object."<init>":()V
       4: aload_1
       5: bipush        95
       7: bipush        46
       9: invokevirtual #11                 // Method java/lang/String.replace:(CC)Ljava/lang/String;
      12: astore_2
      13: aload_0
      14: aload_0
      15: aload_2
      16: invokespecial #12                 // Method tokenize:(Ljava/lang/String;)Ljava/util/List;
      19: putfield      #13                 // Field versionParts:Ljava/util/List;
      22: aload_0
      23: aload_2
      24: putfield      #14                 // Field displayText:Ljava/lang/String;
      27: return

  private org.flywaydb.core.api.MigrationVersion(java.math.BigInteger, java.lang.String);
    Code:
       0: aload_0
       1: invokespecial #10                 // Method java/lang/Object."<init>":()V
       4: aload_0
       5: new           #15                 // class java/util/ArrayList
       8: dup
       9: invokespecial #16                 // Method java/util/ArrayList."<init>":()V
      12: putfield      #13                 // Field versionParts:Ljava/util/List;
      15: aload_0
      16: getfield      #13                 // Field versionParts:Ljava/util/List;
      19: aload_1
      20: invokeinterface #17,  2           // InterfaceMethod java/util/List.add:(Ljava/lang/Object;)Z
      25: pop
      26: aload_0
      27: aload_2
      28: putfield      #14                 // Field displayText:Ljava/lang/String;
      31: return

  public java.lang.String toString();
    Code:
       0: aload_0
       1: getfield      #14                 // Field displayText:Ljava/lang/String;
       4: areturn

  public java.lang.String getVersion();
    Code:
       0: aload_0
       1: getstatic     #7                  // Field EMPTY:Lorg/flywaydb/core/api/MigrationVersion;
       4: invokevirtual #18                 // Method equals:(Ljava/lang/Object;)Z
       7: ifeq          12
      10: aconst_null
      11: areturn
      12: aload_0
      13: getstatic     #4                  // Field LATEST:Lorg/flywaydb/core/api/MigrationVersion;
      16: invokevirtual #18                 // Method equals:(Ljava/lang/Object;)Z
      19: ifeq          29
      22: ldc2_w        #20                 // long 9223372036854775807l
      25: invokestatic  #22                 // Method java/lang/Long.toString:(J)Ljava/lang/String;
      28: areturn
      29: aload_0
      30: getfield      #14                 // Field displayText:Ljava/lang/String;
      33: areturn

  public boolean equals(java.lang.Object);
    Code:
       0: aload_0
       1: aload_1
       2: if_acmpne     7
       5: iconst_1
       6: ireturn
       7: aload_1
       8: ifnull        22
      11: aload_0
      12: invokevirtual #23                 // Method java/lang/Object.getClass:()Ljava/lang/Class;
      15: aload_1
      16: invokevirtual #23                 // Method java/lang/Object.getClass:()Ljava/lang/Class;
      19: if_acmpeq     24
      22: iconst_0
      23: ireturn
      24: aload_1
      25: checkcast     #8                  // class org/flywaydb/core/api/MigrationVersion
      28: astore_2
      29: aload_0
      30: aload_2
      31: invokevirtual #24                 // Method compareTo:(Lorg/flywaydb/core/api/MigrationVersion;)I
      34: ifne          41
      37: iconst_1
      38: goto          42
      41: iconst_0
      42: ireturn

  public int hashCode();
    Code:
       0: aload_0
       1: getfield      #13                 // Field versionParts:Ljava/util/List;
       4: ifnonnull     11
       7: iconst_0
       8: goto          20
      11: aload_0
      12: getfield      #13                 // Field versionParts:Ljava/util/List;
      15: invokeinterface #25,  1           // InterfaceMethod java/util/List.hashCode:()I
      20: ireturn

  public int compareTo(org.flywaydb.core.api.MigrationVersion);
    Code:
       0: aload_1
       1: ifnonnull     6
       4: iconst_1
       5: ireturn
       6: aload_0
       7: getstatic     #7                  // Field EMPTY:Lorg/flywaydb/core/api/MigrationVersion;
      10: if_acmpne     27
      13: aload_1
      14: getstatic     #7                  // Field EMPTY:Lorg/flywaydb/core/api/MigrationVersion;
      17: if_acmpne     24
      20: iconst_0
      21: goto          26
      24: ldc           #27                 // int -2147483648
      26: ireturn
      27: aload_0
      28: getstatic     #3                  // Field CURRENT:Lorg/flywaydb/core/api/MigrationVersion;
      31: if_acmpne     48
      34: aload_1
      35: getstatic     #3                  // Field CURRENT:Lorg/flywaydb/core/api/MigrationVersion;
      38: if_acmpne     45
      41: iconst_0
      42: goto          47
      45: ldc           #27                 // int -2147483648
      47: ireturn
      48: aload_0
      49: getstatic     #4                  // Field LATEST:Lorg/flywaydb/core/api/MigrationVersion;
      52: if_acmpne     69
      55: aload_1
      56: getstatic     #4                  // Field LATEST:Lorg/flywaydb/core/api/MigrationVersion;
      59: if_acmpne     66
      62: iconst_0
      63: goto          68
      66: ldc           #28                 // int 2147483647
      68: ireturn
      69: aload_1
      70: getstatic     #7                  // Field EMPTY:Lorg/flywaydb/core/api/MigrationVersion;
      73: if_acmpne     79
      76: ldc           #28                 // int 2147483647
      78: ireturn
      79: aload_1
      80: getstatic     #3                  // Field CURRENT:Lorg/flywaydb/core/api/MigrationVersion;
      83: if_acmpne     89
      86: ldc           #28                 // int 2147483647
      88: ireturn
      89: aload_1
      90: getstatic     #4                  // Field LATEST:Lorg/flywaydb/core/api/MigrationVersion;
      93: if_acmpne     99
      96: ldc           #27                 // int -2147483648
      98: ireturn
      99: aload_0
     100: getfield      #13                 // Field versionParts:Ljava/util/List;
     103: astore_2
     104: aload_1
     105: getfield      #13                 // Field versionParts:Ljava/util/List;
     108: astore_3
     109: aload_2
     110: invokeinterface #29,  1           // InterfaceMethod java/util/List.size:()I
     115: aload_3
     116: invokeinterface #29,  1           // InterfaceMethod java/util/List.size:()I
     121: invokestatic  #30                 // Method java/lang/Math.max:(II)I
     124: istore        4
     126: iconst_0
     127: istore        5
     129: iload         5
     131: iload         4
     133: if_icmpge     169
     136: aload_0
     137: aload_2
     138: iload         5
     140: invokespecial #31                 // Method getOrZero:(Ljava/util/List;I)Ljava/math/BigInteger;
     143: aload_0
     144: aload_3
     145: iload         5
     147: invokespecial #31                 // Method getOrZero:(Ljava/util/List;I)Ljava/math/BigInteger;
     150: invokevirtual #32                 // Method java/math/BigInteger.compareTo:(Ljava/math/BigInteger;)I
     153: istore        6
     155: iload         6
     157: ifeq          163
     160: iload         6
     162: ireturn
     163: iinc          5, 1
     166: goto          129
     169: iconst_0
     170: ireturn

  private java.math.BigInteger getOrZero(java.util.List<java.math.BigInteger>, int);
    Code:
       0: iload_2
       1: aload_1
       2: invokeinterface #29,  1           // InterfaceMethod java/util/List.size:()I
       7: if_icmpge     23
      10: aload_1
      11: iload_2
      12: invokeinterface #33,  2           // InterfaceMethod java/util/List.get:(I)Ljava/lang/Object;
      17: checkcast     #34                 // class java/math/BigInteger
      20: goto          26
      23: getstatic     #35                 // Field java/math/BigInteger.ZERO:Ljava/math/BigInteger;
      26: areturn

  private java.util.List<java.math.BigInteger> tokenize(java.lang.String);
    Code:
       0: new           #15                 // class java/util/ArrayList
       3: dup
       4: invokespecial #16                 // Method java/util/ArrayList."<init>":()V
       7: astore_2
       8: getstatic     #36                 // Field splitPattern:Ljava/util/regex/Pattern;
      11: aload_1
      12: invokevirtual #37                 // Method java/util/regex/Pattern.split:(Ljava/lang/CharSequence;)[Ljava/lang/String;
      15: astore_3
      16: aload_3
      17: arraylength
      18: istore        4
      20: iconst_0
      21: istore        5
      23: iload         5
      25: iload         4
      27: if_icmpge     90
      30: aload_3
      31: iload         5
      33: aaload
      34: astore        6
      36: aload_2
      37: new           #34                 // class java/math/BigInteger
      40: dup
      41: aload         6
      43: invokespecial #38                 // Method java/math/BigInteger."<init>":(Ljava/lang/String;)V
      46: invokeinterface #17,  2           // InterfaceMethod java/util/List.add:(Ljava/lang/Object;)Z
      51: pop
      52: goto          84
      55: astore        7
      57: new           #40                 // class org/flywaydb/core/api/FlywayException
      60: dup
      61: new           #41                 // class java/lang/StringBuilder
      64: dup
      65: invokespecial #42                 // Method java/lang/StringBuilder."<init>":()V
      68: ldc           #43                 // String Invalid version containing non-numeric characters. Only 0..9 and . are allowed. Invalid version:
      70: invokevirtual #44                 // Method java/lang/StringBuilder.append:(Ljava/lang/String;)Ljava/lang/StringBuilder;
      73: aload_1
      74: invokevirtual #44                 // Method java/lang/StringBuilder.append:(Ljava/lang/String;)Ljava/lang/StringBuilder;
      77: invokevirtual #45                 // Method java/lang/StringBuilder.toString:()Ljava/lang/String;
      80: invokespecial #46                 // Method org/flywaydb/core/api/FlywayException."<init>":(Ljava/lang/String;)V
      83: athrow
      84: iinc          5, 1
      87: goto          23
      90: aload_2
      91: invokeinterface #29,  1           // InterfaceMethod java/util/List.size:()I
      96: iconst_1
      97: isub
      98: istore_3
      99: iload_3
     100: ifle          139
     103: aload_2
     104: iload_3
     105: invokeinterface #33,  2           // InterfaceMethod java/util/List.get:(I)Ljava/lang/Object;
     110: checkcast     #34                 // class java/math/BigInteger
     113: getstatic     #35                 // Field java/math/BigInteger.ZERO:Ljava/math/BigInteger;
     116: invokevirtual #47                 // Method java/math/BigInteger.equals:(Ljava/lang/Object;)Z
     119: ifne          125
     122: goto          139
     125: aload_2
     126: iload_3
     127: invokeinterface #48,  2           // InterfaceMethod java/util/List.remove:(I)Ljava/lang/Object;
     132: pop
     133: iinc          3, -1
     136: goto          99
     139: aload_2
     140: areturn
    Exception table:
       from    to  target type
          36    52    55   Class java/lang/NumberFormatException

  public int compareTo(java.lang.Object);
    Code:
       0: aload_0
       1: aload_1
       2: checkcast     #8                  // class org/flywaydb/core/api/MigrationVersion
       5: invokevirtual #24                 // Method compareTo:(Lorg/flywaydb/core/api/MigrationVersion;)I
       8: ireturn

  static {};
    Code:
       0: new           #8                  // class org/flywaydb/core/api/MigrationVersion
       3: dup
       4: aconst_null
       5: ldc           #49                 // String << Empty Schema >>
       7: invokespecial #50                 // Method "<init>":(Ljava/math/BigInteger;Ljava/lang/String;)V
      10: putstatic     #7                  // Field EMPTY:Lorg/flywaydb/core/api/MigrationVersion;
      13: new           #8                  // class org/flywaydb/core/api/MigrationVersion
      16: dup
      17: ldc2_w        #51                 // long -1l
      20: invokestatic  #53                 // Method java/math/BigInteger.valueOf:(J)Ljava/math/BigInteger;
      23: ldc           #54                 // String << Latest Version >>
      25: invokespecial #50                 // Method "<init>":(Ljava/math/BigInteger;Ljava/lang/String;)V
      28: putstatic     #4                  // Field LATEST:Lorg/flywaydb/core/api/MigrationVersion;
      31: new           #8                  // class org/flywaydb/core/api/MigrationVersion
      34: dup
      35: ldc2_w        #55                 // long -2l
      38: invokestatic  #53                 // Method java/math/BigInteger.valueOf:(J)Ljava/math/BigInteger;
      41: ldc           #57                 // String << Current Version >>
      43: invokespecial #50                 // Method "<init>":(Ljava/math/BigInteger;Ljava/lang/String;)V
      46: putstatic     #3                  // Field CURRENT:Lorg/flywaydb/core/api/MigrationVersion;
      49: ldc           #58                 // String \\.(?=\\d)
      51: invokestatic  #59                 // Method java/util/regex/Pattern.compile:(Ljava/lang/String;)Ljava/util/regex/Pattern;
      54: putstatic     #36                 // Field splitPattern:Ljava/util/regex/Pattern;
      57: return
}
