Compiled from "CompactionOptionsUniversal.java"
public class org.rocksdb.CompactionOptionsUniversal extends org.rocksdb.RocksObject {
  public org.rocksdb.CompactionOptionsUniversal();
    Code:
       0: aload_0
       1: invokestatic  #1                  // Method newCompactionOptionsUniversal:()J
       4: invokespecial #2                  // Method org/rocksdb/RocksObject."<init>":(J)V
       7: return

  public org.rocksdb.CompactionOptionsUniversal setSizeRatio(int);
    Code:
       0: aload_0
       1: aload_0
       2: getfield      #3                  // Field nativeHandle_:J
       5: iload_1
       6: invokespecial #4                  // Method setSizeRatio:(JI)V
       9: aload_0
      10: areturn

  public int sizeRatio();
    Code:
       0: aload_0
       1: aload_0
       2: getfield      #3                  // Field nativeHandle_:J
       5: invokespecial #5                  // Method sizeRatio:(J)I
       8: ireturn

  public org.rocksdb.CompactionOptionsUniversal setMinMergeWidth(int);
    Code:
       0: aload_0
       1: aload_0
       2: getfield      #3                  // Field nativeHandle_:J
       5: iload_1
       6: invokespecial #6                  // Method setMinMergeWidth:(JI)V
       9: aload_0
      10: areturn

  public int minMergeWidth();
    Code:
       0: aload_0
       1: aload_0
       2: getfield      #3                  // Field nativeHandle_:J
       5: invokespecial #7                  // Method minMergeWidth:(J)I
       8: ireturn

  public org.rocksdb.CompactionOptionsUniversal setMaxMergeWidth(int);
    Code:
       0: aload_0
       1: aload_0
       2: getfield      #3                  // Field nativeHandle_:J
       5: iload_1
       6: invokespecial #8                  // Method setMaxMergeWidth:(JI)V
       9: aload_0
      10: areturn

  public int maxMergeWidth();
    Code:
       0: aload_0
       1: aload_0
       2: getfield      #3                  // Field nativeHandle_:J
       5: invokespecial #9                  // Method maxMergeWidth:(J)I
       8: ireturn

  public org.rocksdb.CompactionOptionsUniversal setMaxSizeAmplificationPercent(int);
    Code:
       0: aload_0
       1: aload_0
       2: getfield      #3                  // Field nativeHandle_:J
       5: iload_1
       6: invokespecial #10                 // Method setMaxSizeAmplificationPercent:(JI)V
       9: aload_0
      10: areturn

  public int maxSizeAmplificationPercent();
    Code:
       0: aload_0
       1: aload_0
       2: getfield      #3                  // Field nativeHandle_:J
       5: invokespecial #11                 // Method maxSizeAmplificationPercent:(J)I
       8: ireturn

  public org.rocksdb.CompactionOptionsUniversal setCompressionSizePercent(int);
    Code:
       0: aload_0
       1: aload_0
       2: getfield      #3                  // Field nativeHandle_:J
       5: iload_1
       6: invokespecial #12                 // Method setCompressionSizePercent:(JI)V
       9: aload_0
      10: areturn

  public int compressionSizePercent();
    Code:
       0: aload_0
       1: aload_0
       2: getfield      #3                  // Field nativeHandle_:J
       5: invokespecial #13                 // Method compressionSizePercent:(J)I
       8: ireturn

  public org.rocksdb.CompactionOptionsUniversal setStopStyle(org.rocksdb.CompactionStopStyle);
    Code:
       0: aload_0
       1: aload_0
       2: getfield      #3                  // Field nativeHandle_:J
       5: aload_1
       6: invokevirtual #14                 // Method org/rocksdb/CompactionStopStyle.getValue:()B
       9: invokespecial #15                 // Method setStopStyle:(JB)V
      12: aload_0
      13: areturn

  public org.rocksdb.CompactionStopStyle stopStyle();
    Code:
       0: aload_0
       1: aload_0
       2: getfield      #3                  // Field nativeHandle_:J
       5: invokespecial #16                 // Method stopStyle:(J)B
       8: invokestatic  #17                 // Method org/rocksdb/CompactionStopStyle.getCompactionStopStyle:(B)Lorg/rocksdb/CompactionStopStyle;
      11: areturn

  public org.rocksdb.CompactionOptionsUniversal setAllowTrivialMove(boolean);
    Code:
       0: aload_0
       1: aload_0
       2: getfield      #3                  // Field nativeHandle_:J
       5: iload_1
       6: invokespecial #18                 // Method setAllowTrivialMove:(JZ)V
       9: aload_0
      10: areturn

  public boolean allowTrivialMove();
    Code:
       0: aload_0
       1: aload_0
       2: getfield      #3                  // Field nativeHandle_:J
       5: invokespecial #19                 // Method allowTrivialMove:(J)Z
       8: ireturn

  private static native long newCompactionOptionsUniversal();

  protected final native void disposeInternal(long);

  private native void setSizeRatio(long, int);

  private native int sizeRatio(long);

  private native void setMinMergeWidth(long, int);

  private native int minMergeWidth(long);

  private native void setMaxMergeWidth(long, int);

  private native int maxMergeWidth(long);

  private native void setMaxSizeAmplificationPercent(long, int);

  private native int maxSizeAmplificationPercent(long);

  private native void setCompressionSizePercent(long, int);

  private native int compressionSizePercent(long);

  private native void setStopStyle(long, byte);

  private native byte stopStyle(long);

  private native void setAllowTrivialMove(long, boolean);

  private native boolean allowTrivialMove(long);
}
