Compiled from "JsonSmartMappingProvider.java"
class com.jayway.jsonpath.spi.mapper.JsonSmartMappingProvider$LongReader extends net.minidev.json.writer.JsonReaderI<java.lang.Long> {
  public com.jayway.jsonpath.spi.mapper.JsonSmartMappingProvider$LongReader();
    Code:
       0: aload_0
       1: aconst_null
       2: invokespecial #1                  // Method net/minidev/json/writer/JsonReaderI."<init>":(Lnet/minidev/json/writer/JsonReader;)V
       5: return

  public java.lang.Long convert(java.lang.Object);
    Code:
       0: aload_1
       1: ifnonnull     6
       4: aconst_null
       5: areturn
       6: ldc           #2                  // class java/lang/Long
       8: aload_1
       9: invokevirtual #3                  // Method java/lang/Object.getClass:()Ljava/lang/Class;
      12: invokevirtual #4                  // Method java/lang/Class.isAssignableFrom:(Ljava/lang/Class;)Z
      15: ifeq          23
      18: aload_1
      19: checkcast     #2                  // class java/lang/Long
      22: areturn
      23: ldc           #5                  // class java/lang/Integer
      25: aload_1
      26: invokevirtual #3                  // Method java/lang/Object.getClass:()Ljava/lang/Class;
      29: invokevirtual #4                  // Method java/lang/Class.isAssignableFrom:(Ljava/lang/Class;)Z
      32: ifeq          46
      35: aload_1
      36: checkcast     #5                  // class java/lang/Integer
      39: invokevirtual #6                  // Method java/lang/Integer.longValue:()J
      42: invokestatic  #7                  // Method java/lang/Long.valueOf:(J)Ljava/lang/Long;
      45: areturn
      46: ldc           #8                  // class java/lang/Double
      48: aload_1
      49: invokevirtual #3                  // Method java/lang/Object.getClass:()Ljava/lang/Class;
      52: invokevirtual #4                  // Method java/lang/Class.isAssignableFrom:(Ljava/lang/Class;)Z
      55: ifeq          69
      58: aload_1
      59: checkcast     #8                  // class java/lang/Double
      62: invokevirtual #9                  // Method java/lang/Double.longValue:()J
      65: invokestatic  #7                  // Method java/lang/Long.valueOf:(J)Ljava/lang/Long;
      68: areturn
      69: ldc           #10                 // class java/math/BigDecimal
      71: aload_1
      72: invokevirtual #3                  // Method java/lang/Object.getClass:()Ljava/lang/Class;
      75: invokevirtual #4                  // Method java/lang/Class.isAssignableFrom:(Ljava/lang/Class;)Z
      78: ifeq          92
      81: aload_1
      82: checkcast     #10                 // class java/math/BigDecimal
      85: invokevirtual #11                 // Method java/math/BigDecimal.longValue:()J
      88: invokestatic  #7                  // Method java/lang/Long.valueOf:(J)Ljava/lang/Long;
      91: areturn
      92: ldc           #12                 // class java/lang/Float
      94: aload_1
      95: invokevirtual #3                  // Method java/lang/Object.getClass:()Ljava/lang/Class;
      98: invokevirtual #4                  // Method java/lang/Class.isAssignableFrom:(Ljava/lang/Class;)Z
     101: ifeq          115
     104: aload_1
     105: checkcast     #12                 // class java/lang/Float
     108: invokevirtual #13                 // Method java/lang/Float.longValue:()J
     111: invokestatic  #7                  // Method java/lang/Long.valueOf:(J)Ljava/lang/Long;
     114: areturn
     115: ldc           #14                 // class java/lang/String
     117: aload_1
     118: invokevirtual #3                  // Method java/lang/Object.getClass:()Ljava/lang/Class;
     121: invokevirtual #4                  // Method java/lang/Class.isAssignableFrom:(Ljava/lang/Class;)Z
     124: ifeq          135
     127: aload_1
     128: invokevirtual #15                 // Method java/lang/Object.toString:()Ljava/lang/String;
     131: invokestatic  #16                 // Method java/lang/Long.valueOf:(Ljava/lang/String;)Ljava/lang/Long;
     134: areturn
     135: new           #17                 // class com/jayway/jsonpath/spi/mapper/MappingException
     138: dup
     139: new           #18                 // class java/lang/StringBuilder
     142: dup
     143: invokespecial #19                 // Method java/lang/StringBuilder."<init>":()V
     146: ldc           #20                 // String can not map a
     148: invokevirtual #21                 // Method java/lang/StringBuilder.append:(Ljava/lang/String;)Ljava/lang/StringBuilder;
     151: aload_1
     152: invokevirtual #3                  // Method java/lang/Object.getClass:()Ljava/lang/Class;
     155: invokevirtual #22                 // Method java/lang/StringBuilder.append:(Ljava/lang/Object;)Ljava/lang/StringBuilder;
     158: ldc           #23                 // String  to
     160: invokevirtual #21                 // Method java/lang/StringBuilder.append:(Ljava/lang/String;)Ljava/lang/StringBuilder;
     163: ldc           #2                  // class java/lang/Long
     165: invokevirtual #24                 // Method java/lang/Class.getName:()Ljava/lang/String;
     168: invokevirtual #21                 // Method java/lang/StringBuilder.append:(Ljava/lang/String;)Ljava/lang/StringBuilder;
     171: invokevirtual #25                 // Method java/lang/StringBuilder.toString:()Ljava/lang/String;
     174: invokespecial #26                 // Method com/jayway/jsonpath/spi/mapper/MappingException."<init>":(Ljava/lang/String;)V
     177: athrow

  public java.lang.Object convert(java.lang.Object);
    Code:
       0: aload_0
       1: aload_1
       2: invokevirtual #27                 // Method convert:(Ljava/lang/Object;)Ljava/lang/Long;
       5: areturn
}
