Compiled from "JspConfigDescriptorImpl.java"
public class org.apache.tomcat.util.descriptor.web.JspConfigDescriptorImpl implements javax.servlet.descriptor.JspConfigDescriptor {
  private final java.util.Collection<javax.servlet.descriptor.JspPropertyGroupDescriptor> jspPropertyGroups;

  private final java.util.Collection<javax.servlet.descriptor.TaglibDescriptor> taglibs;

  public org.apache.tomcat.util.descriptor.web.JspConfigDescriptorImpl(java.util.Collection<javax.servlet.descriptor.JspPropertyGroupDescriptor>, java.util.Collection<javax.servlet.descriptor.TaglibDescriptor>);
    Code:
       0: aload_0
       1: invokespecial #1                  // Method java/lang/Object."<init>":()V
       4: aload_0
       5: aload_1
       6: putfield      #2                  // Field jspPropertyGroups:Ljava/util/Collection;
       9: aload_0
      10: aload_2
      11: putfield      #3                  // Field taglibs:Ljava/util/Collection;
      14: return

  public java.util.Collection<javax.servlet.descriptor.JspPropertyGroupDescriptor> getJspPropertyGroups();
    Code:
       0: new           #4                  // class java/util/ArrayList
       3: dup
       4: aload_0
       5: getfield      #2                  // Field jspPropertyGroups:Ljava/util/Collection;
       8: invokespecial #5                  // Method java/util/ArrayList."<init>":(Ljava/util/Collection;)V
      11: areturn

  public java.util.Collection<javax.servlet.descriptor.TaglibDescriptor> getTaglibs();
    Code:
       0: new           #4                  // class java/util/ArrayList
       3: dup
       4: aload_0
       5: getfield      #3                  // Field taglibs:Ljava/util/Collection;
       8: invokespecial #5                  // Method java/util/ArrayList."<init>":(Ljava/util/Collection;)V
      11: areturn
}
