Compiled from "HttpRouterAccessHandler.kt"
final class net.mamoe.mirai.api.http.adapter.http.feature.handler.HttpRouterAccessHandler$Feature$install$1 extends kotlin.coroutines.jvm.internal.SuspendLambda implements kotlin.jvm.functions.Function3<io.ktor.util.pipeline.PipelineContext<kotlin.Unit, io.ktor.application.ApplicationCall>, kotlin.Unit, kotlin.coroutines.Continuation<? super kotlin.Unit>, java.lang.Object> {
  int label;

  private java.lang.Object L$0;

  final net.mamoe.mirai.api.http.adapter.http.feature.handler.HttpRouterAccessHandler $feature;

  net.mamoe.mirai.api.http.adapter.http.feature.handler.HttpRouterAccessHandler$Feature$install$1(net.mamoe.mirai.api.http.adapter.http.feature.handler.HttpRouterAccessHandler, kotlin.coroutines.Continuation<? super net.mamoe.mirai.api.http.adapter.http.feature.handler.HttpRouterAccessHandler$Feature$install$1>);
    Code:
       0: aload_0
       1: aload_1
       2: putfield      #14                 // Field $feature:Lnet/mamoe/mirai/api/http/adapter/http/feature/handler/HttpRouterAccessHandler;
       5: aload_0
       6: iconst_3
       7: aload_2
       8: invokespecial #17                 // Method kotlin/coroutines/jvm/internal/SuspendLambda."<init>":(ILkotlin/coroutines/Continuation;)V
      11: return

  public final java.lang.Object invokeSuspend(java.lang.Object);
    Code:
       0: invokestatic  #42                 // Method kotlin/coroutines/intrinsics/IntrinsicsKt.getCOROUTINE_SUSPENDED:()Ljava/lang/Object;
       3: astore_3
       4: aload_0
       5: getfield      #46                 // Field label:I
       8: tableswitch   { // 0 to 1
                     0: 32
                     1: 68
               default: 78
          }
      32: aload_1
      33: invokestatic  #52                 // Method kotlin/ResultKt.throwOnFailure:(Ljava/lang/Object;)V
      36: aload_0
      37: getfield      #56                 // Field L$0:Ljava/lang/Object;
      40: checkcast     #58                 // class io/ktor/util/pipeline/PipelineContext
      43: astore_2
      44: aload_0
      45: getfield      #14                 // Field $feature:Lnet/mamoe/mirai/api/http/adapter/http/feature/handler/HttpRouterAccessHandler;
      48: aload_2
      49: aload_0
      50: checkcast     #60                 // class kotlin/coroutines/Continuation
      53: aload_0
      54: iconst_1
      55: putfield      #46                 // Field label:I
      58: invokestatic  #66                 // Method net/mamoe/mirai/api/http/adapter/http/feature/handler/HttpRouterAccessHandler.access$intercept:(Lnet/mamoe/mirai/api/http/adapter/http/feature/handler/HttpRouterAccessHandler;Lio/ktor/util/pipeline/PipelineContext;Lkotlin/coroutines/Continuation;)Ljava/lang/Object;
      61: dup
      62: aload_3
      63: if_acmpne     73
      66: aload_3
      67: areturn
      68: aload_1
      69: invokestatic  #52                 // Method kotlin/ResultKt.throwOnFailure:(Ljava/lang/Object;)V
      72: aload_1
      73: pop
      74: getstatic     #72                 // Field kotlin/Unit.INSTANCE:Lkotlin/Unit;
      77: areturn
      78: new           #74                 // class java/lang/IllegalStateException
      81: dup
      82: ldc           #76                 // String call to \'resume\' before \'invoke\' with coroutine
      84: invokespecial #79                 // Method java/lang/IllegalStateException."<init>":(Ljava/lang/String;)V
      87: athrow

  public final java.lang.Object invoke(io.ktor.util.pipeline.PipelineContext<kotlin.Unit, io.ktor.application.ApplicationCall>, kotlin.Unit, kotlin.coroutines.Continuation<? super kotlin.Unit>);
    Code:
       0: new           #2                  // class net/mamoe/mirai/api/http/adapter/http/feature/handler/HttpRouterAccessHandler$Feature$install$1
       3: dup
       4: aload_0
       5: getfield      #14                 // Field $feature:Lnet/mamoe/mirai/api/http/adapter/http/feature/handler/HttpRouterAccessHandler;
       8: aload_3
       9: invokespecial #89                 // Method "<init>":(Lnet/mamoe/mirai/api/http/adapter/http/feature/handler/HttpRouterAccessHandler;Lkotlin/coroutines/Continuation;)V
      12: astore        4
      14: aload         4
      16: aload_1
      17: putfield      #56                 // Field L$0:Ljava/lang/Object;
      20: aload         4
      22: getstatic     #72                 // Field kotlin/Unit.INSTANCE:Lkotlin/Unit;
      25: invokevirtual #91                 // Method invokeSuspend:(Ljava/lang/Object;)Ljava/lang/Object;
      28: areturn

  public java.lang.Object invoke(java.lang.Object, java.lang.Object, java.lang.Object);
    Code:
       0: aload_0
       1: aload_1
       2: checkcast     #58                 // class io/ktor/util/pipeline/PipelineContext
       5: aload_2
       6: checkcast     #68                 // class kotlin/Unit
       9: aload_3
      10: checkcast     #60                 // class kotlin/coroutines/Continuation
      13: invokevirtual #97                 // Method invoke:(Lio/ktor/util/pipeline/PipelineContext;Lkotlin/Unit;Lkotlin/coroutines/Continuation;)Ljava/lang/Object;
      16: areturn
}
