Compiled from "ContainerBuilder.java"
public final class com.fasterxml.jackson.databind.util.ContainerBuilder {
  private static final int MAX_BUF;

  private java.lang.Object[] b;

  private int tail;

  private int start;

  private java.util.List<java.lang.Object> list;

  private java.util.Map<java.lang.String, java.lang.Object> map;

  public com.fasterxml.jackson.databind.util.ContainerBuilder(int);
    Code:
       0: aload_0
       1: invokespecial #1                  // Method java/lang/Object."<init>":()V
       4: aload_0
       5: iload_1
       6: bipush        -2
       8: iand
       9: anewarray     #2                  // class java/lang/Object
      12: putfield      #3                  // Field b:[Ljava/lang/Object;
      15: return

  public boolean canReuse();
    Code:
       0: aload_0
       1: getfield      #4                  // Field list:Ljava/util/List;
       4: ifnonnull     18
       7: aload_0
       8: getfield      #5                  // Field map:Ljava/util/Map;
      11: ifnonnull     18
      14: iconst_1
      15: goto          19
      18: iconst_0
      19: ireturn

  public int bufferLength();
    Code:
       0: aload_0
       1: getfield      #3                  // Field b:[Ljava/lang/Object;
       4: arraylength
       5: ireturn

  public int start();
    Code:
       0: aload_0
       1: getfield      #4                  // Field list:Ljava/util/List;
       4: ifnonnull     14
       7: aload_0
       8: getfield      #5                  // Field map:Ljava/util/Map;
      11: ifnull        22
      14: new           #6                  // class java/lang/IllegalStateException
      17: dup
      18: invokespecial #7                  // Method java/lang/IllegalStateException."<init>":()V
      21: athrow
      22: aload_0
      23: getfield      #8                  // Field start:I
      26: istore_1
      27: aload_0
      28: aload_0
      29: getfield      #9                  // Field tail:I
      32: putfield      #8                  // Field start:I
      35: iload_1
      36: ireturn

  public int startList(java.lang.Object);
    Code:
       0: aload_0
       1: getfield      #4                  // Field list:Ljava/util/List;
       4: ifnonnull     14
       7: aload_0
       8: getfield      #5                  // Field map:Ljava/util/Map;
      11: ifnull        22
      14: new           #6                  // class java/lang/IllegalStateException
      17: dup
      18: invokespecial #7                  // Method java/lang/IllegalStateException."<init>":()V
      21: athrow
      22: aload_0
      23: getfield      #8                  // Field start:I
      26: istore_2
      27: aload_0
      28: aload_0
      29: getfield      #9                  // Field tail:I
      32: putfield      #8                  // Field start:I
      35: aload_0
      36: aload_1
      37: invokevirtual #10                 // Method add:(Ljava/lang/Object;)V
      40: iload_2
      41: ireturn

  public int startMap(java.lang.String, java.lang.Object);
    Code:
       0: aload_0
       1: getfield      #4                  // Field list:Ljava/util/List;
       4: ifnonnull     14
       7: aload_0
       8: getfield      #5                  // Field map:Ljava/util/Map;
      11: ifnull        22
      14: new           #6                  // class java/lang/IllegalStateException
      17: dup
      18: invokespecial #7                  // Method java/lang/IllegalStateException."<init>":()V
      21: athrow
      22: aload_0
      23: getfield      #8                  // Field start:I
      26: istore_3
      27: aload_0
      28: aload_0
      29: getfield      #9                  // Field tail:I
      32: putfield      #8                  // Field start:I
      35: aload_0
      36: aload_1
      37: aload_2
      38: invokevirtual #11                 // Method put:(Ljava/lang/String;Ljava/lang/Object;)V
      41: iload_3
      42: ireturn

  public void add(java.lang.Object);
    Code:
       0: aload_0
       1: getfield      #4                  // Field list:Ljava/util/List;
       4: ifnull        21
       7: aload_0
       8: getfield      #4                  // Field list:Ljava/util/List;
      11: aload_1
      12: invokeinterface #12,  2           // InterfaceMethod java/util/List.add:(Ljava/lang/Object;)Z
      17: pop
      18: goto          58
      21: aload_0
      22: getfield      #9                  // Field tail:I
      25: aload_0
      26: getfield      #3                  // Field b:[Ljava/lang/Object;
      29: arraylength
      30: if_icmplt     41
      33: aload_0
      34: aload_1
      35: invokespecial #13                 // Method _expandList:(Ljava/lang/Object;)V
      38: goto          58
      41: aload_0
      42: getfield      #3                  // Field b:[Ljava/lang/Object;
      45: aload_0
      46: dup
      47: getfield      #9                  // Field tail:I
      50: dup_x1
      51: iconst_1
      52: iadd
      53: putfield      #9                  // Field tail:I
      56: aload_1
      57: aastore
      58: return

  public void put(java.lang.String, java.lang.Object);
    Code:
       0: aload_0
       1: getfield      #5                  // Field map:Ljava/util/Map;
       4: ifnull        22
       7: aload_0
       8: getfield      #5                  // Field map:Ljava/util/Map;
      11: aload_1
      12: aload_2
      13: invokeinterface #14,  3           // InterfaceMethod java/util/Map.put:(Ljava/lang/Object;Ljava/lang/Object;)Ljava/lang/Object;
      18: pop
      19: goto          79
      22: aload_0
      23: getfield      #9                  // Field tail:I
      26: iconst_2
      27: iadd
      28: aload_0
      29: getfield      #3                  // Field b:[Ljava/lang/Object;
      32: arraylength
      33: if_icmple     45
      36: aload_0
      37: aload_1
      38: aload_2
      39: invokespecial #15                 // Method _expandMap:(Ljava/lang/String;Ljava/lang/Object;)V
      42: goto          79
      45: aload_0
      46: getfield      #3                  // Field b:[Ljava/lang/Object;
      49: aload_0
      50: dup
      51: getfield      #9                  // Field tail:I
      54: dup_x1
      55: iconst_1
      56: iadd
      57: putfield      #9                  // Field tail:I
      60: aload_1
      61: aastore
      62: aload_0
      63: getfield      #3                  // Field b:[Ljava/lang/Object;
      66: aload_0
      67: dup
      68: getfield      #9                  // Field tail:I
      71: dup_x1
      72: iconst_1
      73: iadd
      74: putfield      #9                  // Field tail:I
      77: aload_2
      78: aastore
      79: return

  public java.util.List<java.lang.Object> finishList(int);
    Code:
       0: aload_0
       1: getfield      #4                  // Field list:Ljava/util/List;
       4: astore_2
       5: aload_2
       6: ifnonnull     18
       9: aload_0
      10: iconst_1
      11: invokespecial #16                 // Method _buildList:(Z)Ljava/util/List;
      14: astore_2
      15: goto          23
      18: aload_0
      19: aconst_null
      20: putfield      #4                  // Field list:Ljava/util/List;
      23: aload_0
      24: iload_1
      25: putfield      #8                  // Field start:I
      28: aload_2
      29: areturn

  public java.lang.Object[] finishArray(int);
    Code:
       0: aload_0
       1: getfield      #4                  // Field list:Ljava/util/List;
       4: ifnonnull     26
       7: aload_0
       8: getfield      #3                  // Field b:[Ljava/lang/Object;
      11: aload_0
      12: getfield      #8                  // Field start:I
      15: aload_0
      16: getfield      #9                  // Field tail:I
      19: invokestatic  #17                 // Method java/util/Arrays.copyOfRange:([Ljava/lang/Object;II)[Ljava/lang/Object;
      22: astore_2
      23: goto          53
      26: aload_0
      27: getfield      #4                  // Field list:Ljava/util/List;
      30: aload_0
      31: getfield      #9                  // Field tail:I
      34: aload_0
      35: getfield      #8                  // Field start:I
      38: isub
      39: anewarray     #2                  // class java/lang/Object
      42: invokeinterface #18,  2           // InterfaceMethod java/util/List.toArray:([Ljava/lang/Object;)[Ljava/lang/Object;
      47: astore_2
      48: aload_0
      49: aconst_null
      50: putfield      #4                  // Field list:Ljava/util/List;
      53: aload_0
      54: iload_1
      55: putfield      #8                  // Field start:I
      58: aload_2
      59: areturn

  public <T> java.lang.Object[] finishArray(int, java.lang.Class<T>);
    Code:
       0: aload_0
       1: getfield      #9                  // Field tail:I
       4: aload_0
       5: getfield      #8                  // Field start:I
       8: isub
       9: istore_3
      10: aload_2
      11: iload_3
      12: invokestatic  #19                 // Method java/lang/reflect/Array.newInstance:(Ljava/lang/Class;I)Ljava/lang/Object;
      15: checkcast     #20                 // class "[Ljava/lang/Object;"
      18: checkcast     #20                 // class "[Ljava/lang/Object;"
      21: astore        4
      23: aload_0
      24: getfield      #4                  // Field list:Ljava/util/List;
      27: ifnonnull     48
      30: aload_0
      31: getfield      #3                  // Field b:[Ljava/lang/Object;
      34: aload_0
      35: getfield      #8                  // Field start:I
      38: aload         4
      40: iconst_0
      41: iload_3
      42: invokestatic  #21                 // Method java/lang/System.arraycopy:(Ljava/lang/Object;ILjava/lang/Object;II)V
      45: goto          66
      48: aload_0
      49: getfield      #4                  // Field list:Ljava/util/List;
      52: aload         4
      54: invokeinterface #18,  2           // InterfaceMethod java/util/List.toArray:([Ljava/lang/Object;)[Ljava/lang/Object;
      59: astore        4
      61: aload_0
      62: aconst_null
      63: putfield      #4                  // Field list:Ljava/util/List;
      66: aload_0
      67: iload_1
      68: putfield      #8                  // Field start:I
      71: aload         4
      73: areturn

  public java.util.Map<java.lang.String, java.lang.Object> finishMap(int);
    Code:
       0: aload_0
       1: getfield      #5                  // Field map:Ljava/util/Map;
       4: astore_2
       5: aload_2
       6: ifnonnull     18
       9: aload_0
      10: iconst_1
      11: invokespecial #22                 // Method _buildMap:(Z)Ljava/util/Map;
      14: astore_2
      15: goto          23
      18: aload_0
      19: aconst_null
      20: putfield      #5                  // Field map:Ljava/util/Map;
      23: aload_0
      24: iload_1
      25: putfield      #8                  // Field start:I
      28: aload_2
      29: areturn

  private void _expandList(java.lang.Object);
    Code:
       0: aload_0
       1: getfield      #3                  // Field b:[Ljava/lang/Object;
       4: arraylength
       5: sipush        1000
       8: if_icmpge     49
      11: aload_0
      12: aload_0
      13: getfield      #3                  // Field b:[Ljava/lang/Object;
      16: aload_0
      17: getfield      #3                  // Field b:[Ljava/lang/Object;
      20: arraylength
      21: iconst_1
      22: ishl
      23: invokestatic  #23                 // Method java/util/Arrays.copyOf:([Ljava/lang/Object;I)[Ljava/lang/Object;
      26: putfield      #3                  // Field b:[Ljava/lang/Object;
      29: aload_0
      30: getfield      #3                  // Field b:[Ljava/lang/Object;
      33: aload_0
      34: dup
      35: getfield      #9                  // Field tail:I
      38: dup_x1
      39: iconst_1
      40: iadd
      41: putfield      #9                  // Field tail:I
      44: aload_1
      45: aastore
      46: goto          69
      49: aload_0
      50: aload_0
      51: iconst_0
      52: invokespecial #16                 // Method _buildList:(Z)Ljava/util/List;
      55: putfield      #4                  // Field list:Ljava/util/List;
      58: aload_0
      59: getfield      #4                  // Field list:Ljava/util/List;
      62: aload_1
      63: invokeinterface #12,  2           // InterfaceMethod java/util/List.add:(Ljava/lang/Object;)Z
      68: pop
      69: return

  private java.util.List<java.lang.Object> _buildList(boolean);
    Code:
       0: aload_0
       1: getfield      #9                  // Field tail:I
       4: aload_0
       5: getfield      #8                  // Field start:I
       8: isub
       9: istore_2
      10: iload_1
      11: ifeq          24
      14: iload_2
      15: iconst_2
      16: if_icmpge     58
      19: iconst_2
      20: istore_2
      21: goto          58
      24: iload_2
      25: bipush        20
      27: if_icmpge     36
      30: bipush        20
      32: istore_2
      33: goto          58
      36: iload_2
      37: sipush        1000
      40: if_icmpge     52
      43: iload_2
      44: iload_2
      45: iconst_1
      46: ishr
      47: iadd
      48: istore_2
      49: goto          58
      52: iload_2
      53: iload_2
      54: iconst_2
      55: ishr
      56: iadd
      57: istore_2
      58: new           #24                 // class java/util/ArrayList
      61: dup
      62: iload_2
      63: invokespecial #25                 // Method java/util/ArrayList."<init>":(I)V
      66: astore_3
      67: aload_0
      68: getfield      #8                  // Field start:I
      71: istore        4
      73: iload         4
      75: aload_0
      76: getfield      #9                  // Field tail:I
      79: if_icmpge     102
      82: aload_3
      83: aload_0
      84: getfield      #3                  // Field b:[Ljava/lang/Object;
      87: iload         4
      89: aaload
      90: invokeinterface #12,  2           // InterfaceMethod java/util/List.add:(Ljava/lang/Object;)Z
      95: pop
      96: iinc          4, 1
      99: goto          73
     102: aload_0
     103: aload_0
     104: getfield      #8                  // Field start:I
     107: putfield      #9                  // Field tail:I
     110: aload_3
     111: areturn

  private void _expandMap(java.lang.String, java.lang.Object);
    Code:
       0: aload_0
       1: getfield      #3                  // Field b:[Ljava/lang/Object;
       4: arraylength
       5: sipush        1000
       8: if_icmpge     66
      11: aload_0
      12: aload_0
      13: getfield      #3                  // Field b:[Ljava/lang/Object;
      16: aload_0
      17: getfield      #3                  // Field b:[Ljava/lang/Object;
      20: arraylength
      21: iconst_1
      22: ishl
      23: invokestatic  #23                 // Method java/util/Arrays.copyOf:([Ljava/lang/Object;I)[Ljava/lang/Object;
      26: putfield      #3                  // Field b:[Ljava/lang/Object;
      29: aload_0
      30: getfield      #3                  // Field b:[Ljava/lang/Object;
      33: aload_0
      34: dup
      35: getfield      #9                  // Field tail:I
      38: dup_x1
      39: iconst_1
      40: iadd
      41: putfield      #9                  // Field tail:I
      44: aload_1
      45: aastore
      46: aload_0
      47: getfield      #3                  // Field b:[Ljava/lang/Object;
      50: aload_0
      51: dup
      52: getfield      #9                  // Field tail:I
      55: dup_x1
      56: iconst_1
      57: iadd
      58: putfield      #9                  // Field tail:I
      61: aload_2
      62: aastore
      63: goto          87
      66: aload_0
      67: aload_0
      68: iconst_0
      69: invokespecial #22                 // Method _buildMap:(Z)Ljava/util/Map;
      72: putfield      #5                  // Field map:Ljava/util/Map;
      75: aload_0
      76: getfield      #5                  // Field map:Ljava/util/Map;
      79: aload_1
      80: aload_2
      81: invokeinterface #14,  3           // InterfaceMethod java/util/Map.put:(Ljava/lang/Object;Ljava/lang/Object;)Ljava/lang/Object;
      86: pop
      87: return

  private java.util.Map<java.lang.String, java.lang.Object> _buildMap(boolean);
    Code:
       0: aload_0
       1: getfield      #9                  // Field tail:I
       4: aload_0
       5: getfield      #8                  // Field start:I
       8: isub
       9: iconst_1
      10: ishr
      11: istore_2
      12: iload_1
      13: ifeq          54
      16: iload_2
      17: iconst_3
      18: if_icmpgt     26
      21: iconst_4
      22: istore_2
      23: goto          88
      26: iload_2
      27: bipush        40
      29: if_icmpgt     41
      32: iload_2
      33: iload_2
      34: iconst_1
      35: ishr
      36: iadd
      37: istore_2
      38: goto          88
      41: iload_2
      42: iload_2
      43: iconst_2
      44: ishr
      45: iload_2
      46: iconst_4
      47: ishr
      48: iadd
      49: iadd
      50: istore_2
      51: goto          88
      54: iload_2
      55: bipush        10
      57: if_icmpge     66
      60: bipush        16
      62: istore_2
      63: goto          88
      66: iload_2
      67: sipush        1000
      70: if_icmpge     82
      73: iload_2
      74: iload_2
      75: iconst_1
      76: ishr
      77: iadd
      78: istore_2
      79: goto          88
      82: iload_2
      83: iload_2
      84: iconst_3
      85: idiv
      86: iadd
      87: istore_2
      88: new           #26                 // class java/util/LinkedHashMap
      91: dup
      92: iload_2
      93: ldc           #27                 // float 0.8f
      95: invokespecial #28                 // Method java/util/LinkedHashMap."<init>":(IF)V
      98: astore_3
      99: aload_0
     100: getfield      #8                  // Field start:I
     103: istore        4
     105: iload         4
     107: aload_0
     108: getfield      #9                  // Field tail:I
     111: if_icmpge     146
     114: aload_3
     115: aload_0
     116: getfield      #3                  // Field b:[Ljava/lang/Object;
     119: iload         4
     121: aaload
     122: checkcast     #29                 // class java/lang/String
     125: aload_0
     126: getfield      #3                  // Field b:[Ljava/lang/Object;
     129: iload         4
     131: iconst_1
     132: iadd
     133: aaload
     134: invokeinterface #14,  3           // InterfaceMethod java/util/Map.put:(Ljava/lang/Object;Ljava/lang/Object;)Ljava/lang/Object;
     139: pop
     140: iinc          4, 2
     143: goto          105
     146: aload_0
     147: aload_0
     148: getfield      #8                  // Field start:I
     151: putfield      #9                  // Field tail:I
     154: aload_3
     155: areturn
}
