Compiled from "MapBuilder.kt"
public abstract class kotlin.collections.builders.AbstractMapBuilderEntrySet<E extends java.util.Map$Entry<? extends K, ? extends V>, K, V> extends kotlin.collections.AbstractMutableSet<E> {
  public final boolean contains(E);
    Code:
       0: aload_1
       1: ldc           #16                 // String element
       3: invokestatic  #22                 // Method kotlin/jvm/internal/Intrinsics.checkNotNullParameter:(Ljava/lang/Object;Ljava/lang/String;)V
       6: aload_0
       7: aload_1
       8: invokevirtual #25                 // Method containsEntry:(Ljava/util/Map$Entry;)Z
      11: ireturn

  public final boolean contains(java.lang.Object);
    Code:
       0: aload_1
       1: instanceof    #11                 // class java/util/Map$Entry
       4: ifeq          10
       7: goto          12
      10: iconst_0
      11: ireturn
      12: aload_0
      13: aload_1
      14: checkcast     #11                 // class java/util/Map$Entry
      17: invokevirtual #13                 // Method contains:(Ljava/util/Map$Entry;)Z
      20: ireturn

  public abstract boolean containsEntry(java.util.Map$Entry<? extends K, ? extends V>);

  public kotlin.collections.builders.AbstractMapBuilderEntrySet();
    Code:
       0: aload_0
       1: invokespecial #33                 // Method kotlin/collections/AbstractMutableSet."<init>":()V
       4: return

  public boolean remove(java.util.Map$Entry);
    Code:
       0: aload_0
       1: aload_1
       2: invokespecial #36                 // Method kotlin/collections/AbstractMutableSet.remove:(Ljava/lang/Object;)Z
       5: ireturn

  public final boolean remove(java.lang.Object);
    Code:
       0: aload_1
       1: instanceof    #11                 // class java/util/Map$Entry
       4: ifeq          10
       7: goto          12
      10: iconst_0
      11: ireturn
      12: aload_0
      13: aload_1
      14: checkcast     #11                 // class java/util/Map$Entry
      17: invokevirtual #38                 // Method remove:(Ljava/util/Map$Entry;)Z
      20: ireturn
}
