Compiled from "PeerEntityIDCriteria.java"
public final class org.opensaml.xml.security.criteria.PeerEntityIDCriteria implements org.opensaml.xml.security.Criteria {
  private java.lang.String peerID;

  public org.opensaml.xml.security.criteria.PeerEntityIDCriteria(java.lang.String);
    Code:
       0: aload_0
       1: invokespecial #1                  // Method java/lang/Object."<init>":()V
       4: aload_0
       5: aload_1
       6: invokevirtual #2                  // Method setPeerID:(Ljava/lang/String;)V
       9: return

  public java.lang.String getPeerID();
    Code:
       0: aload_0
       1: getfield      #3                  // Field peerID:Ljava/lang/String;
       4: areturn

  public void setPeerID(java.lang.String);
    Code:
       0: aload_1
       1: invokestatic  #4                  // Method org/opensaml/xml/util/DatatypeHelper.safeTrimOrNullString:(Ljava/lang/String;)Ljava/lang/String;
       4: astore_2
       5: aload_2
       6: ifnonnull     19
       9: new           #5                  // class java/lang/IllegalArgumentException
      12: dup
      13: ldc           #6                  // String Peer entity ID criteria must be supplied
      15: invokespecial #7                  // Method java/lang/IllegalArgumentException."<init>":(Ljava/lang/String;)V
      18: athrow
      19: aload_0
      20: aload_2
      21: putfield      #3                  // Field peerID:Ljava/lang/String;
      24: return
}
