Compiled from "ImplicitTldRuleSet.java"
class org.apache.tomcat.util.descriptor.tld.ImplicitTldRuleSet$ElementNotAllowedRule extends org.apache.tomcat.util.digester.Rule {
  private org.apache.tomcat.util.descriptor.tld.ImplicitTldRuleSet$ElementNotAllowedRule();
    Code:
       0: aload_0
       1: invokespecial #2                  // Method org/apache/tomcat/util/digester/Rule."<init>":()V
       4: return

  public void begin(java.lang.String, java.lang.String, org.xml.sax.Attributes) throws java.lang.Exception;
    Code:
       0: new           #3                  // class java/lang/IllegalArgumentException
       3: dup
       4: invokestatic  #4                  // Method org/apache/tomcat/util/descriptor/tld/ImplicitTldRuleSet.access$100:()Lorg/apache/tomcat/util/res/StringManager;
       7: ldc           #5                  // String implicitTldRule.elementNotAllowed
       9: iconst_1
      10: anewarray     #6                  // class java/lang/Object
      13: dup
      14: iconst_0
      15: aload_2
      16: aastore
      17: invokevirtual #7                  // Method org/apache/tomcat/util/res/StringManager.getString:(Ljava/lang/String;[Ljava/lang/Object;)Ljava/lang/String;
      20: invokespecial #8                  // Method java/lang/IllegalArgumentException."<init>":(Ljava/lang/String;)V
      23: athrow

  org.apache.tomcat.util.descriptor.tld.ImplicitTldRuleSet$ElementNotAllowedRule(org.apache.tomcat.util.descriptor.tld.ImplicitTldRuleSet$1);
    Code:
       0: aload_0
       1: invokespecial #1                  // Method "<init>":()V
       4: return
}
