Compiled from "CorsConfigBuilder.java"
public final class io.netty.handler.codec.http.cors.CorsConfigBuilder {
  final java.util.Set<java.lang.String> origins;

  final boolean anyOrigin;

  boolean allowNullOrigin;

  boolean enabled;

  boolean allowCredentials;

  final java.util.Set<java.lang.String> exposeHeaders;

  long maxAge;

  final java.util.Set<io.netty.handler.codec.http.HttpMethod> requestMethods;

  final java.util.Set<java.lang.String> requestHeaders;

  final java.util.Map<java.lang.CharSequence, java.util.concurrent.Callable<?>> preflightHeaders;

  private boolean noPreflightHeaders;

  boolean shortCircuit;

  public static io.netty.handler.codec.http.cors.CorsConfigBuilder forAnyOrigin();
    Code:
       0: new           #1                  // class io/netty/handler/codec/http/cors/CorsConfigBuilder
       3: dup
       4: invokespecial #2                  // Method "<init>":()V
       7: areturn

  public static io.netty.handler.codec.http.cors.CorsConfigBuilder forOrigin(java.lang.String);
    Code:
       0: ldc           #3                  // String *
       2: aload_0
       3: invokevirtual #4                  // Method java/lang/String.equals:(Ljava/lang/Object;)Z
       6: ifeq          17
       9: new           #1                  // class io/netty/handler/codec/http/cors/CorsConfigBuilder
      12: dup
      13: invokespecial #2                  // Method "<init>":()V
      16: areturn
      17: new           #1                  // class io/netty/handler/codec/http/cors/CorsConfigBuilder
      20: dup
      21: iconst_1
      22: anewarray     #5                  // class java/lang/String
      25: dup
      26: iconst_0
      27: aload_0
      28: aastore
      29: invokespecial #6                  // Method "<init>":([Ljava/lang/String;)V
      32: areturn

  public static io.netty.handler.codec.http.cors.CorsConfigBuilder forOrigins(java.lang.String...);
    Code:
       0: new           #1                  // class io/netty/handler/codec/http/cors/CorsConfigBuilder
       3: dup
       4: aload_0
       5: invokespecial #6                  // Method "<init>":([Ljava/lang/String;)V
       8: areturn

  io.netty.handler.codec.http.cors.CorsConfigBuilder(java.lang.String...);
    Code:
       0: aload_0
       1: invokespecial #7                  // Method java/lang/Object."<init>":()V
       4: aload_0
       5: iconst_1
       6: putfield      #8                  // Field enabled:Z
       9: aload_0
      10: new           #9                  // class java/util/HashSet
      13: dup
      14: invokespecial #10                 // Method java/util/HashSet."<init>":()V
      17: putfield      #11                 // Field exposeHeaders:Ljava/util/Set;
      20: aload_0
      21: new           #9                  // class java/util/HashSet
      24: dup
      25: invokespecial #10                 // Method java/util/HashSet."<init>":()V
      28: putfield      #12                 // Field requestMethods:Ljava/util/Set;
      31: aload_0
      32: new           #9                  // class java/util/HashSet
      35: dup
      36: invokespecial #10                 // Method java/util/HashSet."<init>":()V
      39: putfield      #13                 // Field requestHeaders:Ljava/util/Set;
      42: aload_0
      43: new           #14                 // class java/util/HashMap
      46: dup
      47: invokespecial #15                 // Method java/util/HashMap."<init>":()V
      50: putfield      #16                 // Field preflightHeaders:Ljava/util/Map;
      53: aload_0
      54: new           #17                 // class java/util/LinkedHashSet
      57: dup
      58: aload_1
      59: invokestatic  #18                 // Method java/util/Arrays.asList:([Ljava/lang/Object;)Ljava/util/List;
      62: invokespecial #19                 // Method java/util/LinkedHashSet."<init>":(Ljava/util/Collection;)V
      65: putfield      #20                 // Field origins:Ljava/util/Set;
      68: aload_0
      69: iconst_0
      70: putfield      #21                 // Field anyOrigin:Z
      73: return

  io.netty.handler.codec.http.cors.CorsConfigBuilder();
    Code:
       0: aload_0
       1: invokespecial #7                  // Method java/lang/Object."<init>":()V
       4: aload_0
       5: iconst_1
       6: putfield      #8                  // Field enabled:Z
       9: aload_0
      10: new           #9                  // class java/util/HashSet
      13: dup
      14: invokespecial #10                 // Method java/util/HashSet."<init>":()V
      17: putfield      #11                 // Field exposeHeaders:Ljava/util/Set;
      20: aload_0
      21: new           #9                  // class java/util/HashSet
      24: dup
      25: invokespecial #10                 // Method java/util/HashSet."<init>":()V
      28: putfield      #12                 // Field requestMethods:Ljava/util/Set;
      31: aload_0
      32: new           #9                  // class java/util/HashSet
      35: dup
      36: invokespecial #10                 // Method java/util/HashSet."<init>":()V
      39: putfield      #13                 // Field requestHeaders:Ljava/util/Set;
      42: aload_0
      43: new           #14                 // class java/util/HashMap
      46: dup
      47: invokespecial #15                 // Method java/util/HashMap."<init>":()V
      50: putfield      #16                 // Field preflightHeaders:Ljava/util/Map;
      53: aload_0
      54: iconst_1
      55: putfield      #21                 // Field anyOrigin:Z
      58: aload_0
      59: invokestatic  #22                 // Method java/util/Collections.emptySet:()Ljava/util/Set;
      62: putfield      #20                 // Field origins:Ljava/util/Set;
      65: return

  public io.netty.handler.codec.http.cors.CorsConfigBuilder allowNullOrigin();
    Code:
       0: aload_0
       1: iconst_1
       2: putfield      #23                 // Field allowNullOrigin:Z
       5: aload_0
       6: areturn

  public io.netty.handler.codec.http.cors.CorsConfigBuilder disable();
    Code:
       0: aload_0
       1: iconst_0
       2: putfield      #8                  // Field enabled:Z
       5: aload_0
       6: areturn

  public io.netty.handler.codec.http.cors.CorsConfigBuilder exposeHeaders(java.lang.String...);
    Code:
       0: aload_0
       1: getfield      #11                 // Field exposeHeaders:Ljava/util/Set;
       4: aload_1
       5: invokestatic  #18                 // Method java/util/Arrays.asList:([Ljava/lang/Object;)Ljava/util/List;
       8: invokeinterface #24,  2           // InterfaceMethod java/util/Set.addAll:(Ljava/util/Collection;)Z
      13: pop
      14: aload_0
      15: areturn

  public io.netty.handler.codec.http.cors.CorsConfigBuilder exposeHeaders(java.lang.CharSequence...);
    Code:
       0: aload_1
       1: astore_2
       2: aload_2
       3: arraylength
       4: istore_3
       5: iconst_0
       6: istore        4
       8: iload         4
      10: iload_3
      11: if_icmpge     43
      14: aload_2
      15: iload         4
      17: aaload
      18: astore        5
      20: aload_0
      21: getfield      #11                 // Field exposeHeaders:Ljava/util/Set;
      24: aload         5
      26: invokeinterface #25,  1           // InterfaceMethod java/lang/CharSequence.toString:()Ljava/lang/String;
      31: invokeinterface #26,  2           // InterfaceMethod java/util/Set.add:(Ljava/lang/Object;)Z
      36: pop
      37: iinc          4, 1
      40: goto          8
      43: aload_0
      44: areturn

  public io.netty.handler.codec.http.cors.CorsConfigBuilder allowCredentials();
    Code:
       0: aload_0
       1: iconst_1
       2: putfield      #27                 // Field allowCredentials:Z
       5: aload_0
       6: areturn

  public io.netty.handler.codec.http.cors.CorsConfigBuilder maxAge(long);
    Code:
       0: aload_0
       1: lload_1
       2: putfield      #28                 // Field maxAge:J
       5: aload_0
       6: areturn

  public io.netty.handler.codec.http.cors.CorsConfigBuilder allowedRequestMethods(io.netty.handler.codec.http.HttpMethod...);
    Code:
       0: aload_0
       1: getfield      #12                 // Field requestMethods:Ljava/util/Set;
       4: aload_1
       5: invokestatic  #18                 // Method java/util/Arrays.asList:([Ljava/lang/Object;)Ljava/util/List;
       8: invokeinterface #24,  2           // InterfaceMethod java/util/Set.addAll:(Ljava/util/Collection;)Z
      13: pop
      14: aload_0
      15: areturn

  public io.netty.handler.codec.http.cors.CorsConfigBuilder allowedRequestHeaders(java.lang.String...);
    Code:
       0: aload_0
       1: getfield      #13                 // Field requestHeaders:Ljava/util/Set;
       4: aload_1
       5: invokestatic  #18                 // Method java/util/Arrays.asList:([Ljava/lang/Object;)Ljava/util/List;
       8: invokeinterface #24,  2           // InterfaceMethod java/util/Set.addAll:(Ljava/util/Collection;)Z
      13: pop
      14: aload_0
      15: areturn

  public io.netty.handler.codec.http.cors.CorsConfigBuilder allowedRequestHeaders(java.lang.CharSequence...);
    Code:
       0: aload_1
       1: astore_2
       2: aload_2
       3: arraylength
       4: istore_3
       5: iconst_0
       6: istore        4
       8: iload         4
      10: iload_3
      11: if_icmpge     43
      14: aload_2
      15: iload         4
      17: aaload
      18: astore        5
      20: aload_0
      21: getfield      #13                 // Field requestHeaders:Ljava/util/Set;
      24: aload         5
      26: invokeinterface #25,  1           // InterfaceMethod java/lang/CharSequence.toString:()Ljava/lang/String;
      31: invokeinterface #26,  2           // InterfaceMethod java/util/Set.add:(Ljava/lang/Object;)Z
      36: pop
      37: iinc          4, 1
      40: goto          8
      43: aload_0
      44: areturn

  public io.netty.handler.codec.http.cors.CorsConfigBuilder preflightResponseHeader(java.lang.CharSequence, java.lang.Object...);
    Code:
       0: aload_2
       1: arraylength
       2: iconst_1
       3: if_icmpne     31
       6: aload_0
       7: getfield      #16                 // Field preflightHeaders:Ljava/util/Map;
      10: aload_1
      11: new           #29                 // class io/netty/handler/codec/http/cors/CorsConfigBuilder$ConstantValueGenerator
      14: dup
      15: aload_2
      16: iconst_0
      17: aaload
      18: aconst_null
      19: invokespecial #30                 // Method io/netty/handler/codec/http/cors/CorsConfigBuilder$ConstantValueGenerator."<init>":(Ljava/lang/Object;Lio/netty/handler/codec/http/cors/CorsConfigBuilder$1;)V
      22: invokeinterface #31,  3           // InterfaceMethod java/util/Map.put:(Ljava/lang/Object;Ljava/lang/Object;)Ljava/lang/Object;
      27: pop
      28: goto          41
      31: aload_0
      32: aload_1
      33: aload_2
      34: invokestatic  #18                 // Method java/util/Arrays.asList:([Ljava/lang/Object;)Ljava/util/List;
      37: invokevirtual #32                 // Method preflightResponseHeader:(Ljava/lang/CharSequence;Ljava/lang/Iterable;)Lio/netty/handler/codec/http/cors/CorsConfigBuilder;
      40: pop
      41: aload_0
      42: areturn

  public <T> io.netty.handler.codec.http.cors.CorsConfigBuilder preflightResponseHeader(java.lang.CharSequence, java.lang.Iterable<T>);
    Code:
       0: aload_0
       1: getfield      #16                 // Field preflightHeaders:Ljava/util/Map;
       4: aload_1
       5: new           #29                 // class io/netty/handler/codec/http/cors/CorsConfigBuilder$ConstantValueGenerator
       8: dup
       9: aload_2
      10: aconst_null
      11: invokespecial #30                 // Method io/netty/handler/codec/http/cors/CorsConfigBuilder$ConstantValueGenerator."<init>":(Ljava/lang/Object;Lio/netty/handler/codec/http/cors/CorsConfigBuilder$1;)V
      14: invokeinterface #31,  3           // InterfaceMethod java/util/Map.put:(Ljava/lang/Object;Ljava/lang/Object;)Ljava/lang/Object;
      19: pop
      20: aload_0
      21: areturn

  public <T> io.netty.handler.codec.http.cors.CorsConfigBuilder preflightResponseHeader(java.lang.CharSequence, java.util.concurrent.Callable<T>);
    Code:
       0: aload_0
       1: getfield      #16                 // Field preflightHeaders:Ljava/util/Map;
       4: aload_1
       5: aload_2
       6: invokeinterface #31,  3           // InterfaceMethod java/util/Map.put:(Ljava/lang/Object;Ljava/lang/Object;)Ljava/lang/Object;
      11: pop
      12: aload_0
      13: areturn

  public io.netty.handler.codec.http.cors.CorsConfigBuilder noPreflightResponseHeaders();
    Code:
       0: aload_0
       1: iconst_1
       2: putfield      #33                 // Field noPreflightHeaders:Z
       5: aload_0
       6: areturn

  public io.netty.handler.codec.http.cors.CorsConfigBuilder shortCircuit();
    Code:
       0: aload_0
       1: iconst_1
       2: putfield      #34                 // Field shortCircuit:Z
       5: aload_0
       6: areturn

  public io.netty.handler.codec.http.cors.CorsConfig build();
    Code:
       0: aload_0
       1: getfield      #16                 // Field preflightHeaders:Ljava/util/Map;
       4: invokeinterface #35,  1           // InterfaceMethod java/util/Map.isEmpty:()Z
       9: ifeq          58
      12: aload_0
      13: getfield      #33                 // Field noPreflightHeaders:Z
      16: ifne          58
      19: aload_0
      20: getfield      #16                 // Field preflightHeaders:Ljava/util/Map;
      23: getstatic     #36                 // Field io/netty/handler/codec/http/HttpHeaderNames.DATE:Lio/netty/util/AsciiString;
      26: getstatic     #37                 // Field io/netty/handler/codec/http/cors/CorsConfigBuilder$DateValueGenerator.INSTANCE:Lio/netty/handler/codec/http/cors/CorsConfigBuilder$DateValueGenerator;
      29: invokeinterface #31,  3           // InterfaceMethod java/util/Map.put:(Ljava/lang/Object;Ljava/lang/Object;)Ljava/lang/Object;
      34: pop
      35: aload_0
      36: getfield      #16                 // Field preflightHeaders:Ljava/util/Map;
      39: getstatic     #38                 // Field io/netty/handler/codec/http/HttpHeaderNames.CONTENT_LENGTH:Lio/netty/util/AsciiString;
      42: new           #29                 // class io/netty/handler/codec/http/cors/CorsConfigBuilder$ConstantValueGenerator
      45: dup
      46: ldc           #39                 // String 0
      48: aconst_null
      49: invokespecial #30                 // Method io/netty/handler/codec/http/cors/CorsConfigBuilder$ConstantValueGenerator."<init>":(Ljava/lang/Object;Lio/netty/handler/codec/http/cors/CorsConfigBuilder$1;)V
      52: invokeinterface #31,  3           // InterfaceMethod java/util/Map.put:(Ljava/lang/Object;Ljava/lang/Object;)Ljava/lang/Object;
      57: pop
      58: new           #40                 // class io/netty/handler/codec/http/cors/CorsConfig
      61: dup
      62: aload_0
      63: invokespecial #41                 // Method io/netty/handler/codec/http/cors/CorsConfig."<init>":(Lio/netty/handler/codec/http/cors/CorsConfigBuilder;)V
      66: areturn
}
