Compiled from "WebswingAuthenticationException.java"
public class org.webswing.server.services.security.api.WebswingAuthenticationException extends java.lang.Exception {
  private static final long serialVersionUID;

  public static final java.lang.String INVALID_USER_OR_PASSWORD;

  public static final java.lang.String FAILED_TO_AUTHENTICATE;

  public static final java.lang.String SERVER_NOT_AVAILABLE;

  public static final java.lang.String UNEXPECTED_ERROR;

  public static final java.lang.String NO_ACCESS;

  public static final java.lang.String CONFIG_ERROR;

  java.lang.String localizationKey;

  public org.webswing.server.services.security.api.WebswingAuthenticationException(java.lang.String);
    Code:
       0: aload_0
       1: aload_1
       2: invokespecial #1                  // Method java/lang/Exception."<init>":(Ljava/lang/String;)V
       5: return

  public org.webswing.server.services.security.api.WebswingAuthenticationException(java.lang.String, java.lang.Throwable);
    Code:
       0: aload_0
       1: aload_1
       2: aload_2
       3: invokespecial #2                  // Method java/lang/Exception."<init>":(Ljava/lang/String;Ljava/lang/Throwable;)V
       6: return

  public org.webswing.server.services.security.api.WebswingAuthenticationException(java.lang.String, java.lang.String);
    Code:
       0: aload_0
       1: aload_1
       2: invokespecial #1                  // Method java/lang/Exception."<init>":(Ljava/lang/String;)V
       5: aload_0
       6: aload_2
       7: putfield      #3                  // Field localizationKey:Ljava/lang/String;
      10: return

  public org.webswing.server.services.security.api.WebswingAuthenticationException(java.lang.String, java.lang.String, java.lang.Throwable);
    Code:
       0: aload_0
       1: aload_1
       2: aload_3
       3: invokespecial #2                  // Method java/lang/Exception."<init>":(Ljava/lang/String;Ljava/lang/Throwable;)V
       6: aload_0
       7: aload_2
       8: putfield      #3                  // Field localizationKey:Ljava/lang/String;
      11: return

  public java.lang.String getLocalizedMessage();
    Code:
       0: aload_0
       1: getfield      #3                  // Field localizationKey:Ljava/lang/String;
       4: ifnonnull     14
       7: aload_0
       8: invokespecial #4                  // Method java/lang/Exception.getLocalizedMessage:()Ljava/lang/String;
      11: goto          41
      14: new           #5                  // class java/lang/StringBuilder
      17: dup
      18: invokespecial #6                  // Method java/lang/StringBuilder."<init>":()V
      21: ldc           #7                  // String ${
      23: invokevirtual #8                  // Method java/lang/StringBuilder.append:(Ljava/lang/String;)Ljava/lang/StringBuilder;
      26: aload_0
      27: getfield      #3                  // Field localizationKey:Ljava/lang/String;
      30: invokevirtual #8                  // Method java/lang/StringBuilder.append:(Ljava/lang/String;)Ljava/lang/StringBuilder;
      33: ldc           #9                  // String }
      35: invokevirtual #8                  // Method java/lang/StringBuilder.append:(Ljava/lang/String;)Ljava/lang/StringBuilder;
      38: invokevirtual #10                 // Method java/lang/StringBuilder.toString:()Ljava/lang/String;
      41: areturn
}
