Compiled from "HttpProducer.java"
class org.apache.camel.component.http4.HttpProducer$1 extends org.apache.camel.support.SynchronizationAdapter {
  final org.apache.http.HttpResponse val$response;

  final org.apache.camel.component.http4.HttpProducer this$0;

  org.apache.camel.component.http4.HttpProducer$1(org.apache.camel.component.http4.HttpProducer, org.apache.http.HttpResponse);
    Code:
       0: aload_0
       1: aload_1
       2: putfield      #1                  // Field this$0:Lorg/apache/camel/component/http4/HttpProducer;
       5: aload_0
       6: aload_2
       7: putfield      #2                  // Field val$response:Lorg/apache/http/HttpResponse;
      10: aload_0
      11: invokespecial #3                  // Method org/apache/camel/support/SynchronizationAdapter."<init>":()V
      14: return

  public void onDone(org.apache.camel.Exchange);
    Code:
       0: aload_0
       1: getfield      #2                  // Field val$response:Lorg/apache/http/HttpResponse;
       4: invokeinterface #4,  1            // InterfaceMethod org/apache/http/HttpResponse.getEntity:()Lorg/apache/http/HttpEntity;
       9: invokestatic  #5                  // Method org/apache/http/util/EntityUtils.consume:(Lorg/apache/http/HttpEntity;)V
      12: goto          16
      15: astore_2
      16: return
    Exception table:
       from    to  target type
           0    12    15   Class java/lang/Throwable
}
