Compiled from "LookupResponse.java"
class com.sproutsocial.nsq.LookupResponse$Producer {
  private java.lang.String broadcastAddress;

  private int tcpPort;

  com.sproutsocial.nsq.LookupResponse$Producer();
    Code:
       0: aload_0
       1: invokespecial #1                  // Method java/lang/Object."<init>":()V
       4: return

  public java.lang.String getBroadcastAddress();
    Code:
       0: aload_0
       1: getfield      #2                  // Field broadcastAddress:Ljava/lang/String;
       4: areturn

  public void setBroadcastAddress(java.lang.String);
    Code:
       0: aload_0
       1: aload_1
       2: putfield      #2                  // Field broadcastAddress:Ljava/lang/String;
       5: return

  public int getTcpPort();
    Code:
       0: aload_0
       1: getfield      #3                  // Field tcpPort:I
       4: ireturn

  public void setTcpPort(int);
    Code:
       0: aload_0
       1: iload_1
       2: putfield      #3                  // Field tcpPort:I
       5: return

  public java.lang.String toString();
    Code:
       0: new           #4                  // class java/lang/StringBuilder
       3: dup
       4: invokespecial #5                  // Method java/lang/StringBuilder."<init>":()V
       7: ldc           #6                  // String Producer{broadcastAddress=\'
       9: invokevirtual #7                  // Method java/lang/StringBuilder.append:(Ljava/lang/String;)Ljava/lang/StringBuilder;
      12: aload_0
      13: getfield      #2                  // Field broadcastAddress:Ljava/lang/String;
      16: invokevirtual #7                  // Method java/lang/StringBuilder.append:(Ljava/lang/String;)Ljava/lang/StringBuilder;
      19: bipush        39
      21: invokevirtual #8                  // Method java/lang/StringBuilder.append:(C)Ljava/lang/StringBuilder;
      24: ldc           #9                  // String , tcpPort=
      26: invokevirtual #7                  // Method java/lang/StringBuilder.append:(Ljava/lang/String;)Ljava/lang/StringBuilder;
      29: aload_0
      30: getfield      #3                  // Field tcpPort:I
      33: invokevirtual #10                 // Method java/lang/StringBuilder.append:(I)Ljava/lang/StringBuilder;
      36: bipush        125
      38: invokevirtual #8                  // Method java/lang/StringBuilder.append:(C)Ljava/lang/StringBuilder;
      41: invokevirtual #11                 // Method java/lang/StringBuilder.toString:()Ljava/lang/String;
      44: areturn
}
