Compiled from "ClassLoaderHierarchyMatcher.java"
public class net.bytebuddy.matcher.ClassLoaderHierarchyMatcher<T extends java.lang.ClassLoader> extends net.bytebuddy.matcher.ElementMatcher$Junction$AbstractBase<T> {
  private final net.bytebuddy.matcher.ElementMatcher<? super java.lang.ClassLoader> matcher;

  public net.bytebuddy.matcher.ClassLoaderHierarchyMatcher(net.bytebuddy.matcher.ElementMatcher<? super java.lang.ClassLoader>);
    Code:
       0: aload_0
       1: invokespecial #20                 // Method net/bytebuddy/matcher/ElementMatcher$Junction$AbstractBase."<init>":()V
       4: aload_0
       5: aload_1
       6: putfield      #22                 // Field matcher:Lnet/bytebuddy/matcher/ElementMatcher;
       9: return

  public boolean matches(T);
    Code:
       0: aload_1
       1: astore_2
       2: aload_2
       3: ifnull        29
       6: aload_0
       7: getfield      #22                 // Field matcher:Lnet/bytebuddy/matcher/ElementMatcher;
      10: aload_2
      11: invokeinterface #32,  2           // InterfaceMethod net/bytebuddy/matcher/ElementMatcher.matches:(Ljava/lang/Object;)Z
      16: ifeq          21
      19: iconst_1
      20: ireturn
      21: aload_2
      22: invokevirtual #36                 // Method java/lang/ClassLoader.getParent:()Ljava/lang/ClassLoader;
      25: astore_2
      26: goto          2
      29: aload_0
      30: getfield      #22                 // Field matcher:Lnet/bytebuddy/matcher/ElementMatcher;
      33: aconst_null
      34: invokeinterface #32,  2           // InterfaceMethod net/bytebuddy/matcher/ElementMatcher.matches:(Ljava/lang/Object;)Z
      39: ireturn

  public java.lang.String toString();
    Code:
       0: new           #44                 // class java/lang/StringBuilder
       3: dup
       4: invokespecial #45                 // Method java/lang/StringBuilder."<init>":()V
       7: ldc           #47                 // String hasChild(
       9: invokevirtual #51                 // Method java/lang/StringBuilder.append:(Ljava/lang/String;)Ljava/lang/StringBuilder;
      12: aload_0
      13: getfield      #22                 // Field matcher:Lnet/bytebuddy/matcher/ElementMatcher;
      16: invokevirtual #54                 // Method java/lang/StringBuilder.append:(Ljava/lang/Object;)Ljava/lang/StringBuilder;
      19: bipush        41
      21: invokevirtual #57                 // Method java/lang/StringBuilder.append:(C)Ljava/lang/StringBuilder;
      24: invokevirtual #59                 // Method java/lang/StringBuilder.toString:()Ljava/lang/String;
      27: areturn

  public boolean equals(java.lang.Object);
    Code:
       0: aload_1
       1: aload_0
       2: if_acmpne     7
       5: iconst_1
       6: ireturn
       7: aload_1
       8: instanceof    #2                  // class net/bytebuddy/matcher/ClassLoaderHierarchyMatcher
      11: ifne          16
      14: iconst_0
      15: ireturn
      16: aload_1
      17: checkcast     #2                  // class net/bytebuddy/matcher/ClassLoaderHierarchyMatcher
      20: astore_2
      21: aload_2
      22: aload_0
      23: invokevirtual #63                 // Method canEqual:(Ljava/lang/Object;)Z
      26: ifne          31
      29: iconst_0
      30: ireturn
      31: aload_0
      32: getfield      #22                 // Field matcher:Lnet/bytebuddy/matcher/ElementMatcher;
      35: astore_3
      36: aload_2
      37: getfield      #22                 // Field matcher:Lnet/bytebuddy/matcher/ElementMatcher;
      40: astore        4
      42: aload_3
      43: ifnonnull     54
      46: aload         4
      48: ifnull        65
      51: goto          63
      54: aload_3
      55: aload         4
      57: invokevirtual #67                 // Method java/lang/Object.equals:(Ljava/lang/Object;)Z
      60: ifne          65
      63: iconst_0
      64: ireturn
      65: iconst_1
      66: ireturn

  protected boolean canEqual(java.lang.Object);
    Code:
       0: aload_1
       1: instanceof    #2                  // class net/bytebuddy/matcher/ClassLoaderHierarchyMatcher
       4: ireturn

  public int hashCode();
    Code:
       0: bipush        59
       2: istore_1
       3: iconst_1
       4: istore_2
       5: aload_0
       6: getfield      #22                 // Field matcher:Lnet/bytebuddy/matcher/ElementMatcher;
       9: astore_3
      10: iload_2
      11: bipush        59
      13: imul
      14: aload_3
      15: ifnonnull     23
      18: bipush        43
      20: goto          27
      23: aload_3
      24: invokevirtual #77                 // Method java/lang/Object.hashCode:()I
      27: iadd
      28: istore_2
      29: iload_2
      30: ireturn

  public boolean matches(java.lang.Object);
    Code:
       0: aload_0
       1: aload_1
       2: checkcast     #29                 // class java/lang/ClassLoader
       5: invokevirtual #83                 // Method matches:(Ljava/lang/ClassLoader;)Z
       8: ireturn
}
