Compiled from "ListLinks.java"
public class org.jsoup.examples.ListLinks {
  public org.jsoup.examples.ListLinks();
    Code:
       0: aload_0
       1: invokespecial #1                  // Method java/lang/Object."<init>":()V
       4: return

  public static void main(java.lang.String[]) throws java.io.IOException;
    Code:
       0: aload_0
       1: arraylength
       2: iconst_1
       3: if_icmpne     10
       6: iconst_1
       7: goto          11
      10: iconst_0
      11: ldc           #2                  // String usage: supply url to fetch
      13: invokestatic  #3                  // Method org/jsoup/helper/Validate.isTrue:(ZLjava/lang/String;)V
      16: aload_0
      17: iconst_0
      18: aaload
      19: astore_1
      20: ldc           #4                  // String Fetching %s...
      22: iconst_1
      23: anewarray     #5                  // class java/lang/Object
      26: dup
      27: iconst_0
      28: aload_1
      29: aastore
      30: invokestatic  #6                  // Method print:(Ljava/lang/String;[Ljava/lang/Object;)V
      33: aload_1
      34: invokestatic  #7                  // Method org/jsoup/Jsoup.connect:(Ljava/lang/String;)Lorg/jsoup/Connection;
      37: invokeinterface #8,  1            // InterfaceMethod org/jsoup/Connection.get:()Lorg/jsoup/nodes/Document;
      42: astore_2
      43: aload_2
      44: ldc           #9                  // String a[href]
      46: invokevirtual #10                 // Method org/jsoup/nodes/Document.select:(Ljava/lang/String;)Lorg/jsoup/select/Elements;
      49: astore_3
      50: aload_2
      51: ldc           #11                 // String [src]
      53: invokevirtual #10                 // Method org/jsoup/nodes/Document.select:(Ljava/lang/String;)Lorg/jsoup/select/Elements;
      56: astore        4
      58: aload_2
      59: ldc           #12                 // String link[href]
      61: invokevirtual #10                 // Method org/jsoup/nodes/Document.select:(Ljava/lang/String;)Lorg/jsoup/select/Elements;
      64: astore        5
      66: ldc           #13                 // String \nMedia: (%d)
      68: iconst_1
      69: anewarray     #5                  // class java/lang/Object
      72: dup
      73: iconst_0
      74: aload         4
      76: invokevirtual #14                 // Method org/jsoup/select/Elements.size:()I
      79: invokestatic  #15                 // Method java/lang/Integer.valueOf:(I)Ljava/lang/Integer;
      82: aastore
      83: invokestatic  #6                  // Method print:(Ljava/lang/String;[Ljava/lang/Object;)V
      86: aload         4
      88: invokevirtual #16                 // Method org/jsoup/select/Elements.iterator:()Ljava/util/Iterator;
      91: astore        6
      93: aload         6
      95: invokeinterface #17,  1           // InterfaceMethod java/util/Iterator.hasNext:()Z
     100: ifeq          223
     103: aload         6
     105: invokeinterface #18,  1           // InterfaceMethod java/util/Iterator.next:()Ljava/lang/Object;
     110: checkcast     #19                 // class org/jsoup/nodes/Element
     113: astore        7
     115: aload         7
     117: invokevirtual #20                 // Method org/jsoup/nodes/Element.tagName:()Ljava/lang/String;
     120: ldc           #21                 // String img
     122: invokevirtual #22                 // Method java/lang/String.equals:(Ljava/lang/Object;)Z
     125: ifeq          193
     128: ldc           #23                 // String  * %s: <%s> %sx%s (%s)
     130: iconst_5
     131: anewarray     #5                  // class java/lang/Object
     134: dup
     135: iconst_0
     136: aload         7
     138: invokevirtual #20                 // Method org/jsoup/nodes/Element.tagName:()Ljava/lang/String;
     141: aastore
     142: dup
     143: iconst_1
     144: aload         7
     146: ldc           #24                 // String abs:src
     148: invokevirtual #25                 // Method org/jsoup/nodes/Element.attr:(Ljava/lang/String;)Ljava/lang/String;
     151: aastore
     152: dup
     153: iconst_2
     154: aload         7
     156: ldc           #26                 // String width
     158: invokevirtual #25                 // Method org/jsoup/nodes/Element.attr:(Ljava/lang/String;)Ljava/lang/String;
     161: aastore
     162: dup
     163: iconst_3
     164: aload         7
     166: ldc           #27                 // String height
     168: invokevirtual #25                 // Method org/jsoup/nodes/Element.attr:(Ljava/lang/String;)Ljava/lang/String;
     171: aastore
     172: dup
     173: iconst_4
     174: aload         7
     176: ldc           #28                 // String alt
     178: invokevirtual #25                 // Method org/jsoup/nodes/Element.attr:(Ljava/lang/String;)Ljava/lang/String;
     181: bipush        20
     183: invokestatic  #29                 // Method trim:(Ljava/lang/String;I)Ljava/lang/String;
     186: aastore
     187: invokestatic  #6                  // Method print:(Ljava/lang/String;[Ljava/lang/Object;)V
     190: goto          220
     193: ldc           #30                 // String  * %s: <%s>
     195: iconst_2
     196: anewarray     #5                  // class java/lang/Object
     199: dup
     200: iconst_0
     201: aload         7
     203: invokevirtual #20                 // Method org/jsoup/nodes/Element.tagName:()Ljava/lang/String;
     206: aastore
     207: dup
     208: iconst_1
     209: aload         7
     211: ldc           #24                 // String abs:src
     213: invokevirtual #25                 // Method org/jsoup/nodes/Element.attr:(Ljava/lang/String;)Ljava/lang/String;
     216: aastore
     217: invokestatic  #6                  // Method print:(Ljava/lang/String;[Ljava/lang/Object;)V
     220: goto          93
     223: ldc           #31                 // String \nImports: (%d)
     225: iconst_1
     226: anewarray     #5                  // class java/lang/Object
     229: dup
     230: iconst_0
     231: aload         5
     233: invokevirtual #14                 // Method org/jsoup/select/Elements.size:()I
     236: invokestatic  #15                 // Method java/lang/Integer.valueOf:(I)Ljava/lang/Integer;
     239: aastore
     240: invokestatic  #6                  // Method print:(Ljava/lang/String;[Ljava/lang/Object;)V
     243: aload         5
     245: invokevirtual #16                 // Method org/jsoup/select/Elements.iterator:()Ljava/util/Iterator;
     248: astore        6
     250: aload         6
     252: invokeinterface #17,  1           // InterfaceMethod java/util/Iterator.hasNext:()Z
     257: ifeq          312
     260: aload         6
     262: invokeinterface #18,  1           // InterfaceMethod java/util/Iterator.next:()Ljava/lang/Object;
     267: checkcast     #19                 // class org/jsoup/nodes/Element
     270: astore        7
     272: ldc           #32                 // String  * %s <%s> (%s)
     274: iconst_3
     275: anewarray     #5                  // class java/lang/Object
     278: dup
     279: iconst_0
     280: aload         7
     282: invokevirtual #20                 // Method org/jsoup/nodes/Element.tagName:()Ljava/lang/String;
     285: aastore
     286: dup
     287: iconst_1
     288: aload         7
     290: ldc           #33                 // String abs:href
     292: invokevirtual #25                 // Method org/jsoup/nodes/Element.attr:(Ljava/lang/String;)Ljava/lang/String;
     295: aastore
     296: dup
     297: iconst_2
     298: aload         7
     300: ldc           #34                 // String rel
     302: invokevirtual #25                 // Method org/jsoup/nodes/Element.attr:(Ljava/lang/String;)Ljava/lang/String;
     305: aastore
     306: invokestatic  #6                  // Method print:(Ljava/lang/String;[Ljava/lang/Object;)V
     309: goto          250
     312: ldc           #35                 // String \nLinks: (%d)
     314: iconst_1
     315: anewarray     #5                  // class java/lang/Object
     318: dup
     319: iconst_0
     320: aload_3
     321: invokevirtual #14                 // Method org/jsoup/select/Elements.size:()I
     324: invokestatic  #15                 // Method java/lang/Integer.valueOf:(I)Ljava/lang/Integer;
     327: aastore
     328: invokestatic  #6                  // Method print:(Ljava/lang/String;[Ljava/lang/Object;)V
     331: aload_3
     332: invokevirtual #16                 // Method org/jsoup/select/Elements.iterator:()Ljava/util/Iterator;
     335: astore        6
     337: aload         6
     339: invokeinterface #17,  1           // InterfaceMethod java/util/Iterator.hasNext:()Z
     344: ifeq          394
     347: aload         6
     349: invokeinterface #18,  1           // InterfaceMethod java/util/Iterator.next:()Ljava/lang/Object;
     354: checkcast     #19                 // class org/jsoup/nodes/Element
     357: astore        7
     359: ldc           #36                 // String  * a: <%s>  (%s)
     361: iconst_2
     362: anewarray     #5                  // class java/lang/Object
     365: dup
     366: iconst_0
     367: aload         7
     369: ldc           #33                 // String abs:href
     371: invokevirtual #25                 // Method org/jsoup/nodes/Element.attr:(Ljava/lang/String;)Ljava/lang/String;
     374: aastore
     375: dup
     376: iconst_1
     377: aload         7
     379: invokevirtual #37                 // Method org/jsoup/nodes/Element.text:()Ljava/lang/String;
     382: bipush        35
     384: invokestatic  #29                 // Method trim:(Ljava/lang/String;I)Ljava/lang/String;
     387: aastore
     388: invokestatic  #6                  // Method print:(Ljava/lang/String;[Ljava/lang/Object;)V
     391: goto          337
     394: return

  private static void print(java.lang.String, java.lang.Object...);
    Code:
       0: getstatic     #38                 // Field java/lang/System.out:Ljava/io/PrintStream;
       3: aload_0
       4: aload_1
       5: invokestatic  #39                 // Method java/lang/String.format:(Ljava/lang/String;[Ljava/lang/Object;)Ljava/lang/String;
       8: invokevirtual #40                 // Method java/io/PrintStream.println:(Ljava/lang/String;)V
      11: return

  private static java.lang.String trim(java.lang.String, int);
    Code:
       0: aload_0
       1: invokevirtual #41                 // Method java/lang/String.length:()I
       4: iload_1
       5: if_icmple     35
       8: new           #42                 // class java/lang/StringBuilder
      11: dup
      12: invokespecial #43                 // Method java/lang/StringBuilder."<init>":()V
      15: aload_0
      16: iconst_0
      17: iload_1
      18: iconst_1
      19: isub
      20: invokevirtual #44                 // Method java/lang/String.substring:(II)Ljava/lang/String;
      23: invokevirtual #45                 // Method java/lang/StringBuilder.append:(Ljava/lang/String;)Ljava/lang/StringBuilder;
      26: ldc           #46                 // String .
      28: invokevirtual #45                 // Method java/lang/StringBuilder.append:(Ljava/lang/String;)Ljava/lang/StringBuilder;
      31: invokevirtual #47                 // Method java/lang/StringBuilder.toString:()Ljava/lang/String;
      34: areturn
      35: aload_0
      36: areturn
}
