Compiled from "ListMilestonesPublisher.java"
class software.amazon.awssdk.services.wellarchitected.paginators.ListMilestonesPublisher$ListMilestonesResponseFetcher implements software.amazon.awssdk.core.pagination.async.AsyncPageFetcher<software.amazon.awssdk.services.wellarchitected.model.ListMilestonesResponse> {
  final software.amazon.awssdk.services.wellarchitected.paginators.ListMilestonesPublisher this$0;

  private software.amazon.awssdk.services.wellarchitected.paginators.ListMilestonesPublisher$ListMilestonesResponseFetcher(software.amazon.awssdk.services.wellarchitected.paginators.ListMilestonesPublisher);
    Code:
       0: aload_0
       1: aload_1
       2: putfield      #2                  // Field this$0:Lsoftware/amazon/awssdk/services/wellarchitected/paginators/ListMilestonesPublisher;
       5: aload_0
       6: invokespecial #3                  // Method java/lang/Object."<init>":()V
       9: return

  public boolean hasNextPage(software.amazon.awssdk.services.wellarchitected.model.ListMilestonesResponse);
    Code:
       0: aload_1
       1: invokevirtual #4                  // Method software/amazon/awssdk/services/wellarchitected/model/ListMilestonesResponse.nextToken:()Ljava/lang/String;
       4: invokestatic  #5                  // Method software/amazon/awssdk/core/util/PaginatorUtils.isOutputTokenAvailable:(Ljava/lang/Object;)Z
       7: ireturn

  public java.util.concurrent.CompletableFuture<software.amazon.awssdk.services.wellarchitected.model.ListMilestonesResponse> nextPage(software.amazon.awssdk.services.wellarchitected.model.ListMilestonesResponse);
    Code:
       0: aload_1
       1: ifnonnull     24
       4: aload_0
       5: getfield      #2                  // Field this$0:Lsoftware/amazon/awssdk/services/wellarchitected/paginators/ListMilestonesPublisher;
       8: invokestatic  #6                  // Method software/amazon/awssdk/services/wellarchitected/paginators/ListMilestonesPublisher.access$200:(Lsoftware/amazon/awssdk/services/wellarchitected/paginators/ListMilestonesPublisher;)Lsoftware/amazon/awssdk/services/wellarchitected/WellArchitectedAsyncClient;
      11: aload_0
      12: getfield      #2                  // Field this$0:Lsoftware/amazon/awssdk/services/wellarchitected/paginators/ListMilestonesPublisher;
      15: invokestatic  #7                  // Method software/amazon/awssdk/services/wellarchitected/paginators/ListMilestonesPublisher.access$100:(Lsoftware/amazon/awssdk/services/wellarchitected/paginators/ListMilestonesPublisher;)Lsoftware/amazon/awssdk/services/wellarchitected/model/ListMilestonesRequest;
      18: invokeinterface #8,  2            // InterfaceMethod software/amazon/awssdk/services/wellarchitected/WellArchitectedAsyncClient.listMilestones:(Lsoftware/amazon/awssdk/services/wellarchitected/model/ListMilestonesRequest;)Ljava/util/concurrent/CompletableFuture;
      23: areturn
      24: aload_0
      25: getfield      #2                  // Field this$0:Lsoftware/amazon/awssdk/services/wellarchitected/paginators/ListMilestonesPublisher;
      28: invokestatic  #6                  // Method software/amazon/awssdk/services/wellarchitected/paginators/ListMilestonesPublisher.access$200:(Lsoftware/amazon/awssdk/services/wellarchitected/paginators/ListMilestonesPublisher;)Lsoftware/amazon/awssdk/services/wellarchitected/WellArchitectedAsyncClient;
      31: aload_0
      32: getfield      #2                  // Field this$0:Lsoftware/amazon/awssdk/services/wellarchitected/paginators/ListMilestonesPublisher;
      35: invokestatic  #7                  // Method software/amazon/awssdk/services/wellarchitected/paginators/ListMilestonesPublisher.access$100:(Lsoftware/amazon/awssdk/services/wellarchitected/paginators/ListMilestonesPublisher;)Lsoftware/amazon/awssdk/services/wellarchitected/model/ListMilestonesRequest;
      38: invokevirtual #9                  // Method software/amazon/awssdk/services/wellarchitected/model/ListMilestonesRequest.toBuilder:()Lsoftware/amazon/awssdk/services/wellarchitected/model/ListMilestonesRequest$Builder;
      41: aload_1
      42: invokevirtual #4                  // Method software/amazon/awssdk/services/wellarchitected/model/ListMilestonesResponse.nextToken:()Ljava/lang/String;
      45: invokeinterface #10,  2           // InterfaceMethod software/amazon/awssdk/services/wellarchitected/model/ListMilestonesRequest$Builder.nextToken:(Ljava/lang/String;)Lsoftware/amazon/awssdk/services/wellarchitected/model/ListMilestonesRequest$Builder;
      50: invokeinterface #11,  1           // InterfaceMethod software/amazon/awssdk/services/wellarchitected/model/ListMilestonesRequest$Builder.build:()Ljava/lang/Object;
      55: checkcast     #12                 // class software/amazon/awssdk/services/wellarchitected/model/ListMilestonesRequest
      58: invokeinterface #8,  2            // InterfaceMethod software/amazon/awssdk/services/wellarchitected/WellArchitectedAsyncClient.listMilestones:(Lsoftware/amazon/awssdk/services/wellarchitected/model/ListMilestonesRequest;)Ljava/util/concurrent/CompletableFuture;
      63: areturn

  public java.util.concurrent.CompletableFuture nextPage(java.lang.Object);
    Code:
       0: aload_0
       1: aload_1
       2: checkcast     #13                 // class software/amazon/awssdk/services/wellarchitected/model/ListMilestonesResponse
       5: invokevirtual #14                 // Method nextPage:(Lsoftware/amazon/awssdk/services/wellarchitected/model/ListMilestonesResponse;)Ljava/util/concurrent/CompletableFuture;
       8: areturn

  public boolean hasNextPage(java.lang.Object);
    Code:
       0: aload_0
       1: aload_1
       2: checkcast     #13                 // class software/amazon/awssdk/services/wellarchitected/model/ListMilestonesResponse
       5: invokevirtual #15                 // Method hasNextPage:(Lsoftware/amazon/awssdk/services/wellarchitected/model/ListMilestonesResponse;)Z
       8: ireturn

  software.amazon.awssdk.services.wellarchitected.paginators.ListMilestonesPublisher$ListMilestonesResponseFetcher(software.amazon.awssdk.services.wellarchitected.paginators.ListMilestonesPublisher, software.amazon.awssdk.services.wellarchitected.paginators.ListMilestonesPublisher$1);
    Code:
       0: aload_0
       1: aload_1
       2: invokespecial #1                  // Method "<init>":(Lsoftware/amazon/awssdk/services/wellarchitected/paginators/ListMilestonesPublisher;)V
       5: return
}
