Compiled from "LocalHostWebConnectionHtmlUnitDriver.java"
public class org.springframework.boot.test.web.htmlunit.webdriver.LocalHostWebConnectionHtmlUnitDriver extends org.springframework.test.web.servlet.htmlunit.webdriver.WebConnectionHtmlUnitDriver {
  private final org.springframework.core.env.Environment environment;

  public org.springframework.boot.test.web.htmlunit.webdriver.LocalHostWebConnectionHtmlUnitDriver(org.springframework.core.env.Environment);
    Code:
       0: aload_0
       1: invokespecial #1                  // Method org/springframework/test/web/servlet/htmlunit/webdriver/WebConnectionHtmlUnitDriver."<init>":()V
       4: aload_1
       5: ldc           #2                  // String Environment must not be null
       7: invokestatic  #3                  // Method org/springframework/util/Assert.notNull:(Ljava/lang/Object;Ljava/lang/String;)V
      10: aload_0
      11: aload_1
      12: putfield      #4                  // Field environment:Lorg/springframework/core/env/Environment;
      15: return

  public org.springframework.boot.test.web.htmlunit.webdriver.LocalHostWebConnectionHtmlUnitDriver(org.springframework.core.env.Environment, boolean);
    Code:
       0: aload_0
       1: iload_2
       2: invokespecial #5                  // Method org/springframework/test/web/servlet/htmlunit/webdriver/WebConnectionHtmlUnitDriver."<init>":(Z)V
       5: aload_1
       6: ldc           #2                  // String Environment must not be null
       8: invokestatic  #3                  // Method org/springframework/util/Assert.notNull:(Ljava/lang/Object;Ljava/lang/String;)V
      11: aload_0
      12: aload_1
      13: putfield      #4                  // Field environment:Lorg/springframework/core/env/Environment;
      16: return

  public org.springframework.boot.test.web.htmlunit.webdriver.LocalHostWebConnectionHtmlUnitDriver(org.springframework.core.env.Environment, com.gargoylesoftware.htmlunit.BrowserVersion);
    Code:
       0: aload_0
       1: aload_2
       2: invokespecial #6                  // Method org/springframework/test/web/servlet/htmlunit/webdriver/WebConnectionHtmlUnitDriver."<init>":(Lcom/gargoylesoftware/htmlunit/BrowserVersion;)V
       5: aload_1
       6: ldc           #2                  // String Environment must not be null
       8: invokestatic  #3                  // Method org/springframework/util/Assert.notNull:(Ljava/lang/Object;Ljava/lang/String;)V
      11: aload_0
      12: aload_1
      13: putfield      #4                  // Field environment:Lorg/springframework/core/env/Environment;
      16: return

  public org.springframework.boot.test.web.htmlunit.webdriver.LocalHostWebConnectionHtmlUnitDriver(org.springframework.core.env.Environment, org.openqa.selenium.Capabilities);
    Code:
       0: aload_0
       1: aload_2
       2: invokespecial #7                  // Method org/springframework/test/web/servlet/htmlunit/webdriver/WebConnectionHtmlUnitDriver."<init>":(Lorg/openqa/selenium/Capabilities;)V
       5: aload_1
       6: ldc           #2                  // String Environment must not be null
       8: invokestatic  #3                  // Method org/springframework/util/Assert.notNull:(Ljava/lang/Object;Ljava/lang/String;)V
      11: aload_0
      12: aload_1
      13: putfield      #4                  // Field environment:Lorg/springframework/core/env/Environment;
      16: return

  public void get(java.lang.String);
    Code:
       0: aload_1
       1: ldc           #8                  // String /
       3: invokevirtual #9                  // Method java/lang/String.startsWith:(Ljava/lang/String;)Z
       6: ifeq          47
       9: aload_0
      10: getfield      #4                  // Field environment:Lorg/springframework/core/env/Environment;
      13: ldc           #10                 // String local.server.port
      15: ldc           #11                 // String 8080
      17: invokeinterface #12,  3           // InterfaceMethod org/springframework/core/env/Environment.getProperty:(Ljava/lang/String;Ljava/lang/String;)Ljava/lang/String;
      22: astore_2
      23: new           #13                 // class java/lang/StringBuilder
      26: dup
      27: invokespecial #14                 // Method java/lang/StringBuilder."<init>":()V
      30: ldc           #15                 // String http://localhost:
      32: invokevirtual #16                 // Method java/lang/StringBuilder.append:(Ljava/lang/String;)Ljava/lang/StringBuilder;
      35: aload_2
      36: invokevirtual #16                 // Method java/lang/StringBuilder.append:(Ljava/lang/String;)Ljava/lang/StringBuilder;
      39: aload_1
      40: invokevirtual #16                 // Method java/lang/StringBuilder.append:(Ljava/lang/String;)Ljava/lang/StringBuilder;
      43: invokevirtual #17                 // Method java/lang/StringBuilder.toString:()Ljava/lang/String;
      46: astore_1
      47: aload_0
      48: aload_1
      49: invokespecial #18                 // Method org/springframework/test/web/servlet/htmlunit/webdriver/WebConnectionHtmlUnitDriver.get:(Ljava/lang/String;)V
      52: return
}
