Compiled from "IdentifierCaseStrategy.java"
public final class org.hibernate.engine.jdbc.env.spi.IdentifierCaseStrategy extends java.lang.Enum<org.hibernate.engine.jdbc.env.spi.IdentifierCaseStrategy> {
  public static final org.hibernate.engine.jdbc.env.spi.IdentifierCaseStrategy MIXED;

  public static final org.hibernate.engine.jdbc.env.spi.IdentifierCaseStrategy UPPER;

  public static final org.hibernate.engine.jdbc.env.spi.IdentifierCaseStrategy LOWER;

  private static final org.hibernate.engine.jdbc.env.spi.IdentifierCaseStrategy[] $VALUES;

  public static org.hibernate.engine.jdbc.env.spi.IdentifierCaseStrategy[] values();
    Code:
       0: getstatic     #1                  // Field $VALUES:[Lorg/hibernate/engine/jdbc/env/spi/IdentifierCaseStrategy;
       3: invokevirtual #2                  // Method "[Lorg/hibernate/engine/jdbc/env/spi/IdentifierCaseStrategy;".clone:()Ljava/lang/Object;
       6: checkcast     #3                  // class "[Lorg/hibernate/engine/jdbc/env/spi/IdentifierCaseStrategy;"
       9: areturn

  public static org.hibernate.engine.jdbc.env.spi.IdentifierCaseStrategy valueOf(java.lang.String);
    Code:
       0: ldc           #4                  // class org/hibernate/engine/jdbc/env/spi/IdentifierCaseStrategy
       2: aload_0
       3: invokestatic  #5                  // Method java/lang/Enum.valueOf:(Ljava/lang/Class;Ljava/lang/String;)Ljava/lang/Enum;
       6: checkcast     #4                  // class org/hibernate/engine/jdbc/env/spi/IdentifierCaseStrategy
       9: areturn

  private org.hibernate.engine.jdbc.env.spi.IdentifierCaseStrategy();
    Code:
       0: aload_0
       1: aload_1
       2: iload_2
       3: invokespecial #6                  // Method java/lang/Enum."<init>":(Ljava/lang/String;I)V
       6: return

  static {};
    Code:
       0: new           #4                  // class org/hibernate/engine/jdbc/env/spi/IdentifierCaseStrategy
       3: dup
       4: ldc           #7                  // String MIXED
       6: iconst_0
       7: invokespecial #8                  // Method "<init>":(Ljava/lang/String;I)V
      10: putstatic     #9                  // Field MIXED:Lorg/hibernate/engine/jdbc/env/spi/IdentifierCaseStrategy;
      13: new           #4                  // class org/hibernate/engine/jdbc/env/spi/IdentifierCaseStrategy
      16: dup
      17: ldc           #10                 // String UPPER
      19: iconst_1
      20: invokespecial #8                  // Method "<init>":(Ljava/lang/String;I)V
      23: putstatic     #11                 // Field UPPER:Lorg/hibernate/engine/jdbc/env/spi/IdentifierCaseStrategy;
      26: new           #4                  // class org/hibernate/engine/jdbc/env/spi/IdentifierCaseStrategy
      29: dup
      30: ldc           #12                 // String LOWER
      32: iconst_2
      33: invokespecial #8                  // Method "<init>":(Ljava/lang/String;I)V
      36: putstatic     #13                 // Field LOWER:Lorg/hibernate/engine/jdbc/env/spi/IdentifierCaseStrategy;
      39: iconst_3
      40: anewarray     #4                  // class org/hibernate/engine/jdbc/env/spi/IdentifierCaseStrategy
      43: dup
      44: iconst_0
      45: getstatic     #9                  // Field MIXED:Lorg/hibernate/engine/jdbc/env/spi/IdentifierCaseStrategy;
      48: aastore
      49: dup
      50: iconst_1
      51: getstatic     #11                 // Field UPPER:Lorg/hibernate/engine/jdbc/env/spi/IdentifierCaseStrategy;
      54: aastore
      55: dup
      56: iconst_2
      57: getstatic     #13                 // Field LOWER:Lorg/hibernate/engine/jdbc/env/spi/IdentifierCaseStrategy;
      60: aastore
      61: putstatic     #1                  // Field $VALUES:[Lorg/hibernate/engine/jdbc/env/spi/IdentifierCaseStrategy;
      64: return
}
