Compiled from "ConfidentialityConstraintUrlMappingTestCase.java"
public class io.undertow.servlet.test.security.ssl.ConfidentialityConstraintUrlMappingTestCase {
  public io.undertow.servlet.test.security.ssl.ConfidentialityConstraintUrlMappingTestCase();
    Code:
       0: aload_0
       1: invokespecial #1                  // Method java/lang/Object."<init>":()V
       4: return

  public static void setup() throws java.lang.Exception;
    Code:
       0: invokestatic  #2                  // Method io/undertow/testutils/DefaultServer.startSSLServer:()V
       3: new           #3                  // class io/undertow/server/handlers/PathHandler
       6: dup
       7: invokespecial #4                  // Method io/undertow/server/handlers/PathHandler."<init>":()V
      10: astore_0
      11: invokestatic  #5                  // Method io/undertow/servlet/api/ServletContainer$Factory.newInstance:()Lio/undertow/servlet/api/ServletContainer;
      14: astore_1
      15: new           #6                  // class io/undertow/servlet/api/ServletInfo
      18: dup
      19: ldc           #7                  // String servlet
      21: ldc           #8                  // class io/undertow/servlet/test/security/SendSchemeServlet
      23: invokespecial #9                  // Method io/undertow/servlet/api/ServletInfo."<init>":(Ljava/lang/String;Ljava/lang/Class;)V
      26: ldc           #10                 // String /clear
      28: invokevirtual #11                 // Method io/undertow/servlet/api/ServletInfo.addMapping:(Ljava/lang/String;)Lio/undertow/servlet/api/ServletInfo;
      31: ldc           #12                 // String /integral
      33: invokevirtual #11                 // Method io/undertow/servlet/api/ServletInfo.addMapping:(Ljava/lang/String;)Lio/undertow/servlet/api/ServletInfo;
      36: ldc           #13                 // String /confidential
      38: invokevirtual #11                 // Method io/undertow/servlet/api/ServletInfo.addMapping:(Ljava/lang/String;)Lio/undertow/servlet/api/ServletInfo;
      41: astore_2
      42: new           #14                 // class io/undertow/servlet/api/DeploymentInfo
      45: dup
      46: invokespecial #15                 // Method io/undertow/servlet/api/DeploymentInfo."<init>":()V
      49: ldc           #16                 // class io/undertow/servlet/test/SimpleServletTestCase
      51: invokevirtual #17                 // Method java/lang/Class.getClassLoader:()Ljava/lang/ClassLoader;
      54: invokevirtual #18                 // Method io/undertow/servlet/api/DeploymentInfo.setClassLoader:(Ljava/lang/ClassLoader;)Lio/undertow/servlet/api/DeploymentInfo;
      57: ldc           #19                 // String /servletContext
      59: invokevirtual #20                 // Method io/undertow/servlet/api/DeploymentInfo.setContextPath:(Ljava/lang/String;)Lio/undertow/servlet/api/DeploymentInfo;
      62: getstatic     #21                 // Field io/undertow/servlet/test/util/TestClassIntrospector.INSTANCE:Lio/undertow/servlet/test/util/TestClassIntrospector;
      65: invokevirtual #22                 // Method io/undertow/servlet/api/DeploymentInfo.setClassIntrospecter:(Lio/undertow/servlet/api/ClassIntrospecter;)Lio/undertow/servlet/api/DeploymentInfo;
      68: ldc           #23                 // String servletContext.war
      70: invokevirtual #24                 // Method io/undertow/servlet/api/DeploymentInfo.setDeploymentName:(Ljava/lang/String;)Lio/undertow/servlet/api/DeploymentInfo;
      73: getstatic     #25                 // Field io/undertow/servlet/test/util/TestConfidentialPortManager.INSTANCE:Lio/undertow/servlet/test/util/TestConfidentialPortManager;
      76: invokevirtual #26                 // Method io/undertow/servlet/api/DeploymentInfo.setConfidentialPortManager:(Lio/undertow/servlet/api/ConfidentialPortManager;)Lio/undertow/servlet/api/DeploymentInfo;
      79: aload_2
      80: invokevirtual #27                 // Method io/undertow/servlet/api/DeploymentInfo.addServlet:(Lio/undertow/servlet/api/ServletInfo;)Lio/undertow/servlet/api/DeploymentInfo;
      83: astore_3
      84: aload_3
      85: new           #28                 // class io/undertow/servlet/api/SecurityConstraint
      88: dup
      89: invokespecial #29                 // Method io/undertow/servlet/api/SecurityConstraint."<init>":()V
      92: new           #30                 // class io/undertow/servlet/api/WebResourceCollection
      95: dup
      96: invokespecial #31                 // Method io/undertow/servlet/api/WebResourceCollection."<init>":()V
      99: ldc           #12                 // String /integral
     101: invokevirtual #32                 // Method io/undertow/servlet/api/WebResourceCollection.addUrlPattern:(Ljava/lang/String;)Lio/undertow/servlet/api/WebResourceCollection;
     104: invokevirtual #33                 // Method io/undertow/servlet/api/SecurityConstraint.addWebResourceCollection:(Lio/undertow/servlet/api/WebResourceCollection;)Lio/undertow/servlet/api/SecurityConstraint;
     107: getstatic     #34                 // Field io/undertow/servlet/api/TransportGuaranteeType.INTEGRAL:Lio/undertow/servlet/api/TransportGuaranteeType;
     110: invokevirtual #35                 // Method io/undertow/servlet/api/SecurityConstraint.setTransportGuaranteeType:(Lio/undertow/servlet/api/TransportGuaranteeType;)Lio/undertow/servlet/api/SecurityInfo;
     113: checkcast     #28                 // class io/undertow/servlet/api/SecurityConstraint
     116: getstatic     #36                 // Field io/undertow/servlet/api/SecurityInfo$EmptyRoleSemantic.PERMIT:Lio/undertow/servlet/api/SecurityInfo$EmptyRoleSemantic;
     119: invokevirtual #37                 // Method io/undertow/servlet/api/SecurityConstraint.setEmptyRoleSemantic:(Lio/undertow/servlet/api/SecurityInfo$EmptyRoleSemantic;)Lio/undertow/servlet/api/SecurityInfo;
     122: checkcast     #28                 // class io/undertow/servlet/api/SecurityConstraint
     125: invokevirtual #38                 // Method io/undertow/servlet/api/DeploymentInfo.addSecurityConstraint:(Lio/undertow/servlet/api/SecurityConstraint;)Lio/undertow/servlet/api/DeploymentInfo;
     128: pop
     129: aload_3
     130: new           #28                 // class io/undertow/servlet/api/SecurityConstraint
     133: dup
     134: invokespecial #29                 // Method io/undertow/servlet/api/SecurityConstraint."<init>":()V
     137: new           #30                 // class io/undertow/servlet/api/WebResourceCollection
     140: dup
     141: invokespecial #31                 // Method io/undertow/servlet/api/WebResourceCollection."<init>":()V
     144: ldc           #13                 // String /confidential
     146: invokevirtual #32                 // Method io/undertow/servlet/api/WebResourceCollection.addUrlPattern:(Ljava/lang/String;)Lio/undertow/servlet/api/WebResourceCollection;
     149: invokevirtual #33                 // Method io/undertow/servlet/api/SecurityConstraint.addWebResourceCollection:(Lio/undertow/servlet/api/WebResourceCollection;)Lio/undertow/servlet/api/SecurityConstraint;
     152: getstatic     #39                 // Field io/undertow/servlet/api/TransportGuaranteeType.CONFIDENTIAL:Lio/undertow/servlet/api/TransportGuaranteeType;
     155: invokevirtual #35                 // Method io/undertow/servlet/api/SecurityConstraint.setTransportGuaranteeType:(Lio/undertow/servlet/api/TransportGuaranteeType;)Lio/undertow/servlet/api/SecurityInfo;
     158: checkcast     #28                 // class io/undertow/servlet/api/SecurityConstraint
     161: getstatic     #36                 // Field io/undertow/servlet/api/SecurityInfo$EmptyRoleSemantic.PERMIT:Lio/undertow/servlet/api/SecurityInfo$EmptyRoleSemantic;
     164: invokevirtual #37                 // Method io/undertow/servlet/api/SecurityConstraint.setEmptyRoleSemantic:(Lio/undertow/servlet/api/SecurityInfo$EmptyRoleSemantic;)Lio/undertow/servlet/api/SecurityInfo;
     167: checkcast     #28                 // class io/undertow/servlet/api/SecurityConstraint
     170: invokevirtual #38                 // Method io/undertow/servlet/api/DeploymentInfo.addSecurityConstraint:(Lio/undertow/servlet/api/SecurityConstraint;)Lio/undertow/servlet/api/DeploymentInfo;
     173: pop
     174: aload_1
     175: aload_3
     176: invokeinterface #40,  2           // InterfaceMethod io/undertow/servlet/api/ServletContainer.addDeployment:(Lio/undertow/servlet/api/DeploymentInfo;)Lio/undertow/servlet/api/DeploymentManager;
     181: astore        4
     183: aload         4
     185: invokeinterface #41,  1           // InterfaceMethod io/undertow/servlet/api/DeploymentManager.deploy:()V
     190: aload_0
     191: aload_3
     192: invokevirtual #42                 // Method io/undertow/servlet/api/DeploymentInfo.getContextPath:()Ljava/lang/String;
     195: aload         4
     197: invokeinterface #43,  1           // InterfaceMethod io/undertow/servlet/api/DeploymentManager.start:()Lio/undertow/server/HttpHandler;
     202: invokevirtual #44                 // Method io/undertow/server/handlers/PathHandler.addPrefixPath:(Ljava/lang/String;Lio/undertow/server/HttpHandler;)Lio/undertow/server/handlers/PathHandler;
     205: pop
     206: aload_0
     207: invokestatic  #45                 // Method io/undertow/testutils/DefaultServer.setRootHandler:(Lio/undertow/server/HttpHandler;)V
     210: return

  public static void cleanUp() throws java.lang.Exception;
    Code:
       0: invokestatic  #46                 // Method io/undertow/testutils/DefaultServer.stopSSLServer:()V
       3: return

  public void testClear() throws java.io.IOException;
    Code:
       0: aload_0
       1: ldc           #10                 // String /clear
       3: ldc           #47                 // String http
       5: invokespecial #48                 // Method internalTest:(Ljava/lang/String;Ljava/lang/String;)V
       8: return

  public void testIntegral() throws java.io.IOException;
    Code:
       0: aload_0
       1: ldc           #12                 // String /integral
       3: ldc           #49                 // String https
       5: invokespecial #48                 // Method internalTest:(Ljava/lang/String;Ljava/lang/String;)V
       8: return

  public void testConfidential() throws java.io.IOException;
    Code:
       0: aload_0
       1: ldc           #13                 // String /confidential
       3: ldc           #49                 // String https
       5: invokespecial #48                 // Method internalTest:(Ljava/lang/String;Ljava/lang/String;)V
       8: return

  private void internalTest(java.lang.String, java.lang.String) throws java.io.IOException;
    Code:
       0: new           #50                 // class io/undertow/testutils/TestHttpClient
       3: dup
       4: invokespecial #51                 // Method io/undertow/testutils/TestHttpClient."<init>":()V
       7: astore_3
       8: aload_3
       9: invokestatic  #52                 // Method io/undertow/testutils/DefaultServer.getClientSSLContext:()Ljavax/net/ssl/SSLContext;
      12: invokevirtual #53                 // Method io/undertow/testutils/TestHttpClient.setSSLContext:(Ljavax/net/ssl/SSLContext;)V
      15: new           #54                 // class java/lang/StringBuilder
      18: dup
      19: invokespecial #55                 // Method java/lang/StringBuilder."<init>":()V
      22: invokestatic  #56                 // Method io/undertow/testutils/DefaultServer.getDefaultServerURL:()Ljava/lang/String;
      25: invokevirtual #57                 // Method java/lang/StringBuilder.append:(Ljava/lang/String;)Ljava/lang/StringBuilder;
      28: ldc           #19                 // String /servletContext
      30: invokevirtual #57                 // Method java/lang/StringBuilder.append:(Ljava/lang/String;)Ljava/lang/StringBuilder;
      33: aload_1
      34: invokevirtual #57                 // Method java/lang/StringBuilder.append:(Ljava/lang/String;)Ljava/lang/StringBuilder;
      37: invokevirtual #58                 // Method java/lang/StringBuilder.toString:()Ljava/lang/String;
      40: astore        4
      42: new           #59                 // class org/apache/http/client/methods/HttpGet
      45: dup
      46: aload         4
      48: invokespecial #60                 // Method org/apache/http/client/methods/HttpGet."<init>":(Ljava/lang/String;)V
      51: astore        5
      53: aload_3
      54: aload         5
      56: invokevirtual #61                 // Method io/undertow/testutils/TestHttpClient.execute:(Lorg/apache/http/client/methods/HttpUriRequest;)Lorg/apache/http/HttpResponse;
      59: astore        6
      61: ldc2_w        #63                 // long 200l
      64: aload         6
      66: invokeinterface #65,  1           // InterfaceMethod org/apache/http/HttpResponse.getStatusLine:()Lorg/apache/http/StatusLine;
      71: invokeinterface #66,  1           // InterfaceMethod org/apache/http/StatusLine.getStatusCode:()I
      76: i2l
      77: invokestatic  #67                 // Method org/junit/Assert.assertEquals:(JJ)V
      80: aload         6
      82: invokestatic  #68                 // Method io/undertow/testutils/HttpClientUtils.readResponse:(Lorg/apache/http/HttpResponse;)Ljava/lang/String;
      85: astore        7
      87: aload_2
      88: aload         7
      90: invokestatic  #69                 // Method org/junit/Assert.assertEquals:(Ljava/lang/Object;Ljava/lang/Object;)V
      93: aload_3
      94: invokevirtual #70                 // Method io/undertow/testutils/TestHttpClient.getConnectionManager:()Lorg/apache/http/conn/ClientConnectionManager;
      97: invokeinterface #71,  1           // InterfaceMethod org/apache/http/conn/ClientConnectionManager.shutdown:()V
     102: goto          119
     105: astore        8
     107: aload_3
     108: invokevirtual #70                 // Method io/undertow/testutils/TestHttpClient.getConnectionManager:()Lorg/apache/http/conn/ClientConnectionManager;
     111: invokeinterface #71,  1           // InterfaceMethod org/apache/http/conn/ClientConnectionManager.shutdown:()V
     116: aload         8
     118: athrow
     119: return
    Exception table:
       from    to  target type
          42    93   105   any
         105   107   105   any
}
