Compiled from "DescribeAttachmentResponse.java"
public interface software.amazon.awssdk.services.support.model.DescribeAttachmentResponse$Builder extends software.amazon.awssdk.services.support.model.SupportResponse$Builder, software.amazon.awssdk.core.SdkPojo, software.amazon.awssdk.utils.builder.CopyableBuilder<software.amazon.awssdk.services.support.model.DescribeAttachmentResponse$Builder, software.amazon.awssdk.services.support.model.DescribeAttachmentResponse> {
  public abstract software.amazon.awssdk.services.support.model.DescribeAttachmentResponse$Builder attachment(software.amazon.awssdk.services.support.model.Attachment);

  public default software.amazon.awssdk.services.support.model.DescribeAttachmentResponse$Builder attachment(java.util.function.Consumer<software.amazon.awssdk.services.support.model.Attachment$Builder>);
    Code:
       0: aload_0
       1: invokestatic  #1                  // Method software/amazon/awssdk/services/support/model/Attachment.builder:()Lsoftware/amazon/awssdk/services/support/model/Attachment$Builder;
       4: aload_1
       5: invokeinterface #2,  2            // InterfaceMethod software/amazon/awssdk/services/support/model/Attachment$Builder.applyMutation:(Ljava/util/function/Consumer;)Lsoftware/amazon/awssdk/utils/builder/SdkBuilder;
      10: checkcast     #3                  // class software/amazon/awssdk/services/support/model/Attachment$Builder
      13: invokeinterface #4,  1            // InterfaceMethod software/amazon/awssdk/services/support/model/Attachment$Builder.build:()Ljava/lang/Object;
      18: checkcast     #5                  // class software/amazon/awssdk/services/support/model/Attachment
      21: invokeinterface #6,  2            // InterfaceMethod attachment:(Lsoftware/amazon/awssdk/services/support/model/Attachment;)Lsoftware/amazon/awssdk/services/support/model/DescribeAttachmentResponse$Builder;
      26: areturn
}
