Compiled from "AbstractBroadcasterProxy.java"
public abstract class org.atmosphere.util.AbstractBroadcasterProxy extends org.atmosphere.cpr.DefaultBroadcaster {
  private static final org.slf4j.Logger logger;

  private java.lang.reflect.Method jerseyBroadcast;

  public org.atmosphere.util.AbstractBroadcasterProxy();
    Code:
       0: aload_0
       1: invokespecial #2                  // Method org/atmosphere/cpr/DefaultBroadcaster."<init>":()V
       4: ldc           #3                  // String org.atmosphere.jersey.util.JerseyBroadcasterUtil
       6: invokestatic  #4                  // Method java/lang/Class.forName:(Ljava/lang/String;)Ljava/lang/Class;
       9: astore_1
      10: aload_0
      11: aload_1
      12: ldc           #5                  // String broadcast
      14: iconst_3
      15: anewarray     #6                  // class java/lang/Class
      18: dup
      19: iconst_0
      20: ldc           #7                  // class org/atmosphere/cpr/AtmosphereResource
      22: aastore
      23: dup
      24: iconst_1
      25: ldc           #8                  // class org/atmosphere/cpr/AtmosphereResourceEvent
      27: aastore
      28: dup
      29: iconst_2
      30: ldc           #9                  // class org/atmosphere/cpr/Broadcaster
      32: aastore
      33: invokevirtual #10                 // Method java/lang/Class.getMethod:(Ljava/lang/String;[Ljava/lang/Class;)Ljava/lang/reflect/Method;
      36: putfield      #11                 // Field jerseyBroadcast:Ljava/lang/reflect/Method;
      39: goto          54
      42: astore_1
      43: getstatic     #1                  // Field logger:Lorg/slf4j/Logger;
      46: ldc           #13                 // String
      48: aload_1
      49: invokeinterface #14,  3           // InterfaceMethod org/slf4j/Logger.trace:(Ljava/lang/String;Ljava/lang/Throwable;)V
      54: return
    Exception table:
       from    to  target type
           4    39    42   Class java/lang/Exception

  public org.atmosphere.cpr.Broadcaster initialize(java.lang.String, java.net.URI, org.atmosphere.cpr.AtmosphereConfig);
    Code:
       0: aload_0
       1: aload_1
       2: aload_2
       3: aload_3
       4: invokespecial #15                 // Method org/atmosphere/cpr/DefaultBroadcaster.initialize:(Ljava/lang/String;Ljava/net/URI;Lorg/atmosphere/cpr/AtmosphereConfig;)Lorg/atmosphere/cpr/Broadcaster;
       7: areturn

  public abstract void incomingBroadcast();

  public abstract void outgoingBroadcast(java.lang.Object);

  protected java.lang.Runnable getBroadcastHandler();
    Code:
       0: new           #16                 // class org/atmosphere/util/AbstractBroadcasterProxy$1
       3: dup
       4: aload_0
       5: invokespecial #17                 // Method org/atmosphere/util/AbstractBroadcasterProxy$1."<init>":(Lorg/atmosphere/util/AbstractBroadcasterProxy;)V
       8: areturn

  protected void reconfigure();
    Code:
       0: aload_0
       1: getfield      #18                 // Field started:Ljava/util/concurrent/atomic/AtomicBoolean;
       4: invokevirtual #19                 // Method java/util/concurrent/atomic/AtomicBoolean.get:()Z
       7: ifne          11
      10: return
      11: getstatic     #1                  // Field logger:Lorg/slf4j/Logger;
      14: ldc           #20                 // String Reconfiguring Broadcaster {}
      16: aload_0
      17: invokevirtual #21                 // Method getID:()Ljava/lang/String;
      20: invokeinterface #22,  3           // InterfaceMethod org/slf4j/Logger.debug:(Ljava/lang/String;Ljava/lang/Object;)V
      25: aload_0
      26: invokevirtual #23                 // Method spawnReactor:()V
      29: return

  protected void invokeOnStateChange(org.atmosphere.cpr.AtmosphereResource, org.atmosphere.cpr.AtmosphereResourceEvent);
    Code:
       0: aload_1
       1: invokeinterface #24,  1           // InterfaceMethod org/atmosphere/cpr/AtmosphereResource.getRequest:()Lorg/atmosphere/cpr/AtmosphereRequest;
       6: ldc           #26                 // String org.atmosphere.jersey.containerResponse
       8: invokeinterface #27,  2           // InterfaceMethod org/atmosphere/cpr/AtmosphereRequest.getAttribute:(Ljava/lang/String;)Ljava/lang/Object;
      13: ifnull        59
      16: aload_0
      17: getfield      #11                 // Field jerseyBroadcast:Ljava/lang/reflect/Method;
      20: aconst_null
      21: iconst_3
      22: anewarray     #28                 // class java/lang/Object
      25: dup
      26: iconst_0
      27: aload_1
      28: aastore
      29: dup
      30: iconst_1
      31: aload_2
      32: aastore
      33: dup
      34: iconst_2
      35: aload_1
      36: invokeinterface #29,  1           // InterfaceMethod org/atmosphere/cpr/AtmosphereResource.getBroadcaster:()Lorg/atmosphere/cpr/Broadcaster;
      41: aastore
      42: invokevirtual #30                 // Method java/lang/reflect/Method.invoke:(Ljava/lang/Object;[Ljava/lang/Object;)Ljava/lang/Object;
      45: pop
      46: goto          65
      49: astore_3
      50: aload_0
      51: aload_1
      52: aload_2
      53: invokespecial #32                 // Method org/atmosphere/cpr/DefaultBroadcaster.invokeOnStateChange:(Lorg/atmosphere/cpr/AtmosphereResource;Lorg/atmosphere/cpr/AtmosphereResourceEvent;)V
      56: goto          65
      59: aload_0
      60: aload_1
      61: aload_2
      62: invokespecial #32                 // Method org/atmosphere/cpr/DefaultBroadcaster.invokeOnStateChange:(Lorg/atmosphere/cpr/AtmosphereResource;Lorg/atmosphere/cpr/AtmosphereResourceEvent;)V
      65: return
    Exception table:
       from    to  target type
          16    46    49   Class java/lang/Throwable

  protected void broadcastReceivedMessage(java.lang.Object);
    Code:
       0: aload_0
       1: aload_1
       2: invokevirtual #33                 // Method filter:(Ljava/lang/Object;)Ljava/lang/Object;
       5: astore_2
       6: aload_2
       7: ifnull        31
      10: aload_0
      11: new           #34                 // class org/atmosphere/cpr/Deliver
      14: dup
      15: aload_2
      16: new           #35                 // class org/atmosphere/cpr/BroadcasterFuture
      19: dup
      20: aload_2
      21: invokespecial #36                 // Method org/atmosphere/cpr/BroadcasterFuture."<init>":(Ljava/lang/Object;)V
      24: aload_1
      25: invokespecial #37                 // Method org/atmosphere/cpr/Deliver."<init>":(Ljava/lang/Object;Lorg/atmosphere/cpr/BroadcasterFuture;Ljava/lang/Object;)V
      28: invokevirtual #38                 // Method push:(Lorg/atmosphere/cpr/Deliver;)V
      31: goto          63
      34: astore_2
      35: getstatic     #1                  // Field logger:Lorg/slf4j/Logger;
      38: new           #39                 // class java/lang/StringBuilder
      41: dup
      42: invokespecial #40                 // Method java/lang/StringBuilder."<init>":()V
      45: ldc           #41                 // String failed to push message:
      47: invokevirtual #42                 // Method java/lang/StringBuilder.append:(Ljava/lang/String;)Ljava/lang/StringBuilder;
      50: aload_1
      51: invokevirtual #43                 // Method java/lang/StringBuilder.append:(Ljava/lang/Object;)Ljava/lang/StringBuilder;
      54: invokevirtual #44                 // Method java/lang/StringBuilder.toString:()Ljava/lang/String;
      57: aload_2
      58: invokeinterface #45,  3           // InterfaceMethod org/slf4j/Logger.error:(Ljava/lang/String;Ljava/lang/Throwable;)V
      63: return
    Exception table:
       from    to  target type
           0    31    34   Class java/lang/Throwable

  public java.util.concurrent.Future<java.lang.Object> broadcast(java.lang.Object);
    Code:
       0: aload_0
       1: aload_1
       2: invokevirtual #46                 // Method b:(Ljava/lang/Object;)Ljava/util/concurrent/Future;
       5: areturn

  protected java.util.concurrent.Future<java.lang.Object> b(java.lang.Object);
    Code:
       0: aload_0
       1: getfield      #47                 // Field destroyed:Ljava/util/concurrent/atomic/AtomicBoolean;
       4: invokevirtual #19                 // Method java/util/concurrent/atomic/AtomicBoolean.get:()Z
       7: ifeq          26
      10: getstatic     #1                  // Field logger:Lorg/slf4j/Logger;
      13: ldc           #48                 // String This Broadcaster has been destroyed and cannot be used {}
      15: aload_0
      16: invokevirtual #21                 // Method getID:()Ljava/lang/String;
      19: invokeinterface #49,  3           // InterfaceMethod org/slf4j/Logger.warn:(Ljava/lang/String;Ljava/lang/Object;)V
      24: aconst_null
      25: areturn
      26: aload_0
      27: invokevirtual #50                 // Method start:()V
      30: new           #35                 // class org/atmosphere/cpr/BroadcasterFuture
      33: dup
      34: aload_1
      35: invokespecial #36                 // Method org/atmosphere/cpr/BroadcasterFuture."<init>":(Ljava/lang/Object;)V
      38: astore_2
      39: aload_0
      40: aload_1
      41: invokevirtual #51                 // Method outgoingBroadcast:(Ljava/lang/Object;)V
      44: aload_0
      45: aload_2
      46: invokevirtual #52                 // Method futureDone:(Ljava/lang/Object;)Lorg/atmosphere/cpr/BroadcasterFuture;
      49: pop
      50: goto          62
      53: astore_3
      54: aload_0
      55: aload_2
      56: invokevirtual #52                 // Method futureDone:(Ljava/lang/Object;)Lorg/atmosphere/cpr/BroadcasterFuture;
      59: pop
      60: aload_3
      61: athrow
      62: aload_2
      63: areturn
    Exception table:
       from    to  target type
          39    44    53   any

  public java.util.concurrent.Future<java.lang.Object> broadcast(java.lang.Object, org.atmosphere.cpr.AtmosphereResource);
    Code:
       0: getstatic     #1                  // Field logger:Lorg/slf4j/Logger;
       3: ldc           #53                 // String This feature is not supported with {}
       5: aload_2
       6: invokeinterface #29,  1           // InterfaceMethod org/atmosphere/cpr/AtmosphereResource.getBroadcaster:()Lorg/atmosphere/cpr/Broadcaster;
      11: invokevirtual #54                 // Method java/lang/Object.getClass:()Ljava/lang/Class;
      14: invokevirtual #55                 // Method java/lang/Class.getName:()Ljava/lang/String;
      17: invokeinterface #49,  3           // InterfaceMethod org/slf4j/Logger.warn:(Ljava/lang/String;Ljava/lang/Object;)V
      22: aload_0
      23: aload_1
      24: invokevirtual #46                 // Method b:(Ljava/lang/Object;)Ljava/util/concurrent/Future;
      27: areturn

  public java.util.concurrent.Future<java.lang.Object> broadcast(java.lang.Object, java.util.Set<org.atmosphere.cpr.AtmosphereResource>);
    Code:
       0: getstatic     #1                  // Field logger:Lorg/slf4j/Logger;
       3: ldc           #53                 // String This feature is not supported with {}
       5: aload_2
       6: invokeinterface #56,  1           // InterfaceMethod java/util/Set.iterator:()Ljava/util/Iterator;
      11: invokeinterface #57,  1           // InterfaceMethod java/util/Iterator.next:()Ljava/lang/Object;
      16: checkcast     #7                  // class org/atmosphere/cpr/AtmosphereResource
      19: invokeinterface #29,  1           // InterfaceMethod org/atmosphere/cpr/AtmosphereResource.getBroadcaster:()Lorg/atmosphere/cpr/Broadcaster;
      24: invokevirtual #54                 // Method java/lang/Object.getClass:()Ljava/lang/Class;
      27: invokevirtual #55                 // Method java/lang/Class.getName:()Ljava/lang/String;
      30: invokeinterface #49,  3           // InterfaceMethod org/slf4j/Logger.warn:(Ljava/lang/String;Ljava/lang/Object;)V
      35: aload_0
      36: aload_1
      37: invokevirtual #46                 // Method b:(Ljava/lang/Object;)Ljava/util/concurrent/Future;
      40: areturn

  static org.slf4j.Logger access$000();
    Code:
       0: getstatic     #1                  // Field logger:Lorg/slf4j/Logger;
       3: areturn

  static {};
    Code:
       0: ldc           #58                 // class org/atmosphere/util/AbstractBroadcasterProxy
       2: invokestatic  #59                 // Method org/slf4j/LoggerFactory.getLogger:(Ljava/lang/Class;)Lorg/slf4j/Logger;
       5: putstatic     #1                  // Field logger:Lorg/slf4j/Logger;
       8: return
}
