Compiled from "ConfigOverride.java"
final class io.dekorate.deps.jackson.databind.cfg.ConfigOverride$Empty extends io.dekorate.deps.jackson.databind.cfg.ConfigOverride {
  static final io.dekorate.deps.jackson.databind.cfg.ConfigOverride$Empty INSTANCE;

  private io.dekorate.deps.jackson.databind.cfg.ConfigOverride$Empty();
    Code:
       0: aload_0
       1: invokespecial #12                 // Method io/dekorate/deps/jackson/databind/cfg/ConfigOverride."<init>":()V
       4: return

  static {};
    Code:
       0: new           #2                  // class io/dekorate/deps/jackson/databind/cfg/ConfigOverride$Empty
       3: dup
       4: invokespecial #15                 // Method "<init>":()V
       7: putstatic     #17                 // Field INSTANCE:Lio/dekorate/deps/jackson/databind/cfg/ConfigOverride$Empty;
      10: return
}
