Compiled from "LogDelegateFactory.java"
public final class org.springframework.core.log.LogDelegateFactory {
  private org.springframework.core.log.LogDelegateFactory();
    Code:
       0: aload_0
       1: invokespecial #1                  // Method java/lang/Object."<init>":()V
       4: return

  public static org.apache.commons.logging.Log getCompositeLog(org.apache.commons.logging.Log, org.apache.commons.logging.Log, org.apache.commons.logging.Log...);
    Code:
       0: new           #2                  // class java/util/ArrayList
       3: dup
       4: iconst_2
       5: aload_2
       6: arraylength
       7: iadd
       8: invokespecial #3                  // Method java/util/ArrayList."<init>":(I)V
      11: astore_3
      12: aload_3
      13: aload_0
      14: invokeinterface #4,  2            // InterfaceMethod java/util/List.add:(Ljava/lang/Object;)Z
      19: pop
      20: aload_3
      21: aload_1
      22: invokeinterface #4,  2            // InterfaceMethod java/util/List.add:(Ljava/lang/Object;)Z
      27: pop
      28: aload_3
      29: aload_2
      30: invokestatic  #5                  // Method java/util/Collections.addAll:(Ljava/util/Collection;[Ljava/lang/Object;)Z
      33: pop
      34: new           #6                  // class org/springframework/core/log/CompositeLog
      37: dup
      38: aload_3
      39: invokespecial #7                  // Method org/springframework/core/log/CompositeLog."<init>":(Ljava/util/List;)V
      42: areturn

  public static org.apache.commons.logging.Log getHiddenLog(java.lang.Class<?>);
    Code:
       0: new           #8                  // class java/lang/StringBuilder
       3: dup
       4: invokespecial #9                  // Method java/lang/StringBuilder."<init>":()V
       7: ldc           #10                 // String _
       9: invokevirtual #11                 // Method java/lang/StringBuilder.append:(Ljava/lang/String;)Ljava/lang/StringBuilder;
      12: aload_0
      13: invokevirtual #12                 // Method java/lang/Class.getName:()Ljava/lang/String;
      16: invokevirtual #11                 // Method java/lang/StringBuilder.append:(Ljava/lang/String;)Ljava/lang/StringBuilder;
      19: invokevirtual #13                 // Method java/lang/StringBuilder.toString:()Ljava/lang/String;
      22: invokestatic  #14                 // Method org/apache/commons/logging/LogFactory.getLog:(Ljava/lang/String;)Lorg/apache/commons/logging/Log;
      25: areturn
}
