Compiled from "JsonSrvUtils.java"
public class org.brutusin.jsonsrv.utils.JsonSrvUtils {
  private org.brutusin.jsonsrv.utils.JsonSrvUtils();
    Code:
       0: aload_0
       1: invokespecial #9                  // Method java/lang/Object."<init>":()V
       4: return

  public static java.lang.String getVersion();
    Code:
       0: ldc           #17                 // class org/brutusin/jsonsrv/impl/VersionAction
       2: invokevirtual #23                 // Method java/lang/Class.getClassLoader:()Ljava/lang/ClassLoader;
       5: ldc           #25                 // String jsonsrv.version
       7: invokevirtual #31                 // Method java/lang/ClassLoader.getResourceAsStream:(Ljava/lang/String;)Ljava/io/InputStream;
      10: ldc           #33                 // String UTF-8
      12: invokestatic  #39                 // Method org/brutusin/commons/utils/Miscellaneous.toString:(Ljava/io/InputStream;Ljava/lang/String;)Ljava/lang/String;
      15: areturn
      16: astore_0
      17: new           #41                 // class java/lang/RuntimeException
      20: dup
      21: aload_0
      22: invokespecial #44                 // Method java/lang/RuntimeException."<init>":(Ljava/lang/Throwable;)V
      25: athrow
    Exception table:
       from    to  target type
           0    15    16   Class java/io/IOException
}
