Compiled from "SQLQueryImpl.java"
class org.hibernate.internal.SQLQueryImpl$FetchReturnBuilder$1 implements org.hibernate.SQLQuery$ReturnProperty {
  final java.lang.String val$propertyName;

  final org.hibernate.internal.SQLQueryImpl$FetchReturnBuilder this$0;

  org.hibernate.internal.SQLQueryImpl$FetchReturnBuilder$1(org.hibernate.internal.SQLQueryImpl$FetchReturnBuilder, java.lang.String);
    Code:
       0: aload_0
       1: aload_1
       2: putfield      #1                  // Field this$0:Lorg/hibernate/internal/SQLQueryImpl$FetchReturnBuilder;
       5: aload_0
       6: aload_2
       7: putfield      #2                  // Field val$propertyName:Ljava/lang/String;
      10: aload_0
      11: invokespecial #3                  // Method java/lang/Object."<init>":()V
      14: return

  public org.hibernate.SQLQuery$ReturnProperty addColumnAlias(java.lang.String);
    Code:
       0: aload_0
       1: getfield      #1                  // Field this$0:Lorg/hibernate/internal/SQLQueryImpl$FetchReturnBuilder;
       4: invokestatic  #4                  // Method org/hibernate/internal/SQLQueryImpl$FetchReturnBuilder.access$300:(Lorg/hibernate/internal/SQLQueryImpl$FetchReturnBuilder;)Ljava/util/Map;
       7: aload_0
       8: getfield      #2                  // Field val$propertyName:Ljava/lang/String;
      11: invokeinterface #5,  2            // InterfaceMethod java/util/Map.get:(Ljava/lang/Object;)Ljava/lang/Object;
      16: checkcast     #6                  // class "[Ljava/lang/String;"
      19: astore_2
      20: aload_2
      21: ifnonnull     36
      24: iconst_1
      25: anewarray     #7                  // class java/lang/String
      28: dup
      29: iconst_0
      30: aload_1
      31: aastore
      32: astore_2
      33: goto          60
      36: aload_2
      37: arraylength
      38: iconst_1
      39: iadd
      40: anewarray     #7                  // class java/lang/String
      43: astore_3
      44: aload_2
      45: iconst_0
      46: aload_3
      47: iconst_0
      48: aload_2
      49: arraylength
      50: invokestatic  #8                  // Method java/lang/System.arraycopy:(Ljava/lang/Object;ILjava/lang/Object;II)V
      53: aload_3
      54: aload_2
      55: arraylength
      56: aload_1
      57: aastore
      58: aload_3
      59: astore_2
      60: aload_0
      61: getfield      #1                  // Field this$0:Lorg/hibernate/internal/SQLQueryImpl$FetchReturnBuilder;
      64: invokestatic  #4                  // Method org/hibernate/internal/SQLQueryImpl$FetchReturnBuilder.access$300:(Lorg/hibernate/internal/SQLQueryImpl$FetchReturnBuilder;)Ljava/util/Map;
      67: aload_0
      68: getfield      #2                  // Field val$propertyName:Ljava/lang/String;
      71: aload_2
      72: invokeinterface #9,  3            // InterfaceMethod java/util/Map.put:(Ljava/lang/Object;Ljava/lang/Object;)Ljava/lang/Object;
      77: pop
      78: aload_0
      79: areturn
}
