Compiled from "ProxyFactoryBean.java"
class org.springframework.aop.framework.ProxyFactoryBean$PrototypePlaceholderAdvisor implements org.springframework.aop.Advisor,java.io.Serializable {
  private final java.lang.String beanName;

  private final java.lang.String message;

  public org.springframework.aop.framework.ProxyFactoryBean$PrototypePlaceholderAdvisor(java.lang.String);
    Code:
       0: aload_0
       1: invokespecial #1                  // Method java/lang/Object."<init>":()V
       4: aload_0
       5: aload_1
       6: putfield      #2                  // Field beanName:Ljava/lang/String;
       9: aload_0
      10: new           #3                  // class java/lang/StringBuilder
      13: dup
      14: invokespecial #4                  // Method java/lang/StringBuilder."<init>":()V
      17: ldc           #5                  // String Placeholder for prototype Advisor/Advice with bean name \'
      19: invokevirtual #6                  // Method java/lang/StringBuilder.append:(Ljava/lang/String;)Ljava/lang/StringBuilder;
      22: aload_1
      23: invokevirtual #6                  // Method java/lang/StringBuilder.append:(Ljava/lang/String;)Ljava/lang/StringBuilder;
      26: ldc           #7                  // String \'
      28: invokevirtual #6                  // Method java/lang/StringBuilder.append:(Ljava/lang/String;)Ljava/lang/StringBuilder;
      31: invokevirtual #8                  // Method java/lang/StringBuilder.toString:()Ljava/lang/String;
      34: putfield      #9                  // Field message:Ljava/lang/String;
      37: return

  public java.lang.String getBeanName();
    Code:
       0: aload_0
       1: getfield      #2                  // Field beanName:Ljava/lang/String;
       4: areturn

  public org.aopalliance.aop.Advice getAdvice();
    Code:
       0: new           #10                 // class java/lang/UnsupportedOperationException
       3: dup
       4: new           #3                  // class java/lang/StringBuilder
       7: dup
       8: invokespecial #4                  // Method java/lang/StringBuilder."<init>":()V
      11: ldc           #11                 // String Cannot invoke methods:
      13: invokevirtual #6                  // Method java/lang/StringBuilder.append:(Ljava/lang/String;)Ljava/lang/StringBuilder;
      16: aload_0
      17: getfield      #9                  // Field message:Ljava/lang/String;
      20: invokevirtual #6                  // Method java/lang/StringBuilder.append:(Ljava/lang/String;)Ljava/lang/StringBuilder;
      23: invokevirtual #8                  // Method java/lang/StringBuilder.toString:()Ljava/lang/String;
      26: invokespecial #12                 // Method java/lang/UnsupportedOperationException."<init>":(Ljava/lang/String;)V
      29: athrow

  public boolean isPerInstance();
    Code:
       0: new           #10                 // class java/lang/UnsupportedOperationException
       3: dup
       4: new           #3                  // class java/lang/StringBuilder
       7: dup
       8: invokespecial #4                  // Method java/lang/StringBuilder."<init>":()V
      11: ldc           #11                 // String Cannot invoke methods:
      13: invokevirtual #6                  // Method java/lang/StringBuilder.append:(Ljava/lang/String;)Ljava/lang/StringBuilder;
      16: aload_0
      17: getfield      #9                  // Field message:Ljava/lang/String;
      20: invokevirtual #6                  // Method java/lang/StringBuilder.append:(Ljava/lang/String;)Ljava/lang/StringBuilder;
      23: invokevirtual #8                  // Method java/lang/StringBuilder.toString:()Ljava/lang/String;
      26: invokespecial #12                 // Method java/lang/UnsupportedOperationException."<init>":(Ljava/lang/String;)V
      29: athrow

  public java.lang.String toString();
    Code:
       0: aload_0
       1: getfield      #9                  // Field message:Ljava/lang/String;
       4: areturn
}
