Compiled from "Builders.scala"
public class ai.chronon.api.Builders$Derivation$ {
  public static final ai.chronon.api.Builders$Derivation$ MODULE$;

  public static {};
    Code:
       0: new           #2                  // class ai/chronon/api/Builders$Derivation$
       3: dup
       4: invokespecial #15                 // Method "<init>":()V
       7: putstatic     #17                 // Field MODULE$:Lai/chronon/api/Builders$Derivation$;
      10: return

  public ai.chronon.api.Derivation apply(java.lang.String, java.lang.String);
    Code:
       0: new           #23                 // class ai/chronon/api/Derivation
       3: dup
       4: invokespecial #24                 // Method ai/chronon/api/Derivation."<init>":()V
       7: astore_3
       8: aload_1
       9: ifnull        20
      12: aload_3
      13: aload_1
      14: invokevirtual #28                 // Method ai/chronon/api/Derivation.setName:(Ljava/lang/String;)Lai/chronon/api/Derivation;
      17: goto          23
      20: getstatic     #34                 // Field scala/runtime/BoxedUnit.UNIT:Lscala/runtime/BoxedUnit;
      23: pop
      24: aload_3
      25: ifnull        36
      28: aload_3
      29: aload_2
      30: invokevirtual #37                 // Method ai/chronon/api/Derivation.setExpression:(Ljava/lang/String;)Lai/chronon/api/Derivation;
      33: goto          39
      36: getstatic     #34                 // Field scala/runtime/BoxedUnit.UNIT:Lscala/runtime/BoxedUnit;
      39: pop
      40: aload_3
      41: areturn

  public java.lang.String apply$default$1();
    Code:
       0: aconst_null
       1: areturn

  public java.lang.String apply$default$2();
    Code:
       0: aconst_null
       1: areturn

  public ai.chronon.api.Builders$Derivation$();
    Code:
       0: aload_0
       1: invokespecial #45                 // Method java/lang/Object."<init>":()V
       4: return
}
