Compiled from "Builders.scala"
public class ai.chronon.api.Builders$LabelPart$ {
  public static final ai.chronon.api.Builders$LabelPart$ MODULE$;

  public static {};
    Code:
       0: new           #2                  // class ai/chronon/api/Builders$LabelPart$
       3: dup
       4: invokespecial #20                 // Method "<init>":()V
       7: putstatic     #22                 // Field MODULE$:Lai/chronon/api/Builders$LabelPart$;
      10: return

  public ai.chronon.api.LabelPart apply(scala.collection.Seq<ai.chronon.api.JoinPart>, int, int);
    Code:
       0: new           #30                 // class ai/chronon/api/LabelPart
       3: dup
       4: invokespecial #31                 // Method ai/chronon/api/LabelPart."<init>":()V
       7: astore        4
       9: aload         4
      11: iload_2
      12: invokevirtual #35                 // Method ai/chronon/api/LabelPart.setLeftStartOffset:(I)Lai/chronon/api/LabelPart;
      15: pop
      16: aload         4
      18: iload_3
      19: invokevirtual #38                 // Method ai/chronon/api/LabelPart.setLeftEndOffset:(I)Lai/chronon/api/LabelPart;
      22: pop
      23: aload_1
      24: ifnull        48
      27: aload         4
      29: getstatic     #43                 // Field scala/collection/JavaConverters$.MODULE$:Lscala/collection/JavaConverters$;
      32: aload_1
      33: invokevirtual #47                 // Method scala/collection/JavaConverters$.seqAsJavaListConverter:(Lscala/collection/Seq;)Lscala/collection/JavaConverters$AsJava;
      36: invokevirtual #51                 // Method scala/collection/JavaConverters$AsJava.asJava:()Ljava/lang/Object;
      39: checkcast     #53                 // class java/util/List
      42: invokevirtual #57                 // Method ai/chronon/api/LabelPart.setLabels:(Ljava/util/List;)Lai/chronon/api/LabelPart;
      45: goto          51
      48: getstatic     #63                 // Field scala/runtime/BoxedUnit.UNIT:Lscala/runtime/BoxedUnit;
      51: pop
      52: aload         4
      54: areturn

  public scala.collection.Seq<ai.chronon.api.JoinPart> apply$default$1();
    Code:
       0: aconst_null
       1: areturn

  public int apply$default$2();
    Code:
       0: iconst_0
       1: ireturn

  public int apply$default$3();
    Code:
       0: iconst_0
       1: ireturn

  public ai.chronon.api.Builders$LabelPart$();
    Code:
       0: aload_0
       1: invokespecial #75                 // Method java/lang/Object."<init>":()V
       4: return
}
