Compiled from "Extensions.scala"
public class ai.chronon.api.Extensions$MetadataOps {
  private final ai.chronon.api.MetaData metaData;

  public java.lang.String cleanName();
    Code:
       0: getstatic     #28                 // Field ai/chronon/api/Extensions$.MODULE$:Lai/chronon/api/Extensions$;
       3: aload_0
       4: getfield      #30                 // Field metaData:Lai/chronon/api/MetaData;
       7: getfield      #36                 // Field ai/chronon/api/MetaData.name:Ljava/lang/String;
      10: invokevirtual #39                 // Method ai/chronon/api/Extensions$.StringOps:(Ljava/lang/String;)Lai/chronon/api/Extensions$StringOps;
      13: invokevirtual #42                 // Method ai/chronon/api/Extensions$StringOps.sanitize:()Ljava/lang/String;
      16: areturn

  public java.lang.String outputTable();
    Code:
       0: new           #47                 // class java/lang/StringBuilder
       3: dup
       4: ldc           #48                 // int 1
       6: invokespecial #52                 // Method java/lang/StringBuilder."<init>":(I)V
       9: aload_0
      10: getfield      #30                 // Field metaData:Lai/chronon/api/MetaData;
      13: getfield      #55                 // Field ai/chronon/api/MetaData.outputNamespace:Ljava/lang/String;
      16: invokevirtual #59                 // Method java/lang/StringBuilder.append:(Ljava/lang/String;)Ljava/lang/StringBuilder;
      19: ldc           #61                 // String .
      21: invokevirtual #59                 // Method java/lang/StringBuilder.append:(Ljava/lang/String;)Ljava/lang/StringBuilder;
      24: getstatic     #28                 // Field ai/chronon/api/Extensions$.MODULE$:Lai/chronon/api/Extensions$;
      27: aload_0
      28: getfield      #30                 // Field metaData:Lai/chronon/api/MetaData;
      31: invokevirtual #64                 // Method ai/chronon/api/Extensions$.MetadataOps:(Lai/chronon/api/MetaData;)Lai/chronon/api/Extensions$MetadataOps;
      34: invokevirtual #66                 // Method cleanName:()Ljava/lang/String;
      37: invokevirtual #59                 // Method java/lang/StringBuilder.append:(Ljava/lang/String;)Ljava/lang/StringBuilder;
      40: invokevirtual #69                 // Method java/lang/StringBuilder.toString:()Ljava/lang/String;
      43: areturn

  public java.lang.String outputLabelTable();
    Code:
       0: new           #47                 // class java/lang/StringBuilder
       3: dup
       4: ldc           #71                 // int 8
       6: invokespecial #52                 // Method java/lang/StringBuilder."<init>":(I)V
       9: aload_0
      10: getfield      #30                 // Field metaData:Lai/chronon/api/MetaData;
      13: getfield      #55                 // Field ai/chronon/api/MetaData.outputNamespace:Ljava/lang/String;
      16: invokevirtual #59                 // Method java/lang/StringBuilder.append:(Ljava/lang/String;)Ljava/lang/StringBuilder;
      19: ldc           #61                 // String .
      21: invokevirtual #59                 // Method java/lang/StringBuilder.append:(Ljava/lang/String;)Ljava/lang/StringBuilder;
      24: getstatic     #28                 // Field ai/chronon/api/Extensions$.MODULE$:Lai/chronon/api/Extensions$;
      27: aload_0
      28: getfield      #30                 // Field metaData:Lai/chronon/api/MetaData;
      31: invokevirtual #64                 // Method ai/chronon/api/Extensions$.MetadataOps:(Lai/chronon/api/MetaData;)Lai/chronon/api/Extensions$MetadataOps;
      34: invokevirtual #66                 // Method cleanName:()Ljava/lang/String;
      37: invokevirtual #59                 // Method java/lang/StringBuilder.append:(Ljava/lang/String;)Ljava/lang/StringBuilder;
      40: ldc           #73                 // String _labels
      42: invokevirtual #59                 // Method java/lang/StringBuilder.append:(Ljava/lang/String;)Ljava/lang/StringBuilder;
      45: invokevirtual #69                 // Method java/lang/StringBuilder.toString:()Ljava/lang/String;
      48: areturn

  public java.lang.String outputFinalView();
    Code:
       0: new           #47                 // class java/lang/StringBuilder
       3: dup
       4: ldc           #75                 // int 9
       6: invokespecial #52                 // Method java/lang/StringBuilder."<init>":(I)V
       9: aload_0
      10: getfield      #30                 // Field metaData:Lai/chronon/api/MetaData;
      13: getfield      #55                 // Field ai/chronon/api/MetaData.outputNamespace:Ljava/lang/String;
      16: invokevirtual #59                 // Method java/lang/StringBuilder.append:(Ljava/lang/String;)Ljava/lang/StringBuilder;
      19: ldc           #61                 // String .
      21: invokevirtual #59                 // Method java/lang/StringBuilder.append:(Ljava/lang/String;)Ljava/lang/StringBuilder;
      24: getstatic     #28                 // Field ai/chronon/api/Extensions$.MODULE$:Lai/chronon/api/Extensions$;
      27: aload_0
      28: getfield      #30                 // Field metaData:Lai/chronon/api/MetaData;
      31: invokevirtual #64                 // Method ai/chronon/api/Extensions$.MetadataOps:(Lai/chronon/api/MetaData;)Lai/chronon/api/Extensions$MetadataOps;
      34: invokevirtual #66                 // Method cleanName:()Ljava/lang/String;
      37: invokevirtual #59                 // Method java/lang/StringBuilder.append:(Ljava/lang/String;)Ljava/lang/StringBuilder;
      40: ldc           #77                 // String _labeled
      42: invokevirtual #59                 // Method java/lang/StringBuilder.append:(Ljava/lang/String;)Ljava/lang/StringBuilder;
      45: invokevirtual #69                 // Method java/lang/StringBuilder.toString:()Ljava/lang/String;
      48: areturn

  public java.lang.String outputLatestLabelView();
    Code:
       0: new           #47                 // class java/lang/StringBuilder
       3: dup
       4: ldc           #79                 // int 16
       6: invokespecial #52                 // Method java/lang/StringBuilder."<init>":(I)V
       9: aload_0
      10: getfield      #30                 // Field metaData:Lai/chronon/api/MetaData;
      13: getfield      #55                 // Field ai/chronon/api/MetaData.outputNamespace:Ljava/lang/String;
      16: invokevirtual #59                 // Method java/lang/StringBuilder.append:(Ljava/lang/String;)Ljava/lang/StringBuilder;
      19: ldc           #61                 // String .
      21: invokevirtual #59                 // Method java/lang/StringBuilder.append:(Ljava/lang/String;)Ljava/lang/StringBuilder;
      24: getstatic     #28                 // Field ai/chronon/api/Extensions$.MODULE$:Lai/chronon/api/Extensions$;
      27: aload_0
      28: getfield      #30                 // Field metaData:Lai/chronon/api/MetaData;
      31: invokevirtual #64                 // Method ai/chronon/api/Extensions$.MetadataOps:(Lai/chronon/api/MetaData;)Lai/chronon/api/Extensions$MetadataOps;
      34: invokevirtual #66                 // Method cleanName:()Ljava/lang/String;
      37: invokevirtual #59                 // Method java/lang/StringBuilder.append:(Ljava/lang/String;)Ljava/lang/StringBuilder;
      40: ldc           #81                 // String _labeled_latest
      42: invokevirtual #59                 // Method java/lang/StringBuilder.append:(Ljava/lang/String;)Ljava/lang/StringBuilder;
      45: invokevirtual #69                 // Method java/lang/StringBuilder.toString:()Ljava/lang/String;
      48: areturn

  public java.lang.String loggedTable();
    Code:
       0: new           #47                 // class java/lang/StringBuilder
       3: dup
       4: ldc           #83                 // int 7
       6: invokespecial #52                 // Method java/lang/StringBuilder."<init>":(I)V
       9: aload_0
      10: invokevirtual #85                 // Method outputTable:()Ljava/lang/String;
      13: invokevirtual #59                 // Method java/lang/StringBuilder.append:(Ljava/lang/String;)Ljava/lang/StringBuilder;
      16: ldc           #87                 // String _logged
      18: invokevirtual #59                 // Method java/lang/StringBuilder.append:(Ljava/lang/String;)Ljava/lang/StringBuilder;
      21: invokevirtual #69                 // Method java/lang/StringBuilder.toString:()Ljava/lang/String;
      24: areturn

  public java.lang.String bootstrapTable();
    Code:
       0: new           #47                 // class java/lang/StringBuilder
       3: dup
       4: ldc           #89                 // int 10
       6: invokespecial #52                 // Method java/lang/StringBuilder."<init>":(I)V
       9: aload_0
      10: invokevirtual #85                 // Method outputTable:()Ljava/lang/String;
      13: invokevirtual #59                 // Method java/lang/StringBuilder.append:(Ljava/lang/String;)Ljava/lang/StringBuilder;
      16: ldc           #91                 // String _bootstrap
      18: invokevirtual #59                 // Method java/lang/StringBuilder.append:(Ljava/lang/String;)Ljava/lang/StringBuilder;
      21: invokevirtual #69                 // Method java/lang/StringBuilder.toString:()Ljava/lang/String;
      24: areturn

  private java.lang.String comparisonPrefix();
    Code:
       0: ldc           #94                 // String comparison
       2: areturn

  public java.lang.String comparisonConfName();
    Code:
       0: new           #47                 // class java/lang/StringBuilder
       3: dup
       4: ldc           #48                 // int 1
       6: invokespecial #52                 // Method java/lang/StringBuilder."<init>":(I)V
       9: aload_0
      10: getfield      #30                 // Field metaData:Lai/chronon/api/MetaData;
      13: invokevirtual #98                 // Method ai/chronon/api/MetaData.getName:()Ljava/lang/String;
      16: invokevirtual #59                 // Method java/lang/StringBuilder.append:(Ljava/lang/String;)Ljava/lang/StringBuilder;
      19: ldc           #100                // String _
      21: invokevirtual #59                 // Method java/lang/StringBuilder.append:(Ljava/lang/String;)Ljava/lang/StringBuilder;
      24: aload_0
      25: invokespecial #102                // Method comparisonPrefix:()Ljava/lang/String;
      28: invokevirtual #59                 // Method java/lang/StringBuilder.append:(Ljava/lang/String;)Ljava/lang/StringBuilder;
      31: invokevirtual #69                 // Method java/lang/StringBuilder.toString:()Ljava/lang/String;
      34: areturn

  public java.lang.String comparisonTable();
    Code:
       0: new           #47                 // class java/lang/StringBuilder
       3: dup
       4: ldc           #48                 // int 1
       6: invokespecial #52                 // Method java/lang/StringBuilder."<init>":(I)V
       9: aload_0
      10: invokevirtual #85                 // Method outputTable:()Ljava/lang/String;
      13: invokevirtual #59                 // Method java/lang/StringBuilder.append:(Ljava/lang/String;)Ljava/lang/StringBuilder;
      16: ldc           #100                // String _
      18: invokevirtual #59                 // Method java/lang/StringBuilder.append:(Ljava/lang/String;)Ljava/lang/StringBuilder;
      21: aload_0
      22: invokespecial #102                // Method comparisonPrefix:()Ljava/lang/String;
      25: invokevirtual #59                 // Method java/lang/StringBuilder.append:(Ljava/lang/String;)Ljava/lang/StringBuilder;
      28: invokevirtual #69                 // Method java/lang/StringBuilder.toString:()Ljava/lang/String;
      31: areturn

  public java.lang.String consistencyTable();
    Code:
       0: new           #47                 // class java/lang/StringBuilder
       3: dup
       4: ldc           #105                // int 12
       6: invokespecial #52                 // Method java/lang/StringBuilder."<init>":(I)V
       9: aload_0
      10: invokevirtual #85                 // Method outputTable:()Ljava/lang/String;
      13: invokevirtual #59                 // Method java/lang/StringBuilder.append:(Ljava/lang/String;)Ljava/lang/StringBuilder;
      16: ldc           #107                // String _consistency
      18: invokevirtual #59                 // Method java/lang/StringBuilder.append:(Ljava/lang/String;)Ljava/lang/StringBuilder;
      21: invokevirtual #69                 // Method java/lang/StringBuilder.toString:()Ljava/lang/String;
      24: areturn

  public java.lang.String uploadTable();
    Code:
       0: new           #47                 // class java/lang/StringBuilder
       3: dup
       4: ldc           #83                 // int 7
       6: invokespecial #52                 // Method java/lang/StringBuilder."<init>":(I)V
       9: aload_0
      10: invokevirtual #85                 // Method outputTable:()Ljava/lang/String;
      13: invokevirtual #59                 // Method java/lang/StringBuilder.append:(Ljava/lang/String;)Ljava/lang/StringBuilder;
      16: ldc           #110                // String _upload
      18: invokevirtual #59                 // Method java/lang/StringBuilder.append:(Ljava/lang/String;)Ljava/lang/StringBuilder;
      21: invokevirtual #69                 // Method java/lang/StringBuilder.toString:()Ljava/lang/String;
      24: areturn

  public java.lang.String dailyStatsOutputTable();
    Code:
       0: new           #47                 // class java/lang/StringBuilder
       3: dup
       4: ldc           #105                // int 12
       6: invokespecial #52                 // Method java/lang/StringBuilder."<init>":(I)V
       9: aload_0
      10: invokevirtual #85                 // Method outputTable:()Ljava/lang/String;
      13: invokevirtual #59                 // Method java/lang/StringBuilder.append:(Ljava/lang/String;)Ljava/lang/StringBuilder;
      16: ldc           #113                // String _daily_stats
      18: invokevirtual #59                 // Method java/lang/StringBuilder.append:(Ljava/lang/String;)Ljava/lang/StringBuilder;
      21: invokevirtual #69                 // Method java/lang/StringBuilder.toString:()Ljava/lang/String;
      24: areturn

  public java.lang.String dailyStatsUploadTable();
    Code:
       0: new           #47                 // class java/lang/StringBuilder
       3: dup
       4: ldc           #83                 // int 7
       6: invokespecial #52                 // Method java/lang/StringBuilder."<init>":(I)V
       9: aload_0
      10: invokevirtual #116                // Method dailyStatsOutputTable:()Ljava/lang/String;
      13: invokevirtual #59                 // Method java/lang/StringBuilder.append:(Ljava/lang/String;)Ljava/lang/StringBuilder;
      16: ldc           #110                // String _upload
      18: invokevirtual #59                 // Method java/lang/StringBuilder.append:(Ljava/lang/String;)Ljava/lang/StringBuilder;
      21: invokevirtual #69                 // Method java/lang/StringBuilder.toString:()Ljava/lang/String;
      24: areturn

  public ai.chronon.api.MetaData copyForVersioningComparison();
    Code:
       0: new           #32                 // class ai/chronon/api/MetaData
       3: dup
       4: invokespecial #121                // Method ai/chronon/api/MetaData."<init>":()V
       7: astore_1
       8: aload_1
       9: aload_0
      10: getfield      #30                 // Field metaData:Lai/chronon/api/MetaData;
      13: getfield      #36                 // Field ai/chronon/api/MetaData.name:Ljava/lang/String;
      16: invokevirtual #125                // Method ai/chronon/api/MetaData.setName:(Ljava/lang/String;)Lai/chronon/api/MetaData;
      19: pop
      20: aload_1
      21: areturn

  public scala.collection.immutable.Map<java.lang.String, java.lang.String> tableProps();
    Code:
       0: getstatic     #134                // Field scala/Option$.MODULE$:Lscala/Option$;
       3: aload_0
       4: getfield      #30                 // Field metaData:Lai/chronon/api/MetaData;
       7: getfield      #138                // Field ai/chronon/api/MetaData.tableProperties:Ljava/util/Map;
      10: invokevirtual #142                // Method scala/Option$.apply:(Ljava/lang/Object;)Lscala/Option;
      13: invokedynamic #161,  0            // InvokeDynamic #0:apply:()Lscala/Function1;
      18: invokevirtual #167                // Method scala/Option.map:(Lscala/Function1;)Lscala/Option;
      21: getstatic     #172                // Field scala/$less$colon$less$.MODULE$:Lscala/$less$colon$less$;
      24: invokevirtual #176                // Method scala/$less$colon$less$.refl:()Lscala/$eq$colon$eq;
      27: invokevirtual #180                // Method scala/Option.orNull:(Lscala/$less$colon$less;)Ljava/lang/Object;
      30: checkcast     #182                // class scala/collection/immutable/Map
      33: areturn

  public java.lang.String nameToFilePath();
    Code:
       0: aload_0
       1: getfield      #30                 // Field metaData:Lai/chronon/api/MetaData;
       4: getfield      #36                 // Field ai/chronon/api/MetaData.name:Ljava/lang/String;
       7: ldc           #185                // String \\.
       9: ldc           #187                // String /
      11: invokevirtual #193                // Method java/lang/String.replaceFirst:(Ljava/lang/String;Ljava/lang/String;)Ljava/lang/String;
      14: areturn

  public java.lang.Object customJsonLookUp(java.lang.String);
    Code:
       0: aload_0
       1: getfield      #30                 // Field metaData:Lai/chronon/api/MetaData;
       4: getfield      #199                // Field ai/chronon/api/MetaData.customJson:Ljava/lang/String;
       7: ifnonnull     12
      10: aconst_null
      11: areturn
      12: new           #201                // class com/fasterxml/jackson/databind/ObjectMapper
      15: dup
      16: invokespecial #202                // Method com/fasterxml/jackson/databind/ObjectMapper."<init>":()V
      19: astore_2
      20: new           #10                 // class ai/chronon/api/Extensions$MetadataOps$$anon$1
      23: dup
      24: aconst_null
      25: invokespecial #205                // Method ai/chronon/api/Extensions$MetadataOps$$anon$1."<init>":(Lai/chronon/api/Extensions$MetadataOps;)V
      28: astore_3
      29: aload_2
      30: aload_0
      31: getfield      #30                 // Field metaData:Lai/chronon/api/MetaData;
      34: getfield      #199                // Field ai/chronon/api/MetaData.customJson:Ljava/lang/String;
      37: aload_3
      38: invokevirtual #209                // Method com/fasterxml/jackson/databind/ObjectMapper.readValue:(Ljava/lang/String;Lcom/fasterxml/jackson/core/type/TypeReference;)Ljava/lang/Object;
      41: checkcast     #211                // class java/util/Map
      44: astore        4
      46: getstatic     #216                // Field scala/util/ScalaVersionSpecificCollectionsConverter$.MODULE$:Lscala/util/ScalaVersionSpecificCollectionsConverter$;
      49: aload         4
      51: invokevirtual #219                // Method scala/util/ScalaVersionSpecificCollectionsConverter$.convertJavaMapToScala:(Ljava/util/Map;)Lscala/collection/immutable/Map;
      54: aload_1
      55: invokeinterface #222,  2          // InterfaceMethod scala/collection/immutable/Map.get:(Ljava/lang/Object;)Lscala/Option;
      60: getstatic     #172                // Field scala/$less$colon$less$.MODULE$:Lscala/$less$colon$less$;
      63: invokevirtual #176                // Method scala/$less$colon$less$.refl:()Lscala/$eq$colon$eq;
      66: invokevirtual #180                // Method scala/Option.orNull:(Lscala/$less$colon$less;)Ljava/lang/Object;
      69: areturn

  public java.lang.String owningTeam();
    Code:
       0: getstatic     #233                // Field scala/util/Try$.MODULE$:Lscala/util/Try$;
       3: aload_0
       4: invokedynamic #244,  0            // InvokeDynamic #1:apply:(Lai/chronon/api/Extensions$MetadataOps;)Lscala/Function0;
       9: invokevirtual #247                // Method scala/util/Try$.apply:(Lscala/Function0;)Lscala/util/Try;
      12: invokevirtual #253                // Method scala/util/Try.toOption:()Lscala/Option;
      15: astore_1
      16: aload_1
      17: aload_0
      18: invokedynamic #258,  0            // InvokeDynamic #2:apply:(Lai/chronon/api/Extensions$MetadataOps;)Lscala/Function0;
      23: invokevirtual #262                // Method scala/Option.getOrElse:(Lscala/Function0;)Ljava/lang/Object;
      26: checkcast     #189                // class java/lang/String
      29: areturn

  public static final scala.collection.immutable.Map $anonfun$tableProps$1(java.util.Map);
    Code:
       0: getstatic     #216                // Field scala/util/ScalaVersionSpecificCollectionsConverter$.MODULE$:Lscala/util/ScalaVersionSpecificCollectionsConverter$;
       3: aload_0
       4: invokevirtual #219                // Method scala/util/ScalaVersionSpecificCollectionsConverter$.convertJavaMapToScala:(Ljava/util/Map;)Lscala/collection/immutable/Map;
       7: getstatic     #172                // Field scala/$less$colon$less$.MODULE$:Lscala/$less$colon$less$;
      10: invokevirtual #176                // Method scala/$less$colon$less$.refl:()Lscala/$eq$colon$eq;
      13: invokeinterface #269,  2          // InterfaceMethod scala/collection/immutable/Map.toMap:(Lscala/$less$colon$less;)Lscala/collection/immutable/Map;
      18: areturn

  public static final java.lang.String $anonfun$owningTeam$1(ai.chronon.api.Extensions$MetadataOps);
    Code:
       0: aload_0
       1: getstatic     #275                // Field ai/chronon/api/Constants$.MODULE$:Lai/chronon/api/Constants$;
       4: invokevirtual #278                // Method ai/chronon/api/Constants$.TeamOverride:()Ljava/lang/String;
       7: invokevirtual #280                // Method customJsonLookUp:(Ljava/lang/String;)Ljava/lang/Object;
      10: checkcast     #189                // class java/lang/String
      13: areturn

  public static final java.lang.String $anonfun$owningTeam$2(ai.chronon.api.Extensions$MetadataOps);
    Code:
       0: aload_0
       1: getfield      #30                 // Field metaData:Lai/chronon/api/MetaData;
       4: getfield      #283                // Field ai/chronon/api/MetaData.team:Ljava/lang/String;
       7: areturn

  public ai.chronon.api.Extensions$MetadataOps(ai.chronon.api.MetaData);
    Code:
       0: aload_0
       1: aload_1
       2: putfield      #30                 // Field metaData:Lai/chronon/api/MetaData;
       5: aload_0
       6: invokespecial #285                // Method java/lang/Object."<init>":()V
       9: return

  private static java.lang.Object $deserializeLambda$(java.lang.invoke.SerializedLambda);
    Code:
       0: aload_0
       1: invokedynamic #297,  0            // InvokeDynamic #3:lambdaDeserialize:(Ljava/lang/invoke/SerializedLambda;)Ljava/lang/Object;
       6: areturn
}
