Compiled from "Extensions.scala"
public class ai.chronon.api.Extensions$QueryOps {
  private final ai.chronon.api.Query query;

  public scala.collection.Seq<java.lang.String> setupsSeq();
    Code:
       0: getstatic     #24                 // Field scala/Option$.MODULE$:Lscala/Option$;
       3: aload_0
       4: getfield      #26                 // Field query:Lai/chronon/api/Query;
       7: getfield      #32                 // Field ai/chronon/api/Query.setups:Ljava/util/List;
      10: invokevirtual #36                 // Method scala/Option$.apply:(Ljava/lang/Object;)Lscala/Option;
      13: invokedynamic #56,  0             // InvokeDynamic #0:apply:()Lscala/Function1;
      18: invokevirtual #62                 // Method scala/Option.map:(Lscala/Function1;)Lscala/Option;
      21: invokedynamic #72,  0             // InvokeDynamic #1:apply:()Lscala/Function0;
      26: invokevirtual #76                 // Method scala/Option.getOrElse:(Lscala/Function0;)Ljava/lang/Object;
      29: checkcast     #78                 // class scala/collection/Seq
      32: areturn

  public static final scala.collection.immutable.List $anonfun$setupsSeq$1(java.util.List);
    Code:
       0: getstatic     #86                 // Field scala/util/ScalaVersionSpecificCollectionsConverter$.MODULE$:Lscala/util/ScalaVersionSpecificCollectionsConverter$;
       3: aload_0
       4: invokevirtual #89                 // Method scala/util/ScalaVersionSpecificCollectionsConverter$.convertJavaListToScala:(Ljava/util/List;)Lscala/collection/immutable/List;
       7: invokevirtual #95                 // Method scala/collection/immutable/List.toSeq:()Lscala/collection/immutable/Seq;
      10: checkcast     #91                 // class scala/collection/immutable/List
      13: areturn

  public static final scala.collection.Seq $anonfun$setupsSeq$2();
    Code:
       0: getstatic     #100                // Field scala/collection/Seq$.MODULE$:Lscala/collection/Seq$;
       3: invokevirtual #104                // Method scala/collection/Seq$.empty:()Lscala/collection/SeqOps;
       6: checkcast     #78                 // class scala/collection/Seq
       9: areturn

  public ai.chronon.api.Extensions$QueryOps(ai.chronon.api.Query);
    Code:
       0: aload_0
       1: aload_1
       2: putfield      #26                 // Field query:Lai/chronon/api/Query;
       5: aload_0
       6: invokespecial #109                // Method java/lang/Object."<init>":()V
       9: return

  private static java.lang.Object $deserializeLambda$(java.lang.invoke.SerializedLambda);
    Code:
       0: aload_0
       1: invokedynamic #121,  0            // InvokeDynamic #2:lambdaDeserialize:(Ljava/lang/invoke/SerializedLambda;)Ljava/lang/Object;
       6: areturn
}
