Compiled from "Extensions.scala"
public class ai.chronon.api.Extensions$JoinPartOps extends ai.chronon.api.JoinPart {
  private java.lang.String fullPrefix;

  private scala.collection.immutable.Map<java.lang.String, java.lang.String> leftToRight;

  private final ai.chronon.api.JoinPart joinPart;

  private volatile byte bitmap$0;

  private java.lang.String fullPrefix$lzycompute();
    Code:
       0: aload_0
       1: dup
       2: astore_1
       3: monitorenter
       4: aload_0
       5: getfield      #42                 // Field bitmap$0:B
       8: iconst_1
       9: iand
      10: i2b
      11: iconst_0
      12: if_icmpne     84
      15: aload_0
      16: getstatic     #48                 // Field scala/Option$.MODULE$:Lscala/Option$;
      19: getstatic     #48                 // Field scala/Option$.MODULE$:Lscala/Option$;
      22: aload_0
      23: getfield      #51                 // Field prefix:Ljava/lang/String;
      26: invokevirtual #55                 // Method scala/Option$.apply:(Ljava/lang/Object;)Lscala/Option;
      29: invokevirtual #59                 // Method scala/Option$.option2Iterable:(Lscala/Option;)Lscala/collection/Iterable;
      32: new           #61                 // class scala/Some
      35: dup
      36: getstatic     #66                 // Field ai/chronon/api/Extensions$.MODULE$:Lai/chronon/api/Extensions$;
      39: aload_0
      40: getfield      #70                 // Field groupBy:Lai/chronon/api/GroupBy;
      43: invokevirtual #76                 // Method ai/chronon/api/GroupBy.getMetaData:()Lai/chronon/api/MetaData;
      46: invokevirtual #79                 // Method ai/chronon/api/Extensions$.MetadataOps:(Lai/chronon/api/MetaData;)Lai/chronon/api/Extensions$MetadataOps;
      49: invokevirtual #82                 // Method ai/chronon/api/Extensions$MetadataOps.cleanName:()Ljava/lang/String;
      52: invokespecial #86                 // Method scala/Some."<init>":(Ljava/lang/Object;)V
      55: invokeinterface #92,  2           // InterfaceMethod scala/collection/Iterable.$plus$plus:(Lscala/collection/IterableOnce;)Ljava/lang/Object;
      60: checkcast     #94                 // class scala/collection/IterableOnceOps
      63: ldc           #96                 // String _
      65: invokeinterface #100,  2          // InterfaceMethod scala/collection/IterableOnceOps.mkString:(Ljava/lang/String;)Ljava/lang/String;
      70: putfield      #102                // Field fullPrefix:Ljava/lang/String;
      73: aload_0
      74: aload_0
      75: getfield      #42                 // Field bitmap$0:B
      78: iconst_1
      79: ior
      80: i2b
      81: putfield      #42                 // Field bitmap$0:B
      84: aload_1
      85: monitorexit
      86: goto          92
      89: aload_1
      90: monitorexit
      91: athrow
      92: aload_0
      93: getfield      #102                // Field fullPrefix:Ljava/lang/String;
      96: areturn
    Exception table:
       from    to  target type
           4    84    89   any

  public java.lang.String fullPrefix();
    Code:
       0: aload_0
       1: getfield      #42                 // Field bitmap$0:B
       4: iconst_1
       5: iand
       6: i2b
       7: iconst_0
       8: if_icmpne     18
      11: aload_0
      12: invokespecial #108                // Method fullPrefix$lzycompute:()Ljava/lang/String;
      15: goto          22
      18: aload_0
      19: getfield      #102                // Field fullPrefix:Ljava/lang/String;
      22: areturn

  private scala.collection.immutable.Map<java.lang.String, java.lang.String> leftToRight$lzycompute();
    Code:
       0: aload_0
       1: dup
       2: astore_1
       3: monitorenter
       4: aload_0
       5: getfield      #42                 // Field bitmap$0:B
       8: iconst_2
       9: iand
      10: i2b
      11: iconst_0
      12: if_icmpne     47
      15: aload_0
      16: aload_0
      17: invokevirtual #116                // Method rightToLeft:()Lscala/collection/immutable/Map;
      20: invokedynamic #136,  0            // InvokeDynamic #0:apply:()Lscala/Function1;
      25: invokeinterface #142,  2          // InterfaceMethod scala/collection/immutable/Map.map:(Lscala/Function1;)Lscala/collection/IterableOps;
      30: checkcast     #138                // class scala/collection/immutable/Map
      33: putfield      #144                // Field leftToRight:Lscala/collection/immutable/Map;
      36: aload_0
      37: aload_0
      38: getfield      #42                 // Field bitmap$0:B
      41: iconst_2
      42: ior
      43: i2b
      44: putfield      #42                 // Field bitmap$0:B
      47: aload_1
      48: monitorexit
      49: goto          55
      52: aload_1
      53: monitorexit
      54: athrow
      55: aload_0
      56: getfield      #144                // Field leftToRight:Lscala/collection/immutable/Map;
      59: areturn
    Exception table:
       from    to  target type
           4    47    52   any

  public scala.collection.immutable.Map<java.lang.String, java.lang.String> leftToRight();
    Code:
       0: aload_0
       1: getfield      #42                 // Field bitmap$0:B
       4: iconst_2
       5: iand
       6: i2b
       7: iconst_0
       8: if_icmpne     18
      11: aload_0
      12: invokespecial #146                // Method leftToRight$lzycompute:()Lscala/collection/immutable/Map;
      15: goto          22
      18: aload_0
      19: getfield      #144                // Field leftToRight:Lscala/collection/immutable/Map;
      22: areturn

  public scala.collection.Seq<java.lang.String> valueColumns();
    Code:
       0: getstatic     #154                // Field scala/Predef$.MODULE$:Lscala/Predef$;
       3: getstatic     #159                // Field scala/collection/ArrayOps$.MODULE$:Lscala/collection/ArrayOps$;
       6: getstatic     #154                // Field scala/Predef$.MODULE$:Lscala/Predef$;
       9: getstatic     #66                 // Field ai/chronon/api/Extensions$.MODULE$:Lai/chronon/api/Extensions$;
      12: aload_0
      13: getfield      #161                // Field joinPart:Lai/chronon/api/JoinPart;
      16: getfield      #162                // Field ai/chronon/api/JoinPart.groupBy:Lai/chronon/api/GroupBy;
      19: invokevirtual #165                // Method ai/chronon/api/Extensions$.GroupByOps:(Lai/chronon/api/GroupBy;)Lai/chronon/api/Extensions$GroupByOps;
      22: invokevirtual #168                // Method ai/chronon/api/Extensions$GroupByOps.valueColumns:()[Ljava/lang/String;
      25: checkcast     #170                // class "[Ljava/lang/Object;"
      28: invokevirtual #174                // Method scala/Predef$.refArrayOps:([Ljava/lang/Object;)Ljava/lang/Object;
      31: aload_0
      32: invokedynamic #183,  0            // InvokeDynamic #1:apply:(Lai/chronon/api/Extensions$JoinPartOps;)Lscala/Function1;
      37: getstatic     #188                // Field scala/reflect/ClassTag$.MODULE$:Lscala/reflect/ClassTag$;
      40: ldc           #110                // class java/lang/String
      42: invokevirtual #191                // Method scala/reflect/ClassTag$.apply:(Ljava/lang/Class;)Lscala/reflect/ClassTag;
      45: invokevirtual #195                // Method scala/collection/ArrayOps$.map$extension:(Ljava/lang/Object;Lscala/Function1;Lscala/reflect/ClassTag;)Ljava/lang/Object;
      48: checkcast     #170                // class "[Ljava/lang/Object;"
      51: invokevirtual #199                // Method scala/Predef$.wrapRefArray:([Ljava/lang/Object;)Lscala/collection/mutable/ArraySeq$ofRef;
      54: areturn

  public scala.collection.immutable.Map<java.lang.String, java.lang.String> rightToLeft();
    Code:
       0: getstatic     #204                // Field scala/util/ScalaVersionSpecificCollectionsConverter$.MODULE$:Lscala/util/ScalaVersionSpecificCollectionsConverter$;
       3: aload_0
       4: getfield      #161                // Field joinPart:Lai/chronon/api/JoinPart;
       7: getfield      #162                // Field ai/chronon/api/JoinPart.groupBy:Lai/chronon/api/GroupBy;
      10: getfield      #208                // Field ai/chronon/api/GroupBy.keyColumns:Ljava/util/List;
      13: invokevirtual #212                // Method scala/util/ScalaVersionSpecificCollectionsConverter$.convertJavaListToScala:(Ljava/util/List;)Lscala/collection/immutable/List;
      16: invokedynamic #219,  0            // InvokeDynamic #2:apply:()Lscala/Function1;
      21: invokevirtual #224                // Method scala/collection/immutable/List.map:(Lscala/Function1;)Lscala/collection/immutable/List;
      24: getstatic     #229                // Field scala/$less$colon$less$.MODULE$:Lscala/$less$colon$less$;
      27: invokevirtual #233                // Method scala/$less$colon$less$.refl:()Lscala/$eq$colon$eq;
      30: invokevirtual #237                // Method scala/collection/immutable/List.toMap:(Lscala/$less$colon$less;)Lscala/collection/immutable/Map;
      33: astore_1
      34: getstatic     #48                 // Field scala/Option$.MODULE$:Lscala/Option$;
      37: aload_0
      38: getfield      #161                // Field joinPart:Lai/chronon/api/JoinPart;
      41: getfield      #241                // Field ai/chronon/api/JoinPart.keyMapping:Ljava/util/Map;
      44: invokevirtual #55                 // Method scala/Option$.apply:(Ljava/lang/Object;)Lscala/Option;
      47: aload_1
      48: invokedynamic #251,  0            // InvokeDynamic #3:apply:(Lscala/collection/immutable/Map;)Lscala/Function1;
      53: invokevirtual #256                // Method scala/Option.map:(Lscala/Function1;)Lscala/Option;
      56: aload_1
      57: invokedynamic #267,  0            // InvokeDynamic #4:apply:(Lscala/collection/immutable/Map;)Lscala/Function0;
      62: invokevirtual #271                // Method scala/Option.getOrElse:(Lscala/Function0;)Ljava/lang/Object;
      65: checkcast     #138                // class scala/collection/immutable/Map
      68: areturn

  public ai.chronon.api.JoinPart copyForVersioningComparison();
    Code:
       0: aload_0
       1: getfield      #161                // Field joinPart:Lai/chronon/api/JoinPart;
       4: invokevirtual #277                // Method ai/chronon/api/JoinPart.deepCopy:()Lai/chronon/api/JoinPart;
       7: astore_1
       8: aload_1
       9: getstatic     #66                 // Field ai/chronon/api/Extensions$.MODULE$:Lai/chronon/api/Extensions$;
      12: aload_1
      13: getfield      #162                // Field ai/chronon/api/JoinPart.groupBy:Lai/chronon/api/GroupBy;
      16: invokevirtual #165                // Method ai/chronon/api/Extensions$.GroupByOps:(Lai/chronon/api/GroupBy;)Lai/chronon/api/Extensions$GroupByOps;
      19: invokevirtual #280                // Method ai/chronon/api/Extensions$GroupByOps.copyForVersioningComparison:()Lai/chronon/api/GroupBy;
      22: invokevirtual #284                // Method ai/chronon/api/JoinPart.setGroupBy:(Lai/chronon/api/GroupBy;)Lai/chronon/api/JoinPart;
      25: pop
      26: aload_1
      27: areturn

  public ai.chronon.api.StructField constructJoinPartSchema(ai.chronon.api.StructField);
    Code:
       0: new           #290                // class ai/chronon/api/StructField
       3: dup
       4: new           #292                // class java/lang/StringBuilder
       7: dup
       8: ldc           #126                // int 1
      10: invokespecial #295                // Method java/lang/StringBuilder."<init>":(I)V
      13: getstatic     #66                 // Field ai/chronon/api/Extensions$.MODULE$:Lai/chronon/api/Extensions$;
      16: aload_0
      17: getfield      #161                // Field joinPart:Lai/chronon/api/JoinPart;
      20: invokevirtual #298                // Method ai/chronon/api/Extensions$.JoinPartOps:(Lai/chronon/api/JoinPart;)Lai/chronon/api/Extensions$JoinPartOps;
      23: invokevirtual #300                // Method fullPrefix:()Ljava/lang/String;
      26: invokevirtual #304                // Method java/lang/StringBuilder.append:(Ljava/lang/String;)Ljava/lang/StringBuilder;
      29: ldc           #96                 // String _
      31: invokevirtual #304                // Method java/lang/StringBuilder.append:(Ljava/lang/String;)Ljava/lang/StringBuilder;
      34: aload_1
      35: invokevirtual #307                // Method ai/chronon/api/StructField.name:()Ljava/lang/String;
      38: invokevirtual #304                // Method java/lang/StringBuilder.append:(Ljava/lang/String;)Ljava/lang/StringBuilder;
      41: invokevirtual #310                // Method java/lang/StringBuilder.toString:()Ljava/lang/String;
      44: aload_1
      45: invokevirtual #314                // Method ai/chronon/api/StructField.fieldType:()Lai/chronon/api/DataType;
      48: invokespecial #317                // Method ai/chronon/api/StructField."<init>":(Ljava/lang/String;Lai/chronon/api/DataType;)V
      51: areturn

  public static final scala.Tuple2 $anonfun$leftToRight$1(scala.Tuple2);
    Code:
       0: aload_0
       1: astore_2
       2: aload_2
       3: ifnull        42
       6: aload_2
       7: invokevirtual #324                // Method scala/Tuple2._1:()Ljava/lang/Object;
      10: checkcast     #110                // class java/lang/String
      13: astore_3
      14: aload_2
      15: invokevirtual #327                // Method scala/Tuple2._2:()Ljava/lang/Object;
      18: checkcast     #110                // class java/lang/String
      21: astore        4
      23: getstatic     #330                // Field scala/Predef$ArrowAssoc$.MODULE$:Lscala/Predef$ArrowAssoc$;
      26: getstatic     #154                // Field scala/Predef$.MODULE$:Lscala/Predef$;
      29: aload         4
      31: invokevirtual #333                // Method scala/Predef$.ArrowAssoc:(Ljava/lang/Object;)Ljava/lang/Object;
      34: aload_3
      35: invokevirtual #337                // Method scala/Predef$ArrowAssoc$.$minus$greater$extension:(Ljava/lang/Object;Ljava/lang/Object;)Lscala/Tuple2;
      38: astore_1
      39: goto          54
      42: goto          45
      45: new           #339                // class scala/MatchError
      48: dup
      49: aload_2
      50: invokespecial #340                // Method scala/MatchError."<init>":(Ljava/lang/Object;)V
      53: athrow
      54: aload_1
      55: areturn

  public static final java.lang.String $anonfun$valueColumns$6(ai.chronon.api.Extensions$JoinPartOps, java.lang.String);
    Code:
       0: new           #292                // class java/lang/StringBuilder
       3: dup
       4: ldc           #126                // int 1
       6: invokespecial #295                // Method java/lang/StringBuilder."<init>":(I)V
       9: aload_0
      10: invokevirtual #300                // Method fullPrefix:()Ljava/lang/String;
      13: invokevirtual #304                // Method java/lang/StringBuilder.append:(Ljava/lang/String;)Ljava/lang/StringBuilder;
      16: ldc           #96                 // String _
      18: invokevirtual #304                // Method java/lang/StringBuilder.append:(Ljava/lang/String;)Ljava/lang/StringBuilder;
      21: aload_1
      22: invokevirtual #304                // Method java/lang/StringBuilder.append:(Ljava/lang/String;)Ljava/lang/StringBuilder;
      25: invokevirtual #310                // Method java/lang/StringBuilder.toString:()Ljava/lang/String;
      28: areturn

  public static final scala.Tuple2 $anonfun$rightToLeft$1(java.lang.String);
    Code:
       0: getstatic     #330                // Field scala/Predef$ArrowAssoc$.MODULE$:Lscala/Predef$ArrowAssoc$;
       3: getstatic     #154                // Field scala/Predef$.MODULE$:Lscala/Predef$;
       6: aload_0
       7: invokevirtual #333                // Method scala/Predef$.ArrowAssoc:(Ljava/lang/Object;)Ljava/lang/Object;
      10: aload_0
      11: invokevirtual #337                // Method scala/Predef$ArrowAssoc$.$minus$greater$extension:(Ljava/lang/Object;Ljava/lang/Object;)Lscala/Tuple2;
      14: areturn

  public static final scala.Tuple2 $anonfun$rightToLeft$3(scala.Tuple2);
    Code:
       0: aload_0
       1: astore_2
       2: aload_2
       3: ifnull        42
       6: aload_2
       7: invokevirtual #324                // Method scala/Tuple2._1:()Ljava/lang/Object;
      10: checkcast     #110                // class java/lang/String
      13: astore_3
      14: aload_2
      15: invokevirtual #327                // Method scala/Tuple2._2:()Ljava/lang/Object;
      18: checkcast     #110                // class java/lang/String
      21: astore        4
      23: getstatic     #330                // Field scala/Predef$ArrowAssoc$.MODULE$:Lscala/Predef$ArrowAssoc$;
      26: getstatic     #154                // Field scala/Predef$.MODULE$:Lscala/Predef$;
      29: aload         4
      31: invokevirtual #333                // Method scala/Predef$.ArrowAssoc:(Ljava/lang/Object;)Ljava/lang/Object;
      34: aload_3
      35: invokevirtual #337                // Method scala/Predef$ArrowAssoc$.$minus$greater$extension:(Ljava/lang/Object;Ljava/lang/Object;)Lscala/Tuple2;
      38: astore_1
      39: goto          54
      42: goto          45
      45: new           #339                // class scala/MatchError
      48: dup
      49: aload_2
      50: invokespecial #340                // Method scala/MatchError."<init>":(Ljava/lang/Object;)V
      53: athrow
      54: aload_1
      55: areturn

  public static final scala.collection.immutable.Map $anonfun$rightToLeft$2(scala.collection.immutable.Map, java.util.Map);
    Code:
       0: getstatic     #204                // Field scala/util/ScalaVersionSpecificCollectionsConverter$.MODULE$:Lscala/util/ScalaVersionSpecificCollectionsConverter$;
       3: aload_1
       4: invokevirtual #352                // Method scala/util/ScalaVersionSpecificCollectionsConverter$.convertJavaMapToScala:(Ljava/util/Map;)Lscala/collection/immutable/Map;
       7: invokedynamic #356,  0            // InvokeDynamic #5:apply:()Lscala/Function1;
      12: invokeinterface #142,  2          // InterfaceMethod scala/collection/immutable/Map.map:(Lscala/Function1;)Lscala/collection/IterableOps;
      17: checkcast     #138                // class scala/collection/immutable/Map
      20: getstatic     #229                // Field scala/$less$colon$less$.MODULE$:Lscala/$less$colon$less$;
      23: invokevirtual #233                // Method scala/$less$colon$less$.refl:()Lscala/$eq$colon$eq;
      26: invokeinterface #357,  2          // InterfaceMethod scala/collection/immutable/Map.toMap:(Lscala/$less$colon$less;)Lscala/collection/immutable/Map;
      31: astore_2
      32: aload_0
      33: aload_2
      34: invokeinterface #360,  2          // InterfaceMethod scala/collection/immutable/Map.$plus$plus:(Lscala/collection/IterableOnce;)Lscala/collection/IterableOps;
      39: checkcast     #138                // class scala/collection/immutable/Map
      42: areturn

  public static final scala.collection.immutable.Map $anonfun$rightToLeft$4(scala.collection.immutable.Map);
    Code:
       0: aload_0
       1: areturn

  public ai.chronon.api.Extensions$JoinPartOps(ai.chronon.api.JoinPart);
    Code:
       0: aload_0
       1: aload_1
       2: putfield      #161                // Field joinPart:Lai/chronon/api/JoinPart;
       5: aload_0
       6: aload_1
       7: invokespecial #364                // Method ai/chronon/api/JoinPart."<init>":(Lai/chronon/api/JoinPart;)V
      10: return

  private static java.lang.Object $deserializeLambda$(java.lang.invoke.SerializedLambda);
    Code:
       0: aload_0
       1: invokedynamic #376,  0            // InvokeDynamic #6:lambdaDeserialize:(Ljava/lang/invoke/SerializedLambda;)Ljava/lang/Object;
       6: areturn
}
