Compiled from "MetaData.java"
public final class ai.chronon.api.MetaData$_Fields extends java.lang.Enum<ai.chronon.api.MetaData$_Fields> implements org.apache.thrift.TFieldIdEnum {
  public static final ai.chronon.api.MetaData$_Fields NAME;

  public static final ai.chronon.api.MetaData$_Fields ONLINE;

  public static final ai.chronon.api.MetaData$_Fields PRODUCTION;

  public static final ai.chronon.api.MetaData$_Fields CUSTOM_JSON;

  public static final ai.chronon.api.MetaData$_Fields DEPENDENCIES;

  public static final ai.chronon.api.MetaData$_Fields TABLE_PROPERTIES;

  public static final ai.chronon.api.MetaData$_Fields OUTPUT_NAMESPACE;

  public static final ai.chronon.api.MetaData$_Fields TEAM;

  public static final ai.chronon.api.MetaData$_Fields MODE_TO_ENV_MAP;

  public static final ai.chronon.api.MetaData$_Fields CONSISTENCY_CHECK;

  public static final ai.chronon.api.MetaData$_Fields SAMPLE_PERCENT;

  public static final ai.chronon.api.MetaData$_Fields OFFLINE_SCHEDULE;

  public static final ai.chronon.api.MetaData$_Fields CONSISTENCY_SAMPLE_PERCENT;

  private static final java.util.Map<java.lang.String, ai.chronon.api.MetaData$_Fields> byName;

  private final short _thriftId;

  private final java.lang.String _fieldName;

  private static final ai.chronon.api.MetaData$_Fields[] $VALUES;

  public static ai.chronon.api.MetaData$_Fields[] values();
    Code:
       0: getstatic     #1                  // Field $VALUES:[Lai/chronon/api/MetaData$_Fields;
       3: invokevirtual #2                  // Method "[Lai/chronon/api/MetaData$_Fields;".clone:()Ljava/lang/Object;
       6: checkcast     #3                  // class "[Lai/chronon/api/MetaData$_Fields;"
       9: areturn

  public static ai.chronon.api.MetaData$_Fields valueOf(java.lang.String);
    Code:
       0: ldc           #4                  // class ai/chronon/api/MetaData$_Fields
       2: aload_0
       3: invokestatic  #5                  // Method java/lang/Enum.valueOf:(Ljava/lang/Class;Ljava/lang/String;)Ljava/lang/Enum;
       6: checkcast     #4                  // class ai/chronon/api/MetaData$_Fields
       9: areturn

  public static ai.chronon.api.MetaData$_Fields findByThriftId(int);
    Code:
       0: iload_0
       1: tableswitch   { // 1 to 13
                     1: 68
                     2: 72
                     3: 76
                     4: 80
                     5: 84
                     6: 88
                     7: 92
                     8: 96
                     9: 100
                    10: 104
                    11: 108
                    12: 112
                    13: 116
               default: 120
          }
      68: getstatic     #6                  // Field NAME:Lai/chronon/api/MetaData$_Fields;
      71: areturn
      72: getstatic     #7                  // Field ONLINE:Lai/chronon/api/MetaData$_Fields;
      75: areturn
      76: getstatic     #8                  // Field PRODUCTION:Lai/chronon/api/MetaData$_Fields;
      79: areturn
      80: getstatic     #9                  // Field CUSTOM_JSON:Lai/chronon/api/MetaData$_Fields;
      83: areturn
      84: getstatic     #10                 // Field DEPENDENCIES:Lai/chronon/api/MetaData$_Fields;
      87: areturn
      88: getstatic     #11                 // Field TABLE_PROPERTIES:Lai/chronon/api/MetaData$_Fields;
      91: areturn
      92: getstatic     #12                 // Field OUTPUT_NAMESPACE:Lai/chronon/api/MetaData$_Fields;
      95: areturn
      96: getstatic     #13                 // Field TEAM:Lai/chronon/api/MetaData$_Fields;
      99: areturn
     100: getstatic     #14                 // Field MODE_TO_ENV_MAP:Lai/chronon/api/MetaData$_Fields;
     103: areturn
     104: getstatic     #15                 // Field CONSISTENCY_CHECK:Lai/chronon/api/MetaData$_Fields;
     107: areturn
     108: getstatic     #16                 // Field SAMPLE_PERCENT:Lai/chronon/api/MetaData$_Fields;
     111: areturn
     112: getstatic     #17                 // Field OFFLINE_SCHEDULE:Lai/chronon/api/MetaData$_Fields;
     115: areturn
     116: getstatic     #18                 // Field CONSISTENCY_SAMPLE_PERCENT:Lai/chronon/api/MetaData$_Fields;
     119: areturn
     120: aconst_null
     121: areturn

  public static ai.chronon.api.MetaData$_Fields findByThriftIdOrThrow(int);
    Code:
       0: iload_0
       1: invokestatic  #19                 // Method findByThriftId:(I)Lai/chronon/api/MetaData$_Fields;
       4: astore_1
       5: aload_1
       6: ifnonnull     41
       9: new           #20                 // class java/lang/IllegalArgumentException
      12: dup
      13: new           #21                 // class java/lang/StringBuilder
      16: dup
      17: invokespecial #22                 // Method java/lang/StringBuilder."<init>":()V
      20: ldc           #23                 // String Field
      22: invokevirtual #24                 // Method java/lang/StringBuilder.append:(Ljava/lang/String;)Ljava/lang/StringBuilder;
      25: iload_0
      26: invokevirtual #25                 // Method java/lang/StringBuilder.append:(I)Ljava/lang/StringBuilder;
      29: ldc           #26                 // String  doesn\'t exist!
      31: invokevirtual #24                 // Method java/lang/StringBuilder.append:(Ljava/lang/String;)Ljava/lang/StringBuilder;
      34: invokevirtual #27                 // Method java/lang/StringBuilder.toString:()Ljava/lang/String;
      37: invokespecial #28                 // Method java/lang/IllegalArgumentException."<init>":(Ljava/lang/String;)V
      40: athrow
      41: aload_1
      42: areturn

  public static ai.chronon.api.MetaData$_Fields findByName(java.lang.String);
    Code:
       0: getstatic     #29                 // Field byName:Ljava/util/Map;
       3: aload_0
       4: invokeinterface #30,  2           // InterfaceMethod java/util/Map.get:(Ljava/lang/Object;)Ljava/lang/Object;
       9: checkcast     #4                  // class ai/chronon/api/MetaData$_Fields
      12: areturn

  private ai.chronon.api.MetaData$_Fields(short, java.lang.String);
    Code:
       0: aload_0
       1: aload_1
       2: iload_2
       3: invokespecial #31                 // Method java/lang/Enum."<init>":(Ljava/lang/String;I)V
       6: aload_0
       7: iload_3
       8: putfield      #32                 // Field _thriftId:S
      11: aload_0
      12: aload         4
      14: putfield      #33                 // Field _fieldName:Ljava/lang/String;
      17: return

  public short getThriftFieldId();
    Code:
       0: aload_0
       1: getfield      #32                 // Field _thriftId:S
       4: ireturn

  public java.lang.String getFieldName();
    Code:
       0: aload_0
       1: getfield      #33                 // Field _fieldName:Ljava/lang/String;
       4: areturn

  static {};
    Code:
       0: new           #4                  // class ai/chronon/api/MetaData$_Fields
       3: dup
       4: ldc           #34                 // String NAME
       6: iconst_0
       7: iconst_1
       8: ldc           #35                 // String name
      10: invokespecial #36                 // Method "<init>":(Ljava/lang/String;ISLjava/lang/String;)V
      13: putstatic     #6                  // Field NAME:Lai/chronon/api/MetaData$_Fields;
      16: new           #4                  // class ai/chronon/api/MetaData$_Fields
      19: dup
      20: ldc           #37                 // String ONLINE
      22: iconst_1
      23: iconst_2
      24: ldc           #38                 // String online
      26: invokespecial #36                 // Method "<init>":(Ljava/lang/String;ISLjava/lang/String;)V
      29: putstatic     #7                  // Field ONLINE:Lai/chronon/api/MetaData$_Fields;
      32: new           #4                  // class ai/chronon/api/MetaData$_Fields
      35: dup
      36: ldc           #39                 // String PRODUCTION
      38: iconst_2
      39: iconst_3
      40: ldc           #40                 // String production
      42: invokespecial #36                 // Method "<init>":(Ljava/lang/String;ISLjava/lang/String;)V
      45: putstatic     #8                  // Field PRODUCTION:Lai/chronon/api/MetaData$_Fields;
      48: new           #4                  // class ai/chronon/api/MetaData$_Fields
      51: dup
      52: ldc           #41                 // String CUSTOM_JSON
      54: iconst_3
      55: iconst_4
      56: ldc           #42                 // String customJson
      58: invokespecial #36                 // Method "<init>":(Ljava/lang/String;ISLjava/lang/String;)V
      61: putstatic     #9                  // Field CUSTOM_JSON:Lai/chronon/api/MetaData$_Fields;
      64: new           #4                  // class ai/chronon/api/MetaData$_Fields
      67: dup
      68: ldc           #43                 // String DEPENDENCIES
      70: iconst_4
      71: iconst_5
      72: ldc           #44                 // String dependencies
      74: invokespecial #36                 // Method "<init>":(Ljava/lang/String;ISLjava/lang/String;)V
      77: putstatic     #10                 // Field DEPENDENCIES:Lai/chronon/api/MetaData$_Fields;
      80: new           #4                  // class ai/chronon/api/MetaData$_Fields
      83: dup
      84: ldc           #45                 // String TABLE_PROPERTIES
      86: iconst_5
      87: bipush        6
      89: ldc           #46                 // String tableProperties
      91: invokespecial #36                 // Method "<init>":(Ljava/lang/String;ISLjava/lang/String;)V
      94: putstatic     #11                 // Field TABLE_PROPERTIES:Lai/chronon/api/MetaData$_Fields;
      97: new           #4                  // class ai/chronon/api/MetaData$_Fields
     100: dup
     101: ldc           #47                 // String OUTPUT_NAMESPACE
     103: bipush        6
     105: bipush        7
     107: ldc           #48                 // String outputNamespace
     109: invokespecial #36                 // Method "<init>":(Ljava/lang/String;ISLjava/lang/String;)V
     112: putstatic     #12                 // Field OUTPUT_NAMESPACE:Lai/chronon/api/MetaData$_Fields;
     115: new           #4                  // class ai/chronon/api/MetaData$_Fields
     118: dup
     119: ldc           #49                 // String TEAM
     121: bipush        7
     123: bipush        8
     125: ldc           #50                 // String team
     127: invokespecial #36                 // Method "<init>":(Ljava/lang/String;ISLjava/lang/String;)V
     130: putstatic     #13                 // Field TEAM:Lai/chronon/api/MetaData$_Fields;
     133: new           #4                  // class ai/chronon/api/MetaData$_Fields
     136: dup
     137: ldc           #51                 // String MODE_TO_ENV_MAP
     139: bipush        8
     141: bipush        9
     143: ldc           #52                 // String modeToEnvMap
     145: invokespecial #36                 // Method "<init>":(Ljava/lang/String;ISLjava/lang/String;)V
     148: putstatic     #14                 // Field MODE_TO_ENV_MAP:Lai/chronon/api/MetaData$_Fields;
     151: new           #4                  // class ai/chronon/api/MetaData$_Fields
     154: dup
     155: ldc           #53                 // String CONSISTENCY_CHECK
     157: bipush        9
     159: bipush        10
     161: ldc           #54                 // String consistencyCheck
     163: invokespecial #36                 // Method "<init>":(Ljava/lang/String;ISLjava/lang/String;)V
     166: putstatic     #15                 // Field CONSISTENCY_CHECK:Lai/chronon/api/MetaData$_Fields;
     169: new           #4                  // class ai/chronon/api/MetaData$_Fields
     172: dup
     173: ldc           #55                 // String SAMPLE_PERCENT
     175: bipush        10
     177: bipush        11
     179: ldc           #56                 // String samplePercent
     181: invokespecial #36                 // Method "<init>":(Ljava/lang/String;ISLjava/lang/String;)V
     184: putstatic     #16                 // Field SAMPLE_PERCENT:Lai/chronon/api/MetaData$_Fields;
     187: new           #4                  // class ai/chronon/api/MetaData$_Fields
     190: dup
     191: ldc           #57                 // String OFFLINE_SCHEDULE
     193: bipush        11
     195: bipush        12
     197: ldc           #58                 // String offlineSchedule
     199: invokespecial #36                 // Method "<init>":(Ljava/lang/String;ISLjava/lang/String;)V
     202: putstatic     #17                 // Field OFFLINE_SCHEDULE:Lai/chronon/api/MetaData$_Fields;
     205: new           #4                  // class ai/chronon/api/MetaData$_Fields
     208: dup
     209: ldc           #59                 // String CONSISTENCY_SAMPLE_PERCENT
     211: bipush        12
     213: bipush        13
     215: ldc           #60                 // String consistencySamplePercent
     217: invokespecial #36                 // Method "<init>":(Ljava/lang/String;ISLjava/lang/String;)V
     220: putstatic     #18                 // Field CONSISTENCY_SAMPLE_PERCENT:Lai/chronon/api/MetaData$_Fields;
     223: bipush        13
     225: anewarray     #4                  // class ai/chronon/api/MetaData$_Fields
     228: dup
     229: iconst_0
     230: getstatic     #6                  // Field NAME:Lai/chronon/api/MetaData$_Fields;
     233: aastore
     234: dup
     235: iconst_1
     236: getstatic     #7                  // Field ONLINE:Lai/chronon/api/MetaData$_Fields;
     239: aastore
     240: dup
     241: iconst_2
     242: getstatic     #8                  // Field PRODUCTION:Lai/chronon/api/MetaData$_Fields;
     245: aastore
     246: dup
     247: iconst_3
     248: getstatic     #9                  // Field CUSTOM_JSON:Lai/chronon/api/MetaData$_Fields;
     251: aastore
     252: dup
     253: iconst_4
     254: getstatic     #10                 // Field DEPENDENCIES:Lai/chronon/api/MetaData$_Fields;
     257: aastore
     258: dup
     259: iconst_5
     260: getstatic     #11                 // Field TABLE_PROPERTIES:Lai/chronon/api/MetaData$_Fields;
     263: aastore
     264: dup
     265: bipush        6
     267: getstatic     #12                 // Field OUTPUT_NAMESPACE:Lai/chronon/api/MetaData$_Fields;
     270: aastore
     271: dup
     272: bipush        7
     274: getstatic     #13                 // Field TEAM:Lai/chronon/api/MetaData$_Fields;
     277: aastore
     278: dup
     279: bipush        8
     281: getstatic     #14                 // Field MODE_TO_ENV_MAP:Lai/chronon/api/MetaData$_Fields;
     284: aastore
     285: dup
     286: bipush        9
     288: getstatic     #15                 // Field CONSISTENCY_CHECK:Lai/chronon/api/MetaData$_Fields;
     291: aastore
     292: dup
     293: bipush        10
     295: getstatic     #16                 // Field SAMPLE_PERCENT:Lai/chronon/api/MetaData$_Fields;
     298: aastore
     299: dup
     300: bipush        11
     302: getstatic     #17                 // Field OFFLINE_SCHEDULE:Lai/chronon/api/MetaData$_Fields;
     305: aastore
     306: dup
     307: bipush        12
     309: getstatic     #18                 // Field CONSISTENCY_SAMPLE_PERCENT:Lai/chronon/api/MetaData$_Fields;
     312: aastore
     313: putstatic     #1                  // Field $VALUES:[Lai/chronon/api/MetaData$_Fields;
     316: new           #61                 // class java/util/HashMap
     319: dup
     320: invokespecial #62                 // Method java/util/HashMap."<init>":()V
     323: putstatic     #29                 // Field byName:Ljava/util/Map;
     326: ldc           #4                  // class ai/chronon/api/MetaData$_Fields
     328: invokestatic  #63                 // Method java/util/EnumSet.allOf:(Ljava/lang/Class;)Ljava/util/EnumSet;
     331: invokevirtual #64                 // Method java/util/EnumSet.iterator:()Ljava/util/Iterator;
     334: astore_0
     335: aload_0
     336: invokeinterface #65,  1           // InterfaceMethod java/util/Iterator.hasNext:()Z
     341: ifeq          371
     344: aload_0
     345: invokeinterface #66,  1           // InterfaceMethod java/util/Iterator.next:()Ljava/lang/Object;
     350: checkcast     #4                  // class ai/chronon/api/MetaData$_Fields
     353: astore_1
     354: getstatic     #29                 // Field byName:Ljava/util/Map;
     357: aload_1
     358: invokevirtual #67                 // Method getFieldName:()Ljava/lang/String;
     361: aload_1
     362: invokeinterface #68,  3           // InterfaceMethod java/util/Map.put:(Ljava/lang/Object;Ljava/lang/Object;)Ljava/lang/Object;
     367: pop
     368: goto          335
     371: return
}
