Compiled from "Row.scala"
public interface ai.chronon.api.Row {
  public static <StructType, BinaryType, ListType, MapType> scala.Function1<java.lang.Object, java.lang.Object[]> to$default$7();
    Code:
       0: getstatic     #22                 // Field ai/chronon/api/Row$.MODULE$:Lai/chronon/api/Row$;
       3: invokevirtual #24                 // Method ai/chronon/api/Row$.to$default$7:()Lscala/Function1;
       6: areturn

  public static <StructType, BinaryType, ListType, MapType> java.lang.Object to(java.lang.Object, ai.chronon.api.DataType, scala.Function2<scala.collection.Iterator<java.lang.Object>, ai.chronon.api.DataType, StructType>, scala.Function1<byte[], BinaryType>, scala.Function2<scala.collection.Iterator<java.lang.Object>, java.lang.Object, ListType>, scala.Function1<java.util.Map<java.lang.Object, java.lang.Object>, MapType>, scala.Function1<java.lang.Object, java.lang.Object[]>);
    Code:
       0: getstatic     #22                 // Field ai/chronon/api/Row$.MODULE$:Lai/chronon/api/Row$;
       3: aload_0
       4: aload_1
       5: aload_2
       6: aload_3
       7: aload         4
       9: aload         5
      11: aload         6
      13: invokevirtual #36                 // Method ai/chronon/api/Row$.to:(Ljava/lang/Object;Lai/chronon/api/DataType;Lscala/Function2;Lscala/Function1;Lscala/Function2;Lscala/Function1;Lscala/Function1;)Ljava/lang/Object;
      16: areturn

  public static <CompositeType, BinaryType, ArrayType, StringType> java.lang.Object from(java.lang.Object, ai.chronon.api.DataType, scala.Function2<CompositeType, scala.collection.immutable.Seq<ai.chronon.api.StructField>, scala.collection.Iterator<java.lang.Object>>, scala.Function1<BinaryType, byte[]>, scala.Function1<ArrayType, java.util.ArrayList<java.lang.Object>>, scala.Function1<StringType, java.lang.String>);
    Code:
       0: getstatic     #22                 // Field ai/chronon/api/Row$.MODULE$:Lai/chronon/api/Row$;
       3: aload_0
       4: aload_1
       5: aload_2
       6: aload_3
       7: aload         4
       9: aload         5
      11: invokevirtual #49                 // Method ai/chronon/api/Row$.from:(Ljava/lang/Object;Lai/chronon/api/DataType;Lscala/Function2;Lscala/Function1;Lscala/Function1;Lscala/Function1;)Ljava/lang/Object;
      14: areturn

  public abstract java.lang.Object get(int);

  public abstract long ts();

  public abstract int length();

  public abstract boolean isBefore();

  public abstract long mutationTs();

  public static java.lang.Object getAs$(ai.chronon.api.Row, int);
    Code:
       0: aload_0
       1: iload_1
       2: invokespecial #65                 // InterfaceMethod getAs:(I)Ljava/lang/Object;
       5: areturn

  public default <T> T getAs(int);
    Code:
       0: aload_0
       1: iload_1
       2: invokeinterface #70,  2           // InterfaceMethod get:(I)Ljava/lang/Object;
       7: areturn

  public static java.lang.Object[] values$(ai.chronon.api.Row);
    Code:
       0: aload_0
       1: invokespecial #77                 // InterfaceMethod values:()[Ljava/lang/Object;
       4: areturn

  public default java.lang.Object[] values();
    Code:
       0: getstatic     #82                 // Field scala/runtime/RichInt$.MODULE$:Lscala/runtime/RichInt$;
       3: getstatic     #87                 // Field scala/Predef$.MODULE$:Lscala/Predef$;
       6: iconst_0
       7: invokevirtual #91                 // Method scala/Predef$.intWrapper:(I)I
      10: aload_0
      11: invokeinterface #93,  1           // InterfaceMethod length:()I
      16: invokevirtual #97                 // Method scala/runtime/RichInt$.until$extension:(II)Lscala/collection/immutable/Range;
      19: aload_0
      20: invokedynamic #116,  0            // InvokeDynamic #0:apply:(Lai/chronon/api/Row;)Lscala/Function1;
      25: invokevirtual #122                // Method scala/collection/immutable/Range.map:(Lscala/Function1;)Lscala/collection/immutable/IndexedSeq;
      28: getstatic     #127                // Field scala/reflect/ClassTag$.MODULE$:Lscala/reflect/ClassTag$;
      31: invokevirtual #131                // Method scala/reflect/ClassTag$.Any:()Lscala/reflect/ClassTag;
      34: invokeinterface #137,  2          // InterfaceMethod scala/collection/immutable/IndexedSeq.toArray:(Lscala/reflect/ClassTag;)Ljava/lang/Object;
      39: checkcast     #139                // class "[Ljava/lang/Object;"
      42: areturn

  public static java.lang.String toString$(ai.chronon.api.Row);
    Code:
       0: aload_0
       1: invokespecial #145                // InterfaceMethod toString:()Ljava/lang/String;
       4: areturn

  public default java.lang.String toString();
    Code:
       0: new           #147                // class java/lang/StringBuilder
       3: dup
       4: ldc           #148                // int 2
       6: invokespecial #152                // Method java/lang/StringBuilder."<init>":(I)V
       9: ldc           #154                // String [
      11: invokevirtual #158                // Method java/lang/StringBuilder.append:(Ljava/lang/String;)Ljava/lang/StringBuilder;
      14: getstatic     #87                 // Field scala/Predef$.MODULE$:Lscala/Predef$;
      17: aload_0
      18: invokeinterface #77,  1           // InterfaceMethod values:()[Ljava/lang/Object;
      23: invokevirtual #162                // Method scala/Predef$.genericWrapArray:(Ljava/lang/Object;)Lscala/collection/mutable/ArraySeq;
      26: ldc           #164                // String ,
      28: invokevirtual #170                // Method scala/collection/mutable/ArraySeq.mkString:(Ljava/lang/String;)Ljava/lang/String;
      31: invokevirtual #158                // Method java/lang/StringBuilder.append:(Ljava/lang/String;)Ljava/lang/StringBuilder;
      34: ldc           #172                // String ]
      36: invokevirtual #158                // Method java/lang/StringBuilder.append:(Ljava/lang/String;)Ljava/lang/StringBuilder;
      39: invokevirtual #173                // Method java/lang/StringBuilder.toString:()Ljava/lang/String;
      42: areturn

  public static java.lang.Object $anonfun$values$1(ai.chronon.api.Row, int);
    Code:
       0: aload_0
       1: iload_1
       2: invokeinterface #70,  2           // InterfaceMethod get:(I)Ljava/lang/Object;
       7: areturn

  public static void $init$(ai.chronon.api.Row);
    Code:
       0: return

  public static java.lang.Object $anonfun$values$1$adapted(ai.chronon.api.Row, java.lang.Object);
    Code:
       0: aload_0
       1: aload_1
       2: invokestatic  #182                // Method scala/runtime/BoxesRunTime.unboxToInt:(Ljava/lang/Object;)I
       5: invokestatic  #184                // InterfaceMethod $anonfun$values$1:(Lai/chronon/api/Row;I)Ljava/lang/Object;
       8: areturn

  private static java.lang.Object $deserializeLambda$(java.lang.invoke.SerializedLambda);
    Code:
       0: aload_0
       1: invokedynamic #196,  0            // InvokeDynamic #1:lambdaDeserialize:(Ljava/lang/invoke/SerializedLambda;)Ljava/lang/Object;
       6: areturn
}
