Compiled from "DependencyResult.java"
public class org.sonatype.aether.resolution.DependencyResult {
  private final org.sonatype.aether.resolution.DependencyRequest request;

  private org.sonatype.aether.graph.DependencyNode root;

  private java.util.List<java.lang.Exception> collectExceptions;

  private java.util.List<org.sonatype.aether.resolution.ArtifactResult> artifactResults;

  public org.sonatype.aether.resolution.DependencyResult(org.sonatype.aether.resolution.DependencyRequest);
    Code:
       0: aload_0
       1: invokespecial #1                  // Method java/lang/Object."<init>":()V
       4: aload_1
       5: ifnonnull     18
       8: new           #2                  // class java/lang/IllegalArgumentException
      11: dup
      12: ldc           #3                  // String dependency request has not been specified
      14: invokespecial #4                  // Method java/lang/IllegalArgumentException."<init>":(Ljava/lang/String;)V
      17: athrow
      18: aload_0
      19: aload_1
      20: putfield      #5                  // Field request:Lorg/sonatype/aether/resolution/DependencyRequest;
      23: aload_0
      24: aload_1
      25: invokevirtual #6                  // Method org/sonatype/aether/resolution/DependencyRequest.getRoot:()Lorg/sonatype/aether/graph/DependencyNode;
      28: putfield      #7                  // Field root:Lorg/sonatype/aether/graph/DependencyNode;
      31: aload_0
      32: new           #8                  // class java/util/ArrayList
      35: dup
      36: iconst_2
      37: invokespecial #9                  // Method java/util/ArrayList."<init>":(I)V
      40: putfield      #10                 // Field collectExceptions:Ljava/util/List;
      43: aload_0
      44: new           #8                  // class java/util/ArrayList
      47: dup
      48: iconst_2
      49: invokespecial #9                  // Method java/util/ArrayList."<init>":(I)V
      52: putfield      #11                 // Field artifactResults:Ljava/util/List;
      55: return

  public org.sonatype.aether.resolution.DependencyRequest getRequest();
    Code:
       0: aload_0
       1: getfield      #5                  // Field request:Lorg/sonatype/aether/resolution/DependencyRequest;
       4: areturn

  public org.sonatype.aether.graph.DependencyNode getRoot();
    Code:
       0: aload_0
       1: getfield      #7                  // Field root:Lorg/sonatype/aether/graph/DependencyNode;
       4: areturn

  public org.sonatype.aether.resolution.DependencyResult setRoot(org.sonatype.aether.graph.DependencyNode);
    Code:
       0: aload_0
       1: aload_1
       2: putfield      #7                  // Field root:Lorg/sonatype/aether/graph/DependencyNode;
       5: aload_0
       6: areturn

  public java.util.List<java.lang.Exception> getCollectExceptions();
    Code:
       0: aload_0
       1: getfield      #10                 // Field collectExceptions:Ljava/util/List;
       4: areturn

  public org.sonatype.aether.resolution.DependencyResult setCollectExceptions(java.util.List<java.lang.Exception>);
    Code:
       0: aload_0
       1: aload_1
       2: ifnull        9
       5: aload_1
       6: goto          16
       9: new           #8                  // class java/util/ArrayList
      12: dup
      13: invokespecial #12                 // Method java/util/ArrayList."<init>":()V
      16: putfield      #10                 // Field collectExceptions:Ljava/util/List;
      19: aload_0
      20: areturn

  public java.util.List<org.sonatype.aether.resolution.ArtifactResult> getArtifactResults();
    Code:
       0: aload_0
       1: getfield      #11                 // Field artifactResults:Ljava/util/List;
       4: areturn

  public org.sonatype.aether.resolution.DependencyResult setArtifactResults(java.util.List<org.sonatype.aether.resolution.ArtifactResult>);
    Code:
       0: aload_0
       1: aload_1
       2: ifnull        9
       5: aload_1
       6: goto          16
       9: new           #8                  // class java/util/ArrayList
      12: dup
      13: invokespecial #12                 // Method java/util/ArrayList."<init>":()V
      16: putfield      #11                 // Field artifactResults:Ljava/util/List;
      19: aload_0
      20: areturn

  public java.lang.String toString();
    Code:
       0: aload_0
       1: getfield      #11                 // Field artifactResults:Ljava/util/List;
       4: invokestatic  #13                 // Method java/lang/String.valueOf:(Ljava/lang/Object;)Ljava/lang/String;
       7: areturn
}
