Compiled from "ThreadLocalBufferManager.java"
final class io.dekorate.deps.jackson.core.util.ThreadLocalBufferManager$ThreadLocalBufferManagerHolder {
  static final io.dekorate.deps.jackson.core.util.ThreadLocalBufferManager manager;

  private io.dekorate.deps.jackson.core.util.ThreadLocalBufferManager$ThreadLocalBufferManagerHolder();
    Code:
       0: aload_0
       1: invokespecial #14                 // Method java/lang/Object."<init>":()V
       4: return

  static {};
    Code:
       0: new           #7                  // class io/dekorate/deps/jackson/core/util/ThreadLocalBufferManager
       3: dup
       4: invokespecial #18                 // Method io/dekorate/deps/jackson/core/util/ThreadLocalBufferManager."<init>":()V
       7: putstatic     #20                 // Field manager:Lio/dekorate/deps/jackson/core/util/ThreadLocalBufferManager;
      10: return
}
