Compiled from "AbstractRecursiveAnnotationVisitor.java"
abstract class org.springframework.core.type.classreading.AbstractRecursiveAnnotationVisitor extends org.springframework.asm.AnnotationVisitor {
  protected final org.apache.commons.logging.Log logger;

  protected final org.springframework.core.annotation.AnnotationAttributes attributes;

  protected final java.lang.ClassLoader classLoader;

  public org.springframework.core.type.classreading.AbstractRecursiveAnnotationVisitor(java.lang.ClassLoader, org.springframework.core.annotation.AnnotationAttributes);
    Code:
       0: aload_0
       1: ldc           #2                  // int 17301504
       3: invokespecial #3                  // Method org/springframework/asm/AnnotationVisitor."<init>":(I)V
       6: aload_0
       7: aload_0
       8: invokevirtual #4                  // Method java/lang/Object.getClass:()Ljava/lang/Class;
      11: invokestatic  #5                  // Method org/apache/commons/logging/LogFactory.getLog:(Ljava/lang/Class;)Lorg/apache/commons/logging/Log;
      14: putfield      #6                  // Field logger:Lorg/apache/commons/logging/Log;
      17: aload_0
      18: aload_1
      19: putfield      #7                  // Field classLoader:Ljava/lang/ClassLoader;
      22: aload_0
      23: aload_2
      24: putfield      #8                  // Field attributes:Lorg/springframework/core/annotation/AnnotationAttributes;
      27: return

  public void visit(java.lang.String, java.lang.Object);
    Code:
       0: aload_0
       1: getfield      #8                  // Field attributes:Lorg/springframework/core/annotation/AnnotationAttributes;
       4: aload_1
       5: aload_2
       6: invokevirtual #9                  // Method org/springframework/core/annotation/AnnotationAttributes.put:(Ljava/lang/Object;Ljava/lang/Object;)Ljava/lang/Object;
       9: pop
      10: return

  public org.springframework.asm.AnnotationVisitor visitAnnotation(java.lang.String, java.lang.String);
    Code:
       0: aload_2
       1: invokestatic  #10                 // Method org/springframework/asm/Type.getType:(Ljava/lang/String;)Lorg/springframework/asm/Type;
       4: invokevirtual #11                 // Method org/springframework/asm/Type.getClassName:()Ljava/lang/String;
       7: astore_3
       8: new           #12                 // class org/springframework/core/annotation/AnnotationAttributes
      11: dup
      12: aload_3
      13: aload_0
      14: getfield      #7                  // Field classLoader:Ljava/lang/ClassLoader;
      17: invokespecial #13                 // Method org/springframework/core/annotation/AnnotationAttributes."<init>":(Ljava/lang/String;Ljava/lang/ClassLoader;)V
      20: astore        4
      22: aload_0
      23: getfield      #8                  // Field attributes:Lorg/springframework/core/annotation/AnnotationAttributes;
      26: aload_1
      27: aload         4
      29: invokevirtual #9                  // Method org/springframework/core/annotation/AnnotationAttributes.put:(Ljava/lang/Object;Ljava/lang/Object;)Ljava/lang/Object;
      32: pop
      33: new           #14                 // class org/springframework/core/type/classreading/RecursiveAnnotationAttributesVisitor
      36: dup
      37: aload_3
      38: aload         4
      40: aload_0
      41: getfield      #7                  // Field classLoader:Ljava/lang/ClassLoader;
      44: invokespecial #15                 // Method org/springframework/core/type/classreading/RecursiveAnnotationAttributesVisitor."<init>":(Ljava/lang/String;Lorg/springframework/core/annotation/AnnotationAttributes;Ljava/lang/ClassLoader;)V
      47: areturn

  public org.springframework.asm.AnnotationVisitor visitArray(java.lang.String);
    Code:
       0: new           #16                 // class org/springframework/core/type/classreading/RecursiveAnnotationArrayVisitor
       3: dup
       4: aload_1
       5: aload_0
       6: getfield      #8                  // Field attributes:Lorg/springframework/core/annotation/AnnotationAttributes;
       9: aload_0
      10: getfield      #7                  // Field classLoader:Ljava/lang/ClassLoader;
      13: invokespecial #17                 // Method org/springframework/core/type/classreading/RecursiveAnnotationArrayVisitor."<init>":(Ljava/lang/String;Lorg/springframework/core/annotation/AnnotationAttributes;Ljava/lang/ClassLoader;)V
      16: areturn

  public void visitEnum(java.lang.String, java.lang.String, java.lang.String);
    Code:
       0: aload_0
       1: aload_2
       2: aload_3
       3: invokevirtual #18                 // Method getEnumValue:(Ljava/lang/String;Ljava/lang/String;)Ljava/lang/Object;
       6: astore        4
       8: aload_0
       9: aload_1
      10: aload         4
      12: invokevirtual #19                 // Method visit:(Ljava/lang/String;Ljava/lang/Object;)V
      15: return

  protected java.lang.Object getEnumValue(java.lang.String, java.lang.String);
    Code:
       0: aload_2
       1: astore_3
       2: aload_1
       3: invokestatic  #10                 // Method org/springframework/asm/Type.getType:(Ljava/lang/String;)Lorg/springframework/asm/Type;
       6: invokevirtual #11                 // Method org/springframework/asm/Type.getClassName:()Ljava/lang/String;
       9: aload_0
      10: getfield      #7                  // Field classLoader:Ljava/lang/ClassLoader;
      13: invokestatic  #20                 // Method org/springframework/util/ClassUtils.forName:(Ljava/lang/String;Ljava/lang/ClassLoader;)Ljava/lang/Class;
      16: astore        4
      18: aload         4
      20: aload_2
      21: invokestatic  #21                 // Method org/springframework/util/ReflectionUtils.findField:(Ljava/lang/Class;Ljava/lang/String;)Ljava/lang/reflect/Field;
      24: astore        5
      26: aload         5
      28: ifnull        43
      31: aload         5
      33: invokestatic  #22                 // Method org/springframework/util/ReflectionUtils.makeAccessible:(Ljava/lang/reflect/Field;)V
      36: aload         5
      38: aconst_null
      39: invokevirtual #23                 // Method java/lang/reflect/Field.get:(Ljava/lang/Object;)Ljava/lang/Object;
      42: astore_3
      43: goto          79
      46: astore        4
      48: aload_0
      49: getfield      #6                  // Field logger:Lorg/apache/commons/logging/Log;
      52: ldc           #26                 // String Failed to classload enum type while reading annotation metadata
      54: aload         4
      56: invokeinterface #27,  3           // InterfaceMethod org/apache/commons/logging/Log.debug:(Ljava/lang/Object;Ljava/lang/Throwable;)V
      61: goto          79
      64: astore        4
      66: aload_0
      67: getfield      #6                  // Field logger:Lorg/apache/commons/logging/Log;
      70: ldc           #30                 // String Could not access enum value while reading annotation metadata
      72: aload         4
      74: invokeinterface #27,  3           // InterfaceMethod org/apache/commons/logging/Log.debug:(Ljava/lang/Object;Ljava/lang/Throwable;)V
      79: aload_3
      80: areturn
    Exception table:
       from    to  target type
           2    43    46   Class java/lang/ClassNotFoundException
           2    43    46   Class java/lang/NoClassDefFoundError
           2    43    64   Class java/lang/IllegalAccessException
           2    43    64   Class java/security/AccessControlException
}
