Compiled from "SimpleMethodMetadata.java"
final class org.springframework.core.type.classreading.SimpleMethodMetadata implements org.springframework.core.type.MethodMetadata {
  private final java.lang.String methodName;

  private final int access;

  private final java.lang.String declaringClassName;

  private final java.lang.String returnTypeName;

  private final org.springframework.core.annotation.MergedAnnotations annotations;

  public org.springframework.core.type.classreading.SimpleMethodMetadata(java.lang.String, int, java.lang.String, java.lang.String, org.springframework.core.annotation.MergedAnnotations);
    Code:
       0: aload_0
       1: invokespecial #1                  // Method java/lang/Object."<init>":()V
       4: aload_0
       5: aload_1
       6: putfield      #2                  // Field methodName:Ljava/lang/String;
       9: aload_0
      10: iload_2
      11: putfield      #3                  // Field access:I
      14: aload_0
      15: aload_3
      16: putfield      #4                  // Field declaringClassName:Ljava/lang/String;
      19: aload_0
      20: aload         4
      22: putfield      #5                  // Field returnTypeName:Ljava/lang/String;
      25: aload_0
      26: aload         5
      28: putfield      #6                  // Field annotations:Lorg/springframework/core/annotation/MergedAnnotations;
      31: return

  public java.lang.String getMethodName();
    Code:
       0: aload_0
       1: getfield      #2                  // Field methodName:Ljava/lang/String;
       4: areturn

  public java.lang.String getDeclaringClassName();
    Code:
       0: aload_0
       1: getfield      #4                  // Field declaringClassName:Ljava/lang/String;
       4: areturn

  public java.lang.String getReturnTypeName();
    Code:
       0: aload_0
       1: getfield      #5                  // Field returnTypeName:Ljava/lang/String;
       4: areturn

  public boolean isAbstract();
    Code:
       0: aload_0
       1: getfield      #3                  // Field access:I
       4: sipush        1024
       7: iand
       8: ifeq          15
      11: iconst_1
      12: goto          16
      15: iconst_0
      16: ireturn

  public boolean isStatic();
    Code:
       0: aload_0
       1: getfield      #3                  // Field access:I
       4: bipush        8
       6: iand
       7: ifeq          14
      10: iconst_1
      11: goto          15
      14: iconst_0
      15: ireturn

  public boolean isFinal();
    Code:
       0: aload_0
       1: getfield      #3                  // Field access:I
       4: bipush        16
       6: iand
       7: ifeq          14
      10: iconst_1
      11: goto          15
      14: iconst_0
      15: ireturn

  public boolean isOverridable();
    Code:
       0: aload_0
       1: invokevirtual #8                  // Method isStatic:()Z
       4: ifne          25
       7: aload_0
       8: invokevirtual #9                  // Method isFinal:()Z
      11: ifne          25
      14: aload_0
      15: invokevirtual #10                 // Method isPrivate:()Z
      18: ifne          25
      21: iconst_1
      22: goto          26
      25: iconst_0
      26: ireturn

  public boolean isPrivate();
    Code:
       0: aload_0
       1: getfield      #3                  // Field access:I
       4: iconst_2
       5: iand
       6: ifeq          13
       9: iconst_1
      10: goto          14
      13: iconst_0
      14: ireturn

  public org.springframework.core.annotation.MergedAnnotations getAnnotations();
    Code:
       0: aload_0
       1: getfield      #6                  // Field annotations:Lorg/springframework/core/annotation/MergedAnnotations;
       4: areturn
}
