Compiled from "NoGCObjectCache.java"
public abstract class com.mchange.util.impl.NoGCObjectCache implements com.mchange.util.ObjectCache {
  java.util.Hashtable store;

  public com.mchange.util.impl.NoGCObjectCache();
    Code:
       0: aload_0
       1: invokespecial #1                  // Method java/lang/Object."<init>":()V
       4: aload_0
       5: new           #2                  // class java/util/Hashtable
       8: dup
       9: invokespecial #3                  // Method java/util/Hashtable."<init>":()V
      12: putfield      #4                  // Field store:Ljava/util/Hashtable;
      15: return

  public java.lang.Object find(java.lang.Object) throws java.lang.Exception;
    Code:
       0: aload_0
       1: getfield      #4                  // Field store:Ljava/util/Hashtable;
       4: aload_1
       5: invokevirtual #5                  // Method java/util/Hashtable.get:(Ljava/lang/Object;)Ljava/lang/Object;
       8: astore_2
       9: aload_2
      10: ifnull        22
      13: aload_0
      14: aload_1
      15: aload_2
      16: invokevirtual #6                  // Method isDirty:(Ljava/lang/Object;Ljava/lang/Object;)Z
      19: ifeq          38
      22: aload_0
      23: aload_1
      24: invokevirtual #7                  // Method createFromKey:(Ljava/lang/Object;)Ljava/lang/Object;
      27: astore_2
      28: aload_0
      29: getfield      #4                  // Field store:Ljava/util/Hashtable;
      32: aload_1
      33: aload_2
      34: invokevirtual #8                  // Method java/util/Hashtable.put:(Ljava/lang/Object;Ljava/lang/Object;)Ljava/lang/Object;
      37: pop
      38: aload_2
      39: areturn

  protected boolean isDirty(java.lang.Object, java.lang.Object);
    Code:
       0: iconst_0
       1: ireturn

  protected abstract java.lang.Object createFromKey(java.lang.Object) throws java.lang.Exception;
}
