Compiled from "PropertiesRewritePolicy.java"
public final class org.apache.logging.log4j.core.appender.rewrite.PropertiesRewritePolicy implements org.apache.logging.log4j.core.appender.rewrite.RewritePolicy {
  protected static final org.apache.logging.log4j.Logger LOGGER;

  private final java.util.Map<org.apache.logging.log4j.core.config.Property, java.lang.Boolean> properties;

  private final org.apache.logging.log4j.core.config.Configuration config;

  private org.apache.logging.log4j.core.appender.rewrite.PropertiesRewritePolicy(org.apache.logging.log4j.core.config.Configuration, java.util.List<org.apache.logging.log4j.core.config.Property>);
    Code:
       0: aload_0
       1: invokespecial #1                  // Method java/lang/Object."<init>":()V
       4: aload_0
       5: aload_1
       6: putfield      #2                  // Field config:Lorg/apache/logging/log4j/core/config/Configuration;
       9: aload_0
      10: new           #3                  // class java/util/HashMap
      13: dup
      14: aload_2
      15: invokeinterface #4,  1            // InterfaceMethod java/util/List.size:()I
      20: invokespecial #5                  // Method java/util/HashMap."<init>":(I)V
      23: putfield      #6                  // Field properties:Ljava/util/Map;
      26: aload_2
      27: invokeinterface #7,  1            // InterfaceMethod java/util/List.iterator:()Ljava/util/Iterator;
      32: astore_3
      33: aload_3
      34: invokeinterface #8,  1            // InterfaceMethod java/util/Iterator.hasNext:()Z
      39: ifeq          85
      42: aload_3
      43: invokeinterface #9,  1            // InterfaceMethod java/util/Iterator.next:()Ljava/lang/Object;
      48: checkcast     #10                 // class org/apache/logging/log4j/core/config/Property
      51: astore        4
      53: aload         4
      55: invokevirtual #11                 // Method org/apache/logging/log4j/core/config/Property.getValue:()Ljava/lang/String;
      58: ldc           #12                 // String ${
      60: invokevirtual #13                 // Method java/lang/String.contains:(Ljava/lang/CharSequence;)Z
      63: invokestatic  #14                 // Method java/lang/Boolean.valueOf:(Z)Ljava/lang/Boolean;
      66: astore        5
      68: aload_0
      69: getfield      #6                  // Field properties:Ljava/util/Map;
      72: aload         4
      74: aload         5
      76: invokeinterface #15,  3           // InterfaceMethod java/util/Map.put:(Ljava/lang/Object;Ljava/lang/Object;)Ljava/lang/Object;
      81: pop
      82: goto          33
      85: return

  public org.apache.logging.log4j.core.LogEvent rewrite(org.apache.logging.log4j.core.LogEvent);
    Code:
       0: aload_1
       1: invokeinterface #16,  1           // InterfaceMethod org/apache/logging/log4j/core/LogEvent.getContextData:()Lorg/apache/logging/log4j/util/ReadOnlyStringMap;
       6: invokestatic  #17                 // Method org/apache/logging/log4j/core/impl/ContextDataFactory.createContextData:(Lorg/apache/logging/log4j/util/ReadOnlyStringMap;)Lorg/apache/logging/log4j/util/StringMap;
       9: astore_2
      10: aload_0
      11: getfield      #6                  // Field properties:Ljava/util/Map;
      14: invokeinterface #18,  1           // InterfaceMethod java/util/Map.entrySet:()Ljava/util/Set;
      19: invokeinterface #19,  1           // InterfaceMethod java/util/Set.iterator:()Ljava/util/Iterator;
      24: astore_3
      25: aload_3
      26: invokeinterface #8,  1            // InterfaceMethod java/util/Iterator.hasNext:()Z
      31: ifeq          112
      34: aload_3
      35: invokeinterface #9,  1            // InterfaceMethod java/util/Iterator.next:()Ljava/lang/Object;
      40: checkcast     #20                 // class java/util/Map$Entry
      43: astore        4
      45: aload         4
      47: invokeinterface #21,  1           // InterfaceMethod java/util/Map$Entry.getKey:()Ljava/lang/Object;
      52: checkcast     #10                 // class org/apache/logging/log4j/core/config/Property
      55: astore        5
      57: aload_2
      58: aload         5
      60: invokevirtual #22                 // Method org/apache/logging/log4j/core/config/Property.getName:()Ljava/lang/String;
      63: aload         4
      65: invokeinterface #23,  1           // InterfaceMethod java/util/Map$Entry.getValue:()Ljava/lang/Object;
      70: checkcast     #24                 // class java/lang/Boolean
      73: invokevirtual #25                 // Method java/lang/Boolean.booleanValue:()Z
      76: ifeq          99
      79: aload_0
      80: getfield      #2                  // Field config:Lorg/apache/logging/log4j/core/config/Configuration;
      83: invokeinterface #26,  1           // InterfaceMethod org/apache/logging/log4j/core/config/Configuration.getStrSubstitutor:()Lorg/apache/logging/log4j/core/lookup/StrSubstitutor;
      88: aload         5
      90: invokevirtual #11                 // Method org/apache/logging/log4j/core/config/Property.getValue:()Ljava/lang/String;
      93: invokevirtual #27                 // Method org/apache/logging/log4j/core/lookup/StrSubstitutor.replace:(Ljava/lang/String;)Ljava/lang/String;
      96: goto          104
      99: aload         5
     101: invokevirtual #11                 // Method org/apache/logging/log4j/core/config/Property.getValue:()Ljava/lang/String;
     104: invokeinterface #28,  3           // InterfaceMethod org/apache/logging/log4j/util/StringMap.putValue:(Ljava/lang/String;Ljava/lang/Object;)V
     109: goto          25
     112: new           #29                 // class org/apache/logging/log4j/core/impl/Log4jLogEvent$Builder
     115: dup
     116: aload_1
     117: invokespecial #30                 // Method org/apache/logging/log4j/core/impl/Log4jLogEvent$Builder."<init>":(Lorg/apache/logging/log4j/core/LogEvent;)V
     120: aload_2
     121: invokevirtual #31                 // Method org/apache/logging/log4j/core/impl/Log4jLogEvent$Builder.setContextData:(Lorg/apache/logging/log4j/util/StringMap;)Lorg/apache/logging/log4j/core/impl/Log4jLogEvent$Builder;
     124: invokevirtual #32                 // Method org/apache/logging/log4j/core/impl/Log4jLogEvent$Builder.build:()Lorg/apache/logging/log4j/core/impl/Log4jLogEvent;
     127: areturn

  public java.lang.String toString();
    Code:
       0: new           #33                 // class java/lang/StringBuilder
       3: dup
       4: invokespecial #34                 // Method java/lang/StringBuilder."<init>":()V
       7: astore_1
       8: aload_1
       9: ldc           #35                 // String  {
      11: invokevirtual #36                 // Method java/lang/StringBuilder.append:(Ljava/lang/String;)Ljava/lang/StringBuilder;
      14: pop
      15: iconst_1
      16: istore_2
      17: aload_0
      18: getfield      #6                  // Field properties:Ljava/util/Map;
      21: invokeinterface #18,  1           // InterfaceMethod java/util/Map.entrySet:()Ljava/util/Set;
      26: invokeinterface #19,  1           // InterfaceMethod java/util/Set.iterator:()Ljava/util/Iterator;
      31: astore_3
      32: aload_3
      33: invokeinterface #8,  1            // InterfaceMethod java/util/Iterator.hasNext:()Z
      38: ifeq          103
      41: aload_3
      42: invokeinterface #9,  1            // InterfaceMethod java/util/Iterator.next:()Ljava/lang/Object;
      47: checkcast     #20                 // class java/util/Map$Entry
      50: astore        4
      52: iload_2
      53: ifne          63
      56: aload_1
      57: ldc           #37                 // String ,
      59: invokevirtual #36                 // Method java/lang/StringBuilder.append:(Ljava/lang/String;)Ljava/lang/StringBuilder;
      62: pop
      63: aload         4
      65: invokeinterface #21,  1           // InterfaceMethod java/util/Map$Entry.getKey:()Ljava/lang/Object;
      70: checkcast     #10                 // class org/apache/logging/log4j/core/config/Property
      73: astore        5
      75: aload_1
      76: aload         5
      78: invokevirtual #22                 // Method org/apache/logging/log4j/core/config/Property.getName:()Ljava/lang/String;
      81: invokevirtual #36                 // Method java/lang/StringBuilder.append:(Ljava/lang/String;)Ljava/lang/StringBuilder;
      84: bipush        61
      86: invokevirtual #38                 // Method java/lang/StringBuilder.append:(C)Ljava/lang/StringBuilder;
      89: aload         5
      91: invokevirtual #11                 // Method org/apache/logging/log4j/core/config/Property.getValue:()Ljava/lang/String;
      94: invokevirtual #36                 // Method java/lang/StringBuilder.append:(Ljava/lang/String;)Ljava/lang/StringBuilder;
      97: pop
      98: iconst_0
      99: istore_2
     100: goto          32
     103: aload_1
     104: bipush        125
     106: invokevirtual #38                 // Method java/lang/StringBuilder.append:(C)Ljava/lang/StringBuilder;
     109: pop
     110: aload_1
     111: invokevirtual #39                 // Method java/lang/StringBuilder.toString:()Ljava/lang/String;
     114: areturn

  public static org.apache.logging.log4j.core.appender.rewrite.PropertiesRewritePolicy createPolicy(org.apache.logging.log4j.core.config.Configuration, org.apache.logging.log4j.core.config.Property[]);
    Code:
       0: aload_1
       1: ifnull        9
       4: aload_1
       5: arraylength
       6: ifne          21
       9: getstatic     #40                 // Field LOGGER:Lorg/apache/logging/log4j/Logger;
      12: ldc           #41                 // String Properties must be specified for the PropertiesRewritePolicy
      14: invokeinterface #42,  2           // InterfaceMethod org/apache/logging/log4j/Logger.error:(Ljava/lang/String;)V
      19: aconst_null
      20: areturn
      21: aload_1
      22: invokestatic  #43                 // Method java/util/Arrays.asList:([Ljava/lang/Object;)Ljava/util/List;
      25: astore_2
      26: new           #44                 // class org/apache/logging/log4j/core/appender/rewrite/PropertiesRewritePolicy
      29: dup
      30: aload_0
      31: aload_2
      32: invokespecial #45                 // Method "<init>":(Lorg/apache/logging/log4j/core/config/Configuration;Ljava/util/List;)V
      35: areturn

  static {};
    Code:
       0: invokestatic  #46                 // Method org/apache/logging/log4j/status/StatusLogger.getLogger:()Lorg/apache/logging/log4j/status/StatusLogger;
       3: putstatic     #40                 // Field LOGGER:Lorg/apache/logging/log4j/Logger;
       6: return
}
