Compiled from "GlacierJobDescriptionDocumentDeserializer.kt"
public final class aws.sdk.kotlin.services.glacier.transform.GlacierJobDescriptionDocumentDeserializerKt {
  public static final aws.sdk.kotlin.services.glacier.model.GlacierJobDescription deserializeGlacierJobDescriptionDocument(aws.smithy.kotlin.runtime.serde.Deserializer);
    Code:
       0: aload_0
       1: ldc           #9                  // String deserializer
       3: invokestatic  #15                 // Method kotlin/jvm/internal/Intrinsics.checkNotNullParameter:(Ljava/lang/Object;Ljava/lang/String;)V
       6: new           #17                 // class aws/sdk/kotlin/services/glacier/model/GlacierJobDescription$Builder
       9: dup
      10: invokespecial #21                 // Method aws/sdk/kotlin/services/glacier/model/GlacierJobDescription$Builder."<init>":()V
      13: astore_1
      14: new           #23                 // class aws/smithy/kotlin/runtime/serde/SdkFieldDescriptor
      17: dup
      18: getstatic     #29                 // Field aws/smithy/kotlin/runtime/serde/SerialKind$String.INSTANCE:Laws/smithy/kotlin/runtime/serde/SerialKind$String;
      21: checkcast     #31                 // class aws/smithy/kotlin/runtime/serde/SerialKind
      24: iconst_1
      25: anewarray     #33                 // class aws/smithy/kotlin/runtime/serde/FieldTrait
      28: astore_3
      29: aload_3
      30: iconst_0
      31: new           #35                 // class aws/smithy/kotlin/runtime/serde/json/JsonSerialName
      34: dup
      35: ldc           #37                 // String Action
      37: invokespecial #40                 // Method aws/smithy/kotlin/runtime/serde/json/JsonSerialName."<init>":(Ljava/lang/String;)V
      40: checkcast     #33                 // class aws/smithy/kotlin/runtime/serde/FieldTrait
      43: aastore
      44: aload_3
      45: invokespecial #43                 // Method aws/smithy/kotlin/runtime/serde/SdkFieldDescriptor."<init>":(Laws/smithy/kotlin/runtime/serde/SerialKind;[Laws/smithy/kotlin/runtime/serde/FieldTrait;)V
      48: astore_2
      49: new           #23                 // class aws/smithy/kotlin/runtime/serde/SdkFieldDescriptor
      52: dup
      53: getstatic     #29                 // Field aws/smithy/kotlin/runtime/serde/SerialKind$String.INSTANCE:Laws/smithy/kotlin/runtime/serde/SerialKind$String;
      56: checkcast     #31                 // class aws/smithy/kotlin/runtime/serde/SerialKind
      59: iconst_1
      60: anewarray     #33                 // class aws/smithy/kotlin/runtime/serde/FieldTrait
      63: astore        4
      65: aload         4
      67: iconst_0
      68: new           #35                 // class aws/smithy/kotlin/runtime/serde/json/JsonSerialName
      71: dup
      72: ldc           #45                 // String ArchiveId
      74: invokespecial #40                 // Method aws/smithy/kotlin/runtime/serde/json/JsonSerialName."<init>":(Ljava/lang/String;)V
      77: checkcast     #33                 // class aws/smithy/kotlin/runtime/serde/FieldTrait
      80: aastore
      81: aload         4
      83: invokespecial #43                 // Method aws/smithy/kotlin/runtime/serde/SdkFieldDescriptor."<init>":(Laws/smithy/kotlin/runtime/serde/SerialKind;[Laws/smithy/kotlin/runtime/serde/FieldTrait;)V
      86: astore_3
      87: new           #23                 // class aws/smithy/kotlin/runtime/serde/SdkFieldDescriptor
      90: dup
      91: getstatic     #29                 // Field aws/smithy/kotlin/runtime/serde/SerialKind$String.INSTANCE:Laws/smithy/kotlin/runtime/serde/SerialKind$String;
      94: checkcast     #31                 // class aws/smithy/kotlin/runtime/serde/SerialKind
      97: iconst_1
      98: anewarray     #33                 // class aws/smithy/kotlin/runtime/serde/FieldTrait
     101: astore        5
     103: aload         5
     105: iconst_0
     106: new           #35                 // class aws/smithy/kotlin/runtime/serde/json/JsonSerialName
     109: dup
     110: ldc           #47                 // String ArchiveSHA256TreeHash
     112: invokespecial #40                 // Method aws/smithy/kotlin/runtime/serde/json/JsonSerialName."<init>":(Ljava/lang/String;)V
     115: checkcast     #33                 // class aws/smithy/kotlin/runtime/serde/FieldTrait
     118: aastore
     119: aload         5
     121: invokespecial #43                 // Method aws/smithy/kotlin/runtime/serde/SdkFieldDescriptor."<init>":(Laws/smithy/kotlin/runtime/serde/SerialKind;[Laws/smithy/kotlin/runtime/serde/FieldTrait;)V
     124: astore        4
     126: new           #23                 // class aws/smithy/kotlin/runtime/serde/SdkFieldDescriptor
     129: dup
     130: getstatic     #52                 // Field aws/smithy/kotlin/runtime/serde/SerialKind$Long.INSTANCE:Laws/smithy/kotlin/runtime/serde/SerialKind$Long;
     133: checkcast     #31                 // class aws/smithy/kotlin/runtime/serde/SerialKind
     136: iconst_1
     137: anewarray     #33                 // class aws/smithy/kotlin/runtime/serde/FieldTrait
     140: astore        6
     142: aload         6
     144: iconst_0
     145: new           #35                 // class aws/smithy/kotlin/runtime/serde/json/JsonSerialName
     148: dup
     149: ldc           #54                 // String ArchiveSizeInBytes
     151: invokespecial #40                 // Method aws/smithy/kotlin/runtime/serde/json/JsonSerialName."<init>":(Ljava/lang/String;)V
     154: checkcast     #33                 // class aws/smithy/kotlin/runtime/serde/FieldTrait
     157: aastore
     158: aload         6
     160: invokespecial #43                 // Method aws/smithy/kotlin/runtime/serde/SdkFieldDescriptor."<init>":(Laws/smithy/kotlin/runtime/serde/SerialKind;[Laws/smithy/kotlin/runtime/serde/FieldTrait;)V
     163: astore        5
     165: new           #23                 // class aws/smithy/kotlin/runtime/serde/SdkFieldDescriptor
     168: dup
     169: getstatic     #59                 // Field aws/smithy/kotlin/runtime/serde/SerialKind$Boolean.INSTANCE:Laws/smithy/kotlin/runtime/serde/SerialKind$Boolean;
     172: checkcast     #31                 // class aws/smithy/kotlin/runtime/serde/SerialKind
     175: iconst_1
     176: anewarray     #33                 // class aws/smithy/kotlin/runtime/serde/FieldTrait
     179: astore        7
     181: aload         7
     183: iconst_0
     184: new           #35                 // class aws/smithy/kotlin/runtime/serde/json/JsonSerialName
     187: dup
     188: ldc           #61                 // String Completed
     190: invokespecial #40                 // Method aws/smithy/kotlin/runtime/serde/json/JsonSerialName."<init>":(Ljava/lang/String;)V
     193: checkcast     #33                 // class aws/smithy/kotlin/runtime/serde/FieldTrait
     196: aastore
     197: aload         7
     199: invokespecial #43                 // Method aws/smithy/kotlin/runtime/serde/SdkFieldDescriptor."<init>":(Laws/smithy/kotlin/runtime/serde/SerialKind;[Laws/smithy/kotlin/runtime/serde/FieldTrait;)V
     202: astore        6
     204: new           #23                 // class aws/smithy/kotlin/runtime/serde/SdkFieldDescriptor
     207: dup
     208: getstatic     #29                 // Field aws/smithy/kotlin/runtime/serde/SerialKind$String.INSTANCE:Laws/smithy/kotlin/runtime/serde/SerialKind$String;
     211: checkcast     #31                 // class aws/smithy/kotlin/runtime/serde/SerialKind
     214: iconst_1
     215: anewarray     #33                 // class aws/smithy/kotlin/runtime/serde/FieldTrait
     218: astore        8
     220: aload         8
     222: iconst_0
     223: new           #35                 // class aws/smithy/kotlin/runtime/serde/json/JsonSerialName
     226: dup
     227: ldc           #63                 // String CompletionDate
     229: invokespecial #40                 // Method aws/smithy/kotlin/runtime/serde/json/JsonSerialName."<init>":(Ljava/lang/String;)V
     232: checkcast     #33                 // class aws/smithy/kotlin/runtime/serde/FieldTrait
     235: aastore
     236: aload         8
     238: invokespecial #43                 // Method aws/smithy/kotlin/runtime/serde/SdkFieldDescriptor."<init>":(Laws/smithy/kotlin/runtime/serde/SerialKind;[Laws/smithy/kotlin/runtime/serde/FieldTrait;)V
     241: astore        7
     243: new           #23                 // class aws/smithy/kotlin/runtime/serde/SdkFieldDescriptor
     246: dup
     247: getstatic     #29                 // Field aws/smithy/kotlin/runtime/serde/SerialKind$String.INSTANCE:Laws/smithy/kotlin/runtime/serde/SerialKind$String;
     250: checkcast     #31                 // class aws/smithy/kotlin/runtime/serde/SerialKind
     253: iconst_1
     254: anewarray     #33                 // class aws/smithy/kotlin/runtime/serde/FieldTrait
     257: astore        9
     259: aload         9
     261: iconst_0
     262: new           #35                 // class aws/smithy/kotlin/runtime/serde/json/JsonSerialName
     265: dup
     266: ldc           #65                 // String CreationDate
     268: invokespecial #40                 // Method aws/smithy/kotlin/runtime/serde/json/JsonSerialName."<init>":(Ljava/lang/String;)V
     271: checkcast     #33                 // class aws/smithy/kotlin/runtime/serde/FieldTrait
     274: aastore
     275: aload         9
     277: invokespecial #43                 // Method aws/smithy/kotlin/runtime/serde/SdkFieldDescriptor."<init>":(Laws/smithy/kotlin/runtime/serde/SerialKind;[Laws/smithy/kotlin/runtime/serde/FieldTrait;)V
     280: astore        8
     282: new           #23                 // class aws/smithy/kotlin/runtime/serde/SdkFieldDescriptor
     285: dup
     286: getstatic     #70                 // Field aws/smithy/kotlin/runtime/serde/SerialKind$Struct.INSTANCE:Laws/smithy/kotlin/runtime/serde/SerialKind$Struct;
     289: checkcast     #31                 // class aws/smithy/kotlin/runtime/serde/SerialKind
     292: iconst_1
     293: anewarray     #33                 // class aws/smithy/kotlin/runtime/serde/FieldTrait
     296: astore        10
     298: aload         10
     300: iconst_0
     301: new           #35                 // class aws/smithy/kotlin/runtime/serde/json/JsonSerialName
     304: dup
     305: ldc           #72                 // String InventoryRetrievalParameters
     307: invokespecial #40                 // Method aws/smithy/kotlin/runtime/serde/json/JsonSerialName."<init>":(Ljava/lang/String;)V
     310: checkcast     #33                 // class aws/smithy/kotlin/runtime/serde/FieldTrait
     313: aastore
     314: aload         10
     316: invokespecial #43                 // Method aws/smithy/kotlin/runtime/serde/SdkFieldDescriptor."<init>":(Laws/smithy/kotlin/runtime/serde/SerialKind;[Laws/smithy/kotlin/runtime/serde/FieldTrait;)V
     319: astore        9
     321: new           #23                 // class aws/smithy/kotlin/runtime/serde/SdkFieldDescriptor
     324: dup
     325: getstatic     #52                 // Field aws/smithy/kotlin/runtime/serde/SerialKind$Long.INSTANCE:Laws/smithy/kotlin/runtime/serde/SerialKind$Long;
     328: checkcast     #31                 // class aws/smithy/kotlin/runtime/serde/SerialKind
     331: iconst_1
     332: anewarray     #33                 // class aws/smithy/kotlin/runtime/serde/FieldTrait
     335: astore        11
     337: aload         11
     339: iconst_0
     340: new           #35                 // class aws/smithy/kotlin/runtime/serde/json/JsonSerialName
     343: dup
     344: ldc           #74                 // String InventorySizeInBytes
     346: invokespecial #40                 // Method aws/smithy/kotlin/runtime/serde/json/JsonSerialName."<init>":(Ljava/lang/String;)V
     349: checkcast     #33                 // class aws/smithy/kotlin/runtime/serde/FieldTrait
     352: aastore
     353: aload         11
     355: invokespecial #43                 // Method aws/smithy/kotlin/runtime/serde/SdkFieldDescriptor."<init>":(Laws/smithy/kotlin/runtime/serde/SerialKind;[Laws/smithy/kotlin/runtime/serde/FieldTrait;)V
     358: astore        10
     360: new           #23                 // class aws/smithy/kotlin/runtime/serde/SdkFieldDescriptor
     363: dup
     364: getstatic     #29                 // Field aws/smithy/kotlin/runtime/serde/SerialKind$String.INSTANCE:Laws/smithy/kotlin/runtime/serde/SerialKind$String;
     367: checkcast     #31                 // class aws/smithy/kotlin/runtime/serde/SerialKind
     370: iconst_1
     371: anewarray     #33                 // class aws/smithy/kotlin/runtime/serde/FieldTrait
     374: astore        12
     376: aload         12
     378: iconst_0
     379: new           #35                 // class aws/smithy/kotlin/runtime/serde/json/JsonSerialName
     382: dup
     383: ldc           #76                 // String JobDescription
     385: invokespecial #40                 // Method aws/smithy/kotlin/runtime/serde/json/JsonSerialName."<init>":(Ljava/lang/String;)V
     388: checkcast     #33                 // class aws/smithy/kotlin/runtime/serde/FieldTrait
     391: aastore
     392: aload         12
     394: invokespecial #43                 // Method aws/smithy/kotlin/runtime/serde/SdkFieldDescriptor."<init>":(Laws/smithy/kotlin/runtime/serde/SerialKind;[Laws/smithy/kotlin/runtime/serde/FieldTrait;)V
     397: astore        11
     399: new           #23                 // class aws/smithy/kotlin/runtime/serde/SdkFieldDescriptor
     402: dup
     403: getstatic     #29                 // Field aws/smithy/kotlin/runtime/serde/SerialKind$String.INSTANCE:Laws/smithy/kotlin/runtime/serde/SerialKind$String;
     406: checkcast     #31                 // class aws/smithy/kotlin/runtime/serde/SerialKind
     409: iconst_1
     410: anewarray     #33                 // class aws/smithy/kotlin/runtime/serde/FieldTrait
     413: astore        13
     415: aload         13
     417: iconst_0
     418: new           #35                 // class aws/smithy/kotlin/runtime/serde/json/JsonSerialName
     421: dup
     422: ldc           #78                 // String JobId
     424: invokespecial #40                 // Method aws/smithy/kotlin/runtime/serde/json/JsonSerialName."<init>":(Ljava/lang/String;)V
     427: checkcast     #33                 // class aws/smithy/kotlin/runtime/serde/FieldTrait
     430: aastore
     431: aload         13
     433: invokespecial #43                 // Method aws/smithy/kotlin/runtime/serde/SdkFieldDescriptor."<init>":(Laws/smithy/kotlin/runtime/serde/SerialKind;[Laws/smithy/kotlin/runtime/serde/FieldTrait;)V
     436: astore        12
     438: new           #23                 // class aws/smithy/kotlin/runtime/serde/SdkFieldDescriptor
     441: dup
     442: getstatic     #29                 // Field aws/smithy/kotlin/runtime/serde/SerialKind$String.INSTANCE:Laws/smithy/kotlin/runtime/serde/SerialKind$String;
     445: checkcast     #31                 // class aws/smithy/kotlin/runtime/serde/SerialKind
     448: iconst_1
     449: anewarray     #33                 // class aws/smithy/kotlin/runtime/serde/FieldTrait
     452: astore        14
     454: aload         14
     456: iconst_0
     457: new           #35                 // class aws/smithy/kotlin/runtime/serde/json/JsonSerialName
     460: dup
     461: ldc           #80                 // String JobOutputPath
     463: invokespecial #40                 // Method aws/smithy/kotlin/runtime/serde/json/JsonSerialName."<init>":(Ljava/lang/String;)V
     466: checkcast     #33                 // class aws/smithy/kotlin/runtime/serde/FieldTrait
     469: aastore
     470: aload         14
     472: invokespecial #43                 // Method aws/smithy/kotlin/runtime/serde/SdkFieldDescriptor."<init>":(Laws/smithy/kotlin/runtime/serde/SerialKind;[Laws/smithy/kotlin/runtime/serde/FieldTrait;)V
     475: astore        13
     477: new           #23                 // class aws/smithy/kotlin/runtime/serde/SdkFieldDescriptor
     480: dup
     481: getstatic     #70                 // Field aws/smithy/kotlin/runtime/serde/SerialKind$Struct.INSTANCE:Laws/smithy/kotlin/runtime/serde/SerialKind$Struct;
     484: checkcast     #31                 // class aws/smithy/kotlin/runtime/serde/SerialKind
     487: iconst_1
     488: anewarray     #33                 // class aws/smithy/kotlin/runtime/serde/FieldTrait
     491: astore        15
     493: aload         15
     495: iconst_0
     496: new           #35                 // class aws/smithy/kotlin/runtime/serde/json/JsonSerialName
     499: dup
     500: ldc           #82                 // String OutputLocation
     502: invokespecial #40                 // Method aws/smithy/kotlin/runtime/serde/json/JsonSerialName."<init>":(Ljava/lang/String;)V
     505: checkcast     #33                 // class aws/smithy/kotlin/runtime/serde/FieldTrait
     508: aastore
     509: aload         15
     511: invokespecial #43                 // Method aws/smithy/kotlin/runtime/serde/SdkFieldDescriptor."<init>":(Laws/smithy/kotlin/runtime/serde/SerialKind;[Laws/smithy/kotlin/runtime/serde/FieldTrait;)V
     514: astore        14
     516: new           #23                 // class aws/smithy/kotlin/runtime/serde/SdkFieldDescriptor
     519: dup
     520: getstatic     #29                 // Field aws/smithy/kotlin/runtime/serde/SerialKind$String.INSTANCE:Laws/smithy/kotlin/runtime/serde/SerialKind$String;
     523: checkcast     #31                 // class aws/smithy/kotlin/runtime/serde/SerialKind
     526: iconst_1
     527: anewarray     #33                 // class aws/smithy/kotlin/runtime/serde/FieldTrait
     530: astore        16
     532: aload         16
     534: iconst_0
     535: new           #35                 // class aws/smithy/kotlin/runtime/serde/json/JsonSerialName
     538: dup
     539: ldc           #84                 // String RetrievalByteRange
     541: invokespecial #40                 // Method aws/smithy/kotlin/runtime/serde/json/JsonSerialName."<init>":(Ljava/lang/String;)V
     544: checkcast     #33                 // class aws/smithy/kotlin/runtime/serde/FieldTrait
     547: aastore
     548: aload         16
     550: invokespecial #43                 // Method aws/smithy/kotlin/runtime/serde/SdkFieldDescriptor."<init>":(Laws/smithy/kotlin/runtime/serde/SerialKind;[Laws/smithy/kotlin/runtime/serde/FieldTrait;)V
     553: astore        15
     555: new           #23                 // class aws/smithy/kotlin/runtime/serde/SdkFieldDescriptor
     558: dup
     559: getstatic     #29                 // Field aws/smithy/kotlin/runtime/serde/SerialKind$String.INSTANCE:Laws/smithy/kotlin/runtime/serde/SerialKind$String;
     562: checkcast     #31                 // class aws/smithy/kotlin/runtime/serde/SerialKind
     565: iconst_1
     566: anewarray     #33                 // class aws/smithy/kotlin/runtime/serde/FieldTrait
     569: astore        17
     571: aload         17
     573: iconst_0
     574: new           #35                 // class aws/smithy/kotlin/runtime/serde/json/JsonSerialName
     577: dup
     578: ldc           #86                 // String SHA256TreeHash
     580: invokespecial #40                 // Method aws/smithy/kotlin/runtime/serde/json/JsonSerialName."<init>":(Ljava/lang/String;)V
     583: checkcast     #33                 // class aws/smithy/kotlin/runtime/serde/FieldTrait
     586: aastore
     587: aload         17
     589: invokespecial #43                 // Method aws/smithy/kotlin/runtime/serde/SdkFieldDescriptor."<init>":(Laws/smithy/kotlin/runtime/serde/SerialKind;[Laws/smithy/kotlin/runtime/serde/FieldTrait;)V
     592: astore        16
     594: new           #23                 // class aws/smithy/kotlin/runtime/serde/SdkFieldDescriptor
     597: dup
     598: getstatic     #29                 // Field aws/smithy/kotlin/runtime/serde/SerialKind$String.INSTANCE:Laws/smithy/kotlin/runtime/serde/SerialKind$String;
     601: checkcast     #31                 // class aws/smithy/kotlin/runtime/serde/SerialKind
     604: iconst_1
     605: anewarray     #33                 // class aws/smithy/kotlin/runtime/serde/FieldTrait
     608: astore        18
     610: aload         18
     612: iconst_0
     613: new           #35                 // class aws/smithy/kotlin/runtime/serde/json/JsonSerialName
     616: dup
     617: ldc           #88                 // String SNSTopic
     619: invokespecial #40                 // Method aws/smithy/kotlin/runtime/serde/json/JsonSerialName."<init>":(Ljava/lang/String;)V
     622: checkcast     #33                 // class aws/smithy/kotlin/runtime/serde/FieldTrait
     625: aastore
     626: aload         18
     628: invokespecial #43                 // Method aws/smithy/kotlin/runtime/serde/SdkFieldDescriptor."<init>":(Laws/smithy/kotlin/runtime/serde/SerialKind;[Laws/smithy/kotlin/runtime/serde/FieldTrait;)V
     631: astore        17
     633: new           #23                 // class aws/smithy/kotlin/runtime/serde/SdkFieldDescriptor
     636: dup
     637: getstatic     #70                 // Field aws/smithy/kotlin/runtime/serde/SerialKind$Struct.INSTANCE:Laws/smithy/kotlin/runtime/serde/SerialKind$Struct;
     640: checkcast     #31                 // class aws/smithy/kotlin/runtime/serde/SerialKind
     643: iconst_1
     644: anewarray     #33                 // class aws/smithy/kotlin/runtime/serde/FieldTrait
     647: astore        19
     649: aload         19
     651: iconst_0
     652: new           #35                 // class aws/smithy/kotlin/runtime/serde/json/JsonSerialName
     655: dup
     656: ldc           #90                 // String SelectParameters
     658: invokespecial #40                 // Method aws/smithy/kotlin/runtime/serde/json/JsonSerialName."<init>":(Ljava/lang/String;)V
     661: checkcast     #33                 // class aws/smithy/kotlin/runtime/serde/FieldTrait
     664: aastore
     665: aload         19
     667: invokespecial #43                 // Method aws/smithy/kotlin/runtime/serde/SdkFieldDescriptor."<init>":(Laws/smithy/kotlin/runtime/serde/SerialKind;[Laws/smithy/kotlin/runtime/serde/FieldTrait;)V
     670: astore        18
     672: new           #23                 // class aws/smithy/kotlin/runtime/serde/SdkFieldDescriptor
     675: dup
     676: getstatic     #29                 // Field aws/smithy/kotlin/runtime/serde/SerialKind$String.INSTANCE:Laws/smithy/kotlin/runtime/serde/SerialKind$String;
     679: checkcast     #31                 // class aws/smithy/kotlin/runtime/serde/SerialKind
     682: iconst_1
     683: anewarray     #33                 // class aws/smithy/kotlin/runtime/serde/FieldTrait
     686: astore        20
     688: aload         20
     690: iconst_0
     691: new           #35                 // class aws/smithy/kotlin/runtime/serde/json/JsonSerialName
     694: dup
     695: ldc           #92                 // String StatusCode
     697: invokespecial #40                 // Method aws/smithy/kotlin/runtime/serde/json/JsonSerialName."<init>":(Ljava/lang/String;)V
     700: checkcast     #33                 // class aws/smithy/kotlin/runtime/serde/FieldTrait
     703: aastore
     704: aload         20
     706: invokespecial #43                 // Method aws/smithy/kotlin/runtime/serde/SdkFieldDescriptor."<init>":(Laws/smithy/kotlin/runtime/serde/SerialKind;[Laws/smithy/kotlin/runtime/serde/FieldTrait;)V
     709: astore        19
     711: new           #23                 // class aws/smithy/kotlin/runtime/serde/SdkFieldDescriptor
     714: dup
     715: getstatic     #29                 // Field aws/smithy/kotlin/runtime/serde/SerialKind$String.INSTANCE:Laws/smithy/kotlin/runtime/serde/SerialKind$String;
     718: checkcast     #31                 // class aws/smithy/kotlin/runtime/serde/SerialKind
     721: iconst_1
     722: anewarray     #33                 // class aws/smithy/kotlin/runtime/serde/FieldTrait
     725: astore        21
     727: aload         21
     729: iconst_0
     730: new           #35                 // class aws/smithy/kotlin/runtime/serde/json/JsonSerialName
     733: dup
     734: ldc           #94                 // String StatusMessage
     736: invokespecial #40                 // Method aws/smithy/kotlin/runtime/serde/json/JsonSerialName."<init>":(Ljava/lang/String;)V
     739: checkcast     #33                 // class aws/smithy/kotlin/runtime/serde/FieldTrait
     742: aastore
     743: aload         21
     745: invokespecial #43                 // Method aws/smithy/kotlin/runtime/serde/SdkFieldDescriptor."<init>":(Laws/smithy/kotlin/runtime/serde/SerialKind;[Laws/smithy/kotlin/runtime/serde/FieldTrait;)V
     748: astore        20
     750: new           #23                 // class aws/smithy/kotlin/runtime/serde/SdkFieldDescriptor
     753: dup
     754: getstatic     #29                 // Field aws/smithy/kotlin/runtime/serde/SerialKind$String.INSTANCE:Laws/smithy/kotlin/runtime/serde/SerialKind$String;
     757: checkcast     #31                 // class aws/smithy/kotlin/runtime/serde/SerialKind
     760: iconst_1
     761: anewarray     #33                 // class aws/smithy/kotlin/runtime/serde/FieldTrait
     764: astore        22
     766: aload         22
     768: iconst_0
     769: new           #35                 // class aws/smithy/kotlin/runtime/serde/json/JsonSerialName
     772: dup
     773: ldc           #96                 // String Tier
     775: invokespecial #40                 // Method aws/smithy/kotlin/runtime/serde/json/JsonSerialName."<init>":(Ljava/lang/String;)V
     778: checkcast     #33                 // class aws/smithy/kotlin/runtime/serde/FieldTrait
     781: aastore
     782: aload         22
     784: invokespecial #43                 // Method aws/smithy/kotlin/runtime/serde/SdkFieldDescriptor."<init>":(Laws/smithy/kotlin/runtime/serde/SerialKind;[Laws/smithy/kotlin/runtime/serde/FieldTrait;)V
     787: astore        21
     789: new           #23                 // class aws/smithy/kotlin/runtime/serde/SdkFieldDescriptor
     792: dup
     793: getstatic     #29                 // Field aws/smithy/kotlin/runtime/serde/SerialKind$String.INSTANCE:Laws/smithy/kotlin/runtime/serde/SerialKind$String;
     796: checkcast     #31                 // class aws/smithy/kotlin/runtime/serde/SerialKind
     799: iconst_1
     800: anewarray     #33                 // class aws/smithy/kotlin/runtime/serde/FieldTrait
     803: astore        23
     805: aload         23
     807: iconst_0
     808: new           #35                 // class aws/smithy/kotlin/runtime/serde/json/JsonSerialName
     811: dup
     812: ldc           #98                 // String VaultARN
     814: invokespecial #40                 // Method aws/smithy/kotlin/runtime/serde/json/JsonSerialName."<init>":(Ljava/lang/String;)V
     817: checkcast     #33                 // class aws/smithy/kotlin/runtime/serde/FieldTrait
     820: aastore
     821: aload         23
     823: invokespecial #43                 // Method aws/smithy/kotlin/runtime/serde/SdkFieldDescriptor."<init>":(Laws/smithy/kotlin/runtime/serde/SerialKind;[Laws/smithy/kotlin/runtime/serde/FieldTrait;)V
     826: astore        22
     828: getstatic     #104                // Field aws/smithy/kotlin/runtime/serde/SdkObjectDescriptor.Companion:Laws/smithy/kotlin/runtime/serde/SdkObjectDescriptor$Companion;
     831: astore        24
     833: iconst_0
     834: istore        25
     836: new           #106                // class aws/smithy/kotlin/runtime/serde/SdkObjectDescriptor$Builder
     839: dup
     840: invokespecial #107                // Method aws/smithy/kotlin/runtime/serde/SdkObjectDescriptor$Builder."<init>":()V
     843: astore        26
     845: aload         26
     847: astore        27
     849: iconst_0
     850: istore        28
     852: aload         27
     854: aload_2
     855: invokevirtual #111                // Method aws/smithy/kotlin/runtime/serde/SdkObjectDescriptor$Builder.field:(Laws/smithy/kotlin/runtime/serde/SdkFieldDescriptor;)V
     858: aload         27
     860: aload_3
     861: invokevirtual #111                // Method aws/smithy/kotlin/runtime/serde/SdkObjectDescriptor$Builder.field:(Laws/smithy/kotlin/runtime/serde/SdkFieldDescriptor;)V
     864: aload         27
     866: aload         4
     868: invokevirtual #111                // Method aws/smithy/kotlin/runtime/serde/SdkObjectDescriptor$Builder.field:(Laws/smithy/kotlin/runtime/serde/SdkFieldDescriptor;)V
     871: aload         27
     873: aload         5
     875: invokevirtual #111                // Method aws/smithy/kotlin/runtime/serde/SdkObjectDescriptor$Builder.field:(Laws/smithy/kotlin/runtime/serde/SdkFieldDescriptor;)V
     878: aload         27
     880: aload         6
     882: invokevirtual #111                // Method aws/smithy/kotlin/runtime/serde/SdkObjectDescriptor$Builder.field:(Laws/smithy/kotlin/runtime/serde/SdkFieldDescriptor;)V
     885: aload         27
     887: aload         7
     889: invokevirtual #111                // Method aws/smithy/kotlin/runtime/serde/SdkObjectDescriptor$Builder.field:(Laws/smithy/kotlin/runtime/serde/SdkFieldDescriptor;)V
     892: aload         27
     894: aload         8
     896: invokevirtual #111                // Method aws/smithy/kotlin/runtime/serde/SdkObjectDescriptor$Builder.field:(Laws/smithy/kotlin/runtime/serde/SdkFieldDescriptor;)V
     899: aload         27
     901: aload         9
     903: invokevirtual #111                // Method aws/smithy/kotlin/runtime/serde/SdkObjectDescriptor$Builder.field:(Laws/smithy/kotlin/runtime/serde/SdkFieldDescriptor;)V
     906: aload         27
     908: aload         10
     910: invokevirtual #111                // Method aws/smithy/kotlin/runtime/serde/SdkObjectDescriptor$Builder.field:(Laws/smithy/kotlin/runtime/serde/SdkFieldDescriptor;)V
     913: aload         27
     915: aload         11
     917: invokevirtual #111                // Method aws/smithy/kotlin/runtime/serde/SdkObjectDescriptor$Builder.field:(Laws/smithy/kotlin/runtime/serde/SdkFieldDescriptor;)V
     920: aload         27
     922: aload         12
     924: invokevirtual #111                // Method aws/smithy/kotlin/runtime/serde/SdkObjectDescriptor$Builder.field:(Laws/smithy/kotlin/runtime/serde/SdkFieldDescriptor;)V
     927: aload         27
     929: aload         13
     931: invokevirtual #111                // Method aws/smithy/kotlin/runtime/serde/SdkObjectDescriptor$Builder.field:(Laws/smithy/kotlin/runtime/serde/SdkFieldDescriptor;)V
     934: aload         27
     936: aload         14
     938: invokevirtual #111                // Method aws/smithy/kotlin/runtime/serde/SdkObjectDescriptor$Builder.field:(Laws/smithy/kotlin/runtime/serde/SdkFieldDescriptor;)V
     941: aload         27
     943: aload         15
     945: invokevirtual #111                // Method aws/smithy/kotlin/runtime/serde/SdkObjectDescriptor$Builder.field:(Laws/smithy/kotlin/runtime/serde/SdkFieldDescriptor;)V
     948: aload         27
     950: aload         16
     952: invokevirtual #111                // Method aws/smithy/kotlin/runtime/serde/SdkObjectDescriptor$Builder.field:(Laws/smithy/kotlin/runtime/serde/SdkFieldDescriptor;)V
     955: aload         27
     957: aload         17
     959: invokevirtual #111                // Method aws/smithy/kotlin/runtime/serde/SdkObjectDescriptor$Builder.field:(Laws/smithy/kotlin/runtime/serde/SdkFieldDescriptor;)V
     962: aload         27
     964: aload         18
     966: invokevirtual #111                // Method aws/smithy/kotlin/runtime/serde/SdkObjectDescriptor$Builder.field:(Laws/smithy/kotlin/runtime/serde/SdkFieldDescriptor;)V
     969: aload         27
     971: aload         19
     973: invokevirtual #111                // Method aws/smithy/kotlin/runtime/serde/SdkObjectDescriptor$Builder.field:(Laws/smithy/kotlin/runtime/serde/SdkFieldDescriptor;)V
     976: aload         27
     978: aload         20
     980: invokevirtual #111                // Method aws/smithy/kotlin/runtime/serde/SdkObjectDescriptor$Builder.field:(Laws/smithy/kotlin/runtime/serde/SdkFieldDescriptor;)V
     983: aload         27
     985: aload         21
     987: invokevirtual #111                // Method aws/smithy/kotlin/runtime/serde/SdkObjectDescriptor$Builder.field:(Laws/smithy/kotlin/runtime/serde/SdkFieldDescriptor;)V
     990: aload         27
     992: aload         22
     994: invokevirtual #111                // Method aws/smithy/kotlin/runtime/serde/SdkObjectDescriptor$Builder.field:(Laws/smithy/kotlin/runtime/serde/SdkFieldDescriptor;)V
     997: nop
     998: aload         26
    1000: invokevirtual #115                // Method aws/smithy/kotlin/runtime/serde/SdkObjectDescriptor$Builder.build:()Laws/smithy/kotlin/runtime/serde/SdkObjectDescriptor;
    1003: astore        23
    1005: aload_0
    1006: astore        24
    1008: iconst_0
    1009: istore        25
    1011: aload         24
    1013: aload         23
    1015: invokeinterface #121,  2          // InterfaceMethod aws/smithy/kotlin/runtime/serde/Deserializer.deserializeStruct:(Laws/smithy/kotlin/runtime/serde/SdkObjectDescriptor;)Laws/smithy/kotlin/runtime/serde/Deserializer$FieldIterator;
    1020: astore        26
    1022: aload         26
    1024: astore        27
    1026: iconst_0
    1027: istore        28
    1029: nop
    1030: aload         27
    1032: invokeinterface #127,  1          // InterfaceMethod aws/smithy/kotlin/runtime/serde/Deserializer$FieldIterator.findNextFieldIndex:()Ljava/lang/Integer;
    1037: astore        29
    1039: aload         29
    1041: aload_2
    1042: invokevirtual #131                // Method aws/smithy/kotlin/runtime/serde/SdkFieldDescriptor.getIndex:()I
    1045: istore        30
    1047: dup
    1048: ifnonnull     1055
    1051: pop
    1052: goto          1096
    1055: invokevirtual #136                // Method java/lang/Integer.intValue:()I
    1058: iload         30
    1060: if_icmpne     1096
    1063: aload_1
    1064: aload         27
    1066: invokeinterface #140,  1          // InterfaceMethod aws/smithy/kotlin/runtime/serde/Deserializer$FieldIterator.deserializeString:()Ljava/lang/String;
    1071: astore        31
    1073: astore        32
    1075: iconst_0
    1076: istore        33
    1078: getstatic     #145                // Field aws/sdk/kotlin/services/glacier/model/ActionCode.Companion:Laws/sdk/kotlin/services/glacier/model/ActionCode$Companion;
    1081: aload         31
    1083: invokevirtual #151                // Method aws/sdk/kotlin/services/glacier/model/ActionCode$Companion.fromValue:(Ljava/lang/String;)Laws/sdk/kotlin/services/glacier/model/ActionCode;
    1086: aload         32
    1088: swap
    1089: nop
    1090: invokevirtual #155                // Method aws/sdk/kotlin/services/glacier/model/GlacierJobDescription$Builder.setAction:(Laws/sdk/kotlin/services/glacier/model/ActionCode;)V
    1093: goto          1029
    1096: aload         29
    1098: aload_3
    1099: invokevirtual #131                // Method aws/smithy/kotlin/runtime/serde/SdkFieldDescriptor.getIndex:()I
    1102: istore        30
    1104: dup
    1105: ifnonnull     1112
    1108: pop
    1109: goto          1134
    1112: invokevirtual #136                // Method java/lang/Integer.intValue:()I
    1115: iload         30
    1117: if_icmpne     1134
    1120: aload_1
    1121: aload         27
    1123: invokeinterface #140,  1          // InterfaceMethod aws/smithy/kotlin/runtime/serde/Deserializer$FieldIterator.deserializeString:()Ljava/lang/String;
    1128: invokevirtual #158                // Method aws/sdk/kotlin/services/glacier/model/GlacierJobDescription$Builder.setArchiveId:(Ljava/lang/String;)V
    1131: goto          1029
    1134: aload         29
    1136: aload         4
    1138: invokevirtual #131                // Method aws/smithy/kotlin/runtime/serde/SdkFieldDescriptor.getIndex:()I
    1141: istore        30
    1143: dup
    1144: ifnonnull     1151
    1147: pop
    1148: goto          1173
    1151: invokevirtual #136                // Method java/lang/Integer.intValue:()I
    1154: iload         30
    1156: if_icmpne     1173
    1159: aload_1
    1160: aload         27
    1162: invokeinterface #140,  1          // InterfaceMethod aws/smithy/kotlin/runtime/serde/Deserializer$FieldIterator.deserializeString:()Ljava/lang/String;
    1167: invokevirtual #161                // Method aws/sdk/kotlin/services/glacier/model/GlacierJobDescription$Builder.setArchiveSha256TreeHash:(Ljava/lang/String;)V
    1170: goto          1029
    1173: aload         29
    1175: aload         5
    1177: invokevirtual #131                // Method aws/smithy/kotlin/runtime/serde/SdkFieldDescriptor.getIndex:()I
    1180: istore        30
    1182: dup
    1183: ifnonnull     1190
    1186: pop
    1187: goto          1215
    1190: invokevirtual #136                // Method java/lang/Integer.intValue:()I
    1193: iload         30
    1195: if_icmpne     1215
    1198: aload_1
    1199: aload         27
    1201: invokeinterface #165,  1          // InterfaceMethod aws/smithy/kotlin/runtime/serde/Deserializer$FieldIterator.deserializeLong:()J
    1206: invokestatic  #171                // Method java/lang/Long.valueOf:(J)Ljava/lang/Long;
    1209: invokevirtual #175                // Method aws/sdk/kotlin/services/glacier/model/GlacierJobDescription$Builder.setArchiveSizeInBytes:(Ljava/lang/Long;)V
    1212: goto          1029
    1215: aload         29
    1217: aload         6
    1219: invokevirtual #131                // Method aws/smithy/kotlin/runtime/serde/SdkFieldDescriptor.getIndex:()I
    1222: istore        30
    1224: dup
    1225: ifnonnull     1232
    1228: pop
    1229: goto          1254
    1232: invokevirtual #136                // Method java/lang/Integer.intValue:()I
    1235: iload         30
    1237: if_icmpne     1254
    1240: aload_1
    1241: aload         27
    1243: invokeinterface #179,  1          // InterfaceMethod aws/smithy/kotlin/runtime/serde/Deserializer$FieldIterator.deserializeBoolean:()Z
    1248: invokevirtual #183                // Method aws/sdk/kotlin/services/glacier/model/GlacierJobDescription$Builder.setCompleted:(Z)V
    1251: goto          1029
    1254: aload         29
    1256: aload         7
    1258: invokevirtual #131                // Method aws/smithy/kotlin/runtime/serde/SdkFieldDescriptor.getIndex:()I
    1261: istore        30
    1263: dup
    1264: ifnonnull     1271
    1267: pop
    1268: goto          1293
    1271: invokevirtual #136                // Method java/lang/Integer.intValue:()I
    1274: iload         30
    1276: if_icmpne     1293
    1279: aload_1
    1280: aload         27
    1282: invokeinterface #140,  1          // InterfaceMethod aws/smithy/kotlin/runtime/serde/Deserializer$FieldIterator.deserializeString:()Ljava/lang/String;
    1287: invokevirtual #186                // Method aws/sdk/kotlin/services/glacier/model/GlacierJobDescription$Builder.setCompletionDate:(Ljava/lang/String;)V
    1290: goto          1029
    1293: aload         29
    1295: aload         8
    1297: invokevirtual #131                // Method aws/smithy/kotlin/runtime/serde/SdkFieldDescriptor.getIndex:()I
    1300: istore        30
    1302: dup
    1303: ifnonnull     1310
    1306: pop
    1307: goto          1332
    1310: invokevirtual #136                // Method java/lang/Integer.intValue:()I
    1313: iload         30
    1315: if_icmpne     1332
    1318: aload_1
    1319: aload         27
    1321: invokeinterface #140,  1          // InterfaceMethod aws/smithy/kotlin/runtime/serde/Deserializer$FieldIterator.deserializeString:()Ljava/lang/String;
    1326: invokevirtual #189                // Method aws/sdk/kotlin/services/glacier/model/GlacierJobDescription$Builder.setCreationDate:(Ljava/lang/String;)V
    1329: goto          1029
    1332: aload         29
    1334: aload         9
    1336: invokevirtual #131                // Method aws/smithy/kotlin/runtime/serde/SdkFieldDescriptor.getIndex:()I
    1339: istore        30
    1341: dup
    1342: ifnonnull     1349
    1345: pop
    1346: goto          1368
    1349: invokevirtual #136                // Method java/lang/Integer.intValue:()I
    1352: iload         30
    1354: if_icmpne     1368
    1357: aload_1
    1358: aload_0
    1359: invokestatic  #195                // Method aws/sdk/kotlin/services/glacier/transform/InventoryRetrievalJobDescriptionDocumentDeserializerKt.deserializeInventoryRetrievalJobDescriptionDocument:(Laws/smithy/kotlin/runtime/serde/Deserializer;)Laws/sdk/kotlin/services/glacier/model/InventoryRetrievalJobDescription;
    1362: invokevirtual #199                // Method aws/sdk/kotlin/services/glacier/model/GlacierJobDescription$Builder.setInventoryRetrievalParameters:(Laws/sdk/kotlin/services/glacier/model/InventoryRetrievalJobDescription;)V
    1365: goto          1029
    1368: aload         29
    1370: aload         10
    1372: invokevirtual #131                // Method aws/smithy/kotlin/runtime/serde/SdkFieldDescriptor.getIndex:()I
    1375: istore        30
    1377: dup
    1378: ifnonnull     1385
    1381: pop
    1382: goto          1410
    1385: invokevirtual #136                // Method java/lang/Integer.intValue:()I
    1388: iload         30
    1390: if_icmpne     1410
    1393: aload_1
    1394: aload         27
    1396: invokeinterface #165,  1          // InterfaceMethod aws/smithy/kotlin/runtime/serde/Deserializer$FieldIterator.deserializeLong:()J
    1401: invokestatic  #171                // Method java/lang/Long.valueOf:(J)Ljava/lang/Long;
    1404: invokevirtual #202                // Method aws/sdk/kotlin/services/glacier/model/GlacierJobDescription$Builder.setInventorySizeInBytes:(Ljava/lang/Long;)V
    1407: goto          1029
    1410: aload         29
    1412: aload         11
    1414: invokevirtual #131                // Method aws/smithy/kotlin/runtime/serde/SdkFieldDescriptor.getIndex:()I
    1417: istore        30
    1419: dup
    1420: ifnonnull     1427
    1423: pop
    1424: goto          1449
    1427: invokevirtual #136                // Method java/lang/Integer.intValue:()I
    1430: iload         30
    1432: if_icmpne     1449
    1435: aload_1
    1436: aload         27
    1438: invokeinterface #140,  1          // InterfaceMethod aws/smithy/kotlin/runtime/serde/Deserializer$FieldIterator.deserializeString:()Ljava/lang/String;
    1443: invokevirtual #205                // Method aws/sdk/kotlin/services/glacier/model/GlacierJobDescription$Builder.setJobDescription:(Ljava/lang/String;)V
    1446: goto          1029
    1449: aload         29
    1451: aload         12
    1453: invokevirtual #131                // Method aws/smithy/kotlin/runtime/serde/SdkFieldDescriptor.getIndex:()I
    1456: istore        30
    1458: dup
    1459: ifnonnull     1466
    1462: pop
    1463: goto          1488
    1466: invokevirtual #136                // Method java/lang/Integer.intValue:()I
    1469: iload         30
    1471: if_icmpne     1488
    1474: aload_1
    1475: aload         27
    1477: invokeinterface #140,  1          // InterfaceMethod aws/smithy/kotlin/runtime/serde/Deserializer$FieldIterator.deserializeString:()Ljava/lang/String;
    1482: invokevirtual #208                // Method aws/sdk/kotlin/services/glacier/model/GlacierJobDescription$Builder.setJobId:(Ljava/lang/String;)V
    1485: goto          1029
    1488: aload         29
    1490: aload         13
    1492: invokevirtual #131                // Method aws/smithy/kotlin/runtime/serde/SdkFieldDescriptor.getIndex:()I
    1495: istore        30
    1497: dup
    1498: ifnonnull     1505
    1501: pop
    1502: goto          1527
    1505: invokevirtual #136                // Method java/lang/Integer.intValue:()I
    1508: iload         30
    1510: if_icmpne     1527
    1513: aload_1
    1514: aload         27
    1516: invokeinterface #140,  1          // InterfaceMethod aws/smithy/kotlin/runtime/serde/Deserializer$FieldIterator.deserializeString:()Ljava/lang/String;
    1521: invokevirtual #211                // Method aws/sdk/kotlin/services/glacier/model/GlacierJobDescription$Builder.setJobOutputPath:(Ljava/lang/String;)V
    1524: goto          1029
    1527: aload         29
    1529: aload         14
    1531: invokevirtual #131                // Method aws/smithy/kotlin/runtime/serde/SdkFieldDescriptor.getIndex:()I
    1534: istore        30
    1536: dup
    1537: ifnonnull     1544
    1540: pop
    1541: goto          1563
    1544: invokevirtual #136                // Method java/lang/Integer.intValue:()I
    1547: iload         30
    1549: if_icmpne     1563
    1552: aload_1
    1553: aload_0
    1554: invokestatic  #217                // Method aws/sdk/kotlin/services/glacier/transform/OutputLocationDocumentDeserializerKt.deserializeOutputLocationDocument:(Laws/smithy/kotlin/runtime/serde/Deserializer;)Laws/sdk/kotlin/services/glacier/model/OutputLocation;
    1557: invokevirtual #221                // Method aws/sdk/kotlin/services/glacier/model/GlacierJobDescription$Builder.setOutputLocation:(Laws/sdk/kotlin/services/glacier/model/OutputLocation;)V
    1560: goto          1029
    1563: aload         29
    1565: aload         15
    1567: invokevirtual #131                // Method aws/smithy/kotlin/runtime/serde/SdkFieldDescriptor.getIndex:()I
    1570: istore        30
    1572: dup
    1573: ifnonnull     1580
    1576: pop
    1577: goto          1602
    1580: invokevirtual #136                // Method java/lang/Integer.intValue:()I
    1583: iload         30
    1585: if_icmpne     1602
    1588: aload_1
    1589: aload         27
    1591: invokeinterface #140,  1          // InterfaceMethod aws/smithy/kotlin/runtime/serde/Deserializer$FieldIterator.deserializeString:()Ljava/lang/String;
    1596: invokevirtual #224                // Method aws/sdk/kotlin/services/glacier/model/GlacierJobDescription$Builder.setRetrievalByteRange:(Ljava/lang/String;)V
    1599: goto          1029
    1602: aload         29
    1604: aload         16
    1606: invokevirtual #131                // Method aws/smithy/kotlin/runtime/serde/SdkFieldDescriptor.getIndex:()I
    1609: istore        30
    1611: dup
    1612: ifnonnull     1619
    1615: pop
    1616: goto          1641
    1619: invokevirtual #136                // Method java/lang/Integer.intValue:()I
    1622: iload         30
    1624: if_icmpne     1641
    1627: aload_1
    1628: aload         27
    1630: invokeinterface #140,  1          // InterfaceMethod aws/smithy/kotlin/runtime/serde/Deserializer$FieldIterator.deserializeString:()Ljava/lang/String;
    1635: invokevirtual #227                // Method aws/sdk/kotlin/services/glacier/model/GlacierJobDescription$Builder.setSha256TreeHash:(Ljava/lang/String;)V
    1638: goto          1029
    1641: aload         29
    1643: aload         17
    1645: invokevirtual #131                // Method aws/smithy/kotlin/runtime/serde/SdkFieldDescriptor.getIndex:()I
    1648: istore        30
    1650: dup
    1651: ifnonnull     1658
    1654: pop
    1655: goto          1680
    1658: invokevirtual #136                // Method java/lang/Integer.intValue:()I
    1661: iload         30
    1663: if_icmpne     1680
    1666: aload_1
    1667: aload         27
    1669: invokeinterface #140,  1          // InterfaceMethod aws/smithy/kotlin/runtime/serde/Deserializer$FieldIterator.deserializeString:()Ljava/lang/String;
    1674: invokevirtual #230                // Method aws/sdk/kotlin/services/glacier/model/GlacierJobDescription$Builder.setSnsTopic:(Ljava/lang/String;)V
    1677: goto          1029
    1680: aload         29
    1682: aload         18
    1684: invokevirtual #131                // Method aws/smithy/kotlin/runtime/serde/SdkFieldDescriptor.getIndex:()I
    1687: istore        30
    1689: dup
    1690: ifnonnull     1697
    1693: pop
    1694: goto          1716
    1697: invokevirtual #136                // Method java/lang/Integer.intValue:()I
    1700: iload         30
    1702: if_icmpne     1716
    1705: aload_1
    1706: aload_0
    1707: invokestatic  #236                // Method aws/sdk/kotlin/services/glacier/transform/SelectParametersDocumentDeserializerKt.deserializeSelectParametersDocument:(Laws/smithy/kotlin/runtime/serde/Deserializer;)Laws/sdk/kotlin/services/glacier/model/SelectParameters;
    1710: invokevirtual #240                // Method aws/sdk/kotlin/services/glacier/model/GlacierJobDescription$Builder.setSelectParameters:(Laws/sdk/kotlin/services/glacier/model/SelectParameters;)V
    1713: goto          1029
    1716: aload         29
    1718: aload         19
    1720: invokevirtual #131                // Method aws/smithy/kotlin/runtime/serde/SdkFieldDescriptor.getIndex:()I
    1723: istore        30
    1725: dup
    1726: ifnonnull     1733
    1729: pop
    1730: goto          1774
    1733: invokevirtual #136                // Method java/lang/Integer.intValue:()I
    1736: iload         30
    1738: if_icmpne     1774
    1741: aload_1
    1742: aload         27
    1744: invokeinterface #140,  1          // InterfaceMethod aws/smithy/kotlin/runtime/serde/Deserializer$FieldIterator.deserializeString:()Ljava/lang/String;
    1749: astore        31
    1751: astore        32
    1753: iconst_0
    1754: istore        33
    1756: getstatic     #245                // Field aws/sdk/kotlin/services/glacier/model/StatusCode.Companion:Laws/sdk/kotlin/services/glacier/model/StatusCode$Companion;
    1759: aload         31
    1761: invokevirtual #250                // Method aws/sdk/kotlin/services/glacier/model/StatusCode$Companion.fromValue:(Ljava/lang/String;)Laws/sdk/kotlin/services/glacier/model/StatusCode;
    1764: aload         32
    1766: swap
    1767: nop
    1768: invokevirtual #254                // Method aws/sdk/kotlin/services/glacier/model/GlacierJobDescription$Builder.setStatusCode:(Laws/sdk/kotlin/services/glacier/model/StatusCode;)V
    1771: goto          1029
    1774: aload         29
    1776: aload         20
    1778: invokevirtual #131                // Method aws/smithy/kotlin/runtime/serde/SdkFieldDescriptor.getIndex:()I
    1781: istore        30
    1783: dup
    1784: ifnonnull     1791
    1787: pop
    1788: goto          1813
    1791: invokevirtual #136                // Method java/lang/Integer.intValue:()I
    1794: iload         30
    1796: if_icmpne     1813
    1799: aload_1
    1800: aload         27
    1802: invokeinterface #140,  1          // InterfaceMethod aws/smithy/kotlin/runtime/serde/Deserializer$FieldIterator.deserializeString:()Ljava/lang/String;
    1807: invokevirtual #257                // Method aws/sdk/kotlin/services/glacier/model/GlacierJobDescription$Builder.setStatusMessage:(Ljava/lang/String;)V
    1810: goto          1029
    1813: aload         29
    1815: aload         21
    1817: invokevirtual #131                // Method aws/smithy/kotlin/runtime/serde/SdkFieldDescriptor.getIndex:()I
    1820: istore        30
    1822: dup
    1823: ifnonnull     1830
    1826: pop
    1827: goto          1852
    1830: invokevirtual #136                // Method java/lang/Integer.intValue:()I
    1833: iload         30
    1835: if_icmpne     1852
    1838: aload_1
    1839: aload         27
    1841: invokeinterface #140,  1          // InterfaceMethod aws/smithy/kotlin/runtime/serde/Deserializer$FieldIterator.deserializeString:()Ljava/lang/String;
    1846: invokevirtual #260                // Method aws/sdk/kotlin/services/glacier/model/GlacierJobDescription$Builder.setTier:(Ljava/lang/String;)V
    1849: goto          1029
    1852: aload         29
    1854: aload         22
    1856: invokevirtual #131                // Method aws/smithy/kotlin/runtime/serde/SdkFieldDescriptor.getIndex:()I
    1859: istore        30
    1861: dup
    1862: ifnonnull     1869
    1865: pop
    1866: goto          1891
    1869: invokevirtual #136                // Method java/lang/Integer.intValue:()I
    1872: iload         30
    1874: if_icmpne     1891
    1877: aload_1
    1878: aload         27
    1880: invokeinterface #140,  1          // InterfaceMethod aws/smithy/kotlin/runtime/serde/Deserializer$FieldIterator.deserializeString:()Ljava/lang/String;
    1885: invokevirtual #263                // Method aws/sdk/kotlin/services/glacier/model/GlacierJobDescription$Builder.setVaultArn:(Ljava/lang/String;)V
    1888: goto          1029
    1891: aload         29
    1893: ifnonnull     1899
    1896: goto          1909
    1899: aload         27
    1901: invokeinterface #266,  1          // InterfaceMethod aws/smithy/kotlin/runtime/serde/Deserializer$FieldIterator.skipValue:()V
    1906: goto          1029
    1909: nop
    1910: nop
    1911: aload_1
    1912: invokevirtual #269                // Method aws/sdk/kotlin/services/glacier/model/GlacierJobDescription$Builder.build:()Laws/sdk/kotlin/services/glacier/model/GlacierJobDescription;
    1915: areturn
}
