Compiled from "ListJobsOperationSerializer.kt"
final class aws.sdk.kotlin.services.glacier.transform.ListJobsOperationSerializer$serialize$2$1 extends kotlin.jvm.internal.Lambda implements kotlin.jvm.functions.Function1<aws.smithy.kotlin.runtime.http.QueryParametersBuilder, kotlin.Unit> {
  final aws.sdk.kotlin.services.glacier.model.ListJobsRequest $input;

  aws.sdk.kotlin.services.glacier.transform.ListJobsOperationSerializer$serialize$2$1(aws.sdk.kotlin.services.glacier.model.ListJobsRequest);
    Code:
       0: aload_0
       1: aload_1
       2: putfield      #13                 // Field $input:Laws/sdk/kotlin/services/glacier/model/ListJobsRequest;
       5: aload_0
       6: iconst_1
       7: invokespecial #16                 // Method kotlin/jvm/internal/Lambda."<init>":(I)V
      10: return

  public final void invoke(aws.smithy.kotlin.runtime.http.QueryParametersBuilder);
    Code:
       0: aload_1
       1: ldc           #23                 // String $this$parameters
       3: invokestatic  #29                 // Method kotlin/jvm/internal/Intrinsics.checkNotNullParameter:(Ljava/lang/Object;Ljava/lang/String;)V
       6: aload_0
       7: getfield      #13                 // Field $input:Laws/sdk/kotlin/services/glacier/model/ListJobsRequest;
      10: invokevirtual #35                 // Method aws/sdk/kotlin/services/glacier/model/ListJobsRequest.getCompleted:()Ljava/lang/String;
      13: ifnull        29
      16: aload_1
      17: ldc           #37                 // String completed
      19: aload_0
      20: getfield      #13                 // Field $input:Laws/sdk/kotlin/services/glacier/model/ListJobsRequest;
      23: invokevirtual #35                 // Method aws/sdk/kotlin/services/glacier/model/ListJobsRequest.getCompleted:()Ljava/lang/String;
      26: invokevirtual #43                 // Method aws/smithy/kotlin/runtime/http/QueryParametersBuilder.append:(Ljava/lang/String;Ljava/lang/String;)V
      29: aload_0
      30: getfield      #13                 // Field $input:Laws/sdk/kotlin/services/glacier/model/ListJobsRequest;
      33: invokevirtual #47                 // Method aws/sdk/kotlin/services/glacier/model/ListJobsRequest.getLimit:()Ljava/lang/Integer;
      36: ifnull        55
      39: aload_1
      40: ldc           #49                 // String limit
      42: aload_0
      43: getfield      #13                 // Field $input:Laws/sdk/kotlin/services/glacier/model/ListJobsRequest;
      46: invokevirtual #47                 // Method aws/sdk/kotlin/services/glacier/model/ListJobsRequest.getLimit:()Ljava/lang/Integer;
      49: invokestatic  #55                 // Method java/lang/String.valueOf:(Ljava/lang/Object;)Ljava/lang/String;
      52: invokevirtual #43                 // Method aws/smithy/kotlin/runtime/http/QueryParametersBuilder.append:(Ljava/lang/String;Ljava/lang/String;)V
      55: aload_0
      56: getfield      #13                 // Field $input:Laws/sdk/kotlin/services/glacier/model/ListJobsRequest;
      59: invokevirtual #58                 // Method aws/sdk/kotlin/services/glacier/model/ListJobsRequest.getMarker:()Ljava/lang/String;
      62: ifnull        78
      65: aload_1
      66: ldc           #60                 // String marker
      68: aload_0
      69: getfield      #13                 // Field $input:Laws/sdk/kotlin/services/glacier/model/ListJobsRequest;
      72: invokevirtual #58                 // Method aws/sdk/kotlin/services/glacier/model/ListJobsRequest.getMarker:()Ljava/lang/String;
      75: invokevirtual #43                 // Method aws/smithy/kotlin/runtime/http/QueryParametersBuilder.append:(Ljava/lang/String;Ljava/lang/String;)V
      78: aload_0
      79: getfield      #13                 // Field $input:Laws/sdk/kotlin/services/glacier/model/ListJobsRequest;
      82: invokevirtual #63                 // Method aws/sdk/kotlin/services/glacier/model/ListJobsRequest.getStatuscode:()Ljava/lang/String;
      85: ifnull        101
      88: aload_1
      89: ldc           #65                 // String statuscode
      91: aload_0
      92: getfield      #13                 // Field $input:Laws/sdk/kotlin/services/glacier/model/ListJobsRequest;
      95: invokevirtual #63                 // Method aws/sdk/kotlin/services/glacier/model/ListJobsRequest.getStatuscode:()Ljava/lang/String;
      98: invokevirtual #43                 // Method aws/smithy/kotlin/runtime/http/QueryParametersBuilder.append:(Ljava/lang/String;Ljava/lang/String;)V
     101: return

  public java.lang.Object invoke(java.lang.Object);
    Code:
       0: aload_0
       1: aload_1
       2: checkcast     #39                 // class aws/smithy/kotlin/runtime/http/QueryParametersBuilder
       5: invokevirtual #69                 // Method invoke:(Laws/smithy/kotlin/runtime/http/QueryParametersBuilder;)V
       8: getstatic     #75                 // Field kotlin/Unit.INSTANCE:Lkotlin/Unit;
      11: areturn
}
