Compiled from "DescribeEndpointsRequest.scala"
public final class zio.aws.timestreamquery.model.DescribeEndpointsRequest$Wrapper implements zio.aws.timestreamquery.model.DescribeEndpointsRequest$ReadOnly {
  public zio.aws.timestreamquery.model.DescribeEndpointsRequest asEditable();
    Code:
       0: aload_0
       1: invokestatic  #17                 // InterfaceMethod zio/aws/timestreamquery/model/DescribeEndpointsRequest$ReadOnly.asEditable$:(Lzio/aws/timestreamquery/model/DescribeEndpointsRequest$ReadOnly;)Lzio/aws/timestreamquery/model/DescribeEndpointsRequest;
       4: areturn

  public zio.aws.timestreamquery.model.DescribeEndpointsRequest$Wrapper(software.amazon.awssdk.services.timestreamquery.model.DescribeEndpointsRequest);
    Code:
       0: aload_0
       1: invokespecial #25                 // Method java/lang/Object."<init>":()V
       4: aload_0
       5: invokestatic  #29                 // InterfaceMethod zio/aws/timestreamquery/model/DescribeEndpointsRequest$ReadOnly.$init$:(Lzio/aws/timestreamquery/model/DescribeEndpointsRequest$ReadOnly;)V
       8: return
}
