Compiled from "package.scala"
public class zio.aws.timestreamquery.model.package$primitives$MaxScheduledQueriesResults$ extends zio.prelude.Subtype<java.lang.Object> {
  public static zio.aws.timestreamquery.model.package$primitives$MaxScheduledQueriesResults$ MODULE$;

  public static {};
    Code:
       0: new           #2                  // class zio/aws/timestreamquery/model/package$primitives$MaxScheduledQueriesResults$
       3: invokespecial #19                 // Method "<init>":()V
       6: return

  public zio.aws.timestreamquery.model.package$primitives$MaxScheduledQueriesResults$();
    Code:
       0: aload_0
       1: invokespecial #20                 // Method zio/prelude/Subtype."<init>":()V
       4: aload_0
       5: putstatic     #22                 // Field MODULE$:Lzio/aws/timestreamquery/model/package$primitives$MaxScheduledQueriesResults$;
       8: return
}
