Compiled from "QueryResponse.scala"
public final class zio.aws.timestreamquery.model.QueryResponse implements scala.Product,scala.Serializable {
  private final java.lang.String queryId;

  private final zio.prelude.data.Optional<java.lang.String> nextToken;

  private final scala.collection.Iterable<zio.aws.timestreamquery.model.Row> rows;

  private final scala.collection.Iterable<zio.aws.timestreamquery.model.ColumnInfo> columnInfo;

  private final zio.prelude.data.Optional<zio.aws.timestreamquery.model.QueryStatus> queryStatus;

  public static zio.prelude.data.Optional<zio.aws.timestreamquery.model.QueryStatus> $lessinit$greater$default$5();
    Code:
       0: getstatic     #70                 // Field zio/aws/timestreamquery/model/QueryResponse$.MODULE$:Lzio/aws/timestreamquery/model/QueryResponse$;
       3: invokevirtual #72                 // Method zio/aws/timestreamquery/model/QueryResponse$.$lessinit$greater$default$5:()Lzio/prelude/data/Optional;
       6: areturn

  public static zio.prelude.data.Optional<java.lang.String> $lessinit$greater$default$2();
    Code:
       0: getstatic     #70                 // Field zio/aws/timestreamquery/model/QueryResponse$.MODULE$:Lzio/aws/timestreamquery/model/QueryResponse$;
       3: invokevirtual #76                 // Method zio/aws/timestreamquery/model/QueryResponse$.$lessinit$greater$default$2:()Lzio/prelude/data/Optional;
       6: areturn

  public static scala.Option<scala.Tuple5<java.lang.String, zio.prelude.data.Optional<java.lang.String>, scala.collection.Iterable<zio.aws.timestreamquery.model.Row>, scala.collection.Iterable<zio.aws.timestreamquery.model.ColumnInfo>, zio.prelude.data.Optional<zio.aws.timestreamquery.model.QueryStatus>>> unapply(zio.aws.timestreamquery.model.QueryResponse);
    Code:
       0: getstatic     #70                 // Field zio/aws/timestreamquery/model/QueryResponse$.MODULE$:Lzio/aws/timestreamquery/model/QueryResponse$;
       3: aload_0
       4: invokevirtual #82                 // Method zio/aws/timestreamquery/model/QueryResponse$.unapply:(Lzio/aws/timestreamquery/model/QueryResponse;)Lscala/Option;
       7: areturn

  public static zio.prelude.data.Optional<zio.aws.timestreamquery.model.QueryStatus> apply$default$5();
    Code:
       0: getstatic     #70                 // Field zio/aws/timestreamquery/model/QueryResponse$.MODULE$:Lzio/aws/timestreamquery/model/QueryResponse$;
       3: invokevirtual #85                 // Method zio/aws/timestreamquery/model/QueryResponse$.apply$default$5:()Lzio/prelude/data/Optional;
       6: areturn

  public static zio.prelude.data.Optional<java.lang.String> apply$default$2();
    Code:
       0: getstatic     #70                 // Field zio/aws/timestreamquery/model/QueryResponse$.MODULE$:Lzio/aws/timestreamquery/model/QueryResponse$;
       3: invokevirtual #88                 // Method zio/aws/timestreamquery/model/QueryResponse$.apply$default$2:()Lzio/prelude/data/Optional;
       6: areturn

  public static zio.aws.timestreamquery.model.QueryResponse apply(java.lang.String, zio.prelude.data.Optional<java.lang.String>, scala.collection.Iterable<zio.aws.timestreamquery.model.Row>, scala.collection.Iterable<zio.aws.timestreamquery.model.ColumnInfo>, zio.prelude.data.Optional<zio.aws.timestreamquery.model.QueryStatus>);
    Code:
       0: getstatic     #70                 // Field zio/aws/timestreamquery/model/QueryResponse$.MODULE$:Lzio/aws/timestreamquery/model/QueryResponse$;
       3: aload_0
       4: aload_1
       5: aload_2
       6: aload_3
       7: aload         4
       9: invokevirtual #93                 // Method zio/aws/timestreamquery/model/QueryResponse$.apply:(Ljava/lang/String;Lzio/prelude/data/Optional;Lscala/collection/Iterable;Lscala/collection/Iterable;Lzio/prelude/data/Optional;)Lzio/aws/timestreamquery/model/QueryResponse;
      12: areturn

  public static zio.aws.timestreamquery.model.QueryResponse$ReadOnly wrap(software.amazon.awssdk.services.timestreamquery.model.QueryResponse);
    Code:
       0: getstatic     #70                 // Field zio/aws/timestreamquery/model/QueryResponse$.MODULE$:Lzio/aws/timestreamquery/model/QueryResponse$;
       3: aload_0
       4: invokevirtual #98                 // Method zio/aws/timestreamquery/model/QueryResponse$.wrap:(Lsoftware/amazon/awssdk/services/timestreamquery/model/QueryResponse;)Lzio/aws/timestreamquery/model/QueryResponse$ReadOnly;
       7: areturn

  public java.lang.String queryId();
    Code:
       0: aload_0
       1: getfield      #101                // Field queryId:Ljava/lang/String;
       4: areturn

  public zio.prelude.data.Optional<java.lang.String> nextToken();
    Code:
       0: aload_0
       1: getfield      #105                // Field nextToken:Lzio/prelude/data/Optional;
       4: areturn

  public scala.collection.Iterable<zio.aws.timestreamquery.model.Row> rows();
    Code:
       0: aload_0
       1: getfield      #109                // Field rows:Lscala/collection/Iterable;
       4: areturn

  public scala.collection.Iterable<zio.aws.timestreamquery.model.ColumnInfo> columnInfo();
    Code:
       0: aload_0
       1: getfield      #112                // Field columnInfo:Lscala/collection/Iterable;
       4: areturn

  public zio.prelude.data.Optional<zio.aws.timestreamquery.model.QueryStatus> queryStatus();
    Code:
       0: aload_0
       1: getfield      #114                // Field queryStatus:Lzio/prelude/data/Optional;
       4: areturn

  public software.amazon.awssdk.services.timestreamquery.model.QueryResponse buildAwsValue();
    Code:
       0: getstatic     #70                 // Field zio/aws/timestreamquery/model/QueryResponse$.MODULE$:Lzio/aws/timestreamquery/model/QueryResponse$;
       3: invokevirtual #120                // Method zio/aws/timestreamquery/model/QueryResponse$.zio$aws$timestreamquery$model$QueryResponse$$zioAwsBuilderHelper:()Lzio/aws/core/BuilderHelper;
       6: getstatic     #70                 // Field zio/aws/timestreamquery/model/QueryResponse$.MODULE$:Lzio/aws/timestreamquery/model/QueryResponse$;
       9: invokevirtual #120                // Method zio/aws/timestreamquery/model/QueryResponse$.zio$aws$timestreamquery$model$QueryResponse$$zioAwsBuilderHelper:()Lzio/aws/core/BuilderHelper;
      12: invokestatic  #124                // Method software/amazon/awssdk/services/timestreamquery/model/QueryResponse.builder:()Lsoftware/amazon/awssdk/services/timestreamquery/model/QueryResponse$Builder;
      15: getstatic     #127                // Field zio/aws/timestreamquery/model/package$primitives$QueryId$.MODULE$:Lzio/aws/timestreamquery/model/package$primitives$QueryId$;
      18: aload_0
      19: invokevirtual #129                // Method queryId:()Ljava/lang/String;
      22: invokevirtual #133                // Method zio/aws/timestreamquery/model/package$primitives$QueryId$.unwrap:(Ljava/lang/Object;)Ljava/lang/Object;
      25: checkcast     #135                // class java/lang/String
      28: invokeinterface #138,  2          // InterfaceMethod software/amazon/awssdk/services/timestreamquery/model/QueryResponse$Builder.queryId:(Ljava/lang/String;)Lsoftware/amazon/awssdk/services/timestreamquery/model/QueryResponse$Builder;
      33: invokeinterface #141,  2          // InterfaceMethod zio/aws/core/BuilderHelper.BuilderOps:(Lsoftware/amazon/awssdk/utils/builder/SdkBuilder;)Lzio/aws/core/BuilderHelper$BuilderOps;
      38: aload_0
      39: invokevirtual #143                // Method nextToken:()Lzio/prelude/data/Optional;
      42: invokedynamic #162,  0            // InvokeDynamic #0:apply:()Lscala/Function1;
      47: invokeinterface #168,  2          // InterfaceMethod zio/prelude/data/Optional.map:(Lscala/Function1;)Lzio/prelude/data/Optional;
      52: invokedynamic #175,  0            // InvokeDynamic #1:apply:()Lscala/Function1;
      57: invokevirtual #179                // Method zio/aws/core/BuilderHelper$BuilderOps.optionallyWith:(Lzio/prelude/data/Optional;Lscala/Function1;)Lsoftware/amazon/awssdk/utils/builder/SdkBuilder;
      60: checkcast     #24                 // class software/amazon/awssdk/services/timestreamquery/model/QueryResponse$Builder
      63: getstatic     #184                // Field scala/jdk/CollectionConverters$.MODULE$:Lscala/jdk/CollectionConverters$;
      66: aload_0
      67: invokevirtual #186                // Method rows:()Lscala/collection/Iterable;
      70: invokedynamic #193,  0            // InvokeDynamic #2:apply:()Lscala/Function1;
      75: getstatic     #198                // Field scala/collection/Iterable$.MODULE$:Lscala/collection/Iterable$;
      78: invokevirtual #202                // Method scala/collection/Iterable$.canBuildFrom:()Lscala/collection/generic/CanBuildFrom;
      81: invokeinterface #207,  3          // InterfaceMethod scala/collection/Iterable.map:(Lscala/Function1;Lscala/collection/generic/CanBuildFrom;)Ljava/lang/Object;
      86: checkcast     #204                // class scala/collection/Iterable
      89: invokevirtual #211                // Method scala/jdk/CollectionConverters$.asJavaCollectionConverter:(Lscala/collection/Iterable;)Lscala/collection/convert/Decorators$AsJavaCollection;
      92: invokevirtual #215                // Method scala/collection/convert/Decorators$AsJavaCollection.asJavaCollection:()Ljava/util/Collection;
      95: invokeinterface #218,  2          // InterfaceMethod software/amazon/awssdk/services/timestreamquery/model/QueryResponse$Builder.rows:(Ljava/util/Collection;)Lsoftware/amazon/awssdk/services/timestreamquery/model/QueryResponse$Builder;
     100: getstatic     #184                // Field scala/jdk/CollectionConverters$.MODULE$:Lscala/jdk/CollectionConverters$;
     103: aload_0
     104: invokevirtual #220                // Method columnInfo:()Lscala/collection/Iterable;
     107: invokedynamic #227,  0            // InvokeDynamic #3:apply:()Lscala/Function1;
     112: getstatic     #198                // Field scala/collection/Iterable$.MODULE$:Lscala/collection/Iterable$;
     115: invokevirtual #202                // Method scala/collection/Iterable$.canBuildFrom:()Lscala/collection/generic/CanBuildFrom;
     118: invokeinterface #207,  3          // InterfaceMethod scala/collection/Iterable.map:(Lscala/Function1;Lscala/collection/generic/CanBuildFrom;)Ljava/lang/Object;
     123: checkcast     #204                // class scala/collection/Iterable
     126: invokevirtual #211                // Method scala/jdk/CollectionConverters$.asJavaCollectionConverter:(Lscala/collection/Iterable;)Lscala/collection/convert/Decorators$AsJavaCollection;
     129: invokevirtual #215                // Method scala/collection/convert/Decorators$AsJavaCollection.asJavaCollection:()Ljava/util/Collection;
     132: invokeinterface #229,  2          // InterfaceMethod software/amazon/awssdk/services/timestreamquery/model/QueryResponse$Builder.columnInfo:(Ljava/util/Collection;)Lsoftware/amazon/awssdk/services/timestreamquery/model/QueryResponse$Builder;
     137: invokeinterface #141,  2          // InterfaceMethod zio/aws/core/BuilderHelper.BuilderOps:(Lsoftware/amazon/awssdk/utils/builder/SdkBuilder;)Lzio/aws/core/BuilderHelper$BuilderOps;
     142: aload_0
     143: invokevirtual #231                // Method queryStatus:()Lzio/prelude/data/Optional;
     146: invokedynamic #238,  0            // InvokeDynamic #4:apply:()Lscala/Function1;
     151: invokeinterface #168,  2          // InterfaceMethod zio/prelude/data/Optional.map:(Lscala/Function1;)Lzio/prelude/data/Optional;
     156: invokedynamic #243,  0            // InvokeDynamic #5:apply:()Lscala/Function1;
     161: invokevirtual #179                // Method zio/aws/core/BuilderHelper$BuilderOps.optionallyWith:(Lzio/prelude/data/Optional;Lscala/Function1;)Lsoftware/amazon/awssdk/utils/builder/SdkBuilder;
     164: invokeinterface #249,  1          // InterfaceMethod software/amazon/awssdk/utils/builder/SdkBuilder.build:()Ljava/lang/Object;
     169: checkcast     #26                 // class software/amazon/awssdk/services/timestreamquery/model/QueryResponse
     172: areturn

  public zio.aws.timestreamquery.model.QueryResponse$ReadOnly asReadOnly();
    Code:
       0: getstatic     #70                 // Field zio/aws/timestreamquery/model/QueryResponse$.MODULE$:Lzio/aws/timestreamquery/model/QueryResponse$;
       3: aload_0
       4: invokevirtual #253                // Method buildAwsValue:()Lsoftware/amazon/awssdk/services/timestreamquery/model/QueryResponse;
       7: invokevirtual #98                 // Method zio/aws/timestreamquery/model/QueryResponse$.wrap:(Lsoftware/amazon/awssdk/services/timestreamquery/model/QueryResponse;)Lzio/aws/timestreamquery/model/QueryResponse$ReadOnly;
      10: areturn

  public zio.aws.timestreamquery.model.QueryResponse copy(java.lang.String, zio.prelude.data.Optional<java.lang.String>, scala.collection.Iterable<zio.aws.timestreamquery.model.Row>, scala.collection.Iterable<zio.aws.timestreamquery.model.ColumnInfo>, zio.prelude.data.Optional<zio.aws.timestreamquery.model.QueryStatus>);
    Code:
       0: new           #2                  // class zio/aws/timestreamquery/model/QueryResponse
       3: dup
       4: aload_1
       5: aload_2
       6: aload_3
       7: aload         4
       9: aload         5
      11: invokespecial #258                // Method "<init>":(Ljava/lang/String;Lzio/prelude/data/Optional;Lscala/collection/Iterable;Lscala/collection/Iterable;Lzio/prelude/data/Optional;)V
      14: areturn

  public java.lang.String copy$default$1();
    Code:
       0: aload_0
       1: invokevirtual #129                // Method queryId:()Ljava/lang/String;
       4: areturn

  public zio.prelude.data.Optional<java.lang.String> copy$default$2();
    Code:
       0: aload_0
       1: invokevirtual #143                // Method nextToken:()Lzio/prelude/data/Optional;
       4: areturn

  public scala.collection.Iterable<zio.aws.timestreamquery.model.Row> copy$default$3();
    Code:
       0: aload_0
       1: invokevirtual #186                // Method rows:()Lscala/collection/Iterable;
       4: areturn

  public scala.collection.Iterable<zio.aws.timestreamquery.model.ColumnInfo> copy$default$4();
    Code:
       0: aload_0
       1: invokevirtual #220                // Method columnInfo:()Lscala/collection/Iterable;
       4: areturn

  public zio.prelude.data.Optional<zio.aws.timestreamquery.model.QueryStatus> copy$default$5();
    Code:
       0: aload_0
       1: invokevirtual #231                // Method queryStatus:()Lzio/prelude/data/Optional;
       4: areturn

  public java.lang.String productPrefix();
    Code:
       0: ldc_w         #266                // String QueryResponse
       3: areturn

  public int productArity();
    Code:
       0: iconst_5
       1: ireturn

  public java.lang.Object productElement(int);
    Code:
       0: iload_1
       1: istore_2
       2: iload_2
       3: tableswitch   { // 0 to 4
                     0: 36
                     1: 43
                     2: 50
                     3: 57
                     4: 64
               default: 71
          }
      36: aload_0
      37: invokevirtual #129                // Method queryId:()Ljava/lang/String;
      40: goto          83
      43: aload_0
      44: invokevirtual #143                // Method nextToken:()Lzio/prelude/data/Optional;
      47: goto          83
      50: aload_0
      51: invokevirtual #186                // Method rows:()Lscala/collection/Iterable;
      54: goto          83
      57: aload_0
      58: invokevirtual #220                // Method columnInfo:()Lscala/collection/Iterable;
      61: goto          83
      64: aload_0
      65: invokevirtual #231                // Method queryStatus:()Lzio/prelude/data/Optional;
      68: goto          83
      71: new           #273                // class java/lang/IndexOutOfBoundsException
      74: dup
      75: iload_1
      76: invokestatic  #279                // Method java/lang/Integer.toString:(I)Ljava/lang/String;
      79: invokespecial #282                // Method java/lang/IndexOutOfBoundsException."<init>":(Ljava/lang/String;)V
      82: athrow
      83: areturn

  public scala.collection.Iterator<java.lang.Object> productIterator();
    Code:
       0: getstatic     #291                // Field scala/runtime/ScalaRunTime$.MODULE$:Lscala/runtime/ScalaRunTime$;
       3: aload_0
       4: invokevirtual #295                // Method scala/runtime/ScalaRunTime$.typedProductIterator:(Lscala/Product;)Lscala/collection/Iterator;
       7: areturn

  public boolean canEqual(java.lang.Object);
    Code:
       0: aload_1
       1: instanceof    #2                  // class zio/aws/timestreamquery/model/QueryResponse
       4: ireturn

  public int hashCode();
    Code:
       0: getstatic     #291                // Field scala/runtime/ScalaRunTime$.MODULE$:Lscala/runtime/ScalaRunTime$;
       3: aload_0
       4: invokevirtual #303                // Method scala/runtime/ScalaRunTime$._hashCode:(Lscala/Product;)I
       7: ireturn

  public java.lang.String toString();
    Code:
       0: getstatic     #291                // Field scala/runtime/ScalaRunTime$.MODULE$:Lscala/runtime/ScalaRunTime$;
       3: aload_0
       4: invokevirtual #307                // Method scala/runtime/ScalaRunTime$._toString:(Lscala/Product;)Ljava/lang/String;
       7: areturn

  public boolean equals(java.lang.Object);
    Code:
       0: aload_0
       1: aload_1
       2: if_acmpeq     205
       5: aload_1
       6: astore_3
       7: aload_3
       8: instanceof    #2                  // class zio/aws/timestreamquery/model/QueryResponse
      11: ifeq          19
      14: iconst_1
      15: istore_2
      16: goto          27
      19: goto          22
      22: iconst_0
      23: istore_2
      24: goto          27
      27: iload_2
      28: ifeq          209
      31: aload_1
      32: checkcast     #2                  // class zio/aws/timestreamquery/model/QueryResponse
      35: astore        4
      37: aload_0
      38: invokevirtual #129                // Method queryId:()Ljava/lang/String;
      41: aload         4
      43: invokevirtual #129                // Method queryId:()Ljava/lang/String;
      46: astore        5
      48: dup
      49: ifnonnull     61
      52: pop
      53: aload         5
      55: ifnull        69
      58: goto          201
      61: aload         5
      63: invokevirtual #310                // Method java/lang/Object.equals:(Ljava/lang/Object;)Z
      66: ifeq          201
      69: aload_0
      70: invokevirtual #143                // Method nextToken:()Lzio/prelude/data/Optional;
      73: aload         4
      75: invokevirtual #143                // Method nextToken:()Lzio/prelude/data/Optional;
      78: astore        6
      80: dup
      81: ifnonnull     93
      84: pop
      85: aload         6
      87: ifnull        101
      90: goto          201
      93: aload         6
      95: invokevirtual #310                // Method java/lang/Object.equals:(Ljava/lang/Object;)Z
      98: ifeq          201
     101: aload_0
     102: invokevirtual #186                // Method rows:()Lscala/collection/Iterable;
     105: aload         4
     107: invokevirtual #186                // Method rows:()Lscala/collection/Iterable;
     110: astore        7
     112: dup
     113: ifnonnull     125
     116: pop
     117: aload         7
     119: ifnull        133
     122: goto          201
     125: aload         7
     127: invokevirtual #310                // Method java/lang/Object.equals:(Ljava/lang/Object;)Z
     130: ifeq          201
     133: aload_0
     134: invokevirtual #220                // Method columnInfo:()Lscala/collection/Iterable;
     137: aload         4
     139: invokevirtual #220                // Method columnInfo:()Lscala/collection/Iterable;
     142: astore        8
     144: dup
     145: ifnonnull     157
     148: pop
     149: aload         8
     151: ifnull        165
     154: goto          201
     157: aload         8
     159: invokevirtual #310                // Method java/lang/Object.equals:(Ljava/lang/Object;)Z
     162: ifeq          201
     165: aload_0
     166: invokevirtual #231                // Method queryStatus:()Lzio/prelude/data/Optional;
     169: aload         4
     171: invokevirtual #231                // Method queryStatus:()Lzio/prelude/data/Optional;
     174: astore        9
     176: dup
     177: ifnonnull     189
     180: pop
     181: aload         9
     183: ifnull        197
     186: goto          201
     189: aload         9
     191: invokevirtual #310                // Method java/lang/Object.equals:(Ljava/lang/Object;)Z
     194: ifeq          201
     197: iconst_1
     198: goto          202
     201: iconst_0
     202: ifeq          209
     205: iconst_1
     206: goto          210
     209: iconst_0
     210: ireturn

  public static final java.lang.String $anonfun$buildAwsValue$1(java.lang.String);
    Code:
       0: getstatic     #314                // Field zio/aws/timestreamquery/model/package$primitives$PaginationToken$.MODULE$:Lzio/aws/timestreamquery/model/package$primitives$PaginationToken$;
       3: aload_0
       4: invokevirtual #315                // Method zio/aws/timestreamquery/model/package$primitives$PaginationToken$.unwrap:(Ljava/lang/Object;)Ljava/lang/Object;
       7: checkcast     #135                // class java/lang/String
      10: areturn

  public static final software.amazon.awssdk.services.timestreamquery.model.QueryResponse$Builder $anonfun$buildAwsValue$3(software.amazon.awssdk.services.timestreamquery.model.QueryResponse$Builder, java.lang.String);
    Code:
       0: aload_0
       1: aload_1
       2: invokeinterface #320,  2          // InterfaceMethod software/amazon/awssdk/services/timestreamquery/model/QueryResponse$Builder.nextToken:(Ljava/lang/String;)Lsoftware/amazon/awssdk/services/timestreamquery/model/QueryResponse$Builder;
       7: areturn

  public static final scala.Function1 $anonfun$buildAwsValue$2(software.amazon.awssdk.services.timestreamquery.model.QueryResponse$Builder);
    Code:
       0: aload_0
       1: invokedynamic #327,  0            // InvokeDynamic #6:apply:(Lsoftware/amazon/awssdk/services/timestreamquery/model/QueryResponse$Builder;)Lscala/Function1;
       6: areturn

  public static final software.amazon.awssdk.services.timestreamquery.model.Row $anonfun$buildAwsValue$4(zio.aws.timestreamquery.model.Row);
    Code:
       0: aload_0
       1: invokevirtual #333                // Method zio/aws/timestreamquery/model/Row.buildAwsValue:()Lsoftware/amazon/awssdk/services/timestreamquery/model/Row;
       4: areturn

  public static final software.amazon.awssdk.services.timestreamquery.model.ColumnInfo $anonfun$buildAwsValue$5(zio.aws.timestreamquery.model.ColumnInfo);
    Code:
       0: aload_0
       1: invokevirtual #339                // Method zio/aws/timestreamquery/model/ColumnInfo.buildAwsValue:()Lsoftware/amazon/awssdk/services/timestreamquery/model/ColumnInfo;
       4: areturn

  public static final software.amazon.awssdk.services.timestreamquery.model.QueryStatus $anonfun$buildAwsValue$6(zio.aws.timestreamquery.model.QueryStatus);
    Code:
       0: aload_0
       1: invokevirtual #345                // Method zio/aws/timestreamquery/model/QueryStatus.buildAwsValue:()Lsoftware/amazon/awssdk/services/timestreamquery/model/QueryStatus;
       4: areturn

  public static final software.amazon.awssdk.services.timestreamquery.model.QueryResponse$Builder $anonfun$buildAwsValue$8(software.amazon.awssdk.services.timestreamquery.model.QueryResponse$Builder, software.amazon.awssdk.services.timestreamquery.model.QueryStatus);
    Code:
       0: aload_0
       1: aload_1
       2: invokeinterface #352,  2          // InterfaceMethod software/amazon/awssdk/services/timestreamquery/model/QueryResponse$Builder.queryStatus:(Lsoftware/amazon/awssdk/services/timestreamquery/model/QueryStatus;)Lsoftware/amazon/awssdk/services/timestreamquery/model/QueryResponse$Builder;
       7: areturn

  public static final scala.Function1 $anonfun$buildAwsValue$7(software.amazon.awssdk.services.timestreamquery.model.QueryResponse$Builder);
    Code:
       0: aload_0
       1: invokedynamic #359,  0            // InvokeDynamic #7:apply:(Lsoftware/amazon/awssdk/services/timestreamquery/model/QueryResponse$Builder;)Lscala/Function1;
       6: areturn

  public zio.aws.timestreamquery.model.QueryResponse(java.lang.String, zio.prelude.data.Optional<java.lang.String>, scala.collection.Iterable<zio.aws.timestreamquery.model.Row>, scala.collection.Iterable<zio.aws.timestreamquery.model.ColumnInfo>, zio.prelude.data.Optional<zio.aws.timestreamquery.model.QueryStatus>);
    Code:
       0: aload_0
       1: aload_1
       2: putfield      #101                // Field queryId:Ljava/lang/String;
       5: aload_0
       6: aload_2
       7: putfield      #105                // Field nextToken:Lzio/prelude/data/Optional;
      10: aload_0
      11: aload_3
      12: putfield      #109                // Field rows:Lscala/collection/Iterable;
      15: aload_0
      16: aload         4
      18: putfield      #112                // Field columnInfo:Lscala/collection/Iterable;
      21: aload_0
      22: aload         5
      24: putfield      #114                // Field queryStatus:Lzio/prelude/data/Optional;
      27: aload_0
      28: invokespecial #363                // Method java/lang/Object."<init>":()V
      31: aload_0
      32: invokestatic  #367                // InterfaceMethod scala/Product.$init$:(Lscala/Product;)V
      35: return

  private static java.lang.Object $deserializeLambda$(java.lang.invoke.SerializedLambda);
    Code:
       0: aload_0
       1: invokedynamic #379,  0            // InvokeDynamic #8:lambdaDeserialize:(Ljava/lang/invoke/SerializedLambda;)Ljava/lang/Object;
       6: areturn
}
