Compiled from "QueryStatus.scala"
public final class zio.aws.timestreamquery.model.QueryStatus implements scala.Product,scala.Serializable {
  private final zio.prelude.data.Optional<java.lang.Object> progressPercentage;

  private final zio.prelude.data.Optional<java.lang.Object> cumulativeBytesScanned;

  private final zio.prelude.data.Optional<java.lang.Object> cumulativeBytesMetered;

  public static zio.prelude.data.Optional<java.lang.Object> $lessinit$greater$default$3();
    Code:
       0: getstatic     #47                 // Field zio/aws/timestreamquery/model/QueryStatus$.MODULE$:Lzio/aws/timestreamquery/model/QueryStatus$;
       3: invokevirtual #49                 // Method zio/aws/timestreamquery/model/QueryStatus$.$lessinit$greater$default$3:()Lzio/prelude/data/Optional;
       6: areturn

  public static zio.prelude.data.Optional<java.lang.Object> $lessinit$greater$default$2();
    Code:
       0: getstatic     #47                 // Field zio/aws/timestreamquery/model/QueryStatus$.MODULE$:Lzio/aws/timestreamquery/model/QueryStatus$;
       3: invokevirtual #52                 // Method zio/aws/timestreamquery/model/QueryStatus$.$lessinit$greater$default$2:()Lzio/prelude/data/Optional;
       6: areturn

  public static zio.prelude.data.Optional<java.lang.Object> $lessinit$greater$default$1();
    Code:
       0: getstatic     #47                 // Field zio/aws/timestreamquery/model/QueryStatus$.MODULE$:Lzio/aws/timestreamquery/model/QueryStatus$;
       3: invokevirtual #55                 // Method zio/aws/timestreamquery/model/QueryStatus$.$lessinit$greater$default$1:()Lzio/prelude/data/Optional;
       6: areturn

  public static scala.Option<scala.Tuple3<zio.prelude.data.Optional<java.lang.Object>, zio.prelude.data.Optional<java.lang.Object>, zio.prelude.data.Optional<java.lang.Object>>> unapply(zio.aws.timestreamquery.model.QueryStatus);
    Code:
       0: getstatic     #47                 // Field zio/aws/timestreamquery/model/QueryStatus$.MODULE$:Lzio/aws/timestreamquery/model/QueryStatus$;
       3: aload_0
       4: invokevirtual #61                 // Method zio/aws/timestreamquery/model/QueryStatus$.unapply:(Lzio/aws/timestreamquery/model/QueryStatus;)Lscala/Option;
       7: areturn

  public static zio.prelude.data.Optional<java.lang.Object> apply$default$3();
    Code:
       0: getstatic     #47                 // Field zio/aws/timestreamquery/model/QueryStatus$.MODULE$:Lzio/aws/timestreamquery/model/QueryStatus$;
       3: invokevirtual #64                 // Method zio/aws/timestreamquery/model/QueryStatus$.apply$default$3:()Lzio/prelude/data/Optional;
       6: areturn

  public static zio.prelude.data.Optional<java.lang.Object> apply$default$2();
    Code:
       0: getstatic     #47                 // Field zio/aws/timestreamquery/model/QueryStatus$.MODULE$:Lzio/aws/timestreamquery/model/QueryStatus$;
       3: invokevirtual #67                 // Method zio/aws/timestreamquery/model/QueryStatus$.apply$default$2:()Lzio/prelude/data/Optional;
       6: areturn

  public static zio.prelude.data.Optional<java.lang.Object> apply$default$1();
    Code:
       0: getstatic     #47                 // Field zio/aws/timestreamquery/model/QueryStatus$.MODULE$:Lzio/aws/timestreamquery/model/QueryStatus$;
       3: invokevirtual #70                 // Method zio/aws/timestreamquery/model/QueryStatus$.apply$default$1:()Lzio/prelude/data/Optional;
       6: areturn

  public static zio.aws.timestreamquery.model.QueryStatus apply(zio.prelude.data.Optional<java.lang.Object>, zio.prelude.data.Optional<java.lang.Object>, zio.prelude.data.Optional<java.lang.Object>);
    Code:
       0: getstatic     #47                 // Field zio/aws/timestreamquery/model/QueryStatus$.MODULE$:Lzio/aws/timestreamquery/model/QueryStatus$;
       3: aload_0
       4: aload_1
       5: aload_2
       6: invokevirtual #75                 // Method zio/aws/timestreamquery/model/QueryStatus$.apply:(Lzio/prelude/data/Optional;Lzio/prelude/data/Optional;Lzio/prelude/data/Optional;)Lzio/aws/timestreamquery/model/QueryStatus;
       9: areturn

  public static zio.aws.timestreamquery.model.QueryStatus$ReadOnly wrap(software.amazon.awssdk.services.timestreamquery.model.QueryStatus);
    Code:
       0: getstatic     #47                 // Field zio/aws/timestreamquery/model/QueryStatus$.MODULE$:Lzio/aws/timestreamquery/model/QueryStatus$;
       3: aload_0
       4: invokevirtual #80                 // Method zio/aws/timestreamquery/model/QueryStatus$.wrap:(Lsoftware/amazon/awssdk/services/timestreamquery/model/QueryStatus;)Lzio/aws/timestreamquery/model/QueryStatus$ReadOnly;
       7: areturn

  public zio.prelude.data.Optional<java.lang.Object> progressPercentage();
    Code:
       0: aload_0
       1: getfield      #82                 // Field progressPercentage:Lzio/prelude/data/Optional;
       4: areturn

  public zio.prelude.data.Optional<java.lang.Object> cumulativeBytesScanned();
    Code:
       0: aload_0
       1: getfield      #86                 // Field cumulativeBytesScanned:Lzio/prelude/data/Optional;
       4: areturn

  public zio.prelude.data.Optional<java.lang.Object> cumulativeBytesMetered();
    Code:
       0: aload_0
       1: getfield      #88                 // Field cumulativeBytesMetered:Lzio/prelude/data/Optional;
       4: areturn

  public software.amazon.awssdk.services.timestreamquery.model.QueryStatus buildAwsValue();
    Code:
       0: getstatic     #47                 // Field zio/aws/timestreamquery/model/QueryStatus$.MODULE$:Lzio/aws/timestreamquery/model/QueryStatus$;
       3: invokevirtual #94                 // Method zio/aws/timestreamquery/model/QueryStatus$.zio$aws$timestreamquery$model$QueryStatus$$zioAwsBuilderHelper:()Lzio/aws/core/BuilderHelper;
       6: getstatic     #47                 // Field zio/aws/timestreamquery/model/QueryStatus$.MODULE$:Lzio/aws/timestreamquery/model/QueryStatus$;
       9: invokevirtual #94                 // Method zio/aws/timestreamquery/model/QueryStatus$.zio$aws$timestreamquery$model$QueryStatus$$zioAwsBuilderHelper:()Lzio/aws/core/BuilderHelper;
      12: getstatic     #47                 // Field zio/aws/timestreamquery/model/QueryStatus$.MODULE$:Lzio/aws/timestreamquery/model/QueryStatus$;
      15: invokevirtual #94                 // Method zio/aws/timestreamquery/model/QueryStatus$.zio$aws$timestreamquery$model$QueryStatus$$zioAwsBuilderHelper:()Lzio/aws/core/BuilderHelper;
      18: invokestatic  #98                 // Method software/amazon/awssdk/services/timestreamquery/model/QueryStatus.builder:()Lsoftware/amazon/awssdk/services/timestreamquery/model/QueryStatus$Builder;
      21: invokeinterface #101,  2          // InterfaceMethod zio/aws/core/BuilderHelper.BuilderOps:(Lsoftware/amazon/awssdk/utils/builder/SdkBuilder;)Lzio/aws/core/BuilderHelper$BuilderOps;
      26: aload_0
      27: invokevirtual #103                // Method progressPercentage:()Lzio/prelude/data/Optional;
      30: invokedynamic #123,  0            // InvokeDynamic #0:apply:()Lscala/Function1;
      35: invokeinterface #129,  2          // InterfaceMethod zio/prelude/data/Optional.map:(Lscala/Function1;)Lzio/prelude/data/Optional;
      40: invokedynamic #136,  0            // InvokeDynamic #1:apply:()Lscala/Function1;
      45: invokevirtual #140                // Method zio/aws/core/BuilderHelper$BuilderOps.optionallyWith:(Lzio/prelude/data/Optional;Lscala/Function1;)Lsoftware/amazon/awssdk/utils/builder/SdkBuilder;
      48: invokeinterface #101,  2          // InterfaceMethod zio/aws/core/BuilderHelper.BuilderOps:(Lsoftware/amazon/awssdk/utils/builder/SdkBuilder;)Lzio/aws/core/BuilderHelper$BuilderOps;
      53: aload_0
      54: invokevirtual #142                // Method cumulativeBytesScanned:()Lzio/prelude/data/Optional;
      57: invokedynamic #149,  0            // InvokeDynamic #2:apply:()Lscala/Function1;
      62: invokeinterface #129,  2          // InterfaceMethod zio/prelude/data/Optional.map:(Lscala/Function1;)Lzio/prelude/data/Optional;
      67: invokedynamic #154,  0            // InvokeDynamic #3:apply:()Lscala/Function1;
      72: invokevirtual #140                // Method zio/aws/core/BuilderHelper$BuilderOps.optionallyWith:(Lzio/prelude/data/Optional;Lscala/Function1;)Lsoftware/amazon/awssdk/utils/builder/SdkBuilder;
      75: invokeinterface #101,  2          // InterfaceMethod zio/aws/core/BuilderHelper.BuilderOps:(Lsoftware/amazon/awssdk/utils/builder/SdkBuilder;)Lzio/aws/core/BuilderHelper$BuilderOps;
      80: aload_0
      81: invokevirtual #156                // Method cumulativeBytesMetered:()Lzio/prelude/data/Optional;
      84: invokedynamic #161,  0            // InvokeDynamic #4:apply:()Lscala/Function1;
      89: invokeinterface #129,  2          // InterfaceMethod zio/prelude/data/Optional.map:(Lscala/Function1;)Lzio/prelude/data/Optional;
      94: invokedynamic #166,  0            // InvokeDynamic #5:apply:()Lscala/Function1;
      99: invokevirtual #140                // Method zio/aws/core/BuilderHelper$BuilderOps.optionallyWith:(Lzio/prelude/data/Optional;Lscala/Function1;)Lsoftware/amazon/awssdk/utils/builder/SdkBuilder;
     102: invokeinterface #172,  1          // InterfaceMethod software/amazon/awssdk/utils/builder/SdkBuilder.build:()Ljava/lang/Object;
     107: checkcast     #21                 // class software/amazon/awssdk/services/timestreamquery/model/QueryStatus
     110: areturn

  public zio.aws.timestreamquery.model.QueryStatus$ReadOnly asReadOnly();
    Code:
       0: getstatic     #47                 // Field zio/aws/timestreamquery/model/QueryStatus$.MODULE$:Lzio/aws/timestreamquery/model/QueryStatus$;
       3: aload_0
       4: invokevirtual #176                // Method buildAwsValue:()Lsoftware/amazon/awssdk/services/timestreamquery/model/QueryStatus;
       7: invokevirtual #80                 // Method zio/aws/timestreamquery/model/QueryStatus$.wrap:(Lsoftware/amazon/awssdk/services/timestreamquery/model/QueryStatus;)Lzio/aws/timestreamquery/model/QueryStatus$ReadOnly;
      10: areturn

  public zio.aws.timestreamquery.model.QueryStatus copy(zio.prelude.data.Optional<java.lang.Object>, zio.prelude.data.Optional<java.lang.Object>, zio.prelude.data.Optional<java.lang.Object>);
    Code:
       0: new           #2                  // class zio/aws/timestreamquery/model/QueryStatus
       3: dup
       4: aload_1
       5: aload_2
       6: aload_3
       7: invokespecial #181                // Method "<init>":(Lzio/prelude/data/Optional;Lzio/prelude/data/Optional;Lzio/prelude/data/Optional;)V
      10: areturn

  public zio.prelude.data.Optional<java.lang.Object> copy$default$1();
    Code:
       0: aload_0
       1: invokevirtual #103                // Method progressPercentage:()Lzio/prelude/data/Optional;
       4: areturn

  public zio.prelude.data.Optional<java.lang.Object> copy$default$2();
    Code:
       0: aload_0
       1: invokevirtual #142                // Method cumulativeBytesScanned:()Lzio/prelude/data/Optional;
       4: areturn

  public zio.prelude.data.Optional<java.lang.Object> copy$default$3();
    Code:
       0: aload_0
       1: invokevirtual #156                // Method cumulativeBytesMetered:()Lzio/prelude/data/Optional;
       4: areturn

  public java.lang.String productPrefix();
    Code:
       0: ldc           #188                // String QueryStatus
       2: areturn

  public int productArity();
    Code:
       0: iconst_3
       1: ireturn

  public java.lang.Object productElement(int);
    Code:
       0: iload_1
       1: istore_2
       2: iload_2
       3: tableswitch   { // 0 to 2
                     0: 28
                     1: 35
                     2: 42
               default: 49
          }
      28: aload_0
      29: invokevirtual #103                // Method progressPercentage:()Lzio/prelude/data/Optional;
      32: goto          61
      35: aload_0
      36: invokevirtual #142                // Method cumulativeBytesScanned:()Lzio/prelude/data/Optional;
      39: goto          61
      42: aload_0
      43: invokevirtual #156                // Method cumulativeBytesMetered:()Lzio/prelude/data/Optional;
      46: goto          61
      49: new           #195                // class java/lang/IndexOutOfBoundsException
      52: dup
      53: iload_1
      54: invokestatic  #201                // Method java/lang/Integer.toString:(I)Ljava/lang/String;
      57: invokespecial #204                // Method java/lang/IndexOutOfBoundsException."<init>":(Ljava/lang/String;)V
      60: athrow
      61: areturn

  public scala.collection.Iterator<java.lang.Object> productIterator();
    Code:
       0: getstatic     #213                // Field scala/runtime/ScalaRunTime$.MODULE$:Lscala/runtime/ScalaRunTime$;
       3: aload_0
       4: invokevirtual #217                // Method scala/runtime/ScalaRunTime$.typedProductIterator:(Lscala/Product;)Lscala/collection/Iterator;
       7: areturn

  public boolean canEqual(java.lang.Object);
    Code:
       0: aload_1
       1: instanceof    #2                  // class zio/aws/timestreamquery/model/QueryStatus
       4: ireturn

  public int hashCode();
    Code:
       0: getstatic     #213                // Field scala/runtime/ScalaRunTime$.MODULE$:Lscala/runtime/ScalaRunTime$;
       3: aload_0
       4: invokevirtual #225                // Method scala/runtime/ScalaRunTime$._hashCode:(Lscala/Product;)I
       7: ireturn

  public java.lang.String toString();
    Code:
       0: getstatic     #213                // Field scala/runtime/ScalaRunTime$.MODULE$:Lscala/runtime/ScalaRunTime$;
       3: aload_0
       4: invokevirtual #229                // Method scala/runtime/ScalaRunTime$._toString:(Lscala/Product;)Ljava/lang/String;
       7: areturn

  public boolean equals(java.lang.Object);
    Code:
       0: aload_0
       1: aload_1
       2: if_acmpeq     141
       5: aload_1
       6: astore_3
       7: aload_3
       8: instanceof    #2                  // class zio/aws/timestreamquery/model/QueryStatus
      11: ifeq          19
      14: iconst_1
      15: istore_2
      16: goto          27
      19: goto          22
      22: iconst_0
      23: istore_2
      24: goto          27
      27: iload_2
      28: ifeq          145
      31: aload_1
      32: checkcast     #2                  // class zio/aws/timestreamquery/model/QueryStatus
      35: astore        4
      37: aload_0
      38: invokevirtual #103                // Method progressPercentage:()Lzio/prelude/data/Optional;
      41: aload         4
      43: invokevirtual #103                // Method progressPercentage:()Lzio/prelude/data/Optional;
      46: astore        5
      48: dup
      49: ifnonnull     61
      52: pop
      53: aload         5
      55: ifnull        69
      58: goto          137
      61: aload         5
      63: invokevirtual #232                // Method java/lang/Object.equals:(Ljava/lang/Object;)Z
      66: ifeq          137
      69: aload_0
      70: invokevirtual #142                // Method cumulativeBytesScanned:()Lzio/prelude/data/Optional;
      73: aload         4
      75: invokevirtual #142                // Method cumulativeBytesScanned:()Lzio/prelude/data/Optional;
      78: astore        6
      80: dup
      81: ifnonnull     93
      84: pop
      85: aload         6
      87: ifnull        101
      90: goto          137
      93: aload         6
      95: invokevirtual #232                // Method java/lang/Object.equals:(Ljava/lang/Object;)Z
      98: ifeq          137
     101: aload_0
     102: invokevirtual #156                // Method cumulativeBytesMetered:()Lzio/prelude/data/Optional;
     105: aload         4
     107: invokevirtual #156                // Method cumulativeBytesMetered:()Lzio/prelude/data/Optional;
     110: astore        7
     112: dup
     113: ifnonnull     125
     116: pop
     117: aload         7
     119: ifnull        133
     122: goto          137
     125: aload         7
     127: invokevirtual #232                // Method java/lang/Object.equals:(Ljava/lang/Object;)Z
     130: ifeq          137
     133: iconst_1
     134: goto          138
     137: iconst_0
     138: ifeq          145
     141: iconst_1
     142: goto          146
     145: iconst_0
     146: ireturn

  public static final java.lang.Double $anonfun$buildAwsValue$1(double);
    Code:
       0: getstatic     #240                // Field scala/Predef$.MODULE$:Lscala/Predef$;
       3: dload_0
       4: invokevirtual #243                // Method scala/Predef$.double2Double:(D)Ljava/lang/Double;
       7: areturn

  public static final software.amazon.awssdk.services.timestreamquery.model.QueryStatus$Builder $anonfun$buildAwsValue$3(software.amazon.awssdk.services.timestreamquery.model.QueryStatus$Builder, java.lang.Double);
    Code:
       0: aload_0
       1: aload_1
       2: invokeinterface #250,  2          // InterfaceMethod software/amazon/awssdk/services/timestreamquery/model/QueryStatus$Builder.progressPercentage:(Ljava/lang/Double;)Lsoftware/amazon/awssdk/services/timestreamquery/model/QueryStatus$Builder;
       7: areturn

  public static final scala.Function1 $anonfun$buildAwsValue$2(software.amazon.awssdk.services.timestreamquery.model.QueryStatus$Builder);
    Code:
       0: aload_0
       1: invokedynamic #258,  0            // InvokeDynamic #6:apply:(Lsoftware/amazon/awssdk/services/timestreamquery/model/QueryStatus$Builder;)Lscala/Function1;
       6: areturn

  public static final java.lang.Long $anonfun$buildAwsValue$4(long);
    Code:
       0: getstatic     #240                // Field scala/Predef$.MODULE$:Lscala/Predef$;
       3: lload_0
       4: invokevirtual #263                // Method scala/Predef$.long2Long:(J)Ljava/lang/Long;
       7: areturn

  public static final software.amazon.awssdk.services.timestreamquery.model.QueryStatus$Builder $anonfun$buildAwsValue$6(software.amazon.awssdk.services.timestreamquery.model.QueryStatus$Builder, java.lang.Long);
    Code:
       0: aload_0
       1: aload_1
       2: invokeinterface #270,  2          // InterfaceMethod software/amazon/awssdk/services/timestreamquery/model/QueryStatus$Builder.cumulativeBytesScanned:(Ljava/lang/Long;)Lsoftware/amazon/awssdk/services/timestreamquery/model/QueryStatus$Builder;
       7: areturn

  public static final scala.Function1 $anonfun$buildAwsValue$5(software.amazon.awssdk.services.timestreamquery.model.QueryStatus$Builder);
    Code:
       0: aload_0
       1: invokedynamic #277,  0            // InvokeDynamic #7:apply:(Lsoftware/amazon/awssdk/services/timestreamquery/model/QueryStatus$Builder;)Lscala/Function1;
       6: areturn

  public static final java.lang.Long $anonfun$buildAwsValue$7(long);
    Code:
       0: getstatic     #240                // Field scala/Predef$.MODULE$:Lscala/Predef$;
       3: lload_0
       4: invokevirtual #263                // Method scala/Predef$.long2Long:(J)Ljava/lang/Long;
       7: areturn

  public static final software.amazon.awssdk.services.timestreamquery.model.QueryStatus$Builder $anonfun$buildAwsValue$9(software.amazon.awssdk.services.timestreamquery.model.QueryStatus$Builder, java.lang.Long);
    Code:
       0: aload_0
       1: aload_1
       2: invokeinterface #282,  2          // InterfaceMethod software/amazon/awssdk/services/timestreamquery/model/QueryStatus$Builder.cumulativeBytesMetered:(Ljava/lang/Long;)Lsoftware/amazon/awssdk/services/timestreamquery/model/QueryStatus$Builder;
       7: areturn

  public static final scala.Function1 $anonfun$buildAwsValue$8(software.amazon.awssdk.services.timestreamquery.model.QueryStatus$Builder);
    Code:
       0: aload_0
       1: invokedynamic #287,  0            // InvokeDynamic #8:apply:(Lsoftware/amazon/awssdk/services/timestreamquery/model/QueryStatus$Builder;)Lscala/Function1;
       6: areturn

  public zio.aws.timestreamquery.model.QueryStatus(zio.prelude.data.Optional<java.lang.Object>, zio.prelude.data.Optional<java.lang.Object>, zio.prelude.data.Optional<java.lang.Object>);
    Code:
       0: aload_0
       1: aload_1
       2: putfield      #82                 // Field progressPercentage:Lzio/prelude/data/Optional;
       5: aload_0
       6: aload_2
       7: putfield      #86                 // Field cumulativeBytesScanned:Lzio/prelude/data/Optional;
      10: aload_0
      11: aload_3
      12: putfield      #88                 // Field cumulativeBytesMetered:Lzio/prelude/data/Optional;
      15: aload_0
      16: invokespecial #291                // Method java/lang/Object."<init>":()V
      19: aload_0
      20: invokestatic  #295                // InterfaceMethod scala/Product.$init$:(Lscala/Product;)V
      23: return

  public static final java.lang.Double $anonfun$buildAwsValue$1$adapted(java.lang.Object);
    Code:
       0: aload_0
       1: invokestatic  #301                // Method scala/runtime/BoxesRunTime.unboxToDouble:(Ljava/lang/Object;)D
       4: invokestatic  #303                // Method $anonfun$buildAwsValue$1:(D)Ljava/lang/Double;
       7: areturn

  public static final java.lang.Long $anonfun$buildAwsValue$4$adapted(java.lang.Object);
    Code:
       0: aload_0
       1: invokestatic  #307                // Method scala/runtime/BoxesRunTime.unboxToLong:(Ljava/lang/Object;)J
       4: invokestatic  #309                // Method $anonfun$buildAwsValue$4:(J)Ljava/lang/Long;
       7: areturn

  public static final java.lang.Long $anonfun$buildAwsValue$7$adapted(java.lang.Object);
    Code:
       0: aload_0
       1: invokestatic  #307                // Method scala/runtime/BoxesRunTime.unboxToLong:(Ljava/lang/Object;)J
       4: invokestatic  #311                // Method $anonfun$buildAwsValue$7:(J)Ljava/lang/Long;
       7: areturn

  private static java.lang.Object $deserializeLambda$(java.lang.invoke.SerializedLambda);
    Code:
       0: aload_0
       1: invokedynamic #323,  0            // InvokeDynamic #9:lambdaDeserialize:(Ljava/lang/invoke/SerializedLambda;)Ljava/lang/Object;
       6: areturn
}
