Compiled from "S3ReportLocation.scala"
public interface zio.aws.timestreamquery.model.S3ReportLocation$ReadOnly {
  public static zio.aws.timestreamquery.model.S3ReportLocation asEditable$(zio.aws.timestreamquery.model.S3ReportLocation$ReadOnly);
    Code:
       0: aload_0
       1: invokespecial #20                 // InterfaceMethod asEditable:()Lzio/aws/timestreamquery/model/S3ReportLocation;
       4: areturn

  public default zio.aws.timestreamquery.model.S3ReportLocation asEditable();
    Code:
       0: new           #12                 // class zio/aws/timestreamquery/model/S3ReportLocation
       3: dup
       4: aload_0
       5: invokeinterface #25,  1           // InterfaceMethod bucketName:()Lzio/prelude/data/Optional;
      10: invokedynamic #48,  0             // InvokeDynamic #0:apply:()Lscala/Function1;
      15: invokeinterface #54,  2           // InterfaceMethod zio/prelude/data/Optional.map:(Lscala/Function1;)Lzio/prelude/data/Optional;
      20: aload_0
      21: invokeinterface #57,  1           // InterfaceMethod objectKey:()Lzio/prelude/data/Optional;
      26: invokedynamic #62,  0             // InvokeDynamic #1:apply:()Lscala/Function1;
      31: invokeinterface #54,  2           // InterfaceMethod zio/prelude/data/Optional.map:(Lscala/Function1;)Lzio/prelude/data/Optional;
      36: invokespecial #66                 // Method zio/aws/timestreamquery/model/S3ReportLocation."<init>":(Lzio/prelude/data/Optional;Lzio/prelude/data/Optional;)V
      39: areturn

  public abstract zio.prelude.data.Optional<java.lang.String> bucketName();

  public abstract zio.prelude.data.Optional<java.lang.String> objectKey();

  public static zio.ZIO getBucketName$(zio.aws.timestreamquery.model.S3ReportLocation$ReadOnly);
    Code:
       0: aload_0
       1: invokespecial #74                 // InterfaceMethod getBucketName:()Lzio/ZIO;
       4: areturn

  public default zio.ZIO<java.lang.Object, zio.aws.core.AwsError, java.lang.String> getBucketName();
    Code:
       0: getstatic     #81                 // Field zio/aws/core/AwsError$.MODULE$:Lzio/aws/core/AwsError$;
       3: ldc           #82                 // String bucketName
       5: aload_0
       6: invokedynamic #93,  0             // InvokeDynamic #2:apply:(Lzio/aws/timestreamquery/model/S3ReportLocation$ReadOnly;)Lscala/Function0;
      11: invokevirtual #97                 // Method zio/aws/core/AwsError$.unwrapOptionField:(Ljava/lang/String;Lscala/Function0;)Lzio/ZIO;
      14: areturn

  public static zio.ZIO getObjectKey$(zio.aws.timestreamquery.model.S3ReportLocation$ReadOnly);
    Code:
       0: aload_0
       1: invokespecial #101                // InterfaceMethod getObjectKey:()Lzio/ZIO;
       4: areturn

  public default zio.ZIO<java.lang.Object, zio.aws.core.AwsError, java.lang.String> getObjectKey();
    Code:
       0: getstatic     #81                 // Field zio/aws/core/AwsError$.MODULE$:Lzio/aws/core/AwsError$;
       3: ldc           #102                // String objectKey
       5: aload_0
       6: invokedynamic #107,  0            // InvokeDynamic #3:apply:(Lzio/aws/timestreamquery/model/S3ReportLocation$ReadOnly;)Lscala/Function0;
      11: invokevirtual #97                 // Method zio/aws/core/AwsError$.unwrapOptionField:(Ljava/lang/String;Lscala/Function0;)Lzio/ZIO;
      14: areturn

  public static java.lang.String $anonfun$asEditable$1(java.lang.String);
    Code:
       0: aload_0
       1: areturn

  public static java.lang.String $anonfun$asEditable$2(java.lang.String);
    Code:
       0: aload_0
       1: areturn

  public static zio.prelude.data.Optional $anonfun$getBucketName$1(zio.aws.timestreamquery.model.S3ReportLocation$ReadOnly);
    Code:
       0: aload_0
       1: invokeinterface #25,  1           // InterfaceMethod bucketName:()Lzio/prelude/data/Optional;
       6: areturn

  public static zio.prelude.data.Optional $anonfun$getObjectKey$1(zio.aws.timestreamquery.model.S3ReportLocation$ReadOnly);
    Code:
       0: aload_0
       1: invokeinterface #57,  1           // InterfaceMethod objectKey:()Lzio/prelude/data/Optional;
       6: areturn

  public static void $init$(zio.aws.timestreamquery.model.S3ReportLocation$ReadOnly);
    Code:
       0: return

  private static java.lang.Object $deserializeLambda$(java.lang.invoke.SerializedLambda);
    Code:
       0: aload_0
       1: invokedynamic #123,  0            // InvokeDynamic #4:lambdaDeserialize:(Ljava/lang/invoke/SerializedLambda;)Ljava/lang/Object;
       6: areturn
}
