Compiled from "CglibAopProxy.java"
class org.springframework.aop.framework.CglibAopProxy$DynamicAdvisedInterceptor implements org.springframework.cglib.proxy.MethodInterceptor,java.io.Serializable {
  private final org.springframework.aop.framework.AdvisedSupport advised;

  public org.springframework.aop.framework.CglibAopProxy$DynamicAdvisedInterceptor(org.springframework.aop.framework.AdvisedSupport);
    Code:
       0: aload_0
       1: invokespecial #1                  // Method java/lang/Object."<init>":()V
       4: aload_0
       5: aload_1
       6: putfield      #2                  // Field advised:Lorg/springframework/aop/framework/AdvisedSupport;
       9: return

  public java.lang.Object intercept(java.lang.Object, java.lang.reflect.Method, java.lang.Object[], org.springframework.cglib.proxy.MethodProxy) throws java.lang.Throwable;
    Code:
       0: aconst_null
       1: astore        5
       3: iconst_0
       4: istore        6
       6: aconst_null
       7: astore        7
       9: aconst_null
      10: astore        8
      12: aload_0
      13: getfield      #2                  // Field advised:Lorg/springframework/aop/framework/AdvisedSupport;
      16: getfield      #3                  // Field org/springframework/aop/framework/AdvisedSupport.exposeProxy:Z
      19: ifeq          31
      22: aload_1
      23: invokestatic  #4                  // Method org/springframework/aop/framework/AopContext.setCurrentProxy:(Ljava/lang/Object;)Ljava/lang/Object;
      26: astore        5
      28: iconst_1
      29: istore        6
      31: aload_0
      32: invokevirtual #5                  // Method getTarget:()Ljava/lang/Object;
      35: astore        8
      37: aload         8
      39: ifnull        49
      42: aload         8
      44: invokevirtual #6                  // Method java/lang/Object.getClass:()Ljava/lang/Class;
      47: astore        7
      49: aload_0
      50: getfield      #2                  // Field advised:Lorg/springframework/aop/framework/AdvisedSupport;
      53: aload_2
      54: aload         7
      56: invokevirtual #7                  // Method org/springframework/aop/framework/AdvisedSupport.getInterceptorsAndDynamicInterceptionAdvice:(Ljava/lang/reflect/Method;Ljava/lang/Class;)Ljava/util/List;
      59: astore        9
      61: aload         9
      63: invokeinterface #8,  1            // InterfaceMethod java/util/List.isEmpty:()Z
      68: ifeq          102
      71: aload_2
      72: invokevirtual #9                  // Method java/lang/reflect/Method.getModifiers:()I
      75: invokestatic  #10                 // Method java/lang/reflect/Modifier.isPublic:(I)Z
      78: ifeq          102
      81: aload_2
      82: aload_3
      83: invokestatic  #11                 // Method org/springframework/aop/framework/AopProxyUtils.adaptArgumentsIfNecessary:(Ljava/lang/reflect/Method;[Ljava/lang/Object;)[Ljava/lang/Object;
      86: astore        11
      88: aload         4
      90: aload         8
      92: aload         11
      94: invokevirtual #12                 // Method org/springframework/cglib/proxy/MethodProxy.invoke:(Ljava/lang/Object;[Ljava/lang/Object;)Ljava/lang/Object;
      97: astore        10
      99: goto          125
     102: new           #13                 // class org/springframework/aop/framework/CglibAopProxy$CglibMethodInvocation
     105: dup
     106: aload_1
     107: aload         8
     109: aload_2
     110: aload_3
     111: aload         7
     113: aload         9
     115: aload         4
     117: invokespecial #14                 // Method org/springframework/aop/framework/CglibAopProxy$CglibMethodInvocation."<init>":(Ljava/lang/Object;Ljava/lang/Object;Ljava/lang/reflect/Method;[Ljava/lang/Object;Ljava/lang/Class;Ljava/util/List;Lorg/springframework/cglib/proxy/MethodProxy;)V
     120: invokevirtual #15                 // Method org/springframework/aop/framework/CglibAopProxy$CglibMethodInvocation.proceed:()Ljava/lang/Object;
     123: astore        10
     125: aload_1
     126: aload         8
     128: aload_2
     129: aload         10
     131: invokestatic  #16                 // Method org/springframework/aop/framework/CglibAopProxy.access$000:(Ljava/lang/Object;Ljava/lang/Object;Ljava/lang/reflect/Method;Ljava/lang/Object;)Ljava/lang/Object;
     134: astore        10
     136: aload         10
     138: astore        11
     140: aload         8
     142: ifnull        151
     145: aload_0
     146: aload         8
     148: invokevirtual #17                 // Method releaseTarget:(Ljava/lang/Object;)V
     151: iload         6
     153: ifeq          162
     156: aload         5
     158: invokestatic  #4                  // Method org/springframework/aop/framework/AopContext.setCurrentProxy:(Ljava/lang/Object;)Ljava/lang/Object;
     161: pop
     162: aload         11
     164: areturn
     165: astore        12
     167: aload         8
     169: ifnull        178
     172: aload_0
     173: aload         8
     175: invokevirtual #17                 // Method releaseTarget:(Ljava/lang/Object;)V
     178: iload         6
     180: ifeq          189
     183: aload         5
     185: invokestatic  #4                  // Method org/springframework/aop/framework/AopContext.setCurrentProxy:(Ljava/lang/Object;)Ljava/lang/Object;
     188: pop
     189: aload         12
     191: athrow
    Exception table:
       from    to  target type
          12   140   165   any
         165   167   165   any

  public boolean equals(java.lang.Object);
    Code:
       0: aload_0
       1: aload_1
       2: if_acmpeq     29
       5: aload_1
       6: instanceof    #18                 // class org/springframework/aop/framework/CglibAopProxy$DynamicAdvisedInterceptor
       9: ifeq          33
      12: aload_0
      13: getfield      #2                  // Field advised:Lorg/springframework/aop/framework/AdvisedSupport;
      16: aload_1
      17: checkcast     #18                 // class org/springframework/aop/framework/CglibAopProxy$DynamicAdvisedInterceptor
      20: getfield      #2                  // Field advised:Lorg/springframework/aop/framework/AdvisedSupport;
      23: invokevirtual #19                 // Method java/lang/Object.equals:(Ljava/lang/Object;)Z
      26: ifeq          33
      29: iconst_1
      30: goto          34
      33: iconst_0
      34: ireturn

  public int hashCode();
    Code:
       0: aload_0
       1: getfield      #2                  // Field advised:Lorg/springframework/aop/framework/AdvisedSupport;
       4: invokevirtual #20                 // Method java/lang/Object.hashCode:()I
       7: ireturn

  protected java.lang.Object getTarget() throws java.lang.Exception;
    Code:
       0: aload_0
       1: getfield      #2                  // Field advised:Lorg/springframework/aop/framework/AdvisedSupport;
       4: invokevirtual #21                 // Method org/springframework/aop/framework/AdvisedSupport.getTargetSource:()Lorg/springframework/aop/TargetSource;
       7: invokeinterface #22,  1           // InterfaceMethod org/springframework/aop/TargetSource.getTarget:()Ljava/lang/Object;
      12: areturn

  protected void releaseTarget(java.lang.Object) throws java.lang.Exception;
    Code:
       0: aload_0
       1: getfield      #2                  // Field advised:Lorg/springframework/aop/framework/AdvisedSupport;
       4: invokevirtual #21                 // Method org/springframework/aop/framework/AdvisedSupport.getTargetSource:()Lorg/springframework/aop/TargetSource;
       7: aload_1
       8: invokeinterface #23,  2           // InterfaceMethod org/springframework/aop/TargetSource.releaseTarget:(Ljava/lang/Object;)V
      13: return
}
