Compiled from "GenericScope.java"
public class org.springframework.cloud.context.scope.GenericScope implements org.springframework.beans.factory.config.Scope,org.springframework.beans.factory.config.BeanFactoryPostProcessor,org.springframework.beans.factory.support.BeanDefinitionRegistryPostProcessor,org.springframework.beans.factory.DisposableBean {
  private static final org.apache.commons.logging.Log logger;

  public static final java.lang.String SCOPED_TARGET_PREFIX;

  private org.springframework.cloud.context.scope.GenericScope$BeanLifecycleWrapperCache cache;

  private java.lang.String name;

  private org.springframework.beans.factory.config.ConfigurableListableBeanFactory beanFactory;

  private org.springframework.expression.spel.support.StandardEvaluationContext evaluationContext;

  private java.lang.String id;

  private java.util.Map<java.lang.String, java.lang.Exception> errors;

  private java.util.concurrent.ConcurrentMap<java.lang.String, java.util.concurrent.locks.ReadWriteLock> locks;

  public org.springframework.cloud.context.scope.GenericScope();
    Code:
       0: aload_0
       1: invokespecial #2                  // Method java/lang/Object."<init>":()V
       4: aload_0
       5: new           #3                  // class org/springframework/cloud/context/scope/GenericScope$BeanLifecycleWrapperCache
       8: dup
       9: new           #4                  // class org/springframework/cloud/context/scope/StandardScopeCache
      12: dup
      13: invokespecial #5                  // Method org/springframework/cloud/context/scope/StandardScopeCache."<init>":()V
      16: invokespecial #6                  // Method org/springframework/cloud/context/scope/GenericScope$BeanLifecycleWrapperCache."<init>":(Lorg/springframework/cloud/context/scope/ScopeCache;)V
      19: putfield      #7                  // Field cache:Lorg/springframework/cloud/context/scope/GenericScope$BeanLifecycleWrapperCache;
      22: aload_0
      23: ldc           #8                  // String generic
      25: putfield      #9                  // Field name:Ljava/lang/String;
      28: aload_0
      29: new           #10                 // class java/util/concurrent/ConcurrentHashMap
      32: dup
      33: invokespecial #11                 // Method java/util/concurrent/ConcurrentHashMap."<init>":()V
      36: putfield      #12                 // Field errors:Ljava/util/Map;
      39: aload_0
      40: new           #10                 // class java/util/concurrent/ConcurrentHashMap
      43: dup
      44: invokespecial #11                 // Method java/util/concurrent/ConcurrentHashMap."<init>":()V
      47: putfield      #13                 // Field locks:Ljava/util/concurrent/ConcurrentMap;
      50: return

  public void setId(java.lang.String);
    Code:
       0: aload_0
       1: aload_1
       2: putfield      #14                 // Field id:Ljava/lang/String;
       5: return

  public void setName(java.lang.String);
    Code:
       0: aload_0
       1: aload_1
       2: putfield      #9                  // Field name:Ljava/lang/String;
       5: return

  public void setScopeCache(org.springframework.cloud.context.scope.ScopeCache);
    Code:
       0: aload_0
       1: new           #3                  // class org/springframework/cloud/context/scope/GenericScope$BeanLifecycleWrapperCache
       4: dup
       5: aload_1
       6: invokespecial #6                  // Method org/springframework/cloud/context/scope/GenericScope$BeanLifecycleWrapperCache."<init>":(Lorg/springframework/cloud/context/scope/ScopeCache;)V
       9: putfield      #7                  // Field cache:Lorg/springframework/cloud/context/scope/GenericScope$BeanLifecycleWrapperCache;
      12: return

  public java.util.Map<java.lang.String, java.lang.Exception> getErrors();
    Code:
       0: aload_0
       1: getfield      #12                 // Field errors:Ljava/util/Map;
       4: areturn

  public void destroy();
    Code:
       0: new           #15                 // class java/util/ArrayList
       3: dup
       4: invokespecial #16                 // Method java/util/ArrayList."<init>":()V
       7: astore_1
       8: aload_0
       9: getfield      #7                  // Field cache:Lorg/springframework/cloud/context/scope/GenericScope$BeanLifecycleWrapperCache;
      12: invokevirtual #17                 // Method org/springframework/cloud/context/scope/GenericScope$BeanLifecycleWrapperCache.clear:()Ljava/util/Collection;
      15: astore_2
      16: aload_2
      17: invokeinterface #18,  1           // InterfaceMethod java/util/Collection.iterator:()Ljava/util/Iterator;
      22: astore_3
      23: aload_3
      24: invokeinterface #19,  1           // InterfaceMethod java/util/Iterator.hasNext:()Z
      29: ifeq          118
      32: aload_3
      33: invokeinterface #20,  1           // InterfaceMethod java/util/Iterator.next:()Ljava/lang/Object;
      38: checkcast     #21                 // class org/springframework/cloud/context/scope/GenericScope$BeanLifecycleWrapper
      41: astore        4
      43: aload_0
      44: getfield      #13                 // Field locks:Ljava/util/concurrent/ConcurrentMap;
      47: aload         4
      49: invokevirtual #22                 // Method org/springframework/cloud/context/scope/GenericScope$BeanLifecycleWrapper.getName:()Ljava/lang/String;
      52: invokeinterface #23,  2           // InterfaceMethod java/util/concurrent/ConcurrentMap.get:(Ljava/lang/Object;)Ljava/lang/Object;
      57: checkcast     #24                 // class java/util/concurrent/locks/ReadWriteLock
      60: invokeinterface #25,  1           // InterfaceMethod java/util/concurrent/locks/ReadWriteLock.writeLock:()Ljava/util/concurrent/locks/Lock;
      65: astore        5
      67: aload         5
      69: invokeinterface #26,  1           // InterfaceMethod java/util/concurrent/locks/Lock.lock:()V
      74: aload         4
      76: invokevirtual #27                 // Method org/springframework/cloud/context/scope/GenericScope$BeanLifecycleWrapper.destroy:()V
      79: aload         5
      81: invokeinterface #28,  1           // InterfaceMethod java/util/concurrent/locks/Lock.unlock:()V
      86: goto          101
      89: astore        6
      91: aload         5
      93: invokeinterface #28,  1           // InterfaceMethod java/util/concurrent/locks/Lock.unlock:()V
      98: aload         6
     100: athrow
     101: goto          115
     104: astore        5
     106: aload_1
     107: aload         5
     109: invokeinterface #30,  2           // InterfaceMethod java/util/List.add:(Ljava/lang/Object;)Z
     114: pop
     115: goto          23
     118: aload_1
     119: invokeinterface #31,  1           // InterfaceMethod java/util/List.isEmpty:()Z
     124: ifne          141
     127: aload_1
     128: iconst_0
     129: invokeinterface #32,  2           // InterfaceMethod java/util/List.get:(I)Ljava/lang/Object;
     134: checkcast     #33                 // class java/lang/Throwable
     137: invokestatic  #34                 // Method wrapIfNecessary:(Ljava/lang/Throwable;)Ljava/lang/RuntimeException;
     140: athrow
     141: aload_0
     142: getfield      #12                 // Field errors:Ljava/util/Map;
     145: invokeinterface #35,  1           // InterfaceMethod java/util/Map.clear:()V
     150: return
    Exception table:
       from    to  target type
          74    79    89   any
          89    91    89   any
          43   101   104   Class java/lang/RuntimeException

  protected boolean destroy(java.lang.String);
    Code:
       0: aload_0
       1: getfield      #7                  // Field cache:Lorg/springframework/cloud/context/scope/GenericScope$BeanLifecycleWrapperCache;
       4: aload_1
       5: invokevirtual #36                 // Method org/springframework/cloud/context/scope/GenericScope$BeanLifecycleWrapperCache.remove:(Ljava/lang/String;)Lorg/springframework/cloud/context/scope/GenericScope$BeanLifecycleWrapper;
       8: astore_2
       9: aload_2
      10: ifnull        78
      13: aload_0
      14: getfield      #13                 // Field locks:Ljava/util/concurrent/ConcurrentMap;
      17: aload_2
      18: invokevirtual #22                 // Method org/springframework/cloud/context/scope/GenericScope$BeanLifecycleWrapper.getName:()Ljava/lang/String;
      21: invokeinterface #23,  2           // InterfaceMethod java/util/concurrent/ConcurrentMap.get:(Ljava/lang/Object;)Ljava/lang/Object;
      26: checkcast     #24                 // class java/util/concurrent/locks/ReadWriteLock
      29: invokeinterface #25,  1           // InterfaceMethod java/util/concurrent/locks/ReadWriteLock.writeLock:()Ljava/util/concurrent/locks/Lock;
      34: astore_3
      35: aload_3
      36: invokeinterface #26,  1           // InterfaceMethod java/util/concurrent/locks/Lock.lock:()V
      41: aload_2
      42: invokevirtual #27                 // Method org/springframework/cloud/context/scope/GenericScope$BeanLifecycleWrapper.destroy:()V
      45: aload_3
      46: invokeinterface #28,  1           // InterfaceMethod java/util/concurrent/locks/Lock.unlock:()V
      51: goto          65
      54: astore        4
      56: aload_3
      57: invokeinterface #28,  1           // InterfaceMethod java/util/concurrent/locks/Lock.unlock:()V
      62: aload         4
      64: athrow
      65: aload_0
      66: getfield      #12                 // Field errors:Ljava/util/Map;
      69: aload_1
      70: invokeinterface #37,  2           // InterfaceMethod java/util/Map.remove:(Ljava/lang/Object;)Ljava/lang/Object;
      75: pop
      76: iconst_1
      77: ireturn
      78: iconst_0
      79: ireturn
    Exception table:
       from    to  target type
          41    45    54   any
          54    56    54   any

  public java.lang.Object get(java.lang.String, org.springframework.beans.factory.ObjectFactory<?>);
    Code:
       0: aload_0
       1: getfield      #7                  // Field cache:Lorg/springframework/cloud/context/scope/GenericScope$BeanLifecycleWrapperCache;
       4: aload_1
       5: new           #21                 // class org/springframework/cloud/context/scope/GenericScope$BeanLifecycleWrapper
       8: dup
       9: aload_1
      10: aload_2
      11: invokespecial #38                 // Method org/springframework/cloud/context/scope/GenericScope$BeanLifecycleWrapper."<init>":(Ljava/lang/String;Lorg/springframework/beans/factory/ObjectFactory;)V
      14: invokevirtual #39                 // Method org/springframework/cloud/context/scope/GenericScope$BeanLifecycleWrapperCache.put:(Ljava/lang/String;Lorg/springframework/cloud/context/scope/GenericScope$BeanLifecycleWrapper;)Lorg/springframework/cloud/context/scope/GenericScope$BeanLifecycleWrapper;
      17: astore_3
      18: aload_0
      19: getfield      #13                 // Field locks:Ljava/util/concurrent/ConcurrentMap;
      22: aload_1
      23: new           #40                 // class java/util/concurrent/locks/ReentrantReadWriteLock
      26: dup
      27: invokespecial #41                 // Method java/util/concurrent/locks/ReentrantReadWriteLock."<init>":()V
      30: invokeinterface #42,  3           // InterfaceMethod java/util/concurrent/ConcurrentMap.putIfAbsent:(Ljava/lang/Object;Ljava/lang/Object;)Ljava/lang/Object;
      35: pop
      36: aload_3
      37: invokevirtual #43                 // Method org/springframework/cloud/context/scope/GenericScope$BeanLifecycleWrapper.getBean:()Ljava/lang/Object;
      40: areturn
      41: astore        4
      43: aload_0
      44: getfield      #12                 // Field errors:Ljava/util/Map;
      47: aload_1
      48: aload         4
      50: invokeinterface #44,  3           // InterfaceMethod java/util/Map.put:(Ljava/lang/Object;Ljava/lang/Object;)Ljava/lang/Object;
      55: pop
      56: aload         4
      58: athrow
    Exception table:
       from    to  target type
          36    40    41   Class java/lang/RuntimeException

  public java.lang.String getConversationId();
    Code:
       0: aload_0
       1: getfield      #9                  // Field name:Ljava/lang/String;
       4: areturn

  public void registerDestructionCallback(java.lang.String, java.lang.Runnable);
    Code:
       0: aload_0
       1: getfield      #7                  // Field cache:Lorg/springframework/cloud/context/scope/GenericScope$BeanLifecycleWrapperCache;
       4: aload_1
       5: invokevirtual #45                 // Method org/springframework/cloud/context/scope/GenericScope$BeanLifecycleWrapperCache.get:(Ljava/lang/String;)Lorg/springframework/cloud/context/scope/GenericScope$BeanLifecycleWrapper;
       8: astore_3
       9: aload_3
      10: ifnonnull     14
      13: return
      14: aload_3
      15: aload_2
      16: invokevirtual #46                 // Method org/springframework/cloud/context/scope/GenericScope$BeanLifecycleWrapper.setDestroyCallback:(Ljava/lang/Runnable;)V
      19: return

  public java.lang.Object remove(java.lang.String);
    Code:
       0: aload_0
       1: getfield      #7                  // Field cache:Lorg/springframework/cloud/context/scope/GenericScope$BeanLifecycleWrapperCache;
       4: aload_1
       5: invokevirtual #36                 // Method org/springframework/cloud/context/scope/GenericScope$BeanLifecycleWrapperCache.remove:(Ljava/lang/String;)Lorg/springframework/cloud/context/scope/GenericScope$BeanLifecycleWrapper;
       8: astore_2
       9: aload_2
      10: ifnonnull     15
      13: aconst_null
      14: areturn
      15: aload_2
      16: invokevirtual #43                 // Method org/springframework/cloud/context/scope/GenericScope$BeanLifecycleWrapper.getBean:()Ljava/lang/Object;
      19: areturn

  public java.lang.Object resolveContextualObject(java.lang.String);
    Code:
       0: aload_0
       1: aload_1
       2: invokespecial #47                 // Method parseExpression:(Ljava/lang/String;)Lorg/springframework/expression/Expression;
       5: astore_2
       6: aload_2
       7: aload_0
       8: getfield      #48                 // Field evaluationContext:Lorg/springframework/expression/spel/support/StandardEvaluationContext;
      11: aload_0
      12: getfield      #49                 // Field beanFactory:Lorg/springframework/beans/factory/config/ConfigurableListableBeanFactory;
      15: invokeinterface #50,  3           // InterfaceMethod org/springframework/expression/Expression.getValue:(Lorg/springframework/expression/EvaluationContext;Ljava/lang/Object;)Ljava/lang/Object;
      20: areturn

  private org.springframework.expression.Expression parseExpression(java.lang.String);
    Code:
       0: aload_1
       1: invokestatic  #51                 // Method org/springframework/util/StringUtils.hasText:(Ljava/lang/String;)Z
       4: ifeq          52
       7: new           #52                 // class org/springframework/expression/spel/standard/SpelExpressionParser
      10: dup
      11: invokespecial #53                 // Method org/springframework/expression/spel/standard/SpelExpressionParser."<init>":()V
      14: astore_2
      15: aload_2
      16: aload_1
      17: invokeinterface #54,  2           // InterfaceMethod org/springframework/expression/ExpressionParser.parseExpression:(Ljava/lang/String;)Lorg/springframework/expression/Expression;
      22: areturn
      23: astore_3
      24: new           #56                 // class java/lang/IllegalArgumentException
      27: dup
      28: new           #57                 // class java/lang/StringBuilder
      31: dup
      32: invokespecial #58                 // Method java/lang/StringBuilder."<init>":()V
      35: ldc           #59                 // String Cannot parse expression:
      37: invokevirtual #60                 // Method java/lang/StringBuilder.append:(Ljava/lang/String;)Ljava/lang/StringBuilder;
      40: aload_1
      41: invokevirtual #60                 // Method java/lang/StringBuilder.append:(Ljava/lang/String;)Ljava/lang/StringBuilder;
      44: invokevirtual #61                 // Method java/lang/StringBuilder.toString:()Ljava/lang/String;
      47: aload_3
      48: invokespecial #62                 // Method java/lang/IllegalArgumentException."<init>":(Ljava/lang/String;Ljava/lang/Throwable;)V
      51: athrow
      52: aconst_null
      53: areturn
    Exception table:
       from    to  target type
          15    22    23   Class org/springframework/expression/ParseException

  public void postProcessBeanFactory(org.springframework.beans.factory.config.ConfigurableListableBeanFactory) throws org.springframework.beans.BeansException;
    Code:
       0: aload_0
       1: aload_1
       2: putfield      #49                 // Field beanFactory:Lorg/springframework/beans/factory/config/ConfigurableListableBeanFactory;
       5: aload_1
       6: aload_0
       7: getfield      #9                  // Field name:Ljava/lang/String;
      10: aload_0
      11: invokeinterface #63,  3           // InterfaceMethod org/springframework/beans/factory/config/ConfigurableListableBeanFactory.registerScope:(Ljava/lang/String;Lorg/springframework/beans/factory/config/Scope;)V
      16: aload_0
      17: aload_1
      18: invokespecial #64                 // Method setSerializationId:(Lorg/springframework/beans/factory/config/ConfigurableListableBeanFactory;)V
      21: return

  public void postProcessBeanDefinitionRegistry(org.springframework.beans.factory.support.BeanDefinitionRegistry) throws org.springframework.beans.BeansException;
    Code:
       0: aload_1
       1: invokeinterface #65,  1           // InterfaceMethod org/springframework/beans/factory/support/BeanDefinitionRegistry.getBeanDefinitionNames:()[Ljava/lang/String;
       6: astore_2
       7: aload_2
       8: arraylength
       9: istore_3
      10: iconst_0
      11: istore        4
      13: iload         4
      15: iload_3
      16: if_icmpge     127
      19: aload_2
      20: iload         4
      22: aaload
      23: astore        5
      25: aload_1
      26: aload         5
      28: invokeinterface #66,  2           // InterfaceMethod org/springframework/beans/factory/support/BeanDefinitionRegistry.getBeanDefinition:(Ljava/lang/String;)Lorg/springframework/beans/factory/config/BeanDefinition;
      33: astore        6
      35: aload         6
      37: instanceof    #67                 // class org/springframework/beans/factory/support/RootBeanDefinition
      40: ifeq          121
      43: aload         6
      45: checkcast     #67                 // class org/springframework/beans/factory/support/RootBeanDefinition
      48: astore        7
      50: aload         7
      52: invokevirtual #68                 // Method org/springframework/beans/factory/support/RootBeanDefinition.getDecoratedDefinition:()Lorg/springframework/beans/factory/config/BeanDefinitionHolder;
      55: ifnull        121
      58: aload         7
      60: invokevirtual #69                 // Method org/springframework/beans/factory/support/RootBeanDefinition.hasBeanClass:()Z
      63: ifeq          121
      66: aload         7
      68: invokevirtual #70                 // Method org/springframework/beans/factory/support/RootBeanDefinition.getBeanClass:()Ljava/lang/Class;
      71: ldc           #71                 // class org/springframework/aop/scope/ScopedProxyFactoryBean
      73: if_acmpne     121
      76: aload_0
      77: invokevirtual #72                 // Method getName:()Ljava/lang/String;
      80: aload         7
      82: invokevirtual #68                 // Method org/springframework/beans/factory/support/RootBeanDefinition.getDecoratedDefinition:()Lorg/springframework/beans/factory/config/BeanDefinitionHolder;
      85: invokevirtual #73                 // Method org/springframework/beans/factory/config/BeanDefinitionHolder.getBeanDefinition:()Lorg/springframework/beans/factory/config/BeanDefinition;
      88: invokeinterface #74,  1           // InterfaceMethod org/springframework/beans/factory/config/BeanDefinition.getScope:()Ljava/lang/String;
      93: invokevirtual #75                 // Method java/lang/String.equals:(Ljava/lang/Object;)Z
      96: ifeq          121
      99: aload         7
     101: ldc           #76                 // class org/springframework/cloud/context/scope/GenericScope$LockedScopedProxyFactoryBean
     103: invokevirtual #77                 // Method org/springframework/beans/factory/support/RootBeanDefinition.setBeanClass:(Ljava/lang/Class;)V
     106: aload         7
     108: invokevirtual #78                 // Method org/springframework/beans/factory/support/RootBeanDefinition.getConstructorArgumentValues:()Lorg/springframework/beans/factory/config/ConstructorArgumentValues;
     111: aload_0
     112: invokevirtual #79                 // Method org/springframework/beans/factory/config/ConstructorArgumentValues.addGenericArgumentValue:(Ljava/lang/Object;)V
     115: aload         7
     117: iconst_1
     118: invokevirtual #80                 // Method org/springframework/beans/factory/support/RootBeanDefinition.setSynthetic:(Z)V
     121: iinc          4, 1
     124: goto          13
     127: return

  private void setSerializationId(org.springframework.beans.factory.config.ConfigurableListableBeanFactory);
    Code:
       0: aload_1
       1: instanceof    #81                 // class org/springframework/beans/factory/support/DefaultListableBeanFactory
       4: ifeq          121
       7: aload_0
       8: getfield      #14                 // Field id:Ljava/lang/String;
      11: astore_2
      12: aload_2
      13: ifnonnull     83
      16: new           #15                 // class java/util/ArrayList
      19: dup
      20: aload_1
      21: invokeinterface #82,  1           // InterfaceMethod org/springframework/beans/factory/config/ConfigurableListableBeanFactory.getBeanDefinitionNames:()[Ljava/lang/String;
      26: invokestatic  #83                 // Method java/util/Arrays.asList:([Ljava/lang/Object;)Ljava/util/List;
      29: invokespecial #84                 // Method java/util/ArrayList."<init>":(Ljava/util/Collection;)V
      32: astore_3
      33: aload_3
      34: invokestatic  #85                 // Method java/util/Collections.sort:(Ljava/util/List;)V
      37: aload_3
      38: invokevirtual #86                 // Method java/lang/Object.toString:()Ljava/lang/String;
      41: astore        4
      43: getstatic     #1                  // Field logger:Lorg/apache/commons/logging/Log;
      46: new           #57                 // class java/lang/StringBuilder
      49: dup
      50: invokespecial #58                 // Method java/lang/StringBuilder."<init>":()V
      53: ldc           #87                 // String Generating bean factory id from names:
      55: invokevirtual #60                 // Method java/lang/StringBuilder.append:(Ljava/lang/String;)Ljava/lang/StringBuilder;
      58: aload         4
      60: invokevirtual #60                 // Method java/lang/StringBuilder.append:(Ljava/lang/String;)Ljava/lang/StringBuilder;
      63: invokevirtual #61                 // Method java/lang/StringBuilder.toString:()Ljava/lang/String;
      66: invokeinterface #88,  2           // InterfaceMethod org/apache/commons/logging/Log.debug:(Ljava/lang/Object;)V
      71: aload         4
      73: invokevirtual #89                 // Method java/lang/String.getBytes:()[B
      76: invokestatic  #90                 // Method java/util/UUID.nameUUIDFromBytes:([B)Ljava/util/UUID;
      79: invokevirtual #91                 // Method java/util/UUID.toString:()Ljava/lang/String;
      82: astore_2
      83: getstatic     #1                  // Field logger:Lorg/apache/commons/logging/Log;
      86: new           #57                 // class java/lang/StringBuilder
      89: dup
      90: invokespecial #58                 // Method java/lang/StringBuilder."<init>":()V
      93: ldc           #92                 // String BeanFactory id=
      95: invokevirtual #60                 // Method java/lang/StringBuilder.append:(Ljava/lang/String;)Ljava/lang/StringBuilder;
      98: aload_2
      99: invokevirtual #60                 // Method java/lang/StringBuilder.append:(Ljava/lang/String;)Ljava/lang/StringBuilder;
     102: invokevirtual #61                 // Method java/lang/StringBuilder.toString:()Ljava/lang/String;
     105: invokeinterface #93,  2           // InterfaceMethod org/apache/commons/logging/Log.info:(Ljava/lang/Object;)V
     110: aload_1
     111: checkcast     #81                 // class org/springframework/beans/factory/support/DefaultListableBeanFactory
     114: aload_2
     115: invokevirtual #94                 // Method org/springframework/beans/factory/support/DefaultListableBeanFactory.setSerializationId:(Ljava/lang/String;)V
     118: goto          131
     121: getstatic     #1                  // Field logger:Lorg/apache/commons/logging/Log;
     124: ldc           #95                 // String BeanFactory was not a DefaultListableBeanFactory, scoped proxy beans cannot be serialized.
     126: invokeinterface #96,  2           // InterfaceMethod org/apache/commons/logging/Log.warn:(Ljava/lang/Object;)V
     131: return

  static java.lang.RuntimeException wrapIfNecessary(java.lang.Throwable);
    Code:
       0: aload_0
       1: instanceof    #29                 // class java/lang/RuntimeException
       4: ifeq          12
       7: aload_0
       8: checkcast     #29                 // class java/lang/RuntimeException
      11: areturn
      12: aload_0
      13: instanceof    #97                 // class java/lang/Error
      16: ifeq          24
      19: aload_0
      20: checkcast     #97                 // class java/lang/Error
      23: athrow
      24: new           #98                 // class java/lang/IllegalStateException
      27: dup
      28: aload_0
      29: invokespecial #99                 // Method java/lang/IllegalStateException."<init>":(Ljava/lang/Throwable;)V
      32: areturn

  protected java.lang.String getName();
    Code:
       0: aload_0
       1: getfield      #9                  // Field name:Ljava/lang/String;
       4: areturn

  protected java.util.concurrent.locks.ReadWriteLock getLock(java.lang.String);
    Code:
       0: aload_0
       1: getfield      #13                 // Field locks:Ljava/util/concurrent/ConcurrentMap;
       4: aload_1
       5: invokeinterface #23,  2           // InterfaceMethod java/util/concurrent/ConcurrentMap.get:(Ljava/lang/Object;)Ljava/lang/Object;
      10: checkcast     #24                 // class java/util/concurrent/locks/ReadWriteLock
      13: areturn

  static org.apache.commons.logging.Log access$000();
    Code:
       0: getstatic     #1                  // Field logger:Lorg/apache/commons/logging/Log;
       3: areturn

  static {};
    Code:
       0: ldc           #100                // class org/springframework/cloud/context/scope/GenericScope
       2: invokestatic  #101                // Method org/apache/commons/logging/LogFactory.getLog:(Ljava/lang/Class;)Lorg/apache/commons/logging/Log;
       5: putstatic     #1                  // Field logger:Lorg/apache/commons/logging/Log;
       8: return
}
