Compiled from "ConfigurationClassUtils.java"
abstract class org.springframework.context.annotation.ConfigurationClassUtils {
  public static final java.lang.String CONFIGURATION_CLASS_FULL;

  public static final java.lang.String CONFIGURATION_CLASS_LITE;

  public static final java.lang.String CONFIGURATION_CLASS_ATTRIBUTE;

  private static final java.lang.String ORDER_ATTRIBUTE;

  private static final org.apache.commons.logging.Log logger;

  private static final java.util.Set<java.lang.String> candidateIndicators;

  org.springframework.context.annotation.ConfigurationClassUtils();
    Code:
       0: aload_0
       1: invokespecial #1                  // Method java/lang/Object."<init>":()V
       4: return

  public static boolean checkConfigurationClassCandidate(org.springframework.beans.factory.config.BeanDefinition, org.springframework.core.type.classreading.MetadataReaderFactory);
    Code:
       0: aload_0
       1: invokeinterface #2,  1            // InterfaceMethod org/springframework/beans/factory/config/BeanDefinition.getBeanClassName:()Ljava/lang/String;
       6: astore_2
       7: aload_2
       8: ifnull        20
      11: aload_0
      12: invokeinterface #3,  1            // InterfaceMethod org/springframework/beans/factory/config/BeanDefinition.getFactoryMethodName:()Ljava/lang/String;
      17: ifnull        22
      20: iconst_0
      21: ireturn
      22: aload_0
      23: instanceof    #4                  // class org/springframework/beans/factory/annotation/AnnotatedBeanDefinition
      26: ifeq          63
      29: aload_2
      30: aload_0
      31: checkcast     #4                  // class org/springframework/beans/factory/annotation/AnnotatedBeanDefinition
      34: invokeinterface #5,  1            // InterfaceMethod org/springframework/beans/factory/annotation/AnnotatedBeanDefinition.getMetadata:()Lorg/springframework/core/type/AnnotationMetadata;
      39: invokeinterface #6,  1            // InterfaceMethod org/springframework/core/type/AnnotationMetadata.getClassName:()Ljava/lang/String;
      44: invokevirtual #7                  // Method java/lang/String.equals:(Ljava/lang/Object;)Z
      47: ifeq          63
      50: aload_0
      51: checkcast     #4                  // class org/springframework/beans/factory/annotation/AnnotatedBeanDefinition
      54: invokeinterface #5,  1            // InterfaceMethod org/springframework/beans/factory/annotation/AnnotatedBeanDefinition.getMetadata:()Lorg/springframework/core/type/AnnotationMetadata;
      59: astore_3
      60: goto          204
      63: aload_0
      64: instanceof    #8                  // class org/springframework/beans/factory/support/AbstractBeanDefinition
      67: ifeq          140
      70: aload_0
      71: checkcast     #8                  // class org/springframework/beans/factory/support/AbstractBeanDefinition
      74: invokevirtual #9                  // Method org/springframework/beans/factory/support/AbstractBeanDefinition.hasBeanClass:()Z
      77: ifeq          140
      80: aload_0
      81: checkcast     #8                  // class org/springframework/beans/factory/support/AbstractBeanDefinition
      84: invokevirtual #10                 // Method org/springframework/beans/factory/support/AbstractBeanDefinition.getBeanClass:()Ljava/lang/Class;
      87: astore        4
      89: ldc           #11                 // class org/springframework/beans/factory/config/BeanFactoryPostProcessor
      91: aload         4
      93: invokevirtual #12                 // Method java/lang/Class.isAssignableFrom:(Ljava/lang/Class;)Z
      96: ifne          129
      99: ldc           #13                 // class org/springframework/beans/factory/config/BeanPostProcessor
     101: aload         4
     103: invokevirtual #12                 // Method java/lang/Class.isAssignableFrom:(Ljava/lang/Class;)Z
     106: ifne          129
     109: ldc           #14                 // class org/springframework/aop/framework/AopInfrastructureBean
     111: aload         4
     113: invokevirtual #12                 // Method java/lang/Class.isAssignableFrom:(Ljava/lang/Class;)Z
     116: ifne          129
     119: ldc           #15                 // class org/springframework/context/event/EventListenerFactory
     121: aload         4
     123: invokevirtual #12                 // Method java/lang/Class.isAssignableFrom:(Ljava/lang/Class;)Z
     126: ifeq          131
     129: iconst_0
     130: ireturn
     131: aload         4
     133: invokestatic  #16                 // InterfaceMethod org/springframework/core/type/AnnotationMetadata.introspect:(Ljava/lang/Class;)Lorg/springframework/core/type/AnnotationMetadata;
     136: astore_3
     137: goto          204
     140: aload_1
     141: aload_2
     142: invokeinterface #17,  2           // InterfaceMethod org/springframework/core/type/classreading/MetadataReaderFactory.getMetadataReader:(Ljava/lang/String;)Lorg/springframework/core/type/classreading/MetadataReader;
     147: astore        4
     149: aload         4
     151: invokeinterface #18,  1           // InterfaceMethod org/springframework/core/type/classreading/MetadataReader.getAnnotationMetadata:()Lorg/springframework/core/type/AnnotationMetadata;
     156: astore_3
     157: goto          204
     160: astore        4
     162: getstatic     #20                 // Field logger:Lorg/apache/commons/logging/Log;
     165: invokeinterface #21,  1           // InterfaceMethod org/apache/commons/logging/Log.isDebugEnabled:()Z
     170: ifeq          202
     173: getstatic     #20                 // Field logger:Lorg/apache/commons/logging/Log;
     176: new           #22                 // class java/lang/StringBuilder
     179: dup
     180: invokespecial #23                 // Method java/lang/StringBuilder."<init>":()V
     183: ldc           #24                 // String Could not find class file for introspecting configuration annotations:
     185: invokevirtual #25                 // Method java/lang/StringBuilder.append:(Ljava/lang/String;)Ljava/lang/StringBuilder;
     188: aload_2
     189: invokevirtual #25                 // Method java/lang/StringBuilder.append:(Ljava/lang/String;)Ljava/lang/StringBuilder;
     192: invokevirtual #26                 // Method java/lang/StringBuilder.toString:()Ljava/lang/String;
     195: aload         4
     197: invokeinterface #27,  3           // InterfaceMethod org/apache/commons/logging/Log.debug:(Ljava/lang/Object;Ljava/lang/Throwable;)V
     202: iconst_0
     203: ireturn
     204: aload_3
     205: ldc           #28                 // class org/springframework/context/annotation/Configuration
     207: invokevirtual #29                 // Method java/lang/Class.getName:()Ljava/lang/String;
     210: invokeinterface #30,  2           // InterfaceMethod org/springframework/core/type/AnnotationMetadata.getAnnotationAttributes:(Ljava/lang/String;)Ljava/util/Map;
     215: astore        4
     217: aload         4
     219: ifnull        254
     222: getstatic     #31                 // Field java/lang/Boolean.FALSE:Ljava/lang/Boolean;
     225: aload         4
     227: ldc           #32                 // String proxyBeanMethods
     229: invokeinterface #33,  2           // InterfaceMethod java/util/Map.get:(Ljava/lang/Object;)Ljava/lang/Object;
     234: invokevirtual #34                 // Method java/lang/Boolean.equals:(Ljava/lang/Object;)Z
     237: ifne          254
     240: aload_0
     241: getstatic     #35                 // Field CONFIGURATION_CLASS_ATTRIBUTE:Ljava/lang/String;
     244: ldc           #37                 // String full
     246: invokeinterface #38,  3           // InterfaceMethod org/springframework/beans/factory/config/BeanDefinition.setAttribute:(Ljava/lang/String;Ljava/lang/Object;)V
     251: goto          282
     254: aload         4
     256: ifnonnull     266
     259: aload_3
     260: invokestatic  #39                 // Method isConfigurationCandidate:(Lorg/springframework/core/type/AnnotationMetadata;)Z
     263: ifeq          280
     266: aload_0
     267: getstatic     #35                 // Field CONFIGURATION_CLASS_ATTRIBUTE:Ljava/lang/String;
     270: ldc           #40                 // String lite
     272: invokeinterface #38,  3           // InterfaceMethod org/springframework/beans/factory/config/BeanDefinition.setAttribute:(Ljava/lang/String;Ljava/lang/Object;)V
     277: goto          282
     280: iconst_0
     281: ireturn
     282: aload_3
     283: invokestatic  #41                 // Method getOrder:(Lorg/springframework/core/type/AnnotationMetadata;)Ljava/lang/Integer;
     286: astore        5
     288: aload         5
     290: ifnull        304
     293: aload_0
     294: getstatic     #42                 // Field ORDER_ATTRIBUTE:Ljava/lang/String;
     297: aload         5
     299: invokeinterface #38,  3           // InterfaceMethod org/springframework/beans/factory/config/BeanDefinition.setAttribute:(Ljava/lang/String;Ljava/lang/Object;)V
     304: iconst_1
     305: ireturn
    Exception table:
       from    to  target type
         140   157   160   Class java/io/IOException

  public static boolean isConfigurationCandidate(org.springframework.core.type.AnnotationMetadata);
    Code:
       0: aload_0
       1: invokeinterface #43,  1           // InterfaceMethod org/springframework/core/type/AnnotationMetadata.isInterface:()Z
       6: ifeq          11
       9: iconst_0
      10: ireturn
      11: getstatic     #44                 // Field candidateIndicators:Ljava/util/Set;
      14: invokeinterface #45,  1           // InterfaceMethod java/util/Set.iterator:()Ljava/util/Iterator;
      19: astore_1
      20: aload_1
      21: invokeinterface #46,  1           // InterfaceMethod java/util/Iterator.hasNext:()Z
      26: ifeq          54
      29: aload_1
      30: invokeinterface #47,  1           // InterfaceMethod java/util/Iterator.next:()Ljava/lang/Object;
      35: checkcast     #48                 // class java/lang/String
      38: astore_2
      39: aload_0
      40: aload_2
      41: invokeinterface #49,  2           // InterfaceMethod org/springframework/core/type/AnnotationMetadata.isAnnotated:(Ljava/lang/String;)Z
      46: ifeq          51
      49: iconst_1
      50: ireturn
      51: goto          20
      54: aload_0
      55: ldc           #50                 // class org/springframework/context/annotation/Bean
      57: invokevirtual #29                 // Method java/lang/Class.getName:()Ljava/lang/String;
      60: invokeinterface #51,  2           // InterfaceMethod org/springframework/core/type/AnnotationMetadata.hasAnnotatedMethods:(Ljava/lang/String;)Z
      65: ireturn
      66: astore_1
      67: getstatic     #20                 // Field logger:Lorg/apache/commons/logging/Log;
      70: invokeinterface #21,  1           // InterfaceMethod org/apache/commons/logging/Log.isDebugEnabled:()Z
      75: ifeq          119
      78: getstatic     #20                 // Field logger:Lorg/apache/commons/logging/Log;
      81: new           #22                 // class java/lang/StringBuilder
      84: dup
      85: invokespecial #23                 // Method java/lang/StringBuilder."<init>":()V
      88: ldc           #53                 // String Failed to introspect @Bean methods on class [
      90: invokevirtual #25                 // Method java/lang/StringBuilder.append:(Ljava/lang/String;)Ljava/lang/StringBuilder;
      93: aload_0
      94: invokeinterface #6,  1            // InterfaceMethod org/springframework/core/type/AnnotationMetadata.getClassName:()Ljava/lang/String;
      99: invokevirtual #25                 // Method java/lang/StringBuilder.append:(Ljava/lang/String;)Ljava/lang/StringBuilder;
     102: ldc           #54                 // String ]:
     104: invokevirtual #25                 // Method java/lang/StringBuilder.append:(Ljava/lang/String;)Ljava/lang/StringBuilder;
     107: aload_1
     108: invokevirtual #55                 // Method java/lang/StringBuilder.append:(Ljava/lang/Object;)Ljava/lang/StringBuilder;
     111: invokevirtual #26                 // Method java/lang/StringBuilder.toString:()Ljava/lang/String;
     114: invokeinterface #56,  2           // InterfaceMethod org/apache/commons/logging/Log.debug:(Ljava/lang/Object;)V
     119: iconst_0
     120: ireturn
    Exception table:
       from    to  target type
          54    65    66   Class java/lang/Throwable

  public static java.lang.Integer getOrder(org.springframework.core.type.AnnotationMetadata);
    Code:
       0: aload_0
       1: ldc           #57                 // class org/springframework/core/annotation/Order
       3: invokevirtual #29                 // Method java/lang/Class.getName:()Ljava/lang/String;
       6: invokeinterface #30,  2           // InterfaceMethod org/springframework/core/type/AnnotationMetadata.getAnnotationAttributes:(Ljava/lang/String;)Ljava/util/Map;
      11: astore_1
      12: aload_1
      13: ifnull        30
      16: aload_1
      17: ldc           #59                 // String value
      19: invokeinterface #33,  2           // InterfaceMethod java/util/Map.get:(Ljava/lang/Object;)Ljava/lang/Object;
      24: checkcast     #60                 // class java/lang/Integer
      27: goto          31
      30: aconst_null
      31: areturn

  public static int getOrder(org.springframework.beans.factory.config.BeanDefinition);
    Code:
       0: aload_0
       1: getstatic     #42                 // Field ORDER_ATTRIBUTE:Ljava/lang/String;
       4: invokeinterface #61,  2           // InterfaceMethod org/springframework/beans/factory/config/BeanDefinition.getAttribute:(Ljava/lang/String;)Ljava/lang/Object;
       9: checkcast     #60                 // class java/lang/Integer
      12: astore_1
      13: aload_1
      14: ifnull        24
      17: aload_1
      18: invokevirtual #62                 // Method java/lang/Integer.intValue:()I
      21: goto          26
      24: ldc           #64                 // int 2147483647
      26: ireturn

  static {};
    Code:
       0: ldc           #65                 // class org/springframework/context/annotation/ConfigurationClassPostProcessor
       2: ldc           #66                 // String configurationClass
       4: invokestatic  #67                 // Method org/springframework/core/Conventions.getQualifiedAttributeName:(Ljava/lang/Class;Ljava/lang/String;)Ljava/lang/String;
       7: putstatic     #35                 // Field CONFIGURATION_CLASS_ATTRIBUTE:Ljava/lang/String;
      10: ldc           #65                 // class org/springframework/context/annotation/ConfigurationClassPostProcessor
      12: ldc           #68                 // String order
      14: invokestatic  #67                 // Method org/springframework/core/Conventions.getQualifiedAttributeName:(Ljava/lang/Class;Ljava/lang/String;)Ljava/lang/String;
      17: putstatic     #42                 // Field ORDER_ATTRIBUTE:Ljava/lang/String;
      20: ldc           #36                 // class org/springframework/context/annotation/ConfigurationClassUtils
      22: invokestatic  #69                 // Method org/apache/commons/logging/LogFactory.getLog:(Ljava/lang/Class;)Lorg/apache/commons/logging/Log;
      25: putstatic     #20                 // Field logger:Lorg/apache/commons/logging/Log;
      28: new           #70                 // class java/util/HashSet
      31: dup
      32: bipush        8
      34: invokespecial #71                 // Method java/util/HashSet."<init>":(I)V
      37: putstatic     #44                 // Field candidateIndicators:Ljava/util/Set;
      40: getstatic     #44                 // Field candidateIndicators:Ljava/util/Set;
      43: ldc           #72                 // class org/springframework/stereotype/Component
      45: invokevirtual #29                 // Method java/lang/Class.getName:()Ljava/lang/String;
      48: invokeinterface #73,  2           // InterfaceMethod java/util/Set.add:(Ljava/lang/Object;)Z
      53: pop
      54: getstatic     #44                 // Field candidateIndicators:Ljava/util/Set;
      57: ldc           #74                 // class org/springframework/context/annotation/ComponentScan
      59: invokevirtual #29                 // Method java/lang/Class.getName:()Ljava/lang/String;
      62: invokeinterface #73,  2           // InterfaceMethod java/util/Set.add:(Ljava/lang/Object;)Z
      67: pop
      68: getstatic     #44                 // Field candidateIndicators:Ljava/util/Set;
      71: ldc           #75                 // class org/springframework/context/annotation/Import
      73: invokevirtual #29                 // Method java/lang/Class.getName:()Ljava/lang/String;
      76: invokeinterface #73,  2           // InterfaceMethod java/util/Set.add:(Ljava/lang/Object;)Z
      81: pop
      82: getstatic     #44                 // Field candidateIndicators:Ljava/util/Set;
      85: ldc           #76                 // class org/springframework/context/annotation/ImportResource
      87: invokevirtual #29                 // Method java/lang/Class.getName:()Ljava/lang/String;
      90: invokeinterface #73,  2           // InterfaceMethod java/util/Set.add:(Ljava/lang/Object;)Z
      95: pop
      96: return
}
