Compiled from "TypeRepImpl.java"
public final class com.mchange.v1.db.sql.schemarep.TypeRepImpl implements com.mchange.v1.db.sql.schemarep.TypeRep {
  int type_code;

  int[] typeSize;

  public com.mchange.v1.db.sql.schemarep.TypeRepImpl(int, int[]);
    Code:
       0: aload_0
       1: invokespecial #1                  // Method java/lang/Object."<init>":()V
       4: aload_0
       5: iload_1
       6: putfield      #2                  // Field type_code:I
       9: aload_0
      10: aload_2
      11: putfield      #3                  // Field typeSize:[I
      14: return

  public int getTypeCode();
    Code:
       0: aload_0
       1: getfield      #2                  // Field type_code:I
       4: ireturn

  public int[] getTypeSize();
    Code:
       0: aload_0
       1: getfield      #3                  // Field typeSize:[I
       4: areturn

  public boolean equals(java.lang.Object);
    Code:
       0: aload_0
       1: aload_1
       2: if_acmpne     7
       5: iconst_1
       6: ireturn
       7: aload_1
       8: instanceof    #4                  // class com/mchange/v1/db/sql/schemarep/TypeRep
      11: ifeq          23
      14: invokestatic  #5                  // Method com/mchange/v1/db/sql/schemarep/TypeRepIdenticator.getInstance:()Lcom/mchange/v1/db/sql/schemarep/TypeRepIdenticator;
      17: aload_0
      18: aload_1
      19: invokevirtual #6                  // Method com/mchange/v1/db/sql/schemarep/TypeRepIdenticator.identical:(Ljava/lang/Object;Ljava/lang/Object;)Z
      22: ireturn
      23: iconst_0
      24: ireturn

  public int hashCode();
    Code:
       0: invokestatic  #5                  // Method com/mchange/v1/db/sql/schemarep/TypeRepIdenticator.getInstance:()Lcom/mchange/v1/db/sql/schemarep/TypeRepIdenticator;
       3: aload_0
       4: invokevirtual #7                  // Method com/mchange/v1/db/sql/schemarep/TypeRepIdenticator.hash:(Ljava/lang/Object;)I
       7: ireturn
}
