Compiled from "JmxRemoteLifecycleListener.java"
public class org.apache.catalina.mbeans.JmxRemoteLifecycleListener extends org.apache.tomcat.util.net.SSLHostConfig implements org.apache.catalina.LifecycleListener {
  private static final long serialVersionUID;

  private static final org.apache.juli.logging.Log log;

  protected static final org.apache.tomcat.util.res.StringManager sm;

  protected java.lang.String rmiBindAddress;

  protected int rmiRegistryPortPlatform;

  protected int rmiServerPortPlatform;

  protected boolean rmiRegistrySSL;

  protected boolean rmiServerSSL;

  protected boolean authenticate;

  protected java.lang.String passwordFile;

  protected java.lang.String loginModuleName;

  protected java.lang.String accessFile;

  protected boolean useLocalPorts;

  protected transient javax.management.remote.JMXConnectorServer csPlatform;

  public org.apache.catalina.mbeans.JmxRemoteLifecycleListener();
    Code:
       0: aload_0
       1: invokespecial #2                  // Method org/apache/tomcat/util/net/SSLHostConfig."<init>":()V
       4: aload_0
       5: aconst_null
       6: putfield      #3                  // Field rmiBindAddress:Ljava/lang/String;
       9: aload_0
      10: iconst_m1
      11: putfield      #4                  // Field rmiRegistryPortPlatform:I
      14: aload_0
      15: iconst_m1
      16: putfield      #5                  // Field rmiServerPortPlatform:I
      19: aload_0
      20: iconst_1
      21: putfield      #6                  // Field rmiRegistrySSL:Z
      24: aload_0
      25: iconst_1
      26: putfield      #7                  // Field rmiServerSSL:Z
      29: aload_0
      30: iconst_1
      31: putfield      #8                  // Field authenticate:Z
      34: aload_0
      35: aconst_null
      36: putfield      #9                  // Field passwordFile:Ljava/lang/String;
      39: aload_0
      40: aconst_null
      41: putfield      #10                 // Field loginModuleName:Ljava/lang/String;
      44: aload_0
      45: aconst_null
      46: putfield      #11                 // Field accessFile:Ljava/lang/String;
      49: aload_0
      50: iconst_0
      51: putfield      #12                 // Field useLocalPorts:Z
      54: aload_0
      55: aconst_null
      56: putfield      #13                 // Field csPlatform:Ljavax/management/remote/JMXConnectorServer;
      59: return

  public java.lang.String getRmiBindAddress();
    Code:
       0: aload_0
       1: getfield      #3                  // Field rmiBindAddress:Ljava/lang/String;
       4: areturn

  public void setRmiBindAddress(java.lang.String);
    Code:
       0: aload_0
       1: aload_1
       2: putfield      #3                  // Field rmiBindAddress:Ljava/lang/String;
       5: return

  public int getRmiServerPortPlatform();
    Code:
       0: aload_0
       1: getfield      #5                  // Field rmiServerPortPlatform:I
       4: ireturn

  public void setRmiServerPortPlatform(int);
    Code:
       0: aload_0
       1: iload_1
       2: putfield      #5                  // Field rmiServerPortPlatform:I
       5: return

  public int getRmiRegistryPortPlatform();
    Code:
       0: aload_0
       1: getfield      #4                  // Field rmiRegistryPortPlatform:I
       4: ireturn

  public void setRmiRegistryPortPlatform(int);
    Code:
       0: aload_0
       1: iload_1
       2: putfield      #4                  // Field rmiRegistryPortPlatform:I
       5: return

  public boolean getUseLocalPorts();
    Code:
       0: aload_0
       1: getfield      #12                 // Field useLocalPorts:Z
       4: ireturn

  public void setUseLocalPorts(boolean);
    Code:
       0: aload_0
       1: iload_1
       2: putfield      #12                 // Field useLocalPorts:Z
       5: return

  public boolean isRmiRegistrySSL();
    Code:
       0: aload_0
       1: getfield      #6                  // Field rmiRegistrySSL:Z
       4: ireturn

  public void setRmiRegistrySSL(boolean);
    Code:
       0: aload_0
       1: iload_1
       2: putfield      #6                  // Field rmiRegistrySSL:Z
       5: return

  public boolean isRmiServerSSL();
    Code:
       0: aload_0
       1: getfield      #7                  // Field rmiServerSSL:Z
       4: ireturn

  public void setRmiServerSSL(boolean);
    Code:
       0: aload_0
       1: iload_1
       2: putfield      #7                  // Field rmiServerSSL:Z
       5: return

  public boolean isAuthenticate();
    Code:
       0: aload_0
       1: getfield      #8                  // Field authenticate:Z
       4: ireturn

  public void setAuthenticate(boolean);
    Code:
       0: aload_0
       1: iload_1
       2: putfield      #8                  // Field authenticate:Z
       5: return

  public java.lang.String getPasswordFile();
    Code:
       0: aload_0
       1: getfield      #9                  // Field passwordFile:Ljava/lang/String;
       4: areturn

  public void setPasswordFile(java.lang.String);
    Code:
       0: aload_0
       1: aload_1
       2: putfield      #9                  // Field passwordFile:Ljava/lang/String;
       5: return

  public java.lang.String getLoginModuleName();
    Code:
       0: aload_0
       1: getfield      #10                 // Field loginModuleName:Ljava/lang/String;
       4: areturn

  public void setLoginModuleName(java.lang.String);
    Code:
       0: aload_0
       1: aload_1
       2: putfield      #10                 // Field loginModuleName:Ljava/lang/String;
       5: return

  public java.lang.String getAccessFile();
    Code:
       0: aload_0
       1: getfield      #11                 // Field accessFile:Ljava/lang/String;
       4: areturn

  public void setAccessFile(java.lang.String);
    Code:
       0: aload_0
       1: aload_1
       2: putfield      #11                 // Field accessFile:Ljava/lang/String;
       5: return

  protected void init();
    Code:
       0: ldc           #14                 // String com.sun.management.jmxremote.registry.ssl
       2: invokestatic  #15                 // Method java/lang/System.getProperty:(Ljava/lang/String;)Ljava/lang/String;
       5: astore_1
       6: aload_1
       7: ifnull        18
      10: aload_0
      11: aload_1
      12: invokestatic  #16                 // Method java/lang/Boolean.parseBoolean:(Ljava/lang/String;)Z
      15: invokevirtual #17                 // Method setRmiRegistrySSL:(Z)V
      18: ldc           #18                 // String com.sun.management.jmxremote.ssl
      20: invokestatic  #15                 // Method java/lang/System.getProperty:(Ljava/lang/String;)Ljava/lang/String;
      23: astore_2
      24: aload_2
      25: ifnull        36
      28: aload_0
      29: aload_2
      30: invokestatic  #16                 // Method java/lang/Boolean.parseBoolean:(Ljava/lang/String;)Z
      33: invokevirtual #19                 // Method setRmiServerSSL:(Z)V
      36: ldc           #20                 // String com.sun.management.jmxremote.ssl.enabled.protocols
      38: invokestatic  #15                 // Method java/lang/System.getProperty:(Ljava/lang/String;)Ljava/lang/String;
      41: astore_3
      42: aload_3
      43: ifnull        56
      46: aload_0
      47: aload_3
      48: ldc           #21                 // String ,
      50: invokevirtual #22                 // Method java/lang/String.split:(Ljava/lang/String;)[Ljava/lang/String;
      53: invokevirtual #23                 // Method setEnabledProtocols:([Ljava/lang/String;)V
      56: ldc           #24                 // String com.sun.management.jmxremote.ssl.enabled.cipher.suites
      58: invokestatic  #15                 // Method java/lang/System.getProperty:(Ljava/lang/String;)Ljava/lang/String;
      61: astore        4
      63: aload         4
      65: ifnull        74
      68: aload_0
      69: aload         4
      71: invokevirtual #25                 // Method setCiphers:(Ljava/lang/String;)V
      74: ldc           #26                 // String com.sun.management.jmxremote.ssl.need.client.auth
      76: invokestatic  #15                 // Method java/lang/System.getProperty:(Ljava/lang/String;)Ljava/lang/String;
      79: astore        5
      81: aload         5
      83: ifnull        92
      86: aload_0
      87: aload         5
      89: invokevirtual #27                 // Method setCertificateVerification:(Ljava/lang/String;)V
      92: ldc           #28                 // String com.sun.management.jmxremote.authenticate
      94: invokestatic  #15                 // Method java/lang/System.getProperty:(Ljava/lang/String;)Ljava/lang/String;
      97: astore        6
      99: aload         6
     101: ifnull        113
     104: aload_0
     105: aload         6
     107: invokestatic  #16                 // Method java/lang/Boolean.parseBoolean:(Ljava/lang/String;)Z
     110: invokevirtual #29                 // Method setAuthenticate:(Z)V
     113: ldc           #30                 // String com.sun.management.jmxremote.password.file
     115: invokestatic  #15                 // Method java/lang/System.getProperty:(Ljava/lang/String;)Ljava/lang/String;
     118: astore        7
     120: aload         7
     122: ifnull        131
     125: aload_0
     126: aload         7
     128: invokevirtual #31                 // Method setPasswordFile:(Ljava/lang/String;)V
     131: ldc           #32                 // String com.sun.management.jmxremote.access.file
     133: invokestatic  #15                 // Method java/lang/System.getProperty:(Ljava/lang/String;)Ljava/lang/String;
     136: astore        8
     138: aload         8
     140: ifnull        149
     143: aload_0
     144: aload         8
     146: invokevirtual #33                 // Method setAccessFile:(Ljava/lang/String;)V
     149: ldc           #34                 // String com.sun.management.jmxremote.login.config
     151: invokestatic  #15                 // Method java/lang/System.getProperty:(Ljava/lang/String;)Ljava/lang/String;
     154: astore        9
     156: aload         9
     158: ifnull        167
     161: aload_0
     162: aload         9
     164: invokevirtual #35                 // Method setLoginModuleName:(Ljava/lang/String;)V
     167: return

  public void lifecycleEvent(org.apache.catalina.LifecycleEvent);
    Code:
       0: ldc           #37                 // String before_init
       2: aload_1
       3: invokevirtual #38                 // Method org/apache/catalina/LifecycleEvent.getType:()Ljava/lang/String;
       6: invokevirtual #39                 // Method java/lang/String.equals:(Ljava/lang/Object;)Z
       9: ifeq          31
      12: getstatic     #1                  // Field log:Lorg/apache/juli/logging/Log;
      15: getstatic     #40                 // Field sm:Lorg/apache/tomcat/util/res/StringManager;
      18: ldc           #41                 // String jmxRemoteLifecycleListener.deprecated
      20: invokevirtual #42                 // Method org/apache/tomcat/util/res/StringManager.getString:(Ljava/lang/String;)Ljava/lang/String;
      23: invokeinterface #43,  2           // InterfaceMethod org/apache/juli/logging/Log.warn:(Ljava/lang/Object;)V
      28: goto          657
      31: ldc           #44                 // String start
      33: aload_1
      34: invokevirtual #38                 // Method org/apache/catalina/LifecycleEvent.getType:()Ljava/lang/String;
      37: invokevirtual #39                 // Method java/lang/String.equals:(Ljava/lang/Object;)Z
      40: ifeq          635
      43: aload_0
      44: invokevirtual #45                 // Method init:()V
      47: aconst_null
      48: astore_2
      49: aload_0
      50: invokevirtual #46                 // Method getCertificates:()Ljava/util/Set;
      53: invokeinterface #47,  1           // InterfaceMethod java/util/Set.size:()I
      58: ifle          171
      61: aload_0
      62: invokevirtual #46                 // Method getCertificates:()Ljava/util/Set;
      65: invokeinterface #48,  1           // InterfaceMethod java/util/Set.iterator:()Ljava/util/Iterator;
      70: invokeinterface #49,  1           // InterfaceMethod java/util/Iterator.next:()Ljava/lang/Object;
      75: checkcast     #50                 // class org/apache/tomcat/util/net/SSLHostConfigCertificate
      78: astore_3
      79: new           #51                 // class org/apache/tomcat/util/net/jsse/JSSEUtil
      82: dup
      83: aload_3
      84: invokespecial #52                 // Method org/apache/tomcat/util/net/jsse/JSSEUtil."<init>":(Lorg/apache/tomcat/util/net/SSLHostConfigCertificate;)V
      87: astore        4
      89: aload_0
      90: invokevirtual #53                 // Method getSslProtocol:()Ljava/lang/String;
      93: invokestatic  #54                 // Method javax/net/ssl/SSLContext.getInstance:(Ljava/lang/String;)Ljavax/net/ssl/SSLContext;
      96: astore_2
      97: aload_0
      98: aload         4
     100: invokevirtual #55                 // Method org/apache/tomcat/util/net/jsse/JSSEUtil.getEnabledProtocols:()[Ljava/lang/String;
     103: invokevirtual #23                 // Method setEnabledProtocols:([Ljava/lang/String;)V
     106: aload_0
     107: aload         4
     109: invokevirtual #56                 // Method org/apache/tomcat/util/net/jsse/JSSEUtil.getEnabledCiphers:()[Ljava/lang/String;
     112: invokevirtual #57                 // Method setEnabledCiphers:([Ljava/lang/String;)V
     115: aload_2
     116: aload         4
     118: invokevirtual #58                 // Method org/apache/tomcat/util/net/jsse/JSSEUtil.getKeyManagers:()[Ljavax/net/ssl/KeyManager;
     121: aload         4
     123: invokevirtual #59                 // Method org/apache/tomcat/util/net/jsse/JSSEUtil.getTrustManagers:()[Ljavax/net/ssl/TrustManager;
     126: aconst_null
     127: invokevirtual #60                 // Method javax/net/ssl/SSLContext.init:([Ljavax/net/ssl/KeyManager;[Ljavax/net/ssl/TrustManager;Ljava/security/SecureRandom;)V
     130: aload_2
     131: invokevirtual #61                 // Method javax/net/ssl/SSLContext.getServerSessionContext:()Ljavax/net/ssl/SSLSessionContext;
     134: astore        5
     136: aload         5
     138: ifnull        148
     141: aload         4
     143: aload         5
     145: invokevirtual #62                 // Method org/apache/tomcat/util/net/jsse/JSSEUtil.configureSessionContext:(Ljavax/net/ssl/SSLSessionContext;)V
     148: goto          171
     151: astore        5
     153: getstatic     #1                  // Field log:Lorg/apache/juli/logging/Log;
     156: getstatic     #40                 // Field sm:Lorg/apache/tomcat/util/res/StringManager;
     159: ldc           #64                 // String jmxRemoteLifecycleListener.invalidSSLConfiguration
     161: invokevirtual #42                 // Method org/apache/tomcat/util/res/StringManager.getString:(Ljava/lang/String;)Ljava/lang/String;
     164: aload         5
     166: invokeinterface #65,  3           // InterfaceMethod org/apache/juli/logging/Log.error:(Ljava/lang/Object;Ljava/lang/Throwable;)V
     171: ldc           #66                 // String java.rmi.server.randomIDs
     173: ldc           #67                 // String true
     175: invokestatic  #68                 // Method java/lang/System.setProperty:(Ljava/lang/String;Ljava/lang/String;)Ljava/lang/String;
     178: pop
     179: new           #69                 // class java/util/HashMap
     182: dup
     183: invokespecial #70                 // Method java/util/HashMap."<init>":()V
     186: astore_3
     187: aconst_null
     188: astore        4
     190: aconst_null
     191: astore        5
     193: aconst_null
     194: astore        6
     196: aconst_null
     197: astore        7
     199: aload_0
     200: getfield      #6                  // Field rmiRegistrySSL:Z
     203: ifeq          298
     206: new           #71                 // class javax/rmi/ssl/SslRMIClientSocketFactory
     209: dup
     210: invokespecial #72                 // Method javax/rmi/ssl/SslRMIClientSocketFactory."<init>":()V
     213: astore        4
     215: aload_0
     216: getfield      #3                  // Field rmiBindAddress:Ljava/lang/String;
     219: ifnonnull     258
     222: new           #73                 // class javax/rmi/ssl/SslRMIServerSocketFactory
     225: dup
     226: aload_2
     227: aload_0
     228: invokevirtual #74                 // Method getEnabledCiphers:()[Ljava/lang/String;
     231: aload_0
     232: invokevirtual #75                 // Method getEnabledProtocols:()[Ljava/lang/String;
     235: aload_0
     236: invokevirtual #76                 // Method getCertificateVerification:()Lorg/apache/tomcat/util/net/SSLHostConfig$CertificateVerification;
     239: getstatic     #77                 // Field org/apache/tomcat/util/net/SSLHostConfig$CertificateVerification.REQUIRED:Lorg/apache/tomcat/util/net/SSLHostConfig$CertificateVerification;
     242: if_acmpne     249
     245: iconst_1
     246: goto          250
     249: iconst_0
     250: invokespecial #78                 // Method javax/rmi/ssl/SslRMIServerSocketFactory."<init>":(Ljavax/net/ssl/SSLContext;[Ljava/lang/String;[Ljava/lang/String;Z)V
     253: astore        5
     255: goto          318
     258: new           #79                 // class org/apache/catalina/mbeans/JmxRemoteLifecycleListener$SslRmiServerBindSocketFactory
     261: dup
     262: aload_2
     263: aload_0
     264: invokevirtual #74                 // Method getEnabledCiphers:()[Ljava/lang/String;
     267: aload_0
     268: invokevirtual #75                 // Method getEnabledProtocols:()[Ljava/lang/String;
     271: aload_0
     272: invokevirtual #76                 // Method getCertificateVerification:()Lorg/apache/tomcat/util/net/SSLHostConfig$CertificateVerification;
     275: getstatic     #77                 // Field org/apache/tomcat/util/net/SSLHostConfig$CertificateVerification.REQUIRED:Lorg/apache/tomcat/util/net/SSLHostConfig$CertificateVerification;
     278: if_acmpne     285
     281: iconst_1
     282: goto          286
     285: iconst_0
     286: aload_0
     287: getfield      #3                  // Field rmiBindAddress:Ljava/lang/String;
     290: invokespecial #80                 // Method org/apache/catalina/mbeans/JmxRemoteLifecycleListener$SslRmiServerBindSocketFactory."<init>":(Ljavax/net/ssl/SSLContext;[Ljava/lang/String;[Ljava/lang/String;ZLjava/lang/String;)V
     293: astore        5
     295: goto          318
     298: aload_0
     299: getfield      #3                  // Field rmiBindAddress:Ljava/lang/String;
     302: ifnull        318
     305: new           #81                 // class org/apache/catalina/mbeans/JmxRemoteLifecycleListener$RmiServerBindSocketFactory
     308: dup
     309: aload_0
     310: getfield      #3                  // Field rmiBindAddress:Ljava/lang/String;
     313: invokespecial #82                 // Method org/apache/catalina/mbeans/JmxRemoteLifecycleListener$RmiServerBindSocketFactory."<init>":(Ljava/lang/String;)V
     316: astore        5
     318: aload_0
     319: getfield      #7                  // Field rmiServerSSL:Z
     322: ifeq          417
     325: new           #71                 // class javax/rmi/ssl/SslRMIClientSocketFactory
     328: dup
     329: invokespecial #72                 // Method javax/rmi/ssl/SslRMIClientSocketFactory."<init>":()V
     332: astore        6
     334: aload_0
     335: getfield      #3                  // Field rmiBindAddress:Ljava/lang/String;
     338: ifnonnull     377
     341: new           #73                 // class javax/rmi/ssl/SslRMIServerSocketFactory
     344: dup
     345: aload_2
     346: aload_0
     347: invokevirtual #74                 // Method getEnabledCiphers:()[Ljava/lang/String;
     350: aload_0
     351: invokevirtual #75                 // Method getEnabledProtocols:()[Ljava/lang/String;
     354: aload_0
     355: invokevirtual #76                 // Method getCertificateVerification:()Lorg/apache/tomcat/util/net/SSLHostConfig$CertificateVerification;
     358: getstatic     #77                 // Field org/apache/tomcat/util/net/SSLHostConfig$CertificateVerification.REQUIRED:Lorg/apache/tomcat/util/net/SSLHostConfig$CertificateVerification;
     361: if_acmpne     368
     364: iconst_1
     365: goto          369
     368: iconst_0
     369: invokespecial #78                 // Method javax/rmi/ssl/SslRMIServerSocketFactory."<init>":(Ljavax/net/ssl/SSLContext;[Ljava/lang/String;[Ljava/lang/String;Z)V
     372: astore        7
     374: goto          437
     377: new           #79                 // class org/apache/catalina/mbeans/JmxRemoteLifecycleListener$SslRmiServerBindSocketFactory
     380: dup
     381: aload_2
     382: aload_0
     383: invokevirtual #74                 // Method getEnabledCiphers:()[Ljava/lang/String;
     386: aload_0
     387: invokevirtual #75                 // Method getEnabledProtocols:()[Ljava/lang/String;
     390: aload_0
     391: invokevirtual #76                 // Method getCertificateVerification:()Lorg/apache/tomcat/util/net/SSLHostConfig$CertificateVerification;
     394: getstatic     #77                 // Field org/apache/tomcat/util/net/SSLHostConfig$CertificateVerification.REQUIRED:Lorg/apache/tomcat/util/net/SSLHostConfig$CertificateVerification;
     397: if_acmpne     404
     400: iconst_1
     401: goto          405
     404: iconst_0
     405: aload_0
     406: getfield      #3                  // Field rmiBindAddress:Ljava/lang/String;
     409: invokespecial #80                 // Method org/apache/catalina/mbeans/JmxRemoteLifecycleListener$SslRmiServerBindSocketFactory."<init>":(Ljavax/net/ssl/SSLContext;[Ljava/lang/String;[Ljava/lang/String;ZLjava/lang/String;)V
     412: astore        7
     414: goto          437
     417: aload_0
     418: getfield      #3                  // Field rmiBindAddress:Ljava/lang/String;
     421: ifnull        437
     424: new           #81                 // class org/apache/catalina/mbeans/JmxRemoteLifecycleListener$RmiServerBindSocketFactory
     427: dup
     428: aload_0
     429: getfield      #3                  // Field rmiBindAddress:Ljava/lang/String;
     432: invokespecial #82                 // Method org/apache/catalina/mbeans/JmxRemoteLifecycleListener$RmiServerBindSocketFactory."<init>":(Ljava/lang/String;)V
     435: astore        7
     437: aload_0
     438: getfield      #3                  // Field rmiBindAddress:Ljava/lang/String;
     441: ifnull        454
     444: ldc           #83                 // String java.rmi.server.hostname
     446: aload_0
     447: getfield      #3                  // Field rmiBindAddress:Ljava/lang/String;
     450: invokestatic  #68                 // Method java/lang/System.setProperty:(Ljava/lang/String;Ljava/lang/String;)Ljava/lang/String;
     453: pop
     454: aload_0
     455: getfield      #12                 // Field useLocalPorts:Z
     458: ifeq          483
     461: new           #84                 // class org/apache/catalina/mbeans/JmxRemoteLifecycleListener$RmiClientLocalhostSocketFactory
     464: dup
     465: aload         4
     467: invokespecial #85                 // Method org/apache/catalina/mbeans/JmxRemoteLifecycleListener$RmiClientLocalhostSocketFactory."<init>":(Ljava/rmi/server/RMIClientSocketFactory;)V
     470: astore        4
     472: new           #84                 // class org/apache/catalina/mbeans/JmxRemoteLifecycleListener$RmiClientLocalhostSocketFactory
     475: dup
     476: aload         6
     478: invokespecial #85                 // Method org/apache/catalina/mbeans/JmxRemoteLifecycleListener$RmiClientLocalhostSocketFactory."<init>":(Ljava/rmi/server/RMIClientSocketFactory;)V
     481: astore        6
     483: aload_3
     484: ldc           #86                 // String jmx.remote.rmi.server.credential.types
     486: iconst_2
     487: anewarray     #87                 // class java/lang/String
     490: dup
     491: iconst_0
     492: ldc           #88                 // class "[Ljava/lang/String;"
     494: invokevirtual #89                 // Method java/lang/Class.getName:()Ljava/lang/String;
     497: aastore
     498: dup
     499: iconst_1
     500: ldc           #87                 // class java/lang/String
     502: invokevirtual #89                 // Method java/lang/Class.getName:()Ljava/lang/String;
     505: aastore
     506: invokeinterface #90,  3           // InterfaceMethod java/util/Map.put:(Ljava/lang/Object;Ljava/lang/Object;)Ljava/lang/Object;
     511: pop
     512: aload         6
     514: ifnull        539
     517: aload_3
     518: ldc           #92                 // String jmx.remote.rmi.client.socket.factory
     520: aload         6
     522: invokeinterface #90,  3           // InterfaceMethod java/util/Map.put:(Ljava/lang/Object;Ljava/lang/Object;)Ljava/lang/Object;
     527: pop
     528: aload_3
     529: ldc           #93                 // String com.sun.jndi.rmi.factory.socket
     531: aload         4
     533: invokeinterface #90,  3           // InterfaceMethod java/util/Map.put:(Ljava/lang/Object;Ljava/lang/Object;)Ljava/lang/Object;
     538: pop
     539: aload         7
     541: ifnull        555
     544: aload_3
     545: ldc           #94                 // String jmx.remote.rmi.server.socket.factory
     547: aload         7
     549: invokeinterface #90,  3           // InterfaceMethod java/util/Map.put:(Ljava/lang/Object;Ljava/lang/Object;)Ljava/lang/Object;
     554: pop
     555: aload_0
     556: getfield      #8                  // Field authenticate:Z
     559: ifeq          601
     562: aload_3
     563: ldc           #95                 // String jmx.remote.x.password.file
     565: aload_0
     566: getfield      #9                  // Field passwordFile:Ljava/lang/String;
     569: invokeinterface #90,  3           // InterfaceMethod java/util/Map.put:(Ljava/lang/Object;Ljava/lang/Object;)Ljava/lang/Object;
     574: pop
     575: aload_3
     576: ldc           #96                 // String jmx.remote.x.access.file
     578: aload_0
     579: getfield      #11                 // Field accessFile:Ljava/lang/String;
     582: invokeinterface #90,  3           // InterfaceMethod java/util/Map.put:(Ljava/lang/Object;Ljava/lang/Object;)Ljava/lang/Object;
     587: pop
     588: aload_3
     589: ldc           #97                 // String jmx.remote.x.login.config
     591: aload_0
     592: getfield      #10                 // Field loginModuleName:Ljava/lang/String;
     595: invokeinterface #90,  3           // InterfaceMethod java/util/Map.put:(Ljava/lang/Object;Ljava/lang/Object;)Ljava/lang/Object;
     600: pop
     601: aload_0
     602: aload_0
     603: ldc           #98                 // String Platform
     605: aload_0
     606: getfield      #3                  // Field rmiBindAddress:Ljava/lang/String;
     609: aload_0
     610: getfield      #4                  // Field rmiRegistryPortPlatform:I
     613: aload_0
     614: getfield      #5                  // Field rmiServerPortPlatform:I
     617: aload_3
     618: aload         4
     620: aload         5
     622: aload         6
     624: aload         7
     626: invokespecial #99                 // Method createServer:(Ljava/lang/String;Ljava/lang/String;IILjava/util/Map;Ljava/rmi/server/RMIClientSocketFactory;Ljava/rmi/server/RMIServerSocketFactory;Ljava/rmi/server/RMIClientSocketFactory;Ljava/rmi/server/RMIServerSocketFactory;)Ljavax/management/remote/JMXConnectorServer;
     629: putfield      #13                 // Field csPlatform:Ljavax/management/remote/JMXConnectorServer;
     632: goto          657
     635: ldc           #100                // String stop
     637: aload_1
     638: invokevirtual #38                 // Method org/apache/catalina/LifecycleEvent.getType:()Ljava/lang/String;
     641: invokevirtual #39                 // Method java/lang/String.equals:(Ljava/lang/Object;)Z
     644: ifeq          657
     647: aload_0
     648: ldc           #98                 // String Platform
     650: aload_0
     651: getfield      #13                 // Field csPlatform:Ljavax/management/remote/JMXConnectorServer;
     654: invokespecial #101                // Method destroyServer:(Ljava/lang/String;Ljavax/management/remote/JMXConnectorServer;)V
     657: return
    Exception table:
       from    to  target type
          89   148   151   Class java/lang/Exception

  private javax.management.remote.JMXConnectorServer createServer(java.lang.String, java.lang.String, int, int, java.util.Map<java.lang.String, java.lang.Object>, java.rmi.server.RMIClientSocketFactory, java.rmi.server.RMIServerSocketFactory, java.rmi.server.RMIClientSocketFactory, java.rmi.server.RMIServerSocketFactory);
    Code:
       0: aload_2
       1: ifnonnull     7
       4: ldc           #102                // String localhost
       6: astore_2
       7: new           #103                // class java/lang/StringBuilder
      10: dup
      11: invokespecial #104                // Method java/lang/StringBuilder."<init>":()V
      14: ldc           #105                // String service:jmx:rmi://
      16: invokevirtual #106                // Method java/lang/StringBuilder.append:(Ljava/lang/String;)Ljava/lang/StringBuilder;
      19: aload_2
      20: invokevirtual #106                // Method java/lang/StringBuilder.append:(Ljava/lang/String;)Ljava/lang/StringBuilder;
      23: invokevirtual #107                // Method java/lang/StringBuilder.toString:()Ljava/lang/String;
      26: astore        10
      28: new           #108                // class javax/management/remote/JMXServiceURL
      31: dup
      32: aload         10
      34: invokespecial #109                // Method javax/management/remote/JMXServiceURL."<init>":(Ljava/lang/String;)V
      37: astore        11
      39: goto          77
      42: astore        12
      44: getstatic     #1                  // Field log:Lorg/apache/juli/logging/Log;
      47: getstatic     #40                 // Field sm:Lorg/apache/tomcat/util/res/StringManager;
      50: ldc           #111                // String jmxRemoteLifecycleListener.invalidURL
      52: iconst_2
      53: anewarray     #112                // class java/lang/Object
      56: dup
      57: iconst_0
      58: aload_1
      59: aastore
      60: dup
      61: iconst_1
      62: aload         10
      64: aastore
      65: invokevirtual #113                // Method org/apache/tomcat/util/res/StringManager.getString:(Ljava/lang/String;[Ljava/lang/Object;)Ljava/lang/String;
      68: aload         12
      70: invokeinterface #65,  3           // InterfaceMethod org/apache/juli/logging/Log.error:(Ljava/lang/Object;Ljava/lang/Throwable;)V
      75: aconst_null
      76: areturn
      77: aconst_null
      78: astore        12
      80: new           #114                // class javax/management/remote/rmi/RMIJRMPServerImpl
      83: dup
      84: aload_0
      85: getfield      #5                  // Field rmiServerPortPlatform:I
      88: aload         8
      90: aload         9
      92: aload         5
      94: invokespecial #115                // Method javax/management/remote/rmi/RMIJRMPServerImpl."<init>":(ILjava/rmi/server/RMIClientSocketFactory;Ljava/rmi/server/RMIServerSocketFactory;Ljava/util/Map;)V
      97: astore        13
      99: new           #91                 // class javax/management/remote/rmi/RMIConnectorServer
     102: dup
     103: aload         11
     105: aload         5
     107: aload         13
     109: invokestatic  #116                // Method java/lang/management/ManagementFactory.getPlatformMBeanServer:()Ljavax/management/MBeanServer;
     112: invokespecial #117                // Method javax/management/remote/rmi/RMIConnectorServer."<init>":(Ljavax/management/remote/JMXServiceURL;Ljava/util/Map;Ljavax/management/remote/rmi/RMIServerImpl;Ljavax/management/MBeanServer;)V
     115: astore        12
     117: aload         12
     119: invokevirtual #118                // Method javax/management/remote/rmi/RMIConnectorServer.start:()V
     122: aload         13
     124: invokevirtual #119                // Method javax/management/remote/rmi/RMIJRMPServerImpl.toStub:()Ljava/rmi/Remote;
     127: astore        14
     129: new           #120                // class org/apache/catalina/mbeans/JmxRemoteLifecycleListener$JmxRegistry
     132: dup
     133: iload_3
     134: aload         6
     136: aload         7
     138: ldc           #121                // String jmxrmi
     140: aload         14
     142: invokespecial #122                // Method org/apache/catalina/mbeans/JmxRemoteLifecycleListener$JmxRegistry."<init>":(ILjava/rmi/server/RMIClientSocketFactory;Ljava/rmi/server/RMIServerSocketFactory;Ljava/lang/String;Ljava/rmi/Remote;)V
     145: astore        15
     147: goto          187
     150: astore        15
     152: getstatic     #1                  // Field log:Lorg/apache/juli/logging/Log;
     155: getstatic     #40                 // Field sm:Lorg/apache/tomcat/util/res/StringManager;
     158: ldc           #124                // String jmxRemoteLifecycleListener.createRegistryFailed
     160: iconst_2
     161: anewarray     #112                // class java/lang/Object
     164: dup
     165: iconst_0
     166: aload_1
     167: aastore
     168: dup
     169: iconst_1
     170: iload_3
     171: invokestatic  #125                // Method java/lang/Integer.toString:(I)Ljava/lang/String;
     174: aastore
     175: invokevirtual #113                // Method org/apache/tomcat/util/res/StringManager.getString:(Ljava/lang/String;[Ljava/lang/Object;)Ljava/lang/String;
     178: aload         15
     180: invokeinterface #65,  3           // InterfaceMethod org/apache/juli/logging/Log.error:(Ljava/lang/Object;Ljava/lang/Throwable;)V
     185: aconst_null
     186: areturn
     187: getstatic     #1                  // Field log:Lorg/apache/juli/logging/Log;
     190: getstatic     #40                 // Field sm:Lorg/apache/tomcat/util/res/StringManager;
     193: ldc           #126                // String jmxRemoteLifecycleListener.start
     195: iconst_3
     196: anewarray     #112                // class java/lang/Object
     199: dup
     200: iconst_0
     201: iload_3
     202: invokestatic  #125                // Method java/lang/Integer.toString:(I)Ljava/lang/String;
     205: aastore
     206: dup
     207: iconst_1
     208: iload         4
     210: invokestatic  #125                // Method java/lang/Integer.toString:(I)Ljava/lang/String;
     213: aastore
     214: dup
     215: iconst_2
     216: aload_1
     217: aastore
     218: invokevirtual #113                // Method org/apache/tomcat/util/res/StringManager.getString:(Ljava/lang/String;[Ljava/lang/Object;)Ljava/lang/String;
     221: invokeinterface #127,  2          // InterfaceMethod org/apache/juli/logging/Log.info:(Ljava/lang/Object;)V
     226: goto          257
     229: astore        13
     231: getstatic     #1                  // Field log:Lorg/apache/juli/logging/Log;
     234: getstatic     #40                 // Field sm:Lorg/apache/tomcat/util/res/StringManager;
     237: ldc           #129                // String jmxRemoteLifecycleListener.createServerFailed
     239: iconst_1
     240: anewarray     #112                // class java/lang/Object
     243: dup
     244: iconst_0
     245: aload_1
     246: aastore
     247: invokevirtual #113                // Method org/apache/tomcat/util/res/StringManager.getString:(Ljava/lang/String;[Ljava/lang/Object;)Ljava/lang/String;
     250: aload         13
     252: invokeinterface #65,  3           // InterfaceMethod org/apache/juli/logging/Log.error:(Ljava/lang/Object;Ljava/lang/Throwable;)V
     257: aload         12
     259: areturn
    Exception table:
       from    to  target type
          28    39    42   Class java/net/MalformedURLException
         129   147   150   Class java/rmi/RemoteException
          80   186   229   Class java/io/IOException
         187   226   229   Class java/io/IOException

  private void destroyServer(java.lang.String, javax.management.remote.JMXConnectorServer);
    Code:
       0: aload_2
       1: ifnull        37
       4: aload_2
       5: invokevirtual #130                // Method javax/management/remote/JMXConnectorServer.stop:()V
       8: goto          37
      11: astore_3
      12: getstatic     #1                  // Field log:Lorg/apache/juli/logging/Log;
      15: getstatic     #40                 // Field sm:Lorg/apache/tomcat/util/res/StringManager;
      18: ldc           #131                // String jmxRemoteLifecycleListener.destroyServerFailed
      20: iconst_1
      21: anewarray     #112                // class java/lang/Object
      24: dup
      25: iconst_0
      26: aload_1
      27: aastore
      28: invokevirtual #113                // Method org/apache/tomcat/util/res/StringManager.getString:(Ljava/lang/String;[Ljava/lang/Object;)Ljava/lang/String;
      31: aload_3
      32: invokeinterface #65,  3           // InterfaceMethod org/apache/juli/logging/Log.error:(Ljava/lang/Object;Ljava/lang/Throwable;)V
      37: return
    Exception table:
       from    to  target type
           4     8    11   Class java/io/IOException

  static org.apache.juli.logging.Log access$000();
    Code:
       0: getstatic     #1                  // Field log:Lorg/apache/juli/logging/Log;
       3: areturn

  static {};
    Code:
       0: ldc           #132                // class org/apache/catalina/mbeans/JmxRemoteLifecycleListener
       2: invokestatic  #133                // Method org/apache/juli/logging/LogFactory.getLog:(Ljava/lang/Class;)Lorg/apache/juli/logging/Log;
       5: putstatic     #1                  // Field log:Lorg/apache/juli/logging/Log;
       8: ldc           #132                // class org/apache/catalina/mbeans/JmxRemoteLifecycleListener
      10: invokestatic  #134                // Method org/apache/tomcat/util/res/StringManager.getManager:(Ljava/lang/Class;)Lorg/apache/tomcat/util/res/StringManager;
      13: putstatic     #40                 // Field sm:Lorg/apache/tomcat/util/res/StringManager;
      16: return
}
