Compiled from "ExecutorBeanPostProcessor.java"
class org.springframework.cloud.sleuth.instrument.async.ExecutorBeanPostProcessor implements org.springframework.beans.factory.config.BeanPostProcessor {
  private static final org.apache.commons.logging.Log log;

  private final org.springframework.beans.factory.BeanFactory beanFactory;

  org.springframework.cloud.sleuth.instrument.async.ExecutorBeanPostProcessor(org.springframework.beans.factory.BeanFactory);
    Code:
       0: aload_0
       1: invokespecial #1                  // Method java/lang/Object."<init>":()V
       4: aload_0
       5: aload_1
       6: putfield      #2                  // Field beanFactory:Lorg/springframework/beans/factory/BeanFactory;
       9: return

  public java.lang.Object postProcessBeforeInitialization(java.lang.Object, java.lang.String) throws org.springframework.beans.BeansException;
    Code:
       0: aload_1
       1: areturn

  public java.lang.Object postProcessAfterInitialization(java.lang.Object, java.lang.String) throws org.springframework.beans.BeansException;
    Code:
       0: aload_1
       1: instanceof    #3                  // class org/springframework/scheduling/concurrent/ThreadPoolTaskExecutor
       4: ifeq          13
       7: aload_0
       8: aload_1
       9: invokespecial #4                  // Method wrapThreadPoolTaskExecutor:(Ljava/lang/Object;)Ljava/lang/Object;
      12: areturn
      13: aload_1
      14: instanceof    #5                  // class java/util/concurrent/ExecutorService
      17: ifeq          26
      20: aload_0
      21: aload_1
      22: invokespecial #6                  // Method wrapExecutorService:(Ljava/lang/Object;)Ljava/lang/Object;
      25: areturn
      26: aload_1
      27: instanceof    #7                  // class java/util/concurrent/Executor
      30: ifeq          39
      33: aload_0
      34: aload_1
      35: invokespecial #8                  // Method wrapExecutor:(Ljava/lang/Object;)Ljava/lang/Object;
      38: areturn
      39: aload_1
      40: areturn

  private java.lang.Object wrapExecutor(java.lang.Object);
    Code:
       0: aload_1
       1: invokevirtual #9                  // Method java/lang/Object.getClass:()Ljava/lang/Class;
       4: ldc           #10                 // String execute
       6: iconst_1
       7: anewarray     #11                 // class java/lang/Class
      10: dup
      11: iconst_0
      12: ldc           #12                 // class java/lang/Runnable
      14: aastore
      15: invokestatic  #13                 // Method org/springframework/util/ReflectionUtils.findMethod:(Ljava/lang/Class;Ljava/lang/String;[Ljava/lang/Class;)Ljava/lang/reflect/Method;
      18: astore_2
      19: aload_2
      20: invokevirtual #14                 // Method java/lang/reflect/Method.getModifiers:()I
      23: invokestatic  #15                 // Method java/lang/reflect/Modifier.isFinal:(I)Z
      26: istore_3
      27: aload_1
      28: invokevirtual #9                  // Method java/lang/Object.getClass:()Ljava/lang/Class;
      31: invokevirtual #16                 // Method java/lang/Class.getModifiers:()I
      34: invokestatic  #15                 // Method java/lang/reflect/Modifier.isFinal:(I)Z
      37: istore        4
      39: iload_3
      40: ifne          52
      43: iload         4
      45: ifne          52
      48: iconst_1
      49: goto          53
      52: iconst_0
      53: istore        5
      55: aload_1
      56: checkcast     #7                  // class java/util/concurrent/Executor
      59: astore        6
      61: aload_0
      62: aload_1
      63: iload         5
      65: new           #17                 // class org/springframework/cloud/sleuth/instrument/async/ExecutorMethodInterceptor
      68: dup
      69: aload         6
      71: aload_0
      72: getfield      #2                  // Field beanFactory:Lorg/springframework/beans/factory/BeanFactory;
      75: invokespecial #18                 // Method org/springframework/cloud/sleuth/instrument/async/ExecutorMethodInterceptor."<init>":(Ljava/util/concurrent/Executor;Lorg/springframework/beans/factory/BeanFactory;)V
      78: invokevirtual #19                 // Method createProxy:(Ljava/lang/Object;ZLorg/aopalliance/aop/Advice;)Ljava/lang/Object;
      81: areturn
      82: astore        7
      84: iload         5
      86: ifeq          132
      89: getstatic     #21                 // Field log:Lorg/apache/commons/logging/Log;
      92: invokeinterface #22,  1           // InterfaceMethod org/apache/commons/logging/Log.isDebugEnabled:()Z
      97: ifeq          112
     100: getstatic     #21                 // Field log:Lorg/apache/commons/logging/Log;
     103: ldc           #23                 // String Exception occurred while trying to create a proxy, falling back to JDK proxy
     105: aload         7
     107: invokeinterface #24,  3           // InterfaceMethod org/apache/commons/logging/Log.debug:(Ljava/lang/Object;Ljava/lang/Throwable;)V
     112: aload_0
     113: aload_1
     114: iconst_0
     115: new           #17                 // class org/springframework/cloud/sleuth/instrument/async/ExecutorMethodInterceptor
     118: dup
     119: aload         6
     121: aload_0
     122: getfield      #2                  // Field beanFactory:Lorg/springframework/beans/factory/BeanFactory;
     125: invokespecial #18                 // Method org/springframework/cloud/sleuth/instrument/async/ExecutorMethodInterceptor."<init>":(Ljava/util/concurrent/Executor;Lorg/springframework/beans/factory/BeanFactory;)V
     128: invokevirtual #19                 // Method createProxy:(Ljava/lang/Object;ZLorg/aopalliance/aop/Advice;)Ljava/lang/Object;
     131: areturn
     132: aload         7
     134: athrow
    Exception table:
       from    to  target type
          61    81    82   Class org/springframework/aop/framework/AopConfigException

  private java.lang.Object wrapThreadPoolTaskExecutor(java.lang.Object);
    Code:
       0: aload_1
       1: invokevirtual #9                  // Method java/lang/Object.getClass:()Ljava/lang/Class;
       4: invokevirtual #16                 // Method java/lang/Class.getModifiers:()I
       7: invokestatic  #15                 // Method java/lang/reflect/Modifier.isFinal:(I)Z
      10: istore_2
      11: iload_2
      12: ifne          19
      15: iconst_1
      16: goto          20
      19: iconst_0
      20: istore_3
      21: aload_1
      22: checkcast     #3                  // class org/springframework/scheduling/concurrent/ThreadPoolTaskExecutor
      25: astore        4
      27: aload_0
      28: aload_1
      29: iload_3
      30: aload         4
      32: invokevirtual #25                 // Method createThreadPoolTaskExecutorProxy:(Ljava/lang/Object;ZLorg/springframework/scheduling/concurrent/ThreadPoolTaskExecutor;)Ljava/lang/Object;
      35: areturn

  private org.springframework.aop.framework.ProxyFactoryBean wrapThreadPoolTaskScheduler(java.lang.Object);
    Code:
       0: aload_1
       1: invokevirtual #9                  // Method java/lang/Object.getClass:()Ljava/lang/Class;
       4: invokevirtual #16                 // Method java/lang/Class.getModifiers:()I
       7: invokestatic  #15                 // Method java/lang/reflect/Modifier.isFinal:(I)Z
      10: istore_2
      11: iload_2
      12: ifne          19
      15: iconst_1
      16: goto          20
      19: iconst_0
      20: istore_3
      21: aload_1
      22: checkcast     #26                 // class org/springframework/scheduling/concurrent/ThreadPoolTaskScheduler
      25: astore        4
      27: aload_0
      28: aload_1
      29: iload_3
      30: aload         4
      32: aload_0
      33: aload         4
      35: invokevirtual #27                 // Method createThreadPoolTaskSchedulerProxy:(Lorg/springframework/scheduling/concurrent/ThreadPoolTaskScheduler;)Ljava/util/function/Supplier;
      38: invokespecial #28                 // Method proxyFactoryBean:(Ljava/lang/Object;ZLjava/util/concurrent/Executor;Ljava/util/function/Supplier;)Lorg/springframework/aop/framework/ProxyFactoryBean;
      41: areturn

  private org.springframework.aop.framework.ProxyFactoryBean wrapScheduledThreadPoolExecutor(java.lang.Object);
    Code:
       0: aload_1
       1: invokevirtual #9                  // Method java/lang/Object.getClass:()Ljava/lang/Class;
       4: invokevirtual #16                 // Method java/lang/Class.getModifiers:()I
       7: invokestatic  #15                 // Method java/lang/reflect/Modifier.isFinal:(I)Z
      10: istore_2
      11: iload_2
      12: ifne          19
      15: iconst_1
      16: goto          20
      19: iconst_0
      20: istore_3
      21: aload_1
      22: checkcast     #29                 // class java/util/concurrent/ScheduledThreadPoolExecutor
      25: astore        4
      27: aload_0
      28: aload_1
      29: iload_3
      30: aload         4
      32: aload_0
      33: aload         4
      35: invokevirtual #30                 // Method createScheduledThreadPoolExecutorProxy:(Ljava/util/concurrent/ScheduledThreadPoolExecutor;)Ljava/util/function/Supplier;
      38: invokespecial #28                 // Method proxyFactoryBean:(Ljava/lang/Object;ZLjava/util/concurrent/Executor;Ljava/util/function/Supplier;)Lorg/springframework/aop/framework/ProxyFactoryBean;
      41: areturn

  private java.lang.Object wrapExecutorService(java.lang.Object);
    Code:
       0: aload_1
       1: invokevirtual #9                  // Method java/lang/Object.getClass:()Ljava/lang/Class;
       4: invokevirtual #16                 // Method java/lang/Class.getModifiers:()I
       7: invokestatic  #15                 // Method java/lang/reflect/Modifier.isFinal:(I)Z
      10: istore_2
      11: iload_2
      12: ifne          19
      15: iconst_1
      16: goto          20
      19: iconst_0
      20: istore_3
      21: aload_1
      22: checkcast     #5                  // class java/util/concurrent/ExecutorService
      25: astore        4
      27: aload_0
      28: aload_1
      29: iload_3
      30: aload         4
      32: invokevirtual #31                 // Method createExecutorServiceProxy:(Ljava/lang/Object;ZLjava/util/concurrent/ExecutorService;)Ljava/lang/Object;
      35: areturn

  java.lang.Object createThreadPoolTaskExecutorProxy(java.lang.Object, boolean, org.springframework.scheduling.concurrent.ThreadPoolTaskExecutor);
    Code:
       0: aload_0
       1: aload_1
       2: iload_2
       3: aload_3
       4: aload_0
       5: aload_3
       6: invokedynamic #32,  0             // InvokeDynamic #0:get:(Lorg/springframework/cloud/sleuth/instrument/async/ExecutorBeanPostProcessor;Lorg/springframework/scheduling/concurrent/ThreadPoolTaskExecutor;)Ljava/util/function/Supplier;
      11: invokespecial #33                 // Method getProxiedObject:(Ljava/lang/Object;ZLjava/util/concurrent/Executor;Ljava/util/function/Supplier;)Ljava/lang/Object;
      14: areturn

  java.util.function.Supplier createThreadPoolTaskSchedulerProxy(org.springframework.scheduling.concurrent.ThreadPoolTaskScheduler);
    Code:
       0: aload_0
       1: aload_1
       2: invokedynamic #34,  0             // InvokeDynamic #1:get:(Lorg/springframework/cloud/sleuth/instrument/async/ExecutorBeanPostProcessor;Lorg/springframework/scheduling/concurrent/ThreadPoolTaskScheduler;)Ljava/util/function/Supplier;
       7: areturn

  java.util.function.Supplier createScheduledThreadPoolExecutorProxy(java.util.concurrent.ScheduledThreadPoolExecutor);
    Code:
       0: aload_0
       1: aload_1
       2: invokedynamic #35,  0             // InvokeDynamic #2:get:(Lorg/springframework/cloud/sleuth/instrument/async/ExecutorBeanPostProcessor;Ljava/util/concurrent/ScheduledThreadPoolExecutor;)Ljava/util/function/Supplier;
       7: areturn

  java.lang.Object createExecutorServiceProxy(java.lang.Object, boolean, java.util.concurrent.ExecutorService);
    Code:
       0: aload_0
       1: aload_1
       2: iload_2
       3: aload_3
       4: aload_0
       5: aload_3
       6: invokedynamic #36,  0             // InvokeDynamic #3:get:(Lorg/springframework/cloud/sleuth/instrument/async/ExecutorBeanPostProcessor;Ljava/util/concurrent/ExecutorService;)Ljava/util/function/Supplier;
      11: invokespecial #33                 // Method getProxiedObject:(Ljava/lang/Object;ZLjava/util/concurrent/Executor;Ljava/util/function/Supplier;)Ljava/lang/Object;
      14: areturn

  private java.lang.Object getProxiedObject(java.lang.Object, boolean, java.util.concurrent.Executor, java.util.function.Supplier<java.util.concurrent.Executor>);
    Code:
       0: aload_0
       1: aload_1
       2: iload_2
       3: aload_3
       4: aload         4
       6: invokespecial #28                 // Method proxyFactoryBean:(Ljava/lang/Object;ZLjava/util/concurrent/Executor;Ljava/util/function/Supplier;)Lorg/springframework/aop/framework/ProxyFactoryBean;
       9: astore        5
      11: aload_0
      12: aload         5
      14: invokevirtual #37                 // Method getObject:(Lorg/springframework/aop/framework/ProxyFactoryBean;)Ljava/lang/Object;
      17: areturn
      18: astore        6
      20: getstatic     #21                 // Field log:Lorg/apache/commons/logging/Log;
      23: invokeinterface #22,  1           // InterfaceMethod org/apache/commons/logging/Log.isDebugEnabled:()Z
      28: ifeq          43
      31: getstatic     #21                 // Field log:Lorg/apache/commons/logging/Log;
      34: ldc           #39                 // String Exception occurred while trying to get a proxy. Will fallback to a different implementation
      36: aload         6
      38: invokeinterface #24,  3           // InterfaceMethod org/apache/commons/logging/Log.debug:(Ljava/lang/Object;Ljava/lang/Throwable;)V
      43: aload_1
      44: instanceof    #26                 // class org/springframework/scheduling/concurrent/ThreadPoolTaskScheduler
      47: ifeq          85
      50: getstatic     #21                 // Field log:Lorg/apache/commons/logging/Log;
      53: invokeinterface #22,  1           // InterfaceMethod org/apache/commons/logging/Log.isDebugEnabled:()Z
      58: ifeq          71
      61: getstatic     #21                 // Field log:Lorg/apache/commons/logging/Log;
      64: ldc           #40                 // String Will wrap ThreadPoolTaskScheduler in its tracing representation due to previous errors
      66: invokeinterface #41,  2           // InterfaceMethod org/apache/commons/logging/Log.debug:(Ljava/lang/Object;)V
      71: aload_0
      72: aload_1
      73: checkcast     #26                 // class org/springframework/scheduling/concurrent/ThreadPoolTaskScheduler
      76: invokevirtual #27                 // Method createThreadPoolTaskSchedulerProxy:(Lorg/springframework/scheduling/concurrent/ThreadPoolTaskScheduler;)Ljava/util/function/Supplier;
      79: invokeinterface #42,  1           // InterfaceMethod java/util/function/Supplier.get:()Ljava/lang/Object;
      84: areturn
      85: aload_1
      86: instanceof    #29                 // class java/util/concurrent/ScheduledThreadPoolExecutor
      89: ifeq          127
      92: getstatic     #21                 // Field log:Lorg/apache/commons/logging/Log;
      95: invokeinterface #22,  1           // InterfaceMethod org/apache/commons/logging/Log.isDebugEnabled:()Z
     100: ifeq          113
     103: getstatic     #21                 // Field log:Lorg/apache/commons/logging/Log;
     106: ldc           #43                 // String Will wrap ScheduledThreadPoolExecutor in its tracing representation due to previous errors
     108: invokeinterface #41,  2           // InterfaceMethod org/apache/commons/logging/Log.debug:(Ljava/lang/Object;)V
     113: aload_0
     114: aload_1
     115: checkcast     #29                 // class java/util/concurrent/ScheduledThreadPoolExecutor
     118: invokevirtual #30                 // Method createScheduledThreadPoolExecutorProxy:(Ljava/util/concurrent/ScheduledThreadPoolExecutor;)Ljava/util/function/Supplier;
     121: invokeinterface #42,  1           // InterfaceMethod java/util/function/Supplier.get:()Ljava/lang/Object;
     126: areturn
     127: goto          155
     130: astore        7
     132: getstatic     #21                 // Field log:Lorg/apache/commons/logging/Log;
     135: invokeinterface #22,  1           // InterfaceMethod org/apache/commons/logging/Log.isDebugEnabled:()Z
     140: ifeq          155
     143: getstatic     #21                 // Field log:Lorg/apache/commons/logging/Log;
     146: ldc           #44                 // String Fallback for special wrappers failed, will try the tracing representation instead
     148: aload         7
     150: invokeinterface #24,  3           // InterfaceMethod org/apache/commons/logging/Log.debug:(Ljava/lang/Object;Ljava/lang/Throwable;)V
     155: aload         4
     157: invokeinterface #42,  1           // InterfaceMethod java/util/function/Supplier.get:()Ljava/lang/Object;
     162: areturn
    Exception table:
       from    to  target type
          11    17    18   Class java/lang/Exception
          43    84   130   Class java/lang/Exception
          85   126   130   Class java/lang/Exception

  private org.springframework.aop.framework.ProxyFactoryBean proxyFactoryBean(java.lang.Object, boolean, java.util.concurrent.Executor, java.util.function.Supplier<java.util.concurrent.Executor>);
    Code:
       0: new           #45                 // class org/springframework/aop/framework/ProxyFactoryBean
       3: dup
       4: invokespecial #46                 // Method org/springframework/aop/framework/ProxyFactoryBean."<init>":()V
       7: astore        5
       9: aload         5
      11: iload_2
      12: invokevirtual #47                 // Method org/springframework/aop/framework/ProxyFactoryBean.setProxyTargetClass:(Z)V
      15: aload         5
      17: new           #48                 // class org/springframework/cloud/sleuth/instrument/async/ExecutorBeanPostProcessor$1
      20: dup
      21: aload_0
      22: aload_3
      23: aload_0
      24: getfield      #2                  // Field beanFactory:Lorg/springframework/beans/factory/BeanFactory;
      27: aload         4
      29: invokespecial #49                 // Method org/springframework/cloud/sleuth/instrument/async/ExecutorBeanPostProcessor$1."<init>":(Lorg/springframework/cloud/sleuth/instrument/async/ExecutorBeanPostProcessor;Ljava/util/concurrent/Executor;Lorg/springframework/beans/factory/BeanFactory;Ljava/util/function/Supplier;)V
      32: invokevirtual #50                 // Method org/springframework/aop/framework/ProxyFactoryBean.addAdvice:(Lorg/aopalliance/aop/Advice;)V
      35: aload         5
      37: aload_1
      38: invokevirtual #51                 // Method org/springframework/aop/framework/ProxyFactoryBean.setTarget:(Ljava/lang/Object;)V
      41: aload         5
      43: areturn

  java.lang.Object getObject(org.springframework.aop.framework.ProxyFactoryBean);
    Code:
       0: aload_1
       1: invokevirtual #52                 // Method org/springframework/aop/framework/ProxyFactoryBean.getObject:()Ljava/lang/Object;
       4: areturn

  java.lang.Object createProxy(java.lang.Object, boolean, org.aopalliance.aop.Advice);
    Code:
       0: new           #45                 // class org/springframework/aop/framework/ProxyFactoryBean
       3: dup
       4: invokespecial #46                 // Method org/springframework/aop/framework/ProxyFactoryBean."<init>":()V
       7: astore        4
       9: aload         4
      11: iload_2
      12: invokevirtual #47                 // Method org/springframework/aop/framework/ProxyFactoryBean.setProxyTargetClass:(Z)V
      15: aload         4
      17: aload_3
      18: invokevirtual #50                 // Method org/springframework/aop/framework/ProxyFactoryBean.addAdvice:(Lorg/aopalliance/aop/Advice;)V
      21: aload         4
      23: aload_1
      24: invokevirtual #51                 // Method org/springframework/aop/framework/ProxyFactoryBean.setTarget:(Ljava/lang/Object;)V
      27: aload         4
      29: invokevirtual #52                 // Method org/springframework/aop/framework/ProxyFactoryBean.getObject:()Ljava/lang/Object;
      32: areturn

  private java.util.concurrent.Executor lambda$createExecutorServiceProxy$3(java.util.concurrent.ExecutorService);
    Code:
       0: new           #53                 // class org/springframework/cloud/sleuth/instrument/async/TraceableExecutorService
       3: dup
       4: aload_0
       5: getfield      #2                  // Field beanFactory:Lorg/springframework/beans/factory/BeanFactory;
       8: aload_1
       9: invokespecial #54                 // Method org/springframework/cloud/sleuth/instrument/async/TraceableExecutorService."<init>":(Lorg/springframework/beans/factory/BeanFactory;Ljava/util/concurrent/ExecutorService;)V
      12: areturn

  private java.lang.Object lambda$createScheduledThreadPoolExecutorProxy$2(java.util.concurrent.ScheduledThreadPoolExecutor);
    Code:
       0: new           #55                 // class org/springframework/cloud/sleuth/instrument/async/LazyTraceScheduledThreadPoolExecutor
       3: dup
       4: aload_1
       5: invokevirtual #56                 // Method java/util/concurrent/ScheduledThreadPoolExecutor.getCorePoolSize:()I
       8: aload_1
       9: invokevirtual #57                 // Method java/util/concurrent/ScheduledThreadPoolExecutor.getThreadFactory:()Ljava/util/concurrent/ThreadFactory;
      12: aload_1
      13: invokevirtual #58                 // Method java/util/concurrent/ScheduledThreadPoolExecutor.getRejectedExecutionHandler:()Ljava/util/concurrent/RejectedExecutionHandler;
      16: aload_0
      17: getfield      #2                  // Field beanFactory:Lorg/springframework/beans/factory/BeanFactory;
      20: aload_1
      21: invokespecial #59                 // Method org/springframework/cloud/sleuth/instrument/async/LazyTraceScheduledThreadPoolExecutor."<init>":(ILjava/util/concurrent/ThreadFactory;Ljava/util/concurrent/RejectedExecutionHandler;Lorg/springframework/beans/factory/BeanFactory;Ljava/util/concurrent/ScheduledThreadPoolExecutor;)V
      24: areturn

  private java.lang.Object lambda$createThreadPoolTaskSchedulerProxy$1(org.springframework.scheduling.concurrent.ThreadPoolTaskScheduler);
    Code:
       0: new           #60                 // class org/springframework/cloud/sleuth/instrument/async/LazyTraceThreadPoolTaskScheduler
       3: dup
       4: aload_0
       5: getfield      #2                  // Field beanFactory:Lorg/springframework/beans/factory/BeanFactory;
       8: aload_1
       9: invokespecial #61                 // Method org/springframework/cloud/sleuth/instrument/async/LazyTraceThreadPoolTaskScheduler."<init>":(Lorg/springframework/beans/factory/BeanFactory;Lorg/springframework/scheduling/concurrent/ThreadPoolTaskScheduler;)V
      12: areturn

  private java.util.concurrent.Executor lambda$createThreadPoolTaskExecutorProxy$0(org.springframework.scheduling.concurrent.ThreadPoolTaskExecutor);
    Code:
       0: new           #62                 // class org/springframework/cloud/sleuth/instrument/async/LazyTraceThreadPoolTaskExecutor
       3: dup
       4: aload_0
       5: getfield      #2                  // Field beanFactory:Lorg/springframework/beans/factory/BeanFactory;
       8: aload_1
       9: invokespecial #63                 // Method org/springframework/cloud/sleuth/instrument/async/LazyTraceThreadPoolTaskExecutor."<init>":(Lorg/springframework/beans/factory/BeanFactory;Lorg/springframework/scheduling/concurrent/ThreadPoolTaskExecutor;)V
      12: areturn

  static {};
    Code:
       0: ldc           #64                 // class org/springframework/cloud/sleuth/instrument/async/ExecutorBeanPostProcessor
       2: invokestatic  #65                 // Method org/apache/commons/logging/LogFactory.getLog:(Ljava/lang/Class;)Lorg/apache/commons/logging/Log;
       5: putstatic     #21                 // Field log:Lorg/apache/commons/logging/Log;
       8: return
}
