Compiled from "Connector.java"
public class org.apache.catalina.connector.Connector extends org.apache.catalina.util.LifecycleMBeanBase {
  private static final org.apache.juli.logging.Log log;

  public static final boolean RECYCLE_FACADES;

  public static final java.lang.String INTERNAL_EXECUTOR_NAME;

  protected org.apache.catalina.Service service;

  protected boolean allowTrace;

  protected long asyncTimeout;

  protected boolean enableLookups;

  protected boolean xpoweredBy;

  protected java.lang.String proxyName;

  protected int proxyPort;

  protected boolean discardFacades;

  protected int redirectPort;

  protected java.lang.String scheme;

  protected boolean secure;

  protected static final org.apache.tomcat.util.res.StringManager sm;

  private int maxCookieCount;

  protected int maxParameterCount;

  protected int maxPostSize;

  protected int maxSavePostSize;

  protected java.lang.String parseBodyMethods;

  protected java.util.HashSet<java.lang.String> parseBodyMethodsSet;

  protected boolean useIPVHosts;

  protected final java.lang.String protocolHandlerClassName;

  protected final org.apache.coyote.ProtocolHandler protocolHandler;

  protected org.apache.coyote.Adapter adapter;

  private java.nio.charset.Charset uriCharset;

  private org.apache.tomcat.util.buf.EncodedSolidusHandling encodedSolidusHandling;

  protected boolean useBodyEncodingForURI;

  public org.apache.catalina.connector.Connector();
    Code:
       0: aload_0
       1: ldc           #1                  // String HTTP/1.1
       3: invokespecial #2                  // Method "<init>":(Ljava/lang/String;)V
       6: return

  public org.apache.catalina.connector.Connector(java.lang.String);
    Code:
       0: aload_0
       1: invokespecial #3                  // Method org/apache/catalina/util/LifecycleMBeanBase."<init>":()V
       4: aload_0
       5: aconst_null
       6: putfield      #4                  // Field service:Lorg/apache/catalina/Service;
       9: aload_0
      10: iconst_0
      11: putfield      #5                  // Field allowTrace:Z
      14: aload_0
      15: ldc2_w        #6                  // long 30000l
      18: putfield      #8                  // Field asyncTimeout:J
      21: aload_0
      22: iconst_0
      23: putfield      #9                  // Field enableLookups:Z
      26: aload_0
      27: iconst_0
      28: putfield      #10                 // Field xpoweredBy:Z
      31: aload_0
      32: aconst_null
      33: putfield      #11                 // Field proxyName:Ljava/lang/String;
      36: aload_0
      37: iconst_0
      38: putfield      #12                 // Field proxyPort:I
      41: aload_0
      42: getstatic     #13                 // Field RECYCLE_FACADES:Z
      45: putfield      #14                 // Field discardFacades:Z
      48: aload_0
      49: sipush        443
      52: putfield      #15                 // Field redirectPort:I
      55: aload_0
      56: ldc           #16                 // String http
      58: putfield      #17                 // Field scheme:Ljava/lang/String;
      61: aload_0
      62: iconst_0
      63: putfield      #18                 // Field secure:Z
      66: aload_0
      67: sipush        200
      70: putfield      #19                 // Field maxCookieCount:I
      73: aload_0
      74: sipush        10000
      77: putfield      #20                 // Field maxParameterCount:I
      80: aload_0
      81: ldc           #21                 // int 2097152
      83: putfield      #22                 // Field maxPostSize:I
      86: aload_0
      87: sipush        4096
      90: putfield      #23                 // Field maxSavePostSize:I
      93: aload_0
      94: ldc           #24                 // String POST
      96: putfield      #25                 // Field parseBodyMethods:Ljava/lang/String;
      99: aload_0
     100: iconst_0
     101: putfield      #26                 // Field useIPVHosts:Z
     104: aload_0
     105: aconst_null
     106: putfield      #27                 // Field adapter:Lorg/apache/coyote/Adapter;
     109: aload_0
     110: getstatic     #28                 // Field java/nio/charset/StandardCharsets.UTF_8:Ljava/nio/charset/Charset;
     113: putfield      #29                 // Field uriCharset:Ljava/nio/charset/Charset;
     116: aload_0
     117: getstatic     #30                 // Field org/apache/tomcat/util/buf/UDecoder.ALLOW_ENCODED_SLASH:Z
     120: ifeq          129
     123: getstatic     #31                 // Field org/apache/tomcat/util/buf/EncodedSolidusHandling.DECODE:Lorg/apache/tomcat/util/buf/EncodedSolidusHandling;
     126: goto          132
     129: getstatic     #32                 // Field org/apache/tomcat/util/buf/EncodedSolidusHandling.REJECT:Lorg/apache/tomcat/util/buf/EncodedSolidusHandling;
     132: putfield      #33                 // Field encodedSolidusHandling:Lorg/apache/tomcat/util/buf/EncodedSolidusHandling;
     135: aload_0
     136: iconst_0
     137: putfield      #34                 // Field useBodyEncodingForURI:Z
     140: invokestatic  #35                 // Method org/apache/catalina/core/AprStatus.isAprAvailable:()Z
     143: ifeq          156
     146: invokestatic  #36                 // Method org/apache/catalina/core/AprStatus.getUseAprConnector:()Z
     149: ifeq          156
     152: iconst_1
     153: goto          157
     156: iconst_0
     157: istore_2
     158: aconst_null
     159: astore_3
     160: aload_1
     161: iload_2
     162: invokestatic  #37                 // InterfaceMethod org/apache/coyote/ProtocolHandler.create:(Ljava/lang/String;Z)Lorg/apache/coyote/ProtocolHandler;
     165: astore_3
     166: goto          189
     169: astore        4
     171: getstatic     #39                 // Field log:Lorg/apache/juli/logging/Log;
     174: getstatic     #40                 // Field sm:Lorg/apache/tomcat/util/res/StringManager;
     177: ldc           #41                 // String coyoteConnector.protocolHandlerInstantiationFailed
     179: invokevirtual #42                 // Method org/apache/tomcat/util/res/StringManager.getString:(Ljava/lang/String;)Ljava/lang/String;
     182: aload         4
     184: invokeinterface #43,  3           // InterfaceMethod org/apache/juli/logging/Log.error:(Ljava/lang/Object;Ljava/lang/Throwable;)V
     189: aload_3
     190: ifnull        215
     193: aload_0
     194: aload_3
     195: putfield      #44                 // Field protocolHandler:Lorg/apache/coyote/ProtocolHandler;
     198: aload_0
     199: aload_0
     200: getfield      #44                 // Field protocolHandler:Lorg/apache/coyote/ProtocolHandler;
     203: invokevirtual #45                 // Method java/lang/Object.getClass:()Ljava/lang/Class;
     206: invokevirtual #46                 // Method java/lang/Class.getName:()Ljava/lang/String;
     209: putfield      #47                 // Field protocolHandlerClassName:Ljava/lang/String;
     212: goto          225
     215: aload_0
     216: aconst_null
     217: putfield      #44                 // Field protocolHandler:Lorg/apache/coyote/ProtocolHandler;
     220: aload_0
     221: aload_1
     222: putfield      #47                 // Field protocolHandlerClassName:Ljava/lang/String;
     225: aload_0
     226: ldc           #48                 // String org.apache.catalina.startup.EXIT_ON_INIT_FAILURE
     228: invokestatic  #49                 // Method java/lang/Boolean.getBoolean:(Ljava/lang/String;)Z
     231: invokevirtual #50                 // Method setThrowOnFailure:(Z)V
     234: return
    Exception table:
       from    to  target type
         160   166   169   Class java/lang/Exception

  public org.apache.catalina.connector.Connector(org.apache.coyote.ProtocolHandler);
    Code:
       0: aload_0
       1: invokespecial #3                  // Method org/apache/catalina/util/LifecycleMBeanBase."<init>":()V
       4: aload_0
       5: aconst_null
       6: putfield      #4                  // Field service:Lorg/apache/catalina/Service;
       9: aload_0
      10: iconst_0
      11: putfield      #5                  // Field allowTrace:Z
      14: aload_0
      15: ldc2_w        #6                  // long 30000l
      18: putfield      #8                  // Field asyncTimeout:J
      21: aload_0
      22: iconst_0
      23: putfield      #9                  // Field enableLookups:Z
      26: aload_0
      27: iconst_0
      28: putfield      #10                 // Field xpoweredBy:Z
      31: aload_0
      32: aconst_null
      33: putfield      #11                 // Field proxyName:Ljava/lang/String;
      36: aload_0
      37: iconst_0
      38: putfield      #12                 // Field proxyPort:I
      41: aload_0
      42: getstatic     #13                 // Field RECYCLE_FACADES:Z
      45: putfield      #14                 // Field discardFacades:Z
      48: aload_0
      49: sipush        443
      52: putfield      #15                 // Field redirectPort:I
      55: aload_0
      56: ldc           #16                 // String http
      58: putfield      #17                 // Field scheme:Ljava/lang/String;
      61: aload_0
      62: iconst_0
      63: putfield      #18                 // Field secure:Z
      66: aload_0
      67: sipush        200
      70: putfield      #19                 // Field maxCookieCount:I
      73: aload_0
      74: sipush        10000
      77: putfield      #20                 // Field maxParameterCount:I
      80: aload_0
      81: ldc           #21                 // int 2097152
      83: putfield      #22                 // Field maxPostSize:I
      86: aload_0
      87: sipush        4096
      90: putfield      #23                 // Field maxSavePostSize:I
      93: aload_0
      94: ldc           #24                 // String POST
      96: putfield      #25                 // Field parseBodyMethods:Ljava/lang/String;
      99: aload_0
     100: iconst_0
     101: putfield      #26                 // Field useIPVHosts:Z
     104: aload_0
     105: aconst_null
     106: putfield      #27                 // Field adapter:Lorg/apache/coyote/Adapter;
     109: aload_0
     110: getstatic     #28                 // Field java/nio/charset/StandardCharsets.UTF_8:Ljava/nio/charset/Charset;
     113: putfield      #29                 // Field uriCharset:Ljava/nio/charset/Charset;
     116: aload_0
     117: getstatic     #30                 // Field org/apache/tomcat/util/buf/UDecoder.ALLOW_ENCODED_SLASH:Z
     120: ifeq          129
     123: getstatic     #31                 // Field org/apache/tomcat/util/buf/EncodedSolidusHandling.DECODE:Lorg/apache/tomcat/util/buf/EncodedSolidusHandling;
     126: goto          132
     129: getstatic     #32                 // Field org/apache/tomcat/util/buf/EncodedSolidusHandling.REJECT:Lorg/apache/tomcat/util/buf/EncodedSolidusHandling;
     132: putfield      #33                 // Field encodedSolidusHandling:Lorg/apache/tomcat/util/buf/EncodedSolidusHandling;
     135: aload_0
     136: iconst_0
     137: putfield      #34                 // Field useBodyEncodingForURI:Z
     140: aload_0
     141: aload_1
     142: invokevirtual #45                 // Method java/lang/Object.getClass:()Ljava/lang/Class;
     145: invokevirtual #46                 // Method java/lang/Class.getName:()Ljava/lang/String;
     148: putfield      #47                 // Field protocolHandlerClassName:Ljava/lang/String;
     151: aload_0
     152: aload_1
     153: putfield      #44                 // Field protocolHandler:Lorg/apache/coyote/ProtocolHandler;
     156: aload_0
     157: ldc           #48                 // String org.apache.catalina.startup.EXIT_ON_INIT_FAILURE
     159: invokestatic  #49                 // Method java/lang/Boolean.getBoolean:(Ljava/lang/String;)Z
     162: invokevirtual #50                 // Method setThrowOnFailure:(Z)V
     165: return

  public java.lang.Object getProperty(java.lang.String);
    Code:
       0: aload_0
       1: getfield      #44                 // Field protocolHandler:Lorg/apache/coyote/ProtocolHandler;
       4: ifnonnull     9
       7: aconst_null
       8: areturn
       9: aload_0
      10: getfield      #44                 // Field protocolHandler:Lorg/apache/coyote/ProtocolHandler;
      13: aload_1
      14: invokestatic  #51                 // Method org/apache/tomcat/util/IntrospectionUtils.getProperty:(Ljava/lang/Object;Ljava/lang/String;)Ljava/lang/Object;
      17: areturn

  public boolean setProperty(java.lang.String, java.lang.String);
    Code:
       0: aload_0
       1: getfield      #44                 // Field protocolHandler:Lorg/apache/coyote/ProtocolHandler;
       4: ifnonnull     9
       7: iconst_0
       8: ireturn
       9: aload_0
      10: getfield      #44                 // Field protocolHandler:Lorg/apache/coyote/ProtocolHandler;
      13: aload_1
      14: aload_2
      15: invokestatic  #52                 // Method org/apache/tomcat/util/IntrospectionUtils.setProperty:(Ljava/lang/Object;Ljava/lang/String;Ljava/lang/String;)Z
      18: ireturn

  public java.lang.Object getAttribute(java.lang.String);
    Code:
       0: aload_0
       1: aload_1
       2: invokevirtual #53                 // Method getProperty:(Ljava/lang/String;)Ljava/lang/Object;
       5: areturn

  public void setAttribute(java.lang.String, java.lang.Object);
    Code:
       0: aload_0
       1: aload_1
       2: aload_2
       3: invokestatic  #54                 // Method java/lang/String.valueOf:(Ljava/lang/Object;)Ljava/lang/String;
       6: invokevirtual #55                 // Method setProperty:(Ljava/lang/String;Ljava/lang/String;)Z
       9: pop
      10: return

  public org.apache.catalina.Service getService();
    Code:
       0: aload_0
       1: getfield      #4                  // Field service:Lorg/apache/catalina/Service;
       4: areturn

  public void setService(org.apache.catalina.Service);
    Code:
       0: aload_0
       1: aload_1
       2: putfield      #4                  // Field service:Lorg/apache/catalina/Service;
       5: return

  public boolean getAllowTrace();
    Code:
       0: aload_0
       1: getfield      #5                  // Field allowTrace:Z
       4: ireturn

  public void setAllowTrace(boolean);
    Code:
       0: aload_0
       1: iload_1
       2: putfield      #5                  // Field allowTrace:Z
       5: aload_0
       6: ldc           #56                 // String allowTrace
       8: iload_1
       9: invokestatic  #57                 // Method java/lang/String.valueOf:(Z)Ljava/lang/String;
      12: invokevirtual #55                 // Method setProperty:(Ljava/lang/String;Ljava/lang/String;)Z
      15: pop
      16: return

  public long getAsyncTimeout();
    Code:
       0: aload_0
       1: getfield      #8                  // Field asyncTimeout:J
       4: lreturn

  public void setAsyncTimeout(long);
    Code:
       0: aload_0
       1: lload_1
       2: putfield      #8                  // Field asyncTimeout:J
       5: aload_0
       6: ldc           #58                 // String asyncTimeout
       8: lload_1
       9: invokestatic  #59                 // Method java/lang/String.valueOf:(J)Ljava/lang/String;
      12: invokevirtual #55                 // Method setProperty:(Ljava/lang/String;Ljava/lang/String;)Z
      15: pop
      16: return

  public boolean getDiscardFacades();
    Code:
       0: aload_0
       1: getfield      #14                 // Field discardFacades:Z
       4: ifne          13
       7: getstatic     #60                 // Field org/apache/catalina/Globals.IS_SECURITY_ENABLED:Z
      10: ifeq          17
      13: iconst_1
      14: goto          18
      17: iconst_0
      18: ireturn

  public void setDiscardFacades(boolean);
    Code:
       0: aload_0
       1: iload_1
       2: putfield      #14                 // Field discardFacades:Z
       5: return

  public boolean getEnableLookups();
    Code:
       0: aload_0
       1: getfield      #9                  // Field enableLookups:Z
       4: ireturn

  public void setEnableLookups(boolean);
    Code:
       0: aload_0
       1: iload_1
       2: putfield      #9                  // Field enableLookups:Z
       5: aload_0
       6: ldc           #61                 // String enableLookups
       8: iload_1
       9: invokestatic  #57                 // Method java/lang/String.valueOf:(Z)Ljava/lang/String;
      12: invokevirtual #55                 // Method setProperty:(Ljava/lang/String;Ljava/lang/String;)Z
      15: pop
      16: return

  public int getMaxCookieCount();
    Code:
       0: aload_0
       1: getfield      #19                 // Field maxCookieCount:I
       4: ireturn

  public void setMaxCookieCount(int);
    Code:
       0: aload_0
       1: iload_1
       2: putfield      #19                 // Field maxCookieCount:I
       5: return

  public int getMaxParameterCount();
    Code:
       0: aload_0
       1: getfield      #20                 // Field maxParameterCount:I
       4: ireturn

  public void setMaxParameterCount(int);
    Code:
       0: aload_0
       1: iload_1
       2: putfield      #20                 // Field maxParameterCount:I
       5: aload_0
       6: ldc           #62                 // String maxParameterCount
       8: iload_1
       9: invokestatic  #63                 // Method java/lang/String.valueOf:(I)Ljava/lang/String;
      12: invokevirtual #55                 // Method setProperty:(Ljava/lang/String;Ljava/lang/String;)Z
      15: pop
      16: return

  public int getMaxPostSize();
    Code:
       0: aload_0
       1: getfield      #22                 // Field maxPostSize:I
       4: ireturn

  public void setMaxPostSize(int);
    Code:
       0: aload_0
       1: iload_1
       2: putfield      #22                 // Field maxPostSize:I
       5: aload_0
       6: ldc           #64                 // String maxPostSize
       8: iload_1
       9: invokestatic  #63                 // Method java/lang/String.valueOf:(I)Ljava/lang/String;
      12: invokevirtual #55                 // Method setProperty:(Ljava/lang/String;Ljava/lang/String;)Z
      15: pop
      16: return

  public int getMaxSavePostSize();
    Code:
       0: aload_0
       1: getfield      #23                 // Field maxSavePostSize:I
       4: ireturn

  public void setMaxSavePostSize(int);
    Code:
       0: aload_0
       1: iload_1
       2: putfield      #23                 // Field maxSavePostSize:I
       5: aload_0
       6: ldc           #65                 // String maxSavePostSize
       8: iload_1
       9: invokestatic  #63                 // Method java/lang/String.valueOf:(I)Ljava/lang/String;
      12: invokevirtual #55                 // Method setProperty:(Ljava/lang/String;Ljava/lang/String;)Z
      15: pop
      16: return

  public java.lang.String getParseBodyMethods();
    Code:
       0: aload_0
       1: getfield      #25                 // Field parseBodyMethods:Ljava/lang/String;
       4: areturn

  public void setParseBodyMethods(java.lang.String);
    Code:
       0: new           #66                 // class java/util/HashSet
       3: dup
       4: invokespecial #67                 // Method java/util/HashSet."<init>":()V
       7: astore_2
       8: aconst_null
       9: aload_1
      10: if_acmpeq     27
      13: aload_2
      14: aload_1
      15: ldc           #68                 // String \\s*,\\s*
      17: invokevirtual #69                 // Method java/lang/String.split:(Ljava/lang/String;)[Ljava/lang/String;
      20: invokestatic  #70                 // Method java/util/Arrays.asList:([Ljava/lang/Object;)Ljava/util/List;
      23: invokevirtual #71                 // Method java/util/HashSet.addAll:(Ljava/util/Collection;)Z
      26: pop
      27: aload_2
      28: ldc           #72                 // String TRACE
      30: invokevirtual #73                 // Method java/util/HashSet.contains:(Ljava/lang/Object;)Z
      33: ifeq          52
      36: new           #74                 // class java/lang/IllegalArgumentException
      39: dup
      40: getstatic     #40                 // Field sm:Lorg/apache/tomcat/util/res/StringManager;
      43: ldc           #75                 // String coyoteConnector.parseBodyMethodNoTrace
      45: invokevirtual #42                 // Method org/apache/tomcat/util/res/StringManager.getString:(Ljava/lang/String;)Ljava/lang/String;
      48: invokespecial #76                 // Method java/lang/IllegalArgumentException."<init>":(Ljava/lang/String;)V
      51: athrow
      52: aload_0
      53: aload_1
      54: putfield      #25                 // Field parseBodyMethods:Ljava/lang/String;
      57: aload_0
      58: aload_2
      59: putfield      #77                 // Field parseBodyMethodsSet:Ljava/util/HashSet;
      62: aload_0
      63: ldc           #78                 // String parseBodyMethods
      65: aload_1
      66: invokevirtual #55                 // Method setProperty:(Ljava/lang/String;Ljava/lang/String;)Z
      69: pop
      70: return

  protected boolean isParseBodyMethod(java.lang.String);
    Code:
       0: aload_0
       1: getfield      #77                 // Field parseBodyMethodsSet:Ljava/util/HashSet;
       4: aload_1
       5: invokevirtual #73                 // Method java/util/HashSet.contains:(Ljava/lang/Object;)Z
       8: ireturn

  public int getPort();
    Code:
       0: aload_0
       1: getfield      #44                 // Field protocolHandler:Lorg/apache/coyote/ProtocolHandler;
       4: instanceof    #79                 // class org/apache/coyote/AbstractProtocol
       7: ifeq          21
      10: aload_0
      11: getfield      #44                 // Field protocolHandler:Lorg/apache/coyote/ProtocolHandler;
      14: checkcast     #79                 // class org/apache/coyote/AbstractProtocol
      17: invokevirtual #80                 // Method org/apache/coyote/AbstractProtocol.getPort:()I
      20: ireturn
      21: aload_0
      22: ldc           #81                 // String port
      24: invokevirtual #53                 // Method getProperty:(Ljava/lang/String;)Ljava/lang/Object;
      27: astore_1
      28: aload_1
      29: instanceof    #82                 // class java/lang/Integer
      32: ifeq          43
      35: aload_1
      36: checkcast     #82                 // class java/lang/Integer
      39: invokevirtual #83                 // Method java/lang/Integer.intValue:()I
      42: ireturn
      43: iconst_m1
      44: ireturn

  public void setPort(int);
    Code:
       0: aload_0
       1: ldc           #81                 // String port
       3: iload_1
       4: invokestatic  #63                 // Method java/lang/String.valueOf:(I)Ljava/lang/String;
       7: invokevirtual #55                 // Method setProperty:(Ljava/lang/String;Ljava/lang/String;)Z
      10: pop
      11: return

  public int getPortOffset();
    Code:
       0: aload_0
       1: getfield      #44                 // Field protocolHandler:Lorg/apache/coyote/ProtocolHandler;
       4: instanceof    #79                 // class org/apache/coyote/AbstractProtocol
       7: ifeq          21
      10: aload_0
      11: getfield      #44                 // Field protocolHandler:Lorg/apache/coyote/ProtocolHandler;
      14: checkcast     #79                 // class org/apache/coyote/AbstractProtocol
      17: invokevirtual #84                 // Method org/apache/coyote/AbstractProtocol.getPortOffset:()I
      20: ireturn
      21: aload_0
      22: ldc           #85                 // String portOffset
      24: invokevirtual #53                 // Method getProperty:(Ljava/lang/String;)Ljava/lang/Object;
      27: astore_1
      28: aload_1
      29: instanceof    #82                 // class java/lang/Integer
      32: ifeq          43
      35: aload_1
      36: checkcast     #82                 // class java/lang/Integer
      39: invokevirtual #83                 // Method java/lang/Integer.intValue:()I
      42: ireturn
      43: iconst_0
      44: ireturn

  public void setPortOffset(int);
    Code:
       0: aload_0
       1: ldc           #85                 // String portOffset
       3: iload_1
       4: invokestatic  #63                 // Method java/lang/String.valueOf:(I)Ljava/lang/String;
       7: invokevirtual #55                 // Method setProperty:(Ljava/lang/String;Ljava/lang/String;)Z
      10: pop
      11: return

  public int getPortWithOffset();
    Code:
       0: aload_0
       1: invokevirtual #86                 // Method getPort:()I
       4: istore_1
       5: iload_1
       6: ifle          16
       9: iload_1
      10: aload_0
      11: invokevirtual #87                 // Method getPortOffset:()I
      14: iadd
      15: ireturn
      16: iload_1
      17: ireturn

  public int getLocalPort();
    Code:
       0: aload_0
       1: ldc           #88                 // String localPort
       3: invokevirtual #53                 // Method getProperty:(Ljava/lang/String;)Ljava/lang/Object;
       6: checkcast     #82                 // class java/lang/Integer
       9: invokevirtual #83                 // Method java/lang/Integer.intValue:()I
      12: ireturn

  public java.lang.String getProtocol();
    Code:
       0: invokestatic  #36                 // Method org/apache/catalina/core/AprStatus.getUseAprConnector:()Z
       3: istore_1
       4: iload_1
       5: ifne          23
       8: ldc           #89                 // class org/apache/coyote/http11/Http11NioProtocol
      10: invokevirtual #46                 // Method java/lang/Class.getName:()Ljava/lang/String;
      13: aload_0
      14: getfield      #47                 // Field protocolHandlerClassName:Ljava/lang/String;
      17: invokevirtual #90                 // Method java/lang/String.equals:(Ljava/lang/Object;)Z
      20: ifne          42
      23: iload_1
      24: ifeq          45
      27: ldc           #91                 // class org/apache/coyote/http11/Http11AprProtocol
      29: invokevirtual #46                 // Method java/lang/Class.getName:()Ljava/lang/String;
      32: aload_0
      33: getfield      #47                 // Field protocolHandlerClassName:Ljava/lang/String;
      36: invokevirtual #90                 // Method java/lang/String.equals:(Ljava/lang/Object;)Z
      39: ifeq          45
      42: ldc           #1                  // String HTTP/1.1
      44: areturn
      45: iload_1
      46: ifne          64
      49: ldc           #92                 // class org/apache/coyote/ajp/AjpNioProtocol
      51: invokevirtual #46                 // Method java/lang/Class.getName:()Ljava/lang/String;
      54: aload_0
      55: getfield      #47                 // Field protocolHandlerClassName:Ljava/lang/String;
      58: invokevirtual #90                 // Method java/lang/String.equals:(Ljava/lang/Object;)Z
      61: ifne          83
      64: iload_1
      65: ifeq          86
      68: ldc           #93                 // class org/apache/coyote/ajp/AjpAprProtocol
      70: invokevirtual #46                 // Method java/lang/Class.getName:()Ljava/lang/String;
      73: aload_0
      74: getfield      #47                 // Field protocolHandlerClassName:Ljava/lang/String;
      77: invokevirtual #90                 // Method java/lang/String.equals:(Ljava/lang/Object;)Z
      80: ifeq          86
      83: ldc           #94                 // String AJP/1.3
      85: areturn
      86: aload_0
      87: getfield      #47                 // Field protocolHandlerClassName:Ljava/lang/String;
      90: areturn

  public java.lang.String getProtocolHandlerClassName();
    Code:
       0: aload_0
       1: getfield      #47                 // Field protocolHandlerClassName:Ljava/lang/String;
       4: areturn

  public org.apache.coyote.ProtocolHandler getProtocolHandler();
    Code:
       0: aload_0
       1: getfield      #44                 // Field protocolHandler:Lorg/apache/coyote/ProtocolHandler;
       4: areturn

  public java.lang.String getProxyName();
    Code:
       0: aload_0
       1: getfield      #11                 // Field proxyName:Ljava/lang/String;
       4: areturn

  public void setProxyName(java.lang.String);
    Code:
       0: aload_1
       1: ifnull        19
       4: aload_1
       5: invokevirtual #95                 // Method java/lang/String.length:()I
       8: ifle          19
      11: aload_0
      12: aload_1
      13: putfield      #11                 // Field proxyName:Ljava/lang/String;
      16: goto          24
      19: aload_0
      20: aconst_null
      21: putfield      #11                 // Field proxyName:Ljava/lang/String;
      24: aload_0
      25: ldc           #96                 // String proxyName
      27: aload_0
      28: getfield      #11                 // Field proxyName:Ljava/lang/String;
      31: invokevirtual #55                 // Method setProperty:(Ljava/lang/String;Ljava/lang/String;)Z
      34: pop
      35: return

  public int getProxyPort();
    Code:
       0: aload_0
       1: getfield      #12                 // Field proxyPort:I
       4: ireturn

  public void setProxyPort(int);
    Code:
       0: aload_0
       1: iload_1
       2: putfield      #12                 // Field proxyPort:I
       5: aload_0
       6: ldc           #97                 // String proxyPort
       8: iload_1
       9: invokestatic  #63                 // Method java/lang/String.valueOf:(I)Ljava/lang/String;
      12: invokevirtual #55                 // Method setProperty:(Ljava/lang/String;Ljava/lang/String;)Z
      15: pop
      16: return

  public int getRedirectPort();
    Code:
       0: aload_0
       1: getfield      #15                 // Field redirectPort:I
       4: ireturn

  public void setRedirectPort(int);
    Code:
       0: aload_0
       1: iload_1
       2: putfield      #15                 // Field redirectPort:I
       5: aload_0
       6: ldc           #98                 // String redirectPort
       8: iload_1
       9: invokestatic  #63                 // Method java/lang/String.valueOf:(I)Ljava/lang/String;
      12: invokevirtual #55                 // Method setProperty:(Ljava/lang/String;Ljava/lang/String;)Z
      15: pop
      16: return

  public int getRedirectPortWithOffset();
    Code:
       0: aload_0
       1: invokevirtual #99                 // Method getRedirectPort:()I
       4: aload_0
       5: invokevirtual #87                 // Method getPortOffset:()I
       8: iadd
       9: ireturn

  public java.lang.String getScheme();
    Code:
       0: aload_0
       1: getfield      #17                 // Field scheme:Ljava/lang/String;
       4: areturn

  public void setScheme(java.lang.String);
    Code:
       0: aload_0
       1: aload_1
       2: putfield      #17                 // Field scheme:Ljava/lang/String;
       5: return

  public boolean getSecure();
    Code:
       0: aload_0
       1: getfield      #18                 // Field secure:Z
       4: ireturn

  public void setSecure(boolean);
    Code:
       0: aload_0
       1: iload_1
       2: putfield      #18                 // Field secure:Z
       5: aload_0
       6: ldc           #100                // String secure
       8: iload_1
       9: invokestatic  #101                // Method java/lang/Boolean.toString:(Z)Ljava/lang/String;
      12: invokevirtual #55                 // Method setProperty:(Ljava/lang/String;Ljava/lang/String;)Z
      15: pop
      16: return

  public java.lang.String getURIEncoding();
    Code:
       0: aload_0
       1: getfield      #29                 // Field uriCharset:Ljava/nio/charset/Charset;
       4: invokevirtual #102                // Method java/nio/charset/Charset.name:()Ljava/lang/String;
       7: areturn

  public java.nio.charset.Charset getURICharset();
    Code:
       0: aload_0
       1: getfield      #29                 // Field uriCharset:Ljava/nio/charset/Charset;
       4: areturn

  public void setURIEncoding(java.lang.String);
    Code:
       0: aload_1
       1: invokestatic  #103                // Method org/apache/tomcat/util/buf/B2CConverter.getCharset:(Ljava/lang/String;)Ljava/nio/charset/Charset;
       4: astore_2
       5: aload_2
       6: invokestatic  #104                // Method org/apache/tomcat/util/buf/CharsetUtil.isAsciiSuperset:(Ljava/nio/charset/Charset;)Z
       9: ifne          36
      12: getstatic     #39                 // Field log:Lorg/apache/juli/logging/Log;
      15: getstatic     #40                 // Field sm:Lorg/apache/tomcat/util/res/StringManager;
      18: ldc           #105                // String coyoteConnector.notAsciiSuperset
      20: iconst_1
      21: anewarray     #106                // class java/lang/Object
      24: dup
      25: iconst_0
      26: aload_1
      27: aastore
      28: invokevirtual #107                // Method org/apache/tomcat/util/res/StringManager.getString:(Ljava/lang/String;[Ljava/lang/Object;)Ljava/lang/String;
      31: invokeinterface #108,  2          // InterfaceMethod org/apache/juli/logging/Log.error:(Ljava/lang/Object;)V
      36: aload_0
      37: aload_2
      38: putfield      #29                 // Field uriCharset:Ljava/nio/charset/Charset;
      41: goto          80
      44: astore_2
      45: getstatic     #39                 // Field log:Lorg/apache/juli/logging/Log;
      48: getstatic     #40                 // Field sm:Lorg/apache/tomcat/util/res/StringManager;
      51: ldc           #110                // String coyoteConnector.invalidEncoding
      53: iconst_2
      54: anewarray     #106                // class java/lang/Object
      57: dup
      58: iconst_0
      59: aload_1
      60: aastore
      61: dup
      62: iconst_1
      63: aload_0
      64: getfield      #29                 // Field uriCharset:Ljava/nio/charset/Charset;
      67: invokevirtual #102                // Method java/nio/charset/Charset.name:()Ljava/lang/String;
      70: aastore
      71: invokevirtual #107                // Method org/apache/tomcat/util/res/StringManager.getString:(Ljava/lang/String;[Ljava/lang/Object;)Ljava/lang/String;
      74: aload_2
      75: invokeinterface #43,  3           // InterfaceMethod org/apache/juli/logging/Log.error:(Ljava/lang/Object;Ljava/lang/Throwable;)V
      80: return
    Exception table:
       from    to  target type
           0    41    44   Class java/io/UnsupportedEncodingException

  public boolean getUseBodyEncodingForURI();
    Code:
       0: aload_0
       1: getfield      #34                 // Field useBodyEncodingForURI:Z
       4: ireturn

  public void setUseBodyEncodingForURI(boolean);
    Code:
       0: aload_0
       1: iload_1
       2: putfield      #34                 // Field useBodyEncodingForURI:Z
       5: aload_0
       6: ldc           #111                // String useBodyEncodingForURI
       8: iload_1
       9: invokestatic  #57                 // Method java/lang/String.valueOf:(Z)Ljava/lang/String;
      12: invokevirtual #55                 // Method setProperty:(Ljava/lang/String;Ljava/lang/String;)Z
      15: pop
      16: return

  public boolean getXpoweredBy();
    Code:
       0: aload_0
       1: getfield      #10                 // Field xpoweredBy:Z
       4: ireturn

  public void setXpoweredBy(boolean);
    Code:
       0: aload_0
       1: iload_1
       2: putfield      #10                 // Field xpoweredBy:Z
       5: aload_0
       6: ldc           #112                // String xpoweredBy
       8: iload_1
       9: invokestatic  #57                 // Method java/lang/String.valueOf:(Z)Ljava/lang/String;
      12: invokevirtual #55                 // Method setProperty:(Ljava/lang/String;Ljava/lang/String;)Z
      15: pop
      16: return

  public void setUseIPVHosts(boolean);
    Code:
       0: aload_0
       1: iload_1
       2: putfield      #26                 // Field useIPVHosts:Z
       5: aload_0
       6: ldc           #113                // String useIPVHosts
       8: iload_1
       9: invokestatic  #57                 // Method java/lang/String.valueOf:(Z)Ljava/lang/String;
      12: invokevirtual #55                 // Method setProperty:(Ljava/lang/String;Ljava/lang/String;)Z
      15: pop
      16: return

  public boolean getUseIPVHosts();
    Code:
       0: aload_0
       1: getfield      #26                 // Field useIPVHosts:Z
       4: ireturn

  public java.lang.String getExecutorName();
    Code:
       0: aload_0
       1: getfield      #44                 // Field protocolHandler:Lorg/apache/coyote/ProtocolHandler;
       4: invokeinterface #114,  1          // InterfaceMethod org/apache/coyote/ProtocolHandler.getExecutor:()Ljava/util/concurrent/Executor;
       9: astore_1
      10: aload_1
      11: instanceof    #115                // class org/apache/catalina/Executor
      14: ifeq          27
      17: aload_1
      18: checkcast     #115                // class org/apache/catalina/Executor
      21: invokeinterface #116,  1          // InterfaceMethod org/apache/catalina/Executor.getName:()Ljava/lang/String;
      26: areturn
      27: ldc           #118                // String Internal
      29: areturn

  public void addSslHostConfig(org.apache.tomcat.util.net.SSLHostConfig);
    Code:
       0: aload_0
       1: getfield      #44                 // Field protocolHandler:Lorg/apache/coyote/ProtocolHandler;
       4: aload_1
       5: invokeinterface #119,  2          // InterfaceMethod org/apache/coyote/ProtocolHandler.addSslHostConfig:(Lorg/apache/tomcat/util/net/SSLHostConfig;)V
      10: return

  public org.apache.tomcat.util.net.SSLHostConfig[] findSslHostConfigs();
    Code:
       0: aload_0
       1: getfield      #44                 // Field protocolHandler:Lorg/apache/coyote/ProtocolHandler;
       4: invokeinterface #120,  1          // InterfaceMethod org/apache/coyote/ProtocolHandler.findSslHostConfigs:()[Lorg/apache/tomcat/util/net/SSLHostConfig;
       9: areturn

  public void addUpgradeProtocol(org.apache.coyote.UpgradeProtocol);
    Code:
       0: aload_0
       1: getfield      #44                 // Field protocolHandler:Lorg/apache/coyote/ProtocolHandler;
       4: aload_1
       5: invokeinterface #121,  2          // InterfaceMethod org/apache/coyote/ProtocolHandler.addUpgradeProtocol:(Lorg/apache/coyote/UpgradeProtocol;)V
      10: return

  public org.apache.coyote.UpgradeProtocol[] findUpgradeProtocols();
    Code:
       0: aload_0
       1: getfield      #44                 // Field protocolHandler:Lorg/apache/coyote/ProtocolHandler;
       4: invokeinterface #122,  1          // InterfaceMethod org/apache/coyote/ProtocolHandler.findUpgradeProtocols:()[Lorg/apache/coyote/UpgradeProtocol;
       9: areturn

  public java.lang.String getEncodedSolidusHandling();
    Code:
       0: aload_0
       1: getfield      #33                 // Field encodedSolidusHandling:Lorg/apache/tomcat/util/buf/EncodedSolidusHandling;
       4: invokevirtual #123                // Method org/apache/tomcat/util/buf/EncodedSolidusHandling.getValue:()Ljava/lang/String;
       7: areturn

  public void setEncodedSolidusHandling(java.lang.String);
    Code:
       0: aload_0
       1: aload_1
       2: invokestatic  #124                // Method org/apache/tomcat/util/buf/EncodedSolidusHandling.fromString:(Ljava/lang/String;)Lorg/apache/tomcat/util/buf/EncodedSolidusHandling;
       5: putfield      #33                 // Field encodedSolidusHandling:Lorg/apache/tomcat/util/buf/EncodedSolidusHandling;
       8: return

  public org.apache.tomcat.util.buf.EncodedSolidusHandling getEncodedSolidusHandlingInternal();
    Code:
       0: aload_0
       1: getfield      #33                 // Field encodedSolidusHandling:Lorg/apache/tomcat/util/buf/EncodedSolidusHandling;
       4: areturn

  public org.apache.catalina.connector.Request createRequest();
    Code:
       0: new           #125                // class org/apache/catalina/connector/Request
       3: dup
       4: aload_0
       5: invokespecial #126                // Method org/apache/catalina/connector/Request."<init>":(Lorg/apache/catalina/connector/Connector;)V
       8: areturn

  public org.apache.catalina.connector.Response createResponse();
    Code:
       0: aload_0
       1: getfield      #44                 // Field protocolHandler:Lorg/apache/coyote/ProtocolHandler;
       4: invokeinterface #127,  1          // InterfaceMethod org/apache/coyote/ProtocolHandler.getDesiredBufferSize:()I
       9: istore_1
      10: iload_1
      11: ifle          23
      14: new           #128                // class org/apache/catalina/connector/Response
      17: dup
      18: iload_1
      19: invokespecial #129                // Method org/apache/catalina/connector/Response."<init>":(I)V
      22: areturn
      23: new           #128                // class org/apache/catalina/connector/Response
      26: dup
      27: invokespecial #130                // Method org/apache/catalina/connector/Response."<init>":()V
      30: areturn

  protected java.lang.String createObjectNameKeyProperties(java.lang.String);
    Code:
       0: aload_0
       1: ldc           #131                // String address
       3: invokevirtual #53                 // Method getProperty:(Ljava/lang/String;)Ljava/lang/Object;
       6: astore_2
       7: new           #132                // class java/lang/StringBuilder
      10: dup
      11: ldc           #133                // String type=
      13: invokespecial #134                // Method java/lang/StringBuilder."<init>":(Ljava/lang/String;)V
      16: astore_3
      17: aload_3
      18: aload_1
      19: invokevirtual #135                // Method java/lang/StringBuilder.append:(Ljava/lang/String;)Ljava/lang/StringBuilder;
      22: pop
      23: aload_3
      24: ldc           #136                // String ,port=
      26: invokevirtual #135                // Method java/lang/StringBuilder.append:(Ljava/lang/String;)Ljava/lang/StringBuilder;
      29: pop
      30: aload_0
      31: invokevirtual #137                // Method getPortWithOffset:()I
      34: istore        4
      36: iload         4
      38: ifle          51
      41: aload_3
      42: iload         4
      44: invokevirtual #138                // Method java/lang/StringBuilder.append:(I)Ljava/lang/StringBuilder;
      47: pop
      48: goto          69
      51: aload_3
      52: ldc           #139                // String auto-
      54: invokevirtual #135                // Method java/lang/StringBuilder.append:(Ljava/lang/String;)Ljava/lang/StringBuilder;
      57: pop
      58: aload_3
      59: aload_0
      60: ldc           #140                // String nameIndex
      62: invokevirtual #53                 // Method getProperty:(Ljava/lang/String;)Ljava/lang/Object;
      65: invokevirtual #141                // Method java/lang/StringBuilder.append:(Ljava/lang/Object;)Ljava/lang/StringBuilder;
      68: pop
      69: ldc           #142                // String
      71: astore        5
      73: aload_2
      74: instanceof    #143                // class java/net/InetAddress
      77: ifeq          92
      80: aload_2
      81: checkcast     #143                // class java/net/InetAddress
      84: invokevirtual #144                // Method java/net/InetAddress.getHostAddress:()Ljava/lang/String;
      87: astore        5
      89: goto          102
      92: aload_2
      93: ifnull        102
      96: aload_2
      97: invokevirtual #145                // Method java/lang/Object.toString:()Ljava/lang/String;
     100: astore        5
     102: aload         5
     104: invokevirtual #95                 // Method java/lang/String.length:()I
     107: ifle          127
     110: aload_3
     111: ldc           #146                // String ,address=
     113: invokevirtual #135                // Method java/lang/StringBuilder.append:(Ljava/lang/String;)Ljava/lang/StringBuilder;
     116: pop
     117: aload_3
     118: aload         5
     120: invokestatic  #147                // Method javax/management/ObjectName.quote:(Ljava/lang/String;)Ljava/lang/String;
     123: invokevirtual #135                // Method java/lang/StringBuilder.append:(Ljava/lang/String;)Ljava/lang/StringBuilder;
     126: pop
     127: aload_3
     128: invokevirtual #148                // Method java/lang/StringBuilder.toString:()Ljava/lang/String;
     131: areturn

  public void pause();
    Code:
       0: aload_0
       1: getfield      #44                 // Field protocolHandler:Lorg/apache/coyote/ProtocolHandler;
       4: ifnull        16
       7: aload_0
       8: getfield      #44                 // Field protocolHandler:Lorg/apache/coyote/ProtocolHandler;
      11: invokeinterface #149,  1          // InterfaceMethod org/apache/coyote/ProtocolHandler.pause:()V
      16: goto          37
      19: astore_1
      20: getstatic     #39                 // Field log:Lorg/apache/juli/logging/Log;
      23: getstatic     #40                 // Field sm:Lorg/apache/tomcat/util/res/StringManager;
      26: ldc           #150                // String coyoteConnector.protocolHandlerPauseFailed
      28: invokevirtual #42                 // Method org/apache/tomcat/util/res/StringManager.getString:(Ljava/lang/String;)Ljava/lang/String;
      31: aload_1
      32: invokeinterface #43,  3           // InterfaceMethod org/apache/juli/logging/Log.error:(Ljava/lang/Object;Ljava/lang/Throwable;)V
      37: return
    Exception table:
       from    to  target type
           0    16    19   Class java/lang/Exception

  public void resume();
    Code:
       0: aload_0
       1: getfield      #44                 // Field protocolHandler:Lorg/apache/coyote/ProtocolHandler;
       4: ifnull        16
       7: aload_0
       8: getfield      #44                 // Field protocolHandler:Lorg/apache/coyote/ProtocolHandler;
      11: invokeinterface #151,  1          // InterfaceMethod org/apache/coyote/ProtocolHandler.resume:()V
      16: goto          37
      19: astore_1
      20: getstatic     #39                 // Field log:Lorg/apache/juli/logging/Log;
      23: getstatic     #40                 // Field sm:Lorg/apache/tomcat/util/res/StringManager;
      26: ldc           #152                // String coyoteConnector.protocolHandlerResumeFailed
      28: invokevirtual #42                 // Method org/apache/tomcat/util/res/StringManager.getString:(Ljava/lang/String;)Ljava/lang/String;
      31: aload_1
      32: invokeinterface #43,  3           // InterfaceMethod org/apache/juli/logging/Log.error:(Ljava/lang/Object;Ljava/lang/Throwable;)V
      37: return
    Exception table:
       from    to  target type
           0    16    19   Class java/lang/Exception

  protected void initInternal() throws org.apache.catalina.LifecycleException;
    Code:
       0: aload_0
       1: invokespecial #153                // Method org/apache/catalina/util/LifecycleMBeanBase.initInternal:()V
       4: aload_0
       5: getfield      #44                 // Field protocolHandler:Lorg/apache/coyote/ProtocolHandler;
       8: ifnonnull     27
      11: new           #154                // class org/apache/catalina/LifecycleException
      14: dup
      15: getstatic     #40                 // Field sm:Lorg/apache/tomcat/util/res/StringManager;
      18: ldc           #41                 // String coyoteConnector.protocolHandlerInstantiationFailed
      20: invokevirtual #42                 // Method org/apache/tomcat/util/res/StringManager.getString:(Ljava/lang/String;)Ljava/lang/String;
      23: invokespecial #155                // Method org/apache/catalina/LifecycleException."<init>":(Ljava/lang/String;)V
      26: athrow
      27: aload_0
      28: new           #156                // class org/apache/catalina/connector/CoyoteAdapter
      31: dup
      32: aload_0
      33: invokespecial #157                // Method org/apache/catalina/connector/CoyoteAdapter."<init>":(Lorg/apache/catalina/connector/Connector;)V
      36: putfield      #27                 // Field adapter:Lorg/apache/coyote/Adapter;
      39: aload_0
      40: getfield      #44                 // Field protocolHandler:Lorg/apache/coyote/ProtocolHandler;
      43: aload_0
      44: getfield      #27                 // Field adapter:Lorg/apache/coyote/Adapter;
      47: invokeinterface #158,  2          // InterfaceMethod org/apache/coyote/ProtocolHandler.setAdapter:(Lorg/apache/coyote/Adapter;)V
      52: aload_0
      53: getfield      #4                  // Field service:Lorg/apache/catalina/Service;
      56: ifnull        82
      59: aload_0
      60: getfield      #44                 // Field protocolHandler:Lorg/apache/coyote/ProtocolHandler;
      63: aload_0
      64: getfield      #4                  // Field service:Lorg/apache/catalina/Service;
      67: invokeinterface #159,  1          // InterfaceMethod org/apache/catalina/Service.getServer:()Lorg/apache/catalina/Server;
      72: invokeinterface #160,  1          // InterfaceMethod org/apache/catalina/Server.getUtilityExecutor:()Ljava/util/concurrent/ScheduledExecutorService;
      77: invokeinterface #161,  2          // InterfaceMethod org/apache/coyote/ProtocolHandler.setUtilityExecutor:(Ljava/util/concurrent/ScheduledExecutorService;)V
      82: aconst_null
      83: aload_0
      84: getfield      #77                 // Field parseBodyMethodsSet:Ljava/util/HashSet;
      87: if_acmpne     98
      90: aload_0
      91: aload_0
      92: invokevirtual #162                // Method getParseBodyMethods:()Ljava/lang/String;
      95: invokevirtual #163                // Method setParseBodyMethods:(Ljava/lang/String;)V
      98: aload_0
      99: getfield      #44                 // Field protocolHandler:Lorg/apache/coyote/ProtocolHandler;
     102: invokeinterface #164,  1          // InterfaceMethod org/apache/coyote/ProtocolHandler.isAprRequired:()Z
     107: ifeq          143
     110: invokestatic  #165                // Method org/apache/catalina/core/AprStatus.isInstanceCreated:()Z
     113: ifne          143
     116: new           #154                // class org/apache/catalina/LifecycleException
     119: dup
     120: getstatic     #40                 // Field sm:Lorg/apache/tomcat/util/res/StringManager;
     123: ldc           #166                // String coyoteConnector.protocolHandlerNoAprListener
     125: iconst_1
     126: anewarray     #106                // class java/lang/Object
     129: dup
     130: iconst_0
     131: aload_0
     132: invokevirtual #167                // Method getProtocolHandlerClassName:()Ljava/lang/String;
     135: aastore
     136: invokevirtual #107                // Method org/apache/tomcat/util/res/StringManager.getString:(Ljava/lang/String;[Ljava/lang/Object;)Ljava/lang/String;
     139: invokespecial #155                // Method org/apache/catalina/LifecycleException."<init>":(Ljava/lang/String;)V
     142: athrow
     143: aload_0
     144: getfield      #44                 // Field protocolHandler:Lorg/apache/coyote/ProtocolHandler;
     147: invokeinterface #164,  1          // InterfaceMethod org/apache/coyote/ProtocolHandler.isAprRequired:()Z
     152: ifeq          188
     155: invokestatic  #35                 // Method org/apache/catalina/core/AprStatus.isAprAvailable:()Z
     158: ifne          188
     161: new           #154                // class org/apache/catalina/LifecycleException
     164: dup
     165: getstatic     #40                 // Field sm:Lorg/apache/tomcat/util/res/StringManager;
     168: ldc           #168                // String coyoteConnector.protocolHandlerNoAprLibrary
     170: iconst_1
     171: anewarray     #106                // class java/lang/Object
     174: dup
     175: iconst_0
     176: aload_0
     177: invokevirtual #167                // Method getProtocolHandlerClassName:()Ljava/lang/String;
     180: aastore
     181: invokevirtual #107                // Method org/apache/tomcat/util/res/StringManager.getString:(Ljava/lang/String;[Ljava/lang/Object;)Ljava/lang/String;
     184: invokespecial #155                // Method org/apache/catalina/LifecycleException."<init>":(Ljava/lang/String;)V
     187: athrow
     188: invokestatic  #35                 // Method org/apache/catalina/core/AprStatus.isAprAvailable:()Z
     191: ifeq          241
     194: invokestatic  #169                // Method org/apache/catalina/core/AprStatus.getUseOpenSSL:()Z
     197: ifeq          241
     200: aload_0
     201: getfield      #44                 // Field protocolHandler:Lorg/apache/coyote/ProtocolHandler;
     204: instanceof    #170                // class org/apache/coyote/http11/AbstractHttp11JsseProtocol
     207: ifeq          241
     210: aload_0
     211: getfield      #44                 // Field protocolHandler:Lorg/apache/coyote/ProtocolHandler;
     214: checkcast     #170                // class org/apache/coyote/http11/AbstractHttp11JsseProtocol
     217: astore_1
     218: aload_1
     219: invokevirtual #171                // Method org/apache/coyote/http11/AbstractHttp11JsseProtocol.isSSLEnabled:()Z
     222: ifeq          241
     225: aload_1
     226: invokevirtual #172                // Method org/apache/coyote/http11/AbstractHttp11JsseProtocol.getSslImplementationName:()Ljava/lang/String;
     229: ifnonnull     241
     232: aload_1
     233: ldc           #173                // class org/apache/tomcat/util/net/openssl/OpenSSLImplementation
     235: invokevirtual #46                 // Method java/lang/Class.getName:()Ljava/lang/String;
     238: invokevirtual #174                // Method org/apache/coyote/http11/AbstractHttp11JsseProtocol.setSslImplementationName:(Ljava/lang/String;)V
     241: aload_0
     242: getfield      #44                 // Field protocolHandler:Lorg/apache/coyote/ProtocolHandler;
     245: invokeinterface #175,  1          // InterfaceMethod org/apache/coyote/ProtocolHandler.init:()V
     250: goto          271
     253: astore_1
     254: new           #154                // class org/apache/catalina/LifecycleException
     257: dup
     258: getstatic     #40                 // Field sm:Lorg/apache/tomcat/util/res/StringManager;
     261: ldc           #176                // String coyoteConnector.protocolHandlerInitializationFailed
     263: invokevirtual #42                 // Method org/apache/tomcat/util/res/StringManager.getString:(Ljava/lang/String;)Ljava/lang/String;
     266: aload_1
     267: invokespecial #177                // Method org/apache/catalina/LifecycleException."<init>":(Ljava/lang/String;Ljava/lang/Throwable;)V
     270: athrow
     271: return
    Exception table:
       from    to  target type
         241   250   253   Class java/lang/Exception

  protected void startInternal() throws org.apache.catalina.LifecycleException;
    Code:
       0: aload_0
       1: invokevirtual #137                // Method getPortWithOffset:()I
       4: ifge          37
       7: new           #154                // class org/apache/catalina/LifecycleException
      10: dup
      11: getstatic     #40                 // Field sm:Lorg/apache/tomcat/util/res/StringManager;
      14: ldc           #178                // String coyoteConnector.invalidPort
      16: iconst_1
      17: anewarray     #106                // class java/lang/Object
      20: dup
      21: iconst_0
      22: aload_0
      23: invokevirtual #137                // Method getPortWithOffset:()I
      26: invokestatic  #179                // Method java/lang/Integer.valueOf:(I)Ljava/lang/Integer;
      29: aastore
      30: invokevirtual #107                // Method org/apache/tomcat/util/res/StringManager.getString:(Ljava/lang/String;[Ljava/lang/Object;)Ljava/lang/String;
      33: invokespecial #155                // Method org/apache/catalina/LifecycleException."<init>":(Ljava/lang/String;)V
      36: athrow
      37: aload_0
      38: getstatic     #180                // Field org/apache/catalina/LifecycleState.STARTING:Lorg/apache/catalina/LifecycleState;
      41: invokevirtual #181                // Method setState:(Lorg/apache/catalina/LifecycleState;)V
      44: aload_0
      45: getfield      #44                 // Field protocolHandler:Lorg/apache/coyote/ProtocolHandler;
      48: invokeinterface #182,  1          // InterfaceMethod org/apache/coyote/ProtocolHandler.start:()V
      53: goto          74
      56: astore_1
      57: new           #154                // class org/apache/catalina/LifecycleException
      60: dup
      61: getstatic     #40                 // Field sm:Lorg/apache/tomcat/util/res/StringManager;
      64: ldc           #183                // String coyoteConnector.protocolHandlerStartFailed
      66: invokevirtual #42                 // Method org/apache/tomcat/util/res/StringManager.getString:(Ljava/lang/String;)Ljava/lang/String;
      69: aload_1
      70: invokespecial #177                // Method org/apache/catalina/LifecycleException."<init>":(Ljava/lang/String;Ljava/lang/Throwable;)V
      73: athrow
      74: return
    Exception table:
       from    to  target type
          44    53    56   Class java/lang/Exception

  protected void stopInternal() throws org.apache.catalina.LifecycleException;
    Code:
       0: aload_0
       1: getstatic     #184                // Field org/apache/catalina/LifecycleState.STOPPING:Lorg/apache/catalina/LifecycleState;
       4: invokevirtual #181                // Method setState:(Lorg/apache/catalina/LifecycleState;)V
       7: aload_0
       8: getfield      #44                 // Field protocolHandler:Lorg/apache/coyote/ProtocolHandler;
      11: ifnull        23
      14: aload_0
      15: getfield      #44                 // Field protocolHandler:Lorg/apache/coyote/ProtocolHandler;
      18: invokeinterface #185,  1          // InterfaceMethod org/apache/coyote/ProtocolHandler.stop:()V
      23: goto          44
      26: astore_1
      27: new           #154                // class org/apache/catalina/LifecycleException
      30: dup
      31: getstatic     #40                 // Field sm:Lorg/apache/tomcat/util/res/StringManager;
      34: ldc           #186                // String coyoteConnector.protocolHandlerStopFailed
      36: invokevirtual #42                 // Method org/apache/tomcat/util/res/StringManager.getString:(Ljava/lang/String;)Ljava/lang/String;
      39: aload_1
      40: invokespecial #177                // Method org/apache/catalina/LifecycleException."<init>":(Ljava/lang/String;Ljava/lang/Throwable;)V
      43: athrow
      44: return
    Exception table:
       from    to  target type
           7    23    26   Class java/lang/Exception

  protected void destroyInternal() throws org.apache.catalina.LifecycleException;
    Code:
       0: aload_0
       1: getfield      #44                 // Field protocolHandler:Lorg/apache/coyote/ProtocolHandler;
       4: ifnull        16
       7: aload_0
       8: getfield      #44                 // Field protocolHandler:Lorg/apache/coyote/ProtocolHandler;
      11: invokeinterface #187,  1          // InterfaceMethod org/apache/coyote/ProtocolHandler.destroy:()V
      16: goto          37
      19: astore_1
      20: new           #154                // class org/apache/catalina/LifecycleException
      23: dup
      24: getstatic     #40                 // Field sm:Lorg/apache/tomcat/util/res/StringManager;
      27: ldc           #188                // String coyoteConnector.protocolHandlerDestroyFailed
      29: invokevirtual #42                 // Method org/apache/tomcat/util/res/StringManager.getString:(Ljava/lang/String;)Ljava/lang/String;
      32: aload_1
      33: invokespecial #177                // Method org/apache/catalina/LifecycleException."<init>":(Ljava/lang/String;Ljava/lang/Throwable;)V
      36: athrow
      37: aload_0
      38: invokevirtual #189                // Method getService:()Lorg/apache/catalina/Service;
      41: ifnull        54
      44: aload_0
      45: invokevirtual #189                // Method getService:()Lorg/apache/catalina/Service;
      48: aload_0
      49: invokeinterface #190,  2          // InterfaceMethod org/apache/catalina/Service.removeConnector:(Lorg/apache/catalina/connector/Connector;)V
      54: aload_0
      55: invokespecial #191                // Method org/apache/catalina/util/LifecycleMBeanBase.destroyInternal:()V
      58: return
    Exception table:
       from    to  target type
           0    16    19   Class java/lang/Exception

  public java.lang.String toString();
    Code:
       0: new           #132                // class java/lang/StringBuilder
       3: dup
       4: ldc           #192                // String Connector[
       6: invokespecial #134                // Method java/lang/StringBuilder."<init>":(Ljava/lang/String;)V
       9: astore_1
      10: aload_1
      11: aload_0
      12: invokevirtual #193                // Method getProtocol:()Ljava/lang/String;
      15: invokevirtual #135                // Method java/lang/StringBuilder.append:(Ljava/lang/String;)Ljava/lang/StringBuilder;
      18: pop
      19: aload_1
      20: bipush        45
      22: invokevirtual #194                // Method java/lang/StringBuilder.append:(C)Ljava/lang/StringBuilder;
      25: pop
      26: aload_0
      27: invokevirtual #137                // Method getPortWithOffset:()I
      30: istore_2
      31: iload_2
      32: ifle          44
      35: aload_1
      36: iload_2
      37: invokevirtual #138                // Method java/lang/StringBuilder.append:(I)Ljava/lang/StringBuilder;
      40: pop
      41: goto          62
      44: aload_1
      45: ldc           #139                // String auto-
      47: invokevirtual #135                // Method java/lang/StringBuilder.append:(Ljava/lang/String;)Ljava/lang/StringBuilder;
      50: pop
      51: aload_1
      52: aload_0
      53: ldc           #140                // String nameIndex
      55: invokevirtual #53                 // Method getProperty:(Ljava/lang/String;)Ljava/lang/Object;
      58: invokevirtual #141                // Method java/lang/StringBuilder.append:(Ljava/lang/Object;)Ljava/lang/StringBuilder;
      61: pop
      62: aload_1
      63: bipush        93
      65: invokevirtual #194                // Method java/lang/StringBuilder.append:(C)Ljava/lang/StringBuilder;
      68: pop
      69: aload_1
      70: invokevirtual #148                // Method java/lang/StringBuilder.toString:()Ljava/lang/String;
      73: areturn

  protected java.lang.String getDomainInternal();
    Code:
       0: aload_0
       1: invokevirtual #189                // Method getService:()Lorg/apache/catalina/Service;
       4: astore_1
       5: aload_1
       6: ifnonnull     11
       9: aconst_null
      10: areturn
      11: aload_0
      12: getfield      #4                  // Field service:Lorg/apache/catalina/Service;
      15: invokeinterface #195,  1          // InterfaceMethod org/apache/catalina/Service.getDomain:()Ljava/lang/String;
      20: areturn

  protected java.lang.String getObjectNameKeyProperties();
    Code:
       0: aload_0
       1: ldc           #196                // String Connector
       3: invokevirtual #197                // Method createObjectNameKeyProperties:(Ljava/lang/String;)Ljava/lang/String;
       6: areturn

  static {};
    Code:
       0: ldc           #117                // class org/apache/catalina/connector/Connector
       2: invokestatic  #198                // Method org/apache/juli/logging/LogFactory.getLog:(Ljava/lang/Class;)Lorg/apache/juli/logging/Log;
       5: putstatic     #39                 // Field log:Lorg/apache/juli/logging/Log;
       8: ldc           #199                // String org.apache.catalina.connector.RECYCLE_FACADES
      10: ldc           #200                // String false
      12: invokestatic  #201                // Method java/lang/System.getProperty:(Ljava/lang/String;Ljava/lang/String;)Ljava/lang/String;
      15: invokestatic  #202                // Method java/lang/Boolean.parseBoolean:(Ljava/lang/String;)Z
      18: putstatic     #13                 // Field RECYCLE_FACADES:Z
      21: ldc           #117                // class org/apache/catalina/connector/Connector
      23: invokestatic  #203                // Method org/apache/tomcat/util/res/StringManager.getManager:(Ljava/lang/Class;)Lorg/apache/tomcat/util/res/StringManager;
      26: putstatic     #40                 // Field sm:Lorg/apache/tomcat/util/res/StringManager;
      29: return
}
