Compiled from "RequestFacade.java"
public class org.apache.catalina.connector.RequestFacade implements javax.servlet.http.HttpServletRequest {
  protected org.apache.catalina.connector.Request request;

  protected static final org.apache.tomcat.util.res.StringManager sm;

  public org.apache.catalina.connector.RequestFacade(org.apache.catalina.connector.Request);
    Code:
       0: aload_0
       1: invokespecial #1                  // Method java/lang/Object."<init>":()V
       4: aload_0
       5: aconst_null
       6: putfield      #2                  // Field request:Lorg/apache/catalina/connector/Request;
       9: aload_0
      10: aload_1
      11: putfield      #2                  // Field request:Lorg/apache/catalina/connector/Request;
      14: return

  public void clear();
    Code:
       0: aload_0
       1: aconst_null
       2: putfield      #2                  // Field request:Lorg/apache/catalina/connector/Request;
       5: return

  protected java.lang.Object clone() throws java.lang.CloneNotSupportedException;
    Code:
       0: new           #3                  // class java/lang/CloneNotSupportedException
       3: dup
       4: invokespecial #4                  // Method java/lang/CloneNotSupportedException."<init>":()V
       7: athrow

  public java.lang.Object getAttribute(java.lang.String);
    Code:
       0: aload_0
       1: getfield      #2                  // Field request:Lorg/apache/catalina/connector/Request;
       4: ifnonnull     23
       7: new           #5                  // class java/lang/IllegalStateException
      10: dup
      11: getstatic     #6                  // Field sm:Lorg/apache/tomcat/util/res/StringManager;
      14: ldc           #7                  // String requestFacade.nullRequest
      16: invokevirtual #8                  // Method org/apache/tomcat/util/res/StringManager.getString:(Ljava/lang/String;)Ljava/lang/String;
      19: invokespecial #9                  // Method java/lang/IllegalStateException."<init>":(Ljava/lang/String;)V
      22: athrow
      23: aload_0
      24: getfield      #2                  // Field request:Lorg/apache/catalina/connector/Request;
      27: aload_1
      28: invokevirtual #10                 // Method org/apache/catalina/connector/Request.getAttribute:(Ljava/lang/String;)Ljava/lang/Object;
      31: areturn

  public java.util.Enumeration<java.lang.String> getAttributeNames();
    Code:
       0: aload_0
       1: getfield      #2                  // Field request:Lorg/apache/catalina/connector/Request;
       4: ifnonnull     23
       7: new           #5                  // class java/lang/IllegalStateException
      10: dup
      11: getstatic     #6                  // Field sm:Lorg/apache/tomcat/util/res/StringManager;
      14: ldc           #7                  // String requestFacade.nullRequest
      16: invokevirtual #8                  // Method org/apache/tomcat/util/res/StringManager.getString:(Ljava/lang/String;)Ljava/lang/String;
      19: invokespecial #9                  // Method java/lang/IllegalStateException."<init>":(Ljava/lang/String;)V
      22: athrow
      23: getstatic     #11                 // Field org/apache/catalina/Globals.IS_SECURITY_ENABLED:Z
      26: ifeq          45
      29: new           #12                 // class org/apache/catalina/connector/RequestFacade$GetAttributePrivilegedAction
      32: dup
      33: aload_0
      34: aconst_null
      35: invokespecial #13                 // Method org/apache/catalina/connector/RequestFacade$GetAttributePrivilegedAction."<init>":(Lorg/apache/catalina/connector/RequestFacade;Lorg/apache/catalina/connector/RequestFacade$1;)V
      38: invokestatic  #14                 // Method java/security/AccessController.doPrivileged:(Ljava/security/PrivilegedAction;)Ljava/lang/Object;
      41: checkcast     #15                 // class java/util/Enumeration
      44: areturn
      45: aload_0
      46: getfield      #2                  // Field request:Lorg/apache/catalina/connector/Request;
      49: invokevirtual #16                 // Method org/apache/catalina/connector/Request.getAttributeNames:()Ljava/util/Enumeration;
      52: areturn

  public java.lang.String getCharacterEncoding();
    Code:
       0: aload_0
       1: getfield      #2                  // Field request:Lorg/apache/catalina/connector/Request;
       4: ifnonnull     23
       7: new           #5                  // class java/lang/IllegalStateException
      10: dup
      11: getstatic     #6                  // Field sm:Lorg/apache/tomcat/util/res/StringManager;
      14: ldc           #7                  // String requestFacade.nullRequest
      16: invokevirtual #8                  // Method org/apache/tomcat/util/res/StringManager.getString:(Ljava/lang/String;)Ljava/lang/String;
      19: invokespecial #9                  // Method java/lang/IllegalStateException."<init>":(Ljava/lang/String;)V
      22: athrow
      23: getstatic     #11                 // Field org/apache/catalina/Globals.IS_SECURITY_ENABLED:Z
      26: ifeq          45
      29: new           #17                 // class org/apache/catalina/connector/RequestFacade$GetCharacterEncodingPrivilegedAction
      32: dup
      33: aload_0
      34: aconst_null
      35: invokespecial #18                 // Method org/apache/catalina/connector/RequestFacade$GetCharacterEncodingPrivilegedAction."<init>":(Lorg/apache/catalina/connector/RequestFacade;Lorg/apache/catalina/connector/RequestFacade$1;)V
      38: invokestatic  #14                 // Method java/security/AccessController.doPrivileged:(Ljava/security/PrivilegedAction;)Ljava/lang/Object;
      41: checkcast     #19                 // class java/lang/String
      44: areturn
      45: aload_0
      46: getfield      #2                  // Field request:Lorg/apache/catalina/connector/Request;
      49: invokevirtual #20                 // Method org/apache/catalina/connector/Request.getCharacterEncoding:()Ljava/lang/String;
      52: areturn

  public void setCharacterEncoding(java.lang.String) throws java.io.UnsupportedEncodingException;
    Code:
       0: aload_0
       1: getfield      #2                  // Field request:Lorg/apache/catalina/connector/Request;
       4: ifnonnull     23
       7: new           #5                  // class java/lang/IllegalStateException
      10: dup
      11: getstatic     #6                  // Field sm:Lorg/apache/tomcat/util/res/StringManager;
      14: ldc           #7                  // String requestFacade.nullRequest
      16: invokevirtual #8                  // Method org/apache/tomcat/util/res/StringManager.getString:(Ljava/lang/String;)Ljava/lang/String;
      19: invokespecial #9                  // Method java/lang/IllegalStateException."<init>":(Ljava/lang/String;)V
      22: athrow
      23: aload_0
      24: getfield      #2                  // Field request:Lorg/apache/catalina/connector/Request;
      27: aload_1
      28: invokevirtual #21                 // Method org/apache/catalina/connector/Request.setCharacterEncoding:(Ljava/lang/String;)V
      31: return

  public int getContentLength();
    Code:
       0: aload_0
       1: getfield      #2                  // Field request:Lorg/apache/catalina/connector/Request;
       4: ifnonnull     23
       7: new           #5                  // class java/lang/IllegalStateException
      10: dup
      11: getstatic     #6                  // Field sm:Lorg/apache/tomcat/util/res/StringManager;
      14: ldc           #7                  // String requestFacade.nullRequest
      16: invokevirtual #8                  // Method org/apache/tomcat/util/res/StringManager.getString:(Ljava/lang/String;)Ljava/lang/String;
      19: invokespecial #9                  // Method java/lang/IllegalStateException."<init>":(Ljava/lang/String;)V
      22: athrow
      23: aload_0
      24: getfield      #2                  // Field request:Lorg/apache/catalina/connector/Request;
      27: invokevirtual #22                 // Method org/apache/catalina/connector/Request.getContentLength:()I
      30: ireturn

  public java.lang.String getContentType();
    Code:
       0: aload_0
       1: getfield      #2                  // Field request:Lorg/apache/catalina/connector/Request;
       4: ifnonnull     23
       7: new           #5                  // class java/lang/IllegalStateException
      10: dup
      11: getstatic     #6                  // Field sm:Lorg/apache/tomcat/util/res/StringManager;
      14: ldc           #7                  // String requestFacade.nullRequest
      16: invokevirtual #8                  // Method org/apache/tomcat/util/res/StringManager.getString:(Ljava/lang/String;)Ljava/lang/String;
      19: invokespecial #9                  // Method java/lang/IllegalStateException."<init>":(Ljava/lang/String;)V
      22: athrow
      23: aload_0
      24: getfield      #2                  // Field request:Lorg/apache/catalina/connector/Request;
      27: invokevirtual #23                 // Method org/apache/catalina/connector/Request.getContentType:()Ljava/lang/String;
      30: areturn

  public javax.servlet.ServletInputStream getInputStream() throws java.io.IOException;
    Code:
       0: aload_0
       1: getfield      #2                  // Field request:Lorg/apache/catalina/connector/Request;
       4: ifnonnull     23
       7: new           #5                  // class java/lang/IllegalStateException
      10: dup
      11: getstatic     #6                  // Field sm:Lorg/apache/tomcat/util/res/StringManager;
      14: ldc           #7                  // String requestFacade.nullRequest
      16: invokevirtual #8                  // Method org/apache/tomcat/util/res/StringManager.getString:(Ljava/lang/String;)Ljava/lang/String;
      19: invokespecial #9                  // Method java/lang/IllegalStateException."<init>":(Ljava/lang/String;)V
      22: athrow
      23: aload_0
      24: getfield      #2                  // Field request:Lorg/apache/catalina/connector/Request;
      27: invokevirtual #24                 // Method org/apache/catalina/connector/Request.getInputStream:()Ljavax/servlet/ServletInputStream;
      30: areturn

  public java.lang.String getParameter(java.lang.String);
    Code:
       0: aload_0
       1: getfield      #2                  // Field request:Lorg/apache/catalina/connector/Request;
       4: ifnonnull     23
       7: new           #5                  // class java/lang/IllegalStateException
      10: dup
      11: getstatic     #6                  // Field sm:Lorg/apache/tomcat/util/res/StringManager;
      14: ldc           #7                  // String requestFacade.nullRequest
      16: invokevirtual #8                  // Method org/apache/tomcat/util/res/StringManager.getString:(Ljava/lang/String;)Ljava/lang/String;
      19: invokespecial #9                  // Method java/lang/IllegalStateException."<init>":(Ljava/lang/String;)V
      22: athrow
      23: getstatic     #11                 // Field org/apache/catalina/Globals.IS_SECURITY_ENABLED:Z
      26: ifeq          45
      29: new           #25                 // class org/apache/catalina/connector/RequestFacade$GetParameterPrivilegedAction
      32: dup
      33: aload_0
      34: aload_1
      35: invokespecial #26                 // Method org/apache/catalina/connector/RequestFacade$GetParameterPrivilegedAction."<init>":(Lorg/apache/catalina/connector/RequestFacade;Ljava/lang/String;)V
      38: invokestatic  #14                 // Method java/security/AccessController.doPrivileged:(Ljava/security/PrivilegedAction;)Ljava/lang/Object;
      41: checkcast     #19                 // class java/lang/String
      44: areturn
      45: aload_0
      46: getfield      #2                  // Field request:Lorg/apache/catalina/connector/Request;
      49: aload_1
      50: invokevirtual #27                 // Method org/apache/catalina/connector/Request.getParameter:(Ljava/lang/String;)Ljava/lang/String;
      53: areturn

  public java.util.Enumeration<java.lang.String> getParameterNames();
    Code:
       0: aload_0
       1: getfield      #2                  // Field request:Lorg/apache/catalina/connector/Request;
       4: ifnonnull     23
       7: new           #5                  // class java/lang/IllegalStateException
      10: dup
      11: getstatic     #6                  // Field sm:Lorg/apache/tomcat/util/res/StringManager;
      14: ldc           #7                  // String requestFacade.nullRequest
      16: invokevirtual #8                  // Method org/apache/tomcat/util/res/StringManager.getString:(Ljava/lang/String;)Ljava/lang/String;
      19: invokespecial #9                  // Method java/lang/IllegalStateException."<init>":(Ljava/lang/String;)V
      22: athrow
      23: getstatic     #11                 // Field org/apache/catalina/Globals.IS_SECURITY_ENABLED:Z
      26: ifeq          45
      29: new           #28                 // class org/apache/catalina/connector/RequestFacade$GetParameterNamesPrivilegedAction
      32: dup
      33: aload_0
      34: aconst_null
      35: invokespecial #29                 // Method org/apache/catalina/connector/RequestFacade$GetParameterNamesPrivilegedAction."<init>":(Lorg/apache/catalina/connector/RequestFacade;Lorg/apache/catalina/connector/RequestFacade$1;)V
      38: invokestatic  #14                 // Method java/security/AccessController.doPrivileged:(Ljava/security/PrivilegedAction;)Ljava/lang/Object;
      41: checkcast     #15                 // class java/util/Enumeration
      44: areturn
      45: aload_0
      46: getfield      #2                  // Field request:Lorg/apache/catalina/connector/Request;
      49: invokevirtual #30                 // Method org/apache/catalina/connector/Request.getParameterNames:()Ljava/util/Enumeration;
      52: areturn

  public java.lang.String[] getParameterValues(java.lang.String);
    Code:
       0: aload_0
       1: getfield      #2                  // Field request:Lorg/apache/catalina/connector/Request;
       4: ifnonnull     23
       7: new           #5                  // class java/lang/IllegalStateException
      10: dup
      11: getstatic     #6                  // Field sm:Lorg/apache/tomcat/util/res/StringManager;
      14: ldc           #7                  // String requestFacade.nullRequest
      16: invokevirtual #8                  // Method org/apache/tomcat/util/res/StringManager.getString:(Ljava/lang/String;)Ljava/lang/String;
      19: invokespecial #9                  // Method java/lang/IllegalStateException."<init>":(Ljava/lang/String;)V
      22: athrow
      23: aconst_null
      24: astore_2
      25: invokestatic  #31                 // Method org/apache/catalina/security/SecurityUtil.isPackageProtectionEnabled:()Z
      28: ifeq          62
      31: new           #32                 // class org/apache/catalina/connector/RequestFacade$GetParameterValuePrivilegedAction
      34: dup
      35: aload_0
      36: aload_1
      37: invokespecial #33                 // Method org/apache/catalina/connector/RequestFacade$GetParameterValuePrivilegedAction."<init>":(Lorg/apache/catalina/connector/RequestFacade;Ljava/lang/String;)V
      40: invokestatic  #14                 // Method java/security/AccessController.doPrivileged:(Ljava/security/PrivilegedAction;)Ljava/lang/Object;
      43: checkcast     #34                 // class "[Ljava/lang/String;"
      46: astore_2
      47: aload_2
      48: ifnull        71
      51: aload_2
      52: invokevirtual #35                 // Method "[Ljava/lang/String;".clone:()Ljava/lang/Object;
      55: checkcast     #34                 // class "[Ljava/lang/String;"
      58: astore_2
      59: goto          71
      62: aload_0
      63: getfield      #2                  // Field request:Lorg/apache/catalina/connector/Request;
      66: aload_1
      67: invokevirtual #36                 // Method org/apache/catalina/connector/Request.getParameterValues:(Ljava/lang/String;)[Ljava/lang/String;
      70: astore_2
      71: aload_2
      72: areturn

  public java.util.Map<java.lang.String, java.lang.String[]> getParameterMap();
    Code:
       0: aload_0
       1: getfield      #2                  // Field request:Lorg/apache/catalina/connector/Request;
       4: ifnonnull     23
       7: new           #5                  // class java/lang/IllegalStateException
      10: dup
      11: getstatic     #6                  // Field sm:Lorg/apache/tomcat/util/res/StringManager;
      14: ldc           #7                  // String requestFacade.nullRequest
      16: invokevirtual #8                  // Method org/apache/tomcat/util/res/StringManager.getString:(Ljava/lang/String;)Ljava/lang/String;
      19: invokespecial #9                  // Method java/lang/IllegalStateException."<init>":(Ljava/lang/String;)V
      22: athrow
      23: getstatic     #11                 // Field org/apache/catalina/Globals.IS_SECURITY_ENABLED:Z
      26: ifeq          45
      29: new           #37                 // class org/apache/catalina/connector/RequestFacade$GetParameterMapPrivilegedAction
      32: dup
      33: aload_0
      34: aconst_null
      35: invokespecial #38                 // Method org/apache/catalina/connector/RequestFacade$GetParameterMapPrivilegedAction."<init>":(Lorg/apache/catalina/connector/RequestFacade;Lorg/apache/catalina/connector/RequestFacade$1;)V
      38: invokestatic  #14                 // Method java/security/AccessController.doPrivileged:(Ljava/security/PrivilegedAction;)Ljava/lang/Object;
      41: checkcast     #39                 // class java/util/Map
      44: areturn
      45: aload_0
      46: getfield      #2                  // Field request:Lorg/apache/catalina/connector/Request;
      49: invokevirtual #40                 // Method org/apache/catalina/connector/Request.getParameterMap:()Ljava/util/Map;
      52: areturn

  public java.lang.String getProtocol();
    Code:
       0: aload_0
       1: getfield      #2                  // Field request:Lorg/apache/catalina/connector/Request;
       4: ifnonnull     23
       7: new           #5                  // class java/lang/IllegalStateException
      10: dup
      11: getstatic     #6                  // Field sm:Lorg/apache/tomcat/util/res/StringManager;
      14: ldc           #7                  // String requestFacade.nullRequest
      16: invokevirtual #8                  // Method org/apache/tomcat/util/res/StringManager.getString:(Ljava/lang/String;)Ljava/lang/String;
      19: invokespecial #9                  // Method java/lang/IllegalStateException."<init>":(Ljava/lang/String;)V
      22: athrow
      23: aload_0
      24: getfield      #2                  // Field request:Lorg/apache/catalina/connector/Request;
      27: invokevirtual #41                 // Method org/apache/catalina/connector/Request.getProtocol:()Ljava/lang/String;
      30: areturn

  public java.lang.String getScheme();
    Code:
       0: aload_0
       1: getfield      #2                  // Field request:Lorg/apache/catalina/connector/Request;
       4: ifnonnull     23
       7: new           #5                  // class java/lang/IllegalStateException
      10: dup
      11: getstatic     #6                  // Field sm:Lorg/apache/tomcat/util/res/StringManager;
      14: ldc           #7                  // String requestFacade.nullRequest
      16: invokevirtual #8                  // Method org/apache/tomcat/util/res/StringManager.getString:(Ljava/lang/String;)Ljava/lang/String;
      19: invokespecial #9                  // Method java/lang/IllegalStateException."<init>":(Ljava/lang/String;)V
      22: athrow
      23: aload_0
      24: getfield      #2                  // Field request:Lorg/apache/catalina/connector/Request;
      27: invokevirtual #42                 // Method org/apache/catalina/connector/Request.getScheme:()Ljava/lang/String;
      30: areturn

  public java.lang.String getServerName();
    Code:
       0: aload_0
       1: getfield      #2                  // Field request:Lorg/apache/catalina/connector/Request;
       4: ifnonnull     23
       7: new           #5                  // class java/lang/IllegalStateException
      10: dup
      11: getstatic     #6                  // Field sm:Lorg/apache/tomcat/util/res/StringManager;
      14: ldc           #7                  // String requestFacade.nullRequest
      16: invokevirtual #8                  // Method org/apache/tomcat/util/res/StringManager.getString:(Ljava/lang/String;)Ljava/lang/String;
      19: invokespecial #9                  // Method java/lang/IllegalStateException."<init>":(Ljava/lang/String;)V
      22: athrow
      23: aload_0
      24: getfield      #2                  // Field request:Lorg/apache/catalina/connector/Request;
      27: invokevirtual #43                 // Method org/apache/catalina/connector/Request.getServerName:()Ljava/lang/String;
      30: areturn

  public int getServerPort();
    Code:
       0: aload_0
       1: getfield      #2                  // Field request:Lorg/apache/catalina/connector/Request;
       4: ifnonnull     23
       7: new           #5                  // class java/lang/IllegalStateException
      10: dup
      11: getstatic     #6                  // Field sm:Lorg/apache/tomcat/util/res/StringManager;
      14: ldc           #7                  // String requestFacade.nullRequest
      16: invokevirtual #8                  // Method org/apache/tomcat/util/res/StringManager.getString:(Ljava/lang/String;)Ljava/lang/String;
      19: invokespecial #9                  // Method java/lang/IllegalStateException."<init>":(Ljava/lang/String;)V
      22: athrow
      23: aload_0
      24: getfield      #2                  // Field request:Lorg/apache/catalina/connector/Request;
      27: invokevirtual #44                 // Method org/apache/catalina/connector/Request.getServerPort:()I
      30: ireturn

  public java.io.BufferedReader getReader() throws java.io.IOException;
    Code:
       0: aload_0
       1: getfield      #2                  // Field request:Lorg/apache/catalina/connector/Request;
       4: ifnonnull     23
       7: new           #5                  // class java/lang/IllegalStateException
      10: dup
      11: getstatic     #6                  // Field sm:Lorg/apache/tomcat/util/res/StringManager;
      14: ldc           #7                  // String requestFacade.nullRequest
      16: invokevirtual #8                  // Method org/apache/tomcat/util/res/StringManager.getString:(Ljava/lang/String;)Ljava/lang/String;
      19: invokespecial #9                  // Method java/lang/IllegalStateException."<init>":(Ljava/lang/String;)V
      22: athrow
      23: aload_0
      24: getfield      #2                  // Field request:Lorg/apache/catalina/connector/Request;
      27: invokevirtual #45                 // Method org/apache/catalina/connector/Request.getReader:()Ljava/io/BufferedReader;
      30: areturn

  public java.lang.String getRemoteAddr();
    Code:
       0: aload_0
       1: getfield      #2                  // Field request:Lorg/apache/catalina/connector/Request;
       4: ifnonnull     23
       7: new           #5                  // class java/lang/IllegalStateException
      10: dup
      11: getstatic     #6                  // Field sm:Lorg/apache/tomcat/util/res/StringManager;
      14: ldc           #7                  // String requestFacade.nullRequest
      16: invokevirtual #8                  // Method org/apache/tomcat/util/res/StringManager.getString:(Ljava/lang/String;)Ljava/lang/String;
      19: invokespecial #9                  // Method java/lang/IllegalStateException."<init>":(Ljava/lang/String;)V
      22: athrow
      23: aload_0
      24: getfield      #2                  // Field request:Lorg/apache/catalina/connector/Request;
      27: invokevirtual #46                 // Method org/apache/catalina/connector/Request.getRemoteAddr:()Ljava/lang/String;
      30: areturn

  public java.lang.String getRemoteHost();
    Code:
       0: aload_0
       1: getfield      #2                  // Field request:Lorg/apache/catalina/connector/Request;
       4: ifnonnull     23
       7: new           #5                  // class java/lang/IllegalStateException
      10: dup
      11: getstatic     #6                  // Field sm:Lorg/apache/tomcat/util/res/StringManager;
      14: ldc           #7                  // String requestFacade.nullRequest
      16: invokevirtual #8                  // Method org/apache/tomcat/util/res/StringManager.getString:(Ljava/lang/String;)Ljava/lang/String;
      19: invokespecial #9                  // Method java/lang/IllegalStateException."<init>":(Ljava/lang/String;)V
      22: athrow
      23: aload_0
      24: getfield      #2                  // Field request:Lorg/apache/catalina/connector/Request;
      27: invokevirtual #47                 // Method org/apache/catalina/connector/Request.getRemoteHost:()Ljava/lang/String;
      30: areturn

  public void setAttribute(java.lang.String, java.lang.Object);
    Code:
       0: aload_0
       1: getfield      #2                  // Field request:Lorg/apache/catalina/connector/Request;
       4: ifnonnull     23
       7: new           #5                  // class java/lang/IllegalStateException
      10: dup
      11: getstatic     #6                  // Field sm:Lorg/apache/tomcat/util/res/StringManager;
      14: ldc           #7                  // String requestFacade.nullRequest
      16: invokevirtual #8                  // Method org/apache/tomcat/util/res/StringManager.getString:(Ljava/lang/String;)Ljava/lang/String;
      19: invokespecial #9                  // Method java/lang/IllegalStateException."<init>":(Ljava/lang/String;)V
      22: athrow
      23: aload_0
      24: getfield      #2                  // Field request:Lorg/apache/catalina/connector/Request;
      27: aload_1
      28: aload_2
      29: invokevirtual #48                 // Method org/apache/catalina/connector/Request.setAttribute:(Ljava/lang/String;Ljava/lang/Object;)V
      32: return

  public void removeAttribute(java.lang.String);
    Code:
       0: aload_0
       1: getfield      #2                  // Field request:Lorg/apache/catalina/connector/Request;
       4: ifnonnull     23
       7: new           #5                  // class java/lang/IllegalStateException
      10: dup
      11: getstatic     #6                  // Field sm:Lorg/apache/tomcat/util/res/StringManager;
      14: ldc           #7                  // String requestFacade.nullRequest
      16: invokevirtual #8                  // Method org/apache/tomcat/util/res/StringManager.getString:(Ljava/lang/String;)Ljava/lang/String;
      19: invokespecial #9                  // Method java/lang/IllegalStateException."<init>":(Ljava/lang/String;)V
      22: athrow
      23: aload_0
      24: getfield      #2                  // Field request:Lorg/apache/catalina/connector/Request;
      27: aload_1
      28: invokevirtual #49                 // Method org/apache/catalina/connector/Request.removeAttribute:(Ljava/lang/String;)V
      31: return

  public java.util.Locale getLocale();
    Code:
       0: aload_0
       1: getfield      #2                  // Field request:Lorg/apache/catalina/connector/Request;
       4: ifnonnull     23
       7: new           #5                  // class java/lang/IllegalStateException
      10: dup
      11: getstatic     #6                  // Field sm:Lorg/apache/tomcat/util/res/StringManager;
      14: ldc           #7                  // String requestFacade.nullRequest
      16: invokevirtual #8                  // Method org/apache/tomcat/util/res/StringManager.getString:(Ljava/lang/String;)Ljava/lang/String;
      19: invokespecial #9                  // Method java/lang/IllegalStateException."<init>":(Ljava/lang/String;)V
      22: athrow
      23: getstatic     #11                 // Field org/apache/catalina/Globals.IS_SECURITY_ENABLED:Z
      26: ifeq          45
      29: new           #50                 // class org/apache/catalina/connector/RequestFacade$GetLocalePrivilegedAction
      32: dup
      33: aload_0
      34: aconst_null
      35: invokespecial #51                 // Method org/apache/catalina/connector/RequestFacade$GetLocalePrivilegedAction."<init>":(Lorg/apache/catalina/connector/RequestFacade;Lorg/apache/catalina/connector/RequestFacade$1;)V
      38: invokestatic  #14                 // Method java/security/AccessController.doPrivileged:(Ljava/security/PrivilegedAction;)Ljava/lang/Object;
      41: checkcast     #52                 // class java/util/Locale
      44: areturn
      45: aload_0
      46: getfield      #2                  // Field request:Lorg/apache/catalina/connector/Request;
      49: invokevirtual #53                 // Method org/apache/catalina/connector/Request.getLocale:()Ljava/util/Locale;
      52: areturn

  public java.util.Enumeration<java.util.Locale> getLocales();
    Code:
       0: aload_0
       1: getfield      #2                  // Field request:Lorg/apache/catalina/connector/Request;
       4: ifnonnull     23
       7: new           #5                  // class java/lang/IllegalStateException
      10: dup
      11: getstatic     #6                  // Field sm:Lorg/apache/tomcat/util/res/StringManager;
      14: ldc           #7                  // String requestFacade.nullRequest
      16: invokevirtual #8                  // Method org/apache/tomcat/util/res/StringManager.getString:(Ljava/lang/String;)Ljava/lang/String;
      19: invokespecial #9                  // Method java/lang/IllegalStateException."<init>":(Ljava/lang/String;)V
      22: athrow
      23: getstatic     #11                 // Field org/apache/catalina/Globals.IS_SECURITY_ENABLED:Z
      26: ifeq          45
      29: new           #54                 // class org/apache/catalina/connector/RequestFacade$GetLocalesPrivilegedAction
      32: dup
      33: aload_0
      34: aconst_null
      35: invokespecial #55                 // Method org/apache/catalina/connector/RequestFacade$GetLocalesPrivilegedAction."<init>":(Lorg/apache/catalina/connector/RequestFacade;Lorg/apache/catalina/connector/RequestFacade$1;)V
      38: invokestatic  #14                 // Method java/security/AccessController.doPrivileged:(Ljava/security/PrivilegedAction;)Ljava/lang/Object;
      41: checkcast     #15                 // class java/util/Enumeration
      44: areturn
      45: aload_0
      46: getfield      #2                  // Field request:Lorg/apache/catalina/connector/Request;
      49: invokevirtual #56                 // Method org/apache/catalina/connector/Request.getLocales:()Ljava/util/Enumeration;
      52: areturn

  public boolean isSecure();
    Code:
       0: aload_0
       1: getfield      #2                  // Field request:Lorg/apache/catalina/connector/Request;
       4: ifnonnull     23
       7: new           #5                  // class java/lang/IllegalStateException
      10: dup
      11: getstatic     #6                  // Field sm:Lorg/apache/tomcat/util/res/StringManager;
      14: ldc           #7                  // String requestFacade.nullRequest
      16: invokevirtual #8                  // Method org/apache/tomcat/util/res/StringManager.getString:(Ljava/lang/String;)Ljava/lang/String;
      19: invokespecial #9                  // Method java/lang/IllegalStateException."<init>":(Ljava/lang/String;)V
      22: athrow
      23: aload_0
      24: getfield      #2                  // Field request:Lorg/apache/catalina/connector/Request;
      27: invokevirtual #57                 // Method org/apache/catalina/connector/Request.isSecure:()Z
      30: ireturn

  public javax.servlet.RequestDispatcher getRequestDispatcher(java.lang.String);
    Code:
       0: aload_0
       1: getfield      #2                  // Field request:Lorg/apache/catalina/connector/Request;
       4: ifnonnull     23
       7: new           #5                  // class java/lang/IllegalStateException
      10: dup
      11: getstatic     #6                  // Field sm:Lorg/apache/tomcat/util/res/StringManager;
      14: ldc           #7                  // String requestFacade.nullRequest
      16: invokevirtual #8                  // Method org/apache/tomcat/util/res/StringManager.getString:(Ljava/lang/String;)Ljava/lang/String;
      19: invokespecial #9                  // Method java/lang/IllegalStateException."<init>":(Ljava/lang/String;)V
      22: athrow
      23: getstatic     #11                 // Field org/apache/catalina/Globals.IS_SECURITY_ENABLED:Z
      26: ifeq          45
      29: new           #58                 // class org/apache/catalina/connector/RequestFacade$GetRequestDispatcherPrivilegedAction
      32: dup
      33: aload_0
      34: aload_1
      35: invokespecial #59                 // Method org/apache/catalina/connector/RequestFacade$GetRequestDispatcherPrivilegedAction."<init>":(Lorg/apache/catalina/connector/RequestFacade;Ljava/lang/String;)V
      38: invokestatic  #14                 // Method java/security/AccessController.doPrivileged:(Ljava/security/PrivilegedAction;)Ljava/lang/Object;
      41: checkcast     #60                 // class javax/servlet/RequestDispatcher
      44: areturn
      45: aload_0
      46: getfield      #2                  // Field request:Lorg/apache/catalina/connector/Request;
      49: aload_1
      50: invokevirtual #61                 // Method org/apache/catalina/connector/Request.getRequestDispatcher:(Ljava/lang/String;)Ljavax/servlet/RequestDispatcher;
      53: areturn

  public java.lang.String getRealPath(java.lang.String);
    Code:
       0: aload_0
       1: getfield      #2                  // Field request:Lorg/apache/catalina/connector/Request;
       4: ifnonnull     23
       7: new           #5                  // class java/lang/IllegalStateException
      10: dup
      11: getstatic     #6                  // Field sm:Lorg/apache/tomcat/util/res/StringManager;
      14: ldc           #7                  // String requestFacade.nullRequest
      16: invokevirtual #8                  // Method org/apache/tomcat/util/res/StringManager.getString:(Ljava/lang/String;)Ljava/lang/String;
      19: invokespecial #9                  // Method java/lang/IllegalStateException."<init>":(Ljava/lang/String;)V
      22: athrow
      23: aload_0
      24: getfield      #2                  // Field request:Lorg/apache/catalina/connector/Request;
      27: aload_1
      28: invokevirtual #62                 // Method org/apache/catalina/connector/Request.getRealPath:(Ljava/lang/String;)Ljava/lang/String;
      31: areturn

  public java.lang.String getAuthType();
    Code:
       0: aload_0
       1: getfield      #2                  // Field request:Lorg/apache/catalina/connector/Request;
       4: ifnonnull     23
       7: new           #5                  // class java/lang/IllegalStateException
      10: dup
      11: getstatic     #6                  // Field sm:Lorg/apache/tomcat/util/res/StringManager;
      14: ldc           #7                  // String requestFacade.nullRequest
      16: invokevirtual #8                  // Method org/apache/tomcat/util/res/StringManager.getString:(Ljava/lang/String;)Ljava/lang/String;
      19: invokespecial #9                  // Method java/lang/IllegalStateException."<init>":(Ljava/lang/String;)V
      22: athrow
      23: aload_0
      24: getfield      #2                  // Field request:Lorg/apache/catalina/connector/Request;
      27: invokevirtual #63                 // Method org/apache/catalina/connector/Request.getAuthType:()Ljava/lang/String;
      30: areturn

  public javax.servlet.http.Cookie[] getCookies();
    Code:
       0: aload_0
       1: getfield      #2                  // Field request:Lorg/apache/catalina/connector/Request;
       4: ifnonnull     23
       7: new           #5                  // class java/lang/IllegalStateException
      10: dup
      11: getstatic     #6                  // Field sm:Lorg/apache/tomcat/util/res/StringManager;
      14: ldc           #7                  // String requestFacade.nullRequest
      16: invokevirtual #8                  // Method org/apache/tomcat/util/res/StringManager.getString:(Ljava/lang/String;)Ljava/lang/String;
      19: invokespecial #9                  // Method java/lang/IllegalStateException."<init>":(Ljava/lang/String;)V
      22: athrow
      23: aconst_null
      24: astore_1
      25: invokestatic  #31                 // Method org/apache/catalina/security/SecurityUtil.isPackageProtectionEnabled:()Z
      28: ifeq          62
      31: new           #64                 // class org/apache/catalina/connector/RequestFacade$GetCookiesPrivilegedAction
      34: dup
      35: aload_0
      36: aconst_null
      37: invokespecial #65                 // Method org/apache/catalina/connector/RequestFacade$GetCookiesPrivilegedAction."<init>":(Lorg/apache/catalina/connector/RequestFacade;Lorg/apache/catalina/connector/RequestFacade$1;)V
      40: invokestatic  #14                 // Method java/security/AccessController.doPrivileged:(Ljava/security/PrivilegedAction;)Ljava/lang/Object;
      43: checkcast     #66                 // class "[Ljavax/servlet/http/Cookie;"
      46: astore_1
      47: aload_1
      48: ifnull        70
      51: aload_1
      52: invokevirtual #67                 // Method "[Ljavax/servlet/http/Cookie;".clone:()Ljava/lang/Object;
      55: checkcast     #66                 // class "[Ljavax/servlet/http/Cookie;"
      58: astore_1
      59: goto          70
      62: aload_0
      63: getfield      #2                  // Field request:Lorg/apache/catalina/connector/Request;
      66: invokevirtual #68                 // Method org/apache/catalina/connector/Request.getCookies:()[Ljavax/servlet/http/Cookie;
      69: astore_1
      70: aload_1
      71: areturn

  public long getDateHeader(java.lang.String);
    Code:
       0: aload_0
       1: getfield      #2                  // Field request:Lorg/apache/catalina/connector/Request;
       4: ifnonnull     23
       7: new           #5                  // class java/lang/IllegalStateException
      10: dup
      11: getstatic     #6                  // Field sm:Lorg/apache/tomcat/util/res/StringManager;
      14: ldc           #7                  // String requestFacade.nullRequest
      16: invokevirtual #8                  // Method org/apache/tomcat/util/res/StringManager.getString:(Ljava/lang/String;)Ljava/lang/String;
      19: invokespecial #9                  // Method java/lang/IllegalStateException."<init>":(Ljava/lang/String;)V
      22: athrow
      23: aload_0
      24: getfield      #2                  // Field request:Lorg/apache/catalina/connector/Request;
      27: aload_1
      28: invokevirtual #69                 // Method org/apache/catalina/connector/Request.getDateHeader:(Ljava/lang/String;)J
      31: lreturn

  public java.lang.String getHeader(java.lang.String);
    Code:
       0: aload_0
       1: getfield      #2                  // Field request:Lorg/apache/catalina/connector/Request;
       4: ifnonnull     23
       7: new           #5                  // class java/lang/IllegalStateException
      10: dup
      11: getstatic     #6                  // Field sm:Lorg/apache/tomcat/util/res/StringManager;
      14: ldc           #7                  // String requestFacade.nullRequest
      16: invokevirtual #8                  // Method org/apache/tomcat/util/res/StringManager.getString:(Ljava/lang/String;)Ljava/lang/String;
      19: invokespecial #9                  // Method java/lang/IllegalStateException."<init>":(Ljava/lang/String;)V
      22: athrow
      23: aload_0
      24: getfield      #2                  // Field request:Lorg/apache/catalina/connector/Request;
      27: aload_1
      28: invokevirtual #70                 // Method org/apache/catalina/connector/Request.getHeader:(Ljava/lang/String;)Ljava/lang/String;
      31: areturn

  public java.util.Enumeration<java.lang.String> getHeaders(java.lang.String);
    Code:
       0: aload_0
       1: getfield      #2                  // Field request:Lorg/apache/catalina/connector/Request;
       4: ifnonnull     23
       7: new           #5                  // class java/lang/IllegalStateException
      10: dup
      11: getstatic     #6                  // Field sm:Lorg/apache/tomcat/util/res/StringManager;
      14: ldc           #7                  // String requestFacade.nullRequest
      16: invokevirtual #8                  // Method org/apache/tomcat/util/res/StringManager.getString:(Ljava/lang/String;)Ljava/lang/String;
      19: invokespecial #9                  // Method java/lang/IllegalStateException."<init>":(Ljava/lang/String;)V
      22: athrow
      23: getstatic     #11                 // Field org/apache/catalina/Globals.IS_SECURITY_ENABLED:Z
      26: ifeq          45
      29: new           #71                 // class org/apache/catalina/connector/RequestFacade$GetHeadersPrivilegedAction
      32: dup
      33: aload_0
      34: aload_1
      35: invokespecial #72                 // Method org/apache/catalina/connector/RequestFacade$GetHeadersPrivilegedAction."<init>":(Lorg/apache/catalina/connector/RequestFacade;Ljava/lang/String;)V
      38: invokestatic  #14                 // Method java/security/AccessController.doPrivileged:(Ljava/security/PrivilegedAction;)Ljava/lang/Object;
      41: checkcast     #15                 // class java/util/Enumeration
      44: areturn
      45: aload_0
      46: getfield      #2                  // Field request:Lorg/apache/catalina/connector/Request;
      49: aload_1
      50: invokevirtual #73                 // Method org/apache/catalina/connector/Request.getHeaders:(Ljava/lang/String;)Ljava/util/Enumeration;
      53: areturn

  public java.util.Enumeration<java.lang.String> getHeaderNames();
    Code:
       0: aload_0
       1: getfield      #2                  // Field request:Lorg/apache/catalina/connector/Request;
       4: ifnonnull     23
       7: new           #5                  // class java/lang/IllegalStateException
      10: dup
      11: getstatic     #6                  // Field sm:Lorg/apache/tomcat/util/res/StringManager;
      14: ldc           #7                  // String requestFacade.nullRequest
      16: invokevirtual #8                  // Method org/apache/tomcat/util/res/StringManager.getString:(Ljava/lang/String;)Ljava/lang/String;
      19: invokespecial #9                  // Method java/lang/IllegalStateException."<init>":(Ljava/lang/String;)V
      22: athrow
      23: getstatic     #11                 // Field org/apache/catalina/Globals.IS_SECURITY_ENABLED:Z
      26: ifeq          45
      29: new           #74                 // class org/apache/catalina/connector/RequestFacade$GetHeaderNamesPrivilegedAction
      32: dup
      33: aload_0
      34: aconst_null
      35: invokespecial #75                 // Method org/apache/catalina/connector/RequestFacade$GetHeaderNamesPrivilegedAction."<init>":(Lorg/apache/catalina/connector/RequestFacade;Lorg/apache/catalina/connector/RequestFacade$1;)V
      38: invokestatic  #14                 // Method java/security/AccessController.doPrivileged:(Ljava/security/PrivilegedAction;)Ljava/lang/Object;
      41: checkcast     #15                 // class java/util/Enumeration
      44: areturn
      45: aload_0
      46: getfield      #2                  // Field request:Lorg/apache/catalina/connector/Request;
      49: invokevirtual #76                 // Method org/apache/catalina/connector/Request.getHeaderNames:()Ljava/util/Enumeration;
      52: areturn

  public int getIntHeader(java.lang.String);
    Code:
       0: aload_0
       1: getfield      #2                  // Field request:Lorg/apache/catalina/connector/Request;
       4: ifnonnull     23
       7: new           #5                  // class java/lang/IllegalStateException
      10: dup
      11: getstatic     #6                  // Field sm:Lorg/apache/tomcat/util/res/StringManager;
      14: ldc           #7                  // String requestFacade.nullRequest
      16: invokevirtual #8                  // Method org/apache/tomcat/util/res/StringManager.getString:(Ljava/lang/String;)Ljava/lang/String;
      19: invokespecial #9                  // Method java/lang/IllegalStateException."<init>":(Ljava/lang/String;)V
      22: athrow
      23: aload_0
      24: getfield      #2                  // Field request:Lorg/apache/catalina/connector/Request;
      27: aload_1
      28: invokevirtual #77                 // Method org/apache/catalina/connector/Request.getIntHeader:(Ljava/lang/String;)I
      31: ireturn

  public javax.servlet.http.HttpServletMapping getHttpServletMapping();
    Code:
       0: aload_0
       1: getfield      #2                  // Field request:Lorg/apache/catalina/connector/Request;
       4: ifnonnull     23
       7: new           #5                  // class java/lang/IllegalStateException
      10: dup
      11: getstatic     #6                  // Field sm:Lorg/apache/tomcat/util/res/StringManager;
      14: ldc           #7                  // String requestFacade.nullRequest
      16: invokevirtual #8                  // Method org/apache/tomcat/util/res/StringManager.getString:(Ljava/lang/String;)Ljava/lang/String;
      19: invokespecial #9                  // Method java/lang/IllegalStateException."<init>":(Ljava/lang/String;)V
      22: athrow
      23: aload_0
      24: getfield      #2                  // Field request:Lorg/apache/catalina/connector/Request;
      27: invokevirtual #78                 // Method org/apache/catalina/connector/Request.getHttpServletMapping:()Ljavax/servlet/http/HttpServletMapping;
      30: areturn

  public java.lang.String getMethod();
    Code:
       0: aload_0
       1: getfield      #2                  // Field request:Lorg/apache/catalina/connector/Request;
       4: ifnonnull     23
       7: new           #5                  // class java/lang/IllegalStateException
      10: dup
      11: getstatic     #6                  // Field sm:Lorg/apache/tomcat/util/res/StringManager;
      14: ldc           #7                  // String requestFacade.nullRequest
      16: invokevirtual #8                  // Method org/apache/tomcat/util/res/StringManager.getString:(Ljava/lang/String;)Ljava/lang/String;
      19: invokespecial #9                  // Method java/lang/IllegalStateException."<init>":(Ljava/lang/String;)V
      22: athrow
      23: aload_0
      24: getfield      #2                  // Field request:Lorg/apache/catalina/connector/Request;
      27: invokevirtual #79                 // Method org/apache/catalina/connector/Request.getMethod:()Ljava/lang/String;
      30: areturn

  public java.lang.String getPathInfo();
    Code:
       0: aload_0
       1: getfield      #2                  // Field request:Lorg/apache/catalina/connector/Request;
       4: ifnonnull     23
       7: new           #5                  // class java/lang/IllegalStateException
      10: dup
      11: getstatic     #6                  // Field sm:Lorg/apache/tomcat/util/res/StringManager;
      14: ldc           #7                  // String requestFacade.nullRequest
      16: invokevirtual #8                  // Method org/apache/tomcat/util/res/StringManager.getString:(Ljava/lang/String;)Ljava/lang/String;
      19: invokespecial #9                  // Method java/lang/IllegalStateException."<init>":(Ljava/lang/String;)V
      22: athrow
      23: aload_0
      24: getfield      #2                  // Field request:Lorg/apache/catalina/connector/Request;
      27: invokevirtual #80                 // Method org/apache/catalina/connector/Request.getPathInfo:()Ljava/lang/String;
      30: areturn

  public java.lang.String getPathTranslated();
    Code:
       0: aload_0
       1: getfield      #2                  // Field request:Lorg/apache/catalina/connector/Request;
       4: ifnonnull     23
       7: new           #5                  // class java/lang/IllegalStateException
      10: dup
      11: getstatic     #6                  // Field sm:Lorg/apache/tomcat/util/res/StringManager;
      14: ldc           #7                  // String requestFacade.nullRequest
      16: invokevirtual #8                  // Method org/apache/tomcat/util/res/StringManager.getString:(Ljava/lang/String;)Ljava/lang/String;
      19: invokespecial #9                  // Method java/lang/IllegalStateException."<init>":(Ljava/lang/String;)V
      22: athrow
      23: aload_0
      24: getfield      #2                  // Field request:Lorg/apache/catalina/connector/Request;
      27: invokevirtual #81                 // Method org/apache/catalina/connector/Request.getPathTranslated:()Ljava/lang/String;
      30: areturn

  public java.lang.String getContextPath();
    Code:
       0: aload_0
       1: getfield      #2                  // Field request:Lorg/apache/catalina/connector/Request;
       4: ifnonnull     23
       7: new           #5                  // class java/lang/IllegalStateException
      10: dup
      11: getstatic     #6                  // Field sm:Lorg/apache/tomcat/util/res/StringManager;
      14: ldc           #7                  // String requestFacade.nullRequest
      16: invokevirtual #8                  // Method org/apache/tomcat/util/res/StringManager.getString:(Ljava/lang/String;)Ljava/lang/String;
      19: invokespecial #9                  // Method java/lang/IllegalStateException."<init>":(Ljava/lang/String;)V
      22: athrow
      23: aload_0
      24: getfield      #2                  // Field request:Lorg/apache/catalina/connector/Request;
      27: invokevirtual #82                 // Method org/apache/catalina/connector/Request.getContextPath:()Ljava/lang/String;
      30: areturn

  public java.lang.String getQueryString();
    Code:
       0: aload_0
       1: getfield      #2                  // Field request:Lorg/apache/catalina/connector/Request;
       4: ifnonnull     23
       7: new           #5                  // class java/lang/IllegalStateException
      10: dup
      11: getstatic     #6                  // Field sm:Lorg/apache/tomcat/util/res/StringManager;
      14: ldc           #7                  // String requestFacade.nullRequest
      16: invokevirtual #8                  // Method org/apache/tomcat/util/res/StringManager.getString:(Ljava/lang/String;)Ljava/lang/String;
      19: invokespecial #9                  // Method java/lang/IllegalStateException."<init>":(Ljava/lang/String;)V
      22: athrow
      23: aload_0
      24: getfield      #2                  // Field request:Lorg/apache/catalina/connector/Request;
      27: invokevirtual #83                 // Method org/apache/catalina/connector/Request.getQueryString:()Ljava/lang/String;
      30: areturn

  public java.lang.String getRemoteUser();
    Code:
       0: aload_0
       1: getfield      #2                  // Field request:Lorg/apache/catalina/connector/Request;
       4: ifnonnull     23
       7: new           #5                  // class java/lang/IllegalStateException
      10: dup
      11: getstatic     #6                  // Field sm:Lorg/apache/tomcat/util/res/StringManager;
      14: ldc           #7                  // String requestFacade.nullRequest
      16: invokevirtual #8                  // Method org/apache/tomcat/util/res/StringManager.getString:(Ljava/lang/String;)Ljava/lang/String;
      19: invokespecial #9                  // Method java/lang/IllegalStateException."<init>":(Ljava/lang/String;)V
      22: athrow
      23: aload_0
      24: getfield      #2                  // Field request:Lorg/apache/catalina/connector/Request;
      27: invokevirtual #84                 // Method org/apache/catalina/connector/Request.getRemoteUser:()Ljava/lang/String;
      30: areturn

  public boolean isUserInRole(java.lang.String);
    Code:
       0: aload_0
       1: getfield      #2                  // Field request:Lorg/apache/catalina/connector/Request;
       4: ifnonnull     23
       7: new           #5                  // class java/lang/IllegalStateException
      10: dup
      11: getstatic     #6                  // Field sm:Lorg/apache/tomcat/util/res/StringManager;
      14: ldc           #7                  // String requestFacade.nullRequest
      16: invokevirtual #8                  // Method org/apache/tomcat/util/res/StringManager.getString:(Ljava/lang/String;)Ljava/lang/String;
      19: invokespecial #9                  // Method java/lang/IllegalStateException."<init>":(Ljava/lang/String;)V
      22: athrow
      23: aload_0
      24: getfield      #2                  // Field request:Lorg/apache/catalina/connector/Request;
      27: aload_1
      28: invokevirtual #85                 // Method org/apache/catalina/connector/Request.isUserInRole:(Ljava/lang/String;)Z
      31: ireturn

  public java.security.Principal getUserPrincipal();
    Code:
       0: aload_0
       1: getfield      #2                  // Field request:Lorg/apache/catalina/connector/Request;
       4: ifnonnull     23
       7: new           #5                  // class java/lang/IllegalStateException
      10: dup
      11: getstatic     #6                  // Field sm:Lorg/apache/tomcat/util/res/StringManager;
      14: ldc           #7                  // String requestFacade.nullRequest
      16: invokevirtual #8                  // Method org/apache/tomcat/util/res/StringManager.getString:(Ljava/lang/String;)Ljava/lang/String;
      19: invokespecial #9                  // Method java/lang/IllegalStateException."<init>":(Ljava/lang/String;)V
      22: athrow
      23: aload_0
      24: getfield      #2                  // Field request:Lorg/apache/catalina/connector/Request;
      27: invokevirtual #86                 // Method org/apache/catalina/connector/Request.getUserPrincipal:()Ljava/security/Principal;
      30: areturn

  public java.lang.String getRequestedSessionId();
    Code:
       0: aload_0
       1: getfield      #2                  // Field request:Lorg/apache/catalina/connector/Request;
       4: ifnonnull     23
       7: new           #5                  // class java/lang/IllegalStateException
      10: dup
      11: getstatic     #6                  // Field sm:Lorg/apache/tomcat/util/res/StringManager;
      14: ldc           #7                  // String requestFacade.nullRequest
      16: invokevirtual #8                  // Method org/apache/tomcat/util/res/StringManager.getString:(Ljava/lang/String;)Ljava/lang/String;
      19: invokespecial #9                  // Method java/lang/IllegalStateException."<init>":(Ljava/lang/String;)V
      22: athrow
      23: aload_0
      24: getfield      #2                  // Field request:Lorg/apache/catalina/connector/Request;
      27: invokevirtual #87                 // Method org/apache/catalina/connector/Request.getRequestedSessionId:()Ljava/lang/String;
      30: areturn

  public java.lang.String getRequestURI();
    Code:
       0: aload_0
       1: getfield      #2                  // Field request:Lorg/apache/catalina/connector/Request;
       4: ifnonnull     23
       7: new           #5                  // class java/lang/IllegalStateException
      10: dup
      11: getstatic     #6                  // Field sm:Lorg/apache/tomcat/util/res/StringManager;
      14: ldc           #7                  // String requestFacade.nullRequest
      16: invokevirtual #8                  // Method org/apache/tomcat/util/res/StringManager.getString:(Ljava/lang/String;)Ljava/lang/String;
      19: invokespecial #9                  // Method java/lang/IllegalStateException."<init>":(Ljava/lang/String;)V
      22: athrow
      23: aload_0
      24: getfield      #2                  // Field request:Lorg/apache/catalina/connector/Request;
      27: invokevirtual #88                 // Method org/apache/catalina/connector/Request.getRequestURI:()Ljava/lang/String;
      30: areturn

  public java.lang.StringBuffer getRequestURL();
    Code:
       0: aload_0
       1: getfield      #2                  // Field request:Lorg/apache/catalina/connector/Request;
       4: ifnonnull     23
       7: new           #5                  // class java/lang/IllegalStateException
      10: dup
      11: getstatic     #6                  // Field sm:Lorg/apache/tomcat/util/res/StringManager;
      14: ldc           #7                  // String requestFacade.nullRequest
      16: invokevirtual #8                  // Method org/apache/tomcat/util/res/StringManager.getString:(Ljava/lang/String;)Ljava/lang/String;
      19: invokespecial #9                  // Method java/lang/IllegalStateException."<init>":(Ljava/lang/String;)V
      22: athrow
      23: aload_0
      24: getfield      #2                  // Field request:Lorg/apache/catalina/connector/Request;
      27: invokevirtual #89                 // Method org/apache/catalina/connector/Request.getRequestURL:()Ljava/lang/StringBuffer;
      30: areturn

  public java.lang.String getServletPath();
    Code:
       0: aload_0
       1: getfield      #2                  // Field request:Lorg/apache/catalina/connector/Request;
       4: ifnonnull     23
       7: new           #5                  // class java/lang/IllegalStateException
      10: dup
      11: getstatic     #6                  // Field sm:Lorg/apache/tomcat/util/res/StringManager;
      14: ldc           #7                  // String requestFacade.nullRequest
      16: invokevirtual #8                  // Method org/apache/tomcat/util/res/StringManager.getString:(Ljava/lang/String;)Ljava/lang/String;
      19: invokespecial #9                  // Method java/lang/IllegalStateException."<init>":(Ljava/lang/String;)V
      22: athrow
      23: aload_0
      24: getfield      #2                  // Field request:Lorg/apache/catalina/connector/Request;
      27: invokevirtual #90                 // Method org/apache/catalina/connector/Request.getServletPath:()Ljava/lang/String;
      30: areturn

  public javax.servlet.http.HttpSession getSession(boolean);
    Code:
       0: aload_0
       1: getfield      #2                  // Field request:Lorg/apache/catalina/connector/Request;
       4: ifnonnull     23
       7: new           #5                  // class java/lang/IllegalStateException
      10: dup
      11: getstatic     #6                  // Field sm:Lorg/apache/tomcat/util/res/StringManager;
      14: ldc           #7                  // String requestFacade.nullRequest
      16: invokevirtual #8                  // Method org/apache/tomcat/util/res/StringManager.getString:(Ljava/lang/String;)Ljava/lang/String;
      19: invokespecial #9                  // Method java/lang/IllegalStateException."<init>":(Ljava/lang/String;)V
      22: athrow
      23: invokestatic  #31                 // Method org/apache/catalina/security/SecurityUtil.isPackageProtectionEnabled:()Z
      26: ifeq          45
      29: new           #91                 // class org/apache/catalina/connector/RequestFacade$GetSessionPrivilegedAction
      32: dup
      33: aload_0
      34: iload_1
      35: invokespecial #92                 // Method org/apache/catalina/connector/RequestFacade$GetSessionPrivilegedAction."<init>":(Lorg/apache/catalina/connector/RequestFacade;Z)V
      38: invokestatic  #14                 // Method java/security/AccessController.doPrivileged:(Ljava/security/PrivilegedAction;)Ljava/lang/Object;
      41: checkcast     #93                 // class javax/servlet/http/HttpSession
      44: areturn
      45: aload_0
      46: getfield      #2                  // Field request:Lorg/apache/catalina/connector/Request;
      49: iload_1
      50: invokevirtual #94                 // Method org/apache/catalina/connector/Request.getSession:(Z)Ljavax/servlet/http/HttpSession;
      53: areturn

  public javax.servlet.http.HttpSession getSession();
    Code:
       0: aload_0
       1: getfield      #2                  // Field request:Lorg/apache/catalina/connector/Request;
       4: ifnonnull     23
       7: new           #5                  // class java/lang/IllegalStateException
      10: dup
      11: getstatic     #6                  // Field sm:Lorg/apache/tomcat/util/res/StringManager;
      14: ldc           #7                  // String requestFacade.nullRequest
      16: invokevirtual #8                  // Method org/apache/tomcat/util/res/StringManager.getString:(Ljava/lang/String;)Ljava/lang/String;
      19: invokespecial #9                  // Method java/lang/IllegalStateException."<init>":(Ljava/lang/String;)V
      22: athrow
      23: aload_0
      24: iconst_1
      25: invokevirtual #95                 // Method getSession:(Z)Ljavax/servlet/http/HttpSession;
      28: areturn

  public java.lang.String changeSessionId();
    Code:
       0: aload_0
       1: getfield      #2                  // Field request:Lorg/apache/catalina/connector/Request;
       4: ifnonnull     23
       7: new           #5                  // class java/lang/IllegalStateException
      10: dup
      11: getstatic     #6                  // Field sm:Lorg/apache/tomcat/util/res/StringManager;
      14: ldc           #7                  // String requestFacade.nullRequest
      16: invokevirtual #8                  // Method org/apache/tomcat/util/res/StringManager.getString:(Ljava/lang/String;)Ljava/lang/String;
      19: invokespecial #9                  // Method java/lang/IllegalStateException."<init>":(Ljava/lang/String;)V
      22: athrow
      23: aload_0
      24: getfield      #2                  // Field request:Lorg/apache/catalina/connector/Request;
      27: invokevirtual #96                 // Method org/apache/catalina/connector/Request.changeSessionId:()Ljava/lang/String;
      30: areturn

  public boolean isRequestedSessionIdValid();
    Code:
       0: aload_0
       1: getfield      #2                  // Field request:Lorg/apache/catalina/connector/Request;
       4: ifnonnull     23
       7: new           #5                  // class java/lang/IllegalStateException
      10: dup
      11: getstatic     #6                  // Field sm:Lorg/apache/tomcat/util/res/StringManager;
      14: ldc           #7                  // String requestFacade.nullRequest
      16: invokevirtual #8                  // Method org/apache/tomcat/util/res/StringManager.getString:(Ljava/lang/String;)Ljava/lang/String;
      19: invokespecial #9                  // Method java/lang/IllegalStateException."<init>":(Ljava/lang/String;)V
      22: athrow
      23: aload_0
      24: getfield      #2                  // Field request:Lorg/apache/catalina/connector/Request;
      27: invokevirtual #97                 // Method org/apache/catalina/connector/Request.isRequestedSessionIdValid:()Z
      30: ireturn

  public boolean isRequestedSessionIdFromCookie();
    Code:
       0: aload_0
       1: getfield      #2                  // Field request:Lorg/apache/catalina/connector/Request;
       4: ifnonnull     23
       7: new           #5                  // class java/lang/IllegalStateException
      10: dup
      11: getstatic     #6                  // Field sm:Lorg/apache/tomcat/util/res/StringManager;
      14: ldc           #7                  // String requestFacade.nullRequest
      16: invokevirtual #8                  // Method org/apache/tomcat/util/res/StringManager.getString:(Ljava/lang/String;)Ljava/lang/String;
      19: invokespecial #9                  // Method java/lang/IllegalStateException."<init>":(Ljava/lang/String;)V
      22: athrow
      23: aload_0
      24: getfield      #2                  // Field request:Lorg/apache/catalina/connector/Request;
      27: invokevirtual #98                 // Method org/apache/catalina/connector/Request.isRequestedSessionIdFromCookie:()Z
      30: ireturn

  public boolean isRequestedSessionIdFromURL();
    Code:
       0: aload_0
       1: getfield      #2                  // Field request:Lorg/apache/catalina/connector/Request;
       4: ifnonnull     23
       7: new           #5                  // class java/lang/IllegalStateException
      10: dup
      11: getstatic     #6                  // Field sm:Lorg/apache/tomcat/util/res/StringManager;
      14: ldc           #7                  // String requestFacade.nullRequest
      16: invokevirtual #8                  // Method org/apache/tomcat/util/res/StringManager.getString:(Ljava/lang/String;)Ljava/lang/String;
      19: invokespecial #9                  // Method java/lang/IllegalStateException."<init>":(Ljava/lang/String;)V
      22: athrow
      23: aload_0
      24: getfield      #2                  // Field request:Lorg/apache/catalina/connector/Request;
      27: invokevirtual #99                 // Method org/apache/catalina/connector/Request.isRequestedSessionIdFromURL:()Z
      30: ireturn

  public boolean isRequestedSessionIdFromUrl();
    Code:
       0: aload_0
       1: getfield      #2                  // Field request:Lorg/apache/catalina/connector/Request;
       4: ifnonnull     23
       7: new           #5                  // class java/lang/IllegalStateException
      10: dup
      11: getstatic     #6                  // Field sm:Lorg/apache/tomcat/util/res/StringManager;
      14: ldc           #7                  // String requestFacade.nullRequest
      16: invokevirtual #8                  // Method org/apache/tomcat/util/res/StringManager.getString:(Ljava/lang/String;)Ljava/lang/String;
      19: invokespecial #9                  // Method java/lang/IllegalStateException."<init>":(Ljava/lang/String;)V
      22: athrow
      23: aload_0
      24: getfield      #2                  // Field request:Lorg/apache/catalina/connector/Request;
      27: invokevirtual #99                 // Method org/apache/catalina/connector/Request.isRequestedSessionIdFromURL:()Z
      30: ireturn

  public java.lang.String getLocalAddr();
    Code:
       0: aload_0
       1: getfield      #2                  // Field request:Lorg/apache/catalina/connector/Request;
       4: ifnonnull     23
       7: new           #5                  // class java/lang/IllegalStateException
      10: dup
      11: getstatic     #6                  // Field sm:Lorg/apache/tomcat/util/res/StringManager;
      14: ldc           #7                  // String requestFacade.nullRequest
      16: invokevirtual #8                  // Method org/apache/tomcat/util/res/StringManager.getString:(Ljava/lang/String;)Ljava/lang/String;
      19: invokespecial #9                  // Method java/lang/IllegalStateException."<init>":(Ljava/lang/String;)V
      22: athrow
      23: aload_0
      24: getfield      #2                  // Field request:Lorg/apache/catalina/connector/Request;
      27: invokevirtual #100                // Method org/apache/catalina/connector/Request.getLocalAddr:()Ljava/lang/String;
      30: areturn

  public java.lang.String getLocalName();
    Code:
       0: aload_0
       1: getfield      #2                  // Field request:Lorg/apache/catalina/connector/Request;
       4: ifnonnull     23
       7: new           #5                  // class java/lang/IllegalStateException
      10: dup
      11: getstatic     #6                  // Field sm:Lorg/apache/tomcat/util/res/StringManager;
      14: ldc           #7                  // String requestFacade.nullRequest
      16: invokevirtual #8                  // Method org/apache/tomcat/util/res/StringManager.getString:(Ljava/lang/String;)Ljava/lang/String;
      19: invokespecial #9                  // Method java/lang/IllegalStateException."<init>":(Ljava/lang/String;)V
      22: athrow
      23: aload_0
      24: getfield      #2                  // Field request:Lorg/apache/catalina/connector/Request;
      27: invokevirtual #101                // Method org/apache/catalina/connector/Request.getLocalName:()Ljava/lang/String;
      30: areturn

  public int getLocalPort();
    Code:
       0: aload_0
       1: getfield      #2                  // Field request:Lorg/apache/catalina/connector/Request;
       4: ifnonnull     23
       7: new           #5                  // class java/lang/IllegalStateException
      10: dup
      11: getstatic     #6                  // Field sm:Lorg/apache/tomcat/util/res/StringManager;
      14: ldc           #7                  // String requestFacade.nullRequest
      16: invokevirtual #8                  // Method org/apache/tomcat/util/res/StringManager.getString:(Ljava/lang/String;)Ljava/lang/String;
      19: invokespecial #9                  // Method java/lang/IllegalStateException."<init>":(Ljava/lang/String;)V
      22: athrow
      23: aload_0
      24: getfield      #2                  // Field request:Lorg/apache/catalina/connector/Request;
      27: invokevirtual #102                // Method org/apache/catalina/connector/Request.getLocalPort:()I
      30: ireturn

  public int getRemotePort();
    Code:
       0: aload_0
       1: getfield      #2                  // Field request:Lorg/apache/catalina/connector/Request;
       4: ifnonnull     23
       7: new           #5                  // class java/lang/IllegalStateException
      10: dup
      11: getstatic     #6                  // Field sm:Lorg/apache/tomcat/util/res/StringManager;
      14: ldc           #7                  // String requestFacade.nullRequest
      16: invokevirtual #8                  // Method org/apache/tomcat/util/res/StringManager.getString:(Ljava/lang/String;)Ljava/lang/String;
      19: invokespecial #9                  // Method java/lang/IllegalStateException."<init>":(Ljava/lang/String;)V
      22: athrow
      23: aload_0
      24: getfield      #2                  // Field request:Lorg/apache/catalina/connector/Request;
      27: invokevirtual #103                // Method org/apache/catalina/connector/Request.getRemotePort:()I
      30: ireturn

  public javax.servlet.ServletContext getServletContext();
    Code:
       0: aload_0
       1: getfield      #2                  // Field request:Lorg/apache/catalina/connector/Request;
       4: ifnonnull     23
       7: new           #5                  // class java/lang/IllegalStateException
      10: dup
      11: getstatic     #6                  // Field sm:Lorg/apache/tomcat/util/res/StringManager;
      14: ldc           #7                  // String requestFacade.nullRequest
      16: invokevirtual #8                  // Method org/apache/tomcat/util/res/StringManager.getString:(Ljava/lang/String;)Ljava/lang/String;
      19: invokespecial #9                  // Method java/lang/IllegalStateException."<init>":(Ljava/lang/String;)V
      22: athrow
      23: aload_0
      24: getfield      #2                  // Field request:Lorg/apache/catalina/connector/Request;
      27: invokevirtual #104                // Method org/apache/catalina/connector/Request.getServletContext:()Ljavax/servlet/ServletContext;
      30: areturn

  public javax.servlet.AsyncContext startAsync() throws java.lang.IllegalStateException;
    Code:
       0: aload_0
       1: getfield      #2                  // Field request:Lorg/apache/catalina/connector/Request;
       4: invokevirtual #105                // Method org/apache/catalina/connector/Request.startAsync:()Ljavax/servlet/AsyncContext;
       7: areturn

  public javax.servlet.AsyncContext startAsync(javax.servlet.ServletRequest, javax.servlet.ServletResponse) throws java.lang.IllegalStateException;
    Code:
       0: aload_0
       1: getfield      #2                  // Field request:Lorg/apache/catalina/connector/Request;
       4: aload_1
       5: aload_2
       6: invokevirtual #106                // Method org/apache/catalina/connector/Request.startAsync:(Ljavax/servlet/ServletRequest;Ljavax/servlet/ServletResponse;)Ljavax/servlet/AsyncContext;
       9: areturn

  public boolean isAsyncStarted();
    Code:
       0: aload_0
       1: getfield      #2                  // Field request:Lorg/apache/catalina/connector/Request;
       4: invokevirtual #107                // Method org/apache/catalina/connector/Request.isAsyncStarted:()Z
       7: ireturn

  public boolean isAsyncSupported();
    Code:
       0: aload_0
       1: getfield      #2                  // Field request:Lorg/apache/catalina/connector/Request;
       4: invokevirtual #108                // Method org/apache/catalina/connector/Request.isAsyncSupported:()Z
       7: ireturn

  public javax.servlet.AsyncContext getAsyncContext();
    Code:
       0: aload_0
       1: getfield      #2                  // Field request:Lorg/apache/catalina/connector/Request;
       4: invokevirtual #109                // Method org/apache/catalina/connector/Request.getAsyncContext:()Ljavax/servlet/AsyncContext;
       7: areturn

  public javax.servlet.DispatcherType getDispatcherType();
    Code:
       0: aload_0
       1: getfield      #2                  // Field request:Lorg/apache/catalina/connector/Request;
       4: invokevirtual #110                // Method org/apache/catalina/connector/Request.getDispatcherType:()Ljavax/servlet/DispatcherType;
       7: areturn

  public boolean authenticate(javax.servlet.http.HttpServletResponse) throws java.io.IOException, javax.servlet.ServletException;
    Code:
       0: aload_0
       1: getfield      #2                  // Field request:Lorg/apache/catalina/connector/Request;
       4: aload_1
       5: invokevirtual #111                // Method org/apache/catalina/connector/Request.authenticate:(Ljavax/servlet/http/HttpServletResponse;)Z
       8: ireturn

  public void login(java.lang.String, java.lang.String) throws javax.servlet.ServletException;
    Code:
       0: aload_0
       1: getfield      #2                  // Field request:Lorg/apache/catalina/connector/Request;
       4: aload_1
       5: aload_2
       6: invokevirtual #112                // Method org/apache/catalina/connector/Request.login:(Ljava/lang/String;Ljava/lang/String;)V
       9: return

  public void logout() throws javax.servlet.ServletException;
    Code:
       0: aload_0
       1: getfield      #2                  // Field request:Lorg/apache/catalina/connector/Request;
       4: invokevirtual #113                // Method org/apache/catalina/connector/Request.logout:()V
       7: return

  public java.util.Collection<javax.servlet.http.Part> getParts() throws java.lang.IllegalStateException, java.io.IOException, javax.servlet.ServletException;
    Code:
       0: aload_0
       1: getfield      #2                  // Field request:Lorg/apache/catalina/connector/Request;
       4: invokevirtual #114                // Method org/apache/catalina/connector/Request.getParts:()Ljava/util/Collection;
       7: areturn

  public javax.servlet.http.Part getPart(java.lang.String) throws java.lang.IllegalStateException, java.io.IOException, javax.servlet.ServletException;
    Code:
       0: aload_0
       1: getfield      #2                  // Field request:Lorg/apache/catalina/connector/Request;
       4: aload_1
       5: invokevirtual #115                // Method org/apache/catalina/connector/Request.getPart:(Ljava/lang/String;)Ljavax/servlet/http/Part;
       8: areturn

  public boolean getAllowTrace();
    Code:
       0: aload_0
       1: getfield      #2                  // Field request:Lorg/apache/catalina/connector/Request;
       4: invokevirtual #116                // Method org/apache/catalina/connector/Request.getConnector:()Lorg/apache/catalina/connector/Connector;
       7: invokevirtual #117                // Method org/apache/catalina/connector/Connector.getAllowTrace:()Z
      10: ireturn

  public long getContentLengthLong();
    Code:
       0: aload_0
       1: getfield      #2                  // Field request:Lorg/apache/catalina/connector/Request;
       4: invokevirtual #118                // Method org/apache/catalina/connector/Request.getContentLengthLong:()J
       7: lreturn

  public <T extends javax.servlet.http.HttpUpgradeHandler> T upgrade(java.lang.Class<T>) throws java.io.IOException, javax.servlet.ServletException;
    Code:
       0: aload_0
       1: getfield      #2                  // Field request:Lorg/apache/catalina/connector/Request;
       4: aload_1
       5: invokevirtual #119                // Method org/apache/catalina/connector/Request.upgrade:(Ljava/lang/Class;)Ljavax/servlet/http/HttpUpgradeHandler;
       8: areturn

  public javax.servlet.http.PushBuilder newPushBuilder();
    Code:
       0: aload_0
       1: getfield      #2                  // Field request:Lorg/apache/catalina/connector/Request;
       4: invokevirtual #120                // Method org/apache/catalina/connector/Request.newPushBuilder:()Ljavax/servlet/http/PushBuilder;
       7: areturn

  public javax.servlet.http.PushBuilder newPushBuilder(javax.servlet.http.HttpServletRequest);
    Code:
       0: aload_0
       1: getfield      #2                  // Field request:Lorg/apache/catalina/connector/Request;
       4: aload_1
       5: invokevirtual #121                // Method org/apache/catalina/connector/Request.newPushBuilder:(Ljavax/servlet/http/HttpServletRequest;)Ljavax/servlet/http/PushBuilder;
       8: areturn

  public boolean isTrailerFieldsReady();
    Code:
       0: aload_0
       1: getfield      #2                  // Field request:Lorg/apache/catalina/connector/Request;
       4: invokevirtual #122                // Method org/apache/catalina/connector/Request.isTrailerFieldsReady:()Z
       7: ireturn

  public java.util.Map<java.lang.String, java.lang.String> getTrailerFields();
    Code:
       0: aload_0
       1: getfield      #2                  // Field request:Lorg/apache/catalina/connector/Request;
       4: invokevirtual #123                // Method org/apache/catalina/connector/Request.getTrailerFields:()Ljava/util/Map;
       7: areturn

  static {};
    Code:
       0: ldc           #124                // class org/apache/catalina/connector/RequestFacade
       2: invokestatic  #125                // Method org/apache/tomcat/util/res/StringManager.getManager:(Ljava/lang/Class;)Lorg/apache/tomcat/util/res/StringManager;
       5: putstatic     #6                  // Field sm:Lorg/apache/tomcat/util/res/StringManager;
       8: return
}
