Compiled from "Defaults.java"
public final class com.google.common.base.Defaults {
  private static final java.lang.Double DOUBLE_DEFAULT;

  private static final java.lang.Float FLOAT_DEFAULT;

  private com.google.common.base.Defaults();
    Code:
       0: aload_0
       1: invokespecial #1                  // Method java/lang/Object."<init>":()V
       4: return

  public static <T> T defaultValue(java.lang.Class<T>);
    Code:
       0: aload_0
       1: invokestatic  #2                  // Method com/google/common/base/Preconditions.checkNotNull:(Ljava/lang/Object;)Ljava/lang/Object;
       4: pop
       5: aload_0
       6: invokevirtual #3                  // Method java/lang/Class.isPrimitive:()Z
       9: ifeq          105
      12: aload_0
      13: getstatic     #4                  // Field java/lang/Boolean.TYPE:Ljava/lang/Class;
      16: if_acmpne     23
      19: getstatic     #5                  // Field java/lang/Boolean.FALSE:Ljava/lang/Boolean;
      22: areturn
      23: aload_0
      24: getstatic     #6                  // Field java/lang/Character.TYPE:Ljava/lang/Class;
      27: if_acmpne     35
      30: iconst_0
      31: invokestatic  #7                  // Method java/lang/Character.valueOf:(C)Ljava/lang/Character;
      34: areturn
      35: aload_0
      36: getstatic     #8                  // Field java/lang/Byte.TYPE:Ljava/lang/Class;
      39: if_acmpne     47
      42: iconst_0
      43: invokestatic  #9                  // Method java/lang/Byte.valueOf:(B)Ljava/lang/Byte;
      46: areturn
      47: aload_0
      48: getstatic     #10                 // Field java/lang/Short.TYPE:Ljava/lang/Class;
      51: if_acmpne     59
      54: iconst_0
      55: invokestatic  #11                 // Method java/lang/Short.valueOf:(S)Ljava/lang/Short;
      58: areturn
      59: aload_0
      60: getstatic     #12                 // Field java/lang/Integer.TYPE:Ljava/lang/Class;
      63: if_acmpne     71
      66: iconst_0
      67: invokestatic  #13                 // Method java/lang/Integer.valueOf:(I)Ljava/lang/Integer;
      70: areturn
      71: aload_0
      72: getstatic     #14                 // Field java/lang/Long.TYPE:Ljava/lang/Class;
      75: if_acmpne     83
      78: lconst_0
      79: invokestatic  #15                 // Method java/lang/Long.valueOf:(J)Ljava/lang/Long;
      82: areturn
      83: aload_0
      84: getstatic     #16                 // Field java/lang/Float.TYPE:Ljava/lang/Class;
      87: if_acmpne     94
      90: getstatic     #17                 // Field FLOAT_DEFAULT:Ljava/lang/Float;
      93: areturn
      94: aload_0
      95: getstatic     #18                 // Field java/lang/Double.TYPE:Ljava/lang/Class;
      98: if_acmpne     105
     101: getstatic     #19                 // Field DOUBLE_DEFAULT:Ljava/lang/Double;
     104: areturn
     105: aconst_null
     106: areturn

  static {};
    Code:
       0: dconst_0
       1: invokestatic  #20                 // Method java/lang/Double.valueOf:(D)Ljava/lang/Double;
       4: putstatic     #19                 // Field DOUBLE_DEFAULT:Ljava/lang/Double;
       7: fconst_0
       8: invokestatic  #21                 // Method java/lang/Float.valueOf:(F)Ljava/lang/Float;
      11: putstatic     #17                 // Field FLOAT_DEFAULT:Ljava/lang/Float;
      14: return
}
