Compiled from "MoreObjects.java"
public final class com.google.common.base.MoreObjects$ToStringHelper {
  private final java.lang.String className;

  private final com.google.common.base.MoreObjects$ToStringHelper$ValueHolder holderHead;

  private com.google.common.base.MoreObjects$ToStringHelper$ValueHolder holderTail;

  private boolean omitNullValues;

  private boolean omitEmptyValues;

  private com.google.common.base.MoreObjects$ToStringHelper(java.lang.String);
    Code:
       0: aload_0
       1: invokespecial #2                  // Method java/lang/Object."<init>":()V
       4: aload_0
       5: new           #3                  // class com/google/common/base/MoreObjects$ToStringHelper$ValueHolder
       8: dup
       9: aconst_null
      10: invokespecial #4                  // Method com/google/common/base/MoreObjects$ToStringHelper$ValueHolder."<init>":(Lcom/google/common/base/MoreObjects$1;)V
      13: putfield      #5                  // Field holderHead:Lcom/google/common/base/MoreObjects$ToStringHelper$ValueHolder;
      16: aload_0
      17: aload_0
      18: getfield      #5                  // Field holderHead:Lcom/google/common/base/MoreObjects$ToStringHelper$ValueHolder;
      21: putfield      #6                  // Field holderTail:Lcom/google/common/base/MoreObjects$ToStringHelper$ValueHolder;
      24: aload_0
      25: iconst_0
      26: putfield      #7                  // Field omitNullValues:Z
      29: aload_0
      30: iconst_0
      31: putfield      #8                  // Field omitEmptyValues:Z
      34: aload_0
      35: aload_1
      36: invokestatic  #9                  // Method com/google/common/base/Preconditions.checkNotNull:(Ljava/lang/Object;)Ljava/lang/Object;
      39: checkcast     #10                 // class java/lang/String
      42: putfield      #11                 // Field className:Ljava/lang/String;
      45: return

  public com.google.common.base.MoreObjects$ToStringHelper omitNullValues();
    Code:
       0: aload_0
       1: iconst_1
       2: putfield      #7                  // Field omitNullValues:Z
       5: aload_0
       6: areturn

  public com.google.common.base.MoreObjects$ToStringHelper add(java.lang.String, java.lang.Object);
    Code:
       0: aload_0
       1: aload_1
       2: aload_2
       3: invokespecial #12                 // Method addHolder:(Ljava/lang/String;Ljava/lang/Object;)Lcom/google/common/base/MoreObjects$ToStringHelper;
       6: areturn

  public com.google.common.base.MoreObjects$ToStringHelper add(java.lang.String, boolean);
    Code:
       0: aload_0
       1: aload_1
       2: iload_2
       3: invokestatic  #13                 // Method java/lang/String.valueOf:(Z)Ljava/lang/String;
       6: invokespecial #14                 // Method addUnconditionalHolder:(Ljava/lang/String;Ljava/lang/Object;)Lcom/google/common/base/MoreObjects$ToStringHelper;
       9: areturn

  public com.google.common.base.MoreObjects$ToStringHelper add(java.lang.String, char);
    Code:
       0: aload_0
       1: aload_1
       2: iload_2
       3: invokestatic  #15                 // Method java/lang/String.valueOf:(C)Ljava/lang/String;
       6: invokespecial #14                 // Method addUnconditionalHolder:(Ljava/lang/String;Ljava/lang/Object;)Lcom/google/common/base/MoreObjects$ToStringHelper;
       9: areturn

  public com.google.common.base.MoreObjects$ToStringHelper add(java.lang.String, double);
    Code:
       0: aload_0
       1: aload_1
       2: dload_2
       3: invokestatic  #16                 // Method java/lang/String.valueOf:(D)Ljava/lang/String;
       6: invokespecial #14                 // Method addUnconditionalHolder:(Ljava/lang/String;Ljava/lang/Object;)Lcom/google/common/base/MoreObjects$ToStringHelper;
       9: areturn

  public com.google.common.base.MoreObjects$ToStringHelper add(java.lang.String, float);
    Code:
       0: aload_0
       1: aload_1
       2: fload_2
       3: invokestatic  #17                 // Method java/lang/String.valueOf:(F)Ljava/lang/String;
       6: invokespecial #14                 // Method addUnconditionalHolder:(Ljava/lang/String;Ljava/lang/Object;)Lcom/google/common/base/MoreObjects$ToStringHelper;
       9: areturn

  public com.google.common.base.MoreObjects$ToStringHelper add(java.lang.String, int);
    Code:
       0: aload_0
       1: aload_1
       2: iload_2
       3: invokestatic  #18                 // Method java/lang/String.valueOf:(I)Ljava/lang/String;
       6: invokespecial #14                 // Method addUnconditionalHolder:(Ljava/lang/String;Ljava/lang/Object;)Lcom/google/common/base/MoreObjects$ToStringHelper;
       9: areturn

  public com.google.common.base.MoreObjects$ToStringHelper add(java.lang.String, long);
    Code:
       0: aload_0
       1: aload_1
       2: lload_2
       3: invokestatic  #19                 // Method java/lang/String.valueOf:(J)Ljava/lang/String;
       6: invokespecial #14                 // Method addUnconditionalHolder:(Ljava/lang/String;Ljava/lang/Object;)Lcom/google/common/base/MoreObjects$ToStringHelper;
       9: areturn

  public com.google.common.base.MoreObjects$ToStringHelper addValue(java.lang.Object);
    Code:
       0: aload_0
       1: aload_1
       2: invokespecial #20                 // Method addHolder:(Ljava/lang/Object;)Lcom/google/common/base/MoreObjects$ToStringHelper;
       5: areturn

  public com.google.common.base.MoreObjects$ToStringHelper addValue(boolean);
    Code:
       0: aload_0
       1: iload_1
       2: invokestatic  #13                 // Method java/lang/String.valueOf:(Z)Ljava/lang/String;
       5: invokespecial #21                 // Method addUnconditionalHolder:(Ljava/lang/Object;)Lcom/google/common/base/MoreObjects$ToStringHelper;
       8: areturn

  public com.google.common.base.MoreObjects$ToStringHelper addValue(char);
    Code:
       0: aload_0
       1: iload_1
       2: invokestatic  #15                 // Method java/lang/String.valueOf:(C)Ljava/lang/String;
       5: invokespecial #21                 // Method addUnconditionalHolder:(Ljava/lang/Object;)Lcom/google/common/base/MoreObjects$ToStringHelper;
       8: areturn

  public com.google.common.base.MoreObjects$ToStringHelper addValue(double);
    Code:
       0: aload_0
       1: dload_1
       2: invokestatic  #16                 // Method java/lang/String.valueOf:(D)Ljava/lang/String;
       5: invokespecial #21                 // Method addUnconditionalHolder:(Ljava/lang/Object;)Lcom/google/common/base/MoreObjects$ToStringHelper;
       8: areturn

  public com.google.common.base.MoreObjects$ToStringHelper addValue(float);
    Code:
       0: aload_0
       1: fload_1
       2: invokestatic  #17                 // Method java/lang/String.valueOf:(F)Ljava/lang/String;
       5: invokespecial #21                 // Method addUnconditionalHolder:(Ljava/lang/Object;)Lcom/google/common/base/MoreObjects$ToStringHelper;
       8: areturn

  public com.google.common.base.MoreObjects$ToStringHelper addValue(int);
    Code:
       0: aload_0
       1: iload_1
       2: invokestatic  #18                 // Method java/lang/String.valueOf:(I)Ljava/lang/String;
       5: invokespecial #21                 // Method addUnconditionalHolder:(Ljava/lang/Object;)Lcom/google/common/base/MoreObjects$ToStringHelper;
       8: areturn

  public com.google.common.base.MoreObjects$ToStringHelper addValue(long);
    Code:
       0: aload_0
       1: lload_1
       2: invokestatic  #19                 // Method java/lang/String.valueOf:(J)Ljava/lang/String;
       5: invokespecial #21                 // Method addUnconditionalHolder:(Ljava/lang/Object;)Lcom/google/common/base/MoreObjects$ToStringHelper;
       8: areturn

  private static boolean isEmpty(java.lang.Object);
    Code:
       0: aload_0
       1: instanceof    #22                 // class java/lang/CharSequence
       4: ifeq          25
       7: aload_0
       8: checkcast     #22                 // class java/lang/CharSequence
      11: invokeinterface #23,  1           // InterfaceMethod java/lang/CharSequence.length:()I
      16: ifne          23
      19: iconst_1
      20: goto          24
      23: iconst_0
      24: ireturn
      25: aload_0
      26: instanceof    #24                 // class java/util/Collection
      29: ifeq          42
      32: aload_0
      33: checkcast     #24                 // class java/util/Collection
      36: invokeinterface #25,  1           // InterfaceMethod java/util/Collection.isEmpty:()Z
      41: ireturn
      42: aload_0
      43: instanceof    #26                 // class java/util/Map
      46: ifeq          59
      49: aload_0
      50: checkcast     #26                 // class java/util/Map
      53: invokeinterface #27,  1           // InterfaceMethod java/util/Map.isEmpty:()Z
      58: ireturn
      59: aload_0
      60: instanceof    #28                 // class java/util/Optional
      63: ifeq          82
      66: aload_0
      67: checkcast     #28                 // class java/util/Optional
      70: invokevirtual #29                 // Method java/util/Optional.isPresent:()Z
      73: ifne          80
      76: iconst_1
      77: goto          81
      80: iconst_0
      81: ireturn
      82: aload_0
      83: instanceof    #30                 // class java/util/OptionalInt
      86: ifeq          105
      89: aload_0
      90: checkcast     #30                 // class java/util/OptionalInt
      93: invokevirtual #31                 // Method java/util/OptionalInt.isPresent:()Z
      96: ifne          103
      99: iconst_1
     100: goto          104
     103: iconst_0
     104: ireturn
     105: aload_0
     106: instanceof    #32                 // class java/util/OptionalLong
     109: ifeq          128
     112: aload_0
     113: checkcast     #32                 // class java/util/OptionalLong
     116: invokevirtual #33                 // Method java/util/OptionalLong.isPresent:()Z
     119: ifne          126
     122: iconst_1
     123: goto          127
     126: iconst_0
     127: ireturn
     128: aload_0
     129: instanceof    #34                 // class java/util/OptionalDouble
     132: ifeq          151
     135: aload_0
     136: checkcast     #34                 // class java/util/OptionalDouble
     139: invokevirtual #35                 // Method java/util/OptionalDouble.isPresent:()Z
     142: ifne          149
     145: iconst_1
     146: goto          150
     149: iconst_0
     150: ireturn
     151: aload_0
     152: instanceof    #36                 // class com/google/common/base/Optional
     155: ifeq          174
     158: aload_0
     159: checkcast     #36                 // class com/google/common/base/Optional
     162: invokevirtual #37                 // Method com/google/common/base/Optional.isPresent:()Z
     165: ifne          172
     168: iconst_1
     169: goto          173
     172: iconst_0
     173: ireturn
     174: aload_0
     175: invokevirtual #38                 // Method java/lang/Object.getClass:()Ljava/lang/Class;
     178: invokevirtual #39                 // Method java/lang/Class.isArray:()Z
     181: ifeq          197
     184: aload_0
     185: invokestatic  #40                 // Method java/lang/reflect/Array.getLength:(Ljava/lang/Object;)I
     188: ifne          195
     191: iconst_1
     192: goto          196
     195: iconst_0
     196: ireturn
     197: iconst_0
     198: ireturn

  public java.lang.String toString();
    Code:
       0: aload_0
       1: getfield      #7                  // Field omitNullValues:Z
       4: istore_1
       5: aload_0
       6: getfield      #8                  // Field omitEmptyValues:Z
       9: istore_2
      10: ldc           #41                 // String
      12: astore_3
      13: new           #42                 // class java/lang/StringBuilder
      16: dup
      17: bipush        32
      19: invokespecial #43                 // Method java/lang/StringBuilder."<init>":(I)V
      22: aload_0
      23: getfield      #11                 // Field className:Ljava/lang/String;
      26: invokevirtual #44                 // Method java/lang/StringBuilder.append:(Ljava/lang/String;)Ljava/lang/StringBuilder;
      29: bipush        123
      31: invokevirtual #45                 // Method java/lang/StringBuilder.append:(C)Ljava/lang/StringBuilder;
      34: astore        4
      36: aload_0
      37: getfield      #5                  // Field holderHead:Lcom/google/common/base/MoreObjects$ToStringHelper$ValueHolder;
      40: getfield      #46                 // Field com/google/common/base/MoreObjects$ToStringHelper$ValueHolder.next:Lcom/google/common/base/MoreObjects$ToStringHelper$ValueHolder;
      43: astore        5
      45: aload         5
      47: ifnull        194
      50: aload         5
      52: getfield      #47                 // Field com/google/common/base/MoreObjects$ToStringHelper$ValueHolder.value:Ljava/lang/Object;
      55: astore        6
      57: aload         5
      59: instanceof    #48                 // class com/google/common/base/MoreObjects$ToStringHelper$UnconditionalValueHolder
      62: ifne          89
      65: aload         6
      67: ifnonnull     77
      70: iload_1
      71: ifne          184
      74: goto          89
      77: iload_2
      78: ifeq          89
      81: aload         6
      83: invokestatic  #49                 // Method isEmpty:(Ljava/lang/Object;)Z
      86: ifne          184
      89: aload         4
      91: aload_3
      92: invokevirtual #44                 // Method java/lang/StringBuilder.append:(Ljava/lang/String;)Ljava/lang/StringBuilder;
      95: pop
      96: ldc           #50                 // String ,
      98: astore_3
      99: aload         5
     101: getfield      #51                 // Field com/google/common/base/MoreObjects$ToStringHelper$ValueHolder.name:Ljava/lang/String;
     104: ifnull        123
     107: aload         4
     109: aload         5
     111: getfield      #51                 // Field com/google/common/base/MoreObjects$ToStringHelper$ValueHolder.name:Ljava/lang/String;
     114: invokevirtual #44                 // Method java/lang/StringBuilder.append:(Ljava/lang/String;)Ljava/lang/StringBuilder;
     117: bipush        61
     119: invokevirtual #45                 // Method java/lang/StringBuilder.append:(C)Ljava/lang/StringBuilder;
     122: pop
     123: aload         6
     125: ifnull        176
     128: aload         6
     130: invokevirtual #38                 // Method java/lang/Object.getClass:()Ljava/lang/Class;
     133: invokevirtual #39                 // Method java/lang/Class.isArray:()Z
     136: ifeq          176
     139: iconst_1
     140: anewarray     #52                 // class java/lang/Object
     143: dup
     144: iconst_0
     145: aload         6
     147: aastore
     148: astore        7
     150: aload         7
     152: invokestatic  #53                 // Method java/util/Arrays.deepToString:([Ljava/lang/Object;)Ljava/lang/String;
     155: astore        8
     157: aload         4
     159: aload         8
     161: iconst_1
     162: aload         8
     164: invokevirtual #54                 // Method java/lang/String.length:()I
     167: iconst_1
     168: isub
     169: invokevirtual #55                 // Method java/lang/StringBuilder.append:(Ljava/lang/CharSequence;II)Ljava/lang/StringBuilder;
     172: pop
     173: goto          184
     176: aload         4
     178: aload         6
     180: invokevirtual #56                 // Method java/lang/StringBuilder.append:(Ljava/lang/Object;)Ljava/lang/StringBuilder;
     183: pop
     184: aload         5
     186: getfield      #46                 // Field com/google/common/base/MoreObjects$ToStringHelper$ValueHolder.next:Lcom/google/common/base/MoreObjects$ToStringHelper$ValueHolder;
     189: astore        5
     191: goto          45
     194: aload         4
     196: bipush        125
     198: invokevirtual #45                 // Method java/lang/StringBuilder.append:(C)Ljava/lang/StringBuilder;
     201: invokevirtual #57                 // Method java/lang/StringBuilder.toString:()Ljava/lang/String;
     204: areturn

  private com.google.common.base.MoreObjects$ToStringHelper$ValueHolder addHolder();
    Code:
       0: new           #3                  // class com/google/common/base/MoreObjects$ToStringHelper$ValueHolder
       3: dup
       4: aconst_null
       5: invokespecial #4                  // Method com/google/common/base/MoreObjects$ToStringHelper$ValueHolder."<init>":(Lcom/google/common/base/MoreObjects$1;)V
       8: astore_1
       9: aload_0
      10: aload_0
      11: getfield      #6                  // Field holderTail:Lcom/google/common/base/MoreObjects$ToStringHelper$ValueHolder;
      14: aload_1
      15: dup_x1
      16: putfield      #46                 // Field com/google/common/base/MoreObjects$ToStringHelper$ValueHolder.next:Lcom/google/common/base/MoreObjects$ToStringHelper$ValueHolder;
      19: putfield      #6                  // Field holderTail:Lcom/google/common/base/MoreObjects$ToStringHelper$ValueHolder;
      22: aload_1
      23: areturn

  private com.google.common.base.MoreObjects$ToStringHelper addHolder(java.lang.Object);
    Code:
       0: aload_0
       1: invokespecial #58                 // Method addHolder:()Lcom/google/common/base/MoreObjects$ToStringHelper$ValueHolder;
       4: astore_2
       5: aload_2
       6: aload_1
       7: putfield      #47                 // Field com/google/common/base/MoreObjects$ToStringHelper$ValueHolder.value:Ljava/lang/Object;
      10: aload_0
      11: areturn

  private com.google.common.base.MoreObjects$ToStringHelper addHolder(java.lang.String, java.lang.Object);
    Code:
       0: aload_0
       1: invokespecial #58                 // Method addHolder:()Lcom/google/common/base/MoreObjects$ToStringHelper$ValueHolder;
       4: astore_3
       5: aload_3
       6: aload_2
       7: putfield      #47                 // Field com/google/common/base/MoreObjects$ToStringHelper$ValueHolder.value:Ljava/lang/Object;
      10: aload_3
      11: aload_1
      12: invokestatic  #9                  // Method com/google/common/base/Preconditions.checkNotNull:(Ljava/lang/Object;)Ljava/lang/Object;
      15: checkcast     #10                 // class java/lang/String
      18: putfield      #51                 // Field com/google/common/base/MoreObjects$ToStringHelper$ValueHolder.name:Ljava/lang/String;
      21: aload_0
      22: areturn

  private com.google.common.base.MoreObjects$ToStringHelper$UnconditionalValueHolder addUnconditionalHolder();
    Code:
       0: new           #48                 // class com/google/common/base/MoreObjects$ToStringHelper$UnconditionalValueHolder
       3: dup
       4: aconst_null
       5: invokespecial #59                 // Method com/google/common/base/MoreObjects$ToStringHelper$UnconditionalValueHolder."<init>":(Lcom/google/common/base/MoreObjects$1;)V
       8: astore_1
       9: aload_0
      10: aload_0
      11: getfield      #6                  // Field holderTail:Lcom/google/common/base/MoreObjects$ToStringHelper$ValueHolder;
      14: aload_1
      15: dup_x1
      16: putfield      #46                 // Field com/google/common/base/MoreObjects$ToStringHelper$ValueHolder.next:Lcom/google/common/base/MoreObjects$ToStringHelper$ValueHolder;
      19: putfield      #6                  // Field holderTail:Lcom/google/common/base/MoreObjects$ToStringHelper$ValueHolder;
      22: aload_1
      23: areturn

  private com.google.common.base.MoreObjects$ToStringHelper addUnconditionalHolder(java.lang.Object);
    Code:
       0: aload_0
       1: invokespecial #60                 // Method addUnconditionalHolder:()Lcom/google/common/base/MoreObjects$ToStringHelper$UnconditionalValueHolder;
       4: astore_2
       5: aload_2
       6: aload_1
       7: putfield      #61                 // Field com/google/common/base/MoreObjects$ToStringHelper$UnconditionalValueHolder.value:Ljava/lang/Object;
      10: aload_0
      11: areturn

  private com.google.common.base.MoreObjects$ToStringHelper addUnconditionalHolder(java.lang.String, java.lang.Object);
    Code:
       0: aload_0
       1: invokespecial #60                 // Method addUnconditionalHolder:()Lcom/google/common/base/MoreObjects$ToStringHelper$UnconditionalValueHolder;
       4: astore_3
       5: aload_3
       6: aload_2
       7: putfield      #61                 // Field com/google/common/base/MoreObjects$ToStringHelper$UnconditionalValueHolder.value:Ljava/lang/Object;
      10: aload_3
      11: aload_1
      12: invokestatic  #9                  // Method com/google/common/base/Preconditions.checkNotNull:(Ljava/lang/Object;)Ljava/lang/Object;
      15: checkcast     #10                 // class java/lang/String
      18: putfield      #62                 // Field com/google/common/base/MoreObjects$ToStringHelper$UnconditionalValueHolder.name:Ljava/lang/String;
      21: aload_0
      22: areturn

  com.google.common.base.MoreObjects$ToStringHelper(java.lang.String, com.google.common.base.MoreObjects$1);
    Code:
       0: aload_0
       1: aload_1
       2: invokespecial #1                  // Method "<init>":(Ljava/lang/String;)V
       5: return
}
