Compiled from "ClusterClient.scala"
public final class akka.cluster.client.ClusterReceptionist$$anonfun$8 extends scala.runtime.AbstractFunction2<akka.actor.Address, akka.actor.Address, java.lang.Object> implements scala.Serializable {
  public static final long serialVersionUID;

  private final akka.cluster.client.ClusterReceptionist $outer;

  public final boolean apply(akka.actor.Address, akka.actor.Address);
    Code:
       0: aload_0
       1: getfield      #20                 // Field $outer:Lakka/cluster/client/ClusterReceptionist;
       4: aload_1
       5: invokevirtual #24                 // Method akka/cluster/client/ClusterReceptionist.akka$cluster$client$ClusterReceptionist$$hashFor$1:(Lakka/actor/Address;)I
       8: istore_3
       9: aload_0
      10: getfield      #20                 // Field $outer:Lakka/cluster/client/ClusterReceptionist;
      13: aload_2
      14: invokevirtual #24                 // Method akka/cluster/client/ClusterReceptionist.akka$cluster$client$ClusterReceptionist$$hashFor$1:(Lakka/actor/Address;)I
      17: istore        4
      19: iload_3
      20: iload         4
      22: if_icmplt     48
      25: iload_3
      26: iload         4
      28: if_icmpne     52
      31: getstatic     #30                 // Field akka/cluster/Member$.MODULE$:Lakka/cluster/Member$;
      34: invokevirtual #34                 // Method akka/cluster/Member$.addressOrdering:()Lscala/math/Ordering;
      37: aload_1
      38: aload_2
      39: invokeinterface #40,  3           // InterfaceMethod scala/math/Ordering.compare:(Ljava/lang/Object;Ljava/lang/Object;)I
      44: iconst_0
      45: if_icmpge     52
      48: iconst_1
      49: goto          53
      52: iconst_0
      53: ireturn

  public final java.lang.Object apply(java.lang.Object, java.lang.Object);
    Code:
       0: aload_0
       1: aload_1
       2: checkcast     #51                 // class akka/actor/Address
       5: aload_2
       6: checkcast     #51                 // class akka/actor/Address
       9: invokevirtual #53                 // Method apply:(Lakka/actor/Address;Lakka/actor/Address;)Z
      12: invokestatic  #59                 // Method scala/runtime/BoxesRunTime.boxToBoolean:(Z)Ljava/lang/Boolean;
      15: areturn

  public akka.cluster.client.ClusterReceptionist$$anonfun$8(akka.cluster.client.ClusterReceptionist);
    Code:
       0: aload_1
       1: ifnonnull     6
       4: aconst_null
       5: athrow
       6: aload_0
       7: aload_1
       8: putfield      #20                 // Field $outer:Lakka/cluster/client/ClusterReceptionist;
      11: aload_0
      12: invokespecial #67                 // Method scala/runtime/AbstractFunction2."<init>":()V
      15: return
}
