Compiled from "Splitter.java"
final class org.apache.curator.shaded.com.google.common.base.Splitter$1 implements org.apache.curator.shaded.com.google.common.base.Splitter$Strategy {
  final org.apache.curator.shaded.com.google.common.base.CharMatcher val$separatorMatcher;

  org.apache.curator.shaded.com.google.common.base.Splitter$1(org.apache.curator.shaded.com.google.common.base.CharMatcher);
    Code:
       0: aload_0
       1: aload_1
       2: putfield      #24                 // Field val$separatorMatcher:Lorg/apache/curator/shaded/com/google/common/base/CharMatcher;
       5: aload_0
       6: invokespecial #27                 // Method java/lang/Object."<init>":()V
       9: return

  public org.apache.curator.shaded.com.google.common.base.Splitter$SplittingIterator iterator(org.apache.curator.shaded.com.google.common.base.Splitter, java.lang.CharSequence);
    Code:
       0: new           #14                 // class org/apache/curator/shaded/com/google/common/base/Splitter$1$1
       3: dup
       4: aload_0
       5: aload_1
       6: aload_2
       7: invokespecial #34                 // Method org/apache/curator/shaded/com/google/common/base/Splitter$1$1."<init>":(Lorg/apache/curator/shaded/com/google/common/base/Splitter$1;Lorg/apache/curator/shaded/com/google/common/base/Splitter;Ljava/lang/CharSequence;)V
      10: areturn

  public java.util.Iterator iterator(org.apache.curator.shaded.com.google.common.base.Splitter, java.lang.CharSequence);
    Code:
       0: aload_0
       1: aload_1
       2: aload_2
       3: invokevirtual #41                 // Method iterator:(Lorg/apache/curator/shaded/com/google/common/base/Splitter;Ljava/lang/CharSequence;)Lorg/apache/curator/shaded/com/google/common/base/Splitter$SplittingIterator;
       6: areturn
}
