Compiled from "DefaultAnnotationAttributeExtractor.java"
class org.springframework.core.annotation.DefaultAnnotationAttributeExtractor extends org.springframework.core.annotation.AbstractAliasAwareAnnotationAttributeExtractor<java.lang.annotation.Annotation> {
  org.springframework.core.annotation.DefaultAnnotationAttributeExtractor(java.lang.annotation.Annotation, java.lang.Object);
    Code:
       0: aload_0
       1: aload_1
       2: invokeinterface #1,  1            // InterfaceMethod java/lang/annotation/Annotation.annotationType:()Ljava/lang/Class;
       7: aload_2
       8: aload_1
       9: invokespecial #2                  // Method org/springframework/core/annotation/AbstractAliasAwareAnnotationAttributeExtractor."<init>":(Ljava/lang/Class;Ljava/lang/Object;Ljava/lang/Object;)V
      12: return

  protected java.lang.Object getRawAttributeValue(java.lang.reflect.Method);
    Code:
       0: aload_1
       1: invokestatic  #3                  // Method org/springframework/util/ReflectionUtils.makeAccessible:(Ljava/lang/reflect/Method;)V
       4: aload_1
       5: aload_0
       6: invokevirtual #4                  // Method getSource:()Ljava/lang/Object;
       9: invokestatic  #5                  // Method org/springframework/util/ReflectionUtils.invokeMethod:(Ljava/lang/reflect/Method;Ljava/lang/Object;)Ljava/lang/Object;
      12: areturn

  protected java.lang.Object getRawAttributeValue(java.lang.String);
    Code:
       0: aload_0
       1: invokevirtual #6                  // Method getAnnotationType:()Ljava/lang/Class;
       4: aload_1
       5: invokestatic  #7                  // Method org/springframework/util/ReflectionUtils.findMethod:(Ljava/lang/Class;Ljava/lang/String;)Ljava/lang/reflect/Method;
       8: astore_2
       9: aload_2
      10: ifnull        21
      13: aload_0
      14: aload_2
      15: invokevirtual #8                  // Method getRawAttributeValue:(Ljava/lang/reflect/Method;)Ljava/lang/Object;
      18: goto          22
      21: aconst_null
      22: areturn
}
