Compiled from "MethodVariableAccess.java"
public class net.bytebuddy.implementation.bytecode.member.MethodVariableAccess$OffsetIncrementing implements net.bytebuddy.implementation.bytecode.StackManipulation {
  private final int offset;

  private final int value;

  protected net.bytebuddy.implementation.bytecode.member.MethodVariableAccess$OffsetIncrementing(int, int);
    Code:
       0: aload_0
       1: invokespecial #26                 // Method java/lang/Object."<init>":()V
       4: aload_0
       5: iload_1
       6: putfield      #28                 // Field offset:I
       9: aload_0
      10: iload_2
      11: putfield      #30                 // Field value:I
      14: return

  public boolean isValid();
    Code:
       0: iconst_1
       1: ireturn

  public net.bytebuddy.implementation.bytecode.StackManipulation$Size apply(net.bytebuddy.jar.asm.MethodVisitor, net.bytebuddy.implementation.Implementation$Context);
    Code:
       0: aload_1
       1: aload_0
       2: getfield      #28                 // Field offset:I
       5: aload_0
       6: getfield      #30                 // Field value:I
       9: invokevirtual #41                 // Method net/bytebuddy/jar/asm/MethodVisitor.visitIincInsn:(II)V
      12: new           #17                 // class net/bytebuddy/implementation/bytecode/StackManipulation$Size
      15: dup
      16: iconst_0
      17: iconst_0
      18: invokespecial #43                 // Method net/bytebuddy/implementation/bytecode/StackManipulation$Size."<init>":(II)V
      21: areturn

  public boolean equals(java.lang.Object);
    Code:
       0: aload_1
       1: aload_0
       2: if_acmpne     7
       5: iconst_1
       6: ireturn
       7: aload_1
       8: instanceof    #2                  // class net/bytebuddy/implementation/bytecode/member/MethodVariableAccess$OffsetIncrementing
      11: ifne          16
      14: iconst_0
      15: ireturn
      16: aload_1
      17: checkcast     #2                  // class net/bytebuddy/implementation/bytecode/member/MethodVariableAccess$OffsetIncrementing
      20: astore_2
      21: aload_2
      22: aload_0
      23: invokevirtual #52                 // Method canEqual:(Ljava/lang/Object;)Z
      26: ifne          31
      29: iconst_0
      30: ireturn
      31: aload_0
      32: getfield      #28                 // Field offset:I
      35: aload_2
      36: getfield      #28                 // Field offset:I
      39: if_icmpeq     44
      42: iconst_0
      43: ireturn
      44: aload_0
      45: getfield      #30                 // Field value:I
      48: aload_2
      49: getfield      #30                 // Field value:I
      52: if_icmpeq     57
      55: iconst_0
      56: ireturn
      57: iconst_1
      58: ireturn

  protected boolean canEqual(java.lang.Object);
    Code:
       0: aload_1
       1: instanceof    #2                  // class net/bytebuddy/implementation/bytecode/member/MethodVariableAccess$OffsetIncrementing
       4: ireturn

  public int hashCode();
    Code:
       0: bipush        59
       2: istore_1
       3: iconst_1
       4: istore_2
       5: iload_2
       6: bipush        59
       8: imul
       9: aload_0
      10: getfield      #28                 // Field offset:I
      13: iadd
      14: istore_2
      15: iload_2
      16: bipush        59
      18: imul
      19: aload_0
      20: getfield      #30                 // Field value:I
      23: iadd
      24: istore_2
      25: iload_2
      26: ireturn
}
