Compiled from "AssertionClause.java"
public final class org.apache.camel.component.mock.AssertionClause$PredicateValueBuilder extends org.apache.camel.builder.ValueBuilder {
  final org.apache.camel.component.mock.AssertionClause this$0;

  public org.apache.camel.component.mock.AssertionClause$PredicateValueBuilder(org.apache.camel.component.mock.AssertionClause, org.apache.camel.Expression);
    Code:
       0: aload_0
       1: aload_1
       2: putfield      #14                 // Field this$0:Lorg/apache/camel/component/mock/AssertionClause;
       5: aload_0
       6: aload_2
       7: invokespecial #17                 // Method org/apache/camel/builder/ValueBuilder."<init>":(Lorg/apache/camel/Expression;)V
      10: return

  protected org.apache.camel.Predicate onNewPredicate(org.apache.camel.Predicate);
    Code:
       0: aload_0
       1: aload_1
       2: invokespecial #25                 // Method org/apache/camel/builder/ValueBuilder.onNewPredicate:(Lorg/apache/camel/Predicate;)Lorg/apache/camel/Predicate;
       5: astore_1
       6: aload_0
       7: getfield      #14                 // Field this$0:Lorg/apache/camel/component/mock/AssertionClause;
      10: aload_1
      11: invokevirtual #29                 // Method org/apache/camel/component/mock/AssertionClause.addPredicate:(Lorg/apache/camel/Predicate;)V
      14: aload_1
      15: areturn
}
