Compiled from "Text.java"
final class javolution.text.Text$2 extends javolution.context.ObjectFactory {
  javolution.text.Text$2();
    Code:
       0: aload_0
       1: invokespecial #1                  // Method javolution/context/ObjectFactory."<init>":()V
       4: return

  public java.lang.Object create();
    Code:
       0: new           #2                  // class javolution/text/Text
       3: dup
       4: iconst_1
       5: aconst_null
       6: invokespecial #3                  // Method javolution/text/Text."<init>":(ZLjavolution/text/Text$1;)V
       9: areturn
}
