Compiled from "StandaloneMockMvcBuilder.java"
class org.springframework.test.web.servlet.setup.StandaloneMockMvcBuilder$StaticRequestMappingHandlerMapping extends org.springframework.web.servlet.mvc.method.annotation.RequestMappingHandlerMapping {
  private org.springframework.test.web.servlet.setup.StandaloneMockMvcBuilder$StaticRequestMappingHandlerMapping();
    Code:
       0: aload_0
       1: invokespecial #2                  // Method org/springframework/web/servlet/mvc/method/annotation/RequestMappingHandlerMapping."<init>":()V
       4: return

  public void registerHandlers(java.lang.Object...);
    Code:
       0: aload_1
       1: astore_2
       2: aload_2
       3: arraylength
       4: istore_3
       5: iconst_0
       6: istore        4
       8: iload         4
      10: iload_3
      11: if_icmpge     32
      14: aload_2
      15: iload         4
      17: aaload
      18: astore        5
      20: aload_0
      21: aload         5
      23: invokevirtual #3                  // Method detectHandlerMethods:(Ljava/lang/Object;)V
      26: iinc          4, 1
      29: goto          8
      32: return

  org.springframework.test.web.servlet.setup.StandaloneMockMvcBuilder$StaticRequestMappingHandlerMapping(org.springframework.test.web.servlet.setup.StandaloneMockMvcBuilder$1);
    Code:
       0: aload_0
       1: invokespecial #1                  // Method "<init>":()V
       4: return
}
