Compiled from "StubWebApplicationContext.java"
class org.springframework.test.web.servlet.setup.StubWebApplicationContext$StubBeanFactory extends org.springframework.beans.factory.support.StaticListableBeanFactory implements org.springframework.beans.factory.config.AutowireCapableBeanFactory {
  final org.springframework.test.web.servlet.setup.StubWebApplicationContext this$0;

  private org.springframework.test.web.servlet.setup.StubWebApplicationContext$StubBeanFactory(org.springframework.test.web.servlet.setup.StubWebApplicationContext);
    Code:
       0: aload_0
       1: aload_1
       2: putfield      #2                  // Field this$0:Lorg/springframework/test/web/servlet/setup/StubWebApplicationContext;
       5: aload_0
       6: invokespecial #3                  // Method org/springframework/beans/factory/support/StaticListableBeanFactory."<init>":()V
       9: return

  public java.lang.Object initializeBean(java.lang.Object, java.lang.String) throws org.springframework.beans.BeansException;
    Code:
       0: aload_1
       1: instanceof    #4                  // class org/springframework/context/ApplicationContextAware
       4: ifeq          20
       7: aload_1
       8: checkcast     #4                  // class org/springframework/context/ApplicationContextAware
      11: aload_0
      12: getfield      #2                  // Field this$0:Lorg/springframework/test/web/servlet/setup/StubWebApplicationContext;
      15: invokeinterface #5,  2            // InterfaceMethod org/springframework/context/ApplicationContextAware.setApplicationContext:(Lorg/springframework/context/ApplicationContext;)V
      20: aload_1
      21: areturn

  public <T> T createBean(java.lang.Class<T>);
    Code:
       0: aload_1
       1: invokestatic  #6                  // Method org/springframework/beans/BeanUtils.instantiateClass:(Ljava/lang/Class;)Ljava/lang/Object;
       4: areturn

  public java.lang.Object createBean(java.lang.Class<?>, int, boolean);
    Code:
       0: aload_1
       1: invokestatic  #6                  // Method org/springframework/beans/BeanUtils.instantiateClass:(Ljava/lang/Class;)Ljava/lang/Object;
       4: areturn

  public java.lang.Object autowire(java.lang.Class<?>, int, boolean);
    Code:
       0: aload_1
       1: invokestatic  #6                  // Method org/springframework/beans/BeanUtils.instantiateClass:(Ljava/lang/Class;)Ljava/lang/Object;
       4: areturn

  public void autowireBean(java.lang.Object) throws org.springframework.beans.BeansException;
    Code:
       0: return

  public void autowireBeanProperties(java.lang.Object, int, boolean);
    Code:
       0: return

  public java.lang.Object configureBean(java.lang.Object, java.lang.String);
    Code:
       0: aload_1
       1: areturn

  public <T> org.springframework.beans.factory.config.NamedBeanHolder<T> resolveNamedBean(java.lang.Class<T>) throws org.springframework.beans.BeansException;
    Code:
       0: new           #7                  // class java/lang/UnsupportedOperationException
       3: dup
       4: ldc           #8                  // String Dependency resolution not supported
       6: invokespecial #9                  // Method java/lang/UnsupportedOperationException."<init>":(Ljava/lang/String;)V
       9: athrow

  public java.lang.Object resolveDependency(org.springframework.beans.factory.config.DependencyDescriptor, java.lang.String);
    Code:
       0: new           #7                  // class java/lang/UnsupportedOperationException
       3: dup
       4: ldc           #8                  // String Dependency resolution not supported
       6: invokespecial #9                  // Method java/lang/UnsupportedOperationException."<init>":(Ljava/lang/String;)V
       9: athrow

  public java.lang.Object resolveDependency(org.springframework.beans.factory.config.DependencyDescriptor, java.lang.String, java.util.Set<java.lang.String>, org.springframework.beans.TypeConverter);
    Code:
       0: new           #7                  // class java/lang/UnsupportedOperationException
       3: dup
       4: ldc           #8                  // String Dependency resolution not supported
       6: invokespecial #9                  // Method java/lang/UnsupportedOperationException."<init>":(Ljava/lang/String;)V
       9: athrow

  public void applyBeanPropertyValues(java.lang.Object, java.lang.String) throws org.springframework.beans.BeansException;
    Code:
       0: return

  public java.lang.Object applyBeanPostProcessorsBeforeInitialization(java.lang.Object, java.lang.String);
    Code:
       0: aload_1
       1: areturn

  public java.lang.Object applyBeanPostProcessorsAfterInitialization(java.lang.Object, java.lang.String);
    Code:
       0: aload_1
       1: areturn

  public void destroyBean(java.lang.Object);
    Code:
       0: return

  org.springframework.test.web.servlet.setup.StubWebApplicationContext$StubBeanFactory(org.springframework.test.web.servlet.setup.StubWebApplicationContext, org.springframework.test.web.servlet.setup.StubWebApplicationContext$1);
    Code:
       0: aload_0
       1: aload_1
       2: invokespecial #1                  // Method "<init>":(Lorg/springframework/test/web/servlet/setup/StubWebApplicationContext;)V
       5: return
}
