Compiled from "JsonIOException.java"
public final class org.sonar.api.internal.google.gson.JsonIOException extends org.sonar.api.internal.google.gson.JsonParseException {
  private static final long serialVersionUID;

  public org.sonar.api.internal.google.gson.JsonIOException(java.lang.String);
    Code:
       0: aload_0
       1: aload_1
       2: invokespecial #13                 // Method org/sonar/api/internal/google/gson/JsonParseException."<init>":(Ljava/lang/String;)V
       5: return

  public org.sonar.api.internal.google.gson.JsonIOException(java.lang.String, java.lang.Throwable);
    Code:
       0: aload_0
       1: aload_1
       2: aload_2
       3: invokespecial #20                 // Method org/sonar/api/internal/google/gson/JsonParseException."<init>":(Ljava/lang/String;Ljava/lang/Throwable;)V
       6: return

  public org.sonar.api.internal.google.gson.JsonIOException(java.lang.Throwable);
    Code:
       0: aload_0
       1: aload_1
       2: invokespecial #25                 // Method org/sonar/api/internal/google/gson/JsonParseException."<init>":(Ljava/lang/Throwable;)V
       5: return
}
