Compiled from "ServerSentEventHandler.java"
class io.undertow.server.handlers.sse.ServerSentEventHandler$1 implements org.xnio.ChannelListener<org.xnio.channels.StreamSinkChannel> {
  final io.undertow.server.HttpServerExchange val$exchange;

  final io.undertow.server.handlers.sse.ServerSentEventHandler this$0;

  io.undertow.server.handlers.sse.ServerSentEventHandler$1(io.undertow.server.handlers.sse.ServerSentEventHandler, io.undertow.server.HttpServerExchange);
    Code:
       0: aload_0
       1: aload_1
       2: putfield      #1                  // Field this$0:Lio/undertow/server/handlers/sse/ServerSentEventHandler;
       5: aload_0
       6: aload_2
       7: putfield      #2                  // Field val$exchange:Lio/undertow/server/HttpServerExchange;
      10: aload_0
      11: invokespecial #3                  // Method java/lang/Object."<init>":()V
      14: return

  public void handleEvent(org.xnio.channels.StreamSinkChannel);
    Code:
       0: aload_0
       1: getfield      #1                  // Field this$0:Lio/undertow/server/handlers/sse/ServerSentEventHandler;
       4: aload_1
       5: aload_0
       6: getfield      #2                  // Field val$exchange:Lio/undertow/server/HttpServerExchange;
       9: invokestatic  #4                  // Method io/undertow/server/handlers/sse/ServerSentEventHandler.access$000:(Lio/undertow/server/handlers/sse/ServerSentEventHandler;Lorg/xnio/channels/StreamSinkChannel;Lio/undertow/server/HttpServerExchange;)V
      12: return

  public void handleEvent(java.nio.channels.Channel);
    Code:
       0: aload_0
       1: aload_1
       2: checkcast     #5                  // class org/xnio/channels/StreamSinkChannel
       5: invokevirtual #6                  // Method handleEvent:(Lorg/xnio/channels/StreamSinkChannel;)V
       8: return
}
