Compiled from "RenewingImpl.java"
public class org.opensaml.ws.wstrust.impl.RenewingImpl extends org.opensaml.ws.wstrust.impl.AbstractWSTrustObject implements org.opensaml.ws.wstrust.Renewing {
  private org.opensaml.xml.schema.XSBooleanValue allow;

  private org.opensaml.xml.schema.XSBooleanValue ok;

  public org.opensaml.ws.wstrust.impl.RenewingImpl(java.lang.String, java.lang.String, java.lang.String);
    Code:
       0: aload_0
       1: aload_1
       2: aload_2
       3: aload_3
       4: invokespecial #1                  // Method org/opensaml/ws/wstrust/impl/AbstractWSTrustObject."<init>":(Ljava/lang/String;Ljava/lang/String;Ljava/lang/String;)V
       7: return

  public java.lang.Boolean isAllow();
    Code:
       0: aload_0
       1: getfield      #2                  // Field allow:Lorg/opensaml/xml/schema/XSBooleanValue;
       4: ifnull        15
       7: aload_0
       8: getfield      #2                  // Field allow:Lorg/opensaml/xml/schema/XSBooleanValue;
      11: invokevirtual #3                  // Method org/opensaml/xml/schema/XSBooleanValue.getValue:()Ljava/lang/Boolean;
      14: areturn
      15: getstatic     #4                  // Field java/lang/Boolean.TRUE:Ljava/lang/Boolean;
      18: areturn

  public org.opensaml.xml.schema.XSBooleanValue isAllowXSBoolean();
    Code:
       0: aload_0
       1: getfield      #2                  // Field allow:Lorg/opensaml/xml/schema/XSBooleanValue;
       4: areturn

  public void setAllow(java.lang.Boolean);
    Code:
       0: aload_1
       1: ifnull        31
       4: aload_0
       5: aload_0
       6: aload_0
       7: getfield      #2                  // Field allow:Lorg/opensaml/xml/schema/XSBooleanValue;
      10: new           #5                  // class org/opensaml/xml/schema/XSBooleanValue
      13: dup
      14: aload_1
      15: iconst_0
      16: invokespecial #6                  // Method org/opensaml/xml/schema/XSBooleanValue."<init>":(Ljava/lang/Boolean;Z)V
      19: invokevirtual #7                  // Method prepareForAssignment:(Ljava/lang/Object;Ljava/lang/Object;)Ljava/lang/Object;
      22: checkcast     #5                  // class org/opensaml/xml/schema/XSBooleanValue
      25: putfield      #2                  // Field allow:Lorg/opensaml/xml/schema/XSBooleanValue;
      28: goto          47
      31: aload_0
      32: aload_0
      33: aload_0
      34: getfield      #2                  // Field allow:Lorg/opensaml/xml/schema/XSBooleanValue;
      37: aconst_null
      38: invokevirtual #7                  // Method prepareForAssignment:(Ljava/lang/Object;Ljava/lang/Object;)Ljava/lang/Object;
      41: checkcast     #5                  // class org/opensaml/xml/schema/XSBooleanValue
      44: putfield      #2                  // Field allow:Lorg/opensaml/xml/schema/XSBooleanValue;
      47: return

  public void setAllow(org.opensaml.xml.schema.XSBooleanValue);
    Code:
       0: aload_0
       1: aload_0
       2: aload_0
       3: getfield      #2                  // Field allow:Lorg/opensaml/xml/schema/XSBooleanValue;
       6: aload_1
       7: invokevirtual #7                  // Method prepareForAssignment:(Ljava/lang/Object;Ljava/lang/Object;)Ljava/lang/Object;
      10: checkcast     #5                  // class org/opensaml/xml/schema/XSBooleanValue
      13: putfield      #2                  // Field allow:Lorg/opensaml/xml/schema/XSBooleanValue;
      16: return

  public java.lang.Boolean isOK();
    Code:
       0: aload_0
       1: getfield      #8                  // Field ok:Lorg/opensaml/xml/schema/XSBooleanValue;
       4: ifnull        15
       7: aload_0
       8: getfield      #8                  // Field ok:Lorg/opensaml/xml/schema/XSBooleanValue;
      11: invokevirtual #3                  // Method org/opensaml/xml/schema/XSBooleanValue.getValue:()Ljava/lang/Boolean;
      14: areturn
      15: getstatic     #9                  // Field java/lang/Boolean.FALSE:Ljava/lang/Boolean;
      18: areturn

  public org.opensaml.xml.schema.XSBooleanValue isOKXSBoolean();
    Code:
       0: aload_0
       1: getfield      #8                  // Field ok:Lorg/opensaml/xml/schema/XSBooleanValue;
       4: areturn

  public void setOK(java.lang.Boolean);
    Code:
       0: aload_1
       1: ifnull        31
       4: aload_0
       5: aload_0
       6: aload_0
       7: getfield      #8                  // Field ok:Lorg/opensaml/xml/schema/XSBooleanValue;
      10: new           #5                  // class org/opensaml/xml/schema/XSBooleanValue
      13: dup
      14: aload_1
      15: iconst_0
      16: invokespecial #6                  // Method org/opensaml/xml/schema/XSBooleanValue."<init>":(Ljava/lang/Boolean;Z)V
      19: invokevirtual #7                  // Method prepareForAssignment:(Ljava/lang/Object;Ljava/lang/Object;)Ljava/lang/Object;
      22: checkcast     #5                  // class org/opensaml/xml/schema/XSBooleanValue
      25: putfield      #8                  // Field ok:Lorg/opensaml/xml/schema/XSBooleanValue;
      28: goto          47
      31: aload_0
      32: aload_0
      33: aload_0
      34: getfield      #8                  // Field ok:Lorg/opensaml/xml/schema/XSBooleanValue;
      37: aconst_null
      38: invokevirtual #7                  // Method prepareForAssignment:(Ljava/lang/Object;Ljava/lang/Object;)Ljava/lang/Object;
      41: checkcast     #5                  // class org/opensaml/xml/schema/XSBooleanValue
      44: putfield      #8                  // Field ok:Lorg/opensaml/xml/schema/XSBooleanValue;
      47: return

  public void setOK(org.opensaml.xml.schema.XSBooleanValue);
    Code:
       0: aload_0
       1: aload_0
       2: aload_0
       3: getfield      #8                  // Field ok:Lorg/opensaml/xml/schema/XSBooleanValue;
       6: aload_1
       7: invokevirtual #7                  // Method prepareForAssignment:(Ljava/lang/Object;Ljava/lang/Object;)Ljava/lang/Object;
      10: checkcast     #5                  // class org/opensaml/xml/schema/XSBooleanValue
      13: putfield      #8                  // Field ok:Lorg/opensaml/xml/schema/XSBooleanValue;
      16: return

  public java.util.List<org.opensaml.xml.XMLObject> getOrderedChildren();
    Code:
       0: aconst_null
       1: areturn
}
