Compiled from "BamServerProfileUtils.java"
public class org.wso2.carbon.mediator.bam.config.ui.BamServerProfileUtils {
  private static final org.apache.commons.logging.Log log;

  private org.wso2.carbon.mediator.bam.config.ui.BamServerProfileConfigAdminClient client;

  public org.wso2.carbon.mediator.bam.config.ui.BamServerProfileUtils(java.lang.String, java.lang.String, org.apache.axis2.context.ConfigurationContext, java.util.Locale);
    Code:
       0: aload_0
       1: invokespecial #1                  // Method java/lang/Object."<init>":()V
       4: aload_0
       5: new           #2                  // class org/wso2/carbon/mediator/bam/config/ui/BamServerProfileConfigAdminClient
       8: dup
       9: aload_1
      10: aload_2
      11: aload_3
      12: aload         4
      14: invokespecial #3                  // Method org/wso2/carbon/mediator/bam/config/ui/BamServerProfileConfigAdminClient."<init>":(Ljava/lang/String;Ljava/lang/String;Lorg/apache/axis2/context/ConfigurationContext;Ljava/util/Locale;)V
      17: putfield      #4                  // Field client:Lorg/wso2/carbon/mediator/bam/config/ui/BamServerProfileConfigAdminClient;
      20: goto          62
      23: astore        5
      25: new           #6                  // class java/lang/StringBuilder
      28: dup
      29: invokespecial #7                  // Method java/lang/StringBuilder."<init>":()V
      32: ldc           #8                  // String Error while creating BamServerProfileUtils.
      34: invokevirtual #9                  // Method java/lang/StringBuilder.append:(Ljava/lang/String;)Ljava/lang/StringBuilder;
      37: aload         5
      39: invokevirtual #10                 // Method org/apache/axis2/AxisFault.getMessage:()Ljava/lang/String;
      42: invokevirtual #9                  // Method java/lang/StringBuilder.append:(Ljava/lang/String;)Ljava/lang/StringBuilder;
      45: invokevirtual #11                 // Method java/lang/StringBuilder.toString:()Ljava/lang/String;
      48: astore        6
      50: getstatic     #12                 // Field log:Lorg/apache/commons/logging/Log;
      53: aload         6
      55: aload         5
      57: invokeinterface #13,  3           // InterfaceMethod org/apache/commons/logging/Log.error:(Ljava/lang/Object;Ljava/lang/Throwable;)V
      62: return
    Exception table:
       from    to  target type
           4    20    23   Class org/apache/axis2/AxisFault

  public void addResource(java.lang.String, java.lang.String, java.lang.String, java.lang.String, java.lang.String, java.lang.String, boolean, boolean, java.lang.String, java.lang.String);
    Code:
       0: aload_0
       1: aload         6
       3: invokevirtual #14                 // Method encryptPassword:(Ljava/lang/String;)Ljava/lang/String;
       6: astore        11
       8: iload         7
      10: ifeq          20
      13: ldc           #15                 // String true
      15: astore        12
      17: goto          24
      20: ldc           #16                 // String false
      22: astore        12
      24: iload         8
      26: ifeq          36
      29: ldc           #15                 // String true
      31: astore        13
      33: goto          40
      36: ldc           #16                 // String false
      38: astore        13
      40: new           #17                 // class org/wso2/carbon/mediator/bam/config/ui/StreamConfigListBuilder
      43: dup
      44: invokespecial #18                 // Method org/wso2/carbon/mediator/bam/config/ui/StreamConfigListBuilder."<init>":()V
      47: astore        14
      49: aload         14
      51: aload         9
      53: invokevirtual #19                 // Method org/wso2/carbon/mediator/bam/config/ui/StreamConfigListBuilder.getStreamConfigurationListFromString:(Ljava/lang/String;)Ljava/util/List;
      56: astore        15
      58: new           #20                 // class org/wso2/carbon/mediator/bam/config/BamServerConfigXml
      61: dup
      62: invokespecial #21                 // Method org/wso2/carbon/mediator/bam/config/BamServerConfigXml."<init>":()V
      65: astore        16
      67: aload         16
      69: aload_1
      70: aload_2
      71: aload_3
      72: aload         4
      74: aload         5
      76: aload         11
      78: aload         12
      80: aload         13
      82: aload         15
      84: invokevirtual #22                 // Method org/wso2/carbon/mediator/bam/config/BamServerConfigXml.buildServerProfile:(Ljava/lang/String;Ljava/lang/String;Ljava/lang/String;Ljava/lang/String;Ljava/lang/String;Ljava/lang/String;Ljava/lang/String;Ljava/lang/String;Ljava/util/List;)Lorg/apache/axiom/om/OMElement;
      87: astore        17
      89: aload         17
      91: invokeinterface #23,  1           // InterfaceMethod org/apache/axiom/om/OMElement.toString:()Ljava/lang/String;
      96: astore        18
      98: aload_0
      99: getfield      #4                  // Field client:Lorg/wso2/carbon/mediator/bam/config/ui/BamServerProfileConfigAdminClient;
     102: aload         18
     104: aload_0
     105: aload         10
     107: invokespecial #24                 // Method getRealBamServerProfilePath:(Ljava/lang/String;)Ljava/lang/String;
     110: invokevirtual #25                 // Method org/wso2/carbon/mediator/bam/config/ui/BamServerProfileConfigAdminClient.saveResourceString:(Ljava/lang/String;Ljava/lang/String;)V
     113: goto          155
     116: astore        19
     118: new           #6                  // class java/lang/StringBuilder
     121: dup
     122: invokespecial #7                  // Method java/lang/StringBuilder."<init>":()V
     125: ldc           #27                 // String Error while adding resource.
     127: invokevirtual #9                  // Method java/lang/StringBuilder.append:(Ljava/lang/String;)Ljava/lang/StringBuilder;
     130: aload         19
     132: invokevirtual #28                 // Method java/rmi/RemoteException.getMessage:()Ljava/lang/String;
     135: invokevirtual #9                  // Method java/lang/StringBuilder.append:(Ljava/lang/String;)Ljava/lang/StringBuilder;
     138: invokevirtual #11                 // Method java/lang/StringBuilder.toString:()Ljava/lang/String;
     141: astore        20
     143: getstatic     #12                 // Field log:Lorg/apache/commons/logging/Log;
     146: aload         20
     148: aload         19
     150: invokeinterface #13,  3           // InterfaceMethod org/apache/commons/logging/Log.error:(Ljava/lang/Object;Ljava/lang/Throwable;)V
     155: return
    Exception table:
       from    to  target type
          98   113   116   Class java/rmi/RemoteException

  public org.wso2.carbon.mediator.bam.config.BamServerConfig getResource(java.lang.String);
    Code:
       0: aload_0
       1: getfield      #4                  // Field client:Lorg/wso2/carbon/mediator/bam/config/ui/BamServerProfileConfigAdminClient;
       4: aload_0
       5: aload_1
       6: invokespecial #24                 // Method getRealBamServerProfilePath:(Ljava/lang/String;)Ljava/lang/String;
       9: invokevirtual #29                 // Method org/wso2/carbon/mediator/bam/config/ui/BamServerProfileConfigAdminClient.getResourceString:(Ljava/lang/String;)Ljava/lang/String;
      12: astore_2
      13: new           #30                 // class org/apache/axiom/om/impl/builder/StAXOMBuilder
      16: dup
      17: new           #31                 // class java/io/ByteArrayInputStream
      20: dup
      21: aload_2
      22: ldc           #32                 // String UTF-8
      24: invokestatic  #33                 // Method java/nio/charset/Charset.forName:(Ljava/lang/String;)Ljava/nio/charset/Charset;
      27: invokevirtual #34                 // Method java/lang/String.getBytes:(Ljava/nio/charset/Charset;)[B
      30: invokespecial #35                 // Method java/io/ByteArrayInputStream."<init>":([B)V
      33: invokespecial #36                 // Method org/apache/axiom/om/impl/builder/StAXOMBuilder."<init>":(Ljava/io/InputStream;)V
      36: invokevirtual #37                 // Method org/apache/axiom/om/impl/builder/StAXOMBuilder.getDocumentElement:()Lorg/apache/axiom/om/OMElement;
      39: astore_3
      40: new           #38                 // class org/wso2/carbon/mediator/bam/config/BamServerConfigBuilder
      43: dup
      44: invokespecial #39                 // Method org/wso2/carbon/mediator/bam/config/BamServerConfigBuilder."<init>":()V
      47: astore        4
      49: aload         4
      51: aload_3
      52: invokevirtual #40                 // Method org/wso2/carbon/mediator/bam/config/BamServerConfigBuilder.createBamServerConfig:(Lorg/apache/axiom/om/OMElement;)Z
      55: pop
      56: aload         4
      58: invokevirtual #41                 // Method org/wso2/carbon/mediator/bam/config/BamServerConfigBuilder.getBamServerConfig:()Lorg/wso2/carbon/mediator/bam/config/BamServerConfig;
      61: areturn
      62: astore_2
      63: new           #6                  // class java/lang/StringBuilder
      66: dup
      67: invokespecial #7                  // Method java/lang/StringBuilder."<init>":()V
      70: ldc           #42                 // String Error while getting the resource.
      72: invokevirtual #9                  // Method java/lang/StringBuilder.append:(Ljava/lang/String;)Ljava/lang/StringBuilder;
      75: aload_2
      76: invokevirtual #28                 // Method java/rmi/RemoteException.getMessage:()Ljava/lang/String;
      79: invokevirtual #9                  // Method java/lang/StringBuilder.append:(Ljava/lang/String;)Ljava/lang/StringBuilder;
      82: invokevirtual #11                 // Method java/lang/StringBuilder.toString:()Ljava/lang/String;
      85: astore_3
      86: getstatic     #12                 // Field log:Lorg/apache/commons/logging/Log;
      89: aload_3
      90: aload_2
      91: invokeinterface #13,  3           // InterfaceMethod org/apache/commons/logging/Log.error:(Ljava/lang/Object;Ljava/lang/Throwable;)V
      96: goto          133
      99: astore_2
     100: new           #6                  // class java/lang/StringBuilder
     103: dup
     104: invokespecial #7                  // Method java/lang/StringBuilder."<init>":()V
     107: ldc           #44                 // String Error while creating OMElement from the string.
     109: invokevirtual #9                  // Method java/lang/StringBuilder.append:(Ljava/lang/String;)Ljava/lang/StringBuilder;
     112: aload_2
     113: invokevirtual #45                 // Method javax/xml/stream/XMLStreamException.getMessage:()Ljava/lang/String;
     116: invokevirtual #9                  // Method java/lang/StringBuilder.append:(Ljava/lang/String;)Ljava/lang/StringBuilder;
     119: invokevirtual #11                 // Method java/lang/StringBuilder.toString:()Ljava/lang/String;
     122: astore_3
     123: getstatic     #12                 // Field log:Lorg/apache/commons/logging/Log;
     126: aload_3
     127: aload_2
     128: invokeinterface #13,  3           // InterfaceMethod org/apache/commons/logging/Log.error:(Ljava/lang/Object;Ljava/lang/Throwable;)V
     133: aconst_null
     134: areturn
    Exception table:
       from    to  target type
           0    61    62   Class java/rmi/RemoteException
           0    61    99   Class javax/xml/stream/XMLStreamException

  public boolean resourceAlreadyExists(java.lang.String);
    Code:
       0: aload_0
       1: getfield      #4                  // Field client:Lorg/wso2/carbon/mediator/bam/config/ui/BamServerProfileConfigAdminClient;
       4: aload_0
       5: aload_1
       6: invokespecial #24                 // Method getRealBamServerProfilePath:(Ljava/lang/String;)Ljava/lang/String;
       9: invokevirtual #46                 // Method org/wso2/carbon/mediator/bam/config/ui/BamServerProfileConfigAdminClient.resourceAlreadyExists:(Ljava/lang/String;)Z
      12: ireturn
      13: astore_2
      14: new           #6                  // class java/lang/StringBuilder
      17: dup
      18: invokespecial #7                  // Method java/lang/StringBuilder."<init>":()V
      21: ldc           #47                 // String Error while checking the resource.
      23: invokevirtual #9                  // Method java/lang/StringBuilder.append:(Ljava/lang/String;)Ljava/lang/StringBuilder;
      26: aload_2
      27: invokevirtual #28                 // Method java/rmi/RemoteException.getMessage:()Ljava/lang/String;
      30: invokevirtual #9                  // Method java/lang/StringBuilder.append:(Ljava/lang/String;)Ljava/lang/StringBuilder;
      33: invokevirtual #11                 // Method java/lang/StringBuilder.toString:()Ljava/lang/String;
      36: astore_3
      37: getstatic     #12                 // Field log:Lorg/apache/commons/logging/Log;
      40: aload_3
      41: aload_2
      42: invokeinterface #13,  3           // InterfaceMethod org/apache/commons/logging/Log.error:(Ljava/lang/Object;Ljava/lang/Throwable;)V
      47: iconst_1
      48: ireturn
    Exception table:
       from    to  target type
           0    12    13   Class java/rmi/RemoteException

  public void addCollection(java.lang.String);
    Code:
       0: aload_0
       1: getfield      #4                  // Field client:Lorg/wso2/carbon/mediator/bam/config/ui/BamServerProfileConfigAdminClient;
       4: aload_1
       5: invokevirtual #48                 // Method org/wso2/carbon/mediator/bam/config/ui/BamServerProfileConfigAdminClient.addCollection:(Ljava/lang/String;)Z
       8: pop
       9: goto          46
      12: astore_2
      13: new           #6                  // class java/lang/StringBuilder
      16: dup
      17: invokespecial #7                  // Method java/lang/StringBuilder."<init>":()V
      20: ldc           #49                 // String Error while adding the collection.
      22: invokevirtual #9                  // Method java/lang/StringBuilder.append:(Ljava/lang/String;)Ljava/lang/StringBuilder;
      25: aload_2
      26: invokevirtual #28                 // Method java/rmi/RemoteException.getMessage:()Ljava/lang/String;
      29: invokevirtual #9                  // Method java/lang/StringBuilder.append:(Ljava/lang/String;)Ljava/lang/StringBuilder;
      32: invokevirtual #11                 // Method java/lang/StringBuilder.toString:()Ljava/lang/String;
      35: astore_3
      36: getstatic     #12                 // Field log:Lorg/apache/commons/logging/Log;
      39: aload_3
      40: aload_2
      41: invokeinterface #13,  3           // InterfaceMethod org/apache/commons/logging/Log.error:(Ljava/lang/Object;Ljava/lang/Throwable;)V
      46: return
    Exception table:
       from    to  target type
           0     9    12   Class java/rmi/RemoteException

  public boolean removeResource(java.lang.String);
    Code:
       0: aload_0
       1: getfield      #4                  // Field client:Lorg/wso2/carbon/mediator/bam/config/ui/BamServerProfileConfigAdminClient;
       4: aload_1
       5: invokevirtual #50                 // Method org/wso2/carbon/mediator/bam/config/ui/BamServerProfileConfigAdminClient.removeResource:(Ljava/lang/String;)Z
       8: ireturn
       9: astore_2
      10: new           #6                  // class java/lang/StringBuilder
      13: dup
      14: invokespecial #7                  // Method java/lang/StringBuilder."<init>":()V
      17: ldc           #51                 // String Error while removing the resource.
      19: invokevirtual #9                  // Method java/lang/StringBuilder.append:(Ljava/lang/String;)Ljava/lang/StringBuilder;
      22: aload_2
      23: invokevirtual #28                 // Method java/rmi/RemoteException.getMessage:()Ljava/lang/String;
      26: invokevirtual #9                  // Method java/lang/StringBuilder.append:(Ljava/lang/String;)Ljava/lang/StringBuilder;
      29: invokevirtual #11                 // Method java/lang/StringBuilder.toString:()Ljava/lang/String;
      32: astore_3
      33: getstatic     #12                 // Field log:Lorg/apache/commons/logging/Log;
      36: aload_3
      37: aload_2
      38: invokeinterface #13,  3           // InterfaceMethod org/apache/commons/logging/Log.error:(Ljava/lang/Object;Ljava/lang/Throwable;)V
      43: iconst_0
      44: ireturn
    Exception table:
       from    to  target type
           0     8     9   Class java/rmi/RemoteException

  public java.lang.String encryptPassword(java.lang.String);
    Code:
       0: aload_0
       1: getfield      #4                  // Field client:Lorg/wso2/carbon/mediator/bam/config/ui/BamServerProfileConfigAdminClient;
       4: aload_1
       5: invokevirtual #52                 // Method org/wso2/carbon/mediator/bam/config/ui/BamServerProfileConfigAdminClient.encryptAndBase64Encode:(Ljava/lang/String;)Ljava/lang/String;
       8: areturn
       9: astore_2
      10: new           #6                  // class java/lang/StringBuilder
      13: dup
      14: invokespecial #7                  // Method java/lang/StringBuilder."<init>":()V
      17: ldc           #53                 // String Error while encrypting the password.
      19: invokevirtual #9                  // Method java/lang/StringBuilder.append:(Ljava/lang/String;)Ljava/lang/StringBuilder;
      22: aload_2
      23: invokevirtual #28                 // Method java/rmi/RemoteException.getMessage:()Ljava/lang/String;
      26: invokevirtual #9                  // Method java/lang/StringBuilder.append:(Ljava/lang/String;)Ljava/lang/StringBuilder;
      29: invokevirtual #11                 // Method java/lang/StringBuilder.toString:()Ljava/lang/String;
      32: astore_3
      33: getstatic     #12                 // Field log:Lorg/apache/commons/logging/Log;
      36: aload_3
      37: aload_2
      38: invokeinterface #13,  3           // InterfaceMethod org/apache/commons/logging/Log.error:(Ljava/lang/Object;Ljava/lang/Throwable;)V
      43: ldc           #54                 // String
      45: areturn
    Exception table:
       from    to  target type
           0     8     9   Class java/rmi/RemoteException

  public java.lang.String decryptPassword(java.lang.String);
    Code:
       0: aload_0
       1: getfield      #4                  // Field client:Lorg/wso2/carbon/mediator/bam/config/ui/BamServerProfileConfigAdminClient;
       4: aload_1
       5: invokevirtual #55                 // Method org/wso2/carbon/mediator/bam/config/ui/BamServerProfileConfigAdminClient.base64DecodeAndDecrypt:(Ljava/lang/String;)Ljava/lang/String;
       8: areturn
       9: astore_2
      10: new           #6                  // class java/lang/StringBuilder
      13: dup
      14: invokespecial #7                  // Method java/lang/StringBuilder."<init>":()V
      17: ldc           #56                 // String Error while decrypting the password.
      19: invokevirtual #9                  // Method java/lang/StringBuilder.append:(Ljava/lang/String;)Ljava/lang/StringBuilder;
      22: aload_2
      23: invokevirtual #28                 // Method java/rmi/RemoteException.getMessage:()Ljava/lang/String;
      26: invokevirtual #9                  // Method java/lang/StringBuilder.append:(Ljava/lang/String;)Ljava/lang/StringBuilder;
      29: invokevirtual #11                 // Method java/lang/StringBuilder.toString:()Ljava/lang/String;
      32: astore_3
      33: getstatic     #12                 // Field log:Lorg/apache/commons/logging/Log;
      36: aload_3
      37: aload_2
      38: invokeinterface #13,  3           // InterfaceMethod org/apache/commons/logging/Log.error:(Ljava/lang/Object;Ljava/lang/Throwable;)V
      43: ldc           #54                 // String
      45: areturn
    Exception table:
       from    to  target type
           0     8     9   Class java/rmi/RemoteException

  public java.lang.String getStreamConfigurationListString(org.wso2.carbon.mediator.bam.config.stream.StreamConfiguration);
    Code:
       0: new           #6                  // class java/lang/StringBuilder
       3: dup
       4: ldc           #54                 // String
       6: invokespecial #57                 // Method java/lang/StringBuilder."<init>":(Ljava/lang/String;)V
       9: astore_2
      10: aload_1
      11: ifnull        280
      14: aload_1
      15: invokevirtual #58                 // Method org/wso2/carbon/mediator/bam/config/stream/StreamConfiguration.getProperties:()Ljava/util/List;
      18: astore_3
      19: aload_3
      20: invokeinterface #59,  1           // InterfaceMethod java/util/List.iterator:()Ljava/util/Iterator;
      25: astore        4
      27: aload         4
      29: invokeinterface #60,  1           // InterfaceMethod java/util/Iterator.hasNext:()Z
      34: ifeq          138
      37: aload         4
      39: invokeinterface #61,  1           // InterfaceMethod java/util/Iterator.next:()Ljava/lang/Object;
      44: checkcast     #62                 // class org/wso2/carbon/mediator/bam/config/stream/Property
      47: astore        5
      49: aload_2
      50: new           #6                  // class java/lang/StringBuilder
      53: dup
      54: invokespecial #7                  // Method java/lang/StringBuilder."<init>":()V
      57: aload         5
      59: invokevirtual #63                 // Method org/wso2/carbon/mediator/bam/config/stream/Property.getKey:()Ljava/lang/String;
      62: invokevirtual #9                  // Method java/lang/StringBuilder.append:(Ljava/lang/String;)Ljava/lang/StringBuilder;
      65: ldc           #64                 // String ::
      67: invokevirtual #9                  // Method java/lang/StringBuilder.append:(Ljava/lang/String;)Ljava/lang/StringBuilder;
      70: aload         5
      72: invokevirtual #65                 // Method org/wso2/carbon/mediator/bam/config/stream/Property.getValue:()Ljava/lang/String;
      75: invokevirtual #9                  // Method java/lang/StringBuilder.append:(Ljava/lang/String;)Ljava/lang/StringBuilder;
      78: ldc           #64                 // String ::
      80: invokevirtual #9                  // Method java/lang/StringBuilder.append:(Ljava/lang/String;)Ljava/lang/StringBuilder;
      83: aload         5
      85: invokevirtual #66                 // Method org/wso2/carbon/mediator/bam/config/stream/Property.getType:()Ljava/lang/String;
      88: invokevirtual #9                  // Method java/lang/StringBuilder.append:(Ljava/lang/String;)Ljava/lang/StringBuilder;
      91: ldc           #64                 // String ::
      93: invokevirtual #9                  // Method java/lang/StringBuilder.append:(Ljava/lang/String;)Ljava/lang/StringBuilder;
      96: invokevirtual #11                 // Method java/lang/StringBuilder.toString:()Ljava/lang/String;
      99: invokevirtual #9                  // Method java/lang/StringBuilder.append:(Ljava/lang/String;)Ljava/lang/StringBuilder;
     102: pop
     103: aload         5
     105: invokevirtual #67                 // Method org/wso2/carbon/mediator/bam/config/stream/Property.isExpression:()Z
     108: ifeq          121
     111: aload_2
     112: ldc           #68                 // String expression
     114: invokevirtual #9                  // Method java/lang/StringBuilder.append:(Ljava/lang/String;)Ljava/lang/StringBuilder;
     117: pop
     118: goto          128
     121: aload_2
     122: ldc           #69                 // String value
     124: invokevirtual #9                  // Method java/lang/StringBuilder.append:(Ljava/lang/String;)Ljava/lang/StringBuilder;
     127: pop
     128: aload_2
     129: ldc           #70                 // String ;
     131: invokevirtual #9                  // Method java/lang/StringBuilder.append:(Ljava/lang/String;)Ljava/lang/StringBuilder;
     134: pop
     135: goto          27
     138: aload_2
     139: ldc           #71                 // String ^
     141: invokevirtual #9                  // Method java/lang/StringBuilder.append:(Ljava/lang/String;)Ljava/lang/StringBuilder;
     144: pop
     145: aload_1
     146: invokevirtual #72                 // Method org/wso2/carbon/mediator/bam/config/stream/StreamConfiguration.getEntries:()Ljava/util/List;
     149: astore        4
     151: aload         4
     153: invokeinterface #73,  1           // InterfaceMethod java/util/List.size:()I
     158: iconst_2
     159: if_icmpne     172
     162: aload_2
     163: ldc           #74                 // String dump;dump
     165: invokevirtual #9                  // Method java/lang/StringBuilder.append:(Ljava/lang/String;)Ljava/lang/StringBuilder;
     168: pop
     169: goto          275
     172: aload         4
     174: invokeinterface #73,  1           // InterfaceMethod java/util/List.size:()I
     179: iconst_1
     180: if_icmpne     215
     183: aload         4
     185: iconst_0
     186: invokeinterface #75,  2           // InterfaceMethod java/util/List.get:(I)Ljava/lang/Object;
     191: checkcast     #76                 // class org/wso2/carbon/mediator/bam/config/stream/StreamEntry
     194: invokevirtual #77                 // Method org/wso2/carbon/mediator/bam/config/stream/StreamEntry.getValue:()Ljava/lang/String;
     197: ldc           #78                 // String $SOAPHeader
     199: invokevirtual #79                 // Method java/lang/String.equals:(Ljava/lang/Object;)Z
     202: ifeq          215
     205: aload_2
     206: ldc           #80                 // String dump;notDump
     208: invokevirtual #9                  // Method java/lang/StringBuilder.append:(Ljava/lang/String;)Ljava/lang/StringBuilder;
     211: pop
     212: goto          275
     215: aload         4
     217: invokeinterface #73,  1           // InterfaceMethod java/util/List.size:()I
     222: iconst_1
     223: if_icmpne     258
     226: aload         4
     228: iconst_0
     229: invokeinterface #75,  2           // InterfaceMethod java/util/List.get:(I)Ljava/lang/Object;
     234: checkcast     #76                 // class org/wso2/carbon/mediator/bam/config/stream/StreamEntry
     237: invokevirtual #77                 // Method org/wso2/carbon/mediator/bam/config/stream/StreamEntry.getValue:()Ljava/lang/String;
     240: ldc           #81                 // String $SOAPBody
     242: invokevirtual #79                 // Method java/lang/String.equals:(Ljava/lang/Object;)Z
     245: ifeq          258
     248: aload_2
     249: ldc           #82                 // String notDump;dump
     251: invokevirtual #9                  // Method java/lang/StringBuilder.append:(Ljava/lang/String;)Ljava/lang/StringBuilder;
     254: pop
     255: goto          275
     258: aload         4
     260: invokeinterface #73,  1           // InterfaceMethod java/util/List.size:()I
     265: ifne          275
     268: aload_2
     269: ldc           #83                 // String notDump;notDump
     271: invokevirtual #9                  // Method java/lang/StringBuilder.append:(Ljava/lang/String;)Ljava/lang/StringBuilder;
     274: pop
     275: aload_2
     276: invokevirtual #11                 // Method java/lang/StringBuilder.toString:()Ljava/lang/String;
     279: areturn
     280: ldc           #54                 // String
     282: areturn

  private java.lang.String getRealBamServerProfilePath(java.lang.String);
    Code:
       0: aload_1
       1: ifnull        41
       4: aload_1
       5: ldc           #64                 // String ::
       7: invokevirtual #84                 // Method java/lang/String.split:(Ljava/lang/String;)[Ljava/lang/String;
      10: iconst_0
      11: aaload
      12: astore_2
      13: aload_0
      14: aload_2
      15: invokevirtual #85                 // Method isNotNullOrEmpty:(Ljava/lang/String;)Z
      18: ifeq          39
      21: aload_2
      22: ldc           #86                 // String conf
      24: invokevirtual #79                 // Method java/lang/String.equals:(Ljava/lang/Object;)Z
      27: ifeq          39
      30: aload_1
      31: ldc           #64                 // String ::
      33: invokevirtual #84                 // Method java/lang/String.split:(Ljava/lang/String;)[Ljava/lang/String;
      36: iconst_1
      37: aaload
      38: areturn
      39: aload_1
      40: areturn
      41: aload_1
      42: areturn

  public boolean isNotNullOrEmpty(java.lang.String);
    Code:
       0: aload_1
       1: ifnull        17
       4: aload_1
       5: ldc           #54                 // String
       7: invokevirtual #79                 // Method java/lang/String.equals:(Ljava/lang/Object;)Z
      10: ifne          17
      13: iconst_1
      14: goto          18
      17: iconst_0
      18: ireturn

  static {};
    Code:
       0: ldc           #87                 // class org/wso2/carbon/mediator/bam/config/ui/BamServerProfileUtils
       2: invokestatic  #88                 // Method org/apache/commons/logging/LogFactory.getLog:(Ljava/lang/Class;)Lorg/apache/commons/logging/Log;
       5: putstatic     #12                 // Field log:Lorg/apache/commons/logging/Log;
       8: return
}
