Compiled from "S2iBuildConfigAdapter.java"
public class io.dekorate.s2i.adapter.S2iBuildConfigAdapter {
  public io.dekorate.s2i.adapter.S2iBuildConfigAdapter();
    Code:
       0: aload_0
       1: invokespecial #1                  // Method java/lang/Object."<init>":()V
       4: return

  public static io.dekorate.s2i.config.S2iBuildConfig adapt(io.dekorate.s2i.annotation.S2iBuild);
    Code:
       0: aload_0
       1: invokestatic  #2                  // Method newBuilder:(Lio/dekorate/s2i/annotation/S2iBuild;)Lio/dekorate/s2i/config/S2iBuildConfigBuilder;
       4: invokevirtual #3                  // Method io/dekorate/s2i/config/S2iBuildConfigBuilder.build:()Lio/dekorate/s2i/config/EditableS2iBuildConfig;
       7: areturn

  public static io.dekorate.s2i.config.S2iBuildConfigBuilder newBuilder(io.dekorate.s2i.annotation.S2iBuild);
    Code:
       0: new           #4                  // class io/dekorate/s2i/config/S2iBuildConfigBuilder
       3: dup
       4: new           #5                  // class io/dekorate/s2i/config/S2iBuildConfig
       7: dup
       8: aconst_null
       9: aconst_null
      10: aload_0
      11: invokeinterface #6,  1            // InterfaceMethod io/dekorate/s2i/annotation/S2iBuild.registry:()Ljava/lang/String;
      16: aload_0
      17: invokeinterface #7,  1            // InterfaceMethod io/dekorate/s2i/annotation/S2iBuild.group:()Ljava/lang/String;
      22: aload_0
      23: invokeinterface #8,  1            // InterfaceMethod io/dekorate/s2i/annotation/S2iBuild.name:()Ljava/lang/String;
      28: aload_0
      29: invokeinterface #9,  1            // InterfaceMethod io/dekorate/s2i/annotation/S2iBuild.version:()Ljava/lang/String;
      34: aload_0
      35: invokeinterface #10,  1           // InterfaceMethod io/dekorate/s2i/annotation/S2iBuild.image:()Ljava/lang/String;
      40: aload_0
      41: invokeinterface #11,  1           // InterfaceMethod io/dekorate/s2i/annotation/S2iBuild.dockerFile:()Ljava/lang/String;
      46: aload_0
      47: invokeinterface #12,  1           // InterfaceMethod io/dekorate/s2i/annotation/S2iBuild.autoBuildEnabled:()Z
      52: aload_0
      53: invokeinterface #13,  1           // InterfaceMethod io/dekorate/s2i/annotation/S2iBuild.autoPushEnabled:()Z
      58: aload_0
      59: invokeinterface #14,  1           // InterfaceMethod io/dekorate/s2i/annotation/S2iBuild.enabled:()Z
      64: aload_0
      65: invokeinterface #15,  1           // InterfaceMethod io/dekorate/s2i/annotation/S2iBuild.builderImage:()Ljava/lang/String;
      70: aload_0
      71: invokeinterface #16,  1           // InterfaceMethod io/dekorate/s2i/annotation/S2iBuild.buildEnvVars:()[Lio/dekorate/kubernetes/annotation/Env;
      76: invokestatic  #17                 // Method java/util/Arrays.asList:([Ljava/lang/Object;)Ljava/util/List;
      79: invokeinterface #18,  1           // InterfaceMethod java/util/List.stream:()Ljava/util/stream/Stream;
      84: invokedynamic #19,  0             // InvokeDynamic #0:apply:()Ljava/util/function/Function;
      89: invokeinterface #20,  2           // InterfaceMethod java/util/stream/Stream.map:(Ljava/util/function/Function;)Ljava/util/stream/Stream;
      94: invokestatic  #21                 // Method java/util/stream/Collectors.toList:()Ljava/util/stream/Collector;
      97: invokeinterface #22,  2           // InterfaceMethod java/util/stream/Stream.collect:(Ljava/util/stream/Collector;)Ljava/lang/Object;
     102: checkcast     #23                 // class java/util/List
     105: iconst_0
     106: anewarray     #24                 // class io/dekorate/kubernetes/config/Env
     109: invokeinterface #25,  2           // InterfaceMethod java/util/List.toArray:([Ljava/lang/Object;)[Ljava/lang/Object;
     114: checkcast     #26                 // class "[Lio/dekorate/kubernetes/config/Env;"
     117: aload_0
     118: invokeinterface #27,  1           // InterfaceMethod io/dekorate/s2i/annotation/S2iBuild.autoDeployEnabled:()Z
     123: invokespecial #28                 // Method io/dekorate/s2i/config/S2iBuildConfig."<init>":(Lio/dekorate/project/Project;Ljava/util/Map;Ljava/lang/String;Ljava/lang/String;Ljava/lang/String;Ljava/lang/String;Ljava/lang/String;Ljava/lang/String;ZZZLjava/lang/String;[Lio/dekorate/kubernetes/config/Env;Z)V
     126: invokespecial #29                 // Method io/dekorate/s2i/config/S2iBuildConfigBuilder."<init>":(Lio/dekorate/s2i/config/S2iBuildConfig;)V
     129: areturn

  public static io.dekorate.s2i.config.S2iBuildConfig adapt(java.util.Map);
    Code:
       0: new           #5                  // class io/dekorate/s2i/config/S2iBuildConfig
       3: dup
       4: aconst_null
       5: aconst_null
       6: aload_0
       7: instanceof    #30                 // class java/util/Map
      10: ifeq          26
      13: aload_0
      14: ldc           #31                 // String registry
      16: ldc           #32                 // String
      18: invokeinterface #33,  3           // InterfaceMethod java/util/Map.getOrDefault:(Ljava/lang/Object;Ljava/lang/Object;)Ljava/lang/Object;
      23: goto          28
      26: ldc           #32                 // String
      28: checkcast     #34                 // class java/lang/String
      31: checkcast     #34                 // class java/lang/String
      34: aload_0
      35: instanceof    #30                 // class java/util/Map
      38: ifeq          54
      41: aload_0
      42: ldc           #35                 // String group
      44: ldc           #32                 // String
      46: invokeinterface #33,  3           // InterfaceMethod java/util/Map.getOrDefault:(Ljava/lang/Object;Ljava/lang/Object;)Ljava/lang/Object;
      51: goto          56
      54: ldc           #32                 // String
      56: checkcast     #34                 // class java/lang/String
      59: checkcast     #34                 // class java/lang/String
      62: aload_0
      63: instanceof    #30                 // class java/util/Map
      66: ifeq          82
      69: aload_0
      70: ldc           #36                 // String name
      72: ldc           #32                 // String
      74: invokeinterface #33,  3           // InterfaceMethod java/util/Map.getOrDefault:(Ljava/lang/Object;Ljava/lang/Object;)Ljava/lang/Object;
      79: goto          84
      82: ldc           #32                 // String
      84: checkcast     #34                 // class java/lang/String
      87: checkcast     #34                 // class java/lang/String
      90: aload_0
      91: instanceof    #30                 // class java/util/Map
      94: ifeq          110
      97: aload_0
      98: ldc           #37                 // String version
     100: ldc           #32                 // String
     102: invokeinterface #33,  3           // InterfaceMethod java/util/Map.getOrDefault:(Ljava/lang/Object;Ljava/lang/Object;)Ljava/lang/Object;
     107: goto          112
     110: ldc           #32                 // String
     112: checkcast     #34                 // class java/lang/String
     115: checkcast     #34                 // class java/lang/String
     118: aload_0
     119: instanceof    #30                 // class java/util/Map
     122: ifeq          138
     125: aload_0
     126: ldc           #38                 // String image
     128: ldc           #32                 // String
     130: invokeinterface #33,  3           // InterfaceMethod java/util/Map.getOrDefault:(Ljava/lang/Object;Ljava/lang/Object;)Ljava/lang/Object;
     135: goto          140
     138: ldc           #32                 // String
     140: checkcast     #34                 // class java/lang/String
     143: checkcast     #34                 // class java/lang/String
     146: aload_0
     147: instanceof    #30                 // class java/util/Map
     150: ifeq          166
     153: aload_0
     154: ldc           #39                 // String dockerFile
     156: ldc           #40                 // String Dockerfile
     158: invokeinterface #33,  3           // InterfaceMethod java/util/Map.getOrDefault:(Ljava/lang/Object;Ljava/lang/Object;)Ljava/lang/Object;
     163: goto          168
     166: ldc           #40                 // String Dockerfile
     168: checkcast     #34                 // class java/lang/String
     171: checkcast     #34                 // class java/lang/String
     174: aload_0
     175: instanceof    #30                 // class java/util/Map
     178: ifeq          194
     181: aload_0
     182: ldc           #41                 // String autoBuildEnabled
     184: ldc           #42                 // String false
     186: invokeinterface #33,  3           // InterfaceMethod java/util/Map.getOrDefault:(Ljava/lang/Object;Ljava/lang/Object;)Ljava/lang/Object;
     191: goto          196
     194: ldc           #42                 // String false
     196: invokestatic  #43                 // Method java/lang/String.valueOf:(Ljava/lang/Object;)Ljava/lang/String;
     199: invokestatic  #44                 // Method java/lang/Boolean.parseBoolean:(Ljava/lang/String;)Z
     202: aload_0
     203: instanceof    #30                 // class java/util/Map
     206: ifeq          222
     209: aload_0
     210: ldc           #45                 // String autoPushEnabled
     212: ldc           #42                 // String false
     214: invokeinterface #33,  3           // InterfaceMethod java/util/Map.getOrDefault:(Ljava/lang/Object;Ljava/lang/Object;)Ljava/lang/Object;
     219: goto          224
     222: ldc           #42                 // String false
     224: invokestatic  #43                 // Method java/lang/String.valueOf:(Ljava/lang/Object;)Ljava/lang/String;
     227: invokestatic  #44                 // Method java/lang/Boolean.parseBoolean:(Ljava/lang/String;)Z
     230: aload_0
     231: instanceof    #30                 // class java/util/Map
     234: ifeq          250
     237: aload_0
     238: ldc           #46                 // String enabled
     240: ldc           #47                 // String true
     242: invokeinterface #33,  3           // InterfaceMethod java/util/Map.getOrDefault:(Ljava/lang/Object;Ljava/lang/Object;)Ljava/lang/Object;
     247: goto          252
     250: ldc           #47                 // String true
     252: invokestatic  #43                 // Method java/lang/String.valueOf:(Ljava/lang/Object;)Ljava/lang/String;
     255: invokestatic  #44                 // Method java/lang/Boolean.parseBoolean:(Ljava/lang/String;)Z
     258: aload_0
     259: instanceof    #30                 // class java/util/Map
     262: ifeq          278
     265: aload_0
     266: ldc           #48                 // String builderImage
     268: ldc           #49                 // String fabric8/s2i-java:2.3
     270: invokeinterface #33,  3           // InterfaceMethod java/util/Map.getOrDefault:(Ljava/lang/Object;Ljava/lang/Object;)Ljava/lang/Object;
     275: goto          280
     278: ldc           #49                 // String fabric8/s2i-java:2.3
     280: checkcast     #34                 // class java/lang/String
     283: checkcast     #34                 // class java/lang/String
     286: aload_0
     287: instanceof    #30                 // class java/util/Map
     290: ifeq          308
     293: aload_0
     294: ldc           #50                 // String buildEnvVars
     296: iconst_0
     297: anewarray     #30                 // class java/util/Map
     300: invokeinterface #33,  3           // InterfaceMethod java/util/Map.getOrDefault:(Ljava/lang/Object;Ljava/lang/Object;)Ljava/lang/Object;
     305: goto          312
     308: iconst_0
     309: anewarray     #30                 // class java/util/Map
     312: checkcast     #51                 // class "[Ljava/util/Map;"
     315: checkcast     #51                 // class "[Ljava/util/Map;"
     318: invokestatic  #52                 // Method java/util/Arrays.stream:([Ljava/lang/Object;)Ljava/util/stream/Stream;
     321: invokedynamic #53,  0             // InvokeDynamic #1:apply:()Ljava/util/function/Function;
     326: invokeinterface #20,  2           // InterfaceMethod java/util/stream/Stream.map:(Ljava/util/function/Function;)Ljava/util/stream/Stream;
     331: invokedynamic #54,  0             // InvokeDynamic #2:apply:()Ljava/util/function/IntFunction;
     336: invokeinterface #55,  2           // InterfaceMethod java/util/stream/Stream.toArray:(Ljava/util/function/IntFunction;)[Ljava/lang/Object;
     341: checkcast     #26                 // class "[Lio/dekorate/kubernetes/config/Env;"
     344: aload_0
     345: instanceof    #30                 // class java/util/Map
     348: ifeq          364
     351: aload_0
     352: ldc           #56                 // String autoDeployEnabled
     354: ldc           #42                 // String false
     356: invokeinterface #33,  3           // InterfaceMethod java/util/Map.getOrDefault:(Ljava/lang/Object;Ljava/lang/Object;)Ljava/lang/Object;
     361: goto          366
     364: ldc           #42                 // String false
     366: invokestatic  #43                 // Method java/lang/String.valueOf:(Ljava/lang/Object;)Ljava/lang/String;
     369: invokestatic  #44                 // Method java/lang/Boolean.parseBoolean:(Ljava/lang/String;)Z
     372: invokespecial #28                 // Method io/dekorate/s2i/config/S2iBuildConfig."<init>":(Lio/dekorate/project/Project;Ljava/util/Map;Ljava/lang/String;Ljava/lang/String;Ljava/lang/String;Ljava/lang/String;Ljava/lang/String;Ljava/lang/String;ZZZLjava/lang/String;[Lio/dekorate/kubernetes/config/Env;Z)V
     375: areturn

  public static io.dekorate.s2i.config.S2iBuildConfigBuilder newBuilder(java.util.Map);
    Code:
       0: new           #4                  // class io/dekorate/s2i/config/S2iBuildConfigBuilder
       3: dup
       4: new           #5                  // class io/dekorate/s2i/config/S2iBuildConfig
       7: dup
       8: aconst_null
       9: aconst_null
      10: aload_0
      11: instanceof    #30                 // class java/util/Map
      14: ifeq          30
      17: aload_0
      18: ldc           #31                 // String registry
      20: ldc           #32                 // String
      22: invokeinterface #33,  3           // InterfaceMethod java/util/Map.getOrDefault:(Ljava/lang/Object;Ljava/lang/Object;)Ljava/lang/Object;
      27: goto          32
      30: ldc           #32                 // String
      32: checkcast     #34                 // class java/lang/String
      35: checkcast     #34                 // class java/lang/String
      38: aload_0
      39: instanceof    #30                 // class java/util/Map
      42: ifeq          58
      45: aload_0
      46: ldc           #35                 // String group
      48: ldc           #32                 // String
      50: invokeinterface #33,  3           // InterfaceMethod java/util/Map.getOrDefault:(Ljava/lang/Object;Ljava/lang/Object;)Ljava/lang/Object;
      55: goto          60
      58: ldc           #32                 // String
      60: checkcast     #34                 // class java/lang/String
      63: checkcast     #34                 // class java/lang/String
      66: aload_0
      67: instanceof    #30                 // class java/util/Map
      70: ifeq          86
      73: aload_0
      74: ldc           #36                 // String name
      76: ldc           #32                 // String
      78: invokeinterface #33,  3           // InterfaceMethod java/util/Map.getOrDefault:(Ljava/lang/Object;Ljava/lang/Object;)Ljava/lang/Object;
      83: goto          88
      86: ldc           #32                 // String
      88: checkcast     #34                 // class java/lang/String
      91: checkcast     #34                 // class java/lang/String
      94: aload_0
      95: instanceof    #30                 // class java/util/Map
      98: ifeq          114
     101: aload_0
     102: ldc           #37                 // String version
     104: ldc           #32                 // String
     106: invokeinterface #33,  3           // InterfaceMethod java/util/Map.getOrDefault:(Ljava/lang/Object;Ljava/lang/Object;)Ljava/lang/Object;
     111: goto          116
     114: ldc           #32                 // String
     116: checkcast     #34                 // class java/lang/String
     119: checkcast     #34                 // class java/lang/String
     122: aload_0
     123: instanceof    #30                 // class java/util/Map
     126: ifeq          142
     129: aload_0
     130: ldc           #38                 // String image
     132: ldc           #32                 // String
     134: invokeinterface #33,  3           // InterfaceMethod java/util/Map.getOrDefault:(Ljava/lang/Object;Ljava/lang/Object;)Ljava/lang/Object;
     139: goto          144
     142: ldc           #32                 // String
     144: checkcast     #34                 // class java/lang/String
     147: checkcast     #34                 // class java/lang/String
     150: aload_0
     151: instanceof    #30                 // class java/util/Map
     154: ifeq          170
     157: aload_0
     158: ldc           #39                 // String dockerFile
     160: ldc           #40                 // String Dockerfile
     162: invokeinterface #33,  3           // InterfaceMethod java/util/Map.getOrDefault:(Ljava/lang/Object;Ljava/lang/Object;)Ljava/lang/Object;
     167: goto          172
     170: ldc           #40                 // String Dockerfile
     172: checkcast     #34                 // class java/lang/String
     175: checkcast     #34                 // class java/lang/String
     178: aload_0
     179: instanceof    #30                 // class java/util/Map
     182: ifeq          198
     185: aload_0
     186: ldc           #41                 // String autoBuildEnabled
     188: ldc           #42                 // String false
     190: invokeinterface #33,  3           // InterfaceMethod java/util/Map.getOrDefault:(Ljava/lang/Object;Ljava/lang/Object;)Ljava/lang/Object;
     195: goto          200
     198: ldc           #42                 // String false
     200: invokestatic  #43                 // Method java/lang/String.valueOf:(Ljava/lang/Object;)Ljava/lang/String;
     203: invokestatic  #44                 // Method java/lang/Boolean.parseBoolean:(Ljava/lang/String;)Z
     206: aload_0
     207: instanceof    #30                 // class java/util/Map
     210: ifeq          226
     213: aload_0
     214: ldc           #45                 // String autoPushEnabled
     216: ldc           #42                 // String false
     218: invokeinterface #33,  3           // InterfaceMethod java/util/Map.getOrDefault:(Ljava/lang/Object;Ljava/lang/Object;)Ljava/lang/Object;
     223: goto          228
     226: ldc           #42                 // String false
     228: invokestatic  #43                 // Method java/lang/String.valueOf:(Ljava/lang/Object;)Ljava/lang/String;
     231: invokestatic  #44                 // Method java/lang/Boolean.parseBoolean:(Ljava/lang/String;)Z
     234: aload_0
     235: instanceof    #30                 // class java/util/Map
     238: ifeq          254
     241: aload_0
     242: ldc           #46                 // String enabled
     244: ldc           #47                 // String true
     246: invokeinterface #33,  3           // InterfaceMethod java/util/Map.getOrDefault:(Ljava/lang/Object;Ljava/lang/Object;)Ljava/lang/Object;
     251: goto          256
     254: ldc           #47                 // String true
     256: invokestatic  #43                 // Method java/lang/String.valueOf:(Ljava/lang/Object;)Ljava/lang/String;
     259: invokestatic  #44                 // Method java/lang/Boolean.parseBoolean:(Ljava/lang/String;)Z
     262: aload_0
     263: instanceof    #30                 // class java/util/Map
     266: ifeq          282
     269: aload_0
     270: ldc           #48                 // String builderImage
     272: ldc           #49                 // String fabric8/s2i-java:2.3
     274: invokeinterface #33,  3           // InterfaceMethod java/util/Map.getOrDefault:(Ljava/lang/Object;Ljava/lang/Object;)Ljava/lang/Object;
     279: goto          284
     282: ldc           #49                 // String fabric8/s2i-java:2.3
     284: checkcast     #34                 // class java/lang/String
     287: checkcast     #34                 // class java/lang/String
     290: aload_0
     291: instanceof    #30                 // class java/util/Map
     294: ifeq          312
     297: aload_0
     298: ldc           #50                 // String buildEnvVars
     300: iconst_0
     301: anewarray     #30                 // class java/util/Map
     304: invokeinterface #33,  3           // InterfaceMethod java/util/Map.getOrDefault:(Ljava/lang/Object;Ljava/lang/Object;)Ljava/lang/Object;
     309: goto          316
     312: iconst_0
     313: anewarray     #30                 // class java/util/Map
     316: checkcast     #51                 // class "[Ljava/util/Map;"
     319: checkcast     #51                 // class "[Ljava/util/Map;"
     322: invokestatic  #52                 // Method java/util/Arrays.stream:([Ljava/lang/Object;)Ljava/util/stream/Stream;
     325: invokedynamic #57,  0             // InvokeDynamic #3:apply:()Ljava/util/function/Function;
     330: invokeinterface #20,  2           // InterfaceMethod java/util/stream/Stream.map:(Ljava/util/function/Function;)Ljava/util/stream/Stream;
     335: invokedynamic #58,  0             // InvokeDynamic #4:apply:()Ljava/util/function/IntFunction;
     340: invokeinterface #55,  2           // InterfaceMethod java/util/stream/Stream.toArray:(Ljava/util/function/IntFunction;)[Ljava/lang/Object;
     345: checkcast     #26                 // class "[Lio/dekorate/kubernetes/config/Env;"
     348: aload_0
     349: instanceof    #30                 // class java/util/Map
     352: ifeq          368
     355: aload_0
     356: ldc           #56                 // String autoDeployEnabled
     358: ldc           #42                 // String false
     360: invokeinterface #33,  3           // InterfaceMethod java/util/Map.getOrDefault:(Ljava/lang/Object;Ljava/lang/Object;)Ljava/lang/Object;
     365: goto          370
     368: ldc           #42                 // String false
     370: invokestatic  #43                 // Method java/lang/String.valueOf:(Ljava/lang/Object;)Ljava/lang/String;
     373: invokestatic  #44                 // Method java/lang/Boolean.parseBoolean:(Ljava/lang/String;)Z
     376: invokespecial #28                 // Method io/dekorate/s2i/config/S2iBuildConfig."<init>":(Lio/dekorate/project/Project;Ljava/util/Map;Ljava/lang/String;Ljava/lang/String;Ljava/lang/String;Ljava/lang/String;Ljava/lang/String;Ljava/lang/String;ZZZLjava/lang/String;[Lio/dekorate/kubernetes/config/Env;Z)V
     379: invokespecial #29                 // Method io/dekorate/s2i/config/S2iBuildConfigBuilder."<init>":(Lio/dekorate/s2i/config/S2iBuildConfig;)V
     382: areturn

  private static io.dekorate.kubernetes.config.Env[] lambda$newBuilder$4(int);
    Code:
       0: iload_0
       1: anewarray     #24                 // class io/dekorate/kubernetes/config/Env
       4: areturn

  private static io.dekorate.kubernetes.config.Env lambda$newBuilder$3(java.util.Map);
    Code:
       0: new           #24                 // class io/dekorate/kubernetes/config/Env
       3: dup
       4: aload_0
       5: instanceof    #30                 // class java/util/Map
       8: ifeq          23
      11: aload_0
      12: ldc           #36                 // String name
      14: aconst_null
      15: invokeinterface #33,  3           // InterfaceMethod java/util/Map.getOrDefault:(Ljava/lang/Object;Ljava/lang/Object;)Ljava/lang/Object;
      20: goto          24
      23: aconst_null
      24: checkcast     #34                 // class java/lang/String
      27: checkcast     #34                 // class java/lang/String
      30: aload_0
      31: instanceof    #30                 // class java/util/Map
      34: ifeq          50
      37: aload_0
      38: ldc           #59                 // String value
      40: ldc           #32                 // String
      42: invokeinterface #33,  3           // InterfaceMethod java/util/Map.getOrDefault:(Ljava/lang/Object;Ljava/lang/Object;)Ljava/lang/Object;
      47: goto          52
      50: ldc           #32                 // String
      52: checkcast     #34                 // class java/lang/String
      55: checkcast     #34                 // class java/lang/String
      58: aload_0
      59: instanceof    #30                 // class java/util/Map
      62: ifeq          78
      65: aload_0
      66: ldc           #60                 // String secret
      68: ldc           #32                 // String
      70: invokeinterface #33,  3           // InterfaceMethod java/util/Map.getOrDefault:(Ljava/lang/Object;Ljava/lang/Object;)Ljava/lang/Object;
      75: goto          80
      78: ldc           #32                 // String
      80: checkcast     #34                 // class java/lang/String
      83: checkcast     #34                 // class java/lang/String
      86: aload_0
      87: instanceof    #30                 // class java/util/Map
      90: ifeq          106
      93: aload_0
      94: ldc           #61                 // String configmap
      96: ldc           #32                 // String
      98: invokeinterface #33,  3           // InterfaceMethod java/util/Map.getOrDefault:(Ljava/lang/Object;Ljava/lang/Object;)Ljava/lang/Object;
     103: goto          108
     106: ldc           #32                 // String
     108: checkcast     #34                 // class java/lang/String
     111: checkcast     #34                 // class java/lang/String
     114: aload_0
     115: instanceof    #30                 // class java/util/Map
     118: ifeq          134
     121: aload_0
     122: ldc           #62                 // String field
     124: ldc           #32                 // String
     126: invokeinterface #33,  3           // InterfaceMethod java/util/Map.getOrDefault:(Ljava/lang/Object;Ljava/lang/Object;)Ljava/lang/Object;
     131: goto          136
     134: ldc           #32                 // String
     136: checkcast     #34                 // class java/lang/String
     139: checkcast     #34                 // class java/lang/String
     142: invokespecial #63                 // Method io/dekorate/kubernetes/config/Env."<init>":(Ljava/lang/String;Ljava/lang/String;Ljava/lang/String;Ljava/lang/String;Ljava/lang/String;)V
     145: areturn

  private static io.dekorate.kubernetes.config.Env[] lambda$adapt$2(int);
    Code:
       0: iload_0
       1: anewarray     #24                 // class io/dekorate/kubernetes/config/Env
       4: areturn

  private static io.dekorate.kubernetes.config.Env lambda$adapt$1(java.util.Map);
    Code:
       0: new           #24                 // class io/dekorate/kubernetes/config/Env
       3: dup
       4: aload_0
       5: instanceof    #30                 // class java/util/Map
       8: ifeq          23
      11: aload_0
      12: ldc           #36                 // String name
      14: aconst_null
      15: invokeinterface #33,  3           // InterfaceMethod java/util/Map.getOrDefault:(Ljava/lang/Object;Ljava/lang/Object;)Ljava/lang/Object;
      20: goto          24
      23: aconst_null
      24: checkcast     #34                 // class java/lang/String
      27: checkcast     #34                 // class java/lang/String
      30: aload_0
      31: instanceof    #30                 // class java/util/Map
      34: ifeq          50
      37: aload_0
      38: ldc           #59                 // String value
      40: ldc           #32                 // String
      42: invokeinterface #33,  3           // InterfaceMethod java/util/Map.getOrDefault:(Ljava/lang/Object;Ljava/lang/Object;)Ljava/lang/Object;
      47: goto          52
      50: ldc           #32                 // String
      52: checkcast     #34                 // class java/lang/String
      55: checkcast     #34                 // class java/lang/String
      58: aload_0
      59: instanceof    #30                 // class java/util/Map
      62: ifeq          78
      65: aload_0
      66: ldc           #60                 // String secret
      68: ldc           #32                 // String
      70: invokeinterface #33,  3           // InterfaceMethod java/util/Map.getOrDefault:(Ljava/lang/Object;Ljava/lang/Object;)Ljava/lang/Object;
      75: goto          80
      78: ldc           #32                 // String
      80: checkcast     #34                 // class java/lang/String
      83: checkcast     #34                 // class java/lang/String
      86: aload_0
      87: instanceof    #30                 // class java/util/Map
      90: ifeq          106
      93: aload_0
      94: ldc           #61                 // String configmap
      96: ldc           #32                 // String
      98: invokeinterface #33,  3           // InterfaceMethod java/util/Map.getOrDefault:(Ljava/lang/Object;Ljava/lang/Object;)Ljava/lang/Object;
     103: goto          108
     106: ldc           #32                 // String
     108: checkcast     #34                 // class java/lang/String
     111: checkcast     #34                 // class java/lang/String
     114: aload_0
     115: instanceof    #30                 // class java/util/Map
     118: ifeq          134
     121: aload_0
     122: ldc           #62                 // String field
     124: ldc           #32                 // String
     126: invokeinterface #33,  3           // InterfaceMethod java/util/Map.getOrDefault:(Ljava/lang/Object;Ljava/lang/Object;)Ljava/lang/Object;
     131: goto          136
     134: ldc           #32                 // String
     136: checkcast     #34                 // class java/lang/String
     139: checkcast     #34                 // class java/lang/String
     142: invokespecial #63                 // Method io/dekorate/kubernetes/config/Env."<init>":(Ljava/lang/String;Ljava/lang/String;Ljava/lang/String;Ljava/lang/String;Ljava/lang/String;)V
     145: areturn

  private static io.dekorate.kubernetes.config.Env lambda$newBuilder$0(io.dekorate.kubernetes.annotation.Env);
    Code:
       0: new           #24                 // class io/dekorate/kubernetes/config/Env
       3: dup
       4: aload_0
       5: invokeinterface #64,  1           // InterfaceMethod io/dekorate/kubernetes/annotation/Env.name:()Ljava/lang/String;
      10: aload_0
      11: invokeinterface #65,  1           // InterfaceMethod io/dekorate/kubernetes/annotation/Env.value:()Ljava/lang/String;
      16: aload_0
      17: invokeinterface #66,  1           // InterfaceMethod io/dekorate/kubernetes/annotation/Env.secret:()Ljava/lang/String;
      22: aload_0
      23: invokeinterface #67,  1           // InterfaceMethod io/dekorate/kubernetes/annotation/Env.configmap:()Ljava/lang/String;
      28: aload_0
      29: invokeinterface #68,  1           // InterfaceMethod io/dekorate/kubernetes/annotation/Env.field:()Ljava/lang/String;
      34: invokespecial #63                 // Method io/dekorate/kubernetes/config/Env."<init>":(Ljava/lang/String;Ljava/lang/String;Ljava/lang/String;Ljava/lang/String;Ljava/lang/String;)V
      37: areturn
}
