Compiled from "_ArrayIterator.java"
public class freemarker.core._ArrayIterator implements java.util.Iterator {
  private final java.lang.Object[] array;

  private int nextIndex;

  public freemarker.core._ArrayIterator(java.lang.Object[]);
    Code:
       0: aload_0
       1: invokespecial #1                  // Method java/lang/Object."<init>":()V
       4: aload_0
       5: aload_1
       6: putfield      #2                  // Field array:[Ljava/lang/Object;
       9: aload_0
      10: iconst_0
      11: putfield      #3                  // Field nextIndex:I
      14: return

  public boolean hasNext();
    Code:
       0: aload_0
       1: getfield      #3                  // Field nextIndex:I
       4: aload_0
       5: getfield      #2                  // Field array:[Ljava/lang/Object;
       8: arraylength
       9: if_icmpge     16
      12: iconst_1
      13: goto          17
      16: iconst_0
      17: ireturn

  public java.lang.Object next();
    Code:
       0: aload_0
       1: getfield      #3                  // Field nextIndex:I
       4: aload_0
       5: getfield      #2                  // Field array:[Ljava/lang/Object;
       8: arraylength
       9: if_icmplt     20
      12: new           #4                  // class java/util/NoSuchElementException
      15: dup
      16: invokespecial #5                  // Method java/util/NoSuchElementException."<init>":()V
      19: athrow
      20: aload_0
      21: getfield      #2                  // Field array:[Ljava/lang/Object;
      24: aload_0
      25: dup
      26: getfield      #3                  // Field nextIndex:I
      29: dup_x1
      30: iconst_1
      31: iadd
      32: putfield      #3                  // Field nextIndex:I
      35: aaload
      36: areturn

  public void remove();
    Code:
       0: new           #6                  // class java/lang/UnsupportedOperationException
       3: dup
       4: invokespecial #7                  // Method java/lang/UnsupportedOperationException."<init>":()V
       7: athrow
}
