Compiled from "_DelayedConversionToString.java"
public abstract class freemarker.core._DelayedConversionToString {
  private static final java.lang.String NOT_SET;

  private java.lang.Object object;

  private volatile java.lang.String stringValue;

  public freemarker.core._DelayedConversionToString(java.lang.Object);
    Code:
       0: aload_0
       1: invokespecial #1                  // Method java/lang/Object."<init>":()V
       4: aload_0
       5: getstatic     #2                  // Field NOT_SET:Ljava/lang/String;
       8: putfield      #3                  // Field stringValue:Ljava/lang/String;
      11: aload_0
      12: aload_1
      13: putfield      #4                  // Field object:Ljava/lang/Object;
      16: return

  public java.lang.String toString();
    Code:
       0: aload_0
       1: getfield      #3                  // Field stringValue:Ljava/lang/String;
       4: astore_1
       5: aload_1
       6: getstatic     #2                  // Field NOT_SET:Ljava/lang/String;
       9: if_acmpne     57
      12: aload_0
      13: dup
      14: astore_2
      15: monitorenter
      16: aload_0
      17: getfield      #3                  // Field stringValue:Ljava/lang/String;
      20: astore_1
      21: aload_1
      22: getstatic     #2                  // Field NOT_SET:Ljava/lang/String;
      25: if_acmpne     47
      28: aload_0
      29: aload_0
      30: getfield      #4                  // Field object:Ljava/lang/Object;
      33: invokevirtual #5                  // Method doConversion:(Ljava/lang/Object;)Ljava/lang/String;
      36: astore_1
      37: aload_0
      38: aload_1
      39: putfield      #3                  // Field stringValue:Ljava/lang/String;
      42: aload_0
      43: aconst_null
      44: putfield      #4                  // Field object:Ljava/lang/Object;
      47: aload_2
      48: monitorexit
      49: goto          57
      52: astore_3
      53: aload_2
      54: monitorexit
      55: aload_3
      56: athrow
      57: aload_1
      58: areturn
    Exception table:
       from    to  target type
          16    49    52   any
          52    55    52   any

  protected abstract java.lang.String doConversion(java.lang.Object);

  static {};
    Code:
       0: new           #6                  // class java/lang/String
       3: dup
       4: invokespecial #7                  // Method java/lang/String."<init>":()V
       7: putstatic     #2                  // Field NOT_SET:Ljava/lang/String;
      10: return
}
