Compiled from "BlockAssignment.java"
class freemarker.core.BlockAssignment$CaptureOutput$1 extends java.io.StringWriter {
  final freemarker.core.BlockAssignment$CaptureOutput this$1;

  freemarker.core.BlockAssignment$CaptureOutput$1(freemarker.core.BlockAssignment$CaptureOutput);
    Code:
       0: aload_0
       1: aload_1
       2: putfield      #1                  // Field this$1:Lfreemarker/core/BlockAssignment$CaptureOutput;
       5: aload_0
       6: invokespecial #2                  // Method java/io/StringWriter."<init>":()V
       9: return

  public void close() throws java.io.IOException;
    Code:
       0: aload_0
       1: getfield      #1                  // Field this$1:Lfreemarker/core/BlockAssignment$CaptureOutput;
       4: getfield      #3                  // Field freemarker/core/BlockAssignment$CaptureOutput.this$0:Lfreemarker/core/BlockAssignment;
       7: aload_0
       8: invokevirtual #4                  // Method toString:()Ljava/lang/String;
      11: invokestatic  #5                  // Method freemarker/core/BlockAssignment.access$100:(Lfreemarker/core/BlockAssignment;Ljava/lang/String;)Lfreemarker/template/TemplateModel;
      14: astore_1
      15: goto          46
      18: astore_2
      19: new           #7                  // class java/io/IOException
      22: dup
      23: new           #8                  // class java/lang/StringBuilder
      26: dup
      27: invokespecial #9                  // Method java/lang/StringBuilder."<init>":()V
      30: ldc           #10                 // String Failed to create FTL value from captured string:
      32: invokevirtual #11                 // Method java/lang/StringBuilder.append:(Ljava/lang/String;)Ljava/lang/StringBuilder;
      35: aload_2
      36: invokevirtual #12                 // Method java/lang/StringBuilder.append:(Ljava/lang/Object;)Ljava/lang/StringBuilder;
      39: invokevirtual #13                 // Method java/lang/StringBuilder.toString:()Ljava/lang/String;
      42: invokespecial #14                 // Method java/io/IOException."<init>":(Ljava/lang/String;)V
      45: athrow
      46: aload_0
      47: getfield      #1                  // Field this$1:Lfreemarker/core/BlockAssignment$CaptureOutput;
      50: getfield      #3                  // Field freemarker/core/BlockAssignment$CaptureOutput.this$0:Lfreemarker/core/BlockAssignment;
      53: invokestatic  #15                 // Method freemarker/core/BlockAssignment.access$200:(Lfreemarker/core/BlockAssignment;)I
      56: tableswitch   { // 1 to 3
                     1: 84
                     2: 142
                     3: 166
               default: 187
          }
      84: aload_0
      85: getfield      #1                  // Field this$1:Lfreemarker/core/BlockAssignment$CaptureOutput;
      88: invokestatic  #16                 // Method freemarker/core/BlockAssignment$CaptureOutput.access$300:(Lfreemarker/core/BlockAssignment$CaptureOutput;)Lfreemarker/core/Environment$Namespace;
      91: ifnull        118
      94: aload_0
      95: getfield      #1                  // Field this$1:Lfreemarker/core/BlockAssignment$CaptureOutput;
      98: invokestatic  #16                 // Method freemarker/core/BlockAssignment$CaptureOutput.access$300:(Lfreemarker/core/BlockAssignment$CaptureOutput;)Lfreemarker/core/Environment$Namespace;
     101: aload_0
     102: getfield      #1                  // Field this$1:Lfreemarker/core/BlockAssignment$CaptureOutput;
     105: getfield      #3                  // Field freemarker/core/BlockAssignment$CaptureOutput.this$0:Lfreemarker/core/BlockAssignment;
     108: invokestatic  #17                 // Method freemarker/core/BlockAssignment.access$400:(Lfreemarker/core/BlockAssignment;)Ljava/lang/String;
     111: aload_1
     112: invokevirtual #18                 // Method freemarker/core/Environment$Namespace.put:(Ljava/lang/String;Ljava/lang/Object;)V
     115: goto          187
     118: aload_0
     119: getfield      #1                  // Field this$1:Lfreemarker/core/BlockAssignment$CaptureOutput;
     122: invokestatic  #19                 // Method freemarker/core/BlockAssignment$CaptureOutput.access$500:(Lfreemarker/core/BlockAssignment$CaptureOutput;)Lfreemarker/core/Environment;
     125: aload_0
     126: getfield      #1                  // Field this$1:Lfreemarker/core/BlockAssignment$CaptureOutput;
     129: getfield      #3                  // Field freemarker/core/BlockAssignment$CaptureOutput.this$0:Lfreemarker/core/BlockAssignment;
     132: invokestatic  #17                 // Method freemarker/core/BlockAssignment.access$400:(Lfreemarker/core/BlockAssignment;)Ljava/lang/String;
     135: aload_1
     136: invokevirtual #20                 // Method freemarker/core/Environment.setVariable:(Ljava/lang/String;Lfreemarker/template/TemplateModel;)V
     139: goto          187
     142: aload_0
     143: getfield      #1                  // Field this$1:Lfreemarker/core/BlockAssignment$CaptureOutput;
     146: invokestatic  #19                 // Method freemarker/core/BlockAssignment$CaptureOutput.access$500:(Lfreemarker/core/BlockAssignment$CaptureOutput;)Lfreemarker/core/Environment;
     149: aload_0
     150: getfield      #1                  // Field this$1:Lfreemarker/core/BlockAssignment$CaptureOutput;
     153: getfield      #3                  // Field freemarker/core/BlockAssignment$CaptureOutput.this$0:Lfreemarker/core/BlockAssignment;
     156: invokestatic  #17                 // Method freemarker/core/BlockAssignment.access$400:(Lfreemarker/core/BlockAssignment;)Ljava/lang/String;
     159: aload_1
     160: invokevirtual #21                 // Method freemarker/core/Environment.setLocalVariable:(Ljava/lang/String;Lfreemarker/template/TemplateModel;)V
     163: goto          187
     166: aload_0
     167: getfield      #1                  // Field this$1:Lfreemarker/core/BlockAssignment$CaptureOutput;
     170: invokestatic  #19                 // Method freemarker/core/BlockAssignment$CaptureOutput.access$500:(Lfreemarker/core/BlockAssignment$CaptureOutput;)Lfreemarker/core/Environment;
     173: aload_0
     174: getfield      #1                  // Field this$1:Lfreemarker/core/BlockAssignment$CaptureOutput;
     177: getfield      #3                  // Field freemarker/core/BlockAssignment$CaptureOutput.this$0:Lfreemarker/core/BlockAssignment;
     180: invokestatic  #17                 // Method freemarker/core/BlockAssignment.access$400:(Lfreemarker/core/BlockAssignment;)Ljava/lang/String;
     183: aload_1
     184: invokevirtual #22                 // Method freemarker/core/Environment.setGlobalVariable:(Ljava/lang/String;Lfreemarker/template/TemplateModel;)V
     187: return
    Exception table:
       from    to  target type
           0    15    18   Class freemarker/template/TemplateModelException
}
