Compiled from "BuiltInsForMultipleTypes.java"
abstract class freemarker.core.BuiltInsForMultipleTypes$AbstractCBI extends freemarker.core.BuiltIn {
  freemarker.core.BuiltInsForMultipleTypes$AbstractCBI();
    Code:
       0: aload_0
       1: invokespecial #1                  // Method freemarker/core/BuiltIn."<init>":()V
       4: return

  freemarker.template.TemplateModel _eval(freemarker.core.Environment) throws freemarker.template.TemplateException;
    Code:
       0: aload_0
       1: getfield      #2                  // Field target:Lfreemarker/core/Expression;
       4: aload_1
       5: invokevirtual #3                  // Method freemarker/core/Expression.eval:(Lfreemarker/core/Environment;)Lfreemarker/template/TemplateModel;
       8: astore_2
       9: aload_2
      10: instanceof    #4                  // class freemarker/template/TemplateNumberModel
      13: ifeq          23
      16: aload_0
      17: aload_1
      18: aload_2
      19: invokevirtual #5                  // Method formatNumber:(Lfreemarker/core/Environment;Lfreemarker/template/TemplateModel;)Lfreemarker/template/TemplateModel;
      22: areturn
      23: aload_2
      24: instanceof    #6                  // class freemarker/template/TemplateBooleanModel
      27: ifeq          57
      30: new           #7                  // class freemarker/template/SimpleScalar
      33: dup
      34: aload_2
      35: checkcast     #6                  // class freemarker/template/TemplateBooleanModel
      38: invokeinterface #8,  1            // InterfaceMethod freemarker/template/TemplateBooleanModel.getAsBoolean:()Z
      43: ifeq          51
      46: ldc           #10                 // String true
      48: goto          53
      51: ldc           #11                 // String false
      53: invokespecial #12                 // Method freemarker/template/SimpleScalar."<init>":(Ljava/lang/String;)V
      56: areturn
      57: new           #13                 // class freemarker/core/UnexpectedTypeException
      60: dup
      61: aload_0
      62: getfield      #2                  // Field target:Lfreemarker/core/Expression;
      65: aload_2
      66: ldc           #14                 // String number or boolean
      68: iconst_2
      69: anewarray     #15                 // class java/lang/Class
      72: dup
      73: iconst_0
      74: ldc           #4                  // class freemarker/template/TemplateNumberModel
      76: aastore
      77: dup
      78: iconst_1
      79: ldc           #6                  // class freemarker/template/TemplateBooleanModel
      81: aastore
      82: aload_1
      83: invokespecial #16                 // Method freemarker/core/UnexpectedTypeException."<init>":(Lfreemarker/core/Expression;Lfreemarker/template/TemplateModel;Ljava/lang/String;[Ljava/lang/Class;Lfreemarker/core/Environment;)V
      86: athrow

  protected abstract freemarker.template.TemplateModel formatNumber(freemarker.core.Environment, freemarker.template.TemplateModel) throws freemarker.template.TemplateModelException;
}
