Compiled from "BuiltInsForDates.java"
class freemarker.core.BuiltInsForDates$iso_BI$Result implements freemarker.template.TemplateMethodModelEx {
  private final java.util.Date date;

  private final int dateType;

  private final freemarker.core.Environment env;

  final freemarker.core.BuiltInsForDates$iso_BI this$0;

  freemarker.core.BuiltInsForDates$iso_BI$Result(freemarker.core.BuiltInsForDates$iso_BI, java.util.Date, int, freemarker.core.Environment);
    Code:
       0: aload_0
       1: aload_1
       2: putfield      #1                  // Field this$0:Lfreemarker/core/BuiltInsForDates$iso_BI;
       5: aload_0
       6: invokespecial #2                  // Method java/lang/Object."<init>":()V
       9: aload_0
      10: aload_2
      11: putfield      #3                  // Field date:Ljava/util/Date;
      14: aload_0
      15: iload_3
      16: putfield      #4                  // Field dateType:I
      19: aload_0
      20: aload         4
      22: putfield      #5                  // Field env:Lfreemarker/core/Environment;
      25: return

  public java.lang.Object exec(java.util.List) throws freemarker.template.TemplateModelException;
    Code:
       0: aload_0
       1: getfield      #1                  // Field this$0:Lfreemarker/core/BuiltInsForDates$iso_BI;
       4: aload_1
       5: iconst_1
       6: invokevirtual #6                  // Method freemarker/core/BuiltInsForDates$iso_BI.checkMethodArgCount:(Ljava/util/List;I)V
       9: aload_1
      10: iconst_0
      11: invokeinterface #7,  2            // InterfaceMethod java/util/List.get:(I)Ljava/lang/Object;
      16: checkcast     #8                  // class freemarker/template/TemplateModel
      19: astore_2
      20: aload_2
      21: instanceof    #9                  // class freemarker/template/AdapterTemplateModel
      24: ifeq          56
      27: aload_2
      28: checkcast     #9                  // class freemarker/template/AdapterTemplateModel
      31: ldc           #10                 // class java/util/TimeZone
      33: invokeinterface #11,  2           // InterfaceMethod freemarker/template/AdapterTemplateModel.getAdaptedObject:(Ljava/lang/Class;)Ljava/lang/Object;
      38: dup
      39: astore        4
      41: instanceof    #10                 // class java/util/TimeZone
      44: ifeq          56
      47: aload         4
      49: checkcast     #10                 // class java/util/TimeZone
      52: astore_3
      53: goto          165
      56: aload_2
      57: instanceof    #12                 // class freemarker/template/TemplateScalarModel
      60: ifeq          132
      63: aload_2
      64: checkcast     #12                 // class freemarker/template/TemplateScalarModel
      67: aconst_null
      68: aconst_null
      69: invokestatic  #13                 // Method freemarker/core/EvalUtil.modelToString:(Lfreemarker/template/TemplateScalarModel;Lfreemarker/core/Expression;Lfreemarker/core/Environment;)Ljava/lang/String;
      72: astore        5
      74: aload         5
      76: invokestatic  #14                 // Method freemarker/template/utility/DateUtil.getTimeZone:(Ljava/lang/String;)Ljava/util/TimeZone;
      79: astore_3
      80: goto          129
      83: astore        6
      85: new           #16                 // class freemarker/core/_TemplateModelException
      88: dup
      89: iconst_4
      90: anewarray     #17                 // class java/lang/Object
      93: dup
      94: iconst_0
      95: ldc           #18                 // String The time zone string specified for ?
      97: aastore
      98: dup
      99: iconst_1
     100: aload_0
     101: getfield      #1                  // Field this$0:Lfreemarker/core/BuiltInsForDates$iso_BI;
     104: getfield      #19                 // Field freemarker/core/BuiltInsForDates$iso_BI.key:Ljava/lang/String;
     107: aastore
     108: dup
     109: iconst_2
     110: ldc           #20                 // String (...) is not recognized as a valid time zone name:
     112: aastore
     113: dup
     114: iconst_3
     115: new           #21                 // class freemarker/core/_DelayedJQuote
     118: dup
     119: aload         5
     121: invokespecial #22                 // Method freemarker/core/_DelayedJQuote."<init>":(Ljava/lang/Object;)V
     124: aastore
     125: invokespecial #23                 // Method freemarker/core/_TemplateModelException."<init>":([Ljava/lang/Object;)V
     128: athrow
     129: goto          165
     132: new           #24                 // class java/lang/StringBuilder
     135: dup
     136: invokespecial #25                 // Method java/lang/StringBuilder."<init>":()V
     139: ldc           #26                 // String ?
     141: invokevirtual #27                 // Method java/lang/StringBuilder.append:(Ljava/lang/String;)Ljava/lang/StringBuilder;
     144: aload_0
     145: getfield      #1                  // Field this$0:Lfreemarker/core/BuiltInsForDates$iso_BI;
     148: getfield      #19                 // Field freemarker/core/BuiltInsForDates$iso_BI.key:Ljava/lang/String;
     151: invokevirtual #27                 // Method java/lang/StringBuilder.append:(Ljava/lang/String;)Ljava/lang/StringBuilder;
     154: invokevirtual #28                 // Method java/lang/StringBuilder.toString:()Ljava/lang/String;
     157: iconst_0
     158: ldc           #29                 // String string or java.util.TimeZone
     160: aload_2
     161: invokestatic  #30                 // Method freemarker/core/MessageUtil.newMethodArgUnexpectedTypeException:(Ljava/lang/String;ILjava/lang/String;Lfreemarker/template/TemplateModel;)Lfreemarker/template/TemplateModelException;
     164: athrow
     165: new           #31                 // class freemarker/template/SimpleScalar
     168: dup
     169: aload_0
     170: getfield      #3                  // Field date:Ljava/util/Date;
     173: aload_0
     174: getfield      #4                  // Field dateType:I
     177: iconst_1
     178: if_icmpeq     185
     181: iconst_1
     182: goto          186
     185: iconst_0
     186: aload_0
     187: getfield      #4                  // Field dateType:I
     190: iconst_2
     191: if_icmpeq     198
     194: iconst_1
     195: goto          199
     198: iconst_0
     199: aload_0
     200: getfield      #1                  // Field this$0:Lfreemarker/core/BuiltInsForDates$iso_BI;
     203: aload_0
     204: getfield      #3                  // Field date:Ljava/util/Date;
     207: aload_0
     208: getfield      #4                  // Field dateType:I
     211: aload_0
     212: getfield      #5                  // Field env:Lfreemarker/core/Environment;
     215: invokevirtual #33                 // Method freemarker/core/BuiltInsForDates$iso_BI.shouldShowOffset:(Ljava/util/Date;ILfreemarker/core/Environment;)Z
     218: aload_0
     219: getfield      #1                  // Field this$0:Lfreemarker/core/BuiltInsForDates$iso_BI;
     222: getfield      #34                 // Field freemarker/core/BuiltInsForDates$iso_BI.accuracy:I
     225: aload_3
     226: aload_0
     227: getfield      #5                  // Field env:Lfreemarker/core/Environment;
     230: invokevirtual #35                 // Method freemarker/core/Environment.getISOBuiltInCalendarFactory:()Lfreemarker/template/utility/DateUtil$DateToISO8601CalendarFactory;
     233: invokestatic  #36                 // Method freemarker/template/utility/DateUtil.dateToISO8601String:(Ljava/util/Date;ZZZILjava/util/TimeZone;Lfreemarker/template/utility/DateUtil$DateToISO8601CalendarFactory;)Ljava/lang/String;
     236: invokespecial #37                 // Method freemarker/template/SimpleScalar."<init>":(Ljava/lang/String;)V
     239: areturn
    Exception table:
       from    to  target type
          74    80    83   Class freemarker/template/utility/UnrecognizedTimeZoneException
}
