Compiled from "BuiltInsWithParseTimeParameters.java"
class freemarker.core.BuiltInsWithParseTimeParameters$switch_BI extends freemarker.core.BuiltInWithParseTimeParameters {
  private java.util.List parameters;

  freemarker.core.BuiltInsWithParseTimeParameters$switch_BI();
    Code:
       0: aload_0
       1: invokespecial #1                  // Method freemarker/core/BuiltInWithParseTimeParameters."<init>":()V
       4: return

  void bindToParameters(java.util.List, freemarker.core.Token, freemarker.core.Token) throws freemarker.core.ParseException;
    Code:
       0: aload_1
       1: invokeinterface #2,  1            // InterfaceMethod java/util/List.size:()I
       6: iconst_2
       7: if_icmpge     19
      10: aload_0
      11: ldc           #3                  // String must have at least 2
      13: aload_2
      14: aload_3
      15: invokevirtual #4                  // Method newArgumentCountException:(Ljava/lang/String;Lfreemarker/core/Token;Lfreemarker/core/Token;)Lfreemarker/core/ParseException;
      18: athrow
      19: aload_0
      20: aload_1
      21: putfield      #5                  // Field parameters:Ljava/util/List;
      24: return

  protected java.util.List getArgumentsAsList();
    Code:
       0: aload_0
       1: getfield      #5                  // Field parameters:Ljava/util/List;
       4: areturn

  protected int getArgumentsCount();
    Code:
       0: aload_0
       1: getfield      #5                  // Field parameters:Ljava/util/List;
       4: invokeinterface #2,  1            // InterfaceMethod java/util/List.size:()I
       9: ireturn

  protected freemarker.core.Expression getArgumentParameterValue(int);
    Code:
       0: aload_0
       1: getfield      #5                  // Field parameters:Ljava/util/List;
       4: iload_1
       5: invokeinterface #6,  2            // InterfaceMethod java/util/List.get:(I)Ljava/lang/Object;
      10: checkcast     #7                  // class freemarker/core/Expression
      13: areturn

  protected void cloneArguments(freemarker.core.Expression, java.lang.String, freemarker.core.Expression, freemarker.core.Expression$ReplacemenetState);
    Code:
       0: new           #8                  // class java/util/ArrayList
       3: dup
       4: aload_0
       5: getfield      #5                  // Field parameters:Ljava/util/List;
       8: invokeinterface #2,  1            // InterfaceMethod java/util/List.size:()I
      13: invokespecial #9                  // Method java/util/ArrayList."<init>":(I)V
      16: astore        5
      18: iconst_0
      19: istore        6
      21: iload         6
      23: aload_0
      24: getfield      #5                  // Field parameters:Ljava/util/List;
      27: invokeinterface #2,  1            // InterfaceMethod java/util/List.size:()I
      32: if_icmpge     68
      35: aload         5
      37: aload_0
      38: getfield      #5                  // Field parameters:Ljava/util/List;
      41: iload         6
      43: invokeinterface #6,  2            // InterfaceMethod java/util/List.get:(I)Ljava/lang/Object;
      48: checkcast     #7                  // class freemarker/core/Expression
      51: aload_2
      52: aload_3
      53: aload         4
      55: invokevirtual #10                 // Method freemarker/core/Expression.deepCloneWithIdentifierReplaced:(Ljava/lang/String;Lfreemarker/core/Expression;Lfreemarker/core/Expression$ReplacemenetState;)Lfreemarker/core/Expression;
      58: invokevirtual #11                 // Method java/util/ArrayList.add:(Ljava/lang/Object;)Z
      61: pop
      62: iinc          6, 1
      65: goto          21
      68: aload_1
      69: checkcast     #12                 // class freemarker/core/BuiltInsWithParseTimeParameters$switch_BI
      72: aload         5
      74: putfield      #5                  // Field parameters:Ljava/util/List;
      77: return

  freemarker.template.TemplateModel _eval(freemarker.core.Environment) throws freemarker.template.TemplateException;
    Code:
       0: aload_0
       1: getfield      #13                 // Field target:Lfreemarker/core/Expression;
       4: aload_1
       5: invokevirtual #14                 // Method freemarker/core/Expression.evalToNonMissing:(Lfreemarker/core/Environment;)Lfreemarker/template/TemplateModel;
       8: astore_2
       9: aload_0
      10: getfield      #5                  // Field parameters:Ljava/util/List;
      13: astore_3
      14: aload_3
      15: invokeinterface #2,  1            // InterfaceMethod java/util/List.size:()I
      20: istore        4
      22: iconst_0
      23: istore        5
      25: iload         5
      27: iconst_1
      28: iadd
      29: iload         4
      31: if_icmpge     103
      34: aload_3
      35: iload         5
      37: invokeinterface #6,  2            // InterfaceMethod java/util/List.get:(I)Ljava/lang/Object;
      42: checkcast     #7                  // class freemarker/core/Expression
      45: astore        6
      47: aload         6
      49: aload_1
      50: invokevirtual #14                 // Method freemarker/core/Expression.evalToNonMissing:(Lfreemarker/core/Environment;)Lfreemarker/template/TemplateModel;
      53: astore        7
      55: aload_2
      56: aload_0
      57: getfield      #13                 // Field target:Lfreemarker/core/Expression;
      60: iconst_1
      61: ldc           #16                 // String ==
      63: aload         7
      65: aload         6
      67: aload_0
      68: iconst_1
      69: iconst_0
      70: iconst_0
      71: iconst_0
      72: aload_1
      73: invokestatic  #17                 // Method freemarker/core/EvalUtil.compare:(Lfreemarker/template/TemplateModel;Lfreemarker/core/Expression;ILjava/lang/String;Lfreemarker/template/TemplateModel;Lfreemarker/core/Expression;Lfreemarker/core/Expression;ZZZZLfreemarker/core/Environment;)Z
      76: ifeq          97
      79: aload_3
      80: iload         5
      82: iconst_1
      83: iadd
      84: invokeinterface #6,  2            // InterfaceMethod java/util/List.get:(I)Ljava/lang/Object;
      89: checkcast     #7                  // class freemarker/core/Expression
      92: aload_1
      93: invokevirtual #14                 // Method freemarker/core/Expression.evalToNonMissing:(Lfreemarker/core/Environment;)Lfreemarker/template/TemplateModel;
      96: areturn
      97: iinc          5, 2
     100: goto          25
     103: iload         4
     105: iconst_2
     106: irem
     107: ifne          143
     110: new           #18                 // class freemarker/core/_MiscTemplateException
     113: dup
     114: aload_0
     115: getfield      #13                 // Field target:Lfreemarker/core/Expression;
     118: iconst_3
     119: anewarray     #19                 // class java/lang/Object
     122: dup
     123: iconst_0
     124: ldc           #20                 // String The value before ?
     126: aastore
     127: dup
     128: iconst_1
     129: aload_0
     130: getfield      #21                 // Field key:Ljava/lang/String;
     133: aastore
     134: dup
     135: iconst_2
     136: ldc           #22                 // String (case1, value1, case2, value2, ...) didn\'t match any of the case parameters, and there was no default value parameter (an additional last parameter) eithter.
     138: aastore
     139: invokespecial #23                 // Method freemarker/core/_MiscTemplateException."<init>":(Lfreemarker/core/Expression;[Ljava/lang/Object;)V
     142: athrow
     143: aload_3
     144: iload         4
     146: iconst_1
     147: isub
     148: invokeinterface #6,  2            // InterfaceMethod java/util/List.get:(I)Ljava/lang/Object;
     153: checkcast     #7                  // class freemarker/core/Expression
     156: aload_1
     157: invokevirtual #14                 // Method freemarker/core/Expression.evalToNonMissing:(Lfreemarker/core/Environment;)Lfreemarker/template/TemplateModel;
     160: areturn
}
