Compiled from "BuiltInsForNumbers.java"
class freemarker.core.BuiltInsForNumbers$absBI extends freemarker.core.BuiltInForNumber {
  freemarker.core.BuiltInsForNumbers$absBI();
    Code:
       0: aload_0
       1: invokespecial #1                  // Method freemarker/core/BuiltInForNumber."<init>":()V
       4: return

  freemarker.template.TemplateModel calculateResult(java.lang.Number, freemarker.template.TemplateModel) throws freemarker.template.TemplateModelException;
    Code:
       0: aload_1
       1: instanceof    #2                  // class java/lang/Integer
       4: ifeq          31
       7: aload_1
       8: checkcast     #2                  // class java/lang/Integer
      11: invokevirtual #3                  // Method java/lang/Integer.intValue:()I
      14: istore_3
      15: iload_3
      16: ifge          29
      19: new           #4                  // class freemarker/template/SimpleNumber
      22: dup
      23: iload_3
      24: ineg
      25: invokespecial #5                  // Method freemarker/template/SimpleNumber."<init>":(I)V
      28: areturn
      29: aload_2
      30: areturn
      31: aload_1
      32: instanceof    #6                  // class java/math/BigDecimal
      35: ifeq          64
      38: aload_1
      39: checkcast     #6                  // class java/math/BigDecimal
      42: astore_3
      43: aload_3
      44: invokevirtual #7                  // Method java/math/BigDecimal.signum:()I
      47: ifge          62
      50: new           #4                  // class freemarker/template/SimpleNumber
      53: dup
      54: aload_3
      55: invokevirtual #8                  // Method java/math/BigDecimal.negate:()Ljava/math/BigDecimal;
      58: invokespecial #9                  // Method freemarker/template/SimpleNumber."<init>":(Ljava/lang/Number;)V
      61: areturn
      62: aload_2
      63: areturn
      64: aload_1
      65: instanceof    #10                 // class java/lang/Double
      68: ifeq          97
      71: aload_1
      72: checkcast     #10                 // class java/lang/Double
      75: invokevirtual #11                 // Method java/lang/Double.doubleValue:()D
      78: dstore_3
      79: dload_3
      80: dconst_0
      81: dcmpg
      82: ifge          95
      85: new           #4                  // class freemarker/template/SimpleNumber
      88: dup
      89: dload_3
      90: dneg
      91: invokespecial #12                 // Method freemarker/template/SimpleNumber."<init>":(D)V
      94: areturn
      95: aload_2
      96: areturn
      97: aload_1
      98: instanceof    #13                 // class java/lang/Float
     101: ifeq          130
     104: aload_1
     105: checkcast     #13                 // class java/lang/Float
     108: invokevirtual #14                 // Method java/lang/Float.floatValue:()F
     111: fstore_3
     112: fload_3
     113: fconst_0
     114: fcmpg
     115: ifge          128
     118: new           #4                  // class freemarker/template/SimpleNumber
     121: dup
     122: fload_3
     123: fneg
     124: invokespecial #15                 // Method freemarker/template/SimpleNumber."<init>":(F)V
     127: areturn
     128: aload_2
     129: areturn
     130: aload_1
     131: instanceof    #16                 // class java/lang/Long
     134: ifeq          163
     137: aload_1
     138: checkcast     #16                 // class java/lang/Long
     141: invokevirtual #17                 // Method java/lang/Long.longValue:()J
     144: lstore_3
     145: lload_3
     146: lconst_0
     147: lcmp
     148: ifge          161
     151: new           #4                  // class freemarker/template/SimpleNumber
     154: dup
     155: lload_3
     156: lneg
     157: invokespecial #18                 // Method freemarker/template/SimpleNumber."<init>":(J)V
     160: areturn
     161: aload_2
     162: areturn
     163: aload_1
     164: instanceof    #19                 // class java/lang/Short
     167: ifeq          194
     170: aload_1
     171: checkcast     #19                 // class java/lang/Short
     174: invokevirtual #20                 // Method java/lang/Short.shortValue:()S
     177: istore_3
     178: iload_3
     179: ifge          192
     182: new           #4                  // class freemarker/template/SimpleNumber
     185: dup
     186: iload_3
     187: ineg
     188: invokespecial #5                  // Method freemarker/template/SimpleNumber."<init>":(I)V
     191: areturn
     192: aload_2
     193: areturn
     194: aload_1
     195: instanceof    #21                 // class java/lang/Byte
     198: ifeq          225
     201: aload_1
     202: checkcast     #21                 // class java/lang/Byte
     205: invokevirtual #22                 // Method java/lang/Byte.byteValue:()B
     208: istore_3
     209: iload_3
     210: ifge          223
     213: new           #4                  // class freemarker/template/SimpleNumber
     216: dup
     217: iload_3
     218: ineg
     219: invokespecial #5                  // Method freemarker/template/SimpleNumber."<init>":(I)V
     222: areturn
     223: aload_2
     224: areturn
     225: aload_1
     226: instanceof    #23                 // class java/math/BigInteger
     229: ifeq          258
     232: aload_1
     233: checkcast     #23                 // class java/math/BigInteger
     236: astore_3
     237: aload_3
     238: invokevirtual #24                 // Method java/math/BigInteger.signum:()I
     241: ifge          256
     244: new           #4                  // class freemarker/template/SimpleNumber
     247: dup
     248: aload_3
     249: invokevirtual #25                 // Method java/math/BigInteger.negate:()Ljava/math/BigInteger;
     252: invokespecial #9                  // Method freemarker/template/SimpleNumber."<init>":(Ljava/lang/Number;)V
     255: areturn
     256: aload_2
     257: areturn
     258: new           #26                 // class freemarker/core/_TemplateModelException
     261: dup
     262: iconst_2
     263: anewarray     #27                 // class java/lang/Object
     266: dup
     267: iconst_0
     268: ldc           #28                 // String Unsupported number class:
     270: aastore
     271: dup
     272: iconst_1
     273: aload_1
     274: invokevirtual #29                 // Method java/lang/Object.getClass:()Ljava/lang/Class;
     277: aastore
     278: invokespecial #30                 // Method freemarker/core/_TemplateModelException."<init>":([Ljava/lang/Object;)V
     281: athrow
}
