Compiled from "BuiltInsForStringsRegexp.java"
class freemarker.core.BuiltInsForStringsRegexp$RegexMatchModel implements freemarker.template.TemplateBooleanModel,freemarker.template.TemplateCollectionModel,freemarker.template.TemplateSequenceModel {
  final java.util.regex.Pattern pattern;

  final java.lang.String input;

  private java.util.regex.Matcher firedEntireInputMatcher;

  private java.lang.Boolean entireInputMatched;

  private freemarker.template.TemplateSequenceModel entireInputMatchGroups;

  private java.util.ArrayList matchingInputParts;

  freemarker.core.BuiltInsForStringsRegexp$RegexMatchModel(java.util.regex.Pattern, java.lang.String);
    Code:
       0: aload_0
       1: invokespecial #2                  // Method java/lang/Object."<init>":()V
       4: aload_0
       5: aload_1
       6: putfield      #3                  // Field pattern:Ljava/util/regex/Pattern;
       9: aload_0
      10: aload_2
      11: putfield      #4                  // Field input:Ljava/lang/String;
      14: return

  public freemarker.template.TemplateModel get(int) throws freemarker.template.TemplateModelException;
    Code:
       0: aload_0
       1: getfield      #1                  // Field matchingInputParts:Ljava/util/ArrayList;
       4: astore_2
       5: aload_2
       6: ifnonnull     14
       9: aload_0
      10: invokespecial #5                  // Method getMatchingInputPartsAndStoreResults:()Ljava/util/ArrayList;
      13: astore_2
      14: aload_2
      15: iload_1
      16: invokevirtual #6                  // Method java/util/ArrayList.get:(I)Ljava/lang/Object;
      19: checkcast     #7                  // class freemarker/template/TemplateModel
      22: areturn

  public boolean getAsBoolean();
    Code:
       0: aload_0
       1: getfield      #8                  // Field entireInputMatched:Ljava/lang/Boolean;
       4: astore_1
       5: aload_1
       6: ifnull        16
       9: aload_1
      10: invokevirtual #9                  // Method java/lang/Boolean.booleanValue:()Z
      13: goto          20
      16: aload_0
      17: invokespecial #10                 // Method isEntrieInputMatchesAndStoreResults:()Z
      20: ireturn

  freemarker.template.TemplateModel getGroups();
    Code:
       0: aload_0
       1: getfield      #11                 // Field entireInputMatchGroups:Lfreemarker/template/TemplateSequenceModel;
       4: astore_1
       5: aload_1
       6: ifnonnull     45
       9: aload_0
      10: getfield      #12                 // Field firedEntireInputMatcher:Ljava/util/regex/Matcher;
      13: astore_2
      14: aload_2
      15: ifnonnull     28
      18: aload_0
      19: invokespecial #10                 // Method isEntrieInputMatchesAndStoreResults:()Z
      22: pop
      23: aload_0
      24: getfield      #12                 // Field firedEntireInputMatcher:Ljava/util/regex/Matcher;
      27: astore_2
      28: aload_2
      29: astore_3
      30: new           #13                 // class freemarker/core/BuiltInsForStringsRegexp$RegexMatchModel$1
      33: dup
      34: aload_0
      35: aload_3
      36: invokespecial #14                 // Method freemarker/core/BuiltInsForStringsRegexp$RegexMatchModel$1."<init>":(Lfreemarker/core/BuiltInsForStringsRegexp$RegexMatchModel;Ljava/util/regex/Matcher;)V
      39: astore_1
      40: aload_0
      41: aload_1
      42: putfield      #11                 // Field entireInputMatchGroups:Lfreemarker/template/TemplateSequenceModel;
      45: aload_1
      46: areturn

  private java.util.ArrayList getMatchingInputPartsAndStoreResults() throws freemarker.template.TemplateModelException;
    Code:
       0: new           #15                 // class java/util/ArrayList
       3: dup
       4: invokespecial #16                 // Method java/util/ArrayList."<init>":()V
       7: astore_1
       8: aload_0
       9: getfield      #3                  // Field pattern:Ljava/util/regex/Pattern;
      12: aload_0
      13: getfield      #4                  // Field input:Ljava/lang/String;
      16: invokevirtual #17                 // Method java/util/regex/Pattern.matcher:(Ljava/lang/CharSequence;)Ljava/util/regex/Matcher;
      19: astore_2
      20: aload_2
      21: invokevirtual #18                 // Method java/util/regex/Matcher.find:()Z
      24: ifeq          47
      27: aload_1
      28: new           #19                 // class freemarker/core/BuiltInsForStringsRegexp$RegexMatchModel$MatchWithGroups
      31: dup
      32: aload_0
      33: getfield      #4                  // Field input:Ljava/lang/String;
      36: aload_2
      37: invokespecial #20                 // Method freemarker/core/BuiltInsForStringsRegexp$RegexMatchModel$MatchWithGroups."<init>":(Ljava/lang/String;Ljava/util/regex/Matcher;)V
      40: invokevirtual #21                 // Method java/util/ArrayList.add:(Ljava/lang/Object;)Z
      43: pop
      44: goto          20
      47: aload_0
      48: aload_1
      49: putfield      #1                  // Field matchingInputParts:Ljava/util/ArrayList;
      52: aload_1
      53: areturn

  private boolean isEntrieInputMatchesAndStoreResults();
    Code:
       0: aload_0
       1: getfield      #3                  // Field pattern:Ljava/util/regex/Pattern;
       4: aload_0
       5: getfield      #4                  // Field input:Ljava/lang/String;
       8: invokevirtual #17                 // Method java/util/regex/Pattern.matcher:(Ljava/lang/CharSequence;)Ljava/util/regex/Matcher;
      11: astore_1
      12: aload_1
      13: invokevirtual #22                 // Method java/util/regex/Matcher.matches:()Z
      16: istore_2
      17: aload_0
      18: aload_1
      19: putfield      #12                 // Field firedEntireInputMatcher:Ljava/util/regex/Matcher;
      22: aload_0
      23: iload_2
      24: invokestatic  #23                 // Method java/lang/Boolean.valueOf:(Z)Ljava/lang/Boolean;
      27: putfield      #8                  // Field entireInputMatched:Ljava/lang/Boolean;
      30: iload_2
      31: ireturn

  public freemarker.template.TemplateModelIterator iterator();
    Code:
       0: aload_0
       1: getfield      #1                  // Field matchingInputParts:Ljava/util/ArrayList;
       4: astore_1
       5: aload_1
       6: ifnonnull     31
       9: aload_0
      10: getfield      #3                  // Field pattern:Ljava/util/regex/Pattern;
      13: aload_0
      14: getfield      #4                  // Field input:Ljava/lang/String;
      17: invokevirtual #17                 // Method java/util/regex/Pattern.matcher:(Ljava/lang/CharSequence;)Ljava/util/regex/Matcher;
      20: astore_2
      21: new           #24                 // class freemarker/core/BuiltInsForStringsRegexp$RegexMatchModel$2
      24: dup
      25: aload_0
      26: aload_2
      27: invokespecial #25                 // Method freemarker/core/BuiltInsForStringsRegexp$RegexMatchModel$2."<init>":(Lfreemarker/core/BuiltInsForStringsRegexp$RegexMatchModel;Ljava/util/regex/Matcher;)V
      30: areturn
      31: new           #26                 // class freemarker/core/BuiltInsForStringsRegexp$RegexMatchModel$3
      34: dup
      35: aload_0
      36: aload_1
      37: invokespecial #27                 // Method freemarker/core/BuiltInsForStringsRegexp$RegexMatchModel$3."<init>":(Lfreemarker/core/BuiltInsForStringsRegexp$RegexMatchModel;Ljava/util/ArrayList;)V
      40: areturn

  public int size() throws freemarker.template.TemplateModelException;
    Code:
       0: aload_0
       1: getfield      #1                  // Field matchingInputParts:Ljava/util/ArrayList;
       4: astore_1
       5: aload_1
       6: ifnonnull     14
       9: aload_0
      10: invokespecial #5                  // Method getMatchingInputPartsAndStoreResults:()Ljava/util/ArrayList;
      13: astore_1
      14: aload_1
      15: invokevirtual #28                 // Method java/util/ArrayList.size:()I
      18: ireturn

  static java.util.ArrayList access$000(freemarker.core.BuiltInsForStringsRegexp$RegexMatchModel);
    Code:
       0: aload_0
       1: getfield      #1                  // Field matchingInputParts:Ljava/util/ArrayList;
       4: areturn
}
