Compiled from "BuiltInsForSequences.java"
class freemarker.core.BuiltInsForSequences$chunkBI$ChunkedSequence$1 implements freemarker.template.TemplateSequenceModel {
  private final int baseIndex;

  final int val$chunkIndex;

  final freemarker.core.BuiltInsForSequences$chunkBI$ChunkedSequence this$0;

  freemarker.core.BuiltInsForSequences$chunkBI$ChunkedSequence$1(freemarker.core.BuiltInsForSequences$chunkBI$ChunkedSequence, int);
    Code:
       0: aload_0
       1: aload_1
       2: putfield      #1                  // Field this$0:Lfreemarker/core/BuiltInsForSequences$chunkBI$ChunkedSequence;
       5: aload_0
       6: iload_2
       7: putfield      #2                  // Field val$chunkIndex:I
      10: aload_0
      11: invokespecial #3                  // Method java/lang/Object."<init>":()V
      14: aload_0
      15: aload_0
      16: getfield      #2                  // Field val$chunkIndex:I
      19: aload_0
      20: getfield      #1                  // Field this$0:Lfreemarker/core/BuiltInsForSequences$chunkBI$ChunkedSequence;
      23: invokestatic  #4                  // Method freemarker/core/BuiltInsForSequences$chunkBI$ChunkedSequence.access$100:(Lfreemarker/core/BuiltInsForSequences$chunkBI$ChunkedSequence;)I
      26: imul
      27: putfield      #5                  // Field baseIndex:I
      30: return

  public freemarker.template.TemplateModel get(int) throws freemarker.template.TemplateModelException;
    Code:
       0: aload_0
       1: getfield      #5                  // Field baseIndex:I
       4: iload_1
       5: iadd
       6: istore_2
       7: iload_2
       8: aload_0
       9: getfield      #1                  // Field this$0:Lfreemarker/core/BuiltInsForSequences$chunkBI$ChunkedSequence;
      12: invokestatic  #6                  // Method freemarker/core/BuiltInsForSequences$chunkBI$ChunkedSequence.access$200:(Lfreemarker/core/BuiltInsForSequences$chunkBI$ChunkedSequence;)Lfreemarker/template/TemplateSequenceModel;
      15: invokeinterface #7,  1            // InterfaceMethod freemarker/template/TemplateSequenceModel.size:()I
      20: if_icmpge     37
      23: aload_0
      24: getfield      #1                  // Field this$0:Lfreemarker/core/BuiltInsForSequences$chunkBI$ChunkedSequence;
      27: invokestatic  #6                  // Method freemarker/core/BuiltInsForSequences$chunkBI$ChunkedSequence.access$200:(Lfreemarker/core/BuiltInsForSequences$chunkBI$ChunkedSequence;)Lfreemarker/template/TemplateSequenceModel;
      30: iload_2
      31: invokeinterface #8,  2            // InterfaceMethod freemarker/template/TemplateSequenceModel.get:(I)Lfreemarker/template/TemplateModel;
      36: areturn
      37: iload_2
      38: aload_0
      39: getfield      #1                  // Field this$0:Lfreemarker/core/BuiltInsForSequences$chunkBI$ChunkedSequence;
      42: invokestatic  #9                  // Method freemarker/core/BuiltInsForSequences$chunkBI$ChunkedSequence.access$300:(Lfreemarker/core/BuiltInsForSequences$chunkBI$ChunkedSequence;)I
      45: aload_0
      46: getfield      #1                  // Field this$0:Lfreemarker/core/BuiltInsForSequences$chunkBI$ChunkedSequence;
      49: invokestatic  #4                  // Method freemarker/core/BuiltInsForSequences$chunkBI$ChunkedSequence.access$100:(Lfreemarker/core/BuiltInsForSequences$chunkBI$ChunkedSequence;)I
      52: imul
      53: if_icmpge     66
      56: aload_0
      57: getfield      #1                  // Field this$0:Lfreemarker/core/BuiltInsForSequences$chunkBI$ChunkedSequence;
      60: invokestatic  #10                 // Method freemarker/core/BuiltInsForSequences$chunkBI$ChunkedSequence.access$400:(Lfreemarker/core/BuiltInsForSequences$chunkBI$ChunkedSequence;)Lfreemarker/template/TemplateModel;
      63: goto          67
      66: aconst_null
      67: areturn

  public int size() throws freemarker.template.TemplateModelException;
    Code:
       0: aload_0
       1: getfield      #1                  // Field this$0:Lfreemarker/core/BuiltInsForSequences$chunkBI$ChunkedSequence;
       4: invokestatic  #10                 // Method freemarker/core/BuiltInsForSequences$chunkBI$ChunkedSequence.access$400:(Lfreemarker/core/BuiltInsForSequences$chunkBI$ChunkedSequence;)Lfreemarker/template/TemplateModel;
       7: ifnonnull     26
      10: aload_0
      11: getfield      #2                  // Field val$chunkIndex:I
      14: iconst_1
      15: iadd
      16: aload_0
      17: getfield      #1                  // Field this$0:Lfreemarker/core/BuiltInsForSequences$chunkBI$ChunkedSequence;
      20: invokestatic  #9                  // Method freemarker/core/BuiltInsForSequences$chunkBI$ChunkedSequence.access$300:(Lfreemarker/core/BuiltInsForSequences$chunkBI$ChunkedSequence;)I
      23: if_icmpge     36
      26: aload_0
      27: getfield      #1                  // Field this$0:Lfreemarker/core/BuiltInsForSequences$chunkBI$ChunkedSequence;
      30: invokestatic  #4                  // Method freemarker/core/BuiltInsForSequences$chunkBI$ChunkedSequence.access$100:(Lfreemarker/core/BuiltInsForSequences$chunkBI$ChunkedSequence;)I
      33: goto          53
      36: aload_0
      37: getfield      #1                  // Field this$0:Lfreemarker/core/BuiltInsForSequences$chunkBI$ChunkedSequence;
      40: invokestatic  #6                  // Method freemarker/core/BuiltInsForSequences$chunkBI$ChunkedSequence.access$200:(Lfreemarker/core/BuiltInsForSequences$chunkBI$ChunkedSequence;)Lfreemarker/template/TemplateSequenceModel;
      43: invokeinterface #7,  1            // InterfaceMethod freemarker/template/TemplateSequenceModel.size:()I
      48: aload_0
      49: getfield      #5                  // Field baseIndex:I
      52: isub
      53: ireturn
}
