Compiled from "BuiltInsForStringsRegexp.java"
class freemarker.core.BuiltInsForStringsRegexp$RegexMatchModel$1 implements freemarker.template.TemplateSequenceModel {
  final java.util.regex.Matcher val$firedEntireInputMatcher;

  final freemarker.core.BuiltInsForStringsRegexp$RegexMatchModel this$0;

  freemarker.core.BuiltInsForStringsRegexp$RegexMatchModel$1(freemarker.core.BuiltInsForStringsRegexp$RegexMatchModel, java.util.regex.Matcher);
    Code:
       0: aload_0
       1: aload_1
       2: putfield      #1                  // Field this$0:Lfreemarker/core/BuiltInsForStringsRegexp$RegexMatchModel;
       5: aload_0
       6: aload_2
       7: putfield      #2                  // Field val$firedEntireInputMatcher:Ljava/util/regex/Matcher;
      10: aload_0
      11: invokespecial #3                  // Method java/lang/Object."<init>":()V
      14: return

  public freemarker.template.TemplateModel get(int) throws freemarker.template.TemplateModelException;
    Code:
       0: new           #4                  // class freemarker/template/SimpleScalar
       3: dup
       4: aload_0
       5: getfield      #2                  // Field val$firedEntireInputMatcher:Ljava/util/regex/Matcher;
       8: iload_1
       9: invokevirtual #5                  // Method java/util/regex/Matcher.group:(I)Ljava/lang/String;
      12: invokespecial #6                  // Method freemarker/template/SimpleScalar."<init>":(Ljava/lang/String;)V
      15: areturn
      16: astore_2
      17: new           #8                  // class freemarker/core/_TemplateModelException
      20: dup
      21: aload_2
      22: ldc           #9                  // String Failed to read match group
      24: invokespecial #10                 // Method freemarker/core/_TemplateModelException."<init>":(Ljava/lang/Throwable;Ljava/lang/String;)V
      27: athrow
    Exception table:
       from    to  target type
           0    15    16   Class java/lang/Exception

  public int size() throws freemarker.template.TemplateModelException;
    Code:
       0: aload_0
       1: getfield      #2                  // Field val$firedEntireInputMatcher:Ljava/util/regex/Matcher;
       4: invokevirtual #11                 // Method java/util/regex/Matcher.groupCount:()I
       7: iconst_1
       8: iadd
       9: ireturn
      10: astore_1
      11: new           #8                  // class freemarker/core/_TemplateModelException
      14: dup
      15: aload_1
      16: ldc           #12                 // String Failed to get match group count
      18: invokespecial #10                 // Method freemarker/core/_TemplateModelException."<init>":(Ljava/lang/Throwable;Ljava/lang/String;)V
      21: athrow
    Exception table:
       from    to  target type
           0     9    10   Class java/lang/Exception
}
