Compiled from "Configurable.java"
public class freemarker.core.Configurable$SettingValueAssignmentException extends freemarker.core._MiscTemplateException {
  private freemarker.core.Configurable$SettingValueAssignmentException(freemarker.core.Environment, java.lang.String, java.lang.String, java.lang.Throwable);
    Code:
       0: aload_0
       1: aload         4
       3: aload_1
       4: iconst_5
       5: anewarray     #2                  // class java/lang/Object
       8: dup
       9: iconst_0
      10: ldc           #3                  // String Failed to set FreeMarker configuration setting
      12: aastore
      13: dup
      14: iconst_1
      15: new           #4                  // class freemarker/core/_DelayedJQuote
      18: dup
      19: aload_2
      20: invokespecial #5                  // Method freemarker/core/_DelayedJQuote."<init>":(Ljava/lang/Object;)V
      23: aastore
      24: dup
      25: iconst_2
      26: ldc           #6                  // String  to value
      28: aastore
      29: dup
      30: iconst_3
      31: new           #4                  // class freemarker/core/_DelayedJQuote
      34: dup
      35: aload_3
      36: invokespecial #5                  // Method freemarker/core/_DelayedJQuote."<init>":(Ljava/lang/Object;)V
      39: aastore
      40: dup
      41: iconst_4
      42: ldc           #7                  // String ; see cause exception.
      44: aastore
      45: invokespecial #8                  // Method freemarker/core/_MiscTemplateException."<init>":(Ljava/lang/Throwable;Lfreemarker/core/Environment;[Ljava/lang/Object;)V
      48: return

  freemarker.core.Configurable$SettingValueAssignmentException(freemarker.core.Environment, java.lang.String, java.lang.String, java.lang.Throwable, freemarker.core.Configurable$1);
    Code:
       0: aload_0
       1: aload_1
       2: aload_2
       3: aload_3
       4: aload         4
       6: invokespecial #1                  // Method "<init>":(Lfreemarker/core/Environment;Ljava/lang/String;Ljava/lang/String;Ljava/lang/Throwable;)V
       9: return
}
