Compiled from "DebugBreak.java"
public class freemarker.core.DebugBreak extends freemarker.core.TemplateElement {
  public freemarker.core.DebugBreak(freemarker.core.TemplateElement);
    Code:
       0: aload_0
       1: invokespecial #1                  // Method freemarker/core/TemplateElement."<init>":()V
       4: aload_0
       5: aload_1
       6: invokevirtual #2                  // Method addChild:(Lfreemarker/core/TemplateElement;)V
       9: aload_0
      10: aload_1
      11: invokevirtual #3                  // Method copyLocationFrom:(Lfreemarker/core/TemplateObject;)Lfreemarker/core/TemplateObject;
      14: pop
      15: return

  protected freemarker.core.TemplateElement[] accept(freemarker.core.Environment) throws freemarker.template.TemplateException, java.io.IOException;
    Code:
       0: aload_1
       1: aload_0
       2: invokevirtual #4                  // Method getTemplate:()Lfreemarker/template/Template;
       5: invokevirtual #5                  // Method freemarker/template/Template.getSourceName:()Ljava/lang/String;
       8: aload_0
       9: iconst_0
      10: invokevirtual #6                  // Method getChild:(I)Lfreemarker/core/TemplateElement;
      13: invokevirtual #7                  // Method freemarker/core/TemplateElement.getBeginLine:()I
      16: invokestatic  #8                  // Method freemarker/debug/impl/DebuggerService.suspendEnvironment:(Lfreemarker/core/Environment;Ljava/lang/String;I)Z
      19: ifne          32
      22: aload_0
      23: iconst_0
      24: invokevirtual #6                  // Method getChild:(I)Lfreemarker/core/TemplateElement;
      27: aload_1
      28: invokevirtual #9                  // Method freemarker/core/TemplateElement.accept:(Lfreemarker/core/Environment;)[Lfreemarker/core/TemplateElement;
      31: areturn
      32: new           #10                 // class freemarker/core/StopException
      35: dup
      36: aload_1
      37: ldc           #11                 // String Stopped by debugger
      39: invokespecial #12                 // Method freemarker/core/StopException."<init>":(Lfreemarker/core/Environment;Ljava/lang/String;)V
      42: athrow

  protected java.lang.String dump(boolean);
    Code:
       0: iload_1
       1: ifeq          75
       4: new           #13                 // class java/lang/StringBuilder
       7: dup
       8: invokespecial #14                 // Method java/lang/StringBuilder."<init>":()V
      11: astore_2
      12: aload_2
      13: ldc           #15                 // String <#--
      15: invokevirtual #16                 // Method java/lang/StringBuilder.append:(Ljava/lang/String;)Ljava/lang/StringBuilder;
      18: pop
      19: aload_2
      20: ldc           #17                 // String debug break
      22: invokevirtual #16                 // Method java/lang/StringBuilder.append:(Ljava/lang/String;)Ljava/lang/StringBuilder;
      25: pop
      26: aload_0
      27: invokevirtual #18                 // Method getChildCount:()I
      30: ifne          43
      33: aload_2
      34: ldc           #19                 // String  /-->
      36: invokevirtual #16                 // Method java/lang/StringBuilder.append:(Ljava/lang/String;)Ljava/lang/StringBuilder;
      39: pop
      40: goto          70
      43: aload_2
      44: ldc           #20                 // String  -->
      46: invokevirtual #16                 // Method java/lang/StringBuilder.append:(Ljava/lang/String;)Ljava/lang/StringBuilder;
      49: pop
      50: aload_2
      51: aload_0
      52: iconst_0
      53: invokevirtual #6                  // Method getChild:(I)Lfreemarker/core/TemplateElement;
      56: invokevirtual #21                 // Method freemarker/core/TemplateElement.getCanonicalForm:()Ljava/lang/String;
      59: invokevirtual #16                 // Method java/lang/StringBuilder.append:(Ljava/lang/String;)Ljava/lang/StringBuilder;
      62: pop
      63: aload_2
      64: ldc           #22                 // String <#--/ debug break -->
      66: invokevirtual #16                 // Method java/lang/StringBuilder.append:(Ljava/lang/String;)Ljava/lang/StringBuilder;
      69: pop
      70: aload_2
      71: invokevirtual #23                 // Method java/lang/StringBuilder.toString:()Ljava/lang/String;
      74: areturn
      75: ldc           #17                 // String debug break
      77: areturn

  java.lang.String getNodeTypeSymbol();
    Code:
       0: ldc           #24                 // String #debug_break
       2: areturn

  int getParameterCount();
    Code:
       0: iconst_0
       1: ireturn

  java.lang.Object getParameterValue(int);
    Code:
       0: new           #25                 // class java/lang/IndexOutOfBoundsException
       3: dup
       4: invokespecial #26                 // Method java/lang/IndexOutOfBoundsException."<init>":()V
       7: athrow

  freemarker.core.ParameterRole getParameterRole(int);
    Code:
       0: new           #25                 // class java/lang/IndexOutOfBoundsException
       3: dup
       4: invokespecial #26                 // Method java/lang/IndexOutOfBoundsException."<init>":()V
       7: athrow

  boolean isNestedBlockRepeater();
    Code:
       0: iconst_0
       1: ireturn
}
