Compiled from "InvalidFormatParametersException.java"
public final class freemarker.core.InvalidFormatParametersException extends freemarker.core.InvalidFormatStringException {
  public freemarker.core.InvalidFormatParametersException(java.lang.String, java.lang.Throwable);
    Code:
       0: aload_0
       1: aload_1
       2: aload_2
       3: invokespecial #1                  // Method freemarker/core/InvalidFormatStringException."<init>":(Ljava/lang/String;Ljava/lang/Throwable;)V
       6: return

  public freemarker.core.InvalidFormatParametersException(java.lang.String);
    Code:
       0: aload_0
       1: aload_1
       2: aconst_null
       3: invokespecial #2                  // Method "<init>":(Ljava/lang/String;Ljava/lang/Throwable;)V
       6: return
}
