Compiled from "SKSpannedStringBuilder.kt"
public final class tech.skot.core.view.SKSpannedStringBuilder$Context {
  private final tech.skot.core.view.SKSpan$Format format;

  final tech.skot.core.view.SKSpannedStringBuilder this$0;

  public tech.skot.core.view.SKSpannedStringBuilder$Context(tech.skot.core.view.SKSpan$Format);
    Code:
       0: aload_2
       1: ldc           #10                 // String format
       3: invokestatic  #16                 // Method kotlin/jvm/internal/Intrinsics.checkNotNullParameter:(Ljava/lang/Object;Ljava/lang/String;)V
       6: aload_0
       7: aload_1
       8: putfield      #20                 // Field this$0:Ltech/skot/core/view/SKSpannedStringBuilder;
      11: aload_0
      12: invokespecial #23                 // Method java/lang/Object."<init>":()V
      15: aload_0
      16: aload_2
      17: putfield      #26                 // Field format:Ltech/skot/core/view/SKSpan$Format;
      20: return

  public final tech.skot.core.view.SKSpan$Format getFormat();
    Code:
       0: aload_0
       1: getfield      #26                 // Field format:Ltech/skot/core/view/SKSpan$Format;
       4: areturn

  public final void append(java.lang.String);
    Code:
       0: aload_1
       1: ldc           #34                 // String text
       3: invokestatic  #16                 // Method kotlin/jvm/internal/Intrinsics.checkNotNullParameter:(Ljava/lang/Object;Ljava/lang/String;)V
       6: aload_0
       7: getfield      #20                 // Field this$0:Ltech/skot/core/view/SKSpannedStringBuilder;
      10: invokevirtual #40                 // Method tech/skot/core/view/SKSpannedStringBuilder.getSpans:()Ljava/util/List;
      13: new           #42                 // class tech/skot/core/view/SKSpan
      16: dup
      17: aload_1
      18: aload_0
      19: getfield      #26                 // Field format:Ltech/skot/core/view/SKSpan$Format;
      22: invokespecial #45                 // Method tech/skot/core/view/SKSpan."<init>":(Ljava/lang/String;Ltech/skot/core/view/SKSpan$Format;)V
      25: invokeinterface #51,  2           // InterfaceMethod java/util/List.add:(Ljava/lang/Object;)Z
      30: pop
      31: return

  public final void bold(kotlin.jvm.functions.Function1<? super tech.skot.core.view.SKSpannedStringBuilder$Context, kotlin.Unit>);
    Code:
       0: aload_1
       1: ldc           #57                 // String block
       3: invokestatic  #16                 // Method kotlin/jvm/internal/Intrinsics.checkNotNullParameter:(Ljava/lang/Object;Ljava/lang/String;)V
       6: new           #2                  // class tech/skot/core/view/SKSpannedStringBuilder$Context
       9: dup
      10: aload_0
      11: getfield      #20                 // Field this$0:Ltech/skot/core/view/SKSpannedStringBuilder;
      14: aload_0
      15: getfield      #26                 // Field format:Ltech/skot/core/view/SKSpan$Format;
      18: getstatic     #63                 // Field tech/skot/core/view/SKSpan$Bold.INSTANCE:Ltech/skot/core/view/SKSpan$Bold;
      21: checkcast     #65                 // class tech/skot/core/view/SKSpan$TypeFace
      24: aconst_null
      25: aconst_null
      26: iconst_0
      27: iconst_0
      28: aconst_null
      29: bipush        62
      31: aconst_null
      32: invokestatic  #71                 // Method tech/skot/core/view/SKSpan$Format.copy$default:(Ltech/skot/core/view/SKSpan$Format;Ltech/skot/core/view/SKSpan$TypeFace;Ltech/skot/core/view/Color;Ljava/lang/Float;ZZLkotlin/jvm/functions/Function0;ILjava/lang/Object;)Ltech/skot/core/view/SKSpan$Format;
      35: invokespecial #73                 // Method "<init>":(Ltech/skot/core/view/SKSpannedStringBuilder;Ltech/skot/core/view/SKSpan$Format;)V
      38: astore_2
      39: aload_1
      40: aload_2
      41: invokeinterface #79,  2           // InterfaceMethod kotlin/jvm/functions/Function1.invoke:(Ljava/lang/Object;)Ljava/lang/Object;
      46: pop
      47: return

  public final void font(tech.skot.core.view.Font, kotlin.jvm.functions.Function1<? super tech.skot.core.view.SKSpannedStringBuilder$Context, kotlin.Unit>);
    Code:
       0: aload_1
       1: ldc           #84                 // String font
       3: invokestatic  #16                 // Method kotlin/jvm/internal/Intrinsics.checkNotNullParameter:(Ljava/lang/Object;Ljava/lang/String;)V
       6: aload_2
       7: ldc           #57                 // String block
       9: invokestatic  #16                 // Method kotlin/jvm/internal/Intrinsics.checkNotNullParameter:(Ljava/lang/Object;Ljava/lang/String;)V
      12: new           #2                  // class tech/skot/core/view/SKSpannedStringBuilder$Context
      15: dup
      16: aload_0
      17: getfield      #20                 // Field this$0:Ltech/skot/core/view/SKSpannedStringBuilder;
      20: aload_0
      21: getfield      #26                 // Field format:Ltech/skot/core/view/SKSpan$Format;
      24: new           #86                 // class tech/skot/core/view/SKSpan$WithFont
      27: dup
      28: aload_1
      29: invokespecial #89                 // Method tech/skot/core/view/SKSpan$WithFont."<init>":(Ltech/skot/core/view/Font;)V
      32: checkcast     #65                 // class tech/skot/core/view/SKSpan$TypeFace
      35: aconst_null
      36: aconst_null
      37: iconst_0
      38: iconst_0
      39: aconst_null
      40: bipush        62
      42: aconst_null
      43: invokestatic  #71                 // Method tech/skot/core/view/SKSpan$Format.copy$default:(Ltech/skot/core/view/SKSpan$Format;Ltech/skot/core/view/SKSpan$TypeFace;Ltech/skot/core/view/Color;Ljava/lang/Float;ZZLkotlin/jvm/functions/Function0;ILjava/lang/Object;)Ltech/skot/core/view/SKSpan$Format;
      46: invokespecial #73                 // Method "<init>":(Ltech/skot/core/view/SKSpannedStringBuilder;Ltech/skot/core/view/SKSpan$Format;)V
      49: astore_3
      50: aload_2
      51: aload_3
      52: invokeinterface #79,  2           // InterfaceMethod kotlin/jvm/functions/Function1.invoke:(Ljava/lang/Object;)Ljava/lang/Object;
      57: pop
      58: return

  public final void colored(tech.skot.core.view.Color, kotlin.jvm.functions.Function1<? super tech.skot.core.view.SKSpannedStringBuilder$Context, kotlin.Unit>);
    Code:
       0: aload_1
       1: ldc           #95                 // String color
       3: invokestatic  #16                 // Method kotlin/jvm/internal/Intrinsics.checkNotNullParameter:(Ljava/lang/Object;Ljava/lang/String;)V
       6: aload_2
       7: ldc           #57                 // String block
       9: invokestatic  #16                 // Method kotlin/jvm/internal/Intrinsics.checkNotNullParameter:(Ljava/lang/Object;Ljava/lang/String;)V
      12: new           #2                  // class tech/skot/core/view/SKSpannedStringBuilder$Context
      15: dup
      16: aload_0
      17: getfield      #20                 // Field this$0:Ltech/skot/core/view/SKSpannedStringBuilder;
      20: aload_0
      21: getfield      #26                 // Field format:Ltech/skot/core/view/SKSpan$Format;
      24: aconst_null
      25: aload_1
      26: aconst_null
      27: iconst_0
      28: iconst_0
      29: aconst_null
      30: bipush        61
      32: aconst_null
      33: invokestatic  #71                 // Method tech/skot/core/view/SKSpan$Format.copy$default:(Ltech/skot/core/view/SKSpan$Format;Ltech/skot/core/view/SKSpan$TypeFace;Ltech/skot/core/view/Color;Ljava/lang/Float;ZZLkotlin/jvm/functions/Function0;ILjava/lang/Object;)Ltech/skot/core/view/SKSpan$Format;
      36: invokespecial #73                 // Method "<init>":(Ltech/skot/core/view/SKSpannedStringBuilder;Ltech/skot/core/view/SKSpan$Format;)V
      39: astore_3
      40: aload_2
      41: aload_3
      42: invokeinterface #79,  2           // InterfaceMethod kotlin/jvm/functions/Function1.invoke:(Ljava/lang/Object;)Ljava/lang/Object;
      47: pop
      48: return

  public final void scale(float, kotlin.jvm.functions.Function1<? super tech.skot.core.view.SKSpannedStringBuilder$Context, kotlin.Unit>);
    Code:
       0: aload_2
       1: ldc           #57                 // String block
       3: invokestatic  #16                 // Method kotlin/jvm/internal/Intrinsics.checkNotNullParameter:(Ljava/lang/Object;Ljava/lang/String;)V
       6: new           #2                  // class tech/skot/core/view/SKSpannedStringBuilder$Context
       9: dup
      10: aload_0
      11: getfield      #20                 // Field this$0:Ltech/skot/core/view/SKSpannedStringBuilder;
      14: aload_0
      15: getfield      #26                 // Field format:Ltech/skot/core/view/SKSpan$Format;
      18: aconst_null
      19: aconst_null
      20: fload_1
      21: invokestatic  #105                // Method java/lang/Float.valueOf:(F)Ljava/lang/Float;
      24: iconst_0
      25: iconst_0
      26: aconst_null
      27: bipush        59
      29: aconst_null
      30: invokestatic  #71                 // Method tech/skot/core/view/SKSpan$Format.copy$default:(Ltech/skot/core/view/SKSpan$Format;Ltech/skot/core/view/SKSpan$TypeFace;Ltech/skot/core/view/Color;Ljava/lang/Float;ZZLkotlin/jvm/functions/Function0;ILjava/lang/Object;)Ltech/skot/core/view/SKSpan$Format;
      33: invokespecial #73                 // Method "<init>":(Ltech/skot/core/view/SKSpannedStringBuilder;Ltech/skot/core/view/SKSpan$Format;)V
      36: astore_3
      37: aload_2
      38: aload_3
      39: invokeinterface #79,  2           // InterfaceMethod kotlin/jvm/functions/Function1.invoke:(Ljava/lang/Object;)Ljava/lang/Object;
      44: pop
      45: return

  public final void clickable(kotlin.jvm.functions.Function0<kotlin.Unit>, kotlin.jvm.functions.Function1<? super tech.skot.core.view.SKSpannedStringBuilder$Context, kotlin.Unit>);
    Code:
       0: aload_1
       1: ldc           #111                // String onTap
       3: invokestatic  #16                 // Method kotlin/jvm/internal/Intrinsics.checkNotNullParameter:(Ljava/lang/Object;Ljava/lang/String;)V
       6: aload_2
       7: ldc           #57                 // String block
       9: invokestatic  #16                 // Method kotlin/jvm/internal/Intrinsics.checkNotNullParameter:(Ljava/lang/Object;Ljava/lang/String;)V
      12: new           #2                  // class tech/skot/core/view/SKSpannedStringBuilder$Context
      15: dup
      16: aload_0
      17: getfield      #20                 // Field this$0:Ltech/skot/core/view/SKSpannedStringBuilder;
      20: aload_0
      21: getfield      #26                 // Field format:Ltech/skot/core/view/SKSpan$Format;
      24: aconst_null
      25: aconst_null
      26: aconst_null
      27: iconst_0
      28: iconst_0
      29: aload_1
      30: bipush        31
      32: aconst_null
      33: invokestatic  #71                 // Method tech/skot/core/view/SKSpan$Format.copy$default:(Ltech/skot/core/view/SKSpan$Format;Ltech/skot/core/view/SKSpan$TypeFace;Ltech/skot/core/view/Color;Ljava/lang/Float;ZZLkotlin/jvm/functions/Function0;ILjava/lang/Object;)Ltech/skot/core/view/SKSpan$Format;
      36: invokespecial #73                 // Method "<init>":(Ltech/skot/core/view/SKSpannedStringBuilder;Ltech/skot/core/view/SKSpan$Format;)V
      39: astore_3
      40: aload_2
      41: aload_3
      42: invokeinterface #79,  2           // InterfaceMethod kotlin/jvm/functions/Function1.invoke:(Ljava/lang/Object;)Ljava/lang/Object;
      47: pop
      48: return

  public final void underline(kotlin.jvm.functions.Function1<? super tech.skot.core.view.SKSpannedStringBuilder$Context, kotlin.Unit>);
    Code:
       0: aload_1
       1: ldc           #57                 // String block
       3: invokestatic  #16                 // Method kotlin/jvm/internal/Intrinsics.checkNotNullParameter:(Ljava/lang/Object;Ljava/lang/String;)V
       6: new           #2                  // class tech/skot/core/view/SKSpannedStringBuilder$Context
       9: dup
      10: aload_0
      11: getfield      #20                 // Field this$0:Ltech/skot/core/view/SKSpannedStringBuilder;
      14: aload_0
      15: getfield      #26                 // Field format:Ltech/skot/core/view/SKSpan$Format;
      18: aconst_null
      19: aconst_null
      20: aconst_null
      21: iconst_1
      22: iconst_0
      23: aconst_null
      24: bipush        55
      26: aconst_null
      27: invokestatic  #71                 // Method tech/skot/core/view/SKSpan$Format.copy$default:(Ltech/skot/core/view/SKSpan$Format;Ltech/skot/core/view/SKSpan$TypeFace;Ltech/skot/core/view/Color;Ljava/lang/Float;ZZLkotlin/jvm/functions/Function0;ILjava/lang/Object;)Ltech/skot/core/view/SKSpan$Format;
      30: invokespecial #73                 // Method "<init>":(Ltech/skot/core/view/SKSpannedStringBuilder;Ltech/skot/core/view/SKSpan$Format;)V
      33: astore_2
      34: aload_1
      35: aload_2
      36: invokeinterface #79,  2           // InterfaceMethod kotlin/jvm/functions/Function1.invoke:(Ljava/lang/Object;)Ljava/lang/Object;
      41: pop
      42: return

  public final void striked(kotlin.jvm.functions.Function1<? super tech.skot.core.view.SKSpannedStringBuilder$Context, kotlin.Unit>);
    Code:
       0: aload_1
       1: ldc           #57                 // String block
       3: invokestatic  #16                 // Method kotlin/jvm/internal/Intrinsics.checkNotNullParameter:(Ljava/lang/Object;Ljava/lang/String;)V
       6: new           #2                  // class tech/skot/core/view/SKSpannedStringBuilder$Context
       9: dup
      10: aload_0
      11: getfield      #20                 // Field this$0:Ltech/skot/core/view/SKSpannedStringBuilder;
      14: aload_0
      15: getfield      #26                 // Field format:Ltech/skot/core/view/SKSpan$Format;
      18: aconst_null
      19: aconst_null
      20: aconst_null
      21: iconst_0
      22: iconst_1
      23: aconst_null
      24: bipush        47
      26: aconst_null
      27: invokestatic  #71                 // Method tech/skot/core/view/SKSpan$Format.copy$default:(Ltech/skot/core/view/SKSpan$Format;Ltech/skot/core/view/SKSpan$TypeFace;Ltech/skot/core/view/Color;Ljava/lang/Float;ZZLkotlin/jvm/functions/Function0;ILjava/lang/Object;)Ltech/skot/core/view/SKSpan$Format;
      30: invokespecial #73                 // Method "<init>":(Ltech/skot/core/view/SKSpannedStringBuilder;Ltech/skot/core/view/SKSpan$Format;)V
      33: astore_2
      34: aload_1
      35: aload_2
      36: invokeinterface #79,  2           // InterfaceMethod kotlin/jvm/functions/Function1.invoke:(Ljava/lang/Object;)Ljava/lang/Object;
      41: pop
      42: return
}
