Compiled from "JeeNamespaceHandler.java"
public class org.springframework.ejb.config.JeeNamespaceHandler extends org.springframework.beans.factory.xml.NamespaceHandlerSupport {
  public org.springframework.ejb.config.JeeNamespaceHandler();
    Code:
       0: aload_0
       1: invokespecial #1                  // Method org/springframework/beans/factory/xml/NamespaceHandlerSupport."<init>":()V
       4: return

  public void init();
    Code:
       0: aload_0
       1: ldc           #2                  // String jndi-lookup
       3: new           #3                  // class org/springframework/ejb/config/JndiLookupBeanDefinitionParser
       6: dup
       7: invokespecial #4                  // Method org/springframework/ejb/config/JndiLookupBeanDefinitionParser."<init>":()V
      10: invokevirtual #5                  // Method registerBeanDefinitionParser:(Ljava/lang/String;Lorg/springframework/beans/factory/xml/BeanDefinitionParser;)V
      13: aload_0
      14: ldc           #6                  // String local-slsb
      16: new           #7                  // class org/springframework/ejb/config/LocalStatelessSessionBeanDefinitionParser
      19: dup
      20: invokespecial #8                  // Method org/springframework/ejb/config/LocalStatelessSessionBeanDefinitionParser."<init>":()V
      23: invokevirtual #5                  // Method registerBeanDefinitionParser:(Ljava/lang/String;Lorg/springframework/beans/factory/xml/BeanDefinitionParser;)V
      26: aload_0
      27: ldc           #9                  // String remote-slsb
      29: new           #10                 // class org/springframework/ejb/config/RemoteStatelessSessionBeanDefinitionParser
      32: dup
      33: invokespecial #11                 // Method org/springframework/ejb/config/RemoteStatelessSessionBeanDefinitionParser."<init>":()V
      36: invokevirtual #5                  // Method registerBeanDefinitionParser:(Ljava/lang/String;Lorg/springframework/beans/factory/xml/BeanDefinitionParser;)V
      39: return
}
