Compiled from "OioDatagramChannel.java"
public class io.netty.channel.socket.oio.OioDatagramChannel extends io.netty.channel.oio.AbstractOioMessageChannel implements io.netty.channel.socket.DatagramChannel {
  private static final io.netty.util.internal.logging.InternalLogger logger;

  private static final io.netty.channel.ChannelMetadata METADATA;

  private static final java.lang.String EXPECTED_TYPES;

  private final java.net.MulticastSocket socket;

  private final io.netty.channel.socket.oio.OioDatagramChannelConfig config;

  private final java.net.DatagramPacket tmpPacket;

  private static java.net.MulticastSocket newSocket();
    Code:
       0: new           #1                  // class java/net/MulticastSocket
       3: dup
       4: aconst_null
       5: invokespecial #2                  // Method java/net/MulticastSocket."<init>":(Ljava/net/SocketAddress;)V
       8: areturn
       9: astore_0
      10: new           #4                  // class io/netty/channel/ChannelException
      13: dup
      14: ldc           #5                  // String failed to create a new socket
      16: aload_0
      17: invokespecial #6                  // Method io/netty/channel/ChannelException."<init>":(Ljava/lang/String;Ljava/lang/Throwable;)V
      20: athrow
    Exception table:
       from    to  target type
           0     8     9   Class java/lang/Exception

  public io.netty.channel.socket.oio.OioDatagramChannel();
    Code:
       0: aload_0
       1: invokestatic  #7                  // Method newSocket:()Ljava/net/MulticastSocket;
       4: invokespecial #8                  // Method "<init>":(Ljava/net/MulticastSocket;)V
       7: return

  public io.netty.channel.socket.oio.OioDatagramChannel(java.net.MulticastSocket);
    Code:
       0: aload_0
       1: aconst_null
       2: invokespecial #9                  // Method io/netty/channel/oio/AbstractOioMessageChannel."<init>":(Lio/netty/channel/Channel;)V
       5: aload_0
       6: new           #10                 // class java/net/DatagramPacket
       9: dup
      10: getstatic     #11                 // Field io/netty/util/internal/EmptyArrays.EMPTY_BYTES:[B
      13: iconst_0
      14: invokespecial #12                 // Method java/net/DatagramPacket."<init>":([BI)V
      17: putfield      #13                 // Field tmpPacket:Ljava/net/DatagramPacket;
      20: iconst_0
      21: istore_2
      22: aload_1
      23: sipush        1000
      26: invokevirtual #15                 // Method java/net/MulticastSocket.setSoTimeout:(I)V
      29: aload_1
      30: iconst_0
      31: invokevirtual #16                 // Method java/net/MulticastSocket.setBroadcast:(Z)V
      34: iconst_1
      35: istore_2
      36: iload_2
      37: ifne          72
      40: aload_1
      41: invokevirtual #17                 // Method java/net/MulticastSocket.close:()V
      44: goto          72
      47: astore_3
      48: new           #4                  // class io/netty/channel/ChannelException
      51: dup
      52: ldc           #19                 // String Failed to configure the datagram socket timeout.
      54: aload_3
      55: invokespecial #6                  // Method io/netty/channel/ChannelException."<init>":(Ljava/lang/String;Ljava/lang/Throwable;)V
      58: athrow
      59: astore        4
      61: iload_2
      62: ifne          69
      65: aload_1
      66: invokevirtual #17                 // Method java/net/MulticastSocket.close:()V
      69: aload         4
      71: athrow
      72: aload_0
      73: aload_1
      74: putfield      #20                 // Field socket:Ljava/net/MulticastSocket;
      77: aload_0
      78: new           #21                 // class io/netty/channel/socket/oio/DefaultOioDatagramChannelConfig
      81: dup
      82: aload_0
      83: aload_1
      84: invokespecial #22                 // Method io/netty/channel/socket/oio/DefaultOioDatagramChannelConfig."<init>":(Lio/netty/channel/socket/DatagramChannel;Ljava/net/DatagramSocket;)V
      87: putfield      #23                 // Field config:Lio/netty/channel/socket/oio/OioDatagramChannelConfig;
      90: return
    Exception table:
       from    to  target type
          22    36    47   Class java/net/SocketException
          22    36    59   any
          47    61    59   any

  public io.netty.channel.ChannelMetadata metadata();
    Code:
       0: getstatic     #24                 // Field METADATA:Lio/netty/channel/ChannelMetadata;
       3: areturn

  public io.netty.channel.socket.DatagramChannelConfig config();
    Code:
       0: aload_0
       1: getfield      #23                 // Field config:Lio/netty/channel/socket/oio/OioDatagramChannelConfig;
       4: areturn

  public boolean isOpen();
    Code:
       0: aload_0
       1: getfield      #20                 // Field socket:Ljava/net/MulticastSocket;
       4: invokevirtual #25                 // Method java/net/MulticastSocket.isClosed:()Z
       7: ifne          14
      10: iconst_1
      11: goto          15
      14: iconst_0
      15: ireturn

  public boolean isActive();
    Code:
       0: aload_0
       1: invokevirtual #26                 // Method isOpen:()Z
       4: ifeq          49
       7: aload_0
       8: getfield      #23                 // Field config:Lio/netty/channel/socket/oio/OioDatagramChannelConfig;
      11: getstatic     #27                 // Field io/netty/channel/ChannelOption.DATAGRAM_CHANNEL_ACTIVE_ON_REGISTRATION:Lio/netty/channel/ChannelOption;
      14: invokeinterface #28,  2           // InterfaceMethod io/netty/channel/socket/oio/OioDatagramChannelConfig.getOption:(Lio/netty/channel/ChannelOption;)Ljava/lang/Object;
      19: checkcast     #29                 // class java/lang/Boolean
      22: invokevirtual #30                 // Method java/lang/Boolean.booleanValue:()Z
      25: ifeq          35
      28: aload_0
      29: invokevirtual #31                 // Method isRegistered:()Z
      32: ifne          45
      35: aload_0
      36: getfield      #20                 // Field socket:Ljava/net/MulticastSocket;
      39: invokevirtual #32                 // Method java/net/MulticastSocket.isBound:()Z
      42: ifeq          49
      45: iconst_1
      46: goto          50
      49: iconst_0
      50: ireturn

  public boolean isConnected();
    Code:
       0: aload_0
       1: getfield      #20                 // Field socket:Ljava/net/MulticastSocket;
       4: invokevirtual #33                 // Method java/net/MulticastSocket.isConnected:()Z
       7: ireturn

  protected java.net.SocketAddress localAddress0();
    Code:
       0: aload_0
       1: getfield      #20                 // Field socket:Ljava/net/MulticastSocket;
       4: invokevirtual #34                 // Method java/net/MulticastSocket.getLocalSocketAddress:()Ljava/net/SocketAddress;
       7: areturn

  protected java.net.SocketAddress remoteAddress0();
    Code:
       0: aload_0
       1: getfield      #20                 // Field socket:Ljava/net/MulticastSocket;
       4: invokevirtual #35                 // Method java/net/MulticastSocket.getRemoteSocketAddress:()Ljava/net/SocketAddress;
       7: areturn

  protected void doBind(java.net.SocketAddress) throws java.lang.Exception;
    Code:
       0: aload_0
       1: getfield      #20                 // Field socket:Ljava/net/MulticastSocket;
       4: aload_1
       5: invokevirtual #36                 // Method java/net/MulticastSocket.bind:(Ljava/net/SocketAddress;)V
       8: return

  public java.net.InetSocketAddress localAddress();
    Code:
       0: aload_0
       1: invokespecial #37                 // Method io/netty/channel/oio/AbstractOioMessageChannel.localAddress:()Ljava/net/SocketAddress;
       4: checkcast     #38                 // class java/net/InetSocketAddress
       7: areturn

  public java.net.InetSocketAddress remoteAddress();
    Code:
       0: aload_0
       1: invokespecial #39                 // Method io/netty/channel/oio/AbstractOioMessageChannel.remoteAddress:()Ljava/net/SocketAddress;
       4: checkcast     #38                 // class java/net/InetSocketAddress
       7: areturn

  protected void doConnect(java.net.SocketAddress, java.net.SocketAddress) throws java.lang.Exception;
    Code:
       0: aload_2
       1: ifnull        12
       4: aload_0
       5: getfield      #20                 // Field socket:Ljava/net/MulticastSocket;
       8: aload_2
       9: invokevirtual #36                 // Method java/net/MulticastSocket.bind:(Ljava/net/SocketAddress;)V
      12: iconst_0
      13: istore_3
      14: aload_0
      15: getfield      #20                 // Field socket:Ljava/net/MulticastSocket;
      18: aload_1
      19: invokevirtual #40                 // Method java/net/MulticastSocket.connect:(Ljava/net/SocketAddress;)V
      22: iconst_1
      23: istore_3
      24: iload_3
      25: ifne          88
      28: aload_0
      29: getfield      #20                 // Field socket:Ljava/net/MulticastSocket;
      32: invokevirtual #17                 // Method java/net/MulticastSocket.close:()V
      35: goto          88
      38: astore        4
      40: getstatic     #42                 // Field logger:Lio/netty/util/internal/logging/InternalLogger;
      43: ldc           #43                 // String Failed to close a socket.
      45: aload         4
      47: invokeinterface #44,  3           // InterfaceMethod io/netty/util/internal/logging/InternalLogger.warn:(Ljava/lang/String;Ljava/lang/Throwable;)V
      52: goto          88
      55: astore        5
      57: iload_3
      58: ifne          85
      61: aload_0
      62: getfield      #20                 // Field socket:Ljava/net/MulticastSocket;
      65: invokevirtual #17                 // Method java/net/MulticastSocket.close:()V
      68: goto          85
      71: astore        6
      73: getstatic     #42                 // Field logger:Lio/netty/util/internal/logging/InternalLogger;
      76: ldc           #43                 // String Failed to close a socket.
      78: aload         6
      80: invokeinterface #44,  3           // InterfaceMethod io/netty/util/internal/logging/InternalLogger.warn:(Ljava/lang/String;Ljava/lang/Throwable;)V
      85: aload         5
      87: athrow
      88: return
    Exception table:
       from    to  target type
          28    35    38   Class java/lang/Throwable
          14    24    55   any
          61    68    71   Class java/lang/Throwable
          55    57    55   any

  protected void doDisconnect() throws java.lang.Exception;
    Code:
       0: aload_0
       1: getfield      #20                 // Field socket:Ljava/net/MulticastSocket;
       4: invokevirtual #45                 // Method java/net/MulticastSocket.disconnect:()V
       7: return

  protected void doClose() throws java.lang.Exception;
    Code:
       0: aload_0
       1: getfield      #20                 // Field socket:Ljava/net/MulticastSocket;
       4: invokevirtual #17                 // Method java/net/MulticastSocket.close:()V
       7: return

  protected int doReadMessages(java.util.List<java.lang.Object>) throws java.lang.Exception;
    Code:
       0: aload_0
       1: invokevirtual #46                 // Method config:()Lio/netty/channel/socket/DatagramChannelConfig;
       4: astore_2
       5: aload_0
       6: invokevirtual #47                 // Method unsafe:()Lio/netty/channel/Channel$Unsafe;
       9: invokeinterface #48,  1           // InterfaceMethod io/netty/channel/Channel$Unsafe.recvBufAllocHandle:()Lio/netty/channel/RecvByteBufAllocator$Handle;
      14: astore_3
      15: aload_2
      16: invokeinterface #49,  1           // InterfaceMethod io/netty/channel/socket/DatagramChannelConfig.getAllocator:()Lio/netty/buffer/ByteBufAllocator;
      21: aload_3
      22: invokeinterface #50,  1           // InterfaceMethod io/netty/channel/RecvByteBufAllocator$Handle.guess:()I
      27: invokeinterface #51,  2           // InterfaceMethod io/netty/buffer/ByteBufAllocator.heapBuffer:(I)Lio/netty/buffer/ByteBuf;
      32: astore        4
      34: iconst_1
      35: istore        5
      37: aload_0
      38: getfield      #13                 // Field tmpPacket:Ljava/net/DatagramPacket;
      41: aconst_null
      42: invokevirtual #52                 // Method java/net/DatagramPacket.setAddress:(Ljava/net/InetAddress;)V
      45: aload_0
      46: getfield      #13                 // Field tmpPacket:Ljava/net/DatagramPacket;
      49: aload         4
      51: invokevirtual #53                 // Method io/netty/buffer/ByteBuf.array:()[B
      54: aload         4
      56: invokevirtual #54                 // Method io/netty/buffer/ByteBuf.arrayOffset:()I
      59: aload         4
      61: invokevirtual #55                 // Method io/netty/buffer/ByteBuf.capacity:()I
      64: invokevirtual #56                 // Method java/net/DatagramPacket.setData:([BII)V
      67: aload_0
      68: getfield      #20                 // Field socket:Ljava/net/MulticastSocket;
      71: aload_0
      72: getfield      #13                 // Field tmpPacket:Ljava/net/DatagramPacket;
      75: invokevirtual #57                 // Method java/net/MulticastSocket.receive:(Ljava/net/DatagramPacket;)V
      78: aload_0
      79: getfield      #13                 // Field tmpPacket:Ljava/net/DatagramPacket;
      82: invokevirtual #58                 // Method java/net/DatagramPacket.getSocketAddress:()Ljava/net/SocketAddress;
      85: checkcast     #38                 // class java/net/InetSocketAddress
      88: astore        6
      90: aload_3
      91: aload_0
      92: getfield      #13                 // Field tmpPacket:Ljava/net/DatagramPacket;
      95: invokevirtual #59                 // Method java/net/DatagramPacket.getLength:()I
      98: invokeinterface #60,  2           // InterfaceMethod io/netty/channel/RecvByteBufAllocator$Handle.lastBytesRead:(I)V
     103: aload_1
     104: new           #61                 // class io/netty/channel/socket/DatagramPacket
     107: dup
     108: aload         4
     110: aload_3
     111: invokeinterface #62,  1           // InterfaceMethod io/netty/channel/RecvByteBufAllocator$Handle.lastBytesRead:()I
     116: invokevirtual #63                 // Method io/netty/buffer/ByteBuf.writerIndex:(I)Lio/netty/buffer/ByteBuf;
     119: aload_0
     120: invokevirtual #64                 // Method localAddress:()Ljava/net/InetSocketAddress;
     123: aload         6
     125: invokespecial #65                 // Method io/netty/channel/socket/DatagramPacket."<init>":(Lio/netty/buffer/ByteBuf;Ljava/net/InetSocketAddress;Ljava/net/InetSocketAddress;)V
     128: invokeinterface #66,  2           // InterfaceMethod java/util/List.add:(Ljava/lang/Object;)Z
     133: pop
     134: iconst_0
     135: istore        5
     137: iconst_1
     138: istore        7
     140: iload         5
     142: ifeq          151
     145: aload         4
     147: invokevirtual #67                 // Method io/netty/buffer/ByteBuf.release:()Z
     150: pop
     151: iload         7
     153: ireturn
     154: astore        6
     156: iconst_0
     157: istore        7
     159: iload         5
     161: ifeq          170
     164: aload         4
     166: invokevirtual #67                 // Method io/netty/buffer/ByteBuf.release:()Z
     169: pop
     170: iload         7
     172: ireturn
     173: astore        6
     175: aload         6
     177: invokevirtual #69                 // Method java/net/SocketException.getMessage:()Ljava/lang/String;
     180: getstatic     #70                 // Field java/util/Locale.US:Ljava/util/Locale;
     183: invokevirtual #71                 // Method java/lang/String.toLowerCase:(Ljava/util/Locale;)Ljava/lang/String;
     186: ldc           #72                 // String socket closed
     188: invokevirtual #73                 // Method java/lang/String.contains:(Ljava/lang/CharSequence;)Z
     191: ifne          197
     194: aload         6
     196: athrow
     197: iconst_m1
     198: istore        7
     200: iload         5
     202: ifeq          211
     205: aload         4
     207: invokevirtual #67                 // Method io/netty/buffer/ByteBuf.release:()Z
     210: pop
     211: iload         7
     213: ireturn
     214: astore        6
     216: aload         6
     218: invokestatic  #74                 // Method io/netty/util/internal/PlatformDependent.throwException:(Ljava/lang/Throwable;)V
     221: iconst_m1
     222: istore        7
     224: iload         5
     226: ifeq          235
     229: aload         4
     231: invokevirtual #67                 // Method io/netty/buffer/ByteBuf.release:()Z
     234: pop
     235: iload         7
     237: ireturn
     238: astore        8
     240: iload         5
     242: ifeq          251
     245: aload         4
     247: invokevirtual #67                 // Method io/netty/buffer/ByteBuf.release:()Z
     250: pop
     251: aload         8
     253: athrow
    Exception table:
       from    to  target type
          37   140   154   Class java/net/SocketTimeoutException
          37   140   173   Class java/net/SocketException
          37   140   214   Class java/lang/Throwable
          37   140   238   any
         154   159   238   any
         173   200   238   any
         214   224   238   any
         238   240   238   any

  protected void doWrite(io.netty.channel.ChannelOutboundBuffer) throws java.lang.Exception;
    Code:
       0: aload_1
       1: invokevirtual #75                 // Method io/netty/channel/ChannelOutboundBuffer.current:()Ljava/lang/Object;
       4: astore_2
       5: aload_2
       6: ifnonnull     12
       9: goto          182
      12: aload_2
      13: instanceof    #76                 // class io/netty/channel/AddressedEnvelope
      16: ifeq          48
      19: aload_2
      20: checkcast     #76                 // class io/netty/channel/AddressedEnvelope
      23: astore        5
      25: aload         5
      27: invokeinterface #77,  1           // InterfaceMethod io/netty/channel/AddressedEnvelope.recipient:()Ljava/net/SocketAddress;
      32: astore        4
      34: aload         5
      36: invokeinterface #78,  1           // InterfaceMethod io/netty/channel/AddressedEnvelope.content:()Ljava/lang/Object;
      41: checkcast     #79                 // class io/netty/buffer/ByteBuf
      44: astore_3
      45: goto          56
      48: aload_2
      49: checkcast     #79                 // class io/netty/buffer/ByteBuf
      52: astore_3
      53: aconst_null
      54: astore        4
      56: aload_3
      57: invokevirtual #80                 // Method io/netty/buffer/ByteBuf.readableBytes:()I
      60: istore        5
      62: aload         4
      64: ifnull        79
      67: aload_0
      68: getfield      #13                 // Field tmpPacket:Ljava/net/DatagramPacket;
      71: aload         4
      73: invokevirtual #81                 // Method java/net/DatagramPacket.setSocketAddress:(Ljava/net/SocketAddress;)V
      76: goto          102
      79: aload_0
      80: invokevirtual #82                 // Method isConnected:()Z
      83: ifne          94
      86: new           #83                 // class java/nio/channels/NotYetConnectedException
      89: dup
      90: invokespecial #84                 // Method java/nio/channels/NotYetConnectedException."<init>":()V
      93: athrow
      94: aload_0
      95: getfield      #13                 // Field tmpPacket:Ljava/net/DatagramPacket;
      98: aconst_null
      99: invokevirtual #52                 // Method java/net/DatagramPacket.setAddress:(Ljava/net/InetAddress;)V
     102: aload_3
     103: invokevirtual #85                 // Method io/netty/buffer/ByteBuf.hasArray:()Z
     106: ifeq          134
     109: aload_0
     110: getfield      #13                 // Field tmpPacket:Ljava/net/DatagramPacket;
     113: aload_3
     114: invokevirtual #53                 // Method io/netty/buffer/ByteBuf.array:()[B
     117: aload_3
     118: invokevirtual #54                 // Method io/netty/buffer/ByteBuf.arrayOffset:()I
     121: aload_3
     122: invokevirtual #86                 // Method io/netty/buffer/ByteBuf.readerIndex:()I
     125: iadd
     126: iload         5
     128: invokevirtual #56                 // Method java/net/DatagramPacket.setData:([BII)V
     131: goto          151
     134: aload_0
     135: getfield      #13                 // Field tmpPacket:Ljava/net/DatagramPacket;
     138: aload_3
     139: aload_3
     140: invokevirtual #86                 // Method io/netty/buffer/ByteBuf.readerIndex:()I
     143: iload         5
     145: invokestatic  #87                 // Method io/netty/buffer/ByteBufUtil.getBytes:(Lio/netty/buffer/ByteBuf;II)[B
     148: invokevirtual #88                 // Method java/net/DatagramPacket.setData:([B)V
     151: aload_0
     152: getfield      #20                 // Field socket:Ljava/net/MulticastSocket;
     155: aload_0
     156: getfield      #13                 // Field tmpPacket:Ljava/net/DatagramPacket;
     159: invokevirtual #89                 // Method java/net/MulticastSocket.send:(Ljava/net/DatagramPacket;)V
     162: aload_1
     163: invokevirtual #90                 // Method io/netty/channel/ChannelOutboundBuffer.remove:()Z
     166: pop
     167: goto          179
     170: astore        6
     172: aload_1
     173: aload         6
     175: invokevirtual #91                 // Method io/netty/channel/ChannelOutboundBuffer.remove:(Ljava/lang/Throwable;)Z
     178: pop
     179: goto          0
     182: return
    Exception table:
       from    to  target type
          62   167   170   Class java/lang/Exception

  protected java.lang.Object filterOutboundMessage(java.lang.Object);
    Code:
       0: aload_1
       1: instanceof    #61                 // class io/netty/channel/socket/DatagramPacket
       4: ifne          14
       7: aload_1
       8: instanceof    #79                 // class io/netty/buffer/ByteBuf
      11: ifeq          16
      14: aload_1
      15: areturn
      16: aload_1
      17: instanceof    #76                 // class io/netty/channel/AddressedEnvelope
      20: ifeq          42
      23: aload_1
      24: checkcast     #76                 // class io/netty/channel/AddressedEnvelope
      27: astore_2
      28: aload_2
      29: invokeinterface #78,  1           // InterfaceMethod io/netty/channel/AddressedEnvelope.content:()Ljava/lang/Object;
      34: instanceof    #79                 // class io/netty/buffer/ByteBuf
      37: ifeq          42
      40: aload_1
      41: areturn
      42: new           #92                 // class java/lang/UnsupportedOperationException
      45: dup
      46: new           #93                 // class java/lang/StringBuilder
      49: dup
      50: invokespecial #94                 // Method java/lang/StringBuilder."<init>":()V
      53: ldc           #95                 // String unsupported message type:
      55: invokevirtual #96                 // Method java/lang/StringBuilder.append:(Ljava/lang/String;)Ljava/lang/StringBuilder;
      58: aload_1
      59: invokestatic  #97                 // Method io/netty/util/internal/StringUtil.simpleClassName:(Ljava/lang/Object;)Ljava/lang/String;
      62: invokevirtual #96                 // Method java/lang/StringBuilder.append:(Ljava/lang/String;)Ljava/lang/StringBuilder;
      65: getstatic     #98                 // Field EXPECTED_TYPES:Ljava/lang/String;
      68: invokevirtual #96                 // Method java/lang/StringBuilder.append:(Ljava/lang/String;)Ljava/lang/StringBuilder;
      71: invokevirtual #99                 // Method java/lang/StringBuilder.toString:()Ljava/lang/String;
      74: invokespecial #100                // Method java/lang/UnsupportedOperationException."<init>":(Ljava/lang/String;)V
      77: athrow

  public io.netty.channel.ChannelFuture joinGroup(java.net.InetAddress);
    Code:
       0: aload_0
       1: aload_1
       2: aload_0
       3: invokevirtual #101                // Method newPromise:()Lio/netty/channel/ChannelPromise;
       6: invokevirtual #102                // Method joinGroup:(Ljava/net/InetAddress;Lio/netty/channel/ChannelPromise;)Lio/netty/channel/ChannelFuture;
       9: areturn

  public io.netty.channel.ChannelFuture joinGroup(java.net.InetAddress, io.netty.channel.ChannelPromise);
    Code:
       0: aload_0
       1: invokespecial #103                // Method ensureBound:()V
       4: aload_0
       5: getfield      #20                 // Field socket:Ljava/net/MulticastSocket;
       8: aload_1
       9: invokevirtual #104                // Method java/net/MulticastSocket.joinGroup:(Ljava/net/InetAddress;)V
      12: aload_2
      13: invokeinterface #105,  1          // InterfaceMethod io/netty/channel/ChannelPromise.setSuccess:()Lio/netty/channel/ChannelPromise;
      18: pop
      19: goto          31
      22: astore_3
      23: aload_2
      24: aload_3
      25: invokeinterface #107,  2          // InterfaceMethod io/netty/channel/ChannelPromise.setFailure:(Ljava/lang/Throwable;)Lio/netty/channel/ChannelPromise;
      30: pop
      31: aload_2
      32: areturn
    Exception table:
       from    to  target type
           4    19    22   Class java/io/IOException

  public io.netty.channel.ChannelFuture joinGroup(java.net.InetSocketAddress, java.net.NetworkInterface);
    Code:
       0: aload_0
       1: aload_1
       2: aload_2
       3: aload_0
       4: invokevirtual #101                // Method newPromise:()Lio/netty/channel/ChannelPromise;
       7: invokevirtual #108                // Method joinGroup:(Ljava/net/InetSocketAddress;Ljava/net/NetworkInterface;Lio/netty/channel/ChannelPromise;)Lio/netty/channel/ChannelFuture;
      10: areturn

  public io.netty.channel.ChannelFuture joinGroup(java.net.InetSocketAddress, java.net.NetworkInterface, io.netty.channel.ChannelPromise);
    Code:
       0: aload_0
       1: invokespecial #103                // Method ensureBound:()V
       4: aload_0
       5: getfield      #20                 // Field socket:Ljava/net/MulticastSocket;
       8: aload_1
       9: aload_2
      10: invokevirtual #109                // Method java/net/MulticastSocket.joinGroup:(Ljava/net/SocketAddress;Ljava/net/NetworkInterface;)V
      13: aload_3
      14: invokeinterface #105,  1          // InterfaceMethod io/netty/channel/ChannelPromise.setSuccess:()Lio/netty/channel/ChannelPromise;
      19: pop
      20: goto          34
      23: astore        4
      25: aload_3
      26: aload         4
      28: invokeinterface #107,  2          // InterfaceMethod io/netty/channel/ChannelPromise.setFailure:(Ljava/lang/Throwable;)Lio/netty/channel/ChannelPromise;
      33: pop
      34: aload_3
      35: areturn
    Exception table:
       from    to  target type
           4    20    23   Class java/io/IOException

  public io.netty.channel.ChannelFuture joinGroup(java.net.InetAddress, java.net.NetworkInterface, java.net.InetAddress);
    Code:
       0: aload_0
       1: new           #92                 // class java/lang/UnsupportedOperationException
       4: dup
       5: invokespecial #110                // Method java/lang/UnsupportedOperationException."<init>":()V
       8: invokevirtual #111                // Method newFailedFuture:(Ljava/lang/Throwable;)Lio/netty/channel/ChannelFuture;
      11: areturn

  public io.netty.channel.ChannelFuture joinGroup(java.net.InetAddress, java.net.NetworkInterface, java.net.InetAddress, io.netty.channel.ChannelPromise);
    Code:
       0: aload         4
       2: new           #92                 // class java/lang/UnsupportedOperationException
       5: dup
       6: invokespecial #110                // Method java/lang/UnsupportedOperationException."<init>":()V
       9: invokeinterface #107,  2          // InterfaceMethod io/netty/channel/ChannelPromise.setFailure:(Ljava/lang/Throwable;)Lio/netty/channel/ChannelPromise;
      14: pop
      15: aload         4
      17: areturn

  private void ensureBound();
    Code:
       0: aload_0
       1: invokevirtual #112                // Method isActive:()Z
       4: ifne          38
       7: new           #113                // class java/lang/IllegalStateException
      10: dup
      11: new           #93                 // class java/lang/StringBuilder
      14: dup
      15: invokespecial #94                 // Method java/lang/StringBuilder."<init>":()V
      18: ldc           #114                // class io/netty/channel/socket/DatagramChannel
      20: invokevirtual #115                // Method java/lang/Class.getName:()Ljava/lang/String;
      23: invokevirtual #96                 // Method java/lang/StringBuilder.append:(Ljava/lang/String;)Ljava/lang/StringBuilder;
      26: ldc           #116                // String  must be bound to join a group.
      28: invokevirtual #96                 // Method java/lang/StringBuilder.append:(Ljava/lang/String;)Ljava/lang/StringBuilder;
      31: invokevirtual #99                 // Method java/lang/StringBuilder.toString:()Ljava/lang/String;
      34: invokespecial #117                // Method java/lang/IllegalStateException."<init>":(Ljava/lang/String;)V
      37: athrow
      38: return

  public io.netty.channel.ChannelFuture leaveGroup(java.net.InetAddress);
    Code:
       0: aload_0
       1: aload_1
       2: aload_0
       3: invokevirtual #101                // Method newPromise:()Lio/netty/channel/ChannelPromise;
       6: invokevirtual #118                // Method leaveGroup:(Ljava/net/InetAddress;Lio/netty/channel/ChannelPromise;)Lio/netty/channel/ChannelFuture;
       9: areturn

  public io.netty.channel.ChannelFuture leaveGroup(java.net.InetAddress, io.netty.channel.ChannelPromise);
    Code:
       0: aload_0
       1: getfield      #20                 // Field socket:Ljava/net/MulticastSocket;
       4: aload_1
       5: invokevirtual #119                // Method java/net/MulticastSocket.leaveGroup:(Ljava/net/InetAddress;)V
       8: aload_2
       9: invokeinterface #105,  1          // InterfaceMethod io/netty/channel/ChannelPromise.setSuccess:()Lio/netty/channel/ChannelPromise;
      14: pop
      15: goto          27
      18: astore_3
      19: aload_2
      20: aload_3
      21: invokeinterface #107,  2          // InterfaceMethod io/netty/channel/ChannelPromise.setFailure:(Ljava/lang/Throwable;)Lio/netty/channel/ChannelPromise;
      26: pop
      27: aload_2
      28: areturn
    Exception table:
       from    to  target type
           0    15    18   Class java/io/IOException

  public io.netty.channel.ChannelFuture leaveGroup(java.net.InetSocketAddress, java.net.NetworkInterface);
    Code:
       0: aload_0
       1: aload_1
       2: aload_2
       3: aload_0
       4: invokevirtual #101                // Method newPromise:()Lio/netty/channel/ChannelPromise;
       7: invokevirtual #120                // Method leaveGroup:(Ljava/net/InetSocketAddress;Ljava/net/NetworkInterface;Lio/netty/channel/ChannelPromise;)Lio/netty/channel/ChannelFuture;
      10: areturn

  public io.netty.channel.ChannelFuture leaveGroup(java.net.InetSocketAddress, java.net.NetworkInterface, io.netty.channel.ChannelPromise);
    Code:
       0: aload_0
       1: getfield      #20                 // Field socket:Ljava/net/MulticastSocket;
       4: aload_1
       5: aload_2
       6: invokevirtual #121                // Method java/net/MulticastSocket.leaveGroup:(Ljava/net/SocketAddress;Ljava/net/NetworkInterface;)V
       9: aload_3
      10: invokeinterface #105,  1          // InterfaceMethod io/netty/channel/ChannelPromise.setSuccess:()Lio/netty/channel/ChannelPromise;
      15: pop
      16: goto          30
      19: astore        4
      21: aload_3
      22: aload         4
      24: invokeinterface #107,  2          // InterfaceMethod io/netty/channel/ChannelPromise.setFailure:(Ljava/lang/Throwable;)Lio/netty/channel/ChannelPromise;
      29: pop
      30: aload_3
      31: areturn
    Exception table:
       from    to  target type
           0    16    19   Class java/io/IOException

  public io.netty.channel.ChannelFuture leaveGroup(java.net.InetAddress, java.net.NetworkInterface, java.net.InetAddress);
    Code:
       0: aload_0
       1: new           #92                 // class java/lang/UnsupportedOperationException
       4: dup
       5: invokespecial #110                // Method java/lang/UnsupportedOperationException."<init>":()V
       8: invokevirtual #111                // Method newFailedFuture:(Ljava/lang/Throwable;)Lio/netty/channel/ChannelFuture;
      11: areturn

  public io.netty.channel.ChannelFuture leaveGroup(java.net.InetAddress, java.net.NetworkInterface, java.net.InetAddress, io.netty.channel.ChannelPromise);
    Code:
       0: aload         4
       2: new           #92                 // class java/lang/UnsupportedOperationException
       5: dup
       6: invokespecial #110                // Method java/lang/UnsupportedOperationException."<init>":()V
       9: invokeinterface #107,  2          // InterfaceMethod io/netty/channel/ChannelPromise.setFailure:(Ljava/lang/Throwable;)Lio/netty/channel/ChannelPromise;
      14: pop
      15: aload         4
      17: areturn

  public io.netty.channel.ChannelFuture block(java.net.InetAddress, java.net.NetworkInterface, java.net.InetAddress);
    Code:
       0: aload_0
       1: new           #92                 // class java/lang/UnsupportedOperationException
       4: dup
       5: invokespecial #110                // Method java/lang/UnsupportedOperationException."<init>":()V
       8: invokevirtual #111                // Method newFailedFuture:(Ljava/lang/Throwable;)Lio/netty/channel/ChannelFuture;
      11: areturn

  public io.netty.channel.ChannelFuture block(java.net.InetAddress, java.net.NetworkInterface, java.net.InetAddress, io.netty.channel.ChannelPromise);
    Code:
       0: aload         4
       2: new           #92                 // class java/lang/UnsupportedOperationException
       5: dup
       6: invokespecial #110                // Method java/lang/UnsupportedOperationException."<init>":()V
       9: invokeinterface #107,  2          // InterfaceMethod io/netty/channel/ChannelPromise.setFailure:(Ljava/lang/Throwable;)Lio/netty/channel/ChannelPromise;
      14: pop
      15: aload         4
      17: areturn

  public io.netty.channel.ChannelFuture block(java.net.InetAddress, java.net.InetAddress);
    Code:
       0: aload_0
       1: new           #92                 // class java/lang/UnsupportedOperationException
       4: dup
       5: invokespecial #110                // Method java/lang/UnsupportedOperationException."<init>":()V
       8: invokevirtual #111                // Method newFailedFuture:(Ljava/lang/Throwable;)Lio/netty/channel/ChannelFuture;
      11: areturn

  public io.netty.channel.ChannelFuture block(java.net.InetAddress, java.net.InetAddress, io.netty.channel.ChannelPromise);
    Code:
       0: aload_3
       1: new           #92                 // class java/lang/UnsupportedOperationException
       4: dup
       5: invokespecial #110                // Method java/lang/UnsupportedOperationException."<init>":()V
       8: invokeinterface #107,  2          // InterfaceMethod io/netty/channel/ChannelPromise.setFailure:(Ljava/lang/Throwable;)Lio/netty/channel/ChannelPromise;
      13: pop
      14: aload_3
      15: areturn

  public java.net.SocketAddress remoteAddress();
    Code:
       0: aload_0
       1: invokevirtual #122                // Method remoteAddress:()Ljava/net/InetSocketAddress;
       4: areturn

  public java.net.SocketAddress localAddress();
    Code:
       0: aload_0
       1: invokevirtual #64                 // Method localAddress:()Ljava/net/InetSocketAddress;
       4: areturn

  public io.netty.channel.ChannelConfig config();
    Code:
       0: aload_0
       1: invokevirtual #46                 // Method config:()Lio/netty/channel/socket/DatagramChannelConfig;
       4: areturn

  static {};
    Code:
       0: ldc           #123                // class io/netty/channel/socket/oio/OioDatagramChannel
       2: invokestatic  #124                // Method io/netty/util/internal/logging/InternalLoggerFactory.getInstance:(Ljava/lang/Class;)Lio/netty/util/internal/logging/InternalLogger;
       5: putstatic     #42                 // Field logger:Lio/netty/util/internal/logging/InternalLogger;
       8: new           #125                // class io/netty/channel/ChannelMetadata
      11: dup
      12: iconst_1
      13: invokespecial #126                // Method io/netty/channel/ChannelMetadata."<init>":(Z)V
      16: putstatic     #24                 // Field METADATA:Lio/netty/channel/ChannelMetadata;
      19: new           #93                 // class java/lang/StringBuilder
      22: dup
      23: invokespecial #94                 // Method java/lang/StringBuilder."<init>":()V
      26: ldc           #127                // String  (expected:
      28: invokevirtual #96                 // Method java/lang/StringBuilder.append:(Ljava/lang/String;)Ljava/lang/StringBuilder;
      31: ldc           #61                 // class io/netty/channel/socket/DatagramPacket
      33: invokestatic  #128                // Method io/netty/util/internal/StringUtil.simpleClassName:(Ljava/lang/Class;)Ljava/lang/String;
      36: invokevirtual #96                 // Method java/lang/StringBuilder.append:(Ljava/lang/String;)Ljava/lang/StringBuilder;
      39: ldc           #129                // String ,
      41: invokevirtual #96                 // Method java/lang/StringBuilder.append:(Ljava/lang/String;)Ljava/lang/StringBuilder;
      44: ldc           #76                 // class io/netty/channel/AddressedEnvelope
      46: invokestatic  #128                // Method io/netty/util/internal/StringUtil.simpleClassName:(Ljava/lang/Class;)Ljava/lang/String;
      49: invokevirtual #96                 // Method java/lang/StringBuilder.append:(Ljava/lang/String;)Ljava/lang/StringBuilder;
      52: bipush        60
      54: invokevirtual #130                // Method java/lang/StringBuilder.append:(C)Ljava/lang/StringBuilder;
      57: ldc           #79                 // class io/netty/buffer/ByteBuf
      59: invokestatic  #128                // Method io/netty/util/internal/StringUtil.simpleClassName:(Ljava/lang/Class;)Ljava/lang/String;
      62: invokevirtual #96                 // Method java/lang/StringBuilder.append:(Ljava/lang/String;)Ljava/lang/StringBuilder;
      65: ldc           #129                // String ,
      67: invokevirtual #96                 // Method java/lang/StringBuilder.append:(Ljava/lang/String;)Ljava/lang/StringBuilder;
      70: ldc           #131                // class java/net/SocketAddress
      72: invokestatic  #128                // Method io/netty/util/internal/StringUtil.simpleClassName:(Ljava/lang/Class;)Ljava/lang/String;
      75: invokevirtual #96                 // Method java/lang/StringBuilder.append:(Ljava/lang/String;)Ljava/lang/StringBuilder;
      78: ldc           #132                // String >,
      80: invokevirtual #96                 // Method java/lang/StringBuilder.append:(Ljava/lang/String;)Ljava/lang/StringBuilder;
      83: ldc           #79                 // class io/netty/buffer/ByteBuf
      85: invokestatic  #128                // Method io/netty/util/internal/StringUtil.simpleClassName:(Ljava/lang/Class;)Ljava/lang/String;
      88: invokevirtual #96                 // Method java/lang/StringBuilder.append:(Ljava/lang/String;)Ljava/lang/StringBuilder;
      91: bipush        41
      93: invokevirtual #130                // Method java/lang/StringBuilder.append:(C)Ljava/lang/StringBuilder;
      96: invokevirtual #99                 // Method java/lang/StringBuilder.toString:()Ljava/lang/String;
      99: putstatic     #98                 // Field EXPECTED_TYPES:Ljava/lang/String;
     102: return
}
