Compiled from "TypeSystemContext.kt"
public final class kotlin.reflect.jvm.internal.impl.types.model.ArgumentList extends java.util.ArrayList<kotlin.reflect.jvm.internal.impl.types.model.TypeArgumentMarker> implements kotlin.reflect.jvm.internal.impl.types.model.TypeArgumentListMarker {
  public kotlin.reflect.jvm.internal.impl.types.model.ArgumentList(int);
    Code:
       0: aload_0
       1: iload_1
       2: invokespecial #6                  // Method java/util/ArrayList."<init>":(I)V
       5: return

  public boolean remove(kotlin.reflect.jvm.internal.impl.types.model.TypeArgumentMarker);
    Code:
       0: aload_0
       1: aload_1
       2: invokespecial #10                 // Method java/util/ArrayList.remove:(Ljava/lang/Object;)Z
       5: ireturn

  public final boolean remove(java.lang.Object);
    Code:
       0: aload_1
       1: dup
       2: ifnonnull     10
       5: pop
       6: iconst_1
       7: goto          13
      10: instanceof    #5                  // class kotlin/reflect/jvm/internal/impl/types/model/TypeArgumentMarker
      13: ifne          18
      16: iconst_0
      17: ireturn
      18: aload_0
      19: aload_1
      20: checkcast     #5                  // class kotlin/reflect/jvm/internal/impl/types/model/TypeArgumentMarker
      23: invokevirtual #16                 // Method remove:(Lkotlin/reflect/jvm/internal/impl/types/model/TypeArgumentMarker;)Z
      26: ireturn

  public boolean contains(kotlin.reflect.jvm.internal.impl.types.model.TypeArgumentMarker);
    Code:
       0: aload_0
       1: aload_1
       2: invokespecial #7                  // Method java/util/ArrayList.contains:(Ljava/lang/Object;)Z
       5: ireturn

  public final boolean contains(java.lang.Object);
    Code:
       0: aload_1
       1: dup
       2: ifnonnull     10
       5: pop
       6: iconst_1
       7: goto          13
      10: instanceof    #5                  // class kotlin/reflect/jvm/internal/impl/types/model/TypeArgumentMarker
      13: ifne          18
      16: iconst_0
      17: ireturn
      18: aload_0
      19: aload_1
      20: checkcast     #5                  // class kotlin/reflect/jvm/internal/impl/types/model/TypeArgumentMarker
      23: invokevirtual #12                 // Method contains:(Lkotlin/reflect/jvm/internal/impl/types/model/TypeArgumentMarker;)Z
      26: ireturn

  public int indexOf(kotlin.reflect.jvm.internal.impl.types.model.TypeArgumentMarker);
    Code:
       0: aload_0
       1: aload_1
       2: invokespecial #8                  // Method java/util/ArrayList.indexOf:(Ljava/lang/Object;)I
       5: ireturn

  public final int indexOf(java.lang.Object);
    Code:
       0: aload_1
       1: dup
       2: ifnonnull     10
       5: pop
       6: iconst_1
       7: goto          13
      10: instanceof    #5                  // class kotlin/reflect/jvm/internal/impl/types/model/TypeArgumentMarker
      13: ifne          18
      16: iconst_m1
      17: ireturn
      18: aload_0
      19: aload_1
      20: checkcast     #5                  // class kotlin/reflect/jvm/internal/impl/types/model/TypeArgumentMarker
      23: invokevirtual #14                 // Method indexOf:(Lkotlin/reflect/jvm/internal/impl/types/model/TypeArgumentMarker;)I
      26: ireturn

  public int lastIndexOf(kotlin.reflect.jvm.internal.impl.types.model.TypeArgumentMarker);
    Code:
       0: aload_0
       1: aload_1
       2: invokespecial #9                  // Method java/util/ArrayList.lastIndexOf:(Ljava/lang/Object;)I
       5: ireturn

  public final int lastIndexOf(java.lang.Object);
    Code:
       0: aload_1
       1: dup
       2: ifnonnull     10
       5: pop
       6: iconst_1
       7: goto          13
      10: instanceof    #5                  // class kotlin/reflect/jvm/internal/impl/types/model/TypeArgumentMarker
      13: ifne          18
      16: iconst_m1
      17: ireturn
      18: aload_0
      19: aload_1
      20: checkcast     #5                  // class kotlin/reflect/jvm/internal/impl/types/model/TypeArgumentMarker
      23: invokevirtual #15                 // Method lastIndexOf:(Lkotlin/reflect/jvm/internal/impl/types/model/TypeArgumentMarker;)I
      26: ireturn

  public int getSize();
    Code:
       0: aload_0
       1: invokespecial #11                 // Method java/util/ArrayList.size:()I
       4: ireturn

  public final int size();
    Code:
       0: aload_0
       1: invokevirtual #13                 // Method getSize:()I
       4: ireturn
}
