Compiled from "ConstructorResolver.java"
class org.springframework.beans.factory.support.ConstructorResolver$ArgumentsHolder {
  public final java.lang.Object[] rawArguments;

  public final java.lang.Object[] arguments;

  public final java.lang.Object[] preparedArguments;

  public boolean resolveNecessary;

  public org.springframework.beans.factory.support.ConstructorResolver$ArgumentsHolder(int);
    Code:
       0: aload_0
       1: invokespecial #1                  // Method java/lang/Object."<init>":()V
       4: aload_0
       5: iconst_0
       6: putfield      #2                  // Field resolveNecessary:Z
       9: aload_0
      10: iload_1
      11: anewarray     #3                  // class java/lang/Object
      14: putfield      #4                  // Field rawArguments:[Ljava/lang/Object;
      17: aload_0
      18: iload_1
      19: anewarray     #3                  // class java/lang/Object
      22: putfield      #5                  // Field arguments:[Ljava/lang/Object;
      25: aload_0
      26: iload_1
      27: anewarray     #3                  // class java/lang/Object
      30: putfield      #6                  // Field preparedArguments:[Ljava/lang/Object;
      33: return

  public org.springframework.beans.factory.support.ConstructorResolver$ArgumentsHolder(java.lang.Object[]);
    Code:
       0: aload_0
       1: invokespecial #1                  // Method java/lang/Object."<init>":()V
       4: aload_0
       5: iconst_0
       6: putfield      #2                  // Field resolveNecessary:Z
       9: aload_0
      10: aload_1
      11: putfield      #4                  // Field rawArguments:[Ljava/lang/Object;
      14: aload_0
      15: aload_1
      16: putfield      #5                  // Field arguments:[Ljava/lang/Object;
      19: aload_0
      20: aload_1
      21: putfield      #6                  // Field preparedArguments:[Ljava/lang/Object;
      24: return

  public int getTypeDifferenceWeight(java.lang.Class<?>[]);
    Code:
       0: aload_1
       1: aload_0
       2: getfield      #5                  // Field arguments:[Ljava/lang/Object;
       5: invokestatic  #7                  // Method org/springframework/util/MethodInvoker.getTypeDifferenceWeight:([Ljava/lang/Class;[Ljava/lang/Object;)I
       8: istore_2
       9: aload_1
      10: aload_0
      11: getfield      #4                  // Field rawArguments:[Ljava/lang/Object;
      14: invokestatic  #7                  // Method org/springframework/util/MethodInvoker.getTypeDifferenceWeight:([Ljava/lang/Class;[Ljava/lang/Object;)I
      17: sipush        1024
      20: isub
      21: istore_3
      22: iload_3
      23: iload_2
      24: if_icmpge     31
      27: iload_3
      28: goto          32
      31: iload_2
      32: ireturn

  public int getAssignabilityWeight(java.lang.Class<?>[]);
    Code:
       0: iconst_0
       1: istore_2
       2: iload_2
       3: aload_1
       4: arraylength
       5: if_icmpge     32
       8: aload_1
       9: iload_2
      10: aaload
      11: aload_0
      12: getfield      #5                  // Field arguments:[Ljava/lang/Object;
      15: iload_2
      16: aaload
      17: invokestatic  #8                  // Method org/springframework/util/ClassUtils.isAssignableValue:(Ljava/lang/Class;Ljava/lang/Object;)Z
      20: ifne          26
      23: ldc           #10                 // int 2147483647
      25: ireturn
      26: iinc          2, 1
      29: goto          2
      32: iconst_0
      33: istore_2
      34: iload_2
      35: aload_1
      36: arraylength
      37: if_icmpge     64
      40: aload_1
      41: iload_2
      42: aaload
      43: aload_0
      44: getfield      #4                  // Field rawArguments:[Ljava/lang/Object;
      47: iload_2
      48: aaload
      49: invokestatic  #8                  // Method org/springframework/util/ClassUtils.isAssignableValue:(Ljava/lang/Class;Ljava/lang/Object;)Z
      52: ifne          58
      55: ldc           #11                 // int 2147483135
      57: ireturn
      58: iinc          2, 1
      61: goto          34
      64: ldc           #12                 // int 2147482623
      66: ireturn

  public void storeCache(org.springframework.beans.factory.support.RootBeanDefinition, java.lang.reflect.Executable);
    Code:
       0: aload_1
       1: getfield      #13                 // Field org/springframework/beans/factory/support/RootBeanDefinition.constructorArgumentLock:Ljava/lang/Object;
       4: dup
       5: astore_3
       6: monitorenter
       7: aload_1
       8: aload_2
       9: putfield      #14                 // Field org/springframework/beans/factory/support/RootBeanDefinition.resolvedConstructorOrFactoryMethod:Ljava/lang/reflect/Executable;
      12: aload_1
      13: iconst_1
      14: putfield      #15                 // Field org/springframework/beans/factory/support/RootBeanDefinition.constructorArgumentsResolved:Z
      17: aload_0
      18: getfield      #2                  // Field resolveNecessary:Z
      21: ifeq          35
      24: aload_1
      25: aload_0
      26: getfield      #6                  // Field preparedArguments:[Ljava/lang/Object;
      29: putfield      #16                 // Field org/springframework/beans/factory/support/RootBeanDefinition.preparedConstructorArguments:[Ljava/lang/Object;
      32: goto          43
      35: aload_1
      36: aload_0
      37: getfield      #5                  // Field arguments:[Ljava/lang/Object;
      40: putfield      #17                 // Field org/springframework/beans/factory/support/RootBeanDefinition.resolvedConstructorArguments:[Ljava/lang/Object;
      43: aload_3
      44: monitorexit
      45: goto          55
      48: astore        4
      50: aload_3
      51: monitorexit
      52: aload         4
      54: athrow
      55: return
    Exception table:
       from    to  target type
           7    45    48   any
          48    52    48   any
}
