Compiled from "IfClosure.java"
public class org.apache.commons.collections4.functors.IfClosure<E> implements org.apache.commons.collections4.Closure<E>, java.io.Serializable {
  private static final long serialVersionUID;

  private final org.apache.commons.collections4.Predicate<? super E> iPredicate;

  private final org.apache.commons.collections4.Closure<? super E> iTrueClosure;

  private final org.apache.commons.collections4.Closure<? super E> iFalseClosure;

  public static <E> org.apache.commons.collections4.Closure<E> ifClosure(org.apache.commons.collections4.Predicate<? super E>, org.apache.commons.collections4.Closure<? super E>);
    Code:
       0: aload_0
       1: aload_1
       2: invokestatic  #1                  // Method org/apache/commons/collections4/functors/NOPClosure.nopClosure:()Lorg/apache/commons/collections4/Closure;
       5: invokestatic  #2                  // Method ifClosure:(Lorg/apache/commons/collections4/Predicate;Lorg/apache/commons/collections4/Closure;Lorg/apache/commons/collections4/Closure;)Lorg/apache/commons/collections4/Closure;
       8: areturn

  public static <E> org.apache.commons.collections4.Closure<E> ifClosure(org.apache.commons.collections4.Predicate<? super E>, org.apache.commons.collections4.Closure<? super E>, org.apache.commons.collections4.Closure<? super E>);
    Code:
       0: aload_0
       1: ifnonnull     14
       4: new           #3                  // class java/lang/NullPointerException
       7: dup
       8: ldc           #4                  // String Predicate must not be null
      10: invokespecial #5                  // Method java/lang/NullPointerException."<init>":(Ljava/lang/String;)V
      13: athrow
      14: aload_1
      15: ifnull        22
      18: aload_2
      19: ifnonnull     32
      22: new           #3                  // class java/lang/NullPointerException
      25: dup
      26: ldc           #6                  // String Closures must not be null
      28: invokespecial #5                  // Method java/lang/NullPointerException."<init>":(Ljava/lang/String;)V
      31: athrow
      32: new           #7                  // class org/apache/commons/collections4/functors/IfClosure
      35: dup
      36: aload_0
      37: aload_1
      38: aload_2
      39: invokespecial #8                  // Method "<init>":(Lorg/apache/commons/collections4/Predicate;Lorg/apache/commons/collections4/Closure;Lorg/apache/commons/collections4/Closure;)V
      42: areturn

  public org.apache.commons.collections4.functors.IfClosure(org.apache.commons.collections4.Predicate<? super E>, org.apache.commons.collections4.Closure<? super E>);
    Code:
       0: aload_0
       1: aload_1
       2: aload_2
       3: invokestatic  #1                  // Method org/apache/commons/collections4/functors/NOPClosure.nopClosure:()Lorg/apache/commons/collections4/Closure;
       6: invokespecial #8                  // Method "<init>":(Lorg/apache/commons/collections4/Predicate;Lorg/apache/commons/collections4/Closure;Lorg/apache/commons/collections4/Closure;)V
       9: return

  public org.apache.commons.collections4.functors.IfClosure(org.apache.commons.collections4.Predicate<? super E>, org.apache.commons.collections4.Closure<? super E>, org.apache.commons.collections4.Closure<? super E>);
    Code:
       0: aload_0
       1: invokespecial #9                  // Method java/lang/Object."<init>":()V
       4: aload_0
       5: aload_1
       6: putfield      #10                 // Field iPredicate:Lorg/apache/commons/collections4/Predicate;
       9: aload_0
      10: aload_2
      11: putfield      #11                 // Field iTrueClosure:Lorg/apache/commons/collections4/Closure;
      14: aload_0
      15: aload_3
      16: putfield      #12                 // Field iFalseClosure:Lorg/apache/commons/collections4/Closure;
      19: return

  public void execute(E);
    Code:
       0: aload_0
       1: getfield      #10                 // Field iPredicate:Lorg/apache/commons/collections4/Predicate;
       4: aload_1
       5: invokeinterface #13,  2           // InterfaceMethod org/apache/commons/collections4/Predicate.evaluate:(Ljava/lang/Object;)Z
      10: ifeq          26
      13: aload_0
      14: getfield      #11                 // Field iTrueClosure:Lorg/apache/commons/collections4/Closure;
      17: aload_1
      18: invokeinterface #14,  2           // InterfaceMethod org/apache/commons/collections4/Closure.execute:(Ljava/lang/Object;)V
      23: goto          36
      26: aload_0
      27: getfield      #12                 // Field iFalseClosure:Lorg/apache/commons/collections4/Closure;
      30: aload_1
      31: invokeinterface #14,  2           // InterfaceMethod org/apache/commons/collections4/Closure.execute:(Ljava/lang/Object;)V
      36: return

  public org.apache.commons.collections4.Predicate<? super E> getPredicate();
    Code:
       0: aload_0
       1: getfield      #10                 // Field iPredicate:Lorg/apache/commons/collections4/Predicate;
       4: areturn

  public org.apache.commons.collections4.Closure<? super E> getTrueClosure();
    Code:
       0: aload_0
       1: getfield      #11                 // Field iTrueClosure:Lorg/apache/commons/collections4/Closure;
       4: areturn

  public org.apache.commons.collections4.Closure<? super E> getFalseClosure();
    Code:
       0: aload_0
       1: getfield      #12                 // Field iFalseClosure:Lorg/apache/commons/collections4/Closure;
       4: areturn
}
