Compiled from "StringValueTransformer.java"
public final class org.apache.commons.collections4.functors.StringValueTransformer<T> implements org.apache.commons.collections4.Transformer<T, java.lang.String>, java.io.Serializable {
  private static final long serialVersionUID;

  private static final org.apache.commons.collections4.Transformer<java.lang.Object, java.lang.String> INSTANCE;

  public static <T> org.apache.commons.collections4.Transformer<T, java.lang.String> stringValueTransformer();
    Code:
       0: getstatic     #1                  // Field INSTANCE:Lorg/apache/commons/collections4/Transformer;
       3: areturn

  private org.apache.commons.collections4.functors.StringValueTransformer();
    Code:
       0: aload_0
       1: invokespecial #2                  // Method java/lang/Object."<init>":()V
       4: return

  public java.lang.String transform(T);
    Code:
       0: aload_1
       1: invokestatic  #3                  // Method java/lang/String.valueOf:(Ljava/lang/Object;)Ljava/lang/String;
       4: areturn

  private java.lang.Object readResolve();
    Code:
       0: getstatic     #1                  // Field INSTANCE:Lorg/apache/commons/collections4/Transformer;
       3: areturn

  public java.lang.Object transform(java.lang.Object);
    Code:
       0: aload_0
       1: aload_1
       2: invokevirtual #4                  // Method transform:(Ljava/lang/Object;)Ljava/lang/String;
       5: areturn

  static {};
    Code:
       0: new           #5                  // class org/apache/commons/collections4/functors/StringValueTransformer
       3: dup
       4: invokespecial #6                  // Method "<init>":()V
       7: putstatic     #1                  // Field INSTANCE:Lorg/apache/commons/collections4/Transformer;
      10: return
}
