Compiled from "DefaultNumberExpr.java"
class org.jaxen.expr.DefaultNumberExpr extends org.jaxen.expr.DefaultExpr implements org.jaxen.expr.NumberExpr {
  private static final long serialVersionUID;

  private java.lang.Double number;

  org.jaxen.expr.DefaultNumberExpr(java.lang.Double);
    Code:
       0: aload_0
       1: invokespecial #1                  // Method org/jaxen/expr/DefaultExpr."<init>":()V
       4: aload_0
       5: aload_1
       6: putfield      #2                  // Field number:Ljava/lang/Double;
       9: return

  public java.lang.Number getNumber();
    Code:
       0: aload_0
       1: getfield      #2                  // Field number:Ljava/lang/Double;
       4: areturn

  public java.lang.String toString();
    Code:
       0: new           #3                  // class java/lang/StringBuffer
       3: dup
       4: invokespecial #4                  // Method java/lang/StringBuffer."<init>":()V
       7: ldc           #5                  // String [(DefaultNumberExpr):
       9: invokevirtual #6                  // Method java/lang/StringBuffer.append:(Ljava/lang/String;)Ljava/lang/StringBuffer;
      12: aload_0
      13: invokevirtual #7                  // Method getNumber:()Ljava/lang/Number;
      16: invokevirtual #8                  // Method java/lang/StringBuffer.append:(Ljava/lang/Object;)Ljava/lang/StringBuffer;
      19: ldc           #9                  // String ]
      21: invokevirtual #6                  // Method java/lang/StringBuffer.append:(Ljava/lang/String;)Ljava/lang/StringBuffer;
      24: invokevirtual #10                 // Method java/lang/StringBuffer.toString:()Ljava/lang/String;
      27: areturn

  public java.lang.String getText();
    Code:
       0: aload_0
       1: invokevirtual #7                  // Method getNumber:()Ljava/lang/Number;
       4: invokevirtual #11                 // Method java/lang/Object.toString:()Ljava/lang/String;
       7: areturn

  public java.lang.Object evaluate(org.jaxen.Context);
    Code:
       0: aload_0
       1: invokevirtual #7                  // Method getNumber:()Ljava/lang/Number;
       4: areturn
}
