Compiled from "DefaultProcessingInstructionNodeStep.java"
public class org.jaxen.expr.DefaultProcessingInstructionNodeStep extends org.jaxen.expr.DefaultStep implements org.jaxen.expr.ProcessingInstructionNodeStep {
  private static final long serialVersionUID;

  private java.lang.String name;

  public org.jaxen.expr.DefaultProcessingInstructionNodeStep(org.jaxen.expr.iter.IterableAxis, java.lang.String, org.jaxen.expr.PredicateSet);
    Code:
       0: aload_0
       1: aload_1
       2: aload_3
       3: invokespecial #1                  // Method org/jaxen/expr/DefaultStep."<init>":(Lorg/jaxen/expr/iter/IterableAxis;Lorg/jaxen/expr/PredicateSet;)V
       6: aload_0
       7: aload_2
       8: putfield      #2                  // Field name:Ljava/lang/String;
      11: return

  public java.lang.String getName();
    Code:
       0: aload_0
       1: getfield      #2                  // Field name:Ljava/lang/String;
       4: areturn

  public java.lang.String getText();
    Code:
       0: new           #3                  // class java/lang/StringBuffer
       3: dup
       4: invokespecial #4                  // Method java/lang/StringBuffer."<init>":()V
       7: astore_1
       8: aload_1
       9: aload_0
      10: invokevirtual #5                  // Method getAxisName:()Ljava/lang/String;
      13: invokevirtual #6                  // Method java/lang/StringBuffer.append:(Ljava/lang/String;)Ljava/lang/StringBuffer;
      16: pop
      17: aload_1
      18: ldc           #7                  // String ::processing-instruction(
      20: invokevirtual #6                  // Method java/lang/StringBuffer.append:(Ljava/lang/String;)Ljava/lang/StringBuffer;
      23: pop
      24: aload_0
      25: invokevirtual #8                  // Method getName:()Ljava/lang/String;
      28: astore_2
      29: aload_2
      30: ifnull        60
      33: aload_2
      34: invokevirtual #9                  // Method java/lang/String.length:()I
      37: ifeq          60
      40: aload_1
      41: ldc           #10                 // String \'
      43: invokevirtual #6                  // Method java/lang/StringBuffer.append:(Ljava/lang/String;)Ljava/lang/StringBuffer;
      46: pop
      47: aload_1
      48: aload_2
      49: invokevirtual #6                  // Method java/lang/StringBuffer.append:(Ljava/lang/String;)Ljava/lang/StringBuffer;
      52: pop
      53: aload_1
      54: ldc           #10                 // String \'
      56: invokevirtual #6                  // Method java/lang/StringBuffer.append:(Ljava/lang/String;)Ljava/lang/StringBuffer;
      59: pop
      60: aload_1
      61: ldc           #11                 // String )
      63: invokevirtual #6                  // Method java/lang/StringBuffer.append:(Ljava/lang/String;)Ljava/lang/StringBuffer;
      66: pop
      67: aload_1
      68: aload_0
      69: invokespecial #12                 // Method org/jaxen/expr/DefaultStep.getText:()Ljava/lang/String;
      72: invokevirtual #6                  // Method java/lang/StringBuffer.append:(Ljava/lang/String;)Ljava/lang/StringBuffer;
      75: pop
      76: aload_1
      77: invokevirtual #13                 // Method java/lang/StringBuffer.toString:()Ljava/lang/String;
      80: areturn

  public boolean matches(java.lang.Object, org.jaxen.ContextSupport);
    Code:
       0: aload_2
       1: invokevirtual #14                 // Method org/jaxen/ContextSupport.getNavigator:()Lorg/jaxen/Navigator;
       4: astore_3
       5: aload_3
       6: aload_1
       7: invokeinterface #15,  2           // InterfaceMethod org/jaxen/Navigator.isProcessingInstruction:(Ljava/lang/Object;)Z
      12: ifeq          49
      15: aload_0
      16: invokevirtual #8                  // Method getName:()Ljava/lang/String;
      19: astore        4
      21: aload         4
      23: ifnull        34
      26: aload         4
      28: invokevirtual #9                  // Method java/lang/String.length:()I
      31: ifne          36
      34: iconst_1
      35: ireturn
      36: aload         4
      38: aload_3
      39: aload_1
      40: invokeinterface #16,  2           // InterfaceMethod org/jaxen/Navigator.getProcessingInstructionTarget:(Ljava/lang/Object;)Ljava/lang/String;
      45: invokevirtual #17                 // Method java/lang/String.equals:(Ljava/lang/Object;)Z
      48: ireturn
      49: iconst_0
      50: ireturn
}
