Compiled from "SharedMetadataReaderFactoryContextInitializer.java"
class org.springframework.boot.autoconfigure.SharedMetadataReaderFactoryContextInitializer$SharedMetadataReaderFactoryBean implements org.springframework.beans.factory.FactoryBean<org.springframework.boot.type.classreading.ConcurrentReferenceCachingMetadataReaderFactory>, org.springframework.beans.factory.BeanClassLoaderAware, org.springframework.context.ApplicationListener<org.springframework.context.event.ContextRefreshedEvent> {
  private org.springframework.boot.type.classreading.ConcurrentReferenceCachingMetadataReaderFactory metadataReaderFactory;

  org.springframework.boot.autoconfigure.SharedMetadataReaderFactoryContextInitializer$SharedMetadataReaderFactoryBean();
    Code:
       0: aload_0
       1: invokespecial #1                  // Method java/lang/Object."<init>":()V
       4: return

  public void setBeanClassLoader(java.lang.ClassLoader);
    Code:
       0: aload_0
       1: new           #2                  // class org/springframework/boot/type/classreading/ConcurrentReferenceCachingMetadataReaderFactory
       4: dup
       5: aload_1
       6: invokespecial #3                  // Method org/springframework/boot/type/classreading/ConcurrentReferenceCachingMetadataReaderFactory."<init>":(Ljava/lang/ClassLoader;)V
       9: putfield      #4                  // Field metadataReaderFactory:Lorg/springframework/boot/type/classreading/ConcurrentReferenceCachingMetadataReaderFactory;
      12: return

  public org.springframework.boot.type.classreading.ConcurrentReferenceCachingMetadataReaderFactory getObject() throws java.lang.Exception;
    Code:
       0: aload_0
       1: getfield      #4                  // Field metadataReaderFactory:Lorg/springframework/boot/type/classreading/ConcurrentReferenceCachingMetadataReaderFactory;
       4: areturn

  public java.lang.Class<?> getObjectType();
    Code:
       0: ldc           #5                  // class org/springframework/core/type/classreading/CachingMetadataReaderFactory
       2: areturn

  public boolean isSingleton();
    Code:
       0: iconst_1
       1: ireturn

  public void onApplicationEvent(org.springframework.context.event.ContextRefreshedEvent);
    Code:
       0: aload_0
       1: getfield      #4                  // Field metadataReaderFactory:Lorg/springframework/boot/type/classreading/ConcurrentReferenceCachingMetadataReaderFactory;
       4: invokevirtual #6                  // Method org/springframework/boot/type/classreading/ConcurrentReferenceCachingMetadataReaderFactory.clearCache:()V
       7: return

  public java.lang.Object getObject() throws java.lang.Exception;
    Code:
       0: aload_0
       1: invokevirtual #7                  // Method getObject:()Lorg/springframework/boot/type/classreading/ConcurrentReferenceCachingMetadataReaderFactory;
       4: areturn

  public void onApplicationEvent(org.springframework.context.ApplicationEvent);
    Code:
       0: aload_0
       1: aload_1
       2: checkcast     #8                  // class org/springframework/context/event/ContextRefreshedEvent
       5: invokevirtual #9                  // Method onApplicationEvent:(Lorg/springframework/context/event/ContextRefreshedEvent;)V
       8: return
}
