public class org.bouncycastle.pqc.crypto.xmss.XMSSMTSignature$Builder {
  private final org.bouncycastle.pqc.crypto.xmss.XMSSMTParameters params;

  private long index;

  private byte[] random;

  private java.util.List<org.bouncycastle.pqc.crypto.xmss.XMSSReducedSignature> reducedSignatures;

  private byte[] signature;

  public org.bouncycastle.pqc.crypto.xmss.XMSSMTSignature$Builder(org.bouncycastle.pqc.crypto.xmss.XMSSMTParameters);
    Code:
       0: aload_0
       1: invokespecial #64                 // Method java/lang/Object."<init>":()V
       4: aload_0
       5: lconst_0
       6: putfield      #59                 // Field index:J
       9: aload_0
      10: aconst_null
      11: putfield      #60                 // Field random:[B
      14: aload_0
      15: aconst_null
      16: putfield      #62                 // Field reducedSignatures:Ljava/util/List;
      19: aload_0
      20: aconst_null
      21: putfield      #61                 // Field signature:[B
      24: aload_0
      25: aload_1
      26: putfield      #63                 // Field params:Lorg/bouncycastle/pqc/crypto/xmss/XMSSMTParameters;
      29: return

  public org.bouncycastle.pqc.crypto.xmss.XMSSMTSignature$Builder withIndex(long);
    Code:
       0: aload_0
       1: lload_1
       2: putfield      #59                 // Field index:J
       5: aload_0
       6: areturn

  public org.bouncycastle.pqc.crypto.xmss.XMSSMTSignature$Builder withRandom(byte[]);
    Code:
       0: aload_0
       1: aload_1
       2: invokestatic  #66                 // Method org/bouncycastle/pqc/crypto/xmss/XMSSUtil.cloneArray:([B)[B
       5: putfield      #60                 // Field random:[B
       8: aload_0
       9: areturn

  public org.bouncycastle.pqc.crypto.xmss.XMSSMTSignature$Builder withReducedSignatures(java.util.List<org.bouncycastle.pqc.crypto.xmss.XMSSReducedSignature>);
    Code:
       0: aload_0
       1: aload_1
       2: putfield      #62                 // Field reducedSignatures:Ljava/util/List;
       5: aload_0
       6: areturn

  public org.bouncycastle.pqc.crypto.xmss.XMSSMTSignature$Builder withSignature(byte[]);
    Code:
       0: aload_0
       1: aload_1
       2: invokestatic  #67                 // Method org/bouncycastle/util/Arrays.clone:([B)[B
       5: putfield      #61                 // Field signature:[B
       8: aload_0
       9: areturn

  public org.bouncycastle.pqc.crypto.xmss.XMSSMTSignature build();
    Code:
       0: new           #31                 // class org/bouncycastle/pqc/crypto/xmss/XMSSMTSignature
       3: dup
       4: aload_0
       5: aconst_null
       6: invokespecial #65                 // Method org/bouncycastle/pqc/crypto/xmss/XMSSMTSignature."<init>":(Lorg/bouncycastle/pqc/crypto/xmss/XMSSMTSignature$Builder;Lorg/bouncycastle/pqc/crypto/xmss/XMSSMTSignature$1;)V
       9: areturn

  static org.bouncycastle.pqc.crypto.xmss.XMSSMTParameters access$000(org.bouncycastle.pqc.crypto.xmss.XMSSMTSignature$Builder);
    Code:
       0: aload_0
       1: getfield      #63                 // Field params:Lorg/bouncycastle/pqc/crypto/xmss/XMSSMTParameters;
       4: areturn

  static byte[] access$100(org.bouncycastle.pqc.crypto.xmss.XMSSMTSignature$Builder);
    Code:
       0: aload_0
       1: getfield      #61                 // Field signature:[B
       4: areturn

  static long access$200(org.bouncycastle.pqc.crypto.xmss.XMSSMTSignature$Builder);
    Code:
       0: aload_0
       1: getfield      #59                 // Field index:J
       4: lreturn

  static byte[] access$300(org.bouncycastle.pqc.crypto.xmss.XMSSMTSignature$Builder);
    Code:
       0: aload_0
       1: getfield      #60                 // Field random:[B
       4: areturn

  static java.util.List access$400(org.bouncycastle.pqc.crypto.xmss.XMSSMTSignature$Builder);
    Code:
       0: aload_0
       1: getfield      #62                 // Field reducedSignatures:Ljava/util/List;
       4: areturn
}
