Compiled from "AbstractConfiguration.java"
class org.apache.commons.configuration.AbstractConfiguration$2 implements org.apache.commons.configuration.event.ConfigurationErrorListener {
  final org.apache.commons.configuration.AbstractConfiguration this$0;

  org.apache.commons.configuration.AbstractConfiguration$2(org.apache.commons.configuration.AbstractConfiguration);
    Code:
       0: aload_0
       1: aload_1
       2: putfield      #1                  // Field this$0:Lorg/apache/commons/configuration/AbstractConfiguration;
       5: aload_0
       6: invokespecial #2                  // Method java/lang/Object."<init>":()V
       9: return

  public void configurationError(org.apache.commons.configuration.event.ConfigurationErrorEvent);
    Code:
       0: aload_0
       1: getfield      #1                  // Field this$0:Lorg/apache/commons/configuration/AbstractConfiguration;
       4: invokevirtual #3                  // Method org/apache/commons/configuration/AbstractConfiguration.getLogger:()Lorg/apache/commons/logging/Log;
       7: ldc           #4                  // String Internal error
       9: aload_1
      10: invokevirtual #5                  // Method org/apache/commons/configuration/event/ConfigurationErrorEvent.getCause:()Ljava/lang/Throwable;
      13: invokeinterface #6,  3            // InterfaceMethod org/apache/commons/logging/Log.warn:(Ljava/lang/Object;Ljava/lang/Throwable;)V
      18: return
}
