Compiled from "HierarchicalConfiguration.java"
final class org.apache.commons.configuration.HierarchicalConfiguration$5 extends org.apache.commons.configuration.HierarchicalConfiguration$Node {
  final org.apache.commons.configuration.tree.ViewNode val$viewNode;

  org.apache.commons.configuration.HierarchicalConfiguration$5(org.apache.commons.configuration.tree.ConfigurationNode, org.apache.commons.configuration.tree.ViewNode);
    Code:
       0: aload_0
       1: aload_2
       2: putfield      #1                  // Field val$viewNode:Lorg/apache/commons/configuration/tree/ViewNode;
       5: aload_0
       6: aload_1
       7: invokespecial #2                  // Method org/apache/commons/configuration/HierarchicalConfiguration$Node."<init>":(Lorg/apache/commons/configuration/tree/ConfigurationNode;)V
      10: return

  public void setReference(java.lang.Object);
    Code:
       0: aload_0
       1: aload_1
       2: invokespecial #3                  // Method org/apache/commons/configuration/HierarchicalConfiguration$Node.setReference:(Ljava/lang/Object;)V
       5: aload_0
       6: getfield      #1                  // Field val$viewNode:Lorg/apache/commons/configuration/tree/ViewNode;
       9: aload_1
      10: invokevirtual #4                  // Method org/apache/commons/configuration/tree/ViewNode.setReference:(Ljava/lang/Object;)V
      13: return
}
