Compiled from "DataSourceFilterVariable.java"
public final class software.amazon.awssdk.services.machinelearning.model.DataSourceFilterVariable extends java.lang.Enum<software.amazon.awssdk.services.machinelearning.model.DataSourceFilterVariable> {
  public static final software.amazon.awssdk.services.machinelearning.model.DataSourceFilterVariable CREATED_AT;

  public static final software.amazon.awssdk.services.machinelearning.model.DataSourceFilterVariable LAST_UPDATED_AT;

  public static final software.amazon.awssdk.services.machinelearning.model.DataSourceFilterVariable STATUS;

  public static final software.amazon.awssdk.services.machinelearning.model.DataSourceFilterVariable NAME;

  public static final software.amazon.awssdk.services.machinelearning.model.DataSourceFilterVariable DATA_LOCATION_S3;

  public static final software.amazon.awssdk.services.machinelearning.model.DataSourceFilterVariable IAM_USER;

  public static final software.amazon.awssdk.services.machinelearning.model.DataSourceFilterVariable UNKNOWN_TO_SDK_VERSION;

  private static final java.util.Map<java.lang.String, software.amazon.awssdk.services.machinelearning.model.DataSourceFilterVariable> VALUE_MAP;

  private final java.lang.String value;

  private static final software.amazon.awssdk.services.machinelearning.model.DataSourceFilterVariable[] $VALUES;

  public static software.amazon.awssdk.services.machinelearning.model.DataSourceFilterVariable[] values();
    Code:
       0: getstatic     #1                  // Field $VALUES:[Lsoftware/amazon/awssdk/services/machinelearning/model/DataSourceFilterVariable;
       3: invokevirtual #2                  // Method "[Lsoftware/amazon/awssdk/services/machinelearning/model/DataSourceFilterVariable;".clone:()Ljava/lang/Object;
       6: checkcast     #3                  // class "[Lsoftware/amazon/awssdk/services/machinelearning/model/DataSourceFilterVariable;"
       9: areturn

  public static software.amazon.awssdk.services.machinelearning.model.DataSourceFilterVariable valueOf(java.lang.String);
    Code:
       0: ldc           #4                  // class software/amazon/awssdk/services/machinelearning/model/DataSourceFilterVariable
       2: aload_0
       3: invokestatic  #5                  // Method java/lang/Enum.valueOf:(Ljava/lang/Class;Ljava/lang/String;)Ljava/lang/Enum;
       6: checkcast     #4                  // class software/amazon/awssdk/services/machinelearning/model/DataSourceFilterVariable
       9: areturn

  private software.amazon.awssdk.services.machinelearning.model.DataSourceFilterVariable(java.lang.String);
    Code:
       0: aload_0
       1: aload_1
       2: iload_2
       3: invokespecial #6                  // Method java/lang/Enum."<init>":(Ljava/lang/String;I)V
       6: aload_0
       7: aload_3
       8: putfield      #7                  // Field value:Ljava/lang/String;
      11: return

  public java.lang.String toString();
    Code:
       0: aload_0
       1: getfield      #7                  // Field value:Ljava/lang/String;
       4: invokestatic  #8                  // Method java/lang/String.valueOf:(Ljava/lang/Object;)Ljava/lang/String;
       7: areturn

  public static software.amazon.awssdk.services.machinelearning.model.DataSourceFilterVariable fromValue(java.lang.String);
    Code:
       0: aload_0
       1: ifnonnull     6
       4: aconst_null
       5: areturn
       6: getstatic     #9                  // Field VALUE_MAP:Ljava/util/Map;
       9: aload_0
      10: getstatic     #10                 // Field UNKNOWN_TO_SDK_VERSION:Lsoftware/amazon/awssdk/services/machinelearning/model/DataSourceFilterVariable;
      13: invokeinterface #11,  3           // InterfaceMethod java/util/Map.getOrDefault:(Ljava/lang/Object;Ljava/lang/Object;)Ljava/lang/Object;
      18: checkcast     #4                  // class software/amazon/awssdk/services/machinelearning/model/DataSourceFilterVariable
      21: areturn

  public static java.util.Set<software.amazon.awssdk.services.machinelearning.model.DataSourceFilterVariable> knownValues();
    Code:
       0: ldc           #4                  // class software/amazon/awssdk/services/machinelearning/model/DataSourceFilterVariable
       2: invokestatic  #12                 // Method java/util/EnumSet.allOf:(Ljava/lang/Class;)Ljava/util/EnumSet;
       5: astore_0
       6: aload_0
       7: getstatic     #10                 // Field UNKNOWN_TO_SDK_VERSION:Lsoftware/amazon/awssdk/services/machinelearning/model/DataSourceFilterVariable;
      10: invokeinterface #13,  2           // InterfaceMethod java/util/Set.remove:(Ljava/lang/Object;)Z
      15: pop
      16: aload_0
      17: areturn

  static {};
    Code:
       0: new           #4                  // class software/amazon/awssdk/services/machinelearning/model/DataSourceFilterVariable
       3: dup
       4: ldc           #14                 // String CREATED_AT
       6: iconst_0
       7: ldc           #15                 // String CreatedAt
       9: invokespecial #16                 // Method "<init>":(Ljava/lang/String;ILjava/lang/String;)V
      12: putstatic     #17                 // Field CREATED_AT:Lsoftware/amazon/awssdk/services/machinelearning/model/DataSourceFilterVariable;
      15: new           #4                  // class software/amazon/awssdk/services/machinelearning/model/DataSourceFilterVariable
      18: dup
      19: ldc           #18                 // String LAST_UPDATED_AT
      21: iconst_1
      22: ldc           #19                 // String LastUpdatedAt
      24: invokespecial #16                 // Method "<init>":(Ljava/lang/String;ILjava/lang/String;)V
      27: putstatic     #20                 // Field LAST_UPDATED_AT:Lsoftware/amazon/awssdk/services/machinelearning/model/DataSourceFilterVariable;
      30: new           #4                  // class software/amazon/awssdk/services/machinelearning/model/DataSourceFilterVariable
      33: dup
      34: ldc           #21                 // String STATUS
      36: iconst_2
      37: ldc           #22                 // String Status
      39: invokespecial #16                 // Method "<init>":(Ljava/lang/String;ILjava/lang/String;)V
      42: putstatic     #23                 // Field STATUS:Lsoftware/amazon/awssdk/services/machinelearning/model/DataSourceFilterVariable;
      45: new           #4                  // class software/amazon/awssdk/services/machinelearning/model/DataSourceFilterVariable
      48: dup
      49: ldc           #24                 // String NAME
      51: iconst_3
      52: ldc           #25                 // String Name
      54: invokespecial #16                 // Method "<init>":(Ljava/lang/String;ILjava/lang/String;)V
      57: putstatic     #26                 // Field NAME:Lsoftware/amazon/awssdk/services/machinelearning/model/DataSourceFilterVariable;
      60: new           #4                  // class software/amazon/awssdk/services/machinelearning/model/DataSourceFilterVariable
      63: dup
      64: ldc           #27                 // String DATA_LOCATION_S3
      66: iconst_4
      67: ldc           #28                 // String DataLocationS3
      69: invokespecial #16                 // Method "<init>":(Ljava/lang/String;ILjava/lang/String;)V
      72: putstatic     #29                 // Field DATA_LOCATION_S3:Lsoftware/amazon/awssdk/services/machinelearning/model/DataSourceFilterVariable;
      75: new           #4                  // class software/amazon/awssdk/services/machinelearning/model/DataSourceFilterVariable
      78: dup
      79: ldc           #30                 // String IAM_USER
      81: iconst_5
      82: ldc           #31                 // String IAMUser
      84: invokespecial #16                 // Method "<init>":(Ljava/lang/String;ILjava/lang/String;)V
      87: putstatic     #32                 // Field IAM_USER:Lsoftware/amazon/awssdk/services/machinelearning/model/DataSourceFilterVariable;
      90: new           #4                  // class software/amazon/awssdk/services/machinelearning/model/DataSourceFilterVariable
      93: dup
      94: ldc           #33                 // String UNKNOWN_TO_SDK_VERSION
      96: bipush        6
      98: aconst_null
      99: invokespecial #16                 // Method "<init>":(Ljava/lang/String;ILjava/lang/String;)V
     102: putstatic     #10                 // Field UNKNOWN_TO_SDK_VERSION:Lsoftware/amazon/awssdk/services/machinelearning/model/DataSourceFilterVariable;
     105: bipush        7
     107: anewarray     #4                  // class software/amazon/awssdk/services/machinelearning/model/DataSourceFilterVariable
     110: dup
     111: iconst_0
     112: getstatic     #17                 // Field CREATED_AT:Lsoftware/amazon/awssdk/services/machinelearning/model/DataSourceFilterVariable;
     115: aastore
     116: dup
     117: iconst_1
     118: getstatic     #20                 // Field LAST_UPDATED_AT:Lsoftware/amazon/awssdk/services/machinelearning/model/DataSourceFilterVariable;
     121: aastore
     122: dup
     123: iconst_2
     124: getstatic     #23                 // Field STATUS:Lsoftware/amazon/awssdk/services/machinelearning/model/DataSourceFilterVariable;
     127: aastore
     128: dup
     129: iconst_3
     130: getstatic     #26                 // Field NAME:Lsoftware/amazon/awssdk/services/machinelearning/model/DataSourceFilterVariable;
     133: aastore
     134: dup
     135: iconst_4
     136: getstatic     #29                 // Field DATA_LOCATION_S3:Lsoftware/amazon/awssdk/services/machinelearning/model/DataSourceFilterVariable;
     139: aastore
     140: dup
     141: iconst_5
     142: getstatic     #32                 // Field IAM_USER:Lsoftware/amazon/awssdk/services/machinelearning/model/DataSourceFilterVariable;
     145: aastore
     146: dup
     147: bipush        6
     149: getstatic     #10                 // Field UNKNOWN_TO_SDK_VERSION:Lsoftware/amazon/awssdk/services/machinelearning/model/DataSourceFilterVariable;
     152: aastore
     153: putstatic     #1                  // Field $VALUES:[Lsoftware/amazon/awssdk/services/machinelearning/model/DataSourceFilterVariable;
     156: ldc           #4                  // class software/amazon/awssdk/services/machinelearning/model/DataSourceFilterVariable
     158: invokedynamic #34,  0             // InvokeDynamic #0:apply:()Ljava/util/function/Function;
     163: invokestatic  #35                 // Method software/amazon/awssdk/utils/internal/EnumUtils.uniqueIndex:(Ljava/lang/Class;Ljava/util/function/Function;)Ljava/util/Map;
     166: putstatic     #9                  // Field VALUE_MAP:Ljava/util/Map;
     169: return
}
