Compiled from "DeleteTagsRequest.java"
public interface software.amazon.awssdk.services.machinelearning.model.DeleteTagsRequest$Builder extends software.amazon.awssdk.services.machinelearning.model.MachineLearningRequest$Builder, software.amazon.awssdk.core.SdkPojo, software.amazon.awssdk.utils.builder.CopyableBuilder<software.amazon.awssdk.services.machinelearning.model.DeleteTagsRequest$Builder, software.amazon.awssdk.services.machinelearning.model.DeleteTagsRequest> {
  public abstract software.amazon.awssdk.services.machinelearning.model.DeleteTagsRequest$Builder tagKeys(java.util.Collection<java.lang.String>);

  public abstract software.amazon.awssdk.services.machinelearning.model.DeleteTagsRequest$Builder tagKeys(java.lang.String...);

  public abstract software.amazon.awssdk.services.machinelearning.model.DeleteTagsRequest$Builder resourceId(java.lang.String);

  public abstract software.amazon.awssdk.services.machinelearning.model.DeleteTagsRequest$Builder resourceType(java.lang.String);

  public abstract software.amazon.awssdk.services.machinelearning.model.DeleteTagsRequest$Builder resourceType(software.amazon.awssdk.services.machinelearning.model.TaggableResourceType);

  public abstract software.amazon.awssdk.services.machinelearning.model.DeleteTagsRequest$Builder overrideConfiguration(software.amazon.awssdk.awscore.AwsRequestOverrideConfiguration);

  public abstract software.amazon.awssdk.services.machinelearning.model.DeleteTagsRequest$Builder overrideConfiguration(java.util.function.Consumer<software.amazon.awssdk.awscore.AwsRequestOverrideConfiguration$Builder>);

  public default software.amazon.awssdk.awscore.AwsRequest$Builder overrideConfiguration(java.util.function.Consumer);
    Code:
       0: aload_0
       1: aload_1
       2: invokeinterface #1,  2            // InterfaceMethod overrideConfiguration:(Ljava/util/function/Consumer;)Lsoftware/amazon/awssdk/services/machinelearning/model/DeleteTagsRequest$Builder;
       7: areturn

  public default software.amazon.awssdk.awscore.AwsRequest$Builder overrideConfiguration(software.amazon.awssdk.awscore.AwsRequestOverrideConfiguration);
    Code:
       0: aload_0
       1: aload_1
       2: invokeinterface #2,  2            // InterfaceMethod overrideConfiguration:(Lsoftware/amazon/awssdk/awscore/AwsRequestOverrideConfiguration;)Lsoftware/amazon/awssdk/services/machinelearning/model/DeleteTagsRequest$Builder;
       7: areturn
}
