Compiled from "GetBatchPredictionResponse.java"
final class software.amazon.awssdk.services.machinelearning.model.GetBatchPredictionResponse$BuilderImpl extends software.amazon.awssdk.services.machinelearning.model.MachineLearningResponse$BuilderImpl implements software.amazon.awssdk.services.machinelearning.model.GetBatchPredictionResponse$Builder {
  private java.lang.String batchPredictionId;

  private java.lang.String mlModelId;

  private java.lang.String batchPredictionDataSourceId;

  private java.lang.String inputDataLocationS3;

  private java.lang.String createdByIamUser;

  private java.time.Instant createdAt;

  private java.time.Instant lastUpdatedAt;

  private java.lang.String name;

  private java.lang.String status;

  private java.lang.String outputUri;

  private java.lang.String logUri;

  private java.lang.String message;

  private java.lang.Long computeTime;

  private java.time.Instant finishedAt;

  private java.time.Instant startedAt;

  private java.lang.Long totalRecordCount;

  private java.lang.Long invalidRecordCount;

  private software.amazon.awssdk.services.machinelearning.model.GetBatchPredictionResponse$BuilderImpl();
    Code:
       0: aload_0
       1: invokespecial #20                 // Method software/amazon/awssdk/services/machinelearning/model/MachineLearningResponse$BuilderImpl."<init>":()V
       4: return

  private software.amazon.awssdk.services.machinelearning.model.GetBatchPredictionResponse$BuilderImpl(software.amazon.awssdk.services.machinelearning.model.GetBatchPredictionResponse);
    Code:
       0: aload_0
       1: aload_1
       2: invokespecial #21                 // Method software/amazon/awssdk/services/machinelearning/model/MachineLearningResponse$BuilderImpl."<init>":(Lsoftware/amazon/awssdk/services/machinelearning/model/MachineLearningResponse;)V
       5: aload_0
       6: aload_1
       7: invokestatic  #22                 // Method software/amazon/awssdk/services/machinelearning/model/GetBatchPredictionResponse.access$1900:(Lsoftware/amazon/awssdk/services/machinelearning/model/GetBatchPredictionResponse;)Ljava/lang/String;
      10: invokevirtual #23                 // Method batchPredictionId:(Ljava/lang/String;)Lsoftware/amazon/awssdk/services/machinelearning/model/GetBatchPredictionResponse$Builder;
      13: pop
      14: aload_0
      15: aload_1
      16: invokestatic  #24                 // Method software/amazon/awssdk/services/machinelearning/model/GetBatchPredictionResponse.access$2000:(Lsoftware/amazon/awssdk/services/machinelearning/model/GetBatchPredictionResponse;)Ljava/lang/String;
      19: invokevirtual #25                 // Method mlModelId:(Ljava/lang/String;)Lsoftware/amazon/awssdk/services/machinelearning/model/GetBatchPredictionResponse$Builder;
      22: pop
      23: aload_0
      24: aload_1
      25: invokestatic  #26                 // Method software/amazon/awssdk/services/machinelearning/model/GetBatchPredictionResponse.access$2100:(Lsoftware/amazon/awssdk/services/machinelearning/model/GetBatchPredictionResponse;)Ljava/lang/String;
      28: invokevirtual #27                 // Method batchPredictionDataSourceId:(Ljava/lang/String;)Lsoftware/amazon/awssdk/services/machinelearning/model/GetBatchPredictionResponse$Builder;
      31: pop
      32: aload_0
      33: aload_1
      34: invokestatic  #28                 // Method software/amazon/awssdk/services/machinelearning/model/GetBatchPredictionResponse.access$2200:(Lsoftware/amazon/awssdk/services/machinelearning/model/GetBatchPredictionResponse;)Ljava/lang/String;
      37: invokevirtual #29                 // Method inputDataLocationS3:(Ljava/lang/String;)Lsoftware/amazon/awssdk/services/machinelearning/model/GetBatchPredictionResponse$Builder;
      40: pop
      41: aload_0
      42: aload_1
      43: invokestatic  #30                 // Method software/amazon/awssdk/services/machinelearning/model/GetBatchPredictionResponse.access$2300:(Lsoftware/amazon/awssdk/services/machinelearning/model/GetBatchPredictionResponse;)Ljava/lang/String;
      46: invokevirtual #31                 // Method createdByIamUser:(Ljava/lang/String;)Lsoftware/amazon/awssdk/services/machinelearning/model/GetBatchPredictionResponse$Builder;
      49: pop
      50: aload_0
      51: aload_1
      52: invokestatic  #32                 // Method software/amazon/awssdk/services/machinelearning/model/GetBatchPredictionResponse.access$2400:(Lsoftware/amazon/awssdk/services/machinelearning/model/GetBatchPredictionResponse;)Ljava/time/Instant;
      55: invokevirtual #33                 // Method createdAt:(Ljava/time/Instant;)Lsoftware/amazon/awssdk/services/machinelearning/model/GetBatchPredictionResponse$Builder;
      58: pop
      59: aload_0
      60: aload_1
      61: invokestatic  #34                 // Method software/amazon/awssdk/services/machinelearning/model/GetBatchPredictionResponse.access$2500:(Lsoftware/amazon/awssdk/services/machinelearning/model/GetBatchPredictionResponse;)Ljava/time/Instant;
      64: invokevirtual #35                 // Method lastUpdatedAt:(Ljava/time/Instant;)Lsoftware/amazon/awssdk/services/machinelearning/model/GetBatchPredictionResponse$Builder;
      67: pop
      68: aload_0
      69: aload_1
      70: invokestatic  #36                 // Method software/amazon/awssdk/services/machinelearning/model/GetBatchPredictionResponse.access$2600:(Lsoftware/amazon/awssdk/services/machinelearning/model/GetBatchPredictionResponse;)Ljava/lang/String;
      73: invokevirtual #37                 // Method name:(Ljava/lang/String;)Lsoftware/amazon/awssdk/services/machinelearning/model/GetBatchPredictionResponse$Builder;
      76: pop
      77: aload_0
      78: aload_1
      79: invokestatic  #38                 // Method software/amazon/awssdk/services/machinelearning/model/GetBatchPredictionResponse.access$2700:(Lsoftware/amazon/awssdk/services/machinelearning/model/GetBatchPredictionResponse;)Ljava/lang/String;
      82: invokevirtual #39                 // Method status:(Ljava/lang/String;)Lsoftware/amazon/awssdk/services/machinelearning/model/GetBatchPredictionResponse$Builder;
      85: pop
      86: aload_0
      87: aload_1
      88: invokestatic  #40                 // Method software/amazon/awssdk/services/machinelearning/model/GetBatchPredictionResponse.access$2800:(Lsoftware/amazon/awssdk/services/machinelearning/model/GetBatchPredictionResponse;)Ljava/lang/String;
      91: invokevirtual #41                 // Method outputUri:(Ljava/lang/String;)Lsoftware/amazon/awssdk/services/machinelearning/model/GetBatchPredictionResponse$Builder;
      94: pop
      95: aload_0
      96: aload_1
      97: invokestatic  #42                 // Method software/amazon/awssdk/services/machinelearning/model/GetBatchPredictionResponse.access$2900:(Lsoftware/amazon/awssdk/services/machinelearning/model/GetBatchPredictionResponse;)Ljava/lang/String;
     100: invokevirtual #43                 // Method logUri:(Ljava/lang/String;)Lsoftware/amazon/awssdk/services/machinelearning/model/GetBatchPredictionResponse$Builder;
     103: pop
     104: aload_0
     105: aload_1
     106: invokestatic  #44                 // Method software/amazon/awssdk/services/machinelearning/model/GetBatchPredictionResponse.access$3000:(Lsoftware/amazon/awssdk/services/machinelearning/model/GetBatchPredictionResponse;)Ljava/lang/String;
     109: invokevirtual #45                 // Method message:(Ljava/lang/String;)Lsoftware/amazon/awssdk/services/machinelearning/model/GetBatchPredictionResponse$Builder;
     112: pop
     113: aload_0
     114: aload_1
     115: invokestatic  #46                 // Method software/amazon/awssdk/services/machinelearning/model/GetBatchPredictionResponse.access$3100:(Lsoftware/amazon/awssdk/services/machinelearning/model/GetBatchPredictionResponse;)Ljava/lang/Long;
     118: invokevirtual #47                 // Method computeTime:(Ljava/lang/Long;)Lsoftware/amazon/awssdk/services/machinelearning/model/GetBatchPredictionResponse$Builder;
     121: pop
     122: aload_0
     123: aload_1
     124: invokestatic  #48                 // Method software/amazon/awssdk/services/machinelearning/model/GetBatchPredictionResponse.access$3200:(Lsoftware/amazon/awssdk/services/machinelearning/model/GetBatchPredictionResponse;)Ljava/time/Instant;
     127: invokevirtual #49                 // Method finishedAt:(Ljava/time/Instant;)Lsoftware/amazon/awssdk/services/machinelearning/model/GetBatchPredictionResponse$Builder;
     130: pop
     131: aload_0
     132: aload_1
     133: invokestatic  #50                 // Method software/amazon/awssdk/services/machinelearning/model/GetBatchPredictionResponse.access$3300:(Lsoftware/amazon/awssdk/services/machinelearning/model/GetBatchPredictionResponse;)Ljava/time/Instant;
     136: invokevirtual #51                 // Method startedAt:(Ljava/time/Instant;)Lsoftware/amazon/awssdk/services/machinelearning/model/GetBatchPredictionResponse$Builder;
     139: pop
     140: aload_0
     141: aload_1
     142: invokestatic  #52                 // Method software/amazon/awssdk/services/machinelearning/model/GetBatchPredictionResponse.access$3400:(Lsoftware/amazon/awssdk/services/machinelearning/model/GetBatchPredictionResponse;)Ljava/lang/Long;
     145: invokevirtual #53                 // Method totalRecordCount:(Ljava/lang/Long;)Lsoftware/amazon/awssdk/services/machinelearning/model/GetBatchPredictionResponse$Builder;
     148: pop
     149: aload_0
     150: aload_1
     151: invokestatic  #54                 // Method software/amazon/awssdk/services/machinelearning/model/GetBatchPredictionResponse.access$3500:(Lsoftware/amazon/awssdk/services/machinelearning/model/GetBatchPredictionResponse;)Ljava/lang/Long;
     154: invokevirtual #55                 // Method invalidRecordCount:(Ljava/lang/Long;)Lsoftware/amazon/awssdk/services/machinelearning/model/GetBatchPredictionResponse$Builder;
     157: pop
     158: return

  public final java.lang.String getBatchPredictionId();
    Code:
       0: aload_0
       1: getfield      #19                 // Field batchPredictionId:Ljava/lang/String;
       4: areturn

  public final void setBatchPredictionId(java.lang.String);
    Code:
       0: aload_0
       1: aload_1
       2: putfield      #19                 // Field batchPredictionId:Ljava/lang/String;
       5: return

  public final software.amazon.awssdk.services.machinelearning.model.GetBatchPredictionResponse$Builder batchPredictionId(java.lang.String);
    Code:
       0: aload_0
       1: aload_1
       2: putfield      #19                 // Field batchPredictionId:Ljava/lang/String;
       5: aload_0
       6: areturn

  public final java.lang.String getMlModelId();
    Code:
       0: aload_0
       1: getfield      #18                 // Field mlModelId:Ljava/lang/String;
       4: areturn

  public final void setMlModelId(java.lang.String);
    Code:
       0: aload_0
       1: aload_1
       2: putfield      #18                 // Field mlModelId:Ljava/lang/String;
       5: return

  public final software.amazon.awssdk.services.machinelearning.model.GetBatchPredictionResponse$Builder mlModelId(java.lang.String);
    Code:
       0: aload_0
       1: aload_1
       2: putfield      #18                 // Field mlModelId:Ljava/lang/String;
       5: aload_0
       6: areturn

  public final java.lang.String getBatchPredictionDataSourceId();
    Code:
       0: aload_0
       1: getfield      #17                 // Field batchPredictionDataSourceId:Ljava/lang/String;
       4: areturn

  public final void setBatchPredictionDataSourceId(java.lang.String);
    Code:
       0: aload_0
       1: aload_1
       2: putfield      #17                 // Field batchPredictionDataSourceId:Ljava/lang/String;
       5: return

  public final software.amazon.awssdk.services.machinelearning.model.GetBatchPredictionResponse$Builder batchPredictionDataSourceId(java.lang.String);
    Code:
       0: aload_0
       1: aload_1
       2: putfield      #17                 // Field batchPredictionDataSourceId:Ljava/lang/String;
       5: aload_0
       6: areturn

  public final java.lang.String getInputDataLocationS3();
    Code:
       0: aload_0
       1: getfield      #16                 // Field inputDataLocationS3:Ljava/lang/String;
       4: areturn

  public final void setInputDataLocationS3(java.lang.String);
    Code:
       0: aload_0
       1: aload_1
       2: putfield      #16                 // Field inputDataLocationS3:Ljava/lang/String;
       5: return

  public final software.amazon.awssdk.services.machinelearning.model.GetBatchPredictionResponse$Builder inputDataLocationS3(java.lang.String);
    Code:
       0: aload_0
       1: aload_1
       2: putfield      #16                 // Field inputDataLocationS3:Ljava/lang/String;
       5: aload_0
       6: areturn

  public final java.lang.String getCreatedByIamUser();
    Code:
       0: aload_0
       1: getfield      #15                 // Field createdByIamUser:Ljava/lang/String;
       4: areturn

  public final void setCreatedByIamUser(java.lang.String);
    Code:
       0: aload_0
       1: aload_1
       2: putfield      #15                 // Field createdByIamUser:Ljava/lang/String;
       5: return

  public final software.amazon.awssdk.services.machinelearning.model.GetBatchPredictionResponse$Builder createdByIamUser(java.lang.String);
    Code:
       0: aload_0
       1: aload_1
       2: putfield      #15                 // Field createdByIamUser:Ljava/lang/String;
       5: aload_0
       6: areturn

  public final java.time.Instant getCreatedAt();
    Code:
       0: aload_0
       1: getfield      #14                 // Field createdAt:Ljava/time/Instant;
       4: areturn

  public final void setCreatedAt(java.time.Instant);
    Code:
       0: aload_0
       1: aload_1
       2: putfield      #14                 // Field createdAt:Ljava/time/Instant;
       5: return

  public final software.amazon.awssdk.services.machinelearning.model.GetBatchPredictionResponse$Builder createdAt(java.time.Instant);
    Code:
       0: aload_0
       1: aload_1
       2: putfield      #14                 // Field createdAt:Ljava/time/Instant;
       5: aload_0
       6: areturn

  public final java.time.Instant getLastUpdatedAt();
    Code:
       0: aload_0
       1: getfield      #13                 // Field lastUpdatedAt:Ljava/time/Instant;
       4: areturn

  public final void setLastUpdatedAt(java.time.Instant);
    Code:
       0: aload_0
       1: aload_1
       2: putfield      #13                 // Field lastUpdatedAt:Ljava/time/Instant;
       5: return

  public final software.amazon.awssdk.services.machinelearning.model.GetBatchPredictionResponse$Builder lastUpdatedAt(java.time.Instant);
    Code:
       0: aload_0
       1: aload_1
       2: putfield      #13                 // Field lastUpdatedAt:Ljava/time/Instant;
       5: aload_0
       6: areturn

  public final java.lang.String getName();
    Code:
       0: aload_0
       1: getfield      #12                 // Field name:Ljava/lang/String;
       4: areturn

  public final void setName(java.lang.String);
    Code:
       0: aload_0
       1: aload_1
       2: putfield      #12                 // Field name:Ljava/lang/String;
       5: return

  public final software.amazon.awssdk.services.machinelearning.model.GetBatchPredictionResponse$Builder name(java.lang.String);
    Code:
       0: aload_0
       1: aload_1
       2: putfield      #12                 // Field name:Ljava/lang/String;
       5: aload_0
       6: areturn

  public final java.lang.String getStatus();
    Code:
       0: aload_0
       1: getfield      #11                 // Field status:Ljava/lang/String;
       4: areturn

  public final void setStatus(java.lang.String);
    Code:
       0: aload_0
       1: aload_1
       2: putfield      #11                 // Field status:Ljava/lang/String;
       5: return

  public final software.amazon.awssdk.services.machinelearning.model.GetBatchPredictionResponse$Builder status(java.lang.String);
    Code:
       0: aload_0
       1: aload_1
       2: putfield      #11                 // Field status:Ljava/lang/String;
       5: aload_0
       6: areturn

  public final software.amazon.awssdk.services.machinelearning.model.GetBatchPredictionResponse$Builder status(software.amazon.awssdk.services.machinelearning.model.EntityStatus);
    Code:
       0: aload_0
       1: aload_1
       2: ifnonnull     9
       5: aconst_null
       6: goto          13
       9: aload_1
      10: invokevirtual #56                 // Method software/amazon/awssdk/services/machinelearning/model/EntityStatus.toString:()Ljava/lang/String;
      13: invokevirtual #39                 // Method status:(Ljava/lang/String;)Lsoftware/amazon/awssdk/services/machinelearning/model/GetBatchPredictionResponse$Builder;
      16: pop
      17: aload_0
      18: areturn

  public final java.lang.String getOutputUri();
    Code:
       0: aload_0
       1: getfield      #10                 // Field outputUri:Ljava/lang/String;
       4: areturn

  public final void setOutputUri(java.lang.String);
    Code:
       0: aload_0
       1: aload_1
       2: putfield      #10                 // Field outputUri:Ljava/lang/String;
       5: return

  public final software.amazon.awssdk.services.machinelearning.model.GetBatchPredictionResponse$Builder outputUri(java.lang.String);
    Code:
       0: aload_0
       1: aload_1
       2: putfield      #10                 // Field outputUri:Ljava/lang/String;
       5: aload_0
       6: areturn

  public final java.lang.String getLogUri();
    Code:
       0: aload_0
       1: getfield      #9                  // Field logUri:Ljava/lang/String;
       4: areturn

  public final void setLogUri(java.lang.String);
    Code:
       0: aload_0
       1: aload_1
       2: putfield      #9                  // Field logUri:Ljava/lang/String;
       5: return

  public final software.amazon.awssdk.services.machinelearning.model.GetBatchPredictionResponse$Builder logUri(java.lang.String);
    Code:
       0: aload_0
       1: aload_1
       2: putfield      #9                  // Field logUri:Ljava/lang/String;
       5: aload_0
       6: areturn

  public final java.lang.String getMessage();
    Code:
       0: aload_0
       1: getfield      #8                  // Field message:Ljava/lang/String;
       4: areturn

  public final void setMessage(java.lang.String);
    Code:
       0: aload_0
       1: aload_1
       2: putfield      #8                  // Field message:Ljava/lang/String;
       5: return

  public final software.amazon.awssdk.services.machinelearning.model.GetBatchPredictionResponse$Builder message(java.lang.String);
    Code:
       0: aload_0
       1: aload_1
       2: putfield      #8                  // Field message:Ljava/lang/String;
       5: aload_0
       6: areturn

  public final java.lang.Long getComputeTime();
    Code:
       0: aload_0
       1: getfield      #7                  // Field computeTime:Ljava/lang/Long;
       4: areturn

  public final void setComputeTime(java.lang.Long);
    Code:
       0: aload_0
       1: aload_1
       2: putfield      #7                  // Field computeTime:Ljava/lang/Long;
       5: return

  public final software.amazon.awssdk.services.machinelearning.model.GetBatchPredictionResponse$Builder computeTime(java.lang.Long);
    Code:
       0: aload_0
       1: aload_1
       2: putfield      #7                  // Field computeTime:Ljava/lang/Long;
       5: aload_0
       6: areturn

  public final java.time.Instant getFinishedAt();
    Code:
       0: aload_0
       1: getfield      #6                  // Field finishedAt:Ljava/time/Instant;
       4: areturn

  public final void setFinishedAt(java.time.Instant);
    Code:
       0: aload_0
       1: aload_1
       2: putfield      #6                  // Field finishedAt:Ljava/time/Instant;
       5: return

  public final software.amazon.awssdk.services.machinelearning.model.GetBatchPredictionResponse$Builder finishedAt(java.time.Instant);
    Code:
       0: aload_0
       1: aload_1
       2: putfield      #6                  // Field finishedAt:Ljava/time/Instant;
       5: aload_0
       6: areturn

  public final java.time.Instant getStartedAt();
    Code:
       0: aload_0
       1: getfield      #5                  // Field startedAt:Ljava/time/Instant;
       4: areturn

  public final void setStartedAt(java.time.Instant);
    Code:
       0: aload_0
       1: aload_1
       2: putfield      #5                  // Field startedAt:Ljava/time/Instant;
       5: return

  public final software.amazon.awssdk.services.machinelearning.model.GetBatchPredictionResponse$Builder startedAt(java.time.Instant);
    Code:
       0: aload_0
       1: aload_1
       2: putfield      #5                  // Field startedAt:Ljava/time/Instant;
       5: aload_0
       6: areturn

  public final java.lang.Long getTotalRecordCount();
    Code:
       0: aload_0
       1: getfield      #4                  // Field totalRecordCount:Ljava/lang/Long;
       4: areturn

  public final void setTotalRecordCount(java.lang.Long);
    Code:
       0: aload_0
       1: aload_1
       2: putfield      #4                  // Field totalRecordCount:Ljava/lang/Long;
       5: return

  public final software.amazon.awssdk.services.machinelearning.model.GetBatchPredictionResponse$Builder totalRecordCount(java.lang.Long);
    Code:
       0: aload_0
       1: aload_1
       2: putfield      #4                  // Field totalRecordCount:Ljava/lang/Long;
       5: aload_0
       6: areturn

  public final java.lang.Long getInvalidRecordCount();
    Code:
       0: aload_0
       1: getfield      #3                  // Field invalidRecordCount:Ljava/lang/Long;
       4: areturn

  public final void setInvalidRecordCount(java.lang.Long);
    Code:
       0: aload_0
       1: aload_1
       2: putfield      #3                  // Field invalidRecordCount:Ljava/lang/Long;
       5: return

  public final software.amazon.awssdk.services.machinelearning.model.GetBatchPredictionResponse$Builder invalidRecordCount(java.lang.Long);
    Code:
       0: aload_0
       1: aload_1
       2: putfield      #3                  // Field invalidRecordCount:Ljava/lang/Long;
       5: aload_0
       6: areturn

  public software.amazon.awssdk.services.machinelearning.model.GetBatchPredictionResponse build();
    Code:
       0: new           #57                 // class software/amazon/awssdk/services/machinelearning/model/GetBatchPredictionResponse
       3: dup
       4: aload_0
       5: aconst_null
       6: invokespecial #58                 // Method software/amazon/awssdk/services/machinelearning/model/GetBatchPredictionResponse."<init>":(Lsoftware/amazon/awssdk/services/machinelearning/model/GetBatchPredictionResponse$BuilderImpl;Lsoftware/amazon/awssdk/services/machinelearning/model/GetBatchPredictionResponse$1;)V
       9: areturn

  public java.util.List<software.amazon.awssdk.core.SdkField<?>> sdkFields();
    Code:
       0: invokestatic  #59                 // Method software/amazon/awssdk/services/machinelearning/model/GetBatchPredictionResponse.access$3700:()Ljava/util/List;
       3: areturn

  public software.amazon.awssdk.services.machinelearning.model.MachineLearningResponse build();
    Code:
       0: aload_0
       1: invokevirtual #60                 // Method build:()Lsoftware/amazon/awssdk/services/machinelearning/model/GetBatchPredictionResponse;
       4: areturn

  public software.amazon.awssdk.awscore.AwsResponse build();
    Code:
       0: aload_0
       1: invokevirtual #60                 // Method build:()Lsoftware/amazon/awssdk/services/machinelearning/model/GetBatchPredictionResponse;
       4: areturn

  public software.amazon.awssdk.core.SdkResponse build();
    Code:
       0: aload_0
       1: invokevirtual #60                 // Method build:()Lsoftware/amazon/awssdk/services/machinelearning/model/GetBatchPredictionResponse;
       4: areturn

  public java.lang.Object build();
    Code:
       0: aload_0
       1: invokevirtual #60                 // Method build:()Lsoftware/amazon/awssdk/services/machinelearning/model/GetBatchPredictionResponse;
       4: areturn

  static java.lang.String access$000(software.amazon.awssdk.services.machinelearning.model.GetBatchPredictionResponse$BuilderImpl);
    Code:
       0: aload_0
       1: getfield      #19                 // Field batchPredictionId:Ljava/lang/String;
       4: areturn

  static java.lang.String access$100(software.amazon.awssdk.services.machinelearning.model.GetBatchPredictionResponse$BuilderImpl);
    Code:
       0: aload_0
       1: getfield      #18                 // Field mlModelId:Ljava/lang/String;
       4: areturn

  static java.lang.String access$200(software.amazon.awssdk.services.machinelearning.model.GetBatchPredictionResponse$BuilderImpl);
    Code:
       0: aload_0
       1: getfield      #17                 // Field batchPredictionDataSourceId:Ljava/lang/String;
       4: areturn

  static java.lang.String access$300(software.amazon.awssdk.services.machinelearning.model.GetBatchPredictionResponse$BuilderImpl);
    Code:
       0: aload_0
       1: getfield      #16                 // Field inputDataLocationS3:Ljava/lang/String;
       4: areturn

  static java.lang.String access$400(software.amazon.awssdk.services.machinelearning.model.GetBatchPredictionResponse$BuilderImpl);
    Code:
       0: aload_0
       1: getfield      #15                 // Field createdByIamUser:Ljava/lang/String;
       4: areturn

  static java.time.Instant access$500(software.amazon.awssdk.services.machinelearning.model.GetBatchPredictionResponse$BuilderImpl);
    Code:
       0: aload_0
       1: getfield      #14                 // Field createdAt:Ljava/time/Instant;
       4: areturn

  static java.time.Instant access$600(software.amazon.awssdk.services.machinelearning.model.GetBatchPredictionResponse$BuilderImpl);
    Code:
       0: aload_0
       1: getfield      #13                 // Field lastUpdatedAt:Ljava/time/Instant;
       4: areturn

  static java.lang.String access$700(software.amazon.awssdk.services.machinelearning.model.GetBatchPredictionResponse$BuilderImpl);
    Code:
       0: aload_0
       1: getfield      #12                 // Field name:Ljava/lang/String;
       4: areturn

  static java.lang.String access$800(software.amazon.awssdk.services.machinelearning.model.GetBatchPredictionResponse$BuilderImpl);
    Code:
       0: aload_0
       1: getfield      #11                 // Field status:Ljava/lang/String;
       4: areturn

  static java.lang.String access$900(software.amazon.awssdk.services.machinelearning.model.GetBatchPredictionResponse$BuilderImpl);
    Code:
       0: aload_0
       1: getfield      #10                 // Field outputUri:Ljava/lang/String;
       4: areturn

  static java.lang.String access$1000(software.amazon.awssdk.services.machinelearning.model.GetBatchPredictionResponse$BuilderImpl);
    Code:
       0: aload_0
       1: getfield      #9                  // Field logUri:Ljava/lang/String;
       4: areturn

  static java.lang.String access$1100(software.amazon.awssdk.services.machinelearning.model.GetBatchPredictionResponse$BuilderImpl);
    Code:
       0: aload_0
       1: getfield      #8                  // Field message:Ljava/lang/String;
       4: areturn

  static java.lang.Long access$1200(software.amazon.awssdk.services.machinelearning.model.GetBatchPredictionResponse$BuilderImpl);
    Code:
       0: aload_0
       1: getfield      #7                  // Field computeTime:Ljava/lang/Long;
       4: areturn

  static java.time.Instant access$1300(software.amazon.awssdk.services.machinelearning.model.GetBatchPredictionResponse$BuilderImpl);
    Code:
       0: aload_0
       1: getfield      #6                  // Field finishedAt:Ljava/time/Instant;
       4: areturn

  static java.time.Instant access$1400(software.amazon.awssdk.services.machinelearning.model.GetBatchPredictionResponse$BuilderImpl);
    Code:
       0: aload_0
       1: getfield      #5                  // Field startedAt:Ljava/time/Instant;
       4: areturn

  static java.lang.Long access$1500(software.amazon.awssdk.services.machinelearning.model.GetBatchPredictionResponse$BuilderImpl);
    Code:
       0: aload_0
       1: getfield      #4                  // Field totalRecordCount:Ljava/lang/Long;
       4: areturn

  static java.lang.Long access$1600(software.amazon.awssdk.services.machinelearning.model.GetBatchPredictionResponse$BuilderImpl);
    Code:
       0: aload_0
       1: getfield      #3                  // Field invalidRecordCount:Ljava/lang/Long;
       4: areturn

  software.amazon.awssdk.services.machinelearning.model.GetBatchPredictionResponse$BuilderImpl(software.amazon.awssdk.services.machinelearning.model.GetBatchPredictionResponse, software.amazon.awssdk.services.machinelearning.model.GetBatchPredictionResponse$1);
    Code:
       0: aload_0
       1: aload_1
       2: invokespecial #2                  // Method "<init>":(Lsoftware/amazon/awssdk/services/machinelearning/model/GetBatchPredictionResponse;)V
       5: return

  software.amazon.awssdk.services.machinelearning.model.GetBatchPredictionResponse$BuilderImpl(software.amazon.awssdk.services.machinelearning.model.GetBatchPredictionResponse$1);
    Code:
       0: aload_0
       1: invokespecial #1                  // Method "<init>":()V
       4: return
}
