Compiled from "PredictResponse.java"
public interface software.amazon.awssdk.services.machinelearning.model.PredictResponse$Builder extends software.amazon.awssdk.services.machinelearning.model.MachineLearningResponse$Builder, software.amazon.awssdk.core.SdkPojo, software.amazon.awssdk.utils.builder.CopyableBuilder<software.amazon.awssdk.services.machinelearning.model.PredictResponse$Builder, software.amazon.awssdk.services.machinelearning.model.PredictResponse> {
  public abstract software.amazon.awssdk.services.machinelearning.model.PredictResponse$Builder prediction(software.amazon.awssdk.services.machinelearning.model.Prediction);

  public default software.amazon.awssdk.services.machinelearning.model.PredictResponse$Builder prediction(java.util.function.Consumer<software.amazon.awssdk.services.machinelearning.model.Prediction$Builder>);
    Code:
       0: aload_0
       1: invokestatic  #1                  // Method software/amazon/awssdk/services/machinelearning/model/Prediction.builder:()Lsoftware/amazon/awssdk/services/machinelearning/model/Prediction$Builder;
       4: aload_1
       5: invokeinterface #2,  2            // InterfaceMethod software/amazon/awssdk/services/machinelearning/model/Prediction$Builder.applyMutation:(Ljava/util/function/Consumer;)Lsoftware/amazon/awssdk/utils/builder/SdkBuilder;
      10: checkcast     #3                  // class software/amazon/awssdk/services/machinelearning/model/Prediction$Builder
      13: invokeinterface #4,  1            // InterfaceMethod software/amazon/awssdk/services/machinelearning/model/Prediction$Builder.build:()Ljava/lang/Object;
      18: checkcast     #5                  // class software/amazon/awssdk/services/machinelearning/model/Prediction
      21: invokeinterface #6,  2            // InterfaceMethod prediction:(Lsoftware/amazon/awssdk/services/machinelearning/model/Prediction;)Lsoftware/amazon/awssdk/services/machinelearning/model/PredictResponse$Builder;
      26: areturn
}
