Compiled from "Analyze.scala"
public final class sbt.internal.inc.classfile.Analyze {
  public static <T> void apply(scala.collection.Seq<java.io.File>, scala.collection.Seq<java.io.File>, sbt.util.Logger, xsbti.compile.Output, scala.Option<java.io.File>, xsbti.AnalysisCallback, java.lang.ClassLoader, scala.Function2<java.io.File, scala.collection.Seq<java.lang.Class<?>>, scala.collection.immutable.Set<scala.Tuple2<java.lang.String, java.lang.String>>>);
    Code:
       0: getstatic     #25                 // Field sbt/internal/inc/classfile/Analyze$.MODULE$:Lsbt/internal/inc/classfile/Analyze$;
       3: aload_0
       4: aload_1
       5: aload_2
       6: aload_3
       7: aload         4
       9: aload         5
      11: aload         6
      13: aload         7
      15: invokevirtual #27                 // Method sbt/internal/inc/classfile/Analyze$.apply:(Lscala/collection/Seq;Lscala/collection/Seq;Lsbt/util/Logger;Lxsbti/compile/Output;Lscala/Option;Lxsbti/AnalysisCallback;Ljava/lang/ClassLoader;Lscala/Function2;)V
      18: return
}
