Compiled from "ClassFile.scala"
public final class sbt.internal.inc.classfile.Constant implements scala.Product,scala.Serializable {
  private final byte tag;

  private final int nameIndex;

  private final int typeIndex;

  private final scala.Option<java.lang.Object> value;

  public static scala.Option<scala.Tuple4<java.lang.Object, java.lang.Object, java.lang.Object, scala.Option<java.lang.Object>>> unapply(sbt.internal.inc.classfile.Constant);
    Code:
       0: getstatic     #30                 // Field sbt/internal/inc/classfile/Constant$.MODULE$:Lsbt/internal/inc/classfile/Constant$;
       3: aload_0
       4: invokevirtual #32                 // Method sbt/internal/inc/classfile/Constant$.unapply:(Lsbt/internal/inc/classfile/Constant;)Lscala/Option;
       7: areturn

  public static sbt.internal.inc.classfile.Constant apply(byte, int, int, scala.Option<java.lang.Object>);
    Code:
       0: getstatic     #30                 // Field sbt/internal/inc/classfile/Constant$.MODULE$:Lsbt/internal/inc/classfile/Constant$;
       3: iload_0
       4: iload_1
       5: iload_2
       6: aload_3
       7: invokevirtual #37                 // Method sbt/internal/inc/classfile/Constant$.apply:(BIILscala/Option;)Lsbt/internal/inc/classfile/Constant;
      10: areturn

  public static scala.Function1<scala.Tuple4<java.lang.Object, java.lang.Object, java.lang.Object, scala.Option<java.lang.Object>>, sbt.internal.inc.classfile.Constant> tupled();
    Code:
       0: getstatic     #30                 // Field sbt/internal/inc/classfile/Constant$.MODULE$:Lsbt/internal/inc/classfile/Constant$;
       3: invokevirtual #42                 // Method sbt/internal/inc/classfile/Constant$.tupled:()Lscala/Function1;
       6: areturn

  public static scala.Function1<java.lang.Object, scala.Function1<java.lang.Object, scala.Function1<java.lang.Object, scala.Function1<scala.Option<java.lang.Object>, sbt.internal.inc.classfile.Constant>>>> curried();
    Code:
       0: getstatic     #30                 // Field sbt/internal/inc/classfile/Constant$.MODULE$:Lsbt/internal/inc/classfile/Constant$;
       3: invokevirtual #46                 // Method sbt/internal/inc/classfile/Constant$.curried:()Lscala/Function1;
       6: areturn

  public byte tag();
    Code:
       0: aload_0
       1: getfield      #49                 // Field tag:B
       4: ireturn

  public int nameIndex();
    Code:
       0: aload_0
       1: getfield      #54                 // Field nameIndex:I
       4: ireturn

  public int typeIndex();
    Code:
       0: aload_0
       1: getfield      #56                 // Field typeIndex:I
       4: ireturn

  public scala.Option<java.lang.Object> value();
    Code:
       0: aload_0
       1: getfield      #60                 // Field value:Lscala/Option;
       4: areturn

  public boolean wide();
    Code:
       0: aload_0
       1: invokevirtual #64                 // Method tag:()B
       4: iconst_5
       5: if_icmpeq     17
       8: aload_0
       9: invokevirtual #64                 // Method tag:()B
      12: bipush        6
      14: if_icmpne     19
      17: iconst_1
      18: ireturn
      19: iconst_0
      20: ireturn

  public int hashCode();
    Code:
       0: bipush        37
       2: bipush        37
       4: bipush        37
       6: bipush        37
       8: bipush        17
      10: aload_0
      11: invokevirtual #64                 // Method tag:()B
      14: iadd
      15: imul
      16: aload_0
      17: invokevirtual #67                 // Method nameIndex:()I
      20: iadd
      21: imul
      22: aload_0
      23: invokevirtual #69                 // Method typeIndex:()I
      26: iadd
      27: imul
      28: aload_0
      29: invokevirtual #71                 // Method value:()Lscala/Option;
      32: invokestatic  #77                 // Method scala/runtime/Statics.anyHash:(Ljava/lang/Object;)I
      35: iadd
      36: imul
      37: ireturn

  public sbt.internal.inc.classfile.Constant copy(byte, int, int, scala.Option<java.lang.Object>);
    Code:
       0: new           #2                  // class sbt/internal/inc/classfile/Constant
       3: dup
       4: iload_1
       5: iload_2
       6: iload_3
       7: aload         4
       9: invokespecial #82                 // Method "<init>":(BIILscala/Option;)V
      12: areturn

  public byte copy$default$1();
    Code:
       0: aload_0
       1: invokevirtual #64                 // Method tag:()B
       4: ireturn

  public int copy$default$2();
    Code:
       0: aload_0
       1: invokevirtual #67                 // Method nameIndex:()I
       4: ireturn

  public int copy$default$3();
    Code:
       0: aload_0
       1: invokevirtual #69                 // Method typeIndex:()I
       4: ireturn

  public scala.Option<java.lang.Object> copy$default$4();
    Code:
       0: aload_0
       1: invokevirtual #71                 // Method value:()Lscala/Option;
       4: areturn

  public java.lang.String productPrefix();
    Code:
       0: ldc           #90                 // String Constant
       2: areturn

  public int productArity();
    Code:
       0: iconst_4
       1: ireturn

  public java.lang.Object productElement(int);
    Code:
       0: iload_1
       1: tableswitch   { // 0 to 3
                     0: 32
                     1: 40
                     2: 48
                     3: 56
               default: 61
          }
      32: aload_0
      33: invokevirtual #64                 // Method tag:()B
      36: invokestatic  #100                // Method scala/runtime/BoxesRunTime.boxToByte:(B)Ljava/lang/Byte;
      39: areturn
      40: aload_0
      41: invokevirtual #67                 // Method nameIndex:()I
      44: invokestatic  #104                // Method scala/runtime/BoxesRunTime.boxToInteger:(I)Ljava/lang/Integer;
      47: areturn
      48: aload_0
      49: invokevirtual #69                 // Method typeIndex:()I
      52: invokestatic  #104                // Method scala/runtime/BoxesRunTime.boxToInteger:(I)Ljava/lang/Integer;
      55: areturn
      56: aload_0
      57: invokevirtual #71                 // Method value:()Lscala/Option;
      60: areturn
      61: new           #106                // class java/lang/IndexOutOfBoundsException
      64: dup
      65: iload_1
      66: invokestatic  #104                // Method scala/runtime/BoxesRunTime.boxToInteger:(I)Ljava/lang/Integer;
      69: invokevirtual #109                // Method java/lang/Object.toString:()Ljava/lang/String;
      72: invokespecial #112                // Method java/lang/IndexOutOfBoundsException."<init>":(Ljava/lang/String;)V
      75: athrow

  public scala.collection.Iterator<java.lang.Object> productIterator();
    Code:
       0: getstatic     #120                // Field scala/runtime/ScalaRunTime$.MODULE$:Lscala/runtime/ScalaRunTime$;
       3: aload_0
       4: invokevirtual #124                // Method scala/runtime/ScalaRunTime$.typedProductIterator:(Lscala/Product;)Lscala/collection/Iterator;
       7: areturn

  public boolean canEqual(java.lang.Object);
    Code:
       0: aload_1
       1: instanceof    #2                  // class sbt/internal/inc/classfile/Constant
       4: ireturn

  public java.lang.String toString();
    Code:
       0: getstatic     #120                // Field scala/runtime/ScalaRunTime$.MODULE$:Lscala/runtime/ScalaRunTime$;
       3: aload_0
       4: invokevirtual #131                // Method scala/runtime/ScalaRunTime$._toString:(Lscala/Product;)Ljava/lang/String;
       7: areturn

  public boolean equals(java.lang.Object);
    Code:
       0: aload_0
       1: aload_1
       2: if_acmpeq     100
       5: aload_1
       6: instanceof    #2                  // class sbt/internal/inc/classfile/Constant
       9: ifeq          17
      12: iconst_1
      13: istore_2
      14: goto          19
      17: iconst_0
      18: istore_2
      19: iload_2
      20: ifeq          102
      23: aload_1
      24: checkcast     #2                  // class sbt/internal/inc/classfile/Constant
      27: astore_3
      28: aload_0
      29: invokevirtual #64                 // Method tag:()B
      32: aload_3
      33: invokevirtual #64                 // Method tag:()B
      36: if_icmpne     96
      39: aload_0
      40: invokevirtual #67                 // Method nameIndex:()I
      43: aload_3
      44: invokevirtual #67                 // Method nameIndex:()I
      47: if_icmpne     96
      50: aload_0
      51: invokevirtual #69                 // Method typeIndex:()I
      54: aload_3
      55: invokevirtual #69                 // Method typeIndex:()I
      58: if_icmpne     96
      61: aload_0
      62: invokevirtual #71                 // Method value:()Lscala/Option;
      65: aload_3
      66: invokevirtual #71                 // Method value:()Lscala/Option;
      69: astore        4
      71: dup
      72: ifnonnull     84
      75: pop
      76: aload         4
      78: ifnull        92
      81: goto          96
      84: aload         4
      86: invokevirtual #134                // Method java/lang/Object.equals:(Ljava/lang/Object;)Z
      89: ifeq          96
      92: iconst_1
      93: goto          97
      96: iconst_0
      97: ifeq          102
     100: iconst_1
     101: ireturn
     102: iconst_0
     103: ireturn

  public sbt.internal.inc.classfile.Constant(byte, int, int, scala.Option<java.lang.Object>);
    Code:
       0: aload_0
       1: iload_1
       2: putfield      #49                 // Field tag:B
       5: aload_0
       6: iload_2
       7: putfield      #54                 // Field nameIndex:I
      10: aload_0
      11: iload_3
      12: putfield      #56                 // Field typeIndex:I
      15: aload_0
      16: aload         4
      18: putfield      #60                 // Field value:Lscala/Option;
      21: aload_0
      22: invokespecial #140                // Method java/lang/Object."<init>":()V
      25: aload_0
      26: invokestatic  #144                // InterfaceMethod scala/Product.$init$:(Lscala/Product;)V
      29: return

  public sbt.internal.inc.classfile.Constant(byte, int, int);
    Code:
       0: aload_0
       1: iload_1
       2: iload_2
       3: iload_3
       4: getstatic     #150                // Field scala/None$.MODULE$:Lscala/None$;
       7: invokespecial #82                 // Method "<init>":(BIILscala/Option;)V
      10: return

  public sbt.internal.inc.classfile.Constant(byte, int);
    Code:
       0: aload_0
       1: iload_1
       2: iload_2
       3: iconst_m1
       4: invokespecial #153                // Method "<init>":(BII)V
       7: return

  public sbt.internal.inc.classfile.Constant(byte, java.lang.Object);
    Code:
       0: aload_0
       1: iload_1
       2: iconst_m1
       3: iconst_m1
       4: new           #156                // class scala/Some
       7: dup
       8: aload_2
       9: invokespecial #159                // Method scala/Some."<init>":(Ljava/lang/Object;)V
      12: invokespecial #82                 // Method "<init>":(BIILscala/Option;)V
      15: return
}
