Compiled from "JavaStubCompilationUnit.java"
class org.codehaus.groovy.tools.javac.JavaStubCompilationUnit$2 extends org.codehaus.groovy.control.CompilationUnit$PrimaryClassNodeOperation {
  final org.codehaus.groovy.tools.javac.JavaStubCompilationUnit this$0;

  org.codehaus.groovy.tools.javac.JavaStubCompilationUnit$2(org.codehaus.groovy.tools.javac.JavaStubCompilationUnit);
    Code:
       0: aload_0
       1: aload_1
       2: putfield      #18                 // Field this$0:Lorg/codehaus/groovy/tools/javac/JavaStubCompilationUnit;
       5: aload_0
       6: invokespecial #21                 // Method org/codehaus/groovy/control/CompilationUnit$PrimaryClassNodeOperation."<init>":()V
       9: return

  public void call(org.codehaus.groovy.control.SourceUnit, org.codehaus.groovy.classgen.GeneratorContext, org.codehaus.groovy.ast.ClassNode) throws org.codehaus.groovy.control.CompilationFailedException;
    Code:
       0: aload_0
       1: getfield      #18                 // Field this$0:Lorg/codehaus/groovy/tools/javac/JavaStubCompilationUnit;
       4: invokestatic  #33                 // Method org/codehaus/groovy/tools/javac/JavaStubCompilationUnit.access$000:(Lorg/codehaus/groovy/tools/javac/JavaStubCompilationUnit;)Lorg/codehaus/groovy/tools/javac/JavaStubGenerator;
       7: aload_3
       8: invokevirtual #39                 // Method org/codehaus/groovy/tools/javac/JavaStubGenerator.generateClass:(Lorg/codehaus/groovy/ast/ClassNode;)V
      11: aload_0
      12: getfield      #18                 // Field this$0:Lorg/codehaus/groovy/tools/javac/JavaStubCompilationUnit;
      15: invokestatic  #43                 // Method org/codehaus/groovy/tools/javac/JavaStubCompilationUnit.access$108:(Lorg/codehaus/groovy/tools/javac/JavaStubCompilationUnit;)I
      18: pop
      19: goto          30
      22: astore        4
      24: aload_1
      25: aload         4
      27: invokevirtual #49                 // Method org/codehaus/groovy/control/SourceUnit.addException:(Ljava/lang/Exception;)V
      30: return
    Exception table:
       from    to  target type
           0    19    22   Class java/io/FileNotFoundException
}
