Compiled from "Page.java"
public class org.leo.aws.ddb.data.Page {
  private final int pageSize;

  private final org.leo.aws.ddb.data.PrimaryKey lastEndKey;

  private org.leo.aws.ddb.data.Page(int, org.leo.aws.ddb.data.PrimaryKey);
    Code:
       0: aload_0
       1: invokespecial #13                 // Method java/lang/Object."<init>":()V
       4: aload_0
       5: iload_1
       6: putfield      #16                 // Field pageSize:I
       9: aload_0
      10: aload_2
      11: putfield      #18                 // Field lastEndKey:Lorg/leo/aws/ddb/data/PrimaryKey;
      14: return

  public int getPageSize();
    Code:
       0: aload_0
       1: getfield      #16                 // Field pageSize:I
       4: ireturn

  public org.leo.aws.ddb.data.PrimaryKey getLastEndKey();
    Code:
       0: aload_0
       1: getfield      #18                 // Field lastEndKey:Lorg/leo/aws/ddb/data/PrimaryKey;
       4: areturn

  public static org.leo.aws.ddb.data.Page$Builder builder();
    Code:
       0: new           #30                 // class org/leo/aws/ddb/data/Page$BuilderImpl
       3: dup
       4: invokespecial #32                 // Method org/leo/aws/ddb/data/Page$BuilderImpl."<init>":()V
       7: areturn
}
