Compiled from "Scheduler.java"
public interface net.jodah.failsafe.util.concurrent.Scheduler {
  public static final net.jodah.failsafe.util.concurrent.Scheduler DEFAULT;

  public abstract java.util.concurrent.ScheduledFuture<?> schedule(java.util.concurrent.Callable<?>, long, java.util.concurrent.TimeUnit);

  public static net.jodah.failsafe.util.concurrent.Scheduler of(java.util.concurrent.ScheduledExecutorService);
    Code:
       0: aload_0
       1: ldc           #1                  // String executor
       3: invokestatic  #2                  // Method net/jodah/failsafe/internal/util/Assert.notNull:(Ljava/lang/Object;Ljava/lang/String;)Ljava/lang/Object;
       6: pop
       7: aload_0
       8: dup
       9: invokevirtual #3                  // Method java/lang/Object.getClass:()Ljava/lang/Class;
      12: pop
      13: invokedynamic #4,  0              // InvokeDynamic #0:schedule:(Ljava/util/concurrent/ScheduledExecutorService;)Lnet/jodah/failsafe/util/concurrent/Scheduler;
      18: areturn

  public static net.jodah.failsafe.util.concurrent.Scheduler of(java.util.concurrent.Executor);
    Code:
       0: aload_0
       1: ldc           #1                  // String executor
       3: invokestatic  #2                  // Method net/jodah/failsafe/internal/util/Assert.notNull:(Ljava/lang/Object;Ljava/lang/String;)Ljava/lang/Object;
       6: pop
       7: aload_0
       8: instanceof    #5                  // class java/util/concurrent/ExecutorService
      11: ifeq          21
      14: aload_0
      15: checkcast     #5                  // class java/util/concurrent/ExecutorService
      18: goto          29
      21: new           #6                  // class net/jodah/failsafe/internal/util/DelegatingExecutorService
      24: dup
      25: aload_0
      26: invokespecial #7                  // Method net/jodah/failsafe/internal/util/DelegatingExecutorService."<init>":(Ljava/util/concurrent/Executor;)V
      29: astore_1
      30: new           #8                  // class net/jodah/failsafe/internal/util/DelegatingScheduler
      33: dup
      34: aload_1
      35: invokespecial #9                  // Method net/jodah/failsafe/internal/util/DelegatingScheduler."<init>":(Ljava/util/concurrent/ExecutorService;)V
      38: areturn

  static {};
    Code:
       0: getstatic     #10                 // Field net/jodah/failsafe/internal/util/DelegatingScheduler.INSTANCE:Lnet/jodah/failsafe/internal/util/DelegatingScheduler;
       3: putstatic     #11                 // Field DEFAULT:Lnet/jodah/failsafe/util/concurrent/Scheduler;
       6: return
}
