Compiled from "ServletWebServerInitializedEvent.java"
public class org.springframework.boot.web.servlet.context.ServletWebServerInitializedEvent extends org.springframework.boot.web.context.WebServerInitializedEvent {
  private final org.springframework.boot.web.servlet.context.ServletWebServerApplicationContext applicationContext;

  public org.springframework.boot.web.servlet.context.ServletWebServerInitializedEvent(org.springframework.boot.web.server.WebServer, org.springframework.boot.web.servlet.context.ServletWebServerApplicationContext);
    Code:
       0: aload_0
       1: aload_1
       2: invokespecial #1                  // Method org/springframework/boot/web/context/WebServerInitializedEvent."<init>":(Lorg/springframework/boot/web/server/WebServer;)V
       5: aload_0
       6: aload_2
       7: putfield      #2                  // Field applicationContext:Lorg/springframework/boot/web/servlet/context/ServletWebServerApplicationContext;
      10: return

  public org.springframework.boot.web.servlet.context.ServletWebServerApplicationContext getApplicationContext();
    Code:
       0: aload_0
       1: getfield      #2                  // Field applicationContext:Lorg/springframework/boot/web/servlet/context/ServletWebServerApplicationContext;
       4: areturn

  public org.springframework.boot.web.context.WebServerApplicationContext getApplicationContext();
    Code:
       0: aload_0
       1: invokevirtual #3                  // Method getApplicationContext:()Lorg/springframework/boot/web/servlet/context/ServletWebServerApplicationContext;
       4: areturn
}
