Compiled from "ModuleMappingUtil.kt"
public final class kotlin.reflect.jvm.internal.impl.load.kotlin.ModuleMappingUtilKt {
  public static final kotlin.reflect.jvm.internal.impl.metadata.jvm.deserialization.ModuleMapping loadModuleMapping(kotlin.reflect.jvm.internal.impl.metadata.jvm.deserialization.ModuleMapping$Companion, byte[], java.lang.String, kotlin.reflect.jvm.internal.impl.serialization.deserialization.DeserializationConfiguration, kotlin.jvm.functions.Function1<? super kotlin.reflect.jvm.internal.impl.metadata.jvm.deserialization.JvmMetadataVersion, kotlin.Unit>);
    Code:
       0: aload_0
       1: ldc           #3                  // String receiver$0
       3: invokestatic  #10                 // Method kotlin/jvm/internal/Intrinsics.checkParameterIsNotNull:(Ljava/lang/Object;Ljava/lang/String;)V
       6: aload_2
       7: ldc           #2                  // String debugName
       9: invokestatic  #10                 // Method kotlin/jvm/internal/Intrinsics.checkParameterIsNotNull:(Ljava/lang/Object;Ljava/lang/String;)V
      12: aload_3
      13: ldc           #1                  // String configuration
      15: invokestatic  #10                 // Method kotlin/jvm/internal/Intrinsics.checkParameterIsNotNull:(Ljava/lang/Object;Ljava/lang/String;)V
      18: aload         4
      20: ldc           #4                  // String reportIncompatibleVersionError
      22: invokestatic  #10                 // Method kotlin/jvm/internal/Intrinsics.checkParameterIsNotNull:(Ljava/lang/Object;Ljava/lang/String;)V
      25: aload_0
      26: aload_1
      27: aload_2
      28: aload_3
      29: invokeinterface #12,  1           // InterfaceMethod kotlin/reflect/jvm/internal/impl/serialization/deserialization/DeserializationConfiguration.getSkipMetadataVersionCheck:()Z
      34: aload_3
      35: invokeinterface #13,  1           // InterfaceMethod kotlin/reflect/jvm/internal/impl/serialization/deserialization/DeserializationConfiguration.isJvmPackageNameSupported:()Z
      40: aload         4
      42: invokevirtual #11                 // Method kotlin/reflect/jvm/internal/impl/metadata/jvm/deserialization/ModuleMapping$Companion.loadModuleMapping:([BLjava/lang/String;ZZLkotlin/jvm/functions/Function1;)Lkotlin/reflect/jvm/internal/impl/metadata/jvm/deserialization/ModuleMapping;
      45: areturn
}
