Compiled from "MediaType.java"
public class org.apache.tomcat.util.http.parser.MediaType {
  private final java.lang.String type;

  private final java.lang.String subtype;

  private final java.util.LinkedHashMap<java.lang.String, java.lang.String> parameters;

  private final java.lang.String charset;

  private volatile java.lang.String noCharset;

  private volatile java.lang.String withCharset;

  protected org.apache.tomcat.util.http.parser.MediaType(java.lang.String, java.lang.String, java.util.LinkedHashMap<java.lang.String, java.lang.String>);
    Code:
       0: aload_0
       1: invokespecial #1                  // Method java/lang/Object."<init>":()V
       4: aload_0
       5: aload_1
       6: putfield      #2                  // Field type:Ljava/lang/String;
       9: aload_0
      10: aload_2
      11: putfield      #3                  // Field subtype:Ljava/lang/String;
      14: aload_0
      15: aload_3
      16: putfield      #4                  // Field parameters:Ljava/util/LinkedHashMap;
      19: aload_3
      20: ldc           #5                  // String charset
      22: invokevirtual #6                  // Method java/util/LinkedHashMap.get:(Ljava/lang/Object;)Ljava/lang/Object;
      25: checkcast     #7                  // class java/lang/String
      28: astore        4
      30: aload         4
      32: ifnull        61
      35: aload         4
      37: invokevirtual #8                  // Method java/lang/String.length:()I
      40: ifle          61
      43: aload         4
      45: iconst_0
      46: invokevirtual #9                  // Method java/lang/String.charAt:(I)C
      49: bipush        34
      51: if_icmpne     61
      54: aload         4
      56: invokestatic  #10                 // Method org/apache/tomcat/util/http/parser/HttpParser.unquote:(Ljava/lang/String;)Ljava/lang/String;
      59: astore        4
      61: aload_0
      62: aload         4
      64: putfield      #11                 // Field charset:Ljava/lang/String;
      67: return

  public java.lang.String getType();
    Code:
       0: aload_0
       1: getfield      #2                  // Field type:Ljava/lang/String;
       4: areturn

  public java.lang.String getSubtype();
    Code:
       0: aload_0
       1: getfield      #3                  // Field subtype:Ljava/lang/String;
       4: areturn

  public java.lang.String getCharset();
    Code:
       0: aload_0
       1: getfield      #11                 // Field charset:Ljava/lang/String;
       4: areturn

  public int getParameterCount();
    Code:
       0: aload_0
       1: getfield      #4                  // Field parameters:Ljava/util/LinkedHashMap;
       4: invokevirtual #12                 // Method java/util/LinkedHashMap.size:()I
       7: ireturn

  public java.lang.String getParameterValue(java.lang.String);
    Code:
       0: aload_0
       1: getfield      #4                  // Field parameters:Ljava/util/LinkedHashMap;
       4: aload_1
       5: getstatic     #13                 // Field java/util/Locale.ENGLISH:Ljava/util/Locale;
       8: invokevirtual #14                 // Method java/lang/String.toLowerCase:(Ljava/util/Locale;)Ljava/lang/String;
      11: invokevirtual #6                  // Method java/util/LinkedHashMap.get:(Ljava/lang/Object;)Ljava/lang/Object;
      14: checkcast     #7                  // class java/lang/String
      17: areturn

  public java.lang.String toString();
    Code:
       0: aload_0
       1: getfield      #15                 // Field withCharset:Ljava/lang/String;
       4: ifnonnull     178
       7: aload_0
       8: dup
       9: astore_1
      10: monitorenter
      11: aload_0
      12: getfield      #15                 // Field withCharset:Ljava/lang/String;
      15: ifnonnull     166
      18: new           #16                 // class java/lang/StringBuilder
      21: dup
      22: invokespecial #17                 // Method java/lang/StringBuilder."<init>":()V
      25: astore_2
      26: aload_2
      27: aload_0
      28: getfield      #2                  // Field type:Ljava/lang/String;
      31: invokevirtual #18                 // Method java/lang/StringBuilder.append:(Ljava/lang/String;)Ljava/lang/StringBuilder;
      34: pop
      35: aload_2
      36: bipush        47
      38: invokevirtual #19                 // Method java/lang/StringBuilder.append:(C)Ljava/lang/StringBuilder;
      41: pop
      42: aload_2
      43: aload_0
      44: getfield      #3                  // Field subtype:Ljava/lang/String;
      47: invokevirtual #18                 // Method java/lang/StringBuilder.append:(Ljava/lang/String;)Ljava/lang/StringBuilder;
      50: pop
      51: aload_0
      52: getfield      #4                  // Field parameters:Ljava/util/LinkedHashMap;
      55: invokevirtual #20                 // Method java/util/LinkedHashMap.entrySet:()Ljava/util/Set;
      58: invokeinterface #21,  1           // InterfaceMethod java/util/Set.iterator:()Ljava/util/Iterator;
      63: astore_3
      64: aload_3
      65: invokeinterface #22,  1           // InterfaceMethod java/util/Iterator.hasNext:()Z
      70: ifeq          158
      73: aload_3
      74: invokeinterface #23,  1           // InterfaceMethod java/util/Iterator.next:()Ljava/lang/Object;
      79: checkcast     #24                 // class java/util/Map$Entry
      82: astore        4
      84: aload         4
      86: invokeinterface #25,  1           // InterfaceMethod java/util/Map$Entry.getValue:()Ljava/lang/Object;
      91: checkcast     #7                  // class java/lang/String
      94: astore        5
      96: aload         5
      98: ifnull        64
     101: aload         5
     103: invokevirtual #8                  // Method java/lang/String.length:()I
     106: ifne          112
     109: goto          64
     112: aload_2
     113: bipush        59
     115: invokevirtual #19                 // Method java/lang/StringBuilder.append:(C)Ljava/lang/StringBuilder;
     118: pop
     119: aload_2
     120: bipush        32
     122: invokevirtual #19                 // Method java/lang/StringBuilder.append:(C)Ljava/lang/StringBuilder;
     125: pop
     126: aload_2
     127: aload         4
     129: invokeinterface #26,  1           // InterfaceMethod java/util/Map$Entry.getKey:()Ljava/lang/Object;
     134: checkcast     #7                  // class java/lang/String
     137: invokevirtual #18                 // Method java/lang/StringBuilder.append:(Ljava/lang/String;)Ljava/lang/StringBuilder;
     140: pop
     141: aload_2
     142: bipush        61
     144: invokevirtual #19                 // Method java/lang/StringBuilder.append:(C)Ljava/lang/StringBuilder;
     147: pop
     148: aload_2
     149: aload         5
     151: invokevirtual #18                 // Method java/lang/StringBuilder.append:(Ljava/lang/String;)Ljava/lang/StringBuilder;
     154: pop
     155: goto          64
     158: aload_0
     159: aload_2
     160: invokevirtual #27                 // Method java/lang/StringBuilder.toString:()Ljava/lang/String;
     163: putfield      #15                 // Field withCharset:Ljava/lang/String;
     166: aload_1
     167: monitorexit
     168: goto          178
     171: astore        6
     173: aload_1
     174: monitorexit
     175: aload         6
     177: athrow
     178: aload_0
     179: getfield      #15                 // Field withCharset:Ljava/lang/String;
     182: areturn
    Exception table:
       from    to  target type
          11   168   171   any
         171   175   171   any

  public java.lang.String toStringNoCharset();
    Code:
       0: aload_0
       1: getfield      #28                 // Field noCharset:Ljava/lang/String;
       4: ifnonnull     179
       7: aload_0
       8: dup
       9: astore_1
      10: monitorenter
      11: aload_0
      12: getfield      #28                 // Field noCharset:Ljava/lang/String;
      15: ifnonnull     167
      18: new           #16                 // class java/lang/StringBuilder
      21: dup
      22: invokespecial #17                 // Method java/lang/StringBuilder."<init>":()V
      25: astore_2
      26: aload_2
      27: aload_0
      28: getfield      #2                  // Field type:Ljava/lang/String;
      31: invokevirtual #18                 // Method java/lang/StringBuilder.append:(Ljava/lang/String;)Ljava/lang/StringBuilder;
      34: pop
      35: aload_2
      36: bipush        47
      38: invokevirtual #19                 // Method java/lang/StringBuilder.append:(C)Ljava/lang/StringBuilder;
      41: pop
      42: aload_2
      43: aload_0
      44: getfield      #3                  // Field subtype:Ljava/lang/String;
      47: invokevirtual #18                 // Method java/lang/StringBuilder.append:(Ljava/lang/String;)Ljava/lang/StringBuilder;
      50: pop
      51: aload_0
      52: getfield      #4                  // Field parameters:Ljava/util/LinkedHashMap;
      55: invokevirtual #20                 // Method java/util/LinkedHashMap.entrySet:()Ljava/util/Set;
      58: invokeinterface #21,  1           // InterfaceMethod java/util/Set.iterator:()Ljava/util/Iterator;
      63: astore_3
      64: aload_3
      65: invokeinterface #22,  1           // InterfaceMethod java/util/Iterator.hasNext:()Z
      70: ifeq          159
      73: aload_3
      74: invokeinterface #23,  1           // InterfaceMethod java/util/Iterator.next:()Ljava/lang/Object;
      79: checkcast     #24                 // class java/util/Map$Entry
      82: astore        4
      84: aload         4
      86: invokeinterface #26,  1           // InterfaceMethod java/util/Map$Entry.getKey:()Ljava/lang/Object;
      91: checkcast     #7                  // class java/lang/String
      94: ldc           #5                  // String charset
      96: invokevirtual #29                 // Method java/lang/String.equalsIgnoreCase:(Ljava/lang/String;)Z
      99: ifeq          105
     102: goto          64
     105: aload_2
     106: bipush        59
     108: invokevirtual #19                 // Method java/lang/StringBuilder.append:(C)Ljava/lang/StringBuilder;
     111: pop
     112: aload_2
     113: bipush        32
     115: invokevirtual #19                 // Method java/lang/StringBuilder.append:(C)Ljava/lang/StringBuilder;
     118: pop
     119: aload_2
     120: aload         4
     122: invokeinterface #26,  1           // InterfaceMethod java/util/Map$Entry.getKey:()Ljava/lang/Object;
     127: checkcast     #7                  // class java/lang/String
     130: invokevirtual #18                 // Method java/lang/StringBuilder.append:(Ljava/lang/String;)Ljava/lang/StringBuilder;
     133: pop
     134: aload_2
     135: bipush        61
     137: invokevirtual #19                 // Method java/lang/StringBuilder.append:(C)Ljava/lang/StringBuilder;
     140: pop
     141: aload_2
     142: aload         4
     144: invokeinterface #25,  1           // InterfaceMethod java/util/Map$Entry.getValue:()Ljava/lang/Object;
     149: checkcast     #7                  // class java/lang/String
     152: invokevirtual #18                 // Method java/lang/StringBuilder.append:(Ljava/lang/String;)Ljava/lang/StringBuilder;
     155: pop
     156: goto          64
     159: aload_0
     160: aload_2
     161: invokevirtual #27                 // Method java/lang/StringBuilder.toString:()Ljava/lang/String;
     164: putfield      #28                 // Field noCharset:Ljava/lang/String;
     167: aload_1
     168: monitorexit
     169: goto          179
     172: astore        5
     174: aload_1
     175: monitorexit
     176: aload         5
     178: athrow
     179: aload_0
     180: getfield      #28                 // Field noCharset:Ljava/lang/String;
     183: areturn
    Exception table:
       from    to  target type
          11   169   172   any
         172   176   172   any

  public static org.apache.tomcat.util.http.parser.MediaType parseMediaType(java.io.StringReader) throws java.io.IOException;
    Code:
       0: aload_0
       1: invokestatic  #30                 // Method org/apache/tomcat/util/http/parser/HttpParser.readToken:(Ljava/io/Reader;)Ljava/lang/String;
       4: astore_1
       5: aload_1
       6: ifnull        16
       9: aload_1
      10: invokevirtual #8                  // Method java/lang/String.length:()I
      13: ifne          18
      16: aconst_null
      17: areturn
      18: aload_0
      19: ldc           #31                 // String /
      21: invokestatic  #32                 // Method org/apache/tomcat/util/http/parser/HttpParser.skipConstant:(Ljava/io/Reader;Ljava/lang/String;)Lorg/apache/tomcat/util/http/parser/SkipResult;
      24: getstatic     #33                 // Field org/apache/tomcat/util/http/parser/SkipResult.NOT_FOUND:Lorg/apache/tomcat/util/http/parser/SkipResult;
      27: if_acmpne     32
      30: aconst_null
      31: areturn
      32: aload_0
      33: invokestatic  #30                 // Method org/apache/tomcat/util/http/parser/HttpParser.readToken:(Ljava/io/Reader;)Ljava/lang/String;
      36: astore_2
      37: aload_2
      38: ifnull        48
      41: aload_2
      42: invokevirtual #8                  // Method java/lang/String.length:()I
      45: ifne          50
      48: aconst_null
      49: areturn
      50: new           #34                 // class java/util/LinkedHashMap
      53: dup
      54: invokespecial #35                 // Method java/util/LinkedHashMap."<init>":()V
      57: astore_3
      58: aload_0
      59: ldc           #36                 // String ;
      61: invokestatic  #32                 // Method org/apache/tomcat/util/http/parser/HttpParser.skipConstant:(Ljava/io/Reader;Ljava/lang/String;)Lorg/apache/tomcat/util/http/parser/SkipResult;
      64: astore        4
      66: aload         4
      68: getstatic     #33                 // Field org/apache/tomcat/util/http/parser/SkipResult.NOT_FOUND:Lorg/apache/tomcat/util/http/parser/SkipResult;
      71: if_acmpne     76
      74: aconst_null
      75: areturn
      76: aload         4
      78: getstatic     #37                 // Field org/apache/tomcat/util/http/parser/SkipResult.FOUND:Lorg/apache/tomcat/util/http/parser/SkipResult;
      81: if_acmpne     154
      84: aload_0
      85: invokestatic  #30                 // Method org/apache/tomcat/util/http/parser/HttpParser.readToken:(Ljava/io/Reader;)Ljava/lang/String;
      88: astore        5
      90: ldc           #38                 // String
      92: astore        6
      94: aload_0
      95: ldc           #39                 // String =
      97: invokestatic  #32                 // Method org/apache/tomcat/util/http/parser/HttpParser.skipConstant:(Ljava/io/Reader;Ljava/lang/String;)Lorg/apache/tomcat/util/http/parser/SkipResult;
     100: getstatic     #37                 // Field org/apache/tomcat/util/http/parser/SkipResult.FOUND:Lorg/apache/tomcat/util/http/parser/SkipResult;
     103: if_acmpne     113
     106: aload_0
     107: iconst_1
     108: invokestatic  #40                 // Method org/apache/tomcat/util/http/parser/HttpParser.readTokenOrQuotedString:(Ljava/io/Reader;Z)Ljava/lang/String;
     111: astore        6
     113: aload         5
     115: ifnull        133
     118: aload_3
     119: aload         5
     121: getstatic     #13                 // Field java/util/Locale.ENGLISH:Ljava/util/Locale;
     124: invokevirtual #14                 // Method java/lang/String.toLowerCase:(Ljava/util/Locale;)Ljava/lang/String;
     127: aload         6
     129: invokevirtual #41                 // Method java/util/LinkedHashMap.put:(Ljava/lang/Object;Ljava/lang/Object;)Ljava/lang/Object;
     132: pop
     133: aload_0
     134: ldc           #36                 // String ;
     136: invokestatic  #32                 // Method org/apache/tomcat/util/http/parser/HttpParser.skipConstant:(Ljava/io/Reader;Ljava/lang/String;)Lorg/apache/tomcat/util/http/parser/SkipResult;
     139: astore        4
     141: aload         4
     143: getstatic     #33                 // Field org/apache/tomcat/util/http/parser/SkipResult.NOT_FOUND:Lorg/apache/tomcat/util/http/parser/SkipResult;
     146: if_acmpne     151
     149: aconst_null
     150: areturn
     151: goto          76
     154: new           #42                 // class org/apache/tomcat/util/http/parser/MediaType
     157: dup
     158: aload_1
     159: aload_2
     160: aload_3
     161: invokespecial #43                 // Method "<init>":(Ljava/lang/String;Ljava/lang/String;Ljava/util/LinkedHashMap;)V
     164: areturn
}
