Compiled from "MethodFluentImpl.java"
public class io.sundr.codegen.model.MethodFluentImpl$WildcardRefReturnTypeNestedImpl<N> extends io.sundr.codegen.model.WildcardRefFluentImpl<io.sundr.codegen.model.MethodFluent$WildcardRefReturnTypeNested<N>> implements io.sundr.codegen.model.MethodFluent$WildcardRefReturnTypeNested<N>, io.sundr.builder.Nested<N> {
  private final io.sundr.codegen.model.WildcardRefBuilder builder;

  final io.sundr.codegen.model.MethodFluentImpl this$0;

  io.sundr.codegen.model.MethodFluentImpl$WildcardRefReturnTypeNestedImpl(io.sundr.codegen.model.MethodFluentImpl, io.sundr.codegen.model.WildcardRef);
    Code:
       0: aload_0
       1: aload_1
       2: putfield      #1                  // Field this$0:Lio/sundr/codegen/model/MethodFluentImpl;
       5: aload_0
       6: invokespecial #2                  // Method io/sundr/codegen/model/WildcardRefFluentImpl."<init>":()V
       9: aload_0
      10: new           #3                  // class io/sundr/codegen/model/WildcardRefBuilder
      13: dup
      14: aload_0
      15: aload_2
      16: invokespecial #4                  // Method io/sundr/codegen/model/WildcardRefBuilder."<init>":(Lio/sundr/codegen/model/WildcardRefFluent;Lio/sundr/codegen/model/WildcardRef;)V
      19: putfield      #5                  // Field builder:Lio/sundr/codegen/model/WildcardRefBuilder;
      22: return

  io.sundr.codegen.model.MethodFluentImpl$WildcardRefReturnTypeNestedImpl(io.sundr.codegen.model.MethodFluentImpl);
    Code:
       0: aload_0
       1: aload_1
       2: putfield      #1                  // Field this$0:Lio/sundr/codegen/model/MethodFluentImpl;
       5: aload_0
       6: invokespecial #2                  // Method io/sundr/codegen/model/WildcardRefFluentImpl."<init>":()V
       9: aload_0
      10: new           #3                  // class io/sundr/codegen/model/WildcardRefBuilder
      13: dup
      14: aload_0
      15: invokespecial #6                  // Method io/sundr/codegen/model/WildcardRefBuilder."<init>":(Lio/sundr/codegen/model/WildcardRefFluent;)V
      18: putfield      #5                  // Field builder:Lio/sundr/codegen/model/WildcardRefBuilder;
      21: return

  public N and();
    Code:
       0: aload_0
       1: getfield      #1                  // Field this$0:Lio/sundr/codegen/model/MethodFluentImpl;
       4: aload_0
       5: getfield      #5                  // Field builder:Lio/sundr/codegen/model/WildcardRefBuilder;
       8: invokevirtual #7                  // Method io/sundr/codegen/model/WildcardRefBuilder.build:()Lio/sundr/codegen/model/EditableWildcardRef;
      11: invokevirtual #8                  // Method io/sundr/codegen/model/MethodFluentImpl.withWildcardRefReturnType:(Lio/sundr/codegen/model/WildcardRef;)Lio/sundr/codegen/model/MethodFluent;
      14: areturn

  public N endWildcardRefReturnType();
    Code:
       0: aload_0
       1: invokevirtual #9                  // Method and:()Ljava/lang/Object;
       4: areturn
}
