Compiled from "VoidRef.java"
public class io.sundr.codegen.model.VoidRef extends io.sundr.codegen.model.TypeRef {
  public io.sundr.codegen.model.VoidRef();
    Code:
       0: aload_0
       1: invokestatic  #1                  // Method java/util/Collections.emptyMap:()Ljava/util/Map;
       4: invokespecial #2                  // Method "<init>":(Ljava/util/Map;)V
       7: return

  public io.sundr.codegen.model.VoidRef(java.util.Map<io.sundr.codegen.model.AttributeKey, java.lang.Object>);
    Code:
       0: aload_0
       1: aload_1
       2: invokespecial #3                  // Method io/sundr/codegen/model/TypeRef."<init>":(Ljava/util/Map;)V
       5: return

  public int getDimensions();
    Code:
       0: iconst_0
       1: ireturn

  public io.sundr.codegen.model.TypeRef withDimensions(int);
    Code:
       0: new           #4                  // class java/lang/UnsupportedOperationException
       3: dup
       4: invokespecial #5                  // Method java/lang/UnsupportedOperationException."<init>":()V
       7: athrow

  public java.lang.String toString();
    Code:
       0: ldc           #6                  // String void
       2: areturn

  public boolean isAssignableFrom(io.sundr.codegen.model.TypeRef);
    Code:
       0: iconst_0
       1: ireturn
}
