Compiled from "Iterators.java"
public class hudson.util.Iterators {
  public hudson.util.Iterators();
    Code:
       0: aload_0
       1: invokespecial #1                  // Method java/lang/Object."<init>":()V
       4: return

  public static <T> java.util.Iterator<T> empty();
    Code:
       0: invokestatic  #2                  // Method java/util/Collections.emptyList:()Ljava/util/List;
       3: invokeinterface #3,  1            // InterfaceMethod java/util/List.iterator:()Ljava/util/Iterator;
       8: areturn

  public static <T> java.lang.Iterable<T> reverse(java.util.List<T>);
    Code:
       0: new           #4                  // class hudson/util/Iterators$1
       3: dup
       4: aload_0
       5: invokespecial #5                  // Method hudson/util/Iterators$1."<init>":(Ljava/util/List;)V
       8: areturn

  public static java.util.List<java.lang.Integer> sequence(int, int, int);
    Code:
       0: iload_1
       1: iload_0
       2: isub
       3: iload_2
       4: idiv
       5: istore_3
       6: iload_3
       7: ifge          20
      10: new           #6                  // class java/lang/IllegalArgumentException
      13: dup
      14: ldc           #7                  // String List size is negative
      16: invokespecial #8                  // Method java/lang/IllegalArgumentException."<init>":(Ljava/lang/String;)V
      19: athrow
      20: new           #9                  // class hudson/util/Iterators$2
      23: dup
      24: iload_3
      25: iload_0
      26: iload_2
      27: invokespecial #10                 // Method hudson/util/Iterators$2."<init>":(III)V
      30: areturn

  public static java.util.List<java.lang.Integer> sequence(int, int);
    Code:
       0: iload_0
       1: iload_1
       2: iconst_1
       3: invokestatic  #11                 // Method sequence:(III)Ljava/util/List;
       6: areturn

  public static java.util.List<java.lang.Integer> reverseSequence(int, int, int);
    Code:
       0: iload_1
       1: iconst_1
       2: isub
       3: iload_0
       4: iconst_1
       5: isub
       6: iload_2
       7: ineg
       8: invokestatic  #11                 // Method sequence:(III)Ljava/util/List;
      11: areturn

  public static java.util.List<java.lang.Integer> reverseSequence(int, int);
    Code:
       0: iload_0
       1: iload_1
       2: iconst_1
       3: invokestatic  #12                 // Method reverseSequence:(III)Ljava/util/List;
       6: areturn
}
