Compiled from "MultipartFormDataParser.java"
public class hudson.util.MultipartFormDataParser {
  private final org.apache.commons.fileupload.servlet.ServletFileUpload upload;

  private final java.util.Map<java.lang.String, org.apache.commons.fileupload.FileItem> byName;

  public hudson.util.MultipartFormDataParser(javax.servlet.http.HttpServletRequest) throws javax.servlet.ServletException;
    Code:
       0: aload_0
       1: invokespecial #1                  // Method java/lang/Object."<init>":()V
       4: aload_0
       5: new           #2                  // class org/apache/commons/fileupload/servlet/ServletFileUpload
       8: dup
       9: new           #3                  // class org/apache/commons/fileupload/disk/DiskFileItemFactory
      12: dup
      13: invokespecial #4                  // Method org/apache/commons/fileupload/disk/DiskFileItemFactory."<init>":()V
      16: invokespecial #5                  // Method org/apache/commons/fileupload/servlet/ServletFileUpload."<init>":(Lorg/apache/commons/fileupload/FileItemFactory;)V
      19: putfield      #6                  // Field upload:Lorg/apache/commons/fileupload/servlet/ServletFileUpload;
      22: aload_0
      23: new           #7                  // class java/util/HashMap
      26: dup
      27: invokespecial #8                  // Method java/util/HashMap."<init>":()V
      30: putfield      #9                  // Field byName:Ljava/util/Map;
      33: aload_0
      34: getfield      #6                  // Field upload:Lorg/apache/commons/fileupload/servlet/ServletFileUpload;
      37: aload_1
      38: invokevirtual #10                 // Method org/apache/commons/fileupload/servlet/ServletFileUpload.parseRequest:(Ljavax/servlet/http/HttpServletRequest;)Ljava/util/List;
      41: invokeinterface #11,  1           // InterfaceMethod java/util/List.iterator:()Ljava/util/Iterator;
      46: astore_2
      47: aload_2
      48: invokeinterface #12,  1           // InterfaceMethod java/util/Iterator.hasNext:()Z
      53: ifeq          86
      56: aload_2
      57: invokeinterface #13,  1           // InterfaceMethod java/util/Iterator.next:()Ljava/lang/Object;
      62: checkcast     #14                 // class org/apache/commons/fileupload/FileItem
      65: astore_3
      66: aload_0
      67: getfield      #9                  // Field byName:Ljava/util/Map;
      70: aload_3
      71: invokeinterface #15,  1           // InterfaceMethod org/apache/commons/fileupload/FileItem.getFieldName:()Ljava/lang/String;
      76: aload_3
      77: invokeinterface #16,  3           // InterfaceMethod java/util/Map.put:(Ljava/lang/Object;Ljava/lang/Object;)Ljava/lang/Object;
      82: pop
      83: goto          47
      86: goto          99
      89: astore_2
      90: new           #18                 // class javax/servlet/ServletException
      93: dup
      94: aload_2
      95: invokespecial #19                 // Method javax/servlet/ServletException."<init>":(Ljava/lang/Throwable;)V
      98: athrow
      99: return
    Exception table:
       from    to  target type
          33    86    89   Class org/apache/commons/fileupload/FileUploadException

  public java.lang.String get(java.lang.String);
    Code:
       0: aload_0
       1: getfield      #9                  // Field byName:Ljava/util/Map;
       4: aload_1
       5: invokeinterface #20,  2           // InterfaceMethod java/util/Map.get:(Ljava/lang/Object;)Ljava/lang/Object;
      10: checkcast     #14                 // class org/apache/commons/fileupload/FileItem
      13: astore_2
      14: aload_2
      15: ifnonnull     20
      18: aconst_null
      19: areturn
      20: aload_2
      21: invokeinterface #21,  1           // InterfaceMethod org/apache/commons/fileupload/FileItem.getString:()Ljava/lang/String;
      26: areturn

  public org.apache.commons.fileupload.FileItem getFileItem(java.lang.String);
    Code:
       0: aload_0
       1: getfield      #9                  // Field byName:Ljava/util/Map;
       4: aload_1
       5: invokeinterface #20,  2           // InterfaceMethod java/util/Map.get:(Ljava/lang/Object;)Ljava/lang/Object;
      10: checkcast     #14                 // class org/apache/commons/fileupload/FileItem
      13: areturn

  public void cleanUp();
    Code:
       0: aload_0
       1: getfield      #9                  // Field byName:Ljava/util/Map;
       4: invokeinterface #22,  1           // InterfaceMethod java/util/Map.values:()Ljava/util/Collection;
       9: invokeinterface #23,  1           // InterfaceMethod java/util/Collection.iterator:()Ljava/util/Iterator;
      14: astore_1
      15: aload_1
      16: invokeinterface #12,  1           // InterfaceMethod java/util/Iterator.hasNext:()Z
      21: ifeq          43
      24: aload_1
      25: invokeinterface #13,  1           // InterfaceMethod java/util/Iterator.next:()Ljava/lang/Object;
      30: checkcast     #14                 // class org/apache/commons/fileupload/FileItem
      33: astore_2
      34: aload_2
      35: invokeinterface #24,  1           // InterfaceMethod org/apache/commons/fileupload/FileItem.delete:()V
      40: goto          15
      43: return
}
