Compiled from "RejectedExecutionHandlerPolicy.java"
final class top.dcenter.ums.security.common.executor.RejectedExecutionHandlerPolicy$4 extends top.dcenter.ums.security.common.executor.RejectedExecutionHandlerPolicy {
  top.dcenter.ums.security.common.executor.RejectedExecutionHandlerPolicy$4(java.lang.String, int);
    Code:
       0: aload_0
       1: aload_1
       2: iload_2
       3: aconst_null
       4: invokespecial #1                  // Method top/dcenter/ums/security/common/executor/RejectedExecutionHandlerPolicy."<init>":(Ljava/lang/String;ILtop/dcenter/ums/security/common/executor/RejectedExecutionHandlerPolicy$1;)V
       7: return

  public java.util.concurrent.RejectedExecutionHandler getRejectedHandler();
    Code:
       0: new           #2                  // class java/util/concurrent/ThreadPoolExecutor$DiscardPolicy
       3: dup
       4: invokespecial #3                  // Method java/util/concurrent/ThreadPoolExecutor$DiscardPolicy."<init>":()V
       7: areturn
}
