Compiled from "Segment.java"
public class org.apache.commons.compress.harmony.pack200.Segment$SegmentAnnotationVisitor implements org.objectweb.asm.AnnotationVisitor {
  private int context;

  private int parameter;

  private java.lang.String desc;

  private boolean visible;

  private final java.util.List nameRU;

  private final java.util.List T;

  private final java.util.List values;

  private final java.util.List caseArrayN;

  private final java.util.List nestTypeRS;

  private final java.util.List nestNameRU;

  private final java.util.List nestPairN;

  final org.apache.commons.compress.harmony.pack200.Segment this$0;

  public org.apache.commons.compress.harmony.pack200.Segment$SegmentAnnotationVisitor(org.apache.commons.compress.harmony.pack200.Segment, int, java.lang.String, boolean);
    Code:
       0: aload_0
       1: aload_1
       2: putfield      #5                  // Field this$0:Lorg/apache/commons/compress/harmony/pack200/Segment;
       5: aload_0
       6: invokespecial #6                  // Method java/lang/Object."<init>":()V
       9: aload_0
      10: iconst_m1
      11: putfield      #7                  // Field context:I
      14: aload_0
      15: iconst_m1
      16: putfield      #8                  // Field parameter:I
      19: aload_0
      20: new           #9                  // class java/util/ArrayList
      23: dup
      24: invokespecial #10                 // Method java/util/ArrayList."<init>":()V
      27: putfield      #11                 // Field nameRU:Ljava/util/List;
      30: aload_0
      31: new           #9                  // class java/util/ArrayList
      34: dup
      35: invokespecial #10                 // Method java/util/ArrayList."<init>":()V
      38: putfield      #2                  // Field T:Ljava/util/List;
      41: aload_0
      42: new           #9                  // class java/util/ArrayList
      45: dup
      46: invokespecial #10                 // Method java/util/ArrayList."<init>":()V
      49: putfield      #1                  // Field values:Ljava/util/List;
      52: aload_0
      53: new           #9                  // class java/util/ArrayList
      56: dup
      57: invokespecial #10                 // Method java/util/ArrayList."<init>":()V
      60: putfield      #12                 // Field caseArrayN:Ljava/util/List;
      63: aload_0
      64: new           #9                  // class java/util/ArrayList
      67: dup
      68: invokespecial #10                 // Method java/util/ArrayList."<init>":()V
      71: putfield      #13                 // Field nestTypeRS:Ljava/util/List;
      74: aload_0
      75: new           #9                  // class java/util/ArrayList
      78: dup
      79: invokespecial #10                 // Method java/util/ArrayList."<init>":()V
      82: putfield      #3                  // Field nestNameRU:Ljava/util/List;
      85: aload_0
      86: new           #9                  // class java/util/ArrayList
      89: dup
      90: invokespecial #10                 // Method java/util/ArrayList."<init>":()V
      93: putfield      #4                  // Field nestPairN:Ljava/util/List;
      96: aload_0
      97: iload_2
      98: putfield      #7                  // Field context:I
     101: aload_0
     102: aload_3
     103: putfield      #14                 // Field desc:Ljava/lang/String;
     106: aload_0
     107: iload         4
     109: putfield      #15                 // Field visible:Z
     112: return

  public org.apache.commons.compress.harmony.pack200.Segment$SegmentAnnotationVisitor(org.apache.commons.compress.harmony.pack200.Segment, int);
    Code:
       0: aload_0
       1: aload_1
       2: putfield      #5                  // Field this$0:Lorg/apache/commons/compress/harmony/pack200/Segment;
       5: aload_0
       6: invokespecial #6                  // Method java/lang/Object."<init>":()V
       9: aload_0
      10: iconst_m1
      11: putfield      #7                  // Field context:I
      14: aload_0
      15: iconst_m1
      16: putfield      #8                  // Field parameter:I
      19: aload_0
      20: new           #9                  // class java/util/ArrayList
      23: dup
      24: invokespecial #10                 // Method java/util/ArrayList."<init>":()V
      27: putfield      #11                 // Field nameRU:Ljava/util/List;
      30: aload_0
      31: new           #9                  // class java/util/ArrayList
      34: dup
      35: invokespecial #10                 // Method java/util/ArrayList."<init>":()V
      38: putfield      #2                  // Field T:Ljava/util/List;
      41: aload_0
      42: new           #9                  // class java/util/ArrayList
      45: dup
      46: invokespecial #10                 // Method java/util/ArrayList."<init>":()V
      49: putfield      #1                  // Field values:Ljava/util/List;
      52: aload_0
      53: new           #9                  // class java/util/ArrayList
      56: dup
      57: invokespecial #10                 // Method java/util/ArrayList."<init>":()V
      60: putfield      #12                 // Field caseArrayN:Ljava/util/List;
      63: aload_0
      64: new           #9                  // class java/util/ArrayList
      67: dup
      68: invokespecial #10                 // Method java/util/ArrayList."<init>":()V
      71: putfield      #13                 // Field nestTypeRS:Ljava/util/List;
      74: aload_0
      75: new           #9                  // class java/util/ArrayList
      78: dup
      79: invokespecial #10                 // Method java/util/ArrayList."<init>":()V
      82: putfield      #3                  // Field nestNameRU:Ljava/util/List;
      85: aload_0
      86: new           #9                  // class java/util/ArrayList
      89: dup
      90: invokespecial #10                 // Method java/util/ArrayList."<init>":()V
      93: putfield      #4                  // Field nestPairN:Ljava/util/List;
      96: aload_0
      97: iload_2
      98: putfield      #7                  // Field context:I
     101: return

  public org.apache.commons.compress.harmony.pack200.Segment$SegmentAnnotationVisitor(org.apache.commons.compress.harmony.pack200.Segment, int, int, java.lang.String, boolean);
    Code:
       0: aload_0
       1: aload_1
       2: putfield      #5                  // Field this$0:Lorg/apache/commons/compress/harmony/pack200/Segment;
       5: aload_0
       6: invokespecial #6                  // Method java/lang/Object."<init>":()V
       9: aload_0
      10: iconst_m1
      11: putfield      #7                  // Field context:I
      14: aload_0
      15: iconst_m1
      16: putfield      #8                  // Field parameter:I
      19: aload_0
      20: new           #9                  // class java/util/ArrayList
      23: dup
      24: invokespecial #10                 // Method java/util/ArrayList."<init>":()V
      27: putfield      #11                 // Field nameRU:Ljava/util/List;
      30: aload_0
      31: new           #9                  // class java/util/ArrayList
      34: dup
      35: invokespecial #10                 // Method java/util/ArrayList."<init>":()V
      38: putfield      #2                  // Field T:Ljava/util/List;
      41: aload_0
      42: new           #9                  // class java/util/ArrayList
      45: dup
      46: invokespecial #10                 // Method java/util/ArrayList."<init>":()V
      49: putfield      #1                  // Field values:Ljava/util/List;
      52: aload_0
      53: new           #9                  // class java/util/ArrayList
      56: dup
      57: invokespecial #10                 // Method java/util/ArrayList."<init>":()V
      60: putfield      #12                 // Field caseArrayN:Ljava/util/List;
      63: aload_0
      64: new           #9                  // class java/util/ArrayList
      67: dup
      68: invokespecial #10                 // Method java/util/ArrayList."<init>":()V
      71: putfield      #13                 // Field nestTypeRS:Ljava/util/List;
      74: aload_0
      75: new           #9                  // class java/util/ArrayList
      78: dup
      79: invokespecial #10                 // Method java/util/ArrayList."<init>":()V
      82: putfield      #3                  // Field nestNameRU:Ljava/util/List;
      85: aload_0
      86: new           #9                  // class java/util/ArrayList
      89: dup
      90: invokespecial #10                 // Method java/util/ArrayList."<init>":()V
      93: putfield      #4                  // Field nestPairN:Ljava/util/List;
      96: aload_0
      97: iload_2
      98: putfield      #7                  // Field context:I
     101: aload_0
     102: iload_3
     103: putfield      #8                  // Field parameter:I
     106: aload_0
     107: aload         4
     109: putfield      #14                 // Field desc:Ljava/lang/String;
     112: aload_0
     113: iload         5
     115: putfield      #15                 // Field visible:Z
     118: return

  public void visit(java.lang.String, java.lang.Object);
    Code:
       0: aload_1
       1: ifnonnull     7
       4: ldc           #16                 // String
       6: astore_1
       7: aload_0
       8: getfield      #11                 // Field nameRU:Ljava/util/List;
      11: aload_1
      12: invokeinterface #17,  2           // InterfaceMethod java/util/List.add:(Ljava/lang/Object;)Z
      17: pop
      18: aload_0
      19: getfield      #5                  // Field this$0:Lorg/apache/commons/compress/harmony/pack200/Segment;
      22: aload_2
      23: aload_0
      24: getfield      #2                  // Field T:Ljava/util/List;
      27: aload_0
      28: getfield      #1                  // Field values:Ljava/util/List;
      31: invokestatic  #18                 // Method org/apache/commons/compress/harmony/pack200/Segment.access$500:(Lorg/apache/commons/compress/harmony/pack200/Segment;Ljava/lang/Object;Ljava/util/List;Ljava/util/List;)V
      34: return

  public org.objectweb.asm.AnnotationVisitor visitAnnotation(java.lang.String, java.lang.String);
    Code:
       0: aload_0
       1: getfield      #2                  // Field T:Ljava/util/List;
       4: ldc           #19                 // String @
       6: invokeinterface #17,  2           // InterfaceMethod java/util/List.add:(Ljava/lang/Object;)Z
      11: pop
      12: aload_1
      13: ifnonnull     19
      16: ldc           #16                 // String
      18: astore_1
      19: aload_0
      20: getfield      #11                 // Field nameRU:Ljava/util/List;
      23: aload_1
      24: invokeinterface #17,  2           // InterfaceMethod java/util/List.add:(Ljava/lang/Object;)Z
      29: pop
      30: aload_0
      31: getfield      #13                 // Field nestTypeRS:Ljava/util/List;
      34: aload_2
      35: invokeinterface #17,  2           // InterfaceMethod java/util/List.add:(Ljava/lang/Object;)Z
      40: pop
      41: aload_0
      42: getfield      #4                  // Field nestPairN:Ljava/util/List;
      45: iconst_0
      46: invokestatic  #20                 // Method java/lang/Integer.valueOf:(I)Ljava/lang/Integer;
      49: invokeinterface #17,  2           // InterfaceMethod java/util/List.add:(Ljava/lang/Object;)Z
      54: pop
      55: new           #21                 // class org/apache/commons/compress/harmony/pack200/Segment$SegmentAnnotationVisitor$1
      58: dup
      59: aload_0
      60: invokespecial #22                 // Method org/apache/commons/compress/harmony/pack200/Segment$SegmentAnnotationVisitor$1."<init>":(Lorg/apache/commons/compress/harmony/pack200/Segment$SegmentAnnotationVisitor;)V
      63: areturn

  public org.objectweb.asm.AnnotationVisitor visitArray(java.lang.String);
    Code:
       0: aload_0
       1: getfield      #2                  // Field T:Ljava/util/List;
       4: ldc           #23                 // String [
       6: invokeinterface #17,  2           // InterfaceMethod java/util/List.add:(Ljava/lang/Object;)Z
      11: pop
      12: aload_1
      13: ifnonnull     19
      16: ldc           #16                 // String
      18: astore_1
      19: aload_0
      20: getfield      #11                 // Field nameRU:Ljava/util/List;
      23: aload_1
      24: invokeinterface #17,  2           // InterfaceMethod java/util/List.add:(Ljava/lang/Object;)Z
      29: pop
      30: aload_0
      31: getfield      #12                 // Field caseArrayN:Ljava/util/List;
      34: iconst_0
      35: invokestatic  #20                 // Method java/lang/Integer.valueOf:(I)Ljava/lang/Integer;
      38: invokeinterface #17,  2           // InterfaceMethod java/util/List.add:(Ljava/lang/Object;)Z
      43: pop
      44: new           #24                 // class org/apache/commons/compress/harmony/pack200/Segment$ArrayVisitor
      47: dup
      48: aload_0
      49: getfield      #5                  // Field this$0:Lorg/apache/commons/compress/harmony/pack200/Segment;
      52: aload_0
      53: getfield      #12                 // Field caseArrayN:Ljava/util/List;
      56: aload_0
      57: getfield      #2                  // Field T:Ljava/util/List;
      60: aload_0
      61: getfield      #11                 // Field nameRU:Ljava/util/List;
      64: aload_0
      65: getfield      #1                  // Field values:Ljava/util/List;
      68: invokespecial #25                 // Method org/apache/commons/compress/harmony/pack200/Segment$ArrayVisitor."<init>":(Lorg/apache/commons/compress/harmony/pack200/Segment;Ljava/util/List;Ljava/util/List;Ljava/util/List;Ljava/util/List;)V
      71: areturn

  public void visitEnd();
    Code:
       0: aload_0
       1: getfield      #14                 // Field desc:Ljava/lang/String;
       4: ifnonnull     48
       7: aload_0
       8: getfield      #5                  // Field this$0:Lorg/apache/commons/compress/harmony/pack200/Segment;
      11: invokestatic  #26                 // Method org/apache/commons/compress/harmony/pack200/Segment.access$200:(Lorg/apache/commons/compress/harmony/pack200/Segment;)Lorg/apache/commons/compress/harmony/pack200/ClassBands;
      14: aload_0
      15: getfield      #11                 // Field nameRU:Ljava/util/List;
      18: aload_0
      19: getfield      #2                  // Field T:Ljava/util/List;
      22: aload_0
      23: getfield      #1                  // Field values:Ljava/util/List;
      26: aload_0
      27: getfield      #12                 // Field caseArrayN:Ljava/util/List;
      30: aload_0
      31: getfield      #13                 // Field nestTypeRS:Ljava/util/List;
      34: aload_0
      35: getfield      #3                  // Field nestNameRU:Ljava/util/List;
      38: aload_0
      39: getfield      #4                  // Field nestPairN:Ljava/util/List;
      42: invokevirtual #27                 // Method org/apache/commons/compress/harmony/pack200/ClassBands.addAnnotationDefault:(Ljava/util/List;Ljava/util/List;Ljava/util/List;Ljava/util/List;Ljava/util/List;Ljava/util/List;Ljava/util/List;)V
      45: goto          159
      48: aload_0
      49: getfield      #8                  // Field parameter:I
      52: iconst_m1
      53: if_icmpeq     109
      56: aload_0
      57: getfield      #5                  // Field this$0:Lorg/apache/commons/compress/harmony/pack200/Segment;
      60: invokestatic  #26                 // Method org/apache/commons/compress/harmony/pack200/Segment.access$200:(Lorg/apache/commons/compress/harmony/pack200/Segment;)Lorg/apache/commons/compress/harmony/pack200/ClassBands;
      63: aload_0
      64: getfield      #8                  // Field parameter:I
      67: aload_0
      68: getfield      #14                 // Field desc:Ljava/lang/String;
      71: aload_0
      72: getfield      #15                 // Field visible:Z
      75: aload_0
      76: getfield      #11                 // Field nameRU:Ljava/util/List;
      79: aload_0
      80: getfield      #2                  // Field T:Ljava/util/List;
      83: aload_0
      84: getfield      #1                  // Field values:Ljava/util/List;
      87: aload_0
      88: getfield      #12                 // Field caseArrayN:Ljava/util/List;
      91: aload_0
      92: getfield      #13                 // Field nestTypeRS:Ljava/util/List;
      95: aload_0
      96: getfield      #3                  // Field nestNameRU:Ljava/util/List;
      99: aload_0
     100: getfield      #4                  // Field nestPairN:Ljava/util/List;
     103: invokevirtual #28                 // Method org/apache/commons/compress/harmony/pack200/ClassBands.addParameterAnnotation:(ILjava/lang/String;ZLjava/util/List;Ljava/util/List;Ljava/util/List;Ljava/util/List;Ljava/util/List;Ljava/util/List;Ljava/util/List;)V
     106: goto          159
     109: aload_0
     110: getfield      #5                  // Field this$0:Lorg/apache/commons/compress/harmony/pack200/Segment;
     113: invokestatic  #26                 // Method org/apache/commons/compress/harmony/pack200/Segment.access$200:(Lorg/apache/commons/compress/harmony/pack200/Segment;)Lorg/apache/commons/compress/harmony/pack200/ClassBands;
     116: aload_0
     117: getfield      #7                  // Field context:I
     120: aload_0
     121: getfield      #14                 // Field desc:Ljava/lang/String;
     124: aload_0
     125: getfield      #15                 // Field visible:Z
     128: aload_0
     129: getfield      #11                 // Field nameRU:Ljava/util/List;
     132: aload_0
     133: getfield      #2                  // Field T:Ljava/util/List;
     136: aload_0
     137: getfield      #1                  // Field values:Ljava/util/List;
     140: aload_0
     141: getfield      #12                 // Field caseArrayN:Ljava/util/List;
     144: aload_0
     145: getfield      #13                 // Field nestTypeRS:Ljava/util/List;
     148: aload_0
     149: getfield      #3                  // Field nestNameRU:Ljava/util/List;
     152: aload_0
     153: getfield      #4                  // Field nestPairN:Ljava/util/List;
     156: invokevirtual #29                 // Method org/apache/commons/compress/harmony/pack200/ClassBands.addAnnotation:(ILjava/lang/String;ZLjava/util/List;Ljava/util/List;Ljava/util/List;Ljava/util/List;Ljava/util/List;Ljava/util/List;Ljava/util/List;)V
     159: return

  public void visitEnum(java.lang.String, java.lang.String, java.lang.String);
    Code:
       0: aload_0
       1: getfield      #2                  // Field T:Ljava/util/List;
       4: ldc           #30                 // String e
       6: invokeinterface #17,  2           // InterfaceMethod java/util/List.add:(Ljava/lang/Object;)Z
      11: pop
      12: aload_1
      13: ifnonnull     19
      16: ldc           #16                 // String
      18: astore_1
      19: aload_0
      20: getfield      #11                 // Field nameRU:Ljava/util/List;
      23: aload_1
      24: invokeinterface #17,  2           // InterfaceMethod java/util/List.add:(Ljava/lang/Object;)Z
      29: pop
      30: aload_0
      31: getfield      #1                  // Field values:Ljava/util/List;
      34: aload_2
      35: invokeinterface #17,  2           // InterfaceMethod java/util/List.add:(Ljava/lang/Object;)Z
      40: pop
      41: aload_0
      42: getfield      #1                  // Field values:Ljava/util/List;
      45: aload_3
      46: invokeinterface #17,  2           // InterfaceMethod java/util/List.add:(Ljava/lang/Object;)Z
      51: pop
      52: return

  static java.util.List access$600(org.apache.commons.compress.harmony.pack200.Segment$SegmentAnnotationVisitor);
    Code:
       0: aload_0
       1: getfield      #4                  // Field nestPairN:Ljava/util/List;
       4: areturn

  static java.util.List access$700(org.apache.commons.compress.harmony.pack200.Segment$SegmentAnnotationVisitor);
    Code:
       0: aload_0
       1: getfield      #3                  // Field nestNameRU:Ljava/util/List;
       4: areturn

  static java.util.List access$800(org.apache.commons.compress.harmony.pack200.Segment$SegmentAnnotationVisitor);
    Code:
       0: aload_0
       1: getfield      #2                  // Field T:Ljava/util/List;
       4: areturn

  static java.util.List access$900(org.apache.commons.compress.harmony.pack200.Segment$SegmentAnnotationVisitor);
    Code:
       0: aload_0
       1: getfield      #1                  // Field values:Ljava/util/List;
       4: areturn
}
