Compiled from "SimpleAbstractTypeResolver.java"
public class io.dekorate.deps.jackson.databind.module.SimpleAbstractTypeResolver extends io.dekorate.deps.jackson.databind.AbstractTypeResolver implements java.io.Serializable {
  private static final long serialVersionUID;

  protected final java.util.HashMap<io.dekorate.deps.jackson.databind.type.ClassKey, java.lang.Class<?>> _mappings;

  public io.dekorate.deps.jackson.databind.module.SimpleAbstractTypeResolver();
    Code:
       0: aload_0
       1: invokespecial #18                 // Method io/dekorate/deps/jackson/databind/AbstractTypeResolver."<init>":()V
       4: aload_0
       5: new           #20                 // class java/util/HashMap
       8: dup
       9: invokespecial #21                 // Method java/util/HashMap."<init>":()V
      12: putfield      #23                 // Field _mappings:Ljava/util/HashMap;
      15: return

  public <T> io.dekorate.deps.jackson.databind.module.SimpleAbstractTypeResolver addMapping(java.lang.Class<T>, java.lang.Class<? extends T>);
    Code:
       0: aload_1
       1: aload_2
       2: if_acmpne     15
       5: new           #30                 // class java/lang/IllegalArgumentException
       8: dup
       9: ldc           #32                 // String Cannot add mapping from class to itself
      11: invokespecial #35                 // Method java/lang/IllegalArgumentException."<init>":(Ljava/lang/String;)V
      14: athrow
      15: aload_1
      16: aload_2
      17: invokevirtual #41                 // Method java/lang/Class.isAssignableFrom:(Ljava/lang/Class;)Z
      20: ifne          70
      23: new           #30                 // class java/lang/IllegalArgumentException
      26: dup
      27: new           #43                 // class java/lang/StringBuilder
      30: dup
      31: invokespecial #44                 // Method java/lang/StringBuilder."<init>":()V
      34: ldc           #46                 // String Cannot add mapping from class
      36: invokevirtual #50                 // Method java/lang/StringBuilder.append:(Ljava/lang/String;)Ljava/lang/StringBuilder;
      39: aload_1
      40: invokevirtual #54                 // Method java/lang/Class.getName:()Ljava/lang/String;
      43: invokevirtual #50                 // Method java/lang/StringBuilder.append:(Ljava/lang/String;)Ljava/lang/StringBuilder;
      46: ldc           #56                 // String  to
      48: invokevirtual #50                 // Method java/lang/StringBuilder.append:(Ljava/lang/String;)Ljava/lang/StringBuilder;
      51: aload_2
      52: invokevirtual #54                 // Method java/lang/Class.getName:()Ljava/lang/String;
      55: invokevirtual #50                 // Method java/lang/StringBuilder.append:(Ljava/lang/String;)Ljava/lang/StringBuilder;
      58: ldc           #58                 // String , as latter is not a subtype of former
      60: invokevirtual #50                 // Method java/lang/StringBuilder.append:(Ljava/lang/String;)Ljava/lang/StringBuilder;
      63: invokevirtual #61                 // Method java/lang/StringBuilder.toString:()Ljava/lang/String;
      66: invokespecial #35                 // Method java/lang/IllegalArgumentException."<init>":(Ljava/lang/String;)V
      69: athrow
      70: aload_1
      71: invokevirtual #65                 // Method java/lang/Class.getModifiers:()I
      74: invokestatic  #71                 // Method java/lang/reflect/Modifier.isAbstract:(I)Z
      77: ifne          115
      80: new           #30                 // class java/lang/IllegalArgumentException
      83: dup
      84: new           #43                 // class java/lang/StringBuilder
      87: dup
      88: invokespecial #44                 // Method java/lang/StringBuilder."<init>":()V
      91: ldc           #46                 // String Cannot add mapping from class
      93: invokevirtual #50                 // Method java/lang/StringBuilder.append:(Ljava/lang/String;)Ljava/lang/StringBuilder;
      96: aload_1
      97: invokevirtual #54                 // Method java/lang/Class.getName:()Ljava/lang/String;
     100: invokevirtual #50                 // Method java/lang/StringBuilder.append:(Ljava/lang/String;)Ljava/lang/StringBuilder;
     103: ldc           #73                 // String  since it is not abstract
     105: invokevirtual #50                 // Method java/lang/StringBuilder.append:(Ljava/lang/String;)Ljava/lang/StringBuilder;
     108: invokevirtual #61                 // Method java/lang/StringBuilder.toString:()Ljava/lang/String;
     111: invokespecial #35                 // Method java/lang/IllegalArgumentException."<init>":(Ljava/lang/String;)V
     114: athrow
     115: aload_0
     116: getfield      #23                 // Field _mappings:Ljava/util/HashMap;
     119: new           #75                 // class io/dekorate/deps/jackson/databind/type/ClassKey
     122: dup
     123: aload_1
     124: invokespecial #78                 // Method io/dekorate/deps/jackson/databind/type/ClassKey."<init>":(Ljava/lang/Class;)V
     127: aload_2
     128: invokevirtual #82                 // Method java/util/HashMap.put:(Ljava/lang/Object;Ljava/lang/Object;)Ljava/lang/Object;
     131: pop
     132: aload_0
     133: areturn

  public io.dekorate.deps.jackson.databind.JavaType findTypeMapping(io.dekorate.deps.jackson.databind.DeserializationConfig, io.dekorate.deps.jackson.databind.JavaType);
    Code:
       0: aload_2
       1: invokevirtual #95                 // Method io/dekorate/deps/jackson/databind/JavaType.getRawClass:()Ljava/lang/Class;
       4: astore_3
       5: aload_0
       6: getfield      #23                 // Field _mappings:Ljava/util/HashMap;
       9: new           #75                 // class io/dekorate/deps/jackson/databind/type/ClassKey
      12: dup
      13: aload_3
      14: invokespecial #78                 // Method io/dekorate/deps/jackson/databind/type/ClassKey."<init>":(Ljava/lang/Class;)V
      17: invokevirtual #99                 // Method java/util/HashMap.get:(Ljava/lang/Object;)Ljava/lang/Object;
      20: checkcast     #37                 // class java/lang/Class
      23: astore        4
      25: aload         4
      27: ifnonnull     32
      30: aconst_null
      31: areturn
      32: aload_1
      33: invokevirtual #105                // Method io/dekorate/deps/jackson/databind/DeserializationConfig.getTypeFactory:()Lio/dekorate/deps/jackson/databind/type/TypeFactory;
      36: aload_2
      37: aload         4
      39: invokevirtual #111                // Method io/dekorate/deps/jackson/databind/type/TypeFactory.constructSpecializedType:(Lio/dekorate/deps/jackson/databind/JavaType;Ljava/lang/Class;)Lio/dekorate/deps/jackson/databind/JavaType;
      42: areturn

  public io.dekorate.deps.jackson.databind.JavaType resolveAbstractType(io.dekorate.deps.jackson.databind.DeserializationConfig, io.dekorate.deps.jackson.databind.JavaType);
    Code:
       0: aconst_null
       1: areturn

  public io.dekorate.deps.jackson.databind.JavaType resolveAbstractType(io.dekorate.deps.jackson.databind.DeserializationConfig, io.dekorate.deps.jackson.databind.BeanDescription);
    Code:
       0: aconst_null
       1: areturn
}
