Compiled from "DB2Dialect.java"
public class org.hibernate.dialect.DB2Dialect extends org.hibernate.dialect.Dialect {
  private static final org.hibernate.dialect.pagination.AbstractLimitHandler LIMIT_HANDLER;

  private final org.hibernate.dialect.unique.UniqueDelegate uniqueDelegate;

  public org.hibernate.dialect.DB2Dialect();
    Code:
       0: aload_0
       1: invokespecial #1                  // Method org/hibernate/dialect/Dialect."<init>":()V
       4: aload_0
       5: bipush        -7
       7: ldc           #3                  // String smallint
       9: invokevirtual #4                  // Method registerColumnType:(ILjava/lang/String;)V
      12: aload_0
      13: bipush        -5
      15: ldc           #5                  // String bigint
      17: invokevirtual #4                  // Method registerColumnType:(ILjava/lang/String;)V
      20: aload_0
      21: iconst_5
      22: ldc           #3                  // String smallint
      24: invokevirtual #4                  // Method registerColumnType:(ILjava/lang/String;)V
      27: aload_0
      28: bipush        -6
      30: ldc           #3                  // String smallint
      32: invokevirtual #4                  // Method registerColumnType:(ILjava/lang/String;)V
      35: aload_0
      36: iconst_4
      37: ldc           #6                  // String integer
      39: invokevirtual #4                  // Method registerColumnType:(ILjava/lang/String;)V
      42: aload_0
      43: iconst_1
      44: ldc           #7                  // String char(1)
      46: invokevirtual #4                  // Method registerColumnType:(ILjava/lang/String;)V
      49: aload_0
      50: bipush        12
      52: ldc           #8                  // String varchar($l)
      54: invokevirtual #4                  // Method registerColumnType:(ILjava/lang/String;)V
      57: aload_0
      58: bipush        6
      60: ldc           #9                  // String float
      62: invokevirtual #4                  // Method registerColumnType:(ILjava/lang/String;)V
      65: aload_0
      66: bipush        8
      68: ldc           #10                 // String double
      70: invokevirtual #4                  // Method registerColumnType:(ILjava/lang/String;)V
      73: aload_0
      74: bipush        91
      76: ldc           #11                 // String date
      78: invokevirtual #4                  // Method registerColumnType:(ILjava/lang/String;)V
      81: aload_0
      82: bipush        92
      84: ldc           #12                 // String time
      86: invokevirtual #4                  // Method registerColumnType:(ILjava/lang/String;)V
      89: aload_0
      90: bipush        93
      92: ldc           #13                 // String timestamp
      94: invokevirtual #4                  // Method registerColumnType:(ILjava/lang/String;)V
      97: aload_0
      98: bipush        -3
     100: ldc           #14                 // String varchar($l) for bit data
     102: invokevirtual #4                  // Method registerColumnType:(ILjava/lang/String;)V
     105: aload_0
     106: iconst_2
     107: ldc           #15                 // String decimal($p,$s)
     109: invokevirtual #4                  // Method registerColumnType:(ILjava/lang/String;)V
     112: aload_0
     113: iconst_3
     114: ldc           #15                 // String decimal($p,$s)
     116: invokevirtual #4                  // Method registerColumnType:(ILjava/lang/String;)V
     119: aload_0
     120: sipush        2004
     123: ldc           #16                 // String blob($l)
     125: invokevirtual #4                  // Method registerColumnType:(ILjava/lang/String;)V
     128: aload_0
     129: sipush        2005
     132: ldc           #17                 // String clob($l)
     134: invokevirtual #4                  // Method registerColumnType:(ILjava/lang/String;)V
     137: aload_0
     138: iconst_m1
     139: ldc           #18                 // String long varchar
     141: invokevirtual #4                  // Method registerColumnType:(ILjava/lang/String;)V
     144: aload_0
     145: bipush        -4
     147: ldc           #19                 // String long varchar for bit data
     149: invokevirtual #4                  // Method registerColumnType:(ILjava/lang/String;)V
     152: aload_0
     153: bipush        -2
     155: ldc           #14                 // String varchar($l) for bit data
     157: invokevirtual #4                  // Method registerColumnType:(ILjava/lang/String;)V
     160: aload_0
     161: bipush        -2
     163: ldc2_w        #20                 // long 254l
     166: ldc           #22                 // String char($l) for bit data
     168: invokevirtual #23                 // Method registerColumnType:(IJLjava/lang/String;)V
     171: aload_0
     172: bipush        16
     174: ldc           #3                  // String smallint
     176: invokevirtual #4                  // Method registerColumnType:(ILjava/lang/String;)V
     179: aload_0
     180: ldc           #24                 // String avg
     182: new           #25                 // class org/hibernate/dialect/function/AvgWithArgumentCastFunction
     185: dup
     186: ldc           #10                 // String double
     188: invokespecial #26                 // Method org/hibernate/dialect/function/AvgWithArgumentCastFunction."<init>":(Ljava/lang/String;)V
     191: invokevirtual #27                 // Method registerFunction:(Ljava/lang/String;Lorg/hibernate/dialect/function/SQLFunction;)V
     194: aload_0
     195: ldc           #28                 // String abs
     197: new           #29                 // class org/hibernate/dialect/function/StandardSQLFunction
     200: dup
     201: ldc           #28                 // String abs
     203: invokespecial #30                 // Method org/hibernate/dialect/function/StandardSQLFunction."<init>":(Ljava/lang/String;)V
     206: invokevirtual #27                 // Method registerFunction:(Ljava/lang/String;Lorg/hibernate/dialect/function/SQLFunction;)V
     209: aload_0
     210: ldc           #31                 // String absval
     212: new           #29                 // class org/hibernate/dialect/function/StandardSQLFunction
     215: dup
     216: ldc           #31                 // String absval
     218: invokespecial #30                 // Method org/hibernate/dialect/function/StandardSQLFunction."<init>":(Ljava/lang/String;)V
     221: invokevirtual #27                 // Method registerFunction:(Ljava/lang/String;Lorg/hibernate/dialect/function/SQLFunction;)V
     224: aload_0
     225: ldc           #32                 // String sign
     227: new           #29                 // class org/hibernate/dialect/function/StandardSQLFunction
     230: dup
     231: ldc           #32                 // String sign
     233: getstatic     #33                 // Field org/hibernate/type/StandardBasicTypes.INTEGER:Lorg/hibernate/type/IntegerType;
     236: invokespecial #34                 // Method org/hibernate/dialect/function/StandardSQLFunction."<init>":(Ljava/lang/String;Lorg/hibernate/type/Type;)V
     239: invokevirtual #27                 // Method registerFunction:(Ljava/lang/String;Lorg/hibernate/dialect/function/SQLFunction;)V
     242: aload_0
     243: ldc           #35                 // String ceiling
     245: new           #29                 // class org/hibernate/dialect/function/StandardSQLFunction
     248: dup
     249: ldc           #35                 // String ceiling
     251: invokespecial #30                 // Method org/hibernate/dialect/function/StandardSQLFunction."<init>":(Ljava/lang/String;)V
     254: invokevirtual #27                 // Method registerFunction:(Ljava/lang/String;Lorg/hibernate/dialect/function/SQLFunction;)V
     257: aload_0
     258: ldc           #36                 // String ceil
     260: new           #29                 // class org/hibernate/dialect/function/StandardSQLFunction
     263: dup
     264: ldc           #36                 // String ceil
     266: invokespecial #30                 // Method org/hibernate/dialect/function/StandardSQLFunction."<init>":(Ljava/lang/String;)V
     269: invokevirtual #27                 // Method registerFunction:(Ljava/lang/String;Lorg/hibernate/dialect/function/SQLFunction;)V
     272: aload_0
     273: ldc           #37                 // String floor
     275: new           #29                 // class org/hibernate/dialect/function/StandardSQLFunction
     278: dup
     279: ldc           #37                 // String floor
     281: invokespecial #30                 // Method org/hibernate/dialect/function/StandardSQLFunction."<init>":(Ljava/lang/String;)V
     284: invokevirtual #27                 // Method registerFunction:(Ljava/lang/String;Lorg/hibernate/dialect/function/SQLFunction;)V
     287: aload_0
     288: ldc           #38                 // String round
     290: new           #29                 // class org/hibernate/dialect/function/StandardSQLFunction
     293: dup
     294: ldc           #38                 // String round
     296: invokespecial #30                 // Method org/hibernate/dialect/function/StandardSQLFunction."<init>":(Ljava/lang/String;)V
     299: invokevirtual #27                 // Method registerFunction:(Ljava/lang/String;Lorg/hibernate/dialect/function/SQLFunction;)V
     302: aload_0
     303: ldc           #39                 // String acos
     305: new           #29                 // class org/hibernate/dialect/function/StandardSQLFunction
     308: dup
     309: ldc           #39                 // String acos
     311: getstatic     #40                 // Field org/hibernate/type/StandardBasicTypes.DOUBLE:Lorg/hibernate/type/DoubleType;
     314: invokespecial #34                 // Method org/hibernate/dialect/function/StandardSQLFunction."<init>":(Ljava/lang/String;Lorg/hibernate/type/Type;)V
     317: invokevirtual #27                 // Method registerFunction:(Ljava/lang/String;Lorg/hibernate/dialect/function/SQLFunction;)V
     320: aload_0
     321: ldc           #41                 // String asin
     323: new           #29                 // class org/hibernate/dialect/function/StandardSQLFunction
     326: dup
     327: ldc           #41                 // String asin
     329: getstatic     #40                 // Field org/hibernate/type/StandardBasicTypes.DOUBLE:Lorg/hibernate/type/DoubleType;
     332: invokespecial #34                 // Method org/hibernate/dialect/function/StandardSQLFunction."<init>":(Ljava/lang/String;Lorg/hibernate/type/Type;)V
     335: invokevirtual #27                 // Method registerFunction:(Ljava/lang/String;Lorg/hibernate/dialect/function/SQLFunction;)V
     338: aload_0
     339: ldc           #42                 // String atan
     341: new           #29                 // class org/hibernate/dialect/function/StandardSQLFunction
     344: dup
     345: ldc           #42                 // String atan
     347: getstatic     #40                 // Field org/hibernate/type/StandardBasicTypes.DOUBLE:Lorg/hibernate/type/DoubleType;
     350: invokespecial #34                 // Method org/hibernate/dialect/function/StandardSQLFunction."<init>":(Ljava/lang/String;Lorg/hibernate/type/Type;)V
     353: invokevirtual #27                 // Method registerFunction:(Ljava/lang/String;Lorg/hibernate/dialect/function/SQLFunction;)V
     356: aload_0
     357: ldc           #43                 // String cos
     359: new           #29                 // class org/hibernate/dialect/function/StandardSQLFunction
     362: dup
     363: ldc           #43                 // String cos
     365: getstatic     #40                 // Field org/hibernate/type/StandardBasicTypes.DOUBLE:Lorg/hibernate/type/DoubleType;
     368: invokespecial #34                 // Method org/hibernate/dialect/function/StandardSQLFunction."<init>":(Ljava/lang/String;Lorg/hibernate/type/Type;)V
     371: invokevirtual #27                 // Method registerFunction:(Ljava/lang/String;Lorg/hibernate/dialect/function/SQLFunction;)V
     374: aload_0
     375: ldc           #44                 // String cot
     377: new           #29                 // class org/hibernate/dialect/function/StandardSQLFunction
     380: dup
     381: ldc           #44                 // String cot
     383: getstatic     #40                 // Field org/hibernate/type/StandardBasicTypes.DOUBLE:Lorg/hibernate/type/DoubleType;
     386: invokespecial #34                 // Method org/hibernate/dialect/function/StandardSQLFunction."<init>":(Ljava/lang/String;Lorg/hibernate/type/Type;)V
     389: invokevirtual #27                 // Method registerFunction:(Ljava/lang/String;Lorg/hibernate/dialect/function/SQLFunction;)V
     392: aload_0
     393: ldc           #45                 // String degrees
     395: new           #29                 // class org/hibernate/dialect/function/StandardSQLFunction
     398: dup
     399: ldc           #45                 // String degrees
     401: getstatic     #40                 // Field org/hibernate/type/StandardBasicTypes.DOUBLE:Lorg/hibernate/type/DoubleType;
     404: invokespecial #34                 // Method org/hibernate/dialect/function/StandardSQLFunction."<init>":(Ljava/lang/String;Lorg/hibernate/type/Type;)V
     407: invokevirtual #27                 // Method registerFunction:(Ljava/lang/String;Lorg/hibernate/dialect/function/SQLFunction;)V
     410: aload_0
     411: ldc           #46                 // String exp
     413: new           #29                 // class org/hibernate/dialect/function/StandardSQLFunction
     416: dup
     417: ldc           #46                 // String exp
     419: getstatic     #40                 // Field org/hibernate/type/StandardBasicTypes.DOUBLE:Lorg/hibernate/type/DoubleType;
     422: invokespecial #34                 // Method org/hibernate/dialect/function/StandardSQLFunction."<init>":(Ljava/lang/String;Lorg/hibernate/type/Type;)V
     425: invokevirtual #27                 // Method registerFunction:(Ljava/lang/String;Lorg/hibernate/dialect/function/SQLFunction;)V
     428: aload_0
     429: ldc           #9                  // String float
     431: new           #29                 // class org/hibernate/dialect/function/StandardSQLFunction
     434: dup
     435: ldc           #9                  // String float
     437: getstatic     #40                 // Field org/hibernate/type/StandardBasicTypes.DOUBLE:Lorg/hibernate/type/DoubleType;
     440: invokespecial #34                 // Method org/hibernate/dialect/function/StandardSQLFunction."<init>":(Ljava/lang/String;Lorg/hibernate/type/Type;)V
     443: invokevirtual #27                 // Method registerFunction:(Ljava/lang/String;Lorg/hibernate/dialect/function/SQLFunction;)V
     446: aload_0
     447: ldc           #47                 // String hex
     449: new           #29                 // class org/hibernate/dialect/function/StandardSQLFunction
     452: dup
     453: ldc           #47                 // String hex
     455: getstatic     #48                 // Field org/hibernate/type/StandardBasicTypes.STRING:Lorg/hibernate/type/StringType;
     458: invokespecial #34                 // Method org/hibernate/dialect/function/StandardSQLFunction."<init>":(Ljava/lang/String;Lorg/hibernate/type/Type;)V
     461: invokevirtual #27                 // Method registerFunction:(Ljava/lang/String;Lorg/hibernate/dialect/function/SQLFunction;)V
     464: aload_0
     465: ldc           #49                 // String ln
     467: new           #29                 // class org/hibernate/dialect/function/StandardSQLFunction
     470: dup
     471: ldc           #49                 // String ln
     473: getstatic     #40                 // Field org/hibernate/type/StandardBasicTypes.DOUBLE:Lorg/hibernate/type/DoubleType;
     476: invokespecial #34                 // Method org/hibernate/dialect/function/StandardSQLFunction."<init>":(Ljava/lang/String;Lorg/hibernate/type/Type;)V
     479: invokevirtual #27                 // Method registerFunction:(Ljava/lang/String;Lorg/hibernate/dialect/function/SQLFunction;)V
     482: aload_0
     483: ldc           #50                 // String log
     485: new           #29                 // class org/hibernate/dialect/function/StandardSQLFunction
     488: dup
     489: ldc           #50                 // String log
     491: getstatic     #40                 // Field org/hibernate/type/StandardBasicTypes.DOUBLE:Lorg/hibernate/type/DoubleType;
     494: invokespecial #34                 // Method org/hibernate/dialect/function/StandardSQLFunction."<init>":(Ljava/lang/String;Lorg/hibernate/type/Type;)V
     497: invokevirtual #27                 // Method registerFunction:(Ljava/lang/String;Lorg/hibernate/dialect/function/SQLFunction;)V
     500: aload_0
     501: ldc           #51                 // String log10
     503: new           #29                 // class org/hibernate/dialect/function/StandardSQLFunction
     506: dup
     507: ldc           #51                 // String log10
     509: getstatic     #40                 // Field org/hibernate/type/StandardBasicTypes.DOUBLE:Lorg/hibernate/type/DoubleType;
     512: invokespecial #34                 // Method org/hibernate/dialect/function/StandardSQLFunction."<init>":(Ljava/lang/String;Lorg/hibernate/type/Type;)V
     515: invokevirtual #27                 // Method registerFunction:(Ljava/lang/String;Lorg/hibernate/dialect/function/SQLFunction;)V
     518: aload_0
     519: ldc           #52                 // String radians
     521: new           #29                 // class org/hibernate/dialect/function/StandardSQLFunction
     524: dup
     525: ldc           #52                 // String radians
     527: getstatic     #40                 // Field org/hibernate/type/StandardBasicTypes.DOUBLE:Lorg/hibernate/type/DoubleType;
     530: invokespecial #34                 // Method org/hibernate/dialect/function/StandardSQLFunction."<init>":(Ljava/lang/String;Lorg/hibernate/type/Type;)V
     533: invokevirtual #27                 // Method registerFunction:(Ljava/lang/String;Lorg/hibernate/dialect/function/SQLFunction;)V
     536: aload_0
     537: ldc           #53                 // String rand
     539: new           #54                 // class org/hibernate/dialect/function/NoArgSQLFunction
     542: dup
     543: ldc           #53                 // String rand
     545: getstatic     #40                 // Field org/hibernate/type/StandardBasicTypes.DOUBLE:Lorg/hibernate/type/DoubleType;
     548: invokespecial #55                 // Method org/hibernate/dialect/function/NoArgSQLFunction."<init>":(Ljava/lang/String;Lorg/hibernate/type/Type;)V
     551: invokevirtual #27                 // Method registerFunction:(Ljava/lang/String;Lorg/hibernate/dialect/function/SQLFunction;)V
     554: aload_0
     555: ldc           #56                 // String sin
     557: new           #29                 // class org/hibernate/dialect/function/StandardSQLFunction
     560: dup
     561: ldc           #56                 // String sin
     563: getstatic     #40                 // Field org/hibernate/type/StandardBasicTypes.DOUBLE:Lorg/hibernate/type/DoubleType;
     566: invokespecial #34                 // Method org/hibernate/dialect/function/StandardSQLFunction."<init>":(Ljava/lang/String;Lorg/hibernate/type/Type;)V
     569: invokevirtual #27                 // Method registerFunction:(Ljava/lang/String;Lorg/hibernate/dialect/function/SQLFunction;)V
     572: aload_0
     573: ldc           #57                 // String soundex
     575: new           #29                 // class org/hibernate/dialect/function/StandardSQLFunction
     578: dup
     579: ldc           #57                 // String soundex
     581: getstatic     #48                 // Field org/hibernate/type/StandardBasicTypes.STRING:Lorg/hibernate/type/StringType;
     584: invokespecial #34                 // Method org/hibernate/dialect/function/StandardSQLFunction."<init>":(Ljava/lang/String;Lorg/hibernate/type/Type;)V
     587: invokevirtual #27                 // Method registerFunction:(Ljava/lang/String;Lorg/hibernate/dialect/function/SQLFunction;)V
     590: aload_0
     591: ldc           #58                 // String sqrt
     593: new           #29                 // class org/hibernate/dialect/function/StandardSQLFunction
     596: dup
     597: ldc           #58                 // String sqrt
     599: getstatic     #40                 // Field org/hibernate/type/StandardBasicTypes.DOUBLE:Lorg/hibernate/type/DoubleType;
     602: invokespecial #34                 // Method org/hibernate/dialect/function/StandardSQLFunction."<init>":(Ljava/lang/String;Lorg/hibernate/type/Type;)V
     605: invokevirtual #27                 // Method registerFunction:(Ljava/lang/String;Lorg/hibernate/dialect/function/SQLFunction;)V
     608: aload_0
     609: ldc           #59                 // String stddev
     611: new           #29                 // class org/hibernate/dialect/function/StandardSQLFunction
     614: dup
     615: ldc           #59                 // String stddev
     617: getstatic     #40                 // Field org/hibernate/type/StandardBasicTypes.DOUBLE:Lorg/hibernate/type/DoubleType;
     620: invokespecial #34                 // Method org/hibernate/dialect/function/StandardSQLFunction."<init>":(Ljava/lang/String;Lorg/hibernate/type/Type;)V
     623: invokevirtual #27                 // Method registerFunction:(Ljava/lang/String;Lorg/hibernate/dialect/function/SQLFunction;)V
     626: aload_0
     627: ldc           #60                 // String tan
     629: new           #29                 // class org/hibernate/dialect/function/StandardSQLFunction
     632: dup
     633: ldc           #60                 // String tan
     635: getstatic     #40                 // Field org/hibernate/type/StandardBasicTypes.DOUBLE:Lorg/hibernate/type/DoubleType;
     638: invokespecial #34                 // Method org/hibernate/dialect/function/StandardSQLFunction."<init>":(Ljava/lang/String;Lorg/hibernate/type/Type;)V
     641: invokevirtual #27                 // Method registerFunction:(Ljava/lang/String;Lorg/hibernate/dialect/function/SQLFunction;)V
     644: aload_0
     645: ldc           #61                 // String variance
     647: new           #29                 // class org/hibernate/dialect/function/StandardSQLFunction
     650: dup
     651: ldc           #61                 // String variance
     653: getstatic     #40                 // Field org/hibernate/type/StandardBasicTypes.DOUBLE:Lorg/hibernate/type/DoubleType;
     656: invokespecial #34                 // Method org/hibernate/dialect/function/StandardSQLFunction."<init>":(Ljava/lang/String;Lorg/hibernate/type/Type;)V
     659: invokevirtual #27                 // Method registerFunction:(Ljava/lang/String;Lorg/hibernate/dialect/function/SQLFunction;)V
     662: aload_0
     663: ldc           #62                 // String julian_day
     665: new           #29                 // class org/hibernate/dialect/function/StandardSQLFunction
     668: dup
     669: ldc           #62                 // String julian_day
     671: getstatic     #33                 // Field org/hibernate/type/StandardBasicTypes.INTEGER:Lorg/hibernate/type/IntegerType;
     674: invokespecial #34                 // Method org/hibernate/dialect/function/StandardSQLFunction."<init>":(Ljava/lang/String;Lorg/hibernate/type/Type;)V
     677: invokevirtual #27                 // Method registerFunction:(Ljava/lang/String;Lorg/hibernate/dialect/function/SQLFunction;)V
     680: aload_0
     681: ldc           #63                 // String microsecond
     683: new           #29                 // class org/hibernate/dialect/function/StandardSQLFunction
     686: dup
     687: ldc           #63                 // String microsecond
     689: getstatic     #33                 // Field org/hibernate/type/StandardBasicTypes.INTEGER:Lorg/hibernate/type/IntegerType;
     692: invokespecial #34                 // Method org/hibernate/dialect/function/StandardSQLFunction."<init>":(Ljava/lang/String;Lorg/hibernate/type/Type;)V
     695: invokevirtual #27                 // Method registerFunction:(Ljava/lang/String;Lorg/hibernate/dialect/function/SQLFunction;)V
     698: aload_0
     699: ldc           #64                 // String midnight_seconds
     701: new           #29                 // class org/hibernate/dialect/function/StandardSQLFunction
     704: dup
     705: ldc           #64                 // String midnight_seconds
     707: getstatic     #33                 // Field org/hibernate/type/StandardBasicTypes.INTEGER:Lorg/hibernate/type/IntegerType;
     710: invokespecial #34                 // Method org/hibernate/dialect/function/StandardSQLFunction."<init>":(Ljava/lang/String;Lorg/hibernate/type/Type;)V
     713: invokevirtual #27                 // Method registerFunction:(Ljava/lang/String;Lorg/hibernate/dialect/function/SQLFunction;)V
     716: aload_0
     717: ldc           #65                 // String minute
     719: new           #29                 // class org/hibernate/dialect/function/StandardSQLFunction
     722: dup
     723: ldc           #65                 // String minute
     725: getstatic     #33                 // Field org/hibernate/type/StandardBasicTypes.INTEGER:Lorg/hibernate/type/IntegerType;
     728: invokespecial #34                 // Method org/hibernate/dialect/function/StandardSQLFunction."<init>":(Ljava/lang/String;Lorg/hibernate/type/Type;)V
     731: invokevirtual #27                 // Method registerFunction:(Ljava/lang/String;Lorg/hibernate/dialect/function/SQLFunction;)V
     734: aload_0
     735: ldc           #66                 // String month
     737: new           #29                 // class org/hibernate/dialect/function/StandardSQLFunction
     740: dup
     741: ldc           #66                 // String month
     743: getstatic     #33                 // Field org/hibernate/type/StandardBasicTypes.INTEGER:Lorg/hibernate/type/IntegerType;
     746: invokespecial #34                 // Method org/hibernate/dialect/function/StandardSQLFunction."<init>":(Ljava/lang/String;Lorg/hibernate/type/Type;)V
     749: invokevirtual #27                 // Method registerFunction:(Ljava/lang/String;Lorg/hibernate/dialect/function/SQLFunction;)V
     752: aload_0
     753: ldc           #67                 // String monthname
     755: new           #29                 // class org/hibernate/dialect/function/StandardSQLFunction
     758: dup
     759: ldc           #67                 // String monthname
     761: getstatic     #48                 // Field org/hibernate/type/StandardBasicTypes.STRING:Lorg/hibernate/type/StringType;
     764: invokespecial #34                 // Method org/hibernate/dialect/function/StandardSQLFunction."<init>":(Ljava/lang/String;Lorg/hibernate/type/Type;)V
     767: invokevirtual #27                 // Method registerFunction:(Ljava/lang/String;Lorg/hibernate/dialect/function/SQLFunction;)V
     770: aload_0
     771: ldc           #68                 // String quarter
     773: new           #29                 // class org/hibernate/dialect/function/StandardSQLFunction
     776: dup
     777: ldc           #68                 // String quarter
     779: getstatic     #33                 // Field org/hibernate/type/StandardBasicTypes.INTEGER:Lorg/hibernate/type/IntegerType;
     782: invokespecial #34                 // Method org/hibernate/dialect/function/StandardSQLFunction."<init>":(Ljava/lang/String;Lorg/hibernate/type/Type;)V
     785: invokevirtual #27                 // Method registerFunction:(Ljava/lang/String;Lorg/hibernate/dialect/function/SQLFunction;)V
     788: aload_0
     789: ldc           #69                 // String hour
     791: new           #29                 // class org/hibernate/dialect/function/StandardSQLFunction
     794: dup
     795: ldc           #69                 // String hour
     797: getstatic     #33                 // Field org/hibernate/type/StandardBasicTypes.INTEGER:Lorg/hibernate/type/IntegerType;
     800: invokespecial #34                 // Method org/hibernate/dialect/function/StandardSQLFunction."<init>":(Ljava/lang/String;Lorg/hibernate/type/Type;)V
     803: invokevirtual #27                 // Method registerFunction:(Ljava/lang/String;Lorg/hibernate/dialect/function/SQLFunction;)V
     806: aload_0
     807: ldc           #70                 // String second
     809: new           #29                 // class org/hibernate/dialect/function/StandardSQLFunction
     812: dup
     813: ldc           #70                 // String second
     815: getstatic     #33                 // Field org/hibernate/type/StandardBasicTypes.INTEGER:Lorg/hibernate/type/IntegerType;
     818: invokespecial #34                 // Method org/hibernate/dialect/function/StandardSQLFunction."<init>":(Ljava/lang/String;Lorg/hibernate/type/Type;)V
     821: invokevirtual #27                 // Method registerFunction:(Ljava/lang/String;Lorg/hibernate/dialect/function/SQLFunction;)V
     824: aload_0
     825: ldc           #71                 // String current_date
     827: new           #54                 // class org/hibernate/dialect/function/NoArgSQLFunction
     830: dup
     831: ldc           #72                 // String current date
     833: getstatic     #73                 // Field org/hibernate/type/StandardBasicTypes.DATE:Lorg/hibernate/type/DateType;
     836: iconst_0
     837: invokespecial #74                 // Method org/hibernate/dialect/function/NoArgSQLFunction."<init>":(Ljava/lang/String;Lorg/hibernate/type/Type;Z)V
     840: invokevirtual #27                 // Method registerFunction:(Ljava/lang/String;Lorg/hibernate/dialect/function/SQLFunction;)V
     843: aload_0
     844: ldc           #11                 // String date
     846: new           #29                 // class org/hibernate/dialect/function/StandardSQLFunction
     849: dup
     850: ldc           #11                 // String date
     852: getstatic     #73                 // Field org/hibernate/type/StandardBasicTypes.DATE:Lorg/hibernate/type/DateType;
     855: invokespecial #34                 // Method org/hibernate/dialect/function/StandardSQLFunction."<init>":(Ljava/lang/String;Lorg/hibernate/type/Type;)V
     858: invokevirtual #27                 // Method registerFunction:(Ljava/lang/String;Lorg/hibernate/dialect/function/SQLFunction;)V
     861: aload_0
     862: ldc           #75                 // String day
     864: new           #29                 // class org/hibernate/dialect/function/StandardSQLFunction
     867: dup
     868: ldc           #75                 // String day
     870: getstatic     #33                 // Field org/hibernate/type/StandardBasicTypes.INTEGER:Lorg/hibernate/type/IntegerType;
     873: invokespecial #34                 // Method org/hibernate/dialect/function/StandardSQLFunction."<init>":(Ljava/lang/String;Lorg/hibernate/type/Type;)V
     876: invokevirtual #27                 // Method registerFunction:(Ljava/lang/String;Lorg/hibernate/dialect/function/SQLFunction;)V
     879: aload_0
     880: ldc           #76                 // String dayname
     882: new           #29                 // class org/hibernate/dialect/function/StandardSQLFunction
     885: dup
     886: ldc           #76                 // String dayname
     888: getstatic     #48                 // Field org/hibernate/type/StandardBasicTypes.STRING:Lorg/hibernate/type/StringType;
     891: invokespecial #34                 // Method org/hibernate/dialect/function/StandardSQLFunction."<init>":(Ljava/lang/String;Lorg/hibernate/type/Type;)V
     894: invokevirtual #27                 // Method registerFunction:(Ljava/lang/String;Lorg/hibernate/dialect/function/SQLFunction;)V
     897: aload_0
     898: ldc           #77                 // String dayofweek
     900: new           #29                 // class org/hibernate/dialect/function/StandardSQLFunction
     903: dup
     904: ldc           #77                 // String dayofweek
     906: getstatic     #33                 // Field org/hibernate/type/StandardBasicTypes.INTEGER:Lorg/hibernate/type/IntegerType;
     909: invokespecial #34                 // Method org/hibernate/dialect/function/StandardSQLFunction."<init>":(Ljava/lang/String;Lorg/hibernate/type/Type;)V
     912: invokevirtual #27                 // Method registerFunction:(Ljava/lang/String;Lorg/hibernate/dialect/function/SQLFunction;)V
     915: aload_0
     916: ldc           #78                 // String dayofweek_iso
     918: new           #29                 // class org/hibernate/dialect/function/StandardSQLFunction
     921: dup
     922: ldc           #78                 // String dayofweek_iso
     924: getstatic     #33                 // Field org/hibernate/type/StandardBasicTypes.INTEGER:Lorg/hibernate/type/IntegerType;
     927: invokespecial #34                 // Method org/hibernate/dialect/function/StandardSQLFunction."<init>":(Ljava/lang/String;Lorg/hibernate/type/Type;)V
     930: invokevirtual #27                 // Method registerFunction:(Ljava/lang/String;Lorg/hibernate/dialect/function/SQLFunction;)V
     933: aload_0
     934: ldc           #79                 // String dayofyear
     936: new           #29                 // class org/hibernate/dialect/function/StandardSQLFunction
     939: dup
     940: ldc           #79                 // String dayofyear
     942: getstatic     #33                 // Field org/hibernate/type/StandardBasicTypes.INTEGER:Lorg/hibernate/type/IntegerType;
     945: invokespecial #34                 // Method org/hibernate/dialect/function/StandardSQLFunction."<init>":(Ljava/lang/String;Lorg/hibernate/type/Type;)V
     948: invokevirtual #27                 // Method registerFunction:(Ljava/lang/String;Lorg/hibernate/dialect/function/SQLFunction;)V
     951: aload_0
     952: ldc           #80                 // String days
     954: new           #29                 // class org/hibernate/dialect/function/StandardSQLFunction
     957: dup
     958: ldc           #80                 // String days
     960: getstatic     #81                 // Field org/hibernate/type/StandardBasicTypes.LONG:Lorg/hibernate/type/LongType;
     963: invokespecial #34                 // Method org/hibernate/dialect/function/StandardSQLFunction."<init>":(Ljava/lang/String;Lorg/hibernate/type/Type;)V
     966: invokevirtual #27                 // Method registerFunction:(Ljava/lang/String;Lorg/hibernate/dialect/function/SQLFunction;)V
     969: aload_0
     970: ldc           #82                 // String current_time
     972: new           #54                 // class org/hibernate/dialect/function/NoArgSQLFunction
     975: dup
     976: ldc           #83                 // String current time
     978: getstatic     #84                 // Field org/hibernate/type/StandardBasicTypes.TIME:Lorg/hibernate/type/TimeType;
     981: iconst_0
     982: invokespecial #74                 // Method org/hibernate/dialect/function/NoArgSQLFunction."<init>":(Ljava/lang/String;Lorg/hibernate/type/Type;Z)V
     985: invokevirtual #27                 // Method registerFunction:(Ljava/lang/String;Lorg/hibernate/dialect/function/SQLFunction;)V
     988: aload_0
     989: ldc           #12                 // String time
     991: new           #29                 // class org/hibernate/dialect/function/StandardSQLFunction
     994: dup
     995: ldc           #12                 // String time
     997: getstatic     #84                 // Field org/hibernate/type/StandardBasicTypes.TIME:Lorg/hibernate/type/TimeType;
    1000: invokespecial #34                 // Method org/hibernate/dialect/function/StandardSQLFunction."<init>":(Ljava/lang/String;Lorg/hibernate/type/Type;)V
    1003: invokevirtual #27                 // Method registerFunction:(Ljava/lang/String;Lorg/hibernate/dialect/function/SQLFunction;)V
    1006: aload_0
    1007: ldc           #85                 // String current_timestamp
    1009: new           #54                 // class org/hibernate/dialect/function/NoArgSQLFunction
    1012: dup
    1013: ldc           #86                 // String current timestamp
    1015: getstatic     #87                 // Field org/hibernate/type/StandardBasicTypes.TIMESTAMP:Lorg/hibernate/type/TimestampType;
    1018: iconst_0
    1019: invokespecial #74                 // Method org/hibernate/dialect/function/NoArgSQLFunction."<init>":(Ljava/lang/String;Lorg/hibernate/type/Type;Z)V
    1022: invokevirtual #27                 // Method registerFunction:(Ljava/lang/String;Lorg/hibernate/dialect/function/SQLFunction;)V
    1025: aload_0
    1026: ldc           #13                 // String timestamp
    1028: new           #29                 // class org/hibernate/dialect/function/StandardSQLFunction
    1031: dup
    1032: ldc           #13                 // String timestamp
    1034: getstatic     #87                 // Field org/hibernate/type/StandardBasicTypes.TIMESTAMP:Lorg/hibernate/type/TimestampType;
    1037: invokespecial #34                 // Method org/hibernate/dialect/function/StandardSQLFunction."<init>":(Ljava/lang/String;Lorg/hibernate/type/Type;)V
    1040: invokevirtual #27                 // Method registerFunction:(Ljava/lang/String;Lorg/hibernate/dialect/function/SQLFunction;)V
    1043: aload_0
    1044: ldc           #88                 // String timestamp_iso
    1046: new           #29                 // class org/hibernate/dialect/function/StandardSQLFunction
    1049: dup
    1050: ldc           #88                 // String timestamp_iso
    1052: getstatic     #87                 // Field org/hibernate/type/StandardBasicTypes.TIMESTAMP:Lorg/hibernate/type/TimestampType;
    1055: invokespecial #34                 // Method org/hibernate/dialect/function/StandardSQLFunction."<init>":(Ljava/lang/String;Lorg/hibernate/type/Type;)V
    1058: invokevirtual #27                 // Method registerFunction:(Ljava/lang/String;Lorg/hibernate/dialect/function/SQLFunction;)V
    1061: aload_0
    1062: ldc           #89                 // String week
    1064: new           #29                 // class org/hibernate/dialect/function/StandardSQLFunction
    1067: dup
    1068: ldc           #89                 // String week
    1070: getstatic     #33                 // Field org/hibernate/type/StandardBasicTypes.INTEGER:Lorg/hibernate/type/IntegerType;
    1073: invokespecial #34                 // Method org/hibernate/dialect/function/StandardSQLFunction."<init>":(Ljava/lang/String;Lorg/hibernate/type/Type;)V
    1076: invokevirtual #27                 // Method registerFunction:(Ljava/lang/String;Lorg/hibernate/dialect/function/SQLFunction;)V
    1079: aload_0
    1080: ldc           #90                 // String week_iso
    1082: new           #29                 // class org/hibernate/dialect/function/StandardSQLFunction
    1085: dup
    1086: ldc           #90                 // String week_iso
    1088: getstatic     #33                 // Field org/hibernate/type/StandardBasicTypes.INTEGER:Lorg/hibernate/type/IntegerType;
    1091: invokespecial #34                 // Method org/hibernate/dialect/function/StandardSQLFunction."<init>":(Ljava/lang/String;Lorg/hibernate/type/Type;)V
    1094: invokevirtual #27                 // Method registerFunction:(Ljava/lang/String;Lorg/hibernate/dialect/function/SQLFunction;)V
    1097: aload_0
    1098: ldc           #91                 // String year
    1100: new           #29                 // class org/hibernate/dialect/function/StandardSQLFunction
    1103: dup
    1104: ldc           #91                 // String year
    1106: getstatic     #33                 // Field org/hibernate/type/StandardBasicTypes.INTEGER:Lorg/hibernate/type/IntegerType;
    1109: invokespecial #34                 // Method org/hibernate/dialect/function/StandardSQLFunction."<init>":(Ljava/lang/String;Lorg/hibernate/type/Type;)V
    1112: invokevirtual #27                 // Method registerFunction:(Ljava/lang/String;Lorg/hibernate/dialect/function/SQLFunction;)V
    1115: aload_0
    1116: ldc           #10                 // String double
    1118: new           #29                 // class org/hibernate/dialect/function/StandardSQLFunction
    1121: dup
    1122: ldc           #10                 // String double
    1124: getstatic     #40                 // Field org/hibernate/type/StandardBasicTypes.DOUBLE:Lorg/hibernate/type/DoubleType;
    1127: invokespecial #34                 // Method org/hibernate/dialect/function/StandardSQLFunction."<init>":(Ljava/lang/String;Lorg/hibernate/type/Type;)V
    1130: invokevirtual #27                 // Method registerFunction:(Ljava/lang/String;Lorg/hibernate/dialect/function/SQLFunction;)V
    1133: aload_0
    1134: ldc           #92                 // String varchar
    1136: new           #29                 // class org/hibernate/dialect/function/StandardSQLFunction
    1139: dup
    1140: ldc           #92                 // String varchar
    1142: getstatic     #48                 // Field org/hibernate/type/StandardBasicTypes.STRING:Lorg/hibernate/type/StringType;
    1145: invokespecial #34                 // Method org/hibernate/dialect/function/StandardSQLFunction."<init>":(Ljava/lang/String;Lorg/hibernate/type/Type;)V
    1148: invokevirtual #27                 // Method registerFunction:(Ljava/lang/String;Lorg/hibernate/dialect/function/SQLFunction;)V
    1151: aload_0
    1152: ldc           #93                 // String real
    1154: new           #29                 // class org/hibernate/dialect/function/StandardSQLFunction
    1157: dup
    1158: ldc           #93                 // String real
    1160: getstatic     #94                 // Field org/hibernate/type/StandardBasicTypes.FLOAT:Lorg/hibernate/type/FloatType;
    1163: invokespecial #34                 // Method org/hibernate/dialect/function/StandardSQLFunction."<init>":(Ljava/lang/String;Lorg/hibernate/type/Type;)V
    1166: invokevirtual #27                 // Method registerFunction:(Ljava/lang/String;Lorg/hibernate/dialect/function/SQLFunction;)V
    1169: aload_0
    1170: ldc           #5                  // String bigint
    1172: new           #29                 // class org/hibernate/dialect/function/StandardSQLFunction
    1175: dup
    1176: ldc           #5                  // String bigint
    1178: getstatic     #81                 // Field org/hibernate/type/StandardBasicTypes.LONG:Lorg/hibernate/type/LongType;
    1181: invokespecial #34                 // Method org/hibernate/dialect/function/StandardSQLFunction."<init>":(Ljava/lang/String;Lorg/hibernate/type/Type;)V
    1184: invokevirtual #27                 // Method registerFunction:(Ljava/lang/String;Lorg/hibernate/dialect/function/SQLFunction;)V
    1187: aload_0
    1188: ldc           #95                 // String char
    1190: new           #29                 // class org/hibernate/dialect/function/StandardSQLFunction
    1193: dup
    1194: ldc           #95                 // String char
    1196: getstatic     #96                 // Field org/hibernate/type/StandardBasicTypes.CHARACTER:Lorg/hibernate/type/CharacterType;
    1199: invokespecial #34                 // Method org/hibernate/dialect/function/StandardSQLFunction."<init>":(Ljava/lang/String;Lorg/hibernate/type/Type;)V
    1202: invokevirtual #27                 // Method registerFunction:(Ljava/lang/String;Lorg/hibernate/dialect/function/SQLFunction;)V
    1205: aload_0
    1206: ldc           #6                  // String integer
    1208: new           #29                 // class org/hibernate/dialect/function/StandardSQLFunction
    1211: dup
    1212: ldc           #6                  // String integer
    1214: getstatic     #33                 // Field org/hibernate/type/StandardBasicTypes.INTEGER:Lorg/hibernate/type/IntegerType;
    1217: invokespecial #34                 // Method org/hibernate/dialect/function/StandardSQLFunction."<init>":(Ljava/lang/String;Lorg/hibernate/type/Type;)V
    1220: invokevirtual #27                 // Method registerFunction:(Ljava/lang/String;Lorg/hibernate/dialect/function/SQLFunction;)V
    1223: aload_0
    1224: ldc           #3                  // String smallint
    1226: new           #29                 // class org/hibernate/dialect/function/StandardSQLFunction
    1229: dup
    1230: ldc           #3                  // String smallint
    1232: getstatic     #97                 // Field org/hibernate/type/StandardBasicTypes.SHORT:Lorg/hibernate/type/ShortType;
    1235: invokespecial #34                 // Method org/hibernate/dialect/function/StandardSQLFunction."<init>":(Ljava/lang/String;Lorg/hibernate/type/Type;)V
    1238: invokevirtual #27                 // Method registerFunction:(Ljava/lang/String;Lorg/hibernate/dialect/function/SQLFunction;)V
    1241: aload_0
    1242: ldc           #98                 // String digits
    1244: new           #29                 // class org/hibernate/dialect/function/StandardSQLFunction
    1247: dup
    1248: ldc           #98                 // String digits
    1250: getstatic     #48                 // Field org/hibernate/type/StandardBasicTypes.STRING:Lorg/hibernate/type/StringType;
    1253: invokespecial #34                 // Method org/hibernate/dialect/function/StandardSQLFunction."<init>":(Ljava/lang/String;Lorg/hibernate/type/Type;)V
    1256: invokevirtual #27                 // Method registerFunction:(Ljava/lang/String;Lorg/hibernate/dialect/function/SQLFunction;)V
    1259: aload_0
    1260: ldc           #99                 // String chr
    1262: new           #29                 // class org/hibernate/dialect/function/StandardSQLFunction
    1265: dup
    1266: ldc           #99                 // String chr
    1268: getstatic     #96                 // Field org/hibernate/type/StandardBasicTypes.CHARACTER:Lorg/hibernate/type/CharacterType;
    1271: invokespecial #34                 // Method org/hibernate/dialect/function/StandardSQLFunction."<init>":(Ljava/lang/String;Lorg/hibernate/type/Type;)V
    1274: invokevirtual #27                 // Method registerFunction:(Ljava/lang/String;Lorg/hibernate/dialect/function/SQLFunction;)V
    1277: aload_0
    1278: ldc           #100                // String upper
    1280: new           #29                 // class org/hibernate/dialect/function/StandardSQLFunction
    1283: dup
    1284: ldc           #100                // String upper
    1286: invokespecial #30                 // Method org/hibernate/dialect/function/StandardSQLFunction."<init>":(Ljava/lang/String;)V
    1289: invokevirtual #27                 // Method registerFunction:(Ljava/lang/String;Lorg/hibernate/dialect/function/SQLFunction;)V
    1292: aload_0
    1293: ldc           #101                // String lower
    1295: new           #29                 // class org/hibernate/dialect/function/StandardSQLFunction
    1298: dup
    1299: ldc           #101                // String lower
    1301: invokespecial #30                 // Method org/hibernate/dialect/function/StandardSQLFunction."<init>":(Ljava/lang/String;)V
    1304: invokevirtual #27                 // Method registerFunction:(Ljava/lang/String;Lorg/hibernate/dialect/function/SQLFunction;)V
    1307: aload_0
    1308: ldc           #102                // String ucase
    1310: new           #29                 // class org/hibernate/dialect/function/StandardSQLFunction
    1313: dup
    1314: ldc           #102                // String ucase
    1316: invokespecial #30                 // Method org/hibernate/dialect/function/StandardSQLFunction."<init>":(Ljava/lang/String;)V
    1319: invokevirtual #27                 // Method registerFunction:(Ljava/lang/String;Lorg/hibernate/dialect/function/SQLFunction;)V
    1322: aload_0
    1323: ldc           #103                // String lcase
    1325: new           #29                 // class org/hibernate/dialect/function/StandardSQLFunction
    1328: dup
    1329: ldc           #103                // String lcase
    1331: invokespecial #30                 // Method org/hibernate/dialect/function/StandardSQLFunction."<init>":(Ljava/lang/String;)V
    1334: invokevirtual #27                 // Method registerFunction:(Ljava/lang/String;Lorg/hibernate/dialect/function/SQLFunction;)V
    1337: aload_0
    1338: ldc           #104                // String ltrim
    1340: new           #29                 // class org/hibernate/dialect/function/StandardSQLFunction
    1343: dup
    1344: ldc           #104                // String ltrim
    1346: invokespecial #30                 // Method org/hibernate/dialect/function/StandardSQLFunction."<init>":(Ljava/lang/String;)V
    1349: invokevirtual #27                 // Method registerFunction:(Ljava/lang/String;Lorg/hibernate/dialect/function/SQLFunction;)V
    1352: aload_0
    1353: ldc           #105                // String rtrim
    1355: new           #29                 // class org/hibernate/dialect/function/StandardSQLFunction
    1358: dup
    1359: ldc           #105                // String rtrim
    1361: invokespecial #30                 // Method org/hibernate/dialect/function/StandardSQLFunction."<init>":(Ljava/lang/String;)V
    1364: invokevirtual #27                 // Method registerFunction:(Ljava/lang/String;Lorg/hibernate/dialect/function/SQLFunction;)V
    1367: aload_0
    1368: ldc           #106                // String substr
    1370: new           #29                 // class org/hibernate/dialect/function/StandardSQLFunction
    1373: dup
    1374: ldc           #106                // String substr
    1376: getstatic     #48                 // Field org/hibernate/type/StandardBasicTypes.STRING:Lorg/hibernate/type/StringType;
    1379: invokespecial #34                 // Method org/hibernate/dialect/function/StandardSQLFunction."<init>":(Ljava/lang/String;Lorg/hibernate/type/Type;)V
    1382: invokevirtual #27                 // Method registerFunction:(Ljava/lang/String;Lorg/hibernate/dialect/function/SQLFunction;)V
    1385: aload_0
    1386: ldc           #107                // String posstr
    1388: new           #29                 // class org/hibernate/dialect/function/StandardSQLFunction
    1391: dup
    1392: ldc           #107                // String posstr
    1394: getstatic     #33                 // Field org/hibernate/type/StandardBasicTypes.INTEGER:Lorg/hibernate/type/IntegerType;
    1397: invokespecial #34                 // Method org/hibernate/dialect/function/StandardSQLFunction."<init>":(Ljava/lang/String;Lorg/hibernate/type/Type;)V
    1400: invokevirtual #27                 // Method registerFunction:(Ljava/lang/String;Lorg/hibernate/dialect/function/SQLFunction;)V
    1403: aload_0
    1404: ldc           #108                // String substring
    1406: new           #29                 // class org/hibernate/dialect/function/StandardSQLFunction
    1409: dup
    1410: ldc           #106                // String substr
    1412: getstatic     #48                 // Field org/hibernate/type/StandardBasicTypes.STRING:Lorg/hibernate/type/StringType;
    1415: invokespecial #34                 // Method org/hibernate/dialect/function/StandardSQLFunction."<init>":(Ljava/lang/String;Lorg/hibernate/type/Type;)V
    1418: invokevirtual #27                 // Method registerFunction:(Ljava/lang/String;Lorg/hibernate/dialect/function/SQLFunction;)V
    1421: aload_0
    1422: ldc           #109                // String bit_length
    1424: new           #110                // class org/hibernate/dialect/function/SQLFunctionTemplate
    1427: dup
    1428: getstatic     #33                 // Field org/hibernate/type/StandardBasicTypes.INTEGER:Lorg/hibernate/type/IntegerType;
    1431: ldc           #111                // String length(?1)*8
    1433: invokespecial #112                // Method org/hibernate/dialect/function/SQLFunctionTemplate."<init>":(Lorg/hibernate/type/Type;Ljava/lang/String;)V
    1436: invokevirtual #27                 // Method registerFunction:(Ljava/lang/String;Lorg/hibernate/dialect/function/SQLFunction;)V
    1439: aload_0
    1440: ldc           #113                // String trim
    1442: new           #110                // class org/hibernate/dialect/function/SQLFunctionTemplate
    1445: dup
    1446: getstatic     #48                 // Field org/hibernate/type/StandardBasicTypes.STRING:Lorg/hibernate/type/StringType;
    1449: ldc           #114                // String trim(?1 ?2 ?3 ?4)
    1451: invokespecial #112                // Method org/hibernate/dialect/function/SQLFunctionTemplate."<init>":(Lorg/hibernate/type/Type;Ljava/lang/String;)V
    1454: invokevirtual #27                 // Method registerFunction:(Ljava/lang/String;Lorg/hibernate/dialect/function/SQLFunction;)V
    1457: aload_0
    1458: ldc           #115                // String concat
    1460: new           #116                // class org/hibernate/dialect/function/VarArgsSQLFunction
    1463: dup
    1464: getstatic     #48                 // Field org/hibernate/type/StandardBasicTypes.STRING:Lorg/hibernate/type/StringType;
    1467: ldc           #117                // String
    1469: ldc           #118                // String ||
    1471: ldc           #117                // String
    1473: invokespecial #119                // Method org/hibernate/dialect/function/VarArgsSQLFunction."<init>":(Lorg/hibernate/type/Type;Ljava/lang/String;Ljava/lang/String;Ljava/lang/String;)V
    1476: invokevirtual #27                 // Method registerFunction:(Ljava/lang/String;Lorg/hibernate/dialect/function/SQLFunction;)V
    1479: aload_0
    1480: ldc           #120                // String str
    1482: new           #110                // class org/hibernate/dialect/function/SQLFunctionTemplate
    1485: dup
    1486: getstatic     #48                 // Field org/hibernate/type/StandardBasicTypes.STRING:Lorg/hibernate/type/StringType;
    1489: ldc           #121                // String rtrim(char(?1))
    1491: invokespecial #112                // Method org/hibernate/dialect/function/SQLFunctionTemplate."<init>":(Lorg/hibernate/type/Type;Ljava/lang/String;)V
    1494: invokevirtual #27                 // Method registerFunction:(Ljava/lang/String;Lorg/hibernate/dialect/function/SQLFunction;)V
    1497: aload_0
    1498: ldc           #122                // String current
    1500: invokevirtual #123                // Method registerKeyword:(Ljava/lang/String;)V
    1503: aload_0
    1504: ldc           #11                 // String date
    1506: invokevirtual #123                // Method registerKeyword:(Ljava/lang/String;)V
    1509: aload_0
    1510: ldc           #12                 // String time
    1512: invokevirtual #123                // Method registerKeyword:(Ljava/lang/String;)V
    1515: aload_0
    1516: ldc           #13                 // String timestamp
    1518: invokevirtual #123                // Method registerKeyword:(Ljava/lang/String;)V
    1521: aload_0
    1522: ldc           #124                // String fetch
    1524: invokevirtual #123                // Method registerKeyword:(Ljava/lang/String;)V
    1527: aload_0
    1528: ldc           #125                // String first
    1530: invokevirtual #123                // Method registerKeyword:(Ljava/lang/String;)V
    1533: aload_0
    1534: ldc           #126                // String rows
    1536: invokevirtual #123                // Method registerKeyword:(Ljava/lang/String;)V
    1539: aload_0
    1540: ldc           #127                // String only
    1542: invokevirtual #123                // Method registerKeyword:(Ljava/lang/String;)V
    1545: aload_0
    1546: invokevirtual #128                // Method getDefaultProperties:()Ljava/util/Properties;
    1549: ldc           #130                // String hibernate.jdbc.batch_size
    1551: ldc           #132                // String 0
    1553: invokevirtual #133                // Method java/util/Properties.setProperty:(Ljava/lang/String;Ljava/lang/String;)Ljava/lang/Object;
    1556: pop
    1557: aload_0
    1558: new           #134                // class org/hibernate/dialect/unique/DB2UniqueDelegate
    1561: dup
    1562: aload_0
    1563: invokespecial #135                // Method org/hibernate/dialect/unique/DB2UniqueDelegate."<init>":(Lorg/hibernate/dialect/Dialect;)V
    1566: putfield      #136                // Field uniqueDelegate:Lorg/hibernate/dialect/unique/UniqueDelegate;
    1569: return

  public java.lang.String getLowercaseFunction();
    Code:
       0: ldc           #103                // String lcase
       2: areturn

  public java.lang.String getAddColumnString();
    Code:
       0: ldc           #137                // String add column
       2: areturn

  public boolean dropConstraints();
    Code:
       0: iconst_0
       1: ireturn

  public java.lang.String getSequenceNextValString(java.lang.String);
    Code:
       0: new           #138                // class java/lang/StringBuilder
       3: dup
       4: invokespecial #139                // Method java/lang/StringBuilder."<init>":()V
       7: ldc           #140                // String values nextval for
       9: invokevirtual #141                // Method java/lang/StringBuilder.append:(Ljava/lang/String;)Ljava/lang/StringBuilder;
      12: aload_1
      13: invokevirtual #141                // Method java/lang/StringBuilder.append:(Ljava/lang/String;)Ljava/lang/StringBuilder;
      16: invokevirtual #142                // Method java/lang/StringBuilder.toString:()Ljava/lang/String;
      19: areturn

  public java.lang.String getSelectSequenceNextValString(java.lang.String) throws org.hibernate.MappingException;
    Code:
       0: new           #138                // class java/lang/StringBuilder
       3: dup
       4: invokespecial #139                // Method java/lang/StringBuilder."<init>":()V
       7: ldc           #143                // String next value for
       9: invokevirtual #141                // Method java/lang/StringBuilder.append:(Ljava/lang/String;)Ljava/lang/StringBuilder;
      12: aload_1
      13: invokevirtual #141                // Method java/lang/StringBuilder.append:(Ljava/lang/String;)Ljava/lang/StringBuilder;
      16: invokevirtual #142                // Method java/lang/StringBuilder.toString:()Ljava/lang/String;
      19: areturn

  public java.lang.String getCreateSequenceString(java.lang.String);
    Code:
       0: new           #138                // class java/lang/StringBuilder
       3: dup
       4: invokespecial #139                // Method java/lang/StringBuilder."<init>":()V
       7: ldc           #144                // String create sequence
       9: invokevirtual #141                // Method java/lang/StringBuilder.append:(Ljava/lang/String;)Ljava/lang/StringBuilder;
      12: aload_1
      13: invokevirtual #141                // Method java/lang/StringBuilder.append:(Ljava/lang/String;)Ljava/lang/StringBuilder;
      16: invokevirtual #142                // Method java/lang/StringBuilder.toString:()Ljava/lang/String;
      19: areturn

  public java.lang.String getDropSequenceString(java.lang.String);
    Code:
       0: new           #138                // class java/lang/StringBuilder
       3: dup
       4: invokespecial #139                // Method java/lang/StringBuilder."<init>":()V
       7: ldc           #145                // String drop sequence
       9: invokevirtual #141                // Method java/lang/StringBuilder.append:(Ljava/lang/String;)Ljava/lang/StringBuilder;
      12: aload_1
      13: invokevirtual #141                // Method java/lang/StringBuilder.append:(Ljava/lang/String;)Ljava/lang/StringBuilder;
      16: ldc           #146                // String  restrict
      18: invokevirtual #141                // Method java/lang/StringBuilder.append:(Ljava/lang/String;)Ljava/lang/StringBuilder;
      21: invokevirtual #142                // Method java/lang/StringBuilder.toString:()Ljava/lang/String;
      24: areturn

  public boolean supportsSequences();
    Code:
       0: iconst_1
       1: ireturn

  public boolean supportsPooledSequences();
    Code:
       0: iconst_1
       1: ireturn

  public java.lang.String getQuerySequencesString();
    Code:
       0: ldc           #147                // String select seqname from sysibm.syssequences
       2: areturn

  public boolean supportsLimit();
    Code:
       0: iconst_1
       1: ireturn

  public boolean supportsVariableLimit();
    Code:
       0: iconst_0
       1: ireturn

  public java.lang.String getLimitString(java.lang.String, int, int);
    Code:
       0: iload_2
       1: ifne          33
       4: new           #138                // class java/lang/StringBuilder
       7: dup
       8: invokespecial #139                // Method java/lang/StringBuilder."<init>":()V
      11: aload_1
      12: invokevirtual #141                // Method java/lang/StringBuilder.append:(Ljava/lang/String;)Ljava/lang/StringBuilder;
      15: ldc           #148                // String  fetch first
      17: invokevirtual #141                // Method java/lang/StringBuilder.append:(Ljava/lang/String;)Ljava/lang/StringBuilder;
      20: iload_3
      21: invokevirtual #149                // Method java/lang/StringBuilder.append:(I)Ljava/lang/StringBuilder;
      24: ldc           #150                // String  rows only
      26: invokevirtual #141                // Method java/lang/StringBuilder.append:(Ljava/lang/String;)Ljava/lang/StringBuilder;
      29: invokevirtual #142                // Method java/lang/StringBuilder.toString:()Ljava/lang/String;
      32: areturn
      33: new           #138                // class java/lang/StringBuilder
      36: dup
      37: invokespecial #139                // Method java/lang/StringBuilder."<init>":()V
      40: ldc           #151                // String select * from ( select inner2_.*, rownumber() over(order by order of inner2_) as rownumber_ from (
      42: invokevirtual #141                // Method java/lang/StringBuilder.append:(Ljava/lang/String;)Ljava/lang/StringBuilder;
      45: aload_1
      46: invokevirtual #141                // Method java/lang/StringBuilder.append:(Ljava/lang/String;)Ljava/lang/StringBuilder;
      49: ldc           #148                // String  fetch first
      51: invokevirtual #141                // Method java/lang/StringBuilder.append:(Ljava/lang/String;)Ljava/lang/StringBuilder;
      54: iload_3
      55: invokevirtual #149                // Method java/lang/StringBuilder.append:(I)Ljava/lang/StringBuilder;
      58: ldc           #152                // String  rows only ) as inner2_ ) as inner1_ where rownumber_ >
      60: invokevirtual #141                // Method java/lang/StringBuilder.append:(Ljava/lang/String;)Ljava/lang/StringBuilder;
      63: iload_2
      64: invokevirtual #149                // Method java/lang/StringBuilder.append:(I)Ljava/lang/StringBuilder;
      67: ldc           #153                // String  order by rownumber_
      69: invokevirtual #141                // Method java/lang/StringBuilder.append:(Ljava/lang/String;)Ljava/lang/StringBuilder;
      72: invokevirtual #142                // Method java/lang/StringBuilder.toString:()Ljava/lang/String;
      75: areturn

  public int convertToFirstRowValue(int);
    Code:
       0: iload_1
       1: ireturn

  public java.lang.String getForUpdateString();
    Code:
       0: ldc           #154                // String  for read only with rs use and keep update locks
       2: areturn

  public boolean useMaxForLimit();
    Code:
       0: iconst_1
       1: ireturn

  public boolean supportsOuterJoinForUpdate();
    Code:
       0: iconst_0
       1: ireturn

  public boolean supportsExistsInSelect();
    Code:
       0: iconst_0
       1: ireturn

  public boolean supportsLockTimeouts();
    Code:
       0: iconst_0
       1: ireturn

  public java.lang.String getSelectClauseNullString(int);
    Code:
       0: iload_1
       1: lookupswitch  { // 5
                     1: 52
                    12: 52
                    91: 58
                    92: 70
                    93: 64
               default: 76
          }
      52: ldc           #155                // String \'x\'
      54: astore_2
      55: goto          79
      58: ldc           #156                // String \'2000-1-1\'
      60: astore_2
      61: goto          79
      64: ldc           #157                // String \'2000-1-1 00:00:00\'
      66: astore_2
      67: goto          79
      70: ldc           #158                // String \'00:00:00\'
      72: astore_2
      73: goto          79
      76: ldc           #132                // String 0
      78: astore_2
      79: new           #138                // class java/lang/StringBuilder
      82: dup
      83: invokespecial #139                // Method java/lang/StringBuilder."<init>":()V
      86: ldc           #159                // String nullif(
      88: invokevirtual #141                // Method java/lang/StringBuilder.append:(Ljava/lang/String;)Ljava/lang/StringBuilder;
      91: aload_2
      92: invokevirtual #141                // Method java/lang/StringBuilder.append:(Ljava/lang/String;)Ljava/lang/StringBuilder;
      95: ldc           #160                // String ,
      97: invokevirtual #141                // Method java/lang/StringBuilder.append:(Ljava/lang/String;)Ljava/lang/StringBuilder;
     100: aload_2
     101: invokevirtual #141                // Method java/lang/StringBuilder.append:(Ljava/lang/String;)Ljava/lang/StringBuilder;
     104: bipush        41
     106: invokevirtual #161                // Method java/lang/StringBuilder.append:(C)Ljava/lang/StringBuilder;
     109: invokevirtual #142                // Method java/lang/StringBuilder.toString:()Ljava/lang/String;
     112: areturn

  public boolean supportsUnionAll();
    Code:
       0: iconst_1
       1: ireturn

  public int registerResultSetOutParameter(java.sql.CallableStatement, int) throws java.sql.SQLException;
    Code:
       0: iload_2
       1: ireturn

  public java.sql.ResultSet getResultSet(java.sql.CallableStatement) throws java.sql.SQLException;
    Code:
       0: aload_1
       1: invokeinterface #162,  1          // InterfaceMethod java/sql/CallableStatement.execute:()Z
       6: istore_2
       7: iload_2
       8: ifne          31
      11: aload_1
      12: invokeinterface #163,  1          // InterfaceMethod java/sql/CallableStatement.getUpdateCount:()I
      17: iconst_m1
      18: if_icmpeq     31
      21: aload_1
      22: invokeinterface #164,  1          // InterfaceMethod java/sql/CallableStatement.getMoreResults:()Z
      27: istore_2
      28: goto          7
      31: aload_1
      32: invokeinterface #165,  1          // InterfaceMethod java/sql/CallableStatement.getResultSet:()Ljava/sql/ResultSet;
      37: areturn

  public boolean supportsCommentOn();
    Code:
       0: iconst_1
       1: ireturn

  public org.hibernate.hql.spi.id.MultiTableBulkIdStrategy getDefaultMultiTableBulkIdStrategy();
    Code:
       0: new           #166                // class org/hibernate/hql/spi/id/local/LocalTemporaryTableBulkIdStrategy
       3: dup
       4: new           #167                // class org/hibernate/dialect/DB2Dialect$2
       7: dup
       8: aload_0
       9: invokespecial #168                // Method org/hibernate/dialect/DB2Dialect$2."<init>":(Lorg/hibernate/dialect/DB2Dialect;)V
      12: getstatic     #169                // Field org/hibernate/hql/spi/id/local/AfterUseAction.DROP:Lorg/hibernate/hql/spi/id/local/AfterUseAction;
      15: aconst_null
      16: invokespecial #170                // Method org/hibernate/hql/spi/id/local/LocalTemporaryTableBulkIdStrategy."<init>":(Lorg/hibernate/hql/spi/id/IdTableSupport;Lorg/hibernate/hql/spi/id/local/AfterUseAction;Lorg/hibernate/boot/TempTableDdlTransactionHandling;)V
      19: areturn

  public boolean supportsCurrentTimestampSelection();
    Code:
       0: iconst_1
       1: ireturn

  public java.lang.String getCurrentTimestampSelectString();
    Code:
       0: ldc           #171                // String values current timestamp
       2: areturn

  public boolean isCurrentTimestampSelectStringCallable();
    Code:
       0: iconst_0
       1: ireturn

  public boolean supportsParametersInInsertSelect();
    Code:
       0: iconst_1
       1: ireturn

  public boolean requiresCastingOfParametersInSelectClause();
    Code:
       0: iconst_1
       1: ireturn

  public boolean supportsResultSetPositionQueryMethodsOnForwardOnlyCursor();
    Code:
       0: iconst_0
       1: ireturn

  public java.lang.String getCrossJoinSeparator();
    Code:
       0: ldc           #160                // String ,
       2: areturn

  public boolean supportsEmptyInList();
    Code:
       0: iconst_0
       1: ireturn

  public boolean supportsLobValueChangePropogation();
    Code:
       0: iconst_0
       1: ireturn

  public boolean doesReadCommittedCauseWritersToBlockReaders();
    Code:
       0: iconst_1
       1: ireturn

  public boolean supportsTupleDistinctCounts();
    Code:
       0: iconst_0
       1: ireturn

  protected org.hibernate.type.descriptor.sql.SqlTypeDescriptor getSqlTypeDescriptorOverride(int);
    Code:
       0: iload_1
       1: bipush        16
       3: if_icmpne     10
       6: getstatic     #172                // Field org/hibernate/type/descriptor/sql/SmallIntTypeDescriptor.INSTANCE:Lorg/hibernate/type/descriptor/sql/SmallIntTypeDescriptor;
       9: areturn
      10: iload_1
      11: iconst_2
      12: if_icmpne     19
      15: getstatic     #173                // Field org/hibernate/type/descriptor/sql/DecimalTypeDescriptor.INSTANCE:Lorg/hibernate/type/descriptor/sql/DecimalTypeDescriptor;
      18: areturn
      19: aload_0
      20: iload_1
      21: invokespecial #174                // Method org/hibernate/dialect/Dialect.getSqlTypeDescriptorOverride:(I)Lorg/hibernate/type/descriptor/sql/SqlTypeDescriptor;
      24: areturn

  public org.hibernate.exception.spi.SQLExceptionConversionDelegate buildSQLExceptionConversionDelegate();
    Code:
       0: new           #175                // class org/hibernate/dialect/DB2Dialect$3
       3: dup
       4: aload_0
       5: invokespecial #176                // Method org/hibernate/dialect/DB2Dialect$3."<init>":(Lorg/hibernate/dialect/DB2Dialect;)V
       8: areturn

  public org.hibernate.dialect.unique.UniqueDelegate getUniqueDelegate();
    Code:
       0: aload_0
       1: getfield      #136                // Field uniqueDelegate:Lorg/hibernate/dialect/unique/UniqueDelegate;
       4: areturn

  public java.lang.String getNotExpression(java.lang.String);
    Code:
       0: new           #138                // class java/lang/StringBuilder
       3: dup
       4: invokespecial #139                // Method java/lang/StringBuilder."<init>":()V
       7: ldc           #177                // String not (
       9: invokevirtual #141                // Method java/lang/StringBuilder.append:(Ljava/lang/String;)Ljava/lang/StringBuilder;
      12: aload_1
      13: invokevirtual #141                // Method java/lang/StringBuilder.append:(Ljava/lang/String;)Ljava/lang/StringBuilder;
      16: ldc           #178                // String )
      18: invokevirtual #141                // Method java/lang/StringBuilder.append:(Ljava/lang/String;)Ljava/lang/StringBuilder;
      21: invokevirtual #142                // Method java/lang/StringBuilder.toString:()Ljava/lang/String;
      24: areturn

  public org.hibernate.dialect.pagination.LimitHandler getLimitHandler();
    Code:
       0: getstatic     #179                // Field LIMIT_HANDLER:Lorg/hibernate/dialect/pagination/AbstractLimitHandler;
       3: areturn

  public java.lang.String renderOrderByElement(java.lang.String, java.lang.String, java.lang.String, org.hibernate.NullPrecedence);
    Code:
       0: aload         4
       2: ifnull        13
       5: aload         4
       7: getstatic     #180                // Field org/hibernate/NullPrecedence.NONE:Lorg/hibernate/NullPrecedence;
      10: if_acmpne     24
      13: aload_0
      14: aload_1
      15: aload_2
      16: aload_3
      17: getstatic     #180                // Field org/hibernate/NullPrecedence.NONE:Lorg/hibernate/NullPrecedence;
      20: invokespecial #181                // Method org/hibernate/dialect/Dialect.renderOrderByElement:(Ljava/lang/String;Ljava/lang/String;Ljava/lang/String;Lorg/hibernate/NullPrecedence;)Ljava/lang/String;
      23: areturn
      24: aload         4
      26: getstatic     #182                // Field org/hibernate/NullPrecedence.FIRST:Lorg/hibernate/NullPrecedence;
      29: if_acmpne     41
      32: ldc           #183                // String desc
      34: aload_3
      35: invokevirtual #184                // Method java/lang/String.equalsIgnoreCase:(Ljava/lang/String;)Z
      38: ifne          58
      41: aload         4
      43: getstatic     #185                // Field org/hibernate/NullPrecedence.LAST:Lorg/hibernate/NullPrecedence;
      46: if_acmpne     69
      49: ldc           #186                // String asc
      51: aload_3
      52: invokevirtual #184                // Method java/lang/String.equalsIgnoreCase:(Ljava/lang/String;)Z
      55: ifeq          69
      58: aload_0
      59: aload_1
      60: aload_2
      61: aload_3
      62: getstatic     #180                // Field org/hibernate/NullPrecedence.NONE:Lorg/hibernate/NullPrecedence;
      65: invokespecial #181                // Method org/hibernate/dialect/Dialect.renderOrderByElement:(Ljava/lang/String;Ljava/lang/String;Ljava/lang/String;Lorg/hibernate/NullPrecedence;)Ljava/lang/String;
      68: areturn
      69: getstatic     #187                // Field java/util/Locale.ENGLISH:Ljava/util/Locale;
      72: ldc           #188                // String case when %s is null then %s else %s end, %s %s
      74: iconst_5
      75: anewarray     #189                // class java/lang/Object
      78: dup
      79: iconst_0
      80: aload_1
      81: aastore
      82: dup
      83: iconst_1
      84: aload         4
      86: getstatic     #182                // Field org/hibernate/NullPrecedence.FIRST:Lorg/hibernate/NullPrecedence;
      89: if_acmpne     97
      92: ldc           #132                // String 0
      94: goto          99
      97: ldc           #190                // String 1
      99: aastore
     100: dup
     101: iconst_2
     102: aload         4
     104: getstatic     #182                // Field org/hibernate/NullPrecedence.FIRST:Lorg/hibernate/NullPrecedence;
     107: if_acmpne     115
     110: ldc           #190                // String 1
     112: goto          117
     115: ldc           #132                // String 0
     117: aastore
     118: dup
     119: iconst_3
     120: aload_1
     121: aastore
     122: dup
     123: iconst_4
     124: aload_3
     125: aastore
     126: invokestatic  #191                // Method java/lang/String.format:(Ljava/util/Locale;Ljava/lang/String;[Ljava/lang/Object;)Ljava/lang/String;
     129: areturn

  public org.hibernate.dialect.identity.IdentityColumnSupport getIdentityColumnSupport();
    Code:
       0: new           #192                // class org/hibernate/dialect/identity/DB2IdentityColumnSupport
       3: dup
       4: invokespecial #193                // Method org/hibernate/dialect/identity/DB2IdentityColumnSupport."<init>":()V
       7: areturn

  public boolean supportsPartitionBy();
    Code:
       0: iconst_1
       1: ireturn

  static {};
    Code:
       0: new           #194                // class org/hibernate/dialect/DB2Dialect$1
       3: dup
       4: invokespecial #195                // Method org/hibernate/dialect/DB2Dialect$1."<init>":()V
       7: putstatic     #179                // Field LIMIT_HANDLER:Lorg/hibernate/dialect/pagination/AbstractLimitHandler;
      10: return
}
