Compiled from "SAPDBDialect.java"
public class org.hibernate.dialect.SAPDBDialect extends org.hibernate.dialect.Dialect {
  public org.hibernate.dialect.SAPDBDialect();
    Code:
       0: aload_0
       1: invokespecial #1                  // Method org/hibernate/dialect/Dialect."<init>":()V
       4: aload_0
       5: bipush        -7
       7: ldc           #3                  // String boolean
       9: invokevirtual #4                  // Method registerColumnType:(ILjava/lang/String;)V
      12: aload_0
      13: bipush        -5
      15: ldc           #5                  // String fixed(19,0)
      17: invokevirtual #4                  // Method registerColumnType:(ILjava/lang/String;)V
      20: aload_0
      21: iconst_5
      22: ldc           #6                  // String smallint
      24: invokevirtual #4                  // Method registerColumnType:(ILjava/lang/String;)V
      27: aload_0
      28: bipush        -6
      30: ldc           #7                  // String fixed(3,0)
      32: invokevirtual #4                  // Method registerColumnType:(ILjava/lang/String;)V
      35: aload_0
      36: iconst_4
      37: ldc           #8                  // String int
      39: invokevirtual #4                  // Method registerColumnType:(ILjava/lang/String;)V
      42: aload_0
      43: iconst_1
      44: ldc           #9                  // String char(1)
      46: invokevirtual #4                  // Method registerColumnType:(ILjava/lang/String;)V
      49: aload_0
      50: bipush        12
      52: ldc           #10                 // String varchar($l)
      54: invokevirtual #4                  // Method registerColumnType:(ILjava/lang/String;)V
      57: aload_0
      58: bipush        6
      60: ldc           #11                 // String float
      62: invokevirtual #4                  // Method registerColumnType:(ILjava/lang/String;)V
      65: aload_0
      66: bipush        8
      68: ldc           #12                 // String double precision
      70: invokevirtual #4                  // Method registerColumnType:(ILjava/lang/String;)V
      73: aload_0
      74: bipush        91
      76: ldc           #13                 // String date
      78: invokevirtual #4                  // Method registerColumnType:(ILjava/lang/String;)V
      81: aload_0
      82: bipush        92
      84: ldc           #14                 // String time
      86: invokevirtual #4                  // Method registerColumnType:(ILjava/lang/String;)V
      89: aload_0
      90: bipush        93
      92: ldc           #15                 // String timestamp
      94: invokevirtual #4                  // Method registerColumnType:(ILjava/lang/String;)V
      97: aload_0
      98: bipush        -3
     100: ldc           #16                 // String long byte
     102: invokevirtual #4                  // Method registerColumnType:(ILjava/lang/String;)V
     105: aload_0
     106: iconst_2
     107: ldc           #17                 // String fixed($p,$s)
     109: invokevirtual #4                  // Method registerColumnType:(ILjava/lang/String;)V
     112: aload_0
     113: sipush        2005
     116: ldc           #18                 // String long varchar
     118: invokevirtual #4                  // Method registerColumnType:(ILjava/lang/String;)V
     121: aload_0
     122: sipush        2004
     125: ldc           #16                 // String long byte
     127: invokevirtual #4                  // Method registerColumnType:(ILjava/lang/String;)V
     130: aload_0
     131: ldc           #19                 // String abs
     133: new           #20                 // class org/hibernate/dialect/function/StandardSQLFunction
     136: dup
     137: ldc           #19                 // String abs
     139: invokespecial #21                 // Method org/hibernate/dialect/function/StandardSQLFunction."<init>":(Ljava/lang/String;)V
     142: invokevirtual #22                 // Method registerFunction:(Ljava/lang/String;Lorg/hibernate/dialect/function/SQLFunction;)V
     145: aload_0
     146: ldc           #23                 // String sign
     148: new           #20                 // class org/hibernate/dialect/function/StandardSQLFunction
     151: dup
     152: ldc           #23                 // String sign
     154: getstatic     #24                 // Field org/hibernate/type/StandardBasicTypes.INTEGER:Lorg/hibernate/type/IntegerType;
     157: invokespecial #25                 // Method org/hibernate/dialect/function/StandardSQLFunction."<init>":(Ljava/lang/String;Lorg/hibernate/type/Type;)V
     160: invokevirtual #22                 // Method registerFunction:(Ljava/lang/String;Lorg/hibernate/dialect/function/SQLFunction;)V
     163: aload_0
     164: ldc           #26                 // String exp
     166: new           #20                 // class org/hibernate/dialect/function/StandardSQLFunction
     169: dup
     170: ldc           #26                 // String exp
     172: getstatic     #27                 // Field org/hibernate/type/StandardBasicTypes.DOUBLE:Lorg/hibernate/type/DoubleType;
     175: invokespecial #25                 // Method org/hibernate/dialect/function/StandardSQLFunction."<init>":(Ljava/lang/String;Lorg/hibernate/type/Type;)V
     178: invokevirtual #22                 // Method registerFunction:(Ljava/lang/String;Lorg/hibernate/dialect/function/SQLFunction;)V
     181: aload_0
     182: ldc           #28                 // String ln
     184: new           #20                 // class org/hibernate/dialect/function/StandardSQLFunction
     187: dup
     188: ldc           #28                 // String ln
     190: getstatic     #27                 // Field org/hibernate/type/StandardBasicTypes.DOUBLE:Lorg/hibernate/type/DoubleType;
     193: invokespecial #25                 // Method org/hibernate/dialect/function/StandardSQLFunction."<init>":(Ljava/lang/String;Lorg/hibernate/type/Type;)V
     196: invokevirtual #22                 // Method registerFunction:(Ljava/lang/String;Lorg/hibernate/dialect/function/SQLFunction;)V
     199: aload_0
     200: ldc           #29                 // String log
     202: new           #20                 // class org/hibernate/dialect/function/StandardSQLFunction
     205: dup
     206: ldc           #28                 // String ln
     208: getstatic     #27                 // Field org/hibernate/type/StandardBasicTypes.DOUBLE:Lorg/hibernate/type/DoubleType;
     211: invokespecial #25                 // Method org/hibernate/dialect/function/StandardSQLFunction."<init>":(Ljava/lang/String;Lorg/hibernate/type/Type;)V
     214: invokevirtual #22                 // Method registerFunction:(Ljava/lang/String;Lorg/hibernate/dialect/function/SQLFunction;)V
     217: aload_0
     218: ldc           #30                 // String pi
     220: new           #31                 // class org/hibernate/dialect/function/NoArgSQLFunction
     223: dup
     224: ldc           #30                 // String pi
     226: getstatic     #27                 // Field org/hibernate/type/StandardBasicTypes.DOUBLE:Lorg/hibernate/type/DoubleType;
     229: invokespecial #32                 // Method org/hibernate/dialect/function/NoArgSQLFunction."<init>":(Ljava/lang/String;Lorg/hibernate/type/Type;)V
     232: invokevirtual #22                 // Method registerFunction:(Ljava/lang/String;Lorg/hibernate/dialect/function/SQLFunction;)V
     235: aload_0
     236: ldc           #33                 // String power
     238: new           #20                 // class org/hibernate/dialect/function/StandardSQLFunction
     241: dup
     242: ldc           #33                 // String power
     244: invokespecial #21                 // Method org/hibernate/dialect/function/StandardSQLFunction."<init>":(Ljava/lang/String;)V
     247: invokevirtual #22                 // Method registerFunction:(Ljava/lang/String;Lorg/hibernate/dialect/function/SQLFunction;)V
     250: aload_0
     251: ldc           #34                 // String acos
     253: new           #20                 // class org/hibernate/dialect/function/StandardSQLFunction
     256: dup
     257: ldc           #34                 // String acos
     259: getstatic     #27                 // Field org/hibernate/type/StandardBasicTypes.DOUBLE:Lorg/hibernate/type/DoubleType;
     262: invokespecial #25                 // Method org/hibernate/dialect/function/StandardSQLFunction."<init>":(Ljava/lang/String;Lorg/hibernate/type/Type;)V
     265: invokevirtual #22                 // Method registerFunction:(Ljava/lang/String;Lorg/hibernate/dialect/function/SQLFunction;)V
     268: aload_0
     269: ldc           #35                 // String asin
     271: new           #20                 // class org/hibernate/dialect/function/StandardSQLFunction
     274: dup
     275: ldc           #35                 // String asin
     277: getstatic     #27                 // Field org/hibernate/type/StandardBasicTypes.DOUBLE:Lorg/hibernate/type/DoubleType;
     280: invokespecial #25                 // Method org/hibernate/dialect/function/StandardSQLFunction."<init>":(Ljava/lang/String;Lorg/hibernate/type/Type;)V
     283: invokevirtual #22                 // Method registerFunction:(Ljava/lang/String;Lorg/hibernate/dialect/function/SQLFunction;)V
     286: aload_0
     287: ldc           #36                 // String atan
     289: new           #20                 // class org/hibernate/dialect/function/StandardSQLFunction
     292: dup
     293: ldc           #36                 // String atan
     295: getstatic     #27                 // Field org/hibernate/type/StandardBasicTypes.DOUBLE:Lorg/hibernate/type/DoubleType;
     298: invokespecial #25                 // Method org/hibernate/dialect/function/StandardSQLFunction."<init>":(Ljava/lang/String;Lorg/hibernate/type/Type;)V
     301: invokevirtual #22                 // Method registerFunction:(Ljava/lang/String;Lorg/hibernate/dialect/function/SQLFunction;)V
     304: aload_0
     305: ldc           #37                 // String cos
     307: new           #20                 // class org/hibernate/dialect/function/StandardSQLFunction
     310: dup
     311: ldc           #37                 // String cos
     313: getstatic     #27                 // Field org/hibernate/type/StandardBasicTypes.DOUBLE:Lorg/hibernate/type/DoubleType;
     316: invokespecial #25                 // Method org/hibernate/dialect/function/StandardSQLFunction."<init>":(Ljava/lang/String;Lorg/hibernate/type/Type;)V
     319: invokevirtual #22                 // Method registerFunction:(Ljava/lang/String;Lorg/hibernate/dialect/function/SQLFunction;)V
     322: aload_0
     323: ldc           #38                 // String cosh
     325: new           #20                 // class org/hibernate/dialect/function/StandardSQLFunction
     328: dup
     329: ldc           #38                 // String cosh
     331: getstatic     #27                 // Field org/hibernate/type/StandardBasicTypes.DOUBLE:Lorg/hibernate/type/DoubleType;
     334: invokespecial #25                 // Method org/hibernate/dialect/function/StandardSQLFunction."<init>":(Ljava/lang/String;Lorg/hibernate/type/Type;)V
     337: invokevirtual #22                 // Method registerFunction:(Ljava/lang/String;Lorg/hibernate/dialect/function/SQLFunction;)V
     340: aload_0
     341: ldc           #39                 // String cot
     343: new           #20                 // class org/hibernate/dialect/function/StandardSQLFunction
     346: dup
     347: ldc           #37                 // String cos
     349: getstatic     #27                 // Field org/hibernate/type/StandardBasicTypes.DOUBLE:Lorg/hibernate/type/DoubleType;
     352: invokespecial #25                 // Method org/hibernate/dialect/function/StandardSQLFunction."<init>":(Ljava/lang/String;Lorg/hibernate/type/Type;)V
     355: invokevirtual #22                 // Method registerFunction:(Ljava/lang/String;Lorg/hibernate/dialect/function/SQLFunction;)V
     358: aload_0
     359: ldc           #40                 // String sin
     361: new           #20                 // class org/hibernate/dialect/function/StandardSQLFunction
     364: dup
     365: ldc           #40                 // String sin
     367: getstatic     #27                 // Field org/hibernate/type/StandardBasicTypes.DOUBLE:Lorg/hibernate/type/DoubleType;
     370: invokespecial #25                 // Method org/hibernate/dialect/function/StandardSQLFunction."<init>":(Ljava/lang/String;Lorg/hibernate/type/Type;)V
     373: invokevirtual #22                 // Method registerFunction:(Ljava/lang/String;Lorg/hibernate/dialect/function/SQLFunction;)V
     376: aload_0
     377: ldc           #41                 // String sinh
     379: new           #20                 // class org/hibernate/dialect/function/StandardSQLFunction
     382: dup
     383: ldc           #41                 // String sinh
     385: getstatic     #27                 // Field org/hibernate/type/StandardBasicTypes.DOUBLE:Lorg/hibernate/type/DoubleType;
     388: invokespecial #25                 // Method org/hibernate/dialect/function/StandardSQLFunction."<init>":(Ljava/lang/String;Lorg/hibernate/type/Type;)V
     391: invokevirtual #22                 // Method registerFunction:(Ljava/lang/String;Lorg/hibernate/dialect/function/SQLFunction;)V
     394: aload_0
     395: ldc           #42                 // String tan
     397: new           #20                 // class org/hibernate/dialect/function/StandardSQLFunction
     400: dup
     401: ldc           #42                 // String tan
     403: getstatic     #27                 // Field org/hibernate/type/StandardBasicTypes.DOUBLE:Lorg/hibernate/type/DoubleType;
     406: invokespecial #25                 // Method org/hibernate/dialect/function/StandardSQLFunction."<init>":(Ljava/lang/String;Lorg/hibernate/type/Type;)V
     409: invokevirtual #22                 // Method registerFunction:(Ljava/lang/String;Lorg/hibernate/dialect/function/SQLFunction;)V
     412: aload_0
     413: ldc           #43                 // String tanh
     415: new           #20                 // class org/hibernate/dialect/function/StandardSQLFunction
     418: dup
     419: ldc           #43                 // String tanh
     421: getstatic     #27                 // Field org/hibernate/type/StandardBasicTypes.DOUBLE:Lorg/hibernate/type/DoubleType;
     424: invokespecial #25                 // Method org/hibernate/dialect/function/StandardSQLFunction."<init>":(Ljava/lang/String;Lorg/hibernate/type/Type;)V
     427: invokevirtual #22                 // Method registerFunction:(Ljava/lang/String;Lorg/hibernate/dialect/function/SQLFunction;)V
     430: aload_0
     431: ldc           #44                 // String radians
     433: new           #20                 // class org/hibernate/dialect/function/StandardSQLFunction
     436: dup
     437: ldc           #44                 // String radians
     439: getstatic     #27                 // Field org/hibernate/type/StandardBasicTypes.DOUBLE:Lorg/hibernate/type/DoubleType;
     442: invokespecial #25                 // Method org/hibernate/dialect/function/StandardSQLFunction."<init>":(Ljava/lang/String;Lorg/hibernate/type/Type;)V
     445: invokevirtual #22                 // Method registerFunction:(Ljava/lang/String;Lorg/hibernate/dialect/function/SQLFunction;)V
     448: aload_0
     449: ldc           #45                 // String degrees
     451: new           #20                 // class org/hibernate/dialect/function/StandardSQLFunction
     454: dup
     455: ldc           #45                 // String degrees
     457: getstatic     #27                 // Field org/hibernate/type/StandardBasicTypes.DOUBLE:Lorg/hibernate/type/DoubleType;
     460: invokespecial #25                 // Method org/hibernate/dialect/function/StandardSQLFunction."<init>":(Ljava/lang/String;Lorg/hibernate/type/Type;)V
     463: invokevirtual #22                 // Method registerFunction:(Ljava/lang/String;Lorg/hibernate/dialect/function/SQLFunction;)V
     466: aload_0
     467: ldc           #46                 // String atan2
     469: new           #20                 // class org/hibernate/dialect/function/StandardSQLFunction
     472: dup
     473: ldc           #46                 // String atan2
     475: getstatic     #27                 // Field org/hibernate/type/StandardBasicTypes.DOUBLE:Lorg/hibernate/type/DoubleType;
     478: invokespecial #25                 // Method org/hibernate/dialect/function/StandardSQLFunction."<init>":(Ljava/lang/String;Lorg/hibernate/type/Type;)V
     481: invokevirtual #22                 // Method registerFunction:(Ljava/lang/String;Lorg/hibernate/dialect/function/SQLFunction;)V
     484: aload_0
     485: ldc           #47                 // String round
     487: new           #20                 // class org/hibernate/dialect/function/StandardSQLFunction
     490: dup
     491: ldc           #47                 // String round
     493: invokespecial #21                 // Method org/hibernate/dialect/function/StandardSQLFunction."<init>":(Ljava/lang/String;)V
     496: invokevirtual #22                 // Method registerFunction:(Ljava/lang/String;Lorg/hibernate/dialect/function/SQLFunction;)V
     499: aload_0
     500: ldc           #48                 // String trunc
     502: new           #20                 // class org/hibernate/dialect/function/StandardSQLFunction
     505: dup
     506: ldc           #48                 // String trunc
     508: invokespecial #21                 // Method org/hibernate/dialect/function/StandardSQLFunction."<init>":(Ljava/lang/String;)V
     511: invokevirtual #22                 // Method registerFunction:(Ljava/lang/String;Lorg/hibernate/dialect/function/SQLFunction;)V
     514: aload_0
     515: ldc           #49                 // String ceil
     517: new           #20                 // class org/hibernate/dialect/function/StandardSQLFunction
     520: dup
     521: ldc           #49                 // String ceil
     523: invokespecial #21                 // Method org/hibernate/dialect/function/StandardSQLFunction."<init>":(Ljava/lang/String;)V
     526: invokevirtual #22                 // Method registerFunction:(Ljava/lang/String;Lorg/hibernate/dialect/function/SQLFunction;)V
     529: aload_0
     530: ldc           #50                 // String floor
     532: new           #20                 // class org/hibernate/dialect/function/StandardSQLFunction
     535: dup
     536: ldc           #50                 // String floor
     538: invokespecial #21                 // Method org/hibernate/dialect/function/StandardSQLFunction."<init>":(Ljava/lang/String;)V
     541: invokevirtual #22                 // Method registerFunction:(Ljava/lang/String;Lorg/hibernate/dialect/function/SQLFunction;)V
     544: aload_0
     545: ldc           #51                 // String greatest
     547: new           #20                 // class org/hibernate/dialect/function/StandardSQLFunction
     550: dup
     551: ldc           #51                 // String greatest
     553: invokespecial #21                 // Method org/hibernate/dialect/function/StandardSQLFunction."<init>":(Ljava/lang/String;)V
     556: invokevirtual #22                 // Method registerFunction:(Ljava/lang/String;Lorg/hibernate/dialect/function/SQLFunction;)V
     559: aload_0
     560: ldc           #52                 // String least
     562: new           #20                 // class org/hibernate/dialect/function/StandardSQLFunction
     565: dup
     566: ldc           #52                 // String least
     568: invokespecial #21                 // Method org/hibernate/dialect/function/StandardSQLFunction."<init>":(Ljava/lang/String;)V
     571: invokevirtual #22                 // Method registerFunction:(Ljava/lang/String;Lorg/hibernate/dialect/function/SQLFunction;)V
     574: aload_0
     575: ldc           #14                 // String time
     577: new           #20                 // class org/hibernate/dialect/function/StandardSQLFunction
     580: dup
     581: ldc           #14                 // String time
     583: getstatic     #53                 // Field org/hibernate/type/StandardBasicTypes.TIME:Lorg/hibernate/type/TimeType;
     586: invokespecial #25                 // Method org/hibernate/dialect/function/StandardSQLFunction."<init>":(Ljava/lang/String;Lorg/hibernate/type/Type;)V
     589: invokevirtual #22                 // Method registerFunction:(Ljava/lang/String;Lorg/hibernate/dialect/function/SQLFunction;)V
     592: aload_0
     593: ldc           #15                 // String timestamp
     595: new           #20                 // class org/hibernate/dialect/function/StandardSQLFunction
     598: dup
     599: ldc           #15                 // String timestamp
     601: getstatic     #54                 // Field org/hibernate/type/StandardBasicTypes.TIMESTAMP:Lorg/hibernate/type/TimestampType;
     604: invokespecial #25                 // Method org/hibernate/dialect/function/StandardSQLFunction."<init>":(Ljava/lang/String;Lorg/hibernate/type/Type;)V
     607: invokevirtual #22                 // Method registerFunction:(Ljava/lang/String;Lorg/hibernate/dialect/function/SQLFunction;)V
     610: aload_0
     611: ldc           #13                 // String date
     613: new           #20                 // class org/hibernate/dialect/function/StandardSQLFunction
     616: dup
     617: ldc           #13                 // String date
     619: getstatic     #55                 // Field org/hibernate/type/StandardBasicTypes.DATE:Lorg/hibernate/type/DateType;
     622: invokespecial #25                 // Method org/hibernate/dialect/function/StandardSQLFunction."<init>":(Ljava/lang/String;Lorg/hibernate/type/Type;)V
     625: invokevirtual #22                 // Method registerFunction:(Ljava/lang/String;Lorg/hibernate/dialect/function/SQLFunction;)V
     628: aload_0
     629: ldc           #56                 // String microsecond
     631: new           #20                 // class org/hibernate/dialect/function/StandardSQLFunction
     634: dup
     635: ldc           #56                 // String microsecond
     637: getstatic     #24                 // Field org/hibernate/type/StandardBasicTypes.INTEGER:Lorg/hibernate/type/IntegerType;
     640: invokespecial #25                 // Method org/hibernate/dialect/function/StandardSQLFunction."<init>":(Ljava/lang/String;Lorg/hibernate/type/Type;)V
     643: invokevirtual #22                 // Method registerFunction:(Ljava/lang/String;Lorg/hibernate/dialect/function/SQLFunction;)V
     646: aload_0
     647: ldc           #57                 // String second
     649: new           #58                 // class org/hibernate/dialect/function/SQLFunctionTemplate
     652: dup
     653: getstatic     #24                 // Field org/hibernate/type/StandardBasicTypes.INTEGER:Lorg/hibernate/type/IntegerType;
     656: ldc           #59                 // String second(?1)
     658: invokespecial #60                 // Method org/hibernate/dialect/function/SQLFunctionTemplate."<init>":(Lorg/hibernate/type/Type;Ljava/lang/String;)V
     661: invokevirtual #22                 // Method registerFunction:(Ljava/lang/String;Lorg/hibernate/dialect/function/SQLFunction;)V
     664: aload_0
     665: ldc           #61                 // String minute
     667: new           #58                 // class org/hibernate/dialect/function/SQLFunctionTemplate
     670: dup
     671: getstatic     #24                 // Field org/hibernate/type/StandardBasicTypes.INTEGER:Lorg/hibernate/type/IntegerType;
     674: ldc           #62                 // String minute(?1)
     676: invokespecial #60                 // Method org/hibernate/dialect/function/SQLFunctionTemplate."<init>":(Lorg/hibernate/type/Type;Ljava/lang/String;)V
     679: invokevirtual #22                 // Method registerFunction:(Ljava/lang/String;Lorg/hibernate/dialect/function/SQLFunction;)V
     682: aload_0
     683: ldc           #63                 // String hour
     685: new           #58                 // class org/hibernate/dialect/function/SQLFunctionTemplate
     688: dup
     689: getstatic     #24                 // Field org/hibernate/type/StandardBasicTypes.INTEGER:Lorg/hibernate/type/IntegerType;
     692: ldc           #64                 // String hour(?1)
     694: invokespecial #60                 // Method org/hibernate/dialect/function/SQLFunctionTemplate."<init>":(Lorg/hibernate/type/Type;Ljava/lang/String;)V
     697: invokevirtual #22                 // Method registerFunction:(Ljava/lang/String;Lorg/hibernate/dialect/function/SQLFunction;)V
     700: aload_0
     701: ldc           #65                 // String day
     703: new           #58                 // class org/hibernate/dialect/function/SQLFunctionTemplate
     706: dup
     707: getstatic     #24                 // Field org/hibernate/type/StandardBasicTypes.INTEGER:Lorg/hibernate/type/IntegerType;
     710: ldc           #66                 // String day(?1)
     712: invokespecial #60                 // Method org/hibernate/dialect/function/SQLFunctionTemplate."<init>":(Lorg/hibernate/type/Type;Ljava/lang/String;)V
     715: invokevirtual #22                 // Method registerFunction:(Ljava/lang/String;Lorg/hibernate/dialect/function/SQLFunction;)V
     718: aload_0
     719: ldc           #67                 // String month
     721: new           #58                 // class org/hibernate/dialect/function/SQLFunctionTemplate
     724: dup
     725: getstatic     #24                 // Field org/hibernate/type/StandardBasicTypes.INTEGER:Lorg/hibernate/type/IntegerType;
     728: ldc           #68                 // String month(?1)
     730: invokespecial #60                 // Method org/hibernate/dialect/function/SQLFunctionTemplate."<init>":(Lorg/hibernate/type/Type;Ljava/lang/String;)V
     733: invokevirtual #22                 // Method registerFunction:(Ljava/lang/String;Lorg/hibernate/dialect/function/SQLFunction;)V
     736: aload_0
     737: ldc           #69                 // String year
     739: new           #58                 // class org/hibernate/dialect/function/SQLFunctionTemplate
     742: dup
     743: getstatic     #24                 // Field org/hibernate/type/StandardBasicTypes.INTEGER:Lorg/hibernate/type/IntegerType;
     746: ldc           #70                 // String year(?1)
     748: invokespecial #60                 // Method org/hibernate/dialect/function/SQLFunctionTemplate."<init>":(Lorg/hibernate/type/Type;Ljava/lang/String;)V
     751: invokevirtual #22                 // Method registerFunction:(Ljava/lang/String;Lorg/hibernate/dialect/function/SQLFunction;)V
     754: aload_0
     755: ldc           #71                 // String extract
     757: new           #58                 // class org/hibernate/dialect/function/SQLFunctionTemplate
     760: dup
     761: getstatic     #24                 // Field org/hibernate/type/StandardBasicTypes.INTEGER:Lorg/hibernate/type/IntegerType;
     764: ldc           #72                 // String ?1(?3)
     766: invokespecial #60                 // Method org/hibernate/dialect/function/SQLFunctionTemplate."<init>":(Lorg/hibernate/type/Type;Ljava/lang/String;)V
     769: invokevirtual #22                 // Method registerFunction:(Ljava/lang/String;Lorg/hibernate/dialect/function/SQLFunction;)V
     772: aload_0
     773: ldc           #73                 // String dayname
     775: new           #20                 // class org/hibernate/dialect/function/StandardSQLFunction
     778: dup
     779: ldc           #73                 // String dayname
     781: getstatic     #74                 // Field org/hibernate/type/StandardBasicTypes.STRING:Lorg/hibernate/type/StringType;
     784: invokespecial #25                 // Method org/hibernate/dialect/function/StandardSQLFunction."<init>":(Ljava/lang/String;Lorg/hibernate/type/Type;)V
     787: invokevirtual #22                 // Method registerFunction:(Ljava/lang/String;Lorg/hibernate/dialect/function/SQLFunction;)V
     790: aload_0
     791: ldc           #75                 // String monthname
     793: new           #20                 // class org/hibernate/dialect/function/StandardSQLFunction
     796: dup
     797: ldc           #75                 // String monthname
     799: getstatic     #74                 // Field org/hibernate/type/StandardBasicTypes.STRING:Lorg/hibernate/type/StringType;
     802: invokespecial #25                 // Method org/hibernate/dialect/function/StandardSQLFunction."<init>":(Ljava/lang/String;Lorg/hibernate/type/Type;)V
     805: invokevirtual #22                 // Method registerFunction:(Ljava/lang/String;Lorg/hibernate/dialect/function/SQLFunction;)V
     808: aload_0
     809: ldc           #76                 // String dayofmonth
     811: new           #20                 // class org/hibernate/dialect/function/StandardSQLFunction
     814: dup
     815: ldc           #76                 // String dayofmonth
     817: getstatic     #24                 // Field org/hibernate/type/StandardBasicTypes.INTEGER:Lorg/hibernate/type/IntegerType;
     820: invokespecial #25                 // Method org/hibernate/dialect/function/StandardSQLFunction."<init>":(Ljava/lang/String;Lorg/hibernate/type/Type;)V
     823: invokevirtual #22                 // Method registerFunction:(Ljava/lang/String;Lorg/hibernate/dialect/function/SQLFunction;)V
     826: aload_0
     827: ldc           #77                 // String dayofweek
     829: new           #20                 // class org/hibernate/dialect/function/StandardSQLFunction
     832: dup
     833: ldc           #77                 // String dayofweek
     835: getstatic     #24                 // Field org/hibernate/type/StandardBasicTypes.INTEGER:Lorg/hibernate/type/IntegerType;
     838: invokespecial #25                 // Method org/hibernate/dialect/function/StandardSQLFunction."<init>":(Ljava/lang/String;Lorg/hibernate/type/Type;)V
     841: invokevirtual #22                 // Method registerFunction:(Ljava/lang/String;Lorg/hibernate/dialect/function/SQLFunction;)V
     844: aload_0
     845: ldc           #78                 // String dayofyear
     847: new           #20                 // class org/hibernate/dialect/function/StandardSQLFunction
     850: dup
     851: ldc           #78                 // String dayofyear
     853: getstatic     #24                 // Field org/hibernate/type/StandardBasicTypes.INTEGER:Lorg/hibernate/type/IntegerType;
     856: invokespecial #25                 // Method org/hibernate/dialect/function/StandardSQLFunction."<init>":(Ljava/lang/String;Lorg/hibernate/type/Type;)V
     859: invokevirtual #22                 // Method registerFunction:(Ljava/lang/String;Lorg/hibernate/dialect/function/SQLFunction;)V
     862: aload_0
     863: ldc           #79                 // String weekofyear
     865: new           #20                 // class org/hibernate/dialect/function/StandardSQLFunction
     868: dup
     869: ldc           #79                 // String weekofyear
     871: getstatic     #24                 // Field org/hibernate/type/StandardBasicTypes.INTEGER:Lorg/hibernate/type/IntegerType;
     874: invokespecial #25                 // Method org/hibernate/dialect/function/StandardSQLFunction."<init>":(Ljava/lang/String;Lorg/hibernate/type/Type;)V
     877: invokevirtual #22                 // Method registerFunction:(Ljava/lang/String;Lorg/hibernate/dialect/function/SQLFunction;)V
     880: aload_0
     881: ldc           #80                 // String replace
     883: new           #20                 // class org/hibernate/dialect/function/StandardSQLFunction
     886: dup
     887: ldc           #80                 // String replace
     889: getstatic     #74                 // Field org/hibernate/type/StandardBasicTypes.STRING:Lorg/hibernate/type/StringType;
     892: invokespecial #25                 // Method org/hibernate/dialect/function/StandardSQLFunction."<init>":(Ljava/lang/String;Lorg/hibernate/type/Type;)V
     895: invokevirtual #22                 // Method registerFunction:(Ljava/lang/String;Lorg/hibernate/dialect/function/SQLFunction;)V
     898: aload_0
     899: ldc           #81                 // String translate
     901: new           #20                 // class org/hibernate/dialect/function/StandardSQLFunction
     904: dup
     905: ldc           #81                 // String translate
     907: getstatic     #74                 // Field org/hibernate/type/StandardBasicTypes.STRING:Lorg/hibernate/type/StringType;
     910: invokespecial #25                 // Method org/hibernate/dialect/function/StandardSQLFunction."<init>":(Ljava/lang/String;Lorg/hibernate/type/Type;)V
     913: invokevirtual #22                 // Method registerFunction:(Ljava/lang/String;Lorg/hibernate/dialect/function/SQLFunction;)V
     916: aload_0
     917: ldc           #82                 // String lpad
     919: new           #20                 // class org/hibernate/dialect/function/StandardSQLFunction
     922: dup
     923: ldc           #82                 // String lpad
     925: getstatic     #74                 // Field org/hibernate/type/StandardBasicTypes.STRING:Lorg/hibernate/type/StringType;
     928: invokespecial #25                 // Method org/hibernate/dialect/function/StandardSQLFunction."<init>":(Ljava/lang/String;Lorg/hibernate/type/Type;)V
     931: invokevirtual #22                 // Method registerFunction:(Ljava/lang/String;Lorg/hibernate/dialect/function/SQLFunction;)V
     934: aload_0
     935: ldc           #83                 // String rpad
     937: new           #20                 // class org/hibernate/dialect/function/StandardSQLFunction
     940: dup
     941: ldc           #83                 // String rpad
     943: getstatic     #74                 // Field org/hibernate/type/StandardBasicTypes.STRING:Lorg/hibernate/type/StringType;
     946: invokespecial #25                 // Method org/hibernate/dialect/function/StandardSQLFunction."<init>":(Ljava/lang/String;Lorg/hibernate/type/Type;)V
     949: invokevirtual #22                 // Method registerFunction:(Ljava/lang/String;Lorg/hibernate/dialect/function/SQLFunction;)V
     952: aload_0
     953: ldc           #84                 // String substr
     955: new           #20                 // class org/hibernate/dialect/function/StandardSQLFunction
     958: dup
     959: ldc           #84                 // String substr
     961: getstatic     #74                 // Field org/hibernate/type/StandardBasicTypes.STRING:Lorg/hibernate/type/StringType;
     964: invokespecial #25                 // Method org/hibernate/dialect/function/StandardSQLFunction."<init>":(Ljava/lang/String;Lorg/hibernate/type/Type;)V
     967: invokevirtual #22                 // Method registerFunction:(Ljava/lang/String;Lorg/hibernate/dialect/function/SQLFunction;)V
     970: aload_0
     971: ldc           #85                 // String initcap
     973: new           #20                 // class org/hibernate/dialect/function/StandardSQLFunction
     976: dup
     977: ldc           #85                 // String initcap
     979: getstatic     #74                 // Field org/hibernate/type/StandardBasicTypes.STRING:Lorg/hibernate/type/StringType;
     982: invokespecial #25                 // Method org/hibernate/dialect/function/StandardSQLFunction."<init>":(Ljava/lang/String;Lorg/hibernate/type/Type;)V
     985: invokevirtual #22                 // Method registerFunction:(Ljava/lang/String;Lorg/hibernate/dialect/function/SQLFunction;)V
     988: aload_0
     989: ldc           #86                 // String lower
     991: new           #20                 // class org/hibernate/dialect/function/StandardSQLFunction
     994: dup
     995: ldc           #86                 // String lower
     997: getstatic     #74                 // Field org/hibernate/type/StandardBasicTypes.STRING:Lorg/hibernate/type/StringType;
    1000: invokespecial #25                 // Method org/hibernate/dialect/function/StandardSQLFunction."<init>":(Ljava/lang/String;Lorg/hibernate/type/Type;)V
    1003: invokevirtual #22                 // Method registerFunction:(Ljava/lang/String;Lorg/hibernate/dialect/function/SQLFunction;)V
    1006: aload_0
    1007: ldc           #87                 // String ltrim
    1009: new           #20                 // class org/hibernate/dialect/function/StandardSQLFunction
    1012: dup
    1013: ldc           #87                 // String ltrim
    1015: getstatic     #74                 // Field org/hibernate/type/StandardBasicTypes.STRING:Lorg/hibernate/type/StringType;
    1018: invokespecial #25                 // Method org/hibernate/dialect/function/StandardSQLFunction."<init>":(Ljava/lang/String;Lorg/hibernate/type/Type;)V
    1021: invokevirtual #22                 // Method registerFunction:(Ljava/lang/String;Lorg/hibernate/dialect/function/SQLFunction;)V
    1024: aload_0
    1025: ldc           #88                 // String rtrim
    1027: new           #20                 // class org/hibernate/dialect/function/StandardSQLFunction
    1030: dup
    1031: ldc           #88                 // String rtrim
    1033: getstatic     #74                 // Field org/hibernate/type/StandardBasicTypes.STRING:Lorg/hibernate/type/StringType;
    1036: invokespecial #25                 // Method org/hibernate/dialect/function/StandardSQLFunction."<init>":(Ljava/lang/String;Lorg/hibernate/type/Type;)V
    1039: invokevirtual #22                 // Method registerFunction:(Ljava/lang/String;Lorg/hibernate/dialect/function/SQLFunction;)V
    1042: aload_0
    1043: ldc           #89                 // String lfill
    1045: new           #20                 // class org/hibernate/dialect/function/StandardSQLFunction
    1048: dup
    1049: ldc           #87                 // String ltrim
    1051: getstatic     #74                 // Field org/hibernate/type/StandardBasicTypes.STRING:Lorg/hibernate/type/StringType;
    1054: invokespecial #25                 // Method org/hibernate/dialect/function/StandardSQLFunction."<init>":(Ljava/lang/String;Lorg/hibernate/type/Type;)V
    1057: invokevirtual #22                 // Method registerFunction:(Ljava/lang/String;Lorg/hibernate/dialect/function/SQLFunction;)V
    1060: aload_0
    1061: ldc           #90                 // String rfill
    1063: new           #20                 // class org/hibernate/dialect/function/StandardSQLFunction
    1066: dup
    1067: ldc           #88                 // String rtrim
    1069: getstatic     #74                 // Field org/hibernate/type/StandardBasicTypes.STRING:Lorg/hibernate/type/StringType;
    1072: invokespecial #25                 // Method org/hibernate/dialect/function/StandardSQLFunction."<init>":(Ljava/lang/String;Lorg/hibernate/type/Type;)V
    1075: invokevirtual #22                 // Method registerFunction:(Ljava/lang/String;Lorg/hibernate/dialect/function/SQLFunction;)V
    1078: aload_0
    1079: ldc           #91                 // String soundex
    1081: new           #20                 // class org/hibernate/dialect/function/StandardSQLFunction
    1084: dup
    1085: ldc           #91                 // String soundex
    1087: getstatic     #74                 // Field org/hibernate/type/StandardBasicTypes.STRING:Lorg/hibernate/type/StringType;
    1090: invokespecial #25                 // Method org/hibernate/dialect/function/StandardSQLFunction."<init>":(Ljava/lang/String;Lorg/hibernate/type/Type;)V
    1093: invokevirtual #22                 // Method registerFunction:(Ljava/lang/String;Lorg/hibernate/dialect/function/SQLFunction;)V
    1096: aload_0
    1097: ldc           #92                 // String upper
    1099: new           #20                 // class org/hibernate/dialect/function/StandardSQLFunction
    1102: dup
    1103: ldc           #92                 // String upper
    1105: getstatic     #74                 // Field org/hibernate/type/StandardBasicTypes.STRING:Lorg/hibernate/type/StringType;
    1108: invokespecial #25                 // Method org/hibernate/dialect/function/StandardSQLFunction."<init>":(Ljava/lang/String;Lorg/hibernate/type/Type;)V
    1111: invokevirtual #22                 // Method registerFunction:(Ljava/lang/String;Lorg/hibernate/dialect/function/SQLFunction;)V
    1114: aload_0
    1115: ldc           #93                 // String ascii
    1117: new           #20                 // class org/hibernate/dialect/function/StandardSQLFunction
    1120: dup
    1121: ldc           #93                 // String ascii
    1123: getstatic     #74                 // Field org/hibernate/type/StandardBasicTypes.STRING:Lorg/hibernate/type/StringType;
    1126: invokespecial #25                 // Method org/hibernate/dialect/function/StandardSQLFunction."<init>":(Ljava/lang/String;Lorg/hibernate/type/Type;)V
    1129: invokevirtual #22                 // Method registerFunction:(Ljava/lang/String;Lorg/hibernate/dialect/function/SQLFunction;)V
    1132: aload_0
    1133: ldc           #94                 // String index
    1135: new           #20                 // class org/hibernate/dialect/function/StandardSQLFunction
    1138: dup
    1139: ldc           #94                 // String index
    1141: getstatic     #24                 // Field org/hibernate/type/StandardBasicTypes.INTEGER:Lorg/hibernate/type/IntegerType;
    1144: invokespecial #25                 // Method org/hibernate/dialect/function/StandardSQLFunction."<init>":(Ljava/lang/String;Lorg/hibernate/type/Type;)V
    1147: invokevirtual #22                 // Method registerFunction:(Ljava/lang/String;Lorg/hibernate/dialect/function/SQLFunction;)V
    1150: aload_0
    1151: ldc           #95                 // String value
    1153: new           #20                 // class org/hibernate/dialect/function/StandardSQLFunction
    1156: dup
    1157: ldc           #95                 // String value
    1159: invokespecial #21                 // Method org/hibernate/dialect/function/StandardSQLFunction."<init>":(Ljava/lang/String;)V
    1162: invokevirtual #22                 // Method registerFunction:(Ljava/lang/String;Lorg/hibernate/dialect/function/SQLFunction;)V
    1165: aload_0
    1166: ldc           #96                 // String concat
    1168: new           #97                 // class org/hibernate/dialect/function/VarArgsSQLFunction
    1171: dup
    1172: getstatic     #74                 // Field org/hibernate/type/StandardBasicTypes.STRING:Lorg/hibernate/type/StringType;
    1175: ldc           #98                 // String (
    1177: ldc           #99                 // String ||
    1179: ldc           #100                // String )
    1181: invokespecial #101                // Method org/hibernate/dialect/function/VarArgsSQLFunction."<init>":(Lorg/hibernate/type/Type;Ljava/lang/String;Ljava/lang/String;Ljava/lang/String;)V
    1184: invokevirtual #22                 // Method registerFunction:(Ljava/lang/String;Lorg/hibernate/dialect/function/SQLFunction;)V
    1187: aload_0
    1188: ldc           #102                // String substring
    1190: new           #20                 // class org/hibernate/dialect/function/StandardSQLFunction
    1193: dup
    1194: ldc           #84                 // String substr
    1196: getstatic     #74                 // Field org/hibernate/type/StandardBasicTypes.STRING:Lorg/hibernate/type/StringType;
    1199: invokespecial #25                 // Method org/hibernate/dialect/function/StandardSQLFunction."<init>":(Ljava/lang/String;Lorg/hibernate/type/Type;)V
    1202: invokevirtual #22                 // Method registerFunction:(Ljava/lang/String;Lorg/hibernate/dialect/function/SQLFunction;)V
    1205: aload_0
    1206: ldc           #103                // String locate
    1208: new           #20                 // class org/hibernate/dialect/function/StandardSQLFunction
    1211: dup
    1212: ldc           #94                 // String index
    1214: getstatic     #24                 // Field org/hibernate/type/StandardBasicTypes.INTEGER:Lorg/hibernate/type/IntegerType;
    1217: invokespecial #25                 // Method org/hibernate/dialect/function/StandardSQLFunction."<init>":(Ljava/lang/String;Lorg/hibernate/type/Type;)V
    1220: invokevirtual #22                 // Method registerFunction:(Ljava/lang/String;Lorg/hibernate/dialect/function/SQLFunction;)V
    1223: aload_0
    1224: ldc           #104                // String coalesce
    1226: new           #20                 // class org/hibernate/dialect/function/StandardSQLFunction
    1229: dup
    1230: ldc           #95                 // String value
    1232: invokespecial #21                 // Method org/hibernate/dialect/function/StandardSQLFunction."<init>":(Ljava/lang/String;)V
    1235: invokevirtual #22                 // Method registerFunction:(Ljava/lang/String;Lorg/hibernate/dialect/function/SQLFunction;)V
    1238: aload_0
    1239: invokevirtual #105                // Method getDefaultProperties:()Ljava/util/Properties;
    1242: ldc           #107                // String hibernate.jdbc.batch_size
    1244: ldc           #109                // String 15
    1246: invokevirtual #110                // Method java/util/Properties.setProperty:(Ljava/lang/String;Ljava/lang/String;)Ljava/lang/Object;
    1249: pop
    1250: return

  public boolean dropConstraints();
    Code:
       0: iconst_0
       1: ireturn

  public java.lang.String getAddColumnString();
    Code:
       0: ldc           #111                // String add
       2: areturn

  public java.lang.String getAddForeignKeyConstraintString(java.lang.String, java.lang.String[], java.lang.String, java.lang.String[], boolean);
    Code:
       0: new           #112                // class java/lang/StringBuilder
       3: dup
       4: bipush        30
       6: invokespecial #113                // Method java/lang/StringBuilder."<init>":(I)V
       9: ldc           #114                // String  foreign key
      11: invokevirtual #115                // Method java/lang/StringBuilder.append:(Ljava/lang/String;)Ljava/lang/StringBuilder;
      14: aload_1
      15: invokevirtual #115                // Method java/lang/StringBuilder.append:(Ljava/lang/String;)Ljava/lang/StringBuilder;
      18: ldc           #116                // String  (
      20: invokevirtual #115                // Method java/lang/StringBuilder.append:(Ljava/lang/String;)Ljava/lang/StringBuilder;
      23: ldc           #117                // String ,
      25: aload_2
      26: invokestatic  #118                // Method java/lang/String.join:(Ljava/lang/CharSequence;[Ljava/lang/CharSequence;)Ljava/lang/String;
      29: invokevirtual #115                // Method java/lang/StringBuilder.append:(Ljava/lang/String;)Ljava/lang/StringBuilder;
      32: ldc           #119                // String ) references
      34: invokevirtual #115                // Method java/lang/StringBuilder.append:(Ljava/lang/String;)Ljava/lang/StringBuilder;
      37: aload_3
      38: invokevirtual #115                // Method java/lang/StringBuilder.append:(Ljava/lang/String;)Ljava/lang/StringBuilder;
      41: astore        6
      43: iload         5
      45: ifne          71
      48: aload         6
      50: ldc           #116                // String  (
      52: invokevirtual #115                // Method java/lang/StringBuilder.append:(Ljava/lang/String;)Ljava/lang/StringBuilder;
      55: ldc           #117                // String ,
      57: aload         4
      59: invokestatic  #118                // Method java/lang/String.join:(Ljava/lang/CharSequence;[Ljava/lang/CharSequence;)Ljava/lang/String;
      62: invokevirtual #115                // Method java/lang/StringBuilder.append:(Ljava/lang/String;)Ljava/lang/StringBuilder;
      65: bipush        41
      67: invokevirtual #120                // Method java/lang/StringBuilder.append:(C)Ljava/lang/StringBuilder;
      70: pop
      71: aload         6
      73: invokevirtual #121                // Method java/lang/StringBuilder.toString:()Ljava/lang/String;
      76: areturn

  public java.lang.String getAddForeignKeyConstraintString(java.lang.String, java.lang.String);
    Code:
       0: aload_2
       1: areturn

  public java.lang.String getAddPrimaryKeyConstraintString(java.lang.String);
    Code:
       0: ldc           #122                // String  primary key
       2: areturn

  public java.lang.String getNullColumnString();
    Code:
       0: ldc           #123                // String  null
       2: areturn

  public java.lang.String getSequenceNextValString(java.lang.String);
    Code:
       0: new           #112                // class java/lang/StringBuilder
       3: dup
       4: invokespecial #124                // Method java/lang/StringBuilder."<init>":()V
       7: ldc           #125                // String select
       9: invokevirtual #115                // Method java/lang/StringBuilder.append:(Ljava/lang/String;)Ljava/lang/StringBuilder;
      12: aload_0
      13: aload_1
      14: invokevirtual #126                // Method getSelectSequenceNextValString:(Ljava/lang/String;)Ljava/lang/String;
      17: invokevirtual #115                // Method java/lang/StringBuilder.append:(Ljava/lang/String;)Ljava/lang/StringBuilder;
      20: ldc           #127                // String  from dual
      22: invokevirtual #115                // Method java/lang/StringBuilder.append:(Ljava/lang/String;)Ljava/lang/StringBuilder;
      25: invokevirtual #121                // Method java/lang/StringBuilder.toString:()Ljava/lang/String;
      28: areturn

  public java.lang.String getSelectSequenceNextValString(java.lang.String);
    Code:
       0: new           #112                // class java/lang/StringBuilder
       3: dup
       4: invokespecial #124                // Method java/lang/StringBuilder."<init>":()V
       7: aload_1
       8: invokevirtual #115                // Method java/lang/StringBuilder.append:(Ljava/lang/String;)Ljava/lang/StringBuilder;
      11: ldc           #128                // String .nextval
      13: invokevirtual #115                // Method java/lang/StringBuilder.append:(Ljava/lang/String;)Ljava/lang/StringBuilder;
      16: invokevirtual #121                // Method java/lang/StringBuilder.toString:()Ljava/lang/String;
      19: areturn

  public java.lang.String getCreateSequenceString(java.lang.String);
    Code:
       0: new           #112                // class java/lang/StringBuilder
       3: dup
       4: invokespecial #124                // Method java/lang/StringBuilder."<init>":()V
       7: ldc           #129                // String create sequence
       9: invokevirtual #115                // Method java/lang/StringBuilder.append:(Ljava/lang/String;)Ljava/lang/StringBuilder;
      12: aload_1
      13: invokevirtual #115                // Method java/lang/StringBuilder.append:(Ljava/lang/String;)Ljava/lang/StringBuilder;
      16: invokevirtual #121                // Method java/lang/StringBuilder.toString:()Ljava/lang/String;
      19: areturn

  public java.lang.String getDropSequenceString(java.lang.String);
    Code:
       0: new           #112                // class java/lang/StringBuilder
       3: dup
       4: invokespecial #124                // Method java/lang/StringBuilder."<init>":()V
       7: ldc           #130                // String drop sequence
       9: invokevirtual #115                // Method java/lang/StringBuilder.append:(Ljava/lang/String;)Ljava/lang/StringBuilder;
      12: aload_1
      13: invokevirtual #115                // Method java/lang/StringBuilder.append:(Ljava/lang/String;)Ljava/lang/StringBuilder;
      16: invokevirtual #121                // Method java/lang/StringBuilder.toString:()Ljava/lang/String;
      19: areturn

  public java.lang.String getQuerySequencesString();
    Code:
       0: ldc           #131                // String select sequence_name from domain.sequences
       2: areturn

  public boolean supportsSequences();
    Code:
       0: iconst_1
       1: ireturn

  public org.hibernate.sql.CaseFragment createCaseFragment();
    Code:
       0: new           #132                // class org/hibernate/sql/DecodeCaseFragment
       3: dup
       4: invokespecial #133                // Method org/hibernate/sql/DecodeCaseFragment."<init>":()V
       7: areturn

  public org.hibernate.hql.spi.id.MultiTableBulkIdStrategy getDefaultMultiTableBulkIdStrategy();
    Code:
       0: new           #134                // class org/hibernate/hql/spi/id/local/LocalTemporaryTableBulkIdStrategy
       3: dup
       4: new           #135                // class org/hibernate/dialect/SAPDBDialect$1
       7: dup
       8: aload_0
       9: invokespecial #136                // Method org/hibernate/dialect/SAPDBDialect$1."<init>":(Lorg/hibernate/dialect/SAPDBDialect;)V
      12: getstatic     #137                // Field org/hibernate/hql/spi/id/local/AfterUseAction.DROP:Lorg/hibernate/hql/spi/id/local/AfterUseAction;
      15: aconst_null
      16: invokespecial #138                // Method org/hibernate/hql/spi/id/local/LocalTemporaryTableBulkIdStrategy."<init>":(Lorg/hibernate/hql/spi/id/IdTableSupport;Lorg/hibernate/hql/spi/id/local/AfterUseAction;Lorg/hibernate/boot/TempTableDdlTransactionHandling;)V
      19: areturn
}
