Compiled from "SybaseASE15Dialect.java"
public class org.hibernate.dialect.SybaseASE15Dialect extends org.hibernate.dialect.SybaseDialect {
  public org.hibernate.dialect.SybaseASE15Dialect();
    Code:
       0: aload_0
       1: invokespecial #1                  // Method org/hibernate/dialect/SybaseDialect."<init>":()V
       4: aload_0
       5: bipush        -4
       7: ldc           #3                  // String image
       9: invokevirtual #4                  // Method registerColumnType:(ILjava/lang/String;)V
      12: aload_0
      13: iconst_m1
      14: ldc           #5                  // String text
      16: invokevirtual #4                  // Method registerColumnType:(ILjava/lang/String;)V
      19: aload_0
      20: bipush        -5
      22: ldc           #6                  // String bigint
      24: invokevirtual #4                  // Method registerColumnType:(ILjava/lang/String;)V
      27: aload_0
      28: bipush        91
      30: ldc           #7                  // String date
      32: invokevirtual #4                  // Method registerColumnType:(ILjava/lang/String;)V
      35: aload_0
      36: iconst_3
      37: ldc           #8                  // String numeric($p,$s)
      39: invokevirtual #4                  // Method registerColumnType:(ILjava/lang/String;)V
      42: aload_0
      43: bipush        92
      45: ldc           #9                  // String time
      47: invokevirtual #4                  // Method registerColumnType:(ILjava/lang/String;)V
      50: aload_0
      51: bipush        7
      53: ldc           #10                 // String real
      55: invokevirtual #4                  // Method registerColumnType:(ILjava/lang/String;)V
      58: aload_0
      59: bipush        16
      61: ldc           #11                 // String tinyint
      63: invokevirtual #4                  // Method registerColumnType:(ILjava/lang/String;)V
      66: aload_0
      67: ldc           #12                 // String second
      69: new           #13                 // class org/hibernate/dialect/function/SQLFunctionTemplate
      72: dup
      73: getstatic     #14                 // Field org/hibernate/type/StandardBasicTypes.INTEGER:Lorg/hibernate/type/IntegerType;
      76: ldc           #15                 // String datepart(second, ?1)
      78: invokespecial #16                 // Method org/hibernate/dialect/function/SQLFunctionTemplate."<init>":(Lorg/hibernate/type/Type;Ljava/lang/String;)V
      81: invokevirtual #17                 // Method registerFunction:(Ljava/lang/String;Lorg/hibernate/dialect/function/SQLFunction;)V
      84: aload_0
      85: ldc           #18                 // String minute
      87: new           #13                 // class org/hibernate/dialect/function/SQLFunctionTemplate
      90: dup
      91: getstatic     #14                 // Field org/hibernate/type/StandardBasicTypes.INTEGER:Lorg/hibernate/type/IntegerType;
      94: ldc           #19                 // String datepart(minute, ?1)
      96: invokespecial #16                 // Method org/hibernate/dialect/function/SQLFunctionTemplate."<init>":(Lorg/hibernate/type/Type;Ljava/lang/String;)V
      99: invokevirtual #17                 // Method registerFunction:(Ljava/lang/String;Lorg/hibernate/dialect/function/SQLFunction;)V
     102: aload_0
     103: ldc           #20                 // String hour
     105: new           #13                 // class org/hibernate/dialect/function/SQLFunctionTemplate
     108: dup
     109: getstatic     #14                 // Field org/hibernate/type/StandardBasicTypes.INTEGER:Lorg/hibernate/type/IntegerType;
     112: ldc           #21                 // String datepart(hour, ?1)
     114: invokespecial #16                 // Method org/hibernate/dialect/function/SQLFunctionTemplate."<init>":(Lorg/hibernate/type/Type;Ljava/lang/String;)V
     117: invokevirtual #17                 // Method registerFunction:(Ljava/lang/String;Lorg/hibernate/dialect/function/SQLFunction;)V
     120: aload_0
     121: ldc           #22                 // String extract
     123: new           #13                 // class org/hibernate/dialect/function/SQLFunctionTemplate
     126: dup
     127: getstatic     #14                 // Field org/hibernate/type/StandardBasicTypes.INTEGER:Lorg/hibernate/type/IntegerType;
     130: ldc           #23                 // String datepart(?1, ?3)
     132: invokespecial #16                 // Method org/hibernate/dialect/function/SQLFunctionTemplate."<init>":(Lorg/hibernate/type/Type;Ljava/lang/String;)V
     135: invokevirtual #17                 // Method registerFunction:(Ljava/lang/String;Lorg/hibernate/dialect/function/SQLFunction;)V
     138: aload_0
     139: ldc           #24                 // String mod
     141: new           #13                 // class org/hibernate/dialect/function/SQLFunctionTemplate
     144: dup
     145: getstatic     #14                 // Field org/hibernate/type/StandardBasicTypes.INTEGER:Lorg/hibernate/type/IntegerType;
     148: ldc           #25                 // String ?1 % ?2
     150: invokespecial #16                 // Method org/hibernate/dialect/function/SQLFunctionTemplate."<init>":(Lorg/hibernate/type/Type;Ljava/lang/String;)V
     153: invokevirtual #17                 // Method registerFunction:(Ljava/lang/String;Lorg/hibernate/dialect/function/SQLFunction;)V
     156: aload_0
     157: ldc           #26                 // String bit_length
     159: new           #13                 // class org/hibernate/dialect/function/SQLFunctionTemplate
     162: dup
     163: getstatic     #14                 // Field org/hibernate/type/StandardBasicTypes.INTEGER:Lorg/hibernate/type/IntegerType;
     166: ldc           #27                 // String datalength(?1) * 8
     168: invokespecial #16                 // Method org/hibernate/dialect/function/SQLFunctionTemplate."<init>":(Lorg/hibernate/type/Type;Ljava/lang/String;)V
     171: invokevirtual #17                 // Method registerFunction:(Ljava/lang/String;Lorg/hibernate/dialect/function/SQLFunction;)V
     174: aload_0
     175: ldc           #28                 // String trim
     177: new           #29                 // class org/hibernate/dialect/function/AnsiTrimEmulationFunction
     180: dup
     181: ldc           #30                 // String ltrim
     183: ldc           #31                 // String rtrim
     185: ldc           #32                 // String str_replace
     187: invokespecial #33                 // Method org/hibernate/dialect/function/AnsiTrimEmulationFunction."<init>":(Ljava/lang/String;Ljava/lang/String;Ljava/lang/String;)V
     190: invokevirtual #17                 // Method registerFunction:(Ljava/lang/String;Lorg/hibernate/dialect/function/SQLFunction;)V
     193: aload_0
     194: ldc           #34                 // String atan2
     196: new           #13                 // class org/hibernate/dialect/function/SQLFunctionTemplate
     199: dup
     200: getstatic     #35                 // Field org/hibernate/type/StandardBasicTypes.DOUBLE:Lorg/hibernate/type/DoubleType;
     203: ldc           #36                 // String atn2(?1, ?2)
     205: invokespecial #16                 // Method org/hibernate/dialect/function/SQLFunctionTemplate."<init>":(Lorg/hibernate/type/Type;Ljava/lang/String;)V
     208: invokevirtual #17                 // Method registerFunction:(Ljava/lang/String;Lorg/hibernate/dialect/function/SQLFunction;)V
     211: aload_0
     212: ldc           #37                 // String atn2
     214: new           #13                 // class org/hibernate/dialect/function/SQLFunctionTemplate
     217: dup
     218: getstatic     #35                 // Field org/hibernate/type/StandardBasicTypes.DOUBLE:Lorg/hibernate/type/DoubleType;
     221: ldc           #36                 // String atn2(?1, ?2)
     223: invokespecial #16                 // Method org/hibernate/dialect/function/SQLFunctionTemplate."<init>":(Lorg/hibernate/type/Type;Ljava/lang/String;)V
     226: invokevirtual #17                 // Method registerFunction:(Ljava/lang/String;Lorg/hibernate/dialect/function/SQLFunction;)V
     229: aload_0
     230: ldc           #38                 // String biginttohex
     232: new           #13                 // class org/hibernate/dialect/function/SQLFunctionTemplate
     235: dup
     236: getstatic     #39                 // Field org/hibernate/type/StandardBasicTypes.STRING:Lorg/hibernate/type/StringType;
     239: ldc           #40                 // String biginttohext(?1)
     241: invokespecial #16                 // Method org/hibernate/dialect/function/SQLFunctionTemplate."<init>":(Lorg/hibernate/type/Type;Ljava/lang/String;)V
     244: invokevirtual #17                 // Method registerFunction:(Ljava/lang/String;Lorg/hibernate/dialect/function/SQLFunction;)V
     247: aload_0
     248: ldc           #41                 // String char_length
     250: new           #13                 // class org/hibernate/dialect/function/SQLFunctionTemplate
     253: dup
     254: getstatic     #14                 // Field org/hibernate/type/StandardBasicTypes.INTEGER:Lorg/hibernate/type/IntegerType;
     257: ldc           #42                 // String char_length(?1)
     259: invokespecial #16                 // Method org/hibernate/dialect/function/SQLFunctionTemplate."<init>":(Lorg/hibernate/type/Type;Ljava/lang/String;)V
     262: invokevirtual #17                 // Method registerFunction:(Ljava/lang/String;Lorg/hibernate/dialect/function/SQLFunction;)V
     265: aload_0
     266: ldc           #43                 // String charindex
     268: new           #13                 // class org/hibernate/dialect/function/SQLFunctionTemplate
     271: dup
     272: getstatic     #14                 // Field org/hibernate/type/StandardBasicTypes.INTEGER:Lorg/hibernate/type/IntegerType;
     275: ldc           #44                 // String charindex(?1, ?2)
     277: invokespecial #16                 // Method org/hibernate/dialect/function/SQLFunctionTemplate."<init>":(Lorg/hibernate/type/Type;Ljava/lang/String;)V
     280: invokevirtual #17                 // Method registerFunction:(Ljava/lang/String;Lorg/hibernate/dialect/function/SQLFunction;)V
     283: aload_0
     284: ldc           #45                 // String coalesce
     286: new           #46                 // class org/hibernate/dialect/function/VarArgsSQLFunction
     289: dup
     290: ldc           #47                 // String coalesce(
     292: ldc           #48                 // String ,
     294: ldc           #49                 // String )
     296: invokespecial #50                 // Method org/hibernate/dialect/function/VarArgsSQLFunction."<init>":(Ljava/lang/String;Ljava/lang/String;Ljava/lang/String;)V
     299: invokevirtual #17                 // Method registerFunction:(Ljava/lang/String;Lorg/hibernate/dialect/function/SQLFunction;)V
     302: aload_0
     303: ldc           #51                 // String col_length
     305: new           #13                 // class org/hibernate/dialect/function/SQLFunctionTemplate
     308: dup
     309: getstatic     #14                 // Field org/hibernate/type/StandardBasicTypes.INTEGER:Lorg/hibernate/type/IntegerType;
     312: ldc           #52                 // String col_length(?1, ?2)
     314: invokespecial #16                 // Method org/hibernate/dialect/function/SQLFunctionTemplate."<init>":(Lorg/hibernate/type/Type;Ljava/lang/String;)V
     317: invokevirtual #17                 // Method registerFunction:(Ljava/lang/String;Lorg/hibernate/dialect/function/SQLFunction;)V
     320: aload_0
     321: ldc           #53                 // String col_name
     323: new           #13                 // class org/hibernate/dialect/function/SQLFunctionTemplate
     326: dup
     327: getstatic     #39                 // Field org/hibernate/type/StandardBasicTypes.STRING:Lorg/hibernate/type/StringType;
     330: ldc           #54                 // String col_name(?1, ?2)
     332: invokespecial #16                 // Method org/hibernate/dialect/function/SQLFunctionTemplate."<init>":(Lorg/hibernate/type/Type;Ljava/lang/String;)V
     335: invokevirtual #17                 // Method registerFunction:(Ljava/lang/String;Lorg/hibernate/dialect/function/SQLFunction;)V
     338: aload_0
     339: ldc           #55                 // String current_time
     341: new           #56                 // class org/hibernate/dialect/function/NoArgSQLFunction
     344: dup
     345: ldc           #55                 // String current_time
     347: getstatic     #57                 // Field org/hibernate/type/StandardBasicTypes.TIME:Lorg/hibernate/type/TimeType;
     350: invokespecial #58                 // Method org/hibernate/dialect/function/NoArgSQLFunction."<init>":(Ljava/lang/String;Lorg/hibernate/type/Type;)V
     353: invokevirtual #17                 // Method registerFunction:(Ljava/lang/String;Lorg/hibernate/dialect/function/SQLFunction;)V
     356: aload_0
     357: ldc           #59                 // String current_date
     359: new           #56                 // class org/hibernate/dialect/function/NoArgSQLFunction
     362: dup
     363: ldc           #59                 // String current_date
     365: getstatic     #60                 // Field org/hibernate/type/StandardBasicTypes.DATE:Lorg/hibernate/type/DateType;
     368: invokespecial #58                 // Method org/hibernate/dialect/function/NoArgSQLFunction."<init>":(Ljava/lang/String;Lorg/hibernate/type/Type;)V
     371: invokevirtual #17                 // Method registerFunction:(Ljava/lang/String;Lorg/hibernate/dialect/function/SQLFunction;)V
     374: aload_0
     375: ldc           #61                 // String data_pages
     377: new           #13                 // class org/hibernate/dialect/function/SQLFunctionTemplate
     380: dup
     381: getstatic     #14                 // Field org/hibernate/type/StandardBasicTypes.INTEGER:Lorg/hibernate/type/IntegerType;
     384: ldc           #62                 // String data_pages(?1, ?2)
     386: invokespecial #16                 // Method org/hibernate/dialect/function/SQLFunctionTemplate."<init>":(Lorg/hibernate/type/Type;Ljava/lang/String;)V
     389: invokevirtual #17                 // Method registerFunction:(Ljava/lang/String;Lorg/hibernate/dialect/function/SQLFunction;)V
     392: aload_0
     393: ldc           #61                 // String data_pages
     395: new           #13                 // class org/hibernate/dialect/function/SQLFunctionTemplate
     398: dup
     399: getstatic     #14                 // Field org/hibernate/type/StandardBasicTypes.INTEGER:Lorg/hibernate/type/IntegerType;
     402: ldc           #63                 // String data_pages(?1, ?2, ?3)
     404: invokespecial #16                 // Method org/hibernate/dialect/function/SQLFunctionTemplate."<init>":(Lorg/hibernate/type/Type;Ljava/lang/String;)V
     407: invokevirtual #17                 // Method registerFunction:(Ljava/lang/String;Lorg/hibernate/dialect/function/SQLFunction;)V
     410: aload_0
     411: ldc           #61                 // String data_pages
     413: new           #13                 // class org/hibernate/dialect/function/SQLFunctionTemplate
     416: dup
     417: getstatic     #14                 // Field org/hibernate/type/StandardBasicTypes.INTEGER:Lorg/hibernate/type/IntegerType;
     420: ldc           #64                 // String data_pages(?1, ?2, ?3, ?4)
     422: invokespecial #16                 // Method org/hibernate/dialect/function/SQLFunctionTemplate."<init>":(Lorg/hibernate/type/Type;Ljava/lang/String;)V
     425: invokevirtual #17                 // Method registerFunction:(Ljava/lang/String;Lorg/hibernate/dialect/function/SQLFunction;)V
     428: aload_0
     429: ldc           #65                 // String datalength
     431: new           #13                 // class org/hibernate/dialect/function/SQLFunctionTemplate
     434: dup
     435: getstatic     #14                 // Field org/hibernate/type/StandardBasicTypes.INTEGER:Lorg/hibernate/type/IntegerType;
     438: ldc           #66                 // String datalength(?1)
     440: invokespecial #16                 // Method org/hibernate/dialect/function/SQLFunctionTemplate."<init>":(Lorg/hibernate/type/Type;Ljava/lang/String;)V
     443: invokevirtual #17                 // Method registerFunction:(Ljava/lang/String;Lorg/hibernate/dialect/function/SQLFunction;)V
     446: aload_0
     447: ldc           #67                 // String dateadd
     449: new           #13                 // class org/hibernate/dialect/function/SQLFunctionTemplate
     452: dup
     453: getstatic     #68                 // Field org/hibernate/type/StandardBasicTypes.TIMESTAMP:Lorg/hibernate/type/TimestampType;
     456: ldc           #69                 // String dateadd(?1, ?2, ?3)
     458: invokespecial #16                 // Method org/hibernate/dialect/function/SQLFunctionTemplate."<init>":(Lorg/hibernate/type/Type;Ljava/lang/String;)V
     461: invokevirtual #17                 // Method registerFunction:(Ljava/lang/String;Lorg/hibernate/dialect/function/SQLFunction;)V
     464: aload_0
     465: ldc           #70                 // String datediff
     467: new           #13                 // class org/hibernate/dialect/function/SQLFunctionTemplate
     470: dup
     471: getstatic     #14                 // Field org/hibernate/type/StandardBasicTypes.INTEGER:Lorg/hibernate/type/IntegerType;
     474: ldc           #71                 // String datediff(?1, ?2, ?3)
     476: invokespecial #16                 // Method org/hibernate/dialect/function/SQLFunctionTemplate."<init>":(Lorg/hibernate/type/Type;Ljava/lang/String;)V
     479: invokevirtual #17                 // Method registerFunction:(Ljava/lang/String;Lorg/hibernate/dialect/function/SQLFunction;)V
     482: aload_0
     483: ldc           #72                 // String datepart
     485: new           #13                 // class org/hibernate/dialect/function/SQLFunctionTemplate
     488: dup
     489: getstatic     #14                 // Field org/hibernate/type/StandardBasicTypes.INTEGER:Lorg/hibernate/type/IntegerType;
     492: ldc           #73                 // String datepart(?1, ?2)
     494: invokespecial #16                 // Method org/hibernate/dialect/function/SQLFunctionTemplate."<init>":(Lorg/hibernate/type/Type;Ljava/lang/String;)V
     497: invokevirtual #17                 // Method registerFunction:(Ljava/lang/String;Lorg/hibernate/dialect/function/SQLFunction;)V
     500: aload_0
     501: ldc           #74                 // String datetime
     503: new           #13                 // class org/hibernate/dialect/function/SQLFunctionTemplate
     506: dup
     507: getstatic     #68                 // Field org/hibernate/type/StandardBasicTypes.TIMESTAMP:Lorg/hibernate/type/TimestampType;
     510: ldc           #74                 // String datetime
     512: invokespecial #16                 // Method org/hibernate/dialect/function/SQLFunctionTemplate."<init>":(Lorg/hibernate/type/Type;Ljava/lang/String;)V
     515: invokevirtual #17                 // Method registerFunction:(Ljava/lang/String;Lorg/hibernate/dialect/function/SQLFunction;)V
     518: aload_0
     519: ldc           #75                 // String db_id
     521: new           #13                 // class org/hibernate/dialect/function/SQLFunctionTemplate
     524: dup
     525: getstatic     #14                 // Field org/hibernate/type/StandardBasicTypes.INTEGER:Lorg/hibernate/type/IntegerType;
     528: ldc           #76                 // String db_id(?1)
     530: invokespecial #16                 // Method org/hibernate/dialect/function/SQLFunctionTemplate."<init>":(Lorg/hibernate/type/Type;Ljava/lang/String;)V
     533: invokevirtual #17                 // Method registerFunction:(Ljava/lang/String;Lorg/hibernate/dialect/function/SQLFunction;)V
     536: aload_0
     537: ldc           #77                 // String difference
     539: new           #13                 // class org/hibernate/dialect/function/SQLFunctionTemplate
     542: dup
     543: getstatic     #14                 // Field org/hibernate/type/StandardBasicTypes.INTEGER:Lorg/hibernate/type/IntegerType;
     546: ldc           #78                 // String difference(?1,?2)
     548: invokespecial #16                 // Method org/hibernate/dialect/function/SQLFunctionTemplate."<init>":(Lorg/hibernate/type/Type;Ljava/lang/String;)V
     551: invokevirtual #17                 // Method registerFunction:(Ljava/lang/String;Lorg/hibernate/dialect/function/SQLFunction;)V
     554: aload_0
     555: ldc           #79                 // String db_name
     557: new           #13                 // class org/hibernate/dialect/function/SQLFunctionTemplate
     560: dup
     561: getstatic     #39                 // Field org/hibernate/type/StandardBasicTypes.STRING:Lorg/hibernate/type/StringType;
     564: ldc           #80                 // String db_name(?1)
     566: invokespecial #16                 // Method org/hibernate/dialect/function/SQLFunctionTemplate."<init>":(Lorg/hibernate/type/Type;Ljava/lang/String;)V
     569: invokevirtual #17                 // Method registerFunction:(Ljava/lang/String;Lorg/hibernate/dialect/function/SQLFunction;)V
     572: aload_0
     573: ldc           #81                 // String has_role
     575: new           #13                 // class org/hibernate/dialect/function/SQLFunctionTemplate
     578: dup
     579: getstatic     #14                 // Field org/hibernate/type/StandardBasicTypes.INTEGER:Lorg/hibernate/type/IntegerType;
     582: ldc           #82                 // String has_role(?1, ?2)
     584: invokespecial #16                 // Method org/hibernate/dialect/function/SQLFunctionTemplate."<init>":(Lorg/hibernate/type/Type;Ljava/lang/String;)V
     587: invokevirtual #17                 // Method registerFunction:(Ljava/lang/String;Lorg/hibernate/dialect/function/SQLFunction;)V
     590: aload_0
     591: ldc           #83                 // String hextobigint
     593: new           #13                 // class org/hibernate/dialect/function/SQLFunctionTemplate
     596: dup
     597: getstatic     #14                 // Field org/hibernate/type/StandardBasicTypes.INTEGER:Lorg/hibernate/type/IntegerType;
     600: ldc           #84                 // String hextobigint(?1)
     602: invokespecial #16                 // Method org/hibernate/dialect/function/SQLFunctionTemplate."<init>":(Lorg/hibernate/type/Type;Ljava/lang/String;)V
     605: invokevirtual #17                 // Method registerFunction:(Ljava/lang/String;Lorg/hibernate/dialect/function/SQLFunction;)V
     608: aload_0
     609: ldc           #85                 // String hextoint
     611: new           #13                 // class org/hibernate/dialect/function/SQLFunctionTemplate
     614: dup
     615: getstatic     #14                 // Field org/hibernate/type/StandardBasicTypes.INTEGER:Lorg/hibernate/type/IntegerType;
     618: ldc           #86                 // String hextoint(?1)
     620: invokespecial #16                 // Method org/hibernate/dialect/function/SQLFunctionTemplate."<init>":(Lorg/hibernate/type/Type;Ljava/lang/String;)V
     623: invokevirtual #17                 // Method registerFunction:(Ljava/lang/String;Lorg/hibernate/dialect/function/SQLFunction;)V
     626: aload_0
     627: ldc           #87                 // String host_id
     629: new           #13                 // class org/hibernate/dialect/function/SQLFunctionTemplate
     632: dup
     633: getstatic     #14                 // Field org/hibernate/type/StandardBasicTypes.INTEGER:Lorg/hibernate/type/IntegerType;
     636: ldc           #87                 // String host_id
     638: invokespecial #16                 // Method org/hibernate/dialect/function/SQLFunctionTemplate."<init>":(Lorg/hibernate/type/Type;Ljava/lang/String;)V
     641: invokevirtual #17                 // Method registerFunction:(Ljava/lang/String;Lorg/hibernate/dialect/function/SQLFunction;)V
     644: aload_0
     645: ldc           #88                 // String host_name
     647: new           #13                 // class org/hibernate/dialect/function/SQLFunctionTemplate
     650: dup
     651: getstatic     #39                 // Field org/hibernate/type/StandardBasicTypes.STRING:Lorg/hibernate/type/StringType;
     654: ldc           #88                 // String host_name
     656: invokespecial #16                 // Method org/hibernate/dialect/function/SQLFunctionTemplate."<init>":(Lorg/hibernate/type/Type;Ljava/lang/String;)V
     659: invokevirtual #17                 // Method registerFunction:(Ljava/lang/String;Lorg/hibernate/dialect/function/SQLFunction;)V
     662: aload_0
     663: ldc           #89                 // String inttohex
     665: new           #13                 // class org/hibernate/dialect/function/SQLFunctionTemplate
     668: dup
     669: getstatic     #39                 // Field org/hibernate/type/StandardBasicTypes.STRING:Lorg/hibernate/type/StringType;
     672: ldc           #90                 // String inttohex(?1)
     674: invokespecial #16                 // Method org/hibernate/dialect/function/SQLFunctionTemplate."<init>":(Lorg/hibernate/type/Type;Ljava/lang/String;)V
     677: invokevirtual #17                 // Method registerFunction:(Ljava/lang/String;Lorg/hibernate/dialect/function/SQLFunction;)V
     680: aload_0
     681: ldc           #91                 // String is_quiesced
     683: new           #13                 // class org/hibernate/dialect/function/SQLFunctionTemplate
     686: dup
     687: getstatic     #14                 // Field org/hibernate/type/StandardBasicTypes.INTEGER:Lorg/hibernate/type/IntegerType;
     690: ldc           #92                 // String is_quiesced(?1)
     692: invokespecial #16                 // Method org/hibernate/dialect/function/SQLFunctionTemplate."<init>":(Lorg/hibernate/type/Type;Ljava/lang/String;)V
     695: invokevirtual #17                 // Method registerFunction:(Ljava/lang/String;Lorg/hibernate/dialect/function/SQLFunction;)V
     698: aload_0
     699: ldc           #93                 // String is_sec_service_on
     701: new           #13                 // class org/hibernate/dialect/function/SQLFunctionTemplate
     704: dup
     705: getstatic     #94                 // Field org/hibernate/type/StandardBasicTypes.BOOLEAN:Lorg/hibernate/type/BooleanType;
     708: ldc           #95                 // String is_sec_service_on(?1)
     710: invokespecial #16                 // Method org/hibernate/dialect/function/SQLFunctionTemplate."<init>":(Lorg/hibernate/type/Type;Ljava/lang/String;)V
     713: invokevirtual #17                 // Method registerFunction:(Ljava/lang/String;Lorg/hibernate/dialect/function/SQLFunction;)V
     716: aload_0
     717: ldc           #96                 // String object_id
     719: new           #13                 // class org/hibernate/dialect/function/SQLFunctionTemplate
     722: dup
     723: getstatic     #14                 // Field org/hibernate/type/StandardBasicTypes.INTEGER:Lorg/hibernate/type/IntegerType;
     726: ldc           #97                 // String object_id(?1)
     728: invokespecial #16                 // Method org/hibernate/dialect/function/SQLFunctionTemplate."<init>":(Lorg/hibernate/type/Type;Ljava/lang/String;)V
     731: invokevirtual #17                 // Method registerFunction:(Ljava/lang/String;Lorg/hibernate/dialect/function/SQLFunction;)V
     734: aload_0
     735: ldc           #98                 // String object_name
     737: new           #13                 // class org/hibernate/dialect/function/SQLFunctionTemplate
     740: dup
     741: getstatic     #39                 // Field org/hibernate/type/StandardBasicTypes.STRING:Lorg/hibernate/type/StringType;
     744: ldc           #99                 // String object_name(?1)
     746: invokespecial #16                 // Method org/hibernate/dialect/function/SQLFunctionTemplate."<init>":(Lorg/hibernate/type/Type;Ljava/lang/String;)V
     749: invokevirtual #17                 // Method registerFunction:(Ljava/lang/String;Lorg/hibernate/dialect/function/SQLFunction;)V
     752: aload_0
     753: ldc           #100                // String pagesize
     755: new           #13                 // class org/hibernate/dialect/function/SQLFunctionTemplate
     758: dup
     759: getstatic     #14                 // Field org/hibernate/type/StandardBasicTypes.INTEGER:Lorg/hibernate/type/IntegerType;
     762: ldc           #101                // String pagesize(?1)
     764: invokespecial #16                 // Method org/hibernate/dialect/function/SQLFunctionTemplate."<init>":(Lorg/hibernate/type/Type;Ljava/lang/String;)V
     767: invokevirtual #17                 // Method registerFunction:(Ljava/lang/String;Lorg/hibernate/dialect/function/SQLFunction;)V
     770: aload_0
     771: ldc           #100                // String pagesize
     773: new           #13                 // class org/hibernate/dialect/function/SQLFunctionTemplate
     776: dup
     777: getstatic     #14                 // Field org/hibernate/type/StandardBasicTypes.INTEGER:Lorg/hibernate/type/IntegerType;
     780: ldc           #102                // String pagesize(?1, ?2)
     782: invokespecial #16                 // Method org/hibernate/dialect/function/SQLFunctionTemplate."<init>":(Lorg/hibernate/type/Type;Ljava/lang/String;)V
     785: invokevirtual #17                 // Method registerFunction:(Ljava/lang/String;Lorg/hibernate/dialect/function/SQLFunction;)V
     788: aload_0
     789: ldc           #100                // String pagesize
     791: new           #13                 // class org/hibernate/dialect/function/SQLFunctionTemplate
     794: dup
     795: getstatic     #14                 // Field org/hibernate/type/StandardBasicTypes.INTEGER:Lorg/hibernate/type/IntegerType;
     798: ldc           #103                // String pagesize(?1, ?2, ?3)
     800: invokespecial #16                 // Method org/hibernate/dialect/function/SQLFunctionTemplate."<init>":(Lorg/hibernate/type/Type;Ljava/lang/String;)V
     803: invokevirtual #17                 // Method registerFunction:(Ljava/lang/String;Lorg/hibernate/dialect/function/SQLFunction;)V
     806: aload_0
     807: ldc           #104                // String partition_id
     809: new           #13                 // class org/hibernate/dialect/function/SQLFunctionTemplate
     812: dup
     813: getstatic     #14                 // Field org/hibernate/type/StandardBasicTypes.INTEGER:Lorg/hibernate/type/IntegerType;
     816: ldc           #105                // String partition_id(?1, ?2)
     818: invokespecial #16                 // Method org/hibernate/dialect/function/SQLFunctionTemplate."<init>":(Lorg/hibernate/type/Type;Ljava/lang/String;)V
     821: invokevirtual #17                 // Method registerFunction:(Ljava/lang/String;Lorg/hibernate/dialect/function/SQLFunction;)V
     824: aload_0
     825: ldc           #104                // String partition_id
     827: new           #13                 // class org/hibernate/dialect/function/SQLFunctionTemplate
     830: dup
     831: getstatic     #14                 // Field org/hibernate/type/StandardBasicTypes.INTEGER:Lorg/hibernate/type/IntegerType;
     834: ldc           #106                // String partition_id(?1, ?2, ?3)
     836: invokespecial #16                 // Method org/hibernate/dialect/function/SQLFunctionTemplate."<init>":(Lorg/hibernate/type/Type;Ljava/lang/String;)V
     839: invokevirtual #17                 // Method registerFunction:(Ljava/lang/String;Lorg/hibernate/dialect/function/SQLFunction;)V
     842: aload_0
     843: ldc           #107                // String partition_name
     845: new           #13                 // class org/hibernate/dialect/function/SQLFunctionTemplate
     848: dup
     849: getstatic     #39                 // Field org/hibernate/type/StandardBasicTypes.STRING:Lorg/hibernate/type/StringType;
     852: ldc           #108                // String partition_name(?1, ?2)
     854: invokespecial #16                 // Method org/hibernate/dialect/function/SQLFunctionTemplate."<init>":(Lorg/hibernate/type/Type;Ljava/lang/String;)V
     857: invokevirtual #17                 // Method registerFunction:(Ljava/lang/String;Lorg/hibernate/dialect/function/SQLFunction;)V
     860: aload_0
     861: ldc           #107                // String partition_name
     863: new           #13                 // class org/hibernate/dialect/function/SQLFunctionTemplate
     866: dup
     867: getstatic     #39                 // Field org/hibernate/type/StandardBasicTypes.STRING:Lorg/hibernate/type/StringType;
     870: ldc           #109                // String partition_name(?1, ?2, ?3)
     872: invokespecial #16                 // Method org/hibernate/dialect/function/SQLFunctionTemplate."<init>":(Lorg/hibernate/type/Type;Ljava/lang/String;)V
     875: invokevirtual #17                 // Method registerFunction:(Ljava/lang/String;Lorg/hibernate/dialect/function/SQLFunction;)V
     878: aload_0
     879: ldc           #110                // String patindex
     881: new           #13                 // class org/hibernate/dialect/function/SQLFunctionTemplate
     884: dup
     885: getstatic     #14                 // Field org/hibernate/type/StandardBasicTypes.INTEGER:Lorg/hibernate/type/IntegerType;
     888: ldc           #110                // String patindex
     890: invokespecial #16                 // Method org/hibernate/dialect/function/SQLFunctionTemplate."<init>":(Lorg/hibernate/type/Type;Ljava/lang/String;)V
     893: invokevirtual #17                 // Method registerFunction:(Ljava/lang/String;Lorg/hibernate/dialect/function/SQLFunction;)V
     896: aload_0
     897: ldc           #111                // String proc_role
     899: new           #13                 // class org/hibernate/dialect/function/SQLFunctionTemplate
     902: dup
     903: getstatic     #14                 // Field org/hibernate/type/StandardBasicTypes.INTEGER:Lorg/hibernate/type/IntegerType;
     906: ldc           #111                // String proc_role
     908: invokespecial #16                 // Method org/hibernate/dialect/function/SQLFunctionTemplate."<init>":(Lorg/hibernate/type/Type;Ljava/lang/String;)V
     911: invokevirtual #17                 // Method registerFunction:(Ljava/lang/String;Lorg/hibernate/dialect/function/SQLFunction;)V
     914: aload_0
     915: ldc           #112                // String role_name
     917: new           #13                 // class org/hibernate/dialect/function/SQLFunctionTemplate
     920: dup
     921: getstatic     #39                 // Field org/hibernate/type/StandardBasicTypes.STRING:Lorg/hibernate/type/StringType;
     924: ldc           #112                // String role_name
     926: invokespecial #16                 // Method org/hibernate/dialect/function/SQLFunctionTemplate."<init>":(Lorg/hibernate/type/Type;Ljava/lang/String;)V
     929: invokevirtual #17                 // Method registerFunction:(Ljava/lang/String;Lorg/hibernate/dialect/function/SQLFunction;)V
     932: aload_0
     933: ldc           #113                // String row_count
     935: new           #13                 // class org/hibernate/dialect/function/SQLFunctionTemplate
     938: dup
     939: getstatic     #14                 // Field org/hibernate/type/StandardBasicTypes.INTEGER:Lorg/hibernate/type/IntegerType;
     942: ldc           #113                // String row_count
     944: invokespecial #16                 // Method org/hibernate/dialect/function/SQLFunctionTemplate."<init>":(Lorg/hibernate/type/Type;Ljava/lang/String;)V
     947: invokevirtual #17                 // Method registerFunction:(Ljava/lang/String;Lorg/hibernate/dialect/function/SQLFunction;)V
     950: aload_0
     951: ldc           #114                // String rand2
     953: new           #13                 // class org/hibernate/dialect/function/SQLFunctionTemplate
     956: dup
     957: getstatic     #35                 // Field org/hibernate/type/StandardBasicTypes.DOUBLE:Lorg/hibernate/type/DoubleType;
     960: ldc           #115                // String rand2(?1)
     962: invokespecial #16                 // Method org/hibernate/dialect/function/SQLFunctionTemplate."<init>":(Lorg/hibernate/type/Type;Ljava/lang/String;)V
     965: invokevirtual #17                 // Method registerFunction:(Ljava/lang/String;Lorg/hibernate/dialect/function/SQLFunction;)V
     968: aload_0
     969: ldc           #114                // String rand2
     971: new           #13                 // class org/hibernate/dialect/function/SQLFunctionTemplate
     974: dup
     975: getstatic     #35                 // Field org/hibernate/type/StandardBasicTypes.DOUBLE:Lorg/hibernate/type/DoubleType;
     978: ldc           #114                // String rand2
     980: invokespecial #16                 // Method org/hibernate/dialect/function/SQLFunctionTemplate."<init>":(Lorg/hibernate/type/Type;Ljava/lang/String;)V
     983: invokevirtual #17                 // Method registerFunction:(Ljava/lang/String;Lorg/hibernate/dialect/function/SQLFunction;)V
     986: aload_0
     987: ldc           #116                // String replicate
     989: new           #13                 // class org/hibernate/dialect/function/SQLFunctionTemplate
     992: dup
     993: getstatic     #39                 // Field org/hibernate/type/StandardBasicTypes.STRING:Lorg/hibernate/type/StringType;
     996: ldc           #117                // String replicate(?1,?2)
     998: invokespecial #16                 // Method org/hibernate/dialect/function/SQLFunctionTemplate."<init>":(Lorg/hibernate/type/Type;Ljava/lang/String;)V
    1001: invokevirtual #17                 // Method registerFunction:(Ljava/lang/String;Lorg/hibernate/dialect/function/SQLFunction;)V
    1004: aload_0
    1005: ldc           #118                // String role_contain
    1007: new           #13                 // class org/hibernate/dialect/function/SQLFunctionTemplate
    1010: dup
    1011: getstatic     #94                 // Field org/hibernate/type/StandardBasicTypes.BOOLEAN:Lorg/hibernate/type/BooleanType;
    1014: ldc           #118                // String role_contain
    1016: invokespecial #16                 // Method org/hibernate/dialect/function/SQLFunctionTemplate."<init>":(Lorg/hibernate/type/Type;Ljava/lang/String;)V
    1019: invokevirtual #17                 // Method registerFunction:(Ljava/lang/String;Lorg/hibernate/dialect/function/SQLFunction;)V
    1022: aload_0
    1023: ldc           #119                // String role_id
    1025: new           #13                 // class org/hibernate/dialect/function/SQLFunctionTemplate
    1028: dup
    1029: getstatic     #14                 // Field org/hibernate/type/StandardBasicTypes.INTEGER:Lorg/hibernate/type/IntegerType;
    1032: ldc           #119                // String role_id
    1034: invokespecial #16                 // Method org/hibernate/dialect/function/SQLFunctionTemplate."<init>":(Lorg/hibernate/type/Type;Ljava/lang/String;)V
    1037: invokevirtual #17                 // Method registerFunction:(Ljava/lang/String;Lorg/hibernate/dialect/function/SQLFunction;)V
    1040: aload_0
    1041: ldc           #120                // String reserved_pages
    1043: new           #13                 // class org/hibernate/dialect/function/SQLFunctionTemplate
    1046: dup
    1047: getstatic     #14                 // Field org/hibernate/type/StandardBasicTypes.INTEGER:Lorg/hibernate/type/IntegerType;
    1050: ldc           #120                // String reserved_pages
    1052: invokespecial #16                 // Method org/hibernate/dialect/function/SQLFunctionTemplate."<init>":(Lorg/hibernate/type/Type;Ljava/lang/String;)V
    1055: invokevirtual #17                 // Method registerFunction:(Ljava/lang/String;Lorg/hibernate/dialect/function/SQLFunction;)V
    1058: aload_0
    1059: ldc           #121                // String right
    1061: new           #13                 // class org/hibernate/dialect/function/SQLFunctionTemplate
    1064: dup
    1065: getstatic     #39                 // Field org/hibernate/type/StandardBasicTypes.STRING:Lorg/hibernate/type/StringType;
    1068: ldc           #121                // String right
    1070: invokespecial #16                 // Method org/hibernate/dialect/function/SQLFunctionTemplate."<init>":(Lorg/hibernate/type/Type;Ljava/lang/String;)V
    1073: invokevirtual #17                 // Method registerFunction:(Ljava/lang/String;Lorg/hibernate/dialect/function/SQLFunction;)V
    1076: aload_0
    1077: ldc           #122                // String show_role
    1079: new           #13                 // class org/hibernate/dialect/function/SQLFunctionTemplate
    1082: dup
    1083: getstatic     #39                 // Field org/hibernate/type/StandardBasicTypes.STRING:Lorg/hibernate/type/StringType;
    1086: ldc           #122                // String show_role
    1088: invokespecial #16                 // Method org/hibernate/dialect/function/SQLFunctionTemplate."<init>":(Lorg/hibernate/type/Type;Ljava/lang/String;)V
    1091: invokevirtual #17                 // Method registerFunction:(Ljava/lang/String;Lorg/hibernate/dialect/function/SQLFunction;)V
    1094: aload_0
    1095: ldc           #123                // String show_sec_services
    1097: new           #13                 // class org/hibernate/dialect/function/SQLFunctionTemplate
    1100: dup
    1101: getstatic     #39                 // Field org/hibernate/type/StandardBasicTypes.STRING:Lorg/hibernate/type/StringType;
    1104: ldc           #123                // String show_sec_services
    1106: invokespecial #16                 // Method org/hibernate/dialect/function/SQLFunctionTemplate."<init>":(Lorg/hibernate/type/Type;Ljava/lang/String;)V
    1109: invokevirtual #17                 // Method registerFunction:(Ljava/lang/String;Lorg/hibernate/dialect/function/SQLFunction;)V
    1112: aload_0
    1113: ldc           #124                // String sortkey
    1115: new           #46                 // class org/hibernate/dialect/function/VarArgsSQLFunction
    1118: dup
    1119: getstatic     #125                // Field org/hibernate/type/StandardBasicTypes.BINARY:Lorg/hibernate/type/BinaryType;
    1122: ldc           #126                // String sortkey(
    1124: ldc           #48                 // String ,
    1126: ldc           #49                 // String )
    1128: invokespecial #127                // Method org/hibernate/dialect/function/VarArgsSQLFunction."<init>":(Lorg/hibernate/type/Type;Ljava/lang/String;Ljava/lang/String;Ljava/lang/String;)V
    1131: invokevirtual #17                 // Method registerFunction:(Ljava/lang/String;Lorg/hibernate/dialect/function/SQLFunction;)V
    1134: aload_0
    1135: ldc           #128                // String soundex
    1137: new           #13                 // class org/hibernate/dialect/function/SQLFunctionTemplate
    1140: dup
    1141: getstatic     #39                 // Field org/hibernate/type/StandardBasicTypes.STRING:Lorg/hibernate/type/StringType;
    1144: ldc           #129                // String sounded
    1146: invokespecial #16                 // Method org/hibernate/dialect/function/SQLFunctionTemplate."<init>":(Lorg/hibernate/type/Type;Ljava/lang/String;)V
    1149: invokevirtual #17                 // Method registerFunction:(Ljava/lang/String;Lorg/hibernate/dialect/function/SQLFunction;)V
    1152: aload_0
    1153: ldc           #130                // String stddev
    1155: new           #13                 // class org/hibernate/dialect/function/SQLFunctionTemplate
    1158: dup
    1159: getstatic     #35                 // Field org/hibernate/type/StandardBasicTypes.DOUBLE:Lorg/hibernate/type/DoubleType;
    1162: ldc           #130                // String stddev
    1164: invokespecial #16                 // Method org/hibernate/dialect/function/SQLFunctionTemplate."<init>":(Lorg/hibernate/type/Type;Ljava/lang/String;)V
    1167: invokevirtual #17                 // Method registerFunction:(Ljava/lang/String;Lorg/hibernate/dialect/function/SQLFunction;)V
    1170: aload_0
    1171: ldc           #131                // String stddev_pop
    1173: new           #13                 // class org/hibernate/dialect/function/SQLFunctionTemplate
    1176: dup
    1177: getstatic     #35                 // Field org/hibernate/type/StandardBasicTypes.DOUBLE:Lorg/hibernate/type/DoubleType;
    1180: ldc           #131                // String stddev_pop
    1182: invokespecial #16                 // Method org/hibernate/dialect/function/SQLFunctionTemplate."<init>":(Lorg/hibernate/type/Type;Ljava/lang/String;)V
    1185: invokevirtual #17                 // Method registerFunction:(Ljava/lang/String;Lorg/hibernate/dialect/function/SQLFunction;)V
    1188: aload_0
    1189: ldc           #132                // String stddev_samp
    1191: new           #13                 // class org/hibernate/dialect/function/SQLFunctionTemplate
    1194: dup
    1195: getstatic     #35                 // Field org/hibernate/type/StandardBasicTypes.DOUBLE:Lorg/hibernate/type/DoubleType;
    1198: ldc           #132                // String stddev_samp
    1200: invokespecial #16                 // Method org/hibernate/dialect/function/SQLFunctionTemplate."<init>":(Lorg/hibernate/type/Type;Ljava/lang/String;)V
    1203: invokevirtual #17                 // Method registerFunction:(Ljava/lang/String;Lorg/hibernate/dialect/function/SQLFunction;)V
    1206: aload_0
    1207: ldc           #133                // String stuff
    1209: new           #13                 // class org/hibernate/dialect/function/SQLFunctionTemplate
    1212: dup
    1213: getstatic     #39                 // Field org/hibernate/type/StandardBasicTypes.STRING:Lorg/hibernate/type/StringType;
    1216: ldc           #133                // String stuff
    1218: invokespecial #16                 // Method org/hibernate/dialect/function/SQLFunctionTemplate."<init>":(Lorg/hibernate/type/Type;Ljava/lang/String;)V
    1221: invokevirtual #17                 // Method registerFunction:(Ljava/lang/String;Lorg/hibernate/dialect/function/SQLFunction;)V
    1224: aload_0
    1225: ldc           #134                // String substring
    1227: new           #46                 // class org/hibernate/dialect/function/VarArgsSQLFunction
    1230: dup
    1231: getstatic     #39                 // Field org/hibernate/type/StandardBasicTypes.STRING:Lorg/hibernate/type/StringType;
    1234: ldc           #135                // String substring(
    1236: ldc           #48                 // String ,
    1238: ldc           #49                 // String )
    1240: invokespecial #127                // Method org/hibernate/dialect/function/VarArgsSQLFunction."<init>":(Lorg/hibernate/type/Type;Ljava/lang/String;Ljava/lang/String;Ljava/lang/String;)V
    1243: invokevirtual #17                 // Method registerFunction:(Ljava/lang/String;Lorg/hibernate/dialect/function/SQLFunction;)V
    1246: aload_0
    1247: ldc           #136                // String suser_id
    1249: new           #13                 // class org/hibernate/dialect/function/SQLFunctionTemplate
    1252: dup
    1253: getstatic     #14                 // Field org/hibernate/type/StandardBasicTypes.INTEGER:Lorg/hibernate/type/IntegerType;
    1256: ldc           #136                // String suser_id
    1258: invokespecial #16                 // Method org/hibernate/dialect/function/SQLFunctionTemplate."<init>":(Lorg/hibernate/type/Type;Ljava/lang/String;)V
    1261: invokevirtual #17                 // Method registerFunction:(Ljava/lang/String;Lorg/hibernate/dialect/function/SQLFunction;)V
    1264: aload_0
    1265: ldc           #137                // String suser_name
    1267: new           #13                 // class org/hibernate/dialect/function/SQLFunctionTemplate
    1270: dup
    1271: getstatic     #39                 // Field org/hibernate/type/StandardBasicTypes.STRING:Lorg/hibernate/type/StringType;
    1274: ldc           #137                // String suser_name
    1276: invokespecial #16                 // Method org/hibernate/dialect/function/SQLFunctionTemplate."<init>":(Lorg/hibernate/type/Type;Ljava/lang/String;)V
    1279: invokevirtual #17                 // Method registerFunction:(Ljava/lang/String;Lorg/hibernate/dialect/function/SQLFunction;)V
    1282: aload_0
    1283: ldc           #138                // String tempdb_id
    1285: new           #13                 // class org/hibernate/dialect/function/SQLFunctionTemplate
    1288: dup
    1289: getstatic     #14                 // Field org/hibernate/type/StandardBasicTypes.INTEGER:Lorg/hibernate/type/IntegerType;
    1292: ldc           #138                // String tempdb_id
    1294: invokespecial #16                 // Method org/hibernate/dialect/function/SQLFunctionTemplate."<init>":(Lorg/hibernate/type/Type;Ljava/lang/String;)V
    1297: invokevirtual #17                 // Method registerFunction:(Ljava/lang/String;Lorg/hibernate/dialect/function/SQLFunction;)V
    1300: aload_0
    1301: ldc           #139                // String textvalid
    1303: new           #13                 // class org/hibernate/dialect/function/SQLFunctionTemplate
    1306: dup
    1307: getstatic     #94                 // Field org/hibernate/type/StandardBasicTypes.BOOLEAN:Lorg/hibernate/type/BooleanType;
    1310: ldc           #139                // String textvalid
    1312: invokespecial #16                 // Method org/hibernate/dialect/function/SQLFunctionTemplate."<init>":(Lorg/hibernate/type/Type;Ljava/lang/String;)V
    1315: invokevirtual #17                 // Method registerFunction:(Ljava/lang/String;Lorg/hibernate/dialect/function/SQLFunction;)V
    1318: aload_0
    1319: ldc           #140                // String to_unichar
    1321: new           #13                 // class org/hibernate/dialect/function/SQLFunctionTemplate
    1324: dup
    1325: getstatic     #39                 // Field org/hibernate/type/StandardBasicTypes.STRING:Lorg/hibernate/type/StringType;
    1328: ldc           #141                // String to_unichar(?1)
    1330: invokespecial #16                 // Method org/hibernate/dialect/function/SQLFunctionTemplate."<init>":(Lorg/hibernate/type/Type;Ljava/lang/String;)V
    1333: invokevirtual #17                 // Method registerFunction:(Ljava/lang/String;Lorg/hibernate/dialect/function/SQLFunction;)V
    1336: aload_0
    1337: ldc           #142                // String tran_dumptable_status
    1339: new           #13                 // class org/hibernate/dialect/function/SQLFunctionTemplate
    1342: dup
    1343: getstatic     #14                 // Field org/hibernate/type/StandardBasicTypes.INTEGER:Lorg/hibernate/type/IntegerType;
    1346: ldc           #143                // String ran_dumptable_status(?1)
    1348: invokespecial #16                 // Method org/hibernate/dialect/function/SQLFunctionTemplate."<init>":(Lorg/hibernate/type/Type;Ljava/lang/String;)V
    1351: invokevirtual #17                 // Method registerFunction:(Ljava/lang/String;Lorg/hibernate/dialect/function/SQLFunction;)V
    1354: aload_0
    1355: ldc           #144                // String uhighsurr
    1357: new           #13                 // class org/hibernate/dialect/function/SQLFunctionTemplate
    1360: dup
    1361: getstatic     #94                 // Field org/hibernate/type/StandardBasicTypes.BOOLEAN:Lorg/hibernate/type/BooleanType;
    1364: ldc           #144                // String uhighsurr
    1366: invokespecial #16                 // Method org/hibernate/dialect/function/SQLFunctionTemplate."<init>":(Lorg/hibernate/type/Type;Ljava/lang/String;)V
    1369: invokevirtual #17                 // Method registerFunction:(Ljava/lang/String;Lorg/hibernate/dialect/function/SQLFunction;)V
    1372: aload_0
    1373: ldc           #145                // String ulowsurr
    1375: new           #13                 // class org/hibernate/dialect/function/SQLFunctionTemplate
    1378: dup
    1379: getstatic     #94                 // Field org/hibernate/type/StandardBasicTypes.BOOLEAN:Lorg/hibernate/type/BooleanType;
    1382: ldc           #145                // String ulowsurr
    1384: invokespecial #16                 // Method org/hibernate/dialect/function/SQLFunctionTemplate."<init>":(Lorg/hibernate/type/Type;Ljava/lang/String;)V
    1387: invokevirtual #17                 // Method registerFunction:(Ljava/lang/String;Lorg/hibernate/dialect/function/SQLFunction;)V
    1390: aload_0
    1391: ldc           #146                // String uscalar
    1393: new           #13                 // class org/hibernate/dialect/function/SQLFunctionTemplate
    1396: dup
    1397: getstatic     #14                 // Field org/hibernate/type/StandardBasicTypes.INTEGER:Lorg/hibernate/type/IntegerType;
    1400: ldc           #146                // String uscalar
    1402: invokespecial #16                 // Method org/hibernate/dialect/function/SQLFunctionTemplate."<init>":(Lorg/hibernate/type/Type;Ljava/lang/String;)V
    1405: invokevirtual #17                 // Method registerFunction:(Ljava/lang/String;Lorg/hibernate/dialect/function/SQLFunction;)V
    1408: aload_0
    1409: ldc           #147                // String used_pages
    1411: new           #13                 // class org/hibernate/dialect/function/SQLFunctionTemplate
    1414: dup
    1415: getstatic     #14                 // Field org/hibernate/type/StandardBasicTypes.INTEGER:Lorg/hibernate/type/IntegerType;
    1418: ldc           #147                // String used_pages
    1420: invokespecial #16                 // Method org/hibernate/dialect/function/SQLFunctionTemplate."<init>":(Lorg/hibernate/type/Type;Ljava/lang/String;)V
    1423: invokevirtual #17                 // Method registerFunction:(Ljava/lang/String;Lorg/hibernate/dialect/function/SQLFunction;)V
    1426: aload_0
    1427: ldc           #148                // String user_id
    1429: new           #13                 // class org/hibernate/dialect/function/SQLFunctionTemplate
    1432: dup
    1433: getstatic     #14                 // Field org/hibernate/type/StandardBasicTypes.INTEGER:Lorg/hibernate/type/IntegerType;
    1436: ldc           #148                // String user_id
    1438: invokespecial #16                 // Method org/hibernate/dialect/function/SQLFunctionTemplate."<init>":(Lorg/hibernate/type/Type;Ljava/lang/String;)V
    1441: invokevirtual #17                 // Method registerFunction:(Ljava/lang/String;Lorg/hibernate/dialect/function/SQLFunction;)V
    1444: aload_0
    1445: ldc           #149                // String user_name
    1447: new           #13                 // class org/hibernate/dialect/function/SQLFunctionTemplate
    1450: dup
    1451: getstatic     #39                 // Field org/hibernate/type/StandardBasicTypes.STRING:Lorg/hibernate/type/StringType;
    1454: ldc           #149                // String user_name
    1456: invokespecial #16                 // Method org/hibernate/dialect/function/SQLFunctionTemplate."<init>":(Lorg/hibernate/type/Type;Ljava/lang/String;)V
    1459: invokevirtual #17                 // Method registerFunction:(Ljava/lang/String;Lorg/hibernate/dialect/function/SQLFunction;)V
    1462: aload_0
    1463: ldc           #150                // String valid_name
    1465: new           #13                 // class org/hibernate/dialect/function/SQLFunctionTemplate
    1468: dup
    1469: getstatic     #14                 // Field org/hibernate/type/StandardBasicTypes.INTEGER:Lorg/hibernate/type/IntegerType;
    1472: ldc           #150                // String valid_name
    1474: invokespecial #16                 // Method org/hibernate/dialect/function/SQLFunctionTemplate."<init>":(Lorg/hibernate/type/Type;Ljava/lang/String;)V
    1477: invokevirtual #17                 // Method registerFunction:(Ljava/lang/String;Lorg/hibernate/dialect/function/SQLFunction;)V
    1480: aload_0
    1481: ldc           #151                // String valid_user
    1483: new           #13                 // class org/hibernate/dialect/function/SQLFunctionTemplate
    1486: dup
    1487: getstatic     #14                 // Field org/hibernate/type/StandardBasicTypes.INTEGER:Lorg/hibernate/type/IntegerType;
    1490: ldc           #151                // String valid_user
    1492: invokespecial #16                 // Method org/hibernate/dialect/function/SQLFunctionTemplate."<init>":(Lorg/hibernate/type/Type;Ljava/lang/String;)V
    1495: invokevirtual #17                 // Method registerFunction:(Ljava/lang/String;Lorg/hibernate/dialect/function/SQLFunction;)V
    1498: aload_0
    1499: ldc           #152                // String variance
    1501: new           #13                 // class org/hibernate/dialect/function/SQLFunctionTemplate
    1504: dup
    1505: getstatic     #35                 // Field org/hibernate/type/StandardBasicTypes.DOUBLE:Lorg/hibernate/type/DoubleType;
    1508: ldc           #152                // String variance
    1510: invokespecial #16                 // Method org/hibernate/dialect/function/SQLFunctionTemplate."<init>":(Lorg/hibernate/type/Type;Ljava/lang/String;)V
    1513: invokevirtual #17                 // Method registerFunction:(Ljava/lang/String;Lorg/hibernate/dialect/function/SQLFunction;)V
    1516: aload_0
    1517: ldc           #153                // String var_pop
    1519: new           #13                 // class org/hibernate/dialect/function/SQLFunctionTemplate
    1522: dup
    1523: getstatic     #35                 // Field org/hibernate/type/StandardBasicTypes.DOUBLE:Lorg/hibernate/type/DoubleType;
    1526: ldc           #153                // String var_pop
    1528: invokespecial #16                 // Method org/hibernate/dialect/function/SQLFunctionTemplate."<init>":(Lorg/hibernate/type/Type;Ljava/lang/String;)V
    1531: invokevirtual #17                 // Method registerFunction:(Ljava/lang/String;Lorg/hibernate/dialect/function/SQLFunction;)V
    1534: aload_0
    1535: ldc           #154                // String var_samp
    1537: new           #13                 // class org/hibernate/dialect/function/SQLFunctionTemplate
    1540: dup
    1541: getstatic     #35                 // Field org/hibernate/type/StandardBasicTypes.DOUBLE:Lorg/hibernate/type/DoubleType;
    1544: ldc           #154                // String var_samp
    1546: invokespecial #16                 // Method org/hibernate/dialect/function/SQLFunctionTemplate."<init>":(Lorg/hibernate/type/Type;Ljava/lang/String;)V
    1549: invokevirtual #17                 // Method registerFunction:(Ljava/lang/String;Lorg/hibernate/dialect/function/SQLFunction;)V
    1552: aload_0
    1553: ldc           #155                // String sysdate
    1555: new           #56                 // class org/hibernate/dialect/function/NoArgSQLFunction
    1558: dup
    1559: ldc           #156                // String getdate
    1561: getstatic     #68                 // Field org/hibernate/type/StandardBasicTypes.TIMESTAMP:Lorg/hibernate/type/TimestampType;
    1564: invokespecial #58                 // Method org/hibernate/dialect/function/NoArgSQLFunction."<init>":(Ljava/lang/String;Lorg/hibernate/type/Type;)V
    1567: invokevirtual #17                 // Method registerFunction:(Ljava/lang/String;Lorg/hibernate/dialect/function/SQLFunction;)V
    1570: aload_0
    1571: invokespecial #157                // Method registerSybaseKeywords:()V
    1574: return

  private void registerSybaseKeywords();
    Code:
       0: aload_0
       1: ldc           #158                // String add
       3: invokevirtual #159                // Method registerKeyword:(Ljava/lang/String;)V
       6: aload_0
       7: ldc           #160                // String all
       9: invokevirtual #159                // Method registerKeyword:(Ljava/lang/String;)V
      12: aload_0
      13: ldc           #161                // String alter
      15: invokevirtual #159                // Method registerKeyword:(Ljava/lang/String;)V
      18: aload_0
      19: ldc           #162                // String and
      21: invokevirtual #159                // Method registerKeyword:(Ljava/lang/String;)V
      24: aload_0
      25: ldc           #163                // String any
      27: invokevirtual #159                // Method registerKeyword:(Ljava/lang/String;)V
      30: aload_0
      31: ldc           #164                // String arith_overflow
      33: invokevirtual #159                // Method registerKeyword:(Ljava/lang/String;)V
      36: aload_0
      37: ldc           #165                // String as
      39: invokevirtual #159                // Method registerKeyword:(Ljava/lang/String;)V
      42: aload_0
      43: ldc           #166                // String asc
      45: invokevirtual #159                // Method registerKeyword:(Ljava/lang/String;)V
      48: aload_0
      49: ldc           #167                // String at
      51: invokevirtual #159                // Method registerKeyword:(Ljava/lang/String;)V
      54: aload_0
      55: ldc           #168                // String authorization
      57: invokevirtual #159                // Method registerKeyword:(Ljava/lang/String;)V
      60: aload_0
      61: ldc           #169                // String avg
      63: invokevirtual #159                // Method registerKeyword:(Ljava/lang/String;)V
      66: aload_0
      67: ldc           #170                // String begin
      69: invokevirtual #159                // Method registerKeyword:(Ljava/lang/String;)V
      72: aload_0
      73: ldc           #171                // String between
      75: invokevirtual #159                // Method registerKeyword:(Ljava/lang/String;)V
      78: aload_0
      79: ldc           #172                // String break
      81: invokevirtual #159                // Method registerKeyword:(Ljava/lang/String;)V
      84: aload_0
      85: ldc           #173                // String browse
      87: invokevirtual #159                // Method registerKeyword:(Ljava/lang/String;)V
      90: aload_0
      91: ldc           #174                // String bulk
      93: invokevirtual #159                // Method registerKeyword:(Ljava/lang/String;)V
      96: aload_0
      97: ldc           #175                // String by
      99: invokevirtual #159                // Method registerKeyword:(Ljava/lang/String;)V
     102: aload_0
     103: ldc           #176                // String cascade
     105: invokevirtual #159                // Method registerKeyword:(Ljava/lang/String;)V
     108: aload_0
     109: ldc           #177                // String case
     111: invokevirtual #159                // Method registerKeyword:(Ljava/lang/String;)V
     114: aload_0
     115: ldc           #178                // String char_convert
     117: invokevirtual #159                // Method registerKeyword:(Ljava/lang/String;)V
     120: aload_0
     121: ldc           #179                // String check
     123: invokevirtual #159                // Method registerKeyword:(Ljava/lang/String;)V
     126: aload_0
     127: ldc           #180                // String checkpoint
     129: invokevirtual #159                // Method registerKeyword:(Ljava/lang/String;)V
     132: aload_0
     133: ldc           #181                // String close
     135: invokevirtual #159                // Method registerKeyword:(Ljava/lang/String;)V
     138: aload_0
     139: ldc           #182                // String clustered
     141: invokevirtual #159                // Method registerKeyword:(Ljava/lang/String;)V
     144: aload_0
     145: ldc           #45                 // String coalesce
     147: invokevirtual #159                // Method registerKeyword:(Ljava/lang/String;)V
     150: aload_0
     151: ldc           #183                // String commit
     153: invokevirtual #159                // Method registerKeyword:(Ljava/lang/String;)V
     156: aload_0
     157: ldc           #184                // String compute
     159: invokevirtual #159                // Method registerKeyword:(Ljava/lang/String;)V
     162: aload_0
     163: ldc           #185                // String confirm
     165: invokevirtual #159                // Method registerKeyword:(Ljava/lang/String;)V
     168: aload_0
     169: ldc           #186                // String connect
     171: invokevirtual #159                // Method registerKeyword:(Ljava/lang/String;)V
     174: aload_0
     175: ldc           #187                // String constraint
     177: invokevirtual #159                // Method registerKeyword:(Ljava/lang/String;)V
     180: aload_0
     181: ldc           #188                // String continue
     183: invokevirtual #159                // Method registerKeyword:(Ljava/lang/String;)V
     186: aload_0
     187: ldc           #189                // String controlrow
     189: invokevirtual #159                // Method registerKeyword:(Ljava/lang/String;)V
     192: aload_0
     193: ldc           #190                // String convert
     195: invokevirtual #159                // Method registerKeyword:(Ljava/lang/String;)V
     198: aload_0
     199: ldc           #191                // String count
     201: invokevirtual #159                // Method registerKeyword:(Ljava/lang/String;)V
     204: aload_0
     205: ldc           #192                // String count_big
     207: invokevirtual #159                // Method registerKeyword:(Ljava/lang/String;)V
     210: aload_0
     211: ldc           #193                // String create
     213: invokevirtual #159                // Method registerKeyword:(Ljava/lang/String;)V
     216: aload_0
     217: ldc           #194                // String current
     219: invokevirtual #159                // Method registerKeyword:(Ljava/lang/String;)V
     222: aload_0
     223: ldc           #195                // String cursor
     225: invokevirtual #159                // Method registerKeyword:(Ljava/lang/String;)V
     228: aload_0
     229: ldc           #196                // String database
     231: invokevirtual #159                // Method registerKeyword:(Ljava/lang/String;)V
     234: aload_0
     235: ldc           #197                // String dbcc
     237: invokevirtual #159                // Method registerKeyword:(Ljava/lang/String;)V
     240: aload_0
     241: ldc           #198                // String deallocate
     243: invokevirtual #159                // Method registerKeyword:(Ljava/lang/String;)V
     246: aload_0
     247: ldc           #199                // String declare
     249: invokevirtual #159                // Method registerKeyword:(Ljava/lang/String;)V
     252: aload_0
     253: ldc           #200                // String decrypt
     255: invokevirtual #159                // Method registerKeyword:(Ljava/lang/String;)V
     258: aload_0
     259: ldc           #201                // String default
     261: invokevirtual #159                // Method registerKeyword:(Ljava/lang/String;)V
     264: aload_0
     265: ldc           #202                // String delete
     267: invokevirtual #159                // Method registerKeyword:(Ljava/lang/String;)V
     270: aload_0
     271: ldc           #203                // String desc
     273: invokevirtual #159                // Method registerKeyword:(Ljava/lang/String;)V
     276: aload_0
     277: ldc           #204                // String determnistic
     279: invokevirtual #159                // Method registerKeyword:(Ljava/lang/String;)V
     282: aload_0
     283: ldc           #205                // String disk
     285: invokevirtual #159                // Method registerKeyword:(Ljava/lang/String;)V
     288: aload_0
     289: ldc           #206                // String distinct
     291: invokevirtual #159                // Method registerKeyword:(Ljava/lang/String;)V
     294: aload_0
     295: ldc           #207                // String drop
     297: invokevirtual #159                // Method registerKeyword:(Ljava/lang/String;)V
     300: aload_0
     301: ldc           #208                // String dummy
     303: invokevirtual #159                // Method registerKeyword:(Ljava/lang/String;)V
     306: aload_0
     307: ldc           #209                // String dump
     309: invokevirtual #159                // Method registerKeyword:(Ljava/lang/String;)V
     312: aload_0
     313: ldc           #210                // String else
     315: invokevirtual #159                // Method registerKeyword:(Ljava/lang/String;)V
     318: aload_0
     319: ldc           #211                // String encrypt
     321: invokevirtual #159                // Method registerKeyword:(Ljava/lang/String;)V
     324: aload_0
     325: ldc           #212                // String end
     327: invokevirtual #159                // Method registerKeyword:(Ljava/lang/String;)V
     330: aload_0
     331: ldc           #213                // String endtran
     333: invokevirtual #159                // Method registerKeyword:(Ljava/lang/String;)V
     336: aload_0
     337: ldc           #214                // String errlvl
     339: invokevirtual #159                // Method registerKeyword:(Ljava/lang/String;)V
     342: aload_0
     343: ldc           #215                // String errordata
     345: invokevirtual #159                // Method registerKeyword:(Ljava/lang/String;)V
     348: aload_0
     349: ldc           #216                // String errorexit
     351: invokevirtual #159                // Method registerKeyword:(Ljava/lang/String;)V
     354: aload_0
     355: ldc           #217                // String escape
     357: invokevirtual #159                // Method registerKeyword:(Ljava/lang/String;)V
     360: aload_0
     361: ldc           #218                // String except
     363: invokevirtual #159                // Method registerKeyword:(Ljava/lang/String;)V
     366: aload_0
     367: ldc           #219                // String exclusive
     369: invokevirtual #159                // Method registerKeyword:(Ljava/lang/String;)V
     372: aload_0
     373: ldc           #220                // String exec
     375: invokevirtual #159                // Method registerKeyword:(Ljava/lang/String;)V
     378: aload_0
     379: ldc           #221                // String execute
     381: invokevirtual #159                // Method registerKeyword:(Ljava/lang/String;)V
     384: aload_0
     385: ldc           #222                // String exist
     387: invokevirtual #159                // Method registerKeyword:(Ljava/lang/String;)V
     390: aload_0
     391: ldc           #223                // String exit
     393: invokevirtual #159                // Method registerKeyword:(Ljava/lang/String;)V
     396: aload_0
     397: ldc           #224                // String exp_row_size
     399: invokevirtual #159                // Method registerKeyword:(Ljava/lang/String;)V
     402: aload_0
     403: ldc           #225                // String external
     405: invokevirtual #159                // Method registerKeyword:(Ljava/lang/String;)V
     408: aload_0
     409: ldc           #226                // String fetch
     411: invokevirtual #159                // Method registerKeyword:(Ljava/lang/String;)V
     414: aload_0
     415: ldc           #227                // String fillfactor
     417: invokevirtual #159                // Method registerKeyword:(Ljava/lang/String;)V
     420: aload_0
     421: ldc           #228                // String for
     423: invokevirtual #159                // Method registerKeyword:(Ljava/lang/String;)V
     426: aload_0
     427: ldc           #229                // String foreign
     429: invokevirtual #159                // Method registerKeyword:(Ljava/lang/String;)V
     432: aload_0
     433: ldc           #230                // String from
     435: invokevirtual #159                // Method registerKeyword:(Ljava/lang/String;)V
     438: aload_0
     439: ldc           #231                // String goto
     441: invokevirtual #159                // Method registerKeyword:(Ljava/lang/String;)V
     444: aload_0
     445: ldc           #232                // String grant
     447: invokevirtual #159                // Method registerKeyword:(Ljava/lang/String;)V
     450: aload_0
     451: ldc           #233                // String group
     453: invokevirtual #159                // Method registerKeyword:(Ljava/lang/String;)V
     456: aload_0
     457: ldc           #234                // String having
     459: invokevirtual #159                // Method registerKeyword:(Ljava/lang/String;)V
     462: aload_0
     463: ldc           #235                // String holdlock
     465: invokevirtual #159                // Method registerKeyword:(Ljava/lang/String;)V
     468: aload_0
     469: ldc           #236                // String identity
     471: invokevirtual #159                // Method registerKeyword:(Ljava/lang/String;)V
     474: aload_0
     475: ldc           #237                // String identity_gap
     477: invokevirtual #159                // Method registerKeyword:(Ljava/lang/String;)V
     480: aload_0
     481: ldc           #238                // String identity_start
     483: invokevirtual #159                // Method registerKeyword:(Ljava/lang/String;)V
     486: aload_0
     487: ldc           #239                // String if
     489: invokevirtual #159                // Method registerKeyword:(Ljava/lang/String;)V
     492: aload_0
     493: ldc           #240                // String in
     495: invokevirtual #159                // Method registerKeyword:(Ljava/lang/String;)V
     498: aload_0
     499: ldc           #241                // String index
     501: invokevirtual #159                // Method registerKeyword:(Ljava/lang/String;)V
     504: aload_0
     505: ldc           #242                // String inout
     507: invokevirtual #159                // Method registerKeyword:(Ljava/lang/String;)V
     510: aload_0
     511: ldc           #243                // String insensitive
     513: invokevirtual #159                // Method registerKeyword:(Ljava/lang/String;)V
     516: aload_0
     517: ldc           #244                // String insert
     519: invokevirtual #159                // Method registerKeyword:(Ljava/lang/String;)V
     522: aload_0
     523: ldc           #245                // String install
     525: invokevirtual #159                // Method registerKeyword:(Ljava/lang/String;)V
     528: aload_0
     529: ldc           #246                // String intersect
     531: invokevirtual #159                // Method registerKeyword:(Ljava/lang/String;)V
     534: aload_0
     535: ldc           #247                // String into
     537: invokevirtual #159                // Method registerKeyword:(Ljava/lang/String;)V
     540: aload_0
     541: ldc           #248                // String is
     543: invokevirtual #159                // Method registerKeyword:(Ljava/lang/String;)V
     546: aload_0
     547: ldc           #249                // String isolation
     549: invokevirtual #159                // Method registerKeyword:(Ljava/lang/String;)V
     552: aload_0
     553: ldc           #250                // String jar
     555: invokevirtual #159                // Method registerKeyword:(Ljava/lang/String;)V
     558: aload_0
     559: ldc           #251                // String join
     561: invokevirtual #159                // Method registerKeyword:(Ljava/lang/String;)V
     564: aload_0
     565: ldc           #252                // String key
     567: invokevirtual #159                // Method registerKeyword:(Ljava/lang/String;)V
     570: aload_0
     571: ldc           #253                // String kill
     573: invokevirtual #159                // Method registerKeyword:(Ljava/lang/String;)V
     576: aload_0
     577: ldc           #254                // String level
     579: invokevirtual #159                // Method registerKeyword:(Ljava/lang/String;)V
     582: aload_0
     583: ldc           #255                // String like
     585: invokevirtual #159                // Method registerKeyword:(Ljava/lang/String;)V
     588: aload_0
     589: ldc_w         #256                // String lineno
     592: invokevirtual #159                // Method registerKeyword:(Ljava/lang/String;)V
     595: aload_0
     596: ldc_w         #257                // String load
     599: invokevirtual #159                // Method registerKeyword:(Ljava/lang/String;)V
     602: aload_0
     603: ldc_w         #258                // String lock
     606: invokevirtual #159                // Method registerKeyword:(Ljava/lang/String;)V
     609: aload_0
     610: ldc_w         #259                // String materialized
     613: invokevirtual #159                // Method registerKeyword:(Ljava/lang/String;)V
     616: aload_0
     617: ldc_w         #260                // String max
     620: invokevirtual #159                // Method registerKeyword:(Ljava/lang/String;)V
     623: aload_0
     624: ldc_w         #261                // String max_rows_per_page
     627: invokevirtual #159                // Method registerKeyword:(Ljava/lang/String;)V
     630: aload_0
     631: ldc_w         #262                // String min
     634: invokevirtual #159                // Method registerKeyword:(Ljava/lang/String;)V
     637: aload_0
     638: ldc_w         #263                // String mirror
     641: invokevirtual #159                // Method registerKeyword:(Ljava/lang/String;)V
     644: aload_0
     645: ldc_w         #264                // String mirrorexit
     648: invokevirtual #159                // Method registerKeyword:(Ljava/lang/String;)V
     651: aload_0
     652: ldc_w         #265                // String modify
     655: invokevirtual #159                // Method registerKeyword:(Ljava/lang/String;)V
     658: aload_0
     659: ldc_w         #266                // String national
     662: invokevirtual #159                // Method registerKeyword:(Ljava/lang/String;)V
     665: aload_0
     666: ldc_w         #267                // String new
     669: invokevirtual #159                // Method registerKeyword:(Ljava/lang/String;)V
     672: aload_0
     673: ldc_w         #268                // String noholdlock
     676: invokevirtual #159                // Method registerKeyword:(Ljava/lang/String;)V
     679: aload_0
     680: ldc_w         #269                // String nonclustered
     683: invokevirtual #159                // Method registerKeyword:(Ljava/lang/String;)V
     686: aload_0
     687: ldc_w         #270                // String nonscrollable
     690: invokevirtual #159                // Method registerKeyword:(Ljava/lang/String;)V
     693: aload_0
     694: ldc_w         #271                // String non_sensitive
     697: invokevirtual #159                // Method registerKeyword:(Ljava/lang/String;)V
     700: aload_0
     701: ldc_w         #272                // String not
     704: invokevirtual #159                // Method registerKeyword:(Ljava/lang/String;)V
     707: aload_0
     708: ldc_w         #273                // String null
     711: invokevirtual #159                // Method registerKeyword:(Ljava/lang/String;)V
     714: aload_0
     715: ldc_w         #274                // String nullif
     718: invokevirtual #159                // Method registerKeyword:(Ljava/lang/String;)V
     721: aload_0
     722: ldc_w         #275                // String numeric_truncation
     725: invokevirtual #159                // Method registerKeyword:(Ljava/lang/String;)V
     728: aload_0
     729: ldc_w         #276                // String of
     732: invokevirtual #159                // Method registerKeyword:(Ljava/lang/String;)V
     735: aload_0
     736: ldc_w         #277                // String off
     739: invokevirtual #159                // Method registerKeyword:(Ljava/lang/String;)V
     742: aload_0
     743: ldc_w         #278                // String offsets
     746: invokevirtual #159                // Method registerKeyword:(Ljava/lang/String;)V
     749: aload_0
     750: ldc_w         #279                // String on
     753: invokevirtual #159                // Method registerKeyword:(Ljava/lang/String;)V
     756: aload_0
     757: ldc_w         #280                // String once
     760: invokevirtual #159                // Method registerKeyword:(Ljava/lang/String;)V
     763: aload_0
     764: ldc_w         #281                // String online
     767: invokevirtual #159                // Method registerKeyword:(Ljava/lang/String;)V
     770: aload_0
     771: ldc_w         #282                // String only
     774: invokevirtual #159                // Method registerKeyword:(Ljava/lang/String;)V
     777: aload_0
     778: ldc_w         #283                // String open
     781: invokevirtual #159                // Method registerKeyword:(Ljava/lang/String;)V
     784: aload_0
     785: ldc_w         #284                // String option
     788: invokevirtual #159                // Method registerKeyword:(Ljava/lang/String;)V
     791: aload_0
     792: ldc_w         #285                // String or
     795: invokevirtual #159                // Method registerKeyword:(Ljava/lang/String;)V
     798: aload_0
     799: ldc_w         #286                // String order
     802: invokevirtual #159                // Method registerKeyword:(Ljava/lang/String;)V
     805: aload_0
     806: ldc_w         #287                // String out
     809: invokevirtual #159                // Method registerKeyword:(Ljava/lang/String;)V
     812: aload_0
     813: ldc_w         #288                // String output
     816: invokevirtual #159                // Method registerKeyword:(Ljava/lang/String;)V
     819: aload_0
     820: ldc_w         #289                // String over
     823: invokevirtual #159                // Method registerKeyword:(Ljava/lang/String;)V
     826: aload_0
     827: ldc_w         #290                // String artition
     830: invokevirtual #159                // Method registerKeyword:(Ljava/lang/String;)V
     833: aload_0
     834: ldc_w         #291                // String perm
     837: invokevirtual #159                // Method registerKeyword:(Ljava/lang/String;)V
     840: aload_0
     841: ldc_w         #292                // String permanent
     844: invokevirtual #159                // Method registerKeyword:(Ljava/lang/String;)V
     847: aload_0
     848: ldc_w         #293                // String plan
     851: invokevirtual #159                // Method registerKeyword:(Ljava/lang/String;)V
     854: aload_0
     855: ldc_w         #294                // String prepare
     858: invokevirtual #159                // Method registerKeyword:(Ljava/lang/String;)V
     861: aload_0
     862: ldc_w         #295                // String primary
     865: invokevirtual #159                // Method registerKeyword:(Ljava/lang/String;)V
     868: aload_0
     869: ldc_w         #296                // String print
     872: invokevirtual #159                // Method registerKeyword:(Ljava/lang/String;)V
     875: aload_0
     876: ldc_w         #297                // String privileges
     879: invokevirtual #159                // Method registerKeyword:(Ljava/lang/String;)V
     882: aload_0
     883: ldc_w         #298                // String proc
     886: invokevirtual #159                // Method registerKeyword:(Ljava/lang/String;)V
     889: aload_0
     890: ldc_w         #299                // String procedure
     893: invokevirtual #159                // Method registerKeyword:(Ljava/lang/String;)V
     896: aload_0
     897: ldc_w         #300                // String processexit
     900: invokevirtual #159                // Method registerKeyword:(Ljava/lang/String;)V
     903: aload_0
     904: ldc_w         #301                // String proxy_table
     907: invokevirtual #159                // Method registerKeyword:(Ljava/lang/String;)V
     910: aload_0
     911: ldc_w         #302                // String public
     914: invokevirtual #159                // Method registerKeyword:(Ljava/lang/String;)V
     917: aload_0
     918: ldc_w         #303                // String quiesce
     921: invokevirtual #159                // Method registerKeyword:(Ljava/lang/String;)V
     924: aload_0
     925: ldc_w         #304                // String raiserror
     928: invokevirtual #159                // Method registerKeyword:(Ljava/lang/String;)V
     931: aload_0
     932: ldc_w         #305                // String read
     935: invokevirtual #159                // Method registerKeyword:(Ljava/lang/String;)V
     938: aload_0
     939: ldc_w         #306                // String readpast
     942: invokevirtual #159                // Method registerKeyword:(Ljava/lang/String;)V
     945: aload_0
     946: ldc_w         #307                // String readtext
     949: invokevirtual #159                // Method registerKeyword:(Ljava/lang/String;)V
     952: aload_0
     953: ldc_w         #308                // String reconfigure
     956: invokevirtual #159                // Method registerKeyword:(Ljava/lang/String;)V
     959: aload_0
     960: ldc_w         #309                // String references
     963: invokevirtual #159                // Method registerKeyword:(Ljava/lang/String;)V
     966: aload_0
     967: ldc_w         #310                // String remove
     970: invokevirtual #159                // Method registerKeyword:(Ljava/lang/String;)V
     973: aload_0
     974: ldc_w         #311                // String reorg
     977: invokevirtual #159                // Method registerKeyword:(Ljava/lang/String;)V
     980: aload_0
     981: ldc_w         #312                // String replace
     984: invokevirtual #159                // Method registerKeyword:(Ljava/lang/String;)V
     987: aload_0
     988: ldc_w         #313                // String replication
     991: invokevirtual #159                // Method registerKeyword:(Ljava/lang/String;)V
     994: aload_0
     995: ldc_w         #314                // String reservepagegap
     998: invokevirtual #159                // Method registerKeyword:(Ljava/lang/String;)V
    1001: aload_0
    1002: ldc_w         #315                // String return
    1005: invokevirtual #159                // Method registerKeyword:(Ljava/lang/String;)V
    1008: aload_0
    1009: ldc_w         #316                // String returns
    1012: invokevirtual #159                // Method registerKeyword:(Ljava/lang/String;)V
    1015: aload_0
    1016: ldc_w         #317                // String revoke
    1019: invokevirtual #159                // Method registerKeyword:(Ljava/lang/String;)V
    1022: aload_0
    1023: ldc_w         #318                // String role
    1026: invokevirtual #159                // Method registerKeyword:(Ljava/lang/String;)V
    1029: aload_0
    1030: ldc_w         #319                // String rollback
    1033: invokevirtual #159                // Method registerKeyword:(Ljava/lang/String;)V
    1036: aload_0
    1037: ldc_w         #320                // String rowcount
    1040: invokevirtual #159                // Method registerKeyword:(Ljava/lang/String;)V
    1043: aload_0
    1044: ldc_w         #321                // String rows
    1047: invokevirtual #159                // Method registerKeyword:(Ljava/lang/String;)V
    1050: aload_0
    1051: ldc_w         #322                // String rule
    1054: invokevirtual #159                // Method registerKeyword:(Ljava/lang/String;)V
    1057: aload_0
    1058: ldc_w         #323                // String save
    1061: invokevirtual #159                // Method registerKeyword:(Ljava/lang/String;)V
    1064: aload_0
    1065: ldc_w         #324                // String schema
    1068: invokevirtual #159                // Method registerKeyword:(Ljava/lang/String;)V
    1071: aload_0
    1072: ldc_w         #325                // String scroll
    1075: invokevirtual #159                // Method registerKeyword:(Ljava/lang/String;)V
    1078: aload_0
    1079: ldc_w         #326                // String scrollable
    1082: invokevirtual #159                // Method registerKeyword:(Ljava/lang/String;)V
    1085: aload_0
    1086: ldc_w         #327                // String select
    1089: invokevirtual #159                // Method registerKeyword:(Ljava/lang/String;)V
    1092: aload_0
    1093: ldc_w         #328                // String semi_sensitive
    1096: invokevirtual #159                // Method registerKeyword:(Ljava/lang/String;)V
    1099: aload_0
    1100: ldc_w         #329                // String set
    1103: invokevirtual #159                // Method registerKeyword:(Ljava/lang/String;)V
    1106: aload_0
    1107: ldc_w         #330                // String setuser
    1110: invokevirtual #159                // Method registerKeyword:(Ljava/lang/String;)V
    1113: aload_0
    1114: ldc_w         #331                // String shared
    1117: invokevirtual #159                // Method registerKeyword:(Ljava/lang/String;)V
    1120: aload_0
    1121: ldc_w         #332                // String shutdown
    1124: invokevirtual #159                // Method registerKeyword:(Ljava/lang/String;)V
    1127: aload_0
    1128: ldc_w         #333                // String some
    1131: invokevirtual #159                // Method registerKeyword:(Ljava/lang/String;)V
    1134: aload_0
    1135: ldc_w         #334                // String statistics
    1138: invokevirtual #159                // Method registerKeyword:(Ljava/lang/String;)V
    1141: aload_0
    1142: ldc_w         #335                // String stringsize
    1145: invokevirtual #159                // Method registerKeyword:(Ljava/lang/String;)V
    1148: aload_0
    1149: ldc_w         #336                // String stripe
    1152: invokevirtual #159                // Method registerKeyword:(Ljava/lang/String;)V
    1155: aload_0
    1156: ldc_w         #337                // String sum
    1159: invokevirtual #159                // Method registerKeyword:(Ljava/lang/String;)V
    1162: aload_0
    1163: ldc_w         #338                // String syb_identity
    1166: invokevirtual #159                // Method registerKeyword:(Ljava/lang/String;)V
    1169: aload_0
    1170: ldc_w         #339                // String syb_restree
    1173: invokevirtual #159                // Method registerKeyword:(Ljava/lang/String;)V
    1176: aload_0
    1177: ldc_w         #340                // String syb_terminate
    1180: invokevirtual #159                // Method registerKeyword:(Ljava/lang/String;)V
    1183: aload_0
    1184: ldc_w         #341                // String top
    1187: invokevirtual #159                // Method registerKeyword:(Ljava/lang/String;)V
    1190: aload_0
    1191: ldc_w         #342                // String table
    1194: invokevirtual #159                // Method registerKeyword:(Ljava/lang/String;)V
    1197: aload_0
    1198: ldc_w         #343                // String temp
    1201: invokevirtual #159                // Method registerKeyword:(Ljava/lang/String;)V
    1204: aload_0
    1205: ldc_w         #344                // String temporary
    1208: invokevirtual #159                // Method registerKeyword:(Ljava/lang/String;)V
    1211: aload_0
    1212: ldc_w         #345                // String textsize
    1215: invokevirtual #159                // Method registerKeyword:(Ljava/lang/String;)V
    1218: aload_0
    1219: ldc_w         #346                // String to
    1222: invokevirtual #159                // Method registerKeyword:(Ljava/lang/String;)V
    1225: aload_0
    1226: ldc_w         #347                // String tracefile
    1229: invokevirtual #159                // Method registerKeyword:(Ljava/lang/String;)V
    1232: aload_0
    1233: ldc_w         #348                // String tran
    1236: invokevirtual #159                // Method registerKeyword:(Ljava/lang/String;)V
    1239: aload_0
    1240: ldc_w         #349                // String transaction
    1243: invokevirtual #159                // Method registerKeyword:(Ljava/lang/String;)V
    1246: aload_0
    1247: ldc_w         #350                // String trigger
    1250: invokevirtual #159                // Method registerKeyword:(Ljava/lang/String;)V
    1253: aload_0
    1254: ldc_w         #351                // String truncate
    1257: invokevirtual #159                // Method registerKeyword:(Ljava/lang/String;)V
    1260: aload_0
    1261: ldc_w         #352                // String tsequal
    1264: invokevirtual #159                // Method registerKeyword:(Ljava/lang/String;)V
    1267: aload_0
    1268: ldc_w         #353                // String union
    1271: invokevirtual #159                // Method registerKeyword:(Ljava/lang/String;)V
    1274: aload_0
    1275: ldc_w         #354                // String unique
    1278: invokevirtual #159                // Method registerKeyword:(Ljava/lang/String;)V
    1281: aload_0
    1282: ldc_w         #355                // String unpartition
    1285: invokevirtual #159                // Method registerKeyword:(Ljava/lang/String;)V
    1288: aload_0
    1289: ldc_w         #356                // String update
    1292: invokevirtual #159                // Method registerKeyword:(Ljava/lang/String;)V
    1295: aload_0
    1296: ldc_w         #357                // String use
    1299: invokevirtual #159                // Method registerKeyword:(Ljava/lang/String;)V
    1302: aload_0
    1303: ldc_w         #358                // String user
    1306: invokevirtual #159                // Method registerKeyword:(Ljava/lang/String;)V
    1309: aload_0
    1310: ldc_w         #359                // String user_option
    1313: invokevirtual #159                // Method registerKeyword:(Ljava/lang/String;)V
    1316: aload_0
    1317: ldc_w         #360                // String using
    1320: invokevirtual #159                // Method registerKeyword:(Ljava/lang/String;)V
    1323: aload_0
    1324: ldc_w         #361                // String values
    1327: invokevirtual #159                // Method registerKeyword:(Ljava/lang/String;)V
    1330: aload_0
    1331: ldc_w         #362                // String varying
    1334: invokevirtual #159                // Method registerKeyword:(Ljava/lang/String;)V
    1337: aload_0
    1338: ldc_w         #363                // String view
    1341: invokevirtual #159                // Method registerKeyword:(Ljava/lang/String;)V
    1344: aload_0
    1345: ldc_w         #364                // String waitfor
    1348: invokevirtual #159                // Method registerKeyword:(Ljava/lang/String;)V
    1351: aload_0
    1352: ldc_w         #365                // String when
    1355: invokevirtual #159                // Method registerKeyword:(Ljava/lang/String;)V
    1358: aload_0
    1359: ldc_w         #366                // String where
    1362: invokevirtual #159                // Method registerKeyword:(Ljava/lang/String;)V
    1365: aload_0
    1366: ldc_w         #367                // String while
    1369: invokevirtual #159                // Method registerKeyword:(Ljava/lang/String;)V
    1372: aload_0
    1373: ldc_w         #368                // String with
    1376: invokevirtual #159                // Method registerKeyword:(Ljava/lang/String;)V
    1379: aload_0
    1380: ldc_w         #369                // String work
    1383: invokevirtual #159                // Method registerKeyword:(Ljava/lang/String;)V
    1386: aload_0
    1387: ldc_w         #370                // String writetext
    1390: invokevirtual #159                // Method registerKeyword:(Ljava/lang/String;)V
    1393: aload_0
    1394: ldc_w         #371                // String xmlextract
    1397: invokevirtual #159                // Method registerKeyword:(Ljava/lang/String;)V
    1400: aload_0
    1401: ldc_w         #372                // String xmlparse
    1404: invokevirtual #159                // Method registerKeyword:(Ljava/lang/String;)V
    1407: aload_0
    1408: ldc_w         #373                // String xmltest
    1411: invokevirtual #159                // Method registerKeyword:(Ljava/lang/String;)V
    1414: aload_0
    1415: ldc_w         #374                // String xmlvalidate
    1418: invokevirtual #159                // Method registerKeyword:(Ljava/lang/String;)V
    1421: return

  public boolean supportsCascadeDelete();
    Code:
       0: iconst_0
       1: ireturn

  public int getMaxAliasLength();
    Code:
       0: bipush        30
       2: ireturn

  public boolean areStringComparisonsCaseInsensitive();
    Code:
       0: iconst_1
       1: ireturn

  public java.lang.String getCurrentTimestampSQLFunctionName();
    Code:
       0: ldc_w         #375                // String getdate()
       3: areturn

  public boolean supportsExpectedLobUsagePattern();
    Code:
       0: iconst_0
       1: ireturn

  public java.lang.String getCrossJoinSeparator();
    Code:
       0: ldc_w         #376                // String ,
       3: areturn

  protected org.hibernate.type.descriptor.sql.SqlTypeDescriptor getSqlTypeDescriptorOverride(int);
    Code:
       0: iload_1
       1: bipush        16
       3: if_icmpne     12
       6: getstatic     #377                // Field org/hibernate/type/descriptor/sql/TinyIntTypeDescriptor.INSTANCE:Lorg/hibernate/type/descriptor/sql/TinyIntTypeDescriptor;
       9: goto          17
      12: aload_0
      13: iload_1
      14: invokespecial #378                // Method org/hibernate/dialect/SybaseDialect.getSqlTypeDescriptorOverride:(I)Lorg/hibernate/type/descriptor/sql/SqlTypeDescriptor;
      17: areturn

  public boolean supportsLockTimeouts();
    Code:
       0: iconst_0
       1: ireturn

  public boolean supportsPartitionBy();
    Code:
       0: iconst_0
       1: ireturn
}
