Compiled from "TransactionFactory.java"
public class org.infinispan.transaction.xa.TransactionFactory {
  private static final org.infinispan.util.logging.Log log;

  private org.infinispan.transaction.xa.TransactionFactory$TxFactoryEnum txFactoryEnum;

  private org.infinispan.configuration.cache.Configuration configuration;

  private org.infinispan.container.versioning.VersionGenerator clusterIdGenerator;

  private org.infinispan.util.TimeService timeService;

  private boolean isClustered;

  private org.infinispan.commons.equivalence.Equivalence<java.lang.Object> keyEquivalence;

  public org.infinispan.transaction.xa.TransactionFactory();
    Code:
       0: aload_0
       1: invokespecial #1                  // Method java/lang/Object."<init>":()V
       4: return

  public org.infinispan.transaction.xa.GlobalTransaction newGlobalTransaction();
    Code:
       0: aload_0
       1: getfield      #2                  // Field txFactoryEnum:Lorg/infinispan/transaction/xa/TransactionFactory$TxFactoryEnum;
       4: invokevirtual #3                  // Method org/infinispan/transaction/xa/TransactionFactory$TxFactoryEnum.newGlobalTransaction:()Lorg/infinispan/transaction/xa/GlobalTransaction;
       7: areturn

  public org.infinispan.transaction.xa.GlobalTransaction newGlobalTransaction(org.infinispan.remoting.transport.Address, boolean);
    Code:
       0: aload_0
       1: getfield      #2                  // Field txFactoryEnum:Lorg/infinispan/transaction/xa/TransactionFactory$TxFactoryEnum;
       4: aload_1
       5: iload_2
       6: aload_0
       7: getfield      #4                  // Field clusterIdGenerator:Lorg/infinispan/container/versioning/VersionGenerator;
      10: aload_0
      11: getfield      #5                  // Field isClustered:Z
      14: invokevirtual #6                  // Method org/infinispan/transaction/xa/TransactionFactory$TxFactoryEnum.newGlobalTransaction:(Lorg/infinispan/remoting/transport/Address;ZLorg/infinispan/container/versioning/VersionGenerator;Z)Lorg/infinispan/transaction/xa/GlobalTransaction;
      17: areturn

  public org.infinispan.transaction.impl.LocalTransaction newLocalTransaction(javax.transaction.Transaction, org.infinispan.transaction.xa.GlobalTransaction, boolean, int);
    Code:
       0: aload_0
       1: getfield      #2                  // Field txFactoryEnum:Lorg/infinispan/transaction/xa/TransactionFactory$TxFactoryEnum;
       4: aload_1
       5: aload_2
       6: iload_3
       7: iload         4
       9: aload_0
      10: getfield      #7                  // Field keyEquivalence:Lorg/infinispan/commons/equivalence/Equivalence;
      13: aload_0
      14: getfield      #8                  // Field timeService:Lorg/infinispan/util/TimeService;
      17: invokeinterface #9,  1            // InterfaceMethod org/infinispan/util/TimeService.time:()J
      22: invokevirtual #10                 // Method org/infinispan/transaction/xa/TransactionFactory$TxFactoryEnum.newLocalTransaction:(Ljavax/transaction/Transaction;Lorg/infinispan/transaction/xa/GlobalTransaction;ZILorg/infinispan/commons/equivalence/Equivalence;J)Lorg/infinispan/transaction/impl/LocalTransaction;
      25: areturn

  public org.infinispan.transaction.impl.RemoteTransaction newRemoteTransaction(org.infinispan.commands.write.WriteCommand[], org.infinispan.transaction.xa.GlobalTransaction, int);
    Code:
       0: aload_0
       1: getfield      #2                  // Field txFactoryEnum:Lorg/infinispan/transaction/xa/TransactionFactory$TxFactoryEnum;
       4: aload_1
       5: aload_2
       6: iload_3
       7: aload_0
       8: getfield      #7                  // Field keyEquivalence:Lorg/infinispan/commons/equivalence/Equivalence;
      11: aload_0
      12: getfield      #8                  // Field timeService:Lorg/infinispan/util/TimeService;
      15: invokeinterface #9,  1            // InterfaceMethod org/infinispan/util/TimeService.time:()J
      20: invokevirtual #11                 // Method org/infinispan/transaction/xa/TransactionFactory$TxFactoryEnum.newRemoteTransaction:([Lorg/infinispan/commands/write/WriteCommand;Lorg/infinispan/transaction/xa/GlobalTransaction;ILorg/infinispan/commons/equivalence/Equivalence;J)Lorg/infinispan/transaction/impl/RemoteTransaction;
      23: areturn

  public org.infinispan.transaction.impl.RemoteTransaction newRemoteTransaction(org.infinispan.transaction.xa.GlobalTransaction, int);
    Code:
       0: aload_0
       1: getfield      #2                  // Field txFactoryEnum:Lorg/infinispan/transaction/xa/TransactionFactory$TxFactoryEnum;
       4: aload_1
       5: iload_2
       6: aload_0
       7: getfield      #7                  // Field keyEquivalence:Lorg/infinispan/commons/equivalence/Equivalence;
      10: aload_0
      11: getfield      #8                  // Field timeService:Lorg/infinispan/util/TimeService;
      14: invokeinterface #9,  1            // InterfaceMethod org/infinispan/util/TimeService.time:()J
      19: invokevirtual #12                 // Method org/infinispan/transaction/xa/TransactionFactory$TxFactoryEnum.newRemoteTransaction:(Lorg/infinispan/transaction/xa/GlobalTransaction;ILorg/infinispan/commons/equivalence/Equivalence;J)Lorg/infinispan/transaction/impl/RemoteTransaction;
      22: areturn

  public void init(org.infinispan.configuration.cache.Configuration, org.infinispan.container.versioning.VersionGenerator, org.infinispan.util.TimeService);
    Code:
       0: aload_0
       1: aload_1
       2: putfield      #13                 // Field configuration:Lorg/infinispan/configuration/cache/Configuration;
       5: aload_0
       6: aload_2
       7: putfield      #4                  // Field clusterIdGenerator:Lorg/infinispan/container/versioning/VersionGenerator;
      10: aload_0
      11: aload_3
      12: putfield      #8                  // Field timeService:Lorg/infinispan/util/TimeService;
      15: return

  public void start();
    Code:
       0: aload_0
       1: getfield      #13                 // Field configuration:Lorg/infinispan/configuration/cache/Configuration;
       4: invokevirtual #14                 // Method org/infinispan/configuration/cache/Configuration.deadlockDetection:()Lorg/infinispan/configuration/cache/DeadlockDetectionConfiguration;
       7: invokevirtual #15                 // Method org/infinispan/configuration/cache/DeadlockDetectionConfiguration.enabled:()Z
      10: istore_1
      11: aload_0
      12: getfield      #13                 // Field configuration:Lorg/infinispan/configuration/cache/Configuration;
      15: invokevirtual #16                 // Method org/infinispan/configuration/cache/Configuration.transaction:()Lorg/infinispan/configuration/cache/TransactionConfiguration;
      18: invokevirtual #17                 // Method org/infinispan/configuration/cache/TransactionConfiguration.useSynchronization:()Z
      21: ifne          28
      24: iconst_1
      25: goto          29
      28: iconst_0
      29: istore_2
      30: aload_0
      31: getfield      #13                 // Field configuration:Lorg/infinispan/configuration/cache/Configuration;
      34: invokevirtual #16                 // Method org/infinispan/configuration/cache/Configuration.transaction:()Lorg/infinispan/configuration/cache/TransactionConfiguration;
      37: invokevirtual #18                 // Method org/infinispan/configuration/cache/TransactionConfiguration.recovery:()Lorg/infinispan/configuration/cache/RecoveryConfiguration;
      40: invokevirtual #19                 // Method org/infinispan/configuration/cache/RecoveryConfiguration.enabled:()Z
      43: istore_3
      44: aload_0
      45: getfield      #13                 // Field configuration:Lorg/infinispan/configuration/cache/Configuration;
      48: invokevirtual #20                 // Method org/infinispan/configuration/cache/Configuration.invocationBatching:()Lorg/infinispan/configuration/cache/InvocationBatchingConfiguration;
      51: invokevirtual #21                 // Method org/infinispan/configuration/cache/InvocationBatchingConfiguration.enabled:()Z
      54: istore        4
      56: aload_0
      57: iload_1
      58: iload_3
      59: iload_2
      60: iload         4
      62: invokevirtual #22                 // Method init:(ZZZZ)V
      65: aload_0
      66: aload_0
      67: getfield      #13                 // Field configuration:Lorg/infinispan/configuration/cache/Configuration;
      70: invokevirtual #23                 // Method org/infinispan/configuration/cache/Configuration.clustering:()Lorg/infinispan/configuration/cache/ClusteringConfiguration;
      73: invokevirtual #24                 // Method org/infinispan/configuration/cache/ClusteringConfiguration.cacheMode:()Lorg/infinispan/configuration/cache/CacheMode;
      76: invokevirtual #25                 // Method org/infinispan/configuration/cache/CacheMode.isClustered:()Z
      79: putfield      #5                  // Field isClustered:Z
      82: aload_0
      83: aload_0
      84: getfield      #13                 // Field configuration:Lorg/infinispan/configuration/cache/Configuration;
      87: invokevirtual #26                 // Method org/infinispan/configuration/cache/Configuration.dataContainer:()Lorg/infinispan/configuration/cache/DataContainerConfiguration;
      90: invokevirtual #27                 // Method org/infinispan/configuration/cache/DataContainerConfiguration.keyEquivalence:()Lorg/infinispan/commons/equivalence/Equivalence;
      93: putfield      #7                  // Field keyEquivalence:Lorg/infinispan/commons/equivalence/Equivalence;
      96: return

  public void init(boolean, boolean, boolean, boolean);
    Code:
       0: iload         4
       2: ifeq          29
       5: iload_1
       6: ifeq          19
       9: aload_0
      10: getstatic     #28                 // Field org/infinispan/transaction/xa/TransactionFactory$TxFactoryEnum.DLD_NORECOVERY_NOXA:Lorg/infinispan/transaction/xa/TransactionFactory$TxFactoryEnum;
      13: putfield      #2                  // Field txFactoryEnum:Lorg/infinispan/transaction/xa/TransactionFactory$TxFactoryEnum;
      16: goto          134
      19: aload_0
      20: getstatic     #29                 // Field org/infinispan/transaction/xa/TransactionFactory$TxFactoryEnum.NODLD_NORECOVERY_NOXA:Lorg/infinispan/transaction/xa/TransactionFactory$TxFactoryEnum;
      23: putfield      #2                  // Field txFactoryEnum:Lorg/infinispan/transaction/xa/TransactionFactory$TxFactoryEnum;
      26: goto          134
      29: iload_1
      30: ifeq          85
      33: iload_2
      34: ifeq          61
      37: iload_3
      38: ifeq          51
      41: aload_0
      42: getstatic     #30                 // Field org/infinispan/transaction/xa/TransactionFactory$TxFactoryEnum.DLD_RECOVERY_XA:Lorg/infinispan/transaction/xa/TransactionFactory$TxFactoryEnum;
      45: putfield      #2                  // Field txFactoryEnum:Lorg/infinispan/transaction/xa/TransactionFactory$TxFactoryEnum;
      48: goto          134
      51: aload_0
      52: getstatic     #28                 // Field org/infinispan/transaction/xa/TransactionFactory$TxFactoryEnum.DLD_NORECOVERY_NOXA:Lorg/infinispan/transaction/xa/TransactionFactory$TxFactoryEnum;
      55: putfield      #2                  // Field txFactoryEnum:Lorg/infinispan/transaction/xa/TransactionFactory$TxFactoryEnum;
      58: goto          134
      61: iload_3
      62: ifeq          75
      65: aload_0
      66: getstatic     #31                 // Field org/infinispan/transaction/xa/TransactionFactory$TxFactoryEnum.DLD_NORECOVERY_XA:Lorg/infinispan/transaction/xa/TransactionFactory$TxFactoryEnum;
      69: putfield      #2                  // Field txFactoryEnum:Lorg/infinispan/transaction/xa/TransactionFactory$TxFactoryEnum;
      72: goto          134
      75: aload_0
      76: getstatic     #28                 // Field org/infinispan/transaction/xa/TransactionFactory$TxFactoryEnum.DLD_NORECOVERY_NOXA:Lorg/infinispan/transaction/xa/TransactionFactory$TxFactoryEnum;
      79: putfield      #2                  // Field txFactoryEnum:Lorg/infinispan/transaction/xa/TransactionFactory$TxFactoryEnum;
      82: goto          134
      85: iload_2
      86: ifeq          113
      89: iload_3
      90: ifeq          103
      93: aload_0
      94: getstatic     #32                 // Field org/infinispan/transaction/xa/TransactionFactory$TxFactoryEnum.NODLD_RECOVERY_XA:Lorg/infinispan/transaction/xa/TransactionFactory$TxFactoryEnum;
      97: putfield      #2                  // Field txFactoryEnum:Lorg/infinispan/transaction/xa/TransactionFactory$TxFactoryEnum;
     100: goto          134
     103: aload_0
     104: getstatic     #29                 // Field org/infinispan/transaction/xa/TransactionFactory$TxFactoryEnum.NODLD_NORECOVERY_NOXA:Lorg/infinispan/transaction/xa/TransactionFactory$TxFactoryEnum;
     107: putfield      #2                  // Field txFactoryEnum:Lorg/infinispan/transaction/xa/TransactionFactory$TxFactoryEnum;
     110: goto          134
     113: iload_3
     114: ifeq          127
     117: aload_0
     118: getstatic     #33                 // Field org/infinispan/transaction/xa/TransactionFactory$TxFactoryEnum.NODLD_NORECOVERY_XA:Lorg/infinispan/transaction/xa/TransactionFactory$TxFactoryEnum;
     121: putfield      #2                  // Field txFactoryEnum:Lorg/infinispan/transaction/xa/TransactionFactory$TxFactoryEnum;
     124: goto          134
     127: aload_0
     128: getstatic     #29                 // Field org/infinispan/transaction/xa/TransactionFactory$TxFactoryEnum.NODLD_NORECOVERY_NOXA:Lorg/infinispan/transaction/xa/TransactionFactory$TxFactoryEnum;
     131: putfield      #2                  // Field txFactoryEnum:Lorg/infinispan/transaction/xa/TransactionFactory$TxFactoryEnum;
     134: getstatic     #34                 // Field log:Lorg/infinispan/util/logging/Log;
     137: ldc           #35                 // String Setting factory enum to %s
     139: aload_0
     140: getfield      #2                  // Field txFactoryEnum:Lorg/infinispan/transaction/xa/TransactionFactory$TxFactoryEnum;
     143: invokeinterface #36,  3           // InterfaceMethod org/infinispan/util/logging/Log.tracef:(Ljava/lang/String;Ljava/lang/Object;)V
     148: return

  static {};
    Code:
       0: ldc           #37                 // class org/infinispan/transaction/xa/TransactionFactory
       2: invokestatic  #38                 // Method org/infinispan/util/logging/LogFactory.getLog:(Ljava/lang/Class;)Lorg/infinispan/util/logging/Log;
       5: putstatic     #34                 // Field log:Lorg/infinispan/util/logging/Log;
       8: return
}
