Compiled from "BeanModel.java"
public class freemarker.ext.beans.BeanModel implements freemarker.template.TemplateHashModelEx,freemarker.template.AdapterTemplateModel,freemarker.ext.util.WrapperTemplateModel,freemarker.template.TemplateModelWithAPISupport {
  private static final freemarker.log.Logger LOG;

  protected final java.lang.Object object;

  protected final freemarker.ext.beans.BeansWrapper wrapper;

  static final freemarker.template.TemplateModel UNKNOWN;

  static final freemarker.ext.util.ModelFactory FACTORY;

  private java.util.HashMap memberMap;

  public freemarker.ext.beans.BeanModel(java.lang.Object, freemarker.ext.beans.BeansWrapper);
    Code:
       0: aload_0
       1: aload_1
       2: aload_2
       3: iconst_1
       4: invokespecial #1                  // Method "<init>":(Ljava/lang/Object;Lfreemarker/ext/beans/BeansWrapper;Z)V
       7: return

  freemarker.ext.beans.BeanModel(java.lang.Object, freemarker.ext.beans.BeansWrapper, boolean);
    Code:
       0: aload_0
       1: invokespecial #2                  // Method java/lang/Object."<init>":()V
       4: aload_0
       5: aload_1
       6: putfield      #3                  // Field object:Ljava/lang/Object;
       9: aload_0
      10: aload_2
      11: putfield      #4                  // Field wrapper:Lfreemarker/ext/beans/BeansWrapper;
      14: iload_3
      15: ifeq          34
      18: aload_1
      19: ifnull        34
      22: aload_2
      23: invokevirtual #5                  // Method freemarker/ext/beans/BeansWrapper.getClassIntrospector:()Lfreemarker/ext/beans/ClassIntrospector;
      26: aload_1
      27: invokevirtual #6                  // Method java/lang/Object.getClass:()Ljava/lang/Class;
      30: invokevirtual #7                  // Method freemarker/ext/beans/ClassIntrospector.get:(Ljava/lang/Class;)Ljava/util/Map;
      33: pop
      34: return

  public freemarker.template.TemplateModel get(java.lang.String) throws freemarker.template.TemplateModelException;
    Code:
       0: aload_0
       1: getfield      #3                  // Field object:Ljava/lang/Object;
       4: invokevirtual #6                  // Method java/lang/Object.getClass:()Ljava/lang/Class;
       7: astore_2
       8: aload_0
       9: getfield      #4                  // Field wrapper:Lfreemarker/ext/beans/BeansWrapper;
      12: invokevirtual #5                  // Method freemarker/ext/beans/BeansWrapper.getClassIntrospector:()Lfreemarker/ext/beans/ClassIntrospector;
      15: aload_2
      16: invokevirtual #7                  // Method freemarker/ext/beans/ClassIntrospector.get:(Ljava/lang/Class;)Ljava/util/Map;
      19: astore_3
      20: aconst_null
      21: astore        4
      23: aload_0
      24: getfield      #4                  // Field wrapper:Lfreemarker/ext/beans/BeansWrapper;
      27: invokevirtual #8                  // Method freemarker/ext/beans/BeansWrapper.isMethodsShadowItems:()Z
      30: ifeq          71
      33: aload_3
      34: aload_1
      35: invokeinterface #9,  2            // InterfaceMethod java/util/Map.get:(Ljava/lang/Object;)Ljava/lang/Object;
      40: astore        5
      42: aload         5
      44: ifnull        59
      47: aload_0
      48: aload         5
      50: aload_3
      51: invokespecial #10                 // Method invokeThroughDescriptor:(Ljava/lang/Object;Ljava/util/Map;)Lfreemarker/template/TemplateModel;
      54: astore        4
      56: goto          68
      59: aload_0
      60: aload_3
      61: aload_2
      62: aload_1
      63: invokevirtual #11                 // Method invokeGenericGet:(Ljava/util/Map;Ljava/lang/Class;Ljava/lang/String;)Lfreemarker/template/TemplateModel;
      66: astore        4
      68: goto          150
      71: aload_0
      72: aload_3
      73: aload_2
      74: aload_1
      75: invokevirtual #11                 // Method invokeGenericGet:(Ljava/util/Map;Ljava/lang/Class;Ljava/lang/String;)Lfreemarker/template/TemplateModel;
      78: astore        5
      80: aload_0
      81: getfield      #4                  // Field wrapper:Lfreemarker/ext/beans/BeansWrapper;
      84: aconst_null
      85: invokevirtual #12                 // Method freemarker/ext/beans/BeansWrapper.wrap:(Ljava/lang/Object;)Lfreemarker/template/TemplateModel;
      88: astore        6
      90: aload         5
      92: aload         6
      94: if_acmpeq     108
      97: aload         5
      99: getstatic     #13                 // Field UNKNOWN:Lfreemarker/template/TemplateModel;
     102: if_acmpeq     108
     105: aload         5
     107: areturn
     108: aload_3
     109: aload_1
     110: invokeinterface #9,  2            // InterfaceMethod java/util/Map.get:(Ljava/lang/Object;)Ljava/lang/Object;
     115: astore        7
     117: aload         7
     119: ifnull        150
     122: aload_0
     123: aload         7
     125: aload_3
     126: invokespecial #10                 // Method invokeThroughDescriptor:(Ljava/lang/Object;Ljava/util/Map;)Lfreemarker/template/TemplateModel;
     129: astore        4
     131: aload         4
     133: getstatic     #13                 // Field UNKNOWN:Lfreemarker/template/TemplateModel;
     136: if_acmpne     150
     139: aload         5
     141: aload         6
     143: if_acmpne     150
     146: aload         6
     148: astore        4
     150: aload         4
     152: getstatic     #13                 // Field UNKNOWN:Lfreemarker/template/TemplateModel;
     155: if_acmpne     220
     158: aload_0
     159: getfield      #4                  // Field wrapper:Lfreemarker/ext/beans/BeansWrapper;
     162: invokevirtual #14                 // Method freemarker/ext/beans/BeansWrapper.isStrict:()Z
     165: ifeq          195
     168: new           #15                 // class freemarker/ext/beans/InvalidPropertyException
     171: dup
     172: new           #16                 // class java/lang/StringBuilder
     175: dup
     176: invokespecial #17                 // Method java/lang/StringBuilder."<init>":()V
     179: ldc           #18                 // String No such bean property:
     181: invokevirtual #19                 // Method java/lang/StringBuilder.append:(Ljava/lang/String;)Ljava/lang/StringBuilder;
     184: aload_1
     185: invokevirtual #19                 // Method java/lang/StringBuilder.append:(Ljava/lang/String;)Ljava/lang/StringBuilder;
     188: invokevirtual #20                 // Method java/lang/StringBuilder.toString:()Ljava/lang/String;
     191: invokespecial #21                 // Method freemarker/ext/beans/InvalidPropertyException."<init>":(Ljava/lang/String;)V
     194: athrow
     195: getstatic     #22                 // Field LOG:Lfreemarker/log/Logger;
     198: invokevirtual #23                 // Method freemarker/log/Logger.isDebugEnabled:()Z
     201: ifeq          210
     204: aload_0
     205: aload_1
     206: aload_3
     207: invokespecial #24                 // Method logNoSuchKey:(Ljava/lang/String;Ljava/util/Map;)V
     210: aload_0
     211: getfield      #4                  // Field wrapper:Lfreemarker/ext/beans/BeansWrapper;
     214: aconst_null
     215: invokevirtual #12                 // Method freemarker/ext/beans/BeansWrapper.wrap:(Ljava/lang/Object;)Lfreemarker/template/TemplateModel;
     218: astore        4
     220: aload         4
     222: areturn
     223: astore        5
     225: aload         5
     227: athrow
     228: astore        5
     230: new           #27                 // class freemarker/core/_TemplateModelException
     233: dup
     234: aload         5
     236: iconst_4
     237: anewarray     #28                 // class java/lang/Object
     240: dup
     241: iconst_0
     242: ldc           #29                 // String An error has occurred when reading existing sub-variable
     244: aastore
     245: dup
     246: iconst_1
     247: new           #30                 // class freemarker/core/_DelayedJQuote
     250: dup
     251: aload_1
     252: invokespecial #31                 // Method freemarker/core/_DelayedJQuote."<init>":(Ljava/lang/Object;)V
     255: aastore
     256: dup
     257: iconst_2
     258: ldc           #32                 // String ; see cause exception! The type of the containing value was:
     260: aastore
     261: dup
     262: iconst_3
     263: new           #33                 // class freemarker/core/_DelayedFTLTypeDescription
     266: dup
     267: aload_0
     268: invokespecial #34                 // Method freemarker/core/_DelayedFTLTypeDescription."<init>":(Lfreemarker/template/TemplateModel;)V
     271: aastore
     272: invokespecial #35                 // Method freemarker/core/_TemplateModelException."<init>":(Ljava/lang/Throwable;[Ljava/lang/Object;)V
     275: athrow
    Exception table:
       from    to  target type
          23   107   223   Class freemarker/template/TemplateModelException
         108   222   223   Class freemarker/template/TemplateModelException
          23   107   228   Class java/lang/Exception
         108   222   228   Class java/lang/Exception

  private void logNoSuchKey(java.lang.String, java.util.Map);
    Code:
       0: getstatic     #22                 // Field LOG:Lfreemarker/log/Logger;
       3: new           #16                 // class java/lang/StringBuilder
       6: dup
       7: invokespecial #17                 // Method java/lang/StringBuilder."<init>":()V
      10: ldc           #36                 // String Key
      12: invokevirtual #19                 // Method java/lang/StringBuilder.append:(Ljava/lang/String;)Ljava/lang/StringBuilder;
      15: aload_1
      16: invokestatic  #37                 // Method freemarker/template/utility/StringUtil.jQuoteNoXSS:(Ljava/lang/String;)Ljava/lang/String;
      19: invokevirtual #19                 // Method java/lang/StringBuilder.append:(Ljava/lang/String;)Ljava/lang/StringBuilder;
      22: ldc           #38                 // String  was not found on instance of
      24: invokevirtual #19                 // Method java/lang/StringBuilder.append:(Ljava/lang/String;)Ljava/lang/StringBuilder;
      27: aload_0
      28: getfield      #3                  // Field object:Ljava/lang/Object;
      31: invokevirtual #6                  // Method java/lang/Object.getClass:()Ljava/lang/Class;
      34: invokevirtual #39                 // Method java/lang/Class.getName:()Ljava/lang/String;
      37: invokevirtual #19                 // Method java/lang/StringBuilder.append:(Ljava/lang/String;)Ljava/lang/StringBuilder;
      40: ldc           #40                 // String . Introspection information for
      42: invokevirtual #19                 // Method java/lang/StringBuilder.append:(Ljava/lang/String;)Ljava/lang/StringBuilder;
      45: ldc           #41                 // String the class is:
      47: invokevirtual #19                 // Method java/lang/StringBuilder.append:(Ljava/lang/String;)Ljava/lang/StringBuilder;
      50: aload_2
      51: invokevirtual #42                 // Method java/lang/StringBuilder.append:(Ljava/lang/Object;)Ljava/lang/StringBuilder;
      54: invokevirtual #20                 // Method java/lang/StringBuilder.toString:()Ljava/lang/String;
      57: invokevirtual #43                 // Method freemarker/log/Logger.debug:(Ljava/lang/String;)V
      60: return

  protected boolean hasPlainGetMethod();
    Code:
       0: aload_0
       1: getfield      #4                  // Field wrapper:Lfreemarker/ext/beans/BeansWrapper;
       4: invokevirtual #5                  // Method freemarker/ext/beans/BeansWrapper.getClassIntrospector:()Lfreemarker/ext/beans/ClassIntrospector;
       7: aload_0
       8: getfield      #3                  // Field object:Ljava/lang/Object;
      11: invokevirtual #6                  // Method java/lang/Object.getClass:()Ljava/lang/Class;
      14: invokevirtual #7                  // Method freemarker/ext/beans/ClassIntrospector.get:(Ljava/lang/Class;)Ljava/util/Map;
      17: getstatic     #44                 // Field freemarker/ext/beans/ClassIntrospector.GENERIC_GET_KEY:Ljava/lang/Object;
      20: invokeinterface #9,  2            // InterfaceMethod java/util/Map.get:(Ljava/lang/Object;)Ljava/lang/Object;
      25: ifnull        32
      28: iconst_1
      29: goto          33
      32: iconst_0
      33: ireturn

  private freemarker.template.TemplateModel invokeThroughDescriptor(java.lang.Object, java.util.Map) throws java.lang.IllegalAccessException, java.lang.reflect.InvocationTargetException, freemarker.template.TemplateModelException;
    Code:
       0: aload_0
       1: dup
       2: astore        4
       4: monitorenter
       5: aload_0
       6: getfield      #45                 // Field memberMap:Ljava/util/HashMap;
       9: ifnull        27
      12: aload_0
      13: getfield      #45                 // Field memberMap:Ljava/util/HashMap;
      16: aload_1
      17: invokevirtual #46                 // Method java/util/HashMap.get:(Ljava/lang/Object;)Ljava/lang/Object;
      20: checkcast     #47                 // class freemarker/template/TemplateModel
      23: astore_3
      24: goto          29
      27: aconst_null
      28: astore_3
      29: aload         4
      31: monitorexit
      32: goto          43
      35: astore        5
      37: aload         4
      39: monitorexit
      40: aload         5
      42: athrow
      43: aload_3
      44: ifnull        49
      47: aload_3
      48: areturn
      49: getstatic     #13                 // Field UNKNOWN:Lfreemarker/template/TemplateModel;
      52: astore        4
      54: aload_1
      55: instanceof    #48                 // class java/beans/IndexedPropertyDescriptor
      58: ifeq          100
      61: aload_1
      62: checkcast     #48                 // class java/beans/IndexedPropertyDescriptor
      65: invokevirtual #49                 // Method java/beans/IndexedPropertyDescriptor.getIndexedReadMethod:()Ljava/lang/reflect/Method;
      68: astore        5
      70: new           #50                 // class freemarker/ext/beans/SimpleMethodModel
      73: dup
      74: aload_0
      75: getfield      #3                  // Field object:Ljava/lang/Object;
      78: aload         5
      80: aload_2
      81: aload         5
      83: invokestatic  #51                 // Method freemarker/ext/beans/ClassIntrospector.getArgTypes:(Ljava/util/Map;Ljava/lang/reflect/AccessibleObject;)[Ljava/lang/Class;
      86: aload_0
      87: getfield      #4                  // Field wrapper:Lfreemarker/ext/beans/BeansWrapper;
      90: invokespecial #52                 // Method freemarker/ext/beans/SimpleMethodModel."<init>":(Ljava/lang/Object;Ljava/lang/reflect/Method;[Ljava/lang/Class;Lfreemarker/ext/beans/BeansWrapper;)V
      93: dup
      94: astore_3
      95: astore        4
      97: goto          238
     100: aload_1
     101: instanceof    #53                 // class java/beans/PropertyDescriptor
     104: ifeq          135
     107: aload_1
     108: checkcast     #53                 // class java/beans/PropertyDescriptor
     111: astore        5
     113: aload_0
     114: getfield      #4                  // Field wrapper:Lfreemarker/ext/beans/BeansWrapper;
     117: aload_0
     118: getfield      #3                  // Field object:Ljava/lang/Object;
     121: aload         5
     123: invokevirtual #54                 // Method java/beans/PropertyDescriptor.getReadMethod:()Ljava/lang/reflect/Method;
     126: aconst_null
     127: invokevirtual #55                 // Method freemarker/ext/beans/BeansWrapper.invokeMethod:(Ljava/lang/Object;Ljava/lang/reflect/Method;[Ljava/lang/Object;)Lfreemarker/template/TemplateModel;
     130: astore        4
     132: goto          238
     135: aload_1
     136: instanceof    #56                 // class java/lang/reflect/Field
     139: ifeq          165
     142: aload_0
     143: getfield      #4                  // Field wrapper:Lfreemarker/ext/beans/BeansWrapper;
     146: aload_1
     147: checkcast     #56                 // class java/lang/reflect/Field
     150: aload_0
     151: getfield      #3                  // Field object:Ljava/lang/Object;
     154: invokevirtual #57                 // Method java/lang/reflect/Field.get:(Ljava/lang/Object;)Ljava/lang/Object;
     157: invokevirtual #12                 // Method freemarker/ext/beans/BeansWrapper.wrap:(Ljava/lang/Object;)Lfreemarker/template/TemplateModel;
     160: astore        4
     162: goto          238
     165: aload_1
     166: instanceof    #58                 // class java/lang/reflect/Method
     169: ifeq          208
     172: aload_1
     173: checkcast     #58                 // class java/lang/reflect/Method
     176: astore        5
     178: new           #50                 // class freemarker/ext/beans/SimpleMethodModel
     181: dup
     182: aload_0
     183: getfield      #3                  // Field object:Ljava/lang/Object;
     186: aload         5
     188: aload_2
     189: aload         5
     191: invokestatic  #51                 // Method freemarker/ext/beans/ClassIntrospector.getArgTypes:(Ljava/util/Map;Ljava/lang/reflect/AccessibleObject;)[Ljava/lang/Class;
     194: aload_0
     195: getfield      #4                  // Field wrapper:Lfreemarker/ext/beans/BeansWrapper;
     198: invokespecial #52                 // Method freemarker/ext/beans/SimpleMethodModel."<init>":(Ljava/lang/Object;Ljava/lang/reflect/Method;[Ljava/lang/Class;Lfreemarker/ext/beans/BeansWrapper;)V
     201: dup
     202: astore_3
     203: astore        4
     205: goto          238
     208: aload_1
     209: instanceof    #59                 // class freemarker/ext/beans/OverloadedMethods
     212: ifeq          238
     215: new           #60                 // class freemarker/ext/beans/OverloadedMethodsModel
     218: dup
     219: aload_0
     220: getfield      #3                  // Field object:Ljava/lang/Object;
     223: aload_1
     224: checkcast     #59                 // class freemarker/ext/beans/OverloadedMethods
     227: aload_0
     228: getfield      #4                  // Field wrapper:Lfreemarker/ext/beans/BeansWrapper;
     231: invokespecial #61                 // Method freemarker/ext/beans/OverloadedMethodsModel."<init>":(Ljava/lang/Object;Lfreemarker/ext/beans/OverloadedMethods;Lfreemarker/ext/beans/BeansWrapper;)V
     234: dup
     235: astore_3
     236: astore        4
     238: aload_3
     239: ifnull        289
     242: aload_0
     243: dup
     244: astore        5
     246: monitorenter
     247: aload_0
     248: getfield      #45                 // Field memberMap:Ljava/util/HashMap;
     251: ifnonnull     265
     254: aload_0
     255: new           #62                 // class java/util/HashMap
     258: dup
     259: invokespecial #63                 // Method java/util/HashMap."<init>":()V
     262: putfield      #45                 // Field memberMap:Ljava/util/HashMap;
     265: aload_0
     266: getfield      #45                 // Field memberMap:Ljava/util/HashMap;
     269: aload_1
     270: aload_3
     271: invokevirtual #64                 // Method java/util/HashMap.put:(Ljava/lang/Object;Ljava/lang/Object;)Ljava/lang/Object;
     274: pop
     275: aload         5
     277: monitorexit
     278: goto          289
     281: astore        6
     283: aload         5
     285: monitorexit
     286: aload         6
     288: athrow
     289: aload         4
     291: areturn
    Exception table:
       from    to  target type
           5    32    35   any
          35    40    35   any
         247   278   281   any
         281   286   281   any

  void clearMemberCache();
    Code:
       0: aload_0
       1: dup
       2: astore_1
       3: monitorenter
       4: aload_0
       5: aconst_null
       6: putfield      #45                 // Field memberMap:Ljava/util/HashMap;
       9: aload_1
      10: monitorexit
      11: goto          19
      14: astore_2
      15: aload_1
      16: monitorexit
      17: aload_2
      18: athrow
      19: return
    Exception table:
       from    to  target type
           4    11    14   any
          14    17    14   any

  protected freemarker.template.TemplateModel invokeGenericGet(java.util.Map, java.lang.Class, java.lang.String) throws java.lang.IllegalAccessException, java.lang.reflect.InvocationTargetException, freemarker.template.TemplateModelException;
    Code:
       0: aload_1
       1: getstatic     #44                 // Field freemarker/ext/beans/ClassIntrospector.GENERIC_GET_KEY:Ljava/lang/Object;
       4: invokeinterface #9,  2            // InterfaceMethod java/util/Map.get:(Ljava/lang/Object;)Ljava/lang/Object;
       9: checkcast     #58                 // class java/lang/reflect/Method
      12: astore        4
      14: aload         4
      16: ifnonnull     23
      19: getstatic     #13                 // Field UNKNOWN:Lfreemarker/template/TemplateModel;
      22: areturn
      23: aload_0
      24: getfield      #4                  // Field wrapper:Lfreemarker/ext/beans/BeansWrapper;
      27: aload_0
      28: getfield      #3                  // Field object:Ljava/lang/Object;
      31: aload         4
      33: iconst_1
      34: anewarray     #28                 // class java/lang/Object
      37: dup
      38: iconst_0
      39: aload_3
      40: aastore
      41: invokevirtual #55                 // Method freemarker/ext/beans/BeansWrapper.invokeMethod:(Ljava/lang/Object;Ljava/lang/reflect/Method;[Ljava/lang/Object;)Lfreemarker/template/TemplateModel;
      44: areturn

  protected freemarker.template.TemplateModel wrap(java.lang.Object) throws freemarker.template.TemplateModelException;
    Code:
       0: aload_0
       1: getfield      #4                  // Field wrapper:Lfreemarker/ext/beans/BeansWrapper;
       4: invokevirtual #65                 // Method freemarker/ext/beans/BeansWrapper.getOuterIdentity:()Lfreemarker/template/ObjectWrapper;
       7: aload_1
       8: invokeinterface #66,  2           // InterfaceMethod freemarker/template/ObjectWrapper.wrap:(Ljava/lang/Object;)Lfreemarker/template/TemplateModel;
      13: areturn

  protected java.lang.Object unwrap(freemarker.template.TemplateModel) throws freemarker.template.TemplateModelException;
    Code:
       0: aload_0
       1: getfield      #4                  // Field wrapper:Lfreemarker/ext/beans/BeansWrapper;
       4: aload_1
       5: invokevirtual #67                 // Method freemarker/ext/beans/BeansWrapper.unwrap:(Lfreemarker/template/TemplateModel;)Ljava/lang/Object;
       8: areturn

  public boolean isEmpty();
    Code:
       0: aload_0
       1: getfield      #3                  // Field object:Ljava/lang/Object;
       4: instanceof    #68                 // class java/lang/String
       7: ifeq          29
      10: aload_0
      11: getfield      #3                  // Field object:Ljava/lang/Object;
      14: checkcast     #68                 // class java/lang/String
      17: invokevirtual #69                 // Method java/lang/String.length:()I
      20: ifne          27
      23: iconst_1
      24: goto          28
      27: iconst_0
      28: ireturn
      29: aload_0
      30: getfield      #3                  // Field object:Ljava/lang/Object;
      33: instanceof    #70                 // class java/util/Collection
      36: ifeq          52
      39: aload_0
      40: getfield      #3                  // Field object:Ljava/lang/Object;
      43: checkcast     #70                 // class java/util/Collection
      46: invokeinterface #71,  1           // InterfaceMethod java/util/Collection.isEmpty:()Z
      51: ireturn
      52: aload_0
      53: getfield      #3                  // Field object:Ljava/lang/Object;
      56: instanceof    #72                 // class java/util/Iterator
      59: ifeq          93
      62: aload_0
      63: getfield      #4                  // Field wrapper:Lfreemarker/ext/beans/BeansWrapper;
      66: invokevirtual #73                 // Method freemarker/ext/beans/BeansWrapper.is2324Bugfixed:()Z
      69: ifeq          93
      72: aload_0
      73: getfield      #3                  // Field object:Ljava/lang/Object;
      76: checkcast     #72                 // class java/util/Iterator
      79: invokeinterface #74,  1           // InterfaceMethod java/util/Iterator.hasNext:()Z
      84: ifne          91
      87: iconst_1
      88: goto          92
      91: iconst_0
      92: ireturn
      93: aload_0
      94: getfield      #3                  // Field object:Ljava/lang/Object;
      97: instanceof    #75                 // class java/util/Map
     100: ifeq          116
     103: aload_0
     104: getfield      #3                  // Field object:Ljava/lang/Object;
     107: checkcast     #75                 // class java/util/Map
     110: invokeinterface #76,  1           // InterfaceMethod java/util/Map.isEmpty:()Z
     115: ireturn
     116: aload_0
     117: getfield      #3                  // Field object:Ljava/lang/Object;
     120: ifnull        136
     123: getstatic     #77                 // Field java/lang/Boolean.FALSE:Ljava/lang/Boolean;
     126: aload_0
     127: getfield      #3                  // Field object:Ljava/lang/Object;
     130: invokevirtual #78                 // Method java/lang/Boolean.equals:(Ljava/lang/Object;)Z
     133: ifeq          140
     136: iconst_1
     137: goto          141
     140: iconst_0
     141: ireturn

  public java.lang.Object getAdaptedObject(java.lang.Class);
    Code:
       0: aload_0
       1: getfield      #3                  // Field object:Ljava/lang/Object;
       4: areturn

  public java.lang.Object getWrappedObject();
    Code:
       0: aload_0
       1: getfield      #3                  // Field object:Ljava/lang/Object;
       4: areturn

  public int size();
    Code:
       0: aload_0
       1: getfield      #4                  // Field wrapper:Lfreemarker/ext/beans/BeansWrapper;
       4: invokevirtual #5                  // Method freemarker/ext/beans/BeansWrapper.getClassIntrospector:()Lfreemarker/ext/beans/ClassIntrospector;
       7: aload_0
       8: getfield      #3                  // Field object:Ljava/lang/Object;
      11: invokevirtual #6                  // Method java/lang/Object.getClass:()Ljava/lang/Class;
      14: invokevirtual #79                 // Method freemarker/ext/beans/ClassIntrospector.keyCount:(Ljava/lang/Class;)I
      17: ireturn

  public freemarker.template.TemplateCollectionModel keys();
    Code:
       0: new           #80                 // class freemarker/core/CollectionAndSequence
       3: dup
       4: new           #81                 // class freemarker/template/SimpleSequence
       7: dup
       8: aload_0
       9: invokevirtual #82                 // Method keySet:()Ljava/util/Set;
      12: aload_0
      13: getfield      #4                  // Field wrapper:Lfreemarker/ext/beans/BeansWrapper;
      16: invokespecial #83                 // Method freemarker/template/SimpleSequence."<init>":(Ljava/util/Collection;Lfreemarker/template/ObjectWrapper;)V
      19: invokespecial #84                 // Method freemarker/core/CollectionAndSequence."<init>":(Lfreemarker/template/TemplateSequenceModel;)V
      22: areturn

  public freemarker.template.TemplateCollectionModel values() throws freemarker.template.TemplateModelException;
    Code:
       0: new           #85                 // class java/util/ArrayList
       3: dup
       4: aload_0
       5: invokevirtual #86                 // Method size:()I
       8: invokespecial #87                 // Method java/util/ArrayList."<init>":(I)V
      11: astore_1
      12: aload_0
      13: invokevirtual #88                 // Method keys:()Lfreemarker/template/TemplateCollectionModel;
      16: invokeinterface #89,  1           // InterfaceMethod freemarker/template/TemplateCollectionModel.iterator:()Lfreemarker/template/TemplateModelIterator;
      21: astore_2
      22: aload_2
      23: invokeinterface #90,  1           // InterfaceMethod freemarker/template/TemplateModelIterator.hasNext:()Z
      28: ifeq          61
      31: aload_2
      32: invokeinterface #91,  1           // InterfaceMethod freemarker/template/TemplateModelIterator.next:()Lfreemarker/template/TemplateModel;
      37: checkcast     #92                 // class freemarker/template/TemplateScalarModel
      40: invokeinterface #93,  1           // InterfaceMethod freemarker/template/TemplateScalarModel.getAsString:()Ljava/lang/String;
      45: astore_3
      46: aload_1
      47: aload_0
      48: aload_3
      49: invokevirtual #94                 // Method get:(Ljava/lang/String;)Lfreemarker/template/TemplateModel;
      52: invokeinterface #95,  2           // InterfaceMethod java/util/List.add:(Ljava/lang/Object;)Z
      57: pop
      58: goto          22
      61: new           #80                 // class freemarker/core/CollectionAndSequence
      64: dup
      65: new           #81                 // class freemarker/template/SimpleSequence
      68: dup
      69: aload_1
      70: aload_0
      71: getfield      #4                  // Field wrapper:Lfreemarker/ext/beans/BeansWrapper;
      74: invokespecial #83                 // Method freemarker/template/SimpleSequence."<init>":(Ljava/util/Collection;Lfreemarker/template/ObjectWrapper;)V
      77: invokespecial #84                 // Method freemarker/core/CollectionAndSequence."<init>":(Lfreemarker/template/TemplateSequenceModel;)V
      80: areturn

  java.lang.String getAsClassicCompatibleString();
    Code:
       0: aload_0
       1: getfield      #3                  // Field object:Ljava/lang/Object;
       4: ifnonnull     10
       7: ldc           #96                 // String null
       9: areturn
      10: aload_0
      11: getfield      #3                  // Field object:Ljava/lang/Object;
      14: invokevirtual #97                 // Method java/lang/Object.toString:()Ljava/lang/String;
      17: astore_1
      18: aload_1
      19: ifnull        26
      22: aload_1
      23: goto          28
      26: ldc           #96                 // String null
      28: areturn

  public java.lang.String toString();
    Code:
       0: aload_0
       1: getfield      #3                  // Field object:Ljava/lang/Object;
       4: invokevirtual #97                 // Method java/lang/Object.toString:()Ljava/lang/String;
       7: areturn

  protected java.util.Set keySet();
    Code:
       0: aload_0
       1: getfield      #4                  // Field wrapper:Lfreemarker/ext/beans/BeansWrapper;
       4: invokevirtual #5                  // Method freemarker/ext/beans/BeansWrapper.getClassIntrospector:()Lfreemarker/ext/beans/ClassIntrospector;
       7: aload_0
       8: getfield      #3                  // Field object:Ljava/lang/Object;
      11: invokevirtual #6                  // Method java/lang/Object.getClass:()Ljava/lang/Class;
      14: invokevirtual #98                 // Method freemarker/ext/beans/ClassIntrospector.keySet:(Ljava/lang/Class;)Ljava/util/Set;
      17: areturn

  public freemarker.template.TemplateModel getAPI() throws freemarker.template.TemplateModelException;
    Code:
       0: aload_0
       1: getfield      #4                  // Field wrapper:Lfreemarker/ext/beans/BeansWrapper;
       4: aload_0
       5: getfield      #3                  // Field object:Ljava/lang/Object;
       8: invokevirtual #99                 // Method freemarker/ext/beans/BeansWrapper.wrapAsAPI:(Ljava/lang/Object;)Lfreemarker/template/TemplateHashModel;
      11: areturn

  static {};
    Code:
       0: ldc           #100                // String freemarker.beans
       2: invokestatic  #101                // Method freemarker/log/Logger.getLogger:(Ljava/lang/String;)Lfreemarker/log/Logger;
       5: putstatic     #22                 // Field LOG:Lfreemarker/log/Logger;
       8: new           #102                // class freemarker/template/SimpleScalar
      11: dup
      12: ldc           #103                // String UNKNOWN
      14: invokespecial #104                // Method freemarker/template/SimpleScalar."<init>":(Ljava/lang/String;)V
      17: putstatic     #13                 // Field UNKNOWN:Lfreemarker/template/TemplateModel;
      20: new           #105                // class freemarker/ext/beans/BeanModel$1
      23: dup
      24: invokespecial #106                // Method freemarker/ext/beans/BeanModel$1."<init>":()V
      27: putstatic     #107                // Field FACTORY:Lfreemarker/ext/util/ModelFactory;
      30: return
}
