Compiled from "DefaultHttpRequest.java"
public class io.netty.handler.codec.http.DefaultHttpRequest extends io.netty.handler.codec.http.DefaultHttpMessage implements io.netty.handler.codec.http.HttpRequest {
  private static final int HASH_CODE_PRIME;

  private io.netty.handler.codec.http.HttpMethod method;

  private java.lang.String uri;

  public io.netty.handler.codec.http.DefaultHttpRequest(io.netty.handler.codec.http.HttpVersion, io.netty.handler.codec.http.HttpMethod, java.lang.String);
    Code:
       0: aload_0
       1: aload_1
       2: aload_2
       3: aload_3
       4: iconst_1
       5: invokespecial #1                  // Method "<init>":(Lio/netty/handler/codec/http/HttpVersion;Lio/netty/handler/codec/http/HttpMethod;Ljava/lang/String;Z)V
       8: return

  public io.netty.handler.codec.http.DefaultHttpRequest(io.netty.handler.codec.http.HttpVersion, io.netty.handler.codec.http.HttpMethod, java.lang.String, boolean);
    Code:
       0: aload_0
       1: aload_1
       2: iload         4
       4: iconst_0
       5: invokespecial #2                  // Method io/netty/handler/codec/http/DefaultHttpMessage."<init>":(Lio/netty/handler/codec/http/HttpVersion;ZZ)V
       8: aload_0
       9: aload_2
      10: ldc           #3                  // String method
      12: invokestatic  #4                  // Method io/netty/util/internal/ObjectUtil.checkNotNull:(Ljava/lang/Object;Ljava/lang/String;)Ljava/lang/Object;
      15: checkcast     #5                  // class io/netty/handler/codec/http/HttpMethod
      18: putfield      #6                  // Field method:Lio/netty/handler/codec/http/HttpMethod;
      21: aload_0
      22: aload_3
      23: ldc           #7                  // String uri
      25: invokestatic  #4                  // Method io/netty/util/internal/ObjectUtil.checkNotNull:(Ljava/lang/Object;Ljava/lang/String;)Ljava/lang/Object;
      28: checkcast     #8                  // class java/lang/String
      31: putfield      #9                  // Field uri:Ljava/lang/String;
      34: return

  public io.netty.handler.codec.http.DefaultHttpRequest(io.netty.handler.codec.http.HttpVersion, io.netty.handler.codec.http.HttpMethod, java.lang.String, io.netty.handler.codec.http.HttpHeaders);
    Code:
       0: aload_0
       1: aload_1
       2: aload         4
       4: invokespecial #10                 // Method io/netty/handler/codec/http/DefaultHttpMessage."<init>":(Lio/netty/handler/codec/http/HttpVersion;Lio/netty/handler/codec/http/HttpHeaders;)V
       7: aload_0
       8: aload_2
       9: ldc           #3                  // String method
      11: invokestatic  #4                  // Method io/netty/util/internal/ObjectUtil.checkNotNull:(Ljava/lang/Object;Ljava/lang/String;)Ljava/lang/Object;
      14: checkcast     #5                  // class io/netty/handler/codec/http/HttpMethod
      17: putfield      #6                  // Field method:Lio/netty/handler/codec/http/HttpMethod;
      20: aload_0
      21: aload_3
      22: ldc           #7                  // String uri
      24: invokestatic  #4                  // Method io/netty/util/internal/ObjectUtil.checkNotNull:(Ljava/lang/Object;Ljava/lang/String;)Ljava/lang/Object;
      27: checkcast     #8                  // class java/lang/String
      30: putfield      #9                  // Field uri:Ljava/lang/String;
      33: return

  public io.netty.handler.codec.http.HttpMethod getMethod();
    Code:
       0: aload_0
       1: invokevirtual #11                 // Method method:()Lio/netty/handler/codec/http/HttpMethod;
       4: areturn

  public io.netty.handler.codec.http.HttpMethod method();
    Code:
       0: aload_0
       1: getfield      #6                  // Field method:Lio/netty/handler/codec/http/HttpMethod;
       4: areturn

  public java.lang.String getUri();
    Code:
       0: aload_0
       1: invokevirtual #12                 // Method uri:()Ljava/lang/String;
       4: areturn

  public java.lang.String uri();
    Code:
       0: aload_0
       1: getfield      #9                  // Field uri:Ljava/lang/String;
       4: areturn

  public io.netty.handler.codec.http.HttpRequest setMethod(io.netty.handler.codec.http.HttpMethod);
    Code:
       0: aload_0
       1: aload_1
       2: ldc           #3                  // String method
       4: invokestatic  #4                  // Method io/netty/util/internal/ObjectUtil.checkNotNull:(Ljava/lang/Object;Ljava/lang/String;)Ljava/lang/Object;
       7: checkcast     #5                  // class io/netty/handler/codec/http/HttpMethod
      10: putfield      #6                  // Field method:Lio/netty/handler/codec/http/HttpMethod;
      13: aload_0
      14: areturn

  public io.netty.handler.codec.http.HttpRequest setUri(java.lang.String);
    Code:
       0: aload_0
       1: aload_1
       2: ldc           #7                  // String uri
       4: invokestatic  #4                  // Method io/netty/util/internal/ObjectUtil.checkNotNull:(Ljava/lang/Object;Ljava/lang/String;)Ljava/lang/Object;
       7: checkcast     #8                  // class java/lang/String
      10: putfield      #9                  // Field uri:Ljava/lang/String;
      13: aload_0
      14: areturn

  public io.netty.handler.codec.http.HttpRequest setProtocolVersion(io.netty.handler.codec.http.HttpVersion);
    Code:
       0: aload_0
       1: aload_1
       2: invokespecial #13                 // Method io/netty/handler/codec/http/DefaultHttpMessage.setProtocolVersion:(Lio/netty/handler/codec/http/HttpVersion;)Lio/netty/handler/codec/http/HttpMessage;
       5: pop
       6: aload_0
       7: areturn

  public int hashCode();
    Code:
       0: iconst_1
       1: istore_1
       2: bipush        31
       4: iload_1
       5: imul
       6: aload_0
       7: getfield      #6                  // Field method:Lio/netty/handler/codec/http/HttpMethod;
      10: invokevirtual #15                 // Method io/netty/handler/codec/http/HttpMethod.hashCode:()I
      13: iadd
      14: istore_1
      15: bipush        31
      17: iload_1
      18: imul
      19: aload_0
      20: getfield      #9                  // Field uri:Ljava/lang/String;
      23: invokevirtual #16                 // Method java/lang/String.hashCode:()I
      26: iadd
      27: istore_1
      28: bipush        31
      30: iload_1
      31: imul
      32: aload_0
      33: invokespecial #17                 // Method io/netty/handler/codec/http/DefaultHttpMessage.hashCode:()I
      36: iadd
      37: istore_1
      38: iload_1
      39: ireturn

  public boolean equals(java.lang.Object);
    Code:
       0: aload_1
       1: instanceof    #14                 // class io/netty/handler/codec/http/DefaultHttpRequest
       4: ifne          9
       7: iconst_0
       8: ireturn
       9: aload_1
      10: checkcast     #14                 // class io/netty/handler/codec/http/DefaultHttpRequest
      13: astore_2
      14: aload_0
      15: invokevirtual #11                 // Method method:()Lio/netty/handler/codec/http/HttpMethod;
      18: aload_2
      19: invokevirtual #11                 // Method method:()Lio/netty/handler/codec/http/HttpMethod;
      22: invokevirtual #18                 // Method io/netty/handler/codec/http/HttpMethod.equals:(Ljava/lang/Object;)Z
      25: ifeq          54
      28: aload_0
      29: invokevirtual #12                 // Method uri:()Ljava/lang/String;
      32: aload_2
      33: invokevirtual #12                 // Method uri:()Ljava/lang/String;
      36: invokevirtual #19                 // Method java/lang/String.equalsIgnoreCase:(Ljava/lang/String;)Z
      39: ifeq          54
      42: aload_0
      43: aload_1
      44: invokespecial #20                 // Method io/netty/handler/codec/http/DefaultHttpMessage.equals:(Ljava/lang/Object;)Z
      47: ifeq          54
      50: iconst_1
      51: goto          55
      54: iconst_0
      55: ireturn

  public java.lang.String toString();
    Code:
       0: new           #21                 // class java/lang/StringBuilder
       3: dup
       4: sipush        256
       7: invokespecial #22                 // Method java/lang/StringBuilder."<init>":(I)V
      10: aload_0
      11: invokestatic  #23                 // Method io/netty/handler/codec/http/HttpMessageUtil.appendRequest:(Ljava/lang/StringBuilder;Lio/netty/handler/codec/http/HttpRequest;)Ljava/lang/StringBuilder;
      14: invokevirtual #24                 // Method java/lang/StringBuilder.toString:()Ljava/lang/String;
      17: areturn

  public io.netty.handler.codec.http.HttpMessage setProtocolVersion(io.netty.handler.codec.http.HttpVersion);
    Code:
       0: aload_0
       1: aload_1
       2: invokevirtual #25                 // Method setProtocolVersion:(Lio/netty/handler/codec/http/HttpVersion;)Lio/netty/handler/codec/http/HttpRequest;
       5: areturn
}
