Compiled from "ListNetworksIterable.java"
class software.amazon.awssdk.services.managedblockchain.paginators.ListNetworksIterable$ListNetworksResponseFetcher implements software.amazon.awssdk.core.pagination.sync.SyncPageFetcher<software.amazon.awssdk.services.managedblockchain.model.ListNetworksResponse> {
  final software.amazon.awssdk.services.managedblockchain.paginators.ListNetworksIterable this$0;

  private software.amazon.awssdk.services.managedblockchain.paginators.ListNetworksIterable$ListNetworksResponseFetcher(software.amazon.awssdk.services.managedblockchain.paginators.ListNetworksIterable);
    Code:
       0: aload_0
       1: aload_1
       2: putfield      #2                  // Field this$0:Lsoftware/amazon/awssdk/services/managedblockchain/paginators/ListNetworksIterable;
       5: aload_0
       6: invokespecial #3                  // Method java/lang/Object."<init>":()V
       9: return

  public boolean hasNextPage(software.amazon.awssdk.services.managedblockchain.model.ListNetworksResponse);
    Code:
       0: aload_1
       1: invokevirtual #4                  // Method software/amazon/awssdk/services/managedblockchain/model/ListNetworksResponse.nextToken:()Ljava/lang/String;
       4: invokestatic  #5                  // Method software/amazon/awssdk/core/util/PaginatorUtils.isOutputTokenAvailable:(Ljava/lang/Object;)Z
       7: ireturn

  public software.amazon.awssdk.services.managedblockchain.model.ListNetworksResponse nextPage(software.amazon.awssdk.services.managedblockchain.model.ListNetworksResponse);
    Code:
       0: aload_1
       1: ifnonnull     24
       4: aload_0
       5: getfield      #2                  // Field this$0:Lsoftware/amazon/awssdk/services/managedblockchain/paginators/ListNetworksIterable;
       8: invokestatic  #6                  // Method software/amazon/awssdk/services/managedblockchain/paginators/ListNetworksIterable.access$200:(Lsoftware/amazon/awssdk/services/managedblockchain/paginators/ListNetworksIterable;)Lsoftware/amazon/awssdk/services/managedblockchain/ManagedBlockchainClient;
      11: aload_0
      12: getfield      #2                  // Field this$0:Lsoftware/amazon/awssdk/services/managedblockchain/paginators/ListNetworksIterable;
      15: invokestatic  #7                  // Method software/amazon/awssdk/services/managedblockchain/paginators/ListNetworksIterable.access$100:(Lsoftware/amazon/awssdk/services/managedblockchain/paginators/ListNetworksIterable;)Lsoftware/amazon/awssdk/services/managedblockchain/model/ListNetworksRequest;
      18: invokeinterface #8,  2            // InterfaceMethod software/amazon/awssdk/services/managedblockchain/ManagedBlockchainClient.listNetworks:(Lsoftware/amazon/awssdk/services/managedblockchain/model/ListNetworksRequest;)Lsoftware/amazon/awssdk/services/managedblockchain/model/ListNetworksResponse;
      23: areturn
      24: aload_0
      25: getfield      #2                  // Field this$0:Lsoftware/amazon/awssdk/services/managedblockchain/paginators/ListNetworksIterable;
      28: invokestatic  #6                  // Method software/amazon/awssdk/services/managedblockchain/paginators/ListNetworksIterable.access$200:(Lsoftware/amazon/awssdk/services/managedblockchain/paginators/ListNetworksIterable;)Lsoftware/amazon/awssdk/services/managedblockchain/ManagedBlockchainClient;
      31: aload_0
      32: getfield      #2                  // Field this$0:Lsoftware/amazon/awssdk/services/managedblockchain/paginators/ListNetworksIterable;
      35: invokestatic  #7                  // Method software/amazon/awssdk/services/managedblockchain/paginators/ListNetworksIterable.access$100:(Lsoftware/amazon/awssdk/services/managedblockchain/paginators/ListNetworksIterable;)Lsoftware/amazon/awssdk/services/managedblockchain/model/ListNetworksRequest;
      38: invokevirtual #9                  // Method software/amazon/awssdk/services/managedblockchain/model/ListNetworksRequest.toBuilder:()Lsoftware/amazon/awssdk/services/managedblockchain/model/ListNetworksRequest$Builder;
      41: aload_1
      42: invokevirtual #4                  // Method software/amazon/awssdk/services/managedblockchain/model/ListNetworksResponse.nextToken:()Ljava/lang/String;
      45: invokeinterface #10,  2           // InterfaceMethod software/amazon/awssdk/services/managedblockchain/model/ListNetworksRequest$Builder.nextToken:(Ljava/lang/String;)Lsoftware/amazon/awssdk/services/managedblockchain/model/ListNetworksRequest$Builder;
      50: invokeinterface #11,  1           // InterfaceMethod software/amazon/awssdk/services/managedblockchain/model/ListNetworksRequest$Builder.build:()Ljava/lang/Object;
      55: checkcast     #12                 // class software/amazon/awssdk/services/managedblockchain/model/ListNetworksRequest
      58: invokeinterface #8,  2            // InterfaceMethod software/amazon/awssdk/services/managedblockchain/ManagedBlockchainClient.listNetworks:(Lsoftware/amazon/awssdk/services/managedblockchain/model/ListNetworksRequest;)Lsoftware/amazon/awssdk/services/managedblockchain/model/ListNetworksResponse;
      63: areturn

  public java.lang.Object nextPage(java.lang.Object);
    Code:
       0: aload_0
       1: aload_1
       2: checkcast     #13                 // class software/amazon/awssdk/services/managedblockchain/model/ListNetworksResponse
       5: invokevirtual #14                 // Method nextPage:(Lsoftware/amazon/awssdk/services/managedblockchain/model/ListNetworksResponse;)Lsoftware/amazon/awssdk/services/managedblockchain/model/ListNetworksResponse;
       8: areturn

  public boolean hasNextPage(java.lang.Object);
    Code:
       0: aload_0
       1: aload_1
       2: checkcast     #13                 // class software/amazon/awssdk/services/managedblockchain/model/ListNetworksResponse
       5: invokevirtual #15                 // Method hasNextPage:(Lsoftware/amazon/awssdk/services/managedblockchain/model/ListNetworksResponse;)Z
       8: ireturn

  software.amazon.awssdk.services.managedblockchain.paginators.ListNetworksIterable$ListNetworksResponseFetcher(software.amazon.awssdk.services.managedblockchain.paginators.ListNetworksIterable, software.amazon.awssdk.services.managedblockchain.paginators.ListNetworksIterable$1);
    Code:
       0: aload_0
       1: aload_1
       2: invokespecial #1                  // Method "<init>":(Lsoftware/amazon/awssdk/services/managedblockchain/paginators/ListNetworksIterable;)V
       5: return
}
