Compiled from "ProxySOCKS4.java"
public class com.jcraft.jsch.ProxySOCKS4 implements com.jcraft.jsch.Proxy {
  private static int DEFAULTPORT;

  private java.lang.String proxy_host;

  private int proxy_port;

  private java.io.InputStream in;

  private java.io.OutputStream out;

  private java.net.Socket socket;

  private java.lang.String user;

  private java.lang.String passwd;

  public com.jcraft.jsch.ProxySOCKS4(java.lang.String);
    Code:
       0: aload_0
       1: invokespecial #1                  // Method java/lang/Object."<init>":()V
       4: getstatic     #2                  // Field DEFAULTPORT:I
       7: istore_2
       8: aload_1
       9: astore_3
      10: aload_1
      11: bipush        58
      13: invokevirtual #3                  // Method java/lang/String.indexOf:(I)I
      16: iconst_m1
      17: if_icmpeq     53
      20: aload_1
      21: iconst_0
      22: aload_1
      23: bipush        58
      25: invokevirtual #3                  // Method java/lang/String.indexOf:(I)I
      28: invokevirtual #4                  // Method java/lang/String.substring:(II)Ljava/lang/String;
      31: astore_3
      32: aload_1
      33: aload_1
      34: bipush        58
      36: invokevirtual #3                  // Method java/lang/String.indexOf:(I)I
      39: iconst_1
      40: iadd
      41: invokevirtual #5                  // Method java/lang/String.substring:(I)Ljava/lang/String;
      44: invokestatic  #6                  // Method java/lang/Integer.parseInt:(Ljava/lang/String;)I
      47: istore_2
      48: goto          53
      51: astore        4
      53: aload_0
      54: aload_3
      55: putfield      #8                  // Field proxy_host:Ljava/lang/String;
      58: aload_0
      59: iload_2
      60: putfield      #9                  // Field proxy_port:I
      63: return
    Exception table:
       from    to  target type
          20    48    51   Class java/lang/Exception

  public com.jcraft.jsch.ProxySOCKS4(java.lang.String, int);
    Code:
       0: aload_0
       1: invokespecial #1                  // Method java/lang/Object."<init>":()V
       4: aload_0
       5: aload_1
       6: putfield      #8                  // Field proxy_host:Ljava/lang/String;
       9: aload_0
      10: iload_2
      11: putfield      #9                  // Field proxy_port:I
      14: return

  public void setUserPasswd(java.lang.String, java.lang.String);
    Code:
       0: aload_0
       1: aload_1
       2: putfield      #10                 // Field user:Ljava/lang/String;
       5: aload_0
       6: aload_2
       7: putfield      #11                 // Field passwd:Ljava/lang/String;
      10: return

  public void connect(com.jcraft.jsch.SocketFactory, java.lang.String, int, int) throws com.jcraft.jsch.JSchException;
    Code:
       0: aload_1
       1: ifnonnull     46
       4: aload_0
       5: aload_0
       6: getfield      #8                  // Field proxy_host:Ljava/lang/String;
       9: aload_0
      10: getfield      #9                  // Field proxy_port:I
      13: iload         4
      15: invokestatic  #12                 // Method com/jcraft/jsch/Util.createSocket:(Ljava/lang/String;II)Ljava/net/Socket;
      18: putfield      #13                 // Field socket:Ljava/net/Socket;
      21: aload_0
      22: aload_0
      23: getfield      #13                 // Field socket:Ljava/net/Socket;
      26: invokevirtual #14                 // Method java/net/Socket.getInputStream:()Ljava/io/InputStream;
      29: putfield      #15                 // Field in:Ljava/io/InputStream;
      32: aload_0
      33: aload_0
      34: getfield      #13                 // Field socket:Ljava/net/Socket;
      37: invokevirtual #16                 // Method java/net/Socket.getOutputStream:()Ljava/io/OutputStream;
      40: putfield      #17                 // Field out:Ljava/io/OutputStream;
      43: goto          92
      46: aload_0
      47: aload_1
      48: aload_0
      49: getfield      #8                  // Field proxy_host:Ljava/lang/String;
      52: aload_0
      53: getfield      #9                  // Field proxy_port:I
      56: invokeinterface #18,  3           // InterfaceMethod com/jcraft/jsch/SocketFactory.createSocket:(Ljava/lang/String;I)Ljava/net/Socket;
      61: putfield      #13                 // Field socket:Ljava/net/Socket;
      64: aload_0
      65: aload_1
      66: aload_0
      67: getfield      #13                 // Field socket:Ljava/net/Socket;
      70: invokeinterface #19,  2           // InterfaceMethod com/jcraft/jsch/SocketFactory.getInputStream:(Ljava/net/Socket;)Ljava/io/InputStream;
      75: putfield      #15                 // Field in:Ljava/io/InputStream;
      78: aload_0
      79: aload_1
      80: aload_0
      81: getfield      #13                 // Field socket:Ljava/net/Socket;
      84: invokeinterface #20,  2           // InterfaceMethod com/jcraft/jsch/SocketFactory.getOutputStream:(Ljava/net/Socket;)Ljava/io/OutputStream;
      89: putfield      #17                 // Field out:Ljava/io/OutputStream;
      92: iload         4
      94: ifle          106
      97: aload_0
      98: getfield      #13                 // Field socket:Ljava/net/Socket;
     101: iload         4
     103: invokevirtual #21                 // Method java/net/Socket.setSoTimeout:(I)V
     106: aload_0
     107: getfield      #13                 // Field socket:Ljava/net/Socket;
     110: iconst_1
     111: invokevirtual #22                 // Method java/net/Socket.setTcpNoDelay:(Z)V
     114: sipush        1024
     117: newarray       byte
     119: astore        5
     121: iconst_0
     122: istore        6
     124: iconst_0
     125: istore        6
     127: aload         5
     129: iload         6
     131: iinc          6, 1
     134: iconst_4
     135: bastore
     136: aload         5
     138: iload         6
     140: iinc          6, 1
     143: iconst_1
     144: bastore
     145: aload         5
     147: iload         6
     149: iinc          6, 1
     152: iload_3
     153: bipush        8
     155: iushr
     156: i2b
     157: bastore
     158: aload         5
     160: iload         6
     162: iinc          6, 1
     165: iload_3
     166: sipush        255
     169: iand
     170: i2b
     171: bastore
     172: aload_2
     173: invokestatic  #23                 // Method java/net/InetAddress.getByName:(Ljava/lang/String;)Ljava/net/InetAddress;
     176: astore        7
     178: aload         7
     180: invokevirtual #24                 // Method java/net/InetAddress.getAddress:()[B
     183: astore        8
     185: iconst_0
     186: istore        9
     188: iload         9
     190: aload         8
     192: arraylength
     193: if_icmpge     215
     196: aload         5
     198: iload         6
     200: iinc          6, 1
     203: aload         8
     205: iload         9
     207: baload
     208: bastore
     209: iinc          9, 1
     212: goto          188
     215: goto          253
     218: astore        7
     220: new           #26                 // class com/jcraft/jsch/JSchException
     223: dup
     224: new           #27                 // class java/lang/StringBuilder
     227: dup
     228: invokespecial #28                 // Method java/lang/StringBuilder."<init>":()V
     231: ldc           #29                 // String ProxySOCKS4:
     233: invokevirtual #30                 // Method java/lang/StringBuilder.append:(Ljava/lang/String;)Ljava/lang/StringBuilder;
     236: aload         7
     238: invokevirtual #31                 // Method java/net/UnknownHostException.toString:()Ljava/lang/String;
     241: invokevirtual #30                 // Method java/lang/StringBuilder.append:(Ljava/lang/String;)Ljava/lang/StringBuilder;
     244: invokevirtual #32                 // Method java/lang/StringBuilder.toString:()Ljava/lang/String;
     247: aload         7
     249: invokespecial #33                 // Method com/jcraft/jsch/JSchException."<init>":(Ljava/lang/String;Ljava/lang/Throwable;)V
     252: athrow
     253: aload_0
     254: getfield      #10                 // Field user:Ljava/lang/String;
     257: ifnull        294
     260: aload_0
     261: getfield      #10                 // Field user:Ljava/lang/String;
     264: invokestatic  #34                 // Method com/jcraft/jsch/Util.str2byte:(Ljava/lang/String;)[B
     267: iconst_0
     268: aload         5
     270: iload         6
     272: aload_0
     273: getfield      #10                 // Field user:Ljava/lang/String;
     276: invokevirtual #35                 // Method java/lang/String.length:()I
     279: invokestatic  #36                 // Method java/lang/System.arraycopy:(Ljava/lang/Object;ILjava/lang/Object;II)V
     282: iload         6
     284: aload_0
     285: getfield      #10                 // Field user:Ljava/lang/String;
     288: invokevirtual #35                 // Method java/lang/String.length:()I
     291: iadd
     292: istore        6
     294: aload         5
     296: iload         6
     298: iinc          6, 1
     301: iconst_0
     302: bastore
     303: aload_0
     304: getfield      #17                 // Field out:Ljava/io/OutputStream;
     307: aload         5
     309: iconst_0
     310: iload         6
     312: invokevirtual #37                 // Method java/io/OutputStream.write:([BII)V
     315: bipush        8
     317: istore        7
     319: iconst_0
     320: istore        8
     322: iload         8
     324: iload         7
     326: if_icmpge     372
     329: aload_0
     330: getfield      #15                 // Field in:Ljava/io/InputStream;
     333: aload         5
     335: iload         8
     337: iload         7
     339: iload         8
     341: isub
     342: invokevirtual #38                 // Method java/io/InputStream.read:([BII)I
     345: istore        9
     347: iload         9
     349: ifgt          362
     352: new           #26                 // class com/jcraft/jsch/JSchException
     355: dup
     356: ldc           #39                 // String ProxySOCKS4: stream is closed
     358: invokespecial #40                 // Method com/jcraft/jsch/JSchException."<init>":(Ljava/lang/String;)V
     361: athrow
     362: iload         8
     364: iload         9
     366: iadd
     367: istore        8
     369: goto          322
     372: aload         5
     374: iconst_0
     375: baload
     376: ifeq          409
     379: new           #26                 // class com/jcraft/jsch/JSchException
     382: dup
     383: new           #27                 // class java/lang/StringBuilder
     386: dup
     387: invokespecial #28                 // Method java/lang/StringBuilder."<init>":()V
     390: ldc           #41                 // String ProxySOCKS4: server returns VN
     392: invokevirtual #30                 // Method java/lang/StringBuilder.append:(Ljava/lang/String;)Ljava/lang/StringBuilder;
     395: aload         5
     397: iconst_0
     398: baload
     399: invokevirtual #42                 // Method java/lang/StringBuilder.append:(I)Ljava/lang/StringBuilder;
     402: invokevirtual #32                 // Method java/lang/StringBuilder.toString:()Ljava/lang/String;
     405: invokespecial #40                 // Method com/jcraft/jsch/JSchException."<init>":(Ljava/lang/String;)V
     408: athrow
     409: aload         5
     411: iconst_1
     412: baload
     413: bipush        90
     415: if_icmpeq     464
     418: aload_0
     419: getfield      #13                 // Field socket:Ljava/net/Socket;
     422: invokevirtual #43                 // Method java/net/Socket.close:()V
     425: goto          430
     428: astore        9
     430: new           #27                 // class java/lang/StringBuilder
     433: dup
     434: invokespecial #28                 // Method java/lang/StringBuilder."<init>":()V
     437: ldc           #44                 // String ProxySOCKS4: server returns CD
     439: invokevirtual #30                 // Method java/lang/StringBuilder.append:(Ljava/lang/String;)Ljava/lang/StringBuilder;
     442: aload         5
     444: iconst_1
     445: baload
     446: invokevirtual #42                 // Method java/lang/StringBuilder.append:(I)Ljava/lang/StringBuilder;
     449: invokevirtual #32                 // Method java/lang/StringBuilder.toString:()Ljava/lang/String;
     452: astore        9
     454: new           #26                 // class com/jcraft/jsch/JSchException
     457: dup
     458: aload         9
     460: invokespecial #40                 // Method com/jcraft/jsch/JSchException."<init>":(Ljava/lang/String;)V
     463: athrow
     464: goto          524
     467: astore        5
     469: aload         5
     471: athrow
     472: astore        5
     474: aload_0
     475: getfield      #13                 // Field socket:Ljava/net/Socket;
     478: ifnull        488
     481: aload_0
     482: getfield      #13                 // Field socket:Ljava/net/Socket;
     485: invokevirtual #43                 // Method java/net/Socket.close:()V
     488: goto          493
     491: astore        6
     493: new           #26                 // class com/jcraft/jsch/JSchException
     496: dup
     497: new           #27                 // class java/lang/StringBuilder
     500: dup
     501: invokespecial #28                 // Method java/lang/StringBuilder."<init>":()V
     504: ldc           #29                 // String ProxySOCKS4:
     506: invokevirtual #30                 // Method java/lang/StringBuilder.append:(Ljava/lang/String;)Ljava/lang/StringBuilder;
     509: aload         5
     511: invokevirtual #46                 // Method java/lang/Exception.toString:()Ljava/lang/String;
     514: invokevirtual #30                 // Method java/lang/StringBuilder.append:(Ljava/lang/String;)Ljava/lang/StringBuilder;
     517: invokevirtual #32                 // Method java/lang/StringBuilder.toString:()Ljava/lang/String;
     520: invokespecial #40                 // Method com/jcraft/jsch/JSchException."<init>":(Ljava/lang/String;)V
     523: athrow
     524: return
    Exception table:
       from    to  target type
         172   215   218   Class java/net/UnknownHostException
         418   425   428   Class java/lang/Exception
           0   464   467   Class java/lang/RuntimeException
           0   464   472   Class java/lang/Exception
         474   488   491   Class java/lang/Exception

  public java.io.InputStream getInputStream();
    Code:
       0: aload_0
       1: getfield      #15                 // Field in:Ljava/io/InputStream;
       4: areturn

  public java.io.OutputStream getOutputStream();
    Code:
       0: aload_0
       1: getfield      #17                 // Field out:Ljava/io/OutputStream;
       4: areturn

  public java.net.Socket getSocket();
    Code:
       0: aload_0
       1: getfield      #13                 // Field socket:Ljava/net/Socket;
       4: areturn

  public void close();
    Code:
       0: aload_0
       1: getfield      #15                 // Field in:Ljava/io/InputStream;
       4: ifnull        14
       7: aload_0
       8: getfield      #15                 // Field in:Ljava/io/InputStream;
      11: invokevirtual #47                 // Method java/io/InputStream.close:()V
      14: aload_0
      15: getfield      #17                 // Field out:Ljava/io/OutputStream;
      18: ifnull        28
      21: aload_0
      22: getfield      #17                 // Field out:Ljava/io/OutputStream;
      25: invokevirtual #48                 // Method java/io/OutputStream.close:()V
      28: aload_0
      29: getfield      #13                 // Field socket:Ljava/net/Socket;
      32: ifnull        42
      35: aload_0
      36: getfield      #13                 // Field socket:Ljava/net/Socket;
      39: invokevirtual #43                 // Method java/net/Socket.close:()V
      42: goto          46
      45: astore_1
      46: aload_0
      47: aconst_null
      48: putfield      #15                 // Field in:Ljava/io/InputStream;
      51: aload_0
      52: aconst_null
      53: putfield      #17                 // Field out:Ljava/io/OutputStream;
      56: aload_0
      57: aconst_null
      58: putfield      #13                 // Field socket:Ljava/net/Socket;
      61: return
    Exception table:
       from    to  target type
           0    42    45   Class java/lang/Exception

  public static int getDefaultPort();
    Code:
       0: getstatic     #2                  // Field DEFAULTPORT:I
       3: ireturn

  static {};
    Code:
       0: sipush        1080
       3: putstatic     #2                  // Field DEFAULTPORT:I
       6: return
}
