Compiled from "UpdateRoutingControlStateRequest.kt"
public final class aws.sdk.kotlin.services.route53recoverycluster.model.UpdateRoutingControlStateRequest$Builder {
  private java.lang.String routingControlArn;

  private aws.sdk.kotlin.services.route53recoverycluster.model.RoutingControlState routingControlState;

  private java.util.List<java.lang.String> safetyRulesToOverride;

  public final java.lang.String getRoutingControlArn();
    Code:
       0: aload_0
       1: getfield      #11                 // Field routingControlArn:Ljava/lang/String;
       4: areturn

  public final void setRoutingControlArn(java.lang.String);
    Code:
       0: aload_0
       1: aload_1
       2: putfield      #11                 // Field routingControlArn:Ljava/lang/String;
       5: return

  public final aws.sdk.kotlin.services.route53recoverycluster.model.RoutingControlState getRoutingControlState();
    Code:
       0: aload_0
       1: getfield      #22                 // Field routingControlState:Laws/sdk/kotlin/services/route53recoverycluster/model/RoutingControlState;
       4: areturn

  public final void setRoutingControlState(aws.sdk.kotlin.services.route53recoverycluster.model.RoutingControlState);
    Code:
       0: aload_0
       1: aload_1
       2: putfield      #22                 // Field routingControlState:Laws/sdk/kotlin/services/route53recoverycluster/model/RoutingControlState;
       5: return

  public final java.util.List<java.lang.String> getSafetyRulesToOverride();
    Code:
       0: aload_0
       1: getfield      #31                 // Field safetyRulesToOverride:Ljava/util/List;
       4: areturn

  public final void setSafetyRulesToOverride(java.util.List<java.lang.String>);
    Code:
       0: aload_0
       1: aload_1
       2: putfield      #31                 // Field safetyRulesToOverride:Ljava/util/List;
       5: return

  public aws.sdk.kotlin.services.route53recoverycluster.model.UpdateRoutingControlStateRequest$Builder();
    Code:
       0: aload_0
       1: invokespecial #39                 // Method java/lang/Object."<init>":()V
       4: return

  public aws.sdk.kotlin.services.route53recoverycluster.model.UpdateRoutingControlStateRequest$Builder(aws.sdk.kotlin.services.route53recoverycluster.model.UpdateRoutingControlStateRequest);
    Code:
       0: aload_1
       1: ldc           #43                 // String x
       3: invokestatic  #49                 // Method kotlin/jvm/internal/Intrinsics.checkNotNullParameter:(Ljava/lang/Object;Ljava/lang/String;)V
       6: aload_0
       7: invokespecial #50                 // Method "<init>":()V
      10: aload_0
      11: aload_1
      12: invokevirtual #54                 // Method aws/sdk/kotlin/services/route53recoverycluster/model/UpdateRoutingControlStateRequest.getRoutingControlArn:()Ljava/lang/String;
      15: putfield      #11                 // Field routingControlArn:Ljava/lang/String;
      18: aload_0
      19: aload_1
      20: invokevirtual #56                 // Method aws/sdk/kotlin/services/route53recoverycluster/model/UpdateRoutingControlStateRequest.getRoutingControlState:()Laws/sdk/kotlin/services/route53recoverycluster/model/RoutingControlState;
      23: putfield      #22                 // Field routingControlState:Laws/sdk/kotlin/services/route53recoverycluster/model/RoutingControlState;
      26: aload_0
      27: aload_1
      28: invokevirtual #58                 // Method aws/sdk/kotlin/services/route53recoverycluster/model/UpdateRoutingControlStateRequest.getSafetyRulesToOverride:()Ljava/util/List;
      31: putfield      #31                 // Field safetyRulesToOverride:Ljava/util/List;
      34: return

  public final aws.sdk.kotlin.services.route53recoverycluster.model.UpdateRoutingControlStateRequest build();
    Code:
       0: new           #52                 // class aws/sdk/kotlin/services/route53recoverycluster/model/UpdateRoutingControlStateRequest
       3: dup
       4: aload_0
       5: aconst_null
       6: invokespecial #64                 // Method aws/sdk/kotlin/services/route53recoverycluster/model/UpdateRoutingControlStateRequest."<init>":(Laws/sdk/kotlin/services/route53recoverycluster/model/UpdateRoutingControlStateRequest$Builder;Lkotlin/jvm/internal/DefaultConstructorMarker;)V
       9: areturn
}
