Compiled from "JvmRouteHandler.java"
public class io.undertow.server.JvmRouteHandler$Builder implements io.undertow.server.handlers.builder.HandlerBuilder {
  public io.undertow.server.JvmRouteHandler$Builder();
    Code:
       0: aload_0
       1: invokespecial #1                  // Method java/lang/Object."<init>":()V
       4: return

  public java.lang.String name();
    Code:
       0: ldc           #2                  // String jvm-route
       2: areturn

  public java.util.Map<java.lang.String, java.lang.Class<?>> parameters();
    Code:
       0: new           #3                  // class java/util/HashMap
       3: dup
       4: invokespecial #4                  // Method java/util/HashMap."<init>":()V
       7: astore_1
       8: aload_1
       9: ldc           #5                  // String value
      11: ldc           #6                  // class java/lang/String
      13: invokeinterface #7,  3            // InterfaceMethod java/util/Map.put:(Ljava/lang/Object;Ljava/lang/Object;)Ljava/lang/Object;
      18: pop
      19: aload_1
      20: ldc           #8                  // String session-cookie-name
      22: ldc           #6                  // class java/lang/String
      24: invokeinterface #7,  3            // InterfaceMethod java/util/Map.put:(Ljava/lang/Object;Ljava/lang/Object;)Ljava/lang/Object;
      29: pop
      30: aload_1
      31: areturn

  public java.util.Set<java.lang.String> requiredParameters();
    Code:
       0: ldc           #5                  // String value
       2: invokestatic  #9                  // Method java/util/Collections.singleton:(Ljava/lang/Object;)Ljava/util/Set;
       5: areturn

  public java.lang.String defaultParameter();
    Code:
       0: ldc           #5                  // String value
       2: areturn

  public io.undertow.server.HandlerWrapper build(java.util.Map<java.lang.String, java.lang.Object>);
    Code:
       0: aload_1
       1: ldc           #8                  // String session-cookie-name
       3: invokeinterface #10,  2           // InterfaceMethod java/util/Map.get:(Ljava/lang/Object;)Ljava/lang/Object;
       8: checkcast     #6                  // class java/lang/String
      11: astore_2
      12: new           #11                 // class io/undertow/server/JvmRouteHandler$Wrapper
      15: dup
      16: aload_1
      17: ldc           #5                  // String value
      19: invokeinterface #10,  2           // InterfaceMethod java/util/Map.get:(Ljava/lang/Object;)Ljava/lang/Object;
      24: checkcast     #6                  // class java/lang/String
      27: aload_2
      28: ifnonnull     36
      31: ldc           #12                 // String JSESSIONID
      33: goto          37
      36: aload_2
      37: aconst_null
      38: invokespecial #13                 // Method io/undertow/server/JvmRouteHandler$Wrapper."<init>":(Ljava/lang/String;Ljava/lang/String;Lio/undertow/server/JvmRouteHandler$1;)V
      41: areturn
}
