Compiled from "LinkTag.java"
public abstract class org.ow2.mind.doc.comments.LinkTag<E extends java.lang.Enum<E>> extends org.ow2.mind.doc.comments.CommentTag {
  protected static final java.lang.String THIS_IDENTIFIER;

  protected java.lang.String target;

  protected final E subElemType;

  protected final java.lang.String subElemName;

  public org.ow2.mind.doc.comments.LinkTag(java.lang.String, java.lang.String, java.lang.String, int, int) throws org.ow2.mind.doc.comments.CommentParserException;
    Code:
       0: aload_0
       1: iload         4
       3: iload         5
       5: invokespecial #1                  // Method org/ow2/mind/doc/comments/CommentTag."<init>":(II)V
       8: aload_2
       9: ifnull        24
      12: aload_0
      13: aload_0
      14: aload_2
      15: invokevirtual #2                  // Method parseSubElemType:(Ljava/lang/String;)Ljava/lang/Enum;
      18: putfield      #3                  // Field subElemType:Ljava/lang/Enum;
      21: goto          29
      24: aload_0
      25: aconst_null
      26: putfield      #3                  // Field subElemType:Ljava/lang/Enum;
      29: aload_0
      30: aload_1
      31: putfield      #4                  // Field target:Ljava/lang/String;
      34: aload_0
      35: aload_3
      36: putfield      #5                  // Field subElemName:Ljava/lang/String;
      39: return

  protected abstract E parseSubElemType(java.lang.String) throws org.ow2.mind.doc.comments.CommentParserException;

  public java.lang.String getTarget();
    Code:
       0: aload_0
       1: getfield      #4                  // Field target:Ljava/lang/String;
       4: areturn

  public E getSubElemType();
    Code:
       0: aload_0
       1: getfield      #3                  // Field subElemType:Ljava/lang/Enum;
       4: areturn

  public java.lang.String getSubElemName();
    Code:
       0: aload_0
       1: getfield      #5                  // Field subElemName:Ljava/lang/String;
       4: areturn

  protected abstract java.lang.String getTargetHref(java.lang.String, org.ow2.mind.doc.HTMLDocumentationHelper$SourceKind);

  protected abstract java.lang.String getSubElemHref(java.lang.String, org.ow2.mind.doc.HTMLDocumentationHelper$SourceKind);

  protected abstract java.lang.String getSubElemTypeHref(java.lang.String, org.ow2.mind.doc.HTMLDocumentationHelper$SourceKind);

  protected abstract java.lang.String getSubElemLabel();

  public java.lang.String getReplacement(java.lang.String, org.ow2.mind.doc.HTMLDocumentationHelper$SourceKind);
    Code:
       0: ldc           #6                  // String this
       2: aload_0
       3: getfield      #4                  // Field target:Ljava/lang/String;
       6: invokevirtual #7                  // Method java/lang/String.equals:(Ljava/lang/Object;)Z
       9: ifeq          34
      12: aload_2
      13: getstatic     #8                  // Field org/ow2/mind/doc/HTMLDocumentationHelper$SourceKind.PACKAGE:Lorg/ow2/mind/doc/HTMLDocumentationHelper$SourceKind;
      16: if_acmpne     29
      19: new           #9                  // class java/lang/IllegalArgumentException
      22: dup
      23: ldc           #10                 // String Cannot use \'this\' as a scope in package documentation
      25: invokespecial #11                 // Method java/lang/IllegalArgumentException."<init>":(Ljava/lang/String;)V
      28: athrow
      29: aload_0
      30: aload_1
      31: putfield      #4                  // Field target:Ljava/lang/String;
      34: aload_0
      35: getfield      #3                  // Field subElemType:Ljava/lang/Enum;
      38: ifnonnull     77
      41: ldc           #12                 // String <a href=\"%s\" title=\"%s\">%s</a>
      43: iconst_3
      44: anewarray     #13                 // class java/lang/Object
      47: dup
      48: iconst_0
      49: aload_0
      50: aload_1
      51: aload_2
      52: invokevirtual #14                 // Method getTargetHref:(Ljava/lang/String;Lorg/ow2/mind/doc/HTMLDocumentationHelper$SourceKind;)Ljava/lang/String;
      55: aastore
      56: dup
      57: iconst_1
      58: aload_0
      59: invokevirtual #15                 // Method getTarget:()Ljava/lang/String;
      62: aastore
      63: dup
      64: iconst_2
      65: aload_0
      66: invokevirtual #15                 // Method getTarget:()Ljava/lang/String;
      69: invokestatic  #16                 // Method org/ow2/mind/doc/HTMLDocumentationHelper.getShortName:(Ljava/lang/String;)Ljava/lang/String;
      72: aastore
      73: invokestatic  #17                 // Method java/lang/String.format:(Ljava/lang/String;[Ljava/lang/Object;)Ljava/lang/String;
      76: areturn
      77: aload_0
      78: getfield      #5                  // Field subElemName:Ljava/lang/String;
      81: ifnonnull     116
      84: ldc           #18                 // String <a href=\"%s\">%s</a>
      86: iconst_2
      87: anewarray     #13                 // class java/lang/Object
      90: dup
      91: iconst_0
      92: aload_0
      93: aload_1
      94: aload_2
      95: invokevirtual #19                 // Method getSubElemTypeHref:(Ljava/lang/String;Lorg/ow2/mind/doc/HTMLDocumentationHelper$SourceKind;)Ljava/lang/String;
      98: aastore
      99: dup
     100: iconst_1
     101: aload_0
     102: getfield      #3                  // Field subElemType:Ljava/lang/Enum;
     105: invokevirtual #20                 // Method java/lang/Enum.toString:()Ljava/lang/String;
     108: invokevirtual #21                 // Method java/lang/String.toLowerCase:()Ljava/lang/String;
     111: aastore
     112: invokestatic  #17                 // Method java/lang/String.format:(Ljava/lang/String;[Ljava/lang/Object;)Ljava/lang/String;
     115: areturn
     116: ldc           #22                 // String <a href=\"%s\" title=\"%s %s.%s\">%s.%s</a>
     118: bipush        6
     120: anewarray     #13                 // class java/lang/Object
     123: dup
     124: iconst_0
     125: aload_0
     126: aload_1
     127: aload_2
     128: invokevirtual #23                 // Method getSubElemHref:(Ljava/lang/String;Lorg/ow2/mind/doc/HTMLDocumentationHelper$SourceKind;)Ljava/lang/String;
     131: aastore
     132: dup
     133: iconst_1
     134: aload_0
     135: invokevirtual #24                 // Method getSubElemLabel:()Ljava/lang/String;
     138: aastore
     139: dup
     140: iconst_2
     141: aload_0
     142: invokevirtual #15                 // Method getTarget:()Ljava/lang/String;
     145: aastore
     146: dup
     147: iconst_3
     148: aload_0
     149: invokevirtual #25                 // Method getSubElemName:()Ljava/lang/String;
     152: aastore
     153: dup
     154: iconst_4
     155: aload_0
     156: invokevirtual #15                 // Method getTarget:()Ljava/lang/String;
     159: invokestatic  #16                 // Method org/ow2/mind/doc/HTMLDocumentationHelper.getShortName:(Ljava/lang/String;)Ljava/lang/String;
     162: aastore
     163: dup
     164: iconst_5
     165: aload_0
     166: invokevirtual #25                 // Method getSubElemName:()Ljava/lang/String;
     169: aastore
     170: invokestatic  #17                 // Method java/lang/String.format:(Ljava/lang/String;[Ljava/lang/Object;)Ljava/lang/String;
     173: areturn

  public java.lang.String toString();
    Code:
       0: ldc           #26                 // String link<scope=%s,type=%s,target=%s,begin=%d,end=%d>
       2: iconst_5
       3: anewarray     #13                 // class java/lang/Object
       6: dup
       7: iconst_0
       8: aload_0
       9: getfield      #4                  // Field target:Ljava/lang/String;
      12: aastore
      13: dup
      14: iconst_1
      15: aload_0
      16: getfield      #3                  // Field subElemType:Ljava/lang/Enum;
      19: ifnull        35
      22: aload_0
      23: getfield      #3                  // Field subElemType:Ljava/lang/Enum;
      26: invokevirtual #20                 // Method java/lang/Enum.toString:()Ljava/lang/String;
      29: invokevirtual #21                 // Method java/lang/String.toLowerCase:()Ljava/lang/String;
      32: goto          37
      35: ldc           #27                 // String null
      37: aastore
      38: dup
      39: iconst_2
      40: aload_0
      41: getfield      #5                  // Field subElemName:Ljava/lang/String;
      44: aastore
      45: dup
      46: iconst_3
      47: aload_0
      48: getfield      #28                 // Field beginIndex:I
      51: invokestatic  #29                 // Method java/lang/Integer.valueOf:(I)Ljava/lang/Integer;
      54: aastore
      55: dup
      56: iconst_4
      57: aload_0
      58: getfield      #30                 // Field endIndex:I
      61: invokestatic  #29                 // Method java/lang/Integer.valueOf:(I)Ljava/lang/Integer;
      64: aastore
      65: invokestatic  #17                 // Method java/lang/String.format:(Ljava/lang/String;[Ljava/lang/Object;)Ljava/lang/String;
      68: areturn
}
