Compiled from "GoppaCode.java"
public class org.bouncycastle.pqc.math.linearalgebra.GoppaCode$MaMaPe {
  private org.bouncycastle.pqc.math.linearalgebra.GF2Matrix s;

  private org.bouncycastle.pqc.math.linearalgebra.GF2Matrix h;

  private org.bouncycastle.pqc.math.linearalgebra.Permutation p;

  public org.bouncycastle.pqc.math.linearalgebra.GoppaCode$MaMaPe(org.bouncycastle.pqc.math.linearalgebra.GF2Matrix, org.bouncycastle.pqc.math.linearalgebra.GF2Matrix, org.bouncycastle.pqc.math.linearalgebra.Permutation);
    Code:
       0: aload_0
       1: invokespecial #1                  // Method java/lang/Object."<init>":()V
       4: aload_0
       5: aload_1
       6: putfield      #2                  // Field s:Lorg/bouncycastle/pqc/math/linearalgebra/GF2Matrix;
       9: aload_0
      10: aload_2
      11: putfield      #3                  // Field h:Lorg/bouncycastle/pqc/math/linearalgebra/GF2Matrix;
      14: aload_0
      15: aload_3
      16: putfield      #4                  // Field p:Lorg/bouncycastle/pqc/math/linearalgebra/Permutation;
      19: return

  public org.bouncycastle.pqc.math.linearalgebra.GF2Matrix getFirstMatrix();
    Code:
       0: aload_0
       1: getfield      #2                  // Field s:Lorg/bouncycastle/pqc/math/linearalgebra/GF2Matrix;
       4: areturn

  public org.bouncycastle.pqc.math.linearalgebra.GF2Matrix getSecondMatrix();
    Code:
       0: aload_0
       1: getfield      #3                  // Field h:Lorg/bouncycastle/pqc/math/linearalgebra/GF2Matrix;
       4: areturn

  public org.bouncycastle.pqc.math.linearalgebra.Permutation getPermutation();
    Code:
       0: aload_0
       1: getfield      #4                  // Field p:Lorg/bouncycastle/pqc/math/linearalgebra/Permutation;
       4: areturn
}
