Compiled from "NamedKeyInfoGeneratorManager.java"
public class org.opensaml.xml.security.keyinfo.NamedKeyInfoGeneratorManager {
  private java.util.Map<java.lang.String, org.opensaml.xml.security.keyinfo.KeyInfoGeneratorManager> managers;

  private org.opensaml.xml.security.keyinfo.KeyInfoGeneratorManager defaultManager;

  private boolean useDefaultManager;

  public org.opensaml.xml.security.keyinfo.NamedKeyInfoGeneratorManager();
    Code:
       0: aload_0
       1: invokespecial #1                  // Method java/lang/Object."<init>":()V
       4: aload_0
       5: new           #2                  // class org/opensaml/xml/util/LazyMap
       8: dup
       9: invokespecial #3                  // Method org/opensaml/xml/util/LazyMap."<init>":()V
      12: putfield      #4                  // Field managers:Ljava/util/Map;
      15: aload_0
      16: new           #5                  // class org/opensaml/xml/security/keyinfo/KeyInfoGeneratorManager
      19: dup
      20: invokespecial #6                  // Method org/opensaml/xml/security/keyinfo/KeyInfoGeneratorManager."<init>":()V
      23: putfield      #7                  // Field defaultManager:Lorg/opensaml/xml/security/keyinfo/KeyInfoGeneratorManager;
      26: aload_0
      27: iconst_1
      28: putfield      #8                  // Field useDefaultManager:Z
      31: return

  public void setUseDefaultManager(boolean);
    Code:
       0: aload_0
       1: iload_1
       2: putfield      #8                  // Field useDefaultManager:Z
       5: return

  public java.util.Set<java.lang.String> getManagerNames();
    Code:
       0: aload_0
       1: getfield      #4                  // Field managers:Ljava/util/Map;
       4: invokeinterface #9,  1            // InterfaceMethod java/util/Map.keySet:()Ljava/util/Set;
       9: invokestatic  #10                 // Method java/util/Collections.unmodifiableSet:(Ljava/util/Set;)Ljava/util/Set;
      12: areturn

  public org.opensaml.xml.security.keyinfo.KeyInfoGeneratorManager getManager(java.lang.String);
    Code:
       0: aload_0
       1: getfield      #4                  // Field managers:Ljava/util/Map;
       4: aload_1
       5: invokeinterface #11,  2           // InterfaceMethod java/util/Map.get:(Ljava/lang/Object;)Ljava/lang/Object;
      10: checkcast     #5                  // class org/opensaml/xml/security/keyinfo/KeyInfoGeneratorManager
      13: astore_2
      14: aload_2
      15: ifnonnull     38
      18: new           #5                  // class org/opensaml/xml/security/keyinfo/KeyInfoGeneratorManager
      21: dup
      22: invokespecial #6                  // Method org/opensaml/xml/security/keyinfo/KeyInfoGeneratorManager."<init>":()V
      25: astore_2
      26: aload_0
      27: getfield      #4                  // Field managers:Ljava/util/Map;
      30: aload_1
      31: aload_2
      32: invokeinterface #12,  3           // InterfaceMethod java/util/Map.put:(Ljava/lang/Object;Ljava/lang/Object;)Ljava/lang/Object;
      37: pop
      38: aload_2
      39: areturn

  public void removeManager(java.lang.String);
    Code:
       0: aload_0
       1: getfield      #4                  // Field managers:Ljava/util/Map;
       4: aload_1
       5: invokeinterface #13,  2           // InterfaceMethod java/util/Map.remove:(Ljava/lang/Object;)Ljava/lang/Object;
      10: pop
      11: return

  public void registerFactory(java.lang.String, org.opensaml.xml.security.keyinfo.KeyInfoGeneratorFactory);
    Code:
       0: aload_0
       1: aload_1
       2: invokevirtual #14                 // Method getManager:(Ljava/lang/String;)Lorg/opensaml/xml/security/keyinfo/KeyInfoGeneratorManager;
       5: astore_3
       6: aload_3
       7: aload_2
       8: invokevirtual #15                 // Method org/opensaml/xml/security/keyinfo/KeyInfoGeneratorManager.registerFactory:(Lorg/opensaml/xml/security/keyinfo/KeyInfoGeneratorFactory;)V
      11: return

  public void deregisterFactory(java.lang.String, org.opensaml.xml.security.keyinfo.KeyInfoGeneratorFactory);
    Code:
       0: aload_0
       1: getfield      #4                  // Field managers:Ljava/util/Map;
       4: aload_1
       5: invokeinterface #11,  2           // InterfaceMethod java/util/Map.get:(Ljava/lang/Object;)Ljava/lang/Object;
      10: checkcast     #5                  // class org/opensaml/xml/security/keyinfo/KeyInfoGeneratorManager
      13: astore_3
      14: aload_3
      15: ifnonnull     50
      18: new           #16                 // class java/lang/IllegalArgumentException
      21: dup
      22: new           #17                 // class java/lang/StringBuilder
      25: dup
      26: invokespecial #18                 // Method java/lang/StringBuilder."<init>":()V
      29: ldc           #19                 // String Manager with name \'
      31: invokevirtual #20                 // Method java/lang/StringBuilder.append:(Ljava/lang/String;)Ljava/lang/StringBuilder;
      34: aload_1
      35: invokevirtual #20                 // Method java/lang/StringBuilder.append:(Ljava/lang/String;)Ljava/lang/StringBuilder;
      38: ldc           #21                 // String \' does not exist
      40: invokevirtual #20                 // Method java/lang/StringBuilder.append:(Ljava/lang/String;)Ljava/lang/StringBuilder;
      43: invokevirtual #22                 // Method java/lang/StringBuilder.toString:()Ljava/lang/String;
      46: invokespecial #23                 // Method java/lang/IllegalArgumentException."<init>":(Ljava/lang/String;)V
      49: athrow
      50: aload_3
      51: aload_2
      52: invokevirtual #24                 // Method org/opensaml/xml/security/keyinfo/KeyInfoGeneratorManager.deregisterFactory:(Lorg/opensaml/xml/security/keyinfo/KeyInfoGeneratorFactory;)V
      55: return

  public void registerDefaultFactory(org.opensaml.xml.security.keyinfo.KeyInfoGeneratorFactory);
    Code:
       0: aload_0
       1: getfield      #7                  // Field defaultManager:Lorg/opensaml/xml/security/keyinfo/KeyInfoGeneratorManager;
       4: aload_1
       5: invokevirtual #15                 // Method org/opensaml/xml/security/keyinfo/KeyInfoGeneratorManager.registerFactory:(Lorg/opensaml/xml/security/keyinfo/KeyInfoGeneratorFactory;)V
       8: return

  public void deregisterDefaultFactory(org.opensaml.xml.security.keyinfo.KeyInfoGeneratorFactory);
    Code:
       0: aload_0
       1: getfield      #7                  // Field defaultManager:Lorg/opensaml/xml/security/keyinfo/KeyInfoGeneratorManager;
       4: aload_1
       5: invokevirtual #24                 // Method org/opensaml/xml/security/keyinfo/KeyInfoGeneratorManager.deregisterFactory:(Lorg/opensaml/xml/security/keyinfo/KeyInfoGeneratorFactory;)V
       8: return

  public org.opensaml.xml.security.keyinfo.KeyInfoGeneratorManager getDefaultManager();
    Code:
       0: aload_0
       1: getfield      #7                  // Field defaultManager:Lorg/opensaml/xml/security/keyinfo/KeyInfoGeneratorManager;
       4: areturn

  public org.opensaml.xml.security.keyinfo.KeyInfoGeneratorFactory getFactory(java.lang.String, org.opensaml.xml.security.credential.Credential);
    Code:
       0: aload_0
       1: getfield      #4                  // Field managers:Ljava/util/Map;
       4: aload_1
       5: invokeinterface #11,  2           // InterfaceMethod java/util/Map.get:(Ljava/lang/Object;)Ljava/lang/Object;
      10: checkcast     #5                  // class org/opensaml/xml/security/keyinfo/KeyInfoGeneratorManager
      13: astore_3
      14: aload_3
      15: ifnonnull     50
      18: new           #16                 // class java/lang/IllegalArgumentException
      21: dup
      22: new           #17                 // class java/lang/StringBuilder
      25: dup
      26: invokespecial #18                 // Method java/lang/StringBuilder."<init>":()V
      29: ldc           #19                 // String Manager with name \'
      31: invokevirtual #20                 // Method java/lang/StringBuilder.append:(Ljava/lang/String;)Ljava/lang/StringBuilder;
      34: aload_1
      35: invokevirtual #20                 // Method java/lang/StringBuilder.append:(Ljava/lang/String;)Ljava/lang/StringBuilder;
      38: ldc           #21                 // String \' does not exist
      40: invokevirtual #20                 // Method java/lang/StringBuilder.append:(Ljava/lang/String;)Ljava/lang/StringBuilder;
      43: invokevirtual #22                 // Method java/lang/StringBuilder.toString:()Ljava/lang/String;
      46: invokespecial #23                 // Method java/lang/IllegalArgumentException."<init>":(Ljava/lang/String;)V
      49: athrow
      50: aload_3
      51: aload_2
      52: invokevirtual #25                 // Method org/opensaml/xml/security/keyinfo/KeyInfoGeneratorManager.getFactory:(Lorg/opensaml/xml/security/credential/Credential;)Lorg/opensaml/xml/security/keyinfo/KeyInfoGeneratorFactory;
      55: astore        4
      57: aload         4
      59: ifnonnull     79
      62: aload_0
      63: getfield      #8                  // Field useDefaultManager:Z
      66: ifeq          79
      69: aload_0
      70: getfield      #7                  // Field defaultManager:Lorg/opensaml/xml/security/keyinfo/KeyInfoGeneratorManager;
      73: aload_2
      74: invokevirtual #25                 // Method org/opensaml/xml/security/keyinfo/KeyInfoGeneratorManager.getFactory:(Lorg/opensaml/xml/security/credential/Credential;)Lorg/opensaml/xml/security/keyinfo/KeyInfoGeneratorFactory;
      77: astore        4
      79: aload         4
      81: areturn
}
