Compiled from "ScriptFactoryPostProcessor.java"
public class org.springframework.scripting.support.ScriptFactoryPostProcessor extends org.springframework.beans.factory.config.InstantiationAwareBeanPostProcessorAdapter implements org.springframework.beans.factory.BeanClassLoaderAware,org.springframework.beans.factory.BeanFactoryAware,org.springframework.context.ResourceLoaderAware,org.springframework.beans.factory.DisposableBean,org.springframework.core.Ordered {
  public static final java.lang.String INLINE_SCRIPT_PREFIX;

  public static final java.lang.String REFRESH_CHECK_DELAY_ATTRIBUTE;

  public static final java.lang.String PROXY_TARGET_CLASS_ATTRIBUTE;

  public static final java.lang.String LANGUAGE_ATTRIBUTE;

  private static final java.lang.String SCRIPT_FACTORY_NAME_PREFIX;

  private static final java.lang.String SCRIPTED_OBJECT_NAME_PREFIX;

  protected final org.apache.commons.logging.Log logger;

  private long defaultRefreshCheckDelay;

  private boolean defaultProxyTargetClass;

  private java.lang.ClassLoader beanClassLoader;

  private org.springframework.beans.factory.config.ConfigurableBeanFactory beanFactory;

  private org.springframework.core.io.ResourceLoader resourceLoader;

  final org.springframework.beans.factory.support.DefaultListableBeanFactory scriptBeanFactory;

  private final java.util.Map<java.lang.String, org.springframework.scripting.ScriptSource> scriptSourceCache;

  public org.springframework.scripting.support.ScriptFactoryPostProcessor();
    Code:
       0: aload_0
       1: invokespecial #1                  // Method org/springframework/beans/factory/config/InstantiationAwareBeanPostProcessorAdapter."<init>":()V
       4: aload_0
       5: aload_0
       6: invokevirtual #2                  // Method java/lang/Object.getClass:()Ljava/lang/Class;
       9: invokestatic  #3                  // Method org/apache/commons/logging/LogFactory.getLog:(Ljava/lang/Class;)Lorg/apache/commons/logging/Log;
      12: putfield      #4                  // Field logger:Lorg/apache/commons/logging/Log;
      15: aload_0
      16: ldc2_w        #5                  // long -1l
      19: putfield      #7                  // Field defaultRefreshCheckDelay:J
      22: aload_0
      23: iconst_0
      24: putfield      #8                  // Field defaultProxyTargetClass:Z
      27: aload_0
      28: invokestatic  #9                  // Method org/springframework/util/ClassUtils.getDefaultClassLoader:()Ljava/lang/ClassLoader;
      31: putfield      #10                 // Field beanClassLoader:Ljava/lang/ClassLoader;
      34: aload_0
      35: new           #11                 // class org/springframework/core/io/DefaultResourceLoader
      38: dup
      39: invokespecial #12                 // Method org/springframework/core/io/DefaultResourceLoader."<init>":()V
      42: putfield      #13                 // Field resourceLoader:Lorg/springframework/core/io/ResourceLoader;
      45: aload_0
      46: new           #14                 // class org/springframework/beans/factory/support/DefaultListableBeanFactory
      49: dup
      50: invokespecial #15                 // Method org/springframework/beans/factory/support/DefaultListableBeanFactory."<init>":()V
      53: putfield      #16                 // Field scriptBeanFactory:Lorg/springframework/beans/factory/support/DefaultListableBeanFactory;
      56: aload_0
      57: new           #17                 // class java/util/HashMap
      60: dup
      61: invokespecial #18                 // Method java/util/HashMap."<init>":()V
      64: putfield      #19                 // Field scriptSourceCache:Ljava/util/Map;
      67: return

  public void setDefaultRefreshCheckDelay(long);
    Code:
       0: aload_0
       1: lload_1
       2: putfield      #7                  // Field defaultRefreshCheckDelay:J
       5: return

  public void setDefaultProxyTargetClass(boolean);
    Code:
       0: aload_0
       1: iload_1
       2: putfield      #8                  // Field defaultProxyTargetClass:Z
       5: return

  public void setBeanClassLoader(java.lang.ClassLoader);
    Code:
       0: aload_0
       1: aload_1
       2: putfield      #10                 // Field beanClassLoader:Ljava/lang/ClassLoader;
       5: return

  public void setBeanFactory(org.springframework.beans.factory.BeanFactory);
    Code:
       0: aload_1
       1: instanceof    #20                 // class org/springframework/beans/factory/config/ConfigurableBeanFactory
       4: ifne          37
       7: new           #21                 // class java/lang/IllegalStateException
      10: dup
      11: new           #22                 // class java/lang/StringBuilder
      14: dup
      15: invokespecial #23                 // Method java/lang/StringBuilder."<init>":()V
      18: ldc           #24                 // String ScriptFactoryPostProcessor doesn\'t work with non-ConfigurableBeanFactory:
      20: invokevirtual #25                 // Method java/lang/StringBuilder.append:(Ljava/lang/String;)Ljava/lang/StringBuilder;
      23: aload_1
      24: invokevirtual #2                  // Method java/lang/Object.getClass:()Ljava/lang/Class;
      27: invokevirtual #26                 // Method java/lang/StringBuilder.append:(Ljava/lang/Object;)Ljava/lang/StringBuilder;
      30: invokevirtual #27                 // Method java/lang/StringBuilder.toString:()Ljava/lang/String;
      33: invokespecial #28                 // Method java/lang/IllegalStateException."<init>":(Ljava/lang/String;)V
      36: athrow
      37: aload_0
      38: aload_1
      39: checkcast     #20                 // class org/springframework/beans/factory/config/ConfigurableBeanFactory
      42: putfield      #29                 // Field beanFactory:Lorg/springframework/beans/factory/config/ConfigurableBeanFactory;
      45: aload_0
      46: getfield      #16                 // Field scriptBeanFactory:Lorg/springframework/beans/factory/support/DefaultListableBeanFactory;
      49: aload_0
      50: getfield      #29                 // Field beanFactory:Lorg/springframework/beans/factory/config/ConfigurableBeanFactory;
      53: invokevirtual #30                 // Method org/springframework/beans/factory/support/DefaultListableBeanFactory.setParentBeanFactory:(Lorg/springframework/beans/factory/BeanFactory;)V
      56: aload_0
      57: getfield      #16                 // Field scriptBeanFactory:Lorg/springframework/beans/factory/support/DefaultListableBeanFactory;
      60: aload_0
      61: getfield      #29                 // Field beanFactory:Lorg/springframework/beans/factory/config/ConfigurableBeanFactory;
      64: invokevirtual #31                 // Method org/springframework/beans/factory/support/DefaultListableBeanFactory.copyConfigurationFrom:(Lorg/springframework/beans/factory/config/ConfigurableBeanFactory;)V
      67: aload_0
      68: getfield      #16                 // Field scriptBeanFactory:Lorg/springframework/beans/factory/support/DefaultListableBeanFactory;
      71: invokevirtual #32                 // Method org/springframework/beans/factory/support/DefaultListableBeanFactory.getBeanPostProcessors:()Ljava/util/List;
      74: invokedynamic #33,  0             // InvokeDynamic #0:test:()Ljava/util/function/Predicate;
      79: invokeinterface #34,  2           // InterfaceMethod java/util/List.removeIf:(Ljava/util/function/Predicate;)Z
      84: pop
      85: return

  public void setResourceLoader(org.springframework.core.io.ResourceLoader);
    Code:
       0: aload_0
       1: aload_1
       2: putfield      #13                 // Field resourceLoader:Lorg/springframework/core/io/ResourceLoader;
       5: return

  public int getOrder();
    Code:
       0: ldc           #36                 // int -2147483648
       2: ireturn

  public java.lang.Class<?> predictBeanType(java.lang.Class<?>, java.lang.String);
    Code:
       0: ldc           #37                 // class org/springframework/scripting/ScriptFactory
       2: aload_1
       3: invokevirtual #38                 // Method java/lang/Class.isAssignableFrom:(Ljava/lang/Class;)Z
       6: ifne          11
       9: aconst_null
      10: areturn
      11: aload_0
      12: getfield      #29                 // Field beanFactory:Lorg/springframework/beans/factory/config/ConfigurableBeanFactory;
      15: ifnull        22
      18: iconst_1
      19: goto          23
      22: iconst_0
      23: ldc           #39                 // String No BeanFactory set
      25: invokestatic  #40                 // Method org/springframework/util/Assert.state:(ZLjava/lang/String;)V
      28: aload_0
      29: getfield      #29                 // Field beanFactory:Lorg/springframework/beans/factory/config/ConfigurableBeanFactory;
      32: aload_2
      33: invokeinterface #41,  2           // InterfaceMethod org/springframework/beans/factory/config/ConfigurableBeanFactory.getMergedBeanDefinition:(Ljava/lang/String;)Lorg/springframework/beans/factory/config/BeanDefinition;
      38: astore_3
      39: new           #22                 // class java/lang/StringBuilder
      42: dup
      43: invokespecial #23                 // Method java/lang/StringBuilder."<init>":()V
      46: ldc           #43                 // String scriptFactory.
      48: invokevirtual #25                 // Method java/lang/StringBuilder.append:(Ljava/lang/String;)Ljava/lang/StringBuilder;
      51: aload_2
      52: invokevirtual #25                 // Method java/lang/StringBuilder.append:(Ljava/lang/String;)Ljava/lang/StringBuilder;
      55: invokevirtual #27                 // Method java/lang/StringBuilder.toString:()Ljava/lang/String;
      58: astore        4
      60: new           #22                 // class java/lang/StringBuilder
      63: dup
      64: invokespecial #23                 // Method java/lang/StringBuilder."<init>":()V
      67: ldc           #44                 // String scriptedObject.
      69: invokevirtual #25                 // Method java/lang/StringBuilder.append:(Ljava/lang/String;)Ljava/lang/StringBuilder;
      72: aload_2
      73: invokevirtual #25                 // Method java/lang/StringBuilder.append:(Ljava/lang/String;)Ljava/lang/StringBuilder;
      76: invokevirtual #27                 // Method java/lang/StringBuilder.toString:()Ljava/lang/String;
      79: astore        5
      81: aload_0
      82: aload_3
      83: aload         4
      85: aload         5
      87: invokevirtual #45                 // Method prepareScriptBeans:(Lorg/springframework/beans/factory/config/BeanDefinition;Ljava/lang/String;Ljava/lang/String;)V
      90: aload_0
      91: getfield      #16                 // Field scriptBeanFactory:Lorg/springframework/beans/factory/support/DefaultListableBeanFactory;
      94: aload         4
      96: ldc           #37                 // class org/springframework/scripting/ScriptFactory
      98: invokevirtual #46                 // Method org/springframework/beans/factory/support/DefaultListableBeanFactory.getBean:(Ljava/lang/String;Ljava/lang/Class;)Ljava/lang/Object;
     101: checkcast     #37                 // class org/springframework/scripting/ScriptFactory
     104: astore        6
     106: aload_0
     107: aload         4
     109: aload         6
     111: invokeinterface #47,  1           // InterfaceMethod org/springframework/scripting/ScriptFactory.getScriptSourceLocator:()Ljava/lang/String;
     116: invokevirtual #48                 // Method getScriptSource:(Ljava/lang/String;Ljava/lang/String;)Lorg/springframework/scripting/ScriptSource;
     119: astore        7
     121: aload         6
     123: invokeinterface #49,  1           // InterfaceMethod org/springframework/scripting/ScriptFactory.getScriptInterfaces:()[Ljava/lang/Class;
     128: astore        8
     130: aload         6
     132: aload         7
     134: invokeinterface #50,  2           // InterfaceMethod org/springframework/scripting/ScriptFactory.getScriptedObjectType:(Lorg/springframework/scripting/ScriptSource;)Ljava/lang/Class;
     139: astore        9
     141: aload         9
     143: ifnull        149
     146: aload         9
     148: areturn
     149: aload         8
     151: invokestatic  #51                 // Method org/springframework/util/ObjectUtils.isEmpty:([Ljava/lang/Object;)Z
     154: ifne          178
     157: aload         8
     159: arraylength
     160: iconst_1
     161: if_icmpne     171
     164: aload         8
     166: iconst_0
     167: aaload
     168: goto          177
     171: aload_0
     172: aload         8
     174: invokevirtual #52                 // Method createCompositeInterface:([Ljava/lang/Class;)Ljava/lang/Class;
     177: areturn
     178: aload_3
     179: invokeinterface #53,  1           // InterfaceMethod org/springframework/beans/factory/config/BeanDefinition.isSingleton:()Z
     184: ifeq          200
     187: aload_0
     188: getfield      #16                 // Field scriptBeanFactory:Lorg/springframework/beans/factory/support/DefaultListableBeanFactory;
     191: aload         5
     193: invokevirtual #54                 // Method org/springframework/beans/factory/support/DefaultListableBeanFactory.getBean:(Ljava/lang/String;)Ljava/lang/Object;
     196: invokevirtual #2                  // Method java/lang/Object.getClass:()Ljava/lang/Class;
     199: areturn
     200: goto          330
     203: astore        4
     205: aload         4
     207: instanceof    #56                 // class org/springframework/beans/factory/BeanCreationException
     210: ifeq          283
     213: aload         4
     215: checkcast     #56                 // class org/springframework/beans/factory/BeanCreationException
     218: invokevirtual #57                 // Method org/springframework/beans/factory/BeanCreationException.getMostSpecificCause:()Ljava/lang/Throwable;
     221: instanceof    #58                 // class org/springframework/beans/factory/BeanCurrentlyInCreationException
     224: ifeq          283
     227: aload_0
     228: getfield      #4                  // Field logger:Lorg/apache/commons/logging/Log;
     231: invokeinterface #59,  1           // InterfaceMethod org/apache/commons/logging/Log.isTraceEnabled:()Z
     236: ifeq          330
     239: aload_0
     240: getfield      #4                  // Field logger:Lorg/apache/commons/logging/Log;
     243: new           #22                 // class java/lang/StringBuilder
     246: dup
     247: invokespecial #23                 // Method java/lang/StringBuilder."<init>":()V
     250: ldc           #60                 // String Could not determine scripted object type for bean \'
     252: invokevirtual #25                 // Method java/lang/StringBuilder.append:(Ljava/lang/String;)Ljava/lang/StringBuilder;
     255: aload_2
     256: invokevirtual #25                 // Method java/lang/StringBuilder.append:(Ljava/lang/String;)Ljava/lang/StringBuilder;
     259: ldc           #61                 // String \':
     261: invokevirtual #25                 // Method java/lang/StringBuilder.append:(Ljava/lang/String;)Ljava/lang/StringBuilder;
     264: aload         4
     266: invokevirtual #62                 // Method java/lang/Exception.getMessage:()Ljava/lang/String;
     269: invokevirtual #25                 // Method java/lang/StringBuilder.append:(Ljava/lang/String;)Ljava/lang/StringBuilder;
     272: invokevirtual #27                 // Method java/lang/StringBuilder.toString:()Ljava/lang/String;
     275: invokeinterface #63,  2           // InterfaceMethod org/apache/commons/logging/Log.trace:(Ljava/lang/Object;)V
     280: goto          330
     283: aload_0
     284: getfield      #4                  // Field logger:Lorg/apache/commons/logging/Log;
     287: invokeinterface #64,  1           // InterfaceMethod org/apache/commons/logging/Log.isDebugEnabled:()Z
     292: ifeq          330
     295: aload_0
     296: getfield      #4                  // Field logger:Lorg/apache/commons/logging/Log;
     299: new           #22                 // class java/lang/StringBuilder
     302: dup
     303: invokespecial #23                 // Method java/lang/StringBuilder."<init>":()V
     306: ldc           #60                 // String Could not determine scripted object type for bean \'
     308: invokevirtual #25                 // Method java/lang/StringBuilder.append:(Ljava/lang/String;)Ljava/lang/StringBuilder;
     311: aload_2
     312: invokevirtual #25                 // Method java/lang/StringBuilder.append:(Ljava/lang/String;)Ljava/lang/StringBuilder;
     315: ldc           #65                 // String \'
     317: invokevirtual #25                 // Method java/lang/StringBuilder.append:(Ljava/lang/String;)Ljava/lang/StringBuilder;
     320: invokevirtual #27                 // Method java/lang/StringBuilder.toString:()Ljava/lang/String;
     323: aload         4
     325: invokeinterface #66,  3           // InterfaceMethod org/apache/commons/logging/Log.debug:(Ljava/lang/Object;Ljava/lang/Throwable;)V
     330: aconst_null
     331: areturn
    Exception table:
       from    to  target type
          39   148   203   Class java/lang/Exception
         149   177   203   Class java/lang/Exception
         178   199   203   Class java/lang/Exception

  public java.lang.Object postProcessBeforeInstantiation(java.lang.Class<?>, java.lang.String);
    Code:
       0: ldc           #37                 // class org/springframework/scripting/ScriptFactory
       2: aload_1
       3: invokevirtual #38                 // Method java/lang/Class.isAssignableFrom:(Ljava/lang/Class;)Z
       6: ifne          11
       9: aconst_null
      10: areturn
      11: aload_0
      12: getfield      #29                 // Field beanFactory:Lorg/springframework/beans/factory/config/ConfigurableBeanFactory;
      15: ifnull        22
      18: iconst_1
      19: goto          23
      22: iconst_0
      23: ldc           #39                 // String No BeanFactory set
      25: invokestatic  #40                 // Method org/springframework/util/Assert.state:(ZLjava/lang/String;)V
      28: aload_0
      29: getfield      #29                 // Field beanFactory:Lorg/springframework/beans/factory/config/ConfigurableBeanFactory;
      32: aload_2
      33: invokeinterface #41,  2           // InterfaceMethod org/springframework/beans/factory/config/ConfigurableBeanFactory.getMergedBeanDefinition:(Ljava/lang/String;)Lorg/springframework/beans/factory/config/BeanDefinition;
      38: astore_3
      39: new           #22                 // class java/lang/StringBuilder
      42: dup
      43: invokespecial #23                 // Method java/lang/StringBuilder."<init>":()V
      46: ldc           #43                 // String scriptFactory.
      48: invokevirtual #25                 // Method java/lang/StringBuilder.append:(Ljava/lang/String;)Ljava/lang/StringBuilder;
      51: aload_2
      52: invokevirtual #25                 // Method java/lang/StringBuilder.append:(Ljava/lang/String;)Ljava/lang/StringBuilder;
      55: invokevirtual #27                 // Method java/lang/StringBuilder.toString:()Ljava/lang/String;
      58: astore        4
      60: new           #22                 // class java/lang/StringBuilder
      63: dup
      64: invokespecial #23                 // Method java/lang/StringBuilder."<init>":()V
      67: ldc           #44                 // String scriptedObject.
      69: invokevirtual #25                 // Method java/lang/StringBuilder.append:(Ljava/lang/String;)Ljava/lang/StringBuilder;
      72: aload_2
      73: invokevirtual #25                 // Method java/lang/StringBuilder.append:(Ljava/lang/String;)Ljava/lang/StringBuilder;
      76: invokevirtual #27                 // Method java/lang/StringBuilder.toString:()Ljava/lang/String;
      79: astore        5
      81: aload_0
      82: aload_3
      83: aload         4
      85: aload         5
      87: invokevirtual #45                 // Method prepareScriptBeans:(Lorg/springframework/beans/factory/config/BeanDefinition;Ljava/lang/String;Ljava/lang/String;)V
      90: aload_0
      91: getfield      #16                 // Field scriptBeanFactory:Lorg/springframework/beans/factory/support/DefaultListableBeanFactory;
      94: aload         4
      96: ldc           #37                 // class org/springframework/scripting/ScriptFactory
      98: invokevirtual #46                 // Method org/springframework/beans/factory/support/DefaultListableBeanFactory.getBean:(Ljava/lang/String;Ljava/lang/Class;)Ljava/lang/Object;
     101: checkcast     #37                 // class org/springframework/scripting/ScriptFactory
     104: astore        6
     106: aload_0
     107: aload         4
     109: aload         6
     111: invokeinterface #47,  1           // InterfaceMethod org/springframework/scripting/ScriptFactory.getScriptSourceLocator:()Ljava/lang/String;
     116: invokevirtual #48                 // Method getScriptSource:(Ljava/lang/String;Ljava/lang/String;)Lorg/springframework/scripting/ScriptSource;
     119: astore        7
     121: iconst_0
     122: istore        8
     124: aload         6
     126: aload         7
     128: invokeinterface #50,  2           // InterfaceMethod org/springframework/scripting/ScriptFactory.getScriptedObjectType:(Lorg/springframework/scripting/ScriptSource;)Ljava/lang/Class;
     133: astore        9
     135: aload         9
     137: ifnull        149
     140: ldc           #67                 // class org/springframework/beans/factory/FactoryBean
     142: aload         9
     144: invokevirtual #38                 // Method java/lang/Class.isAssignableFrom:(Ljava/lang/Class;)Z
     147: istore        8
     149: goto          185
     152: astore        9
     154: new           #56                 // class org/springframework/beans/factory/BeanCreationException
     157: dup
     158: aload_2
     159: new           #22                 // class java/lang/StringBuilder
     162: dup
     163: invokespecial #23                 // Method java/lang/StringBuilder."<init>":()V
     166: ldc           #68                 // String Could not determine scripted object type for
     168: invokevirtual #25                 // Method java/lang/StringBuilder.append:(Ljava/lang/String;)Ljava/lang/StringBuilder;
     171: aload         6
     173: invokevirtual #26                 // Method java/lang/StringBuilder.append:(Ljava/lang/Object;)Ljava/lang/StringBuilder;
     176: invokevirtual #27                 // Method java/lang/StringBuilder.toString:()Ljava/lang/String;
     179: aload         9
     181: invokespecial #69                 // Method org/springframework/beans/factory/BeanCreationException."<init>":(Ljava/lang/String;Ljava/lang/String;Ljava/lang/Throwable;)V
     184: athrow
     185: aload_0
     186: aload_3
     187: invokevirtual #70                 // Method resolveRefreshCheckDelay:(Lorg/springframework/beans/factory/config/BeanDefinition;)J
     190: lstore        9
     192: lload         9
     194: lconst_0
     195: lcmp
     196: iflt          321
     199: aload         6
     201: invokeinterface #49,  1           // InterfaceMethod org/springframework/scripting/ScriptFactory.getScriptInterfaces:()[Ljava/lang/Class;
     206: astore        11
     208: new           #71                 // class org/springframework/scripting/support/RefreshableScriptTargetSource
     211: dup
     212: aload_0
     213: getfield      #16                 // Field scriptBeanFactory:Lorg/springframework/beans/factory/support/DefaultListableBeanFactory;
     216: aload         5
     218: aload         6
     220: aload         7
     222: iload         8
     224: invokespecial #72                 // Method org/springframework/scripting/support/RefreshableScriptTargetSource."<init>":(Lorg/springframework/beans/factory/BeanFactory;Ljava/lang/String;Lorg/springframework/scripting/ScriptFactory;Lorg/springframework/scripting/ScriptSource;Z)V
     227: astore        12
     229: aload_0
     230: aload_3
     231: invokevirtual #73                 // Method resolveProxyTargetClass:(Lorg/springframework/beans/factory/config/BeanDefinition;)Z
     234: istore        13
     236: aload_3
     237: getstatic     #74                 // Field LANGUAGE_ATTRIBUTE:Ljava/lang/String;
     240: invokeinterface #75,  2           // InterfaceMethod org/springframework/beans/factory/config/BeanDefinition.getAttribute:(Ljava/lang/String;)Ljava/lang/Object;
     245: checkcast     #76                 // class java/lang/String
     248: astore        14
     250: iload         13
     252: ifeq          303
     255: aload         14
     257: ifnull        270
     260: aload         14
     262: ldc           #77                 // String groovy
     264: invokevirtual #78                 // Method java/lang/String.equals:(Ljava/lang/Object;)Z
     267: ifne          303
     270: new           #79                 // class org/springframework/beans/factory/support/BeanDefinitionValidationException
     273: dup
     274: new           #22                 // class java/lang/StringBuilder
     277: dup
     278: invokespecial #23                 // Method java/lang/StringBuilder."<init>":()V
     281: ldc           #80                 // String Cannot use proxyTargetClass=true with script beans where language is not \'groovy\': \'
     283: invokevirtual #25                 // Method java/lang/StringBuilder.append:(Ljava/lang/String;)Ljava/lang/StringBuilder;
     286: aload         14
     288: invokevirtual #25                 // Method java/lang/StringBuilder.append:(Ljava/lang/String;)Ljava/lang/StringBuilder;
     291: ldc           #65                 // String \'
     293: invokevirtual #25                 // Method java/lang/StringBuilder.append:(Ljava/lang/String;)Ljava/lang/StringBuilder;
     296: invokevirtual #27                 // Method java/lang/StringBuilder.toString:()Ljava/lang/String;
     299: invokespecial #81                 // Method org/springframework/beans/factory/support/BeanDefinitionValidationException."<init>":(Ljava/lang/String;)V
     302: athrow
     303: aload         12
     305: lload         9
     307: invokevirtual #82                 // Method org/springframework/scripting/support/RefreshableScriptTargetSource.setRefreshCheckDelay:(J)V
     310: aload_0
     311: aload         12
     313: aload         11
     315: iload         13
     317: invokevirtual #83                 // Method createRefreshableProxy:(Lorg/springframework/aop/TargetSource;[Ljava/lang/Class;Z)Ljava/lang/Object;
     320: areturn
     321: iload         8
     323: ifeq          348
     326: new           #22                 // class java/lang/StringBuilder
     329: dup
     330: invokespecial #23                 // Method java/lang/StringBuilder."<init>":()V
     333: ldc           #85                 // String &
     335: invokevirtual #25                 // Method java/lang/StringBuilder.append:(Ljava/lang/String;)Ljava/lang/StringBuilder;
     338: aload         5
     340: invokevirtual #25                 // Method java/lang/StringBuilder.append:(Ljava/lang/String;)Ljava/lang/StringBuilder;
     343: invokevirtual #27                 // Method java/lang/StringBuilder.toString:()Ljava/lang/String;
     346: astore        5
     348: aload_0
     349: getfield      #16                 // Field scriptBeanFactory:Lorg/springframework/beans/factory/support/DefaultListableBeanFactory;
     352: aload         5
     354: invokevirtual #54                 // Method org/springframework/beans/factory/support/DefaultListableBeanFactory.getBean:(Ljava/lang/String;)Ljava/lang/Object;
     357: areturn
    Exception table:
       from    to  target type
         124   149   152   Class java/lang/Exception

  protected void prepareScriptBeans(org.springframework.beans.factory.config.BeanDefinition, java.lang.String, java.lang.String);
    Code:
       0: aload_0
       1: getfield      #16                 // Field scriptBeanFactory:Lorg/springframework/beans/factory/support/DefaultListableBeanFactory;
       4: dup
       5: astore        4
       7: monitorenter
       8: aload_0
       9: getfield      #16                 // Field scriptBeanFactory:Lorg/springframework/beans/factory/support/DefaultListableBeanFactory;
      12: aload_3
      13: invokevirtual #86                 // Method org/springframework/beans/factory/support/DefaultListableBeanFactory.containsBeanDefinition:(Ljava/lang/String;)Z
      16: ifne          162
      19: aload_0
      20: getfield      #16                 // Field scriptBeanFactory:Lorg/springframework/beans/factory/support/DefaultListableBeanFactory;
      23: aload_2
      24: aload_0
      25: aload_1
      26: invokevirtual #87                 // Method createScriptFactoryBeanDefinition:(Lorg/springframework/beans/factory/config/BeanDefinition;)Lorg/springframework/beans/factory/config/BeanDefinition;
      29: invokevirtual #88                 // Method org/springframework/beans/factory/support/DefaultListableBeanFactory.registerBeanDefinition:(Ljava/lang/String;Lorg/springframework/beans/factory/config/BeanDefinition;)V
      32: aload_0
      33: getfield      #16                 // Field scriptBeanFactory:Lorg/springframework/beans/factory/support/DefaultListableBeanFactory;
      36: aload_2
      37: ldc           #37                 // class org/springframework/scripting/ScriptFactory
      39: invokevirtual #46                 // Method org/springframework/beans/factory/support/DefaultListableBeanFactory.getBean:(Ljava/lang/String;Ljava/lang/Class;)Ljava/lang/Object;
      42: checkcast     #37                 // class org/springframework/scripting/ScriptFactory
      45: astore        5
      47: aload_0
      48: aload_2
      49: aload         5
      51: invokeinterface #47,  1           // InterfaceMethod org/springframework/scripting/ScriptFactory.getScriptSourceLocator:()Ljava/lang/String;
      56: invokevirtual #48                 // Method getScriptSource:(Ljava/lang/String;Ljava/lang/String;)Lorg/springframework/scripting/ScriptSource;
      59: astore        6
      61: aload         5
      63: invokeinterface #49,  1           // InterfaceMethod org/springframework/scripting/ScriptFactory.getScriptInterfaces:()[Ljava/lang/Class;
      68: astore        7
      70: aload         7
      72: astore        8
      74: aload         5
      76: invokeinterface #89,  1           // InterfaceMethod org/springframework/scripting/ScriptFactory.requiresConfigInterface:()Z
      81: ifeq          117
      84: aload_1
      85: invokeinterface #90,  1           // InterfaceMethod org/springframework/beans/factory/config/BeanDefinition.getPropertyValues:()Lorg/springframework/beans/MutablePropertyValues;
      90: invokevirtual #91                 // Method org/springframework/beans/MutablePropertyValues.isEmpty:()Z
      93: ifne          117
      96: aload_0
      97: aload_1
      98: aload         7
     100: invokevirtual #92                 // Method createConfigInterface:(Lorg/springframework/beans/factory/config/BeanDefinition;[Ljava/lang/Class;)Ljava/lang/Class;
     103: astore        9
     105: aload         7
     107: aload         9
     109: invokestatic  #93                 // Method org/springframework/util/ObjectUtils.addObjectToArray:([Ljava/lang/Object;Ljava/lang/Object;)[Ljava/lang/Object;
     112: checkcast     #94                 // class "[Ljava/lang/Class;"
     115: astore        8
     117: aload_0
     118: aload_1
     119: aload_2
     120: aload         6
     122: aload         8
     124: invokevirtual #95                 // Method createScriptedObjectBeanDefinition:(Lorg/springframework/beans/factory/config/BeanDefinition;Ljava/lang/String;Lorg/springframework/scripting/ScriptSource;[Ljava/lang/Class;)Lorg/springframework/beans/factory/config/BeanDefinition;
     127: astore        9
     129: aload_0
     130: aload_1
     131: invokevirtual #70                 // Method resolveRefreshCheckDelay:(Lorg/springframework/beans/factory/config/BeanDefinition;)J
     134: lstore        10
     136: lload         10
     138: lconst_0
     139: lcmp
     140: iflt          152
     143: aload         9
     145: ldc           #97                 // String prototype
     147: invokeinterface #98,  2           // InterfaceMethod org/springframework/beans/factory/config/BeanDefinition.setScope:(Ljava/lang/String;)V
     152: aload_0
     153: getfield      #16                 // Field scriptBeanFactory:Lorg/springframework/beans/factory/support/DefaultListableBeanFactory;
     156: aload_3
     157: aload         9
     159: invokevirtual #88                 // Method org/springframework/beans/factory/support/DefaultListableBeanFactory.registerBeanDefinition:(Ljava/lang/String;Lorg/springframework/beans/factory/config/BeanDefinition;)V
     162: aload         4
     164: monitorexit
     165: goto          176
     168: astore        12
     170: aload         4
     172: monitorexit
     173: aload         12
     175: athrow
     176: return
    Exception table:
       from    to  target type
           8   165   168   any
         168   173   168   any

  protected long resolveRefreshCheckDelay(org.springframework.beans.factory.config.BeanDefinition);
    Code:
       0: aload_0
       1: getfield      #7                  // Field defaultRefreshCheckDelay:J
       4: lstore_2
       5: aload_1
       6: getstatic     #99                 // Field REFRESH_CHECK_DELAY_ATTRIBUTE:Ljava/lang/String;
       9: invokeinterface #75,  2           // InterfaceMethod org/springframework/beans/factory/config/BeanDefinition.getAttribute:(Ljava/lang/String;)Ljava/lang/Object;
      14: astore        4
      16: aload         4
      18: instanceof    #100                // class java/lang/Number
      21: ifeq          36
      24: aload         4
      26: checkcast     #100                // class java/lang/Number
      29: invokevirtual #101                // Method java/lang/Number.longValue:()J
      32: lstore_2
      33: goto          105
      36: aload         4
      38: instanceof    #76                 // class java/lang/String
      41: ifeq          56
      44: aload         4
      46: checkcast     #76                 // class java/lang/String
      49: invokestatic  #102                // Method java/lang/Long.parseLong:(Ljava/lang/String;)J
      52: lstore_2
      53: goto          105
      56: aload         4
      58: ifnull        105
      61: new           #103                // class org/springframework/beans/factory/BeanDefinitionStoreException
      64: dup
      65: new           #22                 // class java/lang/StringBuilder
      68: dup
      69: invokespecial #23                 // Method java/lang/StringBuilder."<init>":()V
      72: ldc           #104                // String Invalid refresh check delay attribute [
      74: invokevirtual #25                 // Method java/lang/StringBuilder.append:(Ljava/lang/String;)Ljava/lang/StringBuilder;
      77: getstatic     #99                 // Field REFRESH_CHECK_DELAY_ATTRIBUTE:Ljava/lang/String;
      80: invokevirtual #25                 // Method java/lang/StringBuilder.append:(Ljava/lang/String;)Ljava/lang/StringBuilder;
      83: ldc           #105                // String ] with value \'
      85: invokevirtual #25                 // Method java/lang/StringBuilder.append:(Ljava/lang/String;)Ljava/lang/StringBuilder;
      88: aload         4
      90: invokevirtual #26                 // Method java/lang/StringBuilder.append:(Ljava/lang/Object;)Ljava/lang/StringBuilder;
      93: ldc           #106                // String \': needs to be of type Number or String
      95: invokevirtual #25                 // Method java/lang/StringBuilder.append:(Ljava/lang/String;)Ljava/lang/StringBuilder;
      98: invokevirtual #27                 // Method java/lang/StringBuilder.toString:()Ljava/lang/String;
     101: invokespecial #107                // Method org/springframework/beans/factory/BeanDefinitionStoreException."<init>":(Ljava/lang/String;)V
     104: athrow
     105: lload_2
     106: lreturn

  protected boolean resolveProxyTargetClass(org.springframework.beans.factory.config.BeanDefinition);
    Code:
       0: aload_0
       1: getfield      #8                  // Field defaultProxyTargetClass:Z
       4: istore_2
       5: aload_1
       6: getstatic     #108                // Field PROXY_TARGET_CLASS_ATTRIBUTE:Ljava/lang/String;
       9: invokeinterface #75,  2           // InterfaceMethod org/springframework/beans/factory/config/BeanDefinition.getAttribute:(Ljava/lang/String;)Ljava/lang/Object;
      14: astore_3
      15: aload_3
      16: instanceof    #109                // class java/lang/Boolean
      19: ifeq          33
      22: aload_3
      23: checkcast     #109                // class java/lang/Boolean
      26: invokevirtual #110                // Method java/lang/Boolean.booleanValue:()Z
      29: istore_2
      30: goto          101
      33: aload_3
      34: instanceof    #76                 // class java/lang/String
      37: ifeq          54
      40: aload_3
      41: checkcast     #76                 // class java/lang/String
      44: invokestatic  #111                // Method java/lang/Boolean.valueOf:(Ljava/lang/String;)Ljava/lang/Boolean;
      47: invokevirtual #110                // Method java/lang/Boolean.booleanValue:()Z
      50: istore_2
      51: goto          101
      54: aload_3
      55: ifnull        101
      58: new           #103                // class org/springframework/beans/factory/BeanDefinitionStoreException
      61: dup
      62: new           #22                 // class java/lang/StringBuilder
      65: dup
      66: invokespecial #23                 // Method java/lang/StringBuilder."<init>":()V
      69: ldc           #112                // String Invalid proxy target class attribute [
      71: invokevirtual #25                 // Method java/lang/StringBuilder.append:(Ljava/lang/String;)Ljava/lang/StringBuilder;
      74: getstatic     #108                // Field PROXY_TARGET_CLASS_ATTRIBUTE:Ljava/lang/String;
      77: invokevirtual #25                 // Method java/lang/StringBuilder.append:(Ljava/lang/String;)Ljava/lang/StringBuilder;
      80: ldc           #105                // String ] with value \'
      82: invokevirtual #25                 // Method java/lang/StringBuilder.append:(Ljava/lang/String;)Ljava/lang/StringBuilder;
      85: aload_3
      86: invokevirtual #26                 // Method java/lang/StringBuilder.append:(Ljava/lang/Object;)Ljava/lang/StringBuilder;
      89: ldc           #113                // String \': needs to be of type Boolean or String
      91: invokevirtual #25                 // Method java/lang/StringBuilder.append:(Ljava/lang/String;)Ljava/lang/StringBuilder;
      94: invokevirtual #27                 // Method java/lang/StringBuilder.toString:()Ljava/lang/String;
      97: invokespecial #107                // Method org/springframework/beans/factory/BeanDefinitionStoreException."<init>":(Ljava/lang/String;)V
     100: athrow
     101: iload_2
     102: ireturn

  protected org.springframework.beans.factory.config.BeanDefinition createScriptFactoryBeanDefinition(org.springframework.beans.factory.config.BeanDefinition);
    Code:
       0: new           #114                // class org/springframework/beans/factory/support/GenericBeanDefinition
       3: dup
       4: invokespecial #115                // Method org/springframework/beans/factory/support/GenericBeanDefinition."<init>":()V
       7: astore_2
       8: aload_2
       9: aload_1
      10: invokeinterface #116,  1          // InterfaceMethod org/springframework/beans/factory/config/BeanDefinition.getBeanClassName:()Ljava/lang/String;
      15: invokevirtual #117                // Method org/springframework/beans/factory/support/GenericBeanDefinition.setBeanClassName:(Ljava/lang/String;)V
      18: aload_2
      19: invokevirtual #118                // Method org/springframework/beans/factory/support/GenericBeanDefinition.getConstructorArgumentValues:()Lorg/springframework/beans/factory/config/ConstructorArgumentValues;
      22: aload_1
      23: invokeinterface #119,  1          // InterfaceMethod org/springframework/beans/factory/config/BeanDefinition.getConstructorArgumentValues:()Lorg/springframework/beans/factory/config/ConstructorArgumentValues;
      28: invokevirtual #120                // Method org/springframework/beans/factory/config/ConstructorArgumentValues.addArgumentValues:(Lorg/springframework/beans/factory/config/ConstructorArgumentValues;)V
      31: aload_2
      32: areturn

  protected org.springframework.scripting.ScriptSource getScriptSource(java.lang.String, java.lang.String);
    Code:
       0: aload_0
       1: getfield      #19                 // Field scriptSourceCache:Ljava/util/Map;
       4: dup
       5: astore_3
       6: monitorenter
       7: aload_0
       8: getfield      #19                 // Field scriptSourceCache:Ljava/util/Map;
      11: aload_1
      12: invokeinterface #121,  2          // InterfaceMethod java/util/Map.get:(Ljava/lang/Object;)Ljava/lang/Object;
      17: checkcast     #122                // class org/springframework/scripting/ScriptSource
      20: astore        4
      22: aload         4
      24: ifnonnull     52
      27: aload_0
      28: aload_1
      29: aload_2
      30: aload_0
      31: getfield      #13                 // Field resourceLoader:Lorg/springframework/core/io/ResourceLoader;
      34: invokevirtual #123                // Method convertToScriptSource:(Ljava/lang/String;Ljava/lang/String;Lorg/springframework/core/io/ResourceLoader;)Lorg/springframework/scripting/ScriptSource;
      37: astore        4
      39: aload_0
      40: getfield      #19                 // Field scriptSourceCache:Ljava/util/Map;
      43: aload_1
      44: aload         4
      46: invokeinterface #124,  3          // InterfaceMethod java/util/Map.put:(Ljava/lang/Object;Ljava/lang/Object;)Ljava/lang/Object;
      51: pop
      52: aload         4
      54: aload_3
      55: monitorexit
      56: areturn
      57: astore        5
      59: aload_3
      60: monitorexit
      61: aload         5
      63: athrow
    Exception table:
       from    to  target type
           7    56    57   any
          57    61    57   any

  protected org.springframework.scripting.ScriptSource convertToScriptSource(java.lang.String, java.lang.String, org.springframework.core.io.ResourceLoader);
    Code:
       0: aload_2
       1: ldc           #125                // String inline:
       3: invokevirtual #126                // Method java/lang/String.startsWith:(Ljava/lang/String;)Z
       6: ifeq          27
       9: new           #127                // class org/springframework/scripting/support/StaticScriptSource
      12: dup
      13: aload_2
      14: ldc           #125                // String inline:
      16: invokevirtual #128                // Method java/lang/String.length:()I
      19: invokevirtual #129                // Method java/lang/String.substring:(I)Ljava/lang/String;
      22: aload_1
      23: invokespecial #130                // Method org/springframework/scripting/support/StaticScriptSource."<init>":(Ljava/lang/String;Ljava/lang/String;)V
      26: areturn
      27: new           #131                // class org/springframework/scripting/support/ResourceScriptSource
      30: dup
      31: aload_3
      32: aload_2
      33: invokeinterface #132,  2          // InterfaceMethod org/springframework/core/io/ResourceLoader.getResource:(Ljava/lang/String;)Lorg/springframework/core/io/Resource;
      38: invokespecial #133                // Method org/springframework/scripting/support/ResourceScriptSource."<init>":(Lorg/springframework/core/io/Resource;)V
      41: areturn

  protected java.lang.Class<?> createConfigInterface(org.springframework.beans.factory.config.BeanDefinition, java.lang.Class<?>[]);
    Code:
       0: new           #134                // class org/springframework/cglib/proxy/InterfaceMaker
       3: dup
       4: invokespecial #135                // Method org/springframework/cglib/proxy/InterfaceMaker."<init>":()V
       7: astore_3
       8: aload_1
       9: invokeinterface #90,  1           // InterfaceMethod org/springframework/beans/factory/config/BeanDefinition.getPropertyValues:()Lorg/springframework/beans/MutablePropertyValues;
      14: invokevirtual #136                // Method org/springframework/beans/MutablePropertyValues.getPropertyValues:()[Lorg/springframework/beans/PropertyValue;
      17: astore        4
      19: aload         4
      21: astore        5
      23: aload         5
      25: arraylength
      26: istore        6
      28: iconst_0
      29: istore        7
      31: iload         7
      33: iload         6
      35: if_icmpge     127
      38: aload         5
      40: iload         7
      42: aaload
      43: astore        8
      45: aload         8
      47: invokevirtual #137                // Method org/springframework/beans/PropertyValue.getName:()Ljava/lang/String;
      50: astore        9
      52: aload         9
      54: aload_2
      55: invokestatic  #138                // Method org/springframework/beans/BeanUtils.findPropertyType:(Ljava/lang/String;[Ljava/lang/Class;)Ljava/lang/Class;
      58: astore        10
      60: new           #22                 // class java/lang/StringBuilder
      63: dup
      64: invokespecial #23                 // Method java/lang/StringBuilder."<init>":()V
      67: ldc           #139                // String set
      69: invokevirtual #25                 // Method java/lang/StringBuilder.append:(Ljava/lang/String;)Ljava/lang/StringBuilder;
      72: aload         9
      74: invokestatic  #140                // Method org/springframework/util/StringUtils.capitalize:(Ljava/lang/String;)Ljava/lang/String;
      77: invokevirtual #25                 // Method java/lang/StringBuilder.append:(Ljava/lang/String;)Ljava/lang/StringBuilder;
      80: invokevirtual #27                 // Method java/lang/StringBuilder.toString:()Ljava/lang/String;
      83: astore        11
      85: new           #141                // class org/springframework/cglib/core/Signature
      88: dup
      89: aload         11
      91: getstatic     #142                // Field org/springframework/asm/Type.VOID_TYPE:Lorg/springframework/asm/Type;
      94: iconst_1
      95: anewarray     #143                // class org/springframework/asm/Type
      98: dup
      99: iconst_0
     100: aload         10
     102: invokestatic  #144                // Method org/springframework/asm/Type.getType:(Ljava/lang/Class;)Lorg/springframework/asm/Type;
     105: aastore
     106: invokespecial #145                // Method org/springframework/cglib/core/Signature."<init>":(Ljava/lang/String;Lorg/springframework/asm/Type;[Lorg/springframework/asm/Type;)V
     109: astore        12
     111: aload_3
     112: aload         12
     114: iconst_0
     115: anewarray     #143                // class org/springframework/asm/Type
     118: invokevirtual #146                // Method org/springframework/cglib/proxy/InterfaceMaker.add:(Lorg/springframework/cglib/core/Signature;[Lorg/springframework/asm/Type;)V
     121: iinc          7, 1
     124: goto          31
     127: aload_1
     128: instanceof    #147                // class org/springframework/beans/factory/support/AbstractBeanDefinition
     131: ifeq          221
     134: aload_1
     135: checkcast     #147                // class org/springframework/beans/factory/support/AbstractBeanDefinition
     138: astore        5
     140: aload         5
     142: invokevirtual #148                // Method org/springframework/beans/factory/support/AbstractBeanDefinition.getInitMethodName:()Ljava/lang/String;
     145: ifnull        179
     148: new           #141                // class org/springframework/cglib/core/Signature
     151: dup
     152: aload         5
     154: invokevirtual #148                // Method org/springframework/beans/factory/support/AbstractBeanDefinition.getInitMethodName:()Ljava/lang/String;
     157: getstatic     #142                // Field org/springframework/asm/Type.VOID_TYPE:Lorg/springframework/asm/Type;
     160: iconst_0
     161: anewarray     #143                // class org/springframework/asm/Type
     164: invokespecial #145                // Method org/springframework/cglib/core/Signature."<init>":(Ljava/lang/String;Lorg/springframework/asm/Type;[Lorg/springframework/asm/Type;)V
     167: astore        6
     169: aload_3
     170: aload         6
     172: iconst_0
     173: anewarray     #143                // class org/springframework/asm/Type
     176: invokevirtual #146                // Method org/springframework/cglib/proxy/InterfaceMaker.add:(Lorg/springframework/cglib/core/Signature;[Lorg/springframework/asm/Type;)V
     179: aload         5
     181: invokevirtual #149                // Method org/springframework/beans/factory/support/AbstractBeanDefinition.getDestroyMethodName:()Ljava/lang/String;
     184: invokestatic  #150                // Method org/springframework/util/StringUtils.hasText:(Ljava/lang/String;)Z
     187: ifeq          221
     190: new           #141                // class org/springframework/cglib/core/Signature
     193: dup
     194: aload         5
     196: invokevirtual #149                // Method org/springframework/beans/factory/support/AbstractBeanDefinition.getDestroyMethodName:()Ljava/lang/String;
     199: getstatic     #142                // Field org/springframework/asm/Type.VOID_TYPE:Lorg/springframework/asm/Type;
     202: iconst_0
     203: anewarray     #143                // class org/springframework/asm/Type
     206: invokespecial #145                // Method org/springframework/cglib/core/Signature."<init>":(Ljava/lang/String;Lorg/springframework/asm/Type;[Lorg/springframework/asm/Type;)V
     209: astore        6
     211: aload_3
     212: aload         6
     214: iconst_0
     215: anewarray     #143                // class org/springframework/asm/Type
     218: invokevirtual #146                // Method org/springframework/cglib/proxy/InterfaceMaker.add:(Lorg/springframework/cglib/core/Signature;[Lorg/springframework/asm/Type;)V
     221: aload_3
     222: invokevirtual #151                // Method org/springframework/cglib/proxy/InterfaceMaker.create:()Ljava/lang/Class;
     225: areturn

  protected java.lang.Class<?> createCompositeInterface(java.lang.Class<?>[]);
    Code:
       0: aload_1
       1: aload_0
       2: getfield      #10                 // Field beanClassLoader:Ljava/lang/ClassLoader;
       5: invokestatic  #152                // Method org/springframework/util/ClassUtils.createCompositeInterface:([Ljava/lang/Class;Ljava/lang/ClassLoader;)Ljava/lang/Class;
       8: areturn

  protected org.springframework.beans.factory.config.BeanDefinition createScriptedObjectBeanDefinition(org.springframework.beans.factory.config.BeanDefinition, java.lang.String, org.springframework.scripting.ScriptSource, java.lang.Class<?>[]);
    Code:
       0: new           #114                // class org/springframework/beans/factory/support/GenericBeanDefinition
       3: dup
       4: aload_1
       5: invokespecial #153                // Method org/springframework/beans/factory/support/GenericBeanDefinition."<init>":(Lorg/springframework/beans/factory/config/BeanDefinition;)V
       8: astore        5
      10: aload         5
      12: aload_2
      13: invokevirtual #154                // Method org/springframework/beans/factory/support/GenericBeanDefinition.setFactoryBeanName:(Ljava/lang/String;)V
      16: aload         5
      18: ldc           #155                // String getScriptedObject
      20: invokevirtual #156                // Method org/springframework/beans/factory/support/GenericBeanDefinition.setFactoryMethodName:(Ljava/lang/String;)V
      23: aload         5
      25: invokevirtual #118                // Method org/springframework/beans/factory/support/GenericBeanDefinition.getConstructorArgumentValues:()Lorg/springframework/beans/factory/config/ConstructorArgumentValues;
      28: invokevirtual #157                // Method org/springframework/beans/factory/config/ConstructorArgumentValues.clear:()V
      31: aload         5
      33: invokevirtual #118                // Method org/springframework/beans/factory/support/GenericBeanDefinition.getConstructorArgumentValues:()Lorg/springframework/beans/factory/config/ConstructorArgumentValues;
      36: iconst_0
      37: aload_3
      38: invokevirtual #158                // Method org/springframework/beans/factory/config/ConstructorArgumentValues.addIndexedArgumentValue:(ILjava/lang/Object;)V
      41: aload         5
      43: invokevirtual #118                // Method org/springframework/beans/factory/support/GenericBeanDefinition.getConstructorArgumentValues:()Lorg/springframework/beans/factory/config/ConstructorArgumentValues;
      46: iconst_1
      47: aload         4
      49: invokevirtual #158                // Method org/springframework/beans/factory/config/ConstructorArgumentValues.addIndexedArgumentValue:(ILjava/lang/Object;)V
      52: aload         5
      54: areturn

  protected java.lang.Object createRefreshableProxy(org.springframework.aop.TargetSource, java.lang.Class<?>[], boolean);
    Code:
       0: new           #159                // class org/springframework/aop/framework/ProxyFactory
       3: dup
       4: invokespecial #160                // Method org/springframework/aop/framework/ProxyFactory."<init>":()V
       7: astore        4
       9: aload         4
      11: aload_1
      12: invokevirtual #161                // Method org/springframework/aop/framework/ProxyFactory.setTargetSource:(Lorg/springframework/aop/TargetSource;)V
      15: aload_0
      16: getfield      #10                 // Field beanClassLoader:Ljava/lang/ClassLoader;
      19: astore        5
      21: aload_2
      22: ifnull        34
      25: aload         4
      27: aload_2
      28: invokevirtual #162                // Method org/springframework/aop/framework/ProxyFactory.setInterfaces:([Ljava/lang/Class;)V
      31: goto          61
      34: aload_1
      35: invokeinterface #163,  1          // InterfaceMethod org/springframework/aop/TargetSource.getTargetClass:()Ljava/lang/Class;
      40: astore        6
      42: aload         6
      44: ifnull        61
      47: aload         4
      49: aload         6
      51: aload_0
      52: getfield      #10                 // Field beanClassLoader:Ljava/lang/ClassLoader;
      55: invokestatic  #164                // Method org/springframework/util/ClassUtils.getAllInterfacesForClass:(Ljava/lang/Class;Ljava/lang/ClassLoader;)[Ljava/lang/Class;
      58: invokevirtual #162                // Method org/springframework/aop/framework/ProxyFactory.setInterfaces:([Ljava/lang/Class;)V
      61: iload_3
      62: ifeq          74
      65: aconst_null
      66: astore        5
      68: aload         4
      70: iconst_1
      71: invokevirtual #165                // Method org/springframework/aop/framework/ProxyFactory.setProxyTargetClass:(Z)V
      74: new           #166                // class org/springframework/aop/support/DelegatingIntroductionInterceptor
      77: dup
      78: aload_1
      79: invokespecial #167                // Method org/springframework/aop/support/DelegatingIntroductionInterceptor."<init>":(Ljava/lang/Object;)V
      82: astore        6
      84: aload         6
      86: ldc           #168                // class org/springframework/aop/TargetSource
      88: invokevirtual #169                // Method org/springframework/aop/support/DelegatingIntroductionInterceptor.suppressInterface:(Ljava/lang/Class;)V
      91: aload         4
      93: aload         6
      95: invokevirtual #170                // Method org/springframework/aop/framework/ProxyFactory.addAdvice:(Lorg/aopalliance/aop/Advice;)V
      98: aload         4
     100: aload         5
     102: invokevirtual #171                // Method org/springframework/aop/framework/ProxyFactory.getProxy:(Ljava/lang/ClassLoader;)Ljava/lang/Object;
     105: areturn

  public void destroy();
    Code:
       0: aload_0
       1: getfield      #16                 // Field scriptBeanFactory:Lorg/springframework/beans/factory/support/DefaultListableBeanFactory;
       4: invokevirtual #172                // Method org/springframework/beans/factory/support/DefaultListableBeanFactory.destroySingletons:()V
       7: return

  private static boolean lambda$setBeanFactory$0(org.springframework.beans.factory.config.BeanPostProcessor);
    Code:
       0: aload_0
       1: instanceof    #173                // class org/springframework/aop/framework/AopInfrastructureBean
       4: ireturn

  static {};
    Code:
       0: ldc           #42                 // class org/springframework/scripting/support/ScriptFactoryPostProcessor
       2: ldc           #174                // String refreshCheckDelay
       4: invokestatic  #175                // Method org/springframework/core/Conventions.getQualifiedAttributeName:(Ljava/lang/Class;Ljava/lang/String;)Ljava/lang/String;
       7: putstatic     #99                 // Field REFRESH_CHECK_DELAY_ATTRIBUTE:Ljava/lang/String;
      10: ldc           #42                 // class org/springframework/scripting/support/ScriptFactoryPostProcessor
      12: ldc           #176                // String proxyTargetClass
      14: invokestatic  #175                // Method org/springframework/core/Conventions.getQualifiedAttributeName:(Ljava/lang/Class;Ljava/lang/String;)Ljava/lang/String;
      17: putstatic     #108                // Field PROXY_TARGET_CLASS_ATTRIBUTE:Ljava/lang/String;
      20: ldc           #42                 // class org/springframework/scripting/support/ScriptFactoryPostProcessor
      22: ldc           #177                // String language
      24: invokestatic  #175                // Method org/springframework/core/Conventions.getQualifiedAttributeName:(Ljava/lang/Class;Ljava/lang/String;)Ljava/lang/String;
      27: putstatic     #74                 // Field LANGUAGE_ATTRIBUTE:Ljava/lang/String;
      30: return
}
