Compiled from "ConcurrentServiceNames.java"
public class org.jboss.as.ee.concurrent.service.ConcurrentServiceNames {
  public static final org.jboss.msc.service.ServiceName BASE_SERVICE_NAME;

  private static final org.jboss.msc.service.ServiceName CONTEXT_BASE_SERVICE_NAME;

  private static final org.jboss.msc.service.ServiceName CONTEXT_SERVICE_BASE_SERVICE_NAME;

  private static final org.jboss.msc.service.ServiceName MANAGED_THREAD_FACTORY_BASE_SERVICE_NAME;

  private static final org.jboss.msc.service.ServiceName MANAGED_EXECUTOR_SERVICE_BASE_SERVICE_NAME;

  private static final org.jboss.msc.service.ServiceName MANAGED_SCHEDULED_EXECUTOR_SERVICE_BASE_SERVICE_NAME;

  public static final org.jboss.msc.service.ServiceName TRANSACTION_SETUP_PROVIDER_SERVICE_NAME;

  public static final org.jboss.msc.service.ServiceName CONCURRENT_CONTEXT_BASE_SERVICE_NAME;

  private org.jboss.as.ee.concurrent.service.ConcurrentServiceNames();
    Code:
       0: aload_0
       1: invokespecial #1                  // Method java/lang/Object."<init>":()V
       4: return

  public static org.jboss.msc.service.ServiceName getContextServiceServiceName(java.lang.String);
    Code:
       0: getstatic     #2                  // Field CONTEXT_SERVICE_BASE_SERVICE_NAME:Lorg/jboss/msc/service/ServiceName;
       3: iconst_1
       4: anewarray     #3                  // class java/lang/String
       7: dup
       8: iconst_0
       9: aload_0
      10: aastore
      11: invokevirtual #4                  // Method org/jboss/msc/service/ServiceName.append:([Ljava/lang/String;)Lorg/jboss/msc/service/ServiceName;
      14: areturn

  public static org.jboss.msc.service.ServiceName getManagedThreadFactoryServiceName(java.lang.String);
    Code:
       0: getstatic     #5                  // Field MANAGED_THREAD_FACTORY_BASE_SERVICE_NAME:Lorg/jboss/msc/service/ServiceName;
       3: iconst_1
       4: anewarray     #3                  // class java/lang/String
       7: dup
       8: iconst_0
       9: aload_0
      10: aastore
      11: invokevirtual #4                  // Method org/jboss/msc/service/ServiceName.append:([Ljava/lang/String;)Lorg/jboss/msc/service/ServiceName;
      14: areturn

  public static org.jboss.msc.service.ServiceName getManagedExecutorServiceServiceName(java.lang.String);
    Code:
       0: getstatic     #6                  // Field MANAGED_EXECUTOR_SERVICE_BASE_SERVICE_NAME:Lorg/jboss/msc/service/ServiceName;
       3: iconst_1
       4: anewarray     #3                  // class java/lang/String
       7: dup
       8: iconst_0
       9: aload_0
      10: aastore
      11: invokevirtual #4                  // Method org/jboss/msc/service/ServiceName.append:([Ljava/lang/String;)Lorg/jboss/msc/service/ServiceName;
      14: areturn

  public static org.jboss.msc.service.ServiceName getManagedScheduledExecutorServiceServiceName(java.lang.String);
    Code:
       0: getstatic     #7                  // Field MANAGED_SCHEDULED_EXECUTOR_SERVICE_BASE_SERVICE_NAME:Lorg/jboss/msc/service/ServiceName;
       3: iconst_1
       4: anewarray     #3                  // class java/lang/String
       7: dup
       8: iconst_0
       9: aload_0
      10: aastore
      11: invokevirtual #4                  // Method org/jboss/msc/service/ServiceName.append:([Ljava/lang/String;)Lorg/jboss/msc/service/ServiceName;
      14: areturn

  public static org.jboss.msc.service.ServiceName getConcurrentContextServiceName(java.lang.String, java.lang.String, java.lang.String);
    Code:
       0: getstatic     #8                  // Field CONCURRENT_CONTEXT_BASE_SERVICE_NAME:Lorg/jboss/msc/service/ServiceName;
       3: iconst_1
       4: anewarray     #3                  // class java/lang/String
       7: dup
       8: iconst_0
       9: aload_0
      10: aastore
      11: invokevirtual #4                  // Method org/jboss/msc/service/ServiceName.append:([Ljava/lang/String;)Lorg/jboss/msc/service/ServiceName;
      14: iconst_1
      15: anewarray     #3                  // class java/lang/String
      18: dup
      19: iconst_0
      20: aload_1
      21: aastore
      22: invokevirtual #4                  // Method org/jboss/msc/service/ServiceName.append:([Ljava/lang/String;)Lorg/jboss/msc/service/ServiceName;
      25: astore_3
      26: aload_2
      27: ifnonnull     32
      30: aload_3
      31: areturn
      32: aload_3
      33: iconst_1
      34: anewarray     #3                  // class java/lang/String
      37: dup
      38: iconst_0
      39: aload_2
      40: aastore
      41: invokevirtual #4                  // Method org/jboss/msc/service/ServiceName.append:([Ljava/lang/String;)Lorg/jboss/msc/service/ServiceName;
      44: areturn

  static {};
    Code:
       0: getstatic     #9                  // Field org/jboss/msc/service/ServiceName.JBOSS:Lorg/jboss/msc/service/ServiceName;
       3: iconst_2
       4: anewarray     #3                  // class java/lang/String
       7: dup
       8: iconst_0
       9: ldc           #10                 // String concurrent
      11: aastore
      12: dup
      13: iconst_1
      14: ldc           #11                 // String ee
      16: aastore
      17: invokevirtual #4                  // Method org/jboss/msc/service/ServiceName.append:([Ljava/lang/String;)Lorg/jboss/msc/service/ServiceName;
      20: putstatic     #12                 // Field BASE_SERVICE_NAME:Lorg/jboss/msc/service/ServiceName;
      23: getstatic     #12                 // Field BASE_SERVICE_NAME:Lorg/jboss/msc/service/ServiceName;
      26: iconst_1
      27: anewarray     #3                  // class java/lang/String
      30: dup
      31: iconst_0
      32: ldc           #13                 // String context
      34: aastore
      35: invokevirtual #4                  // Method org/jboss/msc/service/ServiceName.append:([Ljava/lang/String;)Lorg/jboss/msc/service/ServiceName;
      38: putstatic     #14                 // Field CONTEXT_BASE_SERVICE_NAME:Lorg/jboss/msc/service/ServiceName;
      41: getstatic     #14                 // Field CONTEXT_BASE_SERVICE_NAME:Lorg/jboss/msc/service/ServiceName;
      44: iconst_1
      45: anewarray     #3                  // class java/lang/String
      48: dup
      49: iconst_0
      50: ldc           #15                 // String service
      52: aastore
      53: invokevirtual #4                  // Method org/jboss/msc/service/ServiceName.append:([Ljava/lang/String;)Lorg/jboss/msc/service/ServiceName;
      56: putstatic     #2                  // Field CONTEXT_SERVICE_BASE_SERVICE_NAME:Lorg/jboss/msc/service/ServiceName;
      59: getstatic     #12                 // Field BASE_SERVICE_NAME:Lorg/jboss/msc/service/ServiceName;
      62: iconst_1
      63: anewarray     #3                  // class java/lang/String
      66: dup
      67: iconst_0
      68: ldc           #16                 // String threadfactory
      70: aastore
      71: invokevirtual #4                  // Method org/jboss/msc/service/ServiceName.append:([Ljava/lang/String;)Lorg/jboss/msc/service/ServiceName;
      74: putstatic     #5                  // Field MANAGED_THREAD_FACTORY_BASE_SERVICE_NAME:Lorg/jboss/msc/service/ServiceName;
      77: getstatic     #12                 // Field BASE_SERVICE_NAME:Lorg/jboss/msc/service/ServiceName;
      80: iconst_1
      81: anewarray     #3                  // class java/lang/String
      84: dup
      85: iconst_0
      86: ldc           #17                 // String executor
      88: aastore
      89: invokevirtual #4                  // Method org/jboss/msc/service/ServiceName.append:([Ljava/lang/String;)Lorg/jboss/msc/service/ServiceName;
      92: putstatic     #6                  // Field MANAGED_EXECUTOR_SERVICE_BASE_SERVICE_NAME:Lorg/jboss/msc/service/ServiceName;
      95: getstatic     #12                 // Field BASE_SERVICE_NAME:Lorg/jboss/msc/service/ServiceName;
      98: iconst_1
      99: anewarray     #3                  // class java/lang/String
     102: dup
     103: iconst_0
     104: ldc           #18                 // String scheduledexecutor
     106: aastore
     107: invokevirtual #4                  // Method org/jboss/msc/service/ServiceName.append:([Ljava/lang/String;)Lorg/jboss/msc/service/ServiceName;
     110: putstatic     #7                  // Field MANAGED_SCHEDULED_EXECUTOR_SERVICE_BASE_SERVICE_NAME:Lorg/jboss/msc/service/ServiceName;
     113: getstatic     #12                 // Field BASE_SERVICE_NAME:Lorg/jboss/msc/service/ServiceName;
     116: iconst_1
     117: anewarray     #3                  // class java/lang/String
     120: dup
     121: iconst_0
     122: ldc           #19                 // String tsp
     124: aastore
     125: invokevirtual #4                  // Method org/jboss/msc/service/ServiceName.append:([Ljava/lang/String;)Lorg/jboss/msc/service/ServiceName;
     128: putstatic     #20                 // Field TRANSACTION_SETUP_PROVIDER_SERVICE_NAME:Lorg/jboss/msc/service/ServiceName;
     131: getstatic     #14                 // Field CONTEXT_BASE_SERVICE_NAME:Lorg/jboss/msc/service/ServiceName;
     134: iconst_1
     135: anewarray     #3                  // class java/lang/String
     138: dup
     139: iconst_0
     140: ldc           #21                 // String config
     142: aastore
     143: invokevirtual #4                  // Method org/jboss/msc/service/ServiceName.append:([Ljava/lang/String;)Lorg/jboss/msc/service/ServiceName;
     146: putstatic     #8                  // Field CONCURRENT_CONTEXT_BASE_SERVICE_NAME:Lorg/jboss/msc/service/ServiceName;
     149: return
}
