Compiled from "JGroupsPropertiesBroadcastEndpointFactory.java"
public class org.apache.activemq.artemis.api.core.JGroupsPropertiesBroadcastEndpointFactory implements org.apache.activemq.artemis.api.core.BroadcastEndpointFactory {
  private java.lang.String properties;

  private java.lang.String channelName;

  public org.apache.activemq.artemis.api.core.JGroupsPropertiesBroadcastEndpointFactory();
    Code:
       0: aload_0
       1: invokespecial #1                  // Method java/lang/Object."<init>":()V
       4: return

  public org.apache.activemq.artemis.api.core.BroadcastEndpoint createBroadcastEndpoint() throws java.lang.Exception;
    Code:
       0: new           #2                  // class org/apache/activemq/artemis/api/core/JGroupsPropertiesBroadcastEndpoint
       3: dup
       4: aload_0
       5: getfield      #3                  // Field properties:Ljava/lang/String;
       8: aload_0
       9: getfield      #4                  // Field channelName:Ljava/lang/String;
      12: invokespecial #5                  // Method org/apache/activemq/artemis/api/core/JGroupsPropertiesBroadcastEndpoint."<init>":(Ljava/lang/String;Ljava/lang/String;)V
      15: invokevirtual #6                  // Method org/apache/activemq/artemis/api/core/JGroupsPropertiesBroadcastEndpoint.initChannel:()Lorg/apache/activemq/artemis/api/core/JGroupsBroadcastEndpoint;
      18: areturn

  public java.lang.String getProperties();
    Code:
       0: aload_0
       1: getfield      #3                  // Field properties:Ljava/lang/String;
       4: areturn

  public org.apache.activemq.artemis.api.core.JGroupsPropertiesBroadcastEndpointFactory setProperties(java.lang.String);
    Code:
       0: aload_0
       1: aload_1
       2: putfield      #3                  // Field properties:Ljava/lang/String;
       5: aload_0
       6: areturn

  public java.lang.String getChannelName();
    Code:
       0: aload_0
       1: getfield      #4                  // Field channelName:Ljava/lang/String;
       4: areturn

  public org.apache.activemq.artemis.api.core.JGroupsPropertiesBroadcastEndpointFactory setChannelName(java.lang.String);
    Code:
       0: aload_0
       1: aload_1
       2: putfield      #4                  // Field channelName:Ljava/lang/String;
       5: aload_0
       6: areturn
}
