Compiled from "XssProtectionConfigDsl.kt"
public final class org.springframework.security.config.web.servlet.headers.XssProtectionConfigDsl {
  private java.lang.Boolean block;

  private java.lang.Boolean xssProtectionEnabled;

  private boolean disabled;

  public final java.lang.Boolean getBlock();
    Code:
       0: aload_0
       1: getfield      #12                 // Field block:Ljava/lang/Boolean;
       4: areturn

  public final void setBlock(java.lang.Boolean);
    Code:
       0: aload_0
       1: aload_1
       2: putfield      #12                 // Field block:Ljava/lang/Boolean;
       5: return

  public final java.lang.Boolean getXssProtectionEnabled();
    Code:
       0: aload_0
       1: getfield      #21                 // Field xssProtectionEnabled:Ljava/lang/Boolean;
       4: areturn

  public final void setXssProtectionEnabled(java.lang.Boolean);
    Code:
       0: aload_0
       1: aload_1
       2: putfield      #21                 // Field xssProtectionEnabled:Ljava/lang/Boolean;
       5: return

  public final void disable();
    Code:
       0: aload_0
       1: iconst_1
       2: putfield      #28                 // Field disabled:Z
       5: return

  public final kotlin.jvm.functions.Function1<org.springframework.security.config.annotation.web.configurers.HeadersConfigurer<org.springframework.security.config.annotation.web.builders.HttpSecurity>.XXssConfig, kotlin.Unit> get$spring_security_config();
    Code:
       0: new           #34                 // class org/springframework/security/config/web/servlet/headers/XssProtectionConfigDsl$get$1
       3: dup
       4: aload_0
       5: invokespecial #38                 // Method org/springframework/security/config/web/servlet/headers/XssProtectionConfigDsl$get$1."<init>":(Lorg/springframework/security/config/web/servlet/headers/XssProtectionConfigDsl;)V
       8: checkcast     #40                 // class kotlin/jvm/functions/Function1
      11: areturn

  public org.springframework.security.config.web.servlet.headers.XssProtectionConfigDsl();
    Code:
       0: aload_0
       1: invokespecial #42                 // Method java/lang/Object."<init>":()V
       4: return

  public static final boolean access$getDisabled$p(org.springframework.security.config.web.servlet.headers.XssProtectionConfigDsl);
    Code:
       0: aload_0
       1: getfield      #28                 // Field disabled:Z
       4: ireturn

  public static final void access$setDisabled$p(org.springframework.security.config.web.servlet.headers.XssProtectionConfigDsl, boolean);
    Code:
       0: aload_0
       1: iload_1
       2: putfield      #28                 // Field disabled:Z
       5: return
}
