Compiled from "LoopingListIterator.java"
public class org.apache.commons.collections4.iterators.LoopingListIterator<E> implements org.apache.commons.collections4.ResettableListIterator<E> {
  private final java.util.List<E> list;

  private java.util.ListIterator<E> iterator;

  public org.apache.commons.collections4.iterators.LoopingListIterator(java.util.List<E>);
    Code:
       0: aload_0
       1: invokespecial #1                  // Method java/lang/Object."<init>":()V
       4: aload_1
       5: ifnonnull     18
       8: new           #2                  // class java/lang/NullPointerException
      11: dup
      12: ldc           #3                  // String The list must not be null
      14: invokespecial #4                  // Method java/lang/NullPointerException."<init>":(Ljava/lang/String;)V
      17: athrow
      18: aload_0
      19: aload_1
      20: putfield      #5                  // Field list:Ljava/util/List;
      23: aload_0
      24: invokespecial #6                  // Method _reset:()V
      27: return

  public boolean hasNext();
    Code:
       0: aload_0
       1: getfield      #5                  // Field list:Ljava/util/List;
       4: invokeinterface #7,  1            // InterfaceMethod java/util/List.isEmpty:()Z
       9: ifne          16
      12: iconst_1
      13: goto          17
      16: iconst_0
      17: ireturn

  public E next();
    Code:
       0: aload_0
       1: getfield      #5                  // Field list:Ljava/util/List;
       4: invokeinterface #7,  1            // InterfaceMethod java/util/List.isEmpty:()Z
       9: ifeq          22
      12: new           #8                  // class java/util/NoSuchElementException
      15: dup
      16: ldc           #9                  // String There are no elements for this iterator to loop on
      18: invokespecial #10                 // Method java/util/NoSuchElementException."<init>":(Ljava/lang/String;)V
      21: athrow
      22: aload_0
      23: getfield      #11                 // Field iterator:Ljava/util/ListIterator;
      26: invokeinterface #12,  1           // InterfaceMethod java/util/ListIterator.hasNext:()Z
      31: ifne          38
      34: aload_0
      35: invokevirtual #13                 // Method reset:()V
      38: aload_0
      39: getfield      #11                 // Field iterator:Ljava/util/ListIterator;
      42: invokeinterface #14,  1           // InterfaceMethod java/util/ListIterator.next:()Ljava/lang/Object;
      47: areturn

  public int nextIndex();
    Code:
       0: aload_0
       1: getfield      #5                  // Field list:Ljava/util/List;
       4: invokeinterface #7,  1            // InterfaceMethod java/util/List.isEmpty:()Z
       9: ifeq          22
      12: new           #8                  // class java/util/NoSuchElementException
      15: dup
      16: ldc           #9                  // String There are no elements for this iterator to loop on
      18: invokespecial #10                 // Method java/util/NoSuchElementException."<init>":(Ljava/lang/String;)V
      21: athrow
      22: aload_0
      23: getfield      #11                 // Field iterator:Ljava/util/ListIterator;
      26: invokeinterface #12,  1           // InterfaceMethod java/util/ListIterator.hasNext:()Z
      31: ifne          36
      34: iconst_0
      35: ireturn
      36: aload_0
      37: getfield      #11                 // Field iterator:Ljava/util/ListIterator;
      40: invokeinterface #15,  1           // InterfaceMethod java/util/ListIterator.nextIndex:()I
      45: ireturn

  public boolean hasPrevious();
    Code:
       0: aload_0
       1: getfield      #5                  // Field list:Ljava/util/List;
       4: invokeinterface #7,  1            // InterfaceMethod java/util/List.isEmpty:()Z
       9: ifne          16
      12: iconst_1
      13: goto          17
      16: iconst_0
      17: ireturn

  public E previous();
    Code:
       0: aload_0
       1: getfield      #5                  // Field list:Ljava/util/List;
       4: invokeinterface #7,  1            // InterfaceMethod java/util/List.isEmpty:()Z
       9: ifeq          22
      12: new           #8                  // class java/util/NoSuchElementException
      15: dup
      16: ldc           #9                  // String There are no elements for this iterator to loop on
      18: invokespecial #10                 // Method java/util/NoSuchElementException."<init>":(Ljava/lang/String;)V
      21: athrow
      22: aload_0
      23: getfield      #11                 // Field iterator:Ljava/util/ListIterator;
      26: invokeinterface #16,  1           // InterfaceMethod java/util/ListIterator.hasPrevious:()Z
      31: ifne          73
      34: aconst_null
      35: astore_1
      36: aload_0
      37: getfield      #11                 // Field iterator:Ljava/util/ListIterator;
      40: invokeinterface #12,  1           // InterfaceMethod java/util/ListIterator.hasNext:()Z
      45: ifeq          61
      48: aload_0
      49: getfield      #11                 // Field iterator:Ljava/util/ListIterator;
      52: invokeinterface #14,  1           // InterfaceMethod java/util/ListIterator.next:()Ljava/lang/Object;
      57: astore_1
      58: goto          36
      61: aload_0
      62: getfield      #11                 // Field iterator:Ljava/util/ListIterator;
      65: invokeinterface #17,  1           // InterfaceMethod java/util/ListIterator.previous:()Ljava/lang/Object;
      70: pop
      71: aload_1
      72: areturn
      73: aload_0
      74: getfield      #11                 // Field iterator:Ljava/util/ListIterator;
      77: invokeinterface #17,  1           // InterfaceMethod java/util/ListIterator.previous:()Ljava/lang/Object;
      82: areturn

  public int previousIndex();
    Code:
       0: aload_0
       1: getfield      #5                  // Field list:Ljava/util/List;
       4: invokeinterface #7,  1            // InterfaceMethod java/util/List.isEmpty:()Z
       9: ifeq          22
      12: new           #8                  // class java/util/NoSuchElementException
      15: dup
      16: ldc           #9                  // String There are no elements for this iterator to loop on
      18: invokespecial #10                 // Method java/util/NoSuchElementException."<init>":(Ljava/lang/String;)V
      21: athrow
      22: aload_0
      23: getfield      #11                 // Field iterator:Ljava/util/ListIterator;
      26: invokeinterface #16,  1           // InterfaceMethod java/util/ListIterator.hasPrevious:()Z
      31: ifne          46
      34: aload_0
      35: getfield      #5                  // Field list:Ljava/util/List;
      38: invokeinterface #18,  1           // InterfaceMethod java/util/List.size:()I
      43: iconst_1
      44: isub
      45: ireturn
      46: aload_0
      47: getfield      #11                 // Field iterator:Ljava/util/ListIterator;
      50: invokeinterface #19,  1           // InterfaceMethod java/util/ListIterator.previousIndex:()I
      55: ireturn

  public void remove();
    Code:
       0: aload_0
       1: getfield      #11                 // Field iterator:Ljava/util/ListIterator;
       4: invokeinterface #20,  1           // InterfaceMethod java/util/ListIterator.remove:()V
       9: return

  public void add(E);
    Code:
       0: aload_0
       1: getfield      #11                 // Field iterator:Ljava/util/ListIterator;
       4: aload_1
       5: invokeinterface #21,  2           // InterfaceMethod java/util/ListIterator.add:(Ljava/lang/Object;)V
      10: return

  public void set(E);
    Code:
       0: aload_0
       1: getfield      #11                 // Field iterator:Ljava/util/ListIterator;
       4: aload_1
       5: invokeinterface #22,  2           // InterfaceMethod java/util/ListIterator.set:(Ljava/lang/Object;)V
      10: return

  public void reset();
    Code:
       0: aload_0
       1: invokespecial #6                  // Method _reset:()V
       4: return

  private void _reset();
    Code:
       0: aload_0
       1: aload_0
       2: getfield      #5                  // Field list:Ljava/util/List;
       5: invokeinterface #23,  1           // InterfaceMethod java/util/List.listIterator:()Ljava/util/ListIterator;
      10: putfield      #11                 // Field iterator:Ljava/util/ListIterator;
      13: return

  public int size();
    Code:
       0: aload_0
       1: getfield      #5                  // Field list:Ljava/util/List;
       4: invokeinterface #18,  1           // InterfaceMethod java/util/List.size:()I
       9: ireturn
}
