Compiled from "ZippingIterator.java"
public class org.apache.commons.collections4.iterators.ZippingIterator<E> implements java.util.Iterator<E> {
  private final java.util.Iterator<java.util.Iterator<? extends E>> iterators;

  private java.util.Iterator<? extends E> nextIterator;

  private java.util.Iterator<? extends E> lastReturned;

  public org.apache.commons.collections4.iterators.ZippingIterator(java.util.Iterator<? extends E>, java.util.Iterator<? extends E>);
    Code:
       0: aload_0
       1: iconst_2
       2: anewarray     #1                  // class java/util/Iterator
       5: dup
       6: iconst_0
       7: aload_1
       8: aastore
       9: dup
      10: iconst_1
      11: aload_2
      12: aastore
      13: invokespecial #2                  // Method "<init>":([Ljava/util/Iterator;)V
      16: return

  public org.apache.commons.collections4.iterators.ZippingIterator(java.util.Iterator<? extends E>, java.util.Iterator<? extends E>, java.util.Iterator<? extends E>);
    Code:
       0: aload_0
       1: iconst_3
       2: anewarray     #1                  // class java/util/Iterator
       5: dup
       6: iconst_0
       7: aload_1
       8: aastore
       9: dup
      10: iconst_1
      11: aload_2
      12: aastore
      13: dup
      14: iconst_2
      15: aload_3
      16: aastore
      17: invokespecial #2                  // Method "<init>":([Ljava/util/Iterator;)V
      20: return

  public org.apache.commons.collections4.iterators.ZippingIterator(java.util.Iterator<? extends E>...);
    Code:
       0: aload_0
       1: invokespecial #3                  // Method java/lang/Object."<init>":()V
       4: aload_0
       5: aconst_null
       6: putfield      #4                  // Field nextIterator:Ljava/util/Iterator;
       9: aload_0
      10: aconst_null
      11: putfield      #5                  // Field lastReturned:Ljava/util/Iterator;
      14: new           #6                  // class java/util/ArrayList
      17: dup
      18: invokespecial #7                  // Method java/util/ArrayList."<init>":()V
      21: astore_2
      22: aload_1
      23: astore_3
      24: aload_3
      25: arraylength
      26: istore        4
      28: iconst_0
      29: istore        5
      31: iload         5
      33: iload         4
      35: if_icmpge     74
      38: aload_3
      39: iload         5
      41: aaload
      42: astore        6
      44: aload         6
      46: ifnonnull     59
      49: new           #8                  // class java/lang/NullPointerException
      52: dup
      53: ldc           #9                  // String Iterator must not be null.
      55: invokespecial #10                 // Method java/lang/NullPointerException."<init>":(Ljava/lang/String;)V
      58: athrow
      59: aload_2
      60: aload         6
      62: invokeinterface #11,  2           // InterfaceMethod java/util/List.add:(Ljava/lang/Object;)Z
      67: pop
      68: iinc          5, 1
      71: goto          31
      74: aload_0
      75: aload_2
      76: invokestatic  #12                 // Method org/apache/commons/collections4/FluentIterable.of:(Ljava/lang/Iterable;)Lorg/apache/commons/collections4/FluentIterable;
      79: invokevirtual #13                 // Method org/apache/commons/collections4/FluentIterable.loop:()Lorg/apache/commons/collections4/FluentIterable;
      82: invokevirtual #14                 // Method org/apache/commons/collections4/FluentIterable.iterator:()Ljava/util/Iterator;
      85: putfield      #15                 // Field iterators:Ljava/util/Iterator;
      88: return

  public boolean hasNext();
    Code:
       0: aload_0
       1: getfield      #4                  // Field nextIterator:Ljava/util/Iterator;
       4: ifnull        9
       7: iconst_1
       8: ireturn
       9: aload_0
      10: getfield      #15                 // Field iterators:Ljava/util/Iterator;
      13: invokeinterface #16,  1           // InterfaceMethod java/util/Iterator.hasNext:()Z
      18: ifeq          62
      21: aload_0
      22: getfield      #15                 // Field iterators:Ljava/util/Iterator;
      25: invokeinterface #17,  1           // InterfaceMethod java/util/Iterator.next:()Ljava/lang/Object;
      30: checkcast     #1                  // class java/util/Iterator
      33: astore_1
      34: aload_1
      35: invokeinterface #16,  1           // InterfaceMethod java/util/Iterator.hasNext:()Z
      40: ifeq          50
      43: aload_0
      44: aload_1
      45: putfield      #4                  // Field nextIterator:Ljava/util/Iterator;
      48: iconst_1
      49: ireturn
      50: aload_0
      51: getfield      #15                 // Field iterators:Ljava/util/Iterator;
      54: invokeinterface #18,  1           // InterfaceMethod java/util/Iterator.remove:()V
      59: goto          9
      62: iconst_0
      63: ireturn

  public E next() throws java.util.NoSuchElementException;
    Code:
       0: aload_0
       1: invokevirtual #19                 // Method hasNext:()Z
       4: ifne          15
       7: new           #20                 // class java/util/NoSuchElementException
      10: dup
      11: invokespecial #21                 // Method java/util/NoSuchElementException."<init>":()V
      14: athrow
      15: aload_0
      16: getfield      #4                  // Field nextIterator:Ljava/util/Iterator;
      19: invokeinterface #17,  1           // InterfaceMethod java/util/Iterator.next:()Ljava/lang/Object;
      24: astore_1
      25: aload_0
      26: aload_0
      27: getfield      #4                  // Field nextIterator:Ljava/util/Iterator;
      30: putfield      #5                  // Field lastReturned:Ljava/util/Iterator;
      33: aload_0
      34: aconst_null
      35: putfield      #4                  // Field nextIterator:Ljava/util/Iterator;
      38: aload_1
      39: areturn

  public void remove();
    Code:
       0: aload_0
       1: getfield      #5                  // Field lastReturned:Ljava/util/Iterator;
       4: ifnonnull     17
       7: new           #22                 // class java/lang/IllegalStateException
      10: dup
      11: ldc           #23                 // String No value can be removed at present
      13: invokespecial #24                 // Method java/lang/IllegalStateException."<init>":(Ljava/lang/String;)V
      16: athrow
      17: aload_0
      18: getfield      #5                  // Field lastReturned:Ljava/util/Iterator;
      21: invokeinterface #18,  1           // InterfaceMethod java/util/Iterator.remove:()V
      26: aload_0
      27: aconst_null
      28: putfield      #5                  // Field lastReturned:Ljava/util/Iterator;
      31: return
}
