Compiled from "JobListFluentImpl.java"
public class io.fabric8.kubernetes.api.model.batch.JobListFluentImpl$ItemsNestedImpl<N> extends io.fabric8.kubernetes.api.model.batch.JobFluentImpl<io.fabric8.kubernetes.api.model.batch.JobListFluent$ItemsNested<N>> implements io.fabric8.kubernetes.api.model.batch.JobListFluent$ItemsNested<N>, io.fabric8.kubernetes.api.builder.Nested<N> {
  private final io.fabric8.kubernetes.api.model.batch.JobBuilder builder;

  private final int index;

  final io.fabric8.kubernetes.api.model.batch.JobListFluentImpl this$0;

  io.fabric8.kubernetes.api.model.batch.JobListFluentImpl$ItemsNestedImpl(io.fabric8.kubernetes.api.model.batch.JobListFluentImpl, int, io.fabric8.kubernetes.api.model.batch.Job);
    Code:
       0: aload_0
       1: aload_1
       2: putfield      #1                  // Field this$0:Lio/fabric8/kubernetes/api/model/batch/JobListFluentImpl;
       5: aload_0
       6: invokespecial #2                  // Method io/fabric8/kubernetes/api/model/batch/JobFluentImpl."<init>":()V
       9: aload_0
      10: iload_2
      11: putfield      #3                  // Field index:I
      14: aload_0
      15: new           #4                  // class io/fabric8/kubernetes/api/model/batch/JobBuilder
      18: dup
      19: aload_0
      20: aload_3
      21: invokespecial #5                  // Method io/fabric8/kubernetes/api/model/batch/JobBuilder."<init>":(Lio/fabric8/kubernetes/api/model/batch/JobFluent;Lio/fabric8/kubernetes/api/model/batch/Job;)V
      24: putfield      #6                  // Field builder:Lio/fabric8/kubernetes/api/model/batch/JobBuilder;
      27: return

  io.fabric8.kubernetes.api.model.batch.JobListFluentImpl$ItemsNestedImpl(io.fabric8.kubernetes.api.model.batch.JobListFluentImpl);
    Code:
       0: aload_0
       1: aload_1
       2: putfield      #1                  // Field this$0:Lio/fabric8/kubernetes/api/model/batch/JobListFluentImpl;
       5: aload_0
       6: invokespecial #2                  // Method io/fabric8/kubernetes/api/model/batch/JobFluentImpl."<init>":()V
       9: aload_0
      10: iconst_m1
      11: putfield      #3                  // Field index:I
      14: aload_0
      15: new           #4                  // class io/fabric8/kubernetes/api/model/batch/JobBuilder
      18: dup
      19: aload_0
      20: invokespecial #7                  // Method io/fabric8/kubernetes/api/model/batch/JobBuilder."<init>":(Lio/fabric8/kubernetes/api/model/batch/JobFluent;)V
      23: putfield      #6                  // Field builder:Lio/fabric8/kubernetes/api/model/batch/JobBuilder;
      26: return

  public N and();
    Code:
       0: aload_0
       1: getfield      #1                  // Field this$0:Lio/fabric8/kubernetes/api/model/batch/JobListFluentImpl;
       4: aload_0
       5: getfield      #3                  // Field index:I
       8: aload_0
       9: getfield      #6                  // Field builder:Lio/fabric8/kubernetes/api/model/batch/JobBuilder;
      12: invokevirtual #8                  // Method io/fabric8/kubernetes/api/model/batch/JobBuilder.build:()Lio/fabric8/kubernetes/api/model/batch/Job;
      15: invokevirtual #9                  // Method io/fabric8/kubernetes/api/model/batch/JobListFluentImpl.setToItems:(ILio/fabric8/kubernetes/api/model/batch/Job;)Lio/fabric8/kubernetes/api/model/batch/JobListFluent;
      18: areturn

  public N endItem();
    Code:
       0: aload_0
       1: invokevirtual #10                 // Method and:()Ljava/lang/Object;
       4: areturn
}
