Compiled from "BaseDescription.java"
public abstract class org.hamcrest.BaseDescription implements org.hamcrest.Description {
  public org.hamcrest.BaseDescription();
    Code:
       0: aload_0
       1: invokespecial #1                  // Method java/lang/Object."<init>":()V
       4: return

  public org.hamcrest.Description appendText(java.lang.String);
    Code:
       0: aload_0
       1: aload_1
       2: invokevirtual #2                  // Method append:(Ljava/lang/String;)V
       5: aload_0
       6: areturn

  public org.hamcrest.Description appendDescriptionOf(org.hamcrest.SelfDescribing);
    Code:
       0: aload_1
       1: aload_0
       2: invokeinterface #3,  2            // InterfaceMethod org/hamcrest/SelfDescribing.describeTo:(Lorg/hamcrest/Description;)V
       7: aload_0
       8: areturn

  public org.hamcrest.Description appendValue(java.lang.Object);
    Code:
       0: aload_1
       1: ifnonnull     13
       4: aload_0
       5: ldc           #4                  // String null
       7: invokevirtual #2                  // Method append:(Ljava/lang/String;)V
      10: goto          210
      13: aload_1
      14: instanceof    #5                  // class java/lang/String
      17: ifeq          31
      20: aload_0
      21: aload_1
      22: checkcast     #5                  // class java/lang/String
      25: invokespecial #6                  // Method toJavaSyntax:(Ljava/lang/String;)V
      28: goto          210
      31: aload_1
      32: instanceof    #7                  // class java/lang/Character
      35: ifeq          64
      38: aload_0
      39: bipush        34
      41: invokevirtual #8                  // Method append:(C)V
      44: aload_0
      45: aload_1
      46: checkcast     #7                  // class java/lang/Character
      49: invokevirtual #9                  // Method java/lang/Character.charValue:()C
      52: invokespecial #10                 // Method toJavaSyntax:(C)V
      55: aload_0
      56: bipush        34
      58: invokevirtual #8                  // Method append:(C)V
      61: goto          210
      64: aload_1
      65: instanceof    #11                 // class java/lang/Short
      68: ifeq          95
      71: aload_0
      72: bipush        60
      74: invokevirtual #8                  // Method append:(C)V
      77: aload_0
      78: aload_0
      79: aload_1
      80: invokespecial #12                 // Method descriptionOf:(Ljava/lang/Object;)Ljava/lang/String;
      83: invokevirtual #2                  // Method append:(Ljava/lang/String;)V
      86: aload_0
      87: ldc           #13                 // String s>
      89: invokevirtual #2                  // Method append:(Ljava/lang/String;)V
      92: goto          210
      95: aload_1
      96: instanceof    #14                 // class java/lang/Long
      99: ifeq          126
     102: aload_0
     103: bipush        60
     105: invokevirtual #8                  // Method append:(C)V
     108: aload_0
     109: aload_0
     110: aload_1
     111: invokespecial #12                 // Method descriptionOf:(Ljava/lang/Object;)Ljava/lang/String;
     114: invokevirtual #2                  // Method append:(Ljava/lang/String;)V
     117: aload_0
     118: ldc           #15                 // String L>
     120: invokevirtual #2                  // Method append:(Ljava/lang/String;)V
     123: goto          210
     126: aload_1
     127: instanceof    #16                 // class java/lang/Float
     130: ifeq          157
     133: aload_0
     134: bipush        60
     136: invokevirtual #8                  // Method append:(C)V
     139: aload_0
     140: aload_0
     141: aload_1
     142: invokespecial #12                 // Method descriptionOf:(Ljava/lang/Object;)Ljava/lang/String;
     145: invokevirtual #2                  // Method append:(Ljava/lang/String;)V
     148: aload_0
     149: ldc           #17                 // String F>
     151: invokevirtual #2                  // Method append:(Ljava/lang/String;)V
     154: goto          210
     157: aload_1
     158: invokevirtual #18                 // Method java/lang/Object.getClass:()Ljava/lang/Class;
     161: invokevirtual #19                 // Method java/lang/Class.isArray:()Z
     164: ifeq          189
     167: aload_0
     168: ldc           #20                 // String [
     170: ldc           #21                 // String ,
     172: ldc           #22                 // String ]
     174: new           #23                 // class org/hamcrest/internal/ArrayIterator
     177: dup
     178: aload_1
     179: invokespecial #24                 // Method org/hamcrest/internal/ArrayIterator."<init>":(Ljava/lang/Object;)V
     182: invokespecial #25                 // Method appendValueList:(Ljava/lang/String;Ljava/lang/String;Ljava/lang/String;Ljava/util/Iterator;)Lorg/hamcrest/Description;
     185: pop
     186: goto          210
     189: aload_0
     190: bipush        60
     192: invokevirtual #8                  // Method append:(C)V
     195: aload_0
     196: aload_0
     197: aload_1
     198: invokespecial #12                 // Method descriptionOf:(Ljava/lang/Object;)Ljava/lang/String;
     201: invokevirtual #2                  // Method append:(Ljava/lang/String;)V
     204: aload_0
     205: bipush        62
     207: invokevirtual #8                  // Method append:(C)V
     210: aload_0
     211: areturn

  private java.lang.String descriptionOf(java.lang.Object);
    Code:
       0: aload_1
       1: invokestatic  #26                 // Method java/lang/String.valueOf:(Ljava/lang/Object;)Ljava/lang/String;
       4: areturn
       5: astore_2
       6: new           #28                 // class java/lang/StringBuilder
       9: dup
      10: invokespecial #29                 // Method java/lang/StringBuilder."<init>":()V
      13: aload_1
      14: invokevirtual #18                 // Method java/lang/Object.getClass:()Ljava/lang/Class;
      17: invokevirtual #30                 // Method java/lang/Class.getName:()Ljava/lang/String;
      20: invokevirtual #31                 // Method java/lang/StringBuilder.append:(Ljava/lang/String;)Ljava/lang/StringBuilder;
      23: ldc           #32                 // String @
      25: invokevirtual #31                 // Method java/lang/StringBuilder.append:(Ljava/lang/String;)Ljava/lang/StringBuilder;
      28: aload_1
      29: invokevirtual #33                 // Method java/lang/Object.hashCode:()I
      32: invokestatic  #34                 // Method java/lang/Integer.toHexString:(I)Ljava/lang/String;
      35: invokevirtual #31                 // Method java/lang/StringBuilder.append:(Ljava/lang/String;)Ljava/lang/StringBuilder;
      38: invokevirtual #35                 // Method java/lang/StringBuilder.toString:()Ljava/lang/String;
      41: areturn
    Exception table:
       from    to  target type
           0     4     5   Class java/lang/Exception

  public <T> org.hamcrest.Description appendValueList(java.lang.String, java.lang.String, java.lang.String, T...);
    Code:
       0: aload_0
       1: aload_1
       2: aload_2
       3: aload_3
       4: aload         4
       6: invokestatic  #36                 // Method java/util/Arrays.asList:([Ljava/lang/Object;)Ljava/util/List;
       9: invokevirtual #37                 // Method appendValueList:(Ljava/lang/String;Ljava/lang/String;Ljava/lang/String;Ljava/lang/Iterable;)Lorg/hamcrest/Description;
      12: areturn

  public <T> org.hamcrest.Description appendValueList(java.lang.String, java.lang.String, java.lang.String, java.lang.Iterable<T>);
    Code:
       0: aload_0
       1: aload_1
       2: aload_2
       3: aload_3
       4: aload         4
       6: invokeinterface #38,  1           // InterfaceMethod java/lang/Iterable.iterator:()Ljava/util/Iterator;
      11: invokespecial #25                 // Method appendValueList:(Ljava/lang/String;Ljava/lang/String;Ljava/lang/String;Ljava/util/Iterator;)Lorg/hamcrest/Description;
      14: areturn

  private <T> org.hamcrest.Description appendValueList(java.lang.String, java.lang.String, java.lang.String, java.util.Iterator<T>);
    Code:
       0: aload_0
       1: aload_1
       2: aload_2
       3: aload_3
       4: new           #39                 // class org/hamcrest/internal/SelfDescribingValueIterator
       7: dup
       8: aload         4
      10: invokespecial #40                 // Method org/hamcrest/internal/SelfDescribingValueIterator."<init>":(Ljava/util/Iterator;)V
      13: invokespecial #41                 // Method appendList:(Ljava/lang/String;Ljava/lang/String;Ljava/lang/String;Ljava/util/Iterator;)Lorg/hamcrest/Description;
      16: areturn

  public org.hamcrest.Description appendList(java.lang.String, java.lang.String, java.lang.String, java.lang.Iterable<? extends org.hamcrest.SelfDescribing>);
    Code:
       0: aload_0
       1: aload_1
       2: aload_2
       3: aload_3
       4: aload         4
       6: invokeinterface #38,  1           // InterfaceMethod java/lang/Iterable.iterator:()Ljava/util/Iterator;
      11: invokespecial #41                 // Method appendList:(Ljava/lang/String;Ljava/lang/String;Ljava/lang/String;Ljava/util/Iterator;)Lorg/hamcrest/Description;
      14: areturn

  private org.hamcrest.Description appendList(java.lang.String, java.lang.String, java.lang.String, java.util.Iterator<? extends org.hamcrest.SelfDescribing>);
    Code:
       0: iconst_0
       1: istore        5
       3: aload_0
       4: aload_1
       5: invokevirtual #2                  // Method append:(Ljava/lang/String;)V
       8: aload         4
      10: invokeinterface #42,  1           // InterfaceMethod java/util/Iterator.hasNext:()Z
      15: ifeq          49
      18: iload         5
      20: ifeq          28
      23: aload_0
      24: aload_2
      25: invokevirtual #2                  // Method append:(Ljava/lang/String;)V
      28: aload_0
      29: aload         4
      31: invokeinterface #43,  1           // InterfaceMethod java/util/Iterator.next:()Ljava/lang/Object;
      36: checkcast     #44                 // class org/hamcrest/SelfDescribing
      39: invokevirtual #45                 // Method appendDescriptionOf:(Lorg/hamcrest/SelfDescribing;)Lorg/hamcrest/Description;
      42: pop
      43: iconst_1
      44: istore        5
      46: goto          8
      49: aload_0
      50: aload_3
      51: invokevirtual #2                  // Method append:(Ljava/lang/String;)V
      54: aload_0
      55: areturn

  protected void append(java.lang.String);
    Code:
       0: iconst_0
       1: istore_2
       2: iload_2
       3: aload_1
       4: invokevirtual #46                 // Method java/lang/String.length:()I
       7: if_icmpge     25
      10: aload_0
      11: aload_1
      12: iload_2
      13: invokevirtual #47                 // Method java/lang/String.charAt:(I)C
      16: invokevirtual #8                  // Method append:(C)V
      19: iinc          2, 1
      22: goto          2
      25: return

  protected abstract void append(char);

  private void toJavaSyntax(java.lang.String);
    Code:
       0: aload_0
       1: bipush        34
       3: invokevirtual #8                  // Method append:(C)V
       6: iconst_0
       7: istore_2
       8: iload_2
       9: aload_1
      10: invokevirtual #46                 // Method java/lang/String.length:()I
      13: if_icmpge     31
      16: aload_0
      17: aload_1
      18: iload_2
      19: invokevirtual #47                 // Method java/lang/String.charAt:(I)C
      22: invokespecial #10                 // Method toJavaSyntax:(C)V
      25: iinc          2, 1
      28: goto          8
      31: aload_0
      32: bipush        34
      34: invokevirtual #8                  // Method append:(C)V
      37: return

  private void toJavaSyntax(char);
    Code:
       0: iload_1
       1: lookupswitch  { // 4
                     9: 71
                    10: 53
                    13: 62
                    34: 44
               default: 80
          }
      44: aload_0
      45: ldc           #48                 // String \\\"
      47: invokevirtual #2                  // Method append:(Ljava/lang/String;)V
      50: goto          85
      53: aload_0
      54: ldc           #49                 // String \\n
      56: invokevirtual #2                  // Method append:(Ljava/lang/String;)V
      59: goto          85
      62: aload_0
      63: ldc           #50                 // String \\r
      65: invokevirtual #2                  // Method append:(Ljava/lang/String;)V
      68: goto          85
      71: aload_0
      72: ldc           #51                 // String \\t
      74: invokevirtual #2                  // Method append:(Ljava/lang/String;)V
      77: goto          85
      80: aload_0
      81: iload_1
      82: invokevirtual #8                  // Method append:(C)V
      85: return
}
