Compiled from "Condition.java"
final class org.hamcrest.Condition$Matched<T> extends org.hamcrest.Condition<T> {
  private final T theValue;

  private final org.hamcrest.Description mismatch;

  private org.hamcrest.Condition$Matched(T, org.hamcrest.Description);
    Code:
       0: aload_0
       1: aconst_null
       2: invokespecial #2                  // Method org/hamcrest/Condition."<init>":(Lorg/hamcrest/Condition$1;)V
       5: aload_0
       6: aload_1
       7: putfield      #3                  // Field theValue:Ljava/lang/Object;
      10: aload_0
      11: aload_2
      12: putfield      #4                  // Field mismatch:Lorg/hamcrest/Description;
      15: return

  public boolean matching(org.hamcrest.Matcher<T>, java.lang.String);
    Code:
       0: aload_1
       1: aload_0
       2: getfield      #3                  // Field theValue:Ljava/lang/Object;
       5: invokeinterface #5,  2            // InterfaceMethod org/hamcrest/Matcher.matches:(Ljava/lang/Object;)Z
      10: ifeq          15
      13: iconst_1
      14: ireturn
      15: aload_0
      16: getfield      #4                  // Field mismatch:Lorg/hamcrest/Description;
      19: aload_2
      20: invokeinterface #6,  2            // InterfaceMethod org/hamcrest/Description.appendText:(Ljava/lang/String;)Lorg/hamcrest/Description;
      25: pop
      26: aload_1
      27: aload_0
      28: getfield      #3                  // Field theValue:Ljava/lang/Object;
      31: aload_0
      32: getfield      #4                  // Field mismatch:Lorg/hamcrest/Description;
      35: invokeinterface #7,  3            // InterfaceMethod org/hamcrest/Matcher.describeMismatch:(Ljava/lang/Object;Lorg/hamcrest/Description;)V
      40: iconst_0
      41: ireturn

  public <U> org.hamcrest.Condition<U> and(org.hamcrest.Condition$Step<? super T, U>);
    Code:
       0: aload_1
       1: aload_0
       2: getfield      #3                  // Field theValue:Ljava/lang/Object;
       5: aload_0
       6: getfield      #4                  // Field mismatch:Lorg/hamcrest/Description;
       9: invokeinterface #8,  3            // InterfaceMethod org/hamcrest/Condition$Step.apply:(Ljava/lang/Object;Lorg/hamcrest/Description;)Lorg/hamcrest/Condition;
      14: areturn

  org.hamcrest.Condition$Matched(java.lang.Object, org.hamcrest.Description, org.hamcrest.Condition$1);
    Code:
       0: aload_0
       1: aload_1
       2: aload_2
       3: invokespecial #1                  // Method "<init>":(Ljava/lang/Object;Lorg/hamcrest/Description;)V
       6: return
}
