Compiled from "Aes256GcmDecryption.java"
public class org.signal.libsignal.crypto.Aes256GcmDecryption implements org.signal.libsignal.internal.NativeHandleGuard$Owner {
  public static final int TAG_SIZE_IN_BYTES;

  private long unsafeHandle;

  public org.signal.libsignal.crypto.Aes256GcmDecryption(byte[], byte[], byte[]) throws org.signal.libsignal.protocol.InvalidKeyException;
    Code:
       0: aload_0
       1: invokespecial #1                  // Method java/lang/Object."<init>":()V
       4: aload_0
       5: aload_1
       6: aload_2
       7: aload_3
       8: invokestatic  #2                  // Method org/signal/libsignal/internal/Native.Aes256GcmDecryption_New:([B[B[B)J
      11: putfield      #3                  // Field unsafeHandle:J
      14: return

  protected void finalize();
    Code:
       0: aload_0
       1: getfield      #3                  // Field unsafeHandle:J
       4: invokestatic  #4                  // Method org/signal/libsignal/internal/Native.Aes256GcmDecryption_Destroy:(J)V
       7: return

  public long unsafeNativeHandleWithoutGuard();
    Code:
       0: aload_0
       1: getfield      #3                  // Field unsafeHandle:J
       4: lreturn

  public void decrypt(byte[]);
    Code:
       0: new           #5                  // class org/signal/libsignal/internal/NativeHandleGuard
       3: dup
       4: aload_0
       5: invokespecial #6                  // Method org/signal/libsignal/internal/NativeHandleGuard."<init>":(Lorg/signal/libsignal/internal/NativeHandleGuard$Owner;)V
       8: astore_2
       9: aload_2
      10: invokevirtual #7                  // Method org/signal/libsignal/internal/NativeHandleGuard.nativeHandle:()J
      13: aload_1
      14: iconst_0
      15: aload_1
      16: arraylength
      17: invokestatic  #8                  // Method org/signal/libsignal/internal/Native.Aes256GcmDecryption_Update:(J[BII)V
      20: aload_2
      21: invokevirtual #9                  // Method org/signal/libsignal/internal/NativeHandleGuard.close:()V
      24: goto          45
      27: astore_3
      28: aload_2
      29: invokevirtual #9                  // Method org/signal/libsignal/internal/NativeHandleGuard.close:()V
      32: goto          43
      35: astore        4
      37: aload_3
      38: aload         4
      40: invokevirtual #11                 // Method java/lang/Throwable.addSuppressed:(Ljava/lang/Throwable;)V
      43: aload_3
      44: athrow
      45: return
    Exception table:
       from    to  target type
           9    20    27   Class java/lang/Throwable
          28    32    35   Class java/lang/Throwable

  public void decrypt(byte[], int, int);
    Code:
       0: new           #5                  // class org/signal/libsignal/internal/NativeHandleGuard
       3: dup
       4: aload_0
       5: invokespecial #6                  // Method org/signal/libsignal/internal/NativeHandleGuard."<init>":(Lorg/signal/libsignal/internal/NativeHandleGuard$Owner;)V
       8: astore        4
      10: aload         4
      12: invokevirtual #7                  // Method org/signal/libsignal/internal/NativeHandleGuard.nativeHandle:()J
      15: aload_1
      16: iload_2
      17: iload_3
      18: invokestatic  #8                  // Method org/signal/libsignal/internal/Native.Aes256GcmDecryption_Update:(J[BII)V
      21: aload         4
      23: invokevirtual #9                  // Method org/signal/libsignal/internal/NativeHandleGuard.close:()V
      26: goto          51
      29: astore        5
      31: aload         4
      33: invokevirtual #9                  // Method org/signal/libsignal/internal/NativeHandleGuard.close:()V
      36: goto          48
      39: astore        6
      41: aload         5
      43: aload         6
      45: invokevirtual #11                 // Method java/lang/Throwable.addSuppressed:(Ljava/lang/Throwable;)V
      48: aload         5
      50: athrow
      51: return
    Exception table:
       from    to  target type
          10    21    29   Class java/lang/Throwable
          31    36    39   Class java/lang/Throwable

  public boolean verifyTag(byte[]);
    Code:
       0: new           #5                  // class org/signal/libsignal/internal/NativeHandleGuard
       3: dup
       4: aload_0
       5: invokespecial #6                  // Method org/signal/libsignal/internal/NativeHandleGuard."<init>":(Lorg/signal/libsignal/internal/NativeHandleGuard$Owner;)V
       8: astore_2
       9: aload_2
      10: invokevirtual #7                  // Method org/signal/libsignal/internal/NativeHandleGuard.nativeHandle:()J
      13: aload_1
      14: invokestatic  #12                 // Method org/signal/libsignal/internal/Native.Aes256GcmDecryption_VerifyTag:(J[B)Z
      17: istore_3
      18: aload_2
      19: invokevirtual #7                  // Method org/signal/libsignal/internal/NativeHandleGuard.nativeHandle:()J
      22: invokestatic  #4                  // Method org/signal/libsignal/internal/Native.Aes256GcmDecryption_Destroy:(J)V
      25: aload_0
      26: lconst_0
      27: putfield      #3                  // Field unsafeHandle:J
      30: iload_3
      31: istore        4
      33: aload_2
      34: invokevirtual #9                  // Method org/signal/libsignal/internal/NativeHandleGuard.close:()V
      37: iload         4
      39: ireturn
      40: astore_3
      41: aload_2
      42: invokevirtual #9                  // Method org/signal/libsignal/internal/NativeHandleGuard.close:()V
      45: goto          56
      48: astore        4
      50: aload_3
      51: aload         4
      53: invokevirtual #11                 // Method java/lang/Throwable.addSuppressed:(Ljava/lang/Throwable;)V
      56: aload_3
      57: athrow
    Exception table:
       from    to  target type
           9    33    40   Class java/lang/Throwable
          41    45    48   Class java/lang/Throwable
}
