Compiled from "Expression.java"
public final class org.graylog.plugins.pipelineprocessor.ast.expressions.Expression$Type extends java.lang.Enum<org.graylog.plugins.pipelineprocessor.ast.expressions.Expression$Type> {
  public static final org.graylog.plugins.pipelineprocessor.ast.expressions.Expression$Type ADD;

  public static final org.graylog.plugins.pipelineprocessor.ast.expressions.Expression$Type AND;

  public static final org.graylog.plugins.pipelineprocessor.ast.expressions.Expression$Type ARRAY_LITERAL;

  public static final org.graylog.plugins.pipelineprocessor.ast.expressions.Expression$Type BINARY;

  public static final org.graylog.plugins.pipelineprocessor.ast.expressions.Expression$Type BOOLEAN;

  public static final org.graylog.plugins.pipelineprocessor.ast.expressions.Expression$Type BOOLEAN_FUNC_WRAPPER;

  public static final org.graylog.plugins.pipelineprocessor.ast.expressions.Expression$Type COMPARISON;

  public static final org.graylog.plugins.pipelineprocessor.ast.expressions.Expression$Type CONSTANT;

  public static final org.graylog.plugins.pipelineprocessor.ast.expressions.Expression$Type DOUBLE;

  public static final org.graylog.plugins.pipelineprocessor.ast.expressions.Expression$Type EQUALITY;

  public static final org.graylog.plugins.pipelineprocessor.ast.expressions.Expression$Type FIELD_ACCESS;

  public static final org.graylog.plugins.pipelineprocessor.ast.expressions.Expression$Type FIELD_REF;

  public static final org.graylog.plugins.pipelineprocessor.ast.expressions.Expression$Type FUNCTION;

  public static final org.graylog.plugins.pipelineprocessor.ast.expressions.Expression$Type INDEXED_ACCESS;

  public static final org.graylog.plugins.pipelineprocessor.ast.expressions.Expression$Type LOGICAL;

  public static final org.graylog.plugins.pipelineprocessor.ast.expressions.Expression$Type LONG;

  public static final org.graylog.plugins.pipelineprocessor.ast.expressions.Expression$Type MAP_LITERAL;

  public static final org.graylog.plugins.pipelineprocessor.ast.expressions.Expression$Type MESSAGE;

  public static final org.graylog.plugins.pipelineprocessor.ast.expressions.Expression$Type MULT;

  public static final org.graylog.plugins.pipelineprocessor.ast.expressions.Expression$Type NOT;

  public static final org.graylog.plugins.pipelineprocessor.ast.expressions.Expression$Type NUMERIC;

  public static final org.graylog.plugins.pipelineprocessor.ast.expressions.Expression$Type OR;

  public static final org.graylog.plugins.pipelineprocessor.ast.expressions.Expression$Type SIGNED;

  public static final org.graylog.plugins.pipelineprocessor.ast.expressions.Expression$Type STRING;

  public static final org.graylog.plugins.pipelineprocessor.ast.expressions.Expression$Type UNARY;

  public static final org.graylog.plugins.pipelineprocessor.ast.expressions.Expression$Type VAR_REF;

  static java.util.Map<java.lang.Class, org.graylog.plugins.pipelineprocessor.ast.expressions.Expression$Type> classMap;

  private final java.lang.Class<? extends org.graylog.plugins.pipelineprocessor.ast.expressions.Expression> klass;

  private static final org.graylog.plugins.pipelineprocessor.ast.expressions.Expression$Type[] $VALUES;

  public static org.graylog.plugins.pipelineprocessor.ast.expressions.Expression$Type[] values();
    Code:
       0: getstatic     #1                  // Field $VALUES:[Lorg/graylog/plugins/pipelineprocessor/ast/expressions/Expression$Type;
       3: invokevirtual #2                  // Method "[Lorg/graylog/plugins/pipelineprocessor/ast/expressions/Expression$Type;".clone:()Ljava/lang/Object;
       6: checkcast     #3                  // class "[Lorg/graylog/plugins/pipelineprocessor/ast/expressions/Expression$Type;"
       9: areturn

  public static org.graylog.plugins.pipelineprocessor.ast.expressions.Expression$Type valueOf(java.lang.String);
    Code:
       0: ldc           #4                  // class org/graylog/plugins/pipelineprocessor/ast/expressions/Expression$Type
       2: aload_0
       3: invokestatic  #5                  // Method java/lang/Enum.valueOf:(Ljava/lang/Class;Ljava/lang/String;)Ljava/lang/Enum;
       6: checkcast     #4                  // class org/graylog/plugins/pipelineprocessor/ast/expressions/Expression$Type
       9: areturn

  private org.graylog.plugins.pipelineprocessor.ast.expressions.Expression$Type(java.lang.Class<? extends org.graylog.plugins.pipelineprocessor.ast.expressions.Expression>);
    Code:
       0: aload_0
       1: aload_1
       2: iload_2
       3: invokespecial #6                  // Method java/lang/Enum."<init>":(Ljava/lang/String;I)V
       6: aload_0
       7: aload_3
       8: putfield      #7                  // Field klass:Ljava/lang/Class;
      11: return

  static org.graylog.plugins.pipelineprocessor.ast.expressions.Expression$Type fromClass(java.lang.Class);
    Code:
       0: getstatic     #8                  // Field classMap:Ljava/util/Map;
       3: aload_0
       4: invokeinterface #9,  2            // InterfaceMethod java/util/Map.get:(Ljava/lang/Object;)Ljava/lang/Object;
       9: checkcast     #4                  // class org/graylog/plugins/pipelineprocessor/ast/expressions/Expression$Type
      12: areturn

  private static java.lang.Class lambda$static$0(org.graylog.plugins.pipelineprocessor.ast.expressions.Expression$Type);
    Code:
       0: aload_0
       1: getfield      #7                  // Field klass:Ljava/lang/Class;
       4: areturn

  static {};
    Code:
       0: new           #4                  // class org/graylog/plugins/pipelineprocessor/ast/expressions/Expression$Type
       3: dup
       4: ldc           #10                 // String ADD
       6: iconst_0
       7: ldc           #11                 // class org/graylog/plugins/pipelineprocessor/ast/expressions/AdditionExpression
       9: invokespecial #12                 // Method "<init>":(Ljava/lang/String;ILjava/lang/Class;)V
      12: putstatic     #13                 // Field ADD:Lorg/graylog/plugins/pipelineprocessor/ast/expressions/Expression$Type;
      15: new           #4                  // class org/graylog/plugins/pipelineprocessor/ast/expressions/Expression$Type
      18: dup
      19: ldc           #14                 // String AND
      21: iconst_1
      22: ldc           #15                 // class org/graylog/plugins/pipelineprocessor/ast/expressions/AndExpression
      24: invokespecial #12                 // Method "<init>":(Ljava/lang/String;ILjava/lang/Class;)V
      27: putstatic     #16                 // Field AND:Lorg/graylog/plugins/pipelineprocessor/ast/expressions/Expression$Type;
      30: new           #4                  // class org/graylog/plugins/pipelineprocessor/ast/expressions/Expression$Type
      33: dup
      34: ldc           #17                 // String ARRAY_LITERAL
      36: iconst_2
      37: ldc           #18                 // class org/graylog/plugins/pipelineprocessor/ast/expressions/ArrayLiteralExpression
      39: invokespecial #12                 // Method "<init>":(Ljava/lang/String;ILjava/lang/Class;)V
      42: putstatic     #19                 // Field ARRAY_LITERAL:Lorg/graylog/plugins/pipelineprocessor/ast/expressions/Expression$Type;
      45: new           #4                  // class org/graylog/plugins/pipelineprocessor/ast/expressions/Expression$Type
      48: dup
      49: ldc           #20                 // String BINARY
      51: iconst_3
      52: ldc           #21                 // class org/graylog/plugins/pipelineprocessor/ast/expressions/BinaryExpression
      54: invokespecial #12                 // Method "<init>":(Ljava/lang/String;ILjava/lang/Class;)V
      57: putstatic     #22                 // Field BINARY:Lorg/graylog/plugins/pipelineprocessor/ast/expressions/Expression$Type;
      60: new           #4                  // class org/graylog/plugins/pipelineprocessor/ast/expressions/Expression$Type
      63: dup
      64: ldc           #23                 // String BOOLEAN
      66: iconst_4
      67: ldc           #24                 // class org/graylog/plugins/pipelineprocessor/ast/expressions/BooleanExpression
      69: invokespecial #12                 // Method "<init>":(Ljava/lang/String;ILjava/lang/Class;)V
      72: putstatic     #25                 // Field BOOLEAN:Lorg/graylog/plugins/pipelineprocessor/ast/expressions/Expression$Type;
      75: new           #4                  // class org/graylog/plugins/pipelineprocessor/ast/expressions/Expression$Type
      78: dup
      79: ldc           #26                 // String BOOLEAN_FUNC_WRAPPER
      81: iconst_5
      82: ldc           #27                 // class org/graylog/plugins/pipelineprocessor/ast/expressions/BooleanValuedFunctionWrapper
      84: invokespecial #12                 // Method "<init>":(Ljava/lang/String;ILjava/lang/Class;)V
      87: putstatic     #28                 // Field BOOLEAN_FUNC_WRAPPER:Lorg/graylog/plugins/pipelineprocessor/ast/expressions/Expression$Type;
      90: new           #4                  // class org/graylog/plugins/pipelineprocessor/ast/expressions/Expression$Type
      93: dup
      94: ldc           #29                 // String COMPARISON
      96: bipush        6
      98: ldc           #30                 // class org/graylog/plugins/pipelineprocessor/ast/expressions/ComparisonExpression
     100: invokespecial #12                 // Method "<init>":(Ljava/lang/String;ILjava/lang/Class;)V
     103: putstatic     #31                 // Field COMPARISON:Lorg/graylog/plugins/pipelineprocessor/ast/expressions/Expression$Type;
     106: new           #4                  // class org/graylog/plugins/pipelineprocessor/ast/expressions/Expression$Type
     109: dup
     110: ldc           #32                 // String CONSTANT
     112: bipush        7
     114: ldc           #33                 // class org/graylog/plugins/pipelineprocessor/ast/expressions/ConstantExpression
     116: invokespecial #12                 // Method "<init>":(Ljava/lang/String;ILjava/lang/Class;)V
     119: putstatic     #34                 // Field CONSTANT:Lorg/graylog/plugins/pipelineprocessor/ast/expressions/Expression$Type;
     122: new           #4                  // class org/graylog/plugins/pipelineprocessor/ast/expressions/Expression$Type
     125: dup
     126: ldc           #35                 // String DOUBLE
     128: bipush        8
     130: ldc           #36                 // class org/graylog/plugins/pipelineprocessor/ast/expressions/DoubleExpression
     132: invokespecial #12                 // Method "<init>":(Ljava/lang/String;ILjava/lang/Class;)V
     135: putstatic     #37                 // Field DOUBLE:Lorg/graylog/plugins/pipelineprocessor/ast/expressions/Expression$Type;
     138: new           #4                  // class org/graylog/plugins/pipelineprocessor/ast/expressions/Expression$Type
     141: dup
     142: ldc           #38                 // String EQUALITY
     144: bipush        9
     146: ldc           #39                 // class org/graylog/plugins/pipelineprocessor/ast/expressions/EqualityExpression
     148: invokespecial #12                 // Method "<init>":(Ljava/lang/String;ILjava/lang/Class;)V
     151: putstatic     #40                 // Field EQUALITY:Lorg/graylog/plugins/pipelineprocessor/ast/expressions/Expression$Type;
     154: new           #4                  // class org/graylog/plugins/pipelineprocessor/ast/expressions/Expression$Type
     157: dup
     158: ldc           #41                 // String FIELD_ACCESS
     160: bipush        10
     162: ldc           #42                 // class org/graylog/plugins/pipelineprocessor/ast/expressions/FieldAccessExpression
     164: invokespecial #12                 // Method "<init>":(Ljava/lang/String;ILjava/lang/Class;)V
     167: putstatic     #43                 // Field FIELD_ACCESS:Lorg/graylog/plugins/pipelineprocessor/ast/expressions/Expression$Type;
     170: new           #4                  // class org/graylog/plugins/pipelineprocessor/ast/expressions/Expression$Type
     173: dup
     174: ldc           #44                 // String FIELD_REF
     176: bipush        11
     178: ldc           #45                 // class org/graylog/plugins/pipelineprocessor/ast/expressions/FieldRefExpression
     180: invokespecial #12                 // Method "<init>":(Ljava/lang/String;ILjava/lang/Class;)V
     183: putstatic     #46                 // Field FIELD_REF:Lorg/graylog/plugins/pipelineprocessor/ast/expressions/Expression$Type;
     186: new           #4                  // class org/graylog/plugins/pipelineprocessor/ast/expressions/Expression$Type
     189: dup
     190: ldc           #47                 // String FUNCTION
     192: bipush        12
     194: ldc           #48                 // class org/graylog/plugins/pipelineprocessor/ast/expressions/FunctionExpression
     196: invokespecial #12                 // Method "<init>":(Ljava/lang/String;ILjava/lang/Class;)V
     199: putstatic     #49                 // Field FUNCTION:Lorg/graylog/plugins/pipelineprocessor/ast/expressions/Expression$Type;
     202: new           #4                  // class org/graylog/plugins/pipelineprocessor/ast/expressions/Expression$Type
     205: dup
     206: ldc           #50                 // String INDEXED_ACCESS
     208: bipush        13
     210: ldc           #51                 // class org/graylog/plugins/pipelineprocessor/ast/expressions/IndexedAccessExpression
     212: invokespecial #12                 // Method "<init>":(Ljava/lang/String;ILjava/lang/Class;)V
     215: putstatic     #52                 // Field INDEXED_ACCESS:Lorg/graylog/plugins/pipelineprocessor/ast/expressions/Expression$Type;
     218: new           #4                  // class org/graylog/plugins/pipelineprocessor/ast/expressions/Expression$Type
     221: dup
     222: ldc           #53                 // String LOGICAL
     224: bipush        14
     226: ldc           #54                 // class org/graylog/plugins/pipelineprocessor/ast/expressions/LogicalExpression
     228: invokespecial #12                 // Method "<init>":(Ljava/lang/String;ILjava/lang/Class;)V
     231: putstatic     #55                 // Field LOGICAL:Lorg/graylog/plugins/pipelineprocessor/ast/expressions/Expression$Type;
     234: new           #4                  // class org/graylog/plugins/pipelineprocessor/ast/expressions/Expression$Type
     237: dup
     238: ldc           #56                 // String LONG
     240: bipush        15
     242: ldc           #57                 // class org/graylog/plugins/pipelineprocessor/ast/expressions/LongExpression
     244: invokespecial #12                 // Method "<init>":(Ljava/lang/String;ILjava/lang/Class;)V
     247: putstatic     #58                 // Field LONG:Lorg/graylog/plugins/pipelineprocessor/ast/expressions/Expression$Type;
     250: new           #4                  // class org/graylog/plugins/pipelineprocessor/ast/expressions/Expression$Type
     253: dup
     254: ldc           #59                 // String MAP_LITERAL
     256: bipush        16
     258: ldc           #60                 // class org/graylog/plugins/pipelineprocessor/ast/expressions/MapLiteralExpression
     260: invokespecial #12                 // Method "<init>":(Ljava/lang/String;ILjava/lang/Class;)V
     263: putstatic     #61                 // Field MAP_LITERAL:Lorg/graylog/plugins/pipelineprocessor/ast/expressions/Expression$Type;
     266: new           #4                  // class org/graylog/plugins/pipelineprocessor/ast/expressions/Expression$Type
     269: dup
     270: ldc           #62                 // String MESSAGE
     272: bipush        17
     274: ldc           #63                 // class org/graylog/plugins/pipelineprocessor/ast/expressions/MessageRefExpression
     276: invokespecial #12                 // Method "<init>":(Ljava/lang/String;ILjava/lang/Class;)V
     279: putstatic     #64                 // Field MESSAGE:Lorg/graylog/plugins/pipelineprocessor/ast/expressions/Expression$Type;
     282: new           #4                  // class org/graylog/plugins/pipelineprocessor/ast/expressions/Expression$Type
     285: dup
     286: ldc           #65                 // String MULT
     288: bipush        18
     290: ldc           #66                 // class org/graylog/plugins/pipelineprocessor/ast/expressions/MultiplicationExpression
     292: invokespecial #12                 // Method "<init>":(Ljava/lang/String;ILjava/lang/Class;)V
     295: putstatic     #67                 // Field MULT:Lorg/graylog/plugins/pipelineprocessor/ast/expressions/Expression$Type;
     298: new           #4                  // class org/graylog/plugins/pipelineprocessor/ast/expressions/Expression$Type
     301: dup
     302: ldc           #68                 // String NOT
     304: bipush        19
     306: ldc           #69                 // class org/graylog/plugins/pipelineprocessor/ast/expressions/NotExpression
     308: invokespecial #12                 // Method "<init>":(Ljava/lang/String;ILjava/lang/Class;)V
     311: putstatic     #70                 // Field NOT:Lorg/graylog/plugins/pipelineprocessor/ast/expressions/Expression$Type;
     314: new           #4                  // class org/graylog/plugins/pipelineprocessor/ast/expressions/Expression$Type
     317: dup
     318: ldc           #71                 // String NUMERIC
     320: bipush        20
     322: ldc           #72                 // class org/graylog/plugins/pipelineprocessor/ast/expressions/NumericExpression
     324: invokespecial #12                 // Method "<init>":(Ljava/lang/String;ILjava/lang/Class;)V
     327: putstatic     #73                 // Field NUMERIC:Lorg/graylog/plugins/pipelineprocessor/ast/expressions/Expression$Type;
     330: new           #4                  // class org/graylog/plugins/pipelineprocessor/ast/expressions/Expression$Type
     333: dup
     334: ldc           #74                 // String OR
     336: bipush        21
     338: ldc           #75                 // class org/graylog/plugins/pipelineprocessor/ast/expressions/OrExpression
     340: invokespecial #12                 // Method "<init>":(Ljava/lang/String;ILjava/lang/Class;)V
     343: putstatic     #76                 // Field OR:Lorg/graylog/plugins/pipelineprocessor/ast/expressions/Expression$Type;
     346: new           #4                  // class org/graylog/plugins/pipelineprocessor/ast/expressions/Expression$Type
     349: dup
     350: ldc           #77                 // String SIGNED
     352: bipush        22
     354: ldc           #78                 // class org/graylog/plugins/pipelineprocessor/ast/expressions/SignedExpression
     356: invokespecial #12                 // Method "<init>":(Ljava/lang/String;ILjava/lang/Class;)V
     359: putstatic     #79                 // Field SIGNED:Lorg/graylog/plugins/pipelineprocessor/ast/expressions/Expression$Type;
     362: new           #4                  // class org/graylog/plugins/pipelineprocessor/ast/expressions/Expression$Type
     365: dup
     366: ldc           #80                 // String STRING
     368: bipush        23
     370: ldc           #81                 // class org/graylog/plugins/pipelineprocessor/ast/expressions/StringExpression
     372: invokespecial #12                 // Method "<init>":(Ljava/lang/String;ILjava/lang/Class;)V
     375: putstatic     #82                 // Field STRING:Lorg/graylog/plugins/pipelineprocessor/ast/expressions/Expression$Type;
     378: new           #4                  // class org/graylog/plugins/pipelineprocessor/ast/expressions/Expression$Type
     381: dup
     382: ldc           #83                 // String UNARY
     384: bipush        24
     386: ldc           #84                 // class org/graylog/plugins/pipelineprocessor/ast/expressions/UnaryExpression
     388: invokespecial #12                 // Method "<init>":(Ljava/lang/String;ILjava/lang/Class;)V
     391: putstatic     #85                 // Field UNARY:Lorg/graylog/plugins/pipelineprocessor/ast/expressions/Expression$Type;
     394: new           #4                  // class org/graylog/plugins/pipelineprocessor/ast/expressions/Expression$Type
     397: dup
     398: ldc           #86                 // String VAR_REF
     400: bipush        25
     402: ldc           #87                 // class org/graylog/plugins/pipelineprocessor/ast/expressions/VarRefExpression
     404: invokespecial #12                 // Method "<init>":(Ljava/lang/String;ILjava/lang/Class;)V
     407: putstatic     #88                 // Field VAR_REF:Lorg/graylog/plugins/pipelineprocessor/ast/expressions/Expression$Type;
     410: bipush        26
     412: anewarray     #4                  // class org/graylog/plugins/pipelineprocessor/ast/expressions/Expression$Type
     415: dup
     416: iconst_0
     417: getstatic     #13                 // Field ADD:Lorg/graylog/plugins/pipelineprocessor/ast/expressions/Expression$Type;
     420: aastore
     421: dup
     422: iconst_1
     423: getstatic     #16                 // Field AND:Lorg/graylog/plugins/pipelineprocessor/ast/expressions/Expression$Type;
     426: aastore
     427: dup
     428: iconst_2
     429: getstatic     #19                 // Field ARRAY_LITERAL:Lorg/graylog/plugins/pipelineprocessor/ast/expressions/Expression$Type;
     432: aastore
     433: dup
     434: iconst_3
     435: getstatic     #22                 // Field BINARY:Lorg/graylog/plugins/pipelineprocessor/ast/expressions/Expression$Type;
     438: aastore
     439: dup
     440: iconst_4
     441: getstatic     #25                 // Field BOOLEAN:Lorg/graylog/plugins/pipelineprocessor/ast/expressions/Expression$Type;
     444: aastore
     445: dup
     446: iconst_5
     447: getstatic     #28                 // Field BOOLEAN_FUNC_WRAPPER:Lorg/graylog/plugins/pipelineprocessor/ast/expressions/Expression$Type;
     450: aastore
     451: dup
     452: bipush        6
     454: getstatic     #31                 // Field COMPARISON:Lorg/graylog/plugins/pipelineprocessor/ast/expressions/Expression$Type;
     457: aastore
     458: dup
     459: bipush        7
     461: getstatic     #34                 // Field CONSTANT:Lorg/graylog/plugins/pipelineprocessor/ast/expressions/Expression$Type;
     464: aastore
     465: dup
     466: bipush        8
     468: getstatic     #37                 // Field DOUBLE:Lorg/graylog/plugins/pipelineprocessor/ast/expressions/Expression$Type;
     471: aastore
     472: dup
     473: bipush        9
     475: getstatic     #40                 // Field EQUALITY:Lorg/graylog/plugins/pipelineprocessor/ast/expressions/Expression$Type;
     478: aastore
     479: dup
     480: bipush        10
     482: getstatic     #43                 // Field FIELD_ACCESS:Lorg/graylog/plugins/pipelineprocessor/ast/expressions/Expression$Type;
     485: aastore
     486: dup
     487: bipush        11
     489: getstatic     #46                 // Field FIELD_REF:Lorg/graylog/plugins/pipelineprocessor/ast/expressions/Expression$Type;
     492: aastore
     493: dup
     494: bipush        12
     496: getstatic     #49                 // Field FUNCTION:Lorg/graylog/plugins/pipelineprocessor/ast/expressions/Expression$Type;
     499: aastore
     500: dup
     501: bipush        13
     503: getstatic     #52                 // Field INDEXED_ACCESS:Lorg/graylog/plugins/pipelineprocessor/ast/expressions/Expression$Type;
     506: aastore
     507: dup
     508: bipush        14
     510: getstatic     #55                 // Field LOGICAL:Lorg/graylog/plugins/pipelineprocessor/ast/expressions/Expression$Type;
     513: aastore
     514: dup
     515: bipush        15
     517: getstatic     #58                 // Field LONG:Lorg/graylog/plugins/pipelineprocessor/ast/expressions/Expression$Type;
     520: aastore
     521: dup
     522: bipush        16
     524: getstatic     #61                 // Field MAP_LITERAL:Lorg/graylog/plugins/pipelineprocessor/ast/expressions/Expression$Type;
     527: aastore
     528: dup
     529: bipush        17
     531: getstatic     #64                 // Field MESSAGE:Lorg/graylog/plugins/pipelineprocessor/ast/expressions/Expression$Type;
     534: aastore
     535: dup
     536: bipush        18
     538: getstatic     #67                 // Field MULT:Lorg/graylog/plugins/pipelineprocessor/ast/expressions/Expression$Type;
     541: aastore
     542: dup
     543: bipush        19
     545: getstatic     #70                 // Field NOT:Lorg/graylog/plugins/pipelineprocessor/ast/expressions/Expression$Type;
     548: aastore
     549: dup
     550: bipush        20
     552: getstatic     #73                 // Field NUMERIC:Lorg/graylog/plugins/pipelineprocessor/ast/expressions/Expression$Type;
     555: aastore
     556: dup
     557: bipush        21
     559: getstatic     #76                 // Field OR:Lorg/graylog/plugins/pipelineprocessor/ast/expressions/Expression$Type;
     562: aastore
     563: dup
     564: bipush        22
     566: getstatic     #79                 // Field SIGNED:Lorg/graylog/plugins/pipelineprocessor/ast/expressions/Expression$Type;
     569: aastore
     570: dup
     571: bipush        23
     573: getstatic     #82                 // Field STRING:Lorg/graylog/plugins/pipelineprocessor/ast/expressions/Expression$Type;
     576: aastore
     577: dup
     578: bipush        24
     580: getstatic     #85                 // Field UNARY:Lorg/graylog/plugins/pipelineprocessor/ast/expressions/Expression$Type;
     583: aastore
     584: dup
     585: bipush        25
     587: getstatic     #88                 // Field VAR_REF:Lorg/graylog/plugins/pipelineprocessor/ast/expressions/Expression$Type;
     590: aastore
     591: putstatic     #1                  // Field $VALUES:[Lorg/graylog/plugins/pipelineprocessor/ast/expressions/Expression$Type;
     594: invokestatic  #89                 // Method values:()[Lorg/graylog/plugins/pipelineprocessor/ast/expressions/Expression$Type;
     597: invokestatic  #90                 // Method com/google/common/collect/Iterators.forArray:([Ljava/lang/Object;)Lcom/google/common/collect/UnmodifiableIterator;
     600: invokedynamic #91,  0             // InvokeDynamic #0:apply:()Lcom/google/common/base/Function;
     605: invokestatic  #92                 // Method com/google/common/collect/Maps.uniqueIndex:(Ljava/util/Iterator;Lcom/google/common/base/Function;)Lcom/google/common/collect/ImmutableMap;
     608: putstatic     #8                  // Field classMap:Ljava/util/Map;
     611: return
}
