Compiled from "MultiplicationExpression.java"
public class org.graylog.plugins.pipelineprocessor.ast.expressions.MultiplicationExpression extends org.graylog.plugins.pipelineprocessor.ast.expressions.BinaryExpression implements org.graylog.plugins.pipelineprocessor.ast.expressions.NumericExpression {
  private final char operator;

  private java.lang.Class type;

  public org.graylog.plugins.pipelineprocessor.ast.expressions.MultiplicationExpression(org.antlr.v4.runtime.Token, org.graylog.plugins.pipelineprocessor.ast.expressions.Expression, org.graylog.plugins.pipelineprocessor.ast.expressions.Expression, char);
    Code:
       0: aload_0
       1: aload_1
       2: aload_2
       3: aload_3
       4: invokespecial #1                  // Method org/graylog/plugins/pipelineprocessor/ast/expressions/BinaryExpression."<init>":(Lorg/antlr/v4/runtime/Token;Lorg/graylog/plugins/pipelineprocessor/ast/expressions/Expression;Lorg/graylog/plugins/pipelineprocessor/ast/expressions/Expression;)V
       7: aload_0
       8: iload         4
      10: putfield      #2                  // Field operator:C
      13: return

  public boolean isIntegral();
    Code:
       0: aload_0
       1: invokevirtual #3                  // Method getType:()Ljava/lang/Class;
       4: ldc           #4                  // class java/lang/Long
       6: invokevirtual #5                  // Method java/lang/Object.equals:(Ljava/lang/Object;)Z
       9: ireturn

  public long evaluateLong(org.graylog.plugins.pipelineprocessor.EvaluationContext);
    Code:
       0: aload_0
       1: aload_1
       2: invokevirtual #6                  // Method evaluateUnsafe:(Lorg/graylog/plugins/pipelineprocessor/EvaluationContext;)Ljava/lang/Object;
       5: iconst_0
       6: invokestatic  #7                  // Method java/lang/Integer.valueOf:(I)Ljava/lang/Integer;
       9: invokestatic  #8                  // Method com/google/common/base/MoreObjects.firstNonNull:(Ljava/lang/Object;Ljava/lang/Object;)Ljava/lang/Object;
      12: checkcast     #4                  // class java/lang/Long
      15: invokevirtual #9                  // Method java/lang/Long.longValue:()J
      18: lreturn

  public double evaluateDouble(org.graylog.plugins.pipelineprocessor.EvaluationContext);
    Code:
       0: aload_0
       1: aload_1
       2: invokevirtual #6                  // Method evaluateUnsafe:(Lorg/graylog/plugins/pipelineprocessor/EvaluationContext;)Ljava/lang/Object;
       5: dconst_0
       6: invokestatic  #10                 // Method java/lang/Double.valueOf:(D)Ljava/lang/Double;
       9: invokestatic  #8                  // Method com/google/common/base/MoreObjects.firstNonNull:(Ljava/lang/Object;Ljava/lang/Object;)Ljava/lang/Object;
      12: checkcast     #11                 // class java/lang/Double
      15: invokevirtual #12                 // Method java/lang/Double.doubleValue:()D
      18: dreturn

  public java.lang.Object evaluateUnsafe(org.graylog.plugins.pipelineprocessor.EvaluationContext);
    Code:
       0: aload_0
       1: getfield      #13                 // Field left:Lorg/graylog/plugins/pipelineprocessor/ast/expressions/Expression;
       4: aload_1
       5: invokeinterface #14,  2           // InterfaceMethod org/graylog/plugins/pipelineprocessor/ast/expressions/Expression.evaluateUnsafe:(Lorg/graylog/plugins/pipelineprocessor/EvaluationContext;)Ljava/lang/Object;
      10: astore_2
      11: aload_0
      12: getfield      #15                 // Field right:Lorg/graylog/plugins/pipelineprocessor/ast/expressions/Expression;
      15: aload_1
      16: invokeinterface #14,  2           // InterfaceMethod org/graylog/plugins/pipelineprocessor/ast/expressions/Expression.evaluateUnsafe:(Lorg/graylog/plugins/pipelineprocessor/EvaluationContext;)Ljava/lang/Object;
      21: astore_3
      22: aload_0
      23: invokevirtual #16                 // Method isIntegral:()Z
      26: ifeq          121
      29: aload_2
      30: checkcast     #4                  // class java/lang/Long
      33: invokevirtual #9                  // Method java/lang/Long.longValue:()J
      36: lstore        4
      38: aload_3
      39: checkcast     #4                  // class java/lang/Long
      42: invokevirtual #9                  // Method java/lang/Long.longValue:()J
      45: lstore        6
      47: aload_0
      48: getfield      #2                  // Field operator:C
      51: lookupswitch  { // 3
                    37: 102
                    42: 84
                    47: 93
               default: 111
          }
      84: lload         4
      86: lload         6
      88: lmul
      89: invokestatic  #17                 // Method java/lang/Long.valueOf:(J)Ljava/lang/Long;
      92: areturn
      93: lload         4
      95: lload         6
      97: ldiv
      98: invokestatic  #17                 // Method java/lang/Long.valueOf:(J)Ljava/lang/Long;
     101: areturn
     102: lload         4
     104: lload         6
     106: lrem
     107: invokestatic  #17                 // Method java/lang/Long.valueOf:(J)Ljava/lang/Long;
     110: areturn
     111: new           #18                 // class java/lang/IllegalStateException
     114: dup
     115: ldc           #19                 // String Invalid operator, this is a bug.
     117: invokespecial #20                 // Method java/lang/IllegalStateException."<init>":(Ljava/lang/String;)V
     120: athrow
     121: aload_2
     122: checkcast     #11                 // class java/lang/Double
     125: invokevirtual #12                 // Method java/lang/Double.doubleValue:()D
     128: dstore        4
     130: aload_3
     131: checkcast     #11                 // class java/lang/Double
     134: invokevirtual #12                 // Method java/lang/Double.doubleValue:()D
     137: dstore        6
     139: aload_0
     140: getfield      #2                  // Field operator:C
     143: lookupswitch  { // 3
                    37: 194
                    42: 176
                    47: 185
               default: 203
          }
     176: dload         4
     178: dload         6
     180: dmul
     181: invokestatic  #10                 // Method java/lang/Double.valueOf:(D)Ljava/lang/Double;
     184: areturn
     185: dload         4
     187: dload         6
     189: ddiv
     190: invokestatic  #10                 // Method java/lang/Double.valueOf:(D)Ljava/lang/Double;
     193: areturn
     194: dload         4
     196: dload         6
     198: drem
     199: invokestatic  #10                 // Method java/lang/Double.valueOf:(D)Ljava/lang/Double;
     202: areturn
     203: new           #18                 // class java/lang/IllegalStateException
     206: dup
     207: ldc           #19                 // String Invalid operator, this is a bug.
     209: invokespecial #20                 // Method java/lang/IllegalStateException."<init>":(Ljava/lang/String;)V
     212: athrow

  public char getOperator();
    Code:
       0: aload_0
       1: getfield      #2                  // Field operator:C
       4: ireturn

  public java.lang.Class getType();
    Code:
       0: aload_0
       1: getfield      #21                 // Field type:Ljava/lang/Class;
       4: areturn

  public void setType(java.lang.Class);
    Code:
       0: aload_0
       1: aload_1
       2: putfield      #21                 // Field type:Ljava/lang/Class;
       5: return

  public java.lang.String toString();
    Code:
       0: new           #22                 // class java/lang/StringBuilder
       3: dup
       4: invokespecial #23                 // Method java/lang/StringBuilder."<init>":()V
       7: aload_0
       8: getfield      #13                 // Field left:Lorg/graylog/plugins/pipelineprocessor/ast/expressions/Expression;
      11: invokevirtual #24                 // Method java/lang/Object.toString:()Ljava/lang/String;
      14: invokevirtual #25                 // Method java/lang/StringBuilder.append:(Ljava/lang/String;)Ljava/lang/StringBuilder;
      17: ldc           #26                 // String
      19: invokevirtual #25                 // Method java/lang/StringBuilder.append:(Ljava/lang/String;)Ljava/lang/StringBuilder;
      22: aload_0
      23: getfield      #2                  // Field operator:C
      26: invokevirtual #27                 // Method java/lang/StringBuilder.append:(C)Ljava/lang/StringBuilder;
      29: ldc           #26                 // String
      31: invokevirtual #25                 // Method java/lang/StringBuilder.append:(Ljava/lang/String;)Ljava/lang/StringBuilder;
      34: aload_0
      35: getfield      #15                 // Field right:Lorg/graylog/plugins/pipelineprocessor/ast/expressions/Expression;
      38: invokevirtual #24                 // Method java/lang/Object.toString:()Ljava/lang/String;
      41: invokevirtual #25                 // Method java/lang/StringBuilder.append:(Ljava/lang/String;)Ljava/lang/StringBuilder;
      44: invokevirtual #28                 // Method java/lang/StringBuilder.toString:()Ljava/lang/String;
      47: areturn
}
