Compiled from "Constructor.java"
public class org.yaml.snakeyaml.constructor.Constructor$ConstructSequence implements org.yaml.snakeyaml.constructor.Construct {
  final org.yaml.snakeyaml.constructor.Constructor this$0;

  protected org.yaml.snakeyaml.constructor.Constructor$ConstructSequence(org.yaml.snakeyaml.constructor.Constructor);
    Code:
       0: aload_0
       1: aload_1
       2: putfield      #1                  // Field this$0:Lorg/yaml/snakeyaml/constructor/Constructor;
       5: aload_0
       6: invokespecial #2                  // Method java/lang/Object."<init>":()V
       9: return

  public java.lang.Object construct(org.yaml.snakeyaml.nodes.Node);
    Code:
       0: aload_1
       1: checkcast     #3                  // class org/yaml/snakeyaml/nodes/SequenceNode
       4: astore_2
       5: ldc_w         #4                  // class java/util/Set
       8: aload_1
       9: invokevirtual #5                  // Method org/yaml/snakeyaml/nodes/Node.getType:()Ljava/lang/Class;
      12: invokevirtual #6                  // Method java/lang/Class.isAssignableFrom:(Ljava/lang/Class;)Z
      15: ifeq          44
      18: aload_1
      19: invokevirtual #7                  // Method org/yaml/snakeyaml/nodes/Node.isTwoStepsConstruction:()Z
      22: ifeq          35
      25: new           #8                  // class org/yaml/snakeyaml/error/YAMLException
      28: dup
      29: ldc           #9                  // String Set cannot be recursive.
      31: invokespecial #10                 // Method org/yaml/snakeyaml/error/YAMLException."<init>":(Ljava/lang/String;)V
      34: athrow
      35: aload_0
      36: getfield      #1                  // Field this$0:Lorg/yaml/snakeyaml/constructor/Constructor;
      39: aload_2
      40: invokevirtual #11                 // Method org/yaml/snakeyaml/constructor/Constructor.constructSet:(Lorg/yaml/snakeyaml/nodes/SequenceNode;)Ljava/util/Set;
      43: areturn
      44: ldc_w         #12                 // class java/util/Collection
      47: aload_1
      48: invokevirtual #5                  // Method org/yaml/snakeyaml/nodes/Node.getType:()Ljava/lang/Class;
      51: invokevirtual #6                  // Method java/lang/Class.isAssignableFrom:(Ljava/lang/Class;)Z
      54: ifeq          82
      57: aload_1
      58: invokevirtual #7                  // Method org/yaml/snakeyaml/nodes/Node.isTwoStepsConstruction:()Z
      61: ifeq          73
      64: aload_0
      65: getfield      #1                  // Field this$0:Lorg/yaml/snakeyaml/constructor/Constructor;
      68: aload_2
      69: invokevirtual #13                 // Method org/yaml/snakeyaml/constructor/Constructor.newList:(Lorg/yaml/snakeyaml/nodes/SequenceNode;)Ljava/util/List;
      72: areturn
      73: aload_0
      74: getfield      #1                  // Field this$0:Lorg/yaml/snakeyaml/constructor/Constructor;
      77: aload_2
      78: invokevirtual #14                 // Method org/yaml/snakeyaml/constructor/Constructor.constructSequence:(Lorg/yaml/snakeyaml/nodes/SequenceNode;)Ljava/util/List;
      81: areturn
      82: aload_1
      83: invokevirtual #5                  // Method org/yaml/snakeyaml/nodes/Node.getType:()Ljava/lang/Class;
      86: invokevirtual #15                 // Method java/lang/Class.isArray:()Z
      89: ifeq          129
      92: aload_1
      93: invokevirtual #7                  // Method org/yaml/snakeyaml/nodes/Node.isTwoStepsConstruction:()Z
      96: ifeq          120
      99: aload_0
     100: getfield      #1                  // Field this$0:Lorg/yaml/snakeyaml/constructor/Constructor;
     103: aload_1
     104: invokevirtual #5                  // Method org/yaml/snakeyaml/nodes/Node.getType:()Ljava/lang/Class;
     107: aload_2
     108: invokevirtual #16                 // Method org/yaml/snakeyaml/nodes/SequenceNode.getValue:()Ljava/util/List;
     111: invokeinterface #17,  1           // InterfaceMethod java/util/List.size:()I
     116: invokevirtual #18                 // Method org/yaml/snakeyaml/constructor/Constructor.createArray:(Ljava/lang/Class;I)Ljava/lang/Object;
     119: areturn
     120: aload_0
     121: getfield      #1                  // Field this$0:Lorg/yaml/snakeyaml/constructor/Constructor;
     124: aload_2
     125: invokevirtual #19                 // Method org/yaml/snakeyaml/constructor/Constructor.constructArray:(Lorg/yaml/snakeyaml/nodes/SequenceNode;)Ljava/lang/Object;
     128: areturn
     129: new           #20                 // class java/util/ArrayList
     132: dup
     133: aload_2
     134: invokevirtual #16                 // Method org/yaml/snakeyaml/nodes/SequenceNode.getValue:()Ljava/util/List;
     137: invokeinterface #17,  1           // InterfaceMethod java/util/List.size:()I
     142: invokespecial #21                 // Method java/util/ArrayList."<init>":(I)V
     145: astore_3
     146: aload_1
     147: invokevirtual #5                  // Method org/yaml/snakeyaml/nodes/Node.getType:()Ljava/lang/Class;
     150: invokevirtual #22                 // Method java/lang/Class.getDeclaredConstructors:()[Ljava/lang/reflect/Constructor;
     153: astore        4
     155: aload         4
     157: arraylength
     158: istore        5
     160: iconst_0
     161: istore        6
     163: iload         6
     165: iload         5
     167: if_icmpge     210
     170: aload         4
     172: iload         6
     174: aaload
     175: astore        7
     177: aload_2
     178: invokevirtual #16                 // Method org/yaml/snakeyaml/nodes/SequenceNode.getValue:()Ljava/util/List;
     181: invokeinterface #17,  1           // InterfaceMethod java/util/List.size:()I
     186: aload         7
     188: invokevirtual #23                 // Method java/lang/reflect/Constructor.getParameterTypes:()[Ljava/lang/Class;
     191: arraylength
     192: if_icmpne     204
     195: aload_3
     196: aload         7
     198: invokeinterface #24,  2           // InterfaceMethod java/util/List.add:(Ljava/lang/Object;)Z
     203: pop
     204: iinc          6, 1
     207: goto          163
     210: aload_3
     211: invokeinterface #25,  1           // InterfaceMethod java/util/List.isEmpty:()Z
     216: ifne          545
     219: aload_3
     220: invokeinterface #17,  1           // InterfaceMethod java/util/List.size:()I
     225: iconst_1
     226: if_icmpne     354
     229: aload_2
     230: invokevirtual #16                 // Method org/yaml/snakeyaml/nodes/SequenceNode.getValue:()Ljava/util/List;
     233: invokeinterface #17,  1           // InterfaceMethod java/util/List.size:()I
     238: anewarray     #26                 // class java/lang/Object
     241: astore        4
     243: aload_3
     244: iconst_0
     245: invokeinterface #27,  2           // InterfaceMethod java/util/List.get:(I)Ljava/lang/Object;
     250: checkcast     #28                 // class java/lang/reflect/Constructor
     253: astore        5
     255: iconst_0
     256: istore        6
     258: aload_2
     259: invokevirtual #16                 // Method org/yaml/snakeyaml/nodes/SequenceNode.getValue:()Ljava/util/List;
     262: invokeinterface #29,  1           // InterfaceMethod java/util/List.iterator:()Ljava/util/Iterator;
     267: astore        7
     269: aload         7
     271: invokeinterface #30,  1           // InterfaceMethod java/util/Iterator.hasNext:()Z
     276: ifeq          328
     279: aload         7
     281: invokeinterface #31,  1           // InterfaceMethod java/util/Iterator.next:()Ljava/lang/Object;
     286: checkcast     #32                 // class org/yaml/snakeyaml/nodes/Node
     289: astore        8
     291: aload         5
     293: invokevirtual #23                 // Method java/lang/reflect/Constructor.getParameterTypes:()[Ljava/lang/Class;
     296: iload         6
     298: aaload
     299: astore        9
     301: aload         8
     303: aload         9
     305: invokevirtual #33                 // Method org/yaml/snakeyaml/nodes/Node.setType:(Ljava/lang/Class;)V
     308: aload         4
     310: iload         6
     312: iinc          6, 1
     315: aload_0
     316: getfield      #1                  // Field this$0:Lorg/yaml/snakeyaml/constructor/Constructor;
     319: aload         8
     321: invokevirtual #34                 // Method org/yaml/snakeyaml/constructor/Constructor.constructObject:(Lorg/yaml/snakeyaml/nodes/Node;)Ljava/lang/Object;
     324: aastore
     325: goto          269
     328: aload         5
     330: iconst_1
     331: invokevirtual #35                 // Method java/lang/reflect/Constructor.setAccessible:(Z)V
     334: aload         5
     336: aload         4
     338: invokevirtual #36                 // Method java/lang/reflect/Constructor.newInstance:([Ljava/lang/Object;)Ljava/lang/Object;
     341: areturn
     342: astore        7
     344: new           #8                  // class org/yaml/snakeyaml/error/YAMLException
     347: dup
     348: aload         7
     350: invokespecial #38                 // Method org/yaml/snakeyaml/error/YAMLException."<init>":(Ljava/lang/Throwable;)V
     353: athrow
     354: aload_0
     355: getfield      #1                  // Field this$0:Lorg/yaml/snakeyaml/constructor/Constructor;
     358: aload_2
     359: invokevirtual #14                 // Method org/yaml/snakeyaml/constructor/Constructor.constructSequence:(Lorg/yaml/snakeyaml/nodes/SequenceNode;)Ljava/util/List;
     362: astore        4
     364: aload         4
     366: invokeinterface #17,  1           // InterfaceMethod java/util/List.size:()I
     371: anewarray     #39                 // class java/lang/Class
     374: astore        5
     376: iconst_0
     377: istore        6
     379: aload         4
     381: invokeinterface #29,  1           // InterfaceMethod java/util/List.iterator:()Ljava/util/Iterator;
     386: astore        7
     388: aload         7
     390: invokeinterface #30,  1           // InterfaceMethod java/util/Iterator.hasNext:()Z
     395: ifeq          423
     398: aload         7
     400: invokeinterface #31,  1           // InterfaceMethod java/util/Iterator.next:()Ljava/lang/Object;
     405: astore        8
     407: aload         5
     409: iload         6
     411: aload         8
     413: invokevirtual #40                 // Method java/lang/Object.getClass:()Ljava/lang/Class;
     416: aastore
     417: iinc          6, 1
     420: goto          388
     423: aload_3
     424: invokeinterface #29,  1           // InterfaceMethod java/util/List.iterator:()Ljava/util/Iterator;
     429: astore        7
     431: aload         7
     433: invokeinterface #30,  1           // InterfaceMethod java/util/Iterator.hasNext:()Z
     438: ifeq          545
     441: aload         7
     443: invokeinterface #31,  1           // InterfaceMethod java/util/Iterator.next:()Ljava/lang/Object;
     448: checkcast     #28                 // class java/lang/reflect/Constructor
     451: astore        8
     453: aload         8
     455: invokevirtual #23                 // Method java/lang/reflect/Constructor.getParameterTypes:()[Ljava/lang/Class;
     458: astore        9
     460: iconst_1
     461: istore        10
     463: iconst_0
     464: istore        11
     466: iload         11
     468: aload         9
     470: arraylength
     471: if_icmpge     506
     474: aload_0
     475: aload         9
     477: iload         11
     479: aaload
     480: invokespecial #41                 // Method wrapIfPrimitive:(Ljava/lang/Class;)Ljava/lang/Class;
     483: aload         5
     485: iload         11
     487: aaload
     488: invokevirtual #6                  // Method java/lang/Class.isAssignableFrom:(Ljava/lang/Class;)Z
     491: ifne          500
     494: iconst_0
     495: istore        10
     497: goto          506
     500: iinc          11, 1
     503: goto          466
     506: iload         10
     508: ifeq          542
     511: aload         8
     513: iconst_1
     514: invokevirtual #35                 // Method java/lang/reflect/Constructor.setAccessible:(Z)V
     517: aload         8
     519: aload         4
     521: invokeinterface #42,  1           // InterfaceMethod java/util/List.toArray:()[Ljava/lang/Object;
     526: invokevirtual #36                 // Method java/lang/reflect/Constructor.newInstance:([Ljava/lang/Object;)Ljava/lang/Object;
     529: areturn
     530: astore        11
     532: new           #8                  // class org/yaml/snakeyaml/error/YAMLException
     535: dup
     536: aload         11
     538: invokespecial #38                 // Method org/yaml/snakeyaml/error/YAMLException."<init>":(Ljava/lang/Throwable;)V
     541: athrow
     542: goto          431
     545: new           #8                  // class org/yaml/snakeyaml/error/YAMLException
     548: dup
     549: new           #43                 // class java/lang/StringBuilder
     552: dup
     553: invokespecial #44                 // Method java/lang/StringBuilder."<init>":()V
     556: ldc           #45                 // String No suitable constructor with
     558: invokevirtual #46                 // Method java/lang/StringBuilder.append:(Ljava/lang/String;)Ljava/lang/StringBuilder;
     561: aload_2
     562: invokevirtual #16                 // Method org/yaml/snakeyaml/nodes/SequenceNode.getValue:()Ljava/util/List;
     565: invokeinterface #17,  1           // InterfaceMethod java/util/List.size:()I
     570: invokestatic  #47                 // Method java/lang/String.valueOf:(I)Ljava/lang/String;
     573: invokevirtual #46                 // Method java/lang/StringBuilder.append:(Ljava/lang/String;)Ljava/lang/StringBuilder;
     576: ldc           #48                 // String  arguments found for
     578: invokevirtual #46                 // Method java/lang/StringBuilder.append:(Ljava/lang/String;)Ljava/lang/StringBuilder;
     581: aload_1
     582: invokevirtual #5                  // Method org/yaml/snakeyaml/nodes/Node.getType:()Ljava/lang/Class;
     585: invokevirtual #49                 // Method java/lang/StringBuilder.append:(Ljava/lang/Object;)Ljava/lang/StringBuilder;
     588: invokevirtual #50                 // Method java/lang/StringBuilder.toString:()Ljava/lang/String;
     591: invokespecial #10                 // Method org/yaml/snakeyaml/error/YAMLException."<init>":(Ljava/lang/String;)V
     594: athrow
    Exception table:
       from    to  target type
         328   341   342   Class java/lang/Exception
         511   529   530   Class java/lang/Exception

  private final java.lang.Class<? extends java.lang.Object> wrapIfPrimitive(java.lang.Class<?>);
    Code:
       0: aload_1
       1: invokevirtual #51                 // Method java/lang/Class.isPrimitive:()Z
       4: ifne          9
       7: aload_1
       8: areturn
       9: aload_1
      10: getstatic     #52                 // Field java/lang/Integer.TYPE:Ljava/lang/Class;
      13: if_acmpne     20
      16: ldc_w         #53                 // class java/lang/Integer
      19: areturn
      20: aload_1
      21: getstatic     #54                 // Field java/lang/Float.TYPE:Ljava/lang/Class;
      24: if_acmpne     31
      27: ldc_w         #55                 // class java/lang/Float
      30: areturn
      31: aload_1
      32: getstatic     #56                 // Field java/lang/Double.TYPE:Ljava/lang/Class;
      35: if_acmpne     42
      38: ldc_w         #57                 // class java/lang/Double
      41: areturn
      42: aload_1
      43: getstatic     #58                 // Field java/lang/Boolean.TYPE:Ljava/lang/Class;
      46: if_acmpne     53
      49: ldc_w         #59                 // class java/lang/Boolean
      52: areturn
      53: aload_1
      54: getstatic     #60                 // Field java/lang/Long.TYPE:Ljava/lang/Class;
      57: if_acmpne     64
      60: ldc_w         #61                 // class java/lang/Long
      63: areturn
      64: aload_1
      65: getstatic     #62                 // Field java/lang/Character.TYPE:Ljava/lang/Class;
      68: if_acmpne     75
      71: ldc_w         #63                 // class java/lang/Character
      74: areturn
      75: aload_1
      76: getstatic     #64                 // Field java/lang/Short.TYPE:Ljava/lang/Class;
      79: if_acmpne     86
      82: ldc_w         #65                 // class java/lang/Short
      85: areturn
      86: aload_1
      87: getstatic     #66                 // Field java/lang/Byte.TYPE:Ljava/lang/Class;
      90: if_acmpne     97
      93: ldc_w         #67                 // class java/lang/Byte
      96: areturn
      97: new           #8                  // class org/yaml/snakeyaml/error/YAMLException
     100: dup
     101: new           #43                 // class java/lang/StringBuilder
     104: dup
     105: invokespecial #44                 // Method java/lang/StringBuilder."<init>":()V
     108: ldc           #68                 // String Unexpected primitive
     110: invokevirtual #46                 // Method java/lang/StringBuilder.append:(Ljava/lang/String;)Ljava/lang/StringBuilder;
     113: aload_1
     114: invokevirtual #49                 // Method java/lang/StringBuilder.append:(Ljava/lang/Object;)Ljava/lang/StringBuilder;
     117: invokevirtual #50                 // Method java/lang/StringBuilder.toString:()Ljava/lang/String;
     120: invokespecial #10                 // Method org/yaml/snakeyaml/error/YAMLException."<init>":(Ljava/lang/String;)V
     123: athrow

  public void construct2ndStep(org.yaml.snakeyaml.nodes.Node, java.lang.Object);
    Code:
       0: aload_1
       1: checkcast     #3                  // class org/yaml/snakeyaml/nodes/SequenceNode
       4: astore_3
       5: ldc_w         #69                 // class java/util/List
       8: aload_1
       9: invokevirtual #5                  // Method org/yaml/snakeyaml/nodes/Node.getType:()Ljava/lang/Class;
      12: invokevirtual #6                  // Method java/lang/Class.isAssignableFrom:(Ljava/lang/Class;)Z
      15: ifeq          37
      18: aload_2
      19: checkcast     #69                 // class java/util/List
      22: astore        4
      24: aload_0
      25: getfield      #1                  // Field this$0:Lorg/yaml/snakeyaml/constructor/Constructor;
      28: aload_3
      29: aload         4
      31: invokevirtual #70                 // Method org/yaml/snakeyaml/constructor/Constructor.constructSequenceStep2:(Lorg/yaml/snakeyaml/nodes/SequenceNode;Ljava/util/Collection;)V
      34: goto          70
      37: aload_1
      38: invokevirtual #5                  // Method org/yaml/snakeyaml/nodes/Node.getType:()Ljava/lang/Class;
      41: invokevirtual #15                 // Method java/lang/Class.isArray:()Z
      44: ifeq          60
      47: aload_0
      48: getfield      #1                  // Field this$0:Lorg/yaml/snakeyaml/constructor/Constructor;
      51: aload_3
      52: aload_2
      53: invokevirtual #71                 // Method org/yaml/snakeyaml/constructor/Constructor.constructArrayStep2:(Lorg/yaml/snakeyaml/nodes/SequenceNode;Ljava/lang/Object;)Ljava/lang/Object;
      56: pop
      57: goto          70
      60: new           #8                  // class org/yaml/snakeyaml/error/YAMLException
      63: dup
      64: ldc           #72                 // String Immutable objects cannot be recursive.
      66: invokespecial #10                 // Method org/yaml/snakeyaml/error/YAMLException."<init>":(Ljava/lang/String;)V
      69: athrow
      70: return
}
