Compiled from "HttpContextLifecycle.java"
public class org.jboss.weld.servlet.HttpContextLifecycle implements org.jboss.weld.bootstrap.api.Service {
  public static final java.lang.String ASYNC_STARTED_ATTR_NAME;

  private static final java.lang.String HTTP_SESSION;

  private static final java.lang.String INCLUDE_HEADER;

  private static final java.lang.String FORWARD_HEADER;

  private static final java.lang.String REQUEST_DESTROYED;

  private static final java.lang.String GUARD_PARAMETER_NAME;

  private static final java.lang.Object GUARD_PARAMETER_VALUE;

  private org.jboss.weld.context.http.HttpSessionDestructionContext sessionDestructionContextCache;

  private org.jboss.weld.context.http.HttpSessionContext sessionContextCache;

  private org.jboss.weld.context.http.HttpRequestContext requestContextCache;

  private volatile java.lang.Boolean conversationActivationEnabled;

  private final boolean ignoreForwards;

  private final boolean ignoreIncludes;

  private final org.jboss.weld.manager.BeanManagerImpl beanManager;

  private final org.jboss.weld.servlet.ConversationContextActivator conversationContextActivator;

  private final org.jboss.weld.servlet.spi.HttpContextActivationFilter contextActivationFilter;

  private final org.jboss.weld.event.FastEvent<javax.servlet.http.HttpServletRequest> requestInitializedEvent;

  private final org.jboss.weld.event.FastEvent<javax.servlet.http.HttpServletRequest> requestDestroyedEvent;

  private final org.jboss.weld.event.FastEvent<javax.servlet.http.HttpSession> sessionInitializedEvent;

  private final org.jboss.weld.event.FastEvent<javax.servlet.http.HttpSession> sessionDestroyedEvent;

  private final org.jboss.weld.servlet.ServletApiAbstraction servletApi;

  private final org.jboss.weld.servlet.ServletContextService servletContextService;

  private final org.jboss.weld.Container container;

  private final org.jboss.weld.bootstrap.BeanDeploymentModule module;

  private static final java.lang.ThreadLocal<org.jboss.weld.servlet.HttpContextLifecycle$Counter> nestedInvocationGuard;

  private final boolean nestedInvocationGuardEnabled;

  public org.jboss.weld.servlet.HttpContextLifecycle(org.jboss.weld.manager.BeanManagerImpl, org.jboss.weld.servlet.spi.HttpContextActivationFilter, boolean, boolean, boolean, boolean);
    Code:
       0: aload_0
       1: invokespecial #1                  // Method java/lang/Object."<init>":()V
       4: aload_0
       5: aload_1
       6: putfield      #2                  // Field beanManager:Lorg/jboss/weld/manager/BeanManagerImpl;
       9: aload_0
      10: new           #3                  // class org/jboss/weld/servlet/ConversationContextActivator
      13: dup
      14: aload_1
      15: iload         5
      17: invokespecial #4                  // Method org/jboss/weld/servlet/ConversationContextActivator."<init>":(Lorg/jboss/weld/manager/BeanManagerImpl;Z)V
      20: putfield      #5                  // Field conversationContextActivator:Lorg/jboss/weld/servlet/ConversationContextActivator;
      23: aload_0
      24: aconst_null
      25: putfield      #6                  // Field conversationActivationEnabled:Ljava/lang/Boolean;
      28: aload_0
      29: iload_3
      30: putfield      #7                  // Field ignoreForwards:Z
      33: aload_0
      34: iload         4
      36: putfield      #8                  // Field ignoreIncludes:Z
      39: aload_0
      40: aload_2
      41: putfield      #9                  // Field contextActivationFilter:Lorg/jboss/weld/servlet/spi/HttpContextActivationFilter;
      44: aload_0
      45: ldc           #10                 // class javax/servlet/http/HttpServletRequest
      47: aload_1
      48: iconst_1
      49: anewarray     #11                 // class java/lang/annotation/Annotation
      52: dup
      53: iconst_0
      54: getstatic     #12                 // Field org/jboss/weld/literal/InitializedLiteral.REQUEST:Lorg/jboss/weld/literal/InitializedLiteral;
      57: aastore
      58: invokestatic  #13                 // Method org/jboss/weld/event/FastEvent.of:(Ljava/lang/Class;Lorg/jboss/weld/manager/BeanManagerImpl;[Ljava/lang/annotation/Annotation;)Lorg/jboss/weld/event/FastEvent;
      61: putfield      #14                 // Field requestInitializedEvent:Lorg/jboss/weld/event/FastEvent;
      64: aload_0
      65: ldc           #10                 // class javax/servlet/http/HttpServletRequest
      67: aload_1
      68: iconst_1
      69: anewarray     #11                 // class java/lang/annotation/Annotation
      72: dup
      73: iconst_0
      74: getstatic     #15                 // Field org/jboss/weld/literal/DestroyedLiteral.REQUEST:Lorg/jboss/weld/literal/DestroyedLiteral;
      77: aastore
      78: invokestatic  #13                 // Method org/jboss/weld/event/FastEvent.of:(Ljava/lang/Class;Lorg/jboss/weld/manager/BeanManagerImpl;[Ljava/lang/annotation/Annotation;)Lorg/jboss/weld/event/FastEvent;
      81: putfield      #16                 // Field requestDestroyedEvent:Lorg/jboss/weld/event/FastEvent;
      84: aload_0
      85: ldc           #17                 // class javax/servlet/http/HttpSession
      87: aload_1
      88: iconst_1
      89: anewarray     #11                 // class java/lang/annotation/Annotation
      92: dup
      93: iconst_0
      94: getstatic     #18                 // Field org/jboss/weld/literal/InitializedLiteral.SESSION:Lorg/jboss/weld/literal/InitializedLiteral;
      97: aastore
      98: invokestatic  #13                 // Method org/jboss/weld/event/FastEvent.of:(Ljava/lang/Class;Lorg/jboss/weld/manager/BeanManagerImpl;[Ljava/lang/annotation/Annotation;)Lorg/jboss/weld/event/FastEvent;
     101: putfield      #19                 // Field sessionInitializedEvent:Lorg/jboss/weld/event/FastEvent;
     104: aload_0
     105: ldc           #17                 // class javax/servlet/http/HttpSession
     107: aload_1
     108: iconst_1
     109: anewarray     #11                 // class java/lang/annotation/Annotation
     112: dup
     113: iconst_0
     114: getstatic     #20                 // Field org/jboss/weld/literal/DestroyedLiteral.SESSION:Lorg/jboss/weld/literal/DestroyedLiteral;
     117: aastore
     118: invokestatic  #13                 // Method org/jboss/weld/event/FastEvent.of:(Ljava/lang/Class;Lorg/jboss/weld/manager/BeanManagerImpl;[Ljava/lang/annotation/Annotation;)Lorg/jboss/weld/event/FastEvent;
     121: putfield      #21                 // Field sessionDestroyedEvent:Lorg/jboss/weld/event/FastEvent;
     124: aload_0
     125: aload_1
     126: invokevirtual #22                 // Method org/jboss/weld/manager/BeanManagerImpl.getServices:()Lorg/jboss/weld/bootstrap/api/ServiceRegistry;
     129: ldc           #23                 // class org/jboss/weld/servlet/ServletApiAbstraction
     131: invokeinterface #24,  2           // InterfaceMethod org/jboss/weld/bootstrap/api/ServiceRegistry.get:(Ljava/lang/Class;)Lorg/jboss/weld/bootstrap/api/Service;
     136: checkcast     #23                 // class org/jboss/weld/servlet/ServletApiAbstraction
     139: putfield      #25                 // Field servletApi:Lorg/jboss/weld/servlet/ServletApiAbstraction;
     142: aload_0
     143: aload_1
     144: invokevirtual #22                 // Method org/jboss/weld/manager/BeanManagerImpl.getServices:()Lorg/jboss/weld/bootstrap/api/ServiceRegistry;
     147: ldc           #26                 // class org/jboss/weld/servlet/ServletContextService
     149: invokeinterface #24,  2           // InterfaceMethod org/jboss/weld/bootstrap/api/ServiceRegistry.get:(Ljava/lang/Class;)Lorg/jboss/weld/bootstrap/api/Service;
     154: checkcast     #26                 // class org/jboss/weld/servlet/ServletContextService
     157: putfield      #27                 // Field servletContextService:Lorg/jboss/weld/servlet/ServletContextService;
     160: aload_0
     161: iload         6
     163: putfield      #28                 // Field nestedInvocationGuardEnabled:Z
     166: aload_0
     167: aload_1
     168: invokestatic  #29                 // Method org/jboss/weld/Container.instance:(Lorg/jboss/weld/manager/BeanManagerImpl;)Lorg/jboss/weld/Container;
     171: putfield      #30                 // Field container:Lorg/jboss/weld/Container;
     174: aload_0
     175: aload_1
     176: invokevirtual #22                 // Method org/jboss/weld/manager/BeanManagerImpl.getServices:()Lorg/jboss/weld/bootstrap/api/ServiceRegistry;
     179: ldc           #31                 // class org/jboss/weld/bootstrap/BeanDeploymentModules
     181: invokeinterface #24,  2           // InterfaceMethod org/jboss/weld/bootstrap/api/ServiceRegistry.get:(Ljava/lang/Class;)Lorg/jboss/weld/bootstrap/api/Service;
     186: checkcast     #31                 // class org/jboss/weld/bootstrap/BeanDeploymentModules
     189: aload_1
     190: invokevirtual #32                 // Method org/jboss/weld/bootstrap/BeanDeploymentModules.getModule:(Lorg/jboss/weld/manager/BeanManagerImpl;)Lorg/jboss/weld/bootstrap/BeanDeploymentModule;
     193: putfield      #33                 // Field module:Lorg/jboss/weld/bootstrap/BeanDeploymentModule;
     196: return

  private org.jboss.weld.context.http.HttpSessionDestructionContext getSessionDestructionContext();
    Code:
       0: aload_0
       1: getfield      #34                 // Field sessionDestructionContextCache:Lorg/jboss/weld/context/http/HttpSessionDestructionContext;
       4: ifnonnull     37
       7: aload_0
       8: aload_0
       9: getfield      #2                  // Field beanManager:Lorg/jboss/weld/manager/BeanManagerImpl;
      12: invokevirtual #35                 // Method org/jboss/weld/manager/BeanManagerImpl.instance:()Ljavax/enterprise/inject/Instance;
      15: ldc           #36                 // class org/jboss/weld/context/http/HttpSessionDestructionContext
      17: iconst_0
      18: anewarray     #11                 // class java/lang/annotation/Annotation
      21: invokeinterface #37,  3           // InterfaceMethod javax/enterprise/inject/Instance.select:(Ljava/lang/Class;[Ljava/lang/annotation/Annotation;)Ljavax/enterprise/inject/Instance;
      26: invokeinterface #38,  1           // InterfaceMethod javax/enterprise/inject/Instance.get:()Ljava/lang/Object;
      31: checkcast     #36                 // class org/jboss/weld/context/http/HttpSessionDestructionContext
      34: putfield      #34                 // Field sessionDestructionContextCache:Lorg/jboss/weld/context/http/HttpSessionDestructionContext;
      37: aload_0
      38: getfield      #34                 // Field sessionDestructionContextCache:Lorg/jboss/weld/context/http/HttpSessionDestructionContext;
      41: areturn

  private org.jboss.weld.context.http.HttpSessionContext getSessionContext();
    Code:
       0: aload_0
       1: getfield      #39                 // Field sessionContextCache:Lorg/jboss/weld/context/http/HttpSessionContext;
       4: ifnonnull     37
       7: aload_0
       8: aload_0
       9: getfield      #2                  // Field beanManager:Lorg/jboss/weld/manager/BeanManagerImpl;
      12: invokevirtual #35                 // Method org/jboss/weld/manager/BeanManagerImpl.instance:()Ljavax/enterprise/inject/Instance;
      15: ldc           #40                 // class org/jboss/weld/context/http/HttpSessionContext
      17: iconst_0
      18: anewarray     #11                 // class java/lang/annotation/Annotation
      21: invokeinterface #37,  3           // InterfaceMethod javax/enterprise/inject/Instance.select:(Ljava/lang/Class;[Ljava/lang/annotation/Annotation;)Ljavax/enterprise/inject/Instance;
      26: invokeinterface #38,  1           // InterfaceMethod javax/enterprise/inject/Instance.get:()Ljava/lang/Object;
      31: checkcast     #40                 // class org/jboss/weld/context/http/HttpSessionContext
      34: putfield      #39                 // Field sessionContextCache:Lorg/jboss/weld/context/http/HttpSessionContext;
      37: aload_0
      38: getfield      #39                 // Field sessionContextCache:Lorg/jboss/weld/context/http/HttpSessionContext;
      41: areturn

  public org.jboss.weld.context.http.HttpRequestContext getRequestContext();
    Code:
       0: aload_0
       1: getfield      #41                 // Field requestContextCache:Lorg/jboss/weld/context/http/HttpRequestContext;
       4: ifnonnull     37
       7: aload_0
       8: aload_0
       9: getfield      #2                  // Field beanManager:Lorg/jboss/weld/manager/BeanManagerImpl;
      12: invokevirtual #35                 // Method org/jboss/weld/manager/BeanManagerImpl.instance:()Ljavax/enterprise/inject/Instance;
      15: ldc           #42                 // class org/jboss/weld/context/http/HttpRequestContext
      17: iconst_0
      18: anewarray     #11                 // class java/lang/annotation/Annotation
      21: invokeinterface #37,  3           // InterfaceMethod javax/enterprise/inject/Instance.select:(Ljava/lang/Class;[Ljava/lang/annotation/Annotation;)Ljavax/enterprise/inject/Instance;
      26: invokeinterface #38,  1           // InterfaceMethod javax/enterprise/inject/Instance.get:()Ljava/lang/Object;
      31: checkcast     #42                 // class org/jboss/weld/context/http/HttpRequestContext
      34: putfield      #41                 // Field requestContextCache:Lorg/jboss/weld/context/http/HttpRequestContext;
      37: aload_0
      38: getfield      #41                 // Field requestContextCache:Lorg/jboss/weld/context/http/HttpRequestContext;
      41: areturn

  public void contextInitialized(javax.servlet.ServletContext);
    Code:
       0: aload_0
       1: getfield      #27                 // Field servletContextService:Lorg/jboss/weld/servlet/ServletContextService;
       4: aload_1
       5: invokevirtual #43                 // Method org/jboss/weld/servlet/ServletContextService.contextInitialized:(Ljavax/servlet/ServletContext;)V
       8: aload_0
       9: getfield      #30                 // Field container:Lorg/jboss/weld/Container;
      12: dup
      13: astore_2
      14: monitorenter
      15: aload_0
      16: aload_1
      17: getstatic     #44                 // Field org/jboss/weld/literal/InitializedLiteral.APPLICATION:Lorg/jboss/weld/literal/InitializedLiteral;
      20: invokespecial #45                 // Method fireEventForApplicationScope:(Ljavax/servlet/ServletContext;Ljava/lang/annotation/Annotation;)V
      23: aload_2
      24: monitorexit
      25: goto          33
      28: astore_3
      29: aload_2
      30: monitorexit
      31: aload_3
      32: athrow
      33: return
    Exception table:
       from    to  target type
          15    25    28   any
          28    31    28   any

  public void contextDestroyed(javax.servlet.ServletContext);
    Code:
       0: aload_0
       1: getfield      #30                 // Field container:Lorg/jboss/weld/Container;
       4: dup
       5: astore_2
       6: monitorenter
       7: aload_0
       8: aload_1
       9: getstatic     #46                 // Field org/jboss/weld/literal/DestroyedLiteral.APPLICATION:Lorg/jboss/weld/literal/DestroyedLiteral;
      12: invokespecial #45                 // Method fireEventForApplicationScope:(Ljavax/servlet/ServletContext;Ljava/lang/annotation/Annotation;)V
      15: aload_2
      16: monitorexit
      17: goto          25
      20: astore_3
      21: aload_2
      22: monitorexit
      23: aload_3
      24: athrow
      25: return
    Exception table:
       from    to  target type
           7    17    20   any
          20    23    20   any

  private void fireEventForApplicationScope(javax.servlet.ServletContext, java.lang.annotation.Annotation);
    Code:
       0: aload_0
       1: getfield      #33                 // Field module:Lorg/jboss/weld/bootstrap/BeanDeploymentModule;
       4: invokevirtual #47                 // Method org/jboss/weld/bootstrap/BeanDeploymentModule.isWebModule:()Z
       7: ifeq          31
      10: aload_0
      11: getfield      #33                 // Field module:Lorg/jboss/weld/bootstrap/BeanDeploymentModule;
      14: ldc           #48                 // class javax/servlet/ServletContext
      16: aload_1
      17: iconst_1
      18: anewarray     #11                 // class java/lang/annotation/Annotation
      21: dup
      22: iconst_0
      23: aload_2
      24: aastore
      25: invokevirtual #49                 // Method org/jboss/weld/bootstrap/BeanDeploymentModule.fireEvent:(Ljava/lang/reflect/Type;Ljava/lang/Object;[Ljava/lang/annotation/Annotation;)V
      28: goto          68
      31: new           #50                 // class org/jboss/weld/event/EventMetadataImpl
      34: dup
      35: ldc           #48                 // class javax/servlet/ServletContext
      37: aconst_null
      38: aload_2
      39: invokestatic  #51                 // Method java/util/Collections.singleton:(Ljava/lang/Object;)Ljava/util/Set;
      42: invokespecial #52                 // Method org/jboss/weld/event/EventMetadataImpl."<init>":(Ljava/lang/reflect/Type;Ljavax/enterprise/inject/spi/InjectionPoint;Ljava/util/Set;)V
      45: astore_3
      46: aload_0
      47: getfield      #2                  // Field beanManager:Lorg/jboss/weld/manager/BeanManagerImpl;
      50: invokevirtual #53                 // Method org/jboss/weld/manager/BeanManagerImpl.getAccessibleLenientObserverNotifier:()Lorg/jboss/weld/event/ObserverNotifier;
      53: ldc           #48                 // class javax/servlet/ServletContext
      55: aload_1
      56: aload_3
      57: iconst_1
      58: anewarray     #11                 // class java/lang/annotation/Annotation
      61: dup
      62: iconst_0
      63: aload_2
      64: aastore
      65: invokevirtual #54                 // Method org/jboss/weld/event/ObserverNotifier.fireEvent:(Ljava/lang/reflect/Type;Ljava/lang/Object;Ljavax/enterprise/inject/spi/EventMetadata;[Ljava/lang/annotation/Annotation;)V
      68: return

  public void sessionCreated(javax.servlet.http.HttpSession);
    Code:
       0: aload_1
       1: invokestatic  #55                 // Method org/jboss/weld/servlet/SessionHolder.sessionCreated:(Ljavax/servlet/http/HttpSession;)V
       4: aload_0
       5: getfield      #5                  // Field conversationContextActivator:Lorg/jboss/weld/servlet/ConversationContextActivator;
       8: aload_1
       9: invokevirtual #56                 // Method org/jboss/weld/servlet/ConversationContextActivator.sessionCreated:(Ljavax/servlet/http/HttpSession;)V
      12: aload_0
      13: getfield      #19                 // Field sessionInitializedEvent:Lorg/jboss/weld/event/FastEvent;
      16: aload_1
      17: invokevirtual #57                 // Method org/jboss/weld/event/FastEvent.fire:(Ljava/lang/Object;)V
      20: return

  public void sessionDestroyed(javax.servlet.http.HttpSession);
    Code:
       0: aload_0
       1: aload_1
       2: invokespecial #58                 // Method deactivateSessionDestructionContext:(Ljavax/servlet/http/HttpSession;)V
       5: aload_0
       6: invokespecial #59                 // Method getSessionContext:()Lorg/jboss/weld/context/http/HttpSessionContext;
       9: aload_1
      10: invokeinterface #60,  2           // InterfaceMethod org/jboss/weld/context/http/HttpSessionContext.destroy:(Ljavax/servlet/http/HttpSession;)Z
      15: istore_2
      16: invokestatic  #61                 // Method org/jboss/weld/servlet/SessionHolder.clear:()V
      19: invokestatic  #62                 // Method org/jboss/weld/context/cache/RequestScopedCache.endRequest:()V
      22: iload_2
      23: ifeq          37
      26: aload_0
      27: getfield      #21                 // Field sessionDestroyedEvent:Lorg/jboss/weld/event/FastEvent;
      30: aload_1
      31: invokevirtual #57                 // Method org/jboss/weld/event/FastEvent.fire:(Ljava/lang/Object;)V
      34: goto          71
      37: aload_0
      38: invokevirtual #63                 // Method getRequestContext:()Lorg/jboss/weld/context/http/HttpRequestContext;
      41: instanceof    #64                 // class org/jboss/weld/context/http/HttpRequestContextImpl
      44: ifeq          71
      47: aload_0
      48: invokevirtual #63                 // Method getRequestContext:()Lorg/jboss/weld/context/http/HttpRequestContext;
      51: invokestatic  #65                 // Method org/jboss/weld/util/reflection/Reflections.cast:(Ljava/lang/Object;)Ljava/lang/Object;
      54: checkcast     #64                 // class org/jboss/weld/context/http/HttpRequestContextImpl
      57: invokevirtual #66                 // Method org/jboss/weld/context/http/HttpRequestContextImpl.getHttpServletRequest:()Ljavax/servlet/http/HttpServletRequest;
      60: astore_3
      61: aload_3
      62: getstatic     #67                 // Field HTTP_SESSION:Ljava/lang/String;
      65: aload_1
      66: invokeinterface #68,  3           // InterfaceMethod javax/servlet/http/HttpServletRequest.setAttribute:(Ljava/lang/String;Ljava/lang/Object;)V
      71: return

  private void deactivateSessionDestructionContext(javax.servlet.http.HttpSession);
    Code:
       0: aload_0
       1: invokespecial #69                 // Method getSessionDestructionContext:()Lorg/jboss/weld/context/http/HttpSessionDestructionContext;
       4: astore_2
       5: aload_2
       6: invokevirtual #70                 // Method org/jboss/weld/context/http/HttpSessionDestructionContext.isActive:()Z
       9: ifeq          22
      12: aload_2
      13: invokevirtual #71                 // Method org/jboss/weld/context/http/HttpSessionDestructionContext.deactivate:()V
      16: aload_2
      17: aload_1
      18: invokevirtual #72                 // Method org/jboss/weld/context/http/HttpSessionDestructionContext.dissociate:(Ljava/lang/Object;)Z
      21: pop
      22: return

  public void requestInitialized(javax.servlet.http.HttpServletRequest, javax.servlet.ServletContext);
    Code:
       0: aload_0
       1: getfield      #28                 // Field nestedInvocationGuardEnabled:Z
       4: ifeq          88
       7: getstatic     #73                 // Field nestedInvocationGuard:Ljava/lang/ThreadLocal;
      10: invokevirtual #74                 // Method java/lang/ThreadLocal.get:()Ljava/lang/Object;
      13: checkcast     #75                 // class org/jboss/weld/servlet/HttpContextLifecycle$Counter
      16: astore_3
      17: aload_1
      18: ldc           #77                 // String org.jboss.weld.context.ignore.guard.marker
      20: invokeinterface #78,  2           // InterfaceMethod javax/servlet/http/HttpServletRequest.getAttribute:(Ljava/lang/String;)Ljava/lang/Object;
      25: astore        4
      27: aload_3
      28: ifnull        42
      31: aload         4
      33: ifnull        42
      36: aload_3
      37: invokestatic  #79                 // Method org/jboss/weld/servlet/HttpContextLifecycle$Counter.access$008:(Lorg/jboss/weld/servlet/HttpContextLifecycle$Counter;)I
      40: pop
      41: return
      42: aload_3
      43: ifnull        63
      46: aload         4
      48: ifnonnull     63
      51: getstatic     #80                 // Field org/jboss/weld/logging/ServletLogger.LOG:Lorg/jboss/weld/logging/ServletLogger;
      54: aload_3
      55: invokestatic  #81                 // Method org/jboss/weld/servlet/HttpContextLifecycle$Counter.access$000:(Lorg/jboss/weld/servlet/HttpContextLifecycle$Counter;)I
      58: invokeinterface #82,  2           // InterfaceMethod org/jboss/weld/logging/ServletLogger.guardLeak:(I)V
      63: getstatic     #73                 // Field nestedInvocationGuard:Ljava/lang/ThreadLocal;
      66: new           #75                 // class org/jboss/weld/servlet/HttpContextLifecycle$Counter
      69: dup
      70: aconst_null
      71: invokespecial #83                 // Method org/jboss/weld/servlet/HttpContextLifecycle$Counter."<init>":(Lorg/jboss/weld/servlet/HttpContextLifecycle$1;)V
      74: invokevirtual #84                 // Method java/lang/ThreadLocal.set:(Ljava/lang/Object;)V
      77: aload_1
      78: ldc           #77                 // String org.jboss.weld.context.ignore.guard.marker
      80: getstatic     #85                 // Field GUARD_PARAMETER_VALUE:Ljava/lang/Object;
      83: invokeinterface #68,  3           // InterfaceMethod javax/servlet/http/HttpServletRequest.setAttribute:(Ljava/lang/String;Ljava/lang/Object;)V
      88: aload_0
      89: getfield      #7                  // Field ignoreForwards:Z
      92: ifeq          104
      95: aload_0
      96: aload_1
      97: invokespecial #86                 // Method isForwardedRequest:(Ljavax/servlet/http/HttpServletRequest;)Z
     100: ifeq          104
     103: return
     104: aload_0
     105: getfield      #8                  // Field ignoreIncludes:Z
     108: ifeq          120
     111: aload_0
     112: aload_1
     113: invokespecial #87                 // Method isIncludedRequest:(Ljavax/servlet/http/HttpServletRequest;)Z
     116: ifeq          120
     119: return
     120: aload_0
     121: getfield      #9                  // Field contextActivationFilter:Lorg/jboss/weld/servlet/spi/HttpContextActivationFilter;
     124: aload_1
     125: invokeinterface #88,  2           // InterfaceMethod org/jboss/weld/servlet/spi/HttpContextActivationFilter.accepts:(Ljavax/servlet/http/HttpServletRequest;)Z
     130: ifne          134
     133: return
     134: getstatic     #80                 // Field org/jboss/weld/logging/ServletLogger.LOG:Lorg/jboss/weld/logging/ServletLogger;
     137: aload_1
     138: invokeinterface #89,  2           // InterfaceMethod org/jboss/weld/logging/ServletLogger.requestInitialized:(Ljava/lang/Object;)V
     143: aload_1
     144: invokestatic  #90                 // Method org/jboss/weld/servlet/SessionHolder.requestInitialized:(Ljavax/servlet/http/HttpServletRequest;)V
     147: aload_0
     148: invokevirtual #63                 // Method getRequestContext:()Lorg/jboss/weld/context/http/HttpRequestContext;
     151: aload_1
     152: invokeinterface #91,  2           // InterfaceMethod org/jboss/weld/context/http/HttpRequestContext.associate:(Ljava/lang/Object;)Z
     157: pop
     158: aload_0
     159: invokespecial #59                 // Method getSessionContext:()Lorg/jboss/weld/context/http/HttpSessionContext;
     162: aload_1
     163: invokeinterface #92,  2           // InterfaceMethod org/jboss/weld/context/http/HttpSessionContext.associate:(Ljava/lang/Object;)Z
     168: pop
     169: aload_0
     170: getfield      #6                  // Field conversationActivationEnabled:Ljava/lang/Boolean;
     173: invokevirtual #93                 // Method java/lang/Boolean.booleanValue:()Z
     176: ifeq          187
     179: aload_0
     180: getfield      #5                  // Field conversationContextActivator:Lorg/jboss/weld/servlet/ConversationContextActivator;
     183: aload_1
     184: invokevirtual #94                 // Method org/jboss/weld/servlet/ConversationContextActivator.associateConversationContext:(Ljavax/servlet/http/HttpServletRequest;)V
     187: aload_0
     188: invokevirtual #63                 // Method getRequestContext:()Lorg/jboss/weld/context/http/HttpRequestContext;
     191: invokeinterface #95,  1           // InterfaceMethod org/jboss/weld/context/http/HttpRequestContext.activate:()V
     196: aload_0
     197: invokespecial #59                 // Method getSessionContext:()Lorg/jboss/weld/context/http/HttpSessionContext;
     200: invokeinterface #96,  1           // InterfaceMethod org/jboss/weld/context/http/HttpSessionContext.activate:()V
     205: aload_0
     206: getfield      #6                  // Field conversationActivationEnabled:Ljava/lang/Boolean;
     209: invokevirtual #93                 // Method java/lang/Boolean.booleanValue:()Z
     212: ifeq          223
     215: aload_0
     216: getfield      #5                  // Field conversationContextActivator:Lorg/jboss/weld/servlet/ConversationContextActivator;
     219: aload_1
     220: invokevirtual #97                 // Method org/jboss/weld/servlet/ConversationContextActivator.activateConversationContext:(Ljavax/servlet/http/HttpServletRequest;)V
     223: aload_0
     224: getfield      #14                 // Field requestInitializedEvent:Lorg/jboss/weld/event/FastEvent;
     227: aload_1
     228: invokevirtual #57                 // Method org/jboss/weld/event/FastEvent.fire:(Ljava/lang/Object;)V
     231: goto          259
     234: astore_3
     235: aload_0
     236: aload_1
     237: invokevirtual #99                 // Method requestDestroyed:(Ljavax/servlet/http/HttpServletRequest;)V
     240: goto          245
     243: astore        4
     245: aload_1
     246: getstatic     #101                // Field REQUEST_DESTROYED:Ljava/lang/String;
     249: getstatic     #102                // Field java/lang/Boolean.TRUE:Ljava/lang/Boolean;
     252: invokeinterface #68,  3           // InterfaceMethod javax/servlet/http/HttpServletRequest.setAttribute:(Ljava/lang/String;Ljava/lang/Object;)V
     257: aload_3
     258: athrow
     259: return
    Exception table:
       from    to  target type
         205   231   234   Class java/lang/RuntimeException
         235   240   243   Class java/lang/Exception

  public void requestDestroyed(javax.servlet.http.HttpServletRequest);
    Code:
       0: aload_0
       1: aload_1
       2: invokespecial #103                // Method isRequestDestroyed:(Ljavax/servlet/http/HttpServletRequest;)Z
       5: ifeq          9
       8: return
       9: aload_0
      10: getfield      #28                 // Field nestedInvocationGuardEnabled:Z
      13: ifeq          69
      16: getstatic     #73                 // Field nestedInvocationGuard:Ljava/lang/ThreadLocal;
      19: invokevirtual #74                 // Method java/lang/ThreadLocal.get:()Ljava/lang/Object;
      22: checkcast     #75                 // class org/jboss/weld/servlet/HttpContextLifecycle$Counter
      25: astore_2
      26: aload_2
      27: ifnull        60
      30: aload_2
      31: invokestatic  #104                // Method org/jboss/weld/servlet/HttpContextLifecycle$Counter.access$010:(Lorg/jboss/weld/servlet/HttpContextLifecycle$Counter;)I
      34: pop
      35: aload_2
      36: invokestatic  #81                 // Method org/jboss/weld/servlet/HttpContextLifecycle$Counter.access$000:(Lorg/jboss/weld/servlet/HttpContextLifecycle$Counter;)I
      39: ifle          43
      42: return
      43: getstatic     #73                 // Field nestedInvocationGuard:Ljava/lang/ThreadLocal;
      46: invokevirtual #105                // Method java/lang/ThreadLocal.remove:()V
      49: aload_1
      50: ldc           #77                 // String org.jboss.weld.context.ignore.guard.marker
      52: invokeinterface #106,  2          // InterfaceMethod javax/servlet/http/HttpServletRequest.removeAttribute:(Ljava/lang/String;)V
      57: goto          69
      60: getstatic     #80                 // Field org/jboss/weld/logging/ServletLogger.LOG:Lorg/jboss/weld/logging/ServletLogger;
      63: invokeinterface #107,  1          // InterfaceMethod org/jboss/weld/logging/ServletLogger.guardNotSet:()V
      68: return
      69: aload_0
      70: getfield      #7                  // Field ignoreForwards:Z
      73: ifeq          85
      76: aload_0
      77: aload_1
      78: invokespecial #86                 // Method isForwardedRequest:(Ljavax/servlet/http/HttpServletRequest;)Z
      81: ifeq          85
      84: return
      85: aload_0
      86: getfield      #8                  // Field ignoreIncludes:Z
      89: ifeq          101
      92: aload_0
      93: aload_1
      94: invokespecial #87                 // Method isIncludedRequest:(Ljavax/servlet/http/HttpServletRequest;)Z
      97: ifeq          101
     100: return
     101: aload_0
     102: getfield      #9                  // Field contextActivationFilter:Lorg/jboss/weld/servlet/spi/HttpContextActivationFilter;
     105: aload_1
     106: invokeinterface #88,  2           // InterfaceMethod org/jboss/weld/servlet/spi/HttpContextActivationFilter.accepts:(Ljavax/servlet/http/HttpServletRequest;)Z
     111: ifne          115
     114: return
     115: getstatic     #80                 // Field org/jboss/weld/logging/ServletLogger.LOG:Lorg/jboss/weld/logging/ServletLogger;
     118: aload_1
     119: invokeinterface #108,  2          // InterfaceMethod org/jboss/weld/logging/ServletLogger.requestDestroyed:(Ljava/lang/Object;)V
     124: aload_0
     125: getfield      #5                  // Field conversationContextActivator:Lorg/jboss/weld/servlet/ConversationContextActivator;
     128: aload_1
     129: invokevirtual #109                // Method org/jboss/weld/servlet/ConversationContextActivator.deactivateConversationContext:(Ljavax/servlet/http/HttpServletRequest;)V
     132: aload_0
     133: getfield      #25                 // Field servletApi:Lorg/jboss/weld/servlet/ServletApiAbstraction;
     136: invokevirtual #110                // Method org/jboss/weld/servlet/ServletApiAbstraction.isAsyncSupported:()Z
     139: ifeq          168
     142: aload_0
     143: getfield      #25                 // Field servletApi:Lorg/jboss/weld/servlet/ServletApiAbstraction;
     146: aload_1
     147: invokevirtual #111                // Method org/jboss/weld/servlet/ServletApiAbstraction.isAsyncStarted:(Ljavax/servlet/ServletRequest;)Z
     150: ifeq          168
     153: aload_1
     154: ldc           #112                // String org.jboss.weld.context.asyncStarted
     156: iconst_1
     157: invokestatic  #113                // Method java/lang/Boolean.valueOf:(Z)Ljava/lang/Boolean;
     160: invokeinterface #68,  3           // InterfaceMethod javax/servlet/http/HttpServletRequest.setAttribute:(Ljava/lang/String;Ljava/lang/Object;)V
     165: goto          177
     168: aload_0
     169: invokevirtual #63                 // Method getRequestContext:()Lorg/jboss/weld/context/http/HttpRequestContext;
     172: invokeinterface #114,  1          // InterfaceMethod org/jboss/weld/context/http/HttpRequestContext.invalidate:()V
     177: aload_0
     178: aload_0
     179: invokevirtual #63                 // Method getRequestContext:()Lorg/jboss/weld/context/http/HttpRequestContext;
     182: aload_1
     183: invokespecial #115                // Method safelyDeactivate:(Lorg/jboss/weld/context/ManagedContext;Ljavax/servlet/http/HttpServletRequest;)V
     186: aload_0
     187: getfield      #16                 // Field requestDestroyedEvent:Lorg/jboss/weld/event/FastEvent;
     190: aload_1
     191: invokevirtual #57                 // Method org/jboss/weld/event/FastEvent.fire:(Ljava/lang/Object;)V
     194: aload_0
     195: aload_0
     196: invokespecial #59                 // Method getSessionContext:()Lorg/jboss/weld/context/http/HttpSessionContext;
     199: aload_1
     200: invokespecial #115                // Method safelyDeactivate:(Lorg/jboss/weld/context/ManagedContext;Ljavax/servlet/http/HttpServletRequest;)V
     203: aload_1
     204: getstatic     #67                 // Field HTTP_SESSION:Ljava/lang/String;
     207: invokeinterface #78,  2           // InterfaceMethod javax/servlet/http/HttpServletRequest.getAttribute:(Ljava/lang/String;)Ljava/lang/Object;
     212: astore_2
     213: aload_2
     214: ifnull        228
     217: aload_0
     218: getfield      #21                 // Field sessionDestroyedEvent:Lorg/jboss/weld/event/FastEvent;
     221: aload_2
     222: checkcast     #17                 // class javax/servlet/http/HttpSession
     225: invokevirtual #57                 // Method org/jboss/weld/event/FastEvent.fire:(Ljava/lang/Object;)V
     228: aload_0
     229: aload_0
     230: invokevirtual #63                 // Method getRequestContext:()Lorg/jboss/weld/context/http/HttpRequestContext;
     233: aload_1
     234: invokespecial #116                // Method safelyDissociate:(Lorg/jboss/weld/context/BoundContext;Ljava/lang/Object;)V
     237: aload_0
     238: aload_0
     239: invokespecial #59                 // Method getSessionContext:()Lorg/jboss/weld/context/http/HttpSessionContext;
     242: aload_1
     243: invokespecial #116                // Method safelyDissociate:(Lorg/jboss/weld/context/BoundContext;Ljava/lang/Object;)V
     246: aload_0
     247: getfield      #5                  // Field conversationContextActivator:Lorg/jboss/weld/servlet/ConversationContextActivator;
     250: aload_1
     251: invokevirtual #117                // Method org/jboss/weld/servlet/ConversationContextActivator.disassociateConversationContext:(Ljavax/servlet/http/HttpServletRequest;)V
     254: invokestatic  #61                 // Method org/jboss/weld/servlet/SessionHolder.clear:()V
     257: goto          292
     260: astore_3
     261: aload_0
     262: aload_0
     263: invokevirtual #63                 // Method getRequestContext:()Lorg/jboss/weld/context/http/HttpRequestContext;
     266: aload_1
     267: invokespecial #116                // Method safelyDissociate:(Lorg/jboss/weld/context/BoundContext;Ljava/lang/Object;)V
     270: aload_0
     271: aload_0
     272: invokespecial #59                 // Method getSessionContext:()Lorg/jboss/weld/context/http/HttpSessionContext;
     275: aload_1
     276: invokespecial #116                // Method safelyDissociate:(Lorg/jboss/weld/context/BoundContext;Ljava/lang/Object;)V
     279: aload_0
     280: getfield      #5                  // Field conversationContextActivator:Lorg/jboss/weld/servlet/ConversationContextActivator;
     283: aload_1
     284: invokevirtual #117                // Method org/jboss/weld/servlet/ConversationContextActivator.disassociateConversationContext:(Ljavax/servlet/http/HttpServletRequest;)V
     287: invokestatic  #61                 // Method org/jboss/weld/servlet/SessionHolder.clear:()V
     290: aload_3
     291: athrow
     292: return
    Exception table:
       from    to  target type
         124   228   260   any

  public boolean isConversationActivationSet();
    Code:
       0: aload_0
       1: getfield      #6                  // Field conversationActivationEnabled:Ljava/lang/Boolean;
       4: ifnull        11
       7: iconst_1
       8: goto          12
      11: iconst_0
      12: ireturn

  public void setConversationActivationEnabled(boolean);
    Code:
       0: aload_0
       1: iload_1
       2: invokestatic  #113                // Method java/lang/Boolean.valueOf:(Z)Ljava/lang/Boolean;
       5: putfield      #6                  // Field conversationActivationEnabled:Ljava/lang/Boolean;
       8: return

  public void cleanup();
    Code:
       0: return

  private boolean isIncludedRequest(javax.servlet.http.HttpServletRequest);
    Code:
       0: aload_1
       1: ldc           #118                // String javax.servlet.include.request_uri
       3: invokeinterface #78,  2           // InterfaceMethod javax/servlet/http/HttpServletRequest.getAttribute:(Ljava/lang/String;)Ljava/lang/Object;
       8: ifnull        15
      11: iconst_1
      12: goto          16
      15: iconst_0
      16: ireturn

  private boolean isForwardedRequest(javax.servlet.http.HttpServletRequest);
    Code:
       0: aload_1
       1: ldc           #119                // String javax.servlet.forward.request_uri
       3: invokeinterface #78,  2           // InterfaceMethod javax/servlet/http/HttpServletRequest.getAttribute:(Ljava/lang/String;)Ljava/lang/Object;
       8: ifnull        15
      11: iconst_1
      12: goto          16
      15: iconst_0
      16: ireturn

  private boolean isRequestDestroyed(javax.servlet.http.HttpServletRequest);
    Code:
       0: aload_1
       1: getstatic     #101                // Field REQUEST_DESTROYED:Ljava/lang/String;
       4: invokeinterface #78,  2           // InterfaceMethod javax/servlet/http/HttpServletRequest.getAttribute:(Ljava/lang/String;)Ljava/lang/Object;
       9: ifnull        16
      12: iconst_1
      13: goto          17
      16: iconst_0
      17: ireturn

  private <T> void safelyDissociate(org.jboss.weld.context.BoundContext<T>, T);
    Code:
       0: aload_1
       1: aload_2
       2: invokeinterface #120,  2          // InterfaceMethod org/jboss/weld/context/BoundContext.dissociate:(Ljava/lang/Object;)Z
       7: pop
       8: goto          31
      11: astore_3
      12: getstatic     #80                 // Field org/jboss/weld/logging/ServletLogger.LOG:Lorg/jboss/weld/logging/ServletLogger;
      15: aload_1
      16: aload_2
      17: invokeinterface #121,  3          // InterfaceMethod org/jboss/weld/logging/ServletLogger.unableToDissociateContext:(Ljava/lang/Object;Ljava/lang/Object;)V
      22: getstatic     #80                 // Field org/jboss/weld/logging/ServletLogger.LOG:Lorg/jboss/weld/logging/ServletLogger;
      25: aload_3
      26: invokeinterface #122,  2          // InterfaceMethod org/jboss/weld/logging/ServletLogger.catchingDebug:(Ljava/lang/Throwable;)V
      31: return
    Exception table:
       from    to  target type
           0     8    11   Class java/lang/Exception

  private void safelyDeactivate(org.jboss.weld.context.ManagedContext, javax.servlet.http.HttpServletRequest);
    Code:
       0: aload_1
       1: invokeinterface #123,  1          // InterfaceMethod org/jboss/weld/context/ManagedContext.deactivate:()V
       6: goto          29
       9: astore_3
      10: getstatic     #80                 // Field org/jboss/weld/logging/ServletLogger.LOG:Lorg/jboss/weld/logging/ServletLogger;
      13: aload_1
      14: aload_2
      15: invokeinterface #124,  3          // InterfaceMethod org/jboss/weld/logging/ServletLogger.unableToDeactivateContext:(Ljava/lang/Object;Ljava/lang/Object;)V
      20: getstatic     #80                 // Field org/jboss/weld/logging/ServletLogger.LOG:Lorg/jboss/weld/logging/ServletLogger;
      23: aload_3
      24: invokeinterface #122,  2          // InterfaceMethod org/jboss/weld/logging/ServletLogger.catchingDebug:(Ljava/lang/Throwable;)V
      29: return
    Exception table:
       from    to  target type
           0     6     9   Class java/lang/Exception

  static {};
    Code:
       0: new           #125                // class java/lang/StringBuilder
       3: dup
       4: invokespecial #126                // Method java/lang/StringBuilder."<init>":()V
       7: ldc           #127                // String org.jboss.weld.
       9: invokevirtual #128                // Method java/lang/StringBuilder.append:(Ljava/lang/String;)Ljava/lang/StringBuilder;
      12: ldc           #17                 // class javax/servlet/http/HttpSession
      14: invokevirtual #129                // Method java/lang/Class.getName:()Ljava/lang/String;
      17: invokevirtual #128                // Method java/lang/StringBuilder.append:(Ljava/lang/String;)Ljava/lang/StringBuilder;
      20: invokevirtual #130                // Method java/lang/StringBuilder.toString:()Ljava/lang/String;
      23: putstatic     #67                 // Field HTTP_SESSION:Ljava/lang/String;
      26: new           #125                // class java/lang/StringBuilder
      29: dup
      30: invokespecial #126                // Method java/lang/StringBuilder."<init>":()V
      33: ldc           #76                 // class org/jboss/weld/servlet/HttpContextLifecycle
      35: invokevirtual #129                // Method java/lang/Class.getName:()Ljava/lang/String;
      38: invokevirtual #128                // Method java/lang/StringBuilder.append:(Ljava/lang/String;)Ljava/lang/StringBuilder;
      41: ldc           #131                // String .request.destroyed
      43: invokevirtual #128                // Method java/lang/StringBuilder.append:(Ljava/lang/String;)Ljava/lang/StringBuilder;
      46: invokevirtual #130                // Method java/lang/StringBuilder.toString:()Ljava/lang/String;
      49: putstatic     #101                // Field REQUEST_DESTROYED:Ljava/lang/String;
      52: new           #132                // class java/lang/Object
      55: dup
      56: invokespecial #1                  // Method java/lang/Object."<init>":()V
      59: putstatic     #85                 // Field GUARD_PARAMETER_VALUE:Ljava/lang/Object;
      62: new           #133                // class java/lang/ThreadLocal
      65: dup
      66: invokespecial #134                // Method java/lang/ThreadLocal."<init>":()V
      69: putstatic     #73                 // Field nestedInvocationGuard:Ljava/lang/ThreadLocal;
      72: return
}
