Compiled from "DefaultServerEndpointConfig.java"
final class jakarta.websocket.server.DefaultServerEndpointConfig implements jakarta.websocket.server.ServerEndpointConfig {
  private java.lang.String path;

  private java.lang.Class<?> endpointClass;

  private java.util.List<java.lang.String> subprotocols;

  private java.util.List<jakarta.websocket.Extension> extensions;

  private java.util.List<java.lang.Class<? extends jakarta.websocket.Encoder>> encoders;

  private java.util.List<java.lang.Class<? extends jakarta.websocket.Decoder>> decoders;

  private java.util.Map<java.lang.String, java.lang.Object> userProperties;

  private jakarta.websocket.server.ServerEndpointConfig$Configurator serverEndpointConfigurator;

  jakarta.websocket.server.DefaultServerEndpointConfig(java.lang.Class<?>, java.lang.String, java.util.List<java.lang.String>, java.util.List<jakarta.websocket.Extension>, java.util.List<java.lang.Class<? extends jakarta.websocket.Encoder>>, java.util.List<java.lang.Class<? extends jakarta.websocket.Decoder>>, jakarta.websocket.server.ServerEndpointConfig$Configurator);
    Code:
       0: aload_0
       1: invokespecial #1                  // Method java/lang/Object."<init>":()V
       4: aload_0
       5: new           #2                  // class java/util/HashMap
       8: dup
       9: invokespecial #3                  // Method java/util/HashMap."<init>":()V
      12: putfield      #4                  // Field userProperties:Ljava/util/Map;
      15: aload_0
      16: aload_2
      17: putfield      #5                  // Field path:Ljava/lang/String;
      20: aload_0
      21: aload_1
      22: putfield      #6                  // Field endpointClass:Ljava/lang/Class;
      25: aload_0
      26: aload_3
      27: invokestatic  #7                  // Method java/util/Collections.unmodifiableList:(Ljava/util/List;)Ljava/util/List;
      30: putfield      #8                  // Field subprotocols:Ljava/util/List;
      33: aload_0
      34: aload         4
      36: invokestatic  #7                  // Method java/util/Collections.unmodifiableList:(Ljava/util/List;)Ljava/util/List;
      39: putfield      #9                  // Field extensions:Ljava/util/List;
      42: aload_0
      43: aload         5
      45: invokestatic  #7                  // Method java/util/Collections.unmodifiableList:(Ljava/util/List;)Ljava/util/List;
      48: putfield      #10                 // Field encoders:Ljava/util/List;
      51: aload_0
      52: aload         6
      54: invokestatic  #7                  // Method java/util/Collections.unmodifiableList:(Ljava/util/List;)Ljava/util/List;
      57: putfield      #11                 // Field decoders:Ljava/util/List;
      60: aload         7
      62: ifnonnull     75
      65: aload_0
      66: invokestatic  #12                 // Method jakarta/websocket/server/ServerEndpointConfig$Configurator.fetchContainerDefaultConfigurator:()Ljakarta/websocket/server/ServerEndpointConfig$Configurator;
      69: putfield      #13                 // Field serverEndpointConfigurator:Ljakarta/websocket/server/ServerEndpointConfig$Configurator;
      72: goto          81
      75: aload_0
      76: aload         7
      78: putfield      #13                 // Field serverEndpointConfigurator:Ljakarta/websocket/server/ServerEndpointConfig$Configurator;
      81: return

  public java.lang.Class<?> getEndpointClass();
    Code:
       0: aload_0
       1: getfield      #6                  // Field endpointClass:Ljava/lang/Class;
       4: areturn

  jakarta.websocket.server.DefaultServerEndpointConfig(java.lang.Class<? extends jakarta.websocket.Endpoint>, java.lang.String);
    Code:
       0: aload_0
       1: invokespecial #1                  // Method java/lang/Object."<init>":()V
       4: aload_0
       5: new           #2                  // class java/util/HashMap
       8: dup
       9: invokespecial #3                  // Method java/util/HashMap."<init>":()V
      12: putfield      #4                  // Field userProperties:Ljava/util/Map;
      15: aload_0
      16: aload_2
      17: putfield      #5                  // Field path:Ljava/lang/String;
      20: aload_0
      21: aload_1
      22: putfield      #6                  // Field endpointClass:Ljava/lang/Class;
      25: return

  public java.util.List<java.lang.Class<? extends jakarta.websocket.Encoder>> getEncoders();
    Code:
       0: aload_0
       1: getfield      #10                 // Field encoders:Ljava/util/List;
       4: areturn

  public java.util.List<java.lang.Class<? extends jakarta.websocket.Decoder>> getDecoders();
    Code:
       0: aload_0
       1: getfield      #11                 // Field decoders:Ljava/util/List;
       4: areturn

  public java.lang.String getPath();
    Code:
       0: aload_0
       1: getfield      #5                  // Field path:Ljava/lang/String;
       4: areturn

  public jakarta.websocket.server.ServerEndpointConfig$Configurator getConfigurator();
    Code:
       0: aload_0
       1: getfield      #13                 // Field serverEndpointConfigurator:Ljakarta/websocket/server/ServerEndpointConfig$Configurator;
       4: areturn

  public final java.util.Map<java.lang.String, java.lang.Object> getUserProperties();
    Code:
       0: aload_0
       1: getfield      #4                  // Field userProperties:Ljava/util/Map;
       4: areturn

  public final java.util.List<java.lang.String> getSubprotocols();
    Code:
       0: aload_0
       1: getfield      #8                  // Field subprotocols:Ljava/util/List;
       4: areturn

  public final java.util.List<jakarta.websocket.Extension> getExtensions();
    Code:
       0: aload_0
       1: getfield      #9                  // Field extensions:Ljava/util/List;
       4: areturn
}
