Compiled from "RegexReplace.java"
public class org.graylog.plugins.pipelineprocessor.functions.strings.RegexReplace extends org.graylog.plugins.pipelineprocessor.ast.functions.AbstractFunction<java.lang.String> {
  public static final java.lang.String NAME;

  private final org.graylog.plugins.pipelineprocessor.ast.functions.ParameterDescriptor<java.lang.String, java.util.regex.Pattern> patternParam;

  private final org.graylog.plugins.pipelineprocessor.ast.functions.ParameterDescriptor<java.lang.String, java.lang.String> valueParam;

  private final org.graylog.plugins.pipelineprocessor.ast.functions.ParameterDescriptor<java.lang.String, java.lang.String> replacementParam;

  private final org.graylog.plugins.pipelineprocessor.ast.functions.ParameterDescriptor<java.lang.Boolean, java.lang.Boolean> replaceAllParam;

  public org.graylog.plugins.pipelineprocessor.functions.strings.RegexReplace();
    Code:
       0: aload_0
       1: invokespecial #1                  // Method org/graylog/plugins/pipelineprocessor/ast/functions/AbstractFunction."<init>":()V
       4: aload_0
       5: ldc           #2                  // String pattern
       7: ldc           #3                  // class java/util/regex/Pattern
       9: invokestatic  #4                  // Method org/graylog/plugins/pipelineprocessor/ast/functions/ParameterDescriptor.string:(Ljava/lang/String;Ljava/lang/Class;)Lorg/graylog/plugins/pipelineprocessor/ast/functions/ParameterDescriptor$Builder;
      12: invokedynamic #5,  0              // InvokeDynamic #0:apply:()Ljava/util/function/Function;
      17: invokevirtual #6                  // Method org/graylog/plugins/pipelineprocessor/ast/functions/ParameterDescriptor$Builder.transform:(Ljava/util/function/Function;)Lorg/graylog/plugins/pipelineprocessor/ast/functions/ParameterDescriptor$Builder;
      20: ldc           #7                  // String The regular expression to which the \"value\" string is to be matched; uses Java regex syntax
      22: invokevirtual #8                  // Method org/graylog/plugins/pipelineprocessor/ast/functions/ParameterDescriptor$Builder.description:(Ljava/lang/String;)Lorg/graylog/plugins/pipelineprocessor/ast/functions/ParameterDescriptor$Builder;
      25: invokevirtual #9                  // Method org/graylog/plugins/pipelineprocessor/ast/functions/ParameterDescriptor$Builder.build:()Lorg/graylog/plugins/pipelineprocessor/ast/functions/ParameterDescriptor;
      28: putfield      #10                 // Field patternParam:Lorg/graylog/plugins/pipelineprocessor/ast/functions/ParameterDescriptor;
      31: aload_0
      32: ldc           #11                 // String value
      34: invokestatic  #12                 // Method org/graylog/plugins/pipelineprocessor/ast/functions/ParameterDescriptor.string:(Ljava/lang/String;)Lorg/graylog/plugins/pipelineprocessor/ast/functions/ParameterDescriptor$Builder;
      37: ldc           #13                 // String The string to match the pattern against
      39: invokevirtual #8                  // Method org/graylog/plugins/pipelineprocessor/ast/functions/ParameterDescriptor$Builder.description:(Ljava/lang/String;)Lorg/graylog/plugins/pipelineprocessor/ast/functions/ParameterDescriptor$Builder;
      42: invokevirtual #9                  // Method org/graylog/plugins/pipelineprocessor/ast/functions/ParameterDescriptor$Builder.build:()Lorg/graylog/plugins/pipelineprocessor/ast/functions/ParameterDescriptor;
      45: putfield      #14                 // Field valueParam:Lorg/graylog/plugins/pipelineprocessor/ast/functions/ParameterDescriptor;
      48: aload_0
      49: ldc           #15                 // String replacement
      51: invokestatic  #12                 // Method org/graylog/plugins/pipelineprocessor/ast/functions/ParameterDescriptor.string:(Ljava/lang/String;)Lorg/graylog/plugins/pipelineprocessor/ast/functions/ParameterDescriptor$Builder;
      54: ldc           #16                 // String The string to be substituted for the first or all matches
      56: invokevirtual #8                  // Method org/graylog/plugins/pipelineprocessor/ast/functions/ParameterDescriptor$Builder.description:(Ljava/lang/String;)Lorg/graylog/plugins/pipelineprocessor/ast/functions/ParameterDescriptor$Builder;
      59: invokevirtual #9                  // Method org/graylog/plugins/pipelineprocessor/ast/functions/ParameterDescriptor$Builder.build:()Lorg/graylog/plugins/pipelineprocessor/ast/functions/ParameterDescriptor;
      62: putfield      #17                 // Field replacementParam:Lorg/graylog/plugins/pipelineprocessor/ast/functions/ParameterDescriptor;
      65: aload_0
      66: ldc           #18                 // String replace_all
      68: invokestatic  #19                 // Method org/graylog/plugins/pipelineprocessor/ast/functions/ParameterDescriptor.bool:(Ljava/lang/String;)Lorg/graylog/plugins/pipelineprocessor/ast/functions/ParameterDescriptor$Builder;
      71: invokevirtual #20                 // Method org/graylog/plugins/pipelineprocessor/ast/functions/ParameterDescriptor$Builder.optional:()Lorg/graylog/plugins/pipelineprocessor/ast/functions/ParameterDescriptor$Builder;
      74: ldc           #21                 // String Replace all matches if \"true\", otherwise only replace the first match. Default: true
      76: invokevirtual #8                  // Method org/graylog/plugins/pipelineprocessor/ast/functions/ParameterDescriptor$Builder.description:(Ljava/lang/String;)Lorg/graylog/plugins/pipelineprocessor/ast/functions/ParameterDescriptor$Builder;
      79: invokevirtual #9                  // Method org/graylog/plugins/pipelineprocessor/ast/functions/ParameterDescriptor$Builder.build:()Lorg/graylog/plugins/pipelineprocessor/ast/functions/ParameterDescriptor;
      82: putfield      #22                 // Field replaceAllParam:Lorg/graylog/plugins/pipelineprocessor/ast/functions/ParameterDescriptor;
      85: return

  public java.lang.String evaluate(org.graylog.plugins.pipelineprocessor.ast.functions.FunctionArgs, org.graylog.plugins.pipelineprocessor.EvaluationContext);
    Code:
       0: aload_0
       1: getfield      #10                 // Field patternParam:Lorg/graylog/plugins/pipelineprocessor/ast/functions/ParameterDescriptor;
       4: aload_1
       5: aload_2
       6: invokevirtual #23                 // Method org/graylog/plugins/pipelineprocessor/ast/functions/ParameterDescriptor.required:(Lorg/graylog/plugins/pipelineprocessor/ast/functions/FunctionArgs;Lorg/graylog/plugins/pipelineprocessor/EvaluationContext;)Ljava/lang/Object;
       9: checkcast     #3                  // class java/util/regex/Pattern
      12: astore_3
      13: aload_0
      14: getfield      #14                 // Field valueParam:Lorg/graylog/plugins/pipelineprocessor/ast/functions/ParameterDescriptor;
      17: aload_1
      18: aload_2
      19: invokevirtual #23                 // Method org/graylog/plugins/pipelineprocessor/ast/functions/ParameterDescriptor.required:(Lorg/graylog/plugins/pipelineprocessor/ast/functions/FunctionArgs;Lorg/graylog/plugins/pipelineprocessor/EvaluationContext;)Ljava/lang/Object;
      22: checkcast     #24                 // class java/lang/String
      25: astore        4
      27: aload_0
      28: getfield      #17                 // Field replacementParam:Lorg/graylog/plugins/pipelineprocessor/ast/functions/ParameterDescriptor;
      31: aload_1
      32: aload_2
      33: invokevirtual #23                 // Method org/graylog/plugins/pipelineprocessor/ast/functions/ParameterDescriptor.required:(Lorg/graylog/plugins/pipelineprocessor/ast/functions/FunctionArgs;Lorg/graylog/plugins/pipelineprocessor/EvaluationContext;)Ljava/lang/Object;
      36: checkcast     #24                 // class java/lang/String
      39: astore        5
      41: aload_0
      42: getfield      #22                 // Field replaceAllParam:Lorg/graylog/plugins/pipelineprocessor/ast/functions/ParameterDescriptor;
      45: aload_1
      46: aload_2
      47: invokevirtual #25                 // Method org/graylog/plugins/pipelineprocessor/ast/functions/ParameterDescriptor.optional:(Lorg/graylog/plugins/pipelineprocessor/ast/functions/FunctionArgs;Lorg/graylog/plugins/pipelineprocessor/EvaluationContext;)Ljava/util/Optional;
      50: iconst_1
      51: invokestatic  #26                 // Method java/lang/Boolean.valueOf:(Z)Ljava/lang/Boolean;
      54: invokevirtual #27                 // Method java/util/Optional.orElse:(Ljava/lang/Object;)Ljava/lang/Object;
      57: checkcast     #28                 // class java/lang/Boolean
      60: invokevirtual #29                 // Method java/lang/Boolean.booleanValue:()Z
      63: istore        6
      65: aload_3
      66: ifnull        73
      69: iconst_1
      70: goto          74
      73: iconst_0
      74: ldc           #30                 // String Argument \'pattern\' cannot be \'null\'
      76: invokestatic  #31                 // Method com/google/common/base/Preconditions.checkArgument:(ZLjava/lang/Object;)V
      79: aload         4
      81: ifnull        88
      84: iconst_1
      85: goto          89
      88: iconst_0
      89: ldc           #32                 // String Argument \'value\' cannot be \'null\'
      91: invokestatic  #31                 // Method com/google/common/base/Preconditions.checkArgument:(ZLjava/lang/Object;)V
      94: aload         5
      96: ifnull        103
      99: iconst_1
     100: goto          104
     103: iconst_0
     104: ldc           #33                 // String Argument \'replacement\' cannot be \'null\'
     106: invokestatic  #31                 // Method com/google/common/base/Preconditions.checkArgument:(ZLjava/lang/Object;)V
     109: iload         6
     111: ifeq          126
     114: aload_3
     115: aload         4
     117: invokevirtual #34                 // Method java/util/regex/Pattern.matcher:(Ljava/lang/CharSequence;)Ljava/util/regex/Matcher;
     120: aload         5
     122: invokevirtual #35                 // Method java/util/regex/Matcher.replaceAll:(Ljava/lang/String;)Ljava/lang/String;
     125: areturn
     126: aload_3
     127: aload         4
     129: invokevirtual #34                 // Method java/util/regex/Pattern.matcher:(Ljava/lang/CharSequence;)Ljava/util/regex/Matcher;
     132: aload         5
     134: invokevirtual #36                 // Method java/util/regex/Matcher.replaceFirst:(Ljava/lang/String;)Ljava/lang/String;
     137: areturn

  public org.graylog.plugins.pipelineprocessor.ast.functions.FunctionDescriptor<java.lang.String> descriptor();
    Code:
       0: invokestatic  #37                 // Method org/graylog/plugins/pipelineprocessor/ast/functions/FunctionDescriptor.builder:()Lorg/graylog/plugins/pipelineprocessor/ast/functions/FunctionDescriptor$Builder;
       3: ldc           #39                 // String regex_replace
       5: invokevirtual #40                 // Method org/graylog/plugins/pipelineprocessor/ast/functions/FunctionDescriptor$Builder.name:(Ljava/lang/String;)Lorg/graylog/plugins/pipelineprocessor/ast/functions/FunctionDescriptor$Builder;
       8: iconst_1
       9: invokevirtual #41                 // Method org/graylog/plugins/pipelineprocessor/ast/functions/FunctionDescriptor$Builder.pure:(Z)Lorg/graylog/plugins/pipelineprocessor/ast/functions/FunctionDescriptor$Builder;
      12: ldc           #24                 // class java/lang/String
      14: invokevirtual #42                 // Method org/graylog/plugins/pipelineprocessor/ast/functions/FunctionDescriptor$Builder.returnType:(Ljava/lang/Class;)Lorg/graylog/plugins/pipelineprocessor/ast/functions/FunctionDescriptor$Builder;
      17: aload_0
      18: getfield      #10                 // Field patternParam:Lorg/graylog/plugins/pipelineprocessor/ast/functions/ParameterDescriptor;
      21: aload_0
      22: getfield      #14                 // Field valueParam:Lorg/graylog/plugins/pipelineprocessor/ast/functions/ParameterDescriptor;
      25: aload_0
      26: getfield      #17                 // Field replacementParam:Lorg/graylog/plugins/pipelineprocessor/ast/functions/ParameterDescriptor;
      29: aload_0
      30: getfield      #22                 // Field replaceAllParam:Lorg/graylog/plugins/pipelineprocessor/ast/functions/ParameterDescriptor;
      33: invokestatic  #43                 // Method com/google/common/collect/ImmutableList.of:(Ljava/lang/Object;Ljava/lang/Object;Ljava/lang/Object;Ljava/lang/Object;)Lcom/google/common/collect/ImmutableList;
      36: invokevirtual #44                 // Method org/graylog/plugins/pipelineprocessor/ast/functions/FunctionDescriptor$Builder.params:(Lcom/google/common/collect/ImmutableList;)Lorg/graylog/plugins/pipelineprocessor/ast/functions/FunctionDescriptor$Builder;
      39: ldc           #45                 // String Match a string with a regular expression (Java syntax)
      41: invokevirtual #46                 // Method org/graylog/plugins/pipelineprocessor/ast/functions/FunctionDescriptor$Builder.description:(Ljava/lang/String;)Lorg/graylog/plugins/pipelineprocessor/ast/functions/FunctionDescriptor$Builder;
      44: invokevirtual #47                 // Method org/graylog/plugins/pipelineprocessor/ast/functions/FunctionDescriptor$Builder.build:()Lorg/graylog/plugins/pipelineprocessor/ast/functions/FunctionDescriptor;
      47: areturn

  public java.lang.Object evaluate(org.graylog.plugins.pipelineprocessor.ast.functions.FunctionArgs, org.graylog.plugins.pipelineprocessor.EvaluationContext);
    Code:
       0: aload_0
       1: aload_1
       2: aload_2
       3: invokevirtual #48                 // Method evaluate:(Lorg/graylog/plugins/pipelineprocessor/ast/functions/FunctionArgs;Lorg/graylog/plugins/pipelineprocessor/EvaluationContext;)Ljava/lang/String;
       6: areturn
}
