Compiled from "KeyManagerFactoryWrapper.java"
public final class io.netty.handler.ssl.util.KeyManagerFactoryWrapper extends io.netty.handler.ssl.util.SimpleKeyManagerFactory {
  private final javax.net.ssl.KeyManager km;

  public io.netty.handler.ssl.util.KeyManagerFactoryWrapper(javax.net.ssl.KeyManager);
    Code:
       0: aload_0
       1: invokespecial #1                  // Method io/netty/handler/ssl/util/SimpleKeyManagerFactory."<init>":()V
       4: aload_0
       5: aload_1
       6: ldc           #2                  // String km
       8: invokestatic  #3                  // Method io/netty/util/internal/ObjectUtil.checkNotNull:(Ljava/lang/Object;Ljava/lang/String;)Ljava/lang/Object;
      11: checkcast     #4                  // class javax/net/ssl/KeyManager
      14: putfield      #5                  // Field km:Ljavax/net/ssl/KeyManager;
      17: return

  protected void engineInit(java.security.KeyStore, char[]) throws java.lang.Exception;
    Code:
       0: return

  protected void engineInit(javax.net.ssl.ManagerFactoryParameters) throws java.lang.Exception;
    Code:
       0: return

  protected javax.net.ssl.KeyManager[] engineGetKeyManagers();
    Code:
       0: iconst_1
       1: anewarray     #4                  // class javax/net/ssl/KeyManager
       4: dup
       5: iconst_0
       6: aload_0
       7: getfield      #5                  // Field km:Ljavax/net/ssl/KeyManager;
      10: aastore
      11: areturn
}
