Compiled from "SimpleMeterRegistry.java"
class io.micrometer.core.instrument.simple.SimpleMeterRegistry$1 {
  static final int[] $SwitchMap$io$micrometer$core$instrument$simple$CountingMode;

  static {};
    Code:
       0: invokestatic  #1                  // Method io/micrometer/core/instrument/simple/CountingMode.values:()[Lio/micrometer/core/instrument/simple/CountingMode;
       3: arraylength
       4: newarray       int
       6: putstatic     #7                  // Field $SwitchMap$io$micrometer$core$instrument$simple$CountingMode:[I
       9: getstatic     #7                  // Field $SwitchMap$io$micrometer$core$instrument$simple$CountingMode:[I
      12: getstatic     #13                 // Field io/micrometer/core/instrument/simple/CountingMode.CUMULATIVE:Lio/micrometer/core/instrument/simple/CountingMode;
      15: invokevirtual #17                 // Method io/micrometer/core/instrument/simple/CountingMode.ordinal:()I
      18: iconst_1
      19: iastore
      20: goto          24
      23: astore_0
      24: getstatic     #7                  // Field $SwitchMap$io$micrometer$core$instrument$simple$CountingMode:[I
      27: getstatic     #23                 // Field io/micrometer/core/instrument/simple/CountingMode.STEP:Lio/micrometer/core/instrument/simple/CountingMode;
      30: invokevirtual #17                 // Method io/micrometer/core/instrument/simple/CountingMode.ordinal:()I
      33: iconst_2
      34: iastore
      35: goto          39
      38: astore_0
      39: return
    Exception table:
       from    to  target type
           9    20    23   Class java/lang/NoSuchFieldError
          24    35    38   Class java/lang/NoSuchFieldError
}
