Compiled from "HKDF.java"
public abstract class org.whispersystems.libsignal.kdf.HKDF {
  private static final int HASH_OUTPUT_SIZE;

  public org.whispersystems.libsignal.kdf.HKDF();
    Code:
       0: aload_0
       1: invokespecial #1                  // Method java/lang/Object."<init>":()V
       4: return

  public static org.whispersystems.libsignal.kdf.HKDF createFor(int);
    Code:
       0: iload_0
       1: lookupswitch  { // 2
                     2: 28
                     3: 36
               default: 44
          }
      28: new           #2                  // class org/whispersystems/libsignal/kdf/HKDFv2
      31: dup
      32: invokespecial #3                  // Method org/whispersystems/libsignal/kdf/HKDFv2."<init>":()V
      35: areturn
      36: new           #4                  // class org/whispersystems/libsignal/kdf/HKDFv3
      39: dup
      40: invokespecial #5                  // Method org/whispersystems/libsignal/kdf/HKDFv3."<init>":()V
      43: areturn
      44: new           #6                  // class java/lang/AssertionError
      47: dup
      48: new           #7                  // class java/lang/StringBuilder
      51: dup
      52: invokespecial #8                  // Method java/lang/StringBuilder."<init>":()V
      55: ldc           #9                  // String Unknown version:
      57: invokevirtual #10                 // Method java/lang/StringBuilder.append:(Ljava/lang/String;)Ljava/lang/StringBuilder;
      60: iload_0
      61: invokevirtual #11                 // Method java/lang/StringBuilder.append:(I)Ljava/lang/StringBuilder;
      64: invokevirtual #12                 // Method java/lang/StringBuilder.toString:()Ljava/lang/String;
      67: invokespecial #13                 // Method java/lang/AssertionError."<init>":(Ljava/lang/Object;)V
      70: athrow

  public byte[] deriveSecrets(byte[], byte[], int);
    Code:
       0: iload_3
       1: aload_0
       2: invokevirtual #14                 // Method getVersion:()I
       5: aload_1
       6: aload_2
       7: aconst_null
       8: invokestatic  #15                 // Method org/signal/client/internal/Native.HKDF_DeriveSecrets:(II[B[B[B)[B
      11: areturn

  public byte[] deriveSecrets(byte[], byte[], byte[], int);
    Code:
       0: iload         4
       2: aload_0
       3: invokevirtual #14                 // Method getVersion:()I
       6: aload_1
       7: aload_3
       8: aload_2
       9: invokestatic  #15                 // Method org/signal/client/internal/Native.HKDF_DeriveSecrets:(II[B[B[B)[B
      12: areturn

  protected abstract int getVersion();
}
