Compiled from "QueueCfg.java"
public class net.openhft.chronicle.engine.cfg.QueueCfg extends net.openhft.chronicle.wire.AbstractMarshallableCfg implements net.openhft.chronicle.engine.cfg.Installable {
  private int masterId;

  private java.lang.String basePath;

  private java.lang.Class topicClass;

  private java.lang.Class messageClass;

  private boolean acknowledgment;

  private net.openhft.chronicle.engine.tree.MessageAdaptor messageAdaptor;

  private net.openhft.chronicle.wire.WireType wireType;

  private java.lang.String cluster;

  public net.openhft.chronicle.engine.cfg.QueueCfg();
    Code:
       0: aload_0
       1: invokespecial #1                  // Method net/openhft/chronicle/wire/AbstractMarshallableCfg."<init>":()V
       4: aload_0
       5: iconst_1
       6: putfield      #2                  // Field masterId:I
       9: aload_0
      10: aconst_null
      11: putfield      #3                  // Field basePath:Ljava/lang/String;
      14: aload_0
      15: ldc           #4                  // class java/lang/String
      17: putfield      #5                  // Field topicClass:Ljava/lang/Class;
      20: aload_0
      21: ldc           #4                  // class java/lang/String
      23: putfield      #6                  // Field messageClass:Ljava/lang/Class;
      26: aload_0
      27: iconst_0
      28: putfield      #7                  // Field acknowledgment:Z
      31: aload_0
      32: aconst_null
      33: putfield      #8                  // Field messageAdaptor:Lnet/openhft/chronicle/engine/tree/MessageAdaptor;
      36: aload_0
      37: getstatic     #9                  // Field net/openhft/chronicle/wire/WireType.BINARY:Lnet/openhft/chronicle/wire/WireType;
      40: putfield      #10                 // Field wireType:Lnet/openhft/chronicle/wire/WireType;
      43: aload_0
      44: ldc           #11                 // String
      46: putfield      #12                 // Field cluster:Ljava/lang/String;
      49: return

  public java.lang.Void install(java.lang.String, net.openhft.chronicle.engine.api.tree.AssetTree) throws java.lang.Exception;
    Code:
       0: aload_1
       1: invokestatic  #13                 // Method net/openhft/chronicle/engine/api/tree/RequestContext.requestContext:(Ljava/lang/String;)Lnet/openhft/chronicle/engine/api/tree/RequestContext;
       4: astore_3
       5: aload_3
       6: invokevirtual #14                 // Method net/openhft/chronicle/engine/api/tree/RequestContext.bootstrap:()Ljava/lang/Boolean;
       9: ifnull        22
      12: new           #15                 // class java/lang/UnsupportedOperationException
      15: dup
      16: ldc           #16                 // String Its not possible to set the bootstrap when acquiring a queue
      18: invokespecial #17                 // Method java/lang/UnsupportedOperationException."<init>":(Ljava/lang/String;)V
      21: athrow
      22: aload_0
      23: aload_1
      24: invokedynamic #18,  0             // InvokeDynamic #0:apply:(Lnet/openhft/chronicle/engine/cfg/QueueCfg;Ljava/lang/String;)Ljava/util/function/Function;
      29: astore        4
      31: aload_2
      32: aload_1
      33: invokeinterface #19,  2           // InterfaceMethod net/openhft/chronicle/engine/api/tree/AssetTree.acquireAsset:(Ljava/lang/String;)Lnet/openhft/chronicle/engine/api/tree/Asset;
      38: astore        5
      40: aload         5
      42: checkcast     #20                 // class net/openhft/chronicle/engine/tree/VanillaAsset
      45: invokevirtual #21                 // Method net/openhft/chronicle/engine/tree/VanillaAsset.configQueueServer:()V
      48: aload         5
      50: ldc           #22                 // class net/openhft/chronicle/engine/query/QueueConfig
      52: invokeinterface #23,  2           // InterfaceMethod net/openhft/chronicle/engine/api/tree/Asset.getView:(Ljava/lang/Class;)Ljava/lang/Object;
      57: checkcast     #22                 // class net/openhft/chronicle/engine/query/QueueConfig
      60: astore        6
      62: aload         6
      64: ifnonnull     96
      67: aload         5
      69: new           #22                 // class net/openhft/chronicle/engine/query/QueueConfig
      72: dup
      73: aload         4
      75: aload_0
      76: getfield      #7                  // Field acknowledgment:Z
      79: aload_0
      80: getfield      #8                  // Field messageAdaptor:Lnet/openhft/chronicle/engine/tree/MessageAdaptor;
      83: aload_0
      84: getfield      #10                 // Field wireType:Lnet/openhft/chronicle/wire/WireType;
      87: invokespecial #24                 // Method net/openhft/chronicle/engine/query/QueueConfig."<init>":(Ljava/util/function/Function;ZLnet/openhft/chronicle/engine/tree/MessageAdaptor;Lnet/openhft/chronicle/wire/WireType;)V
      90: invokeinterface #25,  2           // InterfaceMethod net/openhft/chronicle/engine/api/tree/Asset.addView:(Ljava/lang/Object;)Ljava/lang/Object;
      95: pop
      96: aload_2
      97: aload_3
      98: ldc           #26                 // String queue
     100: invokevirtual #27                 // Method net/openhft/chronicle/engine/api/tree/RequestContext.view:(Ljava/lang/String;)Lnet/openhft/chronicle/engine/api/tree/RequestContext;
     103: aload_0
     104: getfield      #5                  // Field topicClass:Ljava/lang/Class;
     107: invokevirtual #28                 // Method net/openhft/chronicle/engine/api/tree/RequestContext.type:(Ljava/lang/Class;)Lnet/openhft/chronicle/engine/api/tree/RequestContext;
     110: aload_0
     111: getfield      #6                  // Field messageClass:Ljava/lang/Class;
     114: invokevirtual #29                 // Method net/openhft/chronicle/engine/api/tree/RequestContext.type2:(Ljava/lang/Class;)Lnet/openhft/chronicle/engine/api/tree/RequestContext;
     117: aload_0
     118: getfield      #3                  // Field basePath:Ljava/lang/String;
     121: invokevirtual #30                 // Method net/openhft/chronicle/engine/api/tree/RequestContext.basePath:(Ljava/lang/String;)Lnet/openhft/chronicle/engine/api/tree/RequestContext;
     124: aload_0
     125: getfield      #12                 // Field cluster:Ljava/lang/String;
     128: invokevirtual #31                 // Method net/openhft/chronicle/engine/api/tree/RequestContext.cluster:(Ljava/lang/String;)Lnet/openhft/chronicle/engine/api/tree/RequestContext;
     131: invokeinterface #32,  2           // InterfaceMethod net/openhft/chronicle/engine/api/tree/AssetTree.acquireView:(Lnet/openhft/chronicle/engine/api/tree/RequestContext;)Ljava/lang/Object;
     136: pop
     137: aconst_null
     138: areturn

  public java.lang.Object install(java.lang.String, net.openhft.chronicle.engine.api.tree.AssetTree) throws java.lang.Exception;
    Code:
       0: aload_0
       1: aload_1
       2: aload_2
       3: invokevirtual #33                 // Method install:(Ljava/lang/String;Lnet/openhft/chronicle/engine/api/tree/AssetTree;)Ljava/lang/Void;
       6: areturn

  private java.lang.Integer lambda$install$0(java.lang.String, java.lang.String);
    Code:
       0: aload_2
       1: aload_1
       2: invokevirtual #34                 // Method java/lang/String.equals:(Ljava/lang/Object;)Z
       5: ifeq          15
       8: aload_0
       9: getfield      #2                  // Field masterId:I
      12: goto          16
      15: iconst_1
      16: invokestatic  #35                 // Method java/lang/Integer.valueOf:(I)Ljava/lang/Integer;
      19: areturn
}
