Compiled from "ClassNodeUtils.java"
public class org.codehaus.groovy.ast.tools.ClassNodeUtils {
  public org.codehaus.groovy.ast.tools.ClassNodeUtils();
    Code:
       0: aload_0
       1: invokespecial #9                  // Method java/lang/Object."<init>":()V
       4: return

  public static void addInterfaceMethods(org.codehaus.groovy.ast.ClassNode, java.util.Map<java.lang.String, org.codehaus.groovy.ast.MethodNode>);
    Code:
       0: aload_0
       1: invokevirtual #19                 // Method org/codehaus/groovy/ast/ClassNode.getInterfaces:()[Lorg/codehaus/groovy/ast/ClassNode;
       4: astore_2
       5: aload_2
       6: arraylength
       7: istore_3
       8: iconst_0
       9: istore        4
      11: iload         4
      13: iload_3
      14: if_icmpge     111
      17: aload_2
      18: iload         4
      20: aaload
      21: astore        5
      23: aload         5
      25: invokevirtual #25                 // Method org/codehaus/groovy/ast/ClassNode.getDeclaredMethodsMap:()Ljava/util/Map;
      28: astore        6
      30: aload         6
      32: invokeinterface #31,  1           // InterfaceMethod java/util/Map.keySet:()Ljava/util/Set;
      37: invokeinterface #37,  1           // InterfaceMethod java/util/Set.iterator:()Ljava/util/Iterator;
      42: astore        7
      44: aload         7
      46: invokeinterface #43,  1           // InterfaceMethod java/util/Iterator.hasNext:()Z
      51: ifeq          105
      54: aload         7
      56: invokeinterface #47,  1           // InterfaceMethod java/util/Iterator.next:()Ljava/lang/Object;
      61: checkcast     #49                 // class java/lang/String
      64: astore        8
      66: aload_1
      67: aload         8
      69: invokeinterface #53,  2           // InterfaceMethod java/util/Map.containsKey:(Ljava/lang/Object;)Z
      74: ifne          102
      77: aload         6
      79: aload         8
      81: invokeinterface #57,  2           // InterfaceMethod java/util/Map.get:(Ljava/lang/Object;)Ljava/lang/Object;
      86: checkcast     #59                 // class org/codehaus/groovy/ast/MethodNode
      89: astore        9
      91: aload_1
      92: aload         8
      94: aload         9
      96: invokeinterface #63,  3           // InterfaceMethod java/util/Map.put:(Ljava/lang/Object;Ljava/lang/Object;)Ljava/lang/Object;
     101: pop
     102: goto          44
     105: iinc          4, 1
     108: goto          11
     111: return

  public static java.util.Map<java.lang.String, org.codehaus.groovy.ast.MethodNode> getDeclaredMethodMapsFromInterfaces(org.codehaus.groovy.ast.ClassNode);
    Code:
       0: new           #78                 // class java/util/HashMap
       3: dup
       4: invokespecial #79                 // Method java/util/HashMap."<init>":()V
       7: astore_1
       8: aload_0
       9: invokevirtual #19                 // Method org/codehaus/groovy/ast/ClassNode.getInterfaces:()[Lorg/codehaus/groovy/ast/ClassNode;
      12: astore_2
      13: aload_2
      14: astore_3
      15: aload_3
      16: arraylength
      17: istore        4
      19: iconst_0
      20: istore        5
      22: iload         5
      24: iload         4
      26: if_icmpge     52
      29: aload_3
      30: iload         5
      32: aaload
      33: astore        6
      35: aload_1
      36: aload         6
      38: invokevirtual #25                 // Method org/codehaus/groovy/ast/ClassNode.getDeclaredMethodsMap:()Ljava/util/Map;
      41: invokeinterface #83,  2           // InterfaceMethod java/util/Map.putAll:(Ljava/util/Map;)V
      46: iinc          5, 1
      49: goto          22
      52: aload_1
      53: areturn

  public static void addDeclaredMethodMapsFromSuperInterfaces(org.codehaus.groovy.ast.ClassNode, java.util.Map<java.lang.String, org.codehaus.groovy.ast.MethodNode>);
    Code:
       0: aload_0
       1: invokevirtual #19                 // Method org/codehaus/groovy/ast/ClassNode.getInterfaces:()[Lorg/codehaus/groovy/ast/ClassNode;
       4: invokestatic  #93                 // Method java/util/Arrays.asList:([Ljava/lang/Object;)Ljava/util/List;
       7: astore_2
       8: aload_0
       9: invokevirtual #97                 // Method org/codehaus/groovy/ast/ClassNode.getSuperClass:()Lorg/codehaus/groovy/ast/ClassNode;
      12: astore_3
      13: aload_3
      14: ifnull        95
      17: aload_3
      18: getstatic     #104                // Field org/codehaus/groovy/ast/ClassHelper.OBJECT_TYPE:Lorg/codehaus/groovy/ast/ClassNode;
      21: invokevirtual #107                // Method org/codehaus/groovy/ast/ClassNode.equals:(Ljava/lang/Object;)Z
      24: ifne          95
      27: aload_3
      28: invokevirtual #19                 // Method org/codehaus/groovy/ast/ClassNode.getInterfaces:()[Lorg/codehaus/groovy/ast/ClassNode;
      31: astore        4
      33: aload         4
      35: astore        5
      37: aload         5
      39: arraylength
      40: istore        6
      42: iconst_0
      43: istore        7
      45: iload         7
      47: iload         6
      49: if_icmpge     87
      52: aload         5
      54: iload         7
      56: aaload
      57: astore        8
      59: aload_2
      60: aload         8
      62: invokeinterface #110,  2          // InterfaceMethod java/util/List.contains:(Ljava/lang/Object;)Z
      67: ifne          81
      70: aload_1
      71: aload         8
      73: invokevirtual #25                 // Method org/codehaus/groovy/ast/ClassNode.getDeclaredMethodsMap:()Ljava/util/Map;
      76: invokeinterface #83,  2           // InterfaceMethod java/util/Map.putAll:(Ljava/util/Map;)V
      81: iinc          7, 1
      84: goto          45
      87: aload_3
      88: invokevirtual #97                 // Method org/codehaus/groovy/ast/ClassNode.getSuperClass:()Lorg/codehaus/groovy/ast/ClassNode;
      91: astore_3
      92: goto          13
      95: return
}
