Compiled from "WideningCategories.java"
final class org.codehaus.groovy.ast.tools.WideningCategories$2 implements java.util.Comparator<org.codehaus.groovy.ast.ClassNode> {
  org.codehaus.groovy.ast.tools.WideningCategories$2();
    Code:
       0: aload_0
       1: invokespecial #14                 // Method java/lang/Object."<init>":()V
       4: return

  public int compare(org.codehaus.groovy.ast.ClassNode, org.codehaus.groovy.ast.ClassNode);
    Code:
       0: aload_1
       1: invokevirtual #24                 // Method org/codehaus/groovy/ast/ClassNode.getInterfaces:()[Lorg/codehaus/groovy/ast/ClassNode;
       4: arraylength
       5: istore_3
       6: aload_2
       7: invokevirtual #24                 // Method org/codehaus/groovy/ast/ClassNode.getInterfaces:()[Lorg/codehaus/groovy/ast/ClassNode;
      10: arraylength
      11: istore        4
      13: iload_3
      14: iload         4
      16: if_icmple     21
      19: iconst_m1
      20: ireturn
      21: iload_3
      22: iload         4
      24: if_icmpge     29
      27: iconst_1
      28: ireturn
      29: aload_1
      30: invokevirtual #28                 // Method org/codehaus/groovy/ast/ClassNode.getMethods:()Ljava/util/List;
      33: invokeinterface #34,  1           // InterfaceMethod java/util/List.size:()I
      38: istore        5
      40: aload_2
      41: invokevirtual #28                 // Method org/codehaus/groovy/ast/ClassNode.getMethods:()Ljava/util/List;
      44: invokeinterface #34,  1           // InterfaceMethod java/util/List.size:()I
      49: istore        6
      51: iload         5
      53: iload         6
      55: if_icmple     60
      58: iconst_m1
      59: ireturn
      60: iload         5
      62: iload         6
      64: if_icmpge     69
      67: iconst_1
      68: ireturn
      69: aload_1
      70: invokevirtual #38                 // Method org/codehaus/groovy/ast/ClassNode.getName:()Ljava/lang/String;
      73: aload_2
      74: invokevirtual #38                 // Method org/codehaus/groovy/ast/ClassNode.getName:()Ljava/lang/String;
      77: invokevirtual #44                 // Method java/lang/String.compareTo:(Ljava/lang/String;)I
      80: ireturn

  public int compare(java.lang.Object, java.lang.Object);
    Code:
       0: aload_0
       1: aload_1
       2: checkcast     #20                 // class org/codehaus/groovy/ast/ClassNode
       5: aload_2
       6: checkcast     #20                 // class org/codehaus/groovy/ast/ClassNode
       9: invokevirtual #55                 // Method compare:(Lorg/codehaus/groovy/ast/ClassNode;Lorg/codehaus/groovy/ast/ClassNode;)I
      12: ireturn
}
