Compiled from "AbstractReference.java"
public abstract class jnr.ffi.byref.AbstractReference<T> implements jnr.ffi.byref.ByReference<T> {
  T value;

  protected jnr.ffi.byref.AbstractReference(T);
    Code:
       0: aload_0
       1: invokespecial #1                  // Method java/lang/Object."<init>":()V
       4: aload_0
       5: aload_1
       6: putfield      #2                  // Field value:Ljava/lang/Object;
       9: return

  protected static <T> T checkNull(T);
    Code:
       0: aload_0
       1: ifnonnull     14
       4: new           #3                  // class java/lang/NullPointerException
       7: dup
       8: ldc           #4                  // String reference value cannot be null
      10: invokespecial #5                  // Method java/lang/NullPointerException."<init>":(Ljava/lang/String;)V
      13: athrow
      14: aload_0
      15: areturn

  public T getValue();
    Code:
       0: aload_0
       1: getfield      #2                  // Field value:Ljava/lang/Object;
       4: areturn
}
