Compiled from "NumberByReference.java"
public class jnr.ffi.byref.NumberByReference extends jnr.ffi.byref.AbstractNumberReference<java.lang.Number> {
  private final jnr.ffi.TypeAlias typeAlias;

  public jnr.ffi.byref.NumberByReference(jnr.ffi.TypeAlias, java.lang.Number);
    Code:
       0: aload_0
       1: aload_2
       2: invokestatic  #1                  // Method checkNull:(Ljava/lang/Number;)Ljava/lang/Number;
       5: invokespecial #2                  // Method jnr/ffi/byref/AbstractNumberReference."<init>":(Ljava/lang/Number;)V
       8: aload_0
       9: aload_1
      10: putfield      #3                  // Field typeAlias:Ljnr/ffi/TypeAlias;
      13: return

  public jnr.ffi.byref.NumberByReference(jnr.ffi.TypeAlias);
    Code:
       0: aload_0
       1: iconst_0
       2: invokestatic  #4                  // Method java/lang/Integer.valueOf:(I)Ljava/lang/Integer;
       5: invokespecial #2                  // Method jnr/ffi/byref/AbstractNumberReference."<init>":(Ljava/lang/Number;)V
       8: aload_0
       9: aload_1
      10: putfield      #3                  // Field typeAlias:Ljnr/ffi/TypeAlias;
      13: return

  public int nativeSize(jnr.ffi.Runtime);
    Code:
       0: aload_1
       1: aload_0
       2: getfield      #3                  // Field typeAlias:Ljnr/ffi/TypeAlias;
       5: invokevirtual #5                  // Method jnr/ffi/Runtime.findType:(Ljnr/ffi/TypeAlias;)Ljnr/ffi/Type;
       8: invokevirtual #6                  // Method jnr/ffi/Type.size:()I
      11: ireturn

  public void fromNative(jnr.ffi.Runtime, jnr.ffi.Pointer, long);
    Code:
       0: getstatic     #7                  // Field jnr/ffi/byref/NumberByReference$1.$SwitchMap$jnr$ffi$NativeType:[I
       3: aload_1
       4: aload_0
       5: getfield      #3                  // Field typeAlias:Ljnr/ffi/TypeAlias;
       8: invokevirtual #5                  // Method jnr/ffi/Runtime.findType:(Ljnr/ffi/TypeAlias;)Ljnr/ffi/Type;
      11: invokevirtual #8                  // Method jnr/ffi/Type.getNativeType:()Ljnr/ffi/NativeType;
      14: invokevirtual #9                  // Method jnr/ffi/NativeType.ordinal:()I
      17: iaload
      18: tableswitch   { // 1 to 13
                     1: 84
                     2: 84
                     3: 99
                     4: 99
                     5: 114
                     6: 114
                     7: 129
                     8: 129
                     9: 144
                    10: 144
                    11: 159
                    12: 174
                    13: 189
               default: 204
          }
      84: aload_0
      85: aload_2
      86: lload_3
      87: invokevirtual #10                 // Method jnr/ffi/Pointer.getByte:(J)B
      90: invokestatic  #11                 // Method java/lang/Byte.valueOf:(B)Ljava/lang/Byte;
      93: putfield      #12                 // Field value:Ljava/lang/Number;
      96: goto          234
      99: aload_0
     100: aload_2
     101: lload_3
     102: invokevirtual #13                 // Method jnr/ffi/Pointer.getShort:(J)S
     105: invokestatic  #14                 // Method java/lang/Short.valueOf:(S)Ljava/lang/Short;
     108: putfield      #12                 // Field value:Ljava/lang/Number;
     111: goto          234
     114: aload_0
     115: aload_2
     116: lload_3
     117: invokevirtual #15                 // Method jnr/ffi/Pointer.getInt:(J)I
     120: invokestatic  #4                  // Method java/lang/Integer.valueOf:(I)Ljava/lang/Integer;
     123: putfield      #12                 // Field value:Ljava/lang/Number;
     126: goto          234
     129: aload_0
     130: aload_2
     131: lload_3
     132: invokevirtual #16                 // Method jnr/ffi/Pointer.getLong:(J)J
     135: invokestatic  #17                 // Method java/lang/Long.valueOf:(J)Ljava/lang/Long;
     138: putfield      #12                 // Field value:Ljava/lang/Number;
     141: goto          234
     144: aload_0
     145: aload_2
     146: lload_3
     147: invokevirtual #18                 // Method jnr/ffi/Pointer.getLongLong:(J)J
     150: invokestatic  #17                 // Method java/lang/Long.valueOf:(J)Ljava/lang/Long;
     153: putfield      #12                 // Field value:Ljava/lang/Number;
     156: goto          234
     159: aload_0
     160: aload_2
     161: lload_3
     162: invokevirtual #19                 // Method jnr/ffi/Pointer.getAddress:(J)J
     165: invokestatic  #17                 // Method java/lang/Long.valueOf:(J)Ljava/lang/Long;
     168: putfield      #12                 // Field value:Ljava/lang/Number;
     171: goto          234
     174: aload_0
     175: aload_2
     176: lload_3
     177: invokevirtual #20                 // Method jnr/ffi/Pointer.getFloat:(J)F
     180: invokestatic  #21                 // Method java/lang/Float.valueOf:(F)Ljava/lang/Float;
     183: putfield      #12                 // Field value:Ljava/lang/Number;
     186: goto          234
     189: aload_0
     190: aload_2
     191: lload_3
     192: invokevirtual #22                 // Method jnr/ffi/Pointer.getDouble:(J)D
     195: invokestatic  #23                 // Method java/lang/Double.valueOf:(D)Ljava/lang/Double;
     198: putfield      #12                 // Field value:Ljava/lang/Number;
     201: goto          234
     204: new           #24                 // class java/lang/UnsupportedOperationException
     207: dup
     208: new           #25                 // class java/lang/StringBuilder
     211: dup
     212: invokespecial #26                 // Method java/lang/StringBuilder."<init>":()V
     215: ldc           #27                 // String unsupported type:
     217: invokevirtual #28                 // Method java/lang/StringBuilder.append:(Ljava/lang/String;)Ljava/lang/StringBuilder;
     220: aload_0
     221: getfield      #3                  // Field typeAlias:Ljnr/ffi/TypeAlias;
     224: invokevirtual #29                 // Method java/lang/StringBuilder.append:(Ljava/lang/Object;)Ljava/lang/StringBuilder;
     227: invokevirtual #30                 // Method java/lang/StringBuilder.toString:()Ljava/lang/String;
     230: invokespecial #31                 // Method java/lang/UnsupportedOperationException."<init>":(Ljava/lang/String;)V
     233: athrow
     234: return

  public void toNative(jnr.ffi.Runtime, jnr.ffi.Pointer, long);
    Code:
       0: getstatic     #7                  // Field jnr/ffi/byref/NumberByReference$1.$SwitchMap$jnr$ffi$NativeType:[I
       3: aload_1
       4: aload_0
       5: getfield      #3                  // Field typeAlias:Ljnr/ffi/TypeAlias;
       8: invokevirtual #5                  // Method jnr/ffi/Runtime.findType:(Ljnr/ffi/TypeAlias;)Ljnr/ffi/Type;
      11: invokevirtual #8                  // Method jnr/ffi/Type.getNativeType:()Ljnr/ffi/NativeType;
      14: invokevirtual #9                  // Method jnr/ffi/NativeType.ordinal:()I
      17: iaload
      18: tableswitch   { // 1 to 13
                     1: 84
                     2: 84
                     3: 99
                     4: 99
                     5: 114
                     6: 114
                     7: 129
                     8: 129
                     9: 144
                    10: 144
                    11: 159
                    12: 174
                    13: 189
               default: 204
          }
      84: aload_2
      85: lload_3
      86: aload_0
      87: getfield      #12                 // Field value:Ljava/lang/Number;
      90: invokevirtual #32                 // Method java/lang/Number.byteValue:()B
      93: invokevirtual #33                 // Method jnr/ffi/Pointer.putByte:(JB)V
      96: goto          234
      99: aload_2
     100: lload_3
     101: aload_0
     102: getfield      #12                 // Field value:Ljava/lang/Number;
     105: invokevirtual #34                 // Method java/lang/Number.shortValue:()S
     108: invokevirtual #35                 // Method jnr/ffi/Pointer.putShort:(JS)V
     111: goto          234
     114: aload_2
     115: lload_3
     116: aload_0
     117: getfield      #12                 // Field value:Ljava/lang/Number;
     120: invokevirtual #36                 // Method java/lang/Number.intValue:()I
     123: invokevirtual #37                 // Method jnr/ffi/Pointer.putInt:(JI)V
     126: goto          234
     129: aload_2
     130: lload_3
     131: aload_0
     132: getfield      #12                 // Field value:Ljava/lang/Number;
     135: invokevirtual #38                 // Method java/lang/Number.longValue:()J
     138: invokevirtual #39                 // Method jnr/ffi/Pointer.putLong:(JJ)V
     141: goto          234
     144: aload_2
     145: lload_3
     146: aload_0
     147: getfield      #12                 // Field value:Ljava/lang/Number;
     150: invokevirtual #38                 // Method java/lang/Number.longValue:()J
     153: invokevirtual #40                 // Method jnr/ffi/Pointer.putLongLong:(JJ)V
     156: goto          234
     159: aload_2
     160: lload_3
     161: aload_0
     162: getfield      #12                 // Field value:Ljava/lang/Number;
     165: invokevirtual #38                 // Method java/lang/Number.longValue:()J
     168: invokevirtual #41                 // Method jnr/ffi/Pointer.putAddress:(JJ)V
     171: goto          234
     174: aload_2
     175: lload_3
     176: aload_0
     177: getfield      #12                 // Field value:Ljava/lang/Number;
     180: invokevirtual #42                 // Method java/lang/Number.floatValue:()F
     183: invokevirtual #43                 // Method jnr/ffi/Pointer.putFloat:(JF)V
     186: goto          234
     189: aload_2
     190: lload_3
     191: aload_0
     192: getfield      #12                 // Field value:Ljava/lang/Number;
     195: invokevirtual #44                 // Method java/lang/Number.doubleValue:()D
     198: invokevirtual #45                 // Method jnr/ffi/Pointer.putDouble:(JD)V
     201: goto          234
     204: new           #24                 // class java/lang/UnsupportedOperationException
     207: dup
     208: new           #25                 // class java/lang/StringBuilder
     211: dup
     212: invokespecial #26                 // Method java/lang/StringBuilder."<init>":()V
     215: ldc           #27                 // String unsupported type:
     217: invokevirtual #28                 // Method java/lang/StringBuilder.append:(Ljava/lang/String;)Ljava/lang/StringBuilder;
     220: aload_0
     221: getfield      #3                  // Field typeAlias:Ljnr/ffi/TypeAlias;
     224: invokevirtual #29                 // Method java/lang/StringBuilder.append:(Ljava/lang/Object;)Ljava/lang/StringBuilder;
     227: invokevirtual #30                 // Method java/lang/StringBuilder.toString:()Ljava/lang/String;
     230: invokespecial #31                 // Method java/lang/UnsupportedOperationException."<init>":(Ljava/lang/String;)V
     233: athrow
     234: return
}
