Compiled from "MessagePropertiesMetaData.java"
public class org.jboss.metadata.ejb.jboss.MessagePropertiesMetaData extends org.jboss.metadata.javaee.support.IdMetaDataImpl {
  private org.jboss.metadata.ejb.jboss.MethodAttributeMetaData method;

  private java.lang.String delivery;

  private java.lang.Integer priority;

  private java.lang.String className;

  public org.jboss.metadata.ejb.jboss.MessagePropertiesMetaData();
    Code:
       0: aload_0
       1: invokespecial #1                  // Method org/jboss/metadata/javaee/support/IdMetaDataImpl."<init>":()V
       4: return

  public org.jboss.metadata.ejb.jboss.MethodAttributeMetaData getMethod();
    Code:
       0: aload_0
       1: getfield      #2                  // Field method:Lorg/jboss/metadata/ejb/jboss/MethodAttributeMetaData;
       4: areturn

  public void setMethod(org.jboss.metadata.ejb.jboss.MethodAttributeMetaData);
    Code:
       0: aload_0
       1: aload_1
       2: putfield      #2                  // Field method:Lorg/jboss/metadata/ejb/jboss/MethodAttributeMetaData;
       5: return

  public java.lang.String getDelivery();
    Code:
       0: aload_0
       1: getfield      #3                  // Field delivery:Ljava/lang/String;
       4: areturn

  public void setDelivery(java.lang.String);
    Code:
       0: aload_0
       1: aload_1
       2: putfield      #3                  // Field delivery:Ljava/lang/String;
       5: return

  public java.lang.String getClassName();
    Code:
       0: aload_0
       1: getfield      #4                  // Field className:Ljava/lang/String;
       4: areturn

  public void setClassName(java.lang.String);
    Code:
       0: aload_0
       1: aload_1
       2: putfield      #4                  // Field className:Ljava/lang/String;
       5: return

  public java.lang.Integer getPriority();
    Code:
       0: aload_0
       1: getfield      #5                  // Field priority:Ljava/lang/Integer;
       4: areturn

  public void setPriority(java.lang.Integer);
    Code:
       0: aload_0
       1: aload_1
       2: putfield      #5                  // Field priority:Ljava/lang/Integer;
       5: return

  public java.lang.String toString();
    Code:
       0: new           #6                  // class java/lang/StringBuffer
       3: dup
       4: bipush        100
       6: invokespecial #7                  // Method java/lang/StringBuffer."<init>":(I)V
       9: astore_1
      10: aload_1
      11: ldc           #8                  // String [
      13: invokevirtual #9                  // Method java/lang/StringBuffer.append:(Ljava/lang/String;)Ljava/lang/StringBuffer;
      16: pop
      17: aload_1
      18: ldc           #10                 // String className=
      20: invokevirtual #9                  // Method java/lang/StringBuffer.append:(Ljava/lang/String;)Ljava/lang/StringBuffer;
      23: aload_0
      24: getfield      #4                  // Field className:Ljava/lang/String;
      27: invokevirtual #9                  // Method java/lang/StringBuffer.append:(Ljava/lang/String;)Ljava/lang/StringBuffer;
      30: pop
      31: aload_1
      32: ldc           #11                 // String , priority=
      34: invokevirtual #9                  // Method java/lang/StringBuffer.append:(Ljava/lang/String;)Ljava/lang/StringBuffer;
      37: aload_0
      38: getfield      #5                  // Field priority:Ljava/lang/Integer;
      41: invokevirtual #12                 // Method java/lang/StringBuffer.append:(Ljava/lang/Object;)Ljava/lang/StringBuffer;
      44: pop
      45: aload_1
      46: ldc           #13                 // String , delivery=
      48: invokevirtual #9                  // Method java/lang/StringBuffer.append:(Ljava/lang/String;)Ljava/lang/StringBuffer;
      51: aload_0
      52: getfield      #3                  // Field delivery:Ljava/lang/String;
      55: invokevirtual #9                  // Method java/lang/StringBuffer.append:(Ljava/lang/String;)Ljava/lang/StringBuffer;
      58: pop
      59: aload_1
      60: ldc           #14                 // String , method=
      62: invokevirtual #9                  // Method java/lang/StringBuffer.append:(Ljava/lang/String;)Ljava/lang/StringBuffer;
      65: aload_0
      66: getfield      #2                  // Field method:Lorg/jboss/metadata/ejb/jboss/MethodAttributeMetaData;
      69: invokevirtual #12                 // Method java/lang/StringBuffer.append:(Ljava/lang/Object;)Ljava/lang/StringBuffer;
      72: pop
      73: aload_1
      74: ldc           #15                 // String ]
      76: invokevirtual #9                  // Method java/lang/StringBuffer.append:(Ljava/lang/String;)Ljava/lang/StringBuffer;
      79: pop
      80: aload_1
      81: invokevirtual #16                 // Method java/lang/StringBuffer.toString:()Ljava/lang/String;
      84: areturn
}
