Compiled from "GetUserIdRet.java"
class cicada.authorization.config.GetUserIdRet$GetUserIdRetTupleScheme extends org.apache.thrift.scheme.TupleScheme<cicada.authorization.config.GetUserIdRet> {
  private cicada.authorization.config.GetUserIdRet$GetUserIdRetTupleScheme();
    Code:
       0: aload_0
       1: invokespecial #2                  // Method org/apache/thrift/scheme/TupleScheme."<init>":()V
       4: return

  public void write(org.apache.thrift.protocol.TProtocol, cicada.authorization.config.GetUserIdRet) throws org.apache.thrift.TException;
    Code:
       0: aload_1
       1: checkcast     #3                  // class org/apache/thrift/protocol/TTupleProtocol
       4: astore_3
       5: new           #4                  // class java/util/BitSet
       8: dup
       9: invokespecial #5                  // Method java/util/BitSet."<init>":()V
      12: astore        4
      14: aload_2
      15: invokevirtual #6                  // Method cicada/authorization/config/GetUserIdRet.isSetStatus:()Z
      18: ifeq          27
      21: aload         4
      23: iconst_0
      24: invokevirtual #7                  // Method java/util/BitSet.set:(I)V
      27: aload_2
      28: invokevirtual #8                  // Method cicada/authorization/config/GetUserIdRet.isSetUserId:()Z
      31: ifeq          40
      34: aload         4
      36: iconst_1
      37: invokevirtual #7                  // Method java/util/BitSet.set:(I)V
      40: aload_2
      41: invokevirtual #9                  // Method cicada/authorization/config/GetUserIdRet.isSetUserType:()Z
      44: ifeq          53
      47: aload         4
      49: iconst_2
      50: invokevirtual #7                  // Method java/util/BitSet.set:(I)V
      53: aload_3
      54: aload         4
      56: iconst_3
      57: invokevirtual #10                 // Method org/apache/thrift/protocol/TTupleProtocol.writeBitSet:(Ljava/util/BitSet;I)V
      60: aload_2
      61: invokevirtual #6                  // Method cicada/authorization/config/GetUserIdRet.isSetStatus:()Z
      64: ifeq          78
      67: aload_3
      68: aload_2
      69: getfield      #11                 // Field cicada/authorization/config/GetUserIdRet.status:Lcicada/authorization/config/GetUserIdStatus;
      72: invokevirtual #12                 // Method cicada/authorization/config/GetUserIdStatus.getValue:()I
      75: invokevirtual #13                 // Method org/apache/thrift/protocol/TTupleProtocol.writeI32:(I)V
      78: aload_2
      79: invokevirtual #8                  // Method cicada/authorization/config/GetUserIdRet.isSetUserId:()Z
      82: ifeq          93
      85: aload_3
      86: aload_2
      87: getfield      #14                 // Field cicada/authorization/config/GetUserIdRet.userId:Ljava/lang/String;
      90: invokevirtual #15                 // Method org/apache/thrift/protocol/TTupleProtocol.writeString:(Ljava/lang/String;)V
      93: aload_2
      94: invokevirtual #9                  // Method cicada/authorization/config/GetUserIdRet.isSetUserType:()Z
      97: ifeq          108
     100: aload_3
     101: aload_2
     102: getfield      #16                 // Field cicada/authorization/config/GetUserIdRet.userType:I
     105: invokevirtual #13                 // Method org/apache/thrift/protocol/TTupleProtocol.writeI32:(I)V
     108: return

  public void read(org.apache.thrift.protocol.TProtocol, cicada.authorization.config.GetUserIdRet) throws org.apache.thrift.TException;
    Code:
       0: aload_1
       1: checkcast     #3                  // class org/apache/thrift/protocol/TTupleProtocol
       4: astore_3
       5: aload_3
       6: iconst_3
       7: invokevirtual #17                 // Method org/apache/thrift/protocol/TTupleProtocol.readBitSet:(I)Ljava/util/BitSet;
      10: astore        4
      12: aload         4
      14: iconst_0
      15: invokevirtual #18                 // Method java/util/BitSet.get:(I)Z
      18: ifeq          37
      21: aload_2
      22: aload_3
      23: invokevirtual #19                 // Method org/apache/thrift/protocol/TTupleProtocol.readI32:()I
      26: invokestatic  #20                 // Method cicada/authorization/config/GetUserIdStatus.findByValue:(I)Lcicada/authorization/config/GetUserIdStatus;
      29: putfield      #11                 // Field cicada/authorization/config/GetUserIdRet.status:Lcicada/authorization/config/GetUserIdStatus;
      32: aload_2
      33: iconst_1
      34: invokevirtual #21                 // Method cicada/authorization/config/GetUserIdRet.setStatusIsSet:(Z)V
      37: aload         4
      39: iconst_1
      40: invokevirtual #18                 // Method java/util/BitSet.get:(I)Z
      43: ifeq          59
      46: aload_2
      47: aload_3
      48: invokevirtual #22                 // Method org/apache/thrift/protocol/TTupleProtocol.readString:()Ljava/lang/String;
      51: putfield      #14                 // Field cicada/authorization/config/GetUserIdRet.userId:Ljava/lang/String;
      54: aload_2
      55: iconst_1
      56: invokevirtual #23                 // Method cicada/authorization/config/GetUserIdRet.setUserIdIsSet:(Z)V
      59: aload         4
      61: iconst_2
      62: invokevirtual #18                 // Method java/util/BitSet.get:(I)Z
      65: ifeq          81
      68: aload_2
      69: aload_3
      70: invokevirtual #19                 // Method org/apache/thrift/protocol/TTupleProtocol.readI32:()I
      73: putfield      #16                 // Field cicada/authorization/config/GetUserIdRet.userType:I
      76: aload_2
      77: iconst_1
      78: invokevirtual #24                 // Method cicada/authorization/config/GetUserIdRet.setUserTypeIsSet:(Z)V
      81: return

  public void write(org.apache.thrift.protocol.TProtocol, org.apache.thrift.TBase) throws org.apache.thrift.TException;
    Code:
       0: aload_0
       1: aload_1
       2: aload_2
       3: checkcast     #25                 // class cicada/authorization/config/GetUserIdRet
       6: invokevirtual #26                 // Method write:(Lorg/apache/thrift/protocol/TProtocol;Lcicada/authorization/config/GetUserIdRet;)V
       9: return

  public void read(org.apache.thrift.protocol.TProtocol, org.apache.thrift.TBase) throws org.apache.thrift.TException;
    Code:
       0: aload_0
       1: aload_1
       2: aload_2
       3: checkcast     #25                 // class cicada/authorization/config/GetUserIdRet
       6: invokevirtual #27                 // Method read:(Lorg/apache/thrift/protocol/TProtocol;Lcicada/authorization/config/GetUserIdRet;)V
       9: return

  cicada.authorization.config.GetUserIdRet$GetUserIdRetTupleScheme(cicada.authorization.config.GetUserIdRet$1);
    Code:
       0: aload_0
       1: invokespecial #1                  // Method "<init>":()V
       4: return
}
