Compiled from "UserSessionService.java"
public class cicada.authorization.config.UserSessionService$Processor$CreateSession<I extends cicada.authorization.config.UserSessionService$Iface> extends org.apache.thrift.ProcessFunction<I, cicada.authorization.config.UserSessionService$CreateSession_args> {
  public cicada.authorization.config.UserSessionService$Processor$CreateSession();
    Code:
       0: aload_0
       1: ldc           #1                  // String CreateSession
       3: invokespecial #2                  // Method org/apache/thrift/ProcessFunction."<init>":(Ljava/lang/String;)V
       6: return

  public cicada.authorization.config.UserSessionService$CreateSession_args getEmptyArgsInstance();
    Code:
       0: new           #3                  // class cicada/authorization/config/UserSessionService$CreateSession_args
       3: dup
       4: invokespecial #4                  // Method cicada/authorization/config/UserSessionService$CreateSession_args."<init>":()V
       7: areturn

  protected boolean isOneway();
    Code:
       0: iconst_0
       1: ireturn

  public cicada.authorization.config.UserSessionService$CreateSession_result getResult(I, cicada.authorization.config.UserSessionService$CreateSession_args) throws org.apache.thrift.TException;
    Code:
       0: new           #5                  // class cicada/authorization/config/UserSessionService$CreateSession_result
       3: dup
       4: invokespecial #6                  // Method cicada/authorization/config/UserSessionService$CreateSession_result."<init>":()V
       7: astore_3
       8: aload_3
       9: aload_1
      10: aload_2
      11: getfield      #7                  // Field cicada/authorization/config/UserSessionService$CreateSession_args.userId:Ljava/lang/String;
      14: aload_2
      15: getfield      #8                  // Field cicada/authorization/config/UserSessionService$CreateSession_args.userType:I
      18: aload_2
      19: getfield      #9                  // Field cicada/authorization/config/UserSessionService$CreateSession_args.loginFrom:Ljava/lang/String;
      22: invokeinterface #10,  4           // InterfaceMethod cicada/authorization/config/UserSessionService$Iface.CreateSession:(Ljava/lang/String;ILjava/lang/String;)Lcicada/authorization/config/CreateSessionRet;
      27: putfield      #11                 // Field cicada/authorization/config/UserSessionService$CreateSession_result.success:Lcicada/authorization/config/CreateSessionRet;
      30: aload_3
      31: areturn

  public org.apache.thrift.TBase getEmptyArgsInstance();
    Code:
       0: aload_0
       1: invokevirtual #12                 // Method getEmptyArgsInstance:()Lcicada/authorization/config/UserSessionService$CreateSession_args;
       4: areturn

  public org.apache.thrift.TBase getResult(java.lang.Object, org.apache.thrift.TBase) throws org.apache.thrift.TException;
    Code:
       0: aload_0
       1: aload_1
       2: checkcast     #13                 // class cicada/authorization/config/UserSessionService$Iface
       5: aload_2
       6: checkcast     #3                  // class cicada/authorization/config/UserSessionService$CreateSession_args
       9: invokevirtual #14                 // Method getResult:(Lcicada/authorization/config/UserSessionService$Iface;Lcicada/authorization/config/UserSessionService$CreateSession_args;)Lcicada/authorization/config/UserSessionService$CreateSession_result;
      12: areturn
}
