Compiled from "ClusterState.java"
public class org.apache.solr.common.cloud.ClusterState$CollectionRef {
  protected final java.util.concurrent.atomic.AtomicInteger gets;

  private final org.apache.solr.common.cloud.DocCollection coll;

  public int getCount();
    Code:
       0: aload_0
       1: getfield      #1                  // Field gets:Ljava/util/concurrent/atomic/AtomicInteger;
       4: invokevirtual #2                  // Method java/util/concurrent/atomic/AtomicInteger.get:()I
       7: ireturn

  public org.apache.solr.common.cloud.ClusterState$CollectionRef(org.apache.solr.common.cloud.DocCollection);
    Code:
       0: aload_0
       1: invokespecial #3                  // Method java/lang/Object."<init>":()V
       4: aload_0
       5: new           #4                  // class java/util/concurrent/atomic/AtomicInteger
       8: dup
       9: invokespecial #5                  // Method java/util/concurrent/atomic/AtomicInteger."<init>":()V
      12: putfield      #1                  // Field gets:Ljava/util/concurrent/atomic/AtomicInteger;
      15: aload_0
      16: aload_1
      17: putfield      #6                  // Field coll:Lorg/apache/solr/common/cloud/DocCollection;
      20: return

  public org.apache.solr.common.cloud.DocCollection get();
    Code:
       0: aload_0
       1: getfield      #1                  // Field gets:Ljava/util/concurrent/atomic/AtomicInteger;
       4: invokevirtual #7                  // Method java/util/concurrent/atomic/AtomicInteger.incrementAndGet:()I
       7: pop
       8: aload_0
       9: getfield      #6                  // Field coll:Lorg/apache/solr/common/cloud/DocCollection;
      12: areturn

  public boolean isLazilyLoaded();
    Code:
       0: iconst_0
       1: ireturn

  public java.lang.String toString();
    Code:
       0: aload_0
       1: getfield      #6                  // Field coll:Lorg/apache/solr/common/cloud/DocCollection;
       4: ifnull        15
       7: aload_0
       8: getfield      #6                  // Field coll:Lorg/apache/solr/common/cloud/DocCollection;
      11: invokevirtual #8                  // Method org/apache/solr/common/cloud/DocCollection.toString:()Ljava/lang/String;
      14: areturn
      15: ldc           #9                  // String null DocCollection ref
      17: areturn
}
