Compiled from "ConnectionManager.java"
class org.apache.solr.common.cloud.ConnectionManager$1 extends org.apache.solr.common.cloud.ZkClientConnectionStrategy$ZkUpdate {
  final org.apache.solr.common.cloud.ConnectionManager this$0;

  org.apache.solr.common.cloud.ConnectionManager$1(org.apache.solr.common.cloud.ConnectionManager);
    Code:
       0: aload_0
       1: aload_1
       2: putfield      #1                  // Field this$0:Lorg/apache/solr/common/cloud/ConnectionManager;
       5: aload_0
       6: invokespecial #2                  // Method org/apache/solr/common/cloud/ZkClientConnectionStrategy$ZkUpdate."<init>":()V
       9: return

  public void update(org.apache.solr.common.cloud.SolrZooKeeper);
    Code:
       0: aload_0
       1: getfield      #1                  // Field this$0:Lorg/apache/solr/common/cloud/ConnectionManager;
       4: ldc2_w        #4                  // long 9223372036854775807l
       7: invokevirtual #6                  // Method org/apache/solr/common/cloud/ConnectionManager.waitForConnected:(J)V
      10: goto          31
      13: astore_2
      14: aload_0
      15: getfield      #1                  // Field this$0:Lorg/apache/solr/common/cloud/ConnectionManager;
      18: aload_1
      19: invokestatic  #8                  // Method org/apache/solr/common/cloud/ConnectionManager.access$200:(Lorg/apache/solr/common/cloud/ConnectionManager;Lorg/apache/solr/common/cloud/SolrZooKeeper;)V
      22: new           #9                  // class java/lang/RuntimeException
      25: dup
      26: aload_2
      27: invokespecial #10                 // Method java/lang/RuntimeException."<init>":(Ljava/lang/Throwable;)V
      30: athrow
      31: invokestatic  #11                 // Method org/apache/solr/common/cloud/ConnectionManager.access$300:()Lorg/slf4j/Logger;
      34: ldc           #12                 // String Connection with ZooKeeper reestablished.
      36: invokeinterface #13,  2           // InterfaceMethod org/slf4j/Logger.info:(Ljava/lang/String;)V
      41: aload_0
      42: getfield      #1                  // Field this$0:Lorg/apache/solr/common/cloud/ConnectionManager;
      45: invokestatic  #14                 // Method org/apache/solr/common/cloud/ConnectionManager.access$400:(Lorg/apache/solr/common/cloud/ConnectionManager;)Lorg/apache/solr/common/cloud/SolrZkClient;
      48: aload_1
      49: invokevirtual #15                 // Method org/apache/solr/common/cloud/SolrZkClient.updateKeeper:(Lorg/apache/solr/common/cloud/SolrZooKeeper;)V
      52: goto          97
      55: astore_2
      56: aload_0
      57: getfield      #1                  // Field this$0:Lorg/apache/solr/common/cloud/ConnectionManager;
      60: aload_1
      61: invokestatic  #8                  // Method org/apache/solr/common/cloud/ConnectionManager.access$200:(Lorg/apache/solr/common/cloud/ConnectionManager;Lorg/apache/solr/common/cloud/SolrZooKeeper;)V
      64: invokestatic  #17                 // Method java/lang/Thread.currentThread:()Ljava/lang/Thread;
      67: invokevirtual #18                 // Method java/lang/Thread.interrupt:()V
      70: new           #9                  // class java/lang/RuntimeException
      73: dup
      74: aload_2
      75: invokespecial #10                 // Method java/lang/RuntimeException."<init>":(Ljava/lang/Throwable;)V
      78: athrow
      79: astore_2
      80: aload_0
      81: getfield      #1                  // Field this$0:Lorg/apache/solr/common/cloud/ConnectionManager;
      84: aload_1
      85: invokestatic  #8                  // Method org/apache/solr/common/cloud/ConnectionManager.access$200:(Lorg/apache/solr/common/cloud/ConnectionManager;Lorg/apache/solr/common/cloud/SolrZooKeeper;)V
      88: new           #9                  // class java/lang/RuntimeException
      91: dup
      92: aload_2
      93: invokespecial #10                 // Method java/lang/RuntimeException."<init>":(Ljava/lang/Throwable;)V
      96: athrow
      97: aload_0
      98: getfield      #1                  // Field this$0:Lorg/apache/solr/common/cloud/ConnectionManager;
     101: invokestatic  #19                 // Method org/apache/solr/common/cloud/ConnectionManager.access$500:(Lorg/apache/solr/common/cloud/ConnectionManager;)Lorg/apache/solr/common/cloud/OnReconnect;
     104: ifnull        119
     107: aload_0
     108: getfield      #1                  // Field this$0:Lorg/apache/solr/common/cloud/ConnectionManager;
     111: invokestatic  #19                 // Method org/apache/solr/common/cloud/ConnectionManager.access$500:(Lorg/apache/solr/common/cloud/ConnectionManager;)Lorg/apache/solr/common/cloud/OnReconnect;
     114: invokeinterface #20,  1           // InterfaceMethod org/apache/solr/common/cloud/OnReconnect.command:()V
     119: return
    Exception table:
       from    to  target type
           0    10    13   Class java/lang/Exception
          41    52    55   Class java/lang/InterruptedException
          41    52    79   Class java/lang/Exception
}
