Compiled from "MpmcArrayQueue.java"
public class io.netty.util.internal.shaded.org.jctools.queues.MpmcArrayQueue<E> extends io.netty.util.internal.shaded.org.jctools.queues.MpmcArrayQueueConsumerField<E> implements io.netty.util.internal.shaded.org.jctools.queues.QueueProgressIndicators {
  long p01;

  long p02;

  long p03;

  long p04;

  long p05;

  long p06;

  long p07;

  long p10;

  long p11;

  long p12;

  long p13;

  long p14;

  long p15;

  long p16;

  long p17;

  static final int RECOMENDED_POLL_BATCH;

  static final int RECOMENDED_OFFER_BATCH;

  static final boolean $assertionsDisabled;

  public io.netty.util.internal.shaded.org.jctools.queues.MpmcArrayQueue(int);
    Code:
       0: aload_0
       1: iload_1
       2: invokestatic  #49                 // Method validateCapacity:(I)I
       5: invokespecial #51                 // Method io/netty/util/internal/shaded/org/jctools/queues/MpmcArrayQueueConsumerField."<init>":(I)V
       8: return

  private static int validateCapacity(int);
    Code:
       0: iload_0
       1: iconst_2
       2: if_icmpge     15
       5: new           #57                 // class java/lang/IllegalArgumentException
       8: dup
       9: ldc           #59                 // String Minimum size is 2
      11: invokespecial #62                 // Method java/lang/IllegalArgumentException."<init>":(Ljava/lang/String;)V
      14: athrow
      15: iload_0
      16: ireturn

  public boolean offer(E);
    Code:
       0: aconst_null
       1: aload_1
       2: if_acmpne     13
       5: new           #66                 // class java/lang/NullPointerException
       8: dup
       9: invokespecial #69                 // Method java/lang/NullPointerException."<init>":()V
      12: athrow
      13: aload_0
      14: getfield      #72                 // Field mask:J
      17: lstore_2
      18: lload_2
      19: lconst_1
      20: ladd
      21: lstore        4
      23: aload_0
      24: getfield      #76                 // Field sequenceBuffer:[J
      27: astore        6
      29: ldc2_w        #77                 // long 9223372036854775807l
      32: lstore        7
      34: aload_0
      35: invokevirtual #85                 // Method lvProducerIndex:()J
      38: lstore        9
      40: lload         9
      42: lload_2
      43: invokestatic  #89                 // Method calcSequenceOffset:(JJ)J
      46: lstore        11
      48: aload_0
      49: aload         6
      51: lload         11
      53: invokevirtual #93                 // Method lvSequence:([JJ)J
      56: lstore        13
      58: lload         13
      60: lload         9
      62: lcmp
      63: ifge          101
      66: lload         9
      68: lload         4
      70: lsub
      71: lload         7
      73: lcmp
      74: ifgt          95
      77: lload         9
      79: lload         4
      81: lsub
      82: aload_0
      83: invokevirtual #96                 // Method lvConsumerIndex:()J
      86: dup2
      87: lstore        7
      89: lcmp
      90: ifgt          95
      93: iconst_0
      94: ireturn
      95: lload         9
      97: lconst_1
      98: ladd
      99: lstore        13
     101: lload         13
     103: lload         9
     105: lcmp
     106: ifgt          34
     109: aload_0
     110: lload         9
     112: lload         9
     114: lconst_1
     115: ladd
     116: invokevirtual #100                // Method casProducerIndex:(JJ)Z
     119: ifeq          34
     122: getstatic     #102                // Field $assertionsDisabled:Z
     125: ifne          153
     128: aconst_null
     129: aload_0
     130: getfield      #106                // Field buffer:[Ljava/lang/Object;
     133: lload         9
     135: lload_2
     136: invokestatic  #109                // Method calcElementOffset:(JJ)J
     139: invokestatic  #115                // Method io/netty/util/internal/shaded/org/jctools/util/UnsafeRefArrayAccess.lpElement:([Ljava/lang/Object;J)Ljava/lang/Object;
     142: if_acmpeq     153
     145: new           #117                // class java/lang/AssertionError
     148: dup
     149: invokespecial #118                // Method java/lang/AssertionError."<init>":()V
     152: athrow
     153: aload_0
     154: getfield      #106                // Field buffer:[Ljava/lang/Object;
     157: lload         9
     159: lload_2
     160: invokestatic  #109                // Method calcElementOffset:(JJ)J
     163: aload_1
     164: invokestatic  #122                // Method io/netty/util/internal/shaded/org/jctools/util/UnsafeRefArrayAccess.soElement:([Ljava/lang/Object;JLjava/lang/Object;)V
     167: aload_0
     168: aload         6
     170: lload         11
     172: lload         9
     174: lconst_1
     175: ladd
     176: invokevirtual #126                // Method soSequence:([JJJ)V
     179: iconst_1
     180: ireturn

  public E poll();
    Code:
       0: aload_0
       1: getfield      #76                 // Field sequenceBuffer:[J
       4: astore_1
       5: aload_0
       6: getfield      #72                 // Field mask:J
       9: lstore_2
      10: ldc2_w        #137                // long -1l
      13: lstore        4
      15: aload_0
      16: invokevirtual #96                 // Method lvConsumerIndex:()J
      19: lstore        6
      21: lload         6
      23: lload_2
      24: invokestatic  #89                 // Method calcSequenceOffset:(JJ)J
      27: lstore        8
      29: aload_0
      30: aload_1
      31: lload         8
      33: invokevirtual #93                 // Method lvSequence:([JJ)J
      36: lstore        10
      38: lload         6
      40: lconst_1
      41: ladd
      42: lstore        12
      44: lload         10
      46: lload         12
      48: lcmp
      49: ifge          81
      52: lload         6
      54: lload         4
      56: lcmp
      57: iflt          75
      60: lload         6
      62: aload_0
      63: invokevirtual #85                 // Method lvProducerIndex:()J
      66: dup2
      67: lstore        4
      69: lcmp
      70: ifne          75
      73: aconst_null
      74: areturn
      75: lload         12
      77: lconst_1
      78: ladd
      79: lstore        10
      81: lload         10
      83: lload         12
      85: lcmp
      86: ifgt          15
      89: aload_0
      90: lload         6
      92: lload         6
      94: lconst_1
      95: ladd
      96: invokevirtual #141                // Method casConsumerIndex:(JJ)Z
      99: ifeq          15
     102: lload         6
     104: lload_2
     105: invokestatic  #109                // Method calcElementOffset:(JJ)J
     108: lstore        14
     110: aload_0
     111: getfield      #106                // Field buffer:[Ljava/lang/Object;
     114: lload         14
     116: invokestatic  #115                // Method io/netty/util/internal/shaded/org/jctools/util/UnsafeRefArrayAccess.lpElement:([Ljava/lang/Object;J)Ljava/lang/Object;
     119: astore        16
     121: getstatic     #102                // Field $assertionsDisabled:Z
     124: ifne          140
     127: aload         16
     129: ifnonnull     140
     132: new           #117                // class java/lang/AssertionError
     135: dup
     136: invokespecial #118                // Method java/lang/AssertionError."<init>":()V
     139: athrow
     140: aload_0
     141: getfield      #106                // Field buffer:[Ljava/lang/Object;
     144: lload         14
     146: aconst_null
     147: invokestatic  #122                // Method io/netty/util/internal/shaded/org/jctools/util/UnsafeRefArrayAccess.soElement:([Ljava/lang/Object;JLjava/lang/Object;)V
     150: aload_0
     151: aload_1
     152: lload         8
     154: lload         6
     156: lload_2
     157: ladd
     158: lconst_1
     159: ladd
     160: invokevirtual #126                // Method soSequence:([JJJ)V
     163: aload         16
     165: areturn

  public E peek();
    Code:
       0: aload_0
       1: invokevirtual #96                 // Method lvConsumerIndex:()J
       4: lstore_1
       5: aload_0
       6: getfield      #106                // Field buffer:[Ljava/lang/Object;
       9: aload_0
      10: lload_1
      11: invokevirtual #147                // Method calcElementOffset:(J)J
      14: invokestatic  #115                // Method io/netty/util/internal/shaded/org/jctools/util/UnsafeRefArrayAccess.lpElement:([Ljava/lang/Object;J)Ljava/lang/Object;
      17: astore_3
      18: aload_3
      19: ifnonnull     31
      22: lload_1
      23: aload_0
      24: invokevirtual #85                 // Method lvProducerIndex:()J
      27: lcmp
      28: ifne          0
      31: aload_3
      32: areturn

  public boolean relaxedOffer(E);
    Code:
       0: aconst_null
       1: aload_1
       2: if_acmpne     13
       5: new           #66                 // class java/lang/NullPointerException
       8: dup
       9: invokespecial #69                 // Method java/lang/NullPointerException."<init>":()V
      12: athrow
      13: aload_0
      14: getfield      #72                 // Field mask:J
      17: lstore_2
      18: aload_0
      19: getfield      #76                 // Field sequenceBuffer:[J
      22: astore        4
      24: aload_0
      25: invokevirtual #85                 // Method lvProducerIndex:()J
      28: lstore        5
      30: lload         5
      32: lload_2
      33: invokestatic  #89                 // Method calcSequenceOffset:(JJ)J
      36: lstore        7
      38: aload_0
      39: aload         4
      41: lload         7
      43: invokevirtual #93                 // Method lvSequence:([JJ)J
      46: lstore        9
      48: lload         9
      50: lload         5
      52: lcmp
      53: ifge          58
      56: iconst_0
      57: ireturn
      58: lload         9
      60: lload         5
      62: lcmp
      63: ifgt          24
      66: aload_0
      67: lload         5
      69: lload         5
      71: lconst_1
      72: ladd
      73: invokevirtual #100                // Method casProducerIndex:(JJ)Z
      76: ifeq          24
      79: aload_0
      80: getfield      #106                // Field buffer:[Ljava/lang/Object;
      83: lload         5
      85: lload_2
      86: invokestatic  #109                // Method calcElementOffset:(JJ)J
      89: aload_1
      90: invokestatic  #122                // Method io/netty/util/internal/shaded/org/jctools/util/UnsafeRefArrayAccess.soElement:([Ljava/lang/Object;JLjava/lang/Object;)V
      93: aload_0
      94: aload         4
      96: lload         7
      98: lload         5
     100: lconst_1
     101: ladd
     102: invokevirtual #126                // Method soSequence:([JJJ)V
     105: iconst_1
     106: ireturn

  public E relaxedPoll();
    Code:
       0: aload_0
       1: getfield      #76                 // Field sequenceBuffer:[J
       4: astore_1
       5: aload_0
       6: getfield      #72                 // Field mask:J
       9: lstore_2
      10: aload_0
      11: invokevirtual #96                 // Method lvConsumerIndex:()J
      14: lstore        4
      16: lload         4
      18: lload_2
      19: invokestatic  #89                 // Method calcSequenceOffset:(JJ)J
      22: lstore        6
      24: aload_0
      25: aload_1
      26: lload         6
      28: invokevirtual #93                 // Method lvSequence:([JJ)J
      31: lstore        8
      33: lload         4
      35: lconst_1
      36: ladd
      37: lstore        10
      39: lload         8
      41: lload         10
      43: lcmp
      44: ifge          49
      47: aconst_null
      48: areturn
      49: lload         8
      51: lload         10
      53: lcmp
      54: ifgt          10
      57: aload_0
      58: lload         4
      60: lload         4
      62: lconst_1
      63: ladd
      64: invokevirtual #141                // Method casConsumerIndex:(JJ)Z
      67: ifeq          10
      70: lload         4
      72: lload_2
      73: invokestatic  #109                // Method calcElementOffset:(JJ)J
      76: lstore        12
      78: aload_0
      79: getfield      #106                // Field buffer:[Ljava/lang/Object;
      82: lload         12
      84: invokestatic  #115                // Method io/netty/util/internal/shaded/org/jctools/util/UnsafeRefArrayAccess.lpElement:([Ljava/lang/Object;J)Ljava/lang/Object;
      87: astore        14
      89: aload_0
      90: getfield      #106                // Field buffer:[Ljava/lang/Object;
      93: lload         12
      95: aconst_null
      96: invokestatic  #122                // Method io/netty/util/internal/shaded/org/jctools/util/UnsafeRefArrayAccess.soElement:([Ljava/lang/Object;JLjava/lang/Object;)V
      99: aload_0
     100: aload_1
     101: lload         6
     103: lload         4
     105: lload_2
     106: ladd
     107: lconst_1
     108: ladd
     109: invokevirtual #126                // Method soSequence:([JJJ)V
     112: aload         14
     114: areturn

  public E relaxedPeek();
    Code:
       0: aload_0
       1: invokevirtual #96                 // Method lvConsumerIndex:()J
       4: lstore_1
       5: aload_0
       6: getfield      #106                // Field buffer:[Ljava/lang/Object;
       9: aload_0
      10: lload_1
      11: invokevirtual #147                // Method calcElementOffset:(J)J
      14: invokestatic  #115                // Method io/netty/util/internal/shaded/org/jctools/util/UnsafeRefArrayAccess.lpElement:([Ljava/lang/Object;J)Ljava/lang/Object;
      17: areturn

  public int drain(io.netty.util.internal.shaded.org.jctools.queues.MessagePassingQueue$Consumer<E>);
    Code:
       0: aload_0
       1: invokevirtual #156                // Method capacity:()I
       4: istore_2
       5: iconst_0
       6: istore_3
       7: iload_3
       8: iload_2
       9: if_icmpge     40
      12: iconst_0
      13: istore        4
      15: aload_0
      16: aload_1
      17: getstatic     #158                // Field RECOMENDED_POLL_BATCH:I
      20: invokevirtual #161                // Method drain:(Lio/netty/util/internal/shaded/org/jctools/queues/MessagePassingQueue$Consumer;I)I
      23: dup
      24: istore        4
      26: ifne          32
      29: goto          40
      32: iload_3
      33: iload         4
      35: iadd
      36: istore_3
      37: goto          7
      40: iload_3
      41: ireturn

  public int fill(io.netty.util.internal.shaded.org.jctools.queues.MessagePassingQueue$Supplier<E>);
    Code:
       0: lconst_0
       1: lstore_2
       2: aload_0
       3: invokevirtual #156                // Method capacity:()I
       6: istore        4
       8: aload_0
       9: aload_1
      10: getstatic     #170                // Field RECOMENDED_OFFER_BATCH:I
      13: invokevirtual #173                // Method fill:(Lio/netty/util/internal/shaded/org/jctools/queues/MessagePassingQueue$Supplier;I)I
      16: istore        5
      18: iload         5
      20: ifne          26
      23: lload_2
      24: l2i
      25: ireturn
      26: lload_2
      27: iload         5
      29: i2l
      30: ladd
      31: lstore_2
      32: lload_2
      33: iload         4
      35: i2l
      36: lcmp
      37: ifle          8
      40: lload_2
      41: l2i
      42: ireturn

  public int drain(io.netty.util.internal.shaded.org.jctools.queues.MessagePassingQueue$Consumer<E>, int);
    Code:
       0: aload_0
       1: getfield      #76                 // Field sequenceBuffer:[J
       4: astore_3
       5: aload_0
       6: getfield      #72                 // Field mask:J
       9: lstore        4
      11: aload_0
      12: getfield      #106                // Field buffer:[Ljava/lang/Object;
      15: astore        6
      17: iconst_0
      18: istore        7
      20: iload         7
      22: iload_2
      23: if_icmpge     142
      26: aload_0
      27: invokevirtual #96                 // Method lvConsumerIndex:()J
      30: lstore        8
      32: lload         8
      34: lload         4
      36: invokestatic  #89                 // Method calcSequenceOffset:(JJ)J
      39: lstore        10
      41: aload_0
      42: aload_3
      43: lload         10
      45: invokevirtual #93                 // Method lvSequence:([JJ)J
      48: lstore        12
      50: lload         8
      52: lconst_1
      53: ladd
      54: lstore        14
      56: lload         12
      58: lload         14
      60: lcmp
      61: ifge          67
      64: iload         7
      66: ireturn
      67: lload         12
      69: lload         14
      71: lcmp
      72: ifgt          26
      75: aload_0
      76: lload         8
      78: lload         8
      80: lconst_1
      81: ladd
      82: invokevirtual #141                // Method casConsumerIndex:(JJ)Z
      85: ifeq          26
      88: lload         8
      90: lload         4
      92: invokestatic  #109                // Method calcElementOffset:(JJ)J
      95: lstore        16
      97: aload         6
      99: lload         16
     101: invokestatic  #115                // Method io/netty/util/internal/shaded/org/jctools/util/UnsafeRefArrayAccess.lpElement:([Ljava/lang/Object;J)Ljava/lang/Object;
     104: astore        18
     106: aload         6
     108: lload         16
     110: aconst_null
     111: invokestatic  #122                // Method io/netty/util/internal/shaded/org/jctools/util/UnsafeRefArrayAccess.soElement:([Ljava/lang/Object;JLjava/lang/Object;)V
     114: aload_0
     115: aload_3
     116: lload         10
     118: lload         8
     120: lload         4
     122: ladd
     123: lconst_1
     124: ladd
     125: invokevirtual #126                // Method soSequence:([JJJ)V
     128: aload_1
     129: aload         18
     131: invokeinterface #183,  2          // InterfaceMethod io/netty/util/internal/shaded/org/jctools/queues/MessagePassingQueue$Consumer.accept:(Ljava/lang/Object;)V
     136: iinc          7, 1
     139: goto          20
     142: iload_2
     143: ireturn

  public int fill(io.netty.util.internal.shaded.org.jctools.queues.MessagePassingQueue$Supplier<E>, int);
    Code:
       0: aload_0
       1: getfield      #76                 // Field sequenceBuffer:[J
       4: astore_3
       5: aload_0
       6: getfield      #72                 // Field mask:J
       9: lstore        4
      11: aload_0
      12: getfield      #106                // Field buffer:[Ljava/lang/Object;
      15: astore        6
      17: iconst_0
      18: istore        7
      20: iload         7
      22: iload_2
      23: if_icmpge     117
      26: aload_0
      27: invokevirtual #85                 // Method lvProducerIndex:()J
      30: lstore        8
      32: lload         8
      34: lload         4
      36: invokestatic  #89                 // Method calcSequenceOffset:(JJ)J
      39: lstore        10
      41: aload_0
      42: aload_3
      43: lload         10
      45: invokevirtual #93                 // Method lvSequence:([JJ)J
      48: lstore        12
      50: lload         12
      52: lload         8
      54: lcmp
      55: ifge          61
      58: iload         7
      60: ireturn
      61: lload         12
      63: lload         8
      65: lcmp
      66: ifgt          26
      69: aload_0
      70: lload         8
      72: lload         8
      74: lconst_1
      75: ladd
      76: invokevirtual #100                // Method casProducerIndex:(JJ)Z
      79: ifeq          26
      82: aload         6
      84: lload         8
      86: lload         4
      88: invokestatic  #109                // Method calcElementOffset:(JJ)J
      91: aload_1
      92: invokeinterface #189,  1          // InterfaceMethod io/netty/util/internal/shaded/org/jctools/queues/MessagePassingQueue$Supplier.get:()Ljava/lang/Object;
      97: invokestatic  #122                // Method io/netty/util/internal/shaded/org/jctools/util/UnsafeRefArrayAccess.soElement:([Ljava/lang/Object;JLjava/lang/Object;)V
     100: aload_0
     101: aload_3
     102: lload         10
     104: lload         8
     106: lconst_1
     107: ladd
     108: invokevirtual #126                // Method soSequence:([JJJ)V
     111: iinc          7, 1
     114: goto          20
     117: iload_2
     118: ireturn

  public void drain(io.netty.util.internal.shaded.org.jctools.queues.MessagePassingQueue$Consumer<E>, io.netty.util.internal.shaded.org.jctools.queues.MessagePassingQueue$WaitStrategy, io.netty.util.internal.shaded.org.jctools.queues.MessagePassingQueue$ExitCondition);
    Code:
       0: iconst_0
       1: istore        4
       3: aload_3
       4: invokeinterface #194,  1          // InterfaceMethod io/netty/util/internal/shaded/org/jctools/queues/MessagePassingQueue$ExitCondition.keepRunning:()Z
       9: ifeq          42
      12: aload_0
      13: aload_1
      14: getstatic     #158                // Field RECOMENDED_POLL_BATCH:I
      17: invokevirtual #161                // Method drain:(Lio/netty/util/internal/shaded/org/jctools/queues/MessagePassingQueue$Consumer;I)I
      20: ifne          36
      23: aload_2
      24: iload         4
      26: invokeinterface #197,  2          // InterfaceMethod io/netty/util/internal/shaded/org/jctools/queues/MessagePassingQueue$WaitStrategy.idle:(I)I
      31: istore        4
      33: goto          3
      36: iconst_0
      37: istore        4
      39: goto          3
      42: return

  public void fill(io.netty.util.internal.shaded.org.jctools.queues.MessagePassingQueue$Supplier<E>, io.netty.util.internal.shaded.org.jctools.queues.MessagePassingQueue$WaitStrategy, io.netty.util.internal.shaded.org.jctools.queues.MessagePassingQueue$ExitCondition);
    Code:
       0: iconst_0
       1: istore        4
       3: aload_3
       4: invokeinterface #194,  1          // InterfaceMethod io/netty/util/internal/shaded/org/jctools/queues/MessagePassingQueue$ExitCondition.keepRunning:()Z
       9: ifeq          42
      12: aload_0
      13: aload_1
      14: getstatic     #170                // Field RECOMENDED_OFFER_BATCH:I
      17: invokevirtual #173                // Method fill:(Lio/netty/util/internal/shaded/org/jctools/queues/MessagePassingQueue$Supplier;I)I
      20: ifne          36
      23: aload_2
      24: iload         4
      26: invokeinterface #197,  2          // InterfaceMethod io/netty/util/internal/shaded/org/jctools/queues/MessagePassingQueue$WaitStrategy.idle:(I)I
      31: istore        4
      33: goto          3
      36: iconst_0
      37: istore        4
      39: goto          3
      42: return

  static {};
    Code:
       0: ldc           #2                  // class io/netty/util/internal/shaded/org/jctools/queues/MpmcArrayQueue
       2: invokevirtual #209                // Method java/lang/Class.desiredAssertionStatus:()Z
       5: ifne          12
       8: iconst_1
       9: goto          13
      12: iconst_0
      13: putstatic     #102                // Field $assertionsDisabled:Z
      16: getstatic     #214                // Field io/netty/util/internal/shaded/org/jctools/util/JvmInfo.CPUs:I
      19: iconst_4
      20: imul
      21: putstatic     #158                // Field RECOMENDED_POLL_BATCH:I
      24: getstatic     #214                // Field io/netty/util/internal/shaded/org/jctools/util/JvmInfo.CPUs:I
      27: iconst_4
      28: imul
      29: putstatic     #170                // Field RECOMENDED_OFFER_BATCH:I
      32: return
}
