Compiled from "ParseHandlerForm.java"
class org.apache.jena.sparql.sse.lang.ParseHandlerForm$FrameStack {
  private java.util.Deque<org.apache.jena.sparql.sse.lang.ParseHandlerForm$Frame> frames;

  private org.apache.jena.sparql.sse.lang.ParseHandlerForm$FrameStack();
    Code:
       0: aload_0
       1: invokespecial #2                  // Method java/lang/Object."<init>":()V
       4: aload_0
       5: new           #3                  // class java/util/ArrayDeque
       8: dup
       9: invokespecial #4                  // Method java/util/ArrayDeque."<init>":()V
      12: putfield      #5                  // Field frames:Ljava/util/Deque;
      15: return

  boolean isCurrent(org.apache.jena.sparql.sse.ItemList);
    Code:
       0: aload_0
       1: getfield      #5                  // Field frames:Ljava/util/Deque;
       4: invokeinterface #6,  1            // InterfaceMethod java/util/Deque.size:()I
       9: ifne          14
      12: iconst_0
      13: ireturn
      14: aload_0
      15: getfield      #5                  // Field frames:Ljava/util/Deque;
      18: invokeinterface #7,  1            // InterfaceMethod java/util/Deque.peek:()Ljava/lang/Object;
      23: checkcast     #8                  // class org/apache/jena/sparql/sse/lang/ParseHandlerForm$Frame
      26: astore_2
      27: aload_2
      28: getfield      #9                  // Field org/apache/jena/sparql/sse/lang/ParseHandlerForm$Frame.listItem:Lorg/apache/jena/sparql/sse/ItemList;
      31: aload_1
      32: if_acmpne     39
      35: iconst_1
      36: goto          40
      39: iconst_0
      40: ireturn

  org.apache.jena.sparql.sse.lang.ParseHandlerForm$Frame getCurrent();
    Code:
       0: aload_0
       1: getfield      #5                  // Field frames:Ljava/util/Deque;
       4: invokeinterface #6,  1            // InterfaceMethod java/util/Deque.size:()I
       9: ifne          14
      12: aconst_null
      13: areturn
      14: aload_0
      15: getfield      #5                  // Field frames:Ljava/util/Deque;
      18: invokeinterface #7,  1            // InterfaceMethod java/util/Deque.peek:()Ljava/lang/Object;
      23: checkcast     #8                  // class org/apache/jena/sparql/sse/lang/ParseHandlerForm$Frame
      26: areturn

  void push(org.apache.jena.sparql.sse.lang.ParseHandlerForm$Frame);
    Code:
       0: aload_0
       1: getfield      #5                  // Field frames:Ljava/util/Deque;
       4: aload_1
       5: invokeinterface #10,  2           // InterfaceMethod java/util/Deque.push:(Ljava/lang/Object;)V
      10: return

  org.apache.jena.sparql.sse.lang.ParseHandlerForm$Frame pop();
    Code:
       0: aload_0
       1: getfield      #5                  // Field frames:Ljava/util/Deque;
       4: invokeinterface #11,  1           // InterfaceMethod java/util/Deque.pop:()Ljava/lang/Object;
       9: checkcast     #8                  // class org/apache/jena/sparql/sse/lang/ParseHandlerForm$Frame
      12: areturn

  org.apache.jena.sparql.sse.lang.ParseHandlerForm$FrameStack(org.apache.jena.sparql.sse.lang.ParseHandlerForm$1);
    Code:
       0: aload_0
       1: invokespecial #1                  // Method "<init>":()V
       4: return
}
