Compiled from "JerseyRequestMatcherProvider.java"
public class org.springframework.boot.autoconfigure.security.servlet.JerseyRequestMatcherProvider implements org.springframework.boot.autoconfigure.security.servlet.RequestMatcherProvider {
  private final org.springframework.boot.autoconfigure.web.servlet.JerseyApplicationPath jerseyApplicationPath;

  public org.springframework.boot.autoconfigure.security.servlet.JerseyRequestMatcherProvider(org.springframework.boot.autoconfigure.web.servlet.JerseyApplicationPath);
    Code:
       0: aload_0
       1: invokespecial #1                  // Method java/lang/Object."<init>":()V
       4: aload_0
       5: aload_1
       6: putfield      #2                  // Field jerseyApplicationPath:Lorg/springframework/boot/autoconfigure/web/servlet/JerseyApplicationPath;
       9: return

  public org.springframework.security.web.util.matcher.RequestMatcher getRequestMatcher(java.lang.String);
    Code:
       0: new           #3                  // class org/springframework/security/web/util/matcher/AntPathRequestMatcher
       3: dup
       4: aload_0
       5: getfield      #2                  // Field jerseyApplicationPath:Lorg/springframework/boot/autoconfigure/web/servlet/JerseyApplicationPath;
       8: aload_1
       9: invokeinterface #4,  2            // InterfaceMethod org/springframework/boot/autoconfigure/web/servlet/JerseyApplicationPath.getRelativePath:(Ljava/lang/String;)Ljava/lang/String;
      14: invokespecial #5                  // Method org/springframework/security/web/util/matcher/AntPathRequestMatcher."<init>":(Ljava/lang/String;)V
      17: areturn
}
