Compiled from "ConnectDialog.java"
class org.jboss.as.cli.gui.ConnectDialog$2 extends javax.swing.AbstractAction {
  final org.jboss.as.cli.gui.ConnectDialog this$0;

  org.jboss.as.cli.gui.ConnectDialog$2(org.jboss.as.cli.gui.ConnectDialog, java.lang.String);
    Code:
       0: aload_0
       1: aload_1
       2: putfield      #1                  // Field this$0:Lorg/jboss/as/cli/gui/ConnectDialog;
       5: aload_0
       6: aload_2
       7: invokespecial #2                  // Method javax/swing/AbstractAction."<init>":(Ljava/lang/String;)V
      10: return

  public void actionPerformed(java.awt.event.ActionEvent);
    Code:
       0: aload_0
       1: invokevirtual #3                  // Method isEnabled:()Z
       4: ifeq          17
       7: aload_0
       8: getfield      #1                  // Field this$0:Lorg/jboss/as/cli/gui/ConnectDialog;
      11: invokevirtual #4                  // Method org/jboss/as/cli/gui/ConnectDialog.isVisible:()Z
      14: ifne          18
      17: return
      18: aconst_null
      19: astore_2
      20: aconst_null
      21: astore_3
      22: aconst_null
      23: astore        4
      25: aload_0
      26: getfield      #1                  // Field this$0:Lorg/jboss/as/cli/gui/ConnectDialog;
      29: invokestatic  #5                  // Method org/jboss/as/cli/gui/ConnectDialog.access$100:(Lorg/jboss/as/cli/gui/ConnectDialog;)Ljavax/swing/JTextField;
      32: invokevirtual #6                  // Method javax/swing/JTextField.getText:()Ljava/lang/String;
      35: invokevirtual #7                  // Method java/lang/String.length:()I
      38: ifle          91
      41: aload_0
      42: getfield      #1                  // Field this$0:Lorg/jboss/as/cli/gui/ConnectDialog;
      45: invokestatic  #5                  // Method org/jboss/as/cli/gui/ConnectDialog.access$100:(Lorg/jboss/as/cli/gui/ConnectDialog;)Ljavax/swing/JTextField;
      48: invokevirtual #6                  // Method javax/swing/JTextField.getText:()Ljava/lang/String;
      51: astore_2
      52: aload_0
      53: getfield      #1                  // Field this$0:Lorg/jboss/as/cli/gui/ConnectDialog;
      56: invokestatic  #8                  // Method org/jboss/as/cli/gui/ConnectDialog.access$200:(Lorg/jboss/as/cli/gui/ConnectDialog;)Ljavax/swing/JTextField;
      59: invokevirtual #6                  // Method javax/swing/JTextField.getText:()Ljava/lang/String;
      62: invokevirtual #7                  // Method java/lang/String.length:()I
      65: ifle          91
      68: aload_0
      69: getfield      #1                  // Field this$0:Lorg/jboss/as/cli/gui/ConnectDialog;
      72: invokestatic  #8                  // Method org/jboss/as/cli/gui/ConnectDialog.access$200:(Lorg/jboss/as/cli/gui/ConnectDialog;)Ljavax/swing/JTextField;
      75: invokevirtual #6                  // Method javax/swing/JTextField.getText:()Ljava/lang/String;
      78: astore_3
      79: aload_0
      80: getfield      #1                  // Field this$0:Lorg/jboss/as/cli/gui/ConnectDialog;
      83: invokestatic  #9                  // Method org/jboss/as/cli/gui/ConnectDialog.access$300:(Lorg/jboss/as/cli/gui/ConnectDialog;)Ljavax/swing/JTextField;
      86: invokevirtual #6                  // Method javax/swing/JTextField.getText:()Ljava/lang/String;
      89: astore        4
      91: aload_3
      92: ifnonnull     106
      95: invokestatic  #10                 // Method org/jboss/as/cli/CommandContextFactory.getInstance:()Lorg/jboss/as/cli/CommandContextFactory;
      98: invokevirtual #11                 // Method org/jboss/as/cli/CommandContextFactory.newCommandContext:()Lorg/jboss/as/cli/CommandContext;
     101: astore        5
     103: goto          121
     106: invokestatic  #10                 // Method org/jboss/as/cli/CommandContextFactory.getInstance:()Lorg/jboss/as/cli/CommandContextFactory;
     109: aconst_null
     110: aload_3
     111: aload         4
     113: invokevirtual #12                 // Method java/lang/String.toCharArray:()[C
     116: invokevirtual #13                 // Method org/jboss/as/cli/CommandContextFactory.newCommandContext:(Ljava/lang/String;Ljava/lang/String;[C)Lorg/jboss/as/cli/CommandContext;
     119: astore        5
     121: aload         5
     123: aload_2
     124: invokeinterface #14,  2           // InterfaceMethod org/jboss/as/cli/CommandContext.connectController:(Ljava/lang/String;)V
     129: aload_0
     130: getfield      #1                  // Field this$0:Lorg/jboss/as/cli/gui/ConnectDialog;
     133: invokestatic  #15                 // Method org/jboss/as/cli/gui/ConnectDialog.access$400:(Lorg/jboss/as/cli/gui/ConnectDialog;)Lorg/jboss/as/cli/gui/JConsoleCLIPlugin;
     136: aload         5
     138: invokevirtual #16                 // Method org/jboss/as/cli/gui/JConsoleCLIPlugin.init:(Lorg/jboss/as/cli/CommandContext;)V
     141: goto          213
     144: astore        5
     146: aload_0
     147: getfield      #1                  // Field this$0:Lorg/jboss/as/cli/gui/ConnectDialog;
     150: invokestatic  #18                 // Method org/jboss/as/cli/gui/ConnectDialog.access$500:(Lorg/jboss/as/cli/gui/ConnectDialog;)Ljavax/swing/JLabel;
     153: aload         5
     155: invokevirtual #19                 // Method org/jboss/as/cli/CliInitializationException.getMessage:()Ljava/lang/String;
     158: invokevirtual #20                 // Method javax/swing/JLabel.setText:(Ljava/lang/String;)V
     161: aload         5
     163: invokevirtual #21                 // Method org/jboss/as/cli/CliInitializationException.printStackTrace:()V
     166: return
     167: astore        5
     169: aload_0
     170: getfield      #1                  // Field this$0:Lorg/jboss/as/cli/gui/ConnectDialog;
     173: invokestatic  #18                 // Method org/jboss/as/cli/gui/ConnectDialog.access$500:(Lorg/jboss/as/cli/gui/ConnectDialog;)Ljavax/swing/JLabel;
     176: aload         5
     178: invokevirtual #23                 // Method java/lang/NumberFormatException.getMessage:()Ljava/lang/String;
     181: invokevirtual #20                 // Method javax/swing/JLabel.setText:(Ljava/lang/String;)V
     184: aload         5
     186: invokevirtual #24                 // Method java/lang/NumberFormatException.printStackTrace:()V
     189: return
     190: astore        5
     192: aload         5
     194: invokevirtual #26                 // Method org/jboss/as/cli/CommandLineException.printStackTrace:()V
     197: aload_0
     198: getfield      #1                  // Field this$0:Lorg/jboss/as/cli/gui/ConnectDialog;
     201: invokestatic  #18                 // Method org/jboss/as/cli/gui/ConnectDialog.access$500:(Lorg/jboss/as/cli/gui/ConnectDialog;)Ljavax/swing/JLabel;
     204: aload         5
     206: invokevirtual #27                 // Method org/jboss/as/cli/CommandLineException.getMessage:()Ljava/lang/String;
     209: invokevirtual #20                 // Method javax/swing/JLabel.setText:(Ljava/lang/String;)V
     212: return
     213: aload_0
     214: getfield      #1                  // Field this$0:Lorg/jboss/as/cli/gui/ConnectDialog;
     217: iconst_0
     218: invokevirtual #28                 // Method org/jboss/as/cli/gui/ConnectDialog.setVisible:(Z)V
     221: aload_0
     222: getfield      #1                  // Field this$0:Lorg/jboss/as/cli/gui/ConnectDialog;
     225: invokestatic  #29                 // Method org/jboss/as/cli/gui/ConnectDialog.access$600:(Lorg/jboss/as/cli/gui/ConnectDialog;)V
     228: return
    Exception table:
       from    to  target type
          91   141   144   Class org/jboss/as/cli/CliInitializationException
          91   141   167   Class java/lang/NumberFormatException
          91   141   190   Class org/jboss/as/cli/CommandLineException
}
