Compiled from "OperationMenu.java"
class org.jboss.as.cli.gui.OperationMenu$OperationAction extends javax.swing.AbstractAction {
  private org.jboss.as.cli.gui.ManagementModelNode node;

  private java.lang.String opName;

  private java.lang.String addressPath;

  private org.jboss.dmr.ModelNode opDescription;

  private java.lang.String strDescription;

  final org.jboss.as.cli.gui.OperationMenu this$0;

  public org.jboss.as.cli.gui.OperationMenu$OperationAction(org.jboss.as.cli.gui.OperationMenu, org.jboss.as.cli.gui.ManagementModelNode, java.lang.String, org.jboss.dmr.ModelNode);
    Code:
       0: aload_0
       1: aload_1
       2: putfield      #1                  // Field this$0:Lorg/jboss/as/cli/gui/OperationMenu;
       5: aload_0
       6: aload_3
       7: invokespecial #2                  // Method javax/swing/AbstractAction."<init>":(Ljava/lang/String;)V
      10: aload_0
      11: aload_2
      12: putfield      #3                  // Field node:Lorg/jboss/as/cli/gui/ManagementModelNode;
      15: aload_0
      16: aload_3
      17: putfield      #4                  // Field opName:Ljava/lang/String;
      20: aload_0
      21: aload_2
      22: invokevirtual #5                  // Method org/jboss/as/cli/gui/ManagementModelNode.addressPath:()Ljava/lang/String;
      25: putfield      #6                  // Field addressPath:Ljava/lang/String;
      28: aload_0
      29: aload         4
      31: putfield      #7                  // Field opDescription:Lorg/jboss/dmr/ModelNode;
      34: aload         4
      36: ifnull        75
      39: aload_0
      40: aload         4
      42: iconst_2
      43: anewarray     #8                  // class java/lang/String
      46: dup
      47: iconst_0
      48: ldc           #9                  // String result
      50: aastore
      51: dup
      52: iconst_1
      53: ldc           #10                 // String description
      55: aastore
      56: invokevirtual #11                 // Method org/jboss/dmr/ModelNode.get:([Ljava/lang/String;)Lorg/jboss/dmr/ModelNode;
      59: invokevirtual #12                 // Method org/jboss/dmr/ModelNode.asString:()Ljava/lang/String;
      62: putfield      #13                 // Field strDescription:Ljava/lang/String;
      65: aload_0
      66: ldc           #15                 // String ShortDescription
      68: aload_0
      69: getfield      #13                 // Field strDescription:Ljava/lang/String;
      72: invokevirtual #16                 // Method putValue:(Ljava/lang/String;Ljava/lang/Object;)V
      75: return

  private boolean isNoArgOperation(org.jboss.dmr.ModelNode);
    Code:
       0: aload_0
       1: getfield      #4                  // Field opName:Ljava/lang/String;
       4: ldc           #17                 // String add
       6: invokevirtual #18                 // Method java/lang/String.equals:(Ljava/lang/Object;)Z
       9: ifeq          14
      12: iconst_0
      13: ireturn
      14: aload_1
      15: ifnull        37
      18: aload_1
      19: invokevirtual #19                 // Method org/jboss/dmr/ModelNode.isDefined:()Z
      22: ifeq          37
      25: aload_1
      26: invokevirtual #20                 // Method org/jboss/dmr/ModelNode.asList:()Ljava/util/List;
      29: invokeinterface #21,  1           // InterfaceMethod java/util/List.isEmpty:()Z
      34: ifeq          41
      37: iconst_1
      38: goto          42
      41: iconst_0
      42: ireturn

  public void actionPerformed(java.awt.event.ActionEvent);
    Code:
       0: aload_0
       1: getfield      #1                  // Field this$0:Lorg/jboss/as/cli/gui/OperationMenu;
       4: invokestatic  #22                 // Method org/jboss/as/cli/gui/OperationMenu.access$000:(Lorg/jboss/as/cli/gui/OperationMenu;)Lorg/jboss/as/cli/gui/CliGuiContext;
       7: invokevirtual #23                 // Method org/jboss/as/cli/gui/CliGuiContext.getCommandLine:()Lorg/jboss/as/cli/gui/CommandLine;
      10: invokevirtual #24                 // Method org/jboss/as/cli/gui/CommandLine.getCmdText:()Ljavax/swing/text/JTextComponent;
      13: astore_2
      14: aload_0
      15: getfield      #7                  // Field opDescription:Lorg/jboss/dmr/ModelNode;
      18: iconst_2
      19: anewarray     #8                  // class java/lang/String
      22: dup
      23: iconst_0
      24: ldc           #9                  // String result
      26: aastore
      27: dup
      28: iconst_1
      29: ldc           #25                 // String request-properties
      31: aastore
      32: invokevirtual #11                 // Method org/jboss/dmr/ModelNode.get:([Ljava/lang/String;)Lorg/jboss/dmr/ModelNode;
      35: astore_3
      36: aload_0
      37: aload_3
      38: invokespecial #26                 // Method isNoArgOperation:(Lorg/jboss/dmr/ModelNode;)Z
      41: ifeq          82
      44: aload_2
      45: new           #27                 // class java/lang/StringBuilder
      48: dup
      49: invokespecial #28                 // Method java/lang/StringBuilder."<init>":()V
      52: aload_0
      53: getfield      #6                  // Field addressPath:Ljava/lang/String;
      56: invokevirtual #29                 // Method java/lang/StringBuilder.append:(Ljava/lang/String;)Ljava/lang/StringBuilder;
      59: ldc           #30                 // String :
      61: invokevirtual #29                 // Method java/lang/StringBuilder.append:(Ljava/lang/String;)Ljava/lang/StringBuilder;
      64: aload_0
      65: getfield      #4                  // Field opName:Ljava/lang/String;
      68: invokevirtual #29                 // Method java/lang/StringBuilder.append:(Ljava/lang/String;)Ljava/lang/StringBuilder;
      71: invokevirtual #31                 // Method java/lang/StringBuilder.toString:()Ljava/lang/String;
      74: invokevirtual #32                 // Method javax/swing/text/JTextComponent.setText:(Ljava/lang/String;)V
      77: aload_2
      78: invokevirtual #33                 // Method javax/swing/text/JTextComponent.requestFocus:()V
      81: return
      82: aload_0
      83: getfield      #3                  // Field node:Lorg/jboss/as/cli/gui/ManagementModelNode;
      86: invokevirtual #34                 // Method org/jboss/as/cli/gui/ManagementModelNode.isLeaf:()Z
      89: ifeq          172
      92: aload_0
      93: getfield      #4                  // Field opName:Ljava/lang/String;
      96: ldc           #35                 // String undefine-attribute
      98: invokevirtual #18                 // Method java/lang/String.equals:(Ljava/lang/Object;)Z
     101: ifeq          172
     104: aload_0
     105: getfield      #3                  // Field node:Lorg/jboss/as/cli/gui/ManagementModelNode;
     108: invokevirtual #36                 // Method org/jboss/as/cli/gui/ManagementModelNode.getUserObject:()Ljava/lang/Object;
     111: checkcast     #37                 // class org/jboss/as/cli/gui/ManagementModelNode$UserObject
     114: astore        4
     116: aload_2
     117: new           #27                 // class java/lang/StringBuilder
     120: dup
     121: invokespecial #28                 // Method java/lang/StringBuilder."<init>":()V
     124: aload_0
     125: getfield      #6                  // Field addressPath:Ljava/lang/String;
     128: invokevirtual #29                 // Method java/lang/StringBuilder.append:(Ljava/lang/String;)Ljava/lang/StringBuilder;
     131: ldc           #30                 // String :
     133: invokevirtual #29                 // Method java/lang/StringBuilder.append:(Ljava/lang/String;)Ljava/lang/StringBuilder;
     136: aload_0
     137: getfield      #4                  // Field opName:Ljava/lang/String;
     140: invokevirtual #29                 // Method java/lang/StringBuilder.append:(Ljava/lang/String;)Ljava/lang/StringBuilder;
     143: ldc           #38                 // String (name=
     145: invokevirtual #29                 // Method java/lang/StringBuilder.append:(Ljava/lang/String;)Ljava/lang/StringBuilder;
     148: aload         4
     150: invokevirtual #39                 // Method org/jboss/as/cli/gui/ManagementModelNode$UserObject.getName:()Ljava/lang/String;
     153: invokevirtual #29                 // Method java/lang/StringBuilder.append:(Ljava/lang/String;)Ljava/lang/StringBuilder;
     156: ldc           #40                 // String )
     158: invokevirtual #29                 // Method java/lang/StringBuilder.append:(Ljava/lang/String;)Ljava/lang/StringBuilder;
     161: invokevirtual #31                 // Method java/lang/StringBuilder.toString:()Ljava/lang/String;
     164: invokevirtual #32                 // Method javax/swing/text/JTextComponent.setText:(Ljava/lang/String;)V
     167: aload_2
     168: invokevirtual #33                 // Method javax/swing/text/JTextComponent.requestFocus:()V
     171: return
     172: new           #41                 // class org/jboss/as/cli/gui/OperationDialog
     175: dup
     176: aload_0
     177: getfield      #1                  // Field this$0:Lorg/jboss/as/cli/gui/OperationMenu;
     180: invokestatic  #22                 // Method org/jboss/as/cli/gui/OperationMenu.access$000:(Lorg/jboss/as/cli/gui/OperationMenu;)Lorg/jboss/as/cli/gui/CliGuiContext;
     183: aload_0
     184: getfield      #3                  // Field node:Lorg/jboss/as/cli/gui/ManagementModelNode;
     187: aload_0
     188: getfield      #4                  // Field opName:Ljava/lang/String;
     191: aload_0
     192: getfield      #13                 // Field strDescription:Ljava/lang/String;
     195: aload_3
     196: invokespecial #42                 // Method org/jboss/as/cli/gui/OperationDialog."<init>":(Lorg/jboss/as/cli/gui/CliGuiContext;Lorg/jboss/as/cli/gui/ManagementModelNode;Ljava/lang/String;Ljava/lang/String;Lorg/jboss/dmr/ModelNode;)V
     199: astore        4
     201: aload         4
     203: aload_0
     204: getfield      #1                  // Field this$0:Lorg/jboss/as/cli/gui/OperationMenu;
     207: invokestatic  #22                 // Method org/jboss/as/cli/gui/OperationMenu.access$000:(Lorg/jboss/as/cli/gui/OperationMenu;)Lorg/jboss/as/cli/gui/CliGuiContext;
     210: invokevirtual #43                 // Method org/jboss/as/cli/gui/CliGuiContext.getMainWindow:()Ljava/awt/Window;
     213: invokevirtual #44                 // Method org/jboss/as/cli/gui/OperationDialog.setLocationRelativeTo:(Ljava/awt/Component;)V
     216: aload         4
     218: iconst_1
     219: invokevirtual #45                 // Method org/jboss/as/cli/gui/OperationDialog.setVisible:(Z)V
     222: return
}
