Compiled from "JChannelFactory.java"
class org.jboss.as.clustering.jgroups.JChannelFactory$1 implements java.security.PrivilegedExceptionAction<org.jgroups.JChannel> {
  final org.jboss.as.clustering.jgroups.JChannelFactory this$0;

  org.jboss.as.clustering.jgroups.JChannelFactory$1(org.jboss.as.clustering.jgroups.JChannelFactory);
    Code:
       0: aload_0
       1: aload_1
       2: putfield      #1                  // Field this$0:Lorg/jboss/as/clustering/jgroups/JChannelFactory;
       5: aload_0
       6: invokespecial #2                  // Method java/lang/Object."<init>":()V
       9: return

  public org.jgroups.JChannel run() throws java.lang.Exception;
    Code:
       0: new           #3                  // class org/jgroups/JChannel
       3: dup
       4: aload_0
       5: getfield      #1                  // Field this$0:Lorg/jboss/as/clustering/jgroups/JChannelFactory;
       8: invokespecial #4                  // Method org/jgroups/JChannel."<init>":(Lorg/jgroups/conf/ProtocolStackConfigurator;)V
      11: areturn

  public java.lang.Object run() throws java.lang.Exception;
    Code:
       0: aload_0
       1: invokevirtual #5                  // Method run:()Lorg/jgroups/JChannel;
       4: areturn
}
