Compiled from "JChannelFactory.java"
public class org.jboss.as.clustering.jgroups.JChannelFactory implements org.wildfly.clustering.jgroups.spi.ChannelFactory,org.jgroups.conf.ProtocolStackConfigurator {
  static final java.nio.ByteBuffer UNKNOWN_FORK_RESPONSE;

  private final org.wildfly.clustering.jgroups.spi.ProtocolStackConfiguration configuration;

  public org.jboss.as.clustering.jgroups.JChannelFactory(org.wildfly.clustering.jgroups.spi.ProtocolStackConfiguration);
    Code:
       0: aload_0
       1: invokespecial #1                  // Method java/lang/Object."<init>":()V
       4: aload_0
       5: aload_1
       6: putfield      #2                  // Field configuration:Lorg/wildfly/clustering/jgroups/spi/ProtocolStackConfiguration;
       9: return

  public org.wildfly.clustering.jgroups.spi.ProtocolStackConfiguration getProtocolStackConfiguration();
    Code:
       0: aload_0
       1: getfield      #2                  // Field configuration:Lorg/wildfly/clustering/jgroups/spi/ProtocolStackConfiguration;
       4: areturn

  public org.jgroups.Channel createChannel(java.lang.String) throws java.lang.Exception;
    Code:
       0: getstatic     #3                  // Field org/jboss/as/clustering/jgroups/logging/JGroupsLogger.ROOT_LOGGER:Lorg/jboss/as/clustering/jgroups/logging/JGroupsLogger;
       3: ldc           #4                  // String Creating channel %s from stack %s
       5: aload_1
       6: aload_0
       7: getfield      #2                  // Field configuration:Lorg/wildfly/clustering/jgroups/spi/ProtocolStackConfiguration;
      10: invokeinterface #5,  1            // InterfaceMethod org/wildfly/clustering/jgroups/spi/ProtocolStackConfiguration.getName:()Ljava/lang/String;
      15: invokeinterface #6,  4            // InterfaceMethod org/jboss/as/clustering/jgroups/logging/JGroupsLogger.debugf:(Ljava/lang/String;Ljava/lang/Object;Ljava/lang/Object;)V
      20: new           #7                  // class org/jboss/as/clustering/jgroups/JChannelFactory$1
      23: dup
      24: aload_0
      25: invokespecial #8                  // Method org/jboss/as/clustering/jgroups/JChannelFactory$1."<init>":(Lorg/jboss/as/clustering/jgroups/JChannelFactory;)V
      28: astore_2
      29: aload_2
      30: invokestatic  #9                  // Method org/wildfly/security/manager/WildFlySecurityManager.doChecked:(Ljava/security/PrivilegedExceptionAction;)Ljava/lang/Object;
      33: checkcast     #10                 // class org/jgroups/JChannel
      36: astore_3
      37: aload_3
      38: invokevirtual #11                 // Method org/jgroups/JChannel.getProtocolStack:()Lorg/jgroups/stack/ProtocolStack;
      41: astore        4
      43: aload_0
      44: getfield      #2                  // Field configuration:Lorg/wildfly/clustering/jgroups/spi/ProtocolStackConfiguration;
      47: invokeinterface #12,  1           // InterfaceMethod org/wildfly/clustering/jgroups/spi/ProtocolStackConfiguration.getTransport:()Lorg/wildfly/clustering/jgroups/spi/TransportConfiguration;
      52: astore        5
      54: aload         5
      56: invokeinterface #13,  1           // InterfaceMethod org/wildfly/clustering/jgroups/spi/TransportConfiguration.getSocketBinding:()Lorg/jboss/as/network/SocketBinding;
      61: astore        6
      63: aload         6
      65: ifnull        84
      68: aload_3
      69: new           #14                 // class org/jboss/as/clustering/jgroups/ManagedSocketFactory
      72: dup
      73: aload         6
      75: invokevirtual #15                 // Method org/jboss/as/network/SocketBinding.getSocketBindings:()Lorg/jboss/as/network/SocketBindingManager;
      78: invokespecial #16                 // Method org/jboss/as/clustering/jgroups/ManagedSocketFactory."<init>":(Lorg/jboss/as/network/SocketBindingManager;)V
      81: invokevirtual #17                 // Method org/jgroups/JChannel.setSocketFactory:(Lorg/jgroups/util/SocketFactory;)V
      84: aload_0
      85: getfield      #2                  // Field configuration:Lorg/wildfly/clustering/jgroups/spi/ProtocolStackConfiguration;
      88: invokeinterface #18,  1           // InterfaceMethod org/wildfly/clustering/jgroups/spi/ProtocolStackConfiguration.getRelay:()Lorg/wildfly/clustering/jgroups/spi/RelayConfiguration;
      93: astore        7
      95: aload         7
      97: ifnull        419
     100: aload         7
     102: invokeinterface #19,  1           // InterfaceMethod org/wildfly/clustering/jgroups/spi/RelayConfiguration.getSiteName:()Ljava/lang/String;
     107: astore        8
     109: aload_0
     110: getfield      #2                  // Field configuration:Lorg/wildfly/clustering/jgroups/spi/ProtocolStackConfiguration;
     113: invokeinterface #18,  1           // InterfaceMethod org/wildfly/clustering/jgroups/spi/ProtocolStackConfiguration.getRelay:()Lorg/wildfly/clustering/jgroups/spi/RelayConfiguration;
     118: invokeinterface #20,  1           // InterfaceMethod org/wildfly/clustering/jgroups/spi/RelayConfiguration.getRemoteSites:()Ljava/util/List;
     123: astore        9
     125: new           #21                 // class java/util/ArrayList
     128: dup
     129: aload         9
     131: invokeinterface #22,  1           // InterfaceMethod java/util/List.size:()I
     136: iconst_1
     137: iadd
     138: invokespecial #23                 // Method java/util/ArrayList."<init>":(I)V
     141: astore        10
     143: aload         10
     145: aload         8
     147: invokeinterface #24,  2           // InterfaceMethod java/util/List.add:(Ljava/lang/Object;)Z
     152: pop
     153: new           #25                 // class java/util/HashMap
     156: dup
     157: invokespecial #26                 // Method java/util/HashMap."<init>":()V
     160: astore        11
     162: aload         9
     164: invokeinterface #27,  1           // InterfaceMethod java/util/List.iterator:()Ljava/util/Iterator;
     169: astore        12
     171: aload         12
     173: invokeinterface #28,  1           // InterfaceMethod java/util/Iterator.hasNext:()Z
     178: ifeq          250
     181: aload         12
     183: invokeinterface #29,  1           // InterfaceMethod java/util/Iterator.next:()Ljava/lang/Object;
     188: checkcast     #30                 // class org/wildfly/clustering/jgroups/spi/RemoteSiteConfiguration
     191: astore        13
     193: aload         13
     195: invokeinterface #31,  1           // InterfaceMethod org/wildfly/clustering/jgroups/spi/RemoteSiteConfiguration.getName:()Ljava/lang/String;
     200: astore        14
     202: aload         10
     204: aload         14
     206: invokeinterface #24,  2           // InterfaceMethod java/util/List.add:(Ljava/lang/Object;)Z
     211: pop
     212: aload         13
     214: invokeinterface #32,  1           // InterfaceMethod org/wildfly/clustering/jgroups/spi/RemoteSiteConfiguration.getClusterName:()Ljava/lang/String;
     219: astore        15
     221: new           #33                 // class org/jboss/as/clustering/jgroups/JChannelFactory$2
     224: dup
     225: aload_0
     226: aload         15
     228: aload         13
     230: invokespecial #34                 // Method org/jboss/as/clustering/jgroups/JChannelFactory$2."<init>":(Lorg/jboss/as/clustering/jgroups/JChannelFactory;Ljava/lang/String;Lorg/wildfly/clustering/jgroups/spi/RemoteSiteConfiguration;)V
     233: astore        16
     235: aload         11
     237: aload         15
     239: aload         16
     241: invokeinterface #35,  3           // InterfaceMethod java/util/Map.put:(Ljava/lang/Object;Ljava/lang/Object;)Ljava/lang/Object;
     246: pop
     247: goto          171
     250: new           #36                 // class org/jgroups/protocols/relay/RELAY2
     253: dup
     254: invokespecial #37                 // Method org/jgroups/protocols/relay/RELAY2."<init>":()V
     257: aload         8
     259: invokevirtual #38                 // Method org/jgroups/protocols/relay/RELAY2.site:(Ljava/lang/String;)Lorg/jgroups/protocols/relay/RELAY2;
     262: astore        12
     264: aload         10
     266: invokeinterface #27,  1           // InterfaceMethod java/util/List.iterator:()Ljava/util/Iterator;
     271: astore        13
     273: aload         13
     275: invokeinterface #28,  1           // InterfaceMethod java/util/Iterator.hasNext:()Z
     280: ifeq          376
     283: aload         13
     285: invokeinterface #29,  1           // InterfaceMethod java/util/Iterator.next:()Ljava/lang/Object;
     290: checkcast     #39                 // class java/lang/String
     293: astore        14
     295: new           #40                 // class org/jgroups/protocols/relay/config/RelayConfig$SiteConfig
     298: dup
     299: aload         14
     301: invokespecial #41                 // Method org/jgroups/protocols/relay/config/RelayConfig$SiteConfig."<init>":(Ljava/lang/String;)V
     304: astore        15
     306: aload         12
     308: aload         14
     310: aload         15
     312: invokevirtual #42                 // Method org/jgroups/protocols/relay/RELAY2.addSite:(Ljava/lang/String;Lorg/jgroups/protocols/relay/config/RelayConfig$SiteConfig;)Lorg/jgroups/protocols/relay/RELAY2;
     315: pop
     316: aload         14
     318: aload         8
     320: invokevirtual #43                 // Method java/lang/String.equals:(Ljava/lang/Object;)Z
     323: ifeq          373
     326: aload         11
     328: invokeinterface #44,  1           // InterfaceMethod java/util/Map.values:()Ljava/util/Collection;
     333: invokeinterface #45,  1           // InterfaceMethod java/util/Collection.iterator:()Ljava/util/Iterator;
     338: astore        16
     340: aload         16
     342: invokeinterface #28,  1           // InterfaceMethod java/util/Iterator.hasNext:()Z
     347: ifeq          373
     350: aload         16
     352: invokeinterface #29,  1           // InterfaceMethod java/util/Iterator.next:()Ljava/lang/Object;
     357: checkcast     #46                 // class org/jgroups/protocols/relay/config/RelayConfig$BridgeConfig
     360: astore        17
     362: aload         15
     364: aload         17
     366: invokevirtual #47                 // Method org/jgroups/protocols/relay/config/RelayConfig$SiteConfig.addBridge:(Lorg/jgroups/protocols/relay/config/RelayConfig$BridgeConfig;)Lorg/jgroups/protocols/relay/config/RelayConfig$SiteConfig;
     369: pop
     370: goto          340
     373: goto          273
     376: new           #25                 // class java/util/HashMap
     379: dup
     380: aload         7
     382: invokeinterface #48,  1           // InterfaceMethod org/wildfly/clustering/jgroups/spi/RelayConfiguration.getProperties:()Ljava/util/Map;
     387: invokespecial #49                 // Method java/util/HashMap."<init>":(Ljava/util/Map;)V
     390: astore        13
     392: aload         12
     394: aload         13
     396: invokestatic  #50                 // Method org/jgroups/stack/Configurator.resolveAndAssignFields:(Ljava/lang/Object;Ljava/util/Map;)V
     399: aload         12
     401: aload         13
     403: invokestatic  #51                 // Method org/jgroups/stack/Configurator.resolveAndInvokePropertyMethods:(Ljava/lang/Object;Ljava/util/Map;)V
     406: aload         4
     408: aload         12
     410: invokevirtual #52                 // Method org/jgroups/stack/ProtocolStack.addProtocol:(Lorg/jgroups/stack/Protocol;)Lorg/jgroups/stack/ProtocolStack;
     413: pop
     414: aload         12
     416: invokevirtual #53                 // Method org/jgroups/protocols/relay/RELAY2.init:()V
     419: new           #54                 // class org/jboss/as/clustering/jgroups/JChannelFactory$3
     422: dup
     423: aload_0
     424: aload_3
     425: invokespecial #55                 // Method org/jboss/as/clustering/jgroups/JChannelFactory$3."<init>":(Lorg/jboss/as/clustering/jgroups/JChannelFactory;Lorg/jgroups/JChannel;)V
     428: astore        8
     430: new           #56                 // class org/jgroups/protocols/FORK
     433: dup
     434: invokespecial #57                 // Method org/jgroups/protocols/FORK."<init>":()V
     437: astore        9
     439: aload         9
     441: aload         8
     443: invokevirtual #58                 // Method org/jgroups/protocols/FORK.setUnknownForkHandler:(Lorg/jgroups/fork/UnknownForkHandler;)V
     446: aload         4
     448: aload         9
     450: invokevirtual #52                 // Method org/jgroups/stack/ProtocolStack.addProtocol:(Lorg/jgroups/stack/Protocol;)Lorg/jgroups/stack/ProtocolStack;
     453: pop
     454: aload         9
     456: invokevirtual #59                 // Method org/jgroups/protocols/FORK.init:()V
     459: aload_3
     460: aload_0
     461: getfield      #2                  // Field configuration:Lorg/wildfly/clustering/jgroups/spi/ProtocolStackConfiguration;
     464: invokeinterface #60,  1           // InterfaceMethod org/wildfly/clustering/jgroups/spi/ProtocolStackConfiguration.getNodeName:()Ljava/lang/String;
     469: invokevirtual #61                 // Method org/jgroups/JChannel.setName:(Ljava/lang/String;)V
     472: aload_0
     473: getfield      #2                  // Field configuration:Lorg/wildfly/clustering/jgroups/spi/ProtocolStackConfiguration;
     476: invokeinterface #12,  1           // InterfaceMethod org/wildfly/clustering/jgroups/spi/ProtocolStackConfiguration.getTransport:()Lorg/wildfly/clustering/jgroups/spi/TransportConfiguration;
     481: invokeinterface #62,  1           // InterfaceMethod org/wildfly/clustering/jgroups/spi/TransportConfiguration.getTopology:()Lorg/wildfly/clustering/jgroups/spi/TransportConfiguration$Topology;
     486: astore        10
     488: aload         10
     490: ifnull        506
     493: aload_3
     494: new           #63                 // class org/jboss/as/clustering/jgroups/TopologyAddressGenerator
     497: dup
     498: aload         10
     500: invokespecial #64                 // Method org/jboss/as/clustering/jgroups/TopologyAddressGenerator."<init>":(Lorg/wildfly/clustering/jgroups/spi/TransportConfiguration$Topology;)V
     503: invokevirtual #65                 // Method org/jgroups/JChannel.addAddressGenerator:(Lorg/jgroups/stack/AddressGenerator;)V
     506: aload_3
     507: areturn

  public boolean isUnknownForkResponse(java.nio.ByteBuffer);
    Code:
       0: getstatic     #66                 // Field UNKNOWN_FORK_RESPONSE:Ljava/nio/ByteBuffer;
       3: aload_1
       4: invokevirtual #67                 // Method java/nio/ByteBuffer.equals:(Ljava/lang/Object;)Z
       7: ireturn

  public java.lang.String getProtocolStackString();
    Code:
       0: aconst_null
       1: areturn

  public java.util.List<org.jgroups.conf.ProtocolConfiguration> getProtocolStack();
    Code:
       0: new           #21                 // class java/util/ArrayList
       3: dup
       4: aload_0
       5: getfield      #2                  // Field configuration:Lorg/wildfly/clustering/jgroups/spi/ProtocolStackConfiguration;
       8: invokeinterface #68,  1           // InterfaceMethod org/wildfly/clustering/jgroups/spi/ProtocolStackConfiguration.getProtocols:()Ljava/util/List;
      13: invokeinterface #22,  1           // InterfaceMethod java/util/List.size:()I
      18: iconst_1
      19: iadd
      20: invokespecial #23                 // Method java/util/ArrayList."<init>":(I)V
      23: astore_1
      24: aload_0
      25: getfield      #2                  // Field configuration:Lorg/wildfly/clustering/jgroups/spi/ProtocolStackConfiguration;
      28: invokeinterface #12,  1           // InterfaceMethod org/wildfly/clustering/jgroups/spi/ProtocolStackConfiguration.getTransport:()Lorg/wildfly/clustering/jgroups/spi/TransportConfiguration;
      33: astore_2
      34: aload_0
      35: getfield      #2                  // Field configuration:Lorg/wildfly/clustering/jgroups/spi/ProtocolStackConfiguration;
      38: aload_2
      39: invokestatic  #69                 // Method createProtocol:(Lorg/wildfly/clustering/jgroups/spi/ProtocolStackConfiguration;Lorg/wildfly/clustering/jgroups/spi/ProtocolConfiguration;)Lorg/jgroups/conf/ProtocolConfiguration;
      42: astore_3
      43: aload_3
      44: invokevirtual #70                 // Method org/jgroups/conf/ProtocolConfiguration.getProperties:()Ljava/util/Map;
      47: astore        4
      49: new           #71                 // class org/jboss/as/clustering/jgroups/JChannelFactory$Introspector
      52: dup
      53: aload_3
      54: invokespecial #72                 // Method org/jboss/as/clustering/jgroups/JChannelFactory$Introspector."<init>":(Lorg/jgroups/conf/ProtocolConfiguration;)V
      57: astore        5
      59: aload_2
      60: invokeinterface #13,  1           // InterfaceMethod org/wildfly/clustering/jgroups/spi/TransportConfiguration.getSocketBinding:()Lorg/jboss/as/network/SocketBinding;
      65: astore        6
      67: aload         6
      69: ifnull        102
      72: aload         5
      74: aload_3
      75: aload         6
      77: invokestatic  #73                 // Method configureBindAddress:(Lorg/jboss/as/clustering/jgroups/JChannelFactory$Introspector;Lorg/jgroups/conf/ProtocolConfiguration;Lorg/jboss/as/network/SocketBinding;)V
      80: aload         5
      82: aload_3
      83: ldc           #74                 // String bind_port
      85: aload         6
      87: invokestatic  #75                 // Method configureServerSocket:(Lorg/jboss/as/clustering/jgroups/JChannelFactory$Introspector;Lorg/jgroups/conf/ProtocolConfiguration;Ljava/lang/String;Lorg/jboss/as/network/SocketBinding;)V
      90: aload         5
      92: aload_3
      93: ldc           #76                 // String mcast_addr
      95: ldc           #77                 // String mcast_port
      97: aload         6
      99: invokestatic  #78                 // Method configureMulticastSocket:(Lorg/jboss/as/clustering/jgroups/JChannelFactory$Introspector;Lorg/jgroups/conf/ProtocolConfiguration;Ljava/lang/String;Ljava/lang/String;Lorg/jboss/as/network/SocketBinding;)V
     102: aload_2
     103: invokeinterface #79,  1           // InterfaceMethod org/wildfly/clustering/jgroups/spi/TransportConfiguration.getDiagnosticsSocketBinding:()Lorg/jboss/as/network/SocketBinding;
     108: astore        7
     110: aload         7
     112: ifnull        119
     115: iconst_1
     116: goto          120
     119: iconst_0
     120: istore        8
     122: aload         4
     124: ldc           #80                 // String enable_diagnostics
     126: iload         8
     128: invokestatic  #81                 // Method java/lang/String.valueOf:(Z)Ljava/lang/String;
     131: invokeinterface #35,  3           // InterfaceMethod java/util/Map.put:(Ljava/lang/Object;Ljava/lang/Object;)Ljava/lang/Object;
     136: pop
     137: iload         8
     139: ifeq          154
     142: aload         5
     144: aload_3
     145: ldc           #82                 // String diagnostics_addr
     147: ldc           #83                 // String diagnostics_port
     149: aload         7
     151: invokestatic  #78                 // Method configureMulticastSocket:(Lorg/jboss/as/clustering/jgroups/JChannelFactory$Introspector;Lorg/jgroups/conf/ProtocolConfiguration;Ljava/lang/String;Ljava/lang/String;Lorg/jboss/as/network/SocketBinding;)V
     154: aload_1
     155: aload_3
     156: invokeinterface #24,  2           // InterfaceMethod java/util/List.add:(Ljava/lang/Object;)Z
     161: pop
     162: aload         5
     164: invokevirtual #84                 // Method org/jboss/as/clustering/jgroups/JChannelFactory$Introspector.getProtocolClass:()Ljava/lang/Class;
     167: ldc           #85                 // class org/jgroups/protocols/TP
     169: invokevirtual #86                 // Method java/lang/Class.asSubclass:(Ljava/lang/Class;)Ljava/lang/Class;
     172: astore        9
     174: new           #87                 // class org/jboss/as/clustering/jgroups/JChannelFactory$4
     177: dup
     178: aload_0
     179: aload         9
     181: invokespecial #88                 // Method org/jboss/as/clustering/jgroups/JChannelFactory$4."<init>":(Lorg/jboss/as/clustering/jgroups/JChannelFactory;Ljava/lang/Class;)V
     184: astore        10
     186: aload_1
     187: aload_0
     188: getfield      #2                  // Field configuration:Lorg/wildfly/clustering/jgroups/spi/ProtocolStackConfiguration;
     191: aload         10
     193: invokestatic  #9                  // Method org/wildfly/security/manager/WildFlySecurityManager.doChecked:(Ljava/security/PrivilegedExceptionAction;)Ljava/lang/Object;
     196: checkcast     #85                 // class org/jgroups/protocols/TP
     199: invokevirtual #89                 // Method org/jgroups/protocols/TP.isMulticastCapable:()Z
     202: invokestatic  #90                 // Method createProtocols:(Lorg/wildfly/clustering/jgroups/spi/ProtocolStackConfiguration;Z)Ljava/util/List;
     205: invokeinterface #91,  2           // InterfaceMethod java/util/List.addAll:(Ljava/util/Collection;)Z
     210: pop
     211: goto          229
     214: astore        11
     216: new           #93                 // class java/lang/IllegalStateException
     219: dup
     220: aload         11
     222: invokevirtual #94                 // Method java/security/PrivilegedActionException.getCause:()Ljava/lang/Throwable;
     225: invokespecial #95                 // Method java/lang/IllegalStateException."<init>":(Ljava/lang/Throwable;)V
     228: athrow
     229: aload_1
     230: areturn
    Exception table:
       from    to  target type
         186   211   214   Class java/security/PrivilegedActionException

  static java.util.List<org.jgroups.conf.ProtocolConfiguration> createProtocols(org.wildfly.clustering.jgroups.spi.ProtocolStackConfiguration, boolean);
    Code:
       0: aload_0
       1: invokeinterface #68,  1           // InterfaceMethod org/wildfly/clustering/jgroups/spi/ProtocolStackConfiguration.getProtocols:()Ljava/util/List;
       6: astore_2
       7: new           #21                 // class java/util/ArrayList
      10: dup
      11: aload_2
      12: invokeinterface #22,  1           // InterfaceMethod java/util/List.size:()I
      17: invokespecial #23                 // Method java/util/ArrayList."<init>":(I)V
      20: astore_3
      21: aload_0
      22: invokeinterface #12,  1           // InterfaceMethod org/wildfly/clustering/jgroups/spi/ProtocolStackConfiguration.getTransport:()Lorg/wildfly/clustering/jgroups/spi/TransportConfiguration;
      27: astore        4
      29: aload_2
      30: invokeinterface #27,  1           // InterfaceMethod java/util/List.iterator:()Ljava/util/Iterator;
      35: astore        5
      37: aload         5
      39: invokeinterface #28,  1           // InterfaceMethod java/util/Iterator.hasNext:()Z
      44: ifeq          205
      47: aload         5
      49: invokeinterface #29,  1           // InterfaceMethod java/util/Iterator.next:()Ljava/lang/Object;
      54: checkcast     #96                 // class org/wildfly/clustering/jgroups/spi/ProtocolConfiguration
      57: astore        6
      59: aload_0
      60: aload         6
      62: invokestatic  #69                 // Method createProtocol:(Lorg/wildfly/clustering/jgroups/spi/ProtocolStackConfiguration;Lorg/wildfly/clustering/jgroups/spi/ProtocolConfiguration;)Lorg/jgroups/conf/ProtocolConfiguration;
      65: astore        7
      67: new           #71                 // class org/jboss/as/clustering/jgroups/JChannelFactory$Introspector
      70: dup
      71: aload         7
      73: invokespecial #72                 // Method org/jboss/as/clustering/jgroups/JChannelFactory$Introspector."<init>":(Lorg/jgroups/conf/ProtocolConfiguration;)V
      76: astore        8
      78: aload         6
      80: invokeinterface #97,  1           // InterfaceMethod org/wildfly/clustering/jgroups/spi/ProtocolConfiguration.getSocketBinding:()Lorg/jboss/as/network/SocketBinding;
      85: astore        9
      87: aload         9
      89: ifnull        139
      92: aload         8
      94: aload         7
      96: aload         9
      98: invokestatic  #73                 // Method configureBindAddress:(Lorg/jboss/as/clustering/jgroups/JChannelFactory$Introspector;Lorg/jgroups/conf/ProtocolConfiguration;Lorg/jboss/as/network/SocketBinding;)V
     101: aload         8
     103: aload         7
     105: ldc           #74                 // String bind_port
     107: aload         9
     109: invokestatic  #75                 // Method configureServerSocket:(Lorg/jboss/as/clustering/jgroups/JChannelFactory$Introspector;Lorg/jgroups/conf/ProtocolConfiguration;Ljava/lang/String;Lorg/jboss/as/network/SocketBinding;)V
     112: aload         8
     114: aload         7
     116: ldc           #98                 // String start_port
     118: aload         9
     120: invokestatic  #75                 // Method configureServerSocket:(Lorg/jboss/as/clustering/jgroups/JChannelFactory$Introspector;Lorg/jgroups/conf/ProtocolConfiguration;Ljava/lang/String;Lorg/jboss/as/network/SocketBinding;)V
     123: aload         8
     125: aload         7
     127: ldc           #76                 // String mcast_addr
     129: ldc           #77                 // String mcast_port
     131: aload         9
     133: invokestatic  #78                 // Method configureMulticastSocket:(Lorg/jboss/as/clustering/jgroups/JChannelFactory$Introspector;Lorg/jgroups/conf/ProtocolConfiguration;Ljava/lang/String;Ljava/lang/String;Lorg/jboss/as/network/SocketBinding;)V
     136: goto          163
     139: aload         4
     141: invokeinterface #13,  1           // InterfaceMethod org/wildfly/clustering/jgroups/spi/TransportConfiguration.getSocketBinding:()Lorg/jboss/as/network/SocketBinding;
     146: ifnull        163
     149: aload         8
     151: aload         7
     153: aload         4
     155: invokeinterface #13,  1           // InterfaceMethod org/wildfly/clustering/jgroups/spi/TransportConfiguration.getSocketBinding:()Lorg/jboss/as/network/SocketBinding;
     160: invokestatic  #73                 // Method configureBindAddress:(Lorg/jboss/as/clustering/jgroups/JChannelFactory$Introspector;Lorg/jgroups/conf/ProtocolConfiguration;Lorg/jboss/as/network/SocketBinding;)V
     163: iload_1
     164: ifne          193
     167: aload         8
     169: aload         7
     171: ldc           #99                 // String use_mcast_xmit
     173: iconst_0
     174: invokestatic  #81                 // Method java/lang/String.valueOf:(Z)Ljava/lang/String;
     177: invokestatic  #100                // Method setProperty:(Lorg/jboss/as/clustering/jgroups/JChannelFactory$Introspector;Lorg/jgroups/conf/ProtocolConfiguration;Ljava/lang/String;Ljava/lang/String;)V
     180: aload         8
     182: aload         7
     184: ldc           #101                // String use_mcast_xmit_req
     186: iconst_0
     187: invokestatic  #81                 // Method java/lang/String.valueOf:(Z)Ljava/lang/String;
     190: invokestatic  #100                // Method setProperty:(Lorg/jboss/as/clustering/jgroups/JChannelFactory$Introspector;Lorg/jgroups/conf/ProtocolConfiguration;Ljava/lang/String;Ljava/lang/String;)V
     193: aload_3
     194: aload         7
     196: invokeinterface #24,  2           // InterfaceMethod java/util/List.add:(Ljava/lang/Object;)Z
     201: pop
     202: goto          37
     205: aload_3
     206: areturn

  private static org.jgroups.conf.ProtocolConfiguration createProtocol(org.wildfly.clustering.jgroups.spi.ProtocolStackConfiguration, org.wildfly.clustering.jgroups.spi.ProtocolConfiguration);
    Code:
       0: aload_1
       1: invokeinterface #102,  1          // InterfaceMethod org/wildfly/clustering/jgroups/spi/ProtocolConfiguration.getName:()Ljava/lang/String;
       6: astore_2
       7: aload_1
       8: invokeinterface #103,  1          // InterfaceMethod org/wildfly/clustering/jgroups/spi/ProtocolConfiguration.getModule:()Lorg/jboss/modules/ModuleIdentifier;
      13: astore_3
      14: new           #25                 // class java/util/HashMap
      17: dup
      18: aload_0
      19: aload_2
      20: invokeinterface #104,  2          // InterfaceMethod org/wildfly/clustering/jgroups/spi/ProtocolStackConfiguration.getDefaultProperties:(Ljava/lang/String;)Ljava/util/Map;
      25: invokespecial #49                 // Method java/util/HashMap."<init>":(Ljava/util/Map;)V
      28: astore        4
      30: aload         4
      32: aload_1
      33: invokeinterface #105,  1          // InterfaceMethod org/wildfly/clustering/jgroups/spi/ProtocolConfiguration.getProperties:()Ljava/util/Map;
      38: invokeinterface #106,  2          // InterfaceMethod java/util/Map.putAll:(Ljava/util/Map;)V
      43: new           #107                // class org/jboss/as/clustering/jgroups/JChannelFactory$5
      46: dup
      47: aload_1
      48: invokeinterface #108,  1          // InterfaceMethod org/wildfly/clustering/jgroups/spi/ProtocolConfiguration.getProtocolClassName:()Ljava/lang/String;
      53: aload         4
      55: aload_0
      56: invokeinterface #109,  1          // InterfaceMethod org/wildfly/clustering/jgroups/spi/ProtocolStackConfiguration.getModuleLoader:()Lorg/jboss/modules/ModuleLoader;
      61: aload_3
      62: invokevirtual #110                // Method org/jboss/modules/ModuleLoader.loadModule:(Lorg/jboss/modules/ModuleIdentifier;)Lorg/jboss/modules/Module;
      65: invokevirtual #111                // Method org/jboss/modules/Module.getClassLoader:()Lorg/jboss/modules/ModuleClassLoader;
      68: aload         4
      70: invokespecial #112                // Method org/jboss/as/clustering/jgroups/JChannelFactory$5."<init>":(Ljava/lang/String;Ljava/util/Map;Ljava/lang/ClassLoader;Ljava/util/Map;)V
      73: areturn
      74: astore        5
      76: new           #114                // class java/lang/IllegalArgumentException
      79: dup
      80: aload         5
      82: invokespecial #115                // Method java/lang/IllegalArgumentException."<init>":(Ljava/lang/Throwable;)V
      85: athrow
    Exception table:
       from    to  target type
          43    73    74   Class org/jboss/modules/ModuleLoadException

  private static void configureBindAddress(org.jboss.as.clustering.jgroups.JChannelFactory$Introspector, org.jgroups.conf.ProtocolConfiguration, org.jboss.as.network.SocketBinding);
    Code:
       0: aload_0
       1: aload_1
       2: ldc           #116                // String bind_addr
       4: aload_2
       5: invokevirtual #117                // Method org/jboss/as/network/SocketBinding.getSocketAddress:()Ljava/net/InetSocketAddress;
       8: invokevirtual #118                // Method java/net/InetSocketAddress.getAddress:()Ljava/net/InetAddress;
      11: invokevirtual #119                // Method java/net/InetAddress.getHostAddress:()Ljava/lang/String;
      14: invokestatic  #120                // Method setSocketBindingProperty:(Lorg/jboss/as/clustering/jgroups/JChannelFactory$Introspector;Lorg/jgroups/conf/ProtocolConfiguration;Ljava/lang/String;Ljava/lang/String;)V
      17: return

  private static void configureServerSocket(org.jboss.as.clustering.jgroups.JChannelFactory$Introspector, org.jgroups.conf.ProtocolConfiguration, java.lang.String, org.jboss.as.network.SocketBinding);
    Code:
       0: aload_0
       1: aload_1
       2: aload_2
       3: aload_3
       4: invokevirtual #117                // Method org/jboss/as/network/SocketBinding.getSocketAddress:()Ljava/net/InetSocketAddress;
       7: invokevirtual #121                // Method java/net/InetSocketAddress.getPort:()I
      10: invokestatic  #122                // Method java/lang/String.valueOf:(I)Ljava/lang/String;
      13: invokestatic  #120                // Method setSocketBindingProperty:(Lorg/jboss/as/clustering/jgroups/JChannelFactory$Introspector;Lorg/jgroups/conf/ProtocolConfiguration;Ljava/lang/String;Ljava/lang/String;)V
      16: return

  private static void configureMulticastSocket(org.jboss.as.clustering.jgroups.JChannelFactory$Introspector, org.jgroups.conf.ProtocolConfiguration, java.lang.String, java.lang.String, org.jboss.as.network.SocketBinding);
    Code:
       0: aload         4
       2: invokevirtual #123                // Method org/jboss/as/network/SocketBinding.getMulticastSocketAddress:()Ljava/net/InetSocketAddress;
       5: astore        5
       7: aload_0
       8: aload_1
       9: aload_2
      10: aload         5
      12: invokevirtual #118                // Method java/net/InetSocketAddress.getAddress:()Ljava/net/InetAddress;
      15: invokevirtual #119                // Method java/net/InetAddress.getHostAddress:()Ljava/lang/String;
      18: invokestatic  #120                // Method setSocketBindingProperty:(Lorg/jboss/as/clustering/jgroups/JChannelFactory$Introspector;Lorg/jgroups/conf/ProtocolConfiguration;Ljava/lang/String;Ljava/lang/String;)V
      21: aload_0
      22: aload_1
      23: aload_3
      24: aload         5
      26: invokevirtual #121                // Method java/net/InetSocketAddress.getPort:()I
      29: invokestatic  #122                // Method java/lang/String.valueOf:(I)Ljava/lang/String;
      32: invokestatic  #120                // Method setSocketBindingProperty:(Lorg/jboss/as/clustering/jgroups/JChannelFactory$Introspector;Lorg/jgroups/conf/ProtocolConfiguration;Ljava/lang/String;Ljava/lang/String;)V
      35: goto          65
      38: astore        5
      40: getstatic     #3                  // Field org/jboss/as/clustering/jgroups/logging/JGroupsLogger.ROOT_LOGGER:Lorg/jboss/as/clustering/jgroups/logging/JGroupsLogger;
      43: aload         5
      45: aload_1
      46: invokevirtual #124                // Method org/jgroups/conf/ProtocolConfiguration.getProtocolName:()Ljava/lang/String;
      49: aload_2
      50: aload_1
      51: invokevirtual #124                // Method org/jgroups/conf/ProtocolConfiguration.getProtocolName:()Ljava/lang/String;
      54: aload_3
      55: aload         4
      57: invokevirtual #125                // Method org/jboss/as/network/SocketBinding.getName:()Ljava/lang/String;
      60: invokeinterface #126,  7          // InterfaceMethod org/jboss/as/clustering/jgroups/logging/JGroupsLogger.couldNotSetAddressAndPortNoMulticastSocket:(Ljava/lang/Throwable;Ljava/lang/String;Ljava/lang/String;Ljava/lang/String;Ljava/lang/String;Ljava/lang/String;)V
      65: return
    Exception table:
       from    to  target type
           0    35    38   Class java/lang/IllegalStateException

  private static void setSocketBindingProperty(org.jboss.as.clustering.jgroups.JChannelFactory$Introspector, org.jgroups.conf.ProtocolConfiguration, java.lang.String, java.lang.String);
    Code:
       0: aload_1
       1: invokevirtual #127                // Method org/jgroups/conf/ProtocolConfiguration.getOriginalProperties:()Ljava/util/Map;
       4: astore        4
       6: aload         4
       8: aload_2
       9: invokeinterface #128,  2          // InterfaceMethod java/util/Map.containsKey:(Ljava/lang/Object;)Z
      14: ifeq          39
      17: getstatic     #3                  // Field org/jboss/as/clustering/jgroups/logging/JGroupsLogger.ROOT_LOGGER:Lorg/jboss/as/clustering/jgroups/logging/JGroupsLogger;
      20: aload_2
      21: aload_1
      22: invokevirtual #124                // Method org/jgroups/conf/ProtocolConfiguration.getProtocolName:()Ljava/lang/String;
      25: aload_3
      26: aload         4
      28: aload_2
      29: invokeinterface #129,  2          // InterfaceMethod java/util/Map.get:(Ljava/lang/Object;)Ljava/lang/Object;
      34: invokeinterface #130,  5          // InterfaceMethod org/jboss/as/clustering/jgroups/logging/JGroupsLogger.unableToOverrideSocketBindingValue:(Ljava/lang/String;Ljava/lang/String;Ljava/lang/String;Ljava/lang/Object;)V
      39: aload_0
      40: aload_1
      41: aload_2
      42: aload_3
      43: invokestatic  #100                // Method setProperty:(Lorg/jboss/as/clustering/jgroups/JChannelFactory$Introspector;Lorg/jgroups/conf/ProtocolConfiguration;Ljava/lang/String;Ljava/lang/String;)V
      46: goto          66
      49: astore        4
      51: getstatic     #3                  // Field org/jboss/as/clustering/jgroups/logging/JGroupsLogger.ROOT_LOGGER:Lorg/jboss/as/clustering/jgroups/logging/JGroupsLogger;
      54: aload         4
      56: aload_2
      57: aload_1
      58: invokevirtual #124                // Method org/jgroups/conf/ProtocolConfiguration.getProtocolName:()Ljava/lang/String;
      61: invokeinterface #132,  4          // InterfaceMethod org/jboss/as/clustering/jgroups/logging/JGroupsLogger.unableToAccessProtocolPropertyValue:(Ljava/lang/Throwable;Ljava/lang/String;Ljava/lang/String;)V
      66: return
    Exception table:
       from    to  target type
           0    46    49   Class java/lang/Exception

  private static void setProperty(org.jboss.as.clustering.jgroups.JChannelFactory$Introspector, org.jgroups.conf.ProtocolConfiguration, java.lang.String, java.lang.String);
    Code:
       0: aload_0
       1: aload_2
       2: invokevirtual #133                // Method org/jboss/as/clustering/jgroups/JChannelFactory$Introspector.hasProperty:(Ljava/lang/String;)Z
       5: ifeq          20
       8: aload_1
       9: invokevirtual #70                 // Method org/jgroups/conf/ProtocolConfiguration.getProperties:()Ljava/util/Map;
      12: aload_2
      13: aload_3
      14: invokeinterface #35,  3           // InterfaceMethod java/util/Map.put:(Ljava/lang/Object;Ljava/lang/Object;)Ljava/lang/Object;
      19: pop
      20: return

  static {};
    Code:
       0: iconst_0
       1: invokestatic  #134                // Method java/nio/ByteBuffer.allocate:(I)Ljava/nio/ByteBuffer;
       4: putstatic     #66                 // Field UNKNOWN_FORK_RESPONSE:Ljava/nio/ByteBuffer;
       7: return
}
