Compiled from "AbstractSaslServer.java"
public abstract class org.jboss.sasl.util.AbstractSaslServer extends org.jboss.sasl.util.AbstractSaslParticipant implements javax.security.sasl.SaslServer {
  protected org.jboss.sasl.util.AbstractSaslServer(java.lang.String, java.lang.String, java.lang.String, javax.security.auth.callback.CallbackHandler);
    Code:
       0: aload_0
       1: aload_1
       2: aload_2
       3: aload_3
       4: aload         4
       6: invokespecial #1                  // Method org/jboss/sasl/util/AbstractSaslParticipant."<init>":(Ljava/lang/String;Ljava/lang/String;Ljava/lang/String;Ljavax/security/auth/callback/CallbackHandler;)V
       9: return

  public byte[] evaluateResponse(byte[]) throws javax.security.sasl.SaslException;
    Code:
       0: aload_0
       1: aload_1
       2: invokevirtual #2                  // Method evaluateMessage:([B)[B
       5: areturn
}
