Compiled from "SimpleOutputElement.java"
public final class com.ctc.wstx.sw.SimpleOutputElement extends com.ctc.wstx.sw.OutputElementBase {
  protected com.ctc.wstx.sw.SimpleOutputElement mParent;

  protected java.lang.String mPrefix;

  protected java.lang.String mLocalName;

  protected java.lang.String mURI;

  protected java.util.HashSet<com.ctc.wstx.sw.SimpleOutputElement$AttrName> mAttrSet;

  private com.ctc.wstx.sw.SimpleOutputElement();
    Code:
       0: aload_0
       1: invokespecial #1                  // Method com/ctc/wstx/sw/OutputElementBase."<init>":()V
       4: aload_0
       5: aconst_null
       6: putfield      #2                  // Field mAttrSet:Ljava/util/HashSet;
       9: aload_0
      10: aconst_null
      11: putfield      #3                  // Field mParent:Lcom/ctc/wstx/sw/SimpleOutputElement;
      14: aload_0
      15: aconst_null
      16: putfield      #4                  // Field mPrefix:Ljava/lang/String;
      19: aload_0
      20: ldc           #5                  // String
      22: putfield      #6                  // Field mLocalName:Ljava/lang/String;
      25: aload_0
      26: aconst_null
      27: putfield      #7                  // Field mURI:Ljava/lang/String;
      30: return

  private com.ctc.wstx.sw.SimpleOutputElement(com.ctc.wstx.sw.SimpleOutputElement, java.lang.String, java.lang.String, java.lang.String, com.ctc.wstx.util.BijectiveNsMap);
    Code:
       0: aload_0
       1: aload_1
       2: aload         5
       4: invokespecial #8                  // Method com/ctc/wstx/sw/OutputElementBase."<init>":(Lcom/ctc/wstx/sw/OutputElementBase;Lcom/ctc/wstx/util/BijectiveNsMap;)V
       7: aload_0
       8: aconst_null
       9: putfield      #2                  // Field mAttrSet:Ljava/util/HashSet;
      12: aload_0
      13: aload_1
      14: putfield      #3                  // Field mParent:Lcom/ctc/wstx/sw/SimpleOutputElement;
      17: aload_0
      18: aload_2
      19: putfield      #4                  // Field mPrefix:Ljava/lang/String;
      22: aload_0
      23: aload_3
      24: putfield      #6                  // Field mLocalName:Ljava/lang/String;
      27: aload_0
      28: aload         4
      30: putfield      #7                  // Field mURI:Ljava/lang/String;
      33: return

  private void relink(com.ctc.wstx.sw.SimpleOutputElement, java.lang.String, java.lang.String, java.lang.String);
    Code:
       0: aload_0
       1: aload_1
       2: invokespecial #9                  // Method com/ctc/wstx/sw/OutputElementBase.relink:(Lcom/ctc/wstx/sw/OutputElementBase;)V
       5: aload_0
       6: aload_1
       7: putfield      #3                  // Field mParent:Lcom/ctc/wstx/sw/SimpleOutputElement;
      10: aload_0
      11: aload_2
      12: putfield      #4                  // Field mPrefix:Ljava/lang/String;
      15: aload_0
      16: aload_3
      17: putfield      #6                  // Field mLocalName:Ljava/lang/String;
      20: aload_0
      21: aload         4
      23: putfield      #7                  // Field mURI:Ljava/lang/String;
      26: aload_0
      27: aload_1
      28: getfield      #10                 // Field mNsMapping:Lcom/ctc/wstx/util/BijectiveNsMap;
      31: putfield      #10                 // Field mNsMapping:Lcom/ctc/wstx/util/BijectiveNsMap;
      34: aload_0
      35: aload_0
      36: getfield      #10                 // Field mNsMapping:Lcom/ctc/wstx/util/BijectiveNsMap;
      39: ifnull        46
      42: iconst_1
      43: goto          47
      46: iconst_0
      47: putfield      #11                 // Field mNsMapShared:Z
      50: aload_0
      51: aload_1
      52: getfield      #12                 // Field mDefaultNsURI:Ljava/lang/String;
      55: putfield      #12                 // Field mDefaultNsURI:Ljava/lang/String;
      58: aload_0
      59: aload_1
      60: getfield      #13                 // Field mRootNsContext:Ljavax/xml/namespace/NamespaceContext;
      63: putfield      #13                 // Field mRootNsContext:Ljavax/xml/namespace/NamespaceContext;
      66: return

  public static com.ctc.wstx.sw.SimpleOutputElement createRoot();
    Code:
       0: new           #14                 // class com/ctc/wstx/sw/SimpleOutputElement
       3: dup
       4: invokespecial #15                 // Method "<init>":()V
       7: areturn

  protected com.ctc.wstx.sw.SimpleOutputElement createChild(java.lang.String);
    Code:
       0: aload_0
       1: aconst_null
       2: putfield      #2                  // Field mAttrSet:Ljava/util/HashSet;
       5: new           #14                 // class com/ctc/wstx/sw/SimpleOutputElement
       8: dup
       9: aload_0
      10: aconst_null
      11: aload_1
      12: aload_0
      13: getfield      #12                 // Field mDefaultNsURI:Ljava/lang/String;
      16: aload_0
      17: getfield      #10                 // Field mNsMapping:Lcom/ctc/wstx/util/BijectiveNsMap;
      20: invokespecial #16                 // Method "<init>":(Lcom/ctc/wstx/sw/SimpleOutputElement;Ljava/lang/String;Ljava/lang/String;Ljava/lang/String;Lcom/ctc/wstx/util/BijectiveNsMap;)V
      23: areturn

  protected com.ctc.wstx.sw.SimpleOutputElement reuseAsChild(com.ctc.wstx.sw.SimpleOutputElement, java.lang.String);
    Code:
       0: aload_0
       1: aconst_null
       2: putfield      #2                  // Field mAttrSet:Ljava/util/HashSet;
       5: aload_0
       6: getfield      #3                  // Field mParent:Lcom/ctc/wstx/sw/SimpleOutputElement;
       9: astore_3
      10: aload_0
      11: aload_1
      12: aconst_null
      13: aload_2
      14: aload_0
      15: getfield      #12                 // Field mDefaultNsURI:Ljava/lang/String;
      18: invokespecial #17                 // Method relink:(Lcom/ctc/wstx/sw/SimpleOutputElement;Ljava/lang/String;Ljava/lang/String;Ljava/lang/String;)V
      21: aload_3
      22: areturn

  protected com.ctc.wstx.sw.SimpleOutputElement reuseAsChild(com.ctc.wstx.sw.SimpleOutputElement, java.lang.String, java.lang.String, java.lang.String);
    Code:
       0: aload_0
       1: aconst_null
       2: putfield      #2                  // Field mAttrSet:Ljava/util/HashSet;
       5: aload_0
       6: getfield      #3                  // Field mParent:Lcom/ctc/wstx/sw/SimpleOutputElement;
       9: astore        5
      11: aload_0
      12: aload_1
      13: aload_2
      14: aload_3
      15: aload         4
      17: invokespecial #17                 // Method relink:(Lcom/ctc/wstx/sw/SimpleOutputElement;Ljava/lang/String;Ljava/lang/String;Ljava/lang/String;)V
      20: aload         5
      22: areturn

  protected com.ctc.wstx.sw.SimpleOutputElement createChild(java.lang.String, java.lang.String, java.lang.String);
    Code:
       0: aload_0
       1: aconst_null
       2: putfield      #2                  // Field mAttrSet:Ljava/util/HashSet;
       5: new           #14                 // class com/ctc/wstx/sw/SimpleOutputElement
       8: dup
       9: aload_0
      10: aload_1
      11: aload_2
      12: aload_3
      13: aload_0
      14: getfield      #10                 // Field mNsMapping:Lcom/ctc/wstx/util/BijectiveNsMap;
      17: invokespecial #16                 // Method "<init>":(Lcom/ctc/wstx/sw/SimpleOutputElement;Ljava/lang/String;Ljava/lang/String;Ljava/lang/String;Lcom/ctc/wstx/util/BijectiveNsMap;)V
      20: areturn

  protected void addToPool(com.ctc.wstx.sw.SimpleOutputElement);
    Code:
       0: aload_0
       1: aload_1
       2: putfield      #3                  // Field mParent:Lcom/ctc/wstx/sw/SimpleOutputElement;
       5: return

  public com.ctc.wstx.sw.SimpleOutputElement getParent();
    Code:
       0: aload_0
       1: getfield      #3                  // Field mParent:Lcom/ctc/wstx/sw/SimpleOutputElement;
       4: areturn

  public boolean isRoot();
    Code:
       0: aload_0
       1: getfield      #3                  // Field mParent:Lcom/ctc/wstx/sw/SimpleOutputElement;
       4: ifnonnull     11
       7: iconst_1
       8: goto          12
      11: iconst_0
      12: ireturn

  public java.lang.String getNameDesc();
    Code:
       0: aload_0
       1: getfield      #4                  // Field mPrefix:Ljava/lang/String;
       4: ifnull        47
       7: aload_0
       8: getfield      #4                  // Field mPrefix:Ljava/lang/String;
      11: invokevirtual #18                 // Method java/lang/String.length:()I
      14: ifle          47
      17: new           #19                 // class java/lang/StringBuilder
      20: dup
      21: invokespecial #20                 // Method java/lang/StringBuilder."<init>":()V
      24: aload_0
      25: getfield      #4                  // Field mPrefix:Ljava/lang/String;
      28: invokevirtual #21                 // Method java/lang/StringBuilder.append:(Ljava/lang/String;)Ljava/lang/StringBuilder;
      31: ldc           #22                 // String :
      33: invokevirtual #21                 // Method java/lang/StringBuilder.append:(Ljava/lang/String;)Ljava/lang/StringBuilder;
      36: aload_0
      37: getfield      #6                  // Field mLocalName:Ljava/lang/String;
      40: invokevirtual #21                 // Method java/lang/StringBuilder.append:(Ljava/lang/String;)Ljava/lang/StringBuilder;
      43: invokevirtual #23                 // Method java/lang/StringBuilder.toString:()Ljava/lang/String;
      46: areturn
      47: aload_0
      48: getfield      #6                  // Field mLocalName:Ljava/lang/String;
      51: ifnull        69
      54: aload_0
      55: getfield      #6                  // Field mLocalName:Ljava/lang/String;
      58: invokevirtual #18                 // Method java/lang/String.length:()I
      61: ifle          69
      64: aload_0
      65: getfield      #6                  // Field mLocalName:Ljava/lang/String;
      68: areturn
      69: ldc           #24                 // String #error
      71: areturn

  public java.lang.String getPrefix();
    Code:
       0: aload_0
       1: getfield      #4                  // Field mPrefix:Ljava/lang/String;
       4: areturn

  public java.lang.String getLocalName();
    Code:
       0: aload_0
       1: getfield      #6                  // Field mLocalName:Ljava/lang/String;
       4: areturn

  public java.lang.String getNamespaceURI();
    Code:
       0: aload_0
       1: getfield      #7                  // Field mURI:Ljava/lang/String;
       4: areturn

  public javax.xml.namespace.QName getName();
    Code:
       0: aload_0
       1: getfield      #7                  // Field mURI:Ljava/lang/String;
       4: aload_0
       5: getfield      #6                  // Field mLocalName:Ljava/lang/String;
       8: aload_0
       9: getfield      #4                  // Field mPrefix:Ljava/lang/String;
      12: invokestatic  #25                 // Method com/ctc/wstx/compat/QNameCreator.create:(Ljava/lang/String;Ljava/lang/String;Ljava/lang/String;)Ljavax/xml/namespace/QName;
      15: areturn

  public void checkAttrWrite(java.lang.String, java.lang.String) throws javax.xml.stream.XMLStreamException;
    Code:
       0: new           #26                 // class com/ctc/wstx/sw/SimpleOutputElement$AttrName
       3: dup
       4: aload_1
       5: aload_2
       6: invokespecial #27                 // Method com/ctc/wstx/sw/SimpleOutputElement$AttrName."<init>":(Ljava/lang/String;Ljava/lang/String;)V
       9: astore_3
      10: aload_0
      11: getfield      #2                  // Field mAttrSet:Ljava/util/HashSet;
      14: ifnonnull     28
      17: aload_0
      18: new           #28                 // class java/util/HashSet
      21: dup
      22: invokespecial #29                 // Method java/util/HashSet."<init>":()V
      25: putfield      #2                  // Field mAttrSet:Ljava/util/HashSet;
      28: aload_0
      29: getfield      #2                  // Field mAttrSet:Ljava/util/HashSet;
      32: aload_3
      33: invokevirtual #30                 // Method java/util/HashSet.add:(Ljava/lang/Object;)Z
      36: ifne          71
      39: new           #31                 // class javax/xml/stream/XMLStreamException
      42: dup
      43: new           #19                 // class java/lang/StringBuilder
      46: dup
      47: invokespecial #20                 // Method java/lang/StringBuilder."<init>":()V
      50: ldc           #32                 // String Duplicate attribute write for attribute \'
      52: invokevirtual #21                 // Method java/lang/StringBuilder.append:(Ljava/lang/String;)Ljava/lang/StringBuilder;
      55: aload_3
      56: invokevirtual #33                 // Method java/lang/StringBuilder.append:(Ljava/lang/Object;)Ljava/lang/StringBuilder;
      59: ldc           #34                 // String \'
      61: invokevirtual #21                 // Method java/lang/StringBuilder.append:(Ljava/lang/String;)Ljava/lang/StringBuilder;
      64: invokevirtual #23                 // Method java/lang/StringBuilder.toString:()Ljava/lang/String;
      67: invokespecial #35                 // Method javax/xml/stream/XMLStreamException."<init>":(Ljava/lang/String;)V
      70: athrow
      71: return

  public void setPrefix(java.lang.String);
    Code:
       0: aload_0
       1: aload_1
       2: putfield      #4                  // Field mPrefix:Ljava/lang/String;
       5: return

  public void setDefaultNsUri(java.lang.String);
    Code:
       0: aload_0
       1: aload_1
       2: putfield      #12                 // Field mDefaultNsURI:Ljava/lang/String;
       5: return

  protected final void setRootNsContext(javax.xml.namespace.NamespaceContext);
    Code:
       0: aload_0
       1: aload_1
       2: putfield      #13                 // Field mRootNsContext:Ljavax/xml/namespace/NamespaceContext;
       5: aload_1
       6: ldc           #5                  // String
       8: invokeinterface #36,  2           // InterfaceMethod javax/xml/namespace/NamespaceContext.getNamespaceURI:(Ljava/lang/String;)Ljava/lang/String;
      13: astore_2
      14: aload_2
      15: ifnull        30
      18: aload_2
      19: invokevirtual #18                 // Method java/lang/String.length:()I
      22: ifle          30
      25: aload_0
      26: aload_2
      27: putfield      #12                 // Field mDefaultNsURI:Ljava/lang/String;
      30: return
}
