Compiled from "EvaluatorFactory.java"
class com.jayway.jsonpath.internal.filter.EvaluatorFactory$SizeEvaluator implements com.jayway.jsonpath.internal.filter.Evaluator {
  private com.jayway.jsonpath.internal.filter.EvaluatorFactory$SizeEvaluator();
    Code:
       0: aload_0
       1: invokespecial #2                  // Method java/lang/Object."<init>":()V
       4: return

  public boolean evaluate(com.jayway.jsonpath.internal.filter.ValueNode, com.jayway.jsonpath.internal.filter.ValueNode, com.jayway.jsonpath.Predicate$PredicateContext);
    Code:
       0: aload_2
       1: invokevirtual #3                  // Method com/jayway/jsonpath/internal/filter/ValueNode.isNumberNode:()Z
       4: ifne          9
       7: iconst_0
       8: ireturn
       9: aload_2
      10: invokevirtual #4                  // Method com/jayway/jsonpath/internal/filter/ValueNode.asNumberNode:()Lcom/jayway/jsonpath/internal/filter/ValueNode$NumberNode;
      13: invokevirtual #5                  // Method com/jayway/jsonpath/internal/filter/ValueNode$NumberNode.getNumber:()Ljava/math/BigDecimal;
      16: invokevirtual #6                  // Method java/math/BigDecimal.intValue:()I
      19: istore        4
      21: aload_1
      22: invokevirtual #7                  // Method com/jayway/jsonpath/internal/filter/ValueNode.isStringNode:()Z
      25: ifeq          46
      28: aload_1
      29: invokevirtual #8                  // Method com/jayway/jsonpath/internal/filter/ValueNode.asStringNode:()Lcom/jayway/jsonpath/internal/filter/ValueNode$StringNode;
      32: invokevirtual #9                  // Method com/jayway/jsonpath/internal/filter/ValueNode$StringNode.length:()I
      35: iload         4
      37: if_icmpne     44
      40: iconst_1
      41: goto          45
      44: iconst_0
      45: ireturn
      46: aload_1
      47: invokevirtual #10                 // Method com/jayway/jsonpath/internal/filter/ValueNode.isJsonNode:()Z
      50: ifeq          72
      53: aload_1
      54: invokevirtual #11                 // Method com/jayway/jsonpath/internal/filter/ValueNode.asJsonNode:()Lcom/jayway/jsonpath/internal/filter/ValueNode$JsonNode;
      57: aload_3
      58: invokevirtual #12                 // Method com/jayway/jsonpath/internal/filter/ValueNode$JsonNode.length:(Lcom/jayway/jsonpath/Predicate$PredicateContext;)I
      61: iload         4
      63: if_icmpne     70
      66: iconst_1
      67: goto          71
      70: iconst_0
      71: ireturn
      72: iconst_0
      73: ireturn

  com.jayway.jsonpath.internal.filter.EvaluatorFactory$SizeEvaluator(com.jayway.jsonpath.internal.filter.EvaluatorFactory$1);
    Code:
       0: aload_0
       1: invokespecial #1                  // Method "<init>":()V
       4: return
}
