Compiled from "BlankLine.java"
public class com.vladsch.flexmark.ast.BlankLine extends com.vladsch.flexmark.ast.Block {
  public com.vladsch.flexmark.ast.BlankLine();
    Code:
       0: aload_0
       1: invokespecial #1                  // Method com/vladsch/flexmark/ast/Block."<init>":()V
       4: return

  public com.vladsch.flexmark.ast.BlankLine(com.vladsch.flexmark.util.sequence.BasedSequence);
    Code:
       0: aload_0
       1: aload_1
       2: invokespecial #2                  // Method com/vladsch/flexmark/ast/Block."<init>":(Lcom/vladsch/flexmark/util/sequence/BasedSequence;)V
       5: aload_0
       6: invokevirtual #3                  // Method setCharsFromContent:()V
       9: return

  public com.vladsch.flexmark.util.sequence.BasedSequence[] getSegments();
    Code:
       0: getstatic     #4                  // Field com/vladsch/flexmark/ast/Node.EMPTY_SEGMENTS:[Lcom/vladsch/flexmark/util/sequence/BasedSequence;
       3: areturn
}
