Compiled from "Link.java"
public class com.vladsch.flexmark.ast.Link extends com.vladsch.flexmark.ast.InlineLinkNode {
  public com.vladsch.flexmark.ast.Link();
    Code:
       0: aload_0
       1: invokespecial #1                  // Method com/vladsch/flexmark/ast/InlineLinkNode."<init>":()V
       4: return

  public com.vladsch.flexmark.ast.Link(com.vladsch.flexmark.util.sequence.BasedSequence);
    Code:
       0: aload_0
       1: aload_1
       2: invokespecial #2                  // Method com/vladsch/flexmark/ast/InlineLinkNode."<init>":(Lcom/vladsch/flexmark/util/sequence/BasedSequence;)V
       5: return

  public com.vladsch.flexmark.ast.Link(com.vladsch.flexmark.util.sequence.BasedSequence, com.vladsch.flexmark.util.sequence.BasedSequence, com.vladsch.flexmark.util.sequence.BasedSequence, com.vladsch.flexmark.util.sequence.BasedSequence, com.vladsch.flexmark.util.sequence.BasedSequence, com.vladsch.flexmark.util.sequence.BasedSequence, com.vladsch.flexmark.util.sequence.BasedSequence, com.vladsch.flexmark.util.sequence.BasedSequence, com.vladsch.flexmark.util.sequence.BasedSequence);
    Code:
       0: aload_0
       1: aload_1
       2: aload_2
       3: aload_3
       4: aload         4
       6: aload         5
       8: aload         6
      10: aload         7
      12: aload         8
      14: aload         9
      16: invokespecial #3                  // Method com/vladsch/flexmark/ast/InlineLinkNode."<init>":(Lcom/vladsch/flexmark/util/sequence/BasedSequence;Lcom/vladsch/flexmark/util/sequence/BasedSequence;Lcom/vladsch/flexmark/util/sequence/BasedSequence;Lcom/vladsch/flexmark/util/sequence/BasedSequence;Lcom/vladsch/flexmark/util/sequence/BasedSequence;Lcom/vladsch/flexmark/util/sequence/BasedSequence;Lcom/vladsch/flexmark/util/sequence/BasedSequence;Lcom/vladsch/flexmark/util/sequence/BasedSequence;Lcom/vladsch/flexmark/util/sequence/BasedSequence;)V
      19: return

  public com.vladsch.flexmark.ast.Link(com.vladsch.flexmark.util.sequence.BasedSequence, com.vladsch.flexmark.util.sequence.BasedSequence, com.vladsch.flexmark.util.sequence.BasedSequence, com.vladsch.flexmark.util.sequence.BasedSequence, com.vladsch.flexmark.util.sequence.BasedSequence, com.vladsch.flexmark.util.sequence.BasedSequence, com.vladsch.flexmark.util.sequence.BasedSequence, com.vladsch.flexmark.util.sequence.BasedSequence, com.vladsch.flexmark.util.sequence.BasedSequence, com.vladsch.flexmark.util.sequence.BasedSequence);
    Code:
       0: aload_0
       1: aload_1
       2: aload_2
       3: aload_3
       4: aload         4
       6: aload         5
       8: aload         6
      10: aload         7
      12: aload         8
      14: aload         9
      16: aload         10
      18: invokespecial #4                  // Method com/vladsch/flexmark/ast/InlineLinkNode."<init>":(Lcom/vladsch/flexmark/util/sequence/BasedSequence;Lcom/vladsch/flexmark/util/sequence/BasedSequence;Lcom/vladsch/flexmark/util/sequence/BasedSequence;Lcom/vladsch/flexmark/util/sequence/BasedSequence;Lcom/vladsch/flexmark/util/sequence/BasedSequence;Lcom/vladsch/flexmark/util/sequence/BasedSequence;Lcom/vladsch/flexmark/util/sequence/BasedSequence;Lcom/vladsch/flexmark/util/sequence/BasedSequence;Lcom/vladsch/flexmark/util/sequence/BasedSequence;Lcom/vladsch/flexmark/util/sequence/BasedSequence;)V
      21: return

  public com.vladsch.flexmark.ast.Link(com.vladsch.flexmark.util.sequence.BasedSequence, com.vladsch.flexmark.util.sequence.BasedSequence, com.vladsch.flexmark.util.sequence.BasedSequence, com.vladsch.flexmark.util.sequence.BasedSequence, com.vladsch.flexmark.util.sequence.BasedSequence, com.vladsch.flexmark.util.sequence.BasedSequence);
    Code:
       0: aload_0
       1: aload_1
       2: aload_2
       3: aload_3
       4: aload         4
       6: aload         5
       8: aload         6
      10: invokespecial #5                  // Method com/vladsch/flexmark/ast/InlineLinkNode."<init>":(Lcom/vladsch/flexmark/util/sequence/BasedSequence;Lcom/vladsch/flexmark/util/sequence/BasedSequence;Lcom/vladsch/flexmark/util/sequence/BasedSequence;Lcom/vladsch/flexmark/util/sequence/BasedSequence;Lcom/vladsch/flexmark/util/sequence/BasedSequence;Lcom/vladsch/flexmark/util/sequence/BasedSequence;)V
      13: return

  public com.vladsch.flexmark.ast.Link(com.vladsch.flexmark.util.sequence.BasedSequence, com.vladsch.flexmark.util.sequence.BasedSequence, com.vladsch.flexmark.util.sequence.BasedSequence, com.vladsch.flexmark.util.sequence.BasedSequence, com.vladsch.flexmark.util.sequence.BasedSequence, com.vladsch.flexmark.util.sequence.BasedSequence, com.vladsch.flexmark.util.sequence.BasedSequence);
    Code:
       0: aload_0
       1: aload_1
       2: aload_2
       3: aload_3
       4: aload         4
       6: aload         5
       8: aload         6
      10: aload         7
      12: invokespecial #6                  // Method com/vladsch/flexmark/ast/InlineLinkNode."<init>":(Lcom/vladsch/flexmark/util/sequence/BasedSequence;Lcom/vladsch/flexmark/util/sequence/BasedSequence;Lcom/vladsch/flexmark/util/sequence/BasedSequence;Lcom/vladsch/flexmark/util/sequence/BasedSequence;Lcom/vladsch/flexmark/util/sequence/BasedSequence;Lcom/vladsch/flexmark/util/sequence/BasedSequence;Lcom/vladsch/flexmark/util/sequence/BasedSequence;)V
      15: return

  public void setTextChars(com.vladsch.flexmark.util.sequence.BasedSequence);
    Code:
       0: aload_1
       1: invokeinterface #7,  1            // InterfaceMethod com/vladsch/flexmark/util/sequence/BasedSequence.length:()I
       6: istore_2
       7: aload_0
       8: aload_1
       9: iconst_0
      10: iconst_1
      11: invokeinterface #8,  3            // InterfaceMethod com/vladsch/flexmark/util/sequence/BasedSequence.subSequence:(II)Lcom/vladsch/flexmark/util/sequence/BasedSequence;
      16: putfield      #9                  // Field textOpeningMarker:Lcom/vladsch/flexmark/util/sequence/BasedSequence;
      19: aload_0
      20: aload_1
      21: iconst_1
      22: iload_2
      23: iconst_1
      24: isub
      25: invokeinterface #8,  3            // InterfaceMethod com/vladsch/flexmark/util/sequence/BasedSequence.subSequence:(II)Lcom/vladsch/flexmark/util/sequence/BasedSequence;
      30: invokeinterface #10,  1           // InterfaceMethod com/vladsch/flexmark/util/sequence/BasedSequence.trim:()Lcom/vladsch/flexmark/util/sequence/BasedSequence;
      35: putfield      #11                 // Field text:Lcom/vladsch/flexmark/util/sequence/BasedSequence;
      38: aload_0
      39: aload_1
      40: iload_2
      41: iconst_1
      42: isub
      43: iload_2
      44: invokeinterface #8,  3            // InterfaceMethod com/vladsch/flexmark/util/sequence/BasedSequence.subSequence:(II)Lcom/vladsch/flexmark/util/sequence/BasedSequence;
      49: putfield      #12                 // Field textClosingMarker:Lcom/vladsch/flexmark/util/sequence/BasedSequence;
      52: return
}
