Compiled from "OWLDisjointClassesAxiomFrameSection.java"
public class org.protege.editor.owl.ui.frame.cls.OWLDisjointClassesAxiomFrameSection extends org.protege.editor.owl.ui.frame.cls.AbstractOWLClassAxiomFrameSection<org.semanticweb.owlapi.model.OWLDisjointClassesAxiom, java.util.Set<org.semanticweb.owlapi.model.OWLClassExpression>> {
  public static final java.lang.String LABEL;

  public java.util.Set<org.semanticweb.owlapi.model.OWLClassExpression> added;

  public org.protege.editor.owl.ui.frame.cls.OWLDisjointClassesAxiomFrameSection(org.protege.editor.owl.OWLEditorKit, org.protege.editor.owl.ui.frame.OWLFrame<org.semanticweb.owlapi.model.OWLClass>);
    Code:
       0: aload_0
       1: aload_1
       2: ldc           #2                  // String Disjoint With
       4: ldc           #2                  // String Disjoint With
       6: aload_2
       7: invokespecial #3                  // Method org/protege/editor/owl/ui/frame/cls/AbstractOWLClassAxiomFrameSection."<init>":(Lorg/protege/editor/owl/OWLEditorKit;Ljava/lang/String;Ljava/lang/String;Lorg/protege/editor/owl/ui/frame/OWLFrame;)V
      10: aload_0
      11: new           #4                  // class java/util/HashSet
      14: dup
      15: invokespecial #5                  // Method java/util/HashSet."<init>":()V
      18: putfield      #6                  // Field added:Ljava/util/Set;
      21: return

  protected void clear();
    Code:
       0: aload_0
       1: getfield      #6                  // Field added:Ljava/util/Set;
       4: invokeinterface #7,  1            // InterfaceMethod java/util/Set.clear:()V
       9: return

  protected void addAxiom(org.semanticweb.owlapi.model.OWLDisjointClassesAxiom, org.semanticweb.owlapi.model.OWLOntology);
    Code:
       0: aload_0
       1: new           #8                  // class org/protege/editor/owl/ui/frame/cls/OWLDisjointClassesAxiomFrameSectionRow
       4: dup
       5: aload_0
       6: invokevirtual #9                  // Method getOWLEditorKit:()Lorg/protege/editor/owl/OWLEditorKit;
       9: aload_0
      10: aload_2
      11: aload_0
      12: invokevirtual #10                 // Method getRootObject:()Lorg/semanticweb/owlapi/model/OWLClassExpression;
      15: aload_1
      16: invokespecial #11                 // Method org/protege/editor/owl/ui/frame/cls/OWLDisjointClassesAxiomFrameSectionRow."<init>":(Lorg/protege/editor/owl/OWLEditorKit;Lorg/protege/editor/owl/ui/frame/OWLFrameSection;Lorg/semanticweb/owlapi/model/OWLOntology;Lorg/semanticweb/owlapi/model/OWLClassExpression;Lorg/semanticweb/owlapi/model/OWLDisjointClassesAxiom;)V
      19: invokevirtual #12                 // Method addRow:(Lorg/protege/editor/owl/ui/frame/OWLFrameSectionRow;)V
      22: aload_0
      23: getfield      #6                  // Field added:Ljava/util/Set;
      26: aload_1
      27: invokeinterface #13,  1           // InterfaceMethod org/semanticweb/owlapi/model/OWLDisjointClassesAxiom.getClassExpressions:()Ljava/util/Set;
      32: invokeinterface #14,  2           // InterfaceMethod java/util/Set.addAll:(Ljava/util/Collection;)Z
      37: pop
      38: return

  protected java.util.Set<org.semanticweb.owlapi.model.OWLDisjointClassesAxiom> getClassAxioms(org.semanticweb.owlapi.model.OWLClassExpression, org.semanticweb.owlapi.model.OWLOntology);
    Code:
       0: aload_1
       1: invokeinterface #15,  1           // InterfaceMethod org/semanticweb/owlapi/model/OWLClassExpression.isAnonymous:()Z
       6: ifne          22
       9: aload_2
      10: aload_1
      11: invokeinterface #16,  1           // InterfaceMethod org/semanticweb/owlapi/model/OWLClassExpression.asOWLClass:()Lorg/semanticweb/owlapi/model/OWLClass;
      16: invokeinterface #17,  2           // InterfaceMethod org/semanticweb/owlapi/model/OWLOntology.getDisjointClassesAxioms:(Lorg/semanticweb/owlapi/model/OWLClass;)Ljava/util/Set;
      21: areturn
      22: new           #4                  // class java/util/HashSet
      25: dup
      26: invokespecial #5                  // Method java/util/HashSet."<init>":()V
      29: astore_3
      30: aload_2
      31: getstatic     #18                 // Field org/semanticweb/owlapi/model/AxiomType.DISJOINT_CLASSES:Lorg/semanticweb/owlapi/model/AxiomType;
      34: invokeinterface #19,  2           // InterfaceMethod org/semanticweb/owlapi/model/OWLOntology.getAxioms:(Lorg/semanticweb/owlapi/model/AxiomType;)Ljava/util/Set;
      39: invokeinterface #20,  1           // InterfaceMethod java/util/Set.iterator:()Ljava/util/Iterator;
      44: astore        4
      46: aload         4
      48: invokeinterface #21,  1           // InterfaceMethod java/util/Iterator.hasNext:()Z
      53: ifeq          96
      56: aload         4
      58: invokeinterface #22,  1           // InterfaceMethod java/util/Iterator.next:()Ljava/lang/Object;
      63: checkcast     #23                 // class org/semanticweb/owlapi/model/OWLDisjointClassesAxiom
      66: astore        5
      68: aload         5
      70: invokeinterface #13,  1           // InterfaceMethod org/semanticweb/owlapi/model/OWLDisjointClassesAxiom.getClassExpressions:()Ljava/util/Set;
      75: aload_1
      76: invokeinterface #24,  2           // InterfaceMethod java/util/Set.contains:(Ljava/lang/Object;)Z
      81: ifeq          93
      84: aload_3
      85: aload         5
      87: invokeinterface #25,  2           // InterfaceMethod java/util/Set.add:(Ljava/lang/Object;)Z
      92: pop
      93: goto          46
      96: aload_3
      97: areturn

  protected org.semanticweb.owlapi.model.OWLDisjointClassesAxiom createAxiom(java.util.Set<org.semanticweb.owlapi.model.OWLClassExpression>);
    Code:
       0: aload_1
       1: aload_0
       2: invokevirtual #10                 // Method getRootObject:()Lorg/semanticweb/owlapi/model/OWLClassExpression;
       5: invokeinterface #25,  2           // InterfaceMethod java/util/Set.add:(Ljava/lang/Object;)Z
      10: pop
      11: aload_0
      12: invokevirtual #26                 // Method getOWLDataFactory:()Lorg/semanticweb/owlapi/model/OWLDataFactory;
      15: aload_1
      16: invokeinterface #27,  2           // InterfaceMethod org/semanticweb/owlapi/model/OWLDataFactory.getOWLDisjointClassesAxiom:(Ljava/util/Set;)Lorg/semanticweb/owlapi/model/OWLDisjointClassesAxiom;
      21: areturn

  public org.protege.editor.owl.ui.editor.OWLObjectEditor<java.util.Set<org.semanticweb.owlapi.model.OWLClassExpression>> getObjectEditor();
    Code:
       0: new           #28                 // class org/protege/editor/owl/ui/editor/OWLClassExpressionSetEditor
       3: dup
       4: aload_0
       5: invokevirtual #9                  // Method getOWLEditorKit:()Lorg/protege/editor/owl/OWLEditorKit;
       8: invokespecial #29                 // Method org/protege/editor/owl/ui/editor/OWLClassExpressionSetEditor."<init>":(Lorg/protege/editor/owl/OWLEditorKit;)V
      11: areturn

  protected void refillInferred();
    Code:
       0: aload_0
       1: invokevirtual #30                 // Method getOWLModelManager:()Lorg/protege/editor/owl/model/OWLModelManager;
       4: invokeinterface #31,  1           // InterfaceMethod org/protege/editor/owl/model/OWLModelManager.getReasonerPreferences:()Lorg/protege/editor/owl/model/inference/ReasonerPreferences;
       9: getstatic     #32                 // Field org/protege/editor/owl/model/inference/ReasonerPreferences$OptionalInferenceTask.SHOW_INFERRED_DISJOINT_CLASSES:Lorg/protege/editor/owl/model/inference/ReasonerPreferences$OptionalInferenceTask;
      12: aload_0
      13: invokedynamic #33,  0             // InvokeDynamic #0:run:(Lorg/protege/editor/owl/ui/frame/cls/OWLDisjointClassesAxiomFrameSection;)Ljava/lang/Runnable;
      18: invokevirtual #34                 // Method org/protege/editor/owl/model/inference/ReasonerPreferences.executeTask:(Lorg/protege/editor/owl/model/inference/ReasonerPreferences$OptionalInferenceTask;Ljava/lang/Runnable;)V
      21: return

  public boolean checkEditorResults(org.protege.editor.owl.ui.editor.OWLObjectEditor<java.util.Set<org.semanticweb.owlapi.model.OWLClassExpression>>);
    Code:
       0: aload_1
       1: invokeinterface #35,  1           // InterfaceMethod org/protege/editor/owl/ui/editor/OWLObjectEditor.getEditedObject:()Ljava/lang/Object;
       6: checkcast     #36                 // class java/util/Set
       9: astore_2
      10: aload_2
      11: invokeinterface #37,  1           // InterfaceMethod java/util/Set.size:()I
      16: iconst_1
      17: if_icmpne     33
      20: aload_2
      21: aload_0
      22: invokevirtual #10                 // Method getRootObject:()Lorg/semanticweb/owlapi/model/OWLClassExpression;
      25: invokeinterface #24,  2           // InterfaceMethod java/util/Set.contains:(Ljava/lang/Object;)Z
      30: ifne          37
      33: iconst_1
      34: goto          38
      37: iconst_0
      38: ireturn

  public boolean canAcceptDrop(java.util.List<org.semanticweb.owlapi.model.OWLObject>);
    Code:
       0: aload_1
       1: invokeinterface #38,  1           // InterfaceMethod java/util/List.iterator:()Ljava/util/Iterator;
       6: astore_2
       7: aload_2
       8: invokeinterface #21,  1           // InterfaceMethod java/util/Iterator.hasNext:()Z
      13: ifeq          38
      16: aload_2
      17: invokeinterface #22,  1           // InterfaceMethod java/util/Iterator.next:()Ljava/lang/Object;
      22: checkcast     #39                 // class org/semanticweb/owlapi/model/OWLObject
      25: astore_3
      26: aload_3
      27: instanceof    #40                 // class org/semanticweb/owlapi/model/OWLClassExpression
      30: ifne          35
      33: iconst_0
      34: ireturn
      35: goto          7
      38: iconst_1
      39: ireturn

  public boolean dropObjects(java.util.List<org.semanticweb.owlapi.model.OWLObject>);
    Code:
       0: new           #41                 // class java/util/ArrayList
       3: dup
       4: invokespecial #42                 // Method java/util/ArrayList."<init>":()V
       7: astore_2
       8: new           #4                  // class java/util/HashSet
      11: dup
      12: invokespecial #5                  // Method java/util/HashSet."<init>":()V
      15: astore_3
      16: aload_3
      17: aload_0
      18: invokevirtual #10                 // Method getRootObject:()Lorg/semanticweb/owlapi/model/OWLClassExpression;
      21: invokeinterface #25,  2           // InterfaceMethod java/util/Set.add:(Ljava/lang/Object;)Z
      26: pop
      27: aload_1
      28: invokeinterface #38,  1           // InterfaceMethod java/util/List.iterator:()Ljava/util/Iterator;
      33: astore        4
      35: aload         4
      37: invokeinterface #21,  1           // InterfaceMethod java/util/Iterator.hasNext:()Z
      42: ifeq          89
      45: aload         4
      47: invokeinterface #22,  1           // InterfaceMethod java/util/Iterator.next:()Ljava/lang/Object;
      52: checkcast     #39                 // class org/semanticweb/owlapi/model/OWLObject
      55: astore        5
      57: aload         5
      59: instanceof    #40                 // class org/semanticweb/owlapi/model/OWLClassExpression
      62: ifeq          84
      65: aload         5
      67: checkcast     #40                 // class org/semanticweb/owlapi/model/OWLClassExpression
      70: astore        6
      72: aload_3
      73: aload         6
      75: invokeinterface #25,  2           // InterfaceMethod java/util/Set.add:(Ljava/lang/Object;)Z
      80: pop
      81: goto          86
      84: iconst_0
      85: ireturn
      86: goto          35
      89: aload_3
      90: invokeinterface #37,  1           // InterfaceMethod java/util/Set.size:()I
      95: iconst_1
      96: if_icmple     146
      99: aload_0
     100: invokevirtual #26                 // Method getOWLDataFactory:()Lorg/semanticweb/owlapi/model/OWLDataFactory;
     103: aload_3
     104: invokeinterface #27,  2           // InterfaceMethod org/semanticweb/owlapi/model/OWLDataFactory.getOWLDisjointClassesAxiom:(Ljava/util/Set;)Lorg/semanticweb/owlapi/model/OWLDisjointClassesAxiom;
     109: astore        4
     111: aload_2
     112: new           #43                 // class org/semanticweb/owlapi/model/AddAxiom
     115: dup
     116: aload_0
     117: invokevirtual #30                 // Method getOWLModelManager:()Lorg/protege/editor/owl/model/OWLModelManager;
     120: invokeinterface #44,  1           // InterfaceMethod org/protege/editor/owl/model/OWLModelManager.getActiveOntology:()Lorg/semanticweb/owlapi/model/OWLOntology;
     125: aload         4
     127: invokespecial #45                 // Method org/semanticweb/owlapi/model/AddAxiom."<init>":(Lorg/semanticweb/owlapi/model/OWLOntology;Lorg/semanticweb/owlapi/model/OWLAxiom;)V
     130: invokeinterface #46,  2           // InterfaceMethod java/util/List.add:(Ljava/lang/Object;)Z
     135: pop
     136: aload_0
     137: invokevirtual #30                 // Method getOWLModelManager:()Lorg/protege/editor/owl/model/OWLModelManager;
     140: aload_2
     141: invokeinterface #47,  2           // InterfaceMethod org/protege/editor/owl/model/OWLModelManager.applyChanges:(Ljava/util/List;)V
     146: iconst_1
     147: ireturn

  protected boolean isResettingChange(org.semanticweb.owlapi.model.OWLOntologyChange);
    Code:
       0: aload_1
       1: invokevirtual #48                 // Method org/semanticweb/owlapi/model/OWLOntologyChange.isAxiomChange:()Z
       4: ifeq          45
       7: aload_1
       8: invokevirtual #49                 // Method org/semanticweb/owlapi/model/OWLOntologyChange.getAxiom:()Lorg/semanticweb/owlapi/model/OWLAxiom;
      11: instanceof    #23                 // class org/semanticweb/owlapi/model/OWLDisjointClassesAxiom
      14: ifeq          45
      17: aload_1
      18: invokevirtual #49                 // Method org/semanticweb/owlapi/model/OWLOntologyChange.getAxiom:()Lorg/semanticweb/owlapi/model/OWLAxiom;
      21: checkcast     #23                 // class org/semanticweb/owlapi/model/OWLDisjointClassesAxiom
      24: invokeinterface #13,  1           // InterfaceMethod org/semanticweb/owlapi/model/OWLDisjointClassesAxiom.getClassExpressions:()Ljava/util/Set;
      29: aload_0
      30: invokevirtual #10                 // Method getRootObject:()Lorg/semanticweb/owlapi/model/OWLClassExpression;
      33: invokeinterface #24,  2           // InterfaceMethod java/util/Set.contains:(Ljava/lang/Object;)Z
      38: ifeq          45
      41: iconst_1
      42: goto          46
      45: iconst_0
      46: ireturn

  public java.util.Comparator<org.protege.editor.owl.ui.frame.OWLFrameSectionRow<org.semanticweb.owlapi.model.OWLClassExpression, org.semanticweb.owlapi.model.OWLDisjointClassesAxiom, java.util.Set<org.semanticweb.owlapi.model.OWLClassExpression>>> getRowComparator();
    Code:
       0: aconst_null
       1: areturn

  protected void addAxiom(org.semanticweb.owlapi.model.OWLAxiom, org.semanticweb.owlapi.model.OWLOntology);
    Code:
       0: aload_0
       1: aload_1
       2: checkcast     #23                 // class org/semanticweb/owlapi/model/OWLDisjointClassesAxiom
       5: aload_2
       6: invokevirtual #50                 // Method addAxiom:(Lorg/semanticweb/owlapi/model/OWLDisjointClassesAxiom;Lorg/semanticweb/owlapi/model/OWLOntology;)V
       9: return

  protected org.semanticweb.owlapi.model.OWLAxiom createAxiom(java.lang.Object);
    Code:
       0: aload_0
       1: aload_1
       2: checkcast     #36                 // class java/util/Set
       5: invokevirtual #51                 // Method createAxiom:(Ljava/util/Set;)Lorg/semanticweb/owlapi/model/OWLDisjointClassesAxiom;
       8: areturn

  private void lambda$refillInferred$0();
    Code:
       0: aload_0
       1: invokevirtual #30                 // Method getOWLModelManager:()Lorg/protege/editor/owl/model/OWLModelManager;
       4: invokeinterface #52,  1           // InterfaceMethod org/protege/editor/owl/model/OWLModelManager.getReasoner:()Lorg/semanticweb/owlapi/reasoner/OWLReasoner;
       9: astore_1
      10: aload_1
      11: invokeinterface #53,  1           // InterfaceMethod org/semanticweb/owlapi/reasoner/OWLReasoner.isConsistent:()Z
      16: ifne          20
      19: return
      20: aload_1
      21: aload_0
      22: invokevirtual #26                 // Method getOWLDataFactory:()Lorg/semanticweb/owlapi/model/OWLDataFactory;
      25: aload_0
      26: invokevirtual #10                 // Method getRootObject:()Lorg/semanticweb/owlapi/model/OWLClassExpression;
      29: invokeinterface #54,  2           // InterfaceMethod org/semanticweb/owlapi/model/OWLDataFactory.getOWLObjectComplementOf:(Lorg/semanticweb/owlapi/model/OWLClassExpression;)Lorg/semanticweb/owlapi/model/OWLObjectComplementOf;
      34: iconst_1
      35: invokeinterface #55,  3           // InterfaceMethod org/semanticweb/owlapi/reasoner/OWLReasoner.getSubClasses:(Lorg/semanticweb/owlapi/model/OWLClassExpression;Z)Lorg/semanticweb/owlapi/reasoner/NodeSet;
      40: astore_2
      41: aload_2
      42: invokeinterface #56,  1           // InterfaceMethod org/semanticweb/owlapi/reasoner/NodeSet.getFlattened:()Ljava/util/Set;
      47: invokeinterface #20,  1           // InterfaceMethod java/util/Set.iterator:()Ljava/util/Iterator;
      52: astore_3
      53: aload_3
      54: invokeinterface #21,  1           // InterfaceMethod java/util/Iterator.hasNext:()Z
      59: ifeq          165
      62: aload_3
      63: invokeinterface #22,  1           // InterfaceMethod java/util/Iterator.next:()Ljava/lang/Object;
      68: checkcast     #57                 // class org/semanticweb/owlapi/model/OWLClass
      71: astore        4
      73: aload_0
      74: getfield      #6                  // Field added:Ljava/util/Set;
      77: aload         4
      79: invokeinterface #24,  2           // InterfaceMethod java/util/Set.contains:(Ljava/lang/Object;)Z
      84: ifne          162
      87: aload         4
      89: aload_0
      90: invokevirtual #10                 // Method getRootObject:()Lorg/semanticweb/owlapi/model/OWLClassExpression;
      93: invokevirtual #58                 // Method java/lang/Object.equals:(Ljava/lang/Object;)Z
      96: ifne          162
      99: aload_0
     100: new           #8                  // class org/protege/editor/owl/ui/frame/cls/OWLDisjointClassesAxiomFrameSectionRow
     103: dup
     104: aload_0
     105: invokevirtual #9                  // Method getOWLEditorKit:()Lorg/protege/editor/owl/OWLEditorKit;
     108: aload_0
     109: aconst_null
     110: aload_0
     111: invokevirtual #10                 // Method getRootObject:()Lorg/semanticweb/owlapi/model/OWLClassExpression;
     114: aload_0
     115: invokevirtual #30                 // Method getOWLModelManager:()Lorg/protege/editor/owl/model/OWLModelManager;
     118: invokeinterface #59,  1           // InterfaceMethod org/protege/editor/owl/model/OWLModelManager.getOWLDataFactory:()Lorg/semanticweb/owlapi/model/OWLDataFactory;
     123: iconst_2
     124: anewarray     #40                 // class org/semanticweb/owlapi/model/OWLClassExpression
     127: dup
     128: iconst_0
     129: aload_0
     130: invokevirtual #10                 // Method getRootObject:()Lorg/semanticweb/owlapi/model/OWLClassExpression;
     133: aastore
     134: dup
     135: iconst_1
     136: aload         4
     138: aastore
     139: invokeinterface #60,  2           // InterfaceMethod org/semanticweb/owlapi/model/OWLDataFactory.getOWLDisjointClassesAxiom:([Lorg/semanticweb/owlapi/model/OWLClassExpression;)Lorg/semanticweb/owlapi/model/OWLDisjointClassesAxiom;
     144: invokespecial #11                 // Method org/protege/editor/owl/ui/frame/cls/OWLDisjointClassesAxiomFrameSectionRow."<init>":(Lorg/protege/editor/owl/OWLEditorKit;Lorg/protege/editor/owl/ui/frame/OWLFrameSection;Lorg/semanticweb/owlapi/model/OWLOntology;Lorg/semanticweb/owlapi/model/OWLClassExpression;Lorg/semanticweb/owlapi/model/OWLDisjointClassesAxiom;)V
     147: invokevirtual #61                 // Method addInferredRowIfNontrivial:(Lorg/protege/editor/owl/ui/frame/OWLFrameSectionRow;)V
     150: aload_0
     151: getfield      #6                  // Field added:Ljava/util/Set;
     154: aload         4
     156: invokeinterface #25,  2           // InterfaceMethod java/util/Set.add:(Ljava/lang/Object;)Z
     161: pop
     162: goto          53
     165: return
}
