Compiled from "EventExpressionRootObject.java"
class org.springframework.context.event.EventExpressionRootObject {
  private final org.springframework.context.ApplicationEvent event;

  private final java.lang.Object[] args;

  public org.springframework.context.event.EventExpressionRootObject(org.springframework.context.ApplicationEvent, java.lang.Object[]);
    Code:
       0: aload_0
       1: invokespecial #1                  // Method java/lang/Object."<init>":()V
       4: aload_0
       5: aload_1
       6: putfield      #2                  // Field event:Lorg/springframework/context/ApplicationEvent;
       9: aload_0
      10: aload_2
      11: putfield      #3                  // Field args:[Ljava/lang/Object;
      14: return

  public org.springframework.context.ApplicationEvent getEvent();
    Code:
       0: aload_0
       1: getfield      #2                  // Field event:Lorg/springframework/context/ApplicationEvent;
       4: areturn

  public java.lang.Object[] getArgs();
    Code:
       0: aload_0
       1: getfield      #3                  // Field args:[Ljava/lang/Object;
       4: areturn
}
