Compiled from "AnnotationExtractorViaEnumClass.java"
public class ch.qos.cal10n.util.AnnotationExtractorViaEnumClass extends ch.qos.cal10n.util.AbstractAnnotationExtractor {
  final java.lang.Class<?> enumClass;

  public ch.qos.cal10n.util.AnnotationExtractorViaEnumClass(java.lang.Class<?>);
    Code:
       0: aload_0
       1: invokespecial #1                  // Method ch/qos/cal10n/util/AbstractAnnotationExtractor."<init>":()V
       4: aload_0
       5: aload_1
       6: putfield      #2                  // Field enumClass:Ljava/lang/Class;
       9: return

  public java.lang.String getBaseName();
    Code:
       0: aload_0
       1: getfield      #2                  // Field enumClass:Ljava/lang/Class;
       4: ldc_w         #3                  // class ch/qos/cal10n/BaseName
       7: invokevirtual #4                  // Method java/lang/Class.getAnnotation:(Ljava/lang/Class;)Ljava/lang/annotation/Annotation;
      10: checkcast     #3                  // class ch/qos/cal10n/BaseName
      13: astore_1
      14: aload_1
      15: ifnonnull     20
      18: aconst_null
      19: areturn
      20: aload_1
      21: invokeinterface #5,  1            // InterfaceMethod ch/qos/cal10n/BaseName.value:()Ljava/lang/String;
      26: areturn

  protected ch.qos.cal10n.LocaleData extractLocaleData();
    Code:
       0: aload_0
       1: getfield      #2                  // Field enumClass:Ljava/lang/Class;
       4: ldc_w         #6                  // class ch/qos/cal10n/LocaleData
       7: invokevirtual #4                  // Method java/lang/Class.getAnnotation:(Ljava/lang/Class;)Ljava/lang/annotation/Annotation;
      10: checkcast     #6                  // class ch/qos/cal10n/LocaleData
      13: areturn
}
