Compiled from "CAL10NBundle.java"
public class ch.qos.cal10n.util.CAL10NBundle extends java.util.ResourceBundle {
  static long CHECK_DELAY;

  java.util.Map<java.lang.String, java.lang.String> map;

  java.io.File hostFile;

  volatile long nextCheck;

  long lastModified;

  ch.qos.cal10n.util.CAL10NBundle parent;

  public ch.qos.cal10n.util.CAL10NBundle(java.io.Reader, java.io.File) throws java.io.IOException;
    Code:
       0: aload_0
       1: invokespecial #1                  // Method java/util/ResourceBundle."<init>":()V
       4: aload_0
       5: new           #2                  // class java/util/concurrent/ConcurrentHashMap
       8: dup
       9: invokespecial #3                  // Method java/util/concurrent/ConcurrentHashMap."<init>":()V
      12: putfield      #4                  // Field map:Ljava/util/Map;
      15: aload_0
      16: aload_1
      17: invokevirtual #5                  // Method read:(Ljava/io/Reader;)V
      20: aload_0
      21: aload_2
      22: putfield      #6                  // Field hostFile:Ljava/io/File;
      25: aload_0
      26: invokestatic  #7                  // Method java/lang/System.currentTimeMillis:()J
      29: getstatic     #8                  // Field CHECK_DELAY:J
      32: ladd
      33: putfield      #9                  // Field nextCheck:J
      36: return

  void read(java.io.Reader) throws java.io.IOException;
    Code:
       0: new           #10                 // class ch/qos/cal10n/util/Parser
       3: dup
       4: aload_1
       5: aload_0
       6: getfield      #4                  // Field map:Ljava/util/Map;
       9: invokespecial #11                 // Method ch/qos/cal10n/util/Parser."<init>":(Ljava/io/Reader;Ljava/util/Map;)V
      12: astore_2
      13: aload_2
      14: invokevirtual #12                 // Method ch/qos/cal10n/util/Parser.parseAndPopulate:()V
      17: return

  public void setParent(ch.qos.cal10n.util.CAL10NBundle);
    Code:
       0: aload_0
       1: aload_1
       2: putfield      #13                 // Field parent:Lch/qos/cal10n/util/CAL10NBundle;
       5: return

  public boolean hasChanged();
    Code:
       0: aload_0
       1: getfield      #6                  // Field hostFile:Ljava/io/File;
       4: ifnonnull     9
       7: iconst_0
       8: ireturn
       9: invokestatic  #7                  // Method java/lang/System.currentTimeMillis:()J
      12: lstore_1
      13: lload_1
      14: aload_0
      15: getfield      #9                  // Field nextCheck:J
      18: lcmp
      19: ifge          24
      22: iconst_0
      23: ireturn
      24: aload_0
      25: lload_1
      26: getstatic     #8                  // Field CHECK_DELAY:J
      29: ladd
      30: putfield      #9                  // Field nextCheck:J
      33: aload_0
      34: getfield      #14                 // Field lastModified:J
      37: aload_0
      38: getfield      #6                  // Field hostFile:Ljava/io/File;
      41: invokevirtual #15                 // Method java/io/File.lastModified:()J
      44: lcmp
      45: ifeq          61
      48: aload_0
      49: aload_0
      50: getfield      #6                  // Field hostFile:Ljava/io/File;
      53: invokevirtual #15                 // Method java/io/File.lastModified:()J
      56: putfield      #14                 // Field lastModified:J
      59: iconst_1
      60: ireturn
      61: iconst_0
      62: ireturn

  public void resetCheckTimes();
    Code:
       0: aload_0
       1: lconst_0
       2: putfield      #9                  // Field nextCheck:J
       5: aload_0
       6: lconst_0
       7: putfield      #14                 // Field lastModified:J
      10: return

  public java.util.Enumeration<java.lang.String> getKeys();
    Code:
       0: new           #16                 // class java/util/Hashtable
       3: dup
       4: aload_0
       5: getfield      #4                  // Field map:Ljava/util/Map;
       8: invokespecial #17                 // Method java/util/Hashtable."<init>":(Ljava/util/Map;)V
      11: astore_1
      12: aload_0
      13: getfield      #13                 // Field parent:Lch/qos/cal10n/util/CAL10NBundle;
      16: ifnull        30
      19: aload_1
      20: aload_0
      21: getfield      #13                 // Field parent:Lch/qos/cal10n/util/CAL10NBundle;
      24: getfield      #4                  // Field map:Ljava/util/Map;
      27: invokevirtual #18                 // Method java/util/Hashtable.putAll:(Ljava/util/Map;)V
      30: aload_1
      31: invokevirtual #19                 // Method java/util/Hashtable.keys:()Ljava/util/Enumeration;
      34: areturn

  protected java.lang.Object handleGetObject(java.lang.String);
    Code:
       0: aload_1
       1: ifnonnull     12
       4: new           #20                 // class java/lang/NullPointerException
       7: dup
       8: invokespecial #21                 // Method java/lang/NullPointerException."<init>":()V
      11: athrow
      12: aload_0
      13: getfield      #4                  // Field map:Ljava/util/Map;
      16: aload_1
      17: invokeinterface #22,  2           // InterfaceMethod java/util/Map.get:(Ljava/lang/Object;)Ljava/lang/Object;
      22: astore_2
      23: aload_2
      24: ifnonnull     43
      27: aload_0
      28: getfield      #13                 // Field parent:Lch/qos/cal10n/util/CAL10NBundle;
      31: ifnull        43
      34: aload_0
      35: getfield      #13                 // Field parent:Lch/qos/cal10n/util/CAL10NBundle;
      38: aload_1
      39: invokevirtual #23                 // Method handleGetObject:(Ljava/lang/String;)Ljava/lang/Object;
      42: astore_2
      43: aload_2
      44: areturn

  static {};
    Code:
       0: ldc2_w        #24                 // long 600000l
       3: putstatic     #8                  // Field CHECK_DELAY:J
       6: return
}
