Compiled from "Parser.java"
class ch.qos.cal10n.util.Parser$1 {
  static final int[] $SwitchMap$ch$qos$cal10n$util$Token$TokenType;

  static {};
    Code:
       0: invokestatic  #1                  // Method ch/qos/cal10n/util/Token$TokenType.values:()[Lch/qos/cal10n/util/Token$TokenType;
       3: arraylength
       4: newarray       int
       6: putstatic     #2                  // Field $SwitchMap$ch$qos$cal10n$util$Token$TokenType:[I
       9: getstatic     #2                  // Field $SwitchMap$ch$qos$cal10n$util$Token$TokenType:[I
      12: getstatic     #3                  // Field ch/qos/cal10n/util/Token$TokenType.EOL:Lch/qos/cal10n/util/Token$TokenType;
      15: invokevirtual #4                  // Method ch/qos/cal10n/util/Token$TokenType.ordinal:()I
      18: iconst_1
      19: iastore
      20: goto          24
      23: astore_0
      24: getstatic     #2                  // Field $SwitchMap$ch$qos$cal10n$util$Token$TokenType:[I
      27: getstatic     #6                  // Field ch/qos/cal10n/util/Token$TokenType.KEY:Lch/qos/cal10n/util/Token$TokenType;
      30: invokevirtual #4                  // Method ch/qos/cal10n/util/Token$TokenType.ordinal:()I
      33: iconst_2
      34: iastore
      35: goto          39
      38: astore_0
      39: return
    Exception table:
       from    to  target type
           9    20    23   Class java/lang/NoSuchFieldError
          24    35    38   Class java/lang/NoSuchFieldError
}
