Compiled from "FunctionMetaData.java"
public class org.jboss.metadata.web.spec.FunctionMetaData extends org.jboss.metadata.javaee.support.NamedMetaDataWithDescriptionGroup {
  private static final long serialVersionUID;

  private java.lang.String functionClass;

  private java.lang.String functionSignature;

  private java.util.List<java.lang.String> examples;

  private java.util.List<org.jboss.metadata.web.spec.TldExtensionMetaData> functionExtensions;

  public org.jboss.metadata.web.spec.FunctionMetaData();
    Code:
       0: aload_0
       1: invokespecial #1                  // Method org/jboss/metadata/javaee/support/NamedMetaDataWithDescriptionGroup."<init>":()V
       4: return

  public java.lang.String getFunctionClass();
    Code:
       0: aload_0
       1: getfield      #2                  // Field functionClass:Ljava/lang/String;
       4: areturn

  public void setFunctionClass(java.lang.String);
    Code:
       0: aload_0
       1: aload_1
       2: putfield      #2                  // Field functionClass:Ljava/lang/String;
       5: return

  public java.lang.String getFunctionSignature();
    Code:
       0: aload_0
       1: getfield      #3                  // Field functionSignature:Ljava/lang/String;
       4: areturn

  public void setFunctionSignature(java.lang.String);
    Code:
       0: aload_0
       1: aload_1
       2: putfield      #3                  // Field functionSignature:Ljava/lang/String;
       5: return

  public java.util.List<java.lang.String> getExamples();
    Code:
       0: aload_0
       1: getfield      #4                  // Field examples:Ljava/util/List;
       4: areturn

  public void setExamples(java.util.List<java.lang.String>);
    Code:
       0: aload_0
       1: aload_1
       2: putfield      #4                  // Field examples:Ljava/util/List;
       5: return

  public java.util.List<org.jboss.metadata.web.spec.TldExtensionMetaData> getFunctionExtensions();
    Code:
       0: aload_0
       1: getfield      #5                  // Field functionExtensions:Ljava/util/List;
       4: areturn

  public void setFunctionExtensions(java.util.List<org.jboss.metadata.web.spec.TldExtensionMetaData>);
    Code:
       0: aload_0
       1: aload_1
       2: putfield      #5                  // Field functionExtensions:Ljava/util/List;
       5: return

  public java.lang.String toString();
    Code:
       0: new           #6                  // class java/lang/StringBuilder
       3: dup
       4: ldc           #7                  // String FunctionMetaData(id=
       6: invokespecial #8                  // Method java/lang/StringBuilder."<init>":(Ljava/lang/String;)V
       9: astore_1
      10: aload_1
      11: aload_0
      12: invokevirtual #9                  // Method getId:()Ljava/lang/String;
      15: invokevirtual #10                 // Method java/lang/StringBuilder.append:(Ljava/lang/String;)Ljava/lang/StringBuilder;
      18: pop
      19: aload_1
      20: ldc           #11                 // String ,functionClass=
      22: invokevirtual #10                 // Method java/lang/StringBuilder.append:(Ljava/lang/String;)Ljava/lang/StringBuilder;
      25: pop
      26: aload_1
      27: aload_0
      28: getfield      #2                  // Field functionClass:Ljava/lang/String;
      31: invokevirtual #10                 // Method java/lang/StringBuilder.append:(Ljava/lang/String;)Ljava/lang/StringBuilder;
      34: pop
      35: aload_1
      36: ldc           #12                 // String ,functionSignature=
      38: invokevirtual #10                 // Method java/lang/StringBuilder.append:(Ljava/lang/String;)Ljava/lang/StringBuilder;
      41: pop
      42: aload_1
      43: aload_0
      44: getfield      #3                  // Field functionSignature:Ljava/lang/String;
      47: invokevirtual #10                 // Method java/lang/StringBuilder.append:(Ljava/lang/String;)Ljava/lang/StringBuilder;
      50: pop
      51: aload_1
      52: bipush        41
      54: invokevirtual #13                 // Method java/lang/StringBuilder.append:(C)Ljava/lang/StringBuilder;
      57: pop
      58: aload_1
      59: invokevirtual #14                 // Method java/lang/StringBuilder.toString:()Ljava/lang/String;
      62: areturn
}
