Compiled from "LocaleEncodingMetaData.java"
public class org.jboss.metadata.web.spec.LocaleEncodingMetaData extends org.jboss.metadata.javaee.support.IdMetaDataImpl {
  private static final long serialVersionUID;

  protected java.lang.String locale;

  protected java.lang.String encoding;

  public org.jboss.metadata.web.spec.LocaleEncodingMetaData();
    Code:
       0: aload_0
       1: invokespecial #1                  // Method org/jboss/metadata/javaee/support/IdMetaDataImpl."<init>":()V
       4: return

  public java.lang.String getLocale();
    Code:
       0: aload_0
       1: getfield      #2                  // Field locale:Ljava/lang/String;
       4: areturn

  public void setLocale(java.lang.String);
    Code:
       0: aload_0
       1: aload_1
       2: putfield      #2                  // Field locale:Ljava/lang/String;
       5: return

  public java.lang.String getEncoding();
    Code:
       0: aload_0
       1: getfield      #3                  // Field encoding:Ljava/lang/String;
       4: areturn

  public void setEncoding(java.lang.String);
    Code:
       0: aload_0
       1: aload_1
       2: putfield      #3                  // Field encoding:Ljava/lang/String;
       5: return
}
