Compiled from "SimpleActiveIdleMessageSourceAdvice.java"
public class org.springframework.integration.aop.SimpleActiveIdleMessageSourceAdvice extends org.springframework.integration.aop.AbstractMessageSourceAdvice {
  private final org.springframework.integration.util.DynamicPeriodicTrigger trigger;

  private volatile java.time.Duration idlePollPeriod;

  private volatile java.time.Duration activePollPeriod;

  public org.springframework.integration.aop.SimpleActiveIdleMessageSourceAdvice(org.springframework.integration.util.DynamicPeriodicTrigger);
    Code:
       0: aload_0
       1: invokespecial #1                  // Method org/springframework/integration/aop/AbstractMessageSourceAdvice."<init>":()V
       4: aload_0
       5: aload_1
       6: putfield      #2                  // Field trigger:Lorg/springframework/integration/util/DynamicPeriodicTrigger;
       9: aload_0
      10: aload_1
      11: invokevirtual #3                  // Method org/springframework/integration/util/DynamicPeriodicTrigger.getDuration:()Ljava/time/Duration;
      14: putfield      #4                  // Field idlePollPeriod:Ljava/time/Duration;
      17: aload_0
      18: aload_1
      19: invokevirtual #3                  // Method org/springframework/integration/util/DynamicPeriodicTrigger.getDuration:()Ljava/time/Duration;
      22: putfield      #5                  // Field activePollPeriod:Ljava/time/Duration;
      25: return

  public void setIdlePollPeriod(long);
    Code:
       0: aload_0
       1: lload_1
       2: invokestatic  #6                  // Method java/time/Duration.ofMillis:(J)Ljava/time/Duration;
       5: putfield      #4                  // Field idlePollPeriod:Ljava/time/Duration;
       8: return

  public void setActivePollPeriod(long);
    Code:
       0: aload_0
       1: lload_1
       2: invokestatic  #6                  // Method java/time/Duration.ofMillis:(J)Ljava/time/Duration;
       5: putfield      #5                  // Field activePollPeriod:Ljava/time/Duration;
       8: return

  public org.springframework.messaging.Message<?> afterReceive(org.springframework.messaging.Message<?>, org.springframework.integration.core.MessageSource<?>);
    Code:
       0: aload_1
       1: ifnonnull     18
       4: aload_0
       5: getfield      #2                  // Field trigger:Lorg/springframework/integration/util/DynamicPeriodicTrigger;
       8: aload_0
       9: getfield      #4                  // Field idlePollPeriod:Ljava/time/Duration;
      12: invokevirtual #7                  // Method org/springframework/integration/util/DynamicPeriodicTrigger.setDuration:(Ljava/time/Duration;)V
      15: goto          29
      18: aload_0
      19: getfield      #2                  // Field trigger:Lorg/springframework/integration/util/DynamicPeriodicTrigger;
      22: aload_0
      23: getfield      #5                  // Field activePollPeriod:Ljava/time/Duration;
      26: invokevirtual #7                  // Method org/springframework/integration/util/DynamicPeriodicTrigger.setDuration:(Ljava/time/Duration;)V
      29: aload_1
      30: areturn
}
