Compiled from "AbstractDelegatingAdvancedCache.java"
public class org.infinispan.AbstractDelegatingAdvancedCache<K, V> extends org.infinispan.cache.impl.AbstractDelegatingAdvancedCache<K, V> {
  public org.infinispan.AbstractDelegatingAdvancedCache(org.infinispan.AdvancedCache<K, V>);
    Code:
       0: aload_0
       1: aload_1
       2: invokespecial #1                  // Method org/infinispan/cache/impl/AbstractDelegatingAdvancedCache."<init>":(Lorg/infinispan/AdvancedCache;)V
       5: return

  public org.infinispan.AbstractDelegatingAdvancedCache(org.infinispan.AdvancedCache<K, V>, org.infinispan.cache.impl.AbstractDelegatingAdvancedCache$AdvancedCacheWrapper<K, V>);
    Code:
       0: aload_0
       1: aload_1
       2: aload_2
       3: invokespecial #2                  // Method org/infinispan/cache/impl/AbstractDelegatingAdvancedCache."<init>":(Lorg/infinispan/AdvancedCache;Lorg/infinispan/cache/impl/AbstractDelegatingAdvancedCache$AdvancedCacheWrapper;)V
       6: return
}
