Compiled from "NonceUtil.java"
final class org.cryptacular.util.NonceUtil$1 implements org.bouncycastle.crypto.prng.EntropySource {
  final int val$length;

  org.cryptacular.util.NonceUtil$1(int);
    Code:
       0: aload_0
       1: iload_1
       2: putfield      #1                  // Field val$length:I
       5: aload_0
       6: invokespecial #2                  // Method java/lang/Object."<init>":()V
       9: return

  public boolean isPredictionResistant();
    Code:
       0: iconst_0
       1: ireturn

  public byte[] getEntropy();
    Code:
       0: aload_0
       1: getfield      #1                  // Field val$length:I
       4: invokestatic  #3                  // Method org/cryptacular/util/NonceUtil.timestampNonce:(I)[B
       7: areturn

  public int entropySize();
    Code:
       0: aload_0
       1: getfield      #1                  // Field val$length:I
       4: ireturn
}
