Compiled from "CallbackCache.java"
public class org.apache.activemq.artemis.jlibaio.util.CallbackCache<Callback extends org.apache.activemq.artemis.jlibaio.SubmitInfo> {
  private final org.apache.activemq.artemis.jlibaio.SubmitInfo[] pool;

  private int put;

  private int get;

  private int available;

  private final int size;

  private final java.lang.Object lock;

  public org.apache.activemq.artemis.jlibaio.util.CallbackCache(int);
    Code:
       0: aload_0
       1: invokespecial #1                  // Method java/lang/Object."<init>":()V
       4: aload_0
       5: iconst_0
       6: putfield      #2                  // Field put:I
       9: aload_0
      10: iconst_0
      11: putfield      #3                  // Field get:I
      14: aload_0
      15: iconst_0
      16: putfield      #4                  // Field available:I
      19: aload_0
      20: new           #5                  // class java/lang/Object
      23: dup
      24: invokespecial #1                  // Method java/lang/Object."<init>":()V
      27: putfield      #6                  // Field lock:Ljava/lang/Object;
      30: aload_0
      31: iload_1
      32: anewarray     #7                  // class org/apache/activemq/artemis/jlibaio/SubmitInfo
      35: putfield      #8                  // Field pool:[Lorg/apache/activemq/artemis/jlibaio/SubmitInfo;
      38: aload_0
      39: iload_1
      40: putfield      #9                  // Field size:I
      43: return

  public Callback get();
    Code:
       0: aload_0
       1: getfield      #6                  // Field lock:Ljava/lang/Object;
       4: dup
       5: astore_1
       6: monitorenter
       7: aload_0
       8: getfield      #4                  // Field available:I
      11: ifgt          18
      14: aconst_null
      15: aload_1
      16: monitorexit
      17: areturn
      18: aload_0
      19: getfield      #8                  // Field pool:[Lorg/apache/activemq/artemis/jlibaio/SubmitInfo;
      22: aload_0
      23: getfield      #3                  // Field get:I
      26: aaload
      27: astore_2
      28: aload_0
      29: getfield      #8                  // Field pool:[Lorg/apache/activemq/artemis/jlibaio/SubmitInfo;
      32: aload_0
      33: getfield      #3                  // Field get:I
      36: aconst_null
      37: aastore
      38: aload_2
      39: ifnonnull     52
      42: new           #10                 // class java/lang/NullPointerException
      45: dup
      46: ldc           #11                 // String You should initialize the pool before using it
      48: invokespecial #12                 // Method java/lang/NullPointerException."<init>":(Ljava/lang/String;)V
      51: athrow
      52: aload_2
      53: ifnull        92
      56: aload_0
      57: dup
      58: getfield      #4                  // Field available:I
      61: iconst_1
      62: isub
      63: putfield      #4                  // Field available:I
      66: aload_0
      67: dup
      68: getfield      #3                  // Field get:I
      71: iconst_1
      72: iadd
      73: putfield      #3                  // Field get:I
      76: aload_0
      77: getfield      #3                  // Field get:I
      80: aload_0
      81: getfield      #9                  // Field size:I
      84: if_icmplt     92
      87: aload_0
      88: iconst_0
      89: putfield      #3                  // Field get:I
      92: aload_2
      93: aload_1
      94: monitorexit
      95: areturn
      96: astore_3
      97: aload_1
      98: monitorexit
      99: aload_3
     100: athrow
    Exception table:
       from    to  target type
           7    17    96   any
          18    95    96   any
          96    99    96   any

  public org.apache.activemq.artemis.jlibaio.util.CallbackCache put(Callback);
    Code:
       0: aload_1
       1: ifnonnull     6
       4: aconst_null
       5: areturn
       6: aload_0
       7: getfield      #6                  // Field lock:Ljava/lang/Object;
      10: dup
      11: astore_2
      12: monitorenter
      13: aload_0
      14: getfield      #4                  // Field available:I
      17: aload_0
      18: getfield      #9                  // Field size:I
      21: if_icmpge     67
      24: aload_0
      25: dup
      26: getfield      #4                  // Field available:I
      29: iconst_1
      30: iadd
      31: putfield      #4                  // Field available:I
      34: aload_0
      35: getfield      #8                  // Field pool:[Lorg/apache/activemq/artemis/jlibaio/SubmitInfo;
      38: aload_0
      39: dup
      40: getfield      #2                  // Field put:I
      43: dup_x1
      44: iconst_1
      45: iadd
      46: putfield      #2                  // Field put:I
      49: aload_1
      50: aastore
      51: aload_0
      52: getfield      #2                  // Field put:I
      55: aload_0
      56: getfield      #9                  // Field size:I
      59: if_icmplt     67
      62: aload_0
      63: iconst_0
      64: putfield      #2                  // Field put:I
      67: aload_2
      68: monitorexit
      69: goto          77
      72: astore_3
      73: aload_2
      74: monitorexit
      75: aload_3
      76: athrow
      77: aload_0
      78: areturn
    Exception table:
       from    to  target type
          13    69    72   any
          72    75    72   any
}
