Compiled from "ValidationException.java"
public class org.owasp.esapi.errors.ValidationException extends org.owasp.esapi.errors.EnterpriseSecurityException {
  protected static final long serialVersionUID;

  private java.lang.String context;

  protected org.owasp.esapi.errors.ValidationException();
    Code:
       0: aload_0
       1: invokespecial #1                  // Method org/owasp/esapi/errors/EnterpriseSecurityException."<init>":()V
       4: return

  public org.owasp.esapi.errors.ValidationException(java.lang.String, java.lang.String);
    Code:
       0: aload_0
       1: aload_1
       2: aload_2
       3: invokespecial #2                  // Method org/owasp/esapi/errors/EnterpriseSecurityException."<init>":(Ljava/lang/String;Ljava/lang/String;)V
       6: return

  public org.owasp.esapi.errors.ValidationException(java.lang.String, java.lang.String, java.lang.Throwable);
    Code:
       0: aload_0
       1: aload_1
       2: aload_2
       3: aload_3
       4: invokespecial #3                  // Method org/owasp/esapi/errors/EnterpriseSecurityException."<init>":(Ljava/lang/String;Ljava/lang/String;Ljava/lang/Throwable;)V
       7: return

  public org.owasp.esapi.errors.ValidationException(java.lang.String, java.lang.String, java.lang.String);
    Code:
       0: aload_0
       1: aload_1
       2: aload_2
       3: invokespecial #2                  // Method org/owasp/esapi/errors/EnterpriseSecurityException."<init>":(Ljava/lang/String;Ljava/lang/String;)V
       6: aload_0
       7: aload_3
       8: invokevirtual #4                  // Method setContext:(Ljava/lang/String;)V
      11: return

  public org.owasp.esapi.errors.ValidationException(java.lang.String, java.lang.String, java.lang.Throwable, java.lang.String);
    Code:
       0: aload_0
       1: aload_1
       2: aload_2
       3: aload_3
       4: invokespecial #3                  // Method org/owasp/esapi/errors/EnterpriseSecurityException."<init>":(Ljava/lang/String;Ljava/lang/String;Ljava/lang/Throwable;)V
       7: aload_0
       8: aload         4
      10: invokevirtual #4                  // Method setContext:(Ljava/lang/String;)V
      13: return

  public java.lang.String getContext();
    Code:
       0: aload_0
       1: getfield      #5                  // Field context:Ljava/lang/String;
       4: areturn

  public void setContext(java.lang.String);
    Code:
       0: aload_0
       1: aload_1
       2: putfield      #5                  // Field context:Ljava/lang/String;
       5: return
}
