Compiled from "S2iBuildConfigBuilder.java"
public class io.dekorate.s2i.config.S2iBuildConfigBuilder extends io.dekorate.s2i.config.S2iBuildConfigFluentImpl<io.dekorate.s2i.config.S2iBuildConfigBuilder> implements io.dekorate.deps.kubernetes.api.builder.VisitableBuilder<io.dekorate.s2i.config.S2iBuildConfig, io.dekorate.s2i.config.S2iBuildConfigBuilder> {
  io.dekorate.s2i.config.S2iBuildConfigFluent<?> fluent;

  java.lang.Boolean validationEnabled;

  public io.dekorate.s2i.config.S2iBuildConfigBuilder();
    Code:
       0: aload_0
       1: iconst_1
       2: invokestatic  #1                  // Method java/lang/Boolean.valueOf:(Z)Ljava/lang/Boolean;
       5: invokespecial #2                  // Method "<init>":(Ljava/lang/Boolean;)V
       8: return

  public io.dekorate.s2i.config.S2iBuildConfigBuilder(java.lang.Boolean);
    Code:
       0: aload_0
       1: new           #3                  // class io/dekorate/s2i/config/S2iBuildConfig
       4: dup
       5: invokespecial #4                  // Method io/dekorate/s2i/config/S2iBuildConfig."<init>":()V
       8: aload_1
       9: invokespecial #5                  // Method "<init>":(Lio/dekorate/s2i/config/S2iBuildConfig;Ljava/lang/Boolean;)V
      12: return

  public io.dekorate.s2i.config.S2iBuildConfigBuilder(io.dekorate.s2i.config.S2iBuildConfigFluent<?>);
    Code:
       0: aload_0
       1: aload_1
       2: iconst_1
       3: invokestatic  #1                  // Method java/lang/Boolean.valueOf:(Z)Ljava/lang/Boolean;
       6: invokespecial #6                  // Method "<init>":(Lio/dekorate/s2i/config/S2iBuildConfigFluent;Ljava/lang/Boolean;)V
       9: return

  public io.dekorate.s2i.config.S2iBuildConfigBuilder(io.dekorate.s2i.config.S2iBuildConfigFluent<?>, java.lang.Boolean);
    Code:
       0: aload_0
       1: aload_1
       2: new           #3                  // class io/dekorate/s2i/config/S2iBuildConfig
       5: dup
       6: invokespecial #4                  // Method io/dekorate/s2i/config/S2iBuildConfig."<init>":()V
       9: aload_2
      10: invokespecial #7                  // Method "<init>":(Lio/dekorate/s2i/config/S2iBuildConfigFluent;Lio/dekorate/s2i/config/S2iBuildConfig;Ljava/lang/Boolean;)V
      13: return

  public io.dekorate.s2i.config.S2iBuildConfigBuilder(io.dekorate.s2i.config.S2iBuildConfigFluent<?>, io.dekorate.s2i.config.S2iBuildConfig);
    Code:
       0: aload_0
       1: aload_1
       2: aload_2
       3: iconst_1
       4: invokestatic  #1                  // Method java/lang/Boolean.valueOf:(Z)Ljava/lang/Boolean;
       7: invokespecial #7                  // Method "<init>":(Lio/dekorate/s2i/config/S2iBuildConfigFluent;Lio/dekorate/s2i/config/S2iBuildConfig;Ljava/lang/Boolean;)V
      10: return

  public io.dekorate.s2i.config.S2iBuildConfigBuilder(io.dekorate.s2i.config.S2iBuildConfigFluent<?>, io.dekorate.s2i.config.S2iBuildConfig, java.lang.Boolean);
    Code:
       0: aload_0
       1: invokespecial #8                  // Method io/dekorate/s2i/config/S2iBuildConfigFluentImpl."<init>":()V
       4: aload_0
       5: aload_1
       6: putfield      #9                  // Field fluent:Lio/dekorate/s2i/config/S2iBuildConfigFluent;
       9: aload_1
      10: aload_2
      11: invokevirtual #10                 // Method io/dekorate/s2i/config/S2iBuildConfig.getProject:()Lio/dekorate/project/Project;
      14: invokeinterface #11,  2           // InterfaceMethod io/dekorate/s2i/config/S2iBuildConfigFluent.withProject:(Lio/dekorate/project/Project;)Lio/dekorate/kubernetes/config/ConfigurationFluent;
      19: pop
      20: aload_1
      21: aload_2
      22: invokevirtual #12                 // Method io/dekorate/s2i/config/S2iBuildConfig.getAttributes:()Ljava/util/Map;
      25: invokeinterface #13,  2           // InterfaceMethod io/dekorate/s2i/config/S2iBuildConfigFluent.withAttributes:(Ljava/util/Map;)Lio/dekorate/kubernetes/config/ConfigurationFluent;
      30: pop
      31: aload_1
      32: aload_2
      33: invokevirtual #14                 // Method io/dekorate/s2i/config/S2iBuildConfig.getRegistry:()Ljava/lang/String;
      36: invokeinterface #15,  2           // InterfaceMethod io/dekorate/s2i/config/S2iBuildConfigFluent.withRegistry:(Ljava/lang/String;)Lio/dekorate/kubernetes/config/ImageConfigurationFluent;
      41: pop
      42: aload_1
      43: aload_2
      44: invokevirtual #16                 // Method io/dekorate/s2i/config/S2iBuildConfig.getGroup:()Ljava/lang/String;
      47: invokeinterface #17,  2           // InterfaceMethod io/dekorate/s2i/config/S2iBuildConfigFluent.withGroup:(Ljava/lang/String;)Lio/dekorate/kubernetes/config/ImageConfigurationFluent;
      52: pop
      53: aload_1
      54: aload_2
      55: invokevirtual #18                 // Method io/dekorate/s2i/config/S2iBuildConfig.getName:()Ljava/lang/String;
      58: invokeinterface #19,  2           // InterfaceMethod io/dekorate/s2i/config/S2iBuildConfigFluent.withName:(Ljava/lang/String;)Lio/dekorate/kubernetes/config/ImageConfigurationFluent;
      63: pop
      64: aload_1
      65: aload_2
      66: invokevirtual #20                 // Method io/dekorate/s2i/config/S2iBuildConfig.getVersion:()Ljava/lang/String;
      69: invokeinterface #21,  2           // InterfaceMethod io/dekorate/s2i/config/S2iBuildConfigFluent.withVersion:(Ljava/lang/String;)Lio/dekorate/kubernetes/config/ImageConfigurationFluent;
      74: pop
      75: aload_1
      76: aload_2
      77: invokevirtual #22                 // Method io/dekorate/s2i/config/S2iBuildConfig.getImage:()Ljava/lang/String;
      80: invokeinterface #23,  2           // InterfaceMethod io/dekorate/s2i/config/S2iBuildConfigFluent.withImage:(Ljava/lang/String;)Lio/dekorate/kubernetes/config/ImageConfigurationFluent;
      85: pop
      86: aload_1
      87: aload_2
      88: invokevirtual #24                 // Method io/dekorate/s2i/config/S2iBuildConfig.getDockerFile:()Ljava/lang/String;
      91: invokeinterface #25,  2           // InterfaceMethod io/dekorate/s2i/config/S2iBuildConfigFluent.withDockerFile:(Ljava/lang/String;)Lio/dekorate/kubernetes/config/ImageConfigurationFluent;
      96: pop
      97: aload_1
      98: aload_2
      99: invokevirtual #26                 // Method io/dekorate/s2i/config/S2iBuildConfig.isAutoBuildEnabled:()Z
     102: invokeinterface #27,  2           // InterfaceMethod io/dekorate/s2i/config/S2iBuildConfigFluent.withAutoBuildEnabled:(Z)Lio/dekorate/kubernetes/config/ImageConfigurationFluent;
     107: pop
     108: aload_1
     109: aload_2
     110: invokevirtual #28                 // Method io/dekorate/s2i/config/S2iBuildConfig.isAutoPushEnabled:()Z
     113: invokeinterface #29,  2           // InterfaceMethod io/dekorate/s2i/config/S2iBuildConfigFluent.withAutoPushEnabled:(Z)Lio/dekorate/kubernetes/config/ImageConfigurationFluent;
     118: pop
     119: aload_1
     120: aload_2
     121: invokevirtual #30                 // Method io/dekorate/s2i/config/S2iBuildConfig.isEnabled:()Z
     124: invokeinterface #31,  2           // InterfaceMethod io/dekorate/s2i/config/S2iBuildConfigFluent.withEnabled:(Z)Lio/dekorate/s2i/config/S2iBuildConfigFluent;
     129: pop
     130: aload_1
     131: aload_2
     132: invokevirtual #32                 // Method io/dekorate/s2i/config/S2iBuildConfig.getBuilderImage:()Ljava/lang/String;
     135: invokeinterface #33,  2           // InterfaceMethod io/dekorate/s2i/config/S2iBuildConfigFluent.withBuilderImage:(Ljava/lang/String;)Lio/dekorate/s2i/config/S2iBuildConfigFluent;
     140: pop
     141: aload_1
     142: aload_2
     143: invokevirtual #34                 // Method io/dekorate/s2i/config/S2iBuildConfig.getBuildEnvVars:()[Lio/dekorate/kubernetes/config/Env;
     146: invokeinterface #35,  2           // InterfaceMethod io/dekorate/s2i/config/S2iBuildConfigFluent.withBuildEnvVars:([Lio/dekorate/kubernetes/config/Env;)Lio/dekorate/s2i/config/S2iBuildConfigFluent;
     151: pop
     152: aload_1
     153: aload_2
     154: invokevirtual #36                 // Method io/dekorate/s2i/config/S2iBuildConfig.isAutoDeployEnabled:()Z
     157: invokeinterface #37,  2           // InterfaceMethod io/dekorate/s2i/config/S2iBuildConfigFluent.withAutoDeployEnabled:(Z)Lio/dekorate/s2i/config/S2iBuildConfigFluent;
     162: pop
     163: aload_0
     164: aload_3
     165: putfield      #38                 // Field validationEnabled:Ljava/lang/Boolean;
     168: return

  public io.dekorate.s2i.config.S2iBuildConfigBuilder(io.dekorate.s2i.config.S2iBuildConfig);
    Code:
       0: aload_0
       1: aload_1
       2: iconst_1
       3: invokestatic  #1                  // Method java/lang/Boolean.valueOf:(Z)Ljava/lang/Boolean;
       6: invokespecial #5                  // Method "<init>":(Lio/dekorate/s2i/config/S2iBuildConfig;Ljava/lang/Boolean;)V
       9: return

  public io.dekorate.s2i.config.S2iBuildConfigBuilder(io.dekorate.s2i.config.S2iBuildConfig, java.lang.Boolean);
    Code:
       0: aload_0
       1: invokespecial #8                  // Method io/dekorate/s2i/config/S2iBuildConfigFluentImpl."<init>":()V
       4: aload_0
       5: aload_0
       6: putfield      #9                  // Field fluent:Lio/dekorate/s2i/config/S2iBuildConfigFluent;
       9: aload_0
      10: aload_1
      11: invokevirtual #10                 // Method io/dekorate/s2i/config/S2iBuildConfig.getProject:()Lio/dekorate/project/Project;
      14: invokevirtual #39                 // Method withProject:(Lio/dekorate/project/Project;)Lio/dekorate/kubernetes/config/ConfigurationFluent;
      17: pop
      18: aload_0
      19: aload_1
      20: invokevirtual #12                 // Method io/dekorate/s2i/config/S2iBuildConfig.getAttributes:()Ljava/util/Map;
      23: invokevirtual #40                 // Method withAttributes:(Ljava/util/Map;)Lio/dekorate/kubernetes/config/ConfigurationFluent;
      26: pop
      27: aload_0
      28: aload_1
      29: invokevirtual #14                 // Method io/dekorate/s2i/config/S2iBuildConfig.getRegistry:()Ljava/lang/String;
      32: invokevirtual #41                 // Method withRegistry:(Ljava/lang/String;)Lio/dekorate/kubernetes/config/ImageConfigurationFluent;
      35: pop
      36: aload_0
      37: aload_1
      38: invokevirtual #16                 // Method io/dekorate/s2i/config/S2iBuildConfig.getGroup:()Ljava/lang/String;
      41: invokevirtual #42                 // Method withGroup:(Ljava/lang/String;)Lio/dekorate/kubernetes/config/ImageConfigurationFluent;
      44: pop
      45: aload_0
      46: aload_1
      47: invokevirtual #18                 // Method io/dekorate/s2i/config/S2iBuildConfig.getName:()Ljava/lang/String;
      50: invokevirtual #43                 // Method withName:(Ljava/lang/String;)Lio/dekorate/kubernetes/config/ImageConfigurationFluent;
      53: pop
      54: aload_0
      55: aload_1
      56: invokevirtual #20                 // Method io/dekorate/s2i/config/S2iBuildConfig.getVersion:()Ljava/lang/String;
      59: invokevirtual #44                 // Method withVersion:(Ljava/lang/String;)Lio/dekorate/kubernetes/config/ImageConfigurationFluent;
      62: pop
      63: aload_0
      64: aload_1
      65: invokevirtual #22                 // Method io/dekorate/s2i/config/S2iBuildConfig.getImage:()Ljava/lang/String;
      68: invokevirtual #45                 // Method withImage:(Ljava/lang/String;)Lio/dekorate/kubernetes/config/ImageConfigurationFluent;
      71: pop
      72: aload_0
      73: aload_1
      74: invokevirtual #24                 // Method io/dekorate/s2i/config/S2iBuildConfig.getDockerFile:()Ljava/lang/String;
      77: invokevirtual #46                 // Method withDockerFile:(Ljava/lang/String;)Lio/dekorate/kubernetes/config/ImageConfigurationFluent;
      80: pop
      81: aload_0
      82: aload_1
      83: invokevirtual #26                 // Method io/dekorate/s2i/config/S2iBuildConfig.isAutoBuildEnabled:()Z
      86: invokevirtual #47                 // Method withAutoBuildEnabled:(Z)Lio/dekorate/kubernetes/config/ImageConfigurationFluent;
      89: pop
      90: aload_0
      91: aload_1
      92: invokevirtual #28                 // Method io/dekorate/s2i/config/S2iBuildConfig.isAutoPushEnabled:()Z
      95: invokevirtual #48                 // Method withAutoPushEnabled:(Z)Lio/dekorate/kubernetes/config/ImageConfigurationFluent;
      98: pop
      99: aload_0
     100: aload_1
     101: invokevirtual #30                 // Method io/dekorate/s2i/config/S2iBuildConfig.isEnabled:()Z
     104: invokevirtual #49                 // Method withEnabled:(Z)Lio/dekorate/s2i/config/S2iBuildConfigFluent;
     107: pop
     108: aload_0
     109: aload_1
     110: invokevirtual #32                 // Method io/dekorate/s2i/config/S2iBuildConfig.getBuilderImage:()Ljava/lang/String;
     113: invokevirtual #50                 // Method withBuilderImage:(Ljava/lang/String;)Lio/dekorate/s2i/config/S2iBuildConfigFluent;
     116: pop
     117: aload_0
     118: aload_1
     119: invokevirtual #34                 // Method io/dekorate/s2i/config/S2iBuildConfig.getBuildEnvVars:()[Lio/dekorate/kubernetes/config/Env;
     122: invokevirtual #51                 // Method withBuildEnvVars:([Lio/dekorate/kubernetes/config/Env;)Lio/dekorate/s2i/config/S2iBuildConfigFluent;
     125: pop
     126: aload_0
     127: aload_1
     128: invokevirtual #36                 // Method io/dekorate/s2i/config/S2iBuildConfig.isAutoDeployEnabled:()Z
     131: invokevirtual #52                 // Method withAutoDeployEnabled:(Z)Lio/dekorate/s2i/config/S2iBuildConfigFluent;
     134: pop
     135: aload_0
     136: aload_2
     137: putfield      #38                 // Field validationEnabled:Ljava/lang/Boolean;
     140: return

  public io.dekorate.s2i.config.EditableS2iBuildConfig build();
    Code:
       0: new           #53                 // class io/dekorate/s2i/config/EditableS2iBuildConfig
       3: dup
       4: aload_0
       5: getfield      #9                  // Field fluent:Lio/dekorate/s2i/config/S2iBuildConfigFluent;
       8: invokeinterface #54,  1           // InterfaceMethod io/dekorate/s2i/config/S2iBuildConfigFluent.getProject:()Lio/dekorate/project/Project;
      13: aload_0
      14: getfield      #9                  // Field fluent:Lio/dekorate/s2i/config/S2iBuildConfigFluent;
      17: invokeinterface #55,  1           // InterfaceMethod io/dekorate/s2i/config/S2iBuildConfigFluent.getAttributes:()Ljava/util/Map;
      22: aload_0
      23: getfield      #9                  // Field fluent:Lio/dekorate/s2i/config/S2iBuildConfigFluent;
      26: invokeinterface #56,  1           // InterfaceMethod io/dekorate/s2i/config/S2iBuildConfigFluent.getRegistry:()Ljava/lang/String;
      31: aload_0
      32: getfield      #9                  // Field fluent:Lio/dekorate/s2i/config/S2iBuildConfigFluent;
      35: invokeinterface #57,  1           // InterfaceMethod io/dekorate/s2i/config/S2iBuildConfigFluent.getGroup:()Ljava/lang/String;
      40: aload_0
      41: getfield      #9                  // Field fluent:Lio/dekorate/s2i/config/S2iBuildConfigFluent;
      44: invokeinterface #58,  1           // InterfaceMethod io/dekorate/s2i/config/S2iBuildConfigFluent.getName:()Ljava/lang/String;
      49: aload_0
      50: getfield      #9                  // Field fluent:Lio/dekorate/s2i/config/S2iBuildConfigFluent;
      53: invokeinterface #59,  1           // InterfaceMethod io/dekorate/s2i/config/S2iBuildConfigFluent.getVersion:()Ljava/lang/String;
      58: aload_0
      59: getfield      #9                  // Field fluent:Lio/dekorate/s2i/config/S2iBuildConfigFluent;
      62: invokeinterface #60,  1           // InterfaceMethod io/dekorate/s2i/config/S2iBuildConfigFluent.getImage:()Ljava/lang/String;
      67: aload_0
      68: getfield      #9                  // Field fluent:Lio/dekorate/s2i/config/S2iBuildConfigFluent;
      71: invokeinterface #61,  1           // InterfaceMethod io/dekorate/s2i/config/S2iBuildConfigFluent.getDockerFile:()Ljava/lang/String;
      76: aload_0
      77: getfield      #9                  // Field fluent:Lio/dekorate/s2i/config/S2iBuildConfigFluent;
      80: invokeinterface #62,  1           // InterfaceMethod io/dekorate/s2i/config/S2iBuildConfigFluent.isAutoBuildEnabled:()Z
      85: aload_0
      86: getfield      #9                  // Field fluent:Lio/dekorate/s2i/config/S2iBuildConfigFluent;
      89: invokeinterface #63,  1           // InterfaceMethod io/dekorate/s2i/config/S2iBuildConfigFluent.isAutoPushEnabled:()Z
      94: aload_0
      95: getfield      #9                  // Field fluent:Lio/dekorate/s2i/config/S2iBuildConfigFluent;
      98: invokeinterface #64,  1           // InterfaceMethod io/dekorate/s2i/config/S2iBuildConfigFluent.isEnabled:()Z
     103: aload_0
     104: getfield      #9                  // Field fluent:Lio/dekorate/s2i/config/S2iBuildConfigFluent;
     107: invokeinterface #65,  1           // InterfaceMethod io/dekorate/s2i/config/S2iBuildConfigFluent.getBuilderImage:()Ljava/lang/String;
     112: aload_0
     113: getfield      #9                  // Field fluent:Lio/dekorate/s2i/config/S2iBuildConfigFluent;
     116: invokeinterface #66,  1           // InterfaceMethod io/dekorate/s2i/config/S2iBuildConfigFluent.getBuildEnvVars:()[Lio/dekorate/kubernetes/config/Env;
     121: aload_0
     122: getfield      #9                  // Field fluent:Lio/dekorate/s2i/config/S2iBuildConfigFluent;
     125: invokeinterface #67,  1           // InterfaceMethod io/dekorate/s2i/config/S2iBuildConfigFluent.isAutoDeployEnabled:()Z
     130: invokespecial #68                 // Method io/dekorate/s2i/config/EditableS2iBuildConfig."<init>":(Lio/dekorate/project/Project;Ljava/util/Map;Ljava/lang/String;Ljava/lang/String;Ljava/lang/String;Ljava/lang/String;Ljava/lang/String;Ljava/lang/String;ZZZLjava/lang/String;[Lio/dekorate/kubernetes/config/Env;Z)V
     133: astore_1
     134: aload_1
     135: areturn

  public boolean equals(java.lang.Object);
    Code:
       0: aload_0
       1: aload_1
       2: if_acmpne     7
       5: iconst_1
       6: ireturn
       7: aload_1
       8: ifnull        22
      11: aload_0
      12: invokevirtual #69                 // Method java/lang/Object.getClass:()Ljava/lang/Class;
      15: aload_1
      16: invokevirtual #69                 // Method java/lang/Object.getClass:()Ljava/lang/Class;
      19: if_acmpeq     24
      22: iconst_0
      23: ireturn
      24: aload_0
      25: aload_1
      26: invokespecial #70                 // Method io/dekorate/s2i/config/S2iBuildConfigFluentImpl.equals:(Ljava/lang/Object;)Z
      29: ifne          34
      32: iconst_0
      33: ireturn
      34: aload_1
      35: checkcast     #71                 // class io/dekorate/s2i/config/S2iBuildConfigBuilder
      38: astore_2
      39: aload_0
      40: getfield      #9                  // Field fluent:Lio/dekorate/s2i/config/S2iBuildConfigFluent;
      43: ifnull        71
      46: aload_0
      47: getfield      #9                  // Field fluent:Lio/dekorate/s2i/config/S2iBuildConfigFluent;
      50: aload_0
      51: if_acmpeq     71
      54: aload_0
      55: getfield      #9                  // Field fluent:Lio/dekorate/s2i/config/S2iBuildConfigFluent;
      58: aload_2
      59: getfield      #9                  // Field fluent:Lio/dekorate/s2i/config/S2iBuildConfigFluent;
      62: invokevirtual #72                 // Method java/lang/Object.equals:(Ljava/lang/Object;)Z
      65: ifne          88
      68: goto          86
      71: aload_2
      72: getfield      #9                  // Field fluent:Lio/dekorate/s2i/config/S2iBuildConfigFluent;
      75: ifnull        88
      78: aload_0
      79: getfield      #9                  // Field fluent:Lio/dekorate/s2i/config/S2iBuildConfigFluent;
      82: aload_0
      83: if_acmpeq     88
      86: iconst_0
      87: ireturn
      88: aload_0
      89: getfield      #38                 // Field validationEnabled:Ljava/lang/Boolean;
      92: ifnull        112
      95: aload_0
      96: getfield      #38                 // Field validationEnabled:Ljava/lang/Boolean;
      99: aload_2
     100: getfield      #38                 // Field validationEnabled:Ljava/lang/Boolean;
     103: invokevirtual #73                 // Method java/lang/Boolean.equals:(Ljava/lang/Object;)Z
     106: ifne          121
     109: goto          119
     112: aload_2
     113: getfield      #38                 // Field validationEnabled:Ljava/lang/Boolean;
     116: ifnull        121
     119: iconst_0
     120: ireturn
     121: iconst_1
     122: ireturn

  public java.lang.Object build();
    Code:
       0: aload_0
       1: invokevirtual #74                 // Method build:()Lio/dekorate/s2i/config/EditableS2iBuildConfig;
       4: areturn
}
