Compiled from "ImplicitGrant.java"
public class springfox.documentation.service.ImplicitGrant extends springfox.documentation.service.GrantType {
  private final springfox.documentation.service.LoginEndpoint loginEndpoint;

  private final java.lang.String tokenName;

  public springfox.documentation.service.ImplicitGrant(springfox.documentation.service.LoginEndpoint, java.lang.String);
    Code:
       0: aload_0
       1: ldc           #1                  // String implicit
       3: invokespecial #2                  // Method springfox/documentation/service/GrantType."<init>":(Ljava/lang/String;)V
       6: aload_0
       7: aload_1
       8: putfield      #3                  // Field loginEndpoint:Lspringfox/documentation/service/LoginEndpoint;
      11: aload_0
      12: aload_2
      13: putfield      #4                  // Field tokenName:Ljava/lang/String;
      16: return

  public springfox.documentation.service.LoginEndpoint getLoginEndpoint();
    Code:
       0: aload_0
       1: getfield      #3                  // Field loginEndpoint:Lspringfox/documentation/service/LoginEndpoint;
       4: areturn

  public java.lang.String getTokenName();
    Code:
       0: aload_0
       1: getfield      #4                  // Field tokenName:Ljava/lang/String;
       4: areturn
}
