Compiled from "ResourceListing.java"
public class springfox.documentation.service.ResourceListing {
  private final java.lang.String apiVersion;

  private final java.util.List<springfox.documentation.service.ApiListingReference> apis;

  private final java.util.List<springfox.documentation.service.SecurityScheme> securitySchemes;

  private final springfox.documentation.service.ApiInfo info;

  public springfox.documentation.service.ResourceListing(java.lang.String, java.util.List<springfox.documentation.service.ApiListingReference>, java.util.List<springfox.documentation.service.SecurityScheme>, springfox.documentation.service.ApiInfo);
    Code:
       0: aload_0
       1: invokespecial #1                  // Method java/lang/Object."<init>":()V
       4: aload_0
       5: aload_1
       6: putfield      #2                  // Field apiVersion:Ljava/lang/String;
       9: aload_0
      10: aload_2
      11: putfield      #3                  // Field apis:Ljava/util/List;
      14: aload_0
      15: aload_3
      16: putfield      #4                  // Field securitySchemes:Ljava/util/List;
      19: aload_0
      20: aload         4
      22: putfield      #5                  // Field info:Lspringfox/documentation/service/ApiInfo;
      25: return

  public java.lang.String getApiVersion();
    Code:
       0: aload_0
       1: getfield      #2                  // Field apiVersion:Ljava/lang/String;
       4: areturn

  public java.util.List<springfox.documentation.service.ApiListingReference> getApis();
    Code:
       0: aload_0
       1: getfield      #3                  // Field apis:Ljava/util/List;
       4: areturn

  public java.util.List<springfox.documentation.service.SecurityScheme> getSecuritySchemes();
    Code:
       0: aload_0
       1: getfield      #4                  // Field securitySchemes:Ljava/util/List;
       4: areturn

  public springfox.documentation.service.ApiInfo getInfo();
    Code:
       0: aload_0
       1: getfield      #5                  // Field info:Lspringfox/documentation/service/ApiInfo;
       4: areturn
}
