Compiled from "Tags.java"
final class springfox.documentation.service.Tags$7 implements com.google.common.base.Predicate<java.lang.String> {
  springfox.documentation.service.Tags$7();
    Code:
       0: aload_0
       1: invokespecial #1                  // Method java/lang/Object."<init>":()V
       4: return

  public boolean apply(java.lang.String);
    Code:
       0: aload_1
       1: invokestatic  #2                  // Method com/google/common/base/Strings.isNullOrEmpty:(Ljava/lang/String;)Z
       4: ifne          11
       7: iconst_1
       8: goto          12
      11: iconst_0
      12: ireturn

  public boolean apply(java.lang.Object);
    Code:
       0: aload_0
       1: aload_1
       2: checkcast     #3                  // class java/lang/String
       5: invokevirtual #4                  // Method apply:(Ljava/lang/String;)Z
       8: ireturn
}
