Compiled from "ExcelType.java"
public final class ltd.fdsa.component.excel.enums.ExcelType extends java.lang.Enum<ltd.fdsa.component.excel.enums.ExcelType> {
  public static final ltd.fdsa.component.excel.enums.ExcelType ALL;

  public static final ltd.fdsa.component.excel.enums.ExcelType IMPORT;

  public static final ltd.fdsa.component.excel.enums.ExcelType EXPORT;

  private static final ltd.fdsa.component.excel.enums.ExcelType[] $VALUES;

  public static ltd.fdsa.component.excel.enums.ExcelType[] values();
    Code:
       0: getstatic     #1                  // Field $VALUES:[Lltd/fdsa/component/excel/enums/ExcelType;
       3: invokevirtual #2                  // Method "[Lltd/fdsa/component/excel/enums/ExcelType;".clone:()Ljava/lang/Object;
       6: checkcast     #3                  // class "[Lltd/fdsa/component/excel/enums/ExcelType;"
       9: areturn

  public static ltd.fdsa.component.excel.enums.ExcelType valueOf(java.lang.String);
    Code:
       0: ldc           #4                  // class ltd/fdsa/component/excel/enums/ExcelType
       2: aload_0
       3: invokestatic  #5                  // Method java/lang/Enum.valueOf:(Ljava/lang/Class;Ljava/lang/String;)Ljava/lang/Enum;
       6: checkcast     #4                  // class ltd/fdsa/component/excel/enums/ExcelType
       9: areturn

  private ltd.fdsa.component.excel.enums.ExcelType();
    Code:
       0: aload_0
       1: aload_1
       2: iload_2
       3: invokespecial #6                  // Method java/lang/Enum."<init>":(Ljava/lang/String;I)V
       6: return

  static {};
    Code:
       0: new           #4                  // class ltd/fdsa/component/excel/enums/ExcelType
       3: dup
       4: ldc           #7                  // String ALL
       6: iconst_0
       7: invokespecial #8                  // Method "<init>":(Ljava/lang/String;I)V
      10: putstatic     #9                  // Field ALL:Lltd/fdsa/component/excel/enums/ExcelType;
      13: new           #4                  // class ltd/fdsa/component/excel/enums/ExcelType
      16: dup
      17: ldc           #10                 // String IMPORT
      19: iconst_1
      20: invokespecial #8                  // Method "<init>":(Ljava/lang/String;I)V
      23: putstatic     #11                 // Field IMPORT:Lltd/fdsa/component/excel/enums/ExcelType;
      26: new           #4                  // class ltd/fdsa/component/excel/enums/ExcelType
      29: dup
      30: ldc           #12                 // String EXPORT
      32: iconst_2
      33: invokespecial #8                  // Method "<init>":(Ljava/lang/String;I)V
      36: putstatic     #13                 // Field EXPORT:Lltd/fdsa/component/excel/enums/ExcelType;
      39: iconst_3
      40: anewarray     #4                  // class ltd/fdsa/component/excel/enums/ExcelType
      43: dup
      44: iconst_0
      45: getstatic     #9                  // Field ALL:Lltd/fdsa/component/excel/enums/ExcelType;
      48: aastore
      49: dup
      50: iconst_1
      51: getstatic     #11                 // Field IMPORT:Lltd/fdsa/component/excel/enums/ExcelType;
      54: aastore
      55: dup
      56: iconst_2
      57: getstatic     #13                 // Field EXPORT:Lltd/fdsa/component/excel/enums/ExcelType;
      60: aastore
      61: putstatic     #1                  // Field $VALUES:[Lltd/fdsa/component/excel/enums/ExcelType;
      64: return
}
