Compiled from "AbstractPushOMDataSource.java"
public abstract class org.apache.axiom.om.ds.AbstractPushOMDataSource extends org.apache.axiom.om.ds.AbstractOMDataSource {
  public org.apache.axiom.om.ds.AbstractPushOMDataSource();
    Code:
       0: aload_0
       1: invokespecial #1                  // Method org/apache/axiom/om/ds/AbstractOMDataSource."<init>":()V
       4: return

  public final boolean isDestructiveRead();
    Code:
       0: aload_0
       1: invokevirtual #2                  // Method isDestructiveWrite:()Z
       4: ireturn

  public final javax.xml.stream.XMLStreamReader getReader() throws javax.xml.stream.XMLStreamException;
    Code:
       0: new           #3                  // class java/io/ByteArrayOutputStream
       3: dup
       4: invokespecial #4                  // Method java/io/ByteArrayOutputStream."<init>":()V
       7: astore_1
       8: aload_0
       9: aload_1
      10: new           #5                  // class org/apache/axiom/om/OMOutputFormat
      13: dup
      14: invokespecial #6                  // Method org/apache/axiom/om/OMOutputFormat."<init>":()V
      17: invokevirtual #7                  // Method serialize:(Ljava/io/OutputStream;Lorg/apache/axiom/om/OMOutputFormat;)V
      20: new           #8                  // class java/io/ByteArrayInputStream
      23: dup
      24: aload_1
      25: invokevirtual #9                  // Method java/io/ByteArrayOutputStream.toByteArray:()[B
      28: invokespecial #10                 // Method java/io/ByteArrayInputStream."<init>":([B)V
      31: invokestatic  #11                 // Method org/apache/axiom/om/util/StAXUtils.createXMLStreamReader:(Ljava/io/InputStream;)Ljavax/xml/stream/XMLStreamReader;
      34: areturn
}
