Compiled from "Deprecation.java"
public final class io.grpc.xds.shaded.envoy.annotations.Deprecation {
  public static final int DISALLOWED_BY_DEFAULT_FIELD_NUMBER;

  public static final com.google.protobuf.GeneratedMessage$GeneratedExtension<com.google.protobuf.DescriptorProtos$FieldOptions, java.lang.Boolean> disallowedByDefault;

  public static final int DEPRECATED_AT_MINOR_VERSION_FIELD_NUMBER;

  public static final com.google.protobuf.GeneratedMessage$GeneratedExtension<com.google.protobuf.DescriptorProtos$FieldOptions, java.lang.String> deprecatedAtMinorVersion;

  public static final int DISALLOWED_BY_DEFAULT_ENUM_FIELD_NUMBER;

  public static final com.google.protobuf.GeneratedMessage$GeneratedExtension<com.google.protobuf.DescriptorProtos$EnumValueOptions, java.lang.Boolean> disallowedByDefaultEnum;

  public static final int DEPRECATED_AT_MINOR_VERSION_ENUM_FIELD_NUMBER;

  public static final com.google.protobuf.GeneratedMessage$GeneratedExtension<com.google.protobuf.DescriptorProtos$EnumValueOptions, java.lang.String> deprecatedAtMinorVersionEnum;

  private static com.google.protobuf.Descriptors$FileDescriptor descriptor;

  private io.grpc.xds.shaded.envoy.annotations.Deprecation();
    Code:
       0: aload_0
       1: invokespecial #50                 // Method java/lang/Object."<init>":()V
       4: return

  public static void registerAllExtensions(com.google.protobuf.ExtensionRegistryLite);
    Code:
       0: aload_0
       1: getstatic     #56                 // Field disallowedByDefault:Lcom/google/protobuf/GeneratedMessage$GeneratedExtension;
       4: invokevirtual #62                 // Method com/google/protobuf/ExtensionRegistryLite.add:(Lcom/google/protobuf/ExtensionLite;)V
       7: aload_0
       8: getstatic     #64                 // Field deprecatedAtMinorVersion:Lcom/google/protobuf/GeneratedMessage$GeneratedExtension;
      11: invokevirtual #62                 // Method com/google/protobuf/ExtensionRegistryLite.add:(Lcom/google/protobuf/ExtensionLite;)V
      14: aload_0
      15: getstatic     #66                 // Field disallowedByDefaultEnum:Lcom/google/protobuf/GeneratedMessage$GeneratedExtension;
      18: invokevirtual #62                 // Method com/google/protobuf/ExtensionRegistryLite.add:(Lcom/google/protobuf/ExtensionLite;)V
      21: aload_0
      22: getstatic     #68                 // Field deprecatedAtMinorVersionEnum:Lcom/google/protobuf/GeneratedMessage$GeneratedExtension;
      25: invokevirtual #62                 // Method com/google/protobuf/ExtensionRegistryLite.add:(Lcom/google/protobuf/ExtensionLite;)V
      28: return

  public static void registerAllExtensions(com.google.protobuf.ExtensionRegistry);
    Code:
       0: aload_0
       1: invokestatic  #73                 // Method registerAllExtensions:(Lcom/google/protobuf/ExtensionRegistryLite;)V
       4: return

  public static com.google.protobuf.Descriptors$FileDescriptor getDescriptor();
    Code:
       0: getstatic     #78                 // Field descriptor:Lcom/google/protobuf/Descriptors$FileDescriptor;
       3: areturn

  static {};
    Code:
       0: ldc           #81                 // class java/lang/Boolean
       2: aconst_null
       3: invokestatic  #85                 // Method com/google/protobuf/GeneratedMessage.newFileScopedGeneratedExtension:(Ljava/lang/Class;Lcom/google/protobuf/Message;)Lcom/google/protobuf/GeneratedMessage$GeneratedExtension;
       6: putstatic     #56                 // Field disallowedByDefault:Lcom/google/protobuf/GeneratedMessage$GeneratedExtension;
       9: ldc           #87                 // class java/lang/String
      11: aconst_null
      12: invokestatic  #85                 // Method com/google/protobuf/GeneratedMessage.newFileScopedGeneratedExtension:(Ljava/lang/Class;Lcom/google/protobuf/Message;)Lcom/google/protobuf/GeneratedMessage$GeneratedExtension;
      15: putstatic     #64                 // Field deprecatedAtMinorVersion:Lcom/google/protobuf/GeneratedMessage$GeneratedExtension;
      18: ldc           #81                 // class java/lang/Boolean
      20: aconst_null
      21: invokestatic  #85                 // Method com/google/protobuf/GeneratedMessage.newFileScopedGeneratedExtension:(Ljava/lang/Class;Lcom/google/protobuf/Message;)Lcom/google/protobuf/GeneratedMessage$GeneratedExtension;
      24: putstatic     #66                 // Field disallowedByDefaultEnum:Lcom/google/protobuf/GeneratedMessage$GeneratedExtension;
      27: ldc           #87                 // class java/lang/String
      29: aconst_null
      30: invokestatic  #85                 // Method com/google/protobuf/GeneratedMessage.newFileScopedGeneratedExtension:(Ljava/lang/Class;Lcom/google/protobuf/Message;)Lcom/google/protobuf/GeneratedMessage$GeneratedExtension;
      33: putstatic     #68                 // Field deprecatedAtMinorVersionEnum:Lcom/google/protobuf/GeneratedMessage$GeneratedExtension;
      36: iconst_1
      37: anewarray     #87                 // class java/lang/String
      40: dup
      41: iconst_0
      42: ldc           #89                 // String \n#envoy/annotations/deprecation.proto\u0012\u0011envoy.annotations\u001a google/protobuf/descriptor.proto:?\n\u0015disallowed_by_default\u0012\u001d.google.protobuf.FieldOptions\u0018ç­®Z \u0001(\b:E\n\u001bdeprecated_at_minor_version\u0012\u001d.google.protobuf.FieldOptions\u0018òè\u0080K \u0001(\t:H\n\u001adisallowed_by_default_enum\u0012!.google.protobuf.EnumValueOptions\u0018õÎ¶! \u0001(\b:N\n deprecated_at_minor_version_enum\u0012!.google.protobuf.EnumValueOptions\u0018Á¾³V \u0001(\tb\u0006proto3
      44: aastore
      45: astore_0
      46: aload_0
      47: iconst_1
      48: anewarray     #20                 // class com/google/protobuf/Descriptors$FileDescriptor
      51: dup
      52: iconst_0
      53: invokestatic  #91                 // Method com/google/protobuf/DescriptorProtos.getDescriptor:()Lcom/google/protobuf/Descriptors$FileDescriptor;
      56: aastore
      57: invokestatic  #95                 // Method com/google/protobuf/Descriptors$FileDescriptor.internalBuildGeneratedFileFrom:([Ljava/lang/String;[Lcom/google/protobuf/Descriptors$FileDescriptor;)Lcom/google/protobuf/Descriptors$FileDescriptor;
      60: putstatic     #78                 // Field descriptor:Lcom/google/protobuf/Descriptors$FileDescriptor;
      63: getstatic     #56                 // Field disallowedByDefault:Lcom/google/protobuf/GeneratedMessage$GeneratedExtension;
      66: getstatic     #78                 // Field descriptor:Lcom/google/protobuf/Descriptors$FileDescriptor;
      69: invokevirtual #99                 // Method com/google/protobuf/Descriptors$FileDescriptor.getExtensions:()Ljava/util/List;
      72: iconst_0
      73: invokeinterface #105,  2          // InterfaceMethod java/util/List.get:(I)Ljava/lang/Object;
      78: checkcast     #25                 // class com/google/protobuf/Descriptors$FieldDescriptor
      81: invokevirtual #109                // Method com/google/protobuf/GeneratedMessage$GeneratedExtension.internalInit:(Lcom/google/protobuf/Descriptors$FieldDescriptor;)V
      84: getstatic     #64                 // Field deprecatedAtMinorVersion:Lcom/google/protobuf/GeneratedMessage$GeneratedExtension;
      87: getstatic     #78                 // Field descriptor:Lcom/google/protobuf/Descriptors$FileDescriptor;
      90: invokevirtual #99                 // Method com/google/protobuf/Descriptors$FileDescriptor.getExtensions:()Ljava/util/List;
      93: iconst_1
      94: invokeinterface #105,  2          // InterfaceMethod java/util/List.get:(I)Ljava/lang/Object;
      99: checkcast     #25                 // class com/google/protobuf/Descriptors$FieldDescriptor
     102: invokevirtual #109                // Method com/google/protobuf/GeneratedMessage$GeneratedExtension.internalInit:(Lcom/google/protobuf/Descriptors$FieldDescriptor;)V
     105: getstatic     #66                 // Field disallowedByDefaultEnum:Lcom/google/protobuf/GeneratedMessage$GeneratedExtension;
     108: getstatic     #78                 // Field descriptor:Lcom/google/protobuf/Descriptors$FileDescriptor;
     111: invokevirtual #99                 // Method com/google/protobuf/Descriptors$FileDescriptor.getExtensions:()Ljava/util/List;
     114: iconst_2
     115: invokeinterface #105,  2          // InterfaceMethod java/util/List.get:(I)Ljava/lang/Object;
     120: checkcast     #25                 // class com/google/protobuf/Descriptors$FieldDescriptor
     123: invokevirtual #109                // Method com/google/protobuf/GeneratedMessage$GeneratedExtension.internalInit:(Lcom/google/protobuf/Descriptors$FieldDescriptor;)V
     126: getstatic     #68                 // Field deprecatedAtMinorVersionEnum:Lcom/google/protobuf/GeneratedMessage$GeneratedExtension;
     129: getstatic     #78                 // Field descriptor:Lcom/google/protobuf/Descriptors$FileDescriptor;
     132: invokevirtual #99                 // Method com/google/protobuf/Descriptors$FileDescriptor.getExtensions:()Ljava/util/List;
     135: iconst_3
     136: invokeinterface #105,  2          // InterfaceMethod java/util/List.get:(I)Ljava/lang/Object;
     141: checkcast     #25                 // class com/google/protobuf/Descriptors$FieldDescriptor
     144: invokevirtual #109                // Method com/google/protobuf/GeneratedMessage$GeneratedExtension.internalInit:(Lcom/google/protobuf/Descriptors$FieldDescriptor;)V
     147: invokestatic  #91                 // Method com/google/protobuf/DescriptorProtos.getDescriptor:()Lcom/google/protobuf/Descriptors$FileDescriptor;
     150: pop
     151: return
}
