Compiled from "RedirectAction.java"
class io.grpc.xds.shaded.io.envoyproxy.envoy.config.route.v3.RedirectAction$2 {
  static final int[] $SwitchMap$io$envoyproxy$envoy$config$route$v3$RedirectAction$SchemeRewriteSpecifierCase;

  static final int[] $SwitchMap$io$envoyproxy$envoy$config$route$v3$RedirectAction$PathRewriteSpecifierCase;

  static {};
    Code:
       0: invokestatic  #24                 // Method io/grpc/xds/shaded/io/envoyproxy/envoy/config/route/v3/RedirectAction$PathRewriteSpecifierCase.values:()[Lio/grpc/xds/shaded/io/envoyproxy/envoy/config/route/v3/RedirectAction$PathRewriteSpecifierCase;
       3: arraylength
       4: newarray       int
       6: putstatic     #26                 // Field $SwitchMap$io$envoyproxy$envoy$config$route$v3$RedirectAction$PathRewriteSpecifierCase:[I
       9: getstatic     #26                 // Field $SwitchMap$io$envoyproxy$envoy$config$route$v3$RedirectAction$PathRewriteSpecifierCase:[I
      12: getstatic     #30                 // Field io/grpc/xds/shaded/io/envoyproxy/envoy/config/route/v3/RedirectAction$PathRewriteSpecifierCase.PATH_REDIRECT:Lio/grpc/xds/shaded/io/envoyproxy/envoy/config/route/v3/RedirectAction$PathRewriteSpecifierCase;
      15: invokevirtual #34                 // Method io/grpc/xds/shaded/io/envoyproxy/envoy/config/route/v3/RedirectAction$PathRewriteSpecifierCase.ordinal:()I
      18: iconst_1
      19: iastore
      20: goto          24
      23: astore_0
      24: getstatic     #26                 // Field $SwitchMap$io$envoyproxy$envoy$config$route$v3$RedirectAction$PathRewriteSpecifierCase:[I
      27: getstatic     #37                 // Field io/grpc/xds/shaded/io/envoyproxy/envoy/config/route/v3/RedirectAction$PathRewriteSpecifierCase.PREFIX_REWRITE:Lio/grpc/xds/shaded/io/envoyproxy/envoy/config/route/v3/RedirectAction$PathRewriteSpecifierCase;
      30: invokevirtual #34                 // Method io/grpc/xds/shaded/io/envoyproxy/envoy/config/route/v3/RedirectAction$PathRewriteSpecifierCase.ordinal:()I
      33: iconst_2
      34: iastore
      35: goto          39
      38: astore_0
      39: getstatic     #26                 // Field $SwitchMap$io$envoyproxy$envoy$config$route$v3$RedirectAction$PathRewriteSpecifierCase:[I
      42: getstatic     #40                 // Field io/grpc/xds/shaded/io/envoyproxy/envoy/config/route/v3/RedirectAction$PathRewriteSpecifierCase.REGEX_REWRITE:Lio/grpc/xds/shaded/io/envoyproxy/envoy/config/route/v3/RedirectAction$PathRewriteSpecifierCase;
      45: invokevirtual #34                 // Method io/grpc/xds/shaded/io/envoyproxy/envoy/config/route/v3/RedirectAction$PathRewriteSpecifierCase.ordinal:()I
      48: iconst_3
      49: iastore
      50: goto          54
      53: astore_0
      54: getstatic     #26                 // Field $SwitchMap$io$envoyproxy$envoy$config$route$v3$RedirectAction$PathRewriteSpecifierCase:[I
      57: getstatic     #43                 // Field io/grpc/xds/shaded/io/envoyproxy/envoy/config/route/v3/RedirectAction$PathRewriteSpecifierCase.PATHREWRITESPECIFIER_NOT_SET:Lio/grpc/xds/shaded/io/envoyproxy/envoy/config/route/v3/RedirectAction$PathRewriteSpecifierCase;
      60: invokevirtual #34                 // Method io/grpc/xds/shaded/io/envoyproxy/envoy/config/route/v3/RedirectAction$PathRewriteSpecifierCase.ordinal:()I
      63: iconst_4
      64: iastore
      65: goto          69
      68: astore_0
      69: invokestatic  #46                 // Method io/grpc/xds/shaded/io/envoyproxy/envoy/config/route/v3/RedirectAction$SchemeRewriteSpecifierCase.values:()[Lio/grpc/xds/shaded/io/envoyproxy/envoy/config/route/v3/RedirectAction$SchemeRewriteSpecifierCase;
      72: arraylength
      73: newarray       int
      75: putstatic     #48                 // Field $SwitchMap$io$envoyproxy$envoy$config$route$v3$RedirectAction$SchemeRewriteSpecifierCase:[I
      78: getstatic     #48                 // Field $SwitchMap$io$envoyproxy$envoy$config$route$v3$RedirectAction$SchemeRewriteSpecifierCase:[I
      81: getstatic     #52                 // Field io/grpc/xds/shaded/io/envoyproxy/envoy/config/route/v3/RedirectAction$SchemeRewriteSpecifierCase.HTTPS_REDIRECT:Lio/grpc/xds/shaded/io/envoyproxy/envoy/config/route/v3/RedirectAction$SchemeRewriteSpecifierCase;
      84: invokevirtual #53                 // Method io/grpc/xds/shaded/io/envoyproxy/envoy/config/route/v3/RedirectAction$SchemeRewriteSpecifierCase.ordinal:()I
      87: iconst_1
      88: iastore
      89: goto          93
      92: astore_0
      93: getstatic     #48                 // Field $SwitchMap$io$envoyproxy$envoy$config$route$v3$RedirectAction$SchemeRewriteSpecifierCase:[I
      96: getstatic     #56                 // Field io/grpc/xds/shaded/io/envoyproxy/envoy/config/route/v3/RedirectAction$SchemeRewriteSpecifierCase.SCHEME_REDIRECT:Lio/grpc/xds/shaded/io/envoyproxy/envoy/config/route/v3/RedirectAction$SchemeRewriteSpecifierCase;
      99: invokevirtual #53                 // Method io/grpc/xds/shaded/io/envoyproxy/envoy/config/route/v3/RedirectAction$SchemeRewriteSpecifierCase.ordinal:()I
     102: iconst_2
     103: iastore
     104: goto          108
     107: astore_0
     108: getstatic     #48                 // Field $SwitchMap$io$envoyproxy$envoy$config$route$v3$RedirectAction$SchemeRewriteSpecifierCase:[I
     111: getstatic     #59                 // Field io/grpc/xds/shaded/io/envoyproxy/envoy/config/route/v3/RedirectAction$SchemeRewriteSpecifierCase.SCHEMEREWRITESPECIFIER_NOT_SET:Lio/grpc/xds/shaded/io/envoyproxy/envoy/config/route/v3/RedirectAction$SchemeRewriteSpecifierCase;
     114: invokevirtual #53                 // Method io/grpc/xds/shaded/io/envoyproxy/envoy/config/route/v3/RedirectAction$SchemeRewriteSpecifierCase.ordinal:()I
     117: iconst_3
     118: iastore
     119: goto          123
     122: astore_0
     123: return
    Exception table:
       from    to  target type
           9    20    23   Class java/lang/NoSuchFieldError
          24    35    38   Class java/lang/NoSuchFieldError
          39    50    53   Class java/lang/NoSuchFieldError
          54    65    68   Class java/lang/NoSuchFieldError
          78    89    92   Class java/lang/NoSuchFieldError
          93   104   107   Class java/lang/NoSuchFieldError
         108   119   122   Class java/lang/NoSuchFieldError
}
