Compiled from "RouteAction.java"
public final class io.grpc.xds.shaded.io.envoyproxy.envoy.config.route.v3.RouteAction extends com.google.protobuf.GeneratedMessageV3 implements io.grpc.xds.shaded.io.envoyproxy.envoy.config.route.v3.RouteActionOrBuilder {
  private static final long serialVersionUID;

  private int clusterSpecifierCase_;

  private java.lang.Object clusterSpecifier_;

  private int hostRewriteSpecifierCase_;

  private java.lang.Object hostRewriteSpecifier_;

  public static final int CLUSTER_FIELD_NUMBER;

  public static final int CLUSTER_HEADER_FIELD_NUMBER;

  public static final int WEIGHTED_CLUSTERS_FIELD_NUMBER;

  public static final int CLUSTER_SPECIFIER_PLUGIN_FIELD_NUMBER;

  public static final int CLUSTER_NOT_FOUND_RESPONSE_CODE_FIELD_NUMBER;

  private int clusterNotFoundResponseCode_;

  public static final int METADATA_MATCH_FIELD_NUMBER;

  private io.grpc.xds.shaded.io.envoyproxy.envoy.config.core.v3.Metadata metadataMatch_;

  public static final int PREFIX_REWRITE_FIELD_NUMBER;

  private volatile java.lang.Object prefixRewrite_;

  public static final int REGEX_REWRITE_FIELD_NUMBER;

  private io.grpc.xds.shaded.io.envoyproxy.envoy.type.matcher.v3.RegexMatchAndSubstitute regexRewrite_;

  public static final int HOST_REWRITE_LITERAL_FIELD_NUMBER;

  public static final int AUTO_HOST_REWRITE_FIELD_NUMBER;

  public static final int HOST_REWRITE_HEADER_FIELD_NUMBER;

  public static final int HOST_REWRITE_PATH_REGEX_FIELD_NUMBER;

  public static final int TIMEOUT_FIELD_NUMBER;

  private com.google.protobuf.Duration timeout_;

  public static final int IDLE_TIMEOUT_FIELD_NUMBER;

  private com.google.protobuf.Duration idleTimeout_;

  public static final int RETRY_POLICY_FIELD_NUMBER;

  private io.grpc.xds.shaded.io.envoyproxy.envoy.config.route.v3.RetryPolicy retryPolicy_;

  public static final int RETRY_POLICY_TYPED_CONFIG_FIELD_NUMBER;

  private com.google.protobuf.Any retryPolicyTypedConfig_;

  public static final int REQUEST_MIRROR_POLICIES_FIELD_NUMBER;

  private java.util.List<io.grpc.xds.shaded.io.envoyproxy.envoy.config.route.v3.RouteAction$RequestMirrorPolicy> requestMirrorPolicies_;

  public static final int PRIORITY_FIELD_NUMBER;

  private int priority_;

  public static final int RATE_LIMITS_FIELD_NUMBER;

  private java.util.List<io.grpc.xds.shaded.io.envoyproxy.envoy.config.route.v3.RateLimit> rateLimits_;

  public static final int INCLUDE_VH_RATE_LIMITS_FIELD_NUMBER;

  private com.google.protobuf.BoolValue includeVhRateLimits_;

  public static final int HASH_POLICY_FIELD_NUMBER;

  private java.util.List<io.grpc.xds.shaded.io.envoyproxy.envoy.config.route.v3.RouteAction$HashPolicy> hashPolicy_;

  public static final int CORS_FIELD_NUMBER;

  private io.grpc.xds.shaded.io.envoyproxy.envoy.config.route.v3.CorsPolicy cors_;

  public static final int MAX_GRPC_TIMEOUT_FIELD_NUMBER;

  private com.google.protobuf.Duration maxGrpcTimeout_;

  public static final int GRPC_TIMEOUT_OFFSET_FIELD_NUMBER;

  private com.google.protobuf.Duration grpcTimeoutOffset_;

  public static final int UPGRADE_CONFIGS_FIELD_NUMBER;

  private java.util.List<io.grpc.xds.shaded.io.envoyproxy.envoy.config.route.v3.RouteAction$UpgradeConfig> upgradeConfigs_;

  public static final int INTERNAL_REDIRECT_POLICY_FIELD_NUMBER;

  private io.grpc.xds.shaded.io.envoyproxy.envoy.config.route.v3.InternalRedirectPolicy internalRedirectPolicy_;

  public static final int INTERNAL_REDIRECT_ACTION_FIELD_NUMBER;

  private int internalRedirectAction_;

  public static final int MAX_INTERNAL_REDIRECTS_FIELD_NUMBER;

  private com.google.protobuf.UInt32Value maxInternalRedirects_;

  public static final int HEDGE_POLICY_FIELD_NUMBER;

  private io.grpc.xds.shaded.io.envoyproxy.envoy.config.route.v3.HedgePolicy hedgePolicy_;

  public static final int MAX_STREAM_DURATION_FIELD_NUMBER;

  private io.grpc.xds.shaded.io.envoyproxy.envoy.config.route.v3.RouteAction$MaxStreamDuration maxStreamDuration_;

  private byte memoizedIsInitialized;

  private static final io.grpc.xds.shaded.io.envoyproxy.envoy.config.route.v3.RouteAction DEFAULT_INSTANCE;

  private static final com.google.protobuf.Parser<io.grpc.xds.shaded.io.envoyproxy.envoy.config.route.v3.RouteAction> PARSER;

  private io.grpc.xds.shaded.io.envoyproxy.envoy.config.route.v3.RouteAction(com.google.protobuf.GeneratedMessageV3$Builder<?>);
    Code:
       0: aload_0
       1: aload_1
       2: invokespecial #244                // Method com/google/protobuf/GeneratedMessageV3."<init>":(Lcom/google/protobuf/GeneratedMessageV3$Builder;)V
       5: aload_0
       6: iconst_0
       7: putfield      #246                // Field clusterSpecifierCase_:I
      10: aload_0
      11: iconst_0
      12: putfield      #248                // Field hostRewriteSpecifierCase_:I
      15: aload_0
      16: iconst_m1
      17: putfield      #250                // Field memoizedIsInitialized:B
      20: return

  private io.grpc.xds.shaded.io.envoyproxy.envoy.config.route.v3.RouteAction();
    Code:
       0: aload_0
       1: invokespecial #257                // Method com/google/protobuf/GeneratedMessageV3."<init>":()V
       4: aload_0
       5: iconst_0
       6: putfield      #246                // Field clusterSpecifierCase_:I
       9: aload_0
      10: iconst_0
      11: putfield      #248                // Field hostRewriteSpecifierCase_:I
      14: aload_0
      15: iconst_m1
      16: putfield      #250                // Field memoizedIsInitialized:B
      19: aload_0
      20: iconst_0
      21: putfield      #259                // Field clusterNotFoundResponseCode_:I
      24: aload_0
      25: ldc_w         #261                // String
      28: putfield      #263                // Field prefixRewrite_:Ljava/lang/Object;
      31: aload_0
      32: invokestatic  #269                // Method java/util/Collections.emptyList:()Ljava/util/List;
      35: putfield      #271                // Field requestMirrorPolicies_:Ljava/util/List;
      38: aload_0
      39: iconst_0
      40: putfield      #273                // Field priority_:I
      43: aload_0
      44: invokestatic  #269                // Method java/util/Collections.emptyList:()Ljava/util/List;
      47: putfield      #275                // Field rateLimits_:Ljava/util/List;
      50: aload_0
      51: invokestatic  #269                // Method java/util/Collections.emptyList:()Ljava/util/List;
      54: putfield      #277                // Field hashPolicy_:Ljava/util/List;
      57: aload_0
      58: invokestatic  #269                // Method java/util/Collections.emptyList:()Ljava/util/List;
      61: putfield      #279                // Field upgradeConfigs_:Ljava/util/List;
      64: aload_0
      65: iconst_0
      66: putfield      #281                // Field internalRedirectAction_:I
      69: return

  protected java.lang.Object newInstance(com.google.protobuf.GeneratedMessageV3$UnusedPrivateParameter);
    Code:
       0: new           #2                  // class io/grpc/xds/shaded/io/envoyproxy/envoy/config/route/v3/RouteAction
       3: dup
       4: invokespecial #284                // Method "<init>":()V
       7: areturn

  public final com.google.protobuf.UnknownFieldSet getUnknownFields();
    Code:
       0: aload_0
       1: getfield      #292                // Field unknownFields:Lcom/google/protobuf/UnknownFieldSet;
       4: areturn

  private io.grpc.xds.shaded.io.envoyproxy.envoy.config.route.v3.RouteAction(com.google.protobuf.CodedInputStream, com.google.protobuf.ExtensionRegistryLite) throws com.google.protobuf.InvalidProtocolBufferException;
    Code:
       0: aload_0
       1: invokespecial #284                // Method "<init>":()V
       4: aload_2
       5: ifnonnull     16
       8: new           #299                // class java/lang/NullPointerException
      11: dup
      12: invokespecial #300                // Method java/lang/NullPointerException."<init>":()V
      15: athrow
      16: iconst_0
      17: istore_3
      18: invokestatic  #308                // Method com/google/protobuf/UnknownFieldSet.newBuilder:()Lcom/google/protobuf/UnknownFieldSet$Builder;
      21: astore        4
      23: iconst_0
      24: istore        5
      26: iload         5
      28: ifne          1722
      31: aload_1
      32: invokevirtual #312                // Method com/google/protobuf/CodedInputStream.readTag:()I
      35: istore        6
      37: iload         6
      39: lookupswitch  { // 31
                     0: 296
                    10: 302
                    18: 322
                    26: 342
                    34: 412
                    42: 473
                    50: 488
                    58: 509
                    66: 581
                    74: 642
                    88: 703
                   106: 718
                   114: 760
                   122: 821
                   138: 863
                   160: 924
                   186: 939
                   194: 1000
                   202: 1061
                   208: 1105
                   218: 1120
                   226: 1181
                   234: 1242
                   242: 1263
                   250: 1305
                   258: 1366
                   266: 1427
                   274: 1488
                   282: 1549
                   290: 1621
                   298: 1682
               default: 1703
          }
     296: iconst_1
     297: istore        5
     299: goto          1719
     302: aload_1
     303: invokevirtual #316                // Method com/google/protobuf/CodedInputStream.readStringRequireUtf8:()Ljava/lang/String;
     306: astore        7
     308: aload_0
     309: iconst_1
     310: putfield      #246                // Field clusterSpecifierCase_:I
     313: aload_0
     314: aload         7
     316: putfield      #318                // Field clusterSpecifier_:Ljava/lang/Object;
     319: goto          1719
     322: aload_1
     323: invokevirtual #316                // Method com/google/protobuf/CodedInputStream.readStringRequireUtf8:()Ljava/lang/String;
     326: astore        7
     328: aload_0
     329: iconst_2
     330: putfield      #246                // Field clusterSpecifierCase_:I
     333: aload_0
     334: aload         7
     336: putfield      #318                // Field clusterSpecifier_:Ljava/lang/Object;
     339: goto          1719
     342: aconst_null
     343: astore        7
     345: aload_0
     346: getfield      #246                // Field clusterSpecifierCase_:I
     349: iconst_3
     350: if_icmpne     365
     353: aload_0
     354: getfield      #318                // Field clusterSpecifier_:Ljava/lang/Object;
     357: checkcast     #59                 // class io/grpc/xds/shaded/io/envoyproxy/envoy/config/route/v3/WeightedCluster
     360: invokevirtual #322                // Method io/grpc/xds/shaded/io/envoyproxy/envoy/config/route/v3/WeightedCluster.toBuilder:()Lio/grpc/xds/shaded/io/envoyproxy/envoy/config/route/v3/WeightedCluster$Builder;
     363: astore        7
     365: aload_0
     366: aload_1
     367: invokestatic  #326                // Method io/grpc/xds/shaded/io/envoyproxy/envoy/config/route/v3/WeightedCluster.parser:()Lcom/google/protobuf/Parser;
     370: aload_2
     371: invokevirtual #330                // Method com/google/protobuf/CodedInputStream.readMessage:(Lcom/google/protobuf/Parser;Lcom/google/protobuf/ExtensionRegistryLite;)Lcom/google/protobuf/MessageLite;
     374: putfield      #318                // Field clusterSpecifier_:Ljava/lang/Object;
     377: aload         7
     379: ifnull        404
     382: aload         7
     384: aload_0
     385: getfield      #318                // Field clusterSpecifier_:Ljava/lang/Object;
     388: checkcast     #59                 // class io/grpc/xds/shaded/io/envoyproxy/envoy/config/route/v3/WeightedCluster
     391: invokevirtual #334                // Method io/grpc/xds/shaded/io/envoyproxy/envoy/config/route/v3/WeightedCluster$Builder.mergeFrom:(Lio/grpc/xds/shaded/io/envoyproxy/envoy/config/route/v3/WeightedCluster;)Lio/grpc/xds/shaded/io/envoyproxy/envoy/config/route/v3/WeightedCluster$Builder;
     394: pop
     395: aload_0
     396: aload         7
     398: invokevirtual #338                // Method io/grpc/xds/shaded/io/envoyproxy/envoy/config/route/v3/WeightedCluster$Builder.buildPartial:()Lio/grpc/xds/shaded/io/envoyproxy/envoy/config/route/v3/WeightedCluster;
     401: putfield      #318                // Field clusterSpecifier_:Ljava/lang/Object;
     404: aload_0
     405: iconst_3
     406: putfield      #246                // Field clusterSpecifierCase_:I
     409: goto          1719
     412: aconst_null
     413: astore        7
     415: aload_0
     416: getfield      #340                // Field metadataMatch_:Lio/grpc/xds/shaded/io/envoyproxy/envoy/config/core/v3/Metadata;
     419: ifnull        431
     422: aload_0
     423: getfield      #340                // Field metadataMatch_:Lio/grpc/xds/shaded/io/envoyproxy/envoy/config/core/v3/Metadata;
     426: invokevirtual #343                // Method io/grpc/xds/shaded/io/envoyproxy/envoy/config/core/v3/Metadata.toBuilder:()Lio/grpc/xds/shaded/io/envoyproxy/envoy/config/core/v3/Metadata$Builder;
     429: astore        7
     431: aload_0
     432: aload_1
     433: invokestatic  #344                // Method io/grpc/xds/shaded/io/envoyproxy/envoy/config/core/v3/Metadata.parser:()Lcom/google/protobuf/Parser;
     436: aload_2
     437: invokevirtual #330                // Method com/google/protobuf/CodedInputStream.readMessage:(Lcom/google/protobuf/Parser;Lcom/google/protobuf/ExtensionRegistryLite;)Lcom/google/protobuf/MessageLite;
     440: checkcast     #63                 // class io/grpc/xds/shaded/io/envoyproxy/envoy/config/core/v3/Metadata
     443: putfield      #340                // Field metadataMatch_:Lio/grpc/xds/shaded/io/envoyproxy/envoy/config/core/v3/Metadata;
     446: aload         7
     448: ifnull        1719
     451: aload         7
     453: aload_0
     454: getfield      #340                // Field metadataMatch_:Lio/grpc/xds/shaded/io/envoyproxy/envoy/config/core/v3/Metadata;
     457: invokevirtual #347                // Method io/grpc/xds/shaded/io/envoyproxy/envoy/config/core/v3/Metadata$Builder.mergeFrom:(Lio/grpc/xds/shaded/io/envoyproxy/envoy/config/core/v3/Metadata;)Lio/grpc/xds/shaded/io/envoyproxy/envoy/config/core/v3/Metadata$Builder;
     460: pop
     461: aload_0
     462: aload         7
     464: invokevirtual #350                // Method io/grpc/xds/shaded/io/envoyproxy/envoy/config/core/v3/Metadata$Builder.buildPartial:()Lio/grpc/xds/shaded/io/envoyproxy/envoy/config/core/v3/Metadata;
     467: putfield      #340                // Field metadataMatch_:Lio/grpc/xds/shaded/io/envoyproxy/envoy/config/core/v3/Metadata;
     470: goto          1719
     473: aload_1
     474: invokevirtual #316                // Method com/google/protobuf/CodedInputStream.readStringRequireUtf8:()Ljava/lang/String;
     477: astore        7
     479: aload_0
     480: aload         7
     482: putfield      #263                // Field prefixRewrite_:Ljava/lang/Object;
     485: goto          1719
     488: aload_1
     489: invokevirtual #316                // Method com/google/protobuf/CodedInputStream.readStringRequireUtf8:()Ljava/lang/String;
     492: astore        7
     494: aload_0
     495: bipush        6
     497: putfield      #248                // Field hostRewriteSpecifierCase_:I
     500: aload_0
     501: aload         7
     503: putfield      #352                // Field hostRewriteSpecifier_:Ljava/lang/Object;
     506: goto          1719
     509: aconst_null
     510: astore        7
     512: aload_0
     513: getfield      #248                // Field hostRewriteSpecifierCase_:I
     516: bipush        7
     518: if_icmpne     533
     521: aload_0
     522: getfield      #352                // Field hostRewriteSpecifier_:Ljava/lang/Object;
     525: checkcast     #67                 // class com/google/protobuf/BoolValue
     528: invokevirtual #355                // Method com/google/protobuf/BoolValue.toBuilder:()Lcom/google/protobuf/BoolValue$Builder;
     531: astore        7
     533: aload_0
     534: aload_1
     535: invokestatic  #356                // Method com/google/protobuf/BoolValue.parser:()Lcom/google/protobuf/Parser;
     538: aload_2
     539: invokevirtual #330                // Method com/google/protobuf/CodedInputStream.readMessage:(Lcom/google/protobuf/Parser;Lcom/google/protobuf/ExtensionRegistryLite;)Lcom/google/protobuf/MessageLite;
     542: putfield      #352                // Field hostRewriteSpecifier_:Ljava/lang/Object;
     545: aload         7
     547: ifnull        572
     550: aload         7
     552: aload_0
     553: getfield      #352                // Field hostRewriteSpecifier_:Ljava/lang/Object;
     556: checkcast     #67                 // class com/google/protobuf/BoolValue
     559: invokevirtual #359                // Method com/google/protobuf/BoolValue$Builder.mergeFrom:(Lcom/google/protobuf/BoolValue;)Lcom/google/protobuf/BoolValue$Builder;
     562: pop
     563: aload_0
     564: aload         7
     566: invokevirtual #362                // Method com/google/protobuf/BoolValue$Builder.buildPartial:()Lcom/google/protobuf/BoolValue;
     569: putfield      #352                // Field hostRewriteSpecifier_:Ljava/lang/Object;
     572: aload_0
     573: bipush        7
     575: putfield      #248                // Field hostRewriteSpecifierCase_:I
     578: goto          1719
     581: aconst_null
     582: astore        7
     584: aload_0
     585: getfield      #364                // Field timeout_:Lcom/google/protobuf/Duration;
     588: ifnull        600
     591: aload_0
     592: getfield      #364                // Field timeout_:Lcom/google/protobuf/Duration;
     595: invokevirtual #367                // Method com/google/protobuf/Duration.toBuilder:()Lcom/google/protobuf/Duration$Builder;
     598: astore        7
     600: aload_0
     601: aload_1
     602: invokestatic  #368                // Method com/google/protobuf/Duration.parser:()Lcom/google/protobuf/Parser;
     605: aload_2
     606: invokevirtual #330                // Method com/google/protobuf/CodedInputStream.readMessage:(Lcom/google/protobuf/Parser;Lcom/google/protobuf/ExtensionRegistryLite;)Lcom/google/protobuf/MessageLite;
     609: checkcast     #71                 // class com/google/protobuf/Duration
     612: putfield      #364                // Field timeout_:Lcom/google/protobuf/Duration;
     615: aload         7
     617: ifnull        1719
     620: aload         7
     622: aload_0
     623: getfield      #364                // Field timeout_:Lcom/google/protobuf/Duration;
     626: invokevirtual #371                // Method com/google/protobuf/Duration$Builder.mergeFrom:(Lcom/google/protobuf/Duration;)Lcom/google/protobuf/Duration$Builder;
     629: pop
     630: aload_0
     631: aload         7
     633: invokevirtual #374                // Method com/google/protobuf/Duration$Builder.buildPartial:()Lcom/google/protobuf/Duration;
     636: putfield      #364                // Field timeout_:Lcom/google/protobuf/Duration;
     639: goto          1719
     642: aconst_null
     643: astore        7
     645: aload_0
     646: getfield      #376                // Field retryPolicy_:Lio/grpc/xds/shaded/io/envoyproxy/envoy/config/route/v3/RetryPolicy;
     649: ifnull        661
     652: aload_0
     653: getfield      #376                // Field retryPolicy_:Lio/grpc/xds/shaded/io/envoyproxy/envoy/config/route/v3/RetryPolicy;
     656: invokevirtual #379                // Method io/grpc/xds/shaded/io/envoyproxy/envoy/config/route/v3/RetryPolicy.toBuilder:()Lio/grpc/xds/shaded/io/envoyproxy/envoy/config/route/v3/RetryPolicy$Builder;
     659: astore        7
     661: aload_0
     662: aload_1
     663: invokestatic  #380                // Method io/grpc/xds/shaded/io/envoyproxy/envoy/config/route/v3/RetryPolicy.parser:()Lcom/google/protobuf/Parser;
     666: aload_2
     667: invokevirtual #330                // Method com/google/protobuf/CodedInputStream.readMessage:(Lcom/google/protobuf/Parser;Lcom/google/protobuf/ExtensionRegistryLite;)Lcom/google/protobuf/MessageLite;
     670: checkcast     #75                 // class io/grpc/xds/shaded/io/envoyproxy/envoy/config/route/v3/RetryPolicy
     673: putfield      #376                // Field retryPolicy_:Lio/grpc/xds/shaded/io/envoyproxy/envoy/config/route/v3/RetryPolicy;
     676: aload         7
     678: ifnull        1719
     681: aload         7
     683: aload_0
     684: getfield      #376                // Field retryPolicy_:Lio/grpc/xds/shaded/io/envoyproxy/envoy/config/route/v3/RetryPolicy;
     687: invokevirtual #383                // Method io/grpc/xds/shaded/io/envoyproxy/envoy/config/route/v3/RetryPolicy$Builder.mergeFrom:(Lio/grpc/xds/shaded/io/envoyproxy/envoy/config/route/v3/RetryPolicy;)Lio/grpc/xds/shaded/io/envoyproxy/envoy/config/route/v3/RetryPolicy$Builder;
     690: pop
     691: aload_0
     692: aload         7
     694: invokevirtual #386                // Method io/grpc/xds/shaded/io/envoyproxy/envoy/config/route/v3/RetryPolicy$Builder.buildPartial:()Lio/grpc/xds/shaded/io/envoyproxy/envoy/config/route/v3/RetryPolicy;
     697: putfield      #376                // Field retryPolicy_:Lio/grpc/xds/shaded/io/envoyproxy/envoy/config/route/v3/RetryPolicy;
     700: goto          1719
     703: aload_1
     704: invokevirtual #389                // Method com/google/protobuf/CodedInputStream.readEnum:()I
     707: istore        7
     709: aload_0
     710: iload         7
     712: putfield      #273                // Field priority_:I
     715: goto          1719
     718: iload_3
     719: iconst_2
     720: iand
     721: ifne          739
     724: aload_0
     725: new           #391                // class java/util/ArrayList
     728: dup
     729: invokespecial #392                // Method java/util/ArrayList."<init>":()V
     732: putfield      #275                // Field rateLimits_:Ljava/util/List;
     735: iload_3
     736: iconst_2
     737: ior
     738: istore_3
     739: aload_0
     740: getfield      #275                // Field rateLimits_:Ljava/util/List;
     743: aload_1
     744: invokestatic  #395                // Method io/grpc/xds/shaded/io/envoyproxy/envoy/config/route/v3/RateLimit.parser:()Lcom/google/protobuf/Parser;
     747: aload_2
     748: invokevirtual #330                // Method com/google/protobuf/CodedInputStream.readMessage:(Lcom/google/protobuf/Parser;Lcom/google/protobuf/ExtensionRegistryLite;)Lcom/google/protobuf/MessageLite;
     751: invokeinterface #401,  2          // InterfaceMethod java/util/List.add:(Ljava/lang/Object;)Z
     756: pop
     757: goto          1719
     760: aconst_null
     761: astore        7
     763: aload_0
     764: getfield      #403                // Field includeVhRateLimits_:Lcom/google/protobuf/BoolValue;
     767: ifnull        779
     770: aload_0
     771: getfield      #403                // Field includeVhRateLimits_:Lcom/google/protobuf/BoolValue;
     774: invokevirtual #355                // Method com/google/protobuf/BoolValue.toBuilder:()Lcom/google/protobuf/BoolValue$Builder;
     777: astore        7
     779: aload_0
     780: aload_1
     781: invokestatic  #356                // Method com/google/protobuf/BoolValue.parser:()Lcom/google/protobuf/Parser;
     784: aload_2
     785: invokevirtual #330                // Method com/google/protobuf/CodedInputStream.readMessage:(Lcom/google/protobuf/Parser;Lcom/google/protobuf/ExtensionRegistryLite;)Lcom/google/protobuf/MessageLite;
     788: checkcast     #67                 // class com/google/protobuf/BoolValue
     791: putfield      #403                // Field includeVhRateLimits_:Lcom/google/protobuf/BoolValue;
     794: aload         7
     796: ifnull        1719
     799: aload         7
     801: aload_0
     802: getfield      #403                // Field includeVhRateLimits_:Lcom/google/protobuf/BoolValue;
     805: invokevirtual #359                // Method com/google/protobuf/BoolValue$Builder.mergeFrom:(Lcom/google/protobuf/BoolValue;)Lcom/google/protobuf/BoolValue$Builder;
     808: pop
     809: aload_0
     810: aload         7
     812: invokevirtual #362                // Method com/google/protobuf/BoolValue$Builder.buildPartial:()Lcom/google/protobuf/BoolValue;
     815: putfield      #403                // Field includeVhRateLimits_:Lcom/google/protobuf/BoolValue;
     818: goto          1719
     821: iload_3
     822: iconst_4
     823: iand
     824: ifne          842
     827: aload_0
     828: new           #391                // class java/util/ArrayList
     831: dup
     832: invokespecial #392                // Method java/util/ArrayList."<init>":()V
     835: putfield      #277                // Field hashPolicy_:Ljava/util/List;
     838: iload_3
     839: iconst_4
     840: ior
     841: istore_3
     842: aload_0
     843: getfield      #277                // Field hashPolicy_:Ljava/util/List;
     846: aload_1
     847: invokestatic  #404                // Method io/grpc/xds/shaded/io/envoyproxy/envoy/config/route/v3/RouteAction$HashPolicy.parser:()Lcom/google/protobuf/Parser;
     850: aload_2
     851: invokevirtual #330                // Method com/google/protobuf/CodedInputStream.readMessage:(Lcom/google/protobuf/Parser;Lcom/google/protobuf/ExtensionRegistryLite;)Lcom/google/protobuf/MessageLite;
     854: invokeinterface #401,  2          // InterfaceMethod java/util/List.add:(Ljava/lang/Object;)Z
     859: pop
     860: goto          1719
     863: aconst_null
     864: astore        7
     866: aload_0
     867: getfield      #406                // Field cors_:Lio/grpc/xds/shaded/io/envoyproxy/envoy/config/route/v3/CorsPolicy;
     870: ifnull        882
     873: aload_0
     874: getfield      #406                // Field cors_:Lio/grpc/xds/shaded/io/envoyproxy/envoy/config/route/v3/CorsPolicy;
     877: invokevirtual #409                // Method io/grpc/xds/shaded/io/envoyproxy/envoy/config/route/v3/CorsPolicy.toBuilder:()Lio/grpc/xds/shaded/io/envoyproxy/envoy/config/route/v3/CorsPolicy$Builder;
     880: astore        7
     882: aload_0
     883: aload_1
     884: invokestatic  #410                // Method io/grpc/xds/shaded/io/envoyproxy/envoy/config/route/v3/CorsPolicy.parser:()Lcom/google/protobuf/Parser;
     887: aload_2
     888: invokevirtual #330                // Method com/google/protobuf/CodedInputStream.readMessage:(Lcom/google/protobuf/Parser;Lcom/google/protobuf/ExtensionRegistryLite;)Lcom/google/protobuf/MessageLite;
     891: checkcast     #79                 // class io/grpc/xds/shaded/io/envoyproxy/envoy/config/route/v3/CorsPolicy
     894: putfield      #406                // Field cors_:Lio/grpc/xds/shaded/io/envoyproxy/envoy/config/route/v3/CorsPolicy;
     897: aload         7
     899: ifnull        1719
     902: aload         7
     904: aload_0
     905: getfield      #406                // Field cors_:Lio/grpc/xds/shaded/io/envoyproxy/envoy/config/route/v3/CorsPolicy;
     908: invokevirtual #413                // Method io/grpc/xds/shaded/io/envoyproxy/envoy/config/route/v3/CorsPolicy$Builder.mergeFrom:(Lio/grpc/xds/shaded/io/envoyproxy/envoy/config/route/v3/CorsPolicy;)Lio/grpc/xds/shaded/io/envoyproxy/envoy/config/route/v3/CorsPolicy$Builder;
     911: pop
     912: aload_0
     913: aload         7
     915: invokevirtual #416                // Method io/grpc/xds/shaded/io/envoyproxy/envoy/config/route/v3/CorsPolicy$Builder.buildPartial:()Lio/grpc/xds/shaded/io/envoyproxy/envoy/config/route/v3/CorsPolicy;
     918: putfield      #406                // Field cors_:Lio/grpc/xds/shaded/io/envoyproxy/envoy/config/route/v3/CorsPolicy;
     921: goto          1719
     924: aload_1
     925: invokevirtual #389                // Method com/google/protobuf/CodedInputStream.readEnum:()I
     928: istore        7
     930: aload_0
     931: iload         7
     933: putfield      #259                // Field clusterNotFoundResponseCode_:I
     936: goto          1719
     939: aconst_null
     940: astore        7
     942: aload_0
     943: getfield      #418                // Field maxGrpcTimeout_:Lcom/google/protobuf/Duration;
     946: ifnull        958
     949: aload_0
     950: getfield      #418                // Field maxGrpcTimeout_:Lcom/google/protobuf/Duration;
     953: invokevirtual #367                // Method com/google/protobuf/Duration.toBuilder:()Lcom/google/protobuf/Duration$Builder;
     956: astore        7
     958: aload_0
     959: aload_1
     960: invokestatic  #368                // Method com/google/protobuf/Duration.parser:()Lcom/google/protobuf/Parser;
     963: aload_2
     964: invokevirtual #330                // Method com/google/protobuf/CodedInputStream.readMessage:(Lcom/google/protobuf/Parser;Lcom/google/protobuf/ExtensionRegistryLite;)Lcom/google/protobuf/MessageLite;
     967: checkcast     #71                 // class com/google/protobuf/Duration
     970: putfield      #418                // Field maxGrpcTimeout_:Lcom/google/protobuf/Duration;
     973: aload         7
     975: ifnull        1719
     978: aload         7
     980: aload_0
     981: getfield      #418                // Field maxGrpcTimeout_:Lcom/google/protobuf/Duration;
     984: invokevirtual #371                // Method com/google/protobuf/Duration$Builder.mergeFrom:(Lcom/google/protobuf/Duration;)Lcom/google/protobuf/Duration$Builder;
     987: pop
     988: aload_0
     989: aload         7
     991: invokevirtual #374                // Method com/google/protobuf/Duration$Builder.buildPartial:()Lcom/google/protobuf/Duration;
     994: putfield      #418                // Field maxGrpcTimeout_:Lcom/google/protobuf/Duration;
     997: goto          1719
    1000: aconst_null
    1001: astore        7
    1003: aload_0
    1004: getfield      #420                // Field idleTimeout_:Lcom/google/protobuf/Duration;
    1007: ifnull        1019
    1010: aload_0
    1011: getfield      #420                // Field idleTimeout_:Lcom/google/protobuf/Duration;
    1014: invokevirtual #367                // Method com/google/protobuf/Duration.toBuilder:()Lcom/google/protobuf/Duration$Builder;
    1017: astore        7
    1019: aload_0
    1020: aload_1
    1021: invokestatic  #368                // Method com/google/protobuf/Duration.parser:()Lcom/google/protobuf/Parser;
    1024: aload_2
    1025: invokevirtual #330                // Method com/google/protobuf/CodedInputStream.readMessage:(Lcom/google/protobuf/Parser;Lcom/google/protobuf/ExtensionRegistryLite;)Lcom/google/protobuf/MessageLite;
    1028: checkcast     #71                 // class com/google/protobuf/Duration
    1031: putfield      #420                // Field idleTimeout_:Lcom/google/protobuf/Duration;
    1034: aload         7
    1036: ifnull        1719
    1039: aload         7
    1041: aload_0
    1042: getfield      #420                // Field idleTimeout_:Lcom/google/protobuf/Duration;
    1045: invokevirtual #371                // Method com/google/protobuf/Duration$Builder.mergeFrom:(Lcom/google/protobuf/Duration;)Lcom/google/protobuf/Duration$Builder;
    1048: pop
    1049: aload_0
    1050: aload         7
    1052: invokevirtual #374                // Method com/google/protobuf/Duration$Builder.buildPartial:()Lcom/google/protobuf/Duration;
    1055: putfield      #420                // Field idleTimeout_:Lcom/google/protobuf/Duration;
    1058: goto          1719
    1061: iload_3
    1062: bipush        8
    1064: iand
    1065: ifne          1084
    1068: aload_0
    1069: new           #391                // class java/util/ArrayList
    1072: dup
    1073: invokespecial #392                // Method java/util/ArrayList."<init>":()V
    1076: putfield      #279                // Field upgradeConfigs_:Ljava/util/List;
    1079: iload_3
    1080: bipush        8
    1082: ior
    1083: istore_3
    1084: aload_0
    1085: getfield      #279                // Field upgradeConfigs_:Ljava/util/List;
    1088: aload_1
    1089: invokestatic  #421                // Method io/grpc/xds/shaded/io/envoyproxy/envoy/config/route/v3/RouteAction$UpgradeConfig.parser:()Lcom/google/protobuf/Parser;
    1092: aload_2
    1093: invokevirtual #330                // Method com/google/protobuf/CodedInputStream.readMessage:(Lcom/google/protobuf/Parser;Lcom/google/protobuf/ExtensionRegistryLite;)Lcom/google/protobuf/MessageLite;
    1096: invokeinterface #401,  2          // InterfaceMethod java/util/List.add:(Ljava/lang/Object;)Z
    1101: pop
    1102: goto          1719
    1105: aload_1
    1106: invokevirtual #389                // Method com/google/protobuf/CodedInputStream.readEnum:()I
    1109: istore        7
    1111: aload_0
    1112: iload         7
    1114: putfield      #281                // Field internalRedirectAction_:I
    1117: goto          1719
    1120: aconst_null
    1121: astore        7
    1123: aload_0
    1124: getfield      #423                // Field hedgePolicy_:Lio/grpc/xds/shaded/io/envoyproxy/envoy/config/route/v3/HedgePolicy;
    1127: ifnull        1139
    1130: aload_0
    1131: getfield      #423                // Field hedgePolicy_:Lio/grpc/xds/shaded/io/envoyproxy/envoy/config/route/v3/HedgePolicy;
    1134: invokevirtual #426                // Method io/grpc/xds/shaded/io/envoyproxy/envoy/config/route/v3/HedgePolicy.toBuilder:()Lio/grpc/xds/shaded/io/envoyproxy/envoy/config/route/v3/HedgePolicy$Builder;
    1137: astore        7
    1139: aload_0
    1140: aload_1
    1141: invokestatic  #427                // Method io/grpc/xds/shaded/io/envoyproxy/envoy/config/route/v3/HedgePolicy.parser:()Lcom/google/protobuf/Parser;
    1144: aload_2
    1145: invokevirtual #330                // Method com/google/protobuf/CodedInputStream.readMessage:(Lcom/google/protobuf/Parser;Lcom/google/protobuf/ExtensionRegistryLite;)Lcom/google/protobuf/MessageLite;
    1148: checkcast     #83                 // class io/grpc/xds/shaded/io/envoyproxy/envoy/config/route/v3/HedgePolicy
    1151: putfield      #423                // Field hedgePolicy_:Lio/grpc/xds/shaded/io/envoyproxy/envoy/config/route/v3/HedgePolicy;
    1154: aload         7
    1156: ifnull        1719
    1159: aload         7
    1161: aload_0
    1162: getfield      #423                // Field hedgePolicy_:Lio/grpc/xds/shaded/io/envoyproxy/envoy/config/route/v3/HedgePolicy;
    1165: invokevirtual #430                // Method io/grpc/xds/shaded/io/envoyproxy/envoy/config/route/v3/HedgePolicy$Builder.mergeFrom:(Lio/grpc/xds/shaded/io/envoyproxy/envoy/config/route/v3/HedgePolicy;)Lio/grpc/xds/shaded/io/envoyproxy/envoy/config/route/v3/HedgePolicy$Builder;
    1168: pop
    1169: aload_0
    1170: aload         7
    1172: invokevirtual #433                // Method io/grpc/xds/shaded/io/envoyproxy/envoy/config/route/v3/HedgePolicy$Builder.buildPartial:()Lio/grpc/xds/shaded/io/envoyproxy/envoy/config/route/v3/HedgePolicy;
    1175: putfield      #423                // Field hedgePolicy_:Lio/grpc/xds/shaded/io/envoyproxy/envoy/config/route/v3/HedgePolicy;
    1178: goto          1719
    1181: aconst_null
    1182: astore        7
    1184: aload_0
    1185: getfield      #435                // Field grpcTimeoutOffset_:Lcom/google/protobuf/Duration;
    1188: ifnull        1200
    1191: aload_0
    1192: getfield      #435                // Field grpcTimeoutOffset_:Lcom/google/protobuf/Duration;
    1195: invokevirtual #367                // Method com/google/protobuf/Duration.toBuilder:()Lcom/google/protobuf/Duration$Builder;
    1198: astore        7
    1200: aload_0
    1201: aload_1
    1202: invokestatic  #368                // Method com/google/protobuf/Duration.parser:()Lcom/google/protobuf/Parser;
    1205: aload_2
    1206: invokevirtual #330                // Method com/google/protobuf/CodedInputStream.readMessage:(Lcom/google/protobuf/Parser;Lcom/google/protobuf/ExtensionRegistryLite;)Lcom/google/protobuf/MessageLite;
    1209: checkcast     #71                 // class com/google/protobuf/Duration
    1212: putfield      #435                // Field grpcTimeoutOffset_:Lcom/google/protobuf/Duration;
    1215: aload         7
    1217: ifnull        1719
    1220: aload         7
    1222: aload_0
    1223: getfield      #435                // Field grpcTimeoutOffset_:Lcom/google/protobuf/Duration;
    1226: invokevirtual #371                // Method com/google/protobuf/Duration$Builder.mergeFrom:(Lcom/google/protobuf/Duration;)Lcom/google/protobuf/Duration$Builder;
    1229: pop
    1230: aload_0
    1231: aload         7
    1233: invokevirtual #374                // Method com/google/protobuf/Duration$Builder.buildPartial:()Lcom/google/protobuf/Duration;
    1236: putfield      #435                // Field grpcTimeoutOffset_:Lcom/google/protobuf/Duration;
    1239: goto          1719
    1242: aload_1
    1243: invokevirtual #316                // Method com/google/protobuf/CodedInputStream.readStringRequireUtf8:()Ljava/lang/String;
    1246: astore        7
    1248: aload_0
    1249: bipush        29
    1251: putfield      #248                // Field hostRewriteSpecifierCase_:I
    1254: aload_0
    1255: aload         7
    1257: putfield      #352                // Field hostRewriteSpecifier_:Ljava/lang/Object;
    1260: goto          1719
    1263: iload_3
    1264: iconst_1
    1265: iand
    1266: ifne          1284
    1269: aload_0
    1270: new           #391                // class java/util/ArrayList
    1273: dup
    1274: invokespecial #392                // Method java/util/ArrayList."<init>":()V
    1277: putfield      #271                // Field requestMirrorPolicies_:Ljava/util/List;
    1280: iload_3
    1281: iconst_1
    1282: ior
    1283: istore_3
    1284: aload_0
    1285: getfield      #271                // Field requestMirrorPolicies_:Ljava/util/List;
    1288: aload_1
    1289: invokestatic  #436                // Method io/grpc/xds/shaded/io/envoyproxy/envoy/config/route/v3/RouteAction$RequestMirrorPolicy.parser:()Lcom/google/protobuf/Parser;
    1292: aload_2
    1293: invokevirtual #330                // Method com/google/protobuf/CodedInputStream.readMessage:(Lcom/google/protobuf/Parser;Lcom/google/protobuf/ExtensionRegistryLite;)Lcom/google/protobuf/MessageLite;
    1296: invokeinterface #401,  2          // InterfaceMethod java/util/List.add:(Ljava/lang/Object;)Z
    1301: pop
    1302: goto          1719
    1305: aconst_null
    1306: astore        7
    1308: aload_0
    1309: getfield      #438                // Field maxInternalRedirects_:Lcom/google/protobuf/UInt32Value;
    1312: ifnull        1324
    1315: aload_0
    1316: getfield      #438                // Field maxInternalRedirects_:Lcom/google/protobuf/UInt32Value;
    1319: invokevirtual #441                // Method com/google/protobuf/UInt32Value.toBuilder:()Lcom/google/protobuf/UInt32Value$Builder;
    1322: astore        7
    1324: aload_0
    1325: aload_1
    1326: invokestatic  #442                // Method com/google/protobuf/UInt32Value.parser:()Lcom/google/protobuf/Parser;
    1329: aload_2
    1330: invokevirtual #330                // Method com/google/protobuf/CodedInputStream.readMessage:(Lcom/google/protobuf/Parser;Lcom/google/protobuf/ExtensionRegistryLite;)Lcom/google/protobuf/MessageLite;
    1333: checkcast     #87                 // class com/google/protobuf/UInt32Value
    1336: putfield      #438                // Field maxInternalRedirects_:Lcom/google/protobuf/UInt32Value;
    1339: aload         7
    1341: ifnull        1719
    1344: aload         7
    1346: aload_0
    1347: getfield      #438                // Field maxInternalRedirects_:Lcom/google/protobuf/UInt32Value;
    1350: invokevirtual #445                // Method com/google/protobuf/UInt32Value$Builder.mergeFrom:(Lcom/google/protobuf/UInt32Value;)Lcom/google/protobuf/UInt32Value$Builder;
    1353: pop
    1354: aload_0
    1355: aload         7
    1357: invokevirtual #448                // Method com/google/protobuf/UInt32Value$Builder.buildPartial:()Lcom/google/protobuf/UInt32Value;
    1360: putfield      #438                // Field maxInternalRedirects_:Lcom/google/protobuf/UInt32Value;
    1363: goto          1719
    1366: aconst_null
    1367: astore        7
    1369: aload_0
    1370: getfield      #450                // Field regexRewrite_:Lio/grpc/xds/shaded/io/envoyproxy/envoy/type/matcher/v3/RegexMatchAndSubstitute;
    1373: ifnull        1385
    1376: aload_0
    1377: getfield      #450                // Field regexRewrite_:Lio/grpc/xds/shaded/io/envoyproxy/envoy/type/matcher/v3/RegexMatchAndSubstitute;
    1380: invokevirtual #453                // Method io/grpc/xds/shaded/io/envoyproxy/envoy/type/matcher/v3/RegexMatchAndSubstitute.toBuilder:()Lio/grpc/xds/shaded/io/envoyproxy/envoy/type/matcher/v3/RegexMatchAndSubstitute$Builder;
    1383: astore        7
    1385: aload_0
    1386: aload_1
    1387: invokestatic  #454                // Method io/grpc/xds/shaded/io/envoyproxy/envoy/type/matcher/v3/RegexMatchAndSubstitute.parser:()Lcom/google/protobuf/Parser;
    1390: aload_2
    1391: invokevirtual #330                // Method com/google/protobuf/CodedInputStream.readMessage:(Lcom/google/protobuf/Parser;Lcom/google/protobuf/ExtensionRegistryLite;)Lcom/google/protobuf/MessageLite;
    1394: checkcast     #91                 // class io/grpc/xds/shaded/io/envoyproxy/envoy/type/matcher/v3/RegexMatchAndSubstitute
    1397: putfield      #450                // Field regexRewrite_:Lio/grpc/xds/shaded/io/envoyproxy/envoy/type/matcher/v3/RegexMatchAndSubstitute;
    1400: aload         7
    1402: ifnull        1719
    1405: aload         7
    1407: aload_0
    1408: getfield      #450                // Field regexRewrite_:Lio/grpc/xds/shaded/io/envoyproxy/envoy/type/matcher/v3/RegexMatchAndSubstitute;
    1411: invokevirtual #457                // Method io/grpc/xds/shaded/io/envoyproxy/envoy/type/matcher/v3/RegexMatchAndSubstitute$Builder.mergeFrom:(Lio/grpc/xds/shaded/io/envoyproxy/envoy/type/matcher/v3/RegexMatchAndSubstitute;)Lio/grpc/xds/shaded/io/envoyproxy/envoy/type/matcher/v3/RegexMatchAndSubstitute$Builder;
    1414: pop
    1415: aload_0
    1416: aload         7
    1418: invokevirtual #460                // Method io/grpc/xds/shaded/io/envoyproxy/envoy/type/matcher/v3/RegexMatchAndSubstitute$Builder.buildPartial:()Lio/grpc/xds/shaded/io/envoyproxy/envoy/type/matcher/v3/RegexMatchAndSubstitute;
    1421: putfield      #450                // Field regexRewrite_:Lio/grpc/xds/shaded/io/envoyproxy/envoy/type/matcher/v3/RegexMatchAndSubstitute;
    1424: goto          1719
    1427: aconst_null
    1428: astore        7
    1430: aload_0
    1431: getfield      #462                // Field retryPolicyTypedConfig_:Lcom/google/protobuf/Any;
    1434: ifnull        1446
    1437: aload_0
    1438: getfield      #462                // Field retryPolicyTypedConfig_:Lcom/google/protobuf/Any;
    1441: invokevirtual #465                // Method com/google/protobuf/Any.toBuilder:()Lcom/google/protobuf/Any$Builder;
    1444: astore        7
    1446: aload_0
    1447: aload_1
    1448: invokestatic  #466                // Method com/google/protobuf/Any.parser:()Lcom/google/protobuf/Parser;
    1451: aload_2
    1452: invokevirtual #330                // Method com/google/protobuf/CodedInputStream.readMessage:(Lcom/google/protobuf/Parser;Lcom/google/protobuf/ExtensionRegistryLite;)Lcom/google/protobuf/MessageLite;
    1455: checkcast     #95                 // class com/google/protobuf/Any
    1458: putfield      #462                // Field retryPolicyTypedConfig_:Lcom/google/protobuf/Any;
    1461: aload         7
    1463: ifnull        1719
    1466: aload         7
    1468: aload_0
    1469: getfield      #462                // Field retryPolicyTypedConfig_:Lcom/google/protobuf/Any;
    1472: invokevirtual #469                // Method com/google/protobuf/Any$Builder.mergeFrom:(Lcom/google/protobuf/Any;)Lcom/google/protobuf/Any$Builder;
    1475: pop
    1476: aload_0
    1477: aload         7
    1479: invokevirtual #472                // Method com/google/protobuf/Any$Builder.buildPartial:()Lcom/google/protobuf/Any;
    1482: putfield      #462                // Field retryPolicyTypedConfig_:Lcom/google/protobuf/Any;
    1485: goto          1719
    1488: aconst_null
    1489: astore        7
    1491: aload_0
    1492: getfield      #474                // Field internalRedirectPolicy_:Lio/grpc/xds/shaded/io/envoyproxy/envoy/config/route/v3/InternalRedirectPolicy;
    1495: ifnull        1507
    1498: aload_0
    1499: getfield      #474                // Field internalRedirectPolicy_:Lio/grpc/xds/shaded/io/envoyproxy/envoy/config/route/v3/InternalRedirectPolicy;
    1502: invokevirtual #477                // Method io/grpc/xds/shaded/io/envoyproxy/envoy/config/route/v3/InternalRedirectPolicy.toBuilder:()Lio/grpc/xds/shaded/io/envoyproxy/envoy/config/route/v3/InternalRedirectPolicy$Builder;
    1505: astore        7
    1507: aload_0
    1508: aload_1
    1509: invokestatic  #478                // Method io/grpc/xds/shaded/io/envoyproxy/envoy/config/route/v3/InternalRedirectPolicy.parser:()Lcom/google/protobuf/Parser;
    1512: aload_2
    1513: invokevirtual #330                // Method com/google/protobuf/CodedInputStream.readMessage:(Lcom/google/protobuf/Parser;Lcom/google/protobuf/ExtensionRegistryLite;)Lcom/google/protobuf/MessageLite;
    1516: checkcast     #99                 // class io/grpc/xds/shaded/io/envoyproxy/envoy/config/route/v3/InternalRedirectPolicy
    1519: putfield      #474                // Field internalRedirectPolicy_:Lio/grpc/xds/shaded/io/envoyproxy/envoy/config/route/v3/InternalRedirectPolicy;
    1522: aload         7
    1524: ifnull        1719
    1527: aload         7
    1529: aload_0
    1530: getfield      #474                // Field internalRedirectPolicy_:Lio/grpc/xds/shaded/io/envoyproxy/envoy/config/route/v3/InternalRedirectPolicy;
    1533: invokevirtual #481                // Method io/grpc/xds/shaded/io/envoyproxy/envoy/config/route/v3/InternalRedirectPolicy$Builder.mergeFrom:(Lio/grpc/xds/shaded/io/envoyproxy/envoy/config/route/v3/InternalRedirectPolicy;)Lio/grpc/xds/shaded/io/envoyproxy/envoy/config/route/v3/InternalRedirectPolicy$Builder;
    1536: pop
    1537: aload_0
    1538: aload         7
    1540: invokevirtual #484                // Method io/grpc/xds/shaded/io/envoyproxy/envoy/config/route/v3/InternalRedirectPolicy$Builder.buildPartial:()Lio/grpc/xds/shaded/io/envoyproxy/envoy/config/route/v3/InternalRedirectPolicy;
    1543: putfield      #474                // Field internalRedirectPolicy_:Lio/grpc/xds/shaded/io/envoyproxy/envoy/config/route/v3/InternalRedirectPolicy;
    1546: goto          1719
    1549: aconst_null
    1550: astore        7
    1552: aload_0
    1553: getfield      #248                // Field hostRewriteSpecifierCase_:I
    1556: bipush        35
    1558: if_icmpne     1573
    1561: aload_0
    1562: getfield      #352                // Field hostRewriteSpecifier_:Ljava/lang/Object;
    1565: checkcast     #91                 // class io/grpc/xds/shaded/io/envoyproxy/envoy/type/matcher/v3/RegexMatchAndSubstitute
    1568: invokevirtual #453                // Method io/grpc/xds/shaded/io/envoyproxy/envoy/type/matcher/v3/RegexMatchAndSubstitute.toBuilder:()Lio/grpc/xds/shaded/io/envoyproxy/envoy/type/matcher/v3/RegexMatchAndSubstitute$Builder;
    1571: astore        7
    1573: aload_0
    1574: aload_1
    1575: invokestatic  #454                // Method io/grpc/xds/shaded/io/envoyproxy/envoy/type/matcher/v3/RegexMatchAndSubstitute.parser:()Lcom/google/protobuf/Parser;
    1578: aload_2
    1579: invokevirtual #330                // Method com/google/protobuf/CodedInputStream.readMessage:(Lcom/google/protobuf/Parser;Lcom/google/protobuf/ExtensionRegistryLite;)Lcom/google/protobuf/MessageLite;
    1582: putfield      #352                // Field hostRewriteSpecifier_:Ljava/lang/Object;
    1585: aload         7
    1587: ifnull        1612
    1590: aload         7
    1592: aload_0
    1593: getfield      #352                // Field hostRewriteSpecifier_:Ljava/lang/Object;
    1596: checkcast     #91                 // class io/grpc/xds/shaded/io/envoyproxy/envoy/type/matcher/v3/RegexMatchAndSubstitute
    1599: invokevirtual #457                // Method io/grpc/xds/shaded/io/envoyproxy/envoy/type/matcher/v3/RegexMatchAndSubstitute$Builder.mergeFrom:(Lio/grpc/xds/shaded/io/envoyproxy/envoy/type/matcher/v3/RegexMatchAndSubstitute;)Lio/grpc/xds/shaded/io/envoyproxy/envoy/type/matcher/v3/RegexMatchAndSubstitute$Builder;
    1602: pop
    1603: aload_0
    1604: aload         7
    1606: invokevirtual #460                // Method io/grpc/xds/shaded/io/envoyproxy/envoy/type/matcher/v3/RegexMatchAndSubstitute$Builder.buildPartial:()Lio/grpc/xds/shaded/io/envoyproxy/envoy/type/matcher/v3/RegexMatchAndSubstitute;
    1609: putfield      #352                // Field hostRewriteSpecifier_:Ljava/lang/Object;
    1612: aload_0
    1613: bipush        35
    1615: putfield      #248                // Field hostRewriteSpecifierCase_:I
    1618: goto          1719
    1621: aconst_null
    1622: astore        7
    1624: aload_0
    1625: getfield      #486                // Field maxStreamDuration_:Lio/grpc/xds/shaded/io/envoyproxy/envoy/config/route/v3/RouteAction$MaxStreamDuration;
    1628: ifnull        1640
    1631: aload_0
    1632: getfield      #486                // Field maxStreamDuration_:Lio/grpc/xds/shaded/io/envoyproxy/envoy/config/route/v3/RouteAction$MaxStreamDuration;
    1635: invokevirtual #489                // Method io/grpc/xds/shaded/io/envoyproxy/envoy/config/route/v3/RouteAction$MaxStreamDuration.toBuilder:()Lio/grpc/xds/shaded/io/envoyproxy/envoy/config/route/v3/RouteAction$MaxStreamDuration$Builder;
    1638: astore        7
    1640: aload_0
    1641: aload_1
    1642: invokestatic  #490                // Method io/grpc/xds/shaded/io/envoyproxy/envoy/config/route/v3/RouteAction$MaxStreamDuration.parser:()Lcom/google/protobuf/Parser;
    1645: aload_2
    1646: invokevirtual #330                // Method com/google/protobuf/CodedInputStream.readMessage:(Lcom/google/protobuf/Parser;Lcom/google/protobuf/ExtensionRegistryLite;)Lcom/google/protobuf/MessageLite;
    1649: checkcast     #20                 // class io/grpc/xds/shaded/io/envoyproxy/envoy/config/route/v3/RouteAction$MaxStreamDuration
    1652: putfield      #486                // Field maxStreamDuration_:Lio/grpc/xds/shaded/io/envoyproxy/envoy/config/route/v3/RouteAction$MaxStreamDuration;
    1655: aload         7
    1657: ifnull        1719
    1660: aload         7
    1662: aload_0
    1663: getfield      #486                // Field maxStreamDuration_:Lio/grpc/xds/shaded/io/envoyproxy/envoy/config/route/v3/RouteAction$MaxStreamDuration;
    1666: invokevirtual #493                // Method io/grpc/xds/shaded/io/envoyproxy/envoy/config/route/v3/RouteAction$MaxStreamDuration$Builder.mergeFrom:(Lio/grpc/xds/shaded/io/envoyproxy/envoy/config/route/v3/RouteAction$MaxStreamDuration;)Lio/grpc/xds/shaded/io/envoyproxy/envoy/config/route/v3/RouteAction$MaxStreamDuration$Builder;
    1669: pop
    1670: aload_0
    1671: aload         7
    1673: invokevirtual #496                // Method io/grpc/xds/shaded/io/envoyproxy/envoy/config/route/v3/RouteAction$MaxStreamDuration$Builder.buildPartial:()Lio/grpc/xds/shaded/io/envoyproxy/envoy/config/route/v3/RouteAction$MaxStreamDuration;
    1676: putfield      #486                // Field maxStreamDuration_:Lio/grpc/xds/shaded/io/envoyproxy/envoy/config/route/v3/RouteAction$MaxStreamDuration;
    1679: goto          1719
    1682: aload_1
    1683: invokevirtual #316                // Method com/google/protobuf/CodedInputStream.readStringRequireUtf8:()Ljava/lang/String;
    1686: astore        7
    1688: aload_0
    1689: bipush        37
    1691: putfield      #246                // Field clusterSpecifierCase_:I
    1694: aload_0
    1695: aload         7
    1697: putfield      #318                // Field clusterSpecifier_:Ljava/lang/Object;
    1700: goto          1719
    1703: aload_0
    1704: aload_1
    1705: aload         4
    1707: aload_2
    1708: iload         6
    1710: invokevirtual #500                // Method parseUnknownField:(Lcom/google/protobuf/CodedInputStream;Lcom/google/protobuf/UnknownFieldSet$Builder;Lcom/google/protobuf/ExtensionRegistryLite;I)Z
    1713: ifne          1719
    1716: iconst_1
    1717: istore        5
    1719: goto          26
    1722: iload_3
    1723: iconst_2
    1724: iand
    1725: ifeq          1739
    1728: aload_0
    1729: aload_0
    1730: getfield      #275                // Field rateLimits_:Ljava/util/List;
    1733: invokestatic  #504                // Method java/util/Collections.unmodifiableList:(Ljava/util/List;)Ljava/util/List;
    1736: putfield      #275                // Field rateLimits_:Ljava/util/List;
    1739: iload_3
    1740: iconst_4
    1741: iand
    1742: ifeq          1756
    1745: aload_0
    1746: aload_0
    1747: getfield      #277                // Field hashPolicy_:Ljava/util/List;
    1750: invokestatic  #504                // Method java/util/Collections.unmodifiableList:(Ljava/util/List;)Ljava/util/List;
    1753: putfield      #277                // Field hashPolicy_:Ljava/util/List;
    1756: iload_3
    1757: bipush        8
    1759: iand
    1760: ifeq          1774
    1763: aload_0
    1764: aload_0
    1765: getfield      #279                // Field upgradeConfigs_:Ljava/util/List;
    1768: invokestatic  #504                // Method java/util/Collections.unmodifiableList:(Ljava/util/List;)Ljava/util/List;
    1771: putfield      #279                // Field upgradeConfigs_:Ljava/util/List;
    1774: iload_3
    1775: iconst_1
    1776: iand
    1777: ifeq          1791
    1780: aload_0
    1781: aload_0
    1782: getfield      #271                // Field requestMirrorPolicies_:Ljava/util/List;
    1785: invokestatic  #504                // Method java/util/Collections.unmodifiableList:(Ljava/util/List;)Ljava/util/List;
    1788: putfield      #271                // Field requestMirrorPolicies_:Ljava/util/List;
    1791: aload_0
    1792: aload         4
    1794: invokevirtual #507                // Method com/google/protobuf/UnknownFieldSet$Builder.build:()Lcom/google/protobuf/UnknownFieldSet;
    1797: putfield      #292                // Field unknownFields:Lcom/google/protobuf/UnknownFieldSet;
    1800: aload_0
    1801: invokevirtual #510                // Method makeExtensionsImmutable:()V
    1804: goto          1919
    1807: astore        5
    1809: aload         5
    1811: aload_0
    1812: invokevirtual #514                // Method com/google/protobuf/InvalidProtocolBufferException.setUnfinishedMessage:(Lcom/google/protobuf/MessageLite;)Lcom/google/protobuf/InvalidProtocolBufferException;
    1815: athrow
    1816: astore        5
    1818: new           #295                // class com/google/protobuf/InvalidProtocolBufferException
    1821: dup
    1822: aload         5
    1824: invokespecial #517                // Method com/google/protobuf/InvalidProtocolBufferException."<init>":(Ljava/io/IOException;)V
    1827: aload_0
    1828: invokevirtual #514                // Method com/google/protobuf/InvalidProtocolBufferException.setUnfinishedMessage:(Lcom/google/protobuf/MessageLite;)Lcom/google/protobuf/InvalidProtocolBufferException;
    1831: athrow
    1832: astore        8
    1834: iload_3
    1835: iconst_2
    1836: iand
    1837: ifeq          1851
    1840: aload_0
    1841: aload_0
    1842: getfield      #275                // Field rateLimits_:Ljava/util/List;
    1845: invokestatic  #504                // Method java/util/Collections.unmodifiableList:(Ljava/util/List;)Ljava/util/List;
    1848: putfield      #275                // Field rateLimits_:Ljava/util/List;
    1851: iload_3
    1852: iconst_4
    1853: iand
    1854: ifeq          1868
    1857: aload_0
    1858: aload_0
    1859: getfield      #277                // Field hashPolicy_:Ljava/util/List;
    1862: invokestatic  #504                // Method java/util/Collections.unmodifiableList:(Ljava/util/List;)Ljava/util/List;
    1865: putfield      #277                // Field hashPolicy_:Ljava/util/List;
    1868: iload_3
    1869: bipush        8
    1871: iand
    1872: ifeq          1886
    1875: aload_0
    1876: aload_0
    1877: getfield      #279                // Field upgradeConfigs_:Ljava/util/List;
    1880: invokestatic  #504                // Method java/util/Collections.unmodifiableList:(Ljava/util/List;)Ljava/util/List;
    1883: putfield      #279                // Field upgradeConfigs_:Ljava/util/List;
    1886: iload_3
    1887: iconst_1
    1888: iand
    1889: ifeq          1903
    1892: aload_0
    1893: aload_0
    1894: getfield      #271                // Field requestMirrorPolicies_:Ljava/util/List;
    1897: invokestatic  #504                // Method java/util/Collections.unmodifiableList:(Ljava/util/List;)Ljava/util/List;
    1900: putfield      #271                // Field requestMirrorPolicies_:Ljava/util/List;
    1903: aload_0
    1904: aload         4
    1906: invokevirtual #507                // Method com/google/protobuf/UnknownFieldSet$Builder.build:()Lcom/google/protobuf/UnknownFieldSet;
    1909: putfield      #292                // Field unknownFields:Lcom/google/protobuf/UnknownFieldSet;
    1912: aload_0
    1913: invokevirtual #510                // Method makeExtensionsImmutable:()V
    1916: aload         8
    1918: athrow
    1919: return
    Exception table:
       from    to  target type
          23  1722  1807   Class com/google/protobuf/InvalidProtocolBufferException
          23  1722  1816   Class java/io/IOException
          23  1722  1832   any
        1807  1834  1832   any

  public static final com.google.protobuf.Descriptors$Descriptor getDescriptor();
    Code:
       0: getstatic     #555                // Field io/grpc/xds/shaded/io/envoyproxy/envoy/config/route/v3/RouteComponentsProto.internal_static_envoy_config_route_v3_RouteAction_descriptor:Lcom/google/protobuf/Descriptors$Descriptor;
       3: areturn

  protected com.google.protobuf.GeneratedMessageV3$FieldAccessorTable internalGetFieldAccessorTable();
    Code:
       0: getstatic     #561                // Field io/grpc/xds/shaded/io/envoyproxy/envoy/config/route/v3/RouteComponentsProto.internal_static_envoy_config_route_v3_RouteAction_fieldAccessorTable:Lcom/google/protobuf/GeneratedMessageV3$FieldAccessorTable;
       3: ldc           #2                  // class io/grpc/xds/shaded/io/envoyproxy/envoy/config/route/v3/RouteAction
       5: ldc           #11                 // class io/grpc/xds/shaded/io/envoyproxy/envoy/config/route/v3/RouteAction$Builder
       7: invokevirtual #565                // Method com/google/protobuf/GeneratedMessageV3$FieldAccessorTable.ensureFieldAccessorsInitialized:(Ljava/lang/Class;Ljava/lang/Class;)Lcom/google/protobuf/GeneratedMessageV3$FieldAccessorTable;
      10: areturn

  public io.grpc.xds.shaded.io.envoyproxy.envoy.config.route.v3.RouteAction$ClusterSpecifierCase getClusterSpecifierCase();
    Code:
       0: aload_0
       1: getfield      #246                // Field clusterSpecifierCase_:I
       4: invokestatic  #571                // Method io/grpc/xds/shaded/io/envoyproxy/envoy/config/route/v3/RouteAction$ClusterSpecifierCase.forNumber:(I)Lio/grpc/xds/shaded/io/envoyproxy/envoy/config/route/v3/RouteAction$ClusterSpecifierCase;
       7: areturn

  public io.grpc.xds.shaded.io.envoyproxy.envoy.config.route.v3.RouteAction$HostRewriteSpecifierCase getHostRewriteSpecifierCase();
    Code:
       0: aload_0
       1: getfield      #248                // Field hostRewriteSpecifierCase_:I
       4: invokestatic  #576                // Method io/grpc/xds/shaded/io/envoyproxy/envoy/config/route/v3/RouteAction$HostRewriteSpecifierCase.forNumber:(I)Lio/grpc/xds/shaded/io/envoyproxy/envoy/config/route/v3/RouteAction$HostRewriteSpecifierCase;
       7: areturn

  public boolean hasCluster();
    Code:
       0: aload_0
       1: getfield      #246                // Field clusterSpecifierCase_:I
       4: iconst_1
       5: if_icmpne     12
       8: iconst_1
       9: goto          13
      12: iconst_0
      13: ireturn

  public java.lang.String getCluster();
    Code:
       0: ldc_w         #261                // String
       3: astore_1
       4: aload_0
       5: getfield      #246                // Field clusterSpecifierCase_:I
       8: iconst_1
       9: if_icmpne     17
      12: aload_0
      13: getfield      #318                // Field clusterSpecifier_:Ljava/lang/Object;
      16: astore_1
      17: aload_1
      18: instanceof    #583                // class java/lang/String
      21: ifeq          29
      24: aload_1
      25: checkcast     #583                // class java/lang/String
      28: areturn
      29: aload_1
      30: checkcast     #585                // class com/google/protobuf/ByteString
      33: astore_2
      34: aload_2
      35: invokevirtual #588                // Method com/google/protobuf/ByteString.toStringUtf8:()Ljava/lang/String;
      38: astore_3
      39: aload_0
      40: getfield      #246                // Field clusterSpecifierCase_:I
      43: iconst_1
      44: if_icmpne     52
      47: aload_0
      48: aload_3
      49: putfield      #318                // Field clusterSpecifier_:Ljava/lang/Object;
      52: aload_3
      53: areturn

  public com.google.protobuf.ByteString getClusterBytes();
    Code:
       0: ldc_w         #261                // String
       3: astore_1
       4: aload_0
       5: getfield      #246                // Field clusterSpecifierCase_:I
       8: iconst_1
       9: if_icmpne     17
      12: aload_0
      13: getfield      #318                // Field clusterSpecifier_:Ljava/lang/Object;
      16: astore_1
      17: aload_1
      18: instanceof    #583                // class java/lang/String
      21: ifeq          47
      24: aload_1
      25: checkcast     #583                // class java/lang/String
      28: invokestatic  #597                // Method com/google/protobuf/ByteString.copyFromUtf8:(Ljava/lang/String;)Lcom/google/protobuf/ByteString;
      31: astore_2
      32: aload_0
      33: getfield      #246                // Field clusterSpecifierCase_:I
      36: iconst_1
      37: if_icmpne     45
      40: aload_0
      41: aload_2
      42: putfield      #318                // Field clusterSpecifier_:Ljava/lang/Object;
      45: aload_2
      46: areturn
      47: aload_1
      48: checkcast     #585                // class com/google/protobuf/ByteString
      51: areturn

  public boolean hasClusterHeader();
    Code:
       0: aload_0
       1: getfield      #246                // Field clusterSpecifierCase_:I
       4: iconst_2
       5: if_icmpne     12
       8: iconst_1
       9: goto          13
      12: iconst_0
      13: ireturn

  public java.lang.String getClusterHeader();
    Code:
       0: ldc_w         #261                // String
       3: astore_1
       4: aload_0
       5: getfield      #246                // Field clusterSpecifierCase_:I
       8: iconst_2
       9: if_icmpne     17
      12: aload_0
      13: getfield      #318                // Field clusterSpecifier_:Ljava/lang/Object;
      16: astore_1
      17: aload_1
      18: instanceof    #583                // class java/lang/String
      21: ifeq          29
      24: aload_1
      25: checkcast     #583                // class java/lang/String
      28: areturn
      29: aload_1
      30: checkcast     #585                // class com/google/protobuf/ByteString
      33: astore_2
      34: aload_2
      35: invokevirtual #588                // Method com/google/protobuf/ByteString.toStringUtf8:()Ljava/lang/String;
      38: astore_3
      39: aload_0
      40: getfield      #246                // Field clusterSpecifierCase_:I
      43: iconst_2
      44: if_icmpne     52
      47: aload_0
      48: aload_3
      49: putfield      #318                // Field clusterSpecifier_:Ljava/lang/Object;
      52: aload_3
      53: areturn

  public com.google.protobuf.ByteString getClusterHeaderBytes();
    Code:
       0: ldc_w         #261                // String
       3: astore_1
       4: aload_0
       5: getfield      #246                // Field clusterSpecifierCase_:I
       8: iconst_2
       9: if_icmpne     17
      12: aload_0
      13: getfield      #318                // Field clusterSpecifier_:Ljava/lang/Object;
      16: astore_1
      17: aload_1
      18: instanceof    #583                // class java/lang/String
      21: ifeq          47
      24: aload_1
      25: checkcast     #583                // class java/lang/String
      28: invokestatic  #597                // Method com/google/protobuf/ByteString.copyFromUtf8:(Ljava/lang/String;)Lcom/google/protobuf/ByteString;
      31: astore_2
      32: aload_0
      33: getfield      #246                // Field clusterSpecifierCase_:I
      36: iconst_2
      37: if_icmpne     45
      40: aload_0
      41: aload_2
      42: putfield      #318                // Field clusterSpecifier_:Ljava/lang/Object;
      45: aload_2
      46: areturn
      47: aload_1
      48: checkcast     #585                // class com/google/protobuf/ByteString
      51: areturn

  public boolean hasWeightedClusters();
    Code:
       0: aload_0
       1: getfield      #246                // Field clusterSpecifierCase_:I
       4: iconst_3
       5: if_icmpne     12
       8: iconst_1
       9: goto          13
      12: iconst_0
      13: ireturn

  public io.grpc.xds.shaded.io.envoyproxy.envoy.config.route.v3.WeightedCluster getWeightedClusters();
    Code:
       0: aload_0
       1: getfield      #246                // Field clusterSpecifierCase_:I
       4: iconst_3
       5: if_icmpne     16
       8: aload_0
       9: getfield      #318                // Field clusterSpecifier_:Ljava/lang/Object;
      12: checkcast     #59                 // class io/grpc/xds/shaded/io/envoyproxy/envoy/config/route/v3/WeightedCluster
      15: areturn
      16: invokestatic  #606                // Method io/grpc/xds/shaded/io/envoyproxy/envoy/config/route/v3/WeightedCluster.getDefaultInstance:()Lio/grpc/xds/shaded/io/envoyproxy/envoy/config/route/v3/WeightedCluster;
      19: areturn

  public io.grpc.xds.shaded.io.envoyproxy.envoy.config.route.v3.WeightedClusterOrBuilder getWeightedClustersOrBuilder();
    Code:
       0: aload_0
       1: getfield      #246                // Field clusterSpecifierCase_:I
       4: iconst_3
       5: if_icmpne     16
       8: aload_0
       9: getfield      #318                // Field clusterSpecifier_:Ljava/lang/Object;
      12: checkcast     #59                 // class io/grpc/xds/shaded/io/envoyproxy/envoy/config/route/v3/WeightedCluster
      15: areturn
      16: invokestatic  #606                // Method io/grpc/xds/shaded/io/envoyproxy/envoy/config/route/v3/WeightedCluster.getDefaultInstance:()Lio/grpc/xds/shaded/io/envoyproxy/envoy/config/route/v3/WeightedCluster;
      19: areturn

  public boolean hasClusterSpecifierPlugin();
    Code:
       0: aload_0
       1: getfield      #246                // Field clusterSpecifierCase_:I
       4: bipush        37
       6: if_icmpne     13
       9: iconst_1
      10: goto          14
      13: iconst_0
      14: ireturn

  public java.lang.String getClusterSpecifierPlugin();
    Code:
       0: ldc_w         #261                // String
       3: astore_1
       4: aload_0
       5: getfield      #246                // Field clusterSpecifierCase_:I
       8: bipush        37
      10: if_icmpne     18
      13: aload_0
      14: getfield      #318                // Field clusterSpecifier_:Ljava/lang/Object;
      17: astore_1
      18: aload_1
      19: instanceof    #583                // class java/lang/String
      22: ifeq          30
      25: aload_1
      26: checkcast     #583                // class java/lang/String
      29: areturn
      30: aload_1
      31: checkcast     #585                // class com/google/protobuf/ByteString
      34: astore_2
      35: aload_2
      36: invokevirtual #588                // Method com/google/protobuf/ByteString.toStringUtf8:()Ljava/lang/String;
      39: astore_3
      40: aload_0
      41: getfield      #246                // Field clusterSpecifierCase_:I
      44: bipush        37
      46: if_icmpne     54
      49: aload_0
      50: aload_3
      51: putfield      #318                // Field clusterSpecifier_:Ljava/lang/Object;
      54: aload_3
      55: areturn

  public com.google.protobuf.ByteString getClusterSpecifierPluginBytes();
    Code:
       0: ldc_w         #261                // String
       3: astore_1
       4: aload_0
       5: getfield      #246                // Field clusterSpecifierCase_:I
       8: bipush        37
      10: if_icmpne     18
      13: aload_0
      14: getfield      #318                // Field clusterSpecifier_:Ljava/lang/Object;
      17: astore_1
      18: aload_1
      19: instanceof    #583                // class java/lang/String
      22: ifeq          49
      25: aload_1
      26: checkcast     #583                // class java/lang/String
      29: invokestatic  #597                // Method com/google/protobuf/ByteString.copyFromUtf8:(Ljava/lang/String;)Lcom/google/protobuf/ByteString;
      32: astore_2
      33: aload_0
      34: getfield      #246                // Field clusterSpecifierCase_:I
      37: bipush        37
      39: if_icmpne     47
      42: aload_0
      43: aload_2
      44: putfield      #318                // Field clusterSpecifier_:Ljava/lang/Object;
      47: aload_2
      48: areturn
      49: aload_1
      50: checkcast     #585                // class com/google/protobuf/ByteString
      53: areturn

  public int getClusterNotFoundResponseCodeValue();
    Code:
       0: aload_0
       1: getfield      #259                // Field clusterNotFoundResponseCode_:I
       4: ireturn

  public io.grpc.xds.shaded.io.envoyproxy.envoy.config.route.v3.RouteAction$ClusterNotFoundResponseCode getClusterNotFoundResponseCode();
    Code:
       0: aload_0
       1: getfield      #259                // Field clusterNotFoundResponseCode_:I
       4: invokestatic  #618                // Method io/grpc/xds/shaded/io/envoyproxy/envoy/config/route/v3/RouteAction$ClusterNotFoundResponseCode.valueOf:(I)Lio/grpc/xds/shaded/io/envoyproxy/envoy/config/route/v3/RouteAction$ClusterNotFoundResponseCode;
       7: astore_1
       8: aload_1
       9: ifnonnull     18
      12: getstatic     #622                // Field io/grpc/xds/shaded/io/envoyproxy/envoy/config/route/v3/RouteAction$ClusterNotFoundResponseCode.UNRECOGNIZED:Lio/grpc/xds/shaded/io/envoyproxy/envoy/config/route/v3/RouteAction$ClusterNotFoundResponseCode;
      15: goto          19
      18: aload_1
      19: areturn

  public boolean hasMetadataMatch();
    Code:
       0: aload_0
       1: getfield      #340                // Field metadataMatch_:Lio/grpc/xds/shaded/io/envoyproxy/envoy/config/core/v3/Metadata;
       4: ifnull        11
       7: iconst_1
       8: goto          12
      11: iconst_0
      12: ireturn

  public io.grpc.xds.shaded.io.envoyproxy.envoy.config.core.v3.Metadata getMetadataMatch();
    Code:
       0: aload_0
       1: getfield      #340                // Field metadataMatch_:Lio/grpc/xds/shaded/io/envoyproxy/envoy/config/core/v3/Metadata;
       4: ifnonnull     13
       7: invokestatic  #627                // Method io/grpc/xds/shaded/io/envoyproxy/envoy/config/core/v3/Metadata.getDefaultInstance:()Lio/grpc/xds/shaded/io/envoyproxy/envoy/config/core/v3/Metadata;
      10: goto          17
      13: aload_0
      14: getfield      #340                // Field metadataMatch_:Lio/grpc/xds/shaded/io/envoyproxy/envoy/config/core/v3/Metadata;
      17: areturn

  public io.grpc.xds.shaded.io.envoyproxy.envoy.config.core.v3.MetadataOrBuilder getMetadataMatchOrBuilder();
    Code:
       0: aload_0
       1: invokevirtual #631                // Method getMetadataMatch:()Lio/grpc/xds/shaded/io/envoyproxy/envoy/config/core/v3/Metadata;
       4: areturn

  public java.lang.String getPrefixRewrite();
    Code:
       0: aload_0
       1: getfield      #263                // Field prefixRewrite_:Ljava/lang/Object;
       4: astore_1
       5: aload_1
       6: instanceof    #583                // class java/lang/String
       9: ifeq          17
      12: aload_1
      13: checkcast     #583                // class java/lang/String
      16: areturn
      17: aload_1
      18: checkcast     #585                // class com/google/protobuf/ByteString
      21: astore_2
      22: aload_2
      23: invokevirtual #588                // Method com/google/protobuf/ByteString.toStringUtf8:()Ljava/lang/String;
      26: astore_3
      27: aload_0
      28: aload_3
      29: putfield      #263                // Field prefixRewrite_:Ljava/lang/Object;
      32: aload_3
      33: areturn

  public com.google.protobuf.ByteString getPrefixRewriteBytes();
    Code:
       0: aload_0
       1: getfield      #263                // Field prefixRewrite_:Ljava/lang/Object;
       4: astore_1
       5: aload_1
       6: instanceof    #583                // class java/lang/String
       9: ifeq          27
      12: aload_1
      13: checkcast     #583                // class java/lang/String
      16: invokestatic  #597                // Method com/google/protobuf/ByteString.copyFromUtf8:(Ljava/lang/String;)Lcom/google/protobuf/ByteString;
      19: astore_2
      20: aload_0
      21: aload_2
      22: putfield      #263                // Field prefixRewrite_:Ljava/lang/Object;
      25: aload_2
      26: areturn
      27: aload_1
      28: checkcast     #585                // class com/google/protobuf/ByteString
      31: areturn

  public boolean hasRegexRewrite();
    Code:
       0: aload_0
       1: getfield      #450                // Field regexRewrite_:Lio/grpc/xds/shaded/io/envoyproxy/envoy/type/matcher/v3/RegexMatchAndSubstitute;
       4: ifnull        11
       7: iconst_1
       8: goto          12
      11: iconst_0
      12: ireturn

  public io.grpc.xds.shaded.io.envoyproxy.envoy.type.matcher.v3.RegexMatchAndSubstitute getRegexRewrite();
    Code:
       0: aload_0
       1: getfield      #450                // Field regexRewrite_:Lio/grpc/xds/shaded/io/envoyproxy/envoy/type/matcher/v3/RegexMatchAndSubstitute;
       4: ifnonnull     13
       7: invokestatic  #637                // Method io/grpc/xds/shaded/io/envoyproxy/envoy/type/matcher/v3/RegexMatchAndSubstitute.getDefaultInstance:()Lio/grpc/xds/shaded/io/envoyproxy/envoy/type/matcher/v3/RegexMatchAndSubstitute;
      10: goto          17
      13: aload_0
      14: getfield      #450                // Field regexRewrite_:Lio/grpc/xds/shaded/io/envoyproxy/envoy/type/matcher/v3/RegexMatchAndSubstitute;
      17: areturn

  public io.grpc.xds.shaded.io.envoyproxy.envoy.type.matcher.v3.RegexMatchAndSubstituteOrBuilder getRegexRewriteOrBuilder();
    Code:
       0: aload_0
       1: invokevirtual #641                // Method getRegexRewrite:()Lio/grpc/xds/shaded/io/envoyproxy/envoy/type/matcher/v3/RegexMatchAndSubstitute;
       4: areturn

  public boolean hasHostRewriteLiteral();
    Code:
       0: aload_0
       1: getfield      #248                // Field hostRewriteSpecifierCase_:I
       4: bipush        6
       6: if_icmpne     13
       9: iconst_1
      10: goto          14
      13: iconst_0
      14: ireturn

  public java.lang.String getHostRewriteLiteral();
    Code:
       0: ldc_w         #261                // String
       3: astore_1
       4: aload_0
       5: getfield      #248                // Field hostRewriteSpecifierCase_:I
       8: bipush        6
      10: if_icmpne     18
      13: aload_0
      14: getfield      #352                // Field hostRewriteSpecifier_:Ljava/lang/Object;
      17: astore_1
      18: aload_1
      19: instanceof    #583                // class java/lang/String
      22: ifeq          30
      25: aload_1
      26: checkcast     #583                // class java/lang/String
      29: areturn
      30: aload_1
      31: checkcast     #585                // class com/google/protobuf/ByteString
      34: astore_2
      35: aload_2
      36: invokevirtual #588                // Method com/google/protobuf/ByteString.toStringUtf8:()Ljava/lang/String;
      39: astore_3
      40: aload_0
      41: getfield      #248                // Field hostRewriteSpecifierCase_:I
      44: bipush        6
      46: if_icmpne     54
      49: aload_0
      50: aload_3
      51: putfield      #352                // Field hostRewriteSpecifier_:Ljava/lang/Object;
      54: aload_3
      55: areturn

  public com.google.protobuf.ByteString getHostRewriteLiteralBytes();
    Code:
       0: ldc_w         #261                // String
       3: astore_1
       4: aload_0
       5: getfield      #248                // Field hostRewriteSpecifierCase_:I
       8: bipush        6
      10: if_icmpne     18
      13: aload_0
      14: getfield      #352                // Field hostRewriteSpecifier_:Ljava/lang/Object;
      17: astore_1
      18: aload_1
      19: instanceof    #583                // class java/lang/String
      22: ifeq          49
      25: aload_1
      26: checkcast     #583                // class java/lang/String
      29: invokestatic  #597                // Method com/google/protobuf/ByteString.copyFromUtf8:(Ljava/lang/String;)Lcom/google/protobuf/ByteString;
      32: astore_2
      33: aload_0
      34: getfield      #248                // Field hostRewriteSpecifierCase_:I
      37: bipush        6
      39: if_icmpne     47
      42: aload_0
      43: aload_2
      44: putfield      #352                // Field hostRewriteSpecifier_:Ljava/lang/Object;
      47: aload_2
      48: areturn
      49: aload_1
      50: checkcast     #585                // class com/google/protobuf/ByteString
      53: areturn

  public boolean hasAutoHostRewrite();
    Code:
       0: aload_0
       1: getfield      #248                // Field hostRewriteSpecifierCase_:I
       4: bipush        7
       6: if_icmpne     13
       9: iconst_1
      10: goto          14
      13: iconst_0
      14: ireturn

  public com.google.protobuf.BoolValue getAutoHostRewrite();
    Code:
       0: aload_0
       1: getfield      #248                // Field hostRewriteSpecifierCase_:I
       4: bipush        7
       6: if_icmpne     17
       9: aload_0
      10: getfield      #352                // Field hostRewriteSpecifier_:Ljava/lang/Object;
      13: checkcast     #67                 // class com/google/protobuf/BoolValue
      16: areturn
      17: invokestatic  #648                // Method com/google/protobuf/BoolValue.getDefaultInstance:()Lcom/google/protobuf/BoolValue;
      20: areturn

  public com.google.protobuf.BoolValueOrBuilder getAutoHostRewriteOrBuilder();
    Code:
       0: aload_0
       1: getfield      #248                // Field hostRewriteSpecifierCase_:I
       4: bipush        7
       6: if_icmpne     17
       9: aload_0
      10: getfield      #352                // Field hostRewriteSpecifier_:Ljava/lang/Object;
      13: checkcast     #67                 // class com/google/protobuf/BoolValue
      16: areturn
      17: invokestatic  #648                // Method com/google/protobuf/BoolValue.getDefaultInstance:()Lcom/google/protobuf/BoolValue;
      20: areturn

  public boolean hasHostRewriteHeader();
    Code:
       0: aload_0
       1: getfield      #248                // Field hostRewriteSpecifierCase_:I
       4: bipush        29
       6: if_icmpne     13
       9: iconst_1
      10: goto          14
      13: iconst_0
      14: ireturn

  public java.lang.String getHostRewriteHeader();
    Code:
       0: ldc_w         #261                // String
       3: astore_1
       4: aload_0
       5: getfield      #248                // Field hostRewriteSpecifierCase_:I
       8: bipush        29
      10: if_icmpne     18
      13: aload_0
      14: getfield      #352                // Field hostRewriteSpecifier_:Ljava/lang/Object;
      17: astore_1
      18: aload_1
      19: instanceof    #583                // class java/lang/String
      22: ifeq          30
      25: aload_1
      26: checkcast     #583                // class java/lang/String
      29: areturn
      30: aload_1
      31: checkcast     #585                // class com/google/protobuf/ByteString
      34: astore_2
      35: aload_2
      36: invokevirtual #588                // Method com/google/protobuf/ByteString.toStringUtf8:()Ljava/lang/String;
      39: astore_3
      40: aload_0
      41: getfield      #248                // Field hostRewriteSpecifierCase_:I
      44: bipush        29
      46: if_icmpne     54
      49: aload_0
      50: aload_3
      51: putfield      #352                // Field hostRewriteSpecifier_:Ljava/lang/Object;
      54: aload_3
      55: areturn

  public com.google.protobuf.ByteString getHostRewriteHeaderBytes();
    Code:
       0: ldc_w         #261                // String
       3: astore_1
       4: aload_0
       5: getfield      #248                // Field hostRewriteSpecifierCase_:I
       8: bipush        29
      10: if_icmpne     18
      13: aload_0
      14: getfield      #352                // Field hostRewriteSpecifier_:Ljava/lang/Object;
      17: astore_1
      18: aload_1
      19: instanceof    #583                // class java/lang/String
      22: ifeq          49
      25: aload_1
      26: checkcast     #583                // class java/lang/String
      29: invokestatic  #597                // Method com/google/protobuf/ByteString.copyFromUtf8:(Ljava/lang/String;)Lcom/google/protobuf/ByteString;
      32: astore_2
      33: aload_0
      34: getfield      #248                // Field hostRewriteSpecifierCase_:I
      37: bipush        29
      39: if_icmpne     47
      42: aload_0
      43: aload_2
      44: putfield      #352                // Field hostRewriteSpecifier_:Ljava/lang/Object;
      47: aload_2
      48: areturn
      49: aload_1
      50: checkcast     #585                // class com/google/protobuf/ByteString
      53: areturn

  public boolean hasHostRewritePathRegex();
    Code:
       0: aload_0
       1: getfield      #248                // Field hostRewriteSpecifierCase_:I
       4: bipush        35
       6: if_icmpne     13
       9: iconst_1
      10: goto          14
      13: iconst_0
      14: ireturn

  public io.grpc.xds.shaded.io.envoyproxy.envoy.type.matcher.v3.RegexMatchAndSubstitute getHostRewritePathRegex();
    Code:
       0: aload_0
       1: getfield      #248                // Field hostRewriteSpecifierCase_:I
       4: bipush        35
       6: if_icmpne     17
       9: aload_0
      10: getfield      #352                // Field hostRewriteSpecifier_:Ljava/lang/Object;
      13: checkcast     #91                 // class io/grpc/xds/shaded/io/envoyproxy/envoy/type/matcher/v3/RegexMatchAndSubstitute
      16: areturn
      17: invokestatic  #637                // Method io/grpc/xds/shaded/io/envoyproxy/envoy/type/matcher/v3/RegexMatchAndSubstitute.getDefaultInstance:()Lio/grpc/xds/shaded/io/envoyproxy/envoy/type/matcher/v3/RegexMatchAndSubstitute;
      20: areturn

  public io.grpc.xds.shaded.io.envoyproxy.envoy.type.matcher.v3.RegexMatchAndSubstituteOrBuilder getHostRewritePathRegexOrBuilder();
    Code:
       0: aload_0
       1: getfield      #248                // Field hostRewriteSpecifierCase_:I
       4: bipush        35
       6: if_icmpne     17
       9: aload_0
      10: getfield      #352                // Field hostRewriteSpecifier_:Ljava/lang/Object;
      13: checkcast     #91                 // class io/grpc/xds/shaded/io/envoyproxy/envoy/type/matcher/v3/RegexMatchAndSubstitute
      16: areturn
      17: invokestatic  #637                // Method io/grpc/xds/shaded/io/envoyproxy/envoy/type/matcher/v3/RegexMatchAndSubstitute.getDefaultInstance:()Lio/grpc/xds/shaded/io/envoyproxy/envoy/type/matcher/v3/RegexMatchAndSubstitute;
      20: areturn

  public boolean hasTimeout();
    Code:
       0: aload_0
       1: getfield      #364                // Field timeout_:Lcom/google/protobuf/Duration;
       4: ifnull        11
       7: iconst_1
       8: goto          12
      11: iconst_0
      12: ireturn

  public com.google.protobuf.Duration getTimeout();
    Code:
       0: aload_0
       1: getfield      #364                // Field timeout_:Lcom/google/protobuf/Duration;
       4: ifnonnull     13
       7: invokestatic  #660                // Method com/google/protobuf/Duration.getDefaultInstance:()Lcom/google/protobuf/Duration;
      10: goto          17
      13: aload_0
      14: getfield      #364                // Field timeout_:Lcom/google/protobuf/Duration;
      17: areturn

  public com.google.protobuf.DurationOrBuilder getTimeoutOrBuilder();
    Code:
       0: aload_0
       1: invokevirtual #664                // Method getTimeout:()Lcom/google/protobuf/Duration;
       4: areturn

  public boolean hasIdleTimeout();
    Code:
       0: aload_0
       1: getfield      #420                // Field idleTimeout_:Lcom/google/protobuf/Duration;
       4: ifnull        11
       7: iconst_1
       8: goto          12
      11: iconst_0
      12: ireturn

  public com.google.protobuf.Duration getIdleTimeout();
    Code:
       0: aload_0
       1: getfield      #420                // Field idleTimeout_:Lcom/google/protobuf/Duration;
       4: ifnonnull     13
       7: invokestatic  #660                // Method com/google/protobuf/Duration.getDefaultInstance:()Lcom/google/protobuf/Duration;
      10: goto          17
      13: aload_0
      14: getfield      #420                // Field idleTimeout_:Lcom/google/protobuf/Duration;
      17: areturn

  public com.google.protobuf.DurationOrBuilder getIdleTimeoutOrBuilder();
    Code:
       0: aload_0
       1: invokevirtual #669                // Method getIdleTimeout:()Lcom/google/protobuf/Duration;
       4: areturn

  public boolean hasRetryPolicy();
    Code:
       0: aload_0
       1: getfield      #376                // Field retryPolicy_:Lio/grpc/xds/shaded/io/envoyproxy/envoy/config/route/v3/RetryPolicy;
       4: ifnull        11
       7: iconst_1
       8: goto          12
      11: iconst_0
      12: ireturn

  public io.grpc.xds.shaded.io.envoyproxy.envoy.config.route.v3.RetryPolicy getRetryPolicy();
    Code:
       0: aload_0
       1: getfield      #376                // Field retryPolicy_:Lio/grpc/xds/shaded/io/envoyproxy/envoy/config/route/v3/RetryPolicy;
       4: ifnonnull     13
       7: invokestatic  #673                // Method io/grpc/xds/shaded/io/envoyproxy/envoy/config/route/v3/RetryPolicy.getDefaultInstance:()Lio/grpc/xds/shaded/io/envoyproxy/envoy/config/route/v3/RetryPolicy;
      10: goto          17
      13: aload_0
      14: getfield      #376                // Field retryPolicy_:Lio/grpc/xds/shaded/io/envoyproxy/envoy/config/route/v3/RetryPolicy;
      17: areturn

  public io.grpc.xds.shaded.io.envoyproxy.envoy.config.route.v3.RetryPolicyOrBuilder getRetryPolicyOrBuilder();
    Code:
       0: aload_0
       1: invokevirtual #677                // Method getRetryPolicy:()Lio/grpc/xds/shaded/io/envoyproxy/envoy/config/route/v3/RetryPolicy;
       4: areturn

  public boolean hasRetryPolicyTypedConfig();
    Code:
       0: aload_0
       1: getfield      #462                // Field retryPolicyTypedConfig_:Lcom/google/protobuf/Any;
       4: ifnull        11
       7: iconst_1
       8: goto          12
      11: iconst_0
      12: ireturn

  public com.google.protobuf.Any getRetryPolicyTypedConfig();
    Code:
       0: aload_0
       1: getfield      #462                // Field retryPolicyTypedConfig_:Lcom/google/protobuf/Any;
       4: ifnonnull     13
       7: invokestatic  #681                // Method com/google/protobuf/Any.getDefaultInstance:()Lcom/google/protobuf/Any;
      10: goto          17
      13: aload_0
      14: getfield      #462                // Field retryPolicyTypedConfig_:Lcom/google/protobuf/Any;
      17: areturn

  public com.google.protobuf.AnyOrBuilder getRetryPolicyTypedConfigOrBuilder();
    Code:
       0: aload_0
       1: invokevirtual #685                // Method getRetryPolicyTypedConfig:()Lcom/google/protobuf/Any;
       4: areturn

  public java.util.List<io.grpc.xds.shaded.io.envoyproxy.envoy.config.route.v3.RouteAction$RequestMirrorPolicy> getRequestMirrorPoliciesList();
    Code:
       0: aload_0
       1: getfield      #271                // Field requestMirrorPolicies_:Ljava/util/List;
       4: areturn

  public java.util.List<? extends io.grpc.xds.shaded.io.envoyproxy.envoy.config.route.v3.RouteAction$RequestMirrorPolicyOrBuilder> getRequestMirrorPoliciesOrBuilderList();
    Code:
       0: aload_0
       1: getfield      #271                // Field requestMirrorPolicies_:Ljava/util/List;
       4: areturn

  public int getRequestMirrorPoliciesCount();
    Code:
       0: aload_0
       1: getfield      #271                // Field requestMirrorPolicies_:Ljava/util/List;
       4: invokeinterface #693,  1          // InterfaceMethod java/util/List.size:()I
       9: ireturn

  public io.grpc.xds.shaded.io.envoyproxy.envoy.config.route.v3.RouteAction$RequestMirrorPolicy getRequestMirrorPolicies(int);
    Code:
       0: aload_0
       1: getfield      #271                // Field requestMirrorPolicies_:Ljava/util/List;
       4: iload_1
       5: invokeinterface #699,  2          // InterfaceMethod java/util/List.get:(I)Ljava/lang/Object;
      10: checkcast     #38                 // class io/grpc/xds/shaded/io/envoyproxy/envoy/config/route/v3/RouteAction$RequestMirrorPolicy
      13: areturn

  public io.grpc.xds.shaded.io.envoyproxy.envoy.config.route.v3.RouteAction$RequestMirrorPolicyOrBuilder getRequestMirrorPoliciesOrBuilder(int);
    Code:
       0: aload_0
       1: getfield      #271                // Field requestMirrorPolicies_:Ljava/util/List;
       4: iload_1
       5: invokeinterface #699,  2          // InterfaceMethod java/util/List.get:(I)Ljava/lang/Object;
      10: checkcast     #41                 // class io/grpc/xds/shaded/io/envoyproxy/envoy/config/route/v3/RouteAction$RequestMirrorPolicyOrBuilder
      13: areturn

  public int getPriorityValue();
    Code:
       0: aload_0
       1: getfield      #273                // Field priority_:I
       4: ireturn

  public io.grpc.xds.shaded.io.envoyproxy.envoy.config.core.v3.RoutingPriority getPriority();
    Code:
       0: aload_0
       1: getfield      #273                // Field priority_:I
       4: invokestatic  #710                // Method io/grpc/xds/shaded/io/envoyproxy/envoy/config/core/v3/RoutingPriority.valueOf:(I)Lio/grpc/xds/shaded/io/envoyproxy/envoy/config/core/v3/RoutingPriority;
       7: astore_1
       8: aload_1
       9: ifnonnull     18
      12: getstatic     #713                // Field io/grpc/xds/shaded/io/envoyproxy/envoy/config/core/v3/RoutingPriority.UNRECOGNIZED:Lio/grpc/xds/shaded/io/envoyproxy/envoy/config/core/v3/RoutingPriority;
      15: goto          19
      18: aload_1
      19: areturn

  public java.util.List<io.grpc.xds.shaded.io.envoyproxy.envoy.config.route.v3.RateLimit> getRateLimitsList();
    Code:
       0: aload_0
       1: getfield      #275                // Field rateLimits_:Ljava/util/List;
       4: areturn

  public java.util.List<? extends io.grpc.xds.shaded.io.envoyproxy.envoy.config.route.v3.RateLimitOrBuilder> getRateLimitsOrBuilderList();
    Code:
       0: aload_0
       1: getfield      #275                // Field rateLimits_:Ljava/util/List;
       4: areturn

  public int getRateLimitsCount();
    Code:
       0: aload_0
       1: getfield      #275                // Field rateLimits_:Ljava/util/List;
       4: invokeinterface #693,  1          // InterfaceMethod java/util/List.size:()I
       9: ireturn

  public io.grpc.xds.shaded.io.envoyproxy.envoy.config.route.v3.RateLimit getRateLimits(int);
    Code:
       0: aload_0
       1: getfield      #275                // Field rateLimits_:Ljava/util/List;
       4: iload_1
       5: invokeinterface #699,  2          // InterfaceMethod java/util/List.get:(I)Ljava/lang/Object;
      10: checkcast     #394                // class io/grpc/xds/shaded/io/envoyproxy/envoy/config/route/v3/RateLimit
      13: areturn

  public io.grpc.xds.shaded.io.envoyproxy.envoy.config.route.v3.RateLimitOrBuilder getRateLimitsOrBuilder(int);
    Code:
       0: aload_0
       1: getfield      #275                // Field rateLimits_:Ljava/util/List;
       4: iload_1
       5: invokeinterface #699,  2          // InterfaceMethod java/util/List.get:(I)Ljava/lang/Object;
      10: checkcast     #724                // class io/grpc/xds/shaded/io/envoyproxy/envoy/config/route/v3/RateLimitOrBuilder
      13: areturn

  public boolean hasIncludeVhRateLimits();
    Code:
       0: aload_0
       1: getfield      #403                // Field includeVhRateLimits_:Lcom/google/protobuf/BoolValue;
       4: ifnull        11
       7: iconst_1
       8: goto          12
      11: iconst_0
      12: ireturn

  public com.google.protobuf.BoolValue getIncludeVhRateLimits();
    Code:
       0: aload_0
       1: getfield      #403                // Field includeVhRateLimits_:Lcom/google/protobuf/BoolValue;
       4: ifnonnull     13
       7: invokestatic  #648                // Method com/google/protobuf/BoolValue.getDefaultInstance:()Lcom/google/protobuf/BoolValue;
      10: goto          17
      13: aload_0
      14: getfield      #403                // Field includeVhRateLimits_:Lcom/google/protobuf/BoolValue;
      17: areturn

  public com.google.protobuf.BoolValueOrBuilder getIncludeVhRateLimitsOrBuilder();
    Code:
       0: aload_0
       1: invokevirtual #730                // Method getIncludeVhRateLimits:()Lcom/google/protobuf/BoolValue;
       4: areturn

  public java.util.List<io.grpc.xds.shaded.io.envoyproxy.envoy.config.route.v3.RouteAction$HashPolicy> getHashPolicyList();
    Code:
       0: aload_0
       1: getfield      #277                // Field hashPolicy_:Ljava/util/List;
       4: areturn

  public java.util.List<? extends io.grpc.xds.shaded.io.envoyproxy.envoy.config.route.v3.RouteAction$HashPolicyOrBuilder> getHashPolicyOrBuilderList();
    Code:
       0: aload_0
       1: getfield      #277                // Field hashPolicy_:Ljava/util/List;
       4: areturn

  public int getHashPolicyCount();
    Code:
       0: aload_0
       1: getfield      #277                // Field hashPolicy_:Ljava/util/List;
       4: invokeinterface #693,  1          // InterfaceMethod java/util/List.size:()I
       9: ireturn

  public io.grpc.xds.shaded.io.envoyproxy.envoy.config.route.v3.RouteAction$HashPolicy getHashPolicy(int);
    Code:
       0: aload_0
       1: getfield      #277                // Field hashPolicy_:Ljava/util/List;
       4: iload_1
       5: invokeinterface #699,  2          // InterfaceMethod java/util/List.get:(I)Ljava/lang/Object;
      10: checkcast     #32                 // class io/grpc/xds/shaded/io/envoyproxy/envoy/config/route/v3/RouteAction$HashPolicy
      13: areturn

  public io.grpc.xds.shaded.io.envoyproxy.envoy.config.route.v3.RouteAction$HashPolicyOrBuilder getHashPolicyOrBuilder(int);
    Code:
       0: aload_0
       1: getfield      #277                // Field hashPolicy_:Ljava/util/List;
       4: iload_1
       5: invokeinterface #699,  2          // InterfaceMethod java/util/List.get:(I)Ljava/lang/Object;
      10: checkcast     #35                 // class io/grpc/xds/shaded/io/envoyproxy/envoy/config/route/v3/RouteAction$HashPolicyOrBuilder
      13: areturn

  public boolean hasCors();
    Code:
       0: aload_0
       1: getfield      #406                // Field cors_:Lio/grpc/xds/shaded/io/envoyproxy/envoy/config/route/v3/CorsPolicy;
       4: ifnull        11
       7: iconst_1
       8: goto          12
      11: iconst_0
      12: ireturn

  public io.grpc.xds.shaded.io.envoyproxy.envoy.config.route.v3.CorsPolicy getCors();
    Code:
       0: aload_0
       1: getfield      #406                // Field cors_:Lio/grpc/xds/shaded/io/envoyproxy/envoy/config/route/v3/CorsPolicy;
       4: ifnonnull     13
       7: invokestatic  #743                // Method io/grpc/xds/shaded/io/envoyproxy/envoy/config/route/v3/CorsPolicy.getDefaultInstance:()Lio/grpc/xds/shaded/io/envoyproxy/envoy/config/route/v3/CorsPolicy;
      10: goto          17
      13: aload_0
      14: getfield      #406                // Field cors_:Lio/grpc/xds/shaded/io/envoyproxy/envoy/config/route/v3/CorsPolicy;
      17: areturn

  public io.grpc.xds.shaded.io.envoyproxy.envoy.config.route.v3.CorsPolicyOrBuilder getCorsOrBuilder();
    Code:
       0: aload_0
       1: invokevirtual #747                // Method getCors:()Lio/grpc/xds/shaded/io/envoyproxy/envoy/config/route/v3/CorsPolicy;
       4: areturn

  public boolean hasMaxGrpcTimeout();
    Code:
       0: aload_0
       1: getfield      #418                // Field maxGrpcTimeout_:Lcom/google/protobuf/Duration;
       4: ifnull        11
       7: iconst_1
       8: goto          12
      11: iconst_0
      12: ireturn

  public com.google.protobuf.Duration getMaxGrpcTimeout();
    Code:
       0: aload_0
       1: getfield      #418                // Field maxGrpcTimeout_:Lcom/google/protobuf/Duration;
       4: ifnonnull     13
       7: invokestatic  #660                // Method com/google/protobuf/Duration.getDefaultInstance:()Lcom/google/protobuf/Duration;
      10: goto          17
      13: aload_0
      14: getfield      #418                // Field maxGrpcTimeout_:Lcom/google/protobuf/Duration;
      17: areturn

  public com.google.protobuf.DurationOrBuilder getMaxGrpcTimeoutOrBuilder();
    Code:
       0: aload_0
       1: invokevirtual #752                // Method getMaxGrpcTimeout:()Lcom/google/protobuf/Duration;
       4: areturn

  public boolean hasGrpcTimeoutOffset();
    Code:
       0: aload_0
       1: getfield      #435                // Field grpcTimeoutOffset_:Lcom/google/protobuf/Duration;
       4: ifnull        11
       7: iconst_1
       8: goto          12
      11: iconst_0
      12: ireturn

  public com.google.protobuf.Duration getGrpcTimeoutOffset();
    Code:
       0: aload_0
       1: getfield      #435                // Field grpcTimeoutOffset_:Lcom/google/protobuf/Duration;
       4: ifnonnull     13
       7: invokestatic  #660                // Method com/google/protobuf/Duration.getDefaultInstance:()Lcom/google/protobuf/Duration;
      10: goto          17
      13: aload_0
      14: getfield      #435                // Field grpcTimeoutOffset_:Lcom/google/protobuf/Duration;
      17: areturn

  public com.google.protobuf.DurationOrBuilder getGrpcTimeoutOffsetOrBuilder();
    Code:
       0: aload_0
       1: invokevirtual #757                // Method getGrpcTimeoutOffset:()Lcom/google/protobuf/Duration;
       4: areturn

  public java.util.List<io.grpc.xds.shaded.io.envoyproxy.envoy.config.route.v3.RouteAction$UpgradeConfig> getUpgradeConfigsList();
    Code:
       0: aload_0
       1: getfield      #279                // Field upgradeConfigs_:Ljava/util/List;
       4: areturn

  public java.util.List<? extends io.grpc.xds.shaded.io.envoyproxy.envoy.config.route.v3.RouteAction$UpgradeConfigOrBuilder> getUpgradeConfigsOrBuilderList();
    Code:
       0: aload_0
       1: getfield      #279                // Field upgradeConfigs_:Ljava/util/List;
       4: areturn

  public int getUpgradeConfigsCount();
    Code:
       0: aload_0
       1: getfield      #279                // Field upgradeConfigs_:Ljava/util/List;
       4: invokeinterface #693,  1          // InterfaceMethod java/util/List.size:()I
       9: ireturn

  public io.grpc.xds.shaded.io.envoyproxy.envoy.config.route.v3.RouteAction$UpgradeConfig getUpgradeConfigs(int);
    Code:
       0: aload_0
       1: getfield      #279                // Field upgradeConfigs_:Ljava/util/List;
       4: iload_1
       5: invokeinterface #699,  2          // InterfaceMethod java/util/List.get:(I)Ljava/lang/Object;
      10: checkcast     #26                 // class io/grpc/xds/shaded/io/envoyproxy/envoy/config/route/v3/RouteAction$UpgradeConfig
      13: areturn

  public io.grpc.xds.shaded.io.envoyproxy.envoy.config.route.v3.RouteAction$UpgradeConfigOrBuilder getUpgradeConfigsOrBuilder(int);
    Code:
       0: aload_0
       1: getfield      #279                // Field upgradeConfigs_:Ljava/util/List;
       4: iload_1
       5: invokeinterface #699,  2          // InterfaceMethod java/util/List.get:(I)Ljava/lang/Object;
      10: checkcast     #29                 // class io/grpc/xds/shaded/io/envoyproxy/envoy/config/route/v3/RouteAction$UpgradeConfigOrBuilder
      13: areturn

  public boolean hasInternalRedirectPolicy();
    Code:
       0: aload_0
       1: getfield      #474                // Field internalRedirectPolicy_:Lio/grpc/xds/shaded/io/envoyproxy/envoy/config/route/v3/InternalRedirectPolicy;
       4: ifnull        11
       7: iconst_1
       8: goto          12
      11: iconst_0
      12: ireturn

  public io.grpc.xds.shaded.io.envoyproxy.envoy.config.route.v3.InternalRedirectPolicy getInternalRedirectPolicy();
    Code:
       0: aload_0
       1: getfield      #474                // Field internalRedirectPolicy_:Lio/grpc/xds/shaded/io/envoyproxy/envoy/config/route/v3/InternalRedirectPolicy;
       4: ifnonnull     13
       7: invokestatic  #770                // Method io/grpc/xds/shaded/io/envoyproxy/envoy/config/route/v3/InternalRedirectPolicy.getDefaultInstance:()Lio/grpc/xds/shaded/io/envoyproxy/envoy/config/route/v3/InternalRedirectPolicy;
      10: goto          17
      13: aload_0
      14: getfield      #474                // Field internalRedirectPolicy_:Lio/grpc/xds/shaded/io/envoyproxy/envoy/config/route/v3/InternalRedirectPolicy;
      17: areturn

  public io.grpc.xds.shaded.io.envoyproxy.envoy.config.route.v3.InternalRedirectPolicyOrBuilder getInternalRedirectPolicyOrBuilder();
    Code:
       0: aload_0
       1: invokevirtual #774                // Method getInternalRedirectPolicy:()Lio/grpc/xds/shaded/io/envoyproxy/envoy/config/route/v3/InternalRedirectPolicy;
       4: areturn

  public int getInternalRedirectActionValue();
    Code:
       0: aload_0
       1: getfield      #281                // Field internalRedirectAction_:I
       4: ireturn

  public io.grpc.xds.shaded.io.envoyproxy.envoy.config.route.v3.RouteAction$InternalRedirectAction getInternalRedirectAction();
    Code:
       0: aload_0
       1: getfield      #281                // Field internalRedirectAction_:I
       4: invokestatic  #780                // Method io/grpc/xds/shaded/io/envoyproxy/envoy/config/route/v3/RouteAction$InternalRedirectAction.valueOf:(I)Lio/grpc/xds/shaded/io/envoyproxy/envoy/config/route/v3/RouteAction$InternalRedirectAction;
       7: astore_1
       8: aload_1
       9: ifnonnull     18
      12: getstatic     #783                // Field io/grpc/xds/shaded/io/envoyproxy/envoy/config/route/v3/RouteAction$InternalRedirectAction.UNRECOGNIZED:Lio/grpc/xds/shaded/io/envoyproxy/envoy/config/route/v3/RouteAction$InternalRedirectAction;
      15: goto          19
      18: aload_1
      19: areturn

  public boolean hasMaxInternalRedirects();
    Code:
       0: aload_0
       1: getfield      #438                // Field maxInternalRedirects_:Lcom/google/protobuf/UInt32Value;
       4: ifnull        11
       7: iconst_1
       8: goto          12
      11: iconst_0
      12: ireturn

  public com.google.protobuf.UInt32Value getMaxInternalRedirects();
    Code:
       0: aload_0
       1: getfield      #438                // Field maxInternalRedirects_:Lcom/google/protobuf/UInt32Value;
       4: ifnonnull     13
       7: invokestatic  #787                // Method com/google/protobuf/UInt32Value.getDefaultInstance:()Lcom/google/protobuf/UInt32Value;
      10: goto          17
      13: aload_0
      14: getfield      #438                // Field maxInternalRedirects_:Lcom/google/protobuf/UInt32Value;
      17: areturn

  public com.google.protobuf.UInt32ValueOrBuilder getMaxInternalRedirectsOrBuilder();
    Code:
       0: aload_0
       1: invokevirtual #791                // Method getMaxInternalRedirects:()Lcom/google/protobuf/UInt32Value;
       4: areturn

  public boolean hasHedgePolicy();
    Code:
       0: aload_0
       1: getfield      #423                // Field hedgePolicy_:Lio/grpc/xds/shaded/io/envoyproxy/envoy/config/route/v3/HedgePolicy;
       4: ifnull        11
       7: iconst_1
       8: goto          12
      11: iconst_0
      12: ireturn

  public io.grpc.xds.shaded.io.envoyproxy.envoy.config.route.v3.HedgePolicy getHedgePolicy();
    Code:
       0: aload_0
       1: getfield      #423                // Field hedgePolicy_:Lio/grpc/xds/shaded/io/envoyproxy/envoy/config/route/v3/HedgePolicy;
       4: ifnonnull     13
       7: invokestatic  #795                // Method io/grpc/xds/shaded/io/envoyproxy/envoy/config/route/v3/HedgePolicy.getDefaultInstance:()Lio/grpc/xds/shaded/io/envoyproxy/envoy/config/route/v3/HedgePolicy;
      10: goto          17
      13: aload_0
      14: getfield      #423                // Field hedgePolicy_:Lio/grpc/xds/shaded/io/envoyproxy/envoy/config/route/v3/HedgePolicy;
      17: areturn

  public io.grpc.xds.shaded.io.envoyproxy.envoy.config.route.v3.HedgePolicyOrBuilder getHedgePolicyOrBuilder();
    Code:
       0: aload_0
       1: invokevirtual #799                // Method getHedgePolicy:()Lio/grpc/xds/shaded/io/envoyproxy/envoy/config/route/v3/HedgePolicy;
       4: areturn

  public boolean hasMaxStreamDuration();
    Code:
       0: aload_0
       1: getfield      #486                // Field maxStreamDuration_:Lio/grpc/xds/shaded/io/envoyproxy/envoy/config/route/v3/RouteAction$MaxStreamDuration;
       4: ifnull        11
       7: iconst_1
       8: goto          12
      11: iconst_0
      12: ireturn

  public io.grpc.xds.shaded.io.envoyproxy.envoy.config.route.v3.RouteAction$MaxStreamDuration getMaxStreamDuration();
    Code:
       0: aload_0
       1: getfield      #486                // Field maxStreamDuration_:Lio/grpc/xds/shaded/io/envoyproxy/envoy/config/route/v3/RouteAction$MaxStreamDuration;
       4: ifnonnull     13
       7: invokestatic  #803                // Method io/grpc/xds/shaded/io/envoyproxy/envoy/config/route/v3/RouteAction$MaxStreamDuration.getDefaultInstance:()Lio/grpc/xds/shaded/io/envoyproxy/envoy/config/route/v3/RouteAction$MaxStreamDuration;
      10: goto          17
      13: aload_0
      14: getfield      #486                // Field maxStreamDuration_:Lio/grpc/xds/shaded/io/envoyproxy/envoy/config/route/v3/RouteAction$MaxStreamDuration;
      17: areturn

  public io.grpc.xds.shaded.io.envoyproxy.envoy.config.route.v3.RouteAction$MaxStreamDurationOrBuilder getMaxStreamDurationOrBuilder();
    Code:
       0: aload_0
       1: invokevirtual #807                // Method getMaxStreamDuration:()Lio/grpc/xds/shaded/io/envoyproxy/envoy/config/route/v3/RouteAction$MaxStreamDuration;
       4: areturn

  public final boolean isInitialized();
    Code:
       0: aload_0
       1: getfield      #250                // Field memoizedIsInitialized:B
       4: istore_1
       5: iload_1
       6: iconst_1
       7: if_icmpne     12
      10: iconst_1
      11: ireturn
      12: iload_1
      13: ifne          18
      16: iconst_0
      17: ireturn
      18: aload_0
      19: iconst_1
      20: putfield      #250                // Field memoizedIsInitialized:B
      23: iconst_1
      24: ireturn

  public void writeTo(com.google.protobuf.CodedOutputStream) throws java.io.IOException;
    Code:
       0: aload_0
       1: getfield      #246                // Field clusterSpecifierCase_:I
       4: iconst_1
       5: if_icmpne     17
       8: aload_1
       9: iconst_1
      10: aload_0
      11: getfield      #318                // Field clusterSpecifier_:Ljava/lang/Object;
      14: invokestatic  #814                // Method com/google/protobuf/GeneratedMessageV3.writeString:(Lcom/google/protobuf/CodedOutputStream;ILjava/lang/Object;)V
      17: aload_0
      18: getfield      #246                // Field clusterSpecifierCase_:I
      21: iconst_2
      22: if_icmpne     34
      25: aload_1
      26: iconst_2
      27: aload_0
      28: getfield      #318                // Field clusterSpecifier_:Ljava/lang/Object;
      31: invokestatic  #814                // Method com/google/protobuf/GeneratedMessageV3.writeString:(Lcom/google/protobuf/CodedOutputStream;ILjava/lang/Object;)V
      34: aload_0
      35: getfield      #246                // Field clusterSpecifierCase_:I
      38: iconst_3
      39: if_icmpne     54
      42: aload_1
      43: iconst_3
      44: aload_0
      45: getfield      #318                // Field clusterSpecifier_:Ljava/lang/Object;
      48: checkcast     #59                 // class io/grpc/xds/shaded/io/envoyproxy/envoy/config/route/v3/WeightedCluster
      51: invokevirtual #820                // Method com/google/protobuf/CodedOutputStream.writeMessage:(ILcom/google/protobuf/MessageLite;)V
      54: aload_0
      55: getfield      #340                // Field metadataMatch_:Lio/grpc/xds/shaded/io/envoyproxy/envoy/config/core/v3/Metadata;
      58: ifnull        70
      61: aload_1
      62: iconst_4
      63: aload_0
      64: invokevirtual #631                // Method getMetadataMatch:()Lio/grpc/xds/shaded/io/envoyproxy/envoy/config/core/v3/Metadata;
      67: invokevirtual #820                // Method com/google/protobuf/CodedOutputStream.writeMessage:(ILcom/google/protobuf/MessageLite;)V
      70: aload_0
      71: invokevirtual #822                // Method getPrefixRewriteBytes:()Lcom/google/protobuf/ByteString;
      74: invokevirtual #825                // Method com/google/protobuf/ByteString.isEmpty:()Z
      77: ifne          89
      80: aload_1
      81: iconst_5
      82: aload_0
      83: getfield      #263                // Field prefixRewrite_:Ljava/lang/Object;
      86: invokestatic  #814                // Method com/google/protobuf/GeneratedMessageV3.writeString:(Lcom/google/protobuf/CodedOutputStream;ILjava/lang/Object;)V
      89: aload_0
      90: getfield      #248                // Field hostRewriteSpecifierCase_:I
      93: bipush        6
      95: if_icmpne     108
      98: aload_1
      99: bipush        6
     101: aload_0
     102: getfield      #352                // Field hostRewriteSpecifier_:Ljava/lang/Object;
     105: invokestatic  #814                // Method com/google/protobuf/GeneratedMessageV3.writeString:(Lcom/google/protobuf/CodedOutputStream;ILjava/lang/Object;)V
     108: aload_0
     109: getfield      #248                // Field hostRewriteSpecifierCase_:I
     112: bipush        7
     114: if_icmpne     130
     117: aload_1
     118: bipush        7
     120: aload_0
     121: getfield      #352                // Field hostRewriteSpecifier_:Ljava/lang/Object;
     124: checkcast     #67                 // class com/google/protobuf/BoolValue
     127: invokevirtual #820                // Method com/google/protobuf/CodedOutputStream.writeMessage:(ILcom/google/protobuf/MessageLite;)V
     130: aload_0
     131: getfield      #364                // Field timeout_:Lcom/google/protobuf/Duration;
     134: ifnull        147
     137: aload_1
     138: bipush        8
     140: aload_0
     141: invokevirtual #664                // Method getTimeout:()Lcom/google/protobuf/Duration;
     144: invokevirtual #820                // Method com/google/protobuf/CodedOutputStream.writeMessage:(ILcom/google/protobuf/MessageLite;)V
     147: aload_0
     148: getfield      #376                // Field retryPolicy_:Lio/grpc/xds/shaded/io/envoyproxy/envoy/config/route/v3/RetryPolicy;
     151: ifnull        164
     154: aload_1
     155: bipush        9
     157: aload_0
     158: invokevirtual #677                // Method getRetryPolicy:()Lio/grpc/xds/shaded/io/envoyproxy/envoy/config/route/v3/RetryPolicy;
     161: invokevirtual #820                // Method com/google/protobuf/CodedOutputStream.writeMessage:(ILcom/google/protobuf/MessageLite;)V
     164: aload_0
     165: getfield      #273                // Field priority_:I
     168: getstatic     #828                // Field io/grpc/xds/shaded/io/envoyproxy/envoy/config/core/v3/RoutingPriority.DEFAULT:Lio/grpc/xds/shaded/io/envoyproxy/envoy/config/core/v3/RoutingPriority;
     171: invokevirtual #831                // Method io/grpc/xds/shaded/io/envoyproxy/envoy/config/core/v3/RoutingPriority.getNumber:()I
     174: if_icmpeq     187
     177: aload_1
     178: bipush        11
     180: aload_0
     181: getfield      #273                // Field priority_:I
     184: invokevirtual #835                // Method com/google/protobuf/CodedOutputStream.writeEnum:(II)V
     187: iconst_0
     188: istore_2
     189: iload_2
     190: aload_0
     191: getfield      #275                // Field rateLimits_:Ljava/util/List;
     194: invokeinterface #693,  1          // InterfaceMethod java/util/List.size:()I
     199: if_icmpge     227
     202: aload_1
     203: bipush        13
     205: aload_0
     206: getfield      #275                // Field rateLimits_:Ljava/util/List;
     209: iload_2
     210: invokeinterface #699,  2          // InterfaceMethod java/util/List.get:(I)Ljava/lang/Object;
     215: checkcast     #124                // class com/google/protobuf/MessageLite
     218: invokevirtual #820                // Method com/google/protobuf/CodedOutputStream.writeMessage:(ILcom/google/protobuf/MessageLite;)V
     221: iinc          2, 1
     224: goto          189
     227: aload_0
     228: getfield      #403                // Field includeVhRateLimits_:Lcom/google/protobuf/BoolValue;
     231: ifnull        244
     234: aload_1
     235: bipush        14
     237: aload_0
     238: invokevirtual #730                // Method getIncludeVhRateLimits:()Lcom/google/protobuf/BoolValue;
     241: invokevirtual #820                // Method com/google/protobuf/CodedOutputStream.writeMessage:(ILcom/google/protobuf/MessageLite;)V
     244: iconst_0
     245: istore_2
     246: iload_2
     247: aload_0
     248: getfield      #277                // Field hashPolicy_:Ljava/util/List;
     251: invokeinterface #693,  1          // InterfaceMethod java/util/List.size:()I
     256: if_icmpge     284
     259: aload_1
     260: bipush        15
     262: aload_0
     263: getfield      #277                // Field hashPolicy_:Ljava/util/List;
     266: iload_2
     267: invokeinterface #699,  2          // InterfaceMethod java/util/List.get:(I)Ljava/lang/Object;
     272: checkcast     #124                // class com/google/protobuf/MessageLite
     275: invokevirtual #820                // Method com/google/protobuf/CodedOutputStream.writeMessage:(ILcom/google/protobuf/MessageLite;)V
     278: iinc          2, 1
     281: goto          246
     284: aload_0
     285: getfield      #406                // Field cors_:Lio/grpc/xds/shaded/io/envoyproxy/envoy/config/route/v3/CorsPolicy;
     288: ifnull        301
     291: aload_1
     292: bipush        17
     294: aload_0
     295: invokevirtual #747                // Method getCors:()Lio/grpc/xds/shaded/io/envoyproxy/envoy/config/route/v3/CorsPolicy;
     298: invokevirtual #820                // Method com/google/protobuf/CodedOutputStream.writeMessage:(ILcom/google/protobuf/MessageLite;)V
     301: aload_0
     302: getfield      #259                // Field clusterNotFoundResponseCode_:I
     305: getstatic     #838                // Field io/grpc/xds/shaded/io/envoyproxy/envoy/config/route/v3/RouteAction$ClusterNotFoundResponseCode.SERVICE_UNAVAILABLE:Lio/grpc/xds/shaded/io/envoyproxy/envoy/config/route/v3/RouteAction$ClusterNotFoundResponseCode;
     308: invokevirtual #839                // Method io/grpc/xds/shaded/io/envoyproxy/envoy/config/route/v3/RouteAction$ClusterNotFoundResponseCode.getNumber:()I
     311: if_icmpeq     324
     314: aload_1
     315: bipush        20
     317: aload_0
     318: getfield      #259                // Field clusterNotFoundResponseCode_:I
     321: invokevirtual #835                // Method com/google/protobuf/CodedOutputStream.writeEnum:(II)V
     324: aload_0
     325: getfield      #418                // Field maxGrpcTimeout_:Lcom/google/protobuf/Duration;
     328: ifnull        341
     331: aload_1
     332: bipush        23
     334: aload_0
     335: invokevirtual #752                // Method getMaxGrpcTimeout:()Lcom/google/protobuf/Duration;
     338: invokevirtual #820                // Method com/google/protobuf/CodedOutputStream.writeMessage:(ILcom/google/protobuf/MessageLite;)V
     341: aload_0
     342: getfield      #420                // Field idleTimeout_:Lcom/google/protobuf/Duration;
     345: ifnull        358
     348: aload_1
     349: bipush        24
     351: aload_0
     352: invokevirtual #669                // Method getIdleTimeout:()Lcom/google/protobuf/Duration;
     355: invokevirtual #820                // Method com/google/protobuf/CodedOutputStream.writeMessage:(ILcom/google/protobuf/MessageLite;)V
     358: iconst_0
     359: istore_2
     360: iload_2
     361: aload_0
     362: getfield      #279                // Field upgradeConfigs_:Ljava/util/List;
     365: invokeinterface #693,  1          // InterfaceMethod java/util/List.size:()I
     370: if_icmpge     398
     373: aload_1
     374: bipush        25
     376: aload_0
     377: getfield      #279                // Field upgradeConfigs_:Ljava/util/List;
     380: iload_2
     381: invokeinterface #699,  2          // InterfaceMethod java/util/List.get:(I)Ljava/lang/Object;
     386: checkcast     #124                // class com/google/protobuf/MessageLite
     389: invokevirtual #820                // Method com/google/protobuf/CodedOutputStream.writeMessage:(ILcom/google/protobuf/MessageLite;)V
     392: iinc          2, 1
     395: goto          360
     398: aload_0
     399: getfield      #281                // Field internalRedirectAction_:I
     402: getstatic     #842                // Field io/grpc/xds/shaded/io/envoyproxy/envoy/config/route/v3/RouteAction$InternalRedirectAction.PASS_THROUGH_INTERNAL_REDIRECT:Lio/grpc/xds/shaded/io/envoyproxy/envoy/config/route/v3/RouteAction$InternalRedirectAction;
     405: invokevirtual #843                // Method io/grpc/xds/shaded/io/envoyproxy/envoy/config/route/v3/RouteAction$InternalRedirectAction.getNumber:()I
     408: if_icmpeq     421
     411: aload_1
     412: bipush        26
     414: aload_0
     415: getfield      #281                // Field internalRedirectAction_:I
     418: invokevirtual #835                // Method com/google/protobuf/CodedOutputStream.writeEnum:(II)V
     421: aload_0
     422: getfield      #423                // Field hedgePolicy_:Lio/grpc/xds/shaded/io/envoyproxy/envoy/config/route/v3/HedgePolicy;
     425: ifnull        438
     428: aload_1
     429: bipush        27
     431: aload_0
     432: invokevirtual #799                // Method getHedgePolicy:()Lio/grpc/xds/shaded/io/envoyproxy/envoy/config/route/v3/HedgePolicy;
     435: invokevirtual #820                // Method com/google/protobuf/CodedOutputStream.writeMessage:(ILcom/google/protobuf/MessageLite;)V
     438: aload_0
     439: getfield      #435                // Field grpcTimeoutOffset_:Lcom/google/protobuf/Duration;
     442: ifnull        455
     445: aload_1
     446: bipush        28
     448: aload_0
     449: invokevirtual #757                // Method getGrpcTimeoutOffset:()Lcom/google/protobuf/Duration;
     452: invokevirtual #820                // Method com/google/protobuf/CodedOutputStream.writeMessage:(ILcom/google/protobuf/MessageLite;)V
     455: aload_0
     456: getfield      #248                // Field hostRewriteSpecifierCase_:I
     459: bipush        29
     461: if_icmpne     474
     464: aload_1
     465: bipush        29
     467: aload_0
     468: getfield      #352                // Field hostRewriteSpecifier_:Ljava/lang/Object;
     471: invokestatic  #814                // Method com/google/protobuf/GeneratedMessageV3.writeString:(Lcom/google/protobuf/CodedOutputStream;ILjava/lang/Object;)V
     474: iconst_0
     475: istore_2
     476: iload_2
     477: aload_0
     478: getfield      #271                // Field requestMirrorPolicies_:Ljava/util/List;
     481: invokeinterface #693,  1          // InterfaceMethod java/util/List.size:()I
     486: if_icmpge     514
     489: aload_1
     490: bipush        30
     492: aload_0
     493: getfield      #271                // Field requestMirrorPolicies_:Ljava/util/List;
     496: iload_2
     497: invokeinterface #699,  2          // InterfaceMethod java/util/List.get:(I)Ljava/lang/Object;
     502: checkcast     #124                // class com/google/protobuf/MessageLite
     505: invokevirtual #820                // Method com/google/protobuf/CodedOutputStream.writeMessage:(ILcom/google/protobuf/MessageLite;)V
     508: iinc          2, 1
     511: goto          476
     514: aload_0
     515: getfield      #438                // Field maxInternalRedirects_:Lcom/google/protobuf/UInt32Value;
     518: ifnull        531
     521: aload_1
     522: bipush        31
     524: aload_0
     525: invokevirtual #791                // Method getMaxInternalRedirects:()Lcom/google/protobuf/UInt32Value;
     528: invokevirtual #820                // Method com/google/protobuf/CodedOutputStream.writeMessage:(ILcom/google/protobuf/MessageLite;)V
     531: aload_0
     532: getfield      #450                // Field regexRewrite_:Lio/grpc/xds/shaded/io/envoyproxy/envoy/type/matcher/v3/RegexMatchAndSubstitute;
     535: ifnull        548
     538: aload_1
     539: bipush        32
     541: aload_0
     542: invokevirtual #641                // Method getRegexRewrite:()Lio/grpc/xds/shaded/io/envoyproxy/envoy/type/matcher/v3/RegexMatchAndSubstitute;
     545: invokevirtual #820                // Method com/google/protobuf/CodedOutputStream.writeMessage:(ILcom/google/protobuf/MessageLite;)V
     548: aload_0
     549: getfield      #462                // Field retryPolicyTypedConfig_:Lcom/google/protobuf/Any;
     552: ifnull        565
     555: aload_1
     556: bipush        33
     558: aload_0
     559: invokevirtual #685                // Method getRetryPolicyTypedConfig:()Lcom/google/protobuf/Any;
     562: invokevirtual #820                // Method com/google/protobuf/CodedOutputStream.writeMessage:(ILcom/google/protobuf/MessageLite;)V
     565: aload_0
     566: getfield      #474                // Field internalRedirectPolicy_:Lio/grpc/xds/shaded/io/envoyproxy/envoy/config/route/v3/InternalRedirectPolicy;
     569: ifnull        582
     572: aload_1
     573: bipush        34
     575: aload_0
     576: invokevirtual #774                // Method getInternalRedirectPolicy:()Lio/grpc/xds/shaded/io/envoyproxy/envoy/config/route/v3/InternalRedirectPolicy;
     579: invokevirtual #820                // Method com/google/protobuf/CodedOutputStream.writeMessage:(ILcom/google/protobuf/MessageLite;)V
     582: aload_0
     583: getfield      #248                // Field hostRewriteSpecifierCase_:I
     586: bipush        35
     588: if_icmpne     604
     591: aload_1
     592: bipush        35
     594: aload_0
     595: getfield      #352                // Field hostRewriteSpecifier_:Ljava/lang/Object;
     598: checkcast     #91                 // class io/grpc/xds/shaded/io/envoyproxy/envoy/type/matcher/v3/RegexMatchAndSubstitute
     601: invokevirtual #820                // Method com/google/protobuf/CodedOutputStream.writeMessage:(ILcom/google/protobuf/MessageLite;)V
     604: aload_0
     605: getfield      #486                // Field maxStreamDuration_:Lio/grpc/xds/shaded/io/envoyproxy/envoy/config/route/v3/RouteAction$MaxStreamDuration;
     608: ifnull        621
     611: aload_1
     612: bipush        36
     614: aload_0
     615: invokevirtual #807                // Method getMaxStreamDuration:()Lio/grpc/xds/shaded/io/envoyproxy/envoy/config/route/v3/RouteAction$MaxStreamDuration;
     618: invokevirtual #820                // Method com/google/protobuf/CodedOutputStream.writeMessage:(ILcom/google/protobuf/MessageLite;)V
     621: aload_0
     622: getfield      #246                // Field clusterSpecifierCase_:I
     625: bipush        37
     627: if_icmpne     640
     630: aload_1
     631: bipush        37
     633: aload_0
     634: getfield      #318                // Field clusterSpecifier_:Ljava/lang/Object;
     637: invokestatic  #814                // Method com/google/protobuf/GeneratedMessageV3.writeString:(Lcom/google/protobuf/CodedOutputStream;ILjava/lang/Object;)V
     640: aload_0
     641: getfield      #292                // Field unknownFields:Lcom/google/protobuf/UnknownFieldSet;
     644: aload_1
     645: invokevirtual #845                // Method com/google/protobuf/UnknownFieldSet.writeTo:(Lcom/google/protobuf/CodedOutputStream;)V
     648: return

  public int getSerializedSize();
    Code:
       0: aload_0
       1: getfield      #852                // Field memoizedSize:I
       4: istore_1
       5: iload_1
       6: iconst_m1
       7: if_icmpeq     12
      10: iload_1
      11: ireturn
      12: iconst_0
      13: istore_1
      14: aload_0
      15: getfield      #246                // Field clusterSpecifierCase_:I
      18: iconst_1
      19: if_icmpne     33
      22: iload_1
      23: iconst_1
      24: aload_0
      25: getfield      #318                // Field clusterSpecifier_:Ljava/lang/Object;
      28: invokestatic  #856                // Method com/google/protobuf/GeneratedMessageV3.computeStringSize:(ILjava/lang/Object;)I
      31: iadd
      32: istore_1
      33: aload_0
      34: getfield      #246                // Field clusterSpecifierCase_:I
      37: iconst_2
      38: if_icmpne     52
      41: iload_1
      42: iconst_2
      43: aload_0
      44: getfield      #318                // Field clusterSpecifier_:Ljava/lang/Object;
      47: invokestatic  #856                // Method com/google/protobuf/GeneratedMessageV3.computeStringSize:(ILjava/lang/Object;)I
      50: iadd
      51: istore_1
      52: aload_0
      53: getfield      #246                // Field clusterSpecifierCase_:I
      56: iconst_3
      57: if_icmpne     74
      60: iload_1
      61: iconst_3
      62: aload_0
      63: getfield      #318                // Field clusterSpecifier_:Ljava/lang/Object;
      66: checkcast     #59                 // class io/grpc/xds/shaded/io/envoyproxy/envoy/config/route/v3/WeightedCluster
      69: invokestatic  #860                // Method com/google/protobuf/CodedOutputStream.computeMessageSize:(ILcom/google/protobuf/MessageLite;)I
      72: iadd
      73: istore_1
      74: aload_0
      75: getfield      #340                // Field metadataMatch_:Lio/grpc/xds/shaded/io/envoyproxy/envoy/config/core/v3/Metadata;
      78: ifnull        92
      81: iload_1
      82: iconst_4
      83: aload_0
      84: invokevirtual #631                // Method getMetadataMatch:()Lio/grpc/xds/shaded/io/envoyproxy/envoy/config/core/v3/Metadata;
      87: invokestatic  #860                // Method com/google/protobuf/CodedOutputStream.computeMessageSize:(ILcom/google/protobuf/MessageLite;)I
      90: iadd
      91: istore_1
      92: aload_0
      93: invokevirtual #822                // Method getPrefixRewriteBytes:()Lcom/google/protobuf/ByteString;
      96: invokevirtual #825                // Method com/google/protobuf/ByteString.isEmpty:()Z
      99: ifne          113
     102: iload_1
     103: iconst_5
     104: aload_0
     105: getfield      #263                // Field prefixRewrite_:Ljava/lang/Object;
     108: invokestatic  #856                // Method com/google/protobuf/GeneratedMessageV3.computeStringSize:(ILjava/lang/Object;)I
     111: iadd
     112: istore_1
     113: aload_0
     114: getfield      #248                // Field hostRewriteSpecifierCase_:I
     117: bipush        6
     119: if_icmpne     134
     122: iload_1
     123: bipush        6
     125: aload_0
     126: getfield      #352                // Field hostRewriteSpecifier_:Ljava/lang/Object;
     129: invokestatic  #856                // Method com/google/protobuf/GeneratedMessageV3.computeStringSize:(ILjava/lang/Object;)I
     132: iadd
     133: istore_1
     134: aload_0
     135: getfield      #248                // Field hostRewriteSpecifierCase_:I
     138: bipush        7
     140: if_icmpne     158
     143: iload_1
     144: bipush        7
     146: aload_0
     147: getfield      #352                // Field hostRewriteSpecifier_:Ljava/lang/Object;
     150: checkcast     #67                 // class com/google/protobuf/BoolValue
     153: invokestatic  #860                // Method com/google/protobuf/CodedOutputStream.computeMessageSize:(ILcom/google/protobuf/MessageLite;)I
     156: iadd
     157: istore_1
     158: aload_0
     159: getfield      #364                // Field timeout_:Lcom/google/protobuf/Duration;
     162: ifnull        177
     165: iload_1
     166: bipush        8
     168: aload_0
     169: invokevirtual #664                // Method getTimeout:()Lcom/google/protobuf/Duration;
     172: invokestatic  #860                // Method com/google/protobuf/CodedOutputStream.computeMessageSize:(ILcom/google/protobuf/MessageLite;)I
     175: iadd
     176: istore_1
     177: aload_0
     178: getfield      #376                // Field retryPolicy_:Lio/grpc/xds/shaded/io/envoyproxy/envoy/config/route/v3/RetryPolicy;
     181: ifnull        196
     184: iload_1
     185: bipush        9
     187: aload_0
     188: invokevirtual #677                // Method getRetryPolicy:()Lio/grpc/xds/shaded/io/envoyproxy/envoy/config/route/v3/RetryPolicy;
     191: invokestatic  #860                // Method com/google/protobuf/CodedOutputStream.computeMessageSize:(ILcom/google/protobuf/MessageLite;)I
     194: iadd
     195: istore_1
     196: aload_0
     197: getfield      #273                // Field priority_:I
     200: getstatic     #828                // Field io/grpc/xds/shaded/io/envoyproxy/envoy/config/core/v3/RoutingPriority.DEFAULT:Lio/grpc/xds/shaded/io/envoyproxy/envoy/config/core/v3/RoutingPriority;
     203: invokevirtual #831                // Method io/grpc/xds/shaded/io/envoyproxy/envoy/config/core/v3/RoutingPriority.getNumber:()I
     206: if_icmpeq     221
     209: iload_1
     210: bipush        11
     212: aload_0
     213: getfield      #273                // Field priority_:I
     216: invokestatic  #864                // Method com/google/protobuf/CodedOutputStream.computeEnumSize:(II)I
     219: iadd
     220: istore_1
     221: iconst_0
     222: istore_2
     223: iload_2
     224: aload_0
     225: getfield      #275                // Field rateLimits_:Ljava/util/List;
     228: invokeinterface #693,  1          // InterfaceMethod java/util/List.size:()I
     233: if_icmpge     263
     236: iload_1
     237: bipush        13
     239: aload_0
     240: getfield      #275                // Field rateLimits_:Ljava/util/List;
     243: iload_2
     244: invokeinterface #699,  2          // InterfaceMethod java/util/List.get:(I)Ljava/lang/Object;
     249: checkcast     #124                // class com/google/protobuf/MessageLite
     252: invokestatic  #860                // Method com/google/protobuf/CodedOutputStream.computeMessageSize:(ILcom/google/protobuf/MessageLite;)I
     255: iadd
     256: istore_1
     257: iinc          2, 1
     260: goto          223
     263: aload_0
     264: getfield      #403                // Field includeVhRateLimits_:Lcom/google/protobuf/BoolValue;
     267: ifnull        282
     270: iload_1
     271: bipush        14
     273: aload_0
     274: invokevirtual #730                // Method getIncludeVhRateLimits:()Lcom/google/protobuf/BoolValue;
     277: invokestatic  #860                // Method com/google/protobuf/CodedOutputStream.computeMessageSize:(ILcom/google/protobuf/MessageLite;)I
     280: iadd
     281: istore_1
     282: iconst_0
     283: istore_2
     284: iload_2
     285: aload_0
     286: getfield      #277                // Field hashPolicy_:Ljava/util/List;
     289: invokeinterface #693,  1          // InterfaceMethod java/util/List.size:()I
     294: if_icmpge     324
     297: iload_1
     298: bipush        15
     300: aload_0
     301: getfield      #277                // Field hashPolicy_:Ljava/util/List;
     304: iload_2
     305: invokeinterface #699,  2          // InterfaceMethod java/util/List.get:(I)Ljava/lang/Object;
     310: checkcast     #124                // class com/google/protobuf/MessageLite
     313: invokestatic  #860                // Method com/google/protobuf/CodedOutputStream.computeMessageSize:(ILcom/google/protobuf/MessageLite;)I
     316: iadd
     317: istore_1
     318: iinc          2, 1
     321: goto          284
     324: aload_0
     325: getfield      #406                // Field cors_:Lio/grpc/xds/shaded/io/envoyproxy/envoy/config/route/v3/CorsPolicy;
     328: ifnull        343
     331: iload_1
     332: bipush        17
     334: aload_0
     335: invokevirtual #747                // Method getCors:()Lio/grpc/xds/shaded/io/envoyproxy/envoy/config/route/v3/CorsPolicy;
     338: invokestatic  #860                // Method com/google/protobuf/CodedOutputStream.computeMessageSize:(ILcom/google/protobuf/MessageLite;)I
     341: iadd
     342: istore_1
     343: aload_0
     344: getfield      #259                // Field clusterNotFoundResponseCode_:I
     347: getstatic     #838                // Field io/grpc/xds/shaded/io/envoyproxy/envoy/config/route/v3/RouteAction$ClusterNotFoundResponseCode.SERVICE_UNAVAILABLE:Lio/grpc/xds/shaded/io/envoyproxy/envoy/config/route/v3/RouteAction$ClusterNotFoundResponseCode;
     350: invokevirtual #839                // Method io/grpc/xds/shaded/io/envoyproxy/envoy/config/route/v3/RouteAction$ClusterNotFoundResponseCode.getNumber:()I
     353: if_icmpeq     368
     356: iload_1
     357: bipush        20
     359: aload_0
     360: getfield      #259                // Field clusterNotFoundResponseCode_:I
     363: invokestatic  #864                // Method com/google/protobuf/CodedOutputStream.computeEnumSize:(II)I
     366: iadd
     367: istore_1
     368: aload_0
     369: getfield      #418                // Field maxGrpcTimeout_:Lcom/google/protobuf/Duration;
     372: ifnull        387
     375: iload_1
     376: bipush        23
     378: aload_0
     379: invokevirtual #752                // Method getMaxGrpcTimeout:()Lcom/google/protobuf/Duration;
     382: invokestatic  #860                // Method com/google/protobuf/CodedOutputStream.computeMessageSize:(ILcom/google/protobuf/MessageLite;)I
     385: iadd
     386: istore_1
     387: aload_0
     388: getfield      #420                // Field idleTimeout_:Lcom/google/protobuf/Duration;
     391: ifnull        406
     394: iload_1
     395: bipush        24
     397: aload_0
     398: invokevirtual #669                // Method getIdleTimeout:()Lcom/google/protobuf/Duration;
     401: invokestatic  #860                // Method com/google/protobuf/CodedOutputStream.computeMessageSize:(ILcom/google/protobuf/MessageLite;)I
     404: iadd
     405: istore_1
     406: iconst_0
     407: istore_2
     408: iload_2
     409: aload_0
     410: getfield      #279                // Field upgradeConfigs_:Ljava/util/List;
     413: invokeinterface #693,  1          // InterfaceMethod java/util/List.size:()I
     418: if_icmpge     448
     421: iload_1
     422: bipush        25
     424: aload_0
     425: getfield      #279                // Field upgradeConfigs_:Ljava/util/List;
     428: iload_2
     429: invokeinterface #699,  2          // InterfaceMethod java/util/List.get:(I)Ljava/lang/Object;
     434: checkcast     #124                // class com/google/protobuf/MessageLite
     437: invokestatic  #860                // Method com/google/protobuf/CodedOutputStream.computeMessageSize:(ILcom/google/protobuf/MessageLite;)I
     440: iadd
     441: istore_1
     442: iinc          2, 1
     445: goto          408
     448: aload_0
     449: getfield      #281                // Field internalRedirectAction_:I
     452: getstatic     #842                // Field io/grpc/xds/shaded/io/envoyproxy/envoy/config/route/v3/RouteAction$InternalRedirectAction.PASS_THROUGH_INTERNAL_REDIRECT:Lio/grpc/xds/shaded/io/envoyproxy/envoy/config/route/v3/RouteAction$InternalRedirectAction;
     455: invokevirtual #843                // Method io/grpc/xds/shaded/io/envoyproxy/envoy/config/route/v3/RouteAction$InternalRedirectAction.getNumber:()I
     458: if_icmpeq     473
     461: iload_1
     462: bipush        26
     464: aload_0
     465: getfield      #281                // Field internalRedirectAction_:I
     468: invokestatic  #864                // Method com/google/protobuf/CodedOutputStream.computeEnumSize:(II)I
     471: iadd
     472: istore_1
     473: aload_0
     474: getfield      #423                // Field hedgePolicy_:Lio/grpc/xds/shaded/io/envoyproxy/envoy/config/route/v3/HedgePolicy;
     477: ifnull        492
     480: iload_1
     481: bipush        27
     483: aload_0
     484: invokevirtual #799                // Method getHedgePolicy:()Lio/grpc/xds/shaded/io/envoyproxy/envoy/config/route/v3/HedgePolicy;
     487: invokestatic  #860                // Method com/google/protobuf/CodedOutputStream.computeMessageSize:(ILcom/google/protobuf/MessageLite;)I
     490: iadd
     491: istore_1
     492: aload_0
     493: getfield      #435                // Field grpcTimeoutOffset_:Lcom/google/protobuf/Duration;
     496: ifnull        511
     499: iload_1
     500: bipush        28
     502: aload_0
     503: invokevirtual #757                // Method getGrpcTimeoutOffset:()Lcom/google/protobuf/Duration;
     506: invokestatic  #860                // Method com/google/protobuf/CodedOutputStream.computeMessageSize:(ILcom/google/protobuf/MessageLite;)I
     509: iadd
     510: istore_1
     511: aload_0
     512: getfield      #248                // Field hostRewriteSpecifierCase_:I
     515: bipush        29
     517: if_icmpne     532
     520: iload_1
     521: bipush        29
     523: aload_0
     524: getfield      #352                // Field hostRewriteSpecifier_:Ljava/lang/Object;
     527: invokestatic  #856                // Method com/google/protobuf/GeneratedMessageV3.computeStringSize:(ILjava/lang/Object;)I
     530: iadd
     531: istore_1
     532: iconst_0
     533: istore_2
     534: iload_2
     535: aload_0
     536: getfield      #271                // Field requestMirrorPolicies_:Ljava/util/List;
     539: invokeinterface #693,  1          // InterfaceMethod java/util/List.size:()I
     544: if_icmpge     574
     547: iload_1
     548: bipush        30
     550: aload_0
     551: getfield      #271                // Field requestMirrorPolicies_:Ljava/util/List;
     554: iload_2
     555: invokeinterface #699,  2          // InterfaceMethod java/util/List.get:(I)Ljava/lang/Object;
     560: checkcast     #124                // class com/google/protobuf/MessageLite
     563: invokestatic  #860                // Method com/google/protobuf/CodedOutputStream.computeMessageSize:(ILcom/google/protobuf/MessageLite;)I
     566: iadd
     567: istore_1
     568: iinc          2, 1
     571: goto          534
     574: aload_0
     575: getfield      #438                // Field maxInternalRedirects_:Lcom/google/protobuf/UInt32Value;
     578: ifnull        593
     581: iload_1
     582: bipush        31
     584: aload_0
     585: invokevirtual #791                // Method getMaxInternalRedirects:()Lcom/google/protobuf/UInt32Value;
     588: invokestatic  #860                // Method com/google/protobuf/CodedOutputStream.computeMessageSize:(ILcom/google/protobuf/MessageLite;)I
     591: iadd
     592: istore_1
     593: aload_0
     594: getfield      #450                // Field regexRewrite_:Lio/grpc/xds/shaded/io/envoyproxy/envoy/type/matcher/v3/RegexMatchAndSubstitute;
     597: ifnull        612
     600: iload_1
     601: bipush        32
     603: aload_0
     604: invokevirtual #641                // Method getRegexRewrite:()Lio/grpc/xds/shaded/io/envoyproxy/envoy/type/matcher/v3/RegexMatchAndSubstitute;
     607: invokestatic  #860                // Method com/google/protobuf/CodedOutputStream.computeMessageSize:(ILcom/google/protobuf/MessageLite;)I
     610: iadd
     611: istore_1
     612: aload_0
     613: getfield      #462                // Field retryPolicyTypedConfig_:Lcom/google/protobuf/Any;
     616: ifnull        631
     619: iload_1
     620: bipush        33
     622: aload_0
     623: invokevirtual #685                // Method getRetryPolicyTypedConfig:()Lcom/google/protobuf/Any;
     626: invokestatic  #860                // Method com/google/protobuf/CodedOutputStream.computeMessageSize:(ILcom/google/protobuf/MessageLite;)I
     629: iadd
     630: istore_1
     631: aload_0
     632: getfield      #474                // Field internalRedirectPolicy_:Lio/grpc/xds/shaded/io/envoyproxy/envoy/config/route/v3/InternalRedirectPolicy;
     635: ifnull        650
     638: iload_1
     639: bipush        34
     641: aload_0
     642: invokevirtual #774                // Method getInternalRedirectPolicy:()Lio/grpc/xds/shaded/io/envoyproxy/envoy/config/route/v3/InternalRedirectPolicy;
     645: invokestatic  #860                // Method com/google/protobuf/CodedOutputStream.computeMessageSize:(ILcom/google/protobuf/MessageLite;)I
     648: iadd
     649: istore_1
     650: aload_0
     651: getfield      #248                // Field hostRewriteSpecifierCase_:I
     654: bipush        35
     656: if_icmpne     674
     659: iload_1
     660: bipush        35
     662: aload_0
     663: getfield      #352                // Field hostRewriteSpecifier_:Ljava/lang/Object;
     666: checkcast     #91                 // class io/grpc/xds/shaded/io/envoyproxy/envoy/type/matcher/v3/RegexMatchAndSubstitute
     669: invokestatic  #860                // Method com/google/protobuf/CodedOutputStream.computeMessageSize:(ILcom/google/protobuf/MessageLite;)I
     672: iadd
     673: istore_1
     674: aload_0
     675: getfield      #486                // Field maxStreamDuration_:Lio/grpc/xds/shaded/io/envoyproxy/envoy/config/route/v3/RouteAction$MaxStreamDuration;
     678: ifnull        693
     681: iload_1
     682: bipush        36
     684: aload_0
     685: invokevirtual #807                // Method getMaxStreamDuration:()Lio/grpc/xds/shaded/io/envoyproxy/envoy/config/route/v3/RouteAction$MaxStreamDuration;
     688: invokestatic  #860                // Method com/google/protobuf/CodedOutputStream.computeMessageSize:(ILcom/google/protobuf/MessageLite;)I
     691: iadd
     692: istore_1
     693: aload_0
     694: getfield      #246                // Field clusterSpecifierCase_:I
     697: bipush        37
     699: if_icmpne     714
     702: iload_1
     703: bipush        37
     705: aload_0
     706: getfield      #318                // Field clusterSpecifier_:Ljava/lang/Object;
     709: invokestatic  #856                // Method com/google/protobuf/GeneratedMessageV3.computeStringSize:(ILjava/lang/Object;)I
     712: iadd
     713: istore_1
     714: iload_1
     715: aload_0
     716: getfield      #292                // Field unknownFields:Lcom/google/protobuf/UnknownFieldSet;
     719: invokevirtual #866                // Method com/google/protobuf/UnknownFieldSet.getSerializedSize:()I
     722: iadd
     723: istore_1
     724: aload_0
     725: iload_1
     726: putfield      #852                // Field memoizedSize:I
     729: iload_1
     730: ireturn

  public boolean equals(java.lang.Object);
    Code:
       0: aload_1
       1: aload_0
       2: if_acmpne     7
       5: iconst_1
       6: ireturn
       7: aload_1
       8: instanceof    #2                  // class io/grpc/xds/shaded/io/envoyproxy/envoy/config/route/v3/RouteAction
      11: ifne          20
      14: aload_0
      15: aload_1
      16: invokespecial #869                // Method com/google/protobuf/GeneratedMessageV3.equals:(Ljava/lang/Object;)Z
      19: ireturn
      20: aload_1
      21: checkcast     #2                  // class io/grpc/xds/shaded/io/envoyproxy/envoy/config/route/v3/RouteAction
      24: astore_2
      25: aload_0
      26: getfield      #259                // Field clusterNotFoundResponseCode_:I
      29: aload_2
      30: getfield      #259                // Field clusterNotFoundResponseCode_:I
      33: if_icmpeq     38
      36: iconst_0
      37: ireturn
      38: aload_0
      39: invokevirtual #871                // Method hasMetadataMatch:()Z
      42: aload_2
      43: invokevirtual #871                // Method hasMetadataMatch:()Z
      46: if_icmpeq     51
      49: iconst_0
      50: ireturn
      51: aload_0
      52: invokevirtual #871                // Method hasMetadataMatch:()Z
      55: ifeq          74
      58: aload_0
      59: invokevirtual #631                // Method getMetadataMatch:()Lio/grpc/xds/shaded/io/envoyproxy/envoy/config/core/v3/Metadata;
      62: aload_2
      63: invokevirtual #631                // Method getMetadataMatch:()Lio/grpc/xds/shaded/io/envoyproxy/envoy/config/core/v3/Metadata;
      66: invokevirtual #872                // Method io/grpc/xds/shaded/io/envoyproxy/envoy/config/core/v3/Metadata.equals:(Ljava/lang/Object;)Z
      69: ifne          74
      72: iconst_0
      73: ireturn
      74: aload_0
      75: invokevirtual #874                // Method getPrefixRewrite:()Ljava/lang/String;
      78: aload_2
      79: invokevirtual #874                // Method getPrefixRewrite:()Ljava/lang/String;
      82: invokevirtual #875                // Method java/lang/String.equals:(Ljava/lang/Object;)Z
      85: ifne          90
      88: iconst_0
      89: ireturn
      90: aload_0
      91: invokevirtual #877                // Method hasRegexRewrite:()Z
      94: aload_2
      95: invokevirtual #877                // Method hasRegexRewrite:()Z
      98: if_icmpeq     103
     101: iconst_0
     102: ireturn
     103: aload_0
     104: invokevirtual #877                // Method hasRegexRewrite:()Z
     107: ifeq          126
     110: aload_0
     111: invokevirtual #641                // Method getRegexRewrite:()Lio/grpc/xds/shaded/io/envoyproxy/envoy/type/matcher/v3/RegexMatchAndSubstitute;
     114: aload_2
     115: invokevirtual #641                // Method getRegexRewrite:()Lio/grpc/xds/shaded/io/envoyproxy/envoy/type/matcher/v3/RegexMatchAndSubstitute;
     118: invokevirtual #878                // Method io/grpc/xds/shaded/io/envoyproxy/envoy/type/matcher/v3/RegexMatchAndSubstitute.equals:(Ljava/lang/Object;)Z
     121: ifne          126
     124: iconst_0
     125: ireturn
     126: aload_0
     127: invokevirtual #880                // Method hasTimeout:()Z
     130: aload_2
     131: invokevirtual #880                // Method hasTimeout:()Z
     134: if_icmpeq     139
     137: iconst_0
     138: ireturn
     139: aload_0
     140: invokevirtual #880                // Method hasTimeout:()Z
     143: ifeq          162
     146: aload_0
     147: invokevirtual #664                // Method getTimeout:()Lcom/google/protobuf/Duration;
     150: aload_2
     151: invokevirtual #664                // Method getTimeout:()Lcom/google/protobuf/Duration;
     154: invokevirtual #881                // Method com/google/protobuf/Duration.equals:(Ljava/lang/Object;)Z
     157: ifne          162
     160: iconst_0
     161: ireturn
     162: aload_0
     163: invokevirtual #883                // Method hasIdleTimeout:()Z
     166: aload_2
     167: invokevirtual #883                // Method hasIdleTimeout:()Z
     170: if_icmpeq     175
     173: iconst_0
     174: ireturn
     175: aload_0
     176: invokevirtual #883                // Method hasIdleTimeout:()Z
     179: ifeq          198
     182: aload_0
     183: invokevirtual #669                // Method getIdleTimeout:()Lcom/google/protobuf/Duration;
     186: aload_2
     187: invokevirtual #669                // Method getIdleTimeout:()Lcom/google/protobuf/Duration;
     190: invokevirtual #881                // Method com/google/protobuf/Duration.equals:(Ljava/lang/Object;)Z
     193: ifne          198
     196: iconst_0
     197: ireturn
     198: aload_0
     199: invokevirtual #885                // Method hasRetryPolicy:()Z
     202: aload_2
     203: invokevirtual #885                // Method hasRetryPolicy:()Z
     206: if_icmpeq     211
     209: iconst_0
     210: ireturn
     211: aload_0
     212: invokevirtual #885                // Method hasRetryPolicy:()Z
     215: ifeq          234
     218: aload_0
     219: invokevirtual #677                // Method getRetryPolicy:()Lio/grpc/xds/shaded/io/envoyproxy/envoy/config/route/v3/RetryPolicy;
     222: aload_2
     223: invokevirtual #677                // Method getRetryPolicy:()Lio/grpc/xds/shaded/io/envoyproxy/envoy/config/route/v3/RetryPolicy;
     226: invokevirtual #886                // Method io/grpc/xds/shaded/io/envoyproxy/envoy/config/route/v3/RetryPolicy.equals:(Ljava/lang/Object;)Z
     229: ifne          234
     232: iconst_0
     233: ireturn
     234: aload_0
     235: invokevirtual #888                // Method hasRetryPolicyTypedConfig:()Z
     238: aload_2
     239: invokevirtual #888                // Method hasRetryPolicyTypedConfig:()Z
     242: if_icmpeq     247
     245: iconst_0
     246: ireturn
     247: aload_0
     248: invokevirtual #888                // Method hasRetryPolicyTypedConfig:()Z
     251: ifeq          270
     254: aload_0
     255: invokevirtual #685                // Method getRetryPolicyTypedConfig:()Lcom/google/protobuf/Any;
     258: aload_2
     259: invokevirtual #685                // Method getRetryPolicyTypedConfig:()Lcom/google/protobuf/Any;
     262: invokevirtual #889                // Method com/google/protobuf/Any.equals:(Ljava/lang/Object;)Z
     265: ifne          270
     268: iconst_0
     269: ireturn
     270: aload_0
     271: invokevirtual #891                // Method getRequestMirrorPoliciesList:()Ljava/util/List;
     274: aload_2
     275: invokevirtual #891                // Method getRequestMirrorPoliciesList:()Ljava/util/List;
     278: invokeinterface #892,  2          // InterfaceMethod java/util/List.equals:(Ljava/lang/Object;)Z
     283: ifne          288
     286: iconst_0
     287: ireturn
     288: aload_0
     289: getfield      #273                // Field priority_:I
     292: aload_2
     293: getfield      #273                // Field priority_:I
     296: if_icmpeq     301
     299: iconst_0
     300: ireturn
     301: aload_0
     302: invokevirtual #894                // Method getRateLimitsList:()Ljava/util/List;
     305: aload_2
     306: invokevirtual #894                // Method getRateLimitsList:()Ljava/util/List;
     309: invokeinterface #892,  2          // InterfaceMethod java/util/List.equals:(Ljava/lang/Object;)Z
     314: ifne          319
     317: iconst_0
     318: ireturn
     319: aload_0
     320: invokevirtual #896                // Method hasIncludeVhRateLimits:()Z
     323: aload_2
     324: invokevirtual #896                // Method hasIncludeVhRateLimits:()Z
     327: if_icmpeq     332
     330: iconst_0
     331: ireturn
     332: aload_0
     333: invokevirtual #896                // Method hasIncludeVhRateLimits:()Z
     336: ifeq          355
     339: aload_0
     340: invokevirtual #730                // Method getIncludeVhRateLimits:()Lcom/google/protobuf/BoolValue;
     343: aload_2
     344: invokevirtual #730                // Method getIncludeVhRateLimits:()Lcom/google/protobuf/BoolValue;
     347: invokevirtual #897                // Method com/google/protobuf/BoolValue.equals:(Ljava/lang/Object;)Z
     350: ifne          355
     353: iconst_0
     354: ireturn
     355: aload_0
     356: invokevirtual #899                // Method getHashPolicyList:()Ljava/util/List;
     359: aload_2
     360: invokevirtual #899                // Method getHashPolicyList:()Ljava/util/List;
     363: invokeinterface #892,  2          // InterfaceMethod java/util/List.equals:(Ljava/lang/Object;)Z
     368: ifne          373
     371: iconst_0
     372: ireturn
     373: aload_0
     374: invokevirtual #901                // Method hasCors:()Z
     377: aload_2
     378: invokevirtual #901                // Method hasCors:()Z
     381: if_icmpeq     386
     384: iconst_0
     385: ireturn
     386: aload_0
     387: invokevirtual #901                // Method hasCors:()Z
     390: ifeq          409
     393: aload_0
     394: invokevirtual #747                // Method getCors:()Lio/grpc/xds/shaded/io/envoyproxy/envoy/config/route/v3/CorsPolicy;
     397: aload_2
     398: invokevirtual #747                // Method getCors:()Lio/grpc/xds/shaded/io/envoyproxy/envoy/config/route/v3/CorsPolicy;
     401: invokevirtual #902                // Method io/grpc/xds/shaded/io/envoyproxy/envoy/config/route/v3/CorsPolicy.equals:(Ljava/lang/Object;)Z
     404: ifne          409
     407: iconst_0
     408: ireturn
     409: aload_0
     410: invokevirtual #904                // Method hasMaxGrpcTimeout:()Z
     413: aload_2
     414: invokevirtual #904                // Method hasMaxGrpcTimeout:()Z
     417: if_icmpeq     422
     420: iconst_0
     421: ireturn
     422: aload_0
     423: invokevirtual #904                // Method hasMaxGrpcTimeout:()Z
     426: ifeq          445
     429: aload_0
     430: invokevirtual #752                // Method getMaxGrpcTimeout:()Lcom/google/protobuf/Duration;
     433: aload_2
     434: invokevirtual #752                // Method getMaxGrpcTimeout:()Lcom/google/protobuf/Duration;
     437: invokevirtual #881                // Method com/google/protobuf/Duration.equals:(Ljava/lang/Object;)Z
     440: ifne          445
     443: iconst_0
     444: ireturn
     445: aload_0
     446: invokevirtual #906                // Method hasGrpcTimeoutOffset:()Z
     449: aload_2
     450: invokevirtual #906                // Method hasGrpcTimeoutOffset:()Z
     453: if_icmpeq     458
     456: iconst_0
     457: ireturn
     458: aload_0
     459: invokevirtual #906                // Method hasGrpcTimeoutOffset:()Z
     462: ifeq          481
     465: aload_0
     466: invokevirtual #757                // Method getGrpcTimeoutOffset:()Lcom/google/protobuf/Duration;
     469: aload_2
     470: invokevirtual #757                // Method getGrpcTimeoutOffset:()Lcom/google/protobuf/Duration;
     473: invokevirtual #881                // Method com/google/protobuf/Duration.equals:(Ljava/lang/Object;)Z
     476: ifne          481
     479: iconst_0
     480: ireturn
     481: aload_0
     482: invokevirtual #908                // Method getUpgradeConfigsList:()Ljava/util/List;
     485: aload_2
     486: invokevirtual #908                // Method getUpgradeConfigsList:()Ljava/util/List;
     489: invokeinterface #892,  2          // InterfaceMethod java/util/List.equals:(Ljava/lang/Object;)Z
     494: ifne          499
     497: iconst_0
     498: ireturn
     499: aload_0
     500: invokevirtual #910                // Method hasInternalRedirectPolicy:()Z
     503: aload_2
     504: invokevirtual #910                // Method hasInternalRedirectPolicy:()Z
     507: if_icmpeq     512
     510: iconst_0
     511: ireturn
     512: aload_0
     513: invokevirtual #910                // Method hasInternalRedirectPolicy:()Z
     516: ifeq          535
     519: aload_0
     520: invokevirtual #774                // Method getInternalRedirectPolicy:()Lio/grpc/xds/shaded/io/envoyproxy/envoy/config/route/v3/InternalRedirectPolicy;
     523: aload_2
     524: invokevirtual #774                // Method getInternalRedirectPolicy:()Lio/grpc/xds/shaded/io/envoyproxy/envoy/config/route/v3/InternalRedirectPolicy;
     527: invokevirtual #911                // Method io/grpc/xds/shaded/io/envoyproxy/envoy/config/route/v3/InternalRedirectPolicy.equals:(Ljava/lang/Object;)Z
     530: ifne          535
     533: iconst_0
     534: ireturn
     535: aload_0
     536: getfield      #281                // Field internalRedirectAction_:I
     539: aload_2
     540: getfield      #281                // Field internalRedirectAction_:I
     543: if_icmpeq     548
     546: iconst_0
     547: ireturn
     548: aload_0
     549: invokevirtual #913                // Method hasMaxInternalRedirects:()Z
     552: aload_2
     553: invokevirtual #913                // Method hasMaxInternalRedirects:()Z
     556: if_icmpeq     561
     559: iconst_0
     560: ireturn
     561: aload_0
     562: invokevirtual #913                // Method hasMaxInternalRedirects:()Z
     565: ifeq          584
     568: aload_0
     569: invokevirtual #791                // Method getMaxInternalRedirects:()Lcom/google/protobuf/UInt32Value;
     572: aload_2
     573: invokevirtual #791                // Method getMaxInternalRedirects:()Lcom/google/protobuf/UInt32Value;
     576: invokevirtual #914                // Method com/google/protobuf/UInt32Value.equals:(Ljava/lang/Object;)Z
     579: ifne          584
     582: iconst_0
     583: ireturn
     584: aload_0
     585: invokevirtual #916                // Method hasHedgePolicy:()Z
     588: aload_2
     589: invokevirtual #916                // Method hasHedgePolicy:()Z
     592: if_icmpeq     597
     595: iconst_0
     596: ireturn
     597: aload_0
     598: invokevirtual #916                // Method hasHedgePolicy:()Z
     601: ifeq          620
     604: aload_0
     605: invokevirtual #799                // Method getHedgePolicy:()Lio/grpc/xds/shaded/io/envoyproxy/envoy/config/route/v3/HedgePolicy;
     608: aload_2
     609: invokevirtual #799                // Method getHedgePolicy:()Lio/grpc/xds/shaded/io/envoyproxy/envoy/config/route/v3/HedgePolicy;
     612: invokevirtual #917                // Method io/grpc/xds/shaded/io/envoyproxy/envoy/config/route/v3/HedgePolicy.equals:(Ljava/lang/Object;)Z
     615: ifne          620
     618: iconst_0
     619: ireturn
     620: aload_0
     621: invokevirtual #919                // Method hasMaxStreamDuration:()Z
     624: aload_2
     625: invokevirtual #919                // Method hasMaxStreamDuration:()Z
     628: if_icmpeq     633
     631: iconst_0
     632: ireturn
     633: aload_0
     634: invokevirtual #919                // Method hasMaxStreamDuration:()Z
     637: ifeq          656
     640: aload_0
     641: invokevirtual #807                // Method getMaxStreamDuration:()Lio/grpc/xds/shaded/io/envoyproxy/envoy/config/route/v3/RouteAction$MaxStreamDuration;
     644: aload_2
     645: invokevirtual #807                // Method getMaxStreamDuration:()Lio/grpc/xds/shaded/io/envoyproxy/envoy/config/route/v3/RouteAction$MaxStreamDuration;
     648: invokevirtual #920                // Method io/grpc/xds/shaded/io/envoyproxy/envoy/config/route/v3/RouteAction$MaxStreamDuration.equals:(Ljava/lang/Object;)Z
     651: ifne          656
     654: iconst_0
     655: ireturn
     656: aload_0
     657: invokevirtual #922                // Method getClusterSpecifierCase:()Lio/grpc/xds/shaded/io/envoyproxy/envoy/config/route/v3/RouteAction$ClusterSpecifierCase;
     660: aload_2
     661: invokevirtual #922                // Method getClusterSpecifierCase:()Lio/grpc/xds/shaded/io/envoyproxy/envoy/config/route/v3/RouteAction$ClusterSpecifierCase;
     664: invokevirtual #923                // Method io/grpc/xds/shaded/io/envoyproxy/envoy/config/route/v3/RouteAction$ClusterSpecifierCase.equals:(Ljava/lang/Object;)Z
     667: ifne          672
     670: iconst_0
     671: ireturn
     672: aload_0
     673: getfield      #246                // Field clusterSpecifierCase_:I
     676: lookupswitch  { // 5
                     0: 792
                     1: 728
                     2: 744
                     3: 760
                    37: 776
               default: 792
          }
     728: aload_0
     729: invokevirtual #925                // Method getCluster:()Ljava/lang/String;
     732: aload_2
     733: invokevirtual #925                // Method getCluster:()Ljava/lang/String;
     736: invokevirtual #875                // Method java/lang/String.equals:(Ljava/lang/Object;)Z
     739: ifne          792
     742: iconst_0
     743: ireturn
     744: aload_0
     745: invokevirtual #927                // Method getClusterHeader:()Ljava/lang/String;
     748: aload_2
     749: invokevirtual #927                // Method getClusterHeader:()Ljava/lang/String;
     752: invokevirtual #875                // Method java/lang/String.equals:(Ljava/lang/Object;)Z
     755: ifne          792
     758: iconst_0
     759: ireturn
     760: aload_0
     761: invokevirtual #929                // Method getWeightedClusters:()Lio/grpc/xds/shaded/io/envoyproxy/envoy/config/route/v3/WeightedCluster;
     764: aload_2
     765: invokevirtual #929                // Method getWeightedClusters:()Lio/grpc/xds/shaded/io/envoyproxy/envoy/config/route/v3/WeightedCluster;
     768: invokevirtual #930                // Method io/grpc/xds/shaded/io/envoyproxy/envoy/config/route/v3/WeightedCluster.equals:(Ljava/lang/Object;)Z
     771: ifne          792
     774: iconst_0
     775: ireturn
     776: aload_0
     777: invokevirtual #932                // Method getClusterSpecifierPlugin:()Ljava/lang/String;
     780: aload_2
     781: invokevirtual #932                // Method getClusterSpecifierPlugin:()Ljava/lang/String;
     784: invokevirtual #875                // Method java/lang/String.equals:(Ljava/lang/Object;)Z
     787: ifne          792
     790: iconst_0
     791: ireturn
     792: aload_0
     793: invokevirtual #934                // Method getHostRewriteSpecifierCase:()Lio/grpc/xds/shaded/io/envoyproxy/envoy/config/route/v3/RouteAction$HostRewriteSpecifierCase;
     796: aload_2
     797: invokevirtual #934                // Method getHostRewriteSpecifierCase:()Lio/grpc/xds/shaded/io/envoyproxy/envoy/config/route/v3/RouteAction$HostRewriteSpecifierCase;
     800: invokevirtual #935                // Method io/grpc/xds/shaded/io/envoyproxy/envoy/config/route/v3/RouteAction$HostRewriteSpecifierCase.equals:(Ljava/lang/Object;)Z
     803: ifne          808
     806: iconst_0
     807: ireturn
     808: aload_0
     809: getfield      #248                // Field hostRewriteSpecifierCase_:I
     812: lookupswitch  { // 5
                     0: 928
                     6: 864
                     7: 880
                    29: 896
                    35: 912
               default: 928
          }
     864: aload_0
     865: invokevirtual #937                // Method getHostRewriteLiteral:()Ljava/lang/String;
     868: aload_2
     869: invokevirtual #937                // Method getHostRewriteLiteral:()Ljava/lang/String;
     872: invokevirtual #875                // Method java/lang/String.equals:(Ljava/lang/Object;)Z
     875: ifne          928
     878: iconst_0
     879: ireturn
     880: aload_0
     881: invokevirtual #939                // Method getAutoHostRewrite:()Lcom/google/protobuf/BoolValue;
     884: aload_2
     885: invokevirtual #939                // Method getAutoHostRewrite:()Lcom/google/protobuf/BoolValue;
     888: invokevirtual #897                // Method com/google/protobuf/BoolValue.equals:(Ljava/lang/Object;)Z
     891: ifne          928
     894: iconst_0
     895: ireturn
     896: aload_0
     897: invokevirtual #941                // Method getHostRewriteHeader:()Ljava/lang/String;
     900: aload_2
     901: invokevirtual #941                // Method getHostRewriteHeader:()Ljava/lang/String;
     904: invokevirtual #875                // Method java/lang/String.equals:(Ljava/lang/Object;)Z
     907: ifne          928
     910: iconst_0
     911: ireturn
     912: aload_0
     913: invokevirtual #943                // Method getHostRewritePathRegex:()Lio/grpc/xds/shaded/io/envoyproxy/envoy/type/matcher/v3/RegexMatchAndSubstitute;
     916: aload_2
     917: invokevirtual #943                // Method getHostRewritePathRegex:()Lio/grpc/xds/shaded/io/envoyproxy/envoy/type/matcher/v3/RegexMatchAndSubstitute;
     920: invokevirtual #878                // Method io/grpc/xds/shaded/io/envoyproxy/envoy/type/matcher/v3/RegexMatchAndSubstitute.equals:(Ljava/lang/Object;)Z
     923: ifne          928
     926: iconst_0
     927: ireturn
     928: aload_0
     929: getfield      #292                // Field unknownFields:Lcom/google/protobuf/UnknownFieldSet;
     932: aload_2
     933: getfield      #292                // Field unknownFields:Lcom/google/protobuf/UnknownFieldSet;
     936: invokevirtual #944                // Method com/google/protobuf/UnknownFieldSet.equals:(Ljava/lang/Object;)Z
     939: ifne          944
     942: iconst_0
     943: ireturn
     944: iconst_1
     945: ireturn

  public int hashCode();
    Code:
       0: aload_0
       1: getfield      #950                // Field memoizedHashCode:I
       4: ifeq          12
       7: aload_0
       8: getfield      #950                // Field memoizedHashCode:I
      11: ireturn
      12: bipush        41
      14: istore_1
      15: bipush        19
      17: iload_1
      18: imul
      19: invokestatic  #952                // Method getDescriptor:()Lcom/google/protobuf/Descriptors$Descriptor;
      22: invokevirtual #954                // Method java/lang/Object.hashCode:()I
      25: iadd
      26: istore_1
      27: bipush        37
      29: iload_1
      30: imul
      31: bipush        20
      33: iadd
      34: istore_1
      35: bipush        53
      37: iload_1
      38: imul
      39: aload_0
      40: getfield      #259                // Field clusterNotFoundResponseCode_:I
      43: iadd
      44: istore_1
      45: aload_0
      46: invokevirtual #871                // Method hasMetadataMatch:()Z
      49: ifeq          72
      52: bipush        37
      54: iload_1
      55: imul
      56: iconst_4
      57: iadd
      58: istore_1
      59: bipush        53
      61: iload_1
      62: imul
      63: aload_0
      64: invokevirtual #631                // Method getMetadataMatch:()Lio/grpc/xds/shaded/io/envoyproxy/envoy/config/core/v3/Metadata;
      67: invokevirtual #955                // Method io/grpc/xds/shaded/io/envoyproxy/envoy/config/core/v3/Metadata.hashCode:()I
      70: iadd
      71: istore_1
      72: bipush        37
      74: iload_1
      75: imul
      76: iconst_5
      77: iadd
      78: istore_1
      79: bipush        53
      81: iload_1
      82: imul
      83: aload_0
      84: invokevirtual #874                // Method getPrefixRewrite:()Ljava/lang/String;
      87: invokevirtual #956                // Method java/lang/String.hashCode:()I
      90: iadd
      91: istore_1
      92: aload_0
      93: invokevirtual #877                // Method hasRegexRewrite:()Z
      96: ifeq          120
      99: bipush        37
     101: iload_1
     102: imul
     103: bipush        32
     105: iadd
     106: istore_1
     107: bipush        53
     109: iload_1
     110: imul
     111: aload_0
     112: invokevirtual #641                // Method getRegexRewrite:()Lio/grpc/xds/shaded/io/envoyproxy/envoy/type/matcher/v3/RegexMatchAndSubstitute;
     115: invokevirtual #957                // Method io/grpc/xds/shaded/io/envoyproxy/envoy/type/matcher/v3/RegexMatchAndSubstitute.hashCode:()I
     118: iadd
     119: istore_1
     120: aload_0
     121: invokevirtual #880                // Method hasTimeout:()Z
     124: ifeq          148
     127: bipush        37
     129: iload_1
     130: imul
     131: bipush        8
     133: iadd
     134: istore_1
     135: bipush        53
     137: iload_1
     138: imul
     139: aload_0
     140: invokevirtual #664                // Method getTimeout:()Lcom/google/protobuf/Duration;
     143: invokevirtual #958                // Method com/google/protobuf/Duration.hashCode:()I
     146: iadd
     147: istore_1
     148: aload_0
     149: invokevirtual #883                // Method hasIdleTimeout:()Z
     152: ifeq          176
     155: bipush        37
     157: iload_1
     158: imul
     159: bipush        24
     161: iadd
     162: istore_1
     163: bipush        53
     165: iload_1
     166: imul
     167: aload_0
     168: invokevirtual #669                // Method getIdleTimeout:()Lcom/google/protobuf/Duration;
     171: invokevirtual #958                // Method com/google/protobuf/Duration.hashCode:()I
     174: iadd
     175: istore_1
     176: aload_0
     177: invokevirtual #885                // Method hasRetryPolicy:()Z
     180: ifeq          204
     183: bipush        37
     185: iload_1
     186: imul
     187: bipush        9
     189: iadd
     190: istore_1
     191: bipush        53
     193: iload_1
     194: imul
     195: aload_0
     196: invokevirtual #677                // Method getRetryPolicy:()Lio/grpc/xds/shaded/io/envoyproxy/envoy/config/route/v3/RetryPolicy;
     199: invokevirtual #959                // Method io/grpc/xds/shaded/io/envoyproxy/envoy/config/route/v3/RetryPolicy.hashCode:()I
     202: iadd
     203: istore_1
     204: aload_0
     205: invokevirtual #888                // Method hasRetryPolicyTypedConfig:()Z
     208: ifeq          232
     211: bipush        37
     213: iload_1
     214: imul
     215: bipush        33
     217: iadd
     218: istore_1
     219: bipush        53
     221: iload_1
     222: imul
     223: aload_0
     224: invokevirtual #685                // Method getRetryPolicyTypedConfig:()Lcom/google/protobuf/Any;
     227: invokevirtual #960                // Method com/google/protobuf/Any.hashCode:()I
     230: iadd
     231: istore_1
     232: aload_0
     233: invokevirtual #962                // Method getRequestMirrorPoliciesCount:()I
     236: ifle          262
     239: bipush        37
     241: iload_1
     242: imul
     243: bipush        30
     245: iadd
     246: istore_1
     247: bipush        53
     249: iload_1
     250: imul
     251: aload_0
     252: invokevirtual #891                // Method getRequestMirrorPoliciesList:()Ljava/util/List;
     255: invokeinterface #963,  1          // InterfaceMethod java/util/List.hashCode:()I
     260: iadd
     261: istore_1
     262: bipush        37
     264: iload_1
     265: imul
     266: bipush        11
     268: iadd
     269: istore_1
     270: bipush        53
     272: iload_1
     273: imul
     274: aload_0
     275: getfield      #273                // Field priority_:I
     278: iadd
     279: istore_1
     280: aload_0
     281: invokevirtual #965                // Method getRateLimitsCount:()I
     284: ifle          310
     287: bipush        37
     289: iload_1
     290: imul
     291: bipush        13
     293: iadd
     294: istore_1
     295: bipush        53
     297: iload_1
     298: imul
     299: aload_0
     300: invokevirtual #894                // Method getRateLimitsList:()Ljava/util/List;
     303: invokeinterface #963,  1          // InterfaceMethod java/util/List.hashCode:()I
     308: iadd
     309: istore_1
     310: aload_0
     311: invokevirtual #896                // Method hasIncludeVhRateLimits:()Z
     314: ifeq          338
     317: bipush        37
     319: iload_1
     320: imul
     321: bipush        14
     323: iadd
     324: istore_1
     325: bipush        53
     327: iload_1
     328: imul
     329: aload_0
     330: invokevirtual #730                // Method getIncludeVhRateLimits:()Lcom/google/protobuf/BoolValue;
     333: invokevirtual #966                // Method com/google/protobuf/BoolValue.hashCode:()I
     336: iadd
     337: istore_1
     338: aload_0
     339: invokevirtual #968                // Method getHashPolicyCount:()I
     342: ifle          368
     345: bipush        37
     347: iload_1
     348: imul
     349: bipush        15
     351: iadd
     352: istore_1
     353: bipush        53
     355: iload_1
     356: imul
     357: aload_0
     358: invokevirtual #899                // Method getHashPolicyList:()Ljava/util/List;
     361: invokeinterface #963,  1          // InterfaceMethod java/util/List.hashCode:()I
     366: iadd
     367: istore_1
     368: aload_0
     369: invokevirtual #901                // Method hasCors:()Z
     372: ifeq          396
     375: bipush        37
     377: iload_1
     378: imul
     379: bipush        17
     381: iadd
     382: istore_1
     383: bipush        53
     385: iload_1
     386: imul
     387: aload_0
     388: invokevirtual #747                // Method getCors:()Lio/grpc/xds/shaded/io/envoyproxy/envoy/config/route/v3/CorsPolicy;
     391: invokevirtual #969                // Method io/grpc/xds/shaded/io/envoyproxy/envoy/config/route/v3/CorsPolicy.hashCode:()I
     394: iadd
     395: istore_1
     396: aload_0
     397: invokevirtual #904                // Method hasMaxGrpcTimeout:()Z
     400: ifeq          424
     403: bipush        37
     405: iload_1
     406: imul
     407: bipush        23
     409: iadd
     410: istore_1
     411: bipush        53
     413: iload_1
     414: imul
     415: aload_0
     416: invokevirtual #752                // Method getMaxGrpcTimeout:()Lcom/google/protobuf/Duration;
     419: invokevirtual #958                // Method com/google/protobuf/Duration.hashCode:()I
     422: iadd
     423: istore_1
     424: aload_0
     425: invokevirtual #906                // Method hasGrpcTimeoutOffset:()Z
     428: ifeq          452
     431: bipush        37
     433: iload_1
     434: imul
     435: bipush        28
     437: iadd
     438: istore_1
     439: bipush        53
     441: iload_1
     442: imul
     443: aload_0
     444: invokevirtual #757                // Method getGrpcTimeoutOffset:()Lcom/google/protobuf/Duration;
     447: invokevirtual #958                // Method com/google/protobuf/Duration.hashCode:()I
     450: iadd
     451: istore_1
     452: aload_0
     453: invokevirtual #971                // Method getUpgradeConfigsCount:()I
     456: ifle          482
     459: bipush        37
     461: iload_1
     462: imul
     463: bipush        25
     465: iadd
     466: istore_1
     467: bipush        53
     469: iload_1
     470: imul
     471: aload_0
     472: invokevirtual #908                // Method getUpgradeConfigsList:()Ljava/util/List;
     475: invokeinterface #963,  1          // InterfaceMethod java/util/List.hashCode:()I
     480: iadd
     481: istore_1
     482: aload_0
     483: invokevirtual #910                // Method hasInternalRedirectPolicy:()Z
     486: ifeq          510
     489: bipush        37
     491: iload_1
     492: imul
     493: bipush        34
     495: iadd
     496: istore_1
     497: bipush        53
     499: iload_1
     500: imul
     501: aload_0
     502: invokevirtual #774                // Method getInternalRedirectPolicy:()Lio/grpc/xds/shaded/io/envoyproxy/envoy/config/route/v3/InternalRedirectPolicy;
     505: invokevirtual #972                // Method io/grpc/xds/shaded/io/envoyproxy/envoy/config/route/v3/InternalRedirectPolicy.hashCode:()I
     508: iadd
     509: istore_1
     510: bipush        37
     512: iload_1
     513: imul
     514: bipush        26
     516: iadd
     517: istore_1
     518: bipush        53
     520: iload_1
     521: imul
     522: aload_0
     523: getfield      #281                // Field internalRedirectAction_:I
     526: iadd
     527: istore_1
     528: aload_0
     529: invokevirtual #913                // Method hasMaxInternalRedirects:()Z
     532: ifeq          556
     535: bipush        37
     537: iload_1
     538: imul
     539: bipush        31
     541: iadd
     542: istore_1
     543: bipush        53
     545: iload_1
     546: imul
     547: aload_0
     548: invokevirtual #791                // Method getMaxInternalRedirects:()Lcom/google/protobuf/UInt32Value;
     551: invokevirtual #973                // Method com/google/protobuf/UInt32Value.hashCode:()I
     554: iadd
     555: istore_1
     556: aload_0
     557: invokevirtual #916                // Method hasHedgePolicy:()Z
     560: ifeq          584
     563: bipush        37
     565: iload_1
     566: imul
     567: bipush        27
     569: iadd
     570: istore_1
     571: bipush        53
     573: iload_1
     574: imul
     575: aload_0
     576: invokevirtual #799                // Method getHedgePolicy:()Lio/grpc/xds/shaded/io/envoyproxy/envoy/config/route/v3/HedgePolicy;
     579: invokevirtual #974                // Method io/grpc/xds/shaded/io/envoyproxy/envoy/config/route/v3/HedgePolicy.hashCode:()I
     582: iadd
     583: istore_1
     584: aload_0
     585: invokevirtual #919                // Method hasMaxStreamDuration:()Z
     588: ifeq          612
     591: bipush        37
     593: iload_1
     594: imul
     595: bipush        36
     597: iadd
     598: istore_1
     599: bipush        53
     601: iload_1
     602: imul
     603: aload_0
     604: invokevirtual #807                // Method getMaxStreamDuration:()Lio/grpc/xds/shaded/io/envoyproxy/envoy/config/route/v3/RouteAction$MaxStreamDuration;
     607: invokevirtual #975                // Method io/grpc/xds/shaded/io/envoyproxy/envoy/config/route/v3/RouteAction$MaxStreamDuration.hashCode:()I
     610: iadd
     611: istore_1
     612: aload_0
     613: getfield      #246                // Field clusterSpecifierCase_:I
     616: lookupswitch  { // 5
                     0: 761
                     1: 668
                     2: 691
                     3: 714
                    37: 737
               default: 761
          }
     668: bipush        37
     670: iload_1
     671: imul
     672: iconst_1
     673: iadd
     674: istore_1
     675: bipush        53
     677: iload_1
     678: imul
     679: aload_0
     680: invokevirtual #925                // Method getCluster:()Ljava/lang/String;
     683: invokevirtual #956                // Method java/lang/String.hashCode:()I
     686: iadd
     687: istore_1
     688: goto          761
     691: bipush        37
     693: iload_1
     694: imul
     695: iconst_2
     696: iadd
     697: istore_1
     698: bipush        53
     700: iload_1
     701: imul
     702: aload_0
     703: invokevirtual #927                // Method getClusterHeader:()Ljava/lang/String;
     706: invokevirtual #956                // Method java/lang/String.hashCode:()I
     709: iadd
     710: istore_1
     711: goto          761
     714: bipush        37
     716: iload_1
     717: imul
     718: iconst_3
     719: iadd
     720: istore_1
     721: bipush        53
     723: iload_1
     724: imul
     725: aload_0
     726: invokevirtual #929                // Method getWeightedClusters:()Lio/grpc/xds/shaded/io/envoyproxy/envoy/config/route/v3/WeightedCluster;
     729: invokevirtual #976                // Method io/grpc/xds/shaded/io/envoyproxy/envoy/config/route/v3/WeightedCluster.hashCode:()I
     732: iadd
     733: istore_1
     734: goto          761
     737: bipush        37
     739: iload_1
     740: imul
     741: bipush        37
     743: iadd
     744: istore_1
     745: bipush        53
     747: iload_1
     748: imul
     749: aload_0
     750: invokevirtual #932                // Method getClusterSpecifierPlugin:()Ljava/lang/String;
     753: invokevirtual #956                // Method java/lang/String.hashCode:()I
     756: iadd
     757: istore_1
     758: goto          761
     761: aload_0
     762: getfield      #248                // Field hostRewriteSpecifierCase_:I
     765: lookupswitch  { // 5
                     0: 912
                     6: 816
                     7: 840
                    29: 864
                    35: 888
               default: 912
          }
     816: bipush        37
     818: iload_1
     819: imul
     820: bipush        6
     822: iadd
     823: istore_1
     824: bipush        53
     826: iload_1
     827: imul
     828: aload_0
     829: invokevirtual #937                // Method getHostRewriteLiteral:()Ljava/lang/String;
     832: invokevirtual #956                // Method java/lang/String.hashCode:()I
     835: iadd
     836: istore_1
     837: goto          912
     840: bipush        37
     842: iload_1
     843: imul
     844: bipush        7
     846: iadd
     847: istore_1
     848: bipush        53
     850: iload_1
     851: imul
     852: aload_0
     853: invokevirtual #939                // Method getAutoHostRewrite:()Lcom/google/protobuf/BoolValue;
     856: invokevirtual #966                // Method com/google/protobuf/BoolValue.hashCode:()I
     859: iadd
     860: istore_1
     861: goto          912
     864: bipush        37
     866: iload_1
     867: imul
     868: bipush        29
     870: iadd
     871: istore_1
     872: bipush        53
     874: iload_1
     875: imul
     876: aload_0
     877: invokevirtual #941                // Method getHostRewriteHeader:()Ljava/lang/String;
     880: invokevirtual #956                // Method java/lang/String.hashCode:()I
     883: iadd
     884: istore_1
     885: goto          912
     888: bipush        37
     890: iload_1
     891: imul
     892: bipush        35
     894: iadd
     895: istore_1
     896: bipush        53
     898: iload_1
     899: imul
     900: aload_0
     901: invokevirtual #943                // Method getHostRewritePathRegex:()Lio/grpc/xds/shaded/io/envoyproxy/envoy/type/matcher/v3/RegexMatchAndSubstitute;
     904: invokevirtual #957                // Method io/grpc/xds/shaded/io/envoyproxy/envoy/type/matcher/v3/RegexMatchAndSubstitute.hashCode:()I
     907: iadd
     908: istore_1
     909: goto          912
     912: bipush        29
     914: iload_1
     915: imul
     916: aload_0
     917: getfield      #292                // Field unknownFields:Lcom/google/protobuf/UnknownFieldSet;
     920: invokevirtual #977                // Method com/google/protobuf/UnknownFieldSet.hashCode:()I
     923: iadd
     924: istore_1
     925: aload_0
     926: iload_1
     927: putfield      #950                // Field memoizedHashCode:I
     930: iload_1
     931: ireturn

  public static io.grpc.xds.shaded.io.envoyproxy.envoy.config.route.v3.RouteAction parseFrom(java.nio.ByteBuffer) throws com.google.protobuf.InvalidProtocolBufferException;
    Code:
       0: getstatic     #982                // Field PARSER:Lcom/google/protobuf/Parser;
       3: aload_0
       4: invokeinterface #987,  2          // InterfaceMethod com/google/protobuf/Parser.parseFrom:(Ljava/nio/ByteBuffer;)Ljava/lang/Object;
       9: checkcast     #2                  // class io/grpc/xds/shaded/io/envoyproxy/envoy/config/route/v3/RouteAction
      12: areturn

  public static io.grpc.xds.shaded.io.envoyproxy.envoy.config.route.v3.RouteAction parseFrom(java.nio.ByteBuffer, com.google.protobuf.ExtensionRegistryLite) throws com.google.protobuf.InvalidProtocolBufferException;
    Code:
       0: getstatic     #982                // Field PARSER:Lcom/google/protobuf/Parser;
       3: aload_0
       4: aload_1
       5: invokeinterface #993,  3          // InterfaceMethod com/google/protobuf/Parser.parseFrom:(Ljava/nio/ByteBuffer;Lcom/google/protobuf/ExtensionRegistryLite;)Ljava/lang/Object;
      10: checkcast     #2                  // class io/grpc/xds/shaded/io/envoyproxy/envoy/config/route/v3/RouteAction
      13: areturn

  public static io.grpc.xds.shaded.io.envoyproxy.envoy.config.route.v3.RouteAction parseFrom(com.google.protobuf.ByteString) throws com.google.protobuf.InvalidProtocolBufferException;
    Code:
       0: getstatic     #982                // Field PARSER:Lcom/google/protobuf/Parser;
       3: aload_0
       4: invokeinterface #997,  2          // InterfaceMethod com/google/protobuf/Parser.parseFrom:(Lcom/google/protobuf/ByteString;)Ljava/lang/Object;
       9: checkcast     #2                  // class io/grpc/xds/shaded/io/envoyproxy/envoy/config/route/v3/RouteAction
      12: areturn

  public static io.grpc.xds.shaded.io.envoyproxy.envoy.config.route.v3.RouteAction parseFrom(com.google.protobuf.ByteString, com.google.protobuf.ExtensionRegistryLite) throws com.google.protobuf.InvalidProtocolBufferException;
    Code:
       0: getstatic     #982                // Field PARSER:Lcom/google/protobuf/Parser;
       3: aload_0
       4: aload_1
       5: invokeinterface #1001,  3         // InterfaceMethod com/google/protobuf/Parser.parseFrom:(Lcom/google/protobuf/ByteString;Lcom/google/protobuf/ExtensionRegistryLite;)Ljava/lang/Object;
      10: checkcast     #2                  // class io/grpc/xds/shaded/io/envoyproxy/envoy/config/route/v3/RouteAction
      13: areturn

  public static io.grpc.xds.shaded.io.envoyproxy.envoy.config.route.v3.RouteAction parseFrom(byte[]) throws com.google.protobuf.InvalidProtocolBufferException;
    Code:
       0: getstatic     #982                // Field PARSER:Lcom/google/protobuf/Parser;
       3: aload_0
       4: invokeinterface #1005,  2         // InterfaceMethod com/google/protobuf/Parser.parseFrom:([B)Ljava/lang/Object;
       9: checkcast     #2                  // class io/grpc/xds/shaded/io/envoyproxy/envoy/config/route/v3/RouteAction
      12: areturn

  public static io.grpc.xds.shaded.io.envoyproxy.envoy.config.route.v3.RouteAction parseFrom(byte[], com.google.protobuf.ExtensionRegistryLite) throws com.google.protobuf.InvalidProtocolBufferException;
    Code:
       0: getstatic     #982                // Field PARSER:Lcom/google/protobuf/Parser;
       3: aload_0
       4: aload_1
       5: invokeinterface #1010,  3         // InterfaceMethod com/google/protobuf/Parser.parseFrom:([BLcom/google/protobuf/ExtensionRegistryLite;)Ljava/lang/Object;
      10: checkcast     #2                  // class io/grpc/xds/shaded/io/envoyproxy/envoy/config/route/v3/RouteAction
      13: areturn

  public static io.grpc.xds.shaded.io.envoyproxy.envoy.config.route.v3.RouteAction parseFrom(java.io.InputStream) throws java.io.IOException;
    Code:
       0: getstatic     #982                // Field PARSER:Lcom/google/protobuf/Parser;
       3: aload_0
       4: invokestatic  #1015               // Method com/google/protobuf/GeneratedMessageV3.parseWithIOException:(Lcom/google/protobuf/Parser;Ljava/io/InputStream;)Lcom/google/protobuf/Message;
       7: checkcast     #2                  // class io/grpc/xds/shaded/io/envoyproxy/envoy/config/route/v3/RouteAction
      10: areturn

  public static io.grpc.xds.shaded.io.envoyproxy.envoy.config.route.v3.RouteAction parseFrom(java.io.InputStream, com.google.protobuf.ExtensionRegistryLite) throws java.io.IOException;
    Code:
       0: getstatic     #982                // Field PARSER:Lcom/google/protobuf/Parser;
       3: aload_0
       4: aload_1
       5: invokestatic  #1020               // Method com/google/protobuf/GeneratedMessageV3.parseWithIOException:(Lcom/google/protobuf/Parser;Ljava/io/InputStream;Lcom/google/protobuf/ExtensionRegistryLite;)Lcom/google/protobuf/Message;
       8: checkcast     #2                  // class io/grpc/xds/shaded/io/envoyproxy/envoy/config/route/v3/RouteAction
      11: areturn

  public static io.grpc.xds.shaded.io.envoyproxy.envoy.config.route.v3.RouteAction parseDelimitedFrom(java.io.InputStream) throws java.io.IOException;
    Code:
       0: getstatic     #982                // Field PARSER:Lcom/google/protobuf/Parser;
       3: aload_0
       4: invokestatic  #1024               // Method com/google/protobuf/GeneratedMessageV3.parseDelimitedWithIOException:(Lcom/google/protobuf/Parser;Ljava/io/InputStream;)Lcom/google/protobuf/Message;
       7: checkcast     #2                  // class io/grpc/xds/shaded/io/envoyproxy/envoy/config/route/v3/RouteAction
      10: areturn

  public static io.grpc.xds.shaded.io.envoyproxy.envoy.config.route.v3.RouteAction parseDelimitedFrom(java.io.InputStream, com.google.protobuf.ExtensionRegistryLite) throws java.io.IOException;
    Code:
       0: getstatic     #982                // Field PARSER:Lcom/google/protobuf/Parser;
       3: aload_0
       4: aload_1
       5: invokestatic  #1026               // Method com/google/protobuf/GeneratedMessageV3.parseDelimitedWithIOException:(Lcom/google/protobuf/Parser;Ljava/io/InputStream;Lcom/google/protobuf/ExtensionRegistryLite;)Lcom/google/protobuf/Message;
       8: checkcast     #2                  // class io/grpc/xds/shaded/io/envoyproxy/envoy/config/route/v3/RouteAction
      11: areturn

  public static io.grpc.xds.shaded.io.envoyproxy.envoy.config.route.v3.RouteAction parseFrom(com.google.protobuf.CodedInputStream) throws java.io.IOException;
    Code:
       0: getstatic     #982                // Field PARSER:Lcom/google/protobuf/Parser;
       3: aload_0
       4: invokestatic  #1030               // Method com/google/protobuf/GeneratedMessageV3.parseWithIOException:(Lcom/google/protobuf/Parser;Lcom/google/protobuf/CodedInputStream;)Lcom/google/protobuf/Message;
       7: checkcast     #2                  // class io/grpc/xds/shaded/io/envoyproxy/envoy/config/route/v3/RouteAction
      10: areturn

  public static io.grpc.xds.shaded.io.envoyproxy.envoy.config.route.v3.RouteAction parseFrom(com.google.protobuf.CodedInputStream, com.google.protobuf.ExtensionRegistryLite) throws java.io.IOException;
    Code:
       0: getstatic     #982                // Field PARSER:Lcom/google/protobuf/Parser;
       3: aload_0
       4: aload_1
       5: invokestatic  #1034               // Method com/google/protobuf/GeneratedMessageV3.parseWithIOException:(Lcom/google/protobuf/Parser;Lcom/google/protobuf/CodedInputStream;Lcom/google/protobuf/ExtensionRegistryLite;)Lcom/google/protobuf/Message;
       8: checkcast     #2                  // class io/grpc/xds/shaded/io/envoyproxy/envoy/config/route/v3/RouteAction
      11: areturn

  public io.grpc.xds.shaded.io.envoyproxy.envoy.config.route.v3.RouteAction$Builder newBuilderForType();
    Code:
       0: invokestatic  #1038               // Method newBuilder:()Lio/grpc/xds/shaded/io/envoyproxy/envoy/config/route/v3/RouteAction$Builder;
       3: areturn

  public static io.grpc.xds.shaded.io.envoyproxy.envoy.config.route.v3.RouteAction$Builder newBuilder();
    Code:
       0: getstatic     #1040               // Field DEFAULT_INSTANCE:Lio/grpc/xds/shaded/io/envoyproxy/envoy/config/route/v3/RouteAction;
       3: invokevirtual #1042               // Method toBuilder:()Lio/grpc/xds/shaded/io/envoyproxy/envoy/config/route/v3/RouteAction$Builder;
       6: areturn

  public static io.grpc.xds.shaded.io.envoyproxy.envoy.config.route.v3.RouteAction$Builder newBuilder(io.grpc.xds.shaded.io.envoyproxy.envoy.config.route.v3.RouteAction);
    Code:
       0: getstatic     #1040               // Field DEFAULT_INSTANCE:Lio/grpc/xds/shaded/io/envoyproxy/envoy/config/route/v3/RouteAction;
       3: invokevirtual #1042               // Method toBuilder:()Lio/grpc/xds/shaded/io/envoyproxy/envoy/config/route/v3/RouteAction$Builder;
       6: aload_0
       7: invokevirtual #1045               // Method io/grpc/xds/shaded/io/envoyproxy/envoy/config/route/v3/RouteAction$Builder.mergeFrom:(Lio/grpc/xds/shaded/io/envoyproxy/envoy/config/route/v3/RouteAction;)Lio/grpc/xds/shaded/io/envoyproxy/envoy/config/route/v3/RouteAction$Builder;
      10: areturn

  public io.grpc.xds.shaded.io.envoyproxy.envoy.config.route.v3.RouteAction$Builder toBuilder();
    Code:
       0: aload_0
       1: getstatic     #1040               // Field DEFAULT_INSTANCE:Lio/grpc/xds/shaded/io/envoyproxy/envoy/config/route/v3/RouteAction;
       4: if_acmpne     18
       7: new           #11                 // class io/grpc/xds/shaded/io/envoyproxy/envoy/config/route/v3/RouteAction$Builder
      10: dup
      11: aconst_null
      12: invokespecial #1049               // Method io/grpc/xds/shaded/io/envoyproxy/envoy/config/route/v3/RouteAction$Builder."<init>":(Lio/grpc/xds/shaded/io/envoyproxy/envoy/config/route/v3/RouteAction$1;)V
      15: goto          30
      18: new           #11                 // class io/grpc/xds/shaded/io/envoyproxy/envoy/config/route/v3/RouteAction$Builder
      21: dup
      22: aconst_null
      23: invokespecial #1049               // Method io/grpc/xds/shaded/io/envoyproxy/envoy/config/route/v3/RouteAction$Builder."<init>":(Lio/grpc/xds/shaded/io/envoyproxy/envoy/config/route/v3/RouteAction$1;)V
      26: aload_0
      27: invokevirtual #1045               // Method io/grpc/xds/shaded/io/envoyproxy/envoy/config/route/v3/RouteAction$Builder.mergeFrom:(Lio/grpc/xds/shaded/io/envoyproxy/envoy/config/route/v3/RouteAction;)Lio/grpc/xds/shaded/io/envoyproxy/envoy/config/route/v3/RouteAction$Builder;
      30: areturn

  protected io.grpc.xds.shaded.io.envoyproxy.envoy.config.route.v3.RouteAction$Builder newBuilderForType(com.google.protobuf.GeneratedMessageV3$BuilderParent);
    Code:
       0: new           #11                 // class io/grpc/xds/shaded/io/envoyproxy/envoy/config/route/v3/RouteAction$Builder
       3: dup
       4: aload_1
       5: aconst_null
       6: invokespecial #1053               // Method io/grpc/xds/shaded/io/envoyproxy/envoy/config/route/v3/RouteAction$Builder."<init>":(Lcom/google/protobuf/GeneratedMessageV3$BuilderParent;Lio/grpc/xds/shaded/io/envoyproxy/envoy/config/route/v3/RouteAction$1;)V
       9: astore_2
      10: aload_2
      11: areturn

  public static io.grpc.xds.shaded.io.envoyproxy.envoy.config.route.v3.RouteAction getDefaultInstance();
    Code:
       0: getstatic     #1040               // Field DEFAULT_INSTANCE:Lio/grpc/xds/shaded/io/envoyproxy/envoy/config/route/v3/RouteAction;
       3: areturn

  public static com.google.protobuf.Parser<io.grpc.xds.shaded.io.envoyproxy.envoy.config.route.v3.RouteAction> parser();
    Code:
       0: getstatic     #982                // Field PARSER:Lcom/google/protobuf/Parser;
       3: areturn

  public com.google.protobuf.Parser<io.grpc.xds.shaded.io.envoyproxy.envoy.config.route.v3.RouteAction> getParserForType();
    Code:
       0: getstatic     #982                // Field PARSER:Lcom/google/protobuf/Parser;
       3: areturn

  public io.grpc.xds.shaded.io.envoyproxy.envoy.config.route.v3.RouteAction getDefaultInstanceForType();
    Code:
       0: getstatic     #1040               // Field DEFAULT_INSTANCE:Lio/grpc/xds/shaded/io/envoyproxy/envoy/config/route/v3/RouteAction;
       3: areturn

  protected com.google.protobuf.Message$Builder newBuilderForType(com.google.protobuf.GeneratedMessageV3$BuilderParent);
    Code:
       0: aload_0
       1: aload_1
       2: invokevirtual #1063               // Method newBuilderForType:(Lcom/google/protobuf/GeneratedMessageV3$BuilderParent;)Lio/grpc/xds/shaded/io/envoyproxy/envoy/config/route/v3/RouteAction$Builder;
       5: areturn

  public com.google.protobuf.Message$Builder toBuilder();
    Code:
       0: aload_0
       1: invokevirtual #1042               // Method toBuilder:()Lio/grpc/xds/shaded/io/envoyproxy/envoy/config/route/v3/RouteAction$Builder;
       4: areturn

  public com.google.protobuf.Message$Builder newBuilderForType();
    Code:
       0: aload_0
       1: invokevirtual #1066               // Method newBuilderForType:()Lio/grpc/xds/shaded/io/envoyproxy/envoy/config/route/v3/RouteAction$Builder;
       4: areturn

  public com.google.protobuf.MessageLite$Builder toBuilder();
    Code:
       0: aload_0
       1: invokevirtual #1042               // Method toBuilder:()Lio/grpc/xds/shaded/io/envoyproxy/envoy/config/route/v3/RouteAction$Builder;
       4: areturn

  public com.google.protobuf.MessageLite$Builder newBuilderForType();
    Code:
       0: aload_0
       1: invokevirtual #1066               // Method newBuilderForType:()Lio/grpc/xds/shaded/io/envoyproxy/envoy/config/route/v3/RouteAction$Builder;
       4: areturn

  public com.google.protobuf.MessageLite getDefaultInstanceForType();
    Code:
       0: aload_0
       1: invokevirtual #1070               // Method getDefaultInstanceForType:()Lio/grpc/xds/shaded/io/envoyproxy/envoy/config/route/v3/RouteAction;
       4: areturn

  public com.google.protobuf.Message getDefaultInstanceForType();
    Code:
       0: aload_0
       1: invokevirtual #1070               // Method getDefaultInstanceForType:()Lio/grpc/xds/shaded/io/envoyproxy/envoy/config/route/v3/RouteAction;
       4: areturn

  static boolean access$10100();
    Code:
       0: getstatic     #1075               // Field alwaysUseFieldBuilders:Z
       3: ireturn

  io.grpc.xds.shaded.io.envoyproxy.envoy.config.route.v3.RouteAction(com.google.protobuf.GeneratedMessageV3$Builder, io.grpc.xds.shaded.io.envoyproxy.envoy.config.route.v3.RouteAction$1);
    Code:
       0: aload_0
       1: aload_1
       2: invokespecial #1077               // Method "<init>":(Lcom/google/protobuf/GeneratedMessageV3$Builder;)V
       5: return

  static java.lang.Object access$10302(io.grpc.xds.shaded.io.envoyproxy.envoy.config.route.v3.RouteAction, java.lang.Object);
    Code:
       0: aload_0
       1: aload_1
       2: dup_x1
       3: putfield      #318                // Field clusterSpecifier_:Ljava/lang/Object;
       6: areturn

  static int access$10402(io.grpc.xds.shaded.io.envoyproxy.envoy.config.route.v3.RouteAction, int);
    Code:
       0: aload_0
       1: iload_1
       2: dup_x1
       3: putfield      #259                // Field clusterNotFoundResponseCode_:I
       6: ireturn

  static io.grpc.xds.shaded.io.envoyproxy.envoy.config.core.v3.Metadata access$10502(io.grpc.xds.shaded.io.envoyproxy.envoy.config.route.v3.RouteAction, io.grpc.xds.shaded.io.envoyproxy.envoy.config.core.v3.Metadata);
    Code:
       0: aload_0
       1: aload_1
       2: dup_x1
       3: putfield      #340                // Field metadataMatch_:Lio/grpc/xds/shaded/io/envoyproxy/envoy/config/core/v3/Metadata;
       6: areturn

  static java.lang.Object access$10602(io.grpc.xds.shaded.io.envoyproxy.envoy.config.route.v3.RouteAction, java.lang.Object);
    Code:
       0: aload_0
       1: aload_1
       2: dup_x1
       3: putfield      #263                // Field prefixRewrite_:Ljava/lang/Object;
       6: areturn

  static io.grpc.xds.shaded.io.envoyproxy.envoy.type.matcher.v3.RegexMatchAndSubstitute access$10702(io.grpc.xds.shaded.io.envoyproxy.envoy.config.route.v3.RouteAction, io.grpc.xds.shaded.io.envoyproxy.envoy.type.matcher.v3.RegexMatchAndSubstitute);
    Code:
       0: aload_0
       1: aload_1
       2: dup_x1
       3: putfield      #450                // Field regexRewrite_:Lio/grpc/xds/shaded/io/envoyproxy/envoy/type/matcher/v3/RegexMatchAndSubstitute;
       6: areturn

  static java.lang.Object access$10802(io.grpc.xds.shaded.io.envoyproxy.envoy.config.route.v3.RouteAction, java.lang.Object);
    Code:
       0: aload_0
       1: aload_1
       2: dup_x1
       3: putfield      #352                // Field hostRewriteSpecifier_:Ljava/lang/Object;
       6: areturn

  static com.google.protobuf.Duration access$10902(io.grpc.xds.shaded.io.envoyproxy.envoy.config.route.v3.RouteAction, com.google.protobuf.Duration);
    Code:
       0: aload_0
       1: aload_1
       2: dup_x1
       3: putfield      #364                // Field timeout_:Lcom/google/protobuf/Duration;
       6: areturn

  static com.google.protobuf.Duration access$11002(io.grpc.xds.shaded.io.envoyproxy.envoy.config.route.v3.RouteAction, com.google.protobuf.Duration);
    Code:
       0: aload_0
       1: aload_1
       2: dup_x1
       3: putfield      #420                // Field idleTimeout_:Lcom/google/protobuf/Duration;
       6: areturn

  static io.grpc.xds.shaded.io.envoyproxy.envoy.config.route.v3.RetryPolicy access$11102(io.grpc.xds.shaded.io.envoyproxy.envoy.config.route.v3.RouteAction, io.grpc.xds.shaded.io.envoyproxy.envoy.config.route.v3.RetryPolicy);
    Code:
       0: aload_0
       1: aload_1
       2: dup_x1
       3: putfield      #376                // Field retryPolicy_:Lio/grpc/xds/shaded/io/envoyproxy/envoy/config/route/v3/RetryPolicy;
       6: areturn

  static com.google.protobuf.Any access$11202(io.grpc.xds.shaded.io.envoyproxy.envoy.config.route.v3.RouteAction, com.google.protobuf.Any);
    Code:
       0: aload_0
       1: aload_1
       2: dup_x1
       3: putfield      #462                // Field retryPolicyTypedConfig_:Lcom/google/protobuf/Any;
       6: areturn

  static java.util.List access$11302(io.grpc.xds.shaded.io.envoyproxy.envoy.config.route.v3.RouteAction, java.util.List);
    Code:
       0: aload_0
       1: aload_1
       2: dup_x1
       3: putfield      #271                // Field requestMirrorPolicies_:Ljava/util/List;
       6: areturn

  static int access$11402(io.grpc.xds.shaded.io.envoyproxy.envoy.config.route.v3.RouteAction, int);
    Code:
       0: aload_0
       1: iload_1
       2: dup_x1
       3: putfield      #273                // Field priority_:I
       6: ireturn

  static java.util.List access$11502(io.grpc.xds.shaded.io.envoyproxy.envoy.config.route.v3.RouteAction, java.util.List);
    Code:
       0: aload_0
       1: aload_1
       2: dup_x1
       3: putfield      #275                // Field rateLimits_:Ljava/util/List;
       6: areturn

  static com.google.protobuf.BoolValue access$11602(io.grpc.xds.shaded.io.envoyproxy.envoy.config.route.v3.RouteAction, com.google.protobuf.BoolValue);
    Code:
       0: aload_0
       1: aload_1
       2: dup_x1
       3: putfield      #403                // Field includeVhRateLimits_:Lcom/google/protobuf/BoolValue;
       6: areturn

  static java.util.List access$11702(io.grpc.xds.shaded.io.envoyproxy.envoy.config.route.v3.RouteAction, java.util.List);
    Code:
       0: aload_0
       1: aload_1
       2: dup_x1
       3: putfield      #277                // Field hashPolicy_:Ljava/util/List;
       6: areturn

  static io.grpc.xds.shaded.io.envoyproxy.envoy.config.route.v3.CorsPolicy access$11802(io.grpc.xds.shaded.io.envoyproxy.envoy.config.route.v3.RouteAction, io.grpc.xds.shaded.io.envoyproxy.envoy.config.route.v3.CorsPolicy);
    Code:
       0: aload_0
       1: aload_1
       2: dup_x1
       3: putfield      #406                // Field cors_:Lio/grpc/xds/shaded/io/envoyproxy/envoy/config/route/v3/CorsPolicy;
       6: areturn

  static com.google.protobuf.Duration access$11902(io.grpc.xds.shaded.io.envoyproxy.envoy.config.route.v3.RouteAction, com.google.protobuf.Duration);
    Code:
       0: aload_0
       1: aload_1
       2: dup_x1
       3: putfield      #418                // Field maxGrpcTimeout_:Lcom/google/protobuf/Duration;
       6: areturn

  static com.google.protobuf.Duration access$12002(io.grpc.xds.shaded.io.envoyproxy.envoy.config.route.v3.RouteAction, com.google.protobuf.Duration);
    Code:
       0: aload_0
       1: aload_1
       2: dup_x1
       3: putfield      #435                // Field grpcTimeoutOffset_:Lcom/google/protobuf/Duration;
       6: areturn

  static java.util.List access$12102(io.grpc.xds.shaded.io.envoyproxy.envoy.config.route.v3.RouteAction, java.util.List);
    Code:
       0: aload_0
       1: aload_1
       2: dup_x1
       3: putfield      #279                // Field upgradeConfigs_:Ljava/util/List;
       6: areturn

  static io.grpc.xds.shaded.io.envoyproxy.envoy.config.route.v3.InternalRedirectPolicy access$12202(io.grpc.xds.shaded.io.envoyproxy.envoy.config.route.v3.RouteAction, io.grpc.xds.shaded.io.envoyproxy.envoy.config.route.v3.InternalRedirectPolicy);
    Code:
       0: aload_0
       1: aload_1
       2: dup_x1
       3: putfield      #474                // Field internalRedirectPolicy_:Lio/grpc/xds/shaded/io/envoyproxy/envoy/config/route/v3/InternalRedirectPolicy;
       6: areturn

  static int access$12302(io.grpc.xds.shaded.io.envoyproxy.envoy.config.route.v3.RouteAction, int);
    Code:
       0: aload_0
       1: iload_1
       2: dup_x1
       3: putfield      #281                // Field internalRedirectAction_:I
       6: ireturn

  static com.google.protobuf.UInt32Value access$12402(io.grpc.xds.shaded.io.envoyproxy.envoy.config.route.v3.RouteAction, com.google.protobuf.UInt32Value);
    Code:
       0: aload_0
       1: aload_1
       2: dup_x1
       3: putfield      #438                // Field maxInternalRedirects_:Lcom/google/protobuf/UInt32Value;
       6: areturn

  static io.grpc.xds.shaded.io.envoyproxy.envoy.config.route.v3.HedgePolicy access$12502(io.grpc.xds.shaded.io.envoyproxy.envoy.config.route.v3.RouteAction, io.grpc.xds.shaded.io.envoyproxy.envoy.config.route.v3.HedgePolicy);
    Code:
       0: aload_0
       1: aload_1
       2: dup_x1
       3: putfield      #423                // Field hedgePolicy_:Lio/grpc/xds/shaded/io/envoyproxy/envoy/config/route/v3/HedgePolicy;
       6: areturn

  static io.grpc.xds.shaded.io.envoyproxy.envoy.config.route.v3.RouteAction$MaxStreamDuration access$12602(io.grpc.xds.shaded.io.envoyproxy.envoy.config.route.v3.RouteAction, io.grpc.xds.shaded.io.envoyproxy.envoy.config.route.v3.RouteAction$MaxStreamDuration);
    Code:
       0: aload_0
       1: aload_1
       2: dup_x1
       3: putfield      #486                // Field maxStreamDuration_:Lio/grpc/xds/shaded/io/envoyproxy/envoy/config/route/v3/RouteAction$MaxStreamDuration;
       6: areturn

  static int access$12702(io.grpc.xds.shaded.io.envoyproxy.envoy.config.route.v3.RouteAction, int);
    Code:
       0: aload_0
       1: iload_1
       2: dup_x1
       3: putfield      #246                // Field clusterSpecifierCase_:I
       6: ireturn

  static int access$12802(io.grpc.xds.shaded.io.envoyproxy.envoy.config.route.v3.RouteAction, int);
    Code:
       0: aload_0
       1: iload_1
       2: dup_x1
       3: putfield      #248                // Field hostRewriteSpecifierCase_:I
       6: ireturn

  static int access$10400(io.grpc.xds.shaded.io.envoyproxy.envoy.config.route.v3.RouteAction);
    Code:
       0: aload_0
       1: getfield      #259                // Field clusterNotFoundResponseCode_:I
       4: ireturn

  static java.lang.Object access$10600(io.grpc.xds.shaded.io.envoyproxy.envoy.config.route.v3.RouteAction);
    Code:
       0: aload_0
       1: getfield      #263                // Field prefixRewrite_:Ljava/lang/Object;
       4: areturn

  static java.util.List access$11300(io.grpc.xds.shaded.io.envoyproxy.envoy.config.route.v3.RouteAction);
    Code:
       0: aload_0
       1: getfield      #271                // Field requestMirrorPolicies_:Ljava/util/List;
       4: areturn

  static boolean access$12900();
    Code:
       0: getstatic     #1075               // Field alwaysUseFieldBuilders:Z
       3: ireturn

  static int access$11400(io.grpc.xds.shaded.io.envoyproxy.envoy.config.route.v3.RouteAction);
    Code:
       0: aload_0
       1: getfield      #273                // Field priority_:I
       4: ireturn

  static java.util.List access$11500(io.grpc.xds.shaded.io.envoyproxy.envoy.config.route.v3.RouteAction);
    Code:
       0: aload_0
       1: getfield      #275                // Field rateLimits_:Ljava/util/List;
       4: areturn

  static boolean access$13000();
    Code:
       0: getstatic     #1075               // Field alwaysUseFieldBuilders:Z
       3: ireturn

  static java.util.List access$11700(io.grpc.xds.shaded.io.envoyproxy.envoy.config.route.v3.RouteAction);
    Code:
       0: aload_0
       1: getfield      #277                // Field hashPolicy_:Ljava/util/List;
       4: areturn

  static boolean access$13100();
    Code:
       0: getstatic     #1075               // Field alwaysUseFieldBuilders:Z
       3: ireturn

  static java.util.List access$12100(io.grpc.xds.shaded.io.envoyproxy.envoy.config.route.v3.RouteAction);
    Code:
       0: aload_0
       1: getfield      #279                // Field upgradeConfigs_:Ljava/util/List;
       4: areturn

  static boolean access$13200();
    Code:
       0: getstatic     #1075               // Field alwaysUseFieldBuilders:Z
       3: ireturn

  static int access$12300(io.grpc.xds.shaded.io.envoyproxy.envoy.config.route.v3.RouteAction);
    Code:
       0: aload_0
       1: getfield      #281                // Field internalRedirectAction_:I
       4: ireturn

  static java.lang.Object access$10300(io.grpc.xds.shaded.io.envoyproxy.envoy.config.route.v3.RouteAction);
    Code:
       0: aload_0
       1: getfield      #318                // Field clusterSpecifier_:Ljava/lang/Object;
       4: areturn

  static java.lang.Object access$10800(io.grpc.xds.shaded.io.envoyproxy.envoy.config.route.v3.RouteAction);
    Code:
       0: aload_0
       1: getfield      #352                // Field hostRewriteSpecifier_:Ljava/lang/Object;
       4: areturn

  static com.google.protobuf.UnknownFieldSet access$13300(io.grpc.xds.shaded.io.envoyproxy.envoy.config.route.v3.RouteAction);
    Code:
       0: aload_0
       1: getfield      #292                // Field unknownFields:Lcom/google/protobuf/UnknownFieldSet;
       4: areturn

  static com.google.protobuf.Parser access$13400();
    Code:
       0: getstatic     #982                // Field PARSER:Lcom/google/protobuf/Parser;
       3: areturn

  static void access$13500(com.google.protobuf.ByteString) throws java.lang.IllegalArgumentException;
    Code:
       0: aload_0
       1: invokestatic  #1147               // Method checkByteStringIsUtf8:(Lcom/google/protobuf/ByteString;)V
       4: return

  static void access$13600(com.google.protobuf.ByteString) throws java.lang.IllegalArgumentException;
    Code:
       0: aload_0
       1: invokestatic  #1147               // Method checkByteStringIsUtf8:(Lcom/google/protobuf/ByteString;)V
       4: return

  static void access$13700(com.google.protobuf.ByteString) throws java.lang.IllegalArgumentException;
    Code:
       0: aload_0
       1: invokestatic  #1147               // Method checkByteStringIsUtf8:(Lcom/google/protobuf/ByteString;)V
       4: return

  static void access$13800(com.google.protobuf.ByteString) throws java.lang.IllegalArgumentException;
    Code:
       0: aload_0
       1: invokestatic  #1147               // Method checkByteStringIsUtf8:(Lcom/google/protobuf/ByteString;)V
       4: return

  static void access$13900(com.google.protobuf.ByteString) throws java.lang.IllegalArgumentException;
    Code:
       0: aload_0
       1: invokestatic  #1147               // Method checkByteStringIsUtf8:(Lcom/google/protobuf/ByteString;)V
       4: return

  static void access$14000(com.google.protobuf.ByteString) throws java.lang.IllegalArgumentException;
    Code:
       0: aload_0
       1: invokestatic  #1147               // Method checkByteStringIsUtf8:(Lcom/google/protobuf/ByteString;)V
       4: return

  io.grpc.xds.shaded.io.envoyproxy.envoy.config.route.v3.RouteAction(com.google.protobuf.CodedInputStream, com.google.protobuf.ExtensionRegistryLite, io.grpc.xds.shaded.io.envoyproxy.envoy.config.route.v3.RouteAction$1) throws com.google.protobuf.InvalidProtocolBufferException;
    Code:
       0: aload_0
       1: aload_1
       2: aload_2
       3: invokespecial #1155               // Method "<init>":(Lcom/google/protobuf/CodedInputStream;Lcom/google/protobuf/ExtensionRegistryLite;)V
       6: return

  static {};
    Code:
       0: new           #2                  // class io/grpc/xds/shaded/io/envoyproxy/envoy/config/route/v3/RouteAction
       3: dup
       4: invokespecial #284                // Method "<init>":()V
       7: putstatic     #1040               // Field DEFAULT_INSTANCE:Lio/grpc/xds/shaded/io/envoyproxy/envoy/config/route/v3/RouteAction;
      10: new           #50                 // class io/grpc/xds/shaded/io/envoyproxy/envoy/config/route/v3/RouteAction$1
      13: dup
      14: invokespecial #1158               // Method io/grpc/xds/shaded/io/envoyproxy/envoy/config/route/v3/RouteAction$1."<init>":()V
      17: putstatic     #982                // Field PARSER:Lcom/google/protobuf/Parser;
      20: return
}
