Compiled from "OWLDifferentIndividualAxiomFrameSectionRow.java"
public class org.protege.editor.owl.ui.frame.individual.OWLDifferentIndividualAxiomFrameSectionRow extends org.protege.editor.owl.ui.frame.AbstractOWLFrameSectionRow<org.semanticweb.owlapi.model.OWLNamedIndividual, org.semanticweb.owlapi.model.OWLDifferentIndividualsAxiom, java.util.Set<org.semanticweb.owlapi.model.OWLNamedIndividual>> {
  public org.protege.editor.owl.ui.frame.individual.OWLDifferentIndividualAxiomFrameSectionRow(org.protege.editor.owl.OWLEditorKit, org.protege.editor.owl.ui.frame.OWLFrameSection<org.semanticweb.owlapi.model.OWLNamedIndividual, org.semanticweb.owlapi.model.OWLDifferentIndividualsAxiom, java.util.Set<org.semanticweb.owlapi.model.OWLNamedIndividual>>, org.semanticweb.owlapi.model.OWLOntology, org.semanticweb.owlapi.model.OWLNamedIndividual, org.semanticweb.owlapi.model.OWLDifferentIndividualsAxiom);
    Code:
       0: aload_0
       1: aload_1
       2: aload_2
       3: aload_3
       4: aload         4
       6: aload         5
       8: invokespecial #1                  // Method org/protege/editor/owl/ui/frame/AbstractOWLFrameSectionRow."<init>":(Lorg/protege/editor/owl/OWLEditorKit;Lorg/protege/editor/owl/ui/frame/OWLFrameSection;Lorg/semanticweb/owlapi/model/OWLOntology;Ljava/lang/Object;Lorg/semanticweb/owlapi/model/OWLAxiom;)V
      11: return

  protected org.protege.editor.owl.ui.editor.OWLObjectEditor<java.util.Set<org.semanticweb.owlapi.model.OWLNamedIndividual>> getObjectEditor();
    Code:
       0: new           #2                  // class org/protege/editor/owl/ui/editor/OWLIndividualSetEditor
       3: dup
       4: aload_0
       5: invokevirtual #3                  // Method getOWLEditorKit:()Lorg/protege/editor/owl/OWLEditorKit;
       8: invokespecial #4                  // Method org/protege/editor/owl/ui/editor/OWLIndividualSetEditor."<init>":(Lorg/protege/editor/owl/OWLEditorKit;)V
      11: areturn

  public boolean checkEditorResults(org.protege.editor.owl.ui.editor.OWLObjectEditor<java.util.Set<org.semanticweb.owlapi.model.OWLNamedIndividual>>);
    Code:
       0: aload_1
       1: invokeinterface #5,  1            // InterfaceMethod org/protege/editor/owl/ui/editor/OWLObjectEditor.getEditedObject:()Ljava/lang/Object;
       6: checkcast     #6                  // class java/util/Set
       9: astore_2
      10: aload_2
      11: aload_0
      12: invokevirtual #7                  // Method getRootObject:()Ljava/lang/Object;
      15: invokeinterface #8,  2            // InterfaceMethod java/util/Set.contains:(Ljava/lang/Object;)Z
      20: ifne          27
      23: iconst_1
      24: goto          28
      27: iconst_0
      28: ireturn

  protected org.semanticweb.owlapi.model.OWLDifferentIndividualsAxiom createAxiom(java.util.Set<org.semanticweb.owlapi.model.OWLNamedIndividual>);
    Code:
       0: aload_1
       1: aload_0
       2: invokevirtual #7                  // Method getRootObject:()Ljava/lang/Object;
       5: checkcast     #9                  // class org/semanticweb/owlapi/model/OWLNamedIndividual
       8: invokeinterface #10,  2           // InterfaceMethod java/util/Set.add:(Ljava/lang/Object;)Z
      13: pop
      14: aload_0
      15: invokevirtual #11                 // Method getOWLDataFactory:()Lorg/semanticweb/owlapi/model/OWLDataFactory;
      18: aload_1
      19: invokeinterface #12,  2           // InterfaceMethod org/semanticweb/owlapi/model/OWLDataFactory.getOWLDifferentIndividualsAxiom:(Ljava/util/Set;)Lorg/semanticweb/owlapi/model/OWLDifferentIndividualsAxiom;
      24: areturn

  public java.util.List<org.semanticweb.owlapi.model.OWLNamedIndividual> getManipulatableObjects();
    Code:
       0: aload_0
       1: invokevirtual #13                 // Method getAxiom:()Lorg/semanticweb/owlapi/model/OWLAxiom;
       4: checkcast     #14                 // class org/semanticweb/owlapi/model/OWLDifferentIndividualsAxiom
       7: invokeinterface #15,  1           // InterfaceMethod org/semanticweb/owlapi/model/OWLDifferentIndividualsAxiom.getIndividuals:()Ljava/util/Set;
      12: astore_1
      13: new           #16                 // class java/util/ArrayList
      16: dup
      17: invokespecial #17                 // Method java/util/ArrayList."<init>":()V
      20: astore_2
      21: aload_1
      22: invokeinterface #18,  1           // InterfaceMethod java/util/Set.iterator:()Ljava/util/Iterator;
      27: astore_3
      28: aload_3
      29: invokeinterface #19,  1           // InterfaceMethod java/util/Iterator.hasNext:()Z
      34: ifeq          87
      37: aload_3
      38: invokeinterface #20,  1           // InterfaceMethod java/util/Iterator.next:()Ljava/lang/Object;
      43: checkcast     #21                 // class org/semanticweb/owlapi/model/OWLIndividual
      46: astore        4
      48: aload         4
      50: invokeinterface #22,  1           // InterfaceMethod org/semanticweb/owlapi/model/OWLIndividual.isAnonymous:()Z
      55: ifne          84
      58: aload         4
      60: aload_0
      61: invokevirtual #7                  // Method getRootObject:()Ljava/lang/Object;
      64: invokevirtual #23                 // Method java/lang/Object.equals:(Ljava/lang/Object;)Z
      67: ifne          84
      70: aload_2
      71: aload         4
      73: invokeinterface #24,  1           // InterfaceMethod org/semanticweb/owlapi/model/OWLIndividual.asOWLNamedIndividual:()Lorg/semanticweb/owlapi/model/OWLNamedIndividual;
      78: invokeinterface #25,  2           // InterfaceMethod java/util/List.add:(Ljava/lang/Object;)Z
      83: pop
      84: goto          28
      87: aload_2
      88: areturn

  protected org.semanticweb.owlapi.model.OWLAxiom createAxiom(java.lang.Object);
    Code:
       0: aload_0
       1: aload_1
       2: checkcast     #6                  // class java/util/Set
       5: invokevirtual #26                 // Method createAxiom:(Ljava/util/Set;)Lorg/semanticweb/owlapi/model/OWLDifferentIndividualsAxiom;
       8: areturn
}
