Compiled from "OWLObjectPropertyAssertionAxiomFrameSection.java"
public class org.protege.editor.owl.ui.frame.individual.OWLObjectPropertyAssertionAxiomFrameSection extends org.protege.editor.owl.ui.frame.AbstractOWLFrameSection<org.semanticweb.owlapi.model.OWLIndividual, org.semanticweb.owlapi.model.OWLObjectPropertyAssertionAxiom, org.protege.editor.owl.ui.frame.OWLObjectPropertyIndividualPair> {
  public static final java.lang.String LABEL;

  private final java.util.Set<org.semanticweb.owlapi.model.OWLObjectPropertyAssertionAxiom> added;

  private final org.protege.editor.owl.ui.editor.OWLObjectPropertyIndividualPairEditor2 editor;

  public org.protege.editor.owl.ui.frame.individual.OWLObjectPropertyAssertionAxiomFrameSection(org.protege.editor.owl.OWLEditorKit, org.protege.editor.owl.ui.frame.OWLFrame<? extends org.semanticweb.owlapi.model.OWLIndividual>);
    Code:
       0: aload_0
       1: aload_1
       2: ldc           #2                  // String Object property assertions
       4: ldc           #3                  // String Object property assertion
       6: aload_2
       7: invokespecial #4                  // Method org/protege/editor/owl/ui/frame/AbstractOWLFrameSection."<init>":(Lorg/protege/editor/owl/OWLEditorKit;Ljava/lang/String;Ljava/lang/String;Lorg/protege/editor/owl/ui/frame/OWLFrame;)V
      10: aload_0
      11: new           #5                  // class java/util/HashSet
      14: dup
      15: invokespecial #6                  // Method java/util/HashSet."<init>":()V
      18: putfield      #7                  // Field added:Ljava/util/Set;
      21: aload_0
      22: new           #8                  // class org/protege/editor/owl/ui/editor/OWLObjectPropertyIndividualPairEditor2
      25: dup
      26: aload_0
      27: invokevirtual #9                  // Method getOWLEditorKit:()Lorg/protege/editor/owl/OWLEditorKit;
      30: invokespecial #10                 // Method org/protege/editor/owl/ui/editor/OWLObjectPropertyIndividualPairEditor2."<init>":(Lorg/protege/editor/owl/OWLEditorKit;)V
      33: putfield      #11                 // Field editor:Lorg/protege/editor/owl/ui/editor/OWLObjectPropertyIndividualPairEditor2;
      36: return

  protected void clear();
    Code:
       0: aload_0
       1: getfield      #7                  // Field added:Ljava/util/Set;
       4: invokeinterface #12,  1           // InterfaceMethod java/util/Set.clear:()V
       9: return

  protected void refill(org.semanticweb.owlapi.model.OWLOntology);
    Code:
       0: aload_1
       1: aload_0
       2: invokevirtual #13                 // Method getRootObject:()Ljava/lang/Object;
       5: checkcast     #14                 // class org/semanticweb/owlapi/model/OWLIndividual
       8: invokeinterface #15,  2           // InterfaceMethod org/semanticweb/owlapi/model/OWLOntology.getObjectPropertyAssertionAxioms:(Lorg/semanticweb/owlapi/model/OWLIndividual;)Ljava/util/Set;
      13: invokeinterface #16,  1           // InterfaceMethod java/util/Set.iterator:()Ljava/util/Iterator;
      18: astore_2
      19: aload_2
      20: invokeinterface #17,  1           // InterfaceMethod java/util/Iterator.hasNext:()Z
      25: ifeq          77
      28: aload_2
      29: invokeinterface #18,  1           // InterfaceMethod java/util/Iterator.next:()Ljava/lang/Object;
      34: checkcast     #19                 // class org/semanticweb/owlapi/model/OWLObjectPropertyAssertionAxiom
      37: astore_3
      38: aload_0
      39: new           #20                 // class org/protege/editor/owl/ui/frame/individual/OWLObjectPropertyAssertionAxiomFrameSectionRow
      42: dup
      43: aload_0
      44: invokevirtual #9                  // Method getOWLEditorKit:()Lorg/protege/editor/owl/OWLEditorKit;
      47: aload_0
      48: aload_1
      49: aload_0
      50: invokevirtual #13                 // Method getRootObject:()Ljava/lang/Object;
      53: checkcast     #14                 // class org/semanticweb/owlapi/model/OWLIndividual
      56: aload_3
      57: invokespecial #21                 // Method org/protege/editor/owl/ui/frame/individual/OWLObjectPropertyAssertionAxiomFrameSectionRow."<init>":(Lorg/protege/editor/owl/OWLEditorKit;Lorg/protege/editor/owl/ui/frame/OWLFrameSection;Lorg/semanticweb/owlapi/model/OWLOntology;Lorg/semanticweb/owlapi/model/OWLIndividual;Lorg/semanticweb/owlapi/model/OWLObjectPropertyAssertionAxiom;)V
      60: invokevirtual #22                 // Method addRow:(Lorg/protege/editor/owl/ui/frame/OWLFrameSectionRow;)V
      63: aload_0
      64: getfield      #7                  // Field added:Ljava/util/Set;
      67: aload_3
      68: invokeinterface #23,  2           // InterfaceMethod java/util/Set.add:(Ljava/lang/Object;)Z
      73: pop
      74: goto          19
      77: return

  protected void refillInferred();
    Code:
       0: aload_0
       1: invokevirtual #24                 // Method getOWLModelManager:()Lorg/protege/editor/owl/model/OWLModelManager;
       4: invokeinterface #25,  1           // InterfaceMethod org/protege/editor/owl/model/OWLModelManager.getReasonerPreferences:()Lorg/protege/editor/owl/model/inference/ReasonerPreferences;
       9: getstatic     #26                 // Field org/protege/editor/owl/model/inference/ReasonerPreferences$OptionalInferenceTask.SHOW_INFERRED_OBJECT_PROPERTY_ASSERTIONS:Lorg/protege/editor/owl/model/inference/ReasonerPreferences$OptionalInferenceTask;
      12: aload_0
      13: invokedynamic #27,  0             // InvokeDynamic #0:run:(Lorg/protege/editor/owl/ui/frame/individual/OWLObjectPropertyAssertionAxiomFrameSection;)Ljava/lang/Runnable;
      18: invokevirtual #28                 // Method org/protege/editor/owl/model/inference/ReasonerPreferences.executeTask:(Lorg/protege/editor/owl/model/inference/ReasonerPreferences$OptionalInferenceTask;Ljava/lang/Runnable;)V
      21: return

  protected org.semanticweb.owlapi.model.OWLObjectPropertyAssertionAxiom createAxiom(org.protege.editor.owl.ui.frame.OWLObjectPropertyIndividualPair);
    Code:
       0: aload_0
       1: invokevirtual #29                 // Method getOWLDataFactory:()Lorg/semanticweb/owlapi/model/OWLDataFactory;
       4: aload_1
       5: invokevirtual #30                 // Method org/protege/editor/owl/ui/frame/OWLObjectPropertyIndividualPair.getProperty:()Lorg/semanticweb/owlapi/model/OWLObjectPropertyExpression;
       8: aload_0
       9: invokevirtual #13                 // Method getRootObject:()Ljava/lang/Object;
      12: checkcast     #14                 // class org/semanticweb/owlapi/model/OWLIndividual
      15: aload_1
      16: invokevirtual #31                 // Method org/protege/editor/owl/ui/frame/OWLObjectPropertyIndividualPair.getIndividual:()Lorg/semanticweb/owlapi/model/OWLIndividual;
      19: invokeinterface #32,  4           // InterfaceMethod org/semanticweb/owlapi/model/OWLDataFactory.getOWLObjectPropertyAssertionAxiom:(Lorg/semanticweb/owlapi/model/OWLObjectPropertyExpression;Lorg/semanticweb/owlapi/model/OWLIndividual;Lorg/semanticweb/owlapi/model/OWLIndividual;)Lorg/semanticweb/owlapi/model/OWLObjectPropertyAssertionAxiom;
      24: areturn

  public org.protege.editor.owl.ui.editor.OWLObjectEditor<org.protege.editor.owl.ui.frame.OWLObjectPropertyIndividualPair> getObjectEditor();
    Code:
       0: aload_0
       1: getfield      #11                 // Field editor:Lorg/protege/editor/owl/ui/editor/OWLObjectPropertyIndividualPairEditor2;
       4: areturn

  public java.util.Comparator<org.protege.editor.owl.ui.frame.OWLFrameSectionRow<org.semanticweb.owlapi.model.OWLIndividual, org.semanticweb.owlapi.model.OWLObjectPropertyAssertionAxiom, org.protege.editor.owl.ui.frame.OWLObjectPropertyIndividualPair>> getRowComparator();
    Code:
       0: aconst_null
       1: areturn

  protected boolean isResettingChange(org.semanticweb.owlapi.model.OWLOntologyChange);
    Code:
       0: aload_1
       1: invokevirtual #33                 // Method org/semanticweb/owlapi/model/OWLOntologyChange.isAxiomChange:()Z
       4: ifne          9
       7: iconst_0
       8: ireturn
       9: aload_1
      10: invokevirtual #34                 // Method org/semanticweb/owlapi/model/OWLOntologyChange.getAxiom:()Lorg/semanticweb/owlapi/model/OWLAxiom;
      13: astore_2
      14: aload_2
      15: instanceof    #19                 // class org/semanticweb/owlapi/model/OWLObjectPropertyAssertionAxiom
      18: ifeq          38
      21: aload_2
      22: checkcast     #19                 // class org/semanticweb/owlapi/model/OWLObjectPropertyAssertionAxiom
      25: invokeinterface #35,  1           // InterfaceMethod org/semanticweb/owlapi/model/OWLObjectPropertyAssertionAxiom.getSubject:()Lorg/semanticweb/owlapi/model/OWLIndividual;
      30: aload_0
      31: invokevirtual #13                 // Method getRootObject:()Ljava/lang/Object;
      34: invokevirtual #36                 // Method java/lang/Object.equals:(Ljava/lang/Object;)Z
      37: ireturn
      38: iconst_0
      39: ireturn

  protected org.semanticweb.owlapi.model.OWLAxiom createAxiom(java.lang.Object);
    Code:
       0: aload_0
       1: aload_1
       2: checkcast     #37                 // class org/protege/editor/owl/ui/frame/OWLObjectPropertyIndividualPair
       5: invokevirtual #38                 // Method createAxiom:(Lorg/protege/editor/owl/ui/frame/OWLObjectPropertyIndividualPair;)Lorg/semanticweb/owlapi/model/OWLObjectPropertyAssertionAxiom;
       8: areturn

  private void lambda$refillInferred$0();
    Code:
       0: aload_0
       1: invokevirtual #24                 // Method getOWLModelManager:()Lorg/protege/editor/owl/model/OWLModelManager;
       4: invokeinterface #39,  1           // InterfaceMethod org/protege/editor/owl/model/OWLModelManager.getReasoner:()Lorg/semanticweb/owlapi/reasoner/OWLReasoner;
       9: invokeinterface #40,  1           // InterfaceMethod org/semanticweb/owlapi/reasoner/OWLReasoner.isConsistent:()Z
      14: ifne          18
      17: return
      18: aload_0
      19: invokevirtual #29                 // Method getOWLDataFactory:()Lorg/semanticweb/owlapi/model/OWLDataFactory;
      22: astore_1
      23: aload_0
      24: invokevirtual #13                 // Method getRootObject:()Ljava/lang/Object;
      27: checkcast     #14                 // class org/semanticweb/owlapi/model/OWLIndividual
      30: invokeinterface #41,  1           // InterfaceMethod org/semanticweb/owlapi/model/OWLIndividual.isAnonymous:()Z
      35: ifne          221
      38: aload_0
      39: invokevirtual #42                 // Method getReasoner:()Lorg/semanticweb/owlapi/reasoner/OWLReasoner;
      42: invokeinterface #43,  1           // InterfaceMethod org/semanticweb/owlapi/reasoner/OWLReasoner.getRootOntology:()Lorg/semanticweb/owlapi/model/OWLOntology;
      47: iconst_1
      48: invokeinterface #44,  2           // InterfaceMethod org/semanticweb/owlapi/model/OWLOntology.getObjectPropertiesInSignature:(Z)Ljava/util/Set;
      53: invokeinterface #16,  1           // InterfaceMethod java/util/Set.iterator:()Ljava/util/Iterator;
      58: astore_2
      59: aload_2
      60: invokeinterface #17,  1           // InterfaceMethod java/util/Iterator.hasNext:()Z
      65: ifeq          221
      68: aload_2
      69: invokeinterface #18,  1           // InterfaceMethod java/util/Iterator.next:()Ljava/lang/Object;
      74: checkcast     #45                 // class org/semanticweb/owlapi/model/OWLObjectProperty
      77: astore_3
      78: aload_3
      79: aload_1
      80: invokeinterface #46,  1           // InterfaceMethod org/semanticweb/owlapi/model/OWLDataFactory.getOWLTopObjectProperty:()Lorg/semanticweb/owlapi/model/OWLObjectProperty;
      85: invokevirtual #36                 // Method java/lang/Object.equals:(Ljava/lang/Object;)Z
      88: ifeq          94
      91: goto          59
      94: aload_0
      95: invokevirtual #42                 // Method getReasoner:()Lorg/semanticweb/owlapi/reasoner/OWLReasoner;
      98: aload_0
      99: invokevirtual #13                 // Method getRootObject:()Ljava/lang/Object;
     102: checkcast     #14                 // class org/semanticweb/owlapi/model/OWLIndividual
     105: invokeinterface #47,  1           // InterfaceMethod org/semanticweb/owlapi/model/OWLIndividual.asOWLNamedIndividual:()Lorg/semanticweb/owlapi/model/OWLNamedIndividual;
     110: aload_3
     111: invokeinterface #48,  3           // InterfaceMethod org/semanticweb/owlapi/reasoner/OWLReasoner.getObjectPropertyValues:(Lorg/semanticweb/owlapi/model/OWLNamedIndividual;Lorg/semanticweb/owlapi/model/OWLObjectPropertyExpression;)Lorg/semanticweb/owlapi/reasoner/NodeSet;
     116: astore        4
     118: aload         4
     120: invokeinterface #49,  1           // InterfaceMethod org/semanticweb/owlapi/reasoner/NodeSet.getFlattened:()Ljava/util/Set;
     125: invokeinterface #16,  1           // InterfaceMethod java/util/Set.iterator:()Ljava/util/Iterator;
     130: astore        5
     132: aload         5
     134: invokeinterface #17,  1           // InterfaceMethod java/util/Iterator.hasNext:()Z
     139: ifeq          218
     142: aload         5
     144: invokeinterface #18,  1           // InterfaceMethod java/util/Iterator.next:()Ljava/lang/Object;
     149: checkcast     #50                 // class org/semanticweb/owlapi/model/OWLNamedIndividual
     152: astore        6
     154: aload_0
     155: invokevirtual #29                 // Method getOWLDataFactory:()Lorg/semanticweb/owlapi/model/OWLDataFactory;
     158: aload_3
     159: aload_0
     160: invokevirtual #13                 // Method getRootObject:()Ljava/lang/Object;
     163: checkcast     #14                 // class org/semanticweb/owlapi/model/OWLIndividual
     166: aload         6
     168: invokeinterface #32,  4           // InterfaceMethod org/semanticweb/owlapi/model/OWLDataFactory.getOWLObjectPropertyAssertionAxiom:(Lorg/semanticweb/owlapi/model/OWLObjectPropertyExpression;Lorg/semanticweb/owlapi/model/OWLIndividual;Lorg/semanticweb/owlapi/model/OWLIndividual;)Lorg/semanticweb/owlapi/model/OWLObjectPropertyAssertionAxiom;
     173: astore        7
     175: aload_0
     176: getfield      #7                  // Field added:Ljava/util/Set;
     179: aload         7
     181: invokeinterface #51,  2           // InterfaceMethod java/util/Set.contains:(Ljava/lang/Object;)Z
     186: ifne          215
     189: aload_0
     190: new           #20                 // class org/protege/editor/owl/ui/frame/individual/OWLObjectPropertyAssertionAxiomFrameSectionRow
     193: dup
     194: aload_0
     195: invokevirtual #9                  // Method getOWLEditorKit:()Lorg/protege/editor/owl/OWLEditorKit;
     198: aload_0
     199: aconst_null
     200: aload_0
     201: invokevirtual #13                 // Method getRootObject:()Ljava/lang/Object;
     204: checkcast     #14                 // class org/semanticweb/owlapi/model/OWLIndividual
     207: aload         7
     209: invokespecial #21                 // Method org/protege/editor/owl/ui/frame/individual/OWLObjectPropertyAssertionAxiomFrameSectionRow."<init>":(Lorg/protege/editor/owl/OWLEditorKit;Lorg/protege/editor/owl/ui/frame/OWLFrameSection;Lorg/semanticweb/owlapi/model/OWLOntology;Lorg/semanticweb/owlapi/model/OWLIndividual;Lorg/semanticweb/owlapi/model/OWLObjectPropertyAssertionAxiom;)V
     212: invokevirtual #22                 // Method addRow:(Lorg/protege/editor/owl/ui/frame/OWLFrameSectionRow;)V
     215: goto          132
     218: goto          59
     221: return
}
