Compiled from "SendReplyResponder.scala"
public interface de.sciss.synth.proc.graph.impl.SendReplyResponder extends de.sciss.lucre.synth.DynamicUser {
  public static void $init$(de.sciss.synth.proc.graph.impl.SendReplyResponder);
    Code:
       0: aload_0
       1: getstatic     #21                 // Field scala/concurrent/stm/Ref$.MODULE$:Lscala/concurrent/stm/Ref$;
       4: iconst_0
       5: invokevirtual #25                 // Method scala/concurrent/stm/Ref$.apply:(Z)Lscala/concurrent/stm/Ref;
       8: invokeinterface #29,  2           // InterfaceMethod de$sciss$synth$proc$graph$impl$SendReplyResponder$_setter_$de$sciss$synth$proc$graph$impl$SendReplyResponder$$_added_$eq:(Lscala/concurrent/stm/Ref;)V
      13: return

  public abstract de.sciss.lucre.synth.Synth synth();

  public abstract void added(de.sciss.lucre.synth.RT);

  public abstract scala.PartialFunction body();

  public static de.sciss.synth.message.Responder de$sciss$synth$proc$graph$impl$SendReplyResponder$$trigResp$(de.sciss.synth.proc.graph.impl.SendReplyResponder);
    Code:
       0: aload_0
       1: invokespecial #43                 // InterfaceMethod de$sciss$synth$proc$graph$impl$SendReplyResponder$$trigResp:()Lde/sciss/synth/message/Responder;
       4: areturn

  public default de.sciss.synth.message.Responder de$sciss$synth$proc$graph$impl$SendReplyResponder$$trigResp();
    Code:
       0: getstatic     #48                 // Field de/sciss/synth/message/Responder$.MODULE$:Lde/sciss/synth/message/Responder$;
       3: aload_0
       4: invokeinterface #50,  1           // InterfaceMethod synth:()Lde/sciss/lucre/synth/Synth;
       9: invokeinterface #56,  1           // InterfaceMethod de/sciss/lucre/synth/Synth.server:()Lde/sciss/lucre/synth/Server;
      14: invokeinterface #62,  1           // InterfaceMethod de/sciss/lucre/synth/Server.peer:()Lde/sciss/synth/Server;
      19: aload_0
      20: invokeinterface #64,  1           // InterfaceMethod body:()Lscala/PartialFunction;
      25: invokevirtual #67                 // Method de/sciss/synth/message/Responder$.apply:(Lde/sciss/synth/Server;Lscala/PartialFunction;)Lde/sciss/synth/message/Responder;
      28: areturn

  public abstract scala.concurrent.stm.Ref<java.lang.Object> de$sciss$synth$proc$graph$impl$SendReplyResponder$$_added();

  public abstract void de$sciss$synth$proc$graph$impl$SendReplyResponder$_setter_$de$sciss$synth$proc$graph$impl$SendReplyResponder$$_added_$eq(scala.concurrent.stm.Ref);

  public static void add$(de.sciss.synth.proc.graph.impl.SendReplyResponder, de.sciss.lucre.synth.RT);
    Code:
       0: aload_0
       1: aload_1
       2: invokespecial #77                 // InterfaceMethod add:(Lde/sciss/lucre/synth/RT;)V
       5: return

  public default void add(de.sciss.lucre.synth.RT);
    Code:
       0: aload_0
       1: invokeinterface #80,  1           // InterfaceMethod de$sciss$synth$proc$graph$impl$SendReplyResponder$$_added:()Lscala/concurrent/stm/Ref;
       6: iconst_1
       7: invokestatic  #86                 // Method scala/runtime/BoxesRunTime.boxToBoolean:(Z)Ljava/lang/Boolean;
      10: aload_1
      11: invokeinterface #91,  1           // InterfaceMethod de/sciss/lucre/synth/RT.peer:()Lscala/concurrent/stm/InTxn;
      16: invokeinterface #97,  3           // InterfaceMethod scala/concurrent/stm/Ref.swap:(Ljava/lang/Object;Ljava/lang/Object;)Ljava/lang/Object;
      21: invokestatic  #101                // Method scala/runtime/BoxesRunTime.unboxToBoolean:(Ljava/lang/Object;)Z
      24: ifne          64
      27: aload_0
      28: invokeinterface #43,  1           // InterfaceMethod de$sciss$synth$proc$graph$impl$SendReplyResponder$$trigResp:()Lde/sciss/synth/message/Responder;
      33: invokeinterface #105,  1          // InterfaceMethod de/sciss/synth/message/Responder.add:()Lde/sciss/synth/message/Responder;
      38: pop
      39: getstatic     #110                // Field scala/concurrent/stm/Txn$.MODULE$:Lscala/concurrent/stm/Txn$;
      42: aload_0
      43: invokedynamic #131,  0            // InvokeDynamic #0:applyVoid:(Lde/sciss/synth/proc/graph/impl/SendReplyResponder;)Lscala/runtime/function/JProcedure1;
      48: aload_1
      49: invokeinterface #91,  1           // InterfaceMethod de/sciss/lucre/synth/RT.peer:()Lscala/concurrent/stm/InTxn;
      54: invokevirtual #135                // Method scala/concurrent/stm/Txn$.afterRollback:(Lscala/Function1;Lscala/concurrent/stm/InTxnEnd;)V
      57: aload_0
      58: aload_1
      59: invokeinterface #137,  2          // InterfaceMethod added:(Lde/sciss/lucre/synth/RT;)V
      64: return

  public static void remove$(de.sciss.synth.proc.graph.impl.SendReplyResponder, de.sciss.lucre.synth.RT);
    Code:
       0: aload_0
       1: aload_1
       2: invokespecial #141                // InterfaceMethod remove:(Lde/sciss/lucre/synth/RT;)V
       5: return

  public default void remove(de.sciss.lucre.synth.RT);
    Code:
       0: aload_0
       1: invokeinterface #80,  1           // InterfaceMethod de$sciss$synth$proc$graph$impl$SendReplyResponder$$_added:()Lscala/concurrent/stm/Ref;
       6: iconst_0
       7: invokestatic  #86                 // Method scala/runtime/BoxesRunTime.boxToBoolean:(Z)Ljava/lang/Boolean;
      10: aload_1
      11: invokeinterface #91,  1           // InterfaceMethod de/sciss/lucre/synth/RT.peer:()Lscala/concurrent/stm/InTxn;
      16: invokeinterface #97,  3           // InterfaceMethod scala/concurrent/stm/Ref.swap:(Ljava/lang/Object;Ljava/lang/Object;)Ljava/lang/Object;
      21: invokestatic  #101                // Method scala/runtime/BoxesRunTime.unboxToBoolean:(Ljava/lang/Object;)Z
      24: ifeq          57
      27: aload_0
      28: invokeinterface #43,  1           // InterfaceMethod de$sciss$synth$proc$graph$impl$SendReplyResponder$$trigResp:()Lde/sciss/synth/message/Responder;
      33: invokeinterface #143,  1          // InterfaceMethod de/sciss/synth/message/Responder.remove:()Lde/sciss/synth/message/Responder;
      38: pop
      39: getstatic     #110                // Field scala/concurrent/stm/Txn$.MODULE$:Lscala/concurrent/stm/Txn$;
      42: aload_0
      43: invokedynamic #148,  0            // InvokeDynamic #1:applyVoid:(Lde/sciss/synth/proc/graph/impl/SendReplyResponder;)Lscala/runtime/function/JProcedure1;
      48: aload_1
      49: invokeinterface #91,  1           // InterfaceMethod de/sciss/lucre/synth/RT.peer:()Lscala/concurrent/stm/InTxn;
      54: invokevirtual #135                // Method scala/concurrent/stm/Txn$.afterRollback:(Lscala/Function1;Lscala/concurrent/stm/InTxnEnd;)V
      57: return

  private void add$$anonfun$1(scala.concurrent.stm.Txn$Status);
    Code:
       0: aload_0
       1: invokeinterface #43,  1           // InterfaceMethod de$sciss$synth$proc$graph$impl$SendReplyResponder$$trigResp:()Lde/sciss/synth/message/Responder;
       6: invokeinterface #143,  1          // InterfaceMethod de/sciss/synth/message/Responder.remove:()Lde/sciss/synth/message/Responder;
      11: pop
      12: return

  private void remove$$anonfun$1(scala.concurrent.stm.Txn$Status);
    Code:
       0: aload_0
       1: invokeinterface #43,  1           // InterfaceMethod de$sciss$synth$proc$graph$impl$SendReplyResponder$$trigResp:()Lde/sciss/synth/message/Responder;
       6: invokeinterface #105,  1          // InterfaceMethod de/sciss/synth/message/Responder.add:()Lde/sciss/synth/message/Responder;
      11: pop
      12: return

  private static java.lang.Object $deserializeLambda$(java.lang.invoke.SerializedLambda);
    Code:
       0: aload_0
       1: invokedynamic #163,  0            // InvokeDynamic #2:lambdaDeserialize:(Ljava/lang/invoke/SerializedLambda;)Ljava/lang/Object;
       6: areturn
}
