Compiled from "UpgradeServletOutputStream.java"
class io.undertow.servlet.spec.UpgradeServletOutputStream$1 implements java.lang.Runnable {
  final io.undertow.servlet.spec.UpgradeServletOutputStream this$0;

  io.undertow.servlet.spec.UpgradeServletOutputStream$1(io.undertow.servlet.spec.UpgradeServletOutputStream);
    Code:
       0: aload_0
       1: aload_1
       2: putfield      #1                  // Field this$0:Lio/undertow/servlet/spec/UpgradeServletOutputStream;
       5: aload_0
       6: invokespecial #2                  // Method java/lang/Object."<init>":()V
       9: return

  public void run();
    Code:
       0: aload_0
       1: getfield      #1                  // Field this$0:Lio/undertow/servlet/spec/UpgradeServletOutputStream;
       4: invokestatic  #3                  // Method io/undertow/servlet/spec/UpgradeServletOutputStream.access$000:(Lio/undertow/servlet/spec/UpgradeServletOutputStream;)Lorg/xnio/channels/StreamSinkChannel;
       7: invokeinterface #4,  1            // InterfaceMethod org/xnio/channels/StreamSinkChannel.resumeWrites:()V
      12: return
}
