Compiled from "CompilationUnit.java"
class org.codehaus.groovy.control.CompilationUnit$10 extends org.codehaus.groovy.control.CompilationUnit$PrimaryClassNodeOperation {
  final java.lang.String val$name;

  final org.codehaus.groovy.ast.ClassNode[] val$result;

  final org.codehaus.groovy.control.CompilationUnit this$0;

  org.codehaus.groovy.control.CompilationUnit$10(org.codehaus.groovy.control.CompilationUnit, java.lang.String, org.codehaus.groovy.ast.ClassNode[]);
    Code:
       0: aload_0
       1: aload_1
       2: putfield      #21                 // Field this$0:Lorg/codehaus/groovy/control/CompilationUnit;
       5: aload_0
       6: aload_2
       7: putfield      #23                 // Field val$name:Ljava/lang/String;
      10: aload_0
      11: aload_3
      12: putfield      #25                 // Field val$result:[Lorg/codehaus/groovy/ast/ClassNode;
      15: aload_0
      16: invokespecial #28                 // Method org/codehaus/groovy/control/CompilationUnit$PrimaryClassNodeOperation."<init>":()V
      19: return

  public void call(org.codehaus.groovy.control.SourceUnit, org.codehaus.groovy.classgen.GeneratorContext, org.codehaus.groovy.ast.ClassNode);
    Code:
       0: aload_3
       1: invokevirtual #38                 // Method org/codehaus/groovy/ast/ClassNode.getName:()Ljava/lang/String;
       4: aload_0
       5: getfield      #23                 // Field val$name:Ljava/lang/String;
       8: invokevirtual #44                 // Method java/lang/String.equals:(Ljava/lang/Object;)Z
      11: ifeq          21
      14: aload_0
      15: getfield      #25                 // Field val$result:[Lorg/codehaus/groovy/ast/ClassNode;
      18: iconst_0
      19: aload_3
      20: aastore
      21: return
}
