Compiled from "CompilationUnit.java"
class org.codehaus.groovy.control.CompilationUnit$14 extends org.codehaus.groovy.control.CompilationUnit$SourceUnitOperation {
  final org.codehaus.groovy.control.CompilationUnit this$0;

  org.codehaus.groovy.control.CompilationUnit$14(org.codehaus.groovy.control.CompilationUnit);
    Code:
       0: aload_0
       1: aload_1
       2: putfield      #17                 // Field this$0:Lorg/codehaus/groovy/control/CompilationUnit;
       5: aload_0
       6: invokespecial #20                 // Method org/codehaus/groovy/control/CompilationUnit$SourceUnitOperation."<init>":()V
       9: return

  public void call(org.codehaus.groovy.control.SourceUnit) throws org.codehaus.groovy.control.CompilationFailedException;
    Code:
       0: aload_1
       1: invokevirtual #31                 // Method org/codehaus/groovy/control/SourceUnit.convert:()V
       4: aload_0
       5: getfield      #17                 // Field this$0:Lorg/codehaus/groovy/control/CompilationUnit;
       8: getfield      #35                 // Field org/codehaus/groovy/control/CompilationUnit.ast:Lorg/codehaus/groovy/ast/CompileUnit;
      11: aload_1
      12: invokevirtual #39                 // Method org/codehaus/groovy/control/SourceUnit.getAST:()Lorg/codehaus/groovy/ast/ModuleNode;
      15: invokevirtual #45                 // Method org/codehaus/groovy/ast/CompileUnit.addModule:(Lorg/codehaus/groovy/ast/ModuleNode;)V
      18: aload_0
      19: getfield      #17                 // Field this$0:Lorg/codehaus/groovy/control/CompilationUnit;
      22: getfield      #49                 // Field org/codehaus/groovy/control/CompilationUnit.progressCallback:Lorg/codehaus/groovy/control/CompilationUnit$ProgressCallback;
      25: ifnull        46
      28: aload_0
      29: getfield      #17                 // Field this$0:Lorg/codehaus/groovy/control/CompilationUnit;
      32: getfield      #49                 // Field org/codehaus/groovy/control/CompilationUnit.progressCallback:Lorg/codehaus/groovy/control/CompilationUnit$ProgressCallback;
      35: aload_1
      36: aload_0
      37: getfield      #17                 // Field this$0:Lorg/codehaus/groovy/control/CompilationUnit;
      40: getfield      #53                 // Field org/codehaus/groovy/control/CompilationUnit.phase:I
      43: invokevirtual #56                 // Method org/codehaus/groovy/control/CompilationUnit$ProgressCallback.call:(Lorg/codehaus/groovy/control/ProcessingUnit;I)V
      46: return
}
