Compiled from "ProcessingUnit.java"
class org.codehaus.groovy.control.ProcessingUnit$1 implements java.security.PrivilegedAction<groovy.lang.GroovyClassLoader> {
  final groovy.lang.GroovyClassLoader val$loader;

  final org.codehaus.groovy.control.ProcessingUnit this$0;

  org.codehaus.groovy.control.ProcessingUnit$1(org.codehaus.groovy.control.ProcessingUnit, groovy.lang.GroovyClassLoader);
    Code:
       0: aload_0
       1: aload_1
       2: putfield      #21                 // Field this$0:Lorg/codehaus/groovy/control/ProcessingUnit;
       5: aload_0
       6: aload_2
       7: putfield      #23                 // Field val$loader:Lgroovy/lang/GroovyClassLoader;
      10: aload_0
      11: invokespecial #26                 // Method java/lang/Object."<init>":()V
      14: return

  public groovy.lang.GroovyClassLoader run();
    Code:
       0: invokestatic  #36                 // Method java/lang/Thread.currentThread:()Ljava/lang/Thread;
       3: invokevirtual #40                 // Method java/lang/Thread.getContextClassLoader:()Ljava/lang/ClassLoader;
       6: astore_1
       7: aload_1
       8: ifnonnull     17
      11: ldc           #10                 // class org/codehaus/groovy/control/ProcessingUnit
      13: invokevirtual #45                 // Method java/lang/Class.getClassLoader:()Ljava/lang/ClassLoader;
      16: astore_1
      17: aload_0
      18: getfield      #23                 // Field val$loader:Lgroovy/lang/GroovyClassLoader;
      21: ifnonnull     42
      24: new           #49                 // class groovy/lang/GroovyClassLoader
      27: dup
      28: aload_1
      29: aload_0
      30: getfield      #21                 // Field this$0:Lorg/codehaus/groovy/control/ProcessingUnit;
      33: getfield      #53                 // Field org/codehaus/groovy/control/ProcessingUnit.configuration:Lorg/codehaus/groovy/control/CompilerConfiguration;
      36: invokespecial #56                 // Method groovy/lang/GroovyClassLoader."<init>":(Ljava/lang/ClassLoader;Lorg/codehaus/groovy/control/CompilerConfiguration;)V
      39: goto          46
      42: aload_0
      43: getfield      #23                 // Field val$loader:Lgroovy/lang/GroovyClassLoader;
      46: areturn

  public java.lang.Object run();
    Code:
       0: aload_0
       1: invokevirtual #61                 // Method run:()Lgroovy/lang/GroovyClassLoader;
       4: areturn
}
