Compiled from "ProcessingUnit.java"
public abstract class org.codehaus.groovy.control.ProcessingUnit {
  protected int phase;

  protected boolean phaseComplete;

  protected org.codehaus.groovy.control.CompilerConfiguration configuration;

  protected groovy.lang.GroovyClassLoader classLoader;

  protected org.codehaus.groovy.control.ErrorCollector errorCollector;

  public org.codehaus.groovy.control.ProcessingUnit(org.codehaus.groovy.control.CompilerConfiguration, groovy.lang.GroovyClassLoader, org.codehaus.groovy.control.ErrorCollector);
    Code:
       0: aload_0
       1: invokespecial #22                 // Method java/lang/Object."<init>":()V
       4: aload_0
       5: iconst_1
       6: putfield      #24                 // Field phase:I
       9: aload_0
      10: aload_1
      11: putfield      #26                 // Field configuration:Lorg/codehaus/groovy/control/CompilerConfiguration;
      14: aload_0
      15: aload_2
      16: invokevirtual #30                 // Method setClassLoader:(Lgroovy/lang/GroovyClassLoader;)V
      19: aload_0
      20: aload_1
      21: ifnonnull     34
      24: new           #32                 // class org/codehaus/groovy/control/CompilerConfiguration
      27: dup
      28: invokespecial #33                 // Method org/codehaus/groovy/control/CompilerConfiguration."<init>":()V
      31: goto          35
      34: aload_1
      35: invokevirtual #41                 // Method configure:(Lorg/codehaus/groovy/control/CompilerConfiguration;)V
      38: aload_3
      39: ifnonnull     54
      42: new           #37                 // class org/codehaus/groovy/control/ErrorCollector
      45: dup
      46: aload_0
      47: invokevirtual #45                 // Method getConfiguration:()Lorg/codehaus/groovy/control/CompilerConfiguration;
      50: invokespecial #47                 // Method org/codehaus/groovy/control/ErrorCollector."<init>":(Lorg/codehaus/groovy/control/CompilerConfiguration;)V
      53: astore_3
      54: aload_0
      55: aload_3
      56: putfield      #49                 // Field errorCollector:Lorg/codehaus/groovy/control/ErrorCollector;
      59: return

  public void configure(org.codehaus.groovy.control.CompilerConfiguration);
    Code:
       0: aload_0
       1: aload_1
       2: putfield      #26                 // Field configuration:Lorg/codehaus/groovy/control/CompilerConfiguration;
       5: return

  public org.codehaus.groovy.control.CompilerConfiguration getConfiguration();
    Code:
       0: aload_0
       1: getfield      #26                 // Field configuration:Lorg/codehaus/groovy/control/CompilerConfiguration;
       4: areturn

  public void setConfiguration(org.codehaus.groovy.control.CompilerConfiguration);
    Code:
       0: aload_0
       1: aload_1
       2: putfield      #26                 // Field configuration:Lorg/codehaus/groovy/control/CompilerConfiguration;
       5: return

  public groovy.lang.GroovyClassLoader getClassLoader();
    Code:
       0: aload_0
       1: getfield      #57                 // Field classLoader:Lgroovy/lang/GroovyClassLoader;
       4: areturn

  public void setClassLoader(groovy.lang.GroovyClassLoader);
    Code:
       0: aload_0
       1: new           #7                  // class org/codehaus/groovy/control/ProcessingUnit$1
       4: dup
       5: aload_0
       6: aload_1
       7: invokespecial #60                 // Method org/codehaus/groovy/control/ProcessingUnit$1."<init>":(Lorg/codehaus/groovy/control/ProcessingUnit;Lgroovy/lang/GroovyClassLoader;)V
      10: invokestatic  #66                 // Method java/security/AccessController.doPrivileged:(Ljava/security/PrivilegedAction;)Ljava/lang/Object;
      13: checkcast     #35                 // class groovy/lang/GroovyClassLoader
      16: putfield      #57                 // Field classLoader:Lgroovy/lang/GroovyClassLoader;
      19: return

  public int getPhase();
    Code:
       0: aload_0
       1: getfield      #24                 // Field phase:I
       4: ireturn

  public java.lang.String getPhaseDescription();
    Code:
       0: aload_0
       1: getfield      #24                 // Field phase:I
       4: invokestatic  #77                 // Method org/codehaus/groovy/control/Phases.getDescription:(I)Ljava/lang/String;
       7: areturn

  public org.codehaus.groovy.control.ErrorCollector getErrorCollector();
    Code:
       0: aload_0
       1: getfield      #49                 // Field errorCollector:Lorg/codehaus/groovy/control/ErrorCollector;
       4: areturn

  public void completePhase() throws org.codehaus.groovy.control.CompilationFailedException;
    Code:
       0: aload_0
       1: getfield      #49                 // Field errorCollector:Lorg/codehaus/groovy/control/ErrorCollector;
       4: invokevirtual #85                 // Method org/codehaus/groovy/control/ErrorCollector.failIfErrors:()V
       7: aload_0
       8: iconst_1
       9: putfield      #87                 // Field phaseComplete:Z
      12: return

  public void nextPhase() throws org.codehaus.groovy.control.CompilationFailedException;
    Code:
       0: aload_0
       1: aload_0
       2: getfield      #24                 // Field phase:I
       5: iconst_1
       6: iadd
       7: invokevirtual #92                 // Method gotoPhase:(I)V
      10: return

  public void gotoPhase(int) throws org.codehaus.groovy.control.CompilationFailedException;
    Code:
       0: aload_0
       1: getfield      #87                 // Field phaseComplete:Z
       4: ifne          11
       7: aload_0
       8: invokevirtual #94                 // Method completePhase:()V
      11: aload_0
      12: iload_1
      13: putfield      #24                 // Field phase:I
      16: aload_0
      17: iconst_0
      18: putfield      #87                 // Field phaseComplete:Z
      21: return
}
