Compiled from "JvmDefaultGCMetricsLogger.java"
class org.apache.pulsar.common.stats.JvmDefaultGCMetricsLogger$GCMetrics {
  volatile long accumulatedGcCount;

  volatile long currentGcCount;

  volatile long accumulatedGcTime;

  volatile long currentGcTime;

  org.apache.pulsar.common.stats.JvmDefaultGCMetricsLogger$GCMetrics();
    Code:
       0: aload_0
       1: invokespecial #1                  // Method java/lang/Object."<init>":()V
       4: aload_0
       5: lconst_0
       6: putfield      #2                  // Field accumulatedGcCount:J
       9: aload_0
      10: lconst_0
      11: putfield      #3                  // Field currentGcCount:J
      14: aload_0
      15: lconst_0
      16: putfield      #4                  // Field accumulatedGcTime:J
      19: aload_0
      20: lconst_0
      21: putfield      #5                  // Field currentGcTime:J
      24: return
}
