Compiled from "AdamsFieldStepInterpolator.java"
class org.apache.commons.math3.ode.nonstiff.AdamsFieldStepInterpolator<T extends org.apache.commons.math3.RealFieldElement<T>> extends org.apache.commons.math3.ode.sampling.AbstractFieldStepInterpolator<T> {
  private T scalingH;

  private final org.apache.commons.math3.ode.FieldODEStateAndDerivative<T> reference;

  private final T[] scaled;

  private final org.apache.commons.math3.linear.Array2DRowFieldMatrix<T> nordsieck;

  org.apache.commons.math3.ode.nonstiff.AdamsFieldStepInterpolator(T, org.apache.commons.math3.ode.FieldODEStateAndDerivative<T>, T[], org.apache.commons.math3.linear.Array2DRowFieldMatrix<T>, boolean, org.apache.commons.math3.ode.FieldODEStateAndDerivative<T>, org.apache.commons.math3.ode.FieldODEStateAndDerivative<T>, org.apache.commons.math3.ode.FieldEquationsMapper<T>);
    Code:
       0: aload_0
       1: aload_1
       2: aload_2
       3: aload_3
       4: aload         4
       6: iload         5
       8: aload         6
      10: aload         7
      12: aload         6
      14: aload         7
      16: aload         8
      18: invokespecial #1                  // Method "<init>":(Lorg/apache/commons/math3/RealFieldElement;Lorg/apache/commons/math3/ode/FieldODEStateAndDerivative;[Lorg/apache/commons/math3/RealFieldElement;Lorg/apache/commons/math3/linear/Array2DRowFieldMatrix;ZLorg/apache/commons/math3/ode/FieldODEStateAndDerivative;Lorg/apache/commons/math3/ode/FieldODEStateAndDerivative;Lorg/apache/commons/math3/ode/FieldODEStateAndDerivative;Lorg/apache/commons/math3/ode/FieldODEStateAndDerivative;Lorg/apache/commons/math3/ode/FieldEquationsMapper;)V
      21: return

  private org.apache.commons.math3.ode.nonstiff.AdamsFieldStepInterpolator(T, org.apache.commons.math3.ode.FieldODEStateAndDerivative<T>, T[], org.apache.commons.math3.linear.Array2DRowFieldMatrix<T>, boolean, org.apache.commons.math3.ode.FieldODEStateAndDerivative<T>, org.apache.commons.math3.ode.FieldODEStateAndDerivative<T>, org.apache.commons.math3.ode.FieldODEStateAndDerivative<T>, org.apache.commons.math3.ode.FieldODEStateAndDerivative<T>, org.apache.commons.math3.ode.FieldEquationsMapper<T>);
    Code:
       0: aload_0
       1: iload         5
       3: aload         6
       5: aload         7
       7: aload         8
       9: aload         9
      11: aload         10
      13: invokespecial #2                  // Method org/apache/commons/math3/ode/sampling/AbstractFieldStepInterpolator."<init>":(ZLorg/apache/commons/math3/ode/FieldODEStateAndDerivative;Lorg/apache/commons/math3/ode/FieldODEStateAndDerivative;Lorg/apache/commons/math3/ode/FieldODEStateAndDerivative;Lorg/apache/commons/math3/ode/FieldODEStateAndDerivative;Lorg/apache/commons/math3/ode/FieldEquationsMapper;)V
      16: aload_0
      17: aload_1
      18: putfield      #3                  // Field scalingH:Lorg/apache/commons/math3/RealFieldElement;
      21: aload_0
      22: aload_2
      23: putfield      #4                  // Field reference:Lorg/apache/commons/math3/ode/FieldODEStateAndDerivative;
      26: aload_0
      27: aload_3
      28: invokevirtual #5                  // Method "[Lorg/apache/commons/math3/RealFieldElement;".clone:()Ljava/lang/Object;
      31: checkcast     #6                  // class "[Lorg/apache/commons/math3/RealFieldElement;"
      34: putfield      #7                  // Field scaled:[Lorg/apache/commons/math3/RealFieldElement;
      37: aload_0
      38: new           #8                  // class org/apache/commons/math3/linear/Array2DRowFieldMatrix
      41: dup
      42: aload         4
      44: invokevirtual #9                  // Method org/apache/commons/math3/linear/Array2DRowFieldMatrix.getData:()[[Lorg/apache/commons/math3/FieldElement;
      47: iconst_0
      48: invokespecial #10                 // Method org/apache/commons/math3/linear/Array2DRowFieldMatrix."<init>":([[Lorg/apache/commons/math3/FieldElement;Z)V
      51: putfield      #11                 // Field nordsieck:Lorg/apache/commons/math3/linear/Array2DRowFieldMatrix;
      54: return

  protected org.apache.commons.math3.ode.nonstiff.AdamsFieldStepInterpolator<T> create(boolean, org.apache.commons.math3.ode.FieldODEStateAndDerivative<T>, org.apache.commons.math3.ode.FieldODEStateAndDerivative<T>, org.apache.commons.math3.ode.FieldODEStateAndDerivative<T>, org.apache.commons.math3.ode.FieldODEStateAndDerivative<T>, org.apache.commons.math3.ode.FieldEquationsMapper<T>);
    Code:
       0: new           #12                 // class org/apache/commons/math3/ode/nonstiff/AdamsFieldStepInterpolator
       3: dup
       4: aload_0
       5: getfield      #3                  // Field scalingH:Lorg/apache/commons/math3/RealFieldElement;
       8: aload_0
       9: getfield      #4                  // Field reference:Lorg/apache/commons/math3/ode/FieldODEStateAndDerivative;
      12: aload_0
      13: getfield      #7                  // Field scaled:[Lorg/apache/commons/math3/RealFieldElement;
      16: aload_0
      17: getfield      #11                 // Field nordsieck:Lorg/apache/commons/math3/linear/Array2DRowFieldMatrix;
      20: iload_1
      21: aload_2
      22: aload_3
      23: aload         4
      25: aload         5
      27: aload         6
      29: invokespecial #1                  // Method "<init>":(Lorg/apache/commons/math3/RealFieldElement;Lorg/apache/commons/math3/ode/FieldODEStateAndDerivative;[Lorg/apache/commons/math3/RealFieldElement;Lorg/apache/commons/math3/linear/Array2DRowFieldMatrix;ZLorg/apache/commons/math3/ode/FieldODEStateAndDerivative;Lorg/apache/commons/math3/ode/FieldODEStateAndDerivative;Lorg/apache/commons/math3/ode/FieldODEStateAndDerivative;Lorg/apache/commons/math3/ode/FieldODEStateAndDerivative;Lorg/apache/commons/math3/ode/FieldEquationsMapper;)V
      32: areturn

  protected org.apache.commons.math3.ode.FieldODEStateAndDerivative<T> computeInterpolatedStateAndDerivatives(org.apache.commons.math3.ode.FieldEquationsMapper<T>, T, T, T, T);
    Code:
       0: aload_0
       1: getfield      #4                  // Field reference:Lorg/apache/commons/math3/ode/FieldODEStateAndDerivative;
       4: aload_2
       5: aload_0
       6: getfield      #3                  // Field scalingH:Lorg/apache/commons/math3/RealFieldElement;
       9: aload_0
      10: getfield      #7                  // Field scaled:[Lorg/apache/commons/math3/RealFieldElement;
      13: aload_0
      14: getfield      #11                 // Field nordsieck:Lorg/apache/commons/math3/linear/Array2DRowFieldMatrix;
      17: invokestatic  #13                 // Method taylor:(Lorg/apache/commons/math3/ode/FieldODEStateAndDerivative;Lorg/apache/commons/math3/RealFieldElement;Lorg/apache/commons/math3/RealFieldElement;[Lorg/apache/commons/math3/RealFieldElement;Lorg/apache/commons/math3/linear/Array2DRowFieldMatrix;)Lorg/apache/commons/math3/ode/FieldODEStateAndDerivative;
      20: areturn

  public static <S extends org.apache.commons.math3.RealFieldElement<S>> org.apache.commons.math3.ode.FieldODEStateAndDerivative<S> taylor(org.apache.commons.math3.ode.FieldODEStateAndDerivative<S>, S, S, S[], org.apache.commons.math3.linear.Array2DRowFieldMatrix<S>);
    Code:
       0: aload_1
       1: aload_0
       2: invokevirtual #14                 // Method org/apache/commons/math3/ode/FieldODEStateAndDerivative.getTime:()Lorg/apache/commons/math3/RealFieldElement;
       5: invokeinterface #15,  2           // InterfaceMethod org/apache/commons/math3/RealFieldElement.subtract:(Ljava/lang/Object;)Ljava/lang/Object;
      10: checkcast     #16                 // class org/apache/commons/math3/RealFieldElement
      13: astore        5
      15: aload         5
      17: aload_2
      18: invokeinterface #17,  2           // InterfaceMethod org/apache/commons/math3/RealFieldElement.divide:(Ljava/lang/Object;)Ljava/lang/Object;
      23: checkcast     #16                 // class org/apache/commons/math3/RealFieldElement
      26: astore        6
      28: aload_1
      29: invokeinterface #18,  1           // InterfaceMethod org/apache/commons/math3/RealFieldElement.getField:()Lorg/apache/commons/math3/Field;
      34: aload_3
      35: arraylength
      36: invokestatic  #19                 // Method org/apache/commons/math3/util/MathArrays.buildArray:(Lorg/apache/commons/math3/Field;I)[Ljava/lang/Object;
      39: checkcast     #6                  // class "[Lorg/apache/commons/math3/RealFieldElement;"
      42: astore        7
      44: aload         7
      46: aload_1
      47: invokeinterface #18,  1           // InterfaceMethod org/apache/commons/math3/RealFieldElement.getField:()Lorg/apache/commons/math3/Field;
      52: invokeinterface #20,  1           // InterfaceMethod org/apache/commons/math3/Field.getZero:()Ljava/lang/Object;
      57: invokestatic  #21                 // Method java/util/Arrays.fill:([Ljava/lang/Object;Ljava/lang/Object;)V
      60: aload_1
      61: invokeinterface #18,  1           // InterfaceMethod org/apache/commons/math3/RealFieldElement.getField:()Lorg/apache/commons/math3/Field;
      66: aload_3
      67: arraylength
      68: invokestatic  #19                 // Method org/apache/commons/math3/util/MathArrays.buildArray:(Lorg/apache/commons/math3/Field;I)[Ljava/lang/Object;
      71: checkcast     #6                  // class "[Lorg/apache/commons/math3/RealFieldElement;"
      74: astore        8
      76: aload         8
      78: aload_1
      79: invokeinterface #18,  1           // InterfaceMethod org/apache/commons/math3/RealFieldElement.getField:()Lorg/apache/commons/math3/Field;
      84: invokeinterface #20,  1           // InterfaceMethod org/apache/commons/math3/Field.getZero:()Ljava/lang/Object;
      89: invokestatic  #21                 // Method java/util/Arrays.fill:([Ljava/lang/Object;Ljava/lang/Object;)V
      92: aload         4
      94: invokevirtual #22                 // Method org/apache/commons/math3/linear/Array2DRowFieldMatrix.getDataRef:()[[Lorg/apache/commons/math3/FieldElement;
      97: checkcast     #23                 // class "[[Lorg/apache/commons/math3/RealFieldElement;"
     100: astore        9
     102: aload         9
     104: arraylength
     105: iconst_1
     106: isub
     107: istore        10
     109: iload         10
     111: iflt          228
     114: iload         10
     116: iconst_2
     117: iadd
     118: istore        11
     120: aload         9
     122: iload         10
     124: aaload
     125: astore        12
     127: aload         6
     129: iload         11
     131: invokeinterface #24,  2           // InterfaceMethod org/apache/commons/math3/RealFieldElement.pow:(I)Ljava/lang/Object;
     136: checkcast     #16                 // class org/apache/commons/math3/RealFieldElement
     139: astore        13
     141: iconst_0
     142: istore        14
     144: iload         14
     146: aload         12
     148: arraylength
     149: if_icmpge     222
     152: aload         12
     154: iload         14
     156: aaload
     157: aload         13
     159: invokeinterface #25,  2           // InterfaceMethod org/apache/commons/math3/RealFieldElement.multiply:(Ljava/lang/Object;)Ljava/lang/Object;
     164: checkcast     #16                 // class org/apache/commons/math3/RealFieldElement
     167: astore        15
     169: aload         7
     171: iload         14
     173: aload         7
     175: iload         14
     177: aaload
     178: aload         15
     180: invokeinterface #26,  2           // InterfaceMethod org/apache/commons/math3/RealFieldElement.add:(Ljava/lang/Object;)Ljava/lang/Object;
     185: checkcast     #16                 // class org/apache/commons/math3/RealFieldElement
     188: aastore
     189: aload         8
     191: iload         14
     193: aload         8
     195: iload         14
     197: aaload
     198: aload         15
     200: iload         11
     202: invokeinterface #27,  2           // InterfaceMethod org/apache/commons/math3/RealFieldElement.multiply:(I)Ljava/lang/Object;
     207: invokeinterface #26,  2           // InterfaceMethod org/apache/commons/math3/RealFieldElement.add:(Ljava/lang/Object;)Ljava/lang/Object;
     212: checkcast     #16                 // class org/apache/commons/math3/RealFieldElement
     215: aastore
     216: iinc          14, 1
     219: goto          144
     222: iinc          10, -1
     225: goto          109
     228: aload_0
     229: invokevirtual #28                 // Method org/apache/commons/math3/ode/FieldODEStateAndDerivative.getState:()[Lorg/apache/commons/math3/RealFieldElement;
     232: astore        10
     234: iconst_0
     235: istore        11
     237: iload         11
     239: aload         7
     241: arraylength
     242: if_icmpge     342
     245: aload         7
     247: iload         11
     249: aload         7
     251: iload         11
     253: aaload
     254: aload_3
     255: iload         11
     257: aaload
     258: aload         6
     260: invokeinterface #25,  2           // InterfaceMethod org/apache/commons/math3/RealFieldElement.multiply:(Ljava/lang/Object;)Ljava/lang/Object;
     265: invokeinterface #26,  2           // InterfaceMethod org/apache/commons/math3/RealFieldElement.add:(Ljava/lang/Object;)Ljava/lang/Object;
     270: checkcast     #16                 // class org/apache/commons/math3/RealFieldElement
     273: aastore
     274: aload         10
     276: iload         11
     278: aload         10
     280: iload         11
     282: aaload
     283: aload         7
     285: iload         11
     287: aaload
     288: invokeinterface #26,  2           // InterfaceMethod org/apache/commons/math3/RealFieldElement.add:(Ljava/lang/Object;)Ljava/lang/Object;
     293: checkcast     #16                 // class org/apache/commons/math3/RealFieldElement
     296: aastore
     297: aload         8
     299: iload         11
     301: aload         8
     303: iload         11
     305: aaload
     306: aload_3
     307: iload         11
     309: aaload
     310: aload         6
     312: invokeinterface #25,  2           // InterfaceMethod org/apache/commons/math3/RealFieldElement.multiply:(Ljava/lang/Object;)Ljava/lang/Object;
     317: invokeinterface #26,  2           // InterfaceMethod org/apache/commons/math3/RealFieldElement.add:(Ljava/lang/Object;)Ljava/lang/Object;
     322: checkcast     #16                 // class org/apache/commons/math3/RealFieldElement
     325: aload         5
     327: invokeinterface #17,  2           // InterfaceMethod org/apache/commons/math3/RealFieldElement.divide:(Ljava/lang/Object;)Ljava/lang/Object;
     332: checkcast     #16                 // class org/apache/commons/math3/RealFieldElement
     335: aastore
     336: iinc          11, 1
     339: goto          237
     342: new           #29                 // class org/apache/commons/math3/ode/FieldODEStateAndDerivative
     345: dup
     346: aload_1
     347: aload         10
     349: aload         8
     351: invokespecial #30                 // Method org/apache/commons/math3/ode/FieldODEStateAndDerivative."<init>":(Lorg/apache/commons/math3/RealFieldElement;[Lorg/apache/commons/math3/RealFieldElement;[Lorg/apache/commons/math3/RealFieldElement;)V
     354: areturn

  protected org.apache.commons.math3.ode.sampling.AbstractFieldStepInterpolator create(boolean, org.apache.commons.math3.ode.FieldODEStateAndDerivative, org.apache.commons.math3.ode.FieldODEStateAndDerivative, org.apache.commons.math3.ode.FieldODEStateAndDerivative, org.apache.commons.math3.ode.FieldODEStateAndDerivative, org.apache.commons.math3.ode.FieldEquationsMapper);
    Code:
       0: aload_0
       1: iload_1
       2: aload_2
       3: aload_3
       4: aload         4
       6: aload         5
       8: aload         6
      10: invokevirtual #31                 // Method create:(ZLorg/apache/commons/math3/ode/FieldODEStateAndDerivative;Lorg/apache/commons/math3/ode/FieldODEStateAndDerivative;Lorg/apache/commons/math3/ode/FieldODEStateAndDerivative;Lorg/apache/commons/math3/ode/FieldODEStateAndDerivative;Lorg/apache/commons/math3/ode/FieldEquationsMapper;)Lorg/apache/commons/math3/ode/nonstiff/AdamsFieldStepInterpolator;
      13: areturn
}
