Compiled from "ReorderTransformationSubstitution.java"
class org.apache.jena.sparql.engine.optimizer.reorder.ReorderTransformationSubstitution$1 extends org.apache.jena.atlas.iterator.AccString<org.apache.jena.sparql.engine.optimizer.reorder.PatternTriple> {
  final org.apache.jena.sparql.engine.optimizer.reorder.ReorderTransformationSubstitution this$0;

  org.apache.jena.sparql.engine.optimizer.reorder.ReorderTransformationSubstitution$1(org.apache.jena.sparql.engine.optimizer.reorder.ReorderTransformationSubstitution);
    Code:
       0: aload_0
       1: aload_1
       2: putfield      #1                  // Field this$0:Lorg/apache/jena/sparql/engine/optimizer/reorder/ReorderTransformationSubstitution;
       5: aload_0
       6: invokespecial #2                  // Method org/apache/jena/atlas/iterator/AccString."<init>":()V
       9: return

  protected java.lang.String toString(org.apache.jena.sparql.engine.optimizer.reorder.PatternTriple);
    Code:
       0: new           #3                  // class java/lang/StringBuilder
       3: dup
       4: invokespecial #4                  // Method java/lang/StringBuilder."<init>":()V
       7: ldc           #5                  // String (
       9: invokevirtual #6                  // Method java/lang/StringBuilder.append:(Ljava/lang/String;)Ljava/lang/StringBuilder;
      12: aload_1
      13: invokevirtual #7                  // Method org/apache/jena/sparql/engine/optimizer/reorder/PatternTriple.toString:()Ljava/lang/String;
      16: invokestatic  #8                  // Method org/apache/jena/sparql/util/StringUtils.printAbbrev:(Ljava/lang/Object;)Ljava/lang/String;
      19: invokevirtual #6                  // Method java/lang/StringBuilder.append:(Ljava/lang/String;)Ljava/lang/StringBuilder;
      22: ldc           #9                  // String )
      24: invokevirtual #6                  // Method java/lang/StringBuilder.append:(Ljava/lang/String;)Ljava/lang/StringBuilder;
      27: invokevirtual #10                 // Method java/lang/StringBuilder.toString:()Ljava/lang/String;
      30: areturn

  protected java.lang.String toString(java.lang.Object);
    Code:
       0: aload_0
       1: aload_1
       2: checkcast     #11                 // class org/apache/jena/sparql/engine/optimizer/reorder/PatternTriple
       5: invokevirtual #12                 // Method toString:(Lorg/apache/jena/sparql/engine/optimizer/reorder/PatternTriple;)Ljava/lang/String;
       8: areturn
}
