Compiled from "EEDefaultPermissionsProcessor.java"
public final class org.jboss.as.ee.component.deployers.EEDefaultPermissionsProcessor implements org.jboss.as.server.deployment.DeploymentUnitProcessor {
  private static final java.security.Permissions DEFAULT_PERMISSIONS;

  public org.jboss.as.ee.component.deployers.EEDefaultPermissionsProcessor();
    Code:
       0: aload_0
       1: invokespecial #1                  // Method java/lang/Object."<init>":()V
       4: return

  public void deploy(org.jboss.as.server.deployment.DeploymentPhaseContext) throws org.jboss.as.server.deployment.DeploymentUnitProcessingException;
    Code:
       0: aload_1
       1: invokeinterface #2,  1            // InterfaceMethod org/jboss/as/server/deployment/DeploymentPhaseContext.getDeploymentUnit:()Lorg/jboss/as/server/deployment/DeploymentUnit;
       6: astore_2
       7: aload_2
       8: getstatic     #3                  // Field org/jboss/as/server/deployment/Attachments.MODULE_SPECIFICATION:Lorg/jboss/as/server/deployment/AttachmentKey;
      11: invokeinterface #4,  2            // InterfaceMethod org/jboss/as/server/deployment/DeploymentUnit.getAttachment:(Lorg/jboss/as/server/deployment/AttachmentKey;)Ljava/lang/Object;
      16: checkcast     #5                  // class org/jboss/as/server/deployment/module/ModuleSpecification
      19: astore_3
      20: aload_3
      21: ifnonnull     25
      24: return
      25: aload_3
      26: invokevirtual #6                  // Method org/jboss/as/server/deployment/module/ModuleSpecification.getPermissionFactories:()Ljava/util/List;
      29: astore        4
      31: getstatic     #7                  // Field DEFAULT_PERMISSIONS:Ljava/security/Permissions;
      34: invokevirtual #8                  // Method java/security/Permissions.elements:()Ljava/util/Enumeration;
      37: astore        5
      39: aload         5
      41: invokeinterface #9,  1            // InterfaceMethod java/util/Enumeration.hasMoreElements:()Z
      46: ifeq          77
      49: aload         4
      51: new           #10                 // class org/jboss/modules/security/ImmediatePermissionFactory
      54: dup
      55: aload         5
      57: invokeinterface #11,  1           // InterfaceMethod java/util/Enumeration.nextElement:()Ljava/lang/Object;
      62: checkcast     #12                 // class java/security/Permission
      65: invokespecial #13                 // Method org/jboss/modules/security/ImmediatePermissionFactory."<init>":(Ljava/security/Permission;)V
      68: invokeinterface #14,  2           // InterfaceMethod java/util/List.add:(Ljava/lang/Object;)Z
      73: pop
      74: goto          39
      77: aload_2
      78: getstatic     #15                 // Field org/jboss/as/server/deployment/Attachments.DEPLOYMENT_ROOT:Lorg/jboss/as/server/deployment/AttachmentKey;
      81: invokeinterface #4,  2            // InterfaceMethod org/jboss/as/server/deployment/DeploymentUnit.getAttachment:(Lorg/jboss/as/server/deployment/AttachmentKey;)Ljava/lang/Object;
      86: checkcast     #16                 // class org/jboss/as/server/deployment/module/ResourceRoot
      89: astore        6
      91: aload         6
      93: invokevirtual #17                 // Method org/jboss/as/server/deployment/module/ResourceRoot.getRoot:()Lorg/jboss/vfs/VirtualFile;
      96: invokevirtual #18                 // Method org/jboss/vfs/VirtualFile.getPhysicalFile:()Ljava/io/File;
      99: astore        7
     101: aload         7
     103: ifnull        171
     106: aload         7
     108: invokevirtual #19                 // Method java/io/File.isDirectory:()Z
     111: ifeq          171
     114: new           #20                 // class java/io/FilePermission
     117: dup
     118: new           #21                 // class java/lang/StringBuilder
     121: dup
     122: invokespecial #22                 // Method java/lang/StringBuilder."<init>":()V
     125: aload         7
     127: invokevirtual #23                 // Method java/io/File.getAbsolutePath:()Ljava/lang/String;
     130: invokevirtual #24                 // Method java/lang/StringBuilder.append:(Ljava/lang/String;)Ljava/lang/StringBuilder;
     133: getstatic     #25                 // Field java/io/File.separatorChar:C
     136: invokevirtual #26                 // Method java/lang/StringBuilder.append:(C)Ljava/lang/StringBuilder;
     139: ldc           #27                 // String -
     141: invokevirtual #24                 // Method java/lang/StringBuilder.append:(Ljava/lang/String;)Ljava/lang/StringBuilder;
     144: invokevirtual #28                 // Method java/lang/StringBuilder.toString:()Ljava/lang/String;
     147: ldc           #29                 // String read
     149: invokespecial #30                 // Method java/io/FilePermission."<init>":(Ljava/lang/String;Ljava/lang/String;)V
     152: astore        8
     154: aload         4
     156: new           #10                 // class org/jboss/modules/security/ImmediatePermissionFactory
     159: dup
     160: aload         8
     162: invokespecial #13                 // Method org/jboss/modules/security/ImmediatePermissionFactory."<init>":(Ljava/security/Permission;)V
     165: invokeinterface #14,  2           // InterfaceMethod java/util/List.add:(Ljava/lang/Object;)Z
     170: pop
     171: goto          186
     174: astore        7
     176: new           #32                 // class org/jboss/as/server/deployment/DeploymentUnitProcessingException
     179: dup
     180: aload         7
     182: invokespecial #33                 // Method org/jboss/as/server/deployment/DeploymentUnitProcessingException."<init>":(Ljava/lang/Throwable;)V
     185: athrow
     186: return
    Exception table:
       from    to  target type
          91   171   174   Class java/io/IOException

  public void undeploy(org.jboss.as.server.deployment.DeploymentUnit);
    Code:
       0: return

  static {};
    Code:
       0: new           #34                 // class java/security/Permissions
       3: dup
       4: invokespecial #35                 // Method java/security/Permissions."<init>":()V
       7: astore_0
       8: aload_0
       9: new           #36                 // class org/jboss/as/naming/JndiPermission
      12: dup
      13: ldc           #37                 // String java:comp
      15: iconst_3
      16: anewarray     #38                 // class org/jboss/as/naming/JndiPermission$Action
      19: dup
      20: iconst_0
      21: getstatic     #39                 // Field org/jboss/as/naming/JndiPermission$Action.LOOKUP:Lorg/jboss/as/naming/JndiPermission$Action;
      24: aastore
      25: dup
      26: iconst_1
      27: getstatic     #40                 // Field org/jboss/as/naming/JndiPermission$Action.LIST:Lorg/jboss/as/naming/JndiPermission$Action;
      30: aastore
      31: dup
      32: iconst_2
      33: getstatic     #41                 // Field org/jboss/as/naming/JndiPermission$Action.LIST_BINDINGS:Lorg/jboss/as/naming/JndiPermission$Action;
      36: aastore
      37: invokespecial #42                 // Method org/jboss/as/naming/JndiPermission."<init>":(Ljava/lang/String;[Lorg/jboss/as/naming/JndiPermission$Action;)V
      40: invokevirtual #43                 // Method java/security/Permissions.add:(Ljava/security/Permission;)V
      43: aload_0
      44: new           #36                 // class org/jboss/as/naming/JndiPermission
      47: dup
      48: ldc           #44                 // String java:comp/-
      50: iconst_3
      51: anewarray     #38                 // class org/jboss/as/naming/JndiPermission$Action
      54: dup
      55: iconst_0
      56: getstatic     #39                 // Field org/jboss/as/naming/JndiPermission$Action.LOOKUP:Lorg/jboss/as/naming/JndiPermission$Action;
      59: aastore
      60: dup
      61: iconst_1
      62: getstatic     #40                 // Field org/jboss/as/naming/JndiPermission$Action.LIST:Lorg/jboss/as/naming/JndiPermission$Action;
      65: aastore
      66: dup
      67: iconst_2
      68: getstatic     #41                 // Field org/jboss/as/naming/JndiPermission$Action.LIST_BINDINGS:Lorg/jboss/as/naming/JndiPermission$Action;
      71: aastore
      72: invokespecial #42                 // Method org/jboss/as/naming/JndiPermission."<init>":(Ljava/lang/String;[Lorg/jboss/as/naming/JndiPermission$Action;)V
      75: invokevirtual #43                 // Method java/security/Permissions.add:(Ljava/security/Permission;)V
      78: aload_0
      79: new           #36                 // class org/jboss/as/naming/JndiPermission
      82: dup
      83: ldc           #45                 // String java:module
      85: iconst_3
      86: anewarray     #38                 // class org/jboss/as/naming/JndiPermission$Action
      89: dup
      90: iconst_0
      91: getstatic     #39                 // Field org/jboss/as/naming/JndiPermission$Action.LOOKUP:Lorg/jboss/as/naming/JndiPermission$Action;
      94: aastore
      95: dup
      96: iconst_1
      97: getstatic     #40                 // Field org/jboss/as/naming/JndiPermission$Action.LIST:Lorg/jboss/as/naming/JndiPermission$Action;
     100: aastore
     101: dup
     102: iconst_2
     103: getstatic     #41                 // Field org/jboss/as/naming/JndiPermission$Action.LIST_BINDINGS:Lorg/jboss/as/naming/JndiPermission$Action;
     106: aastore
     107: invokespecial #42                 // Method org/jboss/as/naming/JndiPermission."<init>":(Ljava/lang/String;[Lorg/jboss/as/naming/JndiPermission$Action;)V
     110: invokevirtual #43                 // Method java/security/Permissions.add:(Ljava/security/Permission;)V
     113: aload_0
     114: new           #36                 // class org/jboss/as/naming/JndiPermission
     117: dup
     118: ldc           #46                 // String java:module/-
     120: iconst_3
     121: anewarray     #38                 // class org/jboss/as/naming/JndiPermission$Action
     124: dup
     125: iconst_0
     126: getstatic     #39                 // Field org/jboss/as/naming/JndiPermission$Action.LOOKUP:Lorg/jboss/as/naming/JndiPermission$Action;
     129: aastore
     130: dup
     131: iconst_1
     132: getstatic     #40                 // Field org/jboss/as/naming/JndiPermission$Action.LIST:Lorg/jboss/as/naming/JndiPermission$Action;
     135: aastore
     136: dup
     137: iconst_2
     138: getstatic     #41                 // Field org/jboss/as/naming/JndiPermission$Action.LIST_BINDINGS:Lorg/jboss/as/naming/JndiPermission$Action;
     141: aastore
     142: invokespecial #42                 // Method org/jboss/as/naming/JndiPermission."<init>":(Ljava/lang/String;[Lorg/jboss/as/naming/JndiPermission$Action;)V
     145: invokevirtual #43                 // Method java/security/Permissions.add:(Ljava/security/Permission;)V
     148: aload_0
     149: new           #36                 // class org/jboss/as/naming/JndiPermission
     152: dup
     153: ldc           #47                 // String java:app
     155: iconst_3
     156: anewarray     #38                 // class org/jboss/as/naming/JndiPermission$Action
     159: dup
     160: iconst_0
     161: getstatic     #39                 // Field org/jboss/as/naming/JndiPermission$Action.LOOKUP:Lorg/jboss/as/naming/JndiPermission$Action;
     164: aastore
     165: dup
     166: iconst_1
     167: getstatic     #40                 // Field org/jboss/as/naming/JndiPermission$Action.LIST:Lorg/jboss/as/naming/JndiPermission$Action;
     170: aastore
     171: dup
     172: iconst_2
     173: getstatic     #41                 // Field org/jboss/as/naming/JndiPermission$Action.LIST_BINDINGS:Lorg/jboss/as/naming/JndiPermission$Action;
     176: aastore
     177: invokespecial #42                 // Method org/jboss/as/naming/JndiPermission."<init>":(Ljava/lang/String;[Lorg/jboss/as/naming/JndiPermission$Action;)V
     180: invokevirtual #43                 // Method java/security/Permissions.add:(Ljava/security/Permission;)V
     183: aload_0
     184: new           #36                 // class org/jboss/as/naming/JndiPermission
     187: dup
     188: ldc           #48                 // String java:app/-
     190: iconst_3
     191: anewarray     #38                 // class org/jboss/as/naming/JndiPermission$Action
     194: dup
     195: iconst_0
     196: getstatic     #39                 // Field org/jboss/as/naming/JndiPermission$Action.LOOKUP:Lorg/jboss/as/naming/JndiPermission$Action;
     199: aastore
     200: dup
     201: iconst_1
     202: getstatic     #40                 // Field org/jboss/as/naming/JndiPermission$Action.LIST:Lorg/jboss/as/naming/JndiPermission$Action;
     205: aastore
     206: dup
     207: iconst_2
     208: getstatic     #41                 // Field org/jboss/as/naming/JndiPermission$Action.LIST_BINDINGS:Lorg/jboss/as/naming/JndiPermission$Action;
     211: aastore
     212: invokespecial #42                 // Method org/jboss/as/naming/JndiPermission."<init>":(Ljava/lang/String;[Lorg/jboss/as/naming/JndiPermission$Action;)V
     215: invokevirtual #43                 // Method java/security/Permissions.add:(Ljava/security/Permission;)V
     218: aload_0
     219: new           #36                 // class org/jboss/as/naming/JndiPermission
     222: dup
     223: ldc           #49                 // String java:global
     225: iconst_1
     226: anewarray     #38                 // class org/jboss/as/naming/JndiPermission$Action
     229: dup
     230: iconst_0
     231: getstatic     #39                 // Field org/jboss/as/naming/JndiPermission$Action.LOOKUP:Lorg/jboss/as/naming/JndiPermission$Action;
     234: aastore
     235: invokespecial #42                 // Method org/jboss/as/naming/JndiPermission."<init>":(Ljava/lang/String;[Lorg/jboss/as/naming/JndiPermission$Action;)V
     238: invokevirtual #43                 // Method java/security/Permissions.add:(Ljava/security/Permission;)V
     241: aload_0
     242: new           #36                 // class org/jboss/as/naming/JndiPermission
     245: dup
     246: ldc           #50                 // String java:global/-
     248: iconst_1
     249: anewarray     #38                 // class org/jboss/as/naming/JndiPermission$Action
     252: dup
     253: iconst_0
     254: getstatic     #39                 // Field org/jboss/as/naming/JndiPermission$Action.LOOKUP:Lorg/jboss/as/naming/JndiPermission$Action;
     257: aastore
     258: invokespecial #42                 // Method org/jboss/as/naming/JndiPermission."<init>":(Ljava/lang/String;[Lorg/jboss/as/naming/JndiPermission$Action;)V
     261: invokevirtual #43                 // Method java/security/Permissions.add:(Ljava/security/Permission;)V
     264: aload_0
     265: new           #36                 // class org/jboss/as/naming/JndiPermission
     268: dup
     269: ldc           #51                 // String java:jboss
     271: iconst_1
     272: anewarray     #38                 // class org/jboss/as/naming/JndiPermission$Action
     275: dup
     276: iconst_0
     277: getstatic     #39                 // Field org/jboss/as/naming/JndiPermission$Action.LOOKUP:Lorg/jboss/as/naming/JndiPermission$Action;
     280: aastore
     281: invokespecial #42                 // Method org/jboss/as/naming/JndiPermission."<init>":(Ljava/lang/String;[Lorg/jboss/as/naming/JndiPermission$Action;)V
     284: invokevirtual #43                 // Method java/security/Permissions.add:(Ljava/security/Permission;)V
     287: aload_0
     288: new           #36                 // class org/jboss/as/naming/JndiPermission
     291: dup
     292: ldc           #52                 // String java:jboss/-
     294: iconst_1
     295: anewarray     #38                 // class org/jboss/as/naming/JndiPermission$Action
     298: dup
     299: iconst_0
     300: getstatic     #39                 // Field org/jboss/as/naming/JndiPermission$Action.LOOKUP:Lorg/jboss/as/naming/JndiPermission$Action;
     303: aastore
     304: invokespecial #42                 // Method org/jboss/as/naming/JndiPermission."<init>":(Ljava/lang/String;[Lorg/jboss/as/naming/JndiPermission$Action;)V
     307: invokevirtual #43                 // Method java/security/Permissions.add:(Ljava/security/Permission;)V
     310: aload_0
     311: new           #36                 // class org/jboss/as/naming/JndiPermission
     314: dup
     315: ldc           #53                 // String java:/-
     317: iconst_1
     318: anewarray     #38                 // class org/jboss/as/naming/JndiPermission$Action
     321: dup
     322: iconst_0
     323: getstatic     #39                 // Field org/jboss/as/naming/JndiPermission$Action.LOOKUP:Lorg/jboss/as/naming/JndiPermission$Action;
     326: aastore
     327: invokespecial #42                 // Method org/jboss/as/naming/JndiPermission."<init>":(Ljava/lang/String;[Lorg/jboss/as/naming/JndiPermission$Action;)V
     330: invokevirtual #43                 // Method java/security/Permissions.add:(Ljava/security/Permission;)V
     333: aload_0
     334: putstatic     #7                  // Field DEFAULT_PERMISSIONS:Ljava/security/Permissions;
     337: return
}
