Compiled from "Base64Codec.java"
final class com.nimbusds.jose.util.Base64Codec {
  static final boolean $assertionsDisabled;

  com.nimbusds.jose.util.Base64Codec();
    Code:
       0: aload_0
       1: invokespecial #11                 // Method java/lang/Object."<init>":()V
       4: return

  static int computeEncodedLength(int, boolean);
    Code:
       0: iload_0
       1: ifne          6
       4: iconst_0
       5: ireturn
       6: iload_1
       7: ifeq          34
      10: iload_0
      11: iconst_3
      12: idiv
      13: iconst_2
      14: ishl
      15: istore_2
      16: iload_0
      17: iconst_3
      18: irem
      19: istore_3
      20: iload_3
      21: ifne          28
      24: iload_2
      25: goto          33
      28: iload_2
      29: iload_3
      30: iadd
      31: iconst_1
      32: iadd
      33: ireturn
      34: iload_0
      35: iconst_1
      36: isub
      37: iconst_3
      38: idiv
      39: iconst_1
      40: iadd
      41: iconst_2
      42: ishl
      43: ireturn

  static int tpSelect(int, int, int);
    Code:
       0: iload_0
       1: iconst_1
       2: isub
       3: istore_3
       4: iload_1
       5: iload_3
       6: iload_1
       7: iload_2
       8: ixor
       9: iand
      10: ixor
      11: ireturn

  static int tpLT(int, int);
    Code:
       0: iload_0
       1: i2l
       2: iload_1
       3: i2l
       4: lsub
       5: bipush        63
       7: lushr
       8: l2i
       9: ireturn

  static int tpGT(int, int);
    Code:
       0: iload_1
       1: i2l
       2: iload_0
       3: i2l
       4: lsub
       5: bipush        63
       7: lushr
       8: l2i
       9: ireturn

  static int tpEq(int, int);
    Code:
       0: iload_0
       1: iload_1
       2: ixor
       3: istore_2
       4: iload_2
       5: iconst_1
       6: isub
       7: iload_2
       8: iconst_m1
       9: ixor
      10: iand
      11: istore_3
      12: iload_3
      13: bipush        63
      15: iushr
      16: ireturn

  static byte encodeDigitBase64(int);
    Code:
       0: getstatic     #38                 // Field $assertionsDisabled:Z
       3: ifne          24
       6: iload_0
       7: iflt          16
      10: iload_0
      11: bipush        63
      13: if_icmple     24
      16: new           #40                 // class java/lang/AssertionError
      19: dup
      20: invokespecial #41                 // Method java/lang/AssertionError."<init>":()V
      23: athrow
      24: iload_0
      25: bipush        26
      27: invokestatic  #43                 // Method tpLT:(II)I
      30: istore_1
      31: iload_0
      32: bipush        25
      34: invokestatic  #45                 // Method tpGT:(II)I
      37: iload_0
      38: bipush        52
      40: invokestatic  #43                 // Method tpLT:(II)I
      43: iand
      44: istore_2
      45: iload_0
      46: bipush        51
      48: invokestatic  #45                 // Method tpGT:(II)I
      51: iload_0
      52: bipush        62
      54: invokestatic  #43                 // Method tpLT:(II)I
      57: iand
      58: istore_3
      59: iload_0
      60: bipush        62
      62: invokestatic  #47                 // Method tpEq:(II)I
      65: istore        4
      67: iload_0
      68: bipush        63
      70: invokestatic  #47                 // Method tpEq:(II)I
      73: istore        5
      75: iload_0
      76: iconst_0
      77: isub
      78: bipush        65
      80: iadd
      81: istore        6
      83: iload_0
      84: bipush        26
      86: isub
      87: bipush        97
      89: iadd
      90: istore        7
      92: iload_0
      93: bipush        52
      95: isub
      96: bipush        48
      98: iadd
      99: istore        8
     101: bipush        43
     103: istore        9
     105: bipush        47
     107: istore        10
     109: iload_1
     110: iload         6
     112: iconst_0
     113: invokestatic  #49                 // Method tpSelect:(III)I
     116: iload_2
     117: iload         7
     119: iconst_0
     120: invokestatic  #49                 // Method tpSelect:(III)I
     123: ior
     124: iload_3
     125: iload         8
     127: iconst_0
     128: invokestatic  #49                 // Method tpSelect:(III)I
     131: ior
     132: iload         4
     134: bipush        43
     136: iconst_0
     137: invokestatic  #49                 // Method tpSelect:(III)I
     140: ior
     141: iload         5
     143: bipush        47
     145: iconst_0
     146: invokestatic  #49                 // Method tpSelect:(III)I
     149: ior
     150: istore        11
     152: iload         11
     154: i2b
     155: ireturn

  static byte encodeDigitBase64URL(int);
    Code:
       0: getstatic     #38                 // Field $assertionsDisabled:Z
       3: ifne          24
       6: iload_0
       7: iflt          16
      10: iload_0
      11: bipush        63
      13: if_icmple     24
      16: new           #40                 // class java/lang/AssertionError
      19: dup
      20: invokespecial #41                 // Method java/lang/AssertionError."<init>":()V
      23: athrow
      24: iload_0
      25: bipush        26
      27: invokestatic  #43                 // Method tpLT:(II)I
      30: istore_1
      31: iload_0
      32: bipush        25
      34: invokestatic  #45                 // Method tpGT:(II)I
      37: iload_0
      38: bipush        52
      40: invokestatic  #43                 // Method tpLT:(II)I
      43: iand
      44: istore_2
      45: iload_0
      46: bipush        51
      48: invokestatic  #45                 // Method tpGT:(II)I
      51: iload_0
      52: bipush        62
      54: invokestatic  #43                 // Method tpLT:(II)I
      57: iand
      58: istore_3
      59: iload_0
      60: bipush        62
      62: invokestatic  #47                 // Method tpEq:(II)I
      65: istore        4
      67: iload_0
      68: bipush        63
      70: invokestatic  #47                 // Method tpEq:(II)I
      73: istore        5
      75: iload_0
      76: iconst_0
      77: isub
      78: bipush        65
      80: iadd
      81: istore        6
      83: iload_0
      84: bipush        26
      86: isub
      87: bipush        97
      89: iadd
      90: istore        7
      92: iload_0
      93: bipush        52
      95: isub
      96: bipush        48
      98: iadd
      99: istore        8
     101: bipush        45
     103: istore        9
     105: bipush        95
     107: istore        10
     109: iload_1
     110: iload         6
     112: iconst_0
     113: invokestatic  #49                 // Method tpSelect:(III)I
     116: iload_2
     117: iload         7
     119: iconst_0
     120: invokestatic  #49                 // Method tpSelect:(III)I
     123: ior
     124: iload_3
     125: iload         8
     127: iconst_0
     128: invokestatic  #49                 // Method tpSelect:(III)I
     131: ior
     132: iload         4
     134: bipush        45
     136: iconst_0
     137: invokestatic  #49                 // Method tpSelect:(III)I
     140: ior
     141: iload         5
     143: bipush        95
     145: iconst_0
     146: invokestatic  #49                 // Method tpSelect:(III)I
     149: ior
     150: istore        11
     152: iload         11
     154: i2b
     155: ireturn

  static int decodeDigit(byte);
    Code:
       0: iload_0
       1: bipush        64
       3: invokestatic  #45                 // Method tpGT:(II)I
       6: iload_0
       7: bipush        91
       9: invokestatic  #43                 // Method tpLT:(II)I
      12: iand
      13: istore_1
      14: iload_0
      15: bipush        96
      17: invokestatic  #45                 // Method tpGT:(II)I
      20: iload_0
      21: bipush        123
      23: invokestatic  #43                 // Method tpLT:(II)I
      26: iand
      27: istore_2
      28: iload_0
      29: bipush        47
      31: invokestatic  #45                 // Method tpGT:(II)I
      34: iload_0
      35: bipush        58
      37: invokestatic  #43                 // Method tpLT:(II)I
      40: iand
      41: istore_3
      42: iload_0
      43: bipush        45
      45: invokestatic  #47                 // Method tpEq:(II)I
      48: iload_0
      49: bipush        43
      51: invokestatic  #47                 // Method tpEq:(II)I
      54: ior
      55: istore        4
      57: iload_0
      58: bipush        95
      60: invokestatic  #47                 // Method tpEq:(II)I
      63: iload_0
      64: bipush        47
      66: invokestatic  #47                 // Method tpEq:(II)I
      69: ior
      70: istore        5
      72: iload_1
      73: iload_2
      74: ior
      75: iload_3
      76: ior
      77: iload         4
      79: ior
      80: iload         5
      82: ior
      83: istore        6
      85: iload_0
      86: bipush        65
      88: isub
      89: iconst_0
      90: iadd
      91: istore        7
      93: iload_0
      94: bipush        97
      96: isub
      97: bipush        26
      99: iadd
     100: istore        8
     102: iload_0
     103: bipush        48
     105: isub
     106: bipush        52
     108: iadd
     109: istore        9
     111: bipush        62
     113: istore        10
     115: bipush        63
     117: istore        11
     119: iload_1
     120: iload         7
     122: iconst_0
     123: invokestatic  #49                 // Method tpSelect:(III)I
     126: iload_2
     127: iload         8
     129: iconst_0
     130: invokestatic  #49                 // Method tpSelect:(III)I
     133: ior
     134: iload_3
     135: iload         9
     137: iconst_0
     138: invokestatic  #49                 // Method tpSelect:(III)I
     141: ior
     142: iload         4
     144: bipush        62
     146: iconst_0
     147: invokestatic  #49                 // Method tpSelect:(III)I
     150: ior
     151: iload         5
     153: bipush        63
     155: iconst_0
     156: invokestatic  #49                 // Method tpSelect:(III)I
     159: ior
     160: iload         6
     162: iconst_0
     163: iconst_m1
     164: invokestatic  #49                 // Method tpSelect:(III)I
     167: ior
     168: istore        12
     170: getstatic     #38                 // Field $assertionsDisabled:Z
     173: ifne          197
     176: iload         12
     178: iconst_m1
     179: if_icmplt     189
     182: iload         12
     184: bipush        63
     186: if_icmple     197
     189: new           #40                 // class java/lang/AssertionError
     192: dup
     193: invokespecial #41                 // Method java/lang/AssertionError."<init>":()V
     196: athrow
     197: iload         12
     199: ireturn

  public static java.lang.String encodeToString(byte[], boolean);
    Code:
       0: aload_0
       1: ifnull        9
       4: aload_0
       5: arraylength
       6: goto          10
       9: iconst_0
      10: istore_2
      11: iload_2
      12: ifne          18
      15: ldc           #75                 // String
      17: areturn
      18: iload_2
      19: iconst_3
      20: idiv
      21: iconst_3
      22: imul
      23: istore_3
      24: iload_2
      25: iload_1
      26: invokestatic  #77                 // Method computeEncodedLength:(IZ)I
      29: istore        4
      31: iload         4
      33: newarray       byte
      35: astore        5
      37: iconst_0
      38: istore        6
      40: iconst_0
      41: istore        7
      43: iload         6
      45: iload_3
      46: if_icmpge     248
      49: aload_0
      50: iload         6
      52: iinc          6, 1
      55: baload
      56: sipush        255
      59: iand
      60: bipush        16
      62: ishl
      63: aload_0
      64: iload         6
      66: iinc          6, 1
      69: baload
      70: sipush        255
      73: iand
      74: bipush        8
      76: ishl
      77: ior
      78: aload_0
      79: iload         6
      81: iinc          6, 1
      84: baload
      85: sipush        255
      88: iand
      89: ior
      90: istore        8
      92: iload_1
      93: ifeq          172
      96: aload         5
      98: iload         7
     100: iinc          7, 1
     103: iload         8
     105: bipush        18
     107: iushr
     108: bipush        63
     110: iand
     111: invokestatic  #81                 // Method encodeDigitBase64URL:(I)B
     114: bastore
     115: aload         5
     117: iload         7
     119: iinc          7, 1
     122: iload         8
     124: bipush        12
     126: iushr
     127: bipush        63
     129: iand
     130: invokestatic  #81                 // Method encodeDigitBase64URL:(I)B
     133: bastore
     134: aload         5
     136: iload         7
     138: iinc          7, 1
     141: iload         8
     143: bipush        6
     145: iushr
     146: bipush        63
     148: iand
     149: invokestatic  #81                 // Method encodeDigitBase64URL:(I)B
     152: bastore
     153: aload         5
     155: iload         7
     157: iinc          7, 1
     160: iload         8
     162: bipush        63
     164: iand
     165: invokestatic  #81                 // Method encodeDigitBase64URL:(I)B
     168: bastore
     169: goto          245
     172: aload         5
     174: iload         7
     176: iinc          7, 1
     179: iload         8
     181: bipush        18
     183: iushr
     184: bipush        63
     186: iand
     187: invokestatic  #83                 // Method encodeDigitBase64:(I)B
     190: bastore
     191: aload         5
     193: iload         7
     195: iinc          7, 1
     198: iload         8
     200: bipush        12
     202: iushr
     203: bipush        63
     205: iand
     206: invokestatic  #83                 // Method encodeDigitBase64:(I)B
     209: bastore
     210: aload         5
     212: iload         7
     214: iinc          7, 1
     217: iload         8
     219: bipush        6
     221: iushr
     222: bipush        63
     224: iand
     225: invokestatic  #83                 // Method encodeDigitBase64:(I)B
     228: bastore
     229: aload         5
     231: iload         7
     233: iinc          7, 1
     236: iload         8
     238: bipush        63
     240: iand
     241: invokestatic  #83                 // Method encodeDigitBase64:(I)B
     244: bastore
     245: goto          43
     248: iload_2
     249: iload_3
     250: isub
     251: istore        6
     253: iload         6
     255: ifle          457
     258: aload_0
     259: iload_3
     260: baload
     261: sipush        255
     264: iand
     265: bipush        10
     267: ishl
     268: iload         6
     270: iconst_2
     271: if_icmpne     288
     274: aload_0
     275: iload_2
     276: iconst_1
     277: isub
     278: baload
     279: sipush        255
     282: iand
     283: iconst_2
     284: ishl
     285: goto          289
     288: iconst_0
     289: ior
     290: istore        7
     292: iload_1
     293: ifeq          389
     296: iload         6
     298: iconst_2
     299: if_icmpne     353
     302: aload         5
     304: iload         4
     306: iconst_3
     307: isub
     308: iload         7
     310: bipush        12
     312: ishr
     313: invokestatic  #81                 // Method encodeDigitBase64URL:(I)B
     316: bastore
     317: aload         5
     319: iload         4
     321: iconst_2
     322: isub
     323: iload         7
     325: bipush        6
     327: iushr
     328: bipush        63
     330: iand
     331: invokestatic  #81                 // Method encodeDigitBase64URL:(I)B
     334: bastore
     335: aload         5
     337: iload         4
     339: iconst_1
     340: isub
     341: iload         7
     343: bipush        63
     345: iand
     346: invokestatic  #81                 // Method encodeDigitBase64URL:(I)B
     349: bastore
     350: goto          457
     353: aload         5
     355: iload         4
     357: iconst_2
     358: isub
     359: iload         7
     361: bipush        12
     363: ishr
     364: invokestatic  #81                 // Method encodeDigitBase64URL:(I)B
     367: bastore
     368: aload         5
     370: iload         4
     372: iconst_1
     373: isub
     374: iload         7
     376: bipush        6
     378: iushr
     379: bipush        63
     381: iand
     382: invokestatic  #81                 // Method encodeDigitBase64URL:(I)B
     385: bastore
     386: goto          457
     389: aload         5
     391: iload         4
     393: iconst_4
     394: isub
     395: iload         7
     397: bipush        12
     399: ishr
     400: invokestatic  #83                 // Method encodeDigitBase64:(I)B
     403: bastore
     404: aload         5
     406: iload         4
     408: iconst_3
     409: isub
     410: iload         7
     412: bipush        6
     414: iushr
     415: bipush        63
     417: iand
     418: invokestatic  #83                 // Method encodeDigitBase64:(I)B
     421: bastore
     422: aload         5
     424: iload         4
     426: iconst_2
     427: isub
     428: iload         6
     430: iconst_2
     431: if_icmpne     445
     434: iload         7
     436: bipush        63
     438: iand
     439: invokestatic  #83                 // Method encodeDigitBase64:(I)B
     442: goto          447
     445: bipush        61
     447: bastore
     448: aload         5
     450: iload         4
     452: iconst_1
     453: isub
     454: bipush        61
     456: bastore
     457: new           #85                 // class java/lang/String
     460: dup
     461: aload         5
     463: getstatic     #91                 // Field com/nimbusds/jose/util/StandardCharset.UTF_8:Ljava/nio/charset/Charset;
     466: invokespecial #94                 // Method java/lang/String."<init>":([BLjava/nio/charset/Charset;)V
     469: areturn

  public static byte[] decode(java.lang.String);
    Code:
       0: aload_0
       1: ifnull        11
       4: aload_0
       5: invokevirtual #109                // Method java/lang/String.isEmpty:()Z
       8: ifeq          15
      11: iconst_0
      12: newarray       byte
      14: areturn
      15: aload_0
      16: getstatic     #91                 // Field com/nimbusds/jose/util/StandardCharset.UTF_8:Ljava/nio/charset/Charset;
      19: invokevirtual #113                // Method java/lang/String.getBytes:(Ljava/nio/charset/Charset;)[B
      22: astore_1
      23: aload_1
      24: arraylength
      25: istore_2
      26: iload_2
      27: i2l
      28: ldc2_w        #114                // long 6l
      31: lmul
      32: iconst_3
      33: lshr
      34: invokestatic  #119                // Method checkedCast:(J)I
      37: istore_3
      38: iload_3
      39: newarray       byte
      41: astore        4
      43: iconst_0
      44: istore        5
      46: iconst_0
      47: istore        6
      49: iload         6
      51: aload_1
      52: arraylength
      53: if_icmpge     173
      56: iconst_0
      57: istore        7
      59: iconst_0
      60: istore        8
      62: iload         8
      64: iconst_4
      65: if_icmpge     113
      68: iload         6
      70: iload_2
      71: if_icmpge     113
      74: aload_1
      75: iload         6
      77: iinc          6, 1
      80: baload
      81: invokestatic  #121                // Method decodeDigit:(B)I
      84: istore        9
      86: iload         9
      88: iflt          110
      91: iload         7
      93: iload         9
      95: bipush        18
      97: iload         8
      99: bipush        6
     101: imul
     102: isub
     103: ishl
     104: ior
     105: istore        7
     107: iinc          8, 1
     110: goto          62
     113: iload         8
     115: iconst_2
     116: if_icmplt     170
     119: aload         4
     121: iload         5
     123: iinc          5, 1
     126: iload         7
     128: bipush        16
     130: ishr
     131: i2b
     132: bastore
     133: iload         8
     135: iconst_3
     136: if_icmplt     170
     139: aload         4
     141: iload         5
     143: iinc          5, 1
     146: iload         7
     148: bipush        8
     150: ishr
     151: i2b
     152: bastore
     153: iload         8
     155: iconst_4
     156: if_icmplt     170
     159: aload         4
     161: iload         5
     163: iinc          5, 1
     166: iload         7
     168: i2b
     169: bastore
     170: goto          49
     173: aload         4
     175: iload         5
     177: invokestatic  #127                // Method java/util/Arrays.copyOf:([BI)[B
     180: areturn

  private static int checkedCast(long);
    Code:
       0: lload_0
       1: l2i
       2: istore_2
       3: iload_2
       4: i2l
       5: lload_0
       6: lcmp
       7: ifeq          37
      10: new           #136                // class java/lang/IllegalArgumentException
      13: dup
      14: new           #138                // class java/lang/StringBuilder
      17: dup
      18: invokespecial #139                // Method java/lang/StringBuilder."<init>":()V
      21: lload_0
      22: invokevirtual #143                // Method java/lang/StringBuilder.append:(J)Ljava/lang/StringBuilder;
      25: ldc           #145                // String  cannot be cast to int without changing its value.
      27: invokevirtual #148                // Method java/lang/StringBuilder.append:(Ljava/lang/String;)Ljava/lang/StringBuilder;
      30: invokevirtual #152                // Method java/lang/StringBuilder.toString:()Ljava/lang/String;
      33: invokespecial #155                // Method java/lang/IllegalArgumentException."<init>":(Ljava/lang/String;)V
      36: athrow
      37: iload_2
      38: ireturn

  static {};
    Code:
       0: ldc           #2                  // class com/nimbusds/jose/util/Base64Codec
       2: invokevirtual #164                // Method java/lang/Class.desiredAssertionStatus:()Z
       5: ifne          12
       8: iconst_1
       9: goto          13
      12: iconst_0
      13: putstatic     #38                 // Field $assertionsDisabled:Z
      16: return
}
