Compiled from "TempFolderCleaner.java"
public class org.sonar.api.utils.internal.TempFolderCleaner {
  private org.sonar.api.utils.TempFolder defaultTempFolder;

  public org.sonar.api.utils.internal.TempFolderCleaner(org.sonar.api.utils.TempFolder);
    Code:
       0: aload_0
       1: invokespecial #13                 // Method java/lang/Object."<init>":()V
       4: aload_0
       5: aload_1
       6: putfield      #15                 // Field defaultTempFolder:Lorg/sonar/api/utils/TempFolder;
       9: return

  public void start();
    Code:
       0: return

  public void stop();
    Code:
       0: aload_0
       1: getfield      #15                 // Field defaultTempFolder:Lorg/sonar/api/utils/TempFolder;
       4: checkcast     #21                 // class org/sonar/api/utils/internal/DefaultTempFolder
       7: invokevirtual #24                 // Method org/sonar/api/utils/internal/DefaultTempFolder.clean:()V
      10: return
}
