Compiled from "TestSystem2.java"
public class org.sonar.api.utils.internal.TestSystem2 extends org.sonar.api.utils.System2 {
  private long now;

  public org.sonar.api.utils.internal.TestSystem2();
    Code:
       0: aload_0
       1: invokespecial #11                 // Method org/sonar/api/utils/System2."<init>":()V
       4: aload_0
       5: lconst_0
       6: putfield      #13                 // Field now:J
       9: return

  public org.sonar.api.utils.internal.TestSystem2 setNow(long);
    Code:
       0: aload_0
       1: lload_1
       2: putfield      #13                 // Field now:J
       5: aload_0
       6: areturn

  public long now();
    Code:
       0: aload_0
       1: getfield      #13                 // Field now:J
       4: lconst_0
       5: lcmp
       6: ifgt          19
       9: new           #21                 // class java/lang/IllegalStateException
      12: dup
      13: ldc           #23                 // String Method setNow() was not called by test
      15: invokespecial #26                 // Method java/lang/IllegalStateException."<init>":(Ljava/lang/String;)V
      18: athrow
      19: aload_0
      20: getfield      #13                 // Field now:J
      23: lreturn
}
