Compiled from "TransactionAwareDirContextInvocationHandler.java"
public class org.springframework.ldap.transaction.compensating.manager.TransactionAwareDirContextInvocationHandler implements java.lang.reflect.InvocationHandler {
  private static org.slf4j.Logger log;

  private javax.naming.directory.DirContext target;

  private org.springframework.ldap.core.ContextSource contextSource;

  public org.springframework.ldap.transaction.compensating.manager.TransactionAwareDirContextInvocationHandler(javax.naming.directory.DirContext, org.springframework.ldap.core.ContextSource);
    Code:
       0: aload_0
       1: invokespecial #1                  // Method java/lang/Object."<init>":()V
       4: aload_0
       5: aload_1
       6: putfield      #2                  // Field target:Ljavax/naming/directory/DirContext;
       9: aload_0
      10: aload_2
      11: putfield      #3                  // Field contextSource:Lorg/springframework/ldap/core/ContextSource;
      14: return

  public java.lang.Object invoke(java.lang.Object, java.lang.reflect.Method, java.lang.Object[]) throws java.lang.Throwable;
    Code:
       0: aload_2
       1: invokevirtual #4                  // Method java/lang/reflect/Method.getName:()Ljava/lang/String;
       4: astore        4
       6: aload         4
       8: ldc           #5                  // String getTargetContext
      10: invokevirtual #6                  // Method java/lang/String.equals:(Ljava/lang/Object;)Z
      13: ifeq          21
      16: aload_0
      17: getfield      #2                  // Field target:Ljavax/naming/directory/DirContext;
      20: areturn
      21: aload         4
      23: ldc           #7                  // String equals
      25: invokevirtual #6                  // Method java/lang/String.equals:(Ljava/lang/Object;)Z
      28: ifeq          48
      31: aload_1
      32: aload_3
      33: iconst_0
      34: aaload
      35: if_acmpne     44
      38: getstatic     #8                  // Field java/lang/Boolean.TRUE:Ljava/lang/Boolean;
      41: goto          47
      44: getstatic     #9                  // Field java/lang/Boolean.FALSE:Ljava/lang/Boolean;
      47: areturn
      48: aload         4
      50: ldc           #10                 // String hashCode
      52: invokevirtual #6                  // Method java/lang/String.equals:(Ljava/lang/Object;)Z
      55: ifeq          66
      58: aload_0
      59: invokevirtual #11                 // Method java/lang/Object.hashCode:()I
      62: invokestatic  #12                 // Method java/lang/Integer.valueOf:(I)Ljava/lang/Integer;
      65: areturn
      66: aload         4
      68: ldc           #13                 // String close
      70: invokevirtual #6                  // Method java/lang/String.equals:(Ljava/lang/Object;)Z
      73: ifeq          90
      76: aload_0
      77: aload_0
      78: getfield      #2                  // Field target:Ljavax/naming/directory/DirContext;
      81: aload_0
      82: getfield      #3                  // Field contextSource:Lorg/springframework/ldap/core/ContextSource;
      85: invokevirtual #14                 // Method doCloseConnection:(Ljavax/naming/directory/DirContext;Lorg/springframework/ldap/core/ContextSource;)V
      88: aconst_null
      89: areturn
      90: aload         4
      92: invokestatic  #15                 // Method org/springframework/ldap/transaction/compensating/LdapTransactionUtils.isSupportedWriteTransactionOperation:(Ljava/lang/String;)Z
      95: ifeq          113
      98: aload_0
      99: getfield      #3                  // Field contextSource:Lorg/springframework/ldap/core/ContextSource;
     102: aload_0
     103: getfield      #2                  // Field target:Ljavax/naming/directory/DirContext;
     106: aload_2
     107: aload_3
     108: invokestatic  #16                 // Method org/springframework/transaction/compensating/support/CompensatingTransactionUtils.performOperation:(Ljava/lang/Object;Ljava/lang/Object;Ljava/lang/reflect/Method;[Ljava/lang/Object;)V
     111: aconst_null
     112: areturn
     113: aload_2
     114: aload_0
     115: getfield      #2                  // Field target:Ljavax/naming/directory/DirContext;
     118: aload_3
     119: invokevirtual #17                 // Method java/lang/reflect/Method.invoke:(Ljava/lang/Object;[Ljava/lang/Object;)Ljava/lang/Object;
     122: areturn
     123: astore        5
     125: aload         5
     127: invokevirtual #19                 // Method java/lang/reflect/InvocationTargetException.getTargetException:()Ljava/lang/Throwable;
     130: athrow
    Exception table:
       from    to  target type
         113   122   123   Class java/lang/reflect/InvocationTargetException

  void doCloseConnection(javax.naming.directory.DirContext, org.springframework.ldap.core.ContextSource) throws javax.naming.NamingException;
    Code:
       0: aload_2
       1: invokestatic  #20                 // Method org/springframework/transaction/support/TransactionSynchronizationManager.getResource:(Ljava/lang/Object;)Ljava/lang/Object;
       4: checkcast     #21                 // class org/springframework/ldap/transaction/compensating/manager/DirContextHolder
       7: astore_3
       8: aload_3
       9: ifnull        20
      12: aload_3
      13: invokevirtual #22                 // Method org/springframework/ldap/transaction/compensating/manager/DirContextHolder.getCtx:()Ljavax/naming/directory/DirContext;
      16: aload_1
      17: if_acmpeq     39
      20: getstatic     #23                 // Field log:Lorg/slf4j/Logger;
      23: ldc           #24                 // String Closing context
      25: invokeinterface #25,  2           // InterfaceMethod org/slf4j/Logger.debug:(Ljava/lang/String;)V
      30: aload_1
      31: invokeinterface #26,  1           // InterfaceMethod javax/naming/directory/DirContext.close:()V
      36: goto          49
      39: getstatic     #23                 // Field log:Lorg/slf4j/Logger;
      42: ldc           #27                 // String Leaving transactional context open
      44: invokeinterface #25,  2           // InterfaceMethod org/slf4j/Logger.debug:(Ljava/lang/String;)V
      49: return

  static {};
    Code:
       0: ldc           #28                 // class org/springframework/ldap/transaction/compensating/manager/TransactionAwareDirContextInvocationHandler
       2: invokestatic  #29                 // Method org/slf4j/LoggerFactory.getLogger:(Ljava/lang/Class;)Lorg/slf4j/Logger;
       5: putstatic     #23                 // Field log:Lorg/slf4j/Logger;
       8: return
}
