public class org.bouncycastle.crypto.paddings.PKCS7Padding implements org.bouncycastle.crypto.paddings.BlockCipherPadding {
  public org.bouncycastle.crypto.paddings.PKCS7Padding();
    Code:
       0: aload_0
       1: invokespecial #28                 // Method java/lang/Object."<init>":()V
       4: return

  public void init(java.security.SecureRandom) throws java.lang.IllegalArgumentException;
    Code:
       0: return

  public java.lang.String getPaddingName();
    Code:
       0: ldc           #1                  // String PKCS7
       2: areturn

  public int addPadding(byte[], int);
    Code:
       0: aload_1
       1: arraylength
       2: iload_2
       3: isub
       4: i2b
       5: istore_3
       6: iload_2
       7: aload_1
       8: arraylength
       9: if_icmpge     22
      12: aload_1
      13: iload_2
      14: iload_3
      15: bastore
      16: iinc          2, 1
      19: goto          6
      22: iload_3
      23: ireturn

  public int padCount(byte[]) throws org.bouncycastle.crypto.InvalidCipherTextException;
    Code:
       0: aload_1
       1: aload_1
       2: arraylength
       3: iconst_1
       4: isub
       5: baload
       6: sipush        255
       9: iand
      10: istore_2
      11: iload_2
      12: i2b
      13: istore_3
      14: iload_2
      15: aload_1
      16: arraylength
      17: if_icmple     24
      20: iconst_1
      21: goto          25
      24: iconst_0
      25: iload_2
      26: ifne          33
      29: iconst_1
      30: goto          34
      33: iconst_0
      34: ior
      35: istore        4
      37: iconst_0
      38: istore        5
      40: iload         5
      42: aload_1
      43: arraylength
      44: if_icmpge     86
      47: iload         4
      49: aload_1
      50: arraylength
      51: iload         5
      53: isub
      54: iload_2
      55: if_icmpgt     62
      58: iconst_1
      59: goto          63
      62: iconst_0
      63: aload_1
      64: iload         5
      66: baload
      67: iload_3
      68: if_icmpeq     75
      71: iconst_1
      72: goto          76
      75: iconst_0
      76: iand
      77: ior
      78: istore        4
      80: iinc          5, 1
      83: goto          40
      86: iload         4
      88: ifeq          101
      91: new           #20                 // class org/bouncycastle/crypto/InvalidCipherTextException
      94: dup
      95: ldc           #2                  // String pad block corrupted
      97: invokespecial #29                 // Method org/bouncycastle/crypto/InvalidCipherTextException."<init>":(Ljava/lang/String;)V
     100: athrow
     101: iload_2
     102: ireturn
}
