Compiled from "XmlPullParserFactory.java"
public class org.xmlpull.v1.XmlPullParserFactory {
  static final java.lang.Class referenceContextClass;

  public static final java.lang.String PROPERTY_NAME;

  private static final java.lang.String RESOURCE_NAME;

  protected java.util.Vector parserClasses;

  protected java.lang.String classNamesLocation;

  protected java.util.Vector serializerClasses;

  protected java.util.Hashtable features;

  protected org.xmlpull.v1.XmlPullParserFactory();
    Code:
       0: aload_0
       1: invokespecial #1                  // Method java/lang/Object."<init>":()V
       4: aload_0
       5: new           #2                  // class java/util/Hashtable
       8: dup
       9: invokespecial #3                  // Method java/util/Hashtable."<init>":()V
      12: putfield      #4                  // Field features:Ljava/util/Hashtable;
      15: return

  public void setFeature(java.lang.String, boolean) throws org.xmlpull.v1.XmlPullParserException;
    Code:
       0: aload_0
       1: getfield      #4                  // Field features:Ljava/util/Hashtable;
       4: aload_1
       5: new           #5                  // class java/lang/Boolean
       8: dup
       9: iload_2
      10: invokespecial #6                  // Method java/lang/Boolean."<init>":(Z)V
      13: invokevirtual #7                  // Method java/util/Hashtable.put:(Ljava/lang/Object;Ljava/lang/Object;)Ljava/lang/Object;
      16: pop
      17: return

  public boolean getFeature(java.lang.String);
    Code:
       0: aload_0
       1: getfield      #4                  // Field features:Ljava/util/Hashtable;
       4: aload_1
       5: invokevirtual #8                  // Method java/util/Hashtable.get:(Ljava/lang/Object;)Ljava/lang/Object;
       8: checkcast     #5                  // class java/lang/Boolean
      11: astore_2
      12: aload_2
      13: ifnull        23
      16: aload_2
      17: invokevirtual #9                  // Method java/lang/Boolean.booleanValue:()Z
      20: goto          24
      23: iconst_0
      24: ireturn

  public void setNamespaceAware(boolean);
    Code:
       0: aload_0
       1: getfield      #4                  // Field features:Ljava/util/Hashtable;
       4: ldc           #10                 // String http://xmlpull.org/v1/doc/features.html#process-namespaces
       6: new           #5                  // class java/lang/Boolean
       9: dup
      10: iload_1
      11: invokespecial #6                  // Method java/lang/Boolean."<init>":(Z)V
      14: invokevirtual #7                  // Method java/util/Hashtable.put:(Ljava/lang/Object;Ljava/lang/Object;)Ljava/lang/Object;
      17: pop
      18: return

  public boolean isNamespaceAware();
    Code:
       0: aload_0
       1: ldc           #10                 // String http://xmlpull.org/v1/doc/features.html#process-namespaces
       3: invokevirtual #11                 // Method getFeature:(Ljava/lang/String;)Z
       6: ireturn

  public void setValidating(boolean);
    Code:
       0: aload_0
       1: getfield      #4                  // Field features:Ljava/util/Hashtable;
       4: ldc           #12                 // String http://xmlpull.org/v1/doc/features.html#validation
       6: new           #5                  // class java/lang/Boolean
       9: dup
      10: iload_1
      11: invokespecial #6                  // Method java/lang/Boolean."<init>":(Z)V
      14: invokevirtual #7                  // Method java/util/Hashtable.put:(Ljava/lang/Object;Ljava/lang/Object;)Ljava/lang/Object;
      17: pop
      18: return

  public boolean isValidating();
    Code:
       0: aload_0
       1: ldc           #12                 // String http://xmlpull.org/v1/doc/features.html#validation
       3: invokevirtual #11                 // Method getFeature:(Ljava/lang/String;)Z
       6: ireturn

  public org.xmlpull.v1.XmlPullParser newPullParser() throws org.xmlpull.v1.XmlPullParserException;
    Code:
       0: aload_0
       1: getfield      #13                 // Field parserClasses:Ljava/util/Vector;
       4: ifnonnull     37
       7: new           #14                 // class org/xmlpull/v1/XmlPullParserException
      10: dup
      11: new           #15                 // class java/lang/StringBuffer
      14: dup
      15: invokespecial #16                 // Method java/lang/StringBuffer."<init>":()V
      18: ldc           #17                 // String Factory initialization was incomplete - has not tried
      20: invokevirtual #18                 // Method java/lang/StringBuffer.append:(Ljava/lang/String;)Ljava/lang/StringBuffer;
      23: aload_0
      24: getfield      #19                 // Field classNamesLocation:Ljava/lang/String;
      27: invokevirtual #18                 // Method java/lang/StringBuffer.append:(Ljava/lang/String;)Ljava/lang/StringBuffer;
      30: invokevirtual #20                 // Method java/lang/StringBuffer.toString:()Ljava/lang/String;
      33: invokespecial #21                 // Method org/xmlpull/v1/XmlPullParserException."<init>":(Ljava/lang/String;)V
      36: athrow
      37: aload_0
      38: getfield      #13                 // Field parserClasses:Ljava/util/Vector;
      41: invokevirtual #22                 // Method java/util/Vector.size:()I
      44: ifne          77
      47: new           #14                 // class org/xmlpull/v1/XmlPullParserException
      50: dup
      51: new           #15                 // class java/lang/StringBuffer
      54: dup
      55: invokespecial #16                 // Method java/lang/StringBuffer."<init>":()V
      58: ldc           #23                 // String No valid parser classes found in
      60: invokevirtual #18                 // Method java/lang/StringBuffer.append:(Ljava/lang/String;)Ljava/lang/StringBuffer;
      63: aload_0
      64: getfield      #19                 // Field classNamesLocation:Ljava/lang/String;
      67: invokevirtual #18                 // Method java/lang/StringBuffer.append:(Ljava/lang/String;)Ljava/lang/StringBuffer;
      70: invokevirtual #20                 // Method java/lang/StringBuffer.toString:()Ljava/lang/String;
      73: invokespecial #21                 // Method org/xmlpull/v1/XmlPullParserException."<init>":(Ljava/lang/String;)V
      76: athrow
      77: new           #15                 // class java/lang/StringBuffer
      80: dup
      81: invokespecial #16                 // Method java/lang/StringBuffer."<init>":()V
      84: astore_1
      85: iconst_0
      86: istore_2
      87: iload_2
      88: aload_0
      89: getfield      #13                 // Field parserClasses:Ljava/util/Vector;
      92: invokevirtual #22                 // Method java/util/Vector.size:()I
      95: if_icmpge     241
      98: aload_0
      99: getfield      #13                 // Field parserClasses:Ljava/util/Vector;
     102: iload_2
     103: invokevirtual #24                 // Method java/util/Vector.elementAt:(I)Ljava/lang/Object;
     106: checkcast     #25                 // class java/lang/Class
     109: astore_3
     110: aload_3
     111: invokevirtual #26                 // Method java/lang/Class.newInstance:()Ljava/lang/Object;
     114: checkcast     #27                 // class org/xmlpull/v1/XmlPullParser
     117: astore        4
     119: aload_0
     120: getfield      #4                  // Field features:Ljava/util/Hashtable;
     123: invokevirtual #28                 // Method java/util/Hashtable.keys:()Ljava/util/Enumeration;
     126: astore        5
     128: aload         5
     130: invokeinterface #29,  1           // InterfaceMethod java/util/Enumeration.hasMoreElements:()Z
     135: ifeq          190
     138: aload         5
     140: invokeinterface #30,  1           // InterfaceMethod java/util/Enumeration.nextElement:()Ljava/lang/Object;
     145: checkcast     #31                 // class java/lang/String
     148: astore        6
     150: aload_0
     151: getfield      #4                  // Field features:Ljava/util/Hashtable;
     154: aload         6
     156: invokevirtual #8                  // Method java/util/Hashtable.get:(Ljava/lang/Object;)Ljava/lang/Object;
     159: checkcast     #5                  // class java/lang/Boolean
     162: astore        7
     164: aload         7
     166: ifnull        187
     169: aload         7
     171: invokevirtual #9                  // Method java/lang/Boolean.booleanValue:()Z
     174: ifeq          187
     177: aload         4
     179: aload         6
     181: iconst_1
     182: invokeinterface #32,  3           // InterfaceMethod org/xmlpull/v1/XmlPullParser.setFeature:(Ljava/lang/String;Z)V
     187: goto          128
     190: aload         4
     192: areturn
     193: astore        4
     195: aload_1
     196: new           #15                 // class java/lang/StringBuffer
     199: dup
     200: invokespecial #16                 // Method java/lang/StringBuffer."<init>":()V
     203: aload_3
     204: invokevirtual #34                 // Method java/lang/Class.getName:()Ljava/lang/String;
     207: invokevirtual #18                 // Method java/lang/StringBuffer.append:(Ljava/lang/String;)Ljava/lang/StringBuffer;
     210: ldc           #35                 // String :
     212: invokevirtual #18                 // Method java/lang/StringBuffer.append:(Ljava/lang/String;)Ljava/lang/StringBuffer;
     215: aload         4
     217: invokevirtual #36                 // Method java/lang/Throwable.toString:()Ljava/lang/String;
     220: invokevirtual #18                 // Method java/lang/StringBuffer.append:(Ljava/lang/String;)Ljava/lang/StringBuffer;
     223: ldc           #37                 // String ;
     225: invokevirtual #18                 // Method java/lang/StringBuffer.append:(Ljava/lang/String;)Ljava/lang/StringBuffer;
     228: invokevirtual #20                 // Method java/lang/StringBuffer.toString:()Ljava/lang/String;
     231: invokevirtual #18                 // Method java/lang/StringBuffer.append:(Ljava/lang/String;)Ljava/lang/StringBuffer;
     234: pop
     235: iinc          2, 1
     238: goto          87
     241: new           #14                 // class org/xmlpull/v1/XmlPullParserException
     244: dup
     245: new           #15                 // class java/lang/StringBuffer
     248: dup
     249: invokespecial #16                 // Method java/lang/StringBuffer."<init>":()V
     252: ldc           #38                 // String could not create parser:
     254: invokevirtual #18                 // Method java/lang/StringBuffer.append:(Ljava/lang/String;)Ljava/lang/StringBuffer;
     257: aload_1
     258: invokevirtual #39                 // Method java/lang/StringBuffer.append:(Ljava/lang/Object;)Ljava/lang/StringBuffer;
     261: invokevirtual #20                 // Method java/lang/StringBuffer.toString:()Ljava/lang/String;
     264: invokespecial #21                 // Method org/xmlpull/v1/XmlPullParserException."<init>":(Ljava/lang/String;)V
     267: athrow
    Exception table:
       from    to  target type
         110   192   193   Class java/lang/Exception

  public org.xmlpull.v1.XmlSerializer newSerializer() throws org.xmlpull.v1.XmlPullParserException;
    Code:
       0: aload_0
       1: getfield      #40                 // Field serializerClasses:Ljava/util/Vector;
       4: ifnonnull     37
       7: new           #14                 // class org/xmlpull/v1/XmlPullParserException
      10: dup
      11: new           #15                 // class java/lang/StringBuffer
      14: dup
      15: invokespecial #16                 // Method java/lang/StringBuffer."<init>":()V
      18: ldc           #41                 // String Factory initialization incomplete - has not tried
      20: invokevirtual #18                 // Method java/lang/StringBuffer.append:(Ljava/lang/String;)Ljava/lang/StringBuffer;
      23: aload_0
      24: getfield      #19                 // Field classNamesLocation:Ljava/lang/String;
      27: invokevirtual #18                 // Method java/lang/StringBuffer.append:(Ljava/lang/String;)Ljava/lang/StringBuffer;
      30: invokevirtual #20                 // Method java/lang/StringBuffer.toString:()Ljava/lang/String;
      33: invokespecial #21                 // Method org/xmlpull/v1/XmlPullParserException."<init>":(Ljava/lang/String;)V
      36: athrow
      37: aload_0
      38: getfield      #40                 // Field serializerClasses:Ljava/util/Vector;
      41: invokevirtual #22                 // Method java/util/Vector.size:()I
      44: ifne          77
      47: new           #14                 // class org/xmlpull/v1/XmlPullParserException
      50: dup
      51: new           #15                 // class java/lang/StringBuffer
      54: dup
      55: invokespecial #16                 // Method java/lang/StringBuffer."<init>":()V
      58: ldc           #42                 // String No valid serializer classes found in
      60: invokevirtual #18                 // Method java/lang/StringBuffer.append:(Ljava/lang/String;)Ljava/lang/StringBuffer;
      63: aload_0
      64: getfield      #19                 // Field classNamesLocation:Ljava/lang/String;
      67: invokevirtual #18                 // Method java/lang/StringBuffer.append:(Ljava/lang/String;)Ljava/lang/StringBuffer;
      70: invokevirtual #20                 // Method java/lang/StringBuffer.toString:()Ljava/lang/String;
      73: invokespecial #21                 // Method org/xmlpull/v1/XmlPullParserException."<init>":(Ljava/lang/String;)V
      76: athrow
      77: new           #15                 // class java/lang/StringBuffer
      80: dup
      81: invokespecial #16                 // Method java/lang/StringBuffer."<init>":()V
      84: astore_1
      85: iconst_0
      86: istore_2
      87: iload_2
      88: aload_0
      89: getfield      #40                 // Field serializerClasses:Ljava/util/Vector;
      92: invokevirtual #22                 // Method java/util/Vector.size:()I
      95: if_icmpge     170
      98: aload_0
      99: getfield      #40                 // Field serializerClasses:Ljava/util/Vector;
     102: iload_2
     103: invokevirtual #24                 // Method java/util/Vector.elementAt:(I)Ljava/lang/Object;
     106: checkcast     #25                 // class java/lang/Class
     109: astore_3
     110: aload_3
     111: invokevirtual #26                 // Method java/lang/Class.newInstance:()Ljava/lang/Object;
     114: checkcast     #43                 // class org/xmlpull/v1/XmlSerializer
     117: astore        4
     119: aload         4
     121: areturn
     122: astore        4
     124: aload_1
     125: new           #15                 // class java/lang/StringBuffer
     128: dup
     129: invokespecial #16                 // Method java/lang/StringBuffer."<init>":()V
     132: aload_3
     133: invokevirtual #34                 // Method java/lang/Class.getName:()Ljava/lang/String;
     136: invokevirtual #18                 // Method java/lang/StringBuffer.append:(Ljava/lang/String;)Ljava/lang/StringBuffer;
     139: ldc           #35                 // String :
     141: invokevirtual #18                 // Method java/lang/StringBuffer.append:(Ljava/lang/String;)Ljava/lang/StringBuffer;
     144: aload         4
     146: invokevirtual #36                 // Method java/lang/Throwable.toString:()Ljava/lang/String;
     149: invokevirtual #18                 // Method java/lang/StringBuffer.append:(Ljava/lang/String;)Ljava/lang/StringBuffer;
     152: ldc           #37                 // String ;
     154: invokevirtual #18                 // Method java/lang/StringBuffer.append:(Ljava/lang/String;)Ljava/lang/StringBuffer;
     157: invokevirtual #20                 // Method java/lang/StringBuffer.toString:()Ljava/lang/String;
     160: invokevirtual #18                 // Method java/lang/StringBuffer.append:(Ljava/lang/String;)Ljava/lang/StringBuffer;
     163: pop
     164: iinc          2, 1
     167: goto          87
     170: new           #14                 // class org/xmlpull/v1/XmlPullParserException
     173: dup
     174: new           #15                 // class java/lang/StringBuffer
     177: dup
     178: invokespecial #16                 // Method java/lang/StringBuffer."<init>":()V
     181: ldc           #44                 // String could not create serializer:
     183: invokevirtual #18                 // Method java/lang/StringBuffer.append:(Ljava/lang/String;)Ljava/lang/StringBuffer;
     186: aload_1
     187: invokevirtual #39                 // Method java/lang/StringBuffer.append:(Ljava/lang/Object;)Ljava/lang/StringBuffer;
     190: invokevirtual #20                 // Method java/lang/StringBuffer.toString:()Ljava/lang/String;
     193: invokespecial #21                 // Method org/xmlpull/v1/XmlPullParserException."<init>":(Ljava/lang/String;)V
     196: athrow
    Exception table:
       from    to  target type
         110   121   122   Class java/lang/Exception

  public static org.xmlpull.v1.XmlPullParserFactory newInstance() throws org.xmlpull.v1.XmlPullParserException;
    Code:
       0: aconst_null
       1: aconst_null
       2: invokestatic  #45                 // Method newInstance:(Ljava/lang/String;Ljava/lang/Class;)Lorg/xmlpull/v1/XmlPullParserFactory;
       5: areturn

  public static org.xmlpull.v1.XmlPullParserFactory newInstance(java.lang.String, java.lang.Class) throws org.xmlpull.v1.XmlPullParserException;
    Code:
       0: aload_1
       1: ifnonnull     8
       4: getstatic     #46                 // Field referenceContextClass:Ljava/lang/Class;
       7: astore_1
       8: aconst_null
       9: astore_2
      10: aload_0
      11: ifnull        30
      14: aload_0
      15: invokevirtual #47                 // Method java/lang/String.length:()I
      18: ifeq          30
      21: ldc           #48                 // String DEFAULT
      23: aload_0
      24: invokevirtual #49                 // Method java/lang/String.equals:(Ljava/lang/Object;)Z
      27: ifeq          146
      30: aload_1
      31: ldc           #50                 // String /META-INF/services/org.xmlpull.v1.XmlPullParserFactory
      33: invokevirtual #51                 // Method java/lang/Class.getResourceAsStream:(Ljava/lang/String;)Ljava/io/InputStream;
      36: astore_3
      37: aload_3
      38: ifnonnull     51
      41: new           #14                 // class org/xmlpull/v1/XmlPullParserException
      44: dup
      45: ldc           #52                 // String resource not found: /META-INF/services/org.xmlpull.v1.XmlPullParserFactory make sure that parser implementing XmlPull API is available
      47: invokespecial #21                 // Method org/xmlpull/v1/XmlPullParserException."<init>":(Ljava/lang/String;)V
      50: athrow
      51: new           #15                 // class java/lang/StringBuffer
      54: dup
      55: invokespecial #16                 // Method java/lang/StringBuffer."<init>":()V
      58: astore        4
      60: aload_3
      61: invokevirtual #53                 // Method java/io/InputStream.read:()I
      64: istore        5
      66: iload         5
      68: ifge          74
      71: goto          93
      74: iload         5
      76: bipush        32
      78: if_icmple     90
      81: aload         4
      83: iload         5
      85: i2c
      86: invokevirtual #54                 // Method java/lang/StringBuffer.append:(C)Ljava/lang/StringBuffer;
      89: pop
      90: goto          60
      93: aload_3
      94: invokevirtual #55                 // Method java/io/InputStream.close:()V
      97: aload         4
      99: invokevirtual #20                 // Method java/lang/StringBuffer.toString:()Ljava/lang/String;
     102: astore_0
     103: goto          118
     106: astore_3
     107: new           #14                 // class org/xmlpull/v1/XmlPullParserException
     110: dup
     111: aconst_null
     112: aconst_null
     113: aload_3
     114: invokespecial #56                 // Method org/xmlpull/v1/XmlPullParserException."<init>":(Ljava/lang/String;Lorg/xmlpull/v1/XmlPullParser;Ljava/lang/Throwable;)V
     117: athrow
     118: new           #15                 // class java/lang/StringBuffer
     121: dup
     122: invokespecial #16                 // Method java/lang/StringBuffer."<init>":()V
     125: ldc           #57                 // String resource /META-INF/services/org.xmlpull.v1.XmlPullParserFactory that contained \'
     127: invokevirtual #18                 // Method java/lang/StringBuffer.append:(Ljava/lang/String;)Ljava/lang/StringBuffer;
     130: aload_0
     131: invokevirtual #18                 // Method java/lang/StringBuffer.append:(Ljava/lang/String;)Ljava/lang/StringBuffer;
     134: ldc           #58                 // String \'
     136: invokevirtual #18                 // Method java/lang/StringBuffer.append:(Ljava/lang/String;)Ljava/lang/StringBuffer;
     139: invokevirtual #20                 // Method java/lang/StringBuffer.toString:()Ljava/lang/String;
     142: astore_2
     143: goto          171
     146: new           #15                 // class java/lang/StringBuffer
     149: dup
     150: invokespecial #16                 // Method java/lang/StringBuffer."<init>":()V
     153: ldc           #59                 // String parameter classNames to newInstance() that contained \'
     155: invokevirtual #18                 // Method java/lang/StringBuffer.append:(Ljava/lang/String;)Ljava/lang/StringBuffer;
     158: aload_0
     159: invokevirtual #18                 // Method java/lang/StringBuffer.append:(Ljava/lang/String;)Ljava/lang/StringBuffer;
     162: ldc           #58                 // String \'
     164: invokevirtual #18                 // Method java/lang/StringBuffer.append:(Ljava/lang/String;)Ljava/lang/StringBuffer;
     167: invokevirtual #20                 // Method java/lang/StringBuffer.toString:()Ljava/lang/String;
     170: astore_2
     171: aconst_null
     172: astore_3
     173: new           #60                 // class java/util/Vector
     176: dup
     177: invokespecial #61                 // Method java/util/Vector."<init>":()V
     180: astore        4
     182: new           #60                 // class java/util/Vector
     185: dup
     186: invokespecial #61                 // Method java/util/Vector."<init>":()V
     189: astore        5
     191: iconst_0
     192: istore        6
     194: iload         6
     196: aload_0
     197: invokevirtual #47                 // Method java/lang/String.length:()I
     200: if_icmpge     367
     203: aload_0
     204: bipush        44
     206: iload         6
     208: invokevirtual #62                 // Method java/lang/String.indexOf:(II)I
     211: istore        7
     213: iload         7
     215: iconst_m1
     216: if_icmpne     225
     219: aload_0
     220: invokevirtual #47                 // Method java/lang/String.length:()I
     223: istore        7
     225: aload_0
     226: iload         6
     228: iload         7
     230: invokevirtual #63                 // Method java/lang/String.substring:(II)Ljava/lang/String;
     233: astore        8
     235: aconst_null
     236: astore        9
     238: aconst_null
     239: astore        10
     241: aload         8
     243: invokestatic  #64                 // Method java/lang/Class.forName:(Ljava/lang/String;)Ljava/lang/Class;
     246: astore        9
     248: aload         9
     250: invokevirtual #26                 // Method java/lang/Class.newInstance:()Ljava/lang/Object;
     253: astore        10
     255: goto          260
     258: astore        11
     260: aload         9
     262: ifnull        358
     265: iconst_0
     266: istore        11
     268: aload         10
     270: instanceof    #27                 // class org/xmlpull/v1/XmlPullParser
     273: ifeq          286
     276: aload         4
     278: aload         9
     280: invokevirtual #65                 // Method java/util/Vector.addElement:(Ljava/lang/Object;)V
     283: iconst_1
     284: istore        11
     286: aload         10
     288: instanceof    #43                 // class org/xmlpull/v1/XmlSerializer
     291: ifeq          304
     294: aload         5
     296: aload         9
     298: invokevirtual #65                 // Method java/util/Vector.addElement:(Ljava/lang/Object;)V
     301: iconst_1
     302: istore        11
     304: aload         10
     306: instanceof    #66                 // class org/xmlpull/v1/XmlPullParserFactory
     309: ifeq          325
     312: aload_3
     313: ifnonnull     322
     316: aload         10
     318: checkcast     #66                 // class org/xmlpull/v1/XmlPullParserFactory
     321: astore_3
     322: iconst_1
     323: istore        11
     325: iload         11
     327: ifne          358
     330: new           #14                 // class org/xmlpull/v1/XmlPullParserException
     333: dup
     334: new           #15                 // class java/lang/StringBuffer
     337: dup
     338: invokespecial #16                 // Method java/lang/StringBuffer."<init>":()V
     341: ldc           #67                 // String incompatible class:
     343: invokevirtual #18                 // Method java/lang/StringBuffer.append:(Ljava/lang/String;)Ljava/lang/StringBuffer;
     346: aload         8
     348: invokevirtual #18                 // Method java/lang/StringBuffer.append:(Ljava/lang/String;)Ljava/lang/StringBuffer;
     351: invokevirtual #20                 // Method java/lang/StringBuffer.toString:()Ljava/lang/String;
     354: invokespecial #21                 // Method org/xmlpull/v1/XmlPullParserException."<init>":(Ljava/lang/String;)V
     357: athrow
     358: iload         7
     360: iconst_1
     361: iadd
     362: istore        6
     364: goto          194
     367: aload_3
     368: ifnonnull     379
     371: new           #66                 // class org/xmlpull/v1/XmlPullParserFactory
     374: dup
     375: invokespecial #68                 // Method "<init>":()V
     378: astore_3
     379: aload_3
     380: aload         4
     382: putfield      #13                 // Field parserClasses:Ljava/util/Vector;
     385: aload_3
     386: aload         5
     388: putfield      #40                 // Field serializerClasses:Ljava/util/Vector;
     391: aload_3
     392: aload_2
     393: putfield      #19                 // Field classNamesLocation:Ljava/lang/String;
     396: aload_3
     397: areturn
    Exception table:
       from    to  target type
          30   103   106   Class java/lang/Exception
         241   255   258   Class java/lang/Exception

  static {};
    Code:
       0: new           #66                 // class org/xmlpull/v1/XmlPullParserFactory
       3: dup
       4: invokespecial #68                 // Method "<init>":()V
       7: astore_0
       8: aload_0
       9: invokevirtual #69                 // Method java/lang/Object.getClass:()Ljava/lang/Class;
      12: putstatic     #46                 // Field referenceContextClass:Ljava/lang/Class;
      15: return
}
