Compiled from "Projection.scala"
public final class me.lyh.parquet.avro.Projection$$anonfun$applyImpl$1 extends scala.runtime.AbstractFunction1<java.lang.String, scala.reflect.api.Trees$TreeApi> implements scala.Serializable {
  public static final long serialVersionUID;

  private final scala.reflect.macros.blackbox.Context c$1;

  public final scala.reflect.api.Trees$TreeApi apply(java.lang.String);
    Code:
       0: aload_0
       1: getfield      #23                 // Field c$1:Lscala/reflect/macros/blackbox/Context;
       4: invokeinterface #29,  1           // InterfaceMethod scala/reflect/macros/blackbox/Context.universe:()Lscala/reflect/macros/Universe;
       9: invokevirtual #35                 // Method scala/reflect/macros/Universe.Liftable:()Lscala/reflect/api/Liftables$Liftable$;
      12: invokevirtual #41                 // Method scala/reflect/api/Liftables$Liftable$.liftString:()Lscala/reflect/api/Liftables$Liftable;
      15: aload_1
      16: invokeinterface #46,  2           // InterfaceMethod scala/reflect/api/Liftables$Liftable.apply:(Ljava/lang/Object;)Lscala/reflect/api/Trees$TreeApi;
      21: areturn

  public final java.lang.Object apply(java.lang.Object);
    Code:
       0: aload_0
       1: aload_1
       2: checkcast     #53                 // class java/lang/String
       5: invokevirtual #55                 // Method apply:(Ljava/lang/String;)Lscala/reflect/api/Trees$TreeApi;
       8: areturn

  public me.lyh.parquet.avro.Projection$$anonfun$applyImpl$1(scala.reflect.macros.blackbox.Context);
    Code:
       0: aload_0
       1: aload_1
       2: putfield      #23                 // Field c$1:Lscala/reflect/macros/blackbox/Context;
       5: aload_0
       6: invokespecial #62                 // Method scala/runtime/AbstractFunction1."<init>":()V
       9: return
}
