Compiled from "BinaryType.java"
public class cloud.agileframework.elasticsearch.types.BinaryType implements cloud.agileframework.elasticsearch.types.TypeHelper<java.lang.String> {
  public static final cloud.agileframework.elasticsearch.types.BinaryType INSTANCE;

  private cloud.agileframework.elasticsearch.types.BinaryType();
    Code:
       0: aload_0
       1: invokespecial #1                  // Method java/lang/Object."<init>":()V
       4: return

  public java.lang.String fromValue(java.lang.Object, java.util.Map<java.lang.String, java.lang.Object>) throws java.sql.SQLException;
    Code:
       0: aload_1
       1: ifnonnull     6
       4: aconst_null
       5: areturn
       6: aload_1
       7: invokestatic  #2                  // Method java/lang/String.valueOf:(Ljava/lang/Object;)Ljava/lang/String;
      10: areturn

  public java.lang.String getTypeName();
    Code:
       0: ldc           #3                  // String Binary
       2: areturn

  public java.lang.Object fromValue(java.lang.Object, java.util.Map) throws java.sql.SQLException;
    Code:
       0: aload_0
       1: aload_1
       2: aload_2
       3: invokevirtual #4                  // Method fromValue:(Ljava/lang/Object;Ljava/util/Map;)Ljava/lang/String;
       6: areturn

  static {};
    Code:
       0: new           #5                  // class cloud/agileframework/elasticsearch/types/BinaryType
       3: dup
       4: invokespecial #6                  // Method "<init>":()V
       7: putstatic     #7                  // Field INSTANCE:Lcloud/agileframework/elasticsearch/types/BinaryType;
      10: return
}
