Compiled from "TimestampType.java"
public class cloud.agileframework.elasticsearch.types.TimestampType implements cloud.agileframework.elasticsearch.types.TypeHelper<java.sql.Timestamp> {
  public static final cloud.agileframework.elasticsearch.types.TimestampType INSTANCE;

  private cloud.agileframework.elasticsearch.types.TimestampType();
    Code:
       0: aload_0
       1: invokespecial #1                  // Method java/lang/Object."<init>":()V
       4: return

  public java.sql.Timestamp fromValue(java.lang.Object, java.util.Map<java.lang.String, java.lang.Object>) throws java.sql.SQLException;
    Code:
       0: aload_1
       1: ifnonnull     6
       4: aconst_null
       5: areturn
       6: aload_2
       7: ifnull        24
      10: aload_2
      11: ldc           #2                  // String calendar
      13: invokeinterface #3,  2            // InterfaceMethod java/util/Map.get:(Ljava/lang/Object;)Ljava/lang/Object;
      18: checkcast     #4                  // class java/util/Calendar
      21: goto          25
      24: aconst_null
      25: astore_3
      26: aload_1
      27: instanceof    #5                  // class java/sql/Timestamp
      30: ifeq          43
      33: aload_0
      34: aload_1
      35: checkcast     #5                  // class java/sql/Timestamp
      38: aload_3
      39: invokevirtual #6                  // Method asTimestamp:(Ljava/sql/Timestamp;Ljava/util/Calendar;)Ljava/sql/Timestamp;
      42: areturn
      43: aload_1
      44: instanceof    #7                  // class java/lang/String
      47: ifeq          60
      50: aload_0
      51: aload_1
      52: checkcast     #7                  // class java/lang/String
      55: aload_3
      56: invokevirtual #8                  // Method asTimestamp:(Ljava/lang/String;Ljava/util/Calendar;)Ljava/sql/Timestamp;
      59: areturn
      60: aload_1
      61: instanceof    #9                  // class java/lang/Number
      64: ifeq          76
      67: aload_0
      68: aload_1
      69: checkcast     #9                  // class java/lang/Number
      72: invokevirtual #10                 // Method asTimestamp:(Ljava/lang/Number;)Ljava/sql/Timestamp;
      75: areturn
      76: aload_0
      77: aload_1
      78: invokevirtual #11                 // Method objectConversionException:(Ljava/lang/Object;)Ljava/sql/SQLDataException;
      81: athrow

  public java.sql.Timestamp asTimestamp(java.sql.Timestamp, java.util.Calendar) throws java.sql.SQLException;
    Code:
       0: aload_2
       1: ifnonnull     6
       4: aload_1
       5: areturn
       6: aload_0
       7: aload_1
       8: invokevirtual #12                 // Method java/sql/Timestamp.toLocalDateTime:()Ljava/time/LocalDateTime;
      11: aload_2
      12: invokespecial #13                 // Method localDateTimeToTimestamp:(Ljava/time/LocalDateTime;Ljava/util/Calendar;)Ljava/sql/Timestamp;
      15: areturn

  private java.sql.Timestamp localDateTimeToTimestamp(java.time.LocalDateTime, java.util.Calendar);
    Code:
       0: aload_2
       1: aload_1
       2: invokevirtual #14                 // Method java/time/LocalDateTime.getYear:()I
       5: aload_1
       6: invokevirtual #15                 // Method java/time/LocalDateTime.getMonthValue:()I
       9: iconst_1
      10: isub
      11: aload_1
      12: invokevirtual #16                 // Method java/time/LocalDateTime.getDayOfMonth:()I
      15: aload_1
      16: invokevirtual #17                 // Method java/time/LocalDateTime.getHour:()I
      19: aload_1
      20: invokevirtual #18                 // Method java/time/LocalDateTime.getMinute:()I
      23: aload_1
      24: invokevirtual #19                 // Method java/time/LocalDateTime.getSecond:()I
      27: invokevirtual #20                 // Method java/util/Calendar.set:(IIIIII)V
      30: aload_2
      31: bipush        14
      33: aload_1
      34: invokevirtual #21                 // Method java/time/LocalDateTime.getNano:()I
      37: ldc           #22                 // int 1000000
      39: idiv
      40: invokevirtual #23                 // Method java/util/Calendar.set:(II)V
      43: new           #5                  // class java/sql/Timestamp
      46: dup
      47: aload_2
      48: invokevirtual #24                 // Method java/util/Calendar.getTimeInMillis:()J
      51: invokespecial #25                 // Method java/sql/Timestamp."<init>":(J)V
      54: areturn

  public java.sql.Timestamp asTimestamp(java.lang.String, java.util.Calendar) throws java.sql.SQLException;
    Code:
       0: aload_1
       1: invokevirtual #26                 // Method java/lang/String.length:()I
       4: bipush        11
       6: if_icmple     29
       9: aload_1
      10: bipush        10
      12: invokevirtual #27                 // Method java/lang/String.charAt:(I)C
      15: bipush        84
      17: if_icmpne     29
      20: aload_1
      21: bipush        84
      23: bipush        32
      25: invokevirtual #28                 // Method java/lang/String.replace:(CC)Ljava/lang/String;
      28: astore_1
      29: aload_1
      30: invokevirtual #26                 // Method java/lang/String.length:()I
      33: bipush        23
      35: if_icmple     134
      38: aload_1
      39: invokevirtual #26                 // Method java/lang/String.length:()I
      42: bipush        24
      44: if_icmpne     69
      47: aload_1
      48: bipush        23
      50: invokevirtual #27                 // Method java/lang/String.charAt:(I)C
      53: bipush        90
      55: if_icmpne     69
      58: aload_1
      59: iconst_0
      60: bipush        23
      62: invokevirtual #29                 // Method java/lang/String.substring:(II)Ljava/lang/String;
      65: astore_1
      66: goto          134
      69: aload_1
      70: bipush        23
      72: invokevirtual #27                 // Method java/lang/String.charAt:(I)C
      75: bipush        43
      77: if_icmpeq     91
      80: aload_1
      81: bipush        23
      83: invokevirtual #27                 // Method java/lang/String.charAt:(I)C
      86: bipush        45
      88: if_icmpne     134
      91: aload_2
      92: ifnonnull     126
      95: new           #30                 // class java/lang/StringBuilder
      98: dup
      99: invokespecial #31                 // Method java/lang/StringBuilder."<init>":()V
     102: ldc           #32                 // String GMT
     104: invokevirtual #33                 // Method java/lang/StringBuilder.append:(Ljava/lang/String;)Ljava/lang/StringBuilder;
     107: aload_1
     108: bipush        23
     110: invokevirtual #34                 // Method java/lang/String.substring:(I)Ljava/lang/String;
     113: invokevirtual #33                 // Method java/lang/StringBuilder.append:(Ljava/lang/String;)Ljava/lang/StringBuilder;
     116: invokevirtual #35                 // Method java/lang/StringBuilder.toString:()Ljava/lang/String;
     119: invokestatic  #36                 // Method java/util/TimeZone.getTimeZone:(Ljava/lang/String;)Ljava/util/TimeZone;
     122: invokestatic  #37                 // Method java/util/Calendar.getInstance:(Ljava/util/TimeZone;)Ljava/util/Calendar;
     125: astore_2
     126: aload_1
     127: iconst_0
     128: bipush        23
     130: invokevirtual #29                 // Method java/lang/String.substring:(II)Ljava/lang/String;
     133: astore_1
     134: aload_2
     135: ifnonnull     143
     138: aload_1
     139: invokestatic  #38                 // Method java/sql/Timestamp.valueOf:(Ljava/lang/String;)Ljava/sql/Timestamp;
     142: areturn
     143: aload_1
     144: invokestatic  #38                 // Method java/sql/Timestamp.valueOf:(Ljava/lang/String;)Ljava/sql/Timestamp;
     147: astore_3
     148: aload_0
     149: aload_3
     150: invokevirtual #12                 // Method java/sql/Timestamp.toLocalDateTime:()Ljava/time/LocalDateTime;
     153: aload_2
     154: invokespecial #13                 // Method localDateTimeToTimestamp:(Ljava/time/LocalDateTime;Ljava/util/Calendar;)Ljava/sql/Timestamp;
     157: areturn
     158: astore_3
     159: aload_0
     160: aload_1
     161: aload_3
     162: invokevirtual #40                 // Method stringConversionException:(Ljava/lang/String;Ljava/lang/Throwable;)Ljava/sql/SQLDataException;
     165: athrow
    Exception table:
       from    to  target type
           0   142   158   Class java/lang/IllegalArgumentException
         143   157   158   Class java/lang/IllegalArgumentException

  public java.sql.Timestamp asTimestamp(java.lang.Number) throws java.sql.SQLException;
    Code:
       0: new           #5                  // class java/sql/Timestamp
       3: dup
       4: aload_1
       5: invokevirtual #41                 // Method java/lang/Number.longValue:()J
       8: invokespecial #25                 // Method java/sql/Timestamp."<init>":(J)V
      11: areturn

  public java.lang.String getTypeName();
    Code:
       0: ldc           #42                 // String Timestamp
       2: areturn

  public java.lang.Object fromValue(java.lang.Object, java.util.Map) throws java.sql.SQLException;
    Code:
       0: aload_0
       1: aload_1
       2: aload_2
       3: invokevirtual #43                 // Method fromValue:(Ljava/lang/Object;Ljava/util/Map;)Ljava/sql/Timestamp;
       6: areturn

  static {};
    Code:
       0: new           #44                 // class cloud/agileframework/elasticsearch/types/TimestampType
       3: dup
       4: invokespecial #45                 // Method "<init>":()V
       7: putstatic     #46                 // Field INSTANCE:Lcloud/agileframework/elasticsearch/types/TimestampType;
      10: return
}
