Compiled from "XMLCatalogIRIMapper.java"
public class org.protege.xmlcatalog.owlapi.XMLCatalogIRIMapper implements org.semanticweb.owlapi.model.OWLOntologyIRIMapper {
  private org.protege.xmlcatalog.XMLCatalog catalog;

  public org.protege.xmlcatalog.owlapi.XMLCatalogIRIMapper(java.io.File) throws java.net.MalformedURLException, java.io.IOException;
    Code:
       0: aload_0
       1: aload_1
       2: invokevirtual #1                  // Method java/io/File.toURI:()Ljava/net/URI;
       5: invokevirtual #2                  // Method java/net/URI.toURL:()Ljava/net/URL;
       8: invokestatic  #3                  // Method org/protege/xmlcatalog/CatalogUtilities.parseDocument:(Ljava/net/URL;)Lorg/protege/xmlcatalog/XMLCatalog;
      11: invokespecial #4                  // Method "<init>":(Lorg/protege/xmlcatalog/XMLCatalog;)V
      14: return

  public org.protege.xmlcatalog.owlapi.XMLCatalogIRIMapper(org.protege.xmlcatalog.XMLCatalog);
    Code:
       0: aload_0
       1: invokespecial #5                  // Method java/lang/Object."<init>":()V
       4: aload_0
       5: aload_1
       6: putfield      #6                  // Field catalog:Lorg/protege/xmlcatalog/XMLCatalog;
       9: return

  public org.semanticweb.owlapi.model.IRI getDocumentIRI(org.semanticweb.owlapi.model.IRI);
    Code:
       0: aload_1
       1: invokevirtual #7                  // Method org/semanticweb/owlapi/model/IRI.toURI:()Ljava/net/URI;
       4: aload_0
       5: getfield      #6                  // Field catalog:Lorg/protege/xmlcatalog/XMLCatalog;
       8: invokestatic  #8                  // Method org/protege/xmlcatalog/CatalogUtilities.getRedirect:(Ljava/net/URI;Lorg/protege/xmlcatalog/XMLCatalog;)Ljava/net/URI;
      11: astore_2
      12: aload_2
      13: ifnull        21
      16: aload_2
      17: invokestatic  #9                  // Method org/semanticweb/owlapi/model/IRI.create:(Ljava/net/URI;)Lorg/semanticweb/owlapi/model/IRI;
      20: areturn
      21: aconst_null
      22: areturn
}
