Compiled from "Robot.java"
public final class javafx.scene.robot.Robot {
  private final com.sun.glass.ui.GlassRobot peer;

  public javafx.scene.robot.Robot();
    Code:
       0: aload_0
       1: invokespecial #1                  // Method java/lang/Object."<init>":()V
       4: invokestatic  #2                  // Method com/sun/glass/ui/Application.checkEventThread:()V
       7: invokestatic  #3                  // Method java/lang/System.getSecurityManager:()Ljava/lang/SecurityManager;
      10: astore_1
      11: aload_1
      12: ifnull        22
      15: aload_1
      16: getstatic     #4                  // Field com/sun/javafx/FXPermissions.CREATE_ROBOT_PERMISSION:Ljavafx/util/FXPermission;
      19: invokevirtual #5                  // Method java/lang/SecurityManager.checkPermission:(Ljava/security/Permission;)V
      22: aload_0
      23: invokestatic  #6                  // Method com/sun/javafx/tk/Toolkit.getToolkit:()Lcom/sun/javafx/tk/Toolkit;
      26: invokevirtual #7                  // Method com/sun/javafx/tk/Toolkit.createRobot:()Lcom/sun/glass/ui/GlassRobot;
      29: putfield      #8                  // Field peer:Lcom/sun/glass/ui/GlassRobot;
      32: aload_0
      33: getfield      #8                  // Field peer:Lcom/sun/glass/ui/GlassRobot;
      36: invokevirtual #9                  // Method com/sun/glass/ui/GlassRobot.create:()V
      39: return

  public void keyPress(javafx.scene.input.KeyCode);
    Code:
       0: aload_1
       1: ldc           #10                 // String keyCode must not be null
       3: invokestatic  #11                 // Method java/util/Objects.requireNonNull:(Ljava/lang/Object;Ljava/lang/String;)Ljava/lang/Object;
       6: pop
       7: aload_0
       8: getfield      #8                  // Field peer:Lcom/sun/glass/ui/GlassRobot;
      11: aload_1
      12: invokevirtual #12                 // Method com/sun/glass/ui/GlassRobot.keyPress:(Ljavafx/scene/input/KeyCode;)V
      15: return

  public void keyRelease(javafx.scene.input.KeyCode);
    Code:
       0: aload_1
       1: ldc           #10                 // String keyCode must not be null
       3: invokestatic  #11                 // Method java/util/Objects.requireNonNull:(Ljava/lang/Object;Ljava/lang/String;)Ljava/lang/Object;
       6: pop
       7: aload_0
       8: getfield      #8                  // Field peer:Lcom/sun/glass/ui/GlassRobot;
      11: aload_1
      12: invokevirtual #13                 // Method com/sun/glass/ui/GlassRobot.keyRelease:(Ljavafx/scene/input/KeyCode;)V
      15: return

  public void keyType(javafx.scene.input.KeyCode);
    Code:
       0: aload_1
       1: ldc           #10                 // String keyCode must not be null
       3: invokestatic  #11                 // Method java/util/Objects.requireNonNull:(Ljava/lang/Object;Ljava/lang/String;)Ljava/lang/Object;
       6: pop
       7: aload_0
       8: aload_1
       9: invokevirtual #14                 // Method keyPress:(Ljavafx/scene/input/KeyCode;)V
      12: aload_0
      13: aload_1
      14: invokevirtual #15                 // Method keyRelease:(Ljavafx/scene/input/KeyCode;)V
      17: return

  public double getMouseX();
    Code:
       0: aload_0
       1: getfield      #8                  // Field peer:Lcom/sun/glass/ui/GlassRobot;
       4: invokevirtual #16                 // Method com/sun/glass/ui/GlassRobot.getMouseX:()D
       7: dreturn

  public double getMouseY();
    Code:
       0: aload_0
       1: getfield      #8                  // Field peer:Lcom/sun/glass/ui/GlassRobot;
       4: invokevirtual #17                 // Method com/sun/glass/ui/GlassRobot.getMouseY:()D
       7: dreturn

  public javafx.geometry.Point2D getMousePosition();
    Code:
       0: new           #18                 // class javafx/geometry/Point2D
       3: dup
       4: aload_0
       5: invokevirtual #19                 // Method getMouseX:()D
       8: aload_0
       9: invokevirtual #20                 // Method getMouseY:()D
      12: invokespecial #21                 // Method javafx/geometry/Point2D."<init>":(DD)V
      15: areturn

  public void mouseMove(double, double);
    Code:
       0: aload_0
       1: getfield      #8                  // Field peer:Lcom/sun/glass/ui/GlassRobot;
       4: dload_1
       5: dload_3
       6: invokevirtual #22                 // Method com/sun/glass/ui/GlassRobot.mouseMove:(DD)V
       9: return

  public final void mouseMove(javafx.geometry.Point2D);
    Code:
       0: aload_1
       1: invokestatic  #23                 // Method java/util/Objects.requireNonNull:(Ljava/lang/Object;)Ljava/lang/Object;
       4: pop
       5: aload_0
       6: aload_1
       7: invokevirtual #24                 // Method javafx/geometry/Point2D.getX:()D
      10: aload_1
      11: invokevirtual #25                 // Method javafx/geometry/Point2D.getY:()D
      14: invokevirtual #26                 // Method mouseMove:(DD)V
      17: return

  public void mousePress(javafx.scene.input.MouseButton...);
    Code:
       0: aload_1
       1: ldc           #27                 // String buttons must not be null
       3: invokestatic  #11                 // Method java/util/Objects.requireNonNull:(Ljava/lang/Object;Ljava/lang/String;)Ljava/lang/Object;
       6: pop
       7: aload_0
       8: getfield      #8                  // Field peer:Lcom/sun/glass/ui/GlassRobot;
      11: aload_1
      12: invokevirtual #28                 // Method com/sun/glass/ui/GlassRobot.mousePress:([Ljavafx/scene/input/MouseButton;)V
      15: return

  public void mouseRelease(javafx.scene.input.MouseButton...);
    Code:
       0: aload_1
       1: ldc           #27                 // String buttons must not be null
       3: invokestatic  #11                 // Method java/util/Objects.requireNonNull:(Ljava/lang/Object;Ljava/lang/String;)Ljava/lang/Object;
       6: pop
       7: aload_0
       8: getfield      #8                  // Field peer:Lcom/sun/glass/ui/GlassRobot;
      11: aload_1
      12: invokevirtual #29                 // Method com/sun/glass/ui/GlassRobot.mouseRelease:([Ljavafx/scene/input/MouseButton;)V
      15: return

  public void mouseClick(javafx.scene.input.MouseButton...);
    Code:
       0: aload_1
       1: ldc           #27                 // String buttons must not be null
       3: invokestatic  #11                 // Method java/util/Objects.requireNonNull:(Ljava/lang/Object;Ljava/lang/String;)Ljava/lang/Object;
       6: pop
       7: aload_0
       8: aload_1
       9: invokevirtual #30                 // Method mousePress:([Ljavafx/scene/input/MouseButton;)V
      12: aload_0
      13: aload_1
      14: invokevirtual #31                 // Method mouseRelease:([Ljavafx/scene/input/MouseButton;)V
      17: return

  public void mouseWheel(int);
    Code:
       0: aload_0
       1: getfield      #8                  // Field peer:Lcom/sun/glass/ui/GlassRobot;
       4: iload_1
       5: invokevirtual #32                 // Method com/sun/glass/ui/GlassRobot.mouseWheel:(I)V
       8: return

  public javafx.scene.paint.Color getPixelColor(double, double);
    Code:
       0: aload_0
       1: getfield      #8                  // Field peer:Lcom/sun/glass/ui/GlassRobot;
       4: dload_1
       5: dload_3
       6: invokevirtual #33                 // Method com/sun/glass/ui/GlassRobot.getPixelColor:(DD)Ljavafx/scene/paint/Color;
       9: areturn

  public javafx.scene.paint.Color getPixelColor(javafx.geometry.Point2D);
    Code:
       0: aload_0
       1: aload_1
       2: invokevirtual #24                 // Method javafx/geometry/Point2D.getX:()D
       5: aload_1
       6: invokevirtual #25                 // Method javafx/geometry/Point2D.getY:()D
       9: invokevirtual #34                 // Method getPixelColor:(DD)Ljavafx/scene/paint/Color;
      12: areturn

  public javafx.scene.image.WritableImage getScreenCapture(javafx.scene.image.WritableImage, double, double, double, double, boolean);
    Code:
       0: aload_0
       1: getfield      #8                  // Field peer:Lcom/sun/glass/ui/GlassRobot;
       4: aload_1
       5: dload_2
       6: dload         4
       8: dload         6
      10: dload         8
      12: iload         10
      14: invokevirtual #35                 // Method com/sun/glass/ui/GlassRobot.getScreenCapture:(Ljavafx/scene/image/WritableImage;DDDDZ)Ljavafx/scene/image/WritableImage;
      17: areturn

  public javafx.scene.image.WritableImage getScreenCapture(javafx.scene.image.WritableImage, double, double, double, double);
    Code:
       0: aload_0
       1: aload_1
       2: dload_2
       3: dload         4
       5: dload         6
       7: dload         8
       9: iconst_1
      10: invokevirtual #36                 // Method getScreenCapture:(Ljavafx/scene/image/WritableImage;DDDDZ)Ljavafx/scene/image/WritableImage;
      13: areturn

  public javafx.scene.image.WritableImage getScreenCapture(javafx.scene.image.WritableImage, javafx.geometry.Rectangle2D);
    Code:
       0: aload_2
       1: invokestatic  #23                 // Method java/util/Objects.requireNonNull:(Ljava/lang/Object;)Ljava/lang/Object;
       4: pop
       5: aload_0
       6: aload_1
       7: aload_2
       8: invokevirtual #37                 // Method javafx/geometry/Rectangle2D.getMinX:()D
      11: aload_2
      12: invokevirtual #38                 // Method javafx/geometry/Rectangle2D.getMinY:()D
      15: aload_2
      16: invokevirtual #39                 // Method javafx/geometry/Rectangle2D.getWidth:()D
      19: aload_2
      20: invokevirtual #40                 // Method javafx/geometry/Rectangle2D.getHeight:()D
      23: iconst_1
      24: invokevirtual #36                 // Method getScreenCapture:(Ljavafx/scene/image/WritableImage;DDDDZ)Ljavafx/scene/image/WritableImage;
      27: areturn

  public javafx.scene.image.WritableImage getScreenCapture(javafx.scene.image.WritableImage, javafx.geometry.Rectangle2D, boolean);
    Code:
       0: aload_2
       1: invokestatic  #23                 // Method java/util/Objects.requireNonNull:(Ljava/lang/Object;)Ljava/lang/Object;
       4: pop
       5: aload_0
       6: aload_1
       7: aload_2
       8: invokevirtual #37                 // Method javafx/geometry/Rectangle2D.getMinX:()D
      11: aload_2
      12: invokevirtual #38                 // Method javafx/geometry/Rectangle2D.getMinY:()D
      15: aload_2
      16: invokevirtual #39                 // Method javafx/geometry/Rectangle2D.getWidth:()D
      19: aload_2
      20: invokevirtual #40                 // Method javafx/geometry/Rectangle2D.getHeight:()D
      23: iload_3
      24: invokevirtual #36                 // Method getScreenCapture:(Ljavafx/scene/image/WritableImage;DDDDZ)Ljavafx/scene/image/WritableImage;
      27: areturn
}
