Compiled from "AggregationStrategyClause.java"
public class org.apache.camel.builder.AggregationStrategyClause<T> implements org.apache.camel.processor.aggregate.AggregationStrategy {
  private final T parent;

  private org.apache.camel.processor.aggregate.AggregationStrategy strategy;

  public org.apache.camel.builder.AggregationStrategyClause(T);
    Code:
       0: aload_0
       1: invokespecial #23                 // Method java/lang/Object."<init>":()V
       4: aload_0
       5: aload_1
       6: putfield      #25                 // Field parent:Ljava/lang/Object;
       9: aload_0
      10: aconst_null
      11: putfield      #27                 // Field strategy:Lorg/apache/camel/processor/aggregate/AggregationStrategy;
      14: return

  public org.apache.camel.Exchange aggregate(org.apache.camel.Exchange, org.apache.camel.Exchange);
    Code:
       0: aload_0
       1: getfield      #27                 // Field strategy:Lorg/apache/camel/processor/aggregate/AggregationStrategy;
       4: ldc           #34                 // String AggregationStrategy
       6: invokestatic  #40                 // Method org/apache/camel/util/ObjectHelper.notNull:(Ljava/lang/Object;Ljava/lang/String;)Ljava/lang/Object;
       9: checkcast     #7                  // class org/apache/camel/processor/aggregate/AggregationStrategy
      12: aload_1
      13: aload_2
      14: invokeinterface #42,  3           // InterfaceMethod org/apache/camel/processor/aggregate/AggregationStrategy.aggregate:(Lorg/apache/camel/Exchange;Lorg/apache/camel/Exchange;)Lorg/apache/camel/Exchange;
      19: areturn

  public T exchange(java.util.function.BiFunction<org.apache.camel.Exchange, org.apache.camel.Exchange, org.apache.camel.Exchange>);
    Code:
       0: aload_0
       1: aload_1
       2: dup
       3: invokevirtual #51                 // Method java/lang/Object.getClass:()Ljava/lang/Class;
       6: pop
       7: invokedynamic #69,  0             // InvokeDynamic #0:aggregate:(Ljava/util/function/BiFunction;)Lorg/apache/camel/processor/aggregate/AggregationStrategy;
      12: putfield      #27                 // Field strategy:Lorg/apache/camel/processor/aggregate/AggregationStrategy;
      15: aload_0
      16: getfield      #25                 // Field parent:Ljava/lang/Object;
      19: areturn

  public T message(java.util.function.BiFunction<org.apache.camel.Message, org.apache.camel.Message, org.apache.camel.Message>);
    Code:
       0: aload_0
       1: aload_1
       2: invokedynamic #82,  0             // InvokeDynamic #1:apply:(Ljava/util/function/BiFunction;)Ljava/util/function/BiFunction;
       7: invokevirtual #84                 // Method exchange:(Ljava/util/function/BiFunction;)Ljava/lang/Object;
      10: areturn

  public T body(java.util.function.BiFunction<java.lang.Object, java.lang.Object, java.lang.Object>);
    Code:
       0: aload_0
       1: ldc           #5                  // class java/lang/Object
       3: aload_1
       4: invokevirtual #89                 // Method body:(Ljava/lang/Class;Ljava/util/function/BiFunction;)Ljava/lang/Object;
       7: areturn

  public <B> T body(java.lang.Class<B>, java.util.function.BiFunction<B, B, java.lang.Object>);
    Code:
       0: aload_0
       1: aload_1
       2: aload_1
       3: aload_2
       4: invokevirtual #93                 // Method body:(Ljava/lang/Class;Ljava/lang/Class;Ljava/util/function/BiFunction;)Ljava/lang/Object;
       7: areturn

  public <O, N> T body(java.lang.Class<O>, java.lang.Class<N>, java.util.function.BiFunction<O, N, java.lang.Object>);
    Code:
       0: aload_0
       1: aload_3
       2: aload_1
       3: aload_2
       4: invokedynamic #105,  0            // InvokeDynamic #2:apply:(Ljava/util/function/BiFunction;Ljava/lang/Class;Ljava/lang/Class;)Ljava/util/function/BiFunction;
       9: invokevirtual #84                 // Method exchange:(Ljava/util/function/BiFunction;)Ljava/lang/Object;
      12: areturn

  private static org.apache.camel.Exchange lambda$body$6(java.util.function.BiFunction, java.lang.Class, java.lang.Class, org.apache.camel.Exchange, org.apache.camel.Exchange);
    Code:
       0: aload_3
       1: ifnull        13
       4: aload_3
       5: invokeinterface #116,  1          // InterfaceMethod org/apache/camel/Exchange.getIn:()Lorg/apache/camel/Message;
      10: goto          14
      13: aconst_null
      14: astore        5
      16: aload         4
      18: ldc           #120                // String NewExchange
      20: invokestatic  #40                 // Method org/apache/camel/util/ObjectHelper.notNull:(Ljava/lang/Object;Ljava/lang/String;)Ljava/lang/Object;
      23: checkcast     #112                // class org/apache/camel/Exchange
      26: invokeinterface #116,  1          // InterfaceMethod org/apache/camel/Exchange.getIn:()Lorg/apache/camel/Message;
      31: astore        6
      33: aload_0
      34: aload         5
      36: ifnull        50
      39: aload         5
      41: aload_1
      42: invokeinterface #124,  2          // InterfaceMethod org/apache/camel/Message.getBody:(Ljava/lang/Class;)Ljava/lang/Object;
      47: goto          51
      50: aconst_null
      51: aload         6
      53: ifnull        67
      56: aload         6
      58: aload_2
      59: invokeinterface #124,  2          // InterfaceMethod org/apache/camel/Message.getBody:(Ljava/lang/Class;)Ljava/lang/Object;
      64: goto          68
      67: aconst_null
      68: invokeinterface #65,  3           // InterfaceMethod java/util/function/BiFunction.apply:(Ljava/lang/Object;Ljava/lang/Object;)Ljava/lang/Object;
      73: astore        7
      75: aload_3
      76: ifnull        94
      79: aload_3
      80: invokeinterface #116,  1          // InterfaceMethod org/apache/camel/Exchange.getIn:()Lorg/apache/camel/Message;
      85: aload         7
      87: invokeinterface #129,  2          // InterfaceMethod org/apache/camel/Message.setBody:(Ljava/lang/Object;)V
      92: aload_3
      93: areturn
      94: aload         4
      96: invokeinterface #116,  1          // InterfaceMethod org/apache/camel/Exchange.getIn:()Lorg/apache/camel/Message;
     101: aload         7
     103: invokeinterface #129,  2          // InterfaceMethod org/apache/camel/Message.setBody:(Ljava/lang/Object;)V
     108: aload         4
     110: areturn

  private static org.apache.camel.Exchange lambda$message$5(java.util.function.BiFunction, org.apache.camel.Exchange, org.apache.camel.Exchange);
    Code:
       0: aload_1
       1: ifnull        13
       4: aload_1
       5: invokeinterface #116,  1          // InterfaceMethod org/apache/camel/Exchange.getIn:()Lorg/apache/camel/Message;
      10: goto          14
      13: aconst_null
      14: astore_3
      15: aload_2
      16: ldc           #120                // String NewExchange
      18: invokestatic  #40                 // Method org/apache/camel/util/ObjectHelper.notNull:(Ljava/lang/Object;Ljava/lang/String;)Ljava/lang/Object;
      21: checkcast     #112                // class org/apache/camel/Exchange
      24: invokeinterface #116,  1          // InterfaceMethod org/apache/camel/Exchange.getIn:()Lorg/apache/camel/Message;
      29: astore        4
      31: aload_0
      32: aload_3
      33: aload         4
      35: invokeinterface #65,  3           // InterfaceMethod java/util/function/BiFunction.apply:(Ljava/lang/Object;Ljava/lang/Object;)Ljava/lang/Object;
      40: checkcast     #118                // class org/apache/camel/Message
      43: astore        5
      45: aload_1
      46: ifnull        59
      49: aload_1
      50: aload         5
      52: invokeinterface #137,  2          // InterfaceMethod org/apache/camel/Exchange.setIn:(Lorg/apache/camel/Message;)V
      57: aload_1
      58: areturn
      59: aload_2
      60: aload         5
      62: invokeinterface #137,  2          // InterfaceMethod org/apache/camel/Exchange.setIn:(Lorg/apache/camel/Message;)V
      67: aload_2
      68: areturn
}
