Compiled from "StoppedSessionException.java"
public class org.apache.shiro.session.StoppedSessionException extends org.apache.shiro.session.InvalidSessionException {
  public org.apache.shiro.session.StoppedSessionException();
    Code:
       0: aload_0
       1: invokespecial #1                  // Method org/apache/shiro/session/InvalidSessionException."<init>":()V
       4: return

  public org.apache.shiro.session.StoppedSessionException(java.lang.String);
    Code:
       0: aload_0
       1: aload_1
       2: invokespecial #2                  // Method org/apache/shiro/session/InvalidSessionException."<init>":(Ljava/lang/String;)V
       5: return

  public org.apache.shiro.session.StoppedSessionException(java.lang.Throwable);
    Code:
       0: aload_0
       1: aload_1
       2: invokespecial #3                  // Method org/apache/shiro/session/InvalidSessionException."<init>":(Ljava/lang/Throwable;)V
       5: return

  public org.apache.shiro.session.StoppedSessionException(java.lang.String, java.lang.Throwable);
    Code:
       0: aload_0
       1: aload_1
       2: aload_2
       3: invokespecial #4                  // Method org/apache/shiro/session/InvalidSessionException."<init>":(Ljava/lang/String;Ljava/lang/Throwable;)V
       6: return
}
