Compiled from "MMCodeImpl.java"
public class org.mobicents.protocols.ss7.map.service.mobility.subscriberManagement.MMCodeImpl extends org.mobicents.protocols.ss7.map.primitives.OctetStringLength1Base implements org.mobicents.protocols.ss7.map.api.service.mobility.subscriberManagement.MMCode {
  public org.mobicents.protocols.ss7.map.service.mobility.subscriberManagement.MMCodeImpl();
    Code:
       0: aload_0
       1: ldc           #1                  // String MMCode
       3: invokespecial #2                  // Method org/mobicents/protocols/ss7/map/primitives/OctetStringLength1Base."<init>":(Ljava/lang/String;)V
       6: return

  public org.mobicents.protocols.ss7.map.service.mobility.subscriberManagement.MMCodeImpl(org.mobicents.protocols.ss7.map.api.service.mobility.subscriberManagement.MMCodeValue);
    Code:
       0: aload_0
       1: ldc           #1                  // String MMCode
       3: aload_1
       4: ifnull        14
       7: aload_1
       8: invokevirtual #3                  // Method org/mobicents/protocols/ss7/map/api/service/mobility/subscriberManagement/MMCodeValue.getCode:()I
      11: goto          15
      14: iconst_0
      15: invokespecial #4                  // Method org/mobicents/protocols/ss7/map/primitives/OctetStringLength1Base."<init>":(Ljava/lang/String;I)V
      18: return

  public org.mobicents.protocols.ss7.map.api.service.mobility.subscriberManagement.MMCodeValue getMMCodeValue();
    Code:
       0: aload_0
       1: getfield      #5                  // Field data:I
       4: sipush        255
       7: iand
       8: invokestatic  #6                  // Method org/mobicents/protocols/ss7/map/api/service/mobility/subscriberManagement/MMCodeValue.getInstance:(I)Lorg/mobicents/protocols/ss7/map/api/service/mobility/subscriberManagement/MMCodeValue;
      11: areturn
}
