Compiled from "ConsistentHashing.scala"
public final class akka.routing.ConsistentHashingRouter$ {
  public static final akka.routing.ConsistentHashingRouter$ MODULE$;

  public static {};
    Code:
       0: new           #2                  // class akka/routing/ConsistentHashingRouter$
       3: invokespecial #12                 // Method "<init>":()V
       6: return

  public scala.PartialFunction<java.lang.Object, java.lang.Object> hashMappingAdapter(akka.routing.ConsistentHashingRouter$ConsistentHashMapper);
    Code:
       0: new           #16                 // class akka/routing/ConsistentHashingRouter$$anonfun$hashMappingAdapter$1
       3: dup
       4: aload_1
       5: invokespecial #19                 // Method akka/routing/ConsistentHashingRouter$$anonfun$hashMappingAdapter$1."<init>":(Lakka/routing/ConsistentHashingRouter$ConsistentHashMapper;)V
       8: areturn

  private akka.routing.ConsistentHashingRouter$();
    Code:
       0: aload_0
       1: invokespecial #23                 // Method java/lang/Object."<init>":()V
       4: aload_0
       5: putstatic     #25                 // Field MODULE$:Lakka/routing/ConsistentHashingRouter$;
       8: return
}
