Compiled from "MurmurHash.scala"
public final class akka.routing.MurmurHash$ {
  public static final akka.routing.MurmurHash$ MODULE$;

  private final int visibleMagic;

  private final int akka$routing$MurmurHash$$hiddenMagicA;

  private final int akka$routing$MurmurHash$$hiddenMagicB;

  private final int visibleMixer;

  private final int hiddenMixerA;

  private final int hiddenMixerB;

  private final int finalMixer1;

  private final int finalMixer2;

  private final int seedString;

  private final int akka$routing$MurmurHash$$seedArray;

  private final int[] storedMagicA;

  private final int[] storedMagicB;

  public static {};
    Code:
       0: new           #2                  // class akka/routing/MurmurHash$
       3: invokespecial #12                 // Method "<init>":()V
       6: return

  private final int visibleMagic();
    Code:
       0: aload_0
       1: getfield      #29                 // Field visibleMagic:I
       4: ireturn

  public final int akka$routing$MurmurHash$$hiddenMagicA();
    Code:
       0: aload_0
       1: getfield      #32                 // Field akka$routing$MurmurHash$$hiddenMagicA:I
       4: ireturn

  public final int akka$routing$MurmurHash$$hiddenMagicB();
    Code:
       0: aload_0
       1: getfield      #34                 // Field akka$routing$MurmurHash$$hiddenMagicB:I
       4: ireturn

  private final int visibleMixer();
    Code:
       0: aload_0
       1: getfield      #36                 // Field visibleMixer:I
       4: ireturn

  private final int hiddenMixerA();
    Code:
       0: aload_0
       1: getfield      #38                 // Field hiddenMixerA:I
       4: ireturn

  private final int hiddenMixerB();
    Code:
       0: aload_0
       1: getfield      #40                 // Field hiddenMixerB:I
       4: ireturn

  private final int finalMixer1();
    Code:
       0: aload_0
       1: getfield      #42                 // Field finalMixer1:I
       4: ireturn

  private final int finalMixer2();
    Code:
       0: aload_0
       1: getfield      #44                 // Field finalMixer2:I
       4: ireturn

  private final int seedString();
    Code:
       0: aload_0
       1: getfield      #46                 // Field seedString:I
       4: ireturn

  public final int akka$routing$MurmurHash$$seedArray();
    Code:
       0: aload_0
       1: getfield      #48                 // Field akka$routing$MurmurHash$$seedArray:I
       4: ireturn

  private int[] storedMagicA();
    Code:
       0: aload_0
       1: getfield      #51                 // Field storedMagicA:[I
       4: areturn

  private int[] storedMagicB();
    Code:
       0: aload_0
       1: getfield      #53                 // Field storedMagicB:[I
       4: areturn

  public int startHash(int);
    Code:
       0: iload_1
       1: aload_0
       2: invokespecial #57                 // Method visibleMagic:()I
       5: ixor
       6: ireturn

  public int startMagicA();
    Code:
       0: aload_0
       1: invokevirtual #61                 // Method akka$routing$MurmurHash$$hiddenMagicA:()I
       4: ireturn

  public int startMagicB();
    Code:
       0: aload_0
       1: invokevirtual #64                 // Method akka$routing$MurmurHash$$hiddenMagicB:()I
       4: ireturn

  public int extendHash(int, int, int, int);
    Code:
       0: iload_1
       1: iload_2
       2: iload_3
       3: imul
       4: bipush        11
       6: invokestatic  #72                 // Method java/lang/Integer.rotateLeft:(II)I
       9: iload         4
      11: imul
      12: ixor
      13: iconst_3
      14: imul
      15: aload_0
      16: invokespecial #74                 // Method visibleMixer:()I
      19: iadd
      20: ireturn

  public int nextMagicA(int);
    Code:
       0: iload_1
       1: iconst_5
       2: imul
       3: aload_0
       4: invokespecial #81                 // Method hiddenMixerA:()I
       7: iadd
       8: ireturn

  public int nextMagicB(int);
    Code:
       0: iload_1
       1: iconst_5
       2: imul
       3: aload_0
       4: invokespecial #84                 // Method hiddenMixerB:()I
       7: iadd
       8: ireturn

  public int finalizeHash(int);
    Code:
       0: iload_1
       1: iload_1
       2: bipush        16
       4: iushr
       5: ixor
       6: istore_2
       7: iload_2
       8: aload_0
       9: invokespecial #87                 // Method finalMixer1:()I
      12: imul
      13: istore_2
      14: iload_2
      15: iload_2
      16: bipush        13
      18: iushr
      19: ixor
      20: istore_2
      21: iload_2
      22: aload_0
      23: invokespecial #89                 // Method finalMixer2:()I
      26: imul
      27: istore_2
      28: iload_2
      29: iload_2
      30: bipush        16
      32: iushr
      33: ixor
      34: istore_2
      35: iload_2
      36: ireturn

  public <T> int arrayHash(java.lang.Object);
    Code:
       0: aload_0
       1: getstatic     #97                 // Field scala/runtime/ScalaRunTime$.MODULE$:Lscala/runtime/ScalaRunTime$;
       4: aload_1
       5: invokevirtual #100                // Method scala/runtime/ScalaRunTime$.array_length:(Ljava/lang/Object;)I
       8: aload_0
       9: invokevirtual #102                // Method akka$routing$MurmurHash$$seedArray:()I
      12: imul
      13: invokevirtual #104                // Method startHash:(I)I
      16: istore_2
      17: aload_0
      18: invokevirtual #61                 // Method akka$routing$MurmurHash$$hiddenMagicA:()I
      21: istore_3
      22: aload_0
      23: invokevirtual #64                 // Method akka$routing$MurmurHash$$hiddenMagicB:()I
      26: istore        4
      28: iconst_0
      29: istore        5
      31: iload         5
      33: getstatic     #97                 // Field scala/runtime/ScalaRunTime$.MODULE$:Lscala/runtime/ScalaRunTime$;
      36: aload_1
      37: invokevirtual #100                // Method scala/runtime/ScalaRunTime$.array_length:(Ljava/lang/Object;)I
      40: if_icmpge     90
      43: aload_0
      44: iload_2
      45: getstatic     #97                 // Field scala/runtime/ScalaRunTime$.MODULE$:Lscala/runtime/ScalaRunTime$;
      48: getstatic     #97                 // Field scala/runtime/ScalaRunTime$.MODULE$:Lscala/runtime/ScalaRunTime$;
      51: aload_1
      52: iload         5
      54: invokevirtual #108                // Method scala/runtime/ScalaRunTime$.array_apply:(Ljava/lang/Object;I)Ljava/lang/Object;
      57: invokevirtual #110                // Method scala/runtime/ScalaRunTime$.hash:(Ljava/lang/Object;)I
      60: iload_3
      61: iload         4
      63: invokevirtual #112                // Method extendHash:(IIII)I
      66: istore_2
      67: aload_0
      68: iload_3
      69: invokevirtual #114                // Method nextMagicA:(I)I
      72: istore_3
      73: aload_0
      74: iload         4
      76: invokevirtual #116                // Method nextMagicB:(I)I
      79: istore        4
      81: iload         5
      83: iconst_1
      84: iadd
      85: istore        5
      87: goto          31
      90: aload_0
      91: iload_2
      92: invokevirtual #118                // Method finalizeHash:(I)I
      95: ireturn

  public int stringHash(java.lang.String);
    Code:
       0: aload_0
       1: aload_1
       2: invokevirtual #131                // Method java/lang/String.length:()I
       5: aload_0
       6: invokespecial #133                // Method seedString:()I
       9: imul
      10: invokevirtual #104                // Method startHash:(I)I
      13: istore_2
      14: aload_0
      15: invokevirtual #61                 // Method akka$routing$MurmurHash$$hiddenMagicA:()I
      18: istore_3
      19: aload_0
      20: invokevirtual #64                 // Method akka$routing$MurmurHash$$hiddenMagicB:()I
      23: istore        4
      25: iconst_0
      26: istore        5
      28: iload         5
      30: iconst_1
      31: iadd
      32: aload_1
      33: invokevirtual #131                // Method java/lang/String.length:()I
      36: if_icmpge     93
      39: aload_1
      40: iload         5
      42: invokevirtual #137                // Method java/lang/String.charAt:(I)C
      45: bipush        16
      47: ishl
      48: aload_1
      49: iload         5
      51: iconst_1
      52: iadd
      53: invokevirtual #137                // Method java/lang/String.charAt:(I)C
      56: iadd
      57: istore        6
      59: aload_0
      60: iload_2
      61: iload         6
      63: iload_3
      64: iload         4
      66: invokevirtual #112                // Method extendHash:(IIII)I
      69: istore_2
      70: aload_0
      71: iload_3
      72: invokevirtual #114                // Method nextMagicA:(I)I
      75: istore_3
      76: aload_0
      77: iload         4
      79: invokevirtual #116                // Method nextMagicB:(I)I
      82: istore        4
      84: iload         5
      86: iconst_2
      87: iadd
      88: istore        5
      90: goto          28
      93: iload         5
      95: aload_1
      96: invokevirtual #131                // Method java/lang/String.length:()I
      99: if_icmpge     117
     102: aload_0
     103: iload_2
     104: aload_1
     105: iload         5
     107: invokevirtual #137                // Method java/lang/String.charAt:(I)C
     110: iload_3
     111: iload         4
     113: invokevirtual #112                // Method extendHash:(IIII)I
     116: istore_2
     117: aload_0
     118: iload_2
     119: invokevirtual #118                // Method finalizeHash:(I)I
     122: ireturn

  public <T> int symmetricHash(scala.collection.TraversableOnce<T>, int);
    Code:
       0: iconst_0
       1: invokestatic  #147                // Method scala/runtime/IntRef.create:(I)Lscala/runtime/IntRef;
       4: astore_3
       5: iconst_0
       6: invokestatic  #147                // Method scala/runtime/IntRef.create:(I)Lscala/runtime/IntRef;
       9: astore        4
      11: iconst_0
      12: invokestatic  #147                // Method scala/runtime/IntRef.create:(I)Lscala/runtime/IntRef;
      15: astore        5
      17: iconst_1
      18: invokestatic  #147                // Method scala/runtime/IntRef.create:(I)Lscala/runtime/IntRef;
      21: astore        6
      23: aload_1
      24: new           #149                // class akka/routing/MurmurHash$$anonfun$symmetricHash$1
      27: dup
      28: aload_3
      29: aload         4
      31: aload         5
      33: aload         6
      35: invokespecial #152                // Method akka/routing/MurmurHash$$anonfun$symmetricHash$1."<init>":(Lscala/runtime/IntRef;Lscala/runtime/IntRef;Lscala/runtime/IntRef;Lscala/runtime/IntRef;)V
      38: invokeinterface #158,  2          // InterfaceMethod scala/collection/TraversableOnce.foreach:(Lscala/Function1;)V
      43: aload_0
      44: iload_2
      45: aload         5
      47: getfield      #161                // Field scala/runtime/IntRef.elem:I
      50: imul
      51: invokevirtual #104                // Method startHash:(I)I
      54: istore        7
      56: aload_0
      57: iload         7
      59: aload_3
      60: getfield      #161                // Field scala/runtime/IntRef.elem:I
      63: aload_0
      64: invokespecial #163                // Method storedMagicA:()[I
      67: iconst_0
      68: iaload
      69: aload_0
      70: invokespecial #165                // Method storedMagicB:()[I
      73: iconst_0
      74: iaload
      75: invokevirtual #112                // Method extendHash:(IIII)I
      78: istore        7
      80: aload_0
      81: iload         7
      83: aload         4
      85: getfield      #161                // Field scala/runtime/IntRef.elem:I
      88: aload_0
      89: invokespecial #163                // Method storedMagicA:()[I
      92: iconst_1
      93: iaload
      94: aload_0
      95: invokespecial #165                // Method storedMagicB:()[I
      98: iconst_1
      99: iaload
     100: invokevirtual #112                // Method extendHash:(IIII)I
     103: istore        7
     105: aload_0
     106: iload         7
     108: aload         6
     110: getfield      #161                // Field scala/runtime/IntRef.elem:I
     113: aload_0
     114: invokespecial #163                // Method storedMagicA:()[I
     117: iconst_2
     118: iaload
     119: aload_0
     120: invokespecial #165                // Method storedMagicB:()[I
     123: iconst_2
     124: iaload
     125: invokevirtual #112                // Method extendHash:(IIII)I
     128: istore        7
     130: aload_0
     131: iload         7
     133: invokevirtual #118                // Method finalizeHash:(I)I
     136: ireturn

  public int arrayHash$mZc$sp(boolean[]);
    Code:
       0: aload_0
       1: aload_1
       2: arraylength
       3: aload_0
       4: invokevirtual #102                // Method akka$routing$MurmurHash$$seedArray:()I
       7: imul
       8: invokevirtual #104                // Method startHash:(I)I
      11: istore_2
      12: aload_0
      13: invokevirtual #61                 // Method akka$routing$MurmurHash$$hiddenMagicA:()I
      16: istore_3
      17: aload_0
      18: invokevirtual #64                 // Method akka$routing$MurmurHash$$hiddenMagicB:()I
      21: istore        4
      23: iconst_0
      24: istore        5
      26: iload         5
      28: aload_1
      29: arraylength
      30: if_icmpge     81
      33: aload_0
      34: iload_2
      35: aload_1
      36: iload         5
      38: baload
      39: ifeq          48
      42: sipush        1231
      45: goto          51
      48: sipush        1237
      51: iload_3
      52: iload         4
      54: invokevirtual #112                // Method extendHash:(IIII)I
      57: istore_2
      58: aload_0
      59: iload_3
      60: invokevirtual #114                // Method nextMagicA:(I)I
      63: istore_3
      64: aload_0
      65: iload         4
      67: invokevirtual #116                // Method nextMagicB:(I)I
      70: istore        4
      72: iload         5
      74: iconst_1
      75: iadd
      76: istore        5
      78: goto          26
      81: aload_0
      82: iload_2
      83: invokevirtual #118                // Method finalizeHash:(I)I
      86: ireturn

  public int arrayHash$mBc$sp(byte[]);
    Code:
       0: aload_0
       1: aload_1
       2: arraylength
       3: aload_0
       4: invokevirtual #102                // Method akka$routing$MurmurHash$$seedArray:()I
       7: imul
       8: invokevirtual #104                // Method startHash:(I)I
      11: istore_2
      12: aload_0
      13: invokevirtual #61                 // Method akka$routing$MurmurHash$$hiddenMagicA:()I
      16: istore_3
      17: aload_0
      18: invokevirtual #64                 // Method akka$routing$MurmurHash$$hiddenMagicB:()I
      21: istore        4
      23: iconst_0
      24: istore        5
      26: iload         5
      28: aload_1
      29: arraylength
      30: if_icmpge     69
      33: aload_0
      34: iload_2
      35: aload_1
      36: iload         5
      38: baload
      39: iload_3
      40: iload         4
      42: invokevirtual #112                // Method extendHash:(IIII)I
      45: istore_2
      46: aload_0
      47: iload_3
      48: invokevirtual #114                // Method nextMagicA:(I)I
      51: istore_3
      52: aload_0
      53: iload         4
      55: invokevirtual #116                // Method nextMagicB:(I)I
      58: istore        4
      60: iload         5
      62: iconst_1
      63: iadd
      64: istore        5
      66: goto          26
      69: aload_0
      70: iload_2
      71: invokevirtual #118                // Method finalizeHash:(I)I
      74: ireturn

  public int arrayHash$mCc$sp(char[]);
    Code:
       0: aload_0
       1: aload_1
       2: arraylength
       3: aload_0
       4: invokevirtual #102                // Method akka$routing$MurmurHash$$seedArray:()I
       7: imul
       8: invokevirtual #104                // Method startHash:(I)I
      11: istore_2
      12: aload_0
      13: invokevirtual #61                 // Method akka$routing$MurmurHash$$hiddenMagicA:()I
      16: istore_3
      17: aload_0
      18: invokevirtual #64                 // Method akka$routing$MurmurHash$$hiddenMagicB:()I
      21: istore        4
      23: iconst_0
      24: istore        5
      26: iload         5
      28: aload_1
      29: arraylength
      30: if_icmpge     69
      33: aload_0
      34: iload_2
      35: aload_1
      36: iload         5
      38: caload
      39: iload_3
      40: iload         4
      42: invokevirtual #112                // Method extendHash:(IIII)I
      45: istore_2
      46: aload_0
      47: iload_3
      48: invokevirtual #114                // Method nextMagicA:(I)I
      51: istore_3
      52: aload_0
      53: iload         4
      55: invokevirtual #116                // Method nextMagicB:(I)I
      58: istore        4
      60: iload         5
      62: iconst_1
      63: iadd
      64: istore        5
      66: goto          26
      69: aload_0
      70: iload_2
      71: invokevirtual #118                // Method finalizeHash:(I)I
      74: ireturn

  public int arrayHash$mDc$sp(double[]);
    Code:
       0: aload_0
       1: aload_1
       2: arraylength
       3: aload_0
       4: invokevirtual #102                // Method akka$routing$MurmurHash$$seedArray:()I
       7: imul
       8: invokevirtual #104                // Method startHash:(I)I
      11: istore_2
      12: aload_0
      13: invokevirtual #61                 // Method akka$routing$MurmurHash$$hiddenMagicA:()I
      16: istore_3
      17: aload_0
      18: invokevirtual #64                 // Method akka$routing$MurmurHash$$hiddenMagicB:()I
      21: istore        4
      23: iconst_0
      24: istore        5
      26: iload         5
      28: aload_1
      29: arraylength
      30: if_icmpge     75
      33: aload_0
      34: iload_2
      35: getstatic     #97                 // Field scala/runtime/ScalaRunTime$.MODULE$:Lscala/runtime/ScalaRunTime$;
      38: aload_1
      39: iload         5
      41: daload
      42: invokevirtual #187                // Method scala/runtime/ScalaRunTime$.hash:(D)I
      45: iload_3
      46: iload         4
      48: invokevirtual #112                // Method extendHash:(IIII)I
      51: istore_2
      52: aload_0
      53: iload_3
      54: invokevirtual #114                // Method nextMagicA:(I)I
      57: istore_3
      58: aload_0
      59: iload         4
      61: invokevirtual #116                // Method nextMagicB:(I)I
      64: istore        4
      66: iload         5
      68: iconst_1
      69: iadd
      70: istore        5
      72: goto          26
      75: aload_0
      76: iload_2
      77: invokevirtual #118                // Method finalizeHash:(I)I
      80: ireturn

  public int arrayHash$mFc$sp(float[]);
    Code:
       0: aload_0
       1: aload_1
       2: arraylength
       3: aload_0
       4: invokevirtual #102                // Method akka$routing$MurmurHash$$seedArray:()I
       7: imul
       8: invokevirtual #104                // Method startHash:(I)I
      11: istore_2
      12: aload_0
      13: invokevirtual #61                 // Method akka$routing$MurmurHash$$hiddenMagicA:()I
      16: istore_3
      17: aload_0
      18: invokevirtual #64                 // Method akka$routing$MurmurHash$$hiddenMagicB:()I
      21: istore        4
      23: iconst_0
      24: istore        5
      26: iload         5
      28: aload_1
      29: arraylength
      30: if_icmpge     75
      33: aload_0
      34: iload_2
      35: getstatic     #97                 // Field scala/runtime/ScalaRunTime$.MODULE$:Lscala/runtime/ScalaRunTime$;
      38: aload_1
      39: iload         5
      41: faload
      42: invokevirtual #194                // Method scala/runtime/ScalaRunTime$.hash:(F)I
      45: iload_3
      46: iload         4
      48: invokevirtual #112                // Method extendHash:(IIII)I
      51: istore_2
      52: aload_0
      53: iload_3
      54: invokevirtual #114                // Method nextMagicA:(I)I
      57: istore_3
      58: aload_0
      59: iload         4
      61: invokevirtual #116                // Method nextMagicB:(I)I
      64: istore        4
      66: iload         5
      68: iconst_1
      69: iadd
      70: istore        5
      72: goto          26
      75: aload_0
      76: iload_2
      77: invokevirtual #118                // Method finalizeHash:(I)I
      80: ireturn

  public int arrayHash$mIc$sp(int[]);
    Code:
       0: aload_0
       1: aload_1
       2: arraylength
       3: aload_0
       4: invokevirtual #102                // Method akka$routing$MurmurHash$$seedArray:()I
       7: imul
       8: invokevirtual #104                // Method startHash:(I)I
      11: istore_2
      12: aload_0
      13: invokevirtual #61                 // Method akka$routing$MurmurHash$$hiddenMagicA:()I
      16: istore_3
      17: aload_0
      18: invokevirtual #64                 // Method akka$routing$MurmurHash$$hiddenMagicB:()I
      21: istore        4
      23: iconst_0
      24: istore        5
      26: iload         5
      28: aload_1
      29: arraylength
      30: if_icmpge     69
      33: aload_0
      34: iload_2
      35: aload_1
      36: iload         5
      38: iaload
      39: iload_3
      40: iload         4
      42: invokevirtual #112                // Method extendHash:(IIII)I
      45: istore_2
      46: aload_0
      47: iload_3
      48: invokevirtual #114                // Method nextMagicA:(I)I
      51: istore_3
      52: aload_0
      53: iload         4
      55: invokevirtual #116                // Method nextMagicB:(I)I
      58: istore        4
      60: iload         5
      62: iconst_1
      63: iadd
      64: istore        5
      66: goto          26
      69: aload_0
      70: iload_2
      71: invokevirtual #118                // Method finalizeHash:(I)I
      74: ireturn

  public int arrayHash$mJc$sp(long[]);
    Code:
       0: aload_0
       1: aload_1
       2: arraylength
       3: aload_0
       4: invokevirtual #102                // Method akka$routing$MurmurHash$$seedArray:()I
       7: imul
       8: invokevirtual #104                // Method startHash:(I)I
      11: istore_2
      12: aload_0
      13: invokevirtual #61                 // Method akka$routing$MurmurHash$$hiddenMagicA:()I
      16: istore_3
      17: aload_0
      18: invokevirtual #64                 // Method akka$routing$MurmurHash$$hiddenMagicB:()I
      21: istore        4
      23: iconst_0
      24: istore        5
      26: iload         5
      28: aload_1
      29: arraylength
      30: if_icmpge     75
      33: aload_0
      34: iload_2
      35: getstatic     #97                 // Field scala/runtime/ScalaRunTime$.MODULE$:Lscala/runtime/ScalaRunTime$;
      38: aload_1
      39: iload         5
      41: laload
      42: invokevirtual #204                // Method scala/runtime/ScalaRunTime$.hash:(J)I
      45: iload_3
      46: iload         4
      48: invokevirtual #112                // Method extendHash:(IIII)I
      51: istore_2
      52: aload_0
      53: iload_3
      54: invokevirtual #114                // Method nextMagicA:(I)I
      57: istore_3
      58: aload_0
      59: iload         4
      61: invokevirtual #116                // Method nextMagicB:(I)I
      64: istore        4
      66: iload         5
      68: iconst_1
      69: iadd
      70: istore        5
      72: goto          26
      75: aload_0
      76: iload_2
      77: invokevirtual #118                // Method finalizeHash:(I)I
      80: ireturn

  public int arrayHash$mSc$sp(short[]);
    Code:
       0: aload_0
       1: aload_1
       2: arraylength
       3: aload_0
       4: invokevirtual #102                // Method akka$routing$MurmurHash$$seedArray:()I
       7: imul
       8: invokevirtual #104                // Method startHash:(I)I
      11: istore_2
      12: aload_0
      13: invokevirtual #61                 // Method akka$routing$MurmurHash$$hiddenMagicA:()I
      16: istore_3
      17: aload_0
      18: invokevirtual #64                 // Method akka$routing$MurmurHash$$hiddenMagicB:()I
      21: istore        4
      23: iconst_0
      24: istore        5
      26: iload         5
      28: aload_1
      29: arraylength
      30: if_icmpge     69
      33: aload_0
      34: iload_2
      35: aload_1
      36: iload         5
      38: saload
      39: iload_3
      40: iload         4
      42: invokevirtual #112                // Method extendHash:(IIII)I
      45: istore_2
      46: aload_0
      47: iload_3
      48: invokevirtual #114                // Method nextMagicA:(I)I
      51: istore_3
      52: aload_0
      53: iload         4
      55: invokevirtual #116                // Method nextMagicB:(I)I
      58: istore        4
      60: iload         5
      62: iconst_1
      63: iadd
      64: istore        5
      66: goto          26
      69: aload_0
      70: iload_2
      71: invokevirtual #118                // Method finalizeHash:(I)I
      74: ireturn

  public int arrayHash$mVc$sp(scala.runtime.BoxedUnit[]);
    Code:
       0: aload_0
       1: aload_1
       2: arraylength
       3: aload_0
       4: invokevirtual #102                // Method akka$routing$MurmurHash$$seedArray:()I
       7: imul
       8: invokevirtual #104                // Method startHash:(I)I
      11: istore_2
      12: aload_0
      13: invokevirtual #61                 // Method akka$routing$MurmurHash$$hiddenMagicA:()I
      16: istore_3
      17: aload_0
      18: invokevirtual #64                 // Method akka$routing$MurmurHash$$hiddenMagicB:()I
      21: istore        4
      23: iconst_0
      24: istore        5
      26: iload         5
      28: aload_1
      29: arraylength
      30: if_icmpge     66
      33: aload_0
      34: iload_2
      35: iconst_0
      36: iload_3
      37: iload         4
      39: invokevirtual #112                // Method extendHash:(IIII)I
      42: istore_2
      43: aload_0
      44: iload_3
      45: invokevirtual #114                // Method nextMagicA:(I)I
      48: istore_3
      49: aload_0
      50: iload         4
      52: invokevirtual #116                // Method nextMagicB:(I)I
      55: istore        4
      57: iload         5
      59: iconst_1
      60: iadd
      61: istore        5
      63: goto          26
      66: aload_0
      67: iload_2
      68: invokevirtual #118                // Method finalizeHash:(I)I
      71: ireturn

  private akka.routing.MurmurHash$();
    Code:
       0: aload_0
       1: invokespecial #215                // Method java/lang/Object."<init>":()V
       4: aload_0
       5: putstatic     #217                // Field MODULE$:Lakka/routing/MurmurHash$;
       8: aload_0
       9: ldc           #218                // int -1759636613
      11: putfield      #29                 // Field visibleMagic:I
      14: aload_0
      15: ldc           #219                // int -1789642873
      17: putfield      #32                 // Field akka$routing$MurmurHash$$hiddenMagicA:I
      20: aload_0
      21: ldc           #220                // int 718793509
      23: putfield      #34                 // Field akka$routing$MurmurHash$$hiddenMagicB:I
      26: aload_0
      27: ldc           #221                // int 1390208809
      29: putfield      #36                 // Field visibleMixer:I
      32: aload_0
      33: ldc           #222                // int 2071795100
      35: putfield      #38                 // Field hiddenMixerA:I
      38: aload_0
      39: ldc           #223                // int 1808688022
      41: putfield      #40                 // Field hiddenMixerB:I
      44: aload_0
      45: ldc           #224                // int -2048144789
      47: putfield      #42                 // Field finalMixer1:I
      50: aload_0
      51: ldc           #225                // int -1028477387
      53: putfield      #44                 // Field finalMixer2:I
      56: aload_0
      57: ldc           #226                // int -137723950
      59: putfield      #46                 // Field seedString:I
      62: aload_0
      63: ldc           #227                // int 1007110753
      65: putfield      #48                 // Field akka$routing$MurmurHash$$seedArray:I
      68: aload_0
      69: getstatic     #232                // Field scala/package$.MODULE$:Lscala/package$;
      72: invokevirtual #236                // Method scala/package$.Iterator:()Lscala/collection/Iterator$;
      75: aload_0
      76: invokevirtual #61                 // Method akka$routing$MurmurHash$$hiddenMagicA:()I
      79: invokestatic  #242                // Method scala/runtime/BoxesRunTime.boxToInteger:(I)Ljava/lang/Integer;
      82: new           #244                // class akka/routing/MurmurHash$$anonfun$1
      85: dup
      86: invokespecial #245                // Method akka/routing/MurmurHash$$anonfun$1."<init>":()V
      89: invokevirtual #251                // Method scala/collection/Iterator$.iterate:(Ljava/lang/Object;Lscala/Function1;)Lscala/collection/Iterator;
      92: bipush        23
      94: invokeinterface #257,  2          // InterfaceMethod scala/collection/Iterator.take:(I)Lscala/collection/Iterator;
      99: getstatic     #262                // Field scala/reflect/ClassTag$.MODULE$:Lscala/reflect/ClassTag$;
     102: invokevirtual #266                // Method scala/reflect/ClassTag$.Int:()Lscala/reflect/ClassTag;
     105: invokeinterface #270,  2          // InterfaceMethod scala/collection/Iterator.toArray:(Lscala/reflect/ClassTag;)Ljava/lang/Object;
     110: checkcast     #199                // class "[I"
     113: putfield      #51                 // Field storedMagicA:[I
     116: aload_0
     117: getstatic     #232                // Field scala/package$.MODULE$:Lscala/package$;
     120: invokevirtual #236                // Method scala/package$.Iterator:()Lscala/collection/Iterator$;
     123: aload_0
     124: invokevirtual #64                 // Method akka$routing$MurmurHash$$hiddenMagicB:()I
     127: invokestatic  #242                // Method scala/runtime/BoxesRunTime.boxToInteger:(I)Ljava/lang/Integer;
     130: new           #272                // class akka/routing/MurmurHash$$anonfun$2
     133: dup
     134: invokespecial #273                // Method akka/routing/MurmurHash$$anonfun$2."<init>":()V
     137: invokevirtual #251                // Method scala/collection/Iterator$.iterate:(Ljava/lang/Object;Lscala/Function1;)Lscala/collection/Iterator;
     140: bipush        23
     142: invokeinterface #257,  2          // InterfaceMethod scala/collection/Iterator.take:(I)Lscala/collection/Iterator;
     147: getstatic     #262                // Field scala/reflect/ClassTag$.MODULE$:Lscala/reflect/ClassTag$;
     150: invokevirtual #266                // Method scala/reflect/ClassTag$.Int:()Lscala/reflect/ClassTag;
     153: invokeinterface #270,  2          // InterfaceMethod scala/collection/Iterator.toArray:(Lscala/reflect/ClassTag;)Ljava/lang/Object;
     158: checkcast     #199                // class "[I"
     161: putfield      #53                 // Field storedMagicB:[I
     164: return
}
