Compiled from "PathEngineException.java"
public class org.hl7.fhir.exceptions.PathEngineException extends org.hl7.fhir.exceptions.FHIRException {
  private static final long serialVersionUID;

  private org.hl7.fhir.utilities.SourceLocation location;

  private java.lang.String expression;

  public org.hl7.fhir.exceptions.PathEngineException();
    Code:
       0: aload_0
       1: invokespecial #1                  // Method org/hl7/fhir/exceptions/FHIRException."<init>":()V
       4: return

  public org.hl7.fhir.exceptions.PathEngineException(java.lang.String, java.lang.Throwable);
    Code:
       0: aload_0
       1: aload_1
       2: aload_2
       3: invokespecial #2                  // Method org/hl7/fhir/exceptions/FHIRException."<init>":(Ljava/lang/String;Ljava/lang/Throwable;)V
       6: return

  public org.hl7.fhir.exceptions.PathEngineException(java.lang.String);
    Code:
       0: aload_0
       1: aload_1
       2: invokespecial #3                  // Method org/hl7/fhir/exceptions/FHIRException."<init>":(Ljava/lang/String;)V
       5: return

  public org.hl7.fhir.exceptions.PathEngineException(java.lang.String, org.hl7.fhir.utilities.SourceLocation, java.lang.String, java.lang.Throwable);
    Code:
       0: aload_0
       1: new           #4                  // class java/lang/StringBuilder
       4: dup
       5: invokespecial #5                  // Method java/lang/StringBuilder."<init>":()V
       8: aload_1
       9: invokevirtual #6                  // Method java/lang/StringBuilder.append:(Ljava/lang/String;)Ljava/lang/StringBuilder;
      12: aload_2
      13: aload_3
      14: invokestatic  #7                  // Method rep:(Lorg/hl7/fhir/utilities/SourceLocation;Ljava/lang/String;)Ljava/lang/String;
      17: invokevirtual #6                  // Method java/lang/StringBuilder.append:(Ljava/lang/String;)Ljava/lang/StringBuilder;
      20: invokevirtual #8                  // Method java/lang/StringBuilder.toString:()Ljava/lang/String;
      23: aload         4
      25: invokespecial #2                  // Method org/hl7/fhir/exceptions/FHIRException."<init>":(Ljava/lang/String;Ljava/lang/Throwable;)V
      28: return

  public org.hl7.fhir.exceptions.PathEngineException(java.lang.String, org.hl7.fhir.utilities.SourceLocation, java.lang.String);
    Code:
       0: aload_0
       1: new           #4                  // class java/lang/StringBuilder
       4: dup
       5: invokespecial #5                  // Method java/lang/StringBuilder."<init>":()V
       8: aload_1
       9: invokevirtual #6                  // Method java/lang/StringBuilder.append:(Ljava/lang/String;)Ljava/lang/StringBuilder;
      12: aload_2
      13: aload_3
      14: invokestatic  #7                  // Method rep:(Lorg/hl7/fhir/utilities/SourceLocation;Ljava/lang/String;)Ljava/lang/String;
      17: invokevirtual #6                  // Method java/lang/StringBuilder.append:(Ljava/lang/String;)Ljava/lang/StringBuilder;
      20: invokevirtual #8                  // Method java/lang/StringBuilder.toString:()Ljava/lang/String;
      23: invokespecial #3                  // Method org/hl7/fhir/exceptions/FHIRException."<init>":(Ljava/lang/String;)V
      26: return

  private static java.lang.String rep(org.hl7.fhir.utilities.SourceLocation, java.lang.String);
    Code:
       0: aload_0
       1: ifnull        80
       4: aload_0
       5: invokevirtual #9                  // Method org/hl7/fhir/utilities/SourceLocation.getLine:()I
       8: iconst_1
       9: if_icmpne     40
      12: new           #4                  // class java/lang/StringBuilder
      15: dup
      16: invokespecial #5                  // Method java/lang/StringBuilder."<init>":()V
      19: ldc           #10                 // String  (@char
      21: invokevirtual #6                  // Method java/lang/StringBuilder.append:(Ljava/lang/String;)Ljava/lang/StringBuilder;
      24: aload_0
      25: invokevirtual #11                 // Method org/hl7/fhir/utilities/SourceLocation.getColumn:()I
      28: invokevirtual #12                 // Method java/lang/StringBuilder.append:(I)Ljava/lang/StringBuilder;
      31: ldc           #13                 // String )
      33: invokevirtual #6                  // Method java/lang/StringBuilder.append:(Ljava/lang/String;)Ljava/lang/StringBuilder;
      36: invokevirtual #8                  // Method java/lang/StringBuilder.toString:()Ljava/lang/String;
      39: areturn
      40: new           #4                  // class java/lang/StringBuilder
      43: dup
      44: invokespecial #5                  // Method java/lang/StringBuilder."<init>":()V
      47: ldc           #14                 // String  (@line
      49: invokevirtual #6                  // Method java/lang/StringBuilder.append:(Ljava/lang/String;)Ljava/lang/StringBuilder;
      52: aload_0
      53: invokevirtual #9                  // Method org/hl7/fhir/utilities/SourceLocation.getLine:()I
      56: invokevirtual #12                 // Method java/lang/StringBuilder.append:(I)Ljava/lang/StringBuilder;
      59: ldc           #15                 // String  char
      61: invokevirtual #6                  // Method java/lang/StringBuilder.append:(Ljava/lang/String;)Ljava/lang/StringBuilder;
      64: aload_0
      65: invokevirtual #11                 // Method org/hl7/fhir/utilities/SourceLocation.getColumn:()I
      68: invokevirtual #12                 // Method java/lang/StringBuilder.append:(I)Ljava/lang/StringBuilder;
      71: ldc           #13                 // String )
      73: invokevirtual #6                  // Method java/lang/StringBuilder.append:(Ljava/lang/String;)Ljava/lang/StringBuilder;
      76: invokevirtual #8                  // Method java/lang/StringBuilder.toString:()Ljava/lang/String;
      79: areturn
      80: aload_1
      81: invokestatic  #16                 // Method org/hl7/fhir/utilities/Utilities.noString:(Ljava/lang/String;)Z
      84: ifeq          112
      87: new           #4                  // class java/lang/StringBuilder
      90: dup
      91: invokespecial #5                  // Method java/lang/StringBuilder."<init>":()V
      94: ldc           #17                 // String  (@~
      96: invokevirtual #6                  // Method java/lang/StringBuilder.append:(Ljava/lang/String;)Ljava/lang/StringBuilder;
      99: aload_1
     100: invokevirtual #6                  // Method java/lang/StringBuilder.append:(Ljava/lang/String;)Ljava/lang/StringBuilder;
     103: ldc           #13                 // String )
     105: invokevirtual #6                  // Method java/lang/StringBuilder.append:(Ljava/lang/String;)Ljava/lang/StringBuilder;
     108: invokevirtual #8                  // Method java/lang/StringBuilder.toString:()Ljava/lang/String;
     111: areturn
     112: ldc           #18                 // String
     114: areturn

  public org.hl7.fhir.exceptions.PathEngineException(java.lang.Throwable);
    Code:
       0: aload_0
       1: aload_1
       2: invokespecial #19                 // Method org/hl7/fhir/exceptions/FHIRException."<init>":(Ljava/lang/Throwable;)V
       5: return

  public java.lang.String getExpression();
    Code:
       0: aload_0
       1: getfield      #20                 // Field expression:Ljava/lang/String;
       4: areturn

  public void setExpression(java.lang.String);
    Code:
       0: aload_0
       1: aload_1
       2: putfield      #20                 // Field expression:Ljava/lang/String;
       5: return

  public org.hl7.fhir.utilities.SourceLocation getLocation();
    Code:
       0: aload_0
       1: getfield      #21                 // Field location:Lorg/hl7/fhir/utilities/SourceLocation;
       4: areturn

  public void setLocation(org.hl7.fhir.utilities.SourceLocation);
    Code:
       0: aload_0
       1: aload_1
       2: putfield      #21                 // Field location:Lorg/hl7/fhir/utilities/SourceLocation;
       5: return
}
