Compiled from "IDPEntryImpl.java"
public class org.opensaml.saml.saml2.core.impl.IDPEntryImpl extends org.opensaml.saml.common.AbstractSAMLObject implements org.opensaml.saml.saml2.core.IDPEntry {
  private java.lang.String providerID;

  private java.lang.String name;

  private java.lang.String loc;

  protected org.opensaml.saml.saml2.core.impl.IDPEntryImpl(java.lang.String, java.lang.String, java.lang.String);
    Code:
       0: aload_0
       1: aload_1
       2: aload_2
       3: aload_3
       4: invokespecial #1                  // Method org/opensaml/saml/common/AbstractSAMLObject."<init>":(Ljava/lang/String;Ljava/lang/String;Ljava/lang/String;)V
       7: return

  public java.lang.String getProviderID();
    Code:
       0: aload_0
       1: getfield      #2                  // Field providerID:Ljava/lang/String;
       4: areturn

  public void setProviderID(java.lang.String);
    Code:
       0: aload_0
       1: aload_0
       2: aload_0
       3: getfield      #2                  // Field providerID:Ljava/lang/String;
       6: aload_1
       7: invokevirtual #3                  // Method prepareForAssignment:(Ljava/lang/String;Ljava/lang/String;)Ljava/lang/String;
      10: putfield      #2                  // Field providerID:Ljava/lang/String;
      13: return

  public java.lang.String getName();
    Code:
       0: aload_0
       1: getfield      #4                  // Field name:Ljava/lang/String;
       4: areturn

  public void setName(java.lang.String);
    Code:
       0: aload_0
       1: aload_0
       2: aload_0
       3: getfield      #4                  // Field name:Ljava/lang/String;
       6: aload_1
       7: invokevirtual #3                  // Method prepareForAssignment:(Ljava/lang/String;Ljava/lang/String;)Ljava/lang/String;
      10: putfield      #4                  // Field name:Ljava/lang/String;
      13: return

  public java.lang.String getLoc();
    Code:
       0: aload_0
       1: getfield      #5                  // Field loc:Ljava/lang/String;
       4: areturn

  public void setLoc(java.lang.String);
    Code:
       0: aload_0
       1: aload_0
       2: aload_0
       3: getfield      #5                  // Field loc:Ljava/lang/String;
       6: aload_1
       7: invokevirtual #3                  // Method prepareForAssignment:(Ljava/lang/String;Ljava/lang/String;)Ljava/lang/String;
      10: putfield      #5                  // Field loc:Ljava/lang/String;
      13: return

  public java.util.List<org.opensaml.core.xml.XMLObject> getOrderedChildren();
    Code:
       0: aconst_null
       1: areturn
}
