Compiled from "CouchbaseConfigurerAdapterConfiguration.java"
class org.springframework.boot.autoconfigure.data.couchbase.CouchbaseConfigurerAdapterConfiguration {
  private final org.springframework.boot.autoconfigure.couchbase.CouchbaseConfiguration configuration;

  org.springframework.boot.autoconfigure.data.couchbase.CouchbaseConfigurerAdapterConfiguration(org.springframework.boot.autoconfigure.couchbase.CouchbaseConfiguration);
    Code:
       0: aload_0
       1: invokespecial #1                  // Method java/lang/Object."<init>":()V
       4: aload_0
       5: aload_1
       6: putfield      #2                  // Field configuration:Lorg/springframework/boot/autoconfigure/couchbase/CouchbaseConfiguration;
       9: return

  public org.springframework.data.couchbase.config.CouchbaseConfigurer springBootCouchbaseConfigurer() throws java.lang.Exception;
    Code:
       0: new           #3                  // class org/springframework/boot/autoconfigure/data/couchbase/SpringBootCouchbaseConfigurer
       3: dup
       4: aload_0
       5: getfield      #2                  // Field configuration:Lorg/springframework/boot/autoconfigure/couchbase/CouchbaseConfiguration;
       8: invokevirtual #4                  // Method org/springframework/boot/autoconfigure/couchbase/CouchbaseConfiguration.couchbaseEnvironment:()Lcom/couchbase/client/java/env/DefaultCouchbaseEnvironment;
      11: aload_0
      12: getfield      #2                  // Field configuration:Lorg/springframework/boot/autoconfigure/couchbase/CouchbaseConfiguration;
      15: invokevirtual #5                  // Method org/springframework/boot/autoconfigure/couchbase/CouchbaseConfiguration.couchbaseCluster:()Lcom/couchbase/client/java/Cluster;
      18: aload_0
      19: getfield      #2                  // Field configuration:Lorg/springframework/boot/autoconfigure/couchbase/CouchbaseConfiguration;
      22: invokevirtual #6                  // Method org/springframework/boot/autoconfigure/couchbase/CouchbaseConfiguration.couchbaseClusterInfo:()Lcom/couchbase/client/java/cluster/ClusterInfo;
      25: aload_0
      26: getfield      #2                  // Field configuration:Lorg/springframework/boot/autoconfigure/couchbase/CouchbaseConfiguration;
      29: invokevirtual #7                  // Method org/springframework/boot/autoconfigure/couchbase/CouchbaseConfiguration.couchbaseClient:()Lcom/couchbase/client/java/Bucket;
      32: invokespecial #8                  // Method org/springframework/boot/autoconfigure/data/couchbase/SpringBootCouchbaseConfigurer."<init>":(Lcom/couchbase/client/java/env/CouchbaseEnvironment;Lcom/couchbase/client/java/Cluster;Lcom/couchbase/client/java/cluster/ClusterInfo;Lcom/couchbase/client/java/Bucket;)V
      35: areturn
}
