Compiled from "UndertowServerDestination.java"
public class org.jboss.wsf.stack.cxf.addons.transports.undertow.UndertowServerDestination extends org.apache.cxf.transport.http_jaxws_spi.JAXWSHttpSpiDestination {
  static final java.util.logging.Logger LOG;

  private org.jboss.wsf.stack.cxf.addons.transports.undertow.UndertowServerEngineFactory serverEngineFactory;

  private org.jboss.wsf.stack.cxf.addons.transports.undertow.UndertowServerEngine engine;

  private java.net.URL url;

  public org.jboss.wsf.stack.cxf.addons.transports.undertow.UndertowServerDestination(org.apache.cxf.Bus, org.apache.cxf.transport.http.DestinationRegistry, org.apache.cxf.service.model.EndpointInfo) throws java.io.IOException;
    Code:
       0: aload_0
       1: aload_1
       2: aload_2
       3: aload_3
       4: invokespecial #1                  // Method org/apache/cxf/transport/http_jaxws_spi/JAXWSHttpSpiDestination."<init>":(Lorg/apache/cxf/Bus;Lorg/apache/cxf/transport/http/DestinationRegistry;Lorg/apache/cxf/service/model/EndpointInfo;)V
       7: aload_0
       8: aload_0
       9: invokevirtual #2                  // Method getServerEngineFactory:()Lorg/jboss/wsf/stack/cxf/addons/transports/undertow/UndertowServerEngineFactory;
      12: putfield      #3                  // Field serverEngineFactory:Lorg/jboss/wsf/stack/cxf/addons/transports/undertow/UndertowServerEngineFactory;
      15: aload_3
      16: iconst_1
      17: invokestatic  #4                  // Method getAddressValue:(Lorg/apache/cxf/service/model/EndpointInfo;Z)Lorg/apache/cxf/service/model/EndpointInfo;
      20: pop
      21: aload_0
      22: new           #5                  // class java/net/URL
      25: dup
      26: aload_3
      27: invokevirtual #6                  // Method org/apache/cxf/service/model/EndpointInfo.getAddress:()Ljava/lang/String;
      30: invokespecial #7                  // Method java/net/URL."<init>":(Ljava/lang/String;)V
      33: putfield      #8                  // Field url:Ljava/net/URL;
      36: return

  protected java.util.logging.Logger getLogger();
    Code:
       0: getstatic     #9                  // Field LOG:Ljava/util/logging/Logger;
       3: areturn

  public void finalizeConfig();
    Code:
       0: aload_0
       1: aload_0
       2: getfield      #3                  // Field serverEngineFactory:Lorg/jboss/wsf/stack/cxf/addons/transports/undertow/UndertowServerEngineFactory;
       5: aload_0
       6: getfield      #8                  // Field url:Ljava/net/URL;
       9: invokevirtual #10                 // Method java/net/URL.getPort:()I
      12: invokevirtual #11                 // Method org/jboss/wsf/stack/cxf/addons/transports/undertow/UndertowServerEngineFactory.retrieveHttpServerEngine:(I)Lorg/jboss/wsf/stack/cxf/addons/transports/undertow/UndertowServerEngine;
      15: putfield      #12                 // Field engine:Lorg/jboss/wsf/stack/cxf/addons/transports/undertow/UndertowServerEngine;
      18: aload_0
      19: getfield      #12                 // Field engine:Lorg/jboss/wsf/stack/cxf/addons/transports/undertow/UndertowServerEngine;
      22: ifnonnull     70
      25: aload_0
      26: aload_0
      27: getfield      #3                  // Field serverEngineFactory:Lorg/jboss/wsf/stack/cxf/addons/transports/undertow/UndertowServerEngineFactory;
      30: aload_0
      31: getfield      #8                  // Field url:Ljava/net/URL;
      34: invokevirtual #13                 // Method java/net/URL.getHost:()Ljava/lang/String;
      37: aload_0
      38: getfield      #8                  // Field url:Ljava/net/URL;
      41: invokevirtual #10                 // Method java/net/URL.getPort:()I
      44: aload_0
      45: getfield      #8                  // Field url:Ljava/net/URL;
      48: invokevirtual #14                 // Method java/net/URL.getProtocol:()Ljava/lang/String;
      51: invokevirtual #15                 // Method org/jboss/wsf/stack/cxf/addons/transports/undertow/UndertowServerEngineFactory.createHttpServerEngine:(Ljava/lang/String;ILjava/lang/String;)Lorg/jboss/wsf/stack/cxf/addons/transports/undertow/UndertowServerEngine;
      54: putfield      #12                 // Field engine:Lorg/jboss/wsf/stack/cxf/addons/transports/undertow/UndertowServerEngine;
      57: goto          70
      60: astore_1
      61: new           #17                 // class java/lang/RuntimeException
      64: dup
      65: aload_1
      66: invokespecial #18                 // Method java/lang/RuntimeException."<init>":(Ljava/lang/Throwable;)V
      69: athrow
      70: aload_0
      71: getfield      #8                  // Field url:Ljava/net/URL;
      74: invokevirtual #14                 // Method java/net/URL.getProtocol:()Ljava/lang/String;
      77: aload_0
      78: getfield      #12                 // Field engine:Lorg/jboss/wsf/stack/cxf/addons/transports/undertow/UndertowServerEngine;
      81: invokevirtual #19                 // Method org/jboss/wsf/stack/cxf/addons/transports/undertow/UndertowServerEngine.getProtocol:()Ljava/lang/String;
      84: invokevirtual #20                 // Method java/lang/String.equals:(Ljava/lang/Object;)Z
      87: ifne          155
      90: new           #21                 // class java/lang/IllegalStateException
      93: dup
      94: new           #22                 // class java/lang/StringBuilder
      97: dup
      98: invokespecial #23                 // Method java/lang/StringBuilder."<init>":()V
     101: ldc           #24                 // String Port
     103: invokevirtual #25                 // Method java/lang/StringBuilder.append:(Ljava/lang/String;)Ljava/lang/StringBuilder;
     106: aload_0
     107: getfield      #12                 // Field engine:Lorg/jboss/wsf/stack/cxf/addons/transports/undertow/UndertowServerEngine;
     110: invokevirtual #26                 // Method org/jboss/wsf/stack/cxf/addons/transports/undertow/UndertowServerEngine.getPort:()I
     113: invokevirtual #27                 // Method java/lang/StringBuilder.append:(I)Ljava/lang/StringBuilder;
     116: ldc           #28                 // String  is configured with wrong protocol \"
     118: invokevirtual #25                 // Method java/lang/StringBuilder.append:(Ljava/lang/String;)Ljava/lang/StringBuilder;
     121: aload_0
     122: getfield      #12                 // Field engine:Lorg/jboss/wsf/stack/cxf/addons/transports/undertow/UndertowServerEngine;
     125: invokevirtual #19                 // Method org/jboss/wsf/stack/cxf/addons/transports/undertow/UndertowServerEngine.getProtocol:()Ljava/lang/String;
     128: invokevirtual #25                 // Method java/lang/StringBuilder.append:(Ljava/lang/String;)Ljava/lang/StringBuilder;
     131: ldc           #29                 // String \" for \"
     133: invokevirtual #25                 // Method java/lang/StringBuilder.append:(Ljava/lang/String;)Ljava/lang/StringBuilder;
     136: aload_0
     137: getfield      #8                  // Field url:Ljava/net/URL;
     140: invokevirtual #30                 // Method java/lang/StringBuilder.append:(Ljava/lang/Object;)Ljava/lang/StringBuilder;
     143: ldc           #31                 // String \"
     145: invokevirtual #25                 // Method java/lang/StringBuilder.append:(Ljava/lang/String;)Ljava/lang/StringBuilder;
     148: invokevirtual #32                 // Method java/lang/StringBuilder.toString:()Ljava/lang/String;
     151: invokespecial #33                 // Method java/lang/IllegalStateException."<init>":(Ljava/lang/String;)V
     154: athrow
     155: return
    Exception table:
       from    to  target type
          25    57    60   Class java/io/IOException

  protected org.jboss.wsf.stack.cxf.addons.transports.undertow.UndertowServerEngineFactory getServerEngineFactory();
    Code:
       0: aload_0
       1: invokevirtual #34                 // Method getBus:()Lorg/apache/cxf/Bus;
       4: ldc           #35                 // class org/jboss/wsf/stack/cxf/addons/transports/undertow/UndertowServerEngineFactory
       6: invokeinterface #36,  2           // InterfaceMethod org/apache/cxf/Bus.getExtension:(Ljava/lang/Class;)Ljava/lang/Object;
      11: checkcast     #35                 // class org/jboss/wsf/stack/cxf/addons/transports/undertow/UndertowServerEngineFactory
      14: astore_1
      15: aload_1
      16: ifnonnull     31
      19: new           #35                 // class org/jboss/wsf/stack/cxf/addons/transports/undertow/UndertowServerEngineFactory
      22: dup
      23: aload_0
      24: getfield      #37                 // Field bus:Lorg/apache/cxf/Bus;
      27: invokespecial #38                 // Method org/jboss/wsf/stack/cxf/addons/transports/undertow/UndertowServerEngineFactory."<init>":(Lorg/apache/cxf/Bus;)V
      30: astore_1
      31: aload_1
      32: areturn

  protected void activate();
    Code:
       0: getstatic     #9                  // Field LOG:Ljava/util/logging/Logger;
       3: getstatic     #39                 // Field java/util/logging/Level.FINE:Ljava/util/logging/Level;
       6: ldc           #40                 // String Activating receipt of incoming messages
       8: invokevirtual #41                 // Method java/util/logging/Logger.log:(Ljava/util/logging/Level;Ljava/lang/String;)V
      11: aload_0
      12: getfield      #42                 // Field endpointInfo:Lorg/apache/cxf/service/model/EndpointInfo;
      15: invokevirtual #6                  // Method org/apache/cxf/service/model/EndpointInfo.getAddress:()Ljava/lang/String;
      18: astore_1
      19: new           #5                  // class java/net/URL
      22: dup
      23: aload_1
      24: invokespecial #7                  // Method java/net/URL."<init>":(Ljava/lang/String;)V
      27: pop
      28: goto          41
      31: astore_2
      32: new           #44                 // class org/apache/cxf/interceptor/Fault
      35: dup
      36: aload_2
      37: invokespecial #45                 // Method org/apache/cxf/interceptor/Fault."<init>":(Ljava/lang/Throwable;)V
      40: athrow
      41: aload_0
      42: getfield      #12                 // Field engine:Lorg/jboss/wsf/stack/cxf/addons/transports/undertow/UndertowServerEngine;
      45: aload_1
      46: new           #46                 // class org/jboss/wsf/stack/cxf/addons/transports/undertow/UndertowServerDestination$Handler
      49: dup
      50: aload_0
      51: aload_0
      52: invokestatic  #47                 // Method org/jboss/wsf/stack/cxf/addons/transports/undertow/SecurityActions.getContextClassLoader:()Ljava/lang/ClassLoader;
      55: invokespecial #48                 // Method org/jboss/wsf/stack/cxf/addons/transports/undertow/UndertowServerDestination$Handler."<init>":(Lorg/jboss/wsf/stack/cxf/addons/transports/undertow/UndertowServerDestination;Lorg/apache/cxf/transport/http_jaxws_spi/JAXWSHttpSpiDestination;Ljava/lang/ClassLoader;)V
      58: invokevirtual #49                 // Method org/jboss/wsf/stack/cxf/addons/transports/undertow/UndertowServerEngine.addHandler:(Ljava/lang/String;Lio/undertow/server/HttpHandler;)V
      61: return
    Exception table:
       from    to  target type
          19    28    31   Class java/lang/Exception

  protected void deactivate();
    Code:
       0: getstatic     #9                  // Field LOG:Ljava/util/logging/Logger;
       3: getstatic     #39                 // Field java/util/logging/Level.FINE:Ljava/util/logging/Level;
       6: ldc           #50                 // String Deactivating receipt of incoming messages
       8: invokevirtual #41                 // Method java/util/logging/Logger.log:(Ljava/util/logging/Level;Ljava/lang/String;)V
      11: aload_0
      12: getfield      #12                 // Field engine:Lorg/jboss/wsf/stack/cxf/addons/transports/undertow/UndertowServerEngine;
      15: aload_0
      16: getfield      #42                 // Field endpointInfo:Lorg/apache/cxf/service/model/EndpointInfo;
      19: invokevirtual #6                  // Method org/apache/cxf/service/model/EndpointInfo.getAddress:()Ljava/lang/String;
      22: invokevirtual #51                 // Method org/jboss/wsf/stack/cxf/addons/transports/undertow/UndertowServerEngine.removeHandler:(Ljava/lang/String;)V
      25: return

  static {};
    Code:
       0: ldc           #52                 // class org/jboss/wsf/stack/cxf/addons/transports/undertow/UndertowServerDestination
       2: invokestatic  #53                 // Method org/apache/cxf/common/logging/LogUtils.getL7dLogger:(Ljava/lang/Class;)Ljava/util/logging/Logger;
       5: putstatic     #9                  // Field LOG:Ljava/util/logging/Logger;
       8: return
}
