Compiled from "EncodingPredictor.java"
class org.postgresql.core.EncodingPredictor$Translation {
  public final java.lang.String fatalText;

  private final java.lang.String[] texts;

  public final java.lang.String language;

  public final java.lang.String[] encodings;

  org.postgresql.core.EncodingPredictor$Translation(java.lang.String, java.lang.String[], java.lang.String, java.lang.String...);
    Code:
       0: aload_0
       1: invokespecial #2                  // Method java/lang/Object."<init>":()V
       4: aload_0
       5: aload_1
       6: putfield      #3                  // Field fatalText:Ljava/lang/String;
       9: aload_0
      10: aload_2
      11: putfield      #1                  // Field texts:[Ljava/lang/String;
      14: aload_0
      15: aload_3
      16: putfield      #4                  // Field language:Ljava/lang/String;
      19: aload_0
      20: aload         4
      22: putfield      #5                  // Field encodings:[Ljava/lang/String;
      25: return

  static java.lang.String[] access$000(org.postgresql.core.EncodingPredictor$Translation);
    Code:
       0: aload_0
       1: getfield      #1                  // Field texts:[Ljava/lang/String;
       4: areturn
}
