Compiled from "AnnotationAnnotationValue.java"
public class org.jboss.classfilewriter.annotations.AnnotationAnnotationValue extends org.jboss.classfilewriter.annotations.AnnotationValue {
  private final org.jboss.classfilewriter.annotations.ClassAnnotation value;

  public org.jboss.classfilewriter.annotations.AnnotationAnnotationValue(org.jboss.classfilewriter.constpool.ConstPool, java.lang.String, org.jboss.classfilewriter.annotations.ClassAnnotation);
    Code:
       0: aload_0
       1: aload_1
       2: aload_2
       3: invokespecial #1                  // Method org/jboss/classfilewriter/annotations/AnnotationValue."<init>":(Lorg/jboss/classfilewriter/constpool/ConstPool;Ljava/lang/String;)V
       6: aload_0
       7: aload_3
       8: putfield      #2                  // Field value:Lorg/jboss/classfilewriter/annotations/ClassAnnotation;
      11: return

  public char getTag();
    Code:
       0: bipush        64
       2: ireturn

  public void writeData(org.jboss.classfilewriter.util.ByteArrayDataOutputStream) throws java.io.IOException;
    Code:
       0: aload_0
       1: getfield      #2                  // Field value:Lorg/jboss/classfilewriter/annotations/ClassAnnotation;
       4: aload_1
       5: invokevirtual #3                  // Method org/jboss/classfilewriter/annotations/ClassAnnotation.write:(Lorg/jboss/classfilewriter/util/ByteArrayDataOutputStream;)V
       8: return
}
