Compiled from "AnnotationBuilder.java"
public class org.jboss.classfilewriter.annotations.AnnotationBuilder {
  public static org.jboss.classfilewriter.annotations.ClassAnnotation createAnnotation(org.jboss.classfilewriter.constpool.ConstPool, java.lang.annotation.Annotation);
    Code:
       0: aload_1
       1: invokeinterface #1,  1            // InterfaceMethod java/lang/annotation/Annotation.annotationType:()Ljava/lang/Class;
       6: astore_2
       7: new           #2                  // class java/util/ArrayList
      10: dup
      11: invokespecial #3                  // Method java/util/ArrayList."<init>":()V
      14: astore_3
      15: aload_2
      16: invokevirtual #4                  // Method java/lang/Class.getDeclaredMethods:()[Ljava/lang/reflect/Method;
      19: astore        4
      21: aload         4
      23: arraylength
      24: istore        5
      26: iconst_0
      27: istore        6
      29: iload         6
      31: iload         5
      33: if_icmpge     82
      36: aload         4
      38: iload         6
      40: aaload
      41: astore        7
      43: new           #5                  // class org/jboss/classfilewriter/annotations/AnnotationBuilder$1
      46: dup
      47: aload         7
      49: aload_1
      50: invokespecial #6                  // Method org/jboss/classfilewriter/annotations/AnnotationBuilder$1."<init>":(Ljava/lang/reflect/Method;Ljava/lang/annotation/Annotation;)V
      53: invokestatic  #7                  // Method java/security/AccessController.doPrivileged:(Ljava/security/PrivilegedExceptionAction;)Ljava/lang/Object;
      56: astore        8
      58: aload_3
      59: aload_0
      60: aload         7
      62: invokevirtual #8                  // Method java/lang/reflect/Method.getName:()Ljava/lang/String;
      65: aload         8
      67: invokestatic  #9                  // Method createValue:(Lorg/jboss/classfilewriter/constpool/ConstPool;Ljava/lang/String;Ljava/lang/Object;)Lorg/jboss/classfilewriter/annotations/AnnotationValue;
      70: invokeinterface #10,  2           // InterfaceMethod java/util/List.add:(Ljava/lang/Object;)Z
      75: pop
      76: iinc          6, 1
      79: goto          29
      82: goto          109
      85: astore        4
      87: new           #12                 // class java/lang/RuntimeException
      90: dup
      91: aload         4
      93: invokespecial #13                 // Method java/lang/RuntimeException."<init>":(Ljava/lang/Throwable;)V
      96: athrow
      97: astore        4
      99: new           #12                 // class java/lang/RuntimeException
     102: dup
     103: aload         4
     105: invokespecial #13                 // Method java/lang/RuntimeException."<init>":(Ljava/lang/Throwable;)V
     108: athrow
     109: new           #15                 // class org/jboss/classfilewriter/annotations/ClassAnnotation
     112: dup
     113: aload_0
     114: aload_2
     115: invokevirtual #16                 // Method java/lang/Class.getName:()Ljava/lang/String;
     118: aload_3
     119: invokespecial #17                 // Method org/jboss/classfilewriter/annotations/ClassAnnotation."<init>":(Lorg/jboss/classfilewriter/constpool/ConstPool;Ljava/lang/String;Ljava/util/List;)V
     122: areturn
    Exception table:
       from    to  target type
          15    82    85   Class java/lang/IllegalArgumentException
          15    82    97   Class java/security/PrivilegedActionException

  public static org.jboss.classfilewriter.annotations.AnnotationValue createValue(org.jboss.classfilewriter.constpool.ConstPool, java.lang.String, java.lang.Object);
    Code:
       0: aload_2
       1: invokevirtual #18                 // Method java/lang/Object.getClass:()Ljava/lang/Class;
       4: astore_3
       5: aload_3
       6: ldc           #19                 // class java/lang/String
       8: if_acmpne     25
      11: new           #20                 // class org/jboss/classfilewriter/annotations/StringAnnotationValue
      14: dup
      15: aload_0
      16: aload_1
      17: aload_2
      18: checkcast     #19                 // class java/lang/String
      21: invokespecial #21                 // Method org/jboss/classfilewriter/annotations/StringAnnotationValue."<init>":(Lorg/jboss/classfilewriter/constpool/ConstPool;Ljava/lang/String;Ljava/lang/String;)V
      24: areturn
      25: aload_3
      26: getstatic     #22                 // Field java/lang/Integer.TYPE:Ljava/lang/Class;
      29: if_acmpeq     38
      32: aload_3
      33: ldc           #23                 // class java/lang/Integer
      35: if_acmpne     55
      38: new           #24                 // class org/jboss/classfilewriter/annotations/IntAnnotationValue
      41: dup
      42: aload_0
      43: aload_1
      44: aload_2
      45: checkcast     #23                 // class java/lang/Integer
      48: invokevirtual #25                 // Method java/lang/Integer.intValue:()I
      51: invokespecial #26                 // Method org/jboss/classfilewriter/annotations/IntAnnotationValue."<init>":(Lorg/jboss/classfilewriter/constpool/ConstPool;Ljava/lang/String;I)V
      54: areturn
      55: aload_3
      56: getstatic     #27                 // Field java/lang/Short.TYPE:Ljava/lang/Class;
      59: if_acmpeq     68
      62: aload_3
      63: ldc           #28                 // class java/lang/Short
      65: if_acmpne     85
      68: new           #29                 // class org/jboss/classfilewriter/annotations/ShortAnnotationValue
      71: dup
      72: aload_0
      73: aload_1
      74: aload_2
      75: checkcast     #28                 // class java/lang/Short
      78: invokevirtual #30                 // Method java/lang/Short.shortValue:()S
      81: invokespecial #31                 // Method org/jboss/classfilewriter/annotations/ShortAnnotationValue."<init>":(Lorg/jboss/classfilewriter/constpool/ConstPool;Ljava/lang/String;S)V
      84: areturn
      85: aload_3
      86: getstatic     #32                 // Field java/lang/Byte.TYPE:Ljava/lang/Class;
      89: if_acmpeq     98
      92: aload_3
      93: ldc           #33                 // class java/lang/Byte
      95: if_acmpne     115
      98: new           #34                 // class org/jboss/classfilewriter/annotations/ByteAnnotationValue
     101: dup
     102: aload_0
     103: aload_1
     104: aload_2
     105: checkcast     #33                 // class java/lang/Byte
     108: invokevirtual #35                 // Method java/lang/Byte.byteValue:()B
     111: invokespecial #36                 // Method org/jboss/classfilewriter/annotations/ByteAnnotationValue."<init>":(Lorg/jboss/classfilewriter/constpool/ConstPool;Ljava/lang/String;B)V
     114: areturn
     115: aload_3
     116: getstatic     #37                 // Field java/lang/Boolean.TYPE:Ljava/lang/Class;
     119: if_acmpeq     128
     122: aload_3
     123: ldc           #38                 // class java/lang/Boolean
     125: if_acmpne     145
     128: new           #39                 // class org/jboss/classfilewriter/annotations/BooleanAnnotationValue
     131: dup
     132: aload_0
     133: aload_1
     134: aload_2
     135: checkcast     #38                 // class java/lang/Boolean
     138: invokevirtual #40                 // Method java/lang/Boolean.booleanValue:()Z
     141: invokespecial #41                 // Method org/jboss/classfilewriter/annotations/BooleanAnnotationValue."<init>":(Lorg/jboss/classfilewriter/constpool/ConstPool;Ljava/lang/String;Z)V
     144: areturn
     145: aload_3
     146: getstatic     #42                 // Field java/lang/Character.TYPE:Ljava/lang/Class;
     149: if_acmpeq     158
     152: aload_3
     153: ldc           #43                 // class java/lang/Character
     155: if_acmpne     175
     158: new           #44                 // class org/jboss/classfilewriter/annotations/CharAnnotationValue
     161: dup
     162: aload_0
     163: aload_1
     164: aload_2
     165: checkcast     #43                 // class java/lang/Character
     168: invokevirtual #45                 // Method java/lang/Character.charValue:()C
     171: invokespecial #46                 // Method org/jboss/classfilewriter/annotations/CharAnnotationValue."<init>":(Lorg/jboss/classfilewriter/constpool/ConstPool;Ljava/lang/String;C)V
     174: areturn
     175: aload_3
     176: getstatic     #47                 // Field java/lang/Long.TYPE:Ljava/lang/Class;
     179: if_acmpeq     188
     182: aload_3
     183: ldc           #48                 // class java/lang/Long
     185: if_acmpne     205
     188: new           #49                 // class org/jboss/classfilewriter/annotations/LongAnnotationValue
     191: dup
     192: aload_0
     193: aload_1
     194: aload_2
     195: checkcast     #48                 // class java/lang/Long
     198: invokevirtual #50                 // Method java/lang/Long.longValue:()J
     201: invokespecial #51                 // Method org/jboss/classfilewriter/annotations/LongAnnotationValue."<init>":(Lorg/jboss/classfilewriter/constpool/ConstPool;Ljava/lang/String;J)V
     204: areturn
     205: aload_3
     206: getstatic     #52                 // Field java/lang/Float.TYPE:Ljava/lang/Class;
     209: if_acmpeq     218
     212: aload_3
     213: ldc           #53                 // class java/lang/Float
     215: if_acmpne     235
     218: new           #54                 // class org/jboss/classfilewriter/annotations/FloatAnnotationValue
     221: dup
     222: aload_0
     223: aload_1
     224: aload_2
     225: checkcast     #53                 // class java/lang/Float
     228: invokevirtual #55                 // Method java/lang/Float.floatValue:()F
     231: invokespecial #56                 // Method org/jboss/classfilewriter/annotations/FloatAnnotationValue."<init>":(Lorg/jboss/classfilewriter/constpool/ConstPool;Ljava/lang/String;F)V
     234: areturn
     235: aload_3
     236: getstatic     #57                 // Field java/lang/Double.TYPE:Ljava/lang/Class;
     239: if_acmpeq     248
     242: aload_3
     243: ldc           #58                 // class java/lang/Double
     245: if_acmpne     265
     248: new           #59                 // class org/jboss/classfilewriter/annotations/DoubleAnnotationValue
     251: dup
     252: aload_0
     253: aload_1
     254: aload_2
     255: checkcast     #58                 // class java/lang/Double
     258: invokevirtual #60                 // Method java/lang/Double.doubleValue:()D
     261: invokespecial #61                 // Method org/jboss/classfilewriter/annotations/DoubleAnnotationValue."<init>":(Lorg/jboss/classfilewriter/constpool/ConstPool;Ljava/lang/String;D)V
     264: areturn
     265: aload_3
     266: ldc           #62                 // class java/lang/Class
     268: if_acmpne     285
     271: new           #63                 // class org/jboss/classfilewriter/annotations/ClassAnnotationValue
     274: dup
     275: aload_0
     276: aload_1
     277: aload_2
     278: checkcast     #62                 // class java/lang/Class
     281: invokespecial #64                 // Method org/jboss/classfilewriter/annotations/ClassAnnotationValue."<init>":(Lorg/jboss/classfilewriter/constpool/ConstPool;Ljava/lang/String;Ljava/lang/Class;)V
     284: areturn
     285: aload_3
     286: invokevirtual #65                 // Method java/lang/Class.isEnum:()Z
     289: ifne          309
     292: aload_3
     293: invokevirtual #66                 // Method java/lang/Class.getEnclosingClass:()Ljava/lang/Class;
     296: ifnull        323
     299: aload_3
     300: invokevirtual #66                 // Method java/lang/Class.getEnclosingClass:()Ljava/lang/Class;
     303: invokevirtual #65                 // Method java/lang/Class.isEnum:()Z
     306: ifeq          323
     309: new           #67                 // class org/jboss/classfilewriter/annotations/EnumAnnotationValue
     312: dup
     313: aload_0
     314: aload_1
     315: aload_2
     316: checkcast     #68                 // class java/lang/Enum
     319: invokespecial #69                 // Method org/jboss/classfilewriter/annotations/EnumAnnotationValue."<init>":(Lorg/jboss/classfilewriter/constpool/ConstPool;Ljava/lang/String;Ljava/lang/Enum;)V
     322: areturn
     323: aload_2
     324: instanceof    #70                 // class java/lang/annotation/Annotation
     327: ifeq          348
     330: new           #71                 // class org/jboss/classfilewriter/annotations/AnnotationAnnotationValue
     333: dup
     334: aload_0
     335: aload_1
     336: aload_0
     337: aload_2
     338: checkcast     #70                 // class java/lang/annotation/Annotation
     341: invokestatic  #72                 // Method createAnnotation:(Lorg/jboss/classfilewriter/constpool/ConstPool;Ljava/lang/annotation/Annotation;)Lorg/jboss/classfilewriter/annotations/ClassAnnotation;
     344: invokespecial #73                 // Method org/jboss/classfilewriter/annotations/AnnotationAnnotationValue."<init>":(Lorg/jboss/classfilewriter/constpool/ConstPool;Ljava/lang/String;Lorg/jboss/classfilewriter/annotations/ClassAnnotation;)V
     347: areturn
     348: aload_3
     349: invokevirtual #74                 // Method java/lang/Class.isArray:()Z
     352: ifeq          417
     355: aload_2
     356: invokestatic  #75                 // Method java/lang/reflect/Array.getLength:(Ljava/lang/Object;)I
     359: istore        4
     361: new           #2                  // class java/util/ArrayList
     364: dup
     365: invokespecial #3                  // Method java/util/ArrayList."<init>":()V
     368: astore        5
     370: iconst_0
     371: istore        6
     373: iload         6
     375: iload         4
     377: if_icmpge     405
     380: aload         5
     382: aload_0
     383: aconst_null
     384: aload_2
     385: iload         6
     387: invokestatic  #76                 // Method java/lang/reflect/Array.get:(Ljava/lang/Object;I)Ljava/lang/Object;
     390: invokestatic  #9                  // Method createValue:(Lorg/jboss/classfilewriter/constpool/ConstPool;Ljava/lang/String;Ljava/lang/Object;)Lorg/jboss/classfilewriter/annotations/AnnotationValue;
     393: invokeinterface #10,  2           // InterfaceMethod java/util/List.add:(Ljava/lang/Object;)Z
     398: pop
     399: iinc          6, 1
     402: goto          373
     405: new           #77                 // class org/jboss/classfilewriter/annotations/ArrayAnnotationValue
     408: dup
     409: aload_0
     410: aload_1
     411: aload         5
     413: invokespecial #78                 // Method org/jboss/classfilewriter/annotations/ArrayAnnotationValue."<init>":(Lorg/jboss/classfilewriter/constpool/ConstPool;Ljava/lang/String;Ljava/util/List;)V
     416: areturn
     417: new           #12                 // class java/lang/RuntimeException
     420: dup
     421: new           #79                 // class java/lang/StringBuilder
     424: dup
     425: invokespecial #80                 // Method java/lang/StringBuilder."<init>":()V
     428: ldc           #81                 // String Invalid type for annotation value. Type:
     430: invokevirtual #82                 // Method java/lang/StringBuilder.append:(Ljava/lang/String;)Ljava/lang/StringBuilder;
     433: aload_3
     434: invokevirtual #83                 // Method java/lang/StringBuilder.append:(Ljava/lang/Object;)Ljava/lang/StringBuilder;
     437: ldc           #84                 // String  Value:
     439: invokevirtual #82                 // Method java/lang/StringBuilder.append:(Ljava/lang/String;)Ljava/lang/StringBuilder;
     442: aload_2
     443: invokevirtual #83                 // Method java/lang/StringBuilder.append:(Ljava/lang/Object;)Ljava/lang/StringBuilder;
     446: invokevirtual #85                 // Method java/lang/StringBuilder.toString:()Ljava/lang/String;
     449: invokespecial #86                 // Method java/lang/RuntimeException."<init>":(Ljava/lang/String;)V
     452: athrow

  private org.jboss.classfilewriter.annotations.AnnotationBuilder();
    Code:
       0: aload_0
       1: invokespecial #87                 // Method java/lang/Object."<init>":()V
       4: return
}
