Compiled from "ClassAnnotation.java"
public class org.jboss.classfilewriter.annotations.ClassAnnotation implements org.jboss.classfilewriter.WritableEntry {
  private final java.lang.String type;

  private final int typeIndex;

  private final java.util.List<org.jboss.classfilewriter.annotations.AnnotationValue> annotationValues;

  public org.jboss.classfilewriter.annotations.ClassAnnotation(org.jboss.classfilewriter.constpool.ConstPool, java.lang.String, java.util.List<org.jboss.classfilewriter.annotations.AnnotationValue>);
    Code:
       0: aload_0
       1: invokespecial #1                  // Method java/lang/Object."<init>":()V
       4: aload_0
       5: aload_2
       6: putfield      #2                  // Field type:Ljava/lang/String;
       9: aload_0
      10: aload_1
      11: new           #3                  // class java/lang/StringBuilder
      14: dup
      15: invokespecial #4                  // Method java/lang/StringBuilder."<init>":()V
      18: ldc           #5                  // String L
      20: invokevirtual #6                  // Method java/lang/StringBuilder.append:(Ljava/lang/String;)Ljava/lang/StringBuilder;
      23: aload_2
      24: ldc           #7                  // String .
      26: ldc           #8                  // String /
      28: invokevirtual #9                  // Method java/lang/String.replace:(Ljava/lang/CharSequence;Ljava/lang/CharSequence;)Ljava/lang/String;
      31: invokevirtual #6                  // Method java/lang/StringBuilder.append:(Ljava/lang/String;)Ljava/lang/StringBuilder;
      34: ldc           #10                 // String ;
      36: invokevirtual #6                  // Method java/lang/StringBuilder.append:(Ljava/lang/String;)Ljava/lang/StringBuilder;
      39: invokevirtual #11                 // Method java/lang/StringBuilder.toString:()Ljava/lang/String;
      42: invokevirtual #12                 // Method org/jboss/classfilewriter/constpool/ConstPool.addUtf8Entry:(Ljava/lang/String;)S
      45: putfield      #13                 // Field typeIndex:I
      48: aload_0
      49: new           #14                 // class java/util/ArrayList
      52: dup
      53: aload_3
      54: invokespecial #15                 // Method java/util/ArrayList."<init>":(Ljava/util/Collection;)V
      57: putfield      #16                 // Field annotationValues:Ljava/util/List;
      60: return

  public void write(org.jboss.classfilewriter.util.ByteArrayDataOutputStream) throws java.io.IOException;
    Code:
       0: aload_1
       1: aload_0
       2: getfield      #13                 // Field typeIndex:I
       5: invokevirtual #17                 // Method org/jboss/classfilewriter/util/ByteArrayDataOutputStream.writeShort:(I)V
       8: aload_1
       9: aload_0
      10: getfield      #16                 // Field annotationValues:Ljava/util/List;
      13: invokeinterface #18,  1           // InterfaceMethod java/util/List.size:()I
      18: invokevirtual #17                 // Method org/jboss/classfilewriter/util/ByteArrayDataOutputStream.writeShort:(I)V
      21: aload_0
      22: getfield      #16                 // Field annotationValues:Ljava/util/List;
      25: invokeinterface #19,  1           // InterfaceMethod java/util/List.iterator:()Ljava/util/Iterator;
      30: astore_2
      31: aload_2
      32: invokeinterface #20,  1           // InterfaceMethod java/util/Iterator.hasNext:()Z
      37: ifeq          58
      40: aload_2
      41: invokeinterface #21,  1           // InterfaceMethod java/util/Iterator.next:()Ljava/lang/Object;
      46: checkcast     #22                 // class org/jboss/classfilewriter/annotations/AnnotationValue
      49: astore_3
      50: aload_3
      51: aload_1
      52: invokevirtual #23                 // Method org/jboss/classfilewriter/annotations/AnnotationValue.write:(Lorg/jboss/classfilewriter/util/ByteArrayDataOutputStream;)V
      55: goto          31
      58: return

  public java.lang.String getType();
    Code:
       0: aload_0
       1: getfield      #2                  // Field type:Ljava/lang/String;
       4: areturn

  public java.util.List<org.jboss.classfilewriter.annotations.AnnotationValue> getAnnotationValues();
    Code:
       0: aload_0
       1: getfield      #16                 // Field annotationValues:Ljava/util/List;
       4: areturn
}
