Compiled from "MEXServerListener.java"
public class org.apache.cxf.ws.mex.MEXServerListener implements org.apache.cxf.endpoint.ServerLifeCycleListener {
  public org.apache.cxf.ws.mex.MEXServerListener();
    Code:
       0: aload_0
       1: invokespecial #1                  // Method java/lang/Object."<init>":()V
       4: return

  public void startServer(org.apache.cxf.endpoint.Server);
    Code:
       0: aload_1
       1: invokeinterface #2,  1            // InterfaceMethod org/apache/cxf/endpoint/Server.getEndpoint:()Lorg/apache/cxf/endpoint/Endpoint;
       6: invokeinterface #3,  1            // InterfaceMethod org/apache/cxf/endpoint/Endpoint.getBinding:()Lorg/apache/cxf/binding/Binding;
      11: instanceof    #4                  // class org/apache/cxf/binding/soap/SoapBinding
      14: ifeq          71
      17: aload_1
      18: invokeinterface #2,  1            // InterfaceMethod org/apache/cxf/endpoint/Server.getEndpoint:()Lorg/apache/cxf/endpoint/Endpoint;
      23: invokeinterface #5,  1            // InterfaceMethod org/apache/cxf/endpoint/Endpoint.getService:()Lorg/apache/cxf/service/Service;
      28: invokeinterface #6,  1            // InterfaceMethod org/apache/cxf/service/Service.getName:()Ljavax/xml/namespace/QName;
      33: astore_2
      34: aload_2
      35: invokevirtual #7                  // Method javax/xml/namespace/QName.getNamespaceURI:()Ljava/lang/String;
      38: ldc           #8                  // String http://mex.ws.cxf.apache.org/
      40: invokevirtual #9                  // Method java/lang/String.equals:(Ljava/lang/Object;)Z
      43: ifne          71
      46: aload_1
      47: invokeinterface #2,  1            // InterfaceMethod org/apache/cxf/endpoint/Server.getEndpoint:()Lorg/apache/cxf/endpoint/Endpoint;
      52: invokeinterface #10,  1           // InterfaceMethod org/apache/cxf/endpoint/Endpoint.getInInterceptors:()Ljava/util/List;
      57: new           #11                 // class org/apache/cxf/ws/mex/MEXInInterceptor
      60: dup
      61: aload_1
      62: invokespecial #12                 // Method org/apache/cxf/ws/mex/MEXInInterceptor."<init>":(Lorg/apache/cxf/endpoint/Server;)V
      65: invokeinterface #13,  2           // InterfaceMethod java/util/List.add:(Ljava/lang/Object;)Z
      70: pop
      71: return

  public void stopServer(org.apache.cxf.endpoint.Server);
    Code:
       0: return
}
