Compiled from "EndpointSliceFluentImpl.java"
public class io.fabric8.kubernetes.api.model.discovery.EndpointSliceFluentImpl$PortsNestedImpl<N> extends io.fabric8.kubernetes.api.model.discovery.EndpointPortFluentImpl<io.fabric8.kubernetes.api.model.discovery.EndpointSliceFluent$PortsNested<N>> implements io.fabric8.kubernetes.api.model.discovery.EndpointSliceFluent$PortsNested<N>, io.fabric8.kubernetes.api.builder.Nested<N> {
  private final io.fabric8.kubernetes.api.model.discovery.EndpointPortBuilder builder;

  private final int index;

  final io.fabric8.kubernetes.api.model.discovery.EndpointSliceFluentImpl this$0;

  io.fabric8.kubernetes.api.model.discovery.EndpointSliceFluentImpl$PortsNestedImpl(io.fabric8.kubernetes.api.model.discovery.EndpointSliceFluentImpl, int, io.fabric8.kubernetes.api.model.discovery.EndpointPort);
    Code:
       0: aload_0
       1: aload_1
       2: putfield      #1                  // Field this$0:Lio/fabric8/kubernetes/api/model/discovery/EndpointSliceFluentImpl;
       5: aload_0
       6: invokespecial #2                  // Method io/fabric8/kubernetes/api/model/discovery/EndpointPortFluentImpl."<init>":()V
       9: aload_0
      10: iload_2
      11: putfield      #3                  // Field index:I
      14: aload_0
      15: new           #4                  // class io/fabric8/kubernetes/api/model/discovery/EndpointPortBuilder
      18: dup
      19: aload_0
      20: aload_3
      21: invokespecial #5                  // Method io/fabric8/kubernetes/api/model/discovery/EndpointPortBuilder."<init>":(Lio/fabric8/kubernetes/api/model/discovery/EndpointPortFluent;Lio/fabric8/kubernetes/api/model/discovery/EndpointPort;)V
      24: putfield      #6                  // Field builder:Lio/fabric8/kubernetes/api/model/discovery/EndpointPortBuilder;
      27: return

  io.fabric8.kubernetes.api.model.discovery.EndpointSliceFluentImpl$PortsNestedImpl(io.fabric8.kubernetes.api.model.discovery.EndpointSliceFluentImpl);
    Code:
       0: aload_0
       1: aload_1
       2: putfield      #1                  // Field this$0:Lio/fabric8/kubernetes/api/model/discovery/EndpointSliceFluentImpl;
       5: aload_0
       6: invokespecial #2                  // Method io/fabric8/kubernetes/api/model/discovery/EndpointPortFluentImpl."<init>":()V
       9: aload_0
      10: iconst_m1
      11: putfield      #3                  // Field index:I
      14: aload_0
      15: new           #4                  // class io/fabric8/kubernetes/api/model/discovery/EndpointPortBuilder
      18: dup
      19: aload_0
      20: invokespecial #7                  // Method io/fabric8/kubernetes/api/model/discovery/EndpointPortBuilder."<init>":(Lio/fabric8/kubernetes/api/model/discovery/EndpointPortFluent;)V
      23: putfield      #6                  // Field builder:Lio/fabric8/kubernetes/api/model/discovery/EndpointPortBuilder;
      26: return

  public N and();
    Code:
       0: aload_0
       1: getfield      #1                  // Field this$0:Lio/fabric8/kubernetes/api/model/discovery/EndpointSliceFluentImpl;
       4: aload_0
       5: getfield      #3                  // Field index:I
       8: aload_0
       9: getfield      #6                  // Field builder:Lio/fabric8/kubernetes/api/model/discovery/EndpointPortBuilder;
      12: invokevirtual #8                  // Method io/fabric8/kubernetes/api/model/discovery/EndpointPortBuilder.build:()Lio/fabric8/kubernetes/api/model/discovery/EndpointPort;
      15: invokevirtual #9                  // Method io/fabric8/kubernetes/api/model/discovery/EndpointSliceFluentImpl.setToPorts:(ILio/fabric8/kubernetes/api/model/discovery/EndpointPort;)Lio/fabric8/kubernetes/api/model/discovery/EndpointSliceFluent;
      18: areturn

  public N endPort();
    Code:
       0: aload_0
       1: invokevirtual #10                 // Method and:()Ljava/lang/Object;
       4: areturn
}
