Compiled from "UsingList.java"
public class org.apache.jena.sparql.modify.UsingList {
  private java.util.List<org.apache.jena.graph.Node> using;

  private java.util.List<org.apache.jena.graph.Node> usingNamed;

  public org.apache.jena.sparql.modify.UsingList();
    Code:
       0: aload_0
       1: invokespecial #1                  // Method java/lang/Object."<init>":()V
       4: aload_0
       5: new           #2                  // class java/util/ArrayList
       8: dup
       9: invokespecial #3                  // Method java/util/ArrayList."<init>":()V
      12: putfield      #4                  // Field using:Ljava/util/List;
      15: aload_0
      16: new           #2                  // class java/util/ArrayList
      19: dup
      20: invokespecial #3                  // Method java/util/ArrayList."<init>":()V
      23: putfield      #5                  // Field usingNamed:Ljava/util/List;
      26: return

  public void addUsing(org.apache.jena.graph.Node);
    Code:
       0: aload_0
       1: getfield      #4                  // Field using:Ljava/util/List;
       4: aload_1
       5: invokeinterface #6,  2            // InterfaceMethod java/util/List.add:(Ljava/lang/Object;)Z
      10: pop
      11: return

  public void addAllUsing(java.util.Collection<org.apache.jena.graph.Node>);
    Code:
       0: aload_0
       1: getfield      #4                  // Field using:Ljava/util/List;
       4: aload_1
       5: invokeinterface #7,  2            // InterfaceMethod java/util/List.addAll:(Ljava/util/Collection;)Z
      10: pop
      11: return

  public void addUsingNamed(org.apache.jena.graph.Node);
    Code:
       0: aload_0
       1: getfield      #5                  // Field usingNamed:Ljava/util/List;
       4: aload_1
       5: invokeinterface #6,  2            // InterfaceMethod java/util/List.add:(Ljava/lang/Object;)Z
      10: pop
      11: return

  public void addAllUsingNamed(java.util.Collection<org.apache.jena.graph.Node>);
    Code:
       0: aload_0
       1: getfield      #5                  // Field usingNamed:Ljava/util/List;
       4: aload_1
       5: invokeinterface #7,  2            // InterfaceMethod java/util/List.addAll:(Ljava/util/Collection;)Z
      10: pop
      11: return

  public java.util.List<org.apache.jena.graph.Node> getUsing();
    Code:
       0: aload_0
       1: getfield      #4                  // Field using:Ljava/util/List;
       4: invokestatic  #8                  // Method java/util/Collections.unmodifiableList:(Ljava/util/List;)Ljava/util/List;
       7: areturn

  public java.util.List<org.apache.jena.graph.Node> getUsingNamed();
    Code:
       0: aload_0
       1: getfield      #5                  // Field usingNamed:Ljava/util/List;
       4: invokestatic  #8                  // Method java/util/Collections.unmodifiableList:(Ljava/util/List;)Ljava/util/List;
       7: areturn

  public boolean usingIsPresent();
    Code:
       0: aload_0
       1: getfield      #4                  // Field using:Ljava/util/List;
       4: invokeinterface #9,  1            // InterfaceMethod java/util/List.size:()I
       9: ifgt          24
      12: aload_0
      13: getfield      #5                  // Field usingNamed:Ljava/util/List;
      16: invokeinterface #9,  1            // InterfaceMethod java/util/List.size:()I
      21: ifle          28
      24: iconst_1
      25: goto          29
      28: iconst_0
      29: ireturn
}
