public class org.bouncycastle.pqc.jcajce.provider.mceliece.BCMcElieceCCA2PublicKey implements org.bouncycastle.crypto.CipherParameters,java.security.PublicKey {
  private static final long serialVersionUID;

  private java.lang.String oid;

  private int n;

  private int t;

  private org.bouncycastle.pqc.math.linearalgebra.GF2Matrix g;

  private org.bouncycastle.pqc.crypto.mceliece.McElieceCCA2Parameters McElieceCCA2Params;

  public org.bouncycastle.pqc.jcajce.provider.mceliece.BCMcElieceCCA2PublicKey(java.lang.String, int, int, org.bouncycastle.pqc.math.linearalgebra.GF2Matrix);
    Code:
       0: aload_0
       1: invokespecial #126                // Method java/lang/Object."<init>":()V
       4: aload_0
       5: aload_1
       6: putfield      #123                // Field oid:Ljava/lang/String;
       9: aload_0
      10: iload_2
      11: putfield      #121                // Field n:I
      14: aload_0
      15: iload_3
      16: putfield      #122                // Field t:I
      19: aload_0
      20: aload         4
      22: putfield      #125                // Field g:Lorg/bouncycastle/pqc/math/linearalgebra/GF2Matrix;
      25: return

  public org.bouncycastle.pqc.jcajce.provider.mceliece.BCMcElieceCCA2PublicKey(org.bouncycastle.pqc.jcajce.spec.McElieceCCA2PublicKeySpec);
    Code:
       0: aload_0
       1: aload_1
       2: invokevirtual #145                // Method org/bouncycastle/pqc/jcajce/spec/McElieceCCA2PublicKeySpec.getOIDString:()Ljava/lang/String;
       5: aload_1
       6: invokevirtual #143                // Method org/bouncycastle/pqc/jcajce/spec/McElieceCCA2PublicKeySpec.getN:()I
       9: aload_1
      10: invokevirtual #144                // Method org/bouncycastle/pqc/jcajce/spec/McElieceCCA2PublicKeySpec.getT:()I
      13: aload_1
      14: invokevirtual #146                // Method org/bouncycastle/pqc/jcajce/spec/McElieceCCA2PublicKeySpec.getMatrixG:()Lorg/bouncycastle/pqc/math/linearalgebra/GF2Matrix;
      17: invokespecial #142                // Method "<init>":(Ljava/lang/String;IILorg/bouncycastle/pqc/math/linearalgebra/GF2Matrix;)V
      20: return

  public org.bouncycastle.pqc.jcajce.provider.mceliece.BCMcElieceCCA2PublicKey(org.bouncycastle.pqc.crypto.mceliece.McElieceCCA2PublicKeyParameters);
    Code:
       0: aload_0
       1: aload_1
       2: invokevirtual #138                // Method org/bouncycastle/pqc/crypto/mceliece/McElieceCCA2PublicKeyParameters.getOIDString:()Ljava/lang/String;
       5: aload_1
       6: invokevirtual #136                // Method org/bouncycastle/pqc/crypto/mceliece/McElieceCCA2PublicKeyParameters.getN:()I
       9: aload_1
      10: invokevirtual #137                // Method org/bouncycastle/pqc/crypto/mceliece/McElieceCCA2PublicKeyParameters.getT:()I
      13: aload_1
      14: invokevirtual #140                // Method org/bouncycastle/pqc/crypto/mceliece/McElieceCCA2PublicKeyParameters.getMatrixG:()Lorg/bouncycastle/pqc/math/linearalgebra/GF2Matrix;
      17: invokespecial #142                // Method "<init>":(Ljava/lang/String;IILorg/bouncycastle/pqc/math/linearalgebra/GF2Matrix;)V
      20: aload_0
      21: aload_1
      22: invokevirtual #139                // Method org/bouncycastle/pqc/crypto/mceliece/McElieceCCA2PublicKeyParameters.getParameters:()Lorg/bouncycastle/pqc/crypto/mceliece/McElieceCCA2Parameters;
      25: putfield      #124                // Field McElieceCCA2Params:Lorg/bouncycastle/pqc/crypto/mceliece/McElieceCCA2Parameters;
      28: return

  public java.lang.String getAlgorithm();
    Code:
       0: ldc           #6                  // String McEliece
       2: areturn

  public int getN();
    Code:
       0: aload_0
       1: getfield      #121                // Field n:I
       4: ireturn

  public int getK();
    Code:
       0: aload_0
       1: getfield      #125                // Field g:Lorg/bouncycastle/pqc/math/linearalgebra/GF2Matrix;
       4: invokevirtual #147                // Method org/bouncycastle/pqc/math/linearalgebra/GF2Matrix.getNumRows:()I
       7: ireturn

  public int getT();
    Code:
       0: aload_0
       1: getfield      #122                // Field t:I
       4: ireturn

  public org.bouncycastle.pqc.math.linearalgebra.GF2Matrix getG();
    Code:
       0: aload_0
       1: getfield      #125                // Field g:Lorg/bouncycastle/pqc/math/linearalgebra/GF2Matrix;
       4: areturn

  public java.lang.String toString();
    Code:
       0: ldc           #7                  // String McEliecePublicKey:\n
       2: astore_1
       3: new           #64                 // class java/lang/StringBuilder
       6: dup
       7: invokespecial #127                // Method java/lang/StringBuilder."<init>":()V
      10: aload_1
      11: invokevirtual #130                // Method java/lang/StringBuilder.append:(Ljava/lang/String;)Ljava/lang/StringBuilder;
      14: ldc           #4                  // String  length of the code         :
      16: invokevirtual #130                // Method java/lang/StringBuilder.append:(Ljava/lang/String;)Ljava/lang/StringBuilder;
      19: aload_0
      20: getfield      #121                // Field n:I
      23: invokevirtual #129                // Method java/lang/StringBuilder.append:(I)Ljava/lang/StringBuilder;
      26: ldc           #1                  // String \n
      28: invokevirtual #130                // Method java/lang/StringBuilder.append:(Ljava/lang/String;)Ljava/lang/StringBuilder;
      31: invokevirtual #128                // Method java/lang/StringBuilder.toString:()Ljava/lang/String;
      34: astore_1
      35: new           #64                 // class java/lang/StringBuilder
      38: dup
      39: invokespecial #127                // Method java/lang/StringBuilder."<init>":()V
      42: aload_1
      43: invokevirtual #130                // Method java/lang/StringBuilder.append:(Ljava/lang/String;)Ljava/lang/StringBuilder;
      46: ldc           #2                  // String  error correction capability:
      48: invokevirtual #130                // Method java/lang/StringBuilder.append:(Ljava/lang/String;)Ljava/lang/StringBuilder;
      51: aload_0
      52: getfield      #122                // Field t:I
      55: invokevirtual #129                // Method java/lang/StringBuilder.append:(I)Ljava/lang/StringBuilder;
      58: ldc           #1                  // String \n
      60: invokevirtual #130                // Method java/lang/StringBuilder.append:(Ljava/lang/String;)Ljava/lang/StringBuilder;
      63: invokevirtual #128                // Method java/lang/StringBuilder.toString:()Ljava/lang/String;
      66: astore_1
      67: new           #64                 // class java/lang/StringBuilder
      70: dup
      71: invokespecial #127                // Method java/lang/StringBuilder."<init>":()V
      74: aload_1
      75: invokevirtual #130                // Method java/lang/StringBuilder.append:(Ljava/lang/String;)Ljava/lang/StringBuilder;
      78: ldc           #3                  // String  generator matrix           :
      80: invokevirtual #130                // Method java/lang/StringBuilder.append:(Ljava/lang/String;)Ljava/lang/StringBuilder;
      83: aload_0
      84: getfield      #125                // Field g:Lorg/bouncycastle/pqc/math/linearalgebra/GF2Matrix;
      87: invokevirtual #150                // Method org/bouncycastle/pqc/math/linearalgebra/GF2Matrix.toString:()Ljava/lang/String;
      90: invokevirtual #130                // Method java/lang/StringBuilder.append:(Ljava/lang/String;)Ljava/lang/StringBuilder;
      93: invokevirtual #128                // Method java/lang/StringBuilder.toString:()Ljava/lang/String;
      96: astore_1
      97: aload_1
      98: areturn

  public boolean equals(java.lang.Object);
    Code:
       0: aload_1
       1: ifnull        11
       4: aload_1
       5: instanceof    #73                 // class org/bouncycastle/pqc/jcajce/provider/mceliece/BCMcElieceCCA2PublicKey
       8: ifne          13
      11: iconst_0
      12: ireturn
      13: aload_1
      14: checkcast     #73                 // class org/bouncycastle/pqc/jcajce/provider/mceliece/BCMcElieceCCA2PublicKey
      17: astore_2
      18: aload_0
      19: getfield      #121                // Field n:I
      22: aload_2
      23: getfield      #121                // Field n:I
      26: if_icmpne     58
      29: aload_0
      30: getfield      #122                // Field t:I
      33: aload_2
      34: getfield      #122                // Field t:I
      37: if_icmpne     58
      40: aload_0
      41: getfield      #125                // Field g:Lorg/bouncycastle/pqc/math/linearalgebra/GF2Matrix;
      44: aload_2
      45: getfield      #125                // Field g:Lorg/bouncycastle/pqc/math/linearalgebra/GF2Matrix;
      48: invokevirtual #149                // Method org/bouncycastle/pqc/math/linearalgebra/GF2Matrix.equals:(Ljava/lang/Object;)Z
      51: ifeq          58
      54: iconst_1
      55: goto          59
      58: iconst_0
      59: ireturn

  public int hashCode();
    Code:
       0: aload_0
       1: getfield      #121                // Field n:I
       4: aload_0
       5: getfield      #122                // Field t:I
       8: iadd
       9: aload_0
      10: getfield      #125                // Field g:Lorg/bouncycastle/pqc/math/linearalgebra/GF2Matrix;
      13: invokevirtual #148                // Method org/bouncycastle/pqc/math/linearalgebra/GF2Matrix.hashCode:()I
      16: iadd
      17: ireturn

  public java.lang.String getOIDString();
    Code:
       0: aload_0
       1: getfield      #123                // Field oid:Ljava/lang/String;
       4: areturn

  protected org.bouncycastle.asn1.ASN1ObjectIdentifier getOID();
    Code:
       0: new           #66                 // class org/bouncycastle/asn1/ASN1ObjectIdentifier
       3: dup
       4: ldc           #5                  // String 1.3.6.1.4.1.8301.3.1.3.4.2
       6: invokespecial #131                // Method org/bouncycastle/asn1/ASN1ObjectIdentifier."<init>":(Ljava/lang/String;)V
       9: areturn

  protected org.bouncycastle.asn1.ASN1Primitive getAlgParams();
    Code:
       0: aconst_null
       1: areturn

  public byte[] getEncoded();
    Code:
       0: new           #71                 // class org/bouncycastle/pqc/asn1/McElieceCCA2PublicKey
       3: dup
       4: new           #66                 // class org/bouncycastle/asn1/ASN1ObjectIdentifier
       7: dup
       8: aload_0
       9: getfield      #123                // Field oid:Ljava/lang/String;
      12: invokespecial #131                // Method org/bouncycastle/asn1/ASN1ObjectIdentifier."<init>":(Ljava/lang/String;)V
      15: aload_0
      16: getfield      #121                // Field n:I
      19: aload_0
      20: getfield      #122                // Field t:I
      23: aload_0
      24: getfield      #125                // Field g:Lorg/bouncycastle/pqc/math/linearalgebra/GF2Matrix;
      27: invokespecial #135                // Method org/bouncycastle/pqc/asn1/McElieceCCA2PublicKey."<init>":(Lorg/bouncycastle/asn1/ASN1ObjectIdentifier;IILorg/bouncycastle/pqc/math/linearalgebra/GF2Matrix;)V
      30: astore_1
      31: new           #68                 // class org/bouncycastle/asn1/x509/AlgorithmIdentifier
      34: dup
      35: aload_0
      36: invokevirtual #141                // Method getOID:()Lorg/bouncycastle/asn1/ASN1ObjectIdentifier;
      39: getstatic     #120                // Field org/bouncycastle/asn1/DERNull.INSTANCE:Lorg/bouncycastle/asn1/DERNull;
      42: invokespecial #132                // Method org/bouncycastle/asn1/x509/AlgorithmIdentifier."<init>":(Lorg/bouncycastle/asn1/ASN1ObjectIdentifier;Lorg/bouncycastle/asn1/ASN1Encodable;)V
      45: astore_2
      46: new           #69                 // class org/bouncycastle/asn1/x509/SubjectPublicKeyInfo
      49: dup
      50: aload_2
      51: aload_1
      52: invokespecial #134                // Method org/bouncycastle/asn1/x509/SubjectPublicKeyInfo."<init>":(Lorg/bouncycastle/asn1/x509/AlgorithmIdentifier;Lorg/bouncycastle/asn1/ASN1Encodable;)V
      55: astore_3
      56: aload_3
      57: invokevirtual #133                // Method org/bouncycastle/asn1/x509/SubjectPublicKeyInfo.getEncoded:()[B
      60: areturn
      61: astore_3
      62: aconst_null
      63: areturn
    Exception table:
       from    to  target type
          46    60    61   Class java/io/IOException

  public java.lang.String getFormat();
    Code:
       0: aconst_null
       1: areturn

  public org.bouncycastle.pqc.crypto.mceliece.McElieceCCA2Parameters getMcElieceCCA2Parameters();
    Code:
       0: aload_0
       1: getfield      #124                // Field McElieceCCA2Params:Lorg/bouncycastle/pqc/crypto/mceliece/McElieceCCA2Parameters;
       4: areturn
}
