Compiled from "TurtleRDFGraphInserter.java"
public class org.apache.jena.n3.turtle.TurtleRDFGraphInserter implements org.apache.jena.n3.turtle.TurtleEventHandler {
  org.apache.jena.graph.Graph graph;

  public org.apache.jena.n3.turtle.TurtleRDFGraphInserter(org.apache.jena.graph.Graph);
    Code:
       0: aload_0
       1: invokespecial #1                  // Method java/lang/Object."<init>":()V
       4: aload_0
       5: aconst_null
       6: putfield      #2                  // Field graph:Lorg/apache/jena/graph/Graph;
       9: aload_0
      10: aload_1
      11: putfield      #2                  // Field graph:Lorg/apache/jena/graph/Graph;
      14: return

  public void triple(int, int, org.apache.jena.graph.Triple);
    Code:
       0: aload_3
       1: invokevirtual #3                  // Method org/apache/jena/graph/Triple.getSubject:()Lorg/apache/jena/graph/Node;
       4: astore        4
       6: aload_3
       7: invokevirtual #4                  // Method org/apache/jena/graph/Triple.getPredicate:()Lorg/apache/jena/graph/Node;
      10: astore        5
      12: aload_3
      13: invokevirtual #5                  // Method org/apache/jena/graph/Triple.getObject:()Lorg/apache/jena/graph/Node;
      16: astore        6
      18: aload         4
      20: invokevirtual #6                  // Method org/apache/jena/graph/Node.isURI:()Z
      23: ifne          75
      26: aload         4
      28: invokevirtual #7                  // Method org/apache/jena/graph/Node.isBlank:()Z
      31: ifne          75
      34: new           #8                  // class org/apache/jena/n3/turtle/TurtleParseException
      37: dup
      38: new           #9                  // class java/lang/StringBuilder
      41: dup
      42: invokespecial #10                 // Method java/lang/StringBuilder."<init>":()V
      45: ldc           #11                 // String [
      47: invokevirtual #12                 // Method java/lang/StringBuilder.append:(Ljava/lang/String;)Ljava/lang/StringBuilder;
      50: iload_1
      51: invokevirtual #13                 // Method java/lang/StringBuilder.append:(I)Ljava/lang/StringBuilder;
      54: ldc           #14                 // String ,
      56: invokevirtual #12                 // Method java/lang/StringBuilder.append:(Ljava/lang/String;)Ljava/lang/StringBuilder;
      59: iload_2
      60: invokevirtual #13                 // Method java/lang/StringBuilder.append:(I)Ljava/lang/StringBuilder;
      63: ldc           #15                 // String ] : Error: Subject is not a URI or blank node
      65: invokevirtual #12                 // Method java/lang/StringBuilder.append:(Ljava/lang/String;)Ljava/lang/StringBuilder;
      68: invokevirtual #16                 // Method java/lang/StringBuilder.toString:()Ljava/lang/String;
      71: invokespecial #17                 // Method org/apache/jena/n3/turtle/TurtleParseException."<init>":(Ljava/lang/String;)V
      74: athrow
      75: aload         5
      77: invokevirtual #6                  // Method org/apache/jena/graph/Node.isURI:()Z
      80: ifne          124
      83: new           #8                  // class org/apache/jena/n3/turtle/TurtleParseException
      86: dup
      87: new           #9                  // class java/lang/StringBuilder
      90: dup
      91: invokespecial #10                 // Method java/lang/StringBuilder."<init>":()V
      94: ldc           #11                 // String [
      96: invokevirtual #12                 // Method java/lang/StringBuilder.append:(Ljava/lang/String;)Ljava/lang/StringBuilder;
      99: iload_1
     100: invokevirtual #13                 // Method java/lang/StringBuilder.append:(I)Ljava/lang/StringBuilder;
     103: ldc           #14                 // String ,
     105: invokevirtual #12                 // Method java/lang/StringBuilder.append:(Ljava/lang/String;)Ljava/lang/StringBuilder;
     108: iload_2
     109: invokevirtual #13                 // Method java/lang/StringBuilder.append:(I)Ljava/lang/StringBuilder;
     112: ldc           #18                 // String ] : Error: Predicate is not a URI
     114: invokevirtual #12                 // Method java/lang/StringBuilder.append:(Ljava/lang/String;)Ljava/lang/StringBuilder;
     117: invokevirtual #16                 // Method java/lang/StringBuilder.toString:()Ljava/lang/String;
     120: invokespecial #17                 // Method org/apache/jena/n3/turtle/TurtleParseException."<init>":(Ljava/lang/String;)V
     123: athrow
     124: aload         6
     126: invokevirtual #6                  // Method org/apache/jena/graph/Node.isURI:()Z
     129: ifne          189
     132: aload         6
     134: invokevirtual #7                  // Method org/apache/jena/graph/Node.isBlank:()Z
     137: ifne          189
     140: aload         6
     142: invokevirtual #19                 // Method org/apache/jena/graph/Node.isLiteral:()Z
     145: ifne          189
     148: new           #8                  // class org/apache/jena/n3/turtle/TurtleParseException
     151: dup
     152: new           #9                  // class java/lang/StringBuilder
     155: dup
     156: invokespecial #10                 // Method java/lang/StringBuilder."<init>":()V
     159: ldc           #11                 // String [
     161: invokevirtual #12                 // Method java/lang/StringBuilder.append:(Ljava/lang/String;)Ljava/lang/StringBuilder;
     164: iload_1
     165: invokevirtual #13                 // Method java/lang/StringBuilder.append:(I)Ljava/lang/StringBuilder;
     168: ldc           #14                 // String ,
     170: invokevirtual #12                 // Method java/lang/StringBuilder.append:(Ljava/lang/String;)Ljava/lang/StringBuilder;
     173: iload_2
     174: invokevirtual #13                 // Method java/lang/StringBuilder.append:(I)Ljava/lang/StringBuilder;
     177: ldc           #20                 // String ] : Error: Object is not a URI, blank node or literal
     179: invokevirtual #12                 // Method java/lang/StringBuilder.append:(Ljava/lang/String;)Ljava/lang/StringBuilder;
     182: invokevirtual #16                 // Method java/lang/StringBuilder.toString:()Ljava/lang/String;
     185: invokespecial #17                 // Method org/apache/jena/n3/turtle/TurtleParseException."<init>":(Ljava/lang/String;)V
     188: athrow
     189: aload_0
     190: getfield      #2                  // Field graph:Lorg/apache/jena/graph/Graph;
     193: aload_3
     194: invokeinterface #21,  2           // InterfaceMethod org/apache/jena/graph/Graph.add:(Lorg/apache/jena/graph/Triple;)V
     199: return

  public void startFormula(int, int);
    Code:
       0: new           #8                  // class org/apache/jena/n3/turtle/TurtleParseException
       3: dup
       4: new           #9                  // class java/lang/StringBuilder
       7: dup
       8: invokespecial #10                 // Method java/lang/StringBuilder."<init>":()V
      11: ldc           #11                 // String [
      13: invokevirtual #12                 // Method java/lang/StringBuilder.append:(Ljava/lang/String;)Ljava/lang/StringBuilder;
      16: iload_1
      17: invokevirtual #13                 // Method java/lang/StringBuilder.append:(I)Ljava/lang/StringBuilder;
      20: ldc           #14                 // String ,
      22: invokevirtual #12                 // Method java/lang/StringBuilder.append:(Ljava/lang/String;)Ljava/lang/StringBuilder;
      25: iload_2
      26: invokevirtual #13                 // Method java/lang/StringBuilder.append:(I)Ljava/lang/StringBuilder;
      29: ldc           #22                 // String ] : Error: Formula found
      31: invokevirtual #12                 // Method java/lang/StringBuilder.append:(Ljava/lang/String;)Ljava/lang/StringBuilder;
      34: invokevirtual #16                 // Method java/lang/StringBuilder.toString:()Ljava/lang/String;
      37: invokespecial #17                 // Method org/apache/jena/n3/turtle/TurtleParseException."<init>":(Ljava/lang/String;)V
      40: athrow

  public void endFormula(int, int);
    Code:
       0: new           #8                  // class org/apache/jena/n3/turtle/TurtleParseException
       3: dup
       4: new           #9                  // class java/lang/StringBuilder
       7: dup
       8: invokespecial #10                 // Method java/lang/StringBuilder."<init>":()V
      11: ldc           #11                 // String [
      13: invokevirtual #12                 // Method java/lang/StringBuilder.append:(Ljava/lang/String;)Ljava/lang/StringBuilder;
      16: iload_1
      17: invokevirtual #13                 // Method java/lang/StringBuilder.append:(I)Ljava/lang/StringBuilder;
      20: ldc           #14                 // String ,
      22: invokevirtual #12                 // Method java/lang/StringBuilder.append:(Ljava/lang/String;)Ljava/lang/StringBuilder;
      25: iload_2
      26: invokevirtual #13                 // Method java/lang/StringBuilder.append:(I)Ljava/lang/StringBuilder;
      29: ldc           #22                 // String ] : Error: Formula found
      31: invokevirtual #12                 // Method java/lang/StringBuilder.append:(Ljava/lang/String;)Ljava/lang/StringBuilder;
      34: invokevirtual #16                 // Method java/lang/StringBuilder.toString:()Ljava/lang/String;
      37: invokespecial #17                 // Method org/apache/jena/n3/turtle/TurtleParseException."<init>":(Ljava/lang/String;)V
      40: athrow

  public void prefix(int, int, java.lang.String, java.lang.String);
    Code:
       0: aload_0
       1: getfield      #2                  // Field graph:Lorg/apache/jena/graph/Graph;
       4: invokeinterface #23,  1           // InterfaceMethod org/apache/jena/graph/Graph.getPrefixMapping:()Lorg/apache/jena/shared/PrefixMapping;
       9: aload_3
      10: aload         4
      12: invokeinterface #24,  3           // InterfaceMethod org/apache/jena/shared/PrefixMapping.setNsPrefix:(Ljava/lang/String;Ljava/lang/String;)Lorg/apache/jena/shared/PrefixMapping;
      17: pop
      18: return
}
