Compiled from "Scripts.scala"
public final class ammonite.main.Scripts$$anonfun$runScript$3$$anonfun$apply$3 extends scala.runtime.AbstractFunction1<ammonite.util.Imports, ammonite.util.Imports> implements scala.Serializable {
  public static final long serialVersionUID;

  public final ammonite.util.Imports apply(ammonite.util.Imports);
    Code:
       0: aload_1
       1: areturn

  public final java.lang.Object apply(java.lang.Object);
    Code:
       0: aload_0
       1: aload_1
       2: checkcast     #23                 // class ammonite/util/Imports
       5: invokevirtual #25                 // Method apply:(Lammonite/util/Imports;)Lammonite/util/Imports;
       8: areturn

  public ammonite.main.Scripts$$anonfun$runScript$3$$anonfun$apply$3(ammonite.main.Scripts$$anonfun$runScript$3);
    Code:
       0: aload_0
       1: invokespecial #32                 // Method scala/runtime/AbstractFunction1."<init>":()V
       4: return
}
