Compiled from "ConfigurableMapExpressionImpl.java"
class org.modelmapper.internal.ConfigurableMapExpressionImpl<S, D> implements org.modelmapper.builder.ConfigurableMapExpression<S, D> {
  org.modelmapper.internal.TypeMapImpl<S, D> typeMap;

  public org.modelmapper.internal.ConfigurableMapExpressionImpl(org.modelmapper.internal.TypeMapImpl<S, D>);
    Code:
       0: aload_0
       1: invokespecial #21                 // Method java/lang/Object."<init>":()V
       4: aload_0
       5: aload_1
       6: putfield      #23                 // Field typeMap:Lorg/modelmapper/internal/TypeMapImpl;
       9: return

  public org.modelmapper.builder.ReferenceMapExpression<S, D> using(org.modelmapper.Converter<?, ?>);
    Code:
       0: aload_1
       1: ldc           #30                 // String converter
       3: invokestatic  #36                 // Method org/modelmapper/internal/util/Assert.notNull:(Ljava/lang/Object;Ljava/lang/String;)Ljava/lang/Object;
       6: pop
       7: new           #10                 // class org/modelmapper/internal/ExplicitMappingBuilder$MappingOptions
      10: dup
      11: invokespecial #37                 // Method org/modelmapper/internal/ExplicitMappingBuilder$MappingOptions."<init>":()V
      14: astore_2
      15: aload_2
      16: aload_1
      17: putfield      #40                 // Field org/modelmapper/internal/ExplicitMappingBuilder$MappingOptions.converter:Lorg/modelmapper/Converter;
      20: new           #42                 // class org/modelmapper/internal/ReferenceMapExpressionImpl
      23: dup
      24: aload_0
      25: getfield      #23                 // Field typeMap:Lorg/modelmapper/internal/TypeMapImpl;
      28: aload_2
      29: invokespecial #45                 // Method org/modelmapper/internal/ReferenceMapExpressionImpl."<init>":(Lorg/modelmapper/internal/TypeMapImpl;Lorg/modelmapper/internal/ExplicitMappingBuilder$MappingOptions;)V
      32: areturn

  public org.modelmapper.builder.ReferenceMapExpression<S, D> with(org.modelmapper.Provider<?>);
    Code:
       0: aload_1
       1: ldc           #52                 // String provider
       3: invokestatic  #36                 // Method org/modelmapper/internal/util/Assert.notNull:(Ljava/lang/Object;Ljava/lang/String;)Ljava/lang/Object;
       6: pop
       7: new           #10                 // class org/modelmapper/internal/ExplicitMappingBuilder$MappingOptions
      10: dup
      11: invokespecial #37                 // Method org/modelmapper/internal/ExplicitMappingBuilder$MappingOptions."<init>":()V
      14: astore_2
      15: aload_2
      16: aload_1
      17: putfield      #55                 // Field org/modelmapper/internal/ExplicitMappingBuilder$MappingOptions.provider:Lorg/modelmapper/Provider;
      20: new           #42                 // class org/modelmapper/internal/ReferenceMapExpressionImpl
      23: dup
      24: aload_0
      25: getfield      #23                 // Field typeMap:Lorg/modelmapper/internal/TypeMapImpl;
      28: aload_2
      29: invokespecial #45                 // Method org/modelmapper/internal/ReferenceMapExpressionImpl."<init>":(Lorg/modelmapper/internal/TypeMapImpl;Lorg/modelmapper/internal/ExplicitMappingBuilder$MappingOptions;)V
      32: areturn

  public org.modelmapper.builder.ReferenceMapExpression<S, D> when(org.modelmapper.Condition<?, ?>);
    Code:
       0: aload_1
       1: ldc           #60                 // String condition
       3: invokestatic  #36                 // Method org/modelmapper/internal/util/Assert.notNull:(Ljava/lang/Object;Ljava/lang/String;)Ljava/lang/Object;
       6: pop
       7: new           #10                 // class org/modelmapper/internal/ExplicitMappingBuilder$MappingOptions
      10: dup
      11: invokespecial #37                 // Method org/modelmapper/internal/ExplicitMappingBuilder$MappingOptions."<init>":()V
      14: astore_2
      15: aload_2
      16: aload_1
      17: putfield      #63                 // Field org/modelmapper/internal/ExplicitMappingBuilder$MappingOptions.condition:Lorg/modelmapper/Condition;
      20: new           #42                 // class org/modelmapper/internal/ReferenceMapExpressionImpl
      23: dup
      24: aload_0
      25: getfield      #23                 // Field typeMap:Lorg/modelmapper/internal/TypeMapImpl;
      28: aload_2
      29: invokespecial #45                 // Method org/modelmapper/internal/ReferenceMapExpressionImpl."<init>":(Lorg/modelmapper/internal/TypeMapImpl;Lorg/modelmapper/internal/ExplicitMappingBuilder$MappingOptions;)V
      32: areturn

  public <V> void map(org.modelmapper.spi.SourceGetter<S>, org.modelmapper.spi.DestinationSetter<D, V>);
    Code:
       0: aload_1
       1: ldc           #68                 // String sourceGetter
       3: invokestatic  #36                 // Method org/modelmapper/internal/util/Assert.notNull:(Ljava/lang/Object;Ljava/lang/String;)Ljava/lang/Object;
       6: pop
       7: aload_2
       8: ldc           #70                 // String destinationSetter
      10: invokestatic  #36                 // Method org/modelmapper/internal/util/Assert.notNull:(Ljava/lang/Object;Ljava/lang/String;)Ljava/lang/Object;
      13: pop
      14: new           #42                 // class org/modelmapper/internal/ReferenceMapExpressionImpl
      17: dup
      18: aload_0
      19: getfield      #23                 // Field typeMap:Lorg/modelmapper/internal/TypeMapImpl;
      22: invokespecial #72                 // Method org/modelmapper/internal/ReferenceMapExpressionImpl."<init>":(Lorg/modelmapper/internal/TypeMapImpl;)V
      25: aload_1
      26: aload_2
      27: invokevirtual #74                 // Method org/modelmapper/internal/ReferenceMapExpressionImpl.map:(Lorg/modelmapper/spi/SourceGetter;Lorg/modelmapper/spi/DestinationSetter;)V
      30: return

  public <V> void skip(org.modelmapper.spi.DestinationSetter<D, V>);
    Code:
       0: aload_1
       1: ldc           #70                 // String destinationSetter
       3: invokestatic  #36                 // Method org/modelmapper/internal/util/Assert.notNull:(Ljava/lang/Object;Ljava/lang/String;)Ljava/lang/Object;
       6: pop
       7: new           #42                 // class org/modelmapper/internal/ReferenceMapExpressionImpl
      10: dup
      11: aload_0
      12: getfield      #23                 // Field typeMap:Lorg/modelmapper/internal/TypeMapImpl;
      15: invokespecial #72                 // Method org/modelmapper/internal/ReferenceMapExpressionImpl."<init>":(Lorg/modelmapper/internal/TypeMapImpl;)V
      18: aload_1
      19: invokevirtual #82                 // Method org/modelmapper/internal/ReferenceMapExpressionImpl.skip:(Lorg/modelmapper/spi/DestinationSetter;)V
      22: return
}
