Compiled from "Errors.java"
final class org.modelmapper.internal.Errors$3 extends org.modelmapper.internal.Errors$Converter<org.modelmapper.spi.PropertyInfo> {
  org.modelmapper.internal.Errors$3(java.lang.Class);
    Code:
       0: aload_0
       1: aload_1
       2: invokespecial #13                 // Method org/modelmapper/internal/Errors$Converter."<init>":(Ljava/lang/Class;)V
       5: return

  public java.lang.String toString(org.modelmapper.spi.PropertyInfo);
    Code:
       0: aload_1
       1: invokeinterface #26,  1           // InterfaceMethod org/modelmapper/spi/PropertyInfo.getMember:()Ljava/lang/reflect/Member;
       6: invokestatic  #31                 // Method org/modelmapper/internal/util/Types.toString:(Ljava/lang/reflect/Member;)Ljava/lang/String;
       9: areturn

  public java.lang.String toString(java.lang.Object);
    Code:
       0: aload_0
       1: aload_1
       2: checkcast     #22                 // class org/modelmapper/spi/PropertyInfo
       5: invokevirtual #36                 // Method toString:(Lorg/modelmapper/spi/PropertyInfo;)Ljava/lang/String;
       8: areturn
}
