Compiled from "ExplicitMappingVisitor.java"
class org.modelmapper.internal.ExplicitMappingVisitor$VisitedMapping {
  java.util.List<org.modelmapper.internal.Accessor> sourceAccessors;

  java.util.List<org.modelmapper.internal.Accessor> destinationAccessors;

  java.util.List<org.modelmapper.internal.Mutator> destinationMutators;

  org.modelmapper.internal.ExplicitMappingVisitor$VisitedMapping();
    Code:
       0: aload_0
       1: invokespecial #18                 // Method java/lang/Object."<init>":()V
       4: aload_0
       5: new           #20                 // class java/util/ArrayList
       8: dup
       9: invokespecial #21                 // Method java/util/ArrayList."<init>":()V
      12: putfield      #23                 // Field sourceAccessors:Ljava/util/List;
      15: aload_0
      16: new           #20                 // class java/util/ArrayList
      19: dup
      20: invokespecial #21                 // Method java/util/ArrayList."<init>":()V
      23: putfield      #25                 // Field destinationAccessors:Ljava/util/List;
      26: aload_0
      27: new           #20                 // class java/util/ArrayList
      30: dup
      31: invokespecial #21                 // Method java/util/ArrayList."<init>":()V
      34: putfield      #27                 // Field destinationMutators:Ljava/util/List;
      37: return
}
