Compiled from "TypeMapImpl.java"
final class org.modelmapper.internal.TypeMapImpl$PathProperty {
  java.lang.String path;

  org.modelmapper.internal.Mutator mutator;

  private org.modelmapper.internal.TypeMapImpl$PathProperty(java.lang.String, org.modelmapper.internal.Mutator);
    Code:
       0: aload_0
       1: invokespecial #19                 // Method java/lang/Object."<init>":()V
       4: aload_0
       5: aload_1
       6: putfield      #21                 // Field path:Ljava/lang/String;
       9: aload_0
      10: aload_2
      11: putfield      #23                 // Field mutator:Lorg/modelmapper/internal/Mutator;
      14: return

  org.modelmapper.internal.TypeMapImpl$PathProperty(java.lang.String, org.modelmapper.internal.Mutator, org.modelmapper.internal.TypeMapImpl$1);
    Code:
       0: aload_0
       1: aload_1
       2: aload_2
       3: invokespecial #28                 // Method "<init>":(Ljava/lang/String;Lorg/modelmapper/internal/Mutator;)V
       6: return
}
