Compiled from "AbstractLobCreator.java"
public abstract class org.hibernate.engine.jdbc.AbstractLobCreator implements org.hibernate.engine.jdbc.LobCreator {
  public org.hibernate.engine.jdbc.AbstractLobCreator();
    Code:
       0: aload_0
       1: invokespecial #1                  // Method java/lang/Object."<init>":()V
       4: return

  public java.sql.Blob wrap(java.sql.Blob);
    Code:
       0: aload_1
       1: invokestatic  #2                  // Method org/hibernate/engine/jdbc/SerializableBlobProxy.generateProxy:(Ljava/sql/Blob;)Ljava/sql/Blob;
       4: areturn

  public java.sql.Clob wrap(java.sql.Clob);
    Code:
       0: ldc           #3                  // class java/sql/NClob
       2: aload_1
       3: invokevirtual #4                  // Method java/lang/Class.isInstance:(Ljava/lang/Object;)Z
       6: ifeq          18
       9: aload_0
      10: aload_1
      11: checkcast     #3                  // class java/sql/NClob
      14: invokevirtual #5                  // Method wrap:(Ljava/sql/NClob;)Ljava/sql/NClob;
      17: areturn
      18: aload_1
      19: invokestatic  #6                  // Method org/hibernate/engine/jdbc/SerializableClobProxy.generateProxy:(Ljava/sql/Clob;)Ljava/sql/Clob;
      22: areturn

  public java.sql.NClob wrap(java.sql.NClob);
    Code:
       0: aload_1
       1: invokestatic  #7                  // Method org/hibernate/engine/jdbc/SerializableNClobProxy.generateProxy:(Ljava/sql/NClob;)Ljava/sql/NClob;
       4: areturn
}
