public class org.bouncycastle.tsp.TimeStampTokenInfo {
  org.bouncycastle.asn1.tsp.TSTInfo tstInfo;

  java.util.Date genTime;

  org.bouncycastle.tsp.TimeStampTokenInfo(org.bouncycastle.asn1.tsp.TSTInfo) throws org.bouncycastle.tsp.TSPException, java.io.IOException;
    Code:
       0: aload_0
       1: invokespecial #93                 // Method java/lang/Object."<init>":()V
       4: aload_0
       5: aload_1
       6: putfield      #92                 // Field tstInfo:Lorg/bouncycastle/asn1/tsp/TSTInfo;
       9: aload_0
      10: aload_1
      11: invokevirtual #101                // Method org/bouncycastle/asn1/tsp/TSTInfo.getGenTime:()Lorg/bouncycastle/asn1/ASN1GeneralizedTime;
      14: invokevirtual #95                 // Method org/bouncycastle/asn1/ASN1GeneralizedTime.getDate:()Ljava/util/Date;
      17: putfield      #91                 // Field genTime:Ljava/util/Date;
      20: goto          34
      23: astore_2
      24: new           #52                 // class org/bouncycastle/tsp/TSPException
      27: dup
      28: ldc           #1                  // String unable to parse genTime field
      30: invokespecial #110                // Method org/bouncycastle/tsp/TSPException."<init>":(Ljava/lang/String;)V
      33: athrow
      34: return
    Exception table:
       from    to  target type
           9    20    23   Class java/text/ParseException

  public boolean isOrdered();
    Code:
       0: aload_0
       1: getfield      #92                 // Field tstInfo:Lorg/bouncycastle/asn1/tsp/TSTInfo;
       4: invokevirtual #100                // Method org/bouncycastle/asn1/tsp/TSTInfo.getOrdering:()Lorg/bouncycastle/asn1/ASN1Boolean;
       7: invokevirtual #94                 // Method org/bouncycastle/asn1/ASN1Boolean.isTrue:()Z
      10: ireturn

  public org.bouncycastle.asn1.tsp.Accuracy getAccuracy();
    Code:
       0: aload_0
       1: getfield      #92                 // Field tstInfo:Lorg/bouncycastle/asn1/tsp/TSTInfo;
       4: invokevirtual #105                // Method org/bouncycastle/asn1/tsp/TSTInfo.getAccuracy:()Lorg/bouncycastle/asn1/tsp/Accuracy;
       7: areturn

  public java.util.Date getGenTime();
    Code:
       0: aload_0
       1: getfield      #91                 // Field genTime:Ljava/util/Date;
       4: areturn

  public org.bouncycastle.tsp.GenTimeAccuracy getGenTimeAccuracy();
    Code:
       0: aload_0
       1: invokevirtual #111                // Method getAccuracy:()Lorg/bouncycastle/asn1/tsp/Accuracy;
       4: ifnull        19
       7: new           #51                 // class org/bouncycastle/tsp/GenTimeAccuracy
      10: dup
      11: aload_0
      12: invokevirtual #111                // Method getAccuracy:()Lorg/bouncycastle/asn1/tsp/Accuracy;
      15: invokespecial #109                // Method org/bouncycastle/tsp/GenTimeAccuracy."<init>":(Lorg/bouncycastle/asn1/tsp/Accuracy;)V
      18: areturn
      19: aconst_null
      20: areturn

  public org.bouncycastle.asn1.ASN1ObjectIdentifier getPolicy();
    Code:
       0: aload_0
       1: getfield      #92                 // Field tstInfo:Lorg/bouncycastle/asn1/tsp/TSTInfo;
       4: invokevirtual #104                // Method org/bouncycastle/asn1/tsp/TSTInfo.getPolicy:()Lorg/bouncycastle/asn1/ASN1ObjectIdentifier;
       7: areturn

  public java.math.BigInteger getSerialNumber();
    Code:
       0: aload_0
       1: getfield      #92                 // Field tstInfo:Lorg/bouncycastle/asn1/tsp/TSTInfo;
       4: invokevirtual #103                // Method org/bouncycastle/asn1/tsp/TSTInfo.getSerialNumber:()Lorg/bouncycastle/asn1/ASN1Integer;
       7: invokevirtual #96                 // Method org/bouncycastle/asn1/ASN1Integer.getValue:()Ljava/math/BigInteger;
      10: areturn

  public org.bouncycastle.asn1.x509.GeneralName getTsa();
    Code:
       0: aload_0
       1: getfield      #92                 // Field tstInfo:Lorg/bouncycastle/asn1/tsp/TSTInfo;
       4: invokevirtual #107                // Method org/bouncycastle/asn1/tsp/TSTInfo.getTsa:()Lorg/bouncycastle/asn1/x509/GeneralName;
       7: areturn

  public java.math.BigInteger getNonce();
    Code:
       0: aload_0
       1: getfield      #92                 // Field tstInfo:Lorg/bouncycastle/asn1/tsp/TSTInfo;
       4: invokevirtual #102                // Method org/bouncycastle/asn1/tsp/TSTInfo.getNonce:()Lorg/bouncycastle/asn1/ASN1Integer;
       7: ifnull        21
      10: aload_0
      11: getfield      #92                 // Field tstInfo:Lorg/bouncycastle/asn1/tsp/TSTInfo;
      14: invokevirtual #102                // Method org/bouncycastle/asn1/tsp/TSTInfo.getNonce:()Lorg/bouncycastle/asn1/ASN1Integer;
      17: invokevirtual #96                 // Method org/bouncycastle/asn1/ASN1Integer.getValue:()Ljava/math/BigInteger;
      20: areturn
      21: aconst_null
      22: areturn

  public org.bouncycastle.asn1.x509.AlgorithmIdentifier getHashAlgorithm();
    Code:
       0: aload_0
       1: getfield      #92                 // Field tstInfo:Lorg/bouncycastle/asn1/tsp/TSTInfo;
       4: invokevirtual #106                // Method org/bouncycastle/asn1/tsp/TSTInfo.getMessageImprint:()Lorg/bouncycastle/asn1/tsp/MessageImprint;
       7: invokevirtual #98                 // Method org/bouncycastle/asn1/tsp/MessageImprint.getHashAlgorithm:()Lorg/bouncycastle/asn1/x509/AlgorithmIdentifier;
      10: areturn

  public org.bouncycastle.asn1.ASN1ObjectIdentifier getMessageImprintAlgOID();
    Code:
       0: aload_0
       1: getfield      #92                 // Field tstInfo:Lorg/bouncycastle/asn1/tsp/TSTInfo;
       4: invokevirtual #106                // Method org/bouncycastle/asn1/tsp/TSTInfo.getMessageImprint:()Lorg/bouncycastle/asn1/tsp/MessageImprint;
       7: invokevirtual #98                 // Method org/bouncycastle/asn1/tsp/MessageImprint.getHashAlgorithm:()Lorg/bouncycastle/asn1/x509/AlgorithmIdentifier;
      10: invokevirtual #108                // Method org/bouncycastle/asn1/x509/AlgorithmIdentifier.getAlgorithm:()Lorg/bouncycastle/asn1/ASN1ObjectIdentifier;
      13: areturn

  public byte[] getMessageImprintDigest();
    Code:
       0: aload_0
       1: getfield      #92                 // Field tstInfo:Lorg/bouncycastle/asn1/tsp/TSTInfo;
       4: invokevirtual #106                // Method org/bouncycastle/asn1/tsp/TSTInfo.getMessageImprint:()Lorg/bouncycastle/asn1/tsp/MessageImprint;
       7: invokevirtual #97                 // Method org/bouncycastle/asn1/tsp/MessageImprint.getHashedMessage:()[B
      10: areturn

  public byte[] getEncoded() throws java.io.IOException;
    Code:
       0: aload_0
       1: getfield      #92                 // Field tstInfo:Lorg/bouncycastle/asn1/tsp/TSTInfo;
       4: invokevirtual #99                 // Method org/bouncycastle/asn1/tsp/TSTInfo.getEncoded:()[B
       7: areturn

  public org.bouncycastle.asn1.tsp.TSTInfo toTSTInfo();
    Code:
       0: aload_0
       1: getfield      #92                 // Field tstInfo:Lorg/bouncycastle/asn1/tsp/TSTInfo;
       4: areturn

  public org.bouncycastle.asn1.tsp.TSTInfo toASN1Structure();
    Code:
       0: aload_0
       1: getfield      #92                 // Field tstInfo:Lorg/bouncycastle/asn1/tsp/TSTInfo;
       4: areturn
}
