Compiled from "DescribeImagesRequest.java"
final class software.amazon.awssdk.services.ecr.model.DescribeImagesRequest$BuilderImpl extends software.amazon.awssdk.services.ecr.model.EcrRequest$BuilderImpl implements software.amazon.awssdk.services.ecr.model.DescribeImagesRequest$Builder {
  private java.lang.String registryId;

  private java.lang.String repositoryName;

  private java.util.List<software.amazon.awssdk.services.ecr.model.ImageIdentifier> imageIds;

  private java.lang.String nextToken;

  private java.lang.Integer maxResults;

  private software.amazon.awssdk.services.ecr.model.DescribeImagesFilter filter;

  private software.amazon.awssdk.services.ecr.model.DescribeImagesRequest$BuilderImpl();
    Code:
       0: aload_0
       1: invokespecial #9                  // Method software/amazon/awssdk/services/ecr/model/EcrRequest$BuilderImpl."<init>":()V
       4: aload_0
       5: invokestatic  #10                 // Method software/amazon/awssdk/core/util/DefaultSdkAutoConstructList.getInstance:()Lsoftware/amazon/awssdk/core/util/DefaultSdkAutoConstructList;
       8: putfield      #6                  // Field imageIds:Ljava/util/List;
      11: return

  private software.amazon.awssdk.services.ecr.model.DescribeImagesRequest$BuilderImpl(software.amazon.awssdk.services.ecr.model.DescribeImagesRequest);
    Code:
       0: aload_0
       1: aload_1
       2: invokespecial #11                 // Method software/amazon/awssdk/services/ecr/model/EcrRequest$BuilderImpl."<init>":(Lsoftware/amazon/awssdk/services/ecr/model/EcrRequest;)V
       5: aload_0
       6: invokestatic  #10                 // Method software/amazon/awssdk/core/util/DefaultSdkAutoConstructList.getInstance:()Lsoftware/amazon/awssdk/core/util/DefaultSdkAutoConstructList;
       9: putfield      #6                  // Field imageIds:Ljava/util/List;
      12: aload_0
      13: aload_1
      14: invokestatic  #12                 // Method software/amazon/awssdk/services/ecr/model/DescribeImagesRequest.access$800:(Lsoftware/amazon/awssdk/services/ecr/model/DescribeImagesRequest;)Ljava/lang/String;
      17: invokevirtual #13                 // Method registryId:(Ljava/lang/String;)Lsoftware/amazon/awssdk/services/ecr/model/DescribeImagesRequest$Builder;
      20: pop
      21: aload_0
      22: aload_1
      23: invokestatic  #14                 // Method software/amazon/awssdk/services/ecr/model/DescribeImagesRequest.access$900:(Lsoftware/amazon/awssdk/services/ecr/model/DescribeImagesRequest;)Ljava/lang/String;
      26: invokevirtual #15                 // Method repositoryName:(Ljava/lang/String;)Lsoftware/amazon/awssdk/services/ecr/model/DescribeImagesRequest$Builder;
      29: pop
      30: aload_0
      31: aload_1
      32: invokestatic  #16                 // Method software/amazon/awssdk/services/ecr/model/DescribeImagesRequest.access$1000:(Lsoftware/amazon/awssdk/services/ecr/model/DescribeImagesRequest;)Ljava/util/List;
      35: invokevirtual #17                 // Method imageIds:(Ljava/util/Collection;)Lsoftware/amazon/awssdk/services/ecr/model/DescribeImagesRequest$Builder;
      38: pop
      39: aload_0
      40: aload_1
      41: invokestatic  #18                 // Method software/amazon/awssdk/services/ecr/model/DescribeImagesRequest.access$1100:(Lsoftware/amazon/awssdk/services/ecr/model/DescribeImagesRequest;)Ljava/lang/String;
      44: invokevirtual #19                 // Method nextToken:(Ljava/lang/String;)Lsoftware/amazon/awssdk/services/ecr/model/DescribeImagesRequest$Builder;
      47: pop
      48: aload_0
      49: aload_1
      50: invokestatic  #20                 // Method software/amazon/awssdk/services/ecr/model/DescribeImagesRequest.access$1200:(Lsoftware/amazon/awssdk/services/ecr/model/DescribeImagesRequest;)Ljava/lang/Integer;
      53: invokevirtual #21                 // Method maxResults:(Ljava/lang/Integer;)Lsoftware/amazon/awssdk/services/ecr/model/DescribeImagesRequest$Builder;
      56: pop
      57: aload_0
      58: aload_1
      59: invokestatic  #22                 // Method software/amazon/awssdk/services/ecr/model/DescribeImagesRequest.access$1300:(Lsoftware/amazon/awssdk/services/ecr/model/DescribeImagesRequest;)Lsoftware/amazon/awssdk/services/ecr/model/DescribeImagesFilter;
      62: invokevirtual #23                 // Method filter:(Lsoftware/amazon/awssdk/services/ecr/model/DescribeImagesFilter;)Lsoftware/amazon/awssdk/services/ecr/model/DescribeImagesRequest$Builder;
      65: pop
      66: return

  public final java.lang.String getRegistryId();
    Code:
       0: aload_0
       1: getfield      #8                  // Field registryId:Ljava/lang/String;
       4: areturn

  public final void setRegistryId(java.lang.String);
    Code:
       0: aload_0
       1: aload_1
       2: putfield      #8                  // Field registryId:Ljava/lang/String;
       5: return

  public final software.amazon.awssdk.services.ecr.model.DescribeImagesRequest$Builder registryId(java.lang.String);
    Code:
       0: aload_0
       1: aload_1
       2: putfield      #8                  // Field registryId:Ljava/lang/String;
       5: aload_0
       6: areturn

  public final java.lang.String getRepositoryName();
    Code:
       0: aload_0
       1: getfield      #7                  // Field repositoryName:Ljava/lang/String;
       4: areturn

  public final void setRepositoryName(java.lang.String);
    Code:
       0: aload_0
       1: aload_1
       2: putfield      #7                  // Field repositoryName:Ljava/lang/String;
       5: return

  public final software.amazon.awssdk.services.ecr.model.DescribeImagesRequest$Builder repositoryName(java.lang.String);
    Code:
       0: aload_0
       1: aload_1
       2: putfield      #7                  // Field repositoryName:Ljava/lang/String;
       5: aload_0
       6: areturn

  public final java.util.List<software.amazon.awssdk.services.ecr.model.ImageIdentifier$Builder> getImageIds();
    Code:
       0: aload_0
       1: getfield      #6                  // Field imageIds:Ljava/util/List;
       4: invokestatic  #24                 // Method software/amazon/awssdk/services/ecr/model/ImageIdentifierListCopier.copyToBuilder:(Ljava/util/Collection;)Ljava/util/List;
       7: astore_1
       8: aload_1
       9: instanceof    #25                 // class software/amazon/awssdk/core/util/SdkAutoConstructList
      12: ifeq          17
      15: aconst_null
      16: areturn
      17: aload_1
      18: areturn

  public final void setImageIds(java.util.Collection<software.amazon.awssdk.services.ecr.model.ImageIdentifier$BuilderImpl>);
    Code:
       0: aload_0
       1: aload_1
       2: invokestatic  #26                 // Method software/amazon/awssdk/services/ecr/model/ImageIdentifierListCopier.copyFromBuilder:(Ljava/util/Collection;)Ljava/util/List;
       5: putfield      #6                  // Field imageIds:Ljava/util/List;
       8: return

  public final software.amazon.awssdk.services.ecr.model.DescribeImagesRequest$Builder imageIds(java.util.Collection<software.amazon.awssdk.services.ecr.model.ImageIdentifier>);
    Code:
       0: aload_0
       1: aload_1
       2: invokestatic  #27                 // Method software/amazon/awssdk/services/ecr/model/ImageIdentifierListCopier.copy:(Ljava/util/Collection;)Ljava/util/List;
       5: putfield      #6                  // Field imageIds:Ljava/util/List;
       8: aload_0
       9: areturn

  public final software.amazon.awssdk.services.ecr.model.DescribeImagesRequest$Builder imageIds(software.amazon.awssdk.services.ecr.model.ImageIdentifier...);
    Code:
       0: aload_0
       1: aload_1
       2: invokestatic  #28                 // Method java/util/Arrays.asList:([Ljava/lang/Object;)Ljava/util/List;
       5: invokevirtual #17                 // Method imageIds:(Ljava/util/Collection;)Lsoftware/amazon/awssdk/services/ecr/model/DescribeImagesRequest$Builder;
       8: pop
       9: aload_0
      10: areturn

  public final software.amazon.awssdk.services.ecr.model.DescribeImagesRequest$Builder imageIds(java.util.function.Consumer<software.amazon.awssdk.services.ecr.model.ImageIdentifier$Builder>...);
    Code:
       0: aload_0
       1: aload_1
       2: invokestatic  #29                 // InterfaceMethod java/util/stream/Stream.of:([Ljava/lang/Object;)Ljava/util/stream/Stream;
       5: invokedynamic #30,  0             // InvokeDynamic #0:apply:()Ljava/util/function/Function;
      10: invokeinterface #31,  2           // InterfaceMethod java/util/stream/Stream.map:(Ljava/util/function/Function;)Ljava/util/stream/Stream;
      15: invokestatic  #32                 // Method java/util/stream/Collectors.toList:()Ljava/util/stream/Collector;
      18: invokeinterface #33,  2           // InterfaceMethod java/util/stream/Stream.collect:(Ljava/util/stream/Collector;)Ljava/lang/Object;
      23: checkcast     #34                 // class java/util/Collection
      26: invokevirtual #17                 // Method imageIds:(Ljava/util/Collection;)Lsoftware/amazon/awssdk/services/ecr/model/DescribeImagesRequest$Builder;
      29: pop
      30: aload_0
      31: areturn

  public final java.lang.String getNextToken();
    Code:
       0: aload_0
       1: getfield      #5                  // Field nextToken:Ljava/lang/String;
       4: areturn

  public final void setNextToken(java.lang.String);
    Code:
       0: aload_0
       1: aload_1
       2: putfield      #5                  // Field nextToken:Ljava/lang/String;
       5: return

  public final software.amazon.awssdk.services.ecr.model.DescribeImagesRequest$Builder nextToken(java.lang.String);
    Code:
       0: aload_0
       1: aload_1
       2: putfield      #5                  // Field nextToken:Ljava/lang/String;
       5: aload_0
       6: areturn

  public final java.lang.Integer getMaxResults();
    Code:
       0: aload_0
       1: getfield      #4                  // Field maxResults:Ljava/lang/Integer;
       4: areturn

  public final void setMaxResults(java.lang.Integer);
    Code:
       0: aload_0
       1: aload_1
       2: putfield      #4                  // Field maxResults:Ljava/lang/Integer;
       5: return

  public final software.amazon.awssdk.services.ecr.model.DescribeImagesRequest$Builder maxResults(java.lang.Integer);
    Code:
       0: aload_0
       1: aload_1
       2: putfield      #4                  // Field maxResults:Ljava/lang/Integer;
       5: aload_0
       6: areturn

  public final software.amazon.awssdk.services.ecr.model.DescribeImagesFilter$Builder getFilter();
    Code:
       0: aload_0
       1: getfield      #3                  // Field filter:Lsoftware/amazon/awssdk/services/ecr/model/DescribeImagesFilter;
       4: ifnull        17
       7: aload_0
       8: getfield      #3                  // Field filter:Lsoftware/amazon/awssdk/services/ecr/model/DescribeImagesFilter;
      11: invokevirtual #35                 // Method software/amazon/awssdk/services/ecr/model/DescribeImagesFilter.toBuilder:()Lsoftware/amazon/awssdk/services/ecr/model/DescribeImagesFilter$Builder;
      14: goto          18
      17: aconst_null
      18: areturn

  public final void setFilter(software.amazon.awssdk.services.ecr.model.DescribeImagesFilter$BuilderImpl);
    Code:
       0: aload_0
       1: aload_1
       2: ifnull        12
       5: aload_1
       6: invokevirtual #36                 // Method software/amazon/awssdk/services/ecr/model/DescribeImagesFilter$BuilderImpl.build:()Lsoftware/amazon/awssdk/services/ecr/model/DescribeImagesFilter;
       9: goto          13
      12: aconst_null
      13: putfield      #3                  // Field filter:Lsoftware/amazon/awssdk/services/ecr/model/DescribeImagesFilter;
      16: return

  public final software.amazon.awssdk.services.ecr.model.DescribeImagesRequest$Builder filter(software.amazon.awssdk.services.ecr.model.DescribeImagesFilter);
    Code:
       0: aload_0
       1: aload_1
       2: putfield      #3                  // Field filter:Lsoftware/amazon/awssdk/services/ecr/model/DescribeImagesFilter;
       5: aload_0
       6: areturn

  public software.amazon.awssdk.services.ecr.model.DescribeImagesRequest$Builder overrideConfiguration(software.amazon.awssdk.awscore.AwsRequestOverrideConfiguration);
    Code:
       0: aload_0
       1: aload_1
       2: invokespecial #37                 // Method software/amazon/awssdk/services/ecr/model/EcrRequest$BuilderImpl.overrideConfiguration:(Lsoftware/amazon/awssdk/awscore/AwsRequestOverrideConfiguration;)Lsoftware/amazon/awssdk/awscore/AwsRequest$Builder;
       5: pop
       6: aload_0
       7: areturn

  public software.amazon.awssdk.services.ecr.model.DescribeImagesRequest$Builder overrideConfiguration(java.util.function.Consumer<software.amazon.awssdk.awscore.AwsRequestOverrideConfiguration$Builder>);
    Code:
       0: aload_0
       1: aload_1
       2: invokespecial #38                 // Method software/amazon/awssdk/services/ecr/model/EcrRequest$BuilderImpl.overrideConfiguration:(Ljava/util/function/Consumer;)Lsoftware/amazon/awssdk/awscore/AwsRequest$Builder;
       5: pop
       6: aload_0
       7: areturn

  public software.amazon.awssdk.services.ecr.model.DescribeImagesRequest build();
    Code:
       0: new           #39                 // class software/amazon/awssdk/services/ecr/model/DescribeImagesRequest
       3: dup
       4: aload_0
       5: aconst_null
       6: invokespecial #40                 // Method software/amazon/awssdk/services/ecr/model/DescribeImagesRequest."<init>":(Lsoftware/amazon/awssdk/services/ecr/model/DescribeImagesRequest$BuilderImpl;Lsoftware/amazon/awssdk/services/ecr/model/DescribeImagesRequest$1;)V
       9: areturn

  public java.util.List<software.amazon.awssdk.core.SdkField<?>> sdkFields();
    Code:
       0: invokestatic  #41                 // Method software/amazon/awssdk/services/ecr/model/DescribeImagesRequest.access$1500:()Ljava/util/List;
       3: areturn

  public software.amazon.awssdk.services.ecr.model.EcrRequest build();
    Code:
       0: aload_0
       1: invokevirtual #42                 // Method build:()Lsoftware/amazon/awssdk/services/ecr/model/DescribeImagesRequest;
       4: areturn

  public software.amazon.awssdk.awscore.AwsRequest build();
    Code:
       0: aload_0
       1: invokevirtual #42                 // Method build:()Lsoftware/amazon/awssdk/services/ecr/model/DescribeImagesRequest;
       4: areturn

  public software.amazon.awssdk.awscore.AwsRequest$Builder overrideConfiguration(java.util.function.Consumer);
    Code:
       0: aload_0
       1: aload_1
       2: invokevirtual #43                 // Method overrideConfiguration:(Ljava/util/function/Consumer;)Lsoftware/amazon/awssdk/services/ecr/model/DescribeImagesRequest$Builder;
       5: areturn

  public software.amazon.awssdk.awscore.AwsRequest$Builder overrideConfiguration(software.amazon.awssdk.awscore.AwsRequestOverrideConfiguration);
    Code:
       0: aload_0
       1: aload_1
       2: invokevirtual #44                 // Method overrideConfiguration:(Lsoftware/amazon/awssdk/awscore/AwsRequestOverrideConfiguration;)Lsoftware/amazon/awssdk/services/ecr/model/DescribeImagesRequest$Builder;
       5: areturn

  public software.amazon.awssdk.core.SdkRequest build();
    Code:
       0: aload_0
       1: invokevirtual #42                 // Method build:()Lsoftware/amazon/awssdk/services/ecr/model/DescribeImagesRequest;
       4: areturn

  public java.lang.Object build();
    Code:
       0: aload_0
       1: invokevirtual #42                 // Method build:()Lsoftware/amazon/awssdk/services/ecr/model/DescribeImagesRequest;
       4: areturn

  private static software.amazon.awssdk.services.ecr.model.ImageIdentifier lambda$imageIds$0(java.util.function.Consumer);
    Code:
       0: invokestatic  #45                 // Method software/amazon/awssdk/services/ecr/model/ImageIdentifier.builder:()Lsoftware/amazon/awssdk/services/ecr/model/ImageIdentifier$Builder;
       3: aload_0
       4: invokeinterface #46,  2           // InterfaceMethod software/amazon/awssdk/services/ecr/model/ImageIdentifier$Builder.applyMutation:(Ljava/util/function/Consumer;)Lsoftware/amazon/awssdk/utils/builder/SdkBuilder;
       9: checkcast     #47                 // class software/amazon/awssdk/services/ecr/model/ImageIdentifier$Builder
      12: invokeinterface #48,  1           // InterfaceMethod software/amazon/awssdk/services/ecr/model/ImageIdentifier$Builder.build:()Ljava/lang/Object;
      17: checkcast     #49                 // class software/amazon/awssdk/services/ecr/model/ImageIdentifier
      20: areturn

  static java.lang.String access$000(software.amazon.awssdk.services.ecr.model.DescribeImagesRequest$BuilderImpl);
    Code:
       0: aload_0
       1: getfield      #8                  // Field registryId:Ljava/lang/String;
       4: areturn

  static java.lang.String access$100(software.amazon.awssdk.services.ecr.model.DescribeImagesRequest$BuilderImpl);
    Code:
       0: aload_0
       1: getfield      #7                  // Field repositoryName:Ljava/lang/String;
       4: areturn

  static java.util.List access$200(software.amazon.awssdk.services.ecr.model.DescribeImagesRequest$BuilderImpl);
    Code:
       0: aload_0
       1: getfield      #6                  // Field imageIds:Ljava/util/List;
       4: areturn

  static java.lang.String access$300(software.amazon.awssdk.services.ecr.model.DescribeImagesRequest$BuilderImpl);
    Code:
       0: aload_0
       1: getfield      #5                  // Field nextToken:Ljava/lang/String;
       4: areturn

  static java.lang.Integer access$400(software.amazon.awssdk.services.ecr.model.DescribeImagesRequest$BuilderImpl);
    Code:
       0: aload_0
       1: getfield      #4                  // Field maxResults:Ljava/lang/Integer;
       4: areturn

  static software.amazon.awssdk.services.ecr.model.DescribeImagesFilter access$500(software.amazon.awssdk.services.ecr.model.DescribeImagesRequest$BuilderImpl);
    Code:
       0: aload_0
       1: getfield      #3                  // Field filter:Lsoftware/amazon/awssdk/services/ecr/model/DescribeImagesFilter;
       4: areturn

  software.amazon.awssdk.services.ecr.model.DescribeImagesRequest$BuilderImpl(software.amazon.awssdk.services.ecr.model.DescribeImagesRequest, software.amazon.awssdk.services.ecr.model.DescribeImagesRequest$1);
    Code:
       0: aload_0
       1: aload_1
       2: invokespecial #2                  // Method "<init>":(Lsoftware/amazon/awssdk/services/ecr/model/DescribeImagesRequest;)V
       5: return

  software.amazon.awssdk.services.ecr.model.DescribeImagesRequest$BuilderImpl(software.amazon.awssdk.services.ecr.model.DescribeImagesRequest$1);
    Code:
       0: aload_0
       1: invokespecial #1                  // Method "<init>":()V
       4: return
}
