Compiled from "TracingFilter.java"
class brave.servlet.TracingFilter$1 implements brave.propagation.Propagation$Getter<javax.servlet.http.HttpServletRequest, java.lang.String> {
  brave.servlet.TracingFilter$1();
    Code:
       0: aload_0
       1: invokespecial #17                 // Method java/lang/Object."<init>":()V
       4: return

  public java.lang.String get(javax.servlet.http.HttpServletRequest, java.lang.String);
    Code:
       0: aload_1
       1: aload_2
       2: invokeinterface #27,  2           // InterfaceMethod javax/servlet/http/HttpServletRequest.getHeader:(Ljava/lang/String;)Ljava/lang/String;
       7: areturn

  public java.lang.String toString();
    Code:
       0: ldc           #35                 // String HttpServletRequest::getHeader
       2: areturn

  public java.lang.String get(java.lang.Object, java.lang.Object);
    Code:
       0: aload_0
       1: aload_1
       2: checkcast     #23                 // class javax/servlet/http/HttpServletRequest
       5: aload_2
       6: checkcast     #38                 // class java/lang/String
       9: invokevirtual #40                 // Method get:(Ljavax/servlet/http/HttpServletRequest;Ljava/lang/String;)Ljava/lang/String;
      12: areturn
}
