Compiled from "AbstractOutboundGatewayParser.java"
public abstract class org.springframework.integration.config.xml.AbstractOutboundGatewayParser extends org.springframework.integration.config.xml.AbstractConsumerEndpointParser {
  public org.springframework.integration.config.xml.AbstractOutboundGatewayParser();
    Code:
       0: aload_0
       1: invokespecial #1                  // Method org/springframework/integration/config/xml/AbstractConsumerEndpointParser."<init>":()V
       4: return

  protected abstract java.lang.String getGatewayClassName(org.w3c.dom.Element);

  protected java.lang.String getInputChannelAttributeName();
    Code:
       0: ldc           #2                  // String request-channel
       2: areturn

  protected org.springframework.beans.factory.support.BeanDefinitionBuilder parseHandler(org.w3c.dom.Element, org.springframework.beans.factory.xml.ParserContext);
    Code:
       0: aload_0
       1: aload_1
       2: invokevirtual #3                  // Method getGatewayClassName:(Lorg/w3c/dom/Element;)Ljava/lang/String;
       5: invokestatic  #4                  // Method org/springframework/beans/factory/support/BeanDefinitionBuilder.genericBeanDefinition:(Ljava/lang/String;)Lorg/springframework/beans/factory/support/BeanDefinitionBuilder;
       8: astore_3
       9: aload_0
      10: aload_1
      11: aload_2
      12: invokevirtual #5                  // Method parseUrl:(Lorg/w3c/dom/Element;Lorg/springframework/beans/factory/xml/ParserContext;)Ljava/lang/String;
      15: astore        4
      17: aload_3
      18: aload         4
      20: invokevirtual #6                  // Method org/springframework/beans/factory/support/BeanDefinitionBuilder.addConstructorArgValue:(Ljava/lang/Object;)Lorg/springframework/beans/factory/support/BeanDefinitionBuilder;
      23: pop
      24: aload_1
      25: ldc           #7                  // String reply-channel
      27: invokeinterface #8,  2            // InterfaceMethod org/w3c/dom/Element.getAttribute:(Ljava/lang/String;)Ljava/lang/String;
      32: astore        5
      34: aload         5
      36: invokestatic  #9                  // Method org/springframework/util/StringUtils.hasText:(Ljava/lang/String;)Z
      39: ifeq          51
      42: aload_3
      43: ldc           #10                 // String replyChannel
      45: aload         5
      47: invokevirtual #11                 // Method org/springframework/beans/factory/support/BeanDefinitionBuilder.addPropertyReference:(Ljava/lang/String;Ljava/lang/String;)Lorg/springframework/beans/factory/support/BeanDefinitionBuilder;
      50: pop
      51: aload_3
      52: aload_1
      53: ldc           #12                 // String requires-reply
      55: invokestatic  #13                 // Method org/springframework/integration/config/xml/IntegrationNamespaceUtils.setValueIfAttributeDefined:(Lorg/springframework/beans/factory/support/BeanDefinitionBuilder;Lorg/w3c/dom/Element;Ljava/lang/String;)V
      58: aload_0
      59: aload_3
      60: aload_1
      61: aload_2
      62: invokevirtual #14                 // Method postProcessGateway:(Lorg/springframework/beans/factory/support/BeanDefinitionBuilder;Lorg/w3c/dom/Element;Lorg/springframework/beans/factory/xml/ParserContext;)V
      65: aload_3
      66: areturn

  protected java.lang.String parseUrl(org.w3c.dom.Element, org.springframework.beans.factory.xml.ParserContext);
    Code:
       0: aload_1
       1: ldc           #15                 // String url
       3: invokeinterface #8,  2            // InterfaceMethod org/w3c/dom/Element.getAttribute:(Ljava/lang/String;)Ljava/lang/String;
       8: astore_3
       9: aload_3
      10: invokestatic  #9                  // Method org/springframework/util/StringUtils.hasText:(Ljava/lang/String;)Z
      13: ifne          26
      16: aload_2
      17: invokevirtual #16                 // Method org/springframework/beans/factory/xml/ParserContext.getReaderContext:()Lorg/springframework/beans/factory/xml/XmlReaderContext;
      20: ldc           #17                 // String The \'url\' attribute is required.
      22: aload_1
      23: invokevirtual #18                 // Method org/springframework/beans/factory/xml/XmlReaderContext.error:(Ljava/lang/String;Ljava/lang/Object;)V
      26: aload_3
      27: areturn

  protected void postProcessGateway(org.springframework.beans.factory.support.BeanDefinitionBuilder, org.w3c.dom.Element, org.springframework.beans.factory.xml.ParserContext);
    Code:
       0: return
}
