Compiled from "HeaderEnricherParserSupport.java"
public abstract class org.springframework.integration.config.xml.HeaderEnricherParserSupport extends org.springframework.integration.config.xml.AbstractTransformerParser {
  private static final java.util.Map<java.lang.String, java.lang.String[][]> cannedHeaderElementExpressions;

  private final java.util.Map<java.lang.String, java.lang.String> elementToNameMap;

  private final java.util.Map<java.lang.String, java.lang.String> elementToTypeMap;

  public org.springframework.integration.config.xml.HeaderEnricherParserSupport();
    Code:
       0: aload_0
       1: invokespecial #1                  // Method org/springframework/integration/config/xml/AbstractTransformerParser."<init>":()V
       4: aload_0
       5: new           #2                  // class java/util/HashMap
       8: dup
       9: invokespecial #3                  // Method java/util/HashMap."<init>":()V
      12: putfield      #4                  // Field elementToNameMap:Ljava/util/Map;
      15: aload_0
      16: new           #2                  // class java/util/HashMap
      19: dup
      20: invokespecial #3                  // Method java/util/HashMap."<init>":()V
      23: putfield      #5                  // Field elementToTypeMap:Ljava/util/Map;
      26: return

  protected final java.lang.String getTransformerClassName();
    Code:
       0: ldc           #6                  // class org/springframework/integration/transformer/HeaderEnricher
       2: invokevirtual #7                  // Method java/lang/Class.getName:()Ljava/lang/String;
       5: areturn

  protected final void addElementToHeaderMapping(java.lang.String, java.lang.String);
    Code:
       0: aload_0
       1: aload_1
       2: aload_2
       3: aconst_null
       4: invokevirtual #8                  // Method addElementToHeaderMapping:(Ljava/lang/String;Ljava/lang/String;Ljava/lang/String;)V
       7: return

  protected final void addElementToHeaderMapping(java.lang.String, java.lang.String, java.lang.String);
    Code:
       0: aload_0
       1: getfield      #4                  // Field elementToNameMap:Ljava/util/Map;
       4: aload_1
       5: aload_2
       6: invokeinterface #9,  3            // InterfaceMethod java/util/Map.put:(Ljava/lang/Object;Ljava/lang/Object;)Ljava/lang/Object;
      11: pop
      12: aload_3
      13: ifnull        28
      16: aload_0
      17: getfield      #5                  // Field elementToTypeMap:Ljava/util/Map;
      20: aload_1
      21: aload_3
      22: invokeinterface #9,  3            // InterfaceMethod java/util/Map.put:(Ljava/lang/Object;Ljava/lang/Object;)Ljava/lang/Object;
      27: pop
      28: return

  protected void parseTransformer(org.w3c.dom.Element, org.springframework.beans.factory.xml.ParserContext, org.springframework.beans.factory.support.BeanDefinitionBuilder);
    Code:
       0: new           #10                 // class org/springframework/beans/factory/support/ManagedMap
       3: dup
       4: invokespecial #11                 // Method org/springframework/beans/factory/support/ManagedMap."<init>":()V
       7: astore        4
       9: aload_0
      10: aload_1
      11: aload         4
      13: aload_2
      14: invokevirtual #12                 // Method processHeaders:(Lorg/w3c/dom/Element;Lorg/springframework/beans/factory/support/ManagedMap;Lorg/springframework/beans/factory/xml/ParserContext;)V
      17: aload_3
      18: aload         4
      20: invokevirtual #13                 // Method org/springframework/beans/factory/support/BeanDefinitionBuilder.addConstructorArgValue:(Ljava/lang/Object;)Lorg/springframework/beans/factory/support/BeanDefinitionBuilder;
      23: pop
      24: aload_3
      25: aload_1
      26: ldc           #14                 // String default-overwrite
      28: invokestatic  #15                 // Method org/springframework/integration/config/xml/IntegrationNamespaceUtils.setValueIfAttributeDefined:(Lorg/springframework/beans/factory/support/BeanDefinitionBuilder;Lorg/w3c/dom/Element;Ljava/lang/String;)V
      31: aload_3
      32: aload_1
      33: ldc           #16                 // String should-skip-nulls
      35: invokestatic  #15                 // Method org/springframework/integration/config/xml/IntegrationNamespaceUtils.setValueIfAttributeDefined:(Lorg/springframework/beans/factory/support/BeanDefinitionBuilder;Lorg/w3c/dom/Element;Ljava/lang/String;)V
      38: aload_0
      39: aload_3
      40: aload_1
      41: aload_2
      42: invokevirtual #17                 // Method postProcessHeaderEnricher:(Lorg/springframework/beans/factory/support/BeanDefinitionBuilder;Lorg/w3c/dom/Element;Lorg/springframework/beans/factory/xml/ParserContext;)V
      45: return

  protected void processHeaders(org.w3c.dom.Element, org.springframework.beans.factory.support.ManagedMap<java.lang.String, java.lang.Object>, org.springframework.beans.factory.xml.ParserContext);
    Code:
       0: aload_1
       1: invokeinterface #18,  1           // InterfaceMethod org/w3c/dom/Element.getChildNodes:()Lorg/w3c/dom/NodeList;
       6: astore        4
       8: iconst_0
       9: istore        5
      11: iload         5
      13: aload         4
      15: invokeinterface #19,  1           // InterfaceMethod org/w3c/dom/NodeList.getLength:()I
      20: if_icmpge     392
      23: aload         4
      25: iload         5
      27: invokeinterface #20,  2           // InterfaceMethod org/w3c/dom/NodeList.item:(I)Lorg/w3c/dom/Node;
      32: astore        6
      34: aload         6
      36: invokeinterface #21,  1           // InterfaceMethod org/w3c/dom/Node.getNodeType:()S
      41: iconst_1
      42: if_icmpne     386
      45: aconst_null
      46: astore        7
      48: aload         6
      50: checkcast     #23                 // class org/w3c/dom/Element
      53: astore        8
      55: aload         6
      57: invokeinterface #24,  1           // InterfaceMethod org/w3c/dom/Node.getLocalName:()Ljava/lang/String;
      62: astore        9
      64: aconst_null
      65: astore        10
      67: aconst_null
      68: astore        11
      70: aload         8
      72: ldc           #25                 // String overwrite
      74: invokeinterface #26,  2           // InterfaceMethod org/w3c/dom/Element.getAttribute:(Ljava/lang/String;)Ljava/lang/String;
      79: astore        12
      81: ldc           #27                 // String header
      83: aload         9
      85: invokevirtual #28                 // Method java/lang/String.equals:(Ljava/lang/Object;)Z
      88: ifeq          105
      91: aload         8
      93: ldc           #30                 // String name
      95: invokeinterface #26,  2           // InterfaceMethod org/w3c/dom/Element.getAttribute:(Ljava/lang/String;)Ljava/lang/String;
     100: astore        7
     102: goto          200
     105: aload_0
     106: getfield      #4                  // Field elementToNameMap:Ljava/util/Map;
     109: aload         9
     111: invokeinterface #31,  2           // InterfaceMethod java/util/Map.get:(Ljava/lang/Object;)Ljava/lang/Object;
     116: checkcast     #32                 // class java/lang/String
     119: astore        7
     121: aload_0
     122: getfield      #5                  // Field elementToTypeMap:Ljava/util/Map;
     125: aload         9
     127: invokeinterface #31,  2           // InterfaceMethod java/util/Map.get:(Ljava/lang/Object;)Ljava/lang/Object;
     132: checkcast     #32                 // class java/lang/String
     135: astore        10
     137: aload         10
     139: ifnull        200
     142: aload         8
     144: ldc           #33                 // String type
     146: invokeinterface #26,  2           // InterfaceMethod org/w3c/dom/Element.getAttribute:(Ljava/lang/String;)Ljava/lang/String;
     151: invokestatic  #34                 // Method org/springframework/util/StringUtils.hasText:(Ljava/lang/String;)Z
     154: ifeq          200
     157: aload_3
     158: invokevirtual #35                 // Method org/springframework/beans/factory/xml/ParserContext.getReaderContext:()Lorg/springframework/beans/factory/xml/XmlReaderContext;
     161: new           #36                 // class java/lang/StringBuilder
     164: dup
     165: invokespecial #37                 // Method java/lang/StringBuilder."<init>":()V
     168: ldc           #38                 // String The
     170: invokevirtual #39                 // Method java/lang/StringBuilder.append:(Ljava/lang/String;)Ljava/lang/StringBuilder;
     173: aload         9
     175: invokevirtual #39                 // Method java/lang/StringBuilder.append:(Ljava/lang/String;)Ljava/lang/StringBuilder;
     178: ldc           #40                 // String  header does not accept a \'type\' attribute. The required type is [
     180: invokevirtual #39                 // Method java/lang/StringBuilder.append:(Ljava/lang/String;)Ljava/lang/StringBuilder;
     183: aload         10
     185: invokevirtual #39                 // Method java/lang/StringBuilder.append:(Ljava/lang/String;)Ljava/lang/StringBuilder;
     188: ldc           #41                 // String ]
     190: invokevirtual #39                 // Method java/lang/StringBuilder.append:(Ljava/lang/String;)Ljava/lang/StringBuilder;
     193: invokevirtual #42                 // Method java/lang/StringBuilder.toString:()Ljava/lang/String;
     196: aload_1
     197: invokevirtual #43                 // Method org/springframework/beans/factory/xml/XmlReaderContext.error:(Ljava/lang/String;Ljava/lang/Object;)V
     200: aload         10
     202: ifnonnull     216
     205: aload         8
     207: ldc           #33                 // String type
     209: invokeinterface #26,  2           // InterfaceMethod org/w3c/dom/Element.getAttribute:(Ljava/lang/String;)Ljava/lang/String;
     214: astore        10
     216: aload         7
     218: ifnonnull     370
     221: aload         8
     223: ldc           #44                 // String time-to-live-expression
     225: invokeinterface #26,  2           // InterfaceMethod org/w3c/dom/Element.getAttribute:(Ljava/lang/String;)Ljava/lang/String;
     230: astore        13
     232: getstatic     #45                 // Field cannedHeaderElementExpressions:Ljava/util/Map;
     235: aload         9
     237: invokeinterface #46,  2           // InterfaceMethod java/util/Map.containsKey:(Ljava/lang/Object;)Z
     242: ifeq          367
     245: iconst_0
     246: istore        14
     248: iload         14
     250: getstatic     #45                 // Field cannedHeaderElementExpressions:Ljava/util/Map;
     253: aload         9
     255: invokeinterface #31,  2           // InterfaceMethod java/util/Map.get:(Ljava/lang/Object;)Ljava/lang/Object;
     260: checkcast     #47                 // class "[[Ljava/lang/String;"
     263: arraylength
     264: if_icmpge     367
     267: getstatic     #45                 // Field cannedHeaderElementExpressions:Ljava/util/Map;
     270: aload         9
     272: invokeinterface #31,  2           // InterfaceMethod java/util/Map.get:(Ljava/lang/Object;)Ljava/lang/Object;
     277: checkcast     #47                 // class "[[Ljava/lang/String;"
     280: iload         14
     282: aaload
     283: iconst_0
     284: aaload
     285: astore        7
     287: getstatic     #45                 // Field cannedHeaderElementExpressions:Ljava/util/Map;
     290: aload         9
     292: invokeinterface #31,  2           // InterfaceMethod java/util/Map.get:(Ljava/lang/Object;)Ljava/lang/Object;
     297: checkcast     #47                 // class "[[Ljava/lang/String;"
     300: iload         14
     302: aaload
     303: iconst_1
     304: aaload
     305: astore        11
     307: aload         13
     309: invokestatic  #34                 // Method org/springframework/util/StringUtils.hasText:(Ljava/lang/String;)Z
     312: ifeq          329
     315: aload         11
     317: ldc           #48                 // String ####
     319: aload         13
     321: invokevirtual #49                 // Method java/lang/String.replace:(Ljava/lang/CharSequence;Ljava/lang/CharSequence;)Ljava/lang/String;
     324: astore        11
     326: goto          340
     329: aload         11
     331: ldc           #50                 // String , ####
     333: ldc           #51                 // String
     335: invokevirtual #49                 // Method java/lang/String.replace:(Ljava/lang/CharSequence;Ljava/lang/CharSequence;)Ljava/lang/String;
     338: astore        11
     340: ldc           #52                 // String true
     342: astore        12
     344: aload_0
     345: aload_1
     346: aload_2
     347: aload_3
     348: aload         7
     350: aload         8
     352: aload         10
     354: aload         11
     356: aload         12
     358: invokespecial #53                 // Method addHeader:(Lorg/w3c/dom/Element;Lorg/springframework/beans/factory/support/ManagedMap;Lorg/springframework/beans/factory/xml/ParserContext;Ljava/lang/String;Lorg/w3c/dom/Element;Ljava/lang/String;Ljava/lang/String;Ljava/lang/String;)V
     361: iinc          14, 1
     364: goto          248
     367: goto          386
     370: aload_0
     371: aload_1
     372: aload_2
     373: aload_3
     374: aload         7
     376: aload         8
     378: aload         10
     380: aconst_null
     381: aload         12
     383: invokespecial #53                 // Method addHeader:(Lorg/w3c/dom/Element;Lorg/springframework/beans/factory/support/ManagedMap;Lorg/springframework/beans/factory/xml/ParserContext;Ljava/lang/String;Lorg/w3c/dom/Element;Ljava/lang/String;Ljava/lang/String;Ljava/lang/String;)V
     386: iinc          5, 1
     389: goto          11
     392: return

  private void addHeader(org.w3c.dom.Element, org.springframework.beans.factory.support.ManagedMap<java.lang.String, java.lang.Object>, org.springframework.beans.factory.xml.ParserContext, java.lang.String, org.w3c.dom.Element, java.lang.String, java.lang.String, java.lang.String);
    Code:
       0: aload         5
       2: ldc           #54                 // String value
       4: invokeinterface #26,  2           // InterfaceMethod org/w3c/dom/Element.getAttribute:(Ljava/lang/String;)Ljava/lang/String;
       9: astore        9
      11: aload         5
      13: ldc           #56                 // String ref
      15: invokeinterface #26,  2           // InterfaceMethod org/w3c/dom/Element.getAttribute:(Ljava/lang/String;)Ljava/lang/String;
      20: astore        10
      22: aload         5
      24: ldc           #57                 // String method
      26: invokeinterface #26,  2           // InterfaceMethod org/w3c/dom/Element.getAttribute:(Ljava/lang/String;)Ljava/lang/String;
      31: astore        11
      33: aload         7
      35: astore        12
      37: aload         12
      39: ifnonnull     53
      42: aload         5
      44: ldc           #58                 // String expression
      46: invokeinterface #26,  2           // InterfaceMethod org/w3c/dom/Element.getAttribute:(Ljava/lang/String;)Ljava/lang/String;
      51: astore        12
      53: aconst_null
      54: astore        13
      56: aconst_null
      57: astore        14
      59: aconst_null
      60: astore        15
      62: aload         5
      64: invokestatic  #59                 // Method org/springframework/util/xml/DomUtils.getChildElements:(Lorg/w3c/dom/Element;)Ljava/util/List;
      67: astore        16
      69: aload         16
      71: invokeinterface #60,  1           // InterfaceMethod java/util/List.isEmpty:()Z
      76: ifne          174
      79: aload         16
      81: iconst_0
      82: invokeinterface #61,  2           // InterfaceMethod java/util/List.get:(I)Ljava/lang/Object;
      87: checkcast     #23                 // class org/w3c/dom/Element
      90: astore        17
      92: aload         17
      94: invokeinterface #62,  1           // InterfaceMethod org/w3c/dom/Element.getLocalName:()Ljava/lang/String;
      99: astore        18
     101: ldc           #63                 // String bean
     103: aload         18
     105: invokevirtual #28                 // Method java/lang/String.equals:(Ljava/lang/Object;)Z
     108: ifeq          118
     111: aload         17
     113: astore        13
     115: goto          149
     118: ldc           #64                 // String script
     120: aload         18
     122: invokevirtual #28                 // Method java/lang/String.equals:(Ljava/lang/Object;)Z
     125: ifeq          135
     128: aload         17
     130: astore        14
     132: goto          149
     135: ldc           #58                 // String expression
     137: aload         18
     139: invokevirtual #28                 // Method java/lang/String.equals:(Ljava/lang/Object;)Z
     142: ifeq          149
     145: aload         17
     147: astore        15
     149: aload         13
     151: ifnonnull     174
     154: aload         14
     156: ifnonnull     174
     159: aload         15
     161: ifnonnull     174
     164: aload_3
     165: invokevirtual #35                 // Method org/springframework/beans/factory/xml/ParserContext.getReaderContext:()Lorg/springframework/beans/factory/xml/XmlReaderContext;
     168: ldc           #65                 // String Only \'bean\', \'script\' or \'expression\' can be defined as a sub-element
     170: aload_1
     171: invokevirtual #43                 // Method org/springframework/beans/factory/xml/XmlReaderContext.error:(Ljava/lang/String;Ljava/lang/Object;)V
     174: aload         12
     176: invokestatic  #34                 // Method org/springframework/util/StringUtils.hasText:(Ljava/lang/String;)Z
     179: ifeq          197
     182: aload         15
     184: ifnull        197
     187: aload_3
     188: invokevirtual #35                 // Method org/springframework/beans/factory/xml/ParserContext.getReaderContext:()Lorg/springframework/beans/factory/xml/XmlReaderContext;
     191: ldc           #66                 // String The \'expression\' attribute and sub-element are mutually exclusive
     193: aload_1
     194: invokevirtual #43                 // Method org/springframework/beans/factory/xml/XmlReaderContext.error:(Ljava/lang/String;Ljava/lang/Object;)V
     197: aload         9
     199: invokestatic  #34                 // Method org/springframework/util/StringUtils.hasText:(Ljava/lang/String;)Z
     202: istore        17
     204: aload         10
     206: invokestatic  #34                 // Method org/springframework/util/StringUtils.hasText:(Ljava/lang/String;)Z
     209: istore        18
     211: aload         11
     213: invokestatic  #34                 // Method org/springframework/util/StringUtils.hasText:(Ljava/lang/String;)Z
     216: istore        19
     218: aload         12
     220: invokestatic  #34                 // Method org/springframework/util/StringUtils.hasText:(Ljava/lang/String;)Z
     223: ifne          231
     226: aload         15
     228: ifnull        235
     231: iconst_1
     232: goto          236
     235: iconst_0
     236: istore        20
     238: aload         14
     240: ifnull        247
     243: iconst_1
     244: goto          248
     247: iconst_0
     248: istore        21
     250: aconst_null
     251: astore        22
     253: aload         13
     255: ifnull        275
     258: aload_3
     259: invokevirtual #67                 // Method org/springframework/beans/factory/xml/ParserContext.getDelegate:()Lorg/springframework/beans/factory/xml/BeanDefinitionParserDelegate;
     262: aload         13
     264: invokevirtual #68                 // Method org/springframework/beans/factory/xml/BeanDefinitionParserDelegate.parseBeanDefinitionElement:(Lorg/w3c/dom/Element;)Lorg/springframework/beans/factory/config/BeanDefinitionHolder;
     267: invokevirtual #69                 // Method org/springframework/beans/factory/config/BeanDefinitionHolder.getBeanDefinition:()Lorg/springframework/beans/factory/config/BeanDefinition;
     270: astore        22
     272: goto          291
     275: iload         21
     277: ifeq          291
     280: aload_3
     281: invokevirtual #67                 // Method org/springframework/beans/factory/xml/ParserContext.getDelegate:()Lorg/springframework/beans/factory/xml/BeanDefinitionParserDelegate;
     284: aload         14
     286: invokevirtual #70                 // Method org/springframework/beans/factory/xml/BeanDefinitionParserDelegate.parseCustomElement:(Lorg/w3c/dom/Element;)Lorg/springframework/beans/factory/config/BeanDefinition;
     289: astore        22
     291: aload         22
     293: ifnull        300
     296: iconst_1
     297: goto          301
     300: iconst_0
     301: istore        23
     303: iload         19
     305: ifeq          323
     308: iload         21
     310: ifeq          323
     313: aload_3
     314: invokevirtual #35                 // Method org/springframework/beans/factory/xml/ParserContext.getReaderContext:()Lorg/springframework/beans/factory/xml/XmlReaderContext;
     317: ldc           #71                 // String The \'method\' attribute cannot be used when a \'script\' sub-element is defined
     319: aload_1
     320: invokevirtual #43                 // Method org/springframework/beans/factory/xml/XmlReaderContext.error:(Ljava/lang/String;Ljava/lang/Object;)V
     323: iload         17
     325: iload         18
     327: iload         20
     329: iload         23
     331: ixor
     332: ixor
     333: if_icmpne     346
     336: aload_3
     337: invokevirtual #35                 // Method org/springframework/beans/factory/xml/ParserContext.getReaderContext:()Lorg/springframework/beans/factory/xml/XmlReaderContext;
     340: ldc           #72                 // String Exactly one of the \'ref\', \'value\', \'expression\' or inner bean is required.
     342: aload_1
     343: invokevirtual #43                 // Method org/springframework/beans/factory/xml/XmlReaderContext.error:(Ljava/lang/String;Ljava/lang/Object;)V
     346: aconst_null
     347: astore        24
     349: iload         17
     351: ifeq          470
     354: iload         19
     356: ifeq          369
     359: aload_3
     360: invokevirtual #35                 // Method org/springframework/beans/factory/xml/ParserContext.getReaderContext:()Lorg/springframework/beans/factory/xml/XmlReaderContext;
     363: ldc           #73                 // String The \'method\' attribute cannot be used with the \'value\' attribute.
     365: aload_1
     366: invokevirtual #43                 // Method org/springframework/beans/factory/xml/XmlReaderContext.error:(Ljava/lang/String;Ljava/lang/Object;)V
     369: ldc           #75                 // String routingSlip
     371: aload         4
     373: invokevirtual #28                 // Method java/lang/String.equals:(Ljava/lang/Object;)Z
     376: ifeq          421
     379: new           #76                 // class org/springframework/beans/factory/support/ManagedList
     382: dup
     383: invokespecial #77                 // Method org/springframework/beans/factory/support/ManagedList."<init>":()V
     386: astore        25
     388: aload         25
     390: aload         9
     392: ldc           #78                 // String ;
     394: invokestatic  #79                 // Method org/springframework/util/StringUtils.tokenizeToStringArray:(Ljava/lang/String;Ljava/lang/String;)[Ljava/lang/String;
     397: invokestatic  #80                 // Method java/util/Arrays.asList:([Ljava/lang/Object;)Ljava/util/List;
     400: invokeinterface #81,  2           // InterfaceMethod java/util/List.addAll:(Ljava/util/Collection;)Z
     405: pop
     406: ldc           #82                 // class org/springframework/integration/transformer/support/RoutingSlipHeaderValueMessageProcessor
     408: invokestatic  #83                 // Method org/springframework/beans/factory/support/BeanDefinitionBuilder.genericBeanDefinition:(Ljava/lang/Class;)Lorg/springframework/beans/factory/support/BeanDefinitionBuilder;
     411: aload         25
     413: invokevirtual #13                 // Method org/springframework/beans/factory/support/BeanDefinitionBuilder.addConstructorArgValue:(Ljava/lang/Object;)Lorg/springframework/beans/factory/support/BeanDefinitionBuilder;
     416: astore        24
     418: goto          717
     421: aload         9
     423: astore        25
     425: aload         6
     427: invokestatic  #34                 // Method org/springframework/util/StringUtils.hasText:(Ljava/lang/String;)Z
     430: ifeq          455
     433: new           #84                 // class org/springframework/beans/factory/config/TypedStringValue
     436: dup
     437: aload         9
     439: invokespecial #85                 // Method org/springframework/beans/factory/config/TypedStringValue."<init>":(Ljava/lang/String;)V
     442: astore        26
     444: aload         26
     446: aload         6
     448: invokevirtual #86                 // Method org/springframework/beans/factory/config/TypedStringValue.setTargetTypeName:(Ljava/lang/String;)V
     451: aload         26
     453: astore        25
     455: ldc           #87                 // class org/springframework/integration/transformer/support/StaticHeaderValueMessageProcessor
     457: invokestatic  #83                 // Method org/springframework/beans/factory/support/BeanDefinitionBuilder.genericBeanDefinition:(Ljava/lang/Class;)Lorg/springframework/beans/factory/support/BeanDefinitionBuilder;
     460: aload         25
     462: invokevirtual #13                 // Method org/springframework/beans/factory/support/BeanDefinitionBuilder.addConstructorArgValue:(Ljava/lang/Object;)Lorg/springframework/beans/factory/support/BeanDefinitionBuilder;
     465: astore        24
     467: goto          717
     470: iload         20
     472: ifeq          572
     475: iload         19
     477: ifeq          490
     480: aload_3
     481: invokevirtual #35                 // Method org/springframework/beans/factory/xml/ParserContext.getReaderContext:()Lorg/springframework/beans/factory/xml/XmlReaderContext;
     484: ldc           #88                 // String The \'method\' attribute cannot be used with the \'expression\' attribute.
     486: aload_1
     487: invokevirtual #43                 // Method org/springframework/beans/factory/xml/XmlReaderContext.error:(Ljava/lang/String;Ljava/lang/Object;)V
     490: ldc           #89                 // class org/springframework/integration/transformer/support/ExpressionEvaluatingHeaderValueMessageProcessor
     492: invokestatic  #83                 // Method org/springframework/beans/factory/support/BeanDefinitionBuilder.genericBeanDefinition:(Ljava/lang/Class;)Lorg/springframework/beans/factory/support/BeanDefinitionBuilder;
     495: astore        24
     497: aload         15
     499: ifnull        553
     502: ldc           #90                 // class org/springframework/integration/expression/DynamicExpression
     504: invokestatic  #83                 // Method org/springframework/beans/factory/support/BeanDefinitionBuilder.genericBeanDefinition:(Ljava/lang/Class;)Lorg/springframework/beans/factory/support/BeanDefinitionBuilder;
     507: astore        25
     509: aload         25
     511: aload         15
     513: ldc           #91                 // String key
     515: invokeinterface #26,  2           // InterfaceMethod org/w3c/dom/Element.getAttribute:(Ljava/lang/String;)Ljava/lang/String;
     520: invokevirtual #13                 // Method org/springframework/beans/factory/support/BeanDefinitionBuilder.addConstructorArgValue:(Ljava/lang/Object;)Lorg/springframework/beans/factory/support/BeanDefinitionBuilder;
     523: pop
     524: aload         25
     526: aload         15
     528: ldc           #92                 // String source
     530: invokeinterface #26,  2           // InterfaceMethod org/w3c/dom/Element.getAttribute:(Ljava/lang/String;)Ljava/lang/String;
     535: invokevirtual #93                 // Method org/springframework/beans/factory/support/BeanDefinitionBuilder.addConstructorArgReference:(Ljava/lang/String;)Lorg/springframework/beans/factory/support/BeanDefinitionBuilder;
     538: pop
     539: aload         24
     541: aload         25
     543: invokevirtual #94                 // Method org/springframework/beans/factory/support/BeanDefinitionBuilder.getBeanDefinition:()Lorg/springframework/beans/factory/support/AbstractBeanDefinition;
     546: invokevirtual #13                 // Method org/springframework/beans/factory/support/BeanDefinitionBuilder.addConstructorArgValue:(Ljava/lang/Object;)Lorg/springframework/beans/factory/support/BeanDefinitionBuilder;
     549: pop
     550: goto          561
     553: aload         24
     555: aload         12
     557: invokevirtual #13                 // Method org/springframework/beans/factory/support/BeanDefinitionBuilder.addConstructorArgValue:(Ljava/lang/Object;)Lorg/springframework/beans/factory/support/BeanDefinitionBuilder;
     560: pop
     561: aload         24
     563: aload         6
     565: invokevirtual #13                 // Method org/springframework/beans/factory/support/BeanDefinitionBuilder.addConstructorArgValue:(Ljava/lang/Object;)Lorg/springframework/beans/factory/support/BeanDefinitionBuilder;
     568: pop
     569: goto          717
     572: iload         23
     574: ifeq          655
     577: aload         5
     579: ldc           #33                 // String type
     581: invokeinterface #26,  2           // InterfaceMethod org/w3c/dom/Element.getAttribute:(Ljava/lang/String;)Ljava/lang/String;
     586: invokestatic  #34                 // Method org/springframework/util/StringUtils.hasText:(Ljava/lang/String;)Z
     589: ifeq          602
     592: aload_3
     593: invokevirtual #35                 // Method org/springframework/beans/factory/xml/ParserContext.getReaderContext:()Lorg/springframework/beans/factory/xml/XmlReaderContext;
     596: ldc           #95                 // String The \'type\' attribute cannot be used with an inner bean.
     598: aload_1
     599: invokevirtual #43                 // Method org/springframework/beans/factory/xml/XmlReaderContext.error:(Ljava/lang/String;Ljava/lang/Object;)V
     602: iload         19
     604: ifne          612
     607: iload         21
     609: ifeq          640
     612: ldc           #96                 // class org/springframework/integration/transformer/support/MessageProcessingHeaderValueMessageProcessor
     614: invokestatic  #83                 // Method org/springframework/beans/factory/support/BeanDefinitionBuilder.genericBeanDefinition:(Ljava/lang/Class;)Lorg/springframework/beans/factory/support/BeanDefinitionBuilder;
     617: aload         22
     619: invokevirtual #13                 // Method org/springframework/beans/factory/support/BeanDefinitionBuilder.addConstructorArgValue:(Ljava/lang/Object;)Lorg/springframework/beans/factory/support/BeanDefinitionBuilder;
     622: astore        24
     624: iload         19
     626: ifeq          717
     629: aload         24
     631: aload         11
     633: invokevirtual #13                 // Method org/springframework/beans/factory/support/BeanDefinitionBuilder.addConstructorArgValue:(Ljava/lang/Object;)Lorg/springframework/beans/factory/support/BeanDefinitionBuilder;
     636: pop
     637: goto          717
     640: ldc           #87                 // class org/springframework/integration/transformer/support/StaticHeaderValueMessageProcessor
     642: invokestatic  #83                 // Method org/springframework/beans/factory/support/BeanDefinitionBuilder.genericBeanDefinition:(Ljava/lang/Class;)Lorg/springframework/beans/factory/support/BeanDefinitionBuilder;
     645: aload         22
     647: invokevirtual #13                 // Method org/springframework/beans/factory/support/BeanDefinitionBuilder.addConstructorArgValue:(Ljava/lang/Object;)Lorg/springframework/beans/factory/support/BeanDefinitionBuilder;
     650: astore        24
     652: goto          717
     655: aload         5
     657: ldc           #33                 // String type
     659: invokeinterface #26,  2           // InterfaceMethod org/w3c/dom/Element.getAttribute:(Ljava/lang/String;)Ljava/lang/String;
     664: invokestatic  #34                 // Method org/springframework/util/StringUtils.hasText:(Ljava/lang/String;)Z
     667: ifeq          680
     670: aload_3
     671: invokevirtual #35                 // Method org/springframework/beans/factory/xml/ParserContext.getReaderContext:()Lorg/springframework/beans/factory/xml/XmlReaderContext;
     674: ldc           #97                 // String The \'type\' attribute cannot be used with the \'ref\' attribute.
     676: aload_1
     677: invokevirtual #43                 // Method org/springframework/beans/factory/xml/XmlReaderContext.error:(Ljava/lang/String;Ljava/lang/Object;)V
     680: iload         19
     682: ifeq          705
     685: ldc           #96                 // class org/springframework/integration/transformer/support/MessageProcessingHeaderValueMessageProcessor
     687: invokestatic  #83                 // Method org/springframework/beans/factory/support/BeanDefinitionBuilder.genericBeanDefinition:(Ljava/lang/Class;)Lorg/springframework/beans/factory/support/BeanDefinitionBuilder;
     690: aload         10
     692: invokevirtual #93                 // Method org/springframework/beans/factory/support/BeanDefinitionBuilder.addConstructorArgReference:(Ljava/lang/String;)Lorg/springframework/beans/factory/support/BeanDefinitionBuilder;
     695: aload         11
     697: invokevirtual #13                 // Method org/springframework/beans/factory/support/BeanDefinitionBuilder.addConstructorArgValue:(Ljava/lang/Object;)Lorg/springframework/beans/factory/support/BeanDefinitionBuilder;
     700: astore        24
     702: goto          717
     705: ldc           #87                 // class org/springframework/integration/transformer/support/StaticHeaderValueMessageProcessor
     707: invokestatic  #83                 // Method org/springframework/beans/factory/support/BeanDefinitionBuilder.genericBeanDefinition:(Ljava/lang/Class;)Lorg/springframework/beans/factory/support/BeanDefinitionBuilder;
     710: aload         10
     712: invokevirtual #93                 // Method org/springframework/beans/factory/support/BeanDefinitionBuilder.addConstructorArgReference:(Ljava/lang/String;)Lorg/springframework/beans/factory/support/BeanDefinitionBuilder;
     715: astore        24
     717: aload         8
     719: invokestatic  #34                 // Method org/springframework/util/StringUtils.hasText:(Ljava/lang/String;)Z
     722: ifeq          735
     725: aload         24
     727: ldc           #25                 // String overwrite
     729: aload         8
     731: invokevirtual #98                 // Method org/springframework/beans/factory/support/BeanDefinitionBuilder.addPropertyValue:(Ljava/lang/String;Ljava/lang/Object;)Lorg/springframework/beans/factory/support/BeanDefinitionBuilder;
     734: pop
     735: aload_2
     736: aload         4
     738: aload         24
     740: invokevirtual #94                 // Method org/springframework/beans/factory/support/BeanDefinitionBuilder.getBeanDefinition:()Lorg/springframework/beans/factory/support/AbstractBeanDefinition;
     743: invokevirtual #99                 // Method org/springframework/beans/factory/support/ManagedMap.put:(Ljava/lang/Object;Ljava/lang/Object;)Ljava/lang/Object;
     746: pop
     747: return

  protected void postProcessHeaderEnricher(org.springframework.beans.factory.support.BeanDefinitionBuilder, org.w3c.dom.Element, org.springframework.beans.factory.xml.ParserContext);
    Code:
       0: return

  static {};
    Code:
       0: new           #2                  // class java/util/HashMap
       3: dup
       4: invokespecial #3                  // Method java/util/HashMap."<init>":()V
       7: putstatic     #45                 // Field cannedHeaderElementExpressions:Ljava/util/Map;
      10: getstatic     #45                 // Field cannedHeaderElementExpressions:Ljava/util/Map;
      13: ldc           #100                // String header-channels-to-string
      15: iconst_2
      16: anewarray     #101                // class "[Ljava/lang/String;"
      19: dup
      20: iconst_0
      21: iconst_2
      22: anewarray     #32                 // class java/lang/String
      25: dup
      26: iconst_0
      27: ldc           #102                // String replyChannel
      29: aastore
      30: dup
      31: iconst_1
      32: ldc           #104                // String @integrationHeaderChannelRegistry.channelToChannelName(headers.replyChannel, ####)
      34: aastore
      35: aastore
      36: dup
      37: iconst_1
      38: iconst_2
      39: anewarray     #32                 // class java/lang/String
      42: dup
      43: iconst_0
      44: ldc           #105                // String errorChannel
      46: aastore
      47: dup
      48: iconst_1
      49: ldc           #106                // String @integrationHeaderChannelRegistry.channelToChannelName(headers.errorChannel, ####)
      51: aastore
      52: aastore
      53: invokeinterface #9,  3            // InterfaceMethod java/util/Map.put:(Ljava/lang/Object;Ljava/lang/Object;)Ljava/lang/Object;
      58: pop
      59: return
}
