Compiled from "IdempotentReceiverInterceptorParser.java"
public class org.springframework.integration.config.xml.IdempotentReceiverInterceptorParser extends org.springframework.beans.factory.xml.AbstractBeanDefinitionParser {
  public org.springframework.integration.config.xml.IdempotentReceiverInterceptorParser();
    Code:
       0: aload_0
       1: invokespecial #1                  // Method org/springframework/beans/factory/xml/AbstractBeanDefinitionParser."<init>":()V
       4: return

  protected org.springframework.beans.factory.support.AbstractBeanDefinition parseInternal(org.w3c.dom.Element, org.springframework.beans.factory.xml.ParserContext);
    Code:
       0: aload_2
       1: aload_1
       2: invokevirtual #2                  // Method org/springframework/beans/factory/xml/ParserContext.extractSource:(Ljava/lang/Object;)Ljava/lang/Object;
       5: astore_3
       6: aload_1
       7: ldc           #3                  // String selector
       9: invokeinterface #4,  2            // InterfaceMethod org/w3c/dom/Element.getAttribute:(Ljava/lang/String;)Ljava/lang/String;
      14: astore        4
      16: aload         4
      18: invokestatic  #5                  // Method org/springframework/util/StringUtils.hasText:(Ljava/lang/String;)Z
      21: istore        5
      23: aload_1
      24: ldc           #6                  // String metadata-store
      26: invokeinterface #4,  2            // InterfaceMethod org/w3c/dom/Element.getAttribute:(Ljava/lang/String;)Ljava/lang/String;
      31: astore        6
      33: aload         6
      35: invokestatic  #5                  // Method org/springframework/util/StringUtils.hasText:(Ljava/lang/String;)Z
      38: istore        7
      40: aload_1
      41: ldc           #7                  // String key-strategy
      43: invokeinterface #4,  2            // InterfaceMethod org/w3c/dom/Element.getAttribute:(Ljava/lang/String;)Ljava/lang/String;
      48: astore        8
      50: aload         8
      52: invokestatic  #5                  // Method org/springframework/util/StringUtils.hasText:(Ljava/lang/String;)Z
      55: istore        9
      57: aload_1
      58: ldc           #8                  // String key-expression
      60: invokeinterface #4,  2            // InterfaceMethod org/w3c/dom/Element.getAttribute:(Ljava/lang/String;)Ljava/lang/String;
      65: astore        10
      67: aload         10
      69: invokestatic  #5                  // Method org/springframework/util/StringUtils.hasText:(Ljava/lang/String;)Z
      72: istore        11
      74: aload_1
      75: ldc           #9                  // String value-strategy
      77: invokeinterface #4,  2            // InterfaceMethod org/w3c/dom/Element.getAttribute:(Ljava/lang/String;)Ljava/lang/String;
      82: astore        12
      84: aload         12
      86: invokestatic  #5                  // Method org/springframework/util/StringUtils.hasText:(Ljava/lang/String;)Z
      89: istore        13
      91: aload_1
      92: ldc           #10                 // String value-expression
      94: invokeinterface #4,  2            // InterfaceMethod org/w3c/dom/Element.getAttribute:(Ljava/lang/String;)Ljava/lang/String;
      99: astore        14
     101: aload         14
     103: invokestatic  #5                  // Method org/springframework/util/StringUtils.hasText:(Ljava/lang/String;)Z
     106: istore        15
     108: aload_1
     109: ldc           #11                 // String endpoint
     111: invokeinterface #4,  2            // InterfaceMethod org/w3c/dom/Element.getAttribute:(Ljava/lang/String;)Ljava/lang/String;
     116: astore        16
     118: iload         5
     120: ifne          127
     123: iconst_1
     124: goto          128
     127: iconst_0
     128: iload         9
     130: iload         11
     132: ior
     133: ifne          140
     136: iconst_1
     137: goto          141
     140: iconst_0
     141: iand
     142: ifeq          155
     145: aload_2
     146: invokevirtual #12                 // Method org/springframework/beans/factory/xml/ParserContext.getReaderContext:()Lorg/springframework/beans/factory/xml/XmlReaderContext;
     149: ldc           #13                 // String One of the \'selector\', \'key-strategy\' or \'key-expression\' attributes must be provided
     151: aload_3
     152: invokevirtual #14                 // Method org/springframework/beans/factory/xml/XmlReaderContext.error:(Ljava/lang/String;Ljava/lang/Object;)V
     155: iload         5
     157: iload         7
     159: iload         9
     161: ior
     162: iload         11
     164: ior
     165: iload         13
     167: ior
     168: iload         15
     170: ior
     171: iand
     172: ifeq          185
     175: aload_2
     176: invokevirtual #12                 // Method org/springframework/beans/factory/xml/ParserContext.getReaderContext:()Lorg/springframework/beans/factory/xml/XmlReaderContext;
     179: ldc           #15                 // String The \'selector\' attribute is mutually exclusive with \'metadata-store\', \'key-strategy\', \'key-expression\', \'value-strategy\' or \'value-expression\'
     181: aload_3
     182: invokevirtual #14                 // Method org/springframework/beans/factory/xml/XmlReaderContext.error:(Ljava/lang/String;Ljava/lang/Object;)V
     185: iload         9
     187: iload         11
     189: iand
     190: ifeq          203
     193: aload_2
     194: invokevirtual #12                 // Method org/springframework/beans/factory/xml/ParserContext.getReaderContext:()Lorg/springframework/beans/factory/xml/XmlReaderContext;
     197: ldc           #16                 // String The \'key-strategy\' and \'key-expression\' attributes are mutually exclusive
     199: aload_3
     200: invokevirtual #14                 // Method org/springframework/beans/factory/xml/XmlReaderContext.error:(Ljava/lang/String;Ljava/lang/Object;)V
     203: iload         13
     205: iload         15
     207: iand
     208: ifeq          221
     211: aload_2
     212: invokevirtual #12                 // Method org/springframework/beans/factory/xml/ParserContext.getReaderContext:()Lorg/springframework/beans/factory/xml/XmlReaderContext;
     215: ldc           #17                 // String The \'value-strategy\' and \'value-expression\' attributes are mutually exclusive
     217: aload_3
     218: invokevirtual #14                 // Method org/springframework/beans/factory/xml/XmlReaderContext.error:(Ljava/lang/String;Ljava/lang/Object;)V
     221: aload         16
     223: invokestatic  #5                  // Method org/springframework/util/StringUtils.hasText:(Ljava/lang/String;)Z
     226: ifne          239
     229: aload_2
     230: invokevirtual #12                 // Method org/springframework/beans/factory/xml/ParserContext.getReaderContext:()Lorg/springframework/beans/factory/xml/XmlReaderContext;
     233: ldc           #18                 // String The \'endpoint\' attribute is required
     235: aload_3
     236: invokevirtual #14                 // Method org/springframework/beans/factory/xml/XmlReaderContext.error:(Ljava/lang/String;Ljava/lang/Object;)V
     239: aconst_null
     240: astore        17
     242: iload         5
     244: ifeq          261
     247: new           #19                 // class org/springframework/beans/factory/config/RuntimeBeanReference
     250: dup
     251: aload         4
     253: invokespecial #20                 // Method org/springframework/beans/factory/config/RuntimeBeanReference."<init>":(Ljava/lang/String;)V
     256: astore        17
     258: goto          423
     261: ldc           #21                 // class org/springframework/integration/selector/MetadataStoreSelector
     263: invokestatic  #22                 // Method org/springframework/beans/factory/support/BeanDefinitionBuilder.genericBeanDefinition:(Ljava/lang/Class;)Lorg/springframework/beans/factory/support/BeanDefinitionBuilder;
     266: astore        18
     268: aconst_null
     269: astore        19
     271: iload         9
     273: ifeq          290
     276: new           #19                 // class org/springframework/beans/factory/config/RuntimeBeanReference
     279: dup
     280: aload         8
     282: invokespecial #20                 // Method org/springframework/beans/factory/config/RuntimeBeanReference."<init>":(Ljava/lang/String;)V
     285: astore        19
     287: goto          316
     290: ldc           #23                 // class org/springframework/integration/handler/ExpressionEvaluatingMessageProcessor
     292: invokestatic  #22                 // Method org/springframework/beans/factory/support/BeanDefinitionBuilder.genericBeanDefinition:(Ljava/lang/Class;)Lorg/springframework/beans/factory/support/BeanDefinitionBuilder;
     295: ldc           #24                 // class org/springframework/integration/config/ExpressionFactoryBean
     297: invokestatic  #22                 // Method org/springframework/beans/factory/support/BeanDefinitionBuilder.genericBeanDefinition:(Ljava/lang/Class;)Lorg/springframework/beans/factory/support/BeanDefinitionBuilder;
     300: aload         10
     302: invokevirtual #25                 // Method org/springframework/beans/factory/support/BeanDefinitionBuilder.addConstructorArgValue:(Ljava/lang/Object;)Lorg/springframework/beans/factory/support/BeanDefinitionBuilder;
     305: invokevirtual #26                 // Method org/springframework/beans/factory/support/BeanDefinitionBuilder.getBeanDefinition:()Lorg/springframework/beans/factory/support/AbstractBeanDefinition;
     308: invokevirtual #25                 // Method org/springframework/beans/factory/support/BeanDefinitionBuilder.addConstructorArgValue:(Ljava/lang/Object;)Lorg/springframework/beans/factory/support/BeanDefinitionBuilder;
     311: invokevirtual #26                 // Method org/springframework/beans/factory/support/BeanDefinitionBuilder.getBeanDefinition:()Lorg/springframework/beans/factory/support/AbstractBeanDefinition;
     314: astore        19
     316: aload         18
     318: aload         19
     320: invokevirtual #25                 // Method org/springframework/beans/factory/support/BeanDefinitionBuilder.addConstructorArgValue:(Ljava/lang/Object;)Lorg/springframework/beans/factory/support/BeanDefinitionBuilder;
     323: pop
     324: aconst_null
     325: astore        20
     327: iload         13
     329: ifeq          346
     332: new           #19                 // class org/springframework/beans/factory/config/RuntimeBeanReference
     335: dup
     336: aload         12
     338: invokespecial #20                 // Method org/springframework/beans/factory/config/RuntimeBeanReference."<init>":(Ljava/lang/String;)V
     341: astore        20
     343: goto          377
     346: iload         15
     348: ifeq          377
     351: ldc           #23                 // class org/springframework/integration/handler/ExpressionEvaluatingMessageProcessor
     353: invokestatic  #22                 // Method org/springframework/beans/factory/support/BeanDefinitionBuilder.genericBeanDefinition:(Ljava/lang/Class;)Lorg/springframework/beans/factory/support/BeanDefinitionBuilder;
     356: ldc           #24                 // class org/springframework/integration/config/ExpressionFactoryBean
     358: invokestatic  #22                 // Method org/springframework/beans/factory/support/BeanDefinitionBuilder.genericBeanDefinition:(Ljava/lang/Class;)Lorg/springframework/beans/factory/support/BeanDefinitionBuilder;
     361: aload         14
     363: invokevirtual #25                 // Method org/springframework/beans/factory/support/BeanDefinitionBuilder.addConstructorArgValue:(Ljava/lang/Object;)Lorg/springframework/beans/factory/support/BeanDefinitionBuilder;
     366: invokevirtual #26                 // Method org/springframework/beans/factory/support/BeanDefinitionBuilder.getBeanDefinition:()Lorg/springframework/beans/factory/support/AbstractBeanDefinition;
     369: invokevirtual #25                 // Method org/springframework/beans/factory/support/BeanDefinitionBuilder.addConstructorArgValue:(Ljava/lang/Object;)Lorg/springframework/beans/factory/support/BeanDefinitionBuilder;
     372: invokevirtual #26                 // Method org/springframework/beans/factory/support/BeanDefinitionBuilder.getBeanDefinition:()Lorg/springframework/beans/factory/support/AbstractBeanDefinition;
     375: astore        20
     377: aload         18
     379: aload         20
     381: invokevirtual #25                 // Method org/springframework/beans/factory/support/BeanDefinitionBuilder.addConstructorArgValue:(Ljava/lang/Object;)Lorg/springframework/beans/factory/support/BeanDefinitionBuilder;
     384: pop
     385: iload         7
     387: ifeq          401
     390: aload         18
     392: aload         6
     394: invokevirtual #27                 // Method org/springframework/beans/factory/support/BeanDefinitionBuilder.addConstructorArgReference:(Ljava/lang/String;)Lorg/springframework/beans/factory/support/BeanDefinitionBuilder;
     397: pop
     398: goto          416
     401: aload         18
     403: new           #28                 // class org/springframework/beans/factory/support/RootBeanDefinition
     406: dup
     407: ldc           #29                 // class org/springframework/integration/metadata/SimpleMetadataStore
     409: invokespecial #30                 // Method org/springframework/beans/factory/support/RootBeanDefinition."<init>":(Ljava/lang/Class;)V
     412: invokevirtual #25                 // Method org/springframework/beans/factory/support/BeanDefinitionBuilder.addConstructorArgValue:(Ljava/lang/Object;)Lorg/springframework/beans/factory/support/BeanDefinitionBuilder;
     415: pop
     416: aload         18
     418: invokevirtual #26                 // Method org/springframework/beans/factory/support/BeanDefinitionBuilder.getBeanDefinition:()Lorg/springframework/beans/factory/support/AbstractBeanDefinition;
     421: astore        17
     423: ldc           #31                 // class org/springframework/integration/handler/advice/IdempotentReceiverInterceptor
     425: invokestatic  #22                 // Method org/springframework/beans/factory/support/BeanDefinitionBuilder.genericBeanDefinition:(Ljava/lang/Class;)Lorg/springframework/beans/factory/support/BeanDefinitionBuilder;
     428: aload         17
     430: invokevirtual #25                 // Method org/springframework/beans/factory/support/BeanDefinitionBuilder.addConstructorArgValue:(Ljava/lang/Object;)Lorg/springframework/beans/factory/support/BeanDefinitionBuilder;
     433: astore        18
     435: aload         18
     437: aload_1
     438: ldc           #32                 // String throw-exception-on-rejection
     440: invokestatic  #33                 // Method org/springframework/integration/config/xml/IntegrationNamespaceUtils.setValueIfAttributeDefined:(Lorg/springframework/beans/factory/support/BeanDefinitionBuilder;Lorg/w3c/dom/Element;Ljava/lang/String;)V
     443: aload         18
     445: aload_1
     446: ldc           #34                 // String discard-channel
     448: invokestatic  #35                 // Method org/springframework/integration/config/xml/IntegrationNamespaceUtils.setReferenceIfAttributeDefined:(Lorg/springframework/beans/factory/support/BeanDefinitionBuilder;Lorg/w3c/dom/Element;Ljava/lang/String;)V
     451: aload         18
     453: invokevirtual #26                 // Method org/springframework/beans/factory/support/BeanDefinitionBuilder.getBeanDefinition:()Lorg/springframework/beans/factory/support/AbstractBeanDefinition;
     456: astore        19
     458: aload         19
     460: ldc           #37                 // String IDEMPOTENT_ENDPOINTS_MAPPING
     462: aload         16
     464: invokevirtual #38                 // Method org/springframework/beans/factory/support/AbstractBeanDefinition.setAttribute:(Ljava/lang/String;Ljava/lang/Object;)V
     467: aload         19
     469: areturn

  protected boolean shouldGenerateIdAsFallback();
    Code:
       0: iconst_1
       1: ireturn

  protected boolean shouldFireEvents();
    Code:
       0: iconst_0
       1: ireturn
}
