Compiled from "ScanPage.java"
class com.amazonaws.services.dynamodbv2.document.internal.ScanPage extends com.amazonaws.services.dynamodbv2.document.Page<com.amazonaws.services.dynamodbv2.document.Item, com.amazonaws.services.dynamodbv2.document.ScanOutcome> {
  private final com.amazonaws.services.dynamodbv2.AmazonDynamoDB client;

  private final com.amazonaws.services.dynamodbv2.document.spec.ScanSpec spec;

  private final com.amazonaws.services.dynamodbv2.model.ScanRequest request;

  private final int index;

  private final java.util.Map<java.lang.String, com.amazonaws.services.dynamodbv2.model.AttributeValue> lastEvaluatedKey;

  public com.amazonaws.services.dynamodbv2.document.internal.ScanPage(com.amazonaws.services.dynamodbv2.AmazonDynamoDB, com.amazonaws.services.dynamodbv2.document.spec.ScanSpec, com.amazonaws.services.dynamodbv2.model.ScanRequest, int, com.amazonaws.services.dynamodbv2.document.ScanOutcome);
    Code:
       0: aload_0
       1: aload         5
       3: invokevirtual #1                  // Method com/amazonaws/services/dynamodbv2/document/ScanOutcome.getScanResult:()Lcom/amazonaws/services/dynamodbv2/model/ScanResult;
       6: invokevirtual #2                  // Method com/amazonaws/services/dynamodbv2/model/ScanResult.getItems:()Ljava/util/List;
       9: invokestatic  #3                  // Method com/amazonaws/services/dynamodbv2/document/internal/InternalUtils.toItemList:(Ljava/util/List;)Ljava/util/List;
      12: invokestatic  #4                  // Method java/util/Collections.unmodifiableList:(Ljava/util/List;)Ljava/util/List;
      15: aload         5
      17: invokespecial #5                  // Method com/amazonaws/services/dynamodbv2/document/Page."<init>":(Ljava/util/List;Ljava/lang/Object;)V
      20: aload_0
      21: aload_1
      22: putfield      #6                  // Field client:Lcom/amazonaws/services/dynamodbv2/AmazonDynamoDB;
      25: aload_0
      26: aload_2
      27: putfield      #7                  // Field spec:Lcom/amazonaws/services/dynamodbv2/document/spec/ScanSpec;
      30: aload_0
      31: aload_3
      32: putfield      #8                  // Field request:Lcom/amazonaws/services/dynamodbv2/model/ScanRequest;
      35: aload_0
      36: iload         4
      38: putfield      #9                  // Field index:I
      41: aload_2
      42: invokevirtual #10                 // Method com/amazonaws/services/dynamodbv2/document/spec/ScanSpec.getMaxResultSize:()Ljava/lang/Integer;
      45: astore        6
      47: aload         5
      49: invokevirtual #1                  // Method com/amazonaws/services/dynamodbv2/document/ScanOutcome.getScanResult:()Lcom/amazonaws/services/dynamodbv2/model/ScanResult;
      52: astore        7
      54: aload         7
      56: invokevirtual #2                  // Method com/amazonaws/services/dynamodbv2/model/ScanResult.getItems:()Ljava/util/List;
      59: astore        8
      61: aload         8
      63: ifnonnull     70
      66: iconst_0
      67: goto          77
      70: aload         8
      72: invokeinterface #11,  1           // InterfaceMethod java/util/List.size:()I
      77: istore        9
      79: aload         6
      81: ifnull        105
      84: iload         4
      86: iload         9
      88: iadd
      89: aload         6
      91: invokevirtual #12                 // Method java/lang/Integer.intValue:()I
      94: if_icmple     105
      97: aload_0
      98: aconst_null
      99: putfield      #13                 // Field lastEvaluatedKey:Ljava/util/Map;
     102: goto          114
     105: aload_0
     106: aload         7
     108: invokevirtual #14                 // Method com/amazonaws/services/dynamodbv2/model/ScanResult.getLastEvaluatedKey:()Ljava/util/Map;
     111: putfield      #13                 // Field lastEvaluatedKey:Ljava/util/Map;
     114: return

  public boolean hasNextPage();
    Code:
       0: aload_0
       1: getfield      #13                 // Field lastEvaluatedKey:Ljava/util/Map;
       4: ifnonnull     9
       7: iconst_0
       8: ireturn
       9: aload_0
      10: getfield      #7                  // Field spec:Lcom/amazonaws/services/dynamodbv2/document/spec/ScanSpec;
      13: invokevirtual #10                 // Method com/amazonaws/services/dynamodbv2/document/spec/ScanSpec.getMaxResultSize:()Ljava/lang/Integer;
      16: astore_1
      17: aload_1
      18: ifnonnull     23
      21: iconst_1
      22: ireturn
      23: aload_0
      24: aload_1
      25: invokevirtual #12                 // Method java/lang/Integer.intValue:()I
      28: invokespecial #15                 // Method nextRequestLimit:(I)I
      31: ifle          38
      34: iconst_1
      35: goto          39
      38: iconst_0
      39: ireturn

  private int nextRequestLimit(int);
    Code:
       0: aload_0
       1: getfield      #9                  // Field index:I
       4: aload_0
       5: invokevirtual #16                 // Method size:()I
       8: iadd
       9: istore_2
      10: iload_1
      11: iload_2
      12: isub
      13: invokestatic  #17                 // Method java/lang/Integer.valueOf:(I)Ljava/lang/Integer;
      16: aload_0
      17: getfield      #7                  // Field spec:Lcom/amazonaws/services/dynamodbv2/document/spec/ScanSpec;
      20: invokevirtual #18                 // Method com/amazonaws/services/dynamodbv2/document/spec/ScanSpec.getMaxPageSize:()Ljava/lang/Integer;
      23: invokestatic  #19                 // Method com/amazonaws/services/dynamodbv2/document/internal/InternalUtils.minimum:(Ljava/lang/Integer;Ljava/lang/Integer;)Ljava/lang/Integer;
      26: invokevirtual #12                 // Method java/lang/Integer.intValue:()I
      29: ireturn

  public com.amazonaws.services.dynamodbv2.document.Page<com.amazonaws.services.dynamodbv2.document.Item, com.amazonaws.services.dynamodbv2.document.ScanOutcome> nextPage();
    Code:
       0: aload_0
       1: getfield      #13                 // Field lastEvaluatedKey:Ljava/util/Map;
       4: ifnonnull     17
       7: new           #20                 // class java/util/NoSuchElementException
      10: dup
      11: ldc           #21                 // String No more pages
      13: invokespecial #22                 // Method java/util/NoSuchElementException."<init>":(Ljava/lang/String;)V
      16: athrow
      17: aload_0
      18: getfield      #7                  // Field spec:Lcom/amazonaws/services/dynamodbv2/document/spec/ScanSpec;
      21: invokevirtual #10                 // Method com/amazonaws/services/dynamodbv2/document/spec/ScanSpec.getMaxResultSize:()Ljava/lang/Integer;
      24: astore_1
      25: aload_1
      26: ifnull        63
      29: aload_0
      30: aload_1
      31: invokevirtual #12                 // Method java/lang/Integer.intValue:()I
      34: invokespecial #15                 // Method nextRequestLimit:(I)I
      37: istore_2
      38: iload_2
      39: ifne          52
      42: new           #20                 // class java/util/NoSuchElementException
      45: dup
      46: ldc           #21                 // String No more pages
      48: invokespecial #22                 // Method java/util/NoSuchElementException."<init>":(Ljava/lang/String;)V
      51: athrow
      52: aload_0
      53: getfield      #8                  // Field request:Lcom/amazonaws/services/dynamodbv2/model/ScanRequest;
      56: iload_2
      57: invokestatic  #17                 // Method java/lang/Integer.valueOf:(I)Ljava/lang/Integer;
      60: invokevirtual #23                 // Method com/amazonaws/services/dynamodbv2/model/ScanRequest.setLimit:(Ljava/lang/Integer;)V
      63: aload_0
      64: getfield      #8                  // Field request:Lcom/amazonaws/services/dynamodbv2/model/ScanRequest;
      67: aload_0
      68: getfield      #13                 // Field lastEvaluatedKey:Ljava/util/Map;
      71: invokevirtual #24                 // Method com/amazonaws/services/dynamodbv2/model/ScanRequest.setExclusiveStartKey:(Ljava/util/Map;)V
      74: aload_0
      75: getfield      #6                  // Field client:Lcom/amazonaws/services/dynamodbv2/AmazonDynamoDB;
      78: aload_0
      79: getfield      #8                  // Field request:Lcom/amazonaws/services/dynamodbv2/model/ScanRequest;
      82: invokeinterface #25,  2           // InterfaceMethod com/amazonaws/services/dynamodbv2/AmazonDynamoDB.scan:(Lcom/amazonaws/services/dynamodbv2/model/ScanRequest;)Lcom/amazonaws/services/dynamodbv2/model/ScanResult;
      87: astore_2
      88: aload_0
      89: getfield      #9                  // Field index:I
      92: aload_0
      93: invokevirtual #16                 // Method size:()I
      96: iadd
      97: istore_3
      98: new           #26                 // class com/amazonaws/services/dynamodbv2/document/internal/ScanPage
     101: dup
     102: aload_0
     103: getfield      #6                  // Field client:Lcom/amazonaws/services/dynamodbv2/AmazonDynamoDB;
     106: aload_0
     107: getfield      #7                  // Field spec:Lcom/amazonaws/services/dynamodbv2/document/spec/ScanSpec;
     110: aload_0
     111: getfield      #8                  // Field request:Lcom/amazonaws/services/dynamodbv2/model/ScanRequest;
     114: iload_3
     115: new           #27                 // class com/amazonaws/services/dynamodbv2/document/ScanOutcome
     118: dup
     119: aload_2
     120: invokespecial #28                 // Method com/amazonaws/services/dynamodbv2/document/ScanOutcome."<init>":(Lcom/amazonaws/services/dynamodbv2/model/ScanResult;)V
     123: invokespecial #29                 // Method "<init>":(Lcom/amazonaws/services/dynamodbv2/AmazonDynamoDB;Lcom/amazonaws/services/dynamodbv2/document/spec/ScanSpec;Lcom/amazonaws/services/dynamodbv2/model/ScanRequest;ILcom/amazonaws/services/dynamodbv2/document/ScanOutcome;)V
     126: areturn
}
