Compiled from "OneToOneSecondPass.java"
public class org.hibernate.cfg.OneToOneSecondPass implements org.hibernate.cfg.SecondPass {
  private org.hibernate.boot.spi.MetadataBuildingContext buildingContext;

  private java.lang.String mappedBy;

  private java.lang.String ownerEntity;

  private java.lang.String ownerProperty;

  private org.hibernate.cfg.PropertyHolder propertyHolder;

  private boolean ignoreNotFound;

  private org.hibernate.cfg.PropertyData inferredData;

  private org.hibernate.annotations.common.reflection.XClass targetEntity;

  private boolean cascadeOnDelete;

  private boolean optional;

  private java.lang.String cascadeStrategy;

  private org.hibernate.cfg.Ejb3JoinColumn[] joinColumns;

  public org.hibernate.cfg.OneToOneSecondPass(java.lang.String, java.lang.String, java.lang.String, org.hibernate.cfg.PropertyHolder, org.hibernate.cfg.PropertyData, org.hibernate.annotations.common.reflection.XClass, boolean, boolean, boolean, java.lang.String, org.hibernate.cfg.Ejb3JoinColumn[], org.hibernate.boot.spi.MetadataBuildingContext);
    Code:
       0: aload_0
       1: invokespecial #1                  // Method java/lang/Object."<init>":()V
       4: aload_0
       5: aload_2
       6: putfield      #2                  // Field ownerEntity:Ljava/lang/String;
       9: aload_0
      10: aload_3
      11: putfield      #3                  // Field ownerProperty:Ljava/lang/String;
      14: aload_0
      15: aload_1
      16: putfield      #4                  // Field mappedBy:Ljava/lang/String;
      19: aload_0
      20: aload         4
      22: putfield      #5                  // Field propertyHolder:Lorg/hibernate/cfg/PropertyHolder;
      25: aload_0
      26: aload         12
      28: putfield      #6                  // Field buildingContext:Lorg/hibernate/boot/spi/MetadataBuildingContext;
      31: aload_0
      32: iload         7
      34: putfield      #7                  // Field ignoreNotFound:Z
      37: aload_0
      38: aload         5
      40: putfield      #8                  // Field inferredData:Lorg/hibernate/cfg/PropertyData;
      43: aload_0
      44: aload         6
      46: putfield      #9                  // Field targetEntity:Lorg/hibernate/annotations/common/reflection/XClass;
      49: aload_0
      50: iload         8
      52: putfield      #10                 // Field cascadeOnDelete:Z
      55: aload_0
      56: iload         9
      58: putfield      #11                 // Field optional:Z
      61: aload_0
      62: aload         10
      64: putfield      #12                 // Field cascadeStrategy:Ljava/lang/String;
      67: aload_0
      68: aload         11
      70: putfield      #13                 // Field joinColumns:[Lorg/hibernate/cfg/Ejb3JoinColumn;
      73: return

  public void doSecondPass(java.util.Map) throws org.hibernate.MappingException;
    Code:
       0: new           #14                 // class org/hibernate/mapping/OneToOne
       3: dup
       4: aload_0
       5: getfield      #6                  // Field buildingContext:Lorg/hibernate/boot/spi/MetadataBuildingContext;
       8: aload_0
       9: getfield      #5                  // Field propertyHolder:Lorg/hibernate/cfg/PropertyHolder;
      12: invokeinterface #15,  1           // InterfaceMethod org/hibernate/cfg/PropertyHolder.getTable:()Lorg/hibernate/mapping/Table;
      17: aload_0
      18: getfield      #5                  // Field propertyHolder:Lorg/hibernate/cfg/PropertyHolder;
      21: invokeinterface #16,  1           // InterfaceMethod org/hibernate/cfg/PropertyHolder.getPersistentClass:()Lorg/hibernate/mapping/PersistentClass;
      26: invokespecial #17                 // Method org/hibernate/mapping/OneToOne."<init>":(Lorg/hibernate/boot/spi/MetadataBuildingContext;Lorg/hibernate/mapping/Table;Lorg/hibernate/mapping/PersistentClass;)V
      29: astore_2
      30: aload_0
      31: getfield      #8                  // Field inferredData:Lorg/hibernate/cfg/PropertyData;
      34: invokeinterface #18,  1           // InterfaceMethod org/hibernate/cfg/PropertyData.getPropertyName:()Ljava/lang/String;
      39: astore_3
      40: aload_2
      41: aload_3
      42: invokevirtual #19                 // Method org/hibernate/mapping/OneToOne.setPropertyName:(Ljava/lang/String;)V
      45: aload_0
      46: getfield      #8                  // Field inferredData:Lorg/hibernate/cfg/PropertyData;
      49: aload_0
      50: getfield      #9                  // Field targetEntity:Lorg/hibernate/annotations/common/reflection/XClass;
      53: aload_0
      54: getfield      #6                  // Field buildingContext:Lorg/hibernate/boot/spi/MetadataBuildingContext;
      57: invokestatic  #20                 // Method org/hibernate/cfg/ToOneBinder.getReferenceEntityName:(Lorg/hibernate/cfg/PropertyData;Lorg/hibernate/annotations/common/reflection/XClass;Lorg/hibernate/boot/spi/MetadataBuildingContext;)Ljava/lang/String;
      60: astore        4
      62: aload_2
      63: aload         4
      65: invokevirtual #21                 // Method org/hibernate/mapping/OneToOne.setReferencedEntityName:(Ljava/lang/String;)V
      68: aload_2
      69: aload_0
      70: getfield      #8                  // Field inferredData:Lorg/hibernate/cfg/PropertyData;
      73: invokeinterface #22,  1           // InterfaceMethod org/hibernate/cfg/PropertyData.getProperty:()Lorg/hibernate/annotations/common/reflection/XProperty;
      78: invokestatic  #23                 // Method org/hibernate/cfg/AnnotationBinder.defineFetchingStrategy:(Lorg/hibernate/mapping/ToOne;Lorg/hibernate/annotations/common/reflection/XProperty;)V
      81: aload_2
      82: aload_0
      83: getfield      #10                 // Field cascadeOnDelete:Z
      86: invokevirtual #24                 // Method org/hibernate/mapping/OneToOne.setCascadeDeleteEnabled:(Z)V
      89: aload_0
      90: getfield      #11                 // Field optional:Z
      93: ifne          101
      96: aload_2
      97: iconst_1
      98: invokevirtual #25                 // Method org/hibernate/mapping/OneToOne.setConstrained:(Z)V
     101: aload_2
     102: invokevirtual #26                 // Method org/hibernate/mapping/OneToOne.isReferenceToPrimaryKey:()Z
     105: ifeq          118
     108: aload_2
     109: getstatic     #27                 // Field org/hibernate/type/ForeignKeyDirection.TO_PARENT:Lorg/hibernate/type/ForeignKeyDirection;
     112: invokevirtual #28                 // Method org/hibernate/mapping/OneToOne.setForeignKeyType:(Lorg/hibernate/type/ForeignKeyDirection;)V
     115: goto          138
     118: aload_2
     119: aload_2
     120: invokevirtual #29                 // Method org/hibernate/mapping/OneToOne.isConstrained:()Z
     123: ifeq          132
     126: getstatic     #30                 // Field org/hibernate/type/ForeignKeyDirection.FROM_PARENT:Lorg/hibernate/type/ForeignKeyDirection;
     129: goto          135
     132: getstatic     #27                 // Field org/hibernate/type/ForeignKeyDirection.TO_PARENT:Lorg/hibernate/type/ForeignKeyDirection;
     135: invokevirtual #28                 // Method org/hibernate/mapping/OneToOne.setForeignKeyType:(Lorg/hibernate/type/ForeignKeyDirection;)V
     138: new           #31                 // class org/hibernate/cfg/annotations/PropertyBinder
     141: dup
     142: invokespecial #32                 // Method org/hibernate/cfg/annotations/PropertyBinder."<init>":()V
     145: astore        5
     147: aload         5
     149: aload_3
     150: invokevirtual #33                 // Method org/hibernate/cfg/annotations/PropertyBinder.setName:(Ljava/lang/String;)V
     153: aload         5
     155: aload_2
     156: invokevirtual #34                 // Method org/hibernate/cfg/annotations/PropertyBinder.setValue:(Lorg/hibernate/mapping/Value;)V
     159: aload         5
     161: aload_0
     162: getfield      #12                 // Field cascadeStrategy:Ljava/lang/String;
     165: invokevirtual #35                 // Method org/hibernate/cfg/annotations/PropertyBinder.setCascade:(Ljava/lang/String;)V
     168: aload         5
     170: aload_0
     171: getfield      #8                  // Field inferredData:Lorg/hibernate/cfg/PropertyData;
     174: invokeinterface #36,  1           // InterfaceMethod org/hibernate/cfg/PropertyData.getDefaultAccess:()Lorg/hibernate/cfg/AccessType;
     179: invokevirtual #37                 // Method org/hibernate/cfg/annotations/PropertyBinder.setAccessType:(Lorg/hibernate/cfg/AccessType;)V
     182: aload_0
     183: getfield      #8                  // Field inferredData:Lorg/hibernate/cfg/PropertyData;
     186: invokeinterface #22,  1           // InterfaceMethod org/hibernate/cfg/PropertyData.getProperty:()Lorg/hibernate/annotations/common/reflection/XProperty;
     191: ldc           #38                 // class org/hibernate/annotations/LazyGroup
     193: invokeinterface #39,  2           // InterfaceMethod org/hibernate/annotations/common/reflection/XProperty.getAnnotation:(Ljava/lang/Class;)Ljava/lang/annotation/Annotation;
     198: checkcast     #38                 // class org/hibernate/annotations/LazyGroup
     201: astore        6
     203: aload         6
     205: ifnull        220
     208: aload         5
     210: aload         6
     212: invokeinterface #40,  1           // InterfaceMethod org/hibernate/annotations/LazyGroup.value:()Ljava/lang/String;
     217: invokevirtual #41                 // Method org/hibernate/cfg/annotations/PropertyBinder.setLazyGroup:(Ljava/lang/String;)V
     220: aload         5
     222: invokevirtual #42                 // Method org/hibernate/cfg/annotations/PropertyBinder.makeProperty:()Lorg/hibernate/mapping/Property;
     225: astore        7
     227: aload         7
     229: aload_0
     230: getfield      #11                 // Field optional:Z
     233: invokevirtual #43                 // Method org/hibernate/mapping/Property.setOptional:(Z)V
     236: aload_0
     237: getfield      #4                  // Field mappedBy:Ljava/lang/String;
     240: invokestatic  #44                 // Method org/hibernate/cfg/BinderHelper.isEmptyAnnotationValue:(Ljava/lang/String;)Z
     243: ifeq          339
     246: iconst_1
     247: istore        8
     249: iload         8
     251: ifeq          336
     254: aload_0
     255: getfield      #5                  // Field propertyHolder:Lorg/hibernate/cfg/PropertyHolder;
     258: invokeinterface #45,  1           // InterfaceMethod org/hibernate/cfg/PropertyHolder.getPath:()Ljava/lang/String;
     263: aload_3
     264: invokestatic  #46                 // Method org/hibernate/internal/util/StringHelper.qualify:(Ljava/lang/String;Ljava/lang/String;)Ljava/lang/String;
     267: astore        9
     269: new           #47                 // class org/hibernate/cfg/ToOneFkSecondPass
     272: dup
     273: aload_2
     274: aload_0
     275: getfield      #13                 // Field joinColumns:[Lorg/hibernate/cfg/Ejb3JoinColumn;
     278: aload_0
     279: getfield      #11                 // Field optional:Z
     282: ifne          289
     285: iconst_1
     286: goto          290
     289: iconst_0
     290: aload_0
     291: getfield      #5                  // Field propertyHolder:Lorg/hibernate/cfg/PropertyHolder;
     294: invokeinterface #48,  1           // InterfaceMethod org/hibernate/cfg/PropertyHolder.getEntityOwnerClassName:()Ljava/lang/String;
     299: aload         9
     301: aload_0
     302: getfield      #6                  // Field buildingContext:Lorg/hibernate/boot/spi/MetadataBuildingContext;
     305: invokespecial #49                 // Method org/hibernate/cfg/ToOneFkSecondPass."<init>":(Lorg/hibernate/mapping/ToOne;[Lorg/hibernate/cfg/Ejb3JoinColumn;ZLjava/lang/String;Ljava/lang/String;Lorg/hibernate/boot/spi/MetadataBuildingContext;)V
     308: astore        10
     310: aload         10
     312: aload_1
     313: invokevirtual #50                 // Method org/hibernate/cfg/ToOneFkSecondPass.doSecondPass:(Ljava/util/Map;)V
     316: aload_0
     317: getfield      #5                  // Field propertyHolder:Lorg/hibernate/cfg/PropertyHolder;
     320: aload         7
     322: aload_0
     323: getfield      #8                  // Field inferredData:Lorg/hibernate/cfg/PropertyData;
     326: invokeinterface #51,  1           // InterfaceMethod org/hibernate/cfg/PropertyData.getDeclaringClass:()Lorg/hibernate/annotations/common/reflection/XClass;
     331: invokeinterface #52,  3           // InterfaceMethod org/hibernate/cfg/PropertyHolder.addProperty:(Lorg/hibernate/mapping/Property;Lorg/hibernate/annotations/common/reflection/XClass;)V
     336: goto          1101
     339: aload_1
     340: aload_2
     341: invokevirtual #53                 // Method org/hibernate/mapping/OneToOne.getReferencedEntityName:()Ljava/lang/String;
     344: invokeinterface #54,  2           // InterfaceMethod java/util/Map.get:(Ljava/lang/Object;)Ljava/lang/Object;
     349: checkcast     #55                 // class org/hibernate/mapping/PersistentClass
     352: astore        8
     354: aload         8
     356: ifnonnull     389
     359: new           #56                 // class org/hibernate/MappingException
     362: dup
     363: new           #57                 // class java/lang/StringBuilder
     366: dup
     367: invokespecial #58                 // Method java/lang/StringBuilder."<init>":()V
     370: ldc           #59                 // String Unable to find entity:
     372: invokevirtual #60                 // Method java/lang/StringBuilder.append:(Ljava/lang/String;)Ljava/lang/StringBuilder;
     375: aload_2
     376: invokevirtual #53                 // Method org/hibernate/mapping/OneToOne.getReferencedEntityName:()Ljava/lang/String;
     379: invokevirtual #60                 // Method java/lang/StringBuilder.append:(Ljava/lang/String;)Ljava/lang/StringBuilder;
     382: invokevirtual #61                 // Method java/lang/StringBuilder.toString:()Ljava/lang/String;
     385: invokespecial #62                 // Method org/hibernate/MappingException."<init>":(Ljava/lang/String;)V
     388: athrow
     389: aload         8
     391: aload_0
     392: getfield      #4                  // Field mappedBy:Ljava/lang/String;
     395: invokestatic  #63                 // Method org/hibernate/cfg/BinderHelper.findPropertyByName:(Lorg/hibernate/mapping/PersistentClass;Ljava/lang/String;)Lorg/hibernate/mapping/Property;
     398: astore        9
     400: goto          461
     403: astore        10
     405: new           #64                 // class org/hibernate/AnnotationException
     408: dup
     409: new           #57                 // class java/lang/StringBuilder
     412: dup
     413: invokespecial #58                 // Method java/lang/StringBuilder."<init>":()V
     416: ldc           #65                 // String Unknown mappedBy in:
     418: invokevirtual #60                 // Method java/lang/StringBuilder.append:(Ljava/lang/String;)Ljava/lang/StringBuilder;
     421: aload_0
     422: getfield      #2                  // Field ownerEntity:Ljava/lang/String;
     425: aload_0
     426: getfield      #3                  // Field ownerProperty:Ljava/lang/String;
     429: invokestatic  #46                 // Method org/hibernate/internal/util/StringHelper.qualify:(Ljava/lang/String;Ljava/lang/String;)Ljava/lang/String;
     432: invokevirtual #60                 // Method java/lang/StringBuilder.append:(Ljava/lang/String;)Ljava/lang/StringBuilder;
     435: ldc           #66                 // String , referenced property unknown:
     437: invokevirtual #60                 // Method java/lang/StringBuilder.append:(Ljava/lang/String;)Ljava/lang/StringBuilder;
     440: aload_2
     441: invokevirtual #53                 // Method org/hibernate/mapping/OneToOne.getReferencedEntityName:()Ljava/lang/String;
     444: aload_0
     445: getfield      #4                  // Field mappedBy:Ljava/lang/String;
     448: invokestatic  #46                 // Method org/hibernate/internal/util/StringHelper.qualify:(Ljava/lang/String;Ljava/lang/String;)Ljava/lang/String;
     451: invokevirtual #60                 // Method java/lang/StringBuilder.append:(Ljava/lang/String;)Ljava/lang/StringBuilder;
     454: invokevirtual #61                 // Method java/lang/StringBuilder.toString:()Ljava/lang/String;
     457: invokespecial #67                 // Method org/hibernate/AnnotationException."<init>":(Ljava/lang/String;)V
     460: athrow
     461: aload         9
     463: ifnonnull     522
     466: new           #64                 // class org/hibernate/AnnotationException
     469: dup
     470: new           #57                 // class java/lang/StringBuilder
     473: dup
     474: invokespecial #58                 // Method java/lang/StringBuilder."<init>":()V
     477: ldc           #65                 // String Unknown mappedBy in:
     479: invokevirtual #60                 // Method java/lang/StringBuilder.append:(Ljava/lang/String;)Ljava/lang/StringBuilder;
     482: aload_0
     483: getfield      #2                  // Field ownerEntity:Ljava/lang/String;
     486: aload_0
     487: getfield      #3                  // Field ownerProperty:Ljava/lang/String;
     490: invokestatic  #46                 // Method org/hibernate/internal/util/StringHelper.qualify:(Ljava/lang/String;Ljava/lang/String;)Ljava/lang/String;
     493: invokevirtual #60                 // Method java/lang/StringBuilder.append:(Ljava/lang/String;)Ljava/lang/StringBuilder;
     496: ldc           #66                 // String , referenced property unknown:
     498: invokevirtual #60                 // Method java/lang/StringBuilder.append:(Ljava/lang/String;)Ljava/lang/StringBuilder;
     501: aload_2
     502: invokevirtual #53                 // Method org/hibernate/mapping/OneToOne.getReferencedEntityName:()Ljava/lang/String;
     505: aload_0
     506: getfield      #4                  // Field mappedBy:Ljava/lang/String;
     509: invokestatic  #46                 // Method org/hibernate/internal/util/StringHelper.qualify:(Ljava/lang/String;Ljava/lang/String;)Ljava/lang/String;
     512: invokevirtual #60                 // Method java/lang/StringBuilder.append:(Ljava/lang/String;)Ljava/lang/StringBuilder;
     515: invokevirtual #61                 // Method java/lang/StringBuilder.toString:()Ljava/lang/String;
     518: invokespecial #67                 // Method org/hibernate/AnnotationException."<init>":(Ljava/lang/String;)V
     521: athrow
     522: aload         9
     524: invokevirtual #68                 // Method org/hibernate/mapping/Property.getValue:()Lorg/hibernate/mapping/Value;
     527: instanceof    #14                 // class org/hibernate/mapping/OneToOne
     530: ifeq          556
     533: aload_0
     534: getfield      #5                  // Field propertyHolder:Lorg/hibernate/cfg/PropertyHolder;
     537: aload         7
     539: aload_0
     540: getfield      #8                  // Field inferredData:Lorg/hibernate/cfg/PropertyData;
     543: invokeinterface #51,  1           // InterfaceMethod org/hibernate/cfg/PropertyData.getDeclaringClass:()Lorg/hibernate/annotations/common/reflection/XClass;
     548: invokeinterface #52,  3           // InterfaceMethod org/hibernate/cfg/PropertyHolder.addProperty:(Lorg/hibernate/mapping/Property;Lorg/hibernate/annotations/common/reflection/XClass;)V
     553: goto          1101
     556: aload         9
     558: invokevirtual #68                 // Method org/hibernate/mapping/Property.getValue:()Lorg/hibernate/mapping/Value;
     561: instanceof    #69                 // class org/hibernate/mapping/ManyToOne
     564: ifeq          1044
     567: aload         8
     569: invokevirtual #70                 // Method org/hibernate/mapping/PersistentClass.getJoinIterator:()Ljava/util/Iterator;
     572: astore        10
     574: aconst_null
     575: astore        11
     577: aload         10
     579: invokeinterface #71,  1           // InterfaceMethod java/util/Iterator.hasNext:()Z
     584: ifeq          619
     587: aload         10
     589: invokeinterface #72,  1           // InterfaceMethod java/util/Iterator.next:()Ljava/lang/Object;
     594: checkcast     #73                 // class org/hibernate/mapping/Join
     597: astore        12
     599: aload         12
     601: aload         9
     603: invokevirtual #74                 // Method org/hibernate/mapping/Join.containsProperty:(Lorg/hibernate/mapping/Property;)Z
     606: ifeq          616
     609: aload         12
     611: astore        11
     613: goto          619
     616: goto          577
     619: aload         11
     621: ifnull        896
     624: aload_0
     625: aload_1
     626: aload_0
     627: getfield      #2                  // Field ownerEntity:Ljava/lang/String;
     630: invokeinterface #54,  2           // InterfaceMethod java/util/Map.get:(Ljava/lang/Object;)Ljava/lang/Object;
     635: checkcast     #55                 // class org/hibernate/mapping/PersistentClass
     638: aload         9
     640: aload         11
     642: invokespecial #75                 // Method buildJoinFromMappedBySide:(Lorg/hibernate/mapping/PersistentClass;Lorg/hibernate/mapping/Property;Lorg/hibernate/mapping/Join;)Lorg/hibernate/mapping/Join;
     645: astore        12
     647: new           #69                 // class org/hibernate/mapping/ManyToOne
     650: dup
     651: aload_0
     652: getfield      #6                  // Field buildingContext:Lorg/hibernate/boot/spi/MetadataBuildingContext;
     655: aload         12
     657: invokevirtual #76                 // Method org/hibernate/mapping/Join.getTable:()Lorg/hibernate/mapping/Table;
     660: invokespecial #77                 // Method org/hibernate/mapping/ManyToOne."<init>":(Lorg/hibernate/boot/spi/MetadataBuildingContext;Lorg/hibernate/mapping/Table;)V
     663: astore        13
     665: aload         13
     667: aload_0
     668: getfield      #7                  // Field ignoreNotFound:Z
     671: invokevirtual #78                 // Method org/hibernate/mapping/ManyToOne.setIgnoreNotFound:(Z)V
     674: aload         13
     676: aload_2
     677: invokevirtual #79                 // Method org/hibernate/mapping/OneToOne.isCascadeDeleteEnabled:()Z
     680: invokevirtual #80                 // Method org/hibernate/mapping/ManyToOne.setCascadeDeleteEnabled:(Z)V
     683: aload         13
     685: aload_2
     686: invokevirtual #81                 // Method org/hibernate/mapping/OneToOne.getFetchMode:()Lorg/hibernate/FetchMode;
     689: invokevirtual #82                 // Method org/hibernate/mapping/ManyToOne.setFetchMode:(Lorg/hibernate/FetchMode;)V
     692: aload         13
     694: aload_2
     695: invokevirtual #83                 // Method org/hibernate/mapping/OneToOne.isLazy:()Z
     698: invokevirtual #84                 // Method org/hibernate/mapping/ManyToOne.setLazy:(Z)V
     701: aload         13
     703: aload_2
     704: invokevirtual #53                 // Method org/hibernate/mapping/OneToOne.getReferencedEntityName:()Ljava/lang/String;
     707: invokevirtual #85                 // Method org/hibernate/mapping/ManyToOne.setReferencedEntityName:(Ljava/lang/String;)V
     710: aload         13
     712: aload_2
     713: invokevirtual #86                 // Method org/hibernate/mapping/OneToOne.isUnwrapProxy:()Z
     716: invokevirtual #87                 // Method org/hibernate/mapping/ManyToOne.setUnwrapProxy:(Z)V
     719: aload         7
     721: aload         13
     723: invokevirtual #88                 // Method org/hibernate/mapping/Property.setValue:(Lorg/hibernate/mapping/Value;)V
     726: aload         11
     728: invokevirtual #89                 // Method org/hibernate/mapping/Join.getKey:()Lorg/hibernate/mapping/KeyValue;
     731: invokeinterface #90,  1           // InterfaceMethod org/hibernate/mapping/KeyValue.getColumnIterator:()Ljava/util/Iterator;
     736: astore        14
     738: aload         14
     740: invokeinterface #71,  1           // InterfaceMethod java/util/Iterator.hasNext:()Z
     745: ifeq          886
     748: aload         14
     750: invokeinterface #72,  1           // InterfaceMethod java/util/Iterator.next:()Ljava/lang/Object;
     755: checkcast     #91                 // class org/hibernate/mapping/Column
     758: astore        15
     760: new           #91                 // class org/hibernate/mapping/Column
     763: dup
     764: invokespecial #92                 // Method org/hibernate/mapping/Column."<init>":()V
     767: astore        16
     769: aload         16
     771: aload         15
     773: invokevirtual #93                 // Method org/hibernate/mapping/Column.getLength:()I
     776: invokevirtual #94                 // Method org/hibernate/mapping/Column.setLength:(I)V
     779: aload         16
     781: aload         15
     783: invokevirtual #95                 // Method org/hibernate/mapping/Column.getScale:()I
     786: invokevirtual #96                 // Method org/hibernate/mapping/Column.setScale:(I)V
     789: aload         16
     791: aload         13
     793: invokevirtual #97                 // Method org/hibernate/mapping/Column.setValue:(Lorg/hibernate/mapping/Value;)V
     796: aload         16
     798: aload         15
     800: invokevirtual #98                 // Method org/hibernate/mapping/Column.getQuotedName:()Ljava/lang/String;
     803: invokevirtual #99                 // Method org/hibernate/mapping/Column.setName:(Ljava/lang/String;)V
     806: aload         16
     808: aload         15
     810: invokevirtual #100                // Method org/hibernate/mapping/Column.isNullable:()Z
     813: invokevirtual #101                // Method org/hibernate/mapping/Column.setNullable:(Z)V
     816: aload         16
     818: aload         15
     820: invokevirtual #102                // Method org/hibernate/mapping/Column.getPrecision:()I
     823: invokevirtual #103                // Method org/hibernate/mapping/Column.setPrecision:(I)V
     826: aload         16
     828: aload         15
     830: invokevirtual #104                // Method org/hibernate/mapping/Column.isUnique:()Z
     833: invokevirtual #105                // Method org/hibernate/mapping/Column.setUnique:(Z)V
     836: aload         16
     838: aload         15
     840: invokevirtual #106                // Method org/hibernate/mapping/Column.getSqlType:()Ljava/lang/String;
     843: invokevirtual #107                // Method org/hibernate/mapping/Column.setSqlType:(Ljava/lang/String;)V
     846: aload         16
     848: aload         15
     850: invokevirtual #108                // Method org/hibernate/mapping/Column.getCheckConstraint:()Ljava/lang/String;
     853: invokevirtual #109                // Method org/hibernate/mapping/Column.setCheckConstraint:(Ljava/lang/String;)V
     856: aload         16
     858: aload         15
     860: invokevirtual #110                // Method org/hibernate/mapping/Column.getComment:()Ljava/lang/String;
     863: invokevirtual #111                // Method org/hibernate/mapping/Column.setComment:(Ljava/lang/String;)V
     866: aload         16
     868: aload         15
     870: invokevirtual #112                // Method org/hibernate/mapping/Column.getDefaultValue:()Ljava/lang/String;
     873: invokevirtual #113                // Method org/hibernate/mapping/Column.setDefaultValue:(Ljava/lang/String;)V
     876: aload         13
     878: aload         16
     880: invokevirtual #114                // Method org/hibernate/mapping/ManyToOne.addColumn:(Lorg/hibernate/mapping/Column;)V
     883: goto          738
     886: aload         12
     888: aload         7
     890: invokevirtual #115                // Method org/hibernate/mapping/Join.addProperty:(Lorg/hibernate/mapping/Property;)V
     893: goto          916
     896: aload_0
     897: getfield      #5                  // Field propertyHolder:Lorg/hibernate/cfg/PropertyHolder;
     900: aload         7
     902: aload_0
     903: getfield      #8                  // Field inferredData:Lorg/hibernate/cfg/PropertyData;
     906: invokeinterface #51,  1           // InterfaceMethod org/hibernate/cfg/PropertyData.getDeclaringClass:()Lorg/hibernate/annotations/common/reflection/XClass;
     911: invokeinterface #52,  3           // InterfaceMethod org/hibernate/cfg/PropertyHolder.addProperty:(Lorg/hibernate/mapping/Property;Lorg/hibernate/annotations/common/reflection/XClass;)V
     916: aload_2
     917: aload_0
     918: getfield      #4                  // Field mappedBy:Ljava/lang/String;
     921: invokevirtual #116                // Method org/hibernate/mapping/OneToOne.setReferencedPropertyName:(Ljava/lang/String;)V
     924: iconst_0
     925: istore        12
     927: aload         8
     929: invokevirtual #117                // Method org/hibernate/mapping/PersistentClass.getIdentifier:()Lorg/hibernate/mapping/KeyValue;
     932: instanceof    #118                // class org/hibernate/mapping/Component
     935: ifeq          960
     938: aload         8
     940: invokevirtual #117                // Method org/hibernate/mapping/PersistentClass.getIdentifier:()Lorg/hibernate/mapping/KeyValue;
     943: checkcast     #118                // class org/hibernate/mapping/Component
     946: aload_0
     947: getfield      #4                  // Field mappedBy:Ljava/lang/String;
     950: invokevirtual #119                // Method org/hibernate/mapping/Component.getProperty:(Ljava/lang/String;)Lorg/hibernate/mapping/Property;
     953: ifnull        960
     956: iconst_1
     957: goto          961
     960: iconst_0
     961: istore        12
     963: goto          968
     966: astore        13
     968: iload         12
     970: ifne          980
     973: aload_0
     974: getfield      #4                  // Field mappedBy:Ljava/lang/String;
     977: ifnonnull     984
     980: iconst_1
     981: goto          985
     984: iconst_0
     985: istore        13
     987: aload_2
     988: iload         13
     990: invokevirtual #120                // Method org/hibernate/mapping/OneToOne.setReferenceToPrimaryKey:(Z)V
     993: iload         12
     995: ifeq          1010
     998: aload         9
    1000: invokevirtual #68                 // Method org/hibernate/mapping/Property.getValue:()Lorg/hibernate/mapping/Value;
    1003: checkcast     #69                 // class org/hibernate/mapping/ManyToOne
    1006: iconst_0
    1007: invokevirtual #121                // Method org/hibernate/mapping/ManyToOne.setReferenceToPrimaryKey:(Z)V
    1010: aload_2
    1011: invokevirtual #122                // Method org/hibernate/mapping/OneToOne.getReferencedPropertyName:()Ljava/lang/String;
    1014: astore        14
    1016: aload         14
    1018: ifnull        1041
    1021: aload_0
    1022: getfield      #6                  // Field buildingContext:Lorg/hibernate/boot/spi/MetadataBuildingContext;
    1025: invokeinterface #123,  1          // InterfaceMethod org/hibernate/boot/spi/MetadataBuildingContext.getMetadataCollector:()Lorg/hibernate/boot/spi/InFlightMetadataCollector;
    1030: aload_2
    1031: invokevirtual #53                 // Method org/hibernate/mapping/OneToOne.getReferencedEntityName:()Ljava/lang/String;
    1034: aload         14
    1036: invokeinterface #124,  3          // InterfaceMethod org/hibernate/boot/spi/InFlightMetadataCollector.addUniquePropertyReference:(Ljava/lang/String;Ljava/lang/String;)V
    1041: goto          1101
    1044: new           #64                 // class org/hibernate/AnnotationException
    1047: dup
    1048: new           #57                 // class java/lang/StringBuilder
    1051: dup
    1052: invokespecial #58                 // Method java/lang/StringBuilder."<init>":()V
    1055: ldc           #125                // String Referenced property not a (One|Many)ToOne:
    1057: invokevirtual #60                 // Method java/lang/StringBuilder.append:(Ljava/lang/String;)Ljava/lang/StringBuilder;
    1060: aload         8
    1062: invokevirtual #126                // Method org/hibernate/mapping/PersistentClass.getEntityName:()Ljava/lang/String;
    1065: aload_0
    1066: getfield      #4                  // Field mappedBy:Ljava/lang/String;
    1069: invokestatic  #46                 // Method org/hibernate/internal/util/StringHelper.qualify:(Ljava/lang/String;Ljava/lang/String;)Ljava/lang/String;
    1072: invokevirtual #60                 // Method java/lang/StringBuilder.append:(Ljava/lang/String;)Ljava/lang/StringBuilder;
    1075: ldc           #127                // String  in mappedBy of
    1077: invokevirtual #60                 // Method java/lang/StringBuilder.append:(Ljava/lang/String;)Ljava/lang/StringBuilder;
    1080: aload_0
    1081: getfield      #2                  // Field ownerEntity:Ljava/lang/String;
    1084: aload_0
    1085: getfield      #3                  // Field ownerProperty:Ljava/lang/String;
    1088: invokestatic  #46                 // Method org/hibernate/internal/util/StringHelper.qualify:(Ljava/lang/String;Ljava/lang/String;)Ljava/lang/String;
    1091: invokevirtual #60                 // Method java/lang/StringBuilder.append:(Ljava/lang/String;)Ljava/lang/StringBuilder;
    1094: invokevirtual #61                 // Method java/lang/StringBuilder.toString:()Ljava/lang/String;
    1097: invokespecial #67                 // Method org/hibernate/AnnotationException."<init>":(Ljava/lang/String;)V
    1100: athrow
    1101: aload_0
    1102: getfield      #8                  // Field inferredData:Lorg/hibernate/cfg/PropertyData;
    1105: invokeinterface #22,  1           // InterfaceMethod org/hibernate/cfg/PropertyData.getProperty:()Lorg/hibernate/annotations/common/reflection/XProperty;
    1110: ldc           #128                // class org/hibernate/annotations/ForeignKey
    1112: invokeinterface #39,  2           // InterfaceMethod org/hibernate/annotations/common/reflection/XProperty.getAnnotation:(Ljava/lang/Class;)Ljava/lang/annotation/Annotation;
    1117: checkcast     #128                // class org/hibernate/annotations/ForeignKey
    1120: astore        8
    1122: aload         8
    1124: ifnull        1154
    1127: aload         8
    1129: invokeinterface #129,  1          // InterfaceMethod org/hibernate/annotations/ForeignKey.name:()Ljava/lang/String;
    1134: invokestatic  #44                 // Method org/hibernate/cfg/BinderHelper.isEmptyAnnotationValue:(Ljava/lang/String;)Z
    1137: ifne          1154
    1140: aload_2
    1141: aload         8
    1143: invokeinterface #129,  1          // InterfaceMethod org/hibernate/annotations/ForeignKey.name:()Ljava/lang/String;
    1148: invokevirtual #130                // Method org/hibernate/mapping/OneToOne.setForeignKeyName:(Ljava/lang/String;)V
    1151: goto          1230
    1154: aload_0
    1155: getfield      #8                  // Field inferredData:Lorg/hibernate/cfg/PropertyData;
    1158: invokeinterface #22,  1           // InterfaceMethod org/hibernate/cfg/PropertyData.getProperty:()Lorg/hibernate/annotations/common/reflection/XProperty;
    1163: ldc           #131                // class javax/persistence/ForeignKey
    1165: invokeinterface #39,  2           // InterfaceMethod org/hibernate/annotations/common/reflection/XProperty.getAnnotation:(Ljava/lang/Class;)Ljava/lang/annotation/Annotation;
    1170: checkcast     #131                // class javax/persistence/ForeignKey
    1173: astore        9
    1175: aload         9
    1177: ifnull        1230
    1180: aload         9
    1182: invokeinterface #132,  1          // InterfaceMethod javax/persistence/ForeignKey.value:()Ljavax/persistence/ConstraintMode;
    1187: getstatic     #133                // Field javax/persistence/ConstraintMode.NO_CONSTRAINT:Ljavax/persistence/ConstraintMode;
    1190: if_acmpne     1202
    1193: aload_2
    1194: ldc           #134                // String none
    1196: invokevirtual #130                // Method org/hibernate/mapping/OneToOne.setForeignKeyName:(Ljava/lang/String;)V
    1199: goto          1230
    1202: aload_2
    1203: aload         9
    1205: invokeinterface #135,  1          // InterfaceMethod javax/persistence/ForeignKey.name:()Ljava/lang/String;
    1210: invokestatic  #136                // Method org/hibernate/internal/util/StringHelper.nullIfEmpty:(Ljava/lang/String;)Ljava/lang/String;
    1213: invokevirtual #130                // Method org/hibernate/mapping/OneToOne.setForeignKeyName:(Ljava/lang/String;)V
    1216: aload_2
    1217: aload         9
    1219: invokeinterface #137,  1          // InterfaceMethod javax/persistence/ForeignKey.foreignKeyDefinition:()Ljava/lang/String;
    1224: invokestatic  #136                // Method org/hibernate/internal/util/StringHelper.nullIfEmpty:(Ljava/lang/String;)Ljava/lang/String;
    1227: invokevirtual #138                // Method org/hibernate/mapping/OneToOne.setForeignKeyDefinition:(Ljava/lang/String;)V
    1230: return
    Exception table:
       from    to  target type
         354   400   403   Class org/hibernate/MappingException
         927   963   966   Class org/hibernate/MappingException

  private org.hibernate.mapping.Join buildJoinFromMappedBySide(org.hibernate.mapping.PersistentClass, org.hibernate.mapping.Property, org.hibernate.mapping.Join);
    Code:
       0: new           #73                 // class org/hibernate/mapping/Join
       3: dup
       4: invokespecial #139                // Method org/hibernate/mapping/Join."<init>":()V
       7: astore        4
       9: aload         4
      11: aload_1
      12: invokevirtual #140                // Method org/hibernate/mapping/Join.setPersistentClass:(Lorg/hibernate/mapping/PersistentClass;)V
      15: aload         4
      17: aload_3
      18: invokevirtual #76                 // Method org/hibernate/mapping/Join.getTable:()Lorg/hibernate/mapping/Table;
      21: invokevirtual #141                // Method org/hibernate/mapping/Join.setTable:(Lorg/hibernate/mapping/Table;)V
      24: aload         4
      26: iconst_1
      27: invokevirtual #142                // Method org/hibernate/mapping/Join.setInverse:(Z)V
      30: new           #143                // class org/hibernate/mapping/DependantValue
      33: dup
      34: aload_0
      35: getfield      #6                  // Field buildingContext:Lorg/hibernate/boot/spi/MetadataBuildingContext;
      38: aload         4
      40: invokevirtual #76                 // Method org/hibernate/mapping/Join.getTable:()Lorg/hibernate/mapping/Table;
      43: aload_1
      44: invokevirtual #117                // Method org/hibernate/mapping/PersistentClass.getIdentifier:()Lorg/hibernate/mapping/KeyValue;
      47: invokespecial #144                // Method org/hibernate/mapping/DependantValue."<init>":(Lorg/hibernate/boot/spi/MetadataBuildingContext;Lorg/hibernate/mapping/Table;Lorg/hibernate/mapping/KeyValue;)V
      50: astore        5
      52: aload         4
      54: aload         5
      56: invokevirtual #145                // Method org/hibernate/mapping/Join.setKey:(Lorg/hibernate/mapping/KeyValue;)V
      59: aload         4
      61: iconst_0
      62: invokevirtual #146                // Method org/hibernate/mapping/Join.setSequentialSelect:(Z)V
      65: aload         4
      67: iconst_1
      68: invokevirtual #147                // Method org/hibernate/mapping/Join.setOptional:(Z)V
      71: aload         5
      73: iconst_0
      74: invokevirtual #148                // Method org/hibernate/mapping/SimpleValue.setCascadeDeleteEnabled:(Z)V
      77: aload_2
      78: invokevirtual #68                 // Method org/hibernate/mapping/Property.getValue:()Lorg/hibernate/mapping/Value;
      81: invokeinterface #149,  1          // InterfaceMethod org/hibernate/mapping/Value.getColumnIterator:()Ljava/util/Iterator;
      86: astore        6
      88: aload         6
      90: invokeinterface #71,  1           // InterfaceMethod java/util/Iterator.hasNext:()Z
      95: ifeq          236
      98: aload         6
     100: invokeinterface #72,  1           // InterfaceMethod java/util/Iterator.next:()Ljava/lang/Object;
     105: checkcast     #91                 // class org/hibernate/mapping/Column
     108: astore        7
     110: new           #91                 // class org/hibernate/mapping/Column
     113: dup
     114: invokespecial #92                 // Method org/hibernate/mapping/Column."<init>":()V
     117: astore        8
     119: aload         8
     121: aload         7
     123: invokevirtual #93                 // Method org/hibernate/mapping/Column.getLength:()I
     126: invokevirtual #94                 // Method org/hibernate/mapping/Column.setLength:(I)V
     129: aload         8
     131: aload         7
     133: invokevirtual #95                 // Method org/hibernate/mapping/Column.getScale:()I
     136: invokevirtual #96                 // Method org/hibernate/mapping/Column.setScale:(I)V
     139: aload         8
     141: aload         5
     143: invokevirtual #97                 // Method org/hibernate/mapping/Column.setValue:(Lorg/hibernate/mapping/Value;)V
     146: aload         8
     148: aload         7
     150: invokevirtual #98                 // Method org/hibernate/mapping/Column.getQuotedName:()Ljava/lang/String;
     153: invokevirtual #99                 // Method org/hibernate/mapping/Column.setName:(Ljava/lang/String;)V
     156: aload         8
     158: aload         7
     160: invokevirtual #100                // Method org/hibernate/mapping/Column.isNullable:()Z
     163: invokevirtual #101                // Method org/hibernate/mapping/Column.setNullable:(Z)V
     166: aload         8
     168: aload         7
     170: invokevirtual #102                // Method org/hibernate/mapping/Column.getPrecision:()I
     173: invokevirtual #103                // Method org/hibernate/mapping/Column.setPrecision:(I)V
     176: aload         8
     178: aload         7
     180: invokevirtual #104                // Method org/hibernate/mapping/Column.isUnique:()Z
     183: invokevirtual #105                // Method org/hibernate/mapping/Column.setUnique:(Z)V
     186: aload         8
     188: aload         7
     190: invokevirtual #106                // Method org/hibernate/mapping/Column.getSqlType:()Ljava/lang/String;
     193: invokevirtual #107                // Method org/hibernate/mapping/Column.setSqlType:(Ljava/lang/String;)V
     196: aload         8
     198: aload         7
     200: invokevirtual #108                // Method org/hibernate/mapping/Column.getCheckConstraint:()Ljava/lang/String;
     203: invokevirtual #109                // Method org/hibernate/mapping/Column.setCheckConstraint:(Ljava/lang/String;)V
     206: aload         8
     208: aload         7
     210: invokevirtual #110                // Method org/hibernate/mapping/Column.getComment:()Ljava/lang/String;
     213: invokevirtual #111                // Method org/hibernate/mapping/Column.setComment:(Ljava/lang/String;)V
     216: aload         8
     218: aload         7
     220: invokevirtual #112                // Method org/hibernate/mapping/Column.getDefaultValue:()Ljava/lang/String;
     223: invokevirtual #113                // Method org/hibernate/mapping/Column.setDefaultValue:(Ljava/lang/String;)V
     226: aload         5
     228: aload         8
     230: invokevirtual #150                // Method org/hibernate/mapping/SimpleValue.addColumn:(Lorg/hibernate/mapping/Column;)V
     233: goto          88
     236: aload_1
     237: aload         4
     239: invokevirtual #151                // Method org/hibernate/mapping/PersistentClass.addJoin:(Lorg/hibernate/mapping/Join;)V
     242: aload         4
     244: areturn
}
