Compiled from "CharMatcher.java"
final class org.apache.jena.ext.com.google.common.base.CharMatcher$Is extends org.apache.jena.ext.com.google.common.base.CharMatcher$FastMatcher {
  private final char match;

  org.apache.jena.ext.com.google.common.base.CharMatcher$Is(char);
    Code:
       0: aload_0
       1: invokespecial #16                 // Method org/apache/jena/ext/com/google/common/base/CharMatcher$FastMatcher."<init>":()V
       4: aload_0
       5: iload_1
       6: putfield      #18                 // Field match:C
       9: return

  public boolean matches(char);
    Code:
       0: iload_1
       1: aload_0
       2: getfield      #18                 // Field match:C
       5: if_icmpne     12
       8: iconst_1
       9: goto          13
      12: iconst_0
      13: ireturn

  public java.lang.String replaceFrom(java.lang.CharSequence, char);
    Code:
       0: aload_1
       1: invokeinterface #31,  1           // InterfaceMethod java/lang/CharSequence.toString:()Ljava/lang/String;
       6: aload_0
       7: getfield      #18                 // Field match:C
      10: iload_2
      11: invokevirtual #37                 // Method java/lang/String.replace:(CC)Ljava/lang/String;
      14: areturn

  public org.apache.jena.ext.com.google.common.base.CharMatcher and(org.apache.jena.ext.com.google.common.base.CharMatcher);
    Code:
       0: aload_1
       1: aload_0
       2: getfield      #18                 // Field match:C
       5: invokevirtual #44                 // Method org/apache/jena/ext/com/google/common/base/CharMatcher.matches:(C)Z
       8: ifeq          15
      11: aload_0
      12: goto          18
      15: invokestatic  #48                 // Method none:()Lorg/apache/jena/ext/com/google/common/base/CharMatcher;
      18: areturn

  public org.apache.jena.ext.com.google.common.base.CharMatcher or(org.apache.jena.ext.com.google.common.base.CharMatcher);
    Code:
       0: aload_1
       1: aload_0
       2: getfield      #18                 // Field match:C
       5: invokevirtual #44                 // Method org/apache/jena/ext/com/google/common/base/CharMatcher.matches:(C)Z
       8: ifeq          15
      11: aload_1
      12: goto          20
      15: aload_0
      16: aload_1
      17: invokespecial #53                 // Method org/apache/jena/ext/com/google/common/base/CharMatcher$FastMatcher.or:(Lorg/apache/jena/ext/com/google/common/base/CharMatcher;)Lorg/apache/jena/ext/com/google/common/base/CharMatcher;
      20: areturn

  public org.apache.jena.ext.com.google.common.base.CharMatcher negate();
    Code:
       0: aload_0
       1: getfield      #18                 // Field match:C
       4: invokestatic  #58                 // Method isNot:(C)Lorg/apache/jena/ext/com/google/common/base/CharMatcher;
       7: areturn

  void setBits(java.util.BitSet);
    Code:
       0: aload_1
       1: aload_0
       2: getfield      #18                 // Field match:C
       5: invokevirtual #67                 // Method java/util/BitSet.set:(I)V
       8: return

  public java.lang.String toString();
    Code:
       0: new           #71                 // class java/lang/StringBuilder
       3: dup
       4: invokespecial #72                 // Method java/lang/StringBuilder."<init>":()V
       7: ldc           #74                 // String CharMatcher.is(\'
       9: invokevirtual #78                 // Method java/lang/StringBuilder.append:(Ljava/lang/String;)Ljava/lang/StringBuilder;
      12: aload_0
      13: getfield      #18                 // Field match:C
      16: invokestatic  #82                 // Method org/apache/jena/ext/com/google/common/base/CharMatcher.access$100:(C)Ljava/lang/String;
      19: invokevirtual #78                 // Method java/lang/StringBuilder.append:(Ljava/lang/String;)Ljava/lang/StringBuilder;
      22: ldc           #84                 // String \')
      24: invokevirtual #78                 // Method java/lang/StringBuilder.append:(Ljava/lang/String;)Ljava/lang/StringBuilder;
      27: invokevirtual #85                 // Method java/lang/StringBuilder.toString:()Ljava/lang/String;
      30: areturn

  public java.util.function.Predicate negate();
    Code:
       0: aload_0
       1: invokevirtual #88                 // Method negate:()Lorg/apache/jena/ext/com/google/common/base/CharMatcher;
       4: areturn
}
