Compiled from "Functions.java"
public final class org.apache.jena.ext.com.google.common.base.Functions {
  private org.apache.jena.ext.com.google.common.base.Functions();
    Code:
       0: aload_0
       1: invokespecial #36                 // Method java/lang/Object."<init>":()V
       4: return

  public static org.apache.jena.ext.com.google.common.base.Function<java.lang.Object, java.lang.String> toStringFunction();
    Code:
       0: getstatic     #44                 // Field org/apache/jena/ext/com/google/common/base/Functions$ToStringFunction.INSTANCE:Lorg/apache/jena/ext/com/google/common/base/Functions$ToStringFunction;
       3: areturn

  public static <E> org.apache.jena.ext.com.google.common.base.Function<E, E> identity();
    Code:
       0: getstatic     #48                 // Field org/apache/jena/ext/com/google/common/base/Functions$IdentityFunction.INSTANCE:Lorg/apache/jena/ext/com/google/common/base/Functions$IdentityFunction;
       3: areturn

  public static <K, V> org.apache.jena.ext.com.google.common.base.Function<K, V> forMap(java.util.Map<K, V>);
    Code:
       0: new           #25                 // class org/apache/jena/ext/com/google/common/base/Functions$FunctionForMapNoDefault
       3: dup
       4: aload_0
       5: invokespecial #53                 // Method org/apache/jena/ext/com/google/common/base/Functions$FunctionForMapNoDefault."<init>":(Ljava/util/Map;)V
       8: areturn

  public static <K, V> org.apache.jena.ext.com.google.common.base.Function<K, V> forMap(java.util.Map<K, ? extends V>, V);
    Code:
       0: new           #22                 // class org/apache/jena/ext/com/google/common/base/Functions$ForMapWithDefault
       3: dup
       4: aload_0
       5: aload_1
       6: invokespecial #61                 // Method org/apache/jena/ext/com/google/common/base/Functions$ForMapWithDefault."<init>":(Ljava/util/Map;Ljava/lang/Object;)V
       9: areturn

  public static <A, B, C> org.apache.jena.ext.com.google.common.base.Function<A, C> compose(org.apache.jena.ext.com.google.common.base.Function<B, C>, org.apache.jena.ext.com.google.common.base.Function<A, ? extends B>);
    Code:
       0: new           #19                 // class org/apache/jena/ext/com/google/common/base/Functions$FunctionComposition
       3: dup
       4: aload_0
       5: aload_1
       6: invokespecial #70                 // Method org/apache/jena/ext/com/google/common/base/Functions$FunctionComposition."<init>":(Lorg/apache/jena/ext/com/google/common/base/Function;Lorg/apache/jena/ext/com/google/common/base/Function;)V
       9: areturn

  public static <T> org.apache.jena.ext.com.google.common.base.Function<T, java.lang.Boolean> forPredicate(org.apache.jena.ext.com.google.common.base.Predicate<T>);
    Code:
       0: new           #16                 // class org/apache/jena/ext/com/google/common/base/Functions$PredicateFunction
       3: dup
       4: aload_0
       5: aconst_null
       6: invokespecial #80                 // Method org/apache/jena/ext/com/google/common/base/Functions$PredicateFunction."<init>":(Lorg/apache/jena/ext/com/google/common/base/Predicate;Lorg/apache/jena/ext/com/google/common/base/Functions$1;)V
       9: areturn

  public static <E> org.apache.jena.ext.com.google.common.base.Function<java.lang.Object, E> constant(E);
    Code:
       0: new           #13                 // class org/apache/jena/ext/com/google/common/base/Functions$ConstantFunction
       3: dup
       4: aload_0
       5: invokespecial #88                 // Method org/apache/jena/ext/com/google/common/base/Functions$ConstantFunction."<init>":(Ljava/lang/Object;)V
       8: areturn

  public static <T> org.apache.jena.ext.com.google.common.base.Function<java.lang.Object, T> forSupplier(org.apache.jena.ext.com.google.common.base.Supplier<T>);
    Code:
       0: new           #10                 // class org/apache/jena/ext/com/google/common/base/Functions$SupplierFunction
       3: dup
       4: aload_0
       5: aconst_null
       6: invokespecial #95                 // Method org/apache/jena/ext/com/google/common/base/Functions$SupplierFunction."<init>":(Lorg/apache/jena/ext/com/google/common/base/Supplier;Lorg/apache/jena/ext/com/google/common/base/Functions$1;)V
       9: areturn
}
