Compiled from "SpdyHeaderBlockZlibDecoder.java"
final class io.netty.handler.codec.spdy.SpdyHeaderBlockZlibDecoder extends io.netty.handler.codec.spdy.SpdyHeaderBlockRawDecoder {
  private static final int DEFAULT_BUFFER_CAPACITY;

  private static final io.netty.handler.codec.spdy.SpdyProtocolException INVALID_HEADER_BLOCK;

  private final java.util.zip.Inflater decompressor;

  private io.netty.buffer.ByteBuf decompressed;

  io.netty.handler.codec.spdy.SpdyHeaderBlockZlibDecoder(io.netty.handler.codec.spdy.SpdyVersion, int);
    Code:
       0: aload_0
       1: aload_1
       2: iload_2
       3: invokespecial #1                  // Method io/netty/handler/codec/spdy/SpdyHeaderBlockRawDecoder."<init>":(Lio/netty/handler/codec/spdy/SpdyVersion;I)V
       6: aload_0
       7: new           #2                  // class java/util/zip/Inflater
      10: dup
      11: invokespecial #3                  // Method java/util/zip/Inflater."<init>":()V
      14: putfield      #4                  // Field decompressor:Ljava/util/zip/Inflater;
      17: return

  void decode(io.netty.buffer.ByteBufAllocator, io.netty.buffer.ByteBuf, io.netty.handler.codec.spdy.SpdyHeadersFrame) throws java.lang.Exception;
    Code:
       0: aload_0
       1: aload_2
       2: invokespecial #5                  // Method setInput:(Lio/netty/buffer/ByteBuf;)I
       5: istore        4
       7: aload_0
       8: aload_1
       9: aload_3
      10: invokespecial #6                  // Method decompress:(Lio/netty/buffer/ByteBufAllocator;Lio/netty/handler/codec/spdy/SpdyHeadersFrame;)I
      13: istore        5
      15: iload         5
      17: ifgt          7
      20: aload_0
      21: getfield      #4                  // Field decompressor:Ljava/util/zip/Inflater;
      24: invokevirtual #7                  // Method java/util/zip/Inflater.getRemaining:()I
      27: ifeq          34
      30: getstatic     #8                  // Field INVALID_HEADER_BLOCK:Lio/netty/handler/codec/spdy/SpdyProtocolException;
      33: athrow
      34: aload_2
      35: iload         4
      37: invokevirtual #9                  // Method io/netty/buffer/ByteBuf.skipBytes:(I)Lio/netty/buffer/ByteBuf;
      40: pop
      41: return

  private int setInput(io.netty.buffer.ByteBuf);
    Code:
       0: aload_1
       1: invokevirtual #10                 // Method io/netty/buffer/ByteBuf.readableBytes:()I
       4: istore_2
       5: aload_1
       6: invokevirtual #11                 // Method io/netty/buffer/ByteBuf.hasArray:()Z
       9: ifeq          36
      12: aload_0
      13: getfield      #4                  // Field decompressor:Ljava/util/zip/Inflater;
      16: aload_1
      17: invokevirtual #12                 // Method io/netty/buffer/ByteBuf.array:()[B
      20: aload_1
      21: invokevirtual #13                 // Method io/netty/buffer/ByteBuf.arrayOffset:()I
      24: aload_1
      25: invokevirtual #14                 // Method io/netty/buffer/ByteBuf.readerIndex:()I
      28: iadd
      29: iload_2
      30: invokevirtual #15                 // Method java/util/zip/Inflater.setInput:([BII)V
      33: goto          61
      36: iload_2
      37: newarray       byte
      39: astore_3
      40: aload_1
      41: aload_1
      42: invokevirtual #14                 // Method io/netty/buffer/ByteBuf.readerIndex:()I
      45: aload_3
      46: invokevirtual #16                 // Method io/netty/buffer/ByteBuf.getBytes:(I[B)Lio/netty/buffer/ByteBuf;
      49: pop
      50: aload_0
      51: getfield      #4                  // Field decompressor:Ljava/util/zip/Inflater;
      54: aload_3
      55: iconst_0
      56: aload_3
      57: arraylength
      58: invokevirtual #15                 // Method java/util/zip/Inflater.setInput:([BII)V
      61: iload_2
      62: ireturn

  private int decompress(io.netty.buffer.ByteBufAllocator, io.netty.handler.codec.spdy.SpdyHeadersFrame) throws java.lang.Exception;
    Code:
       0: aload_0
       1: aload_1
       2: invokespecial #17                 // Method ensureBuffer:(Lio/netty/buffer/ByteBufAllocator;)V
       5: aload_0
       6: getfield      #18                 // Field decompressed:Lio/netty/buffer/ByteBuf;
       9: invokevirtual #12                 // Method io/netty/buffer/ByteBuf.array:()[B
      12: astore_3
      13: aload_0
      14: getfield      #18                 // Field decompressed:Lio/netty/buffer/ByteBuf;
      17: invokevirtual #13                 // Method io/netty/buffer/ByteBuf.arrayOffset:()I
      20: aload_0
      21: getfield      #18                 // Field decompressed:Lio/netty/buffer/ByteBuf;
      24: invokevirtual #19                 // Method io/netty/buffer/ByteBuf.writerIndex:()I
      27: iadd
      28: istore        4
      30: aload_0
      31: getfield      #4                  // Field decompressor:Ljava/util/zip/Inflater;
      34: aload_3
      35: iload         4
      37: aload_0
      38: getfield      #18                 // Field decompressed:Lio/netty/buffer/ByteBuf;
      41: invokevirtual #20                 // Method io/netty/buffer/ByteBuf.writableBytes:()I
      44: invokevirtual #21                 // Method java/util/zip/Inflater.inflate:([BII)I
      47: istore        5
      49: iload         5
      51: ifne          102
      54: aload_0
      55: getfield      #4                  // Field decompressor:Ljava/util/zip/Inflater;
      58: invokevirtual #22                 // Method java/util/zip/Inflater.needsDictionary:()Z
      61: ifeq          102
      64: aload_0
      65: getfield      #4                  // Field decompressor:Ljava/util/zip/Inflater;
      68: getstatic     #23                 // Field io/netty/handler/codec/spdy/SpdyCodecUtil.SPDY_DICT:[B
      71: invokevirtual #24                 // Method java/util/zip/Inflater.setDictionary:([B)V
      74: goto          83
      77: astore        6
      79: getstatic     #8                  // Field INVALID_HEADER_BLOCK:Lio/netty/handler/codec/spdy/SpdyProtocolException;
      82: athrow
      83: aload_0
      84: getfield      #4                  // Field decompressor:Ljava/util/zip/Inflater;
      87: aload_3
      88: iload         4
      90: aload_0
      91: getfield      #18                 // Field decompressed:Lio/netty/buffer/ByteBuf;
      94: invokevirtual #20                 // Method io/netty/buffer/ByteBuf.writableBytes:()I
      97: invokevirtual #21                 // Method java/util/zip/Inflater.inflate:([BII)I
     100: istore        5
     102: aload_2
     103: ifnull        141
     106: aload_0
     107: getfield      #18                 // Field decompressed:Lio/netty/buffer/ByteBuf;
     110: aload_0
     111: getfield      #18                 // Field decompressed:Lio/netty/buffer/ByteBuf;
     114: invokevirtual #19                 // Method io/netty/buffer/ByteBuf.writerIndex:()I
     117: iload         5
     119: iadd
     120: invokevirtual #26                 // Method io/netty/buffer/ByteBuf.writerIndex:(I)Lio/netty/buffer/ByteBuf;
     123: pop
     124: aload_0
     125: aload_0
     126: getfield      #18                 // Field decompressed:Lio/netty/buffer/ByteBuf;
     129: aload_2
     130: invokevirtual #27                 // Method decodeHeaderBlock:(Lio/netty/buffer/ByteBuf;Lio/netty/handler/codec/spdy/SpdyHeadersFrame;)V
     133: aload_0
     134: getfield      #18                 // Field decompressed:Lio/netty/buffer/ByteBuf;
     137: invokevirtual #28                 // Method io/netty/buffer/ByteBuf.discardReadBytes:()Lio/netty/buffer/ByteBuf;
     140: pop
     141: iload         5
     143: ireturn
     144: astore        5
     146: new           #30                 // class io/netty/handler/codec/spdy/SpdyProtocolException
     149: dup
     150: ldc           #31                 // String Received invalid header block
     152: aload         5
     154: invokespecial #32                 // Method io/netty/handler/codec/spdy/SpdyProtocolException."<init>":(Ljava/lang/String;Ljava/lang/Throwable;)V
     157: athrow
    Exception table:
       from    to  target type
          64    74    77   Class java/lang/IllegalArgumentException
          30   143   144   Class java/util/zip/DataFormatException

  private void ensureBuffer(io.netty.buffer.ByteBufAllocator);
    Code:
       0: aload_0
       1: getfield      #18                 // Field decompressed:Lio/netty/buffer/ByteBuf;
       4: ifnonnull     20
       7: aload_0
       8: aload_1
       9: sipush        4096
      12: invokeinterface #33,  2           // InterfaceMethod io/netty/buffer/ByteBufAllocator.heapBuffer:(I)Lio/netty/buffer/ByteBuf;
      17: putfield      #18                 // Field decompressed:Lio/netty/buffer/ByteBuf;
      20: aload_0
      21: getfield      #18                 // Field decompressed:Lio/netty/buffer/ByteBuf;
      24: iconst_1
      25: invokevirtual #34                 // Method io/netty/buffer/ByteBuf.ensureWritable:(I)Lio/netty/buffer/ByteBuf;
      28: pop
      29: return

  void endHeaderBlock(io.netty.handler.codec.spdy.SpdyHeadersFrame) throws java.lang.Exception;
    Code:
       0: aload_0
       1: aload_1
       2: invokespecial #35                 // Method io/netty/handler/codec/spdy/SpdyHeaderBlockRawDecoder.endHeaderBlock:(Lio/netty/handler/codec/spdy/SpdyHeadersFrame;)V
       5: aload_0
       6: invokespecial #36                 // Method releaseBuffer:()V
       9: return

  public void end();
    Code:
       0: aload_0
       1: invokespecial #37                 // Method io/netty/handler/codec/spdy/SpdyHeaderBlockRawDecoder.end:()V
       4: aload_0
       5: invokespecial #36                 // Method releaseBuffer:()V
       8: aload_0
       9: getfield      #4                  // Field decompressor:Ljava/util/zip/Inflater;
      12: invokevirtual #38                 // Method java/util/zip/Inflater.end:()V
      15: return

  private void releaseBuffer();
    Code:
       0: aload_0
       1: getfield      #18                 // Field decompressed:Lio/netty/buffer/ByteBuf;
       4: ifnull        20
       7: aload_0
       8: getfield      #18                 // Field decompressed:Lio/netty/buffer/ByteBuf;
      11: invokevirtual #39                 // Method io/netty/buffer/ByteBuf.release:()Z
      14: pop
      15: aload_0
      16: aconst_null
      17: putfield      #18                 // Field decompressed:Lio/netty/buffer/ByteBuf;
      20: return

  static {};
    Code:
       0: new           #30                 // class io/netty/handler/codec/spdy/SpdyProtocolException
       3: dup
       4: ldc           #40                 // String Invalid Header Block
       6: invokespecial #41                 // Method io/netty/handler/codec/spdy/SpdyProtocolException."<init>":(Ljava/lang/String;)V
       9: putstatic     #8                  // Field INVALID_HEADER_BLOCK:Lio/netty/handler/codec/spdy/SpdyProtocolException;
      12: return
}
