Compiled from "EntityBeanIsIdenticalInterceptorFactory.java"
class org.jboss.as.ejb3.component.entity.interceptors.EntityBeanIsIdenticalInterceptorFactory$EntityIsIdenticalInterceptor implements org.jboss.invocation.Interceptor {
  private final org.jboss.as.ee.component.ComponentView componentView;

  final org.jboss.as.ejb3.component.entity.interceptors.EntityBeanIsIdenticalInterceptorFactory this$0;

  public org.jboss.as.ejb3.component.entity.interceptors.EntityBeanIsIdenticalInterceptorFactory$EntityIsIdenticalInterceptor(org.jboss.as.ejb3.component.entity.interceptors.EntityBeanIsIdenticalInterceptorFactory, org.jboss.as.ee.component.ComponentView);
    Code:
       0: aload_0
       1: aload_1
       2: putfield      #1                  // Field this$0:Lorg/jboss/as/ejb3/component/entity/interceptors/EntityBeanIsIdenticalInterceptorFactory;
       5: aload_0
       6: invokespecial #2                  // Method java/lang/Object."<init>":()V
       9: aload_0
      10: aload_2
      11: putfield      #3                  // Field componentView:Lorg/jboss/as/ee/component/ComponentView;
      14: return

  public java.lang.Object processInvocation(org.jboss.invocation.InterceptorContext) throws java.lang.Exception;
    Code:
       0: aload_1
       1: ldc           #4                  // class org/jboss/as/ee/component/ComponentInstance
       3: invokevirtual #5                  // Method org/jboss/invocation/InterceptorContext.getPrivateData:(Ljava/lang/Class;)Ljava/lang/Object;
       6: checkcast     #6                  // class org/jboss/as/ejb3/component/entity/EntityBeanComponentInstance
       9: astore_2
      10: aload_1
      11: getstatic     #7                  // Field org/jboss/as/ejb3/component/entity/EntityBeanComponent.PRIMARY_KEY_CONTEXT_KEY:Ljava/lang/Object;
      14: invokevirtual #8                  // Method org/jboss/invocation/InterceptorContext.getPrivateData:(Ljava/lang/Object;)Ljava/lang/Object;
      17: astore_3
      18: aload_1
      19: invokevirtual #9                  // Method org/jboss/invocation/InterceptorContext.getParameters:()[Ljava/lang/Object;
      22: iconst_0
      23: aaload
      24: astore        4
      26: aload_0
      27: getfield      #3                  // Field componentView:Lorg/jboss/as/ee/component/ComponentView;
      30: invokeinterface #10,  1           // InterfaceMethod org/jboss/as/ee/component/ComponentView.getViewClass:()Ljava/lang/Class;
      35: aload         4
      37: invokevirtual #11                 // Method java/lang/Object.getClass:()Ljava/lang/Class;
      40: invokevirtual #12                 // Method java/lang/Class.isAssignableFrom:(Ljava/lang/Class;)Z
      43: ifne          69
      46: iconst_0
      47: invokestatic  #13                 // Method java/lang/Boolean.valueOf:(Z)Ljava/lang/Boolean;
      50: astore        5
      52: aload_2
      53: invokevirtual #14                 // Method org/jboss/as/ejb3/component/entity/EntityBeanComponentInstance.getComponent:()Lorg/jboss/as/ejb3/component/entity/EntityBeanComponent;
      56: invokevirtual #15                 // Method org/jboss/as/ejb3/component/entity/EntityBeanComponent.getCache:()Lorg/jboss/as/ejb3/component/entity/entitycache/ReadyEntityCache;
      59: aload_2
      60: iconst_1
      61: invokeinterface #16,  3           // InterfaceMethod org/jboss/as/ejb3/component/entity/entitycache/ReadyEntityCache.release:(Lorg/jboss/as/ejb3/component/entity/EntityBeanComponentInstance;Z)V
      66: aload         5
      68: areturn
      69: aload_1
      70: invokevirtual #17                 // Method org/jboss/invocation/InterceptorContext.getMethod:()Ljava/lang/reflect/Method;
      73: invokevirtual #18                 // Method java/lang/reflect/Method.getParameterTypes:()[Ljava/lang/Class;
      76: iconst_0
      77: aaload
      78: ldc           #19                 // class javax/ejb/EJBLocalObject
      80: invokevirtual #20                 // Method java/lang/Object.equals:(Ljava/lang/Object;)Z
      83: ifeq          122
      86: aload         4
      88: checkcast     #19                 // class javax/ejb/EJBLocalObject
      91: invokeinterface #21,  1           // InterfaceMethod javax/ejb/EJBLocalObject.getPrimaryKey:()Ljava/lang/Object;
      96: aload_3
      97: invokevirtual #20                 // Method java/lang/Object.equals:(Ljava/lang/Object;)Z
     100: invokestatic  #13                 // Method java/lang/Boolean.valueOf:(Z)Ljava/lang/Boolean;
     103: astore        5
     105: aload_2
     106: invokevirtual #14                 // Method org/jboss/as/ejb3/component/entity/EntityBeanComponentInstance.getComponent:()Lorg/jboss/as/ejb3/component/entity/EntityBeanComponent;
     109: invokevirtual #15                 // Method org/jboss/as/ejb3/component/entity/EntityBeanComponent.getCache:()Lorg/jboss/as/ejb3/component/entity/entitycache/ReadyEntityCache;
     112: aload_2
     113: iconst_1
     114: invokeinterface #16,  3           // InterfaceMethod org/jboss/as/ejb3/component/entity/entitycache/ReadyEntityCache.release:(Lorg/jboss/as/ejb3/component/entity/EntityBeanComponentInstance;Z)V
     119: aload         5
     121: areturn
     122: aload         4
     124: checkcast     #22                 // class javax/ejb/EJBObject
     127: invokeinterface #23,  1           // InterfaceMethod javax/ejb/EJBObject.getPrimaryKey:()Ljava/lang/Object;
     132: aload_3
     133: invokevirtual #20                 // Method java/lang/Object.equals:(Ljava/lang/Object;)Z
     136: invokestatic  #13                 // Method java/lang/Boolean.valueOf:(Z)Ljava/lang/Boolean;
     139: astore        5
     141: aload_2
     142: invokevirtual #14                 // Method org/jboss/as/ejb3/component/entity/EntityBeanComponentInstance.getComponent:()Lorg/jboss/as/ejb3/component/entity/EntityBeanComponent;
     145: invokevirtual #15                 // Method org/jboss/as/ejb3/component/entity/EntityBeanComponent.getCache:()Lorg/jboss/as/ejb3/component/entity/entitycache/ReadyEntityCache;
     148: aload_2
     149: iconst_1
     150: invokeinterface #16,  3           // InterfaceMethod org/jboss/as/ejb3/component/entity/entitycache/ReadyEntityCache.release:(Lorg/jboss/as/ejb3/component/entity/EntityBeanComponentInstance;Z)V
     155: aload         5
     157: areturn
     158: astore        6
     160: aload_2
     161: invokevirtual #14                 // Method org/jboss/as/ejb3/component/entity/EntityBeanComponentInstance.getComponent:()Lorg/jboss/as/ejb3/component/entity/EntityBeanComponent;
     164: invokevirtual #15                 // Method org/jboss/as/ejb3/component/entity/EntityBeanComponent.getCache:()Lorg/jboss/as/ejb3/component/entity/entitycache/ReadyEntityCache;
     167: aload_2
     168: iconst_1
     169: invokeinterface #16,  3           // InterfaceMethod org/jboss/as/ejb3/component/entity/entitycache/ReadyEntityCache.release:(Lorg/jboss/as/ejb3/component/entity/EntityBeanComponentInstance;Z)V
     174: aload         6
     176: athrow
    Exception table:
       from    to  target type
          10    52   158   any
          69   105   158   any
         122   141   158   any
         158   160   158   any
}
