Compiled from "EntityBeanSynchronizationInterceptor.java"
public class org.jboss.as.ejb3.component.entity.interceptors.EntityBeanSynchronizationInterceptor extends org.jboss.as.ejb3.component.interceptors.AbstractEJBInterceptor {
  public static final org.jboss.invocation.InterceptorFactory FACTORY;

  public org.jboss.as.ejb3.component.entity.interceptors.EntityBeanSynchronizationInterceptor();
    Code:
       0: aload_0
       1: invokespecial #3                  // Method org/jboss/as/ejb3/component/interceptors/AbstractEJBInterceptor."<init>":()V
       4: return

  public java.lang.Object processInvocation(org.jboss.invocation.InterceptorContext) throws java.lang.Exception;
    Code:
       0: aload_1
       1: ldc           #4                  // class org/jboss/as/ejb3/component/entity/EntityBeanComponent
       3: invokestatic  #5                  // Method getComponent:(Lorg/jboss/invocation/InterceptorContext;Ljava/lang/Class;)Lorg/jboss/as/ejb3/component/EJBComponent;
       6: checkcast     #4                  // class org/jboss/as/ejb3/component/entity/EntityBeanComponent
       9: astore_2
      10: aload_1
      11: ldc           #6                  // class org/jboss/as/ee/component/ComponentInstance
      13: invokevirtual #7                  // Method org/jboss/invocation/InterceptorContext.getPrivateData:(Ljava/lang/Class;)Ljava/lang/Object;
      16: checkcast     #8                  // class org/jboss/as/ejb3/component/entity/EntityBeanComponentInstance
      19: astore_3
      20: aload_3
      21: invokevirtual #9                  // Method org/jboss/as/ejb3/component/entity/EntityBeanComponentInstance.getLock:()Lorg/jboss/as/ejb3/tx/OwnableReentrantLock;
      24: astore        4
      26: aload_3
      27: invokevirtual #10                 // Method org/jboss/as/ejb3/component/entity/EntityBeanComponentInstance.getPrimaryKey:()Ljava/lang/Object;
      30: ifnonnull     38
      33: aload_1
      34: invokevirtual #11                 // Method org/jboss/invocation/InterceptorContext.proceed:()Ljava/lang/Object;
      37: areturn
      38: aload_2
      39: invokevirtual #12                 // Method org/jboss/as/ejb3/component/entity/EntityBeanComponent.getTransactionSynchronizationRegistry:()Ljavax/transaction/TransactionSynchronizationRegistry;
      42: astore        5
      44: getstatic     #13                 // Field org/jboss/as/ejb3/logging/EjbLogger.ROOT_LOGGER:Lorg/jboss/as/ejb3/logging/EjbLogger;
      47: invokeinterface #14,  1           // InterfaceMethod org/jboss/as/ejb3/logging/EjbLogger.isTraceEnabled:()Z
      52: ifeq          101
      55: getstatic     #13                 // Field org/jboss/as/ejb3/logging/EjbLogger.ROOT_LOGGER:Lorg/jboss/as/ejb3/logging/EjbLogger;
      58: new           #15                 // class java/lang/StringBuilder
      61: dup
      62: invokespecial #16                 // Method java/lang/StringBuilder."<init>":()V
      65: ldc           #17                 // String Trying to acquire lock:
      67: invokevirtual #18                 // Method java/lang/StringBuilder.append:(Ljava/lang/String;)Ljava/lang/StringBuilder;
      70: aload         4
      72: invokevirtual #19                 // Method java/lang/StringBuilder.append:(Ljava/lang/Object;)Ljava/lang/StringBuilder;
      75: ldc           #20                 // String  for entity bean
      77: invokevirtual #18                 // Method java/lang/StringBuilder.append:(Ljava/lang/String;)Ljava/lang/StringBuilder;
      80: aload_3
      81: invokevirtual #19                 // Method java/lang/StringBuilder.append:(Ljava/lang/Object;)Ljava/lang/StringBuilder;
      84: ldc           #21                 // String  during invocation:
      86: invokevirtual #18                 // Method java/lang/StringBuilder.append:(Ljava/lang/String;)Ljava/lang/StringBuilder;
      89: aload_1
      90: invokevirtual #19                 // Method java/lang/StringBuilder.append:(Ljava/lang/Object;)Ljava/lang/StringBuilder;
      93: invokevirtual #22                 // Method java/lang/StringBuilder.toString:()Ljava/lang/String;
      96: invokeinterface #23,  2           // InterfaceMethod org/jboss/as/ejb3/logging/EjbLogger.trace:(Ljava/lang/Object;)V
     101: aload_0
     102: aload         5
     104: invokespecial #24                 // Method getLockOwner:(Ljavax/transaction/TransactionSynchronizationRegistry;)Ljava/lang/Object;
     107: astore        6
     109: aload         4
     111: aload         6
     113: invokevirtual #25                 // Method org/jboss/as/ejb3/tx/OwnableReentrantLock.lock:(Ljava/lang/Object;)V
     116: iconst_0
     117: istore        7
     119: aload         4
     121: dup
     122: astore        8
     124: monitorenter
     125: aload_3
     126: invokevirtual #26                 // Method org/jboss/as/ejb3/component/entity/EntityBeanComponentInstance.isReloadRequired:()Z
     129: ifeq          136
     132: aload_3
     133: invokevirtual #27                 // Method org/jboss/as/ejb3/component/entity/EntityBeanComponentInstance.reload:()V
     136: getstatic     #13                 // Field org/jboss/as/ejb3/logging/EjbLogger.ROOT_LOGGER:Lorg/jboss/as/ejb3/logging/EjbLogger;
     139: invokeinterface #14,  1           // InterfaceMethod org/jboss/as/ejb3/logging/EjbLogger.isTraceEnabled:()Z
     144: ifeq          193
     147: getstatic     #13                 // Field org/jboss/as/ejb3/logging/EjbLogger.ROOT_LOGGER:Lorg/jboss/as/ejb3/logging/EjbLogger;
     150: new           #15                 // class java/lang/StringBuilder
     153: dup
     154: invokespecial #16                 // Method java/lang/StringBuilder."<init>":()V
     157: ldc           #28                 // String Acquired lock:
     159: invokevirtual #18                 // Method java/lang/StringBuilder.append:(Ljava/lang/String;)Ljava/lang/StringBuilder;
     162: aload         4
     164: invokevirtual #19                 // Method java/lang/StringBuilder.append:(Ljava/lang/Object;)Ljava/lang/StringBuilder;
     167: ldc           #29                 // String  for entity bean instance:
     169: invokevirtual #18                 // Method java/lang/StringBuilder.append:(Ljava/lang/String;)Ljava/lang/StringBuilder;
     172: aload_3
     173: invokevirtual #19                 // Method java/lang/StringBuilder.append:(Ljava/lang/Object;)Ljava/lang/StringBuilder;
     176: ldc           #21                 // String  during invocation:
     178: invokevirtual #18                 // Method java/lang/StringBuilder.append:(Ljava/lang/String;)Ljava/lang/StringBuilder;
     181: aload_1
     182: invokevirtual #19                 // Method java/lang/StringBuilder.append:(Ljava/lang/Object;)Ljava/lang/StringBuilder;
     185: invokevirtual #22                 // Method java/lang/StringBuilder.toString:()Ljava/lang/String;
     188: invokeinterface #23,  2           // InterfaceMethod org/jboss/as/ejb3/logging/EjbLogger.trace:(Ljava/lang/Object;)V
     193: aload_1
     194: ldc           #30                 // class org/jboss/as/ejb3/component/entity/interceptors/InternalInvocationMarker
     196: invokevirtual #7                  // Method org/jboss/invocation/InterceptorContext.getPrivateData:(Ljava/lang/Class;)Ljava/lang/Object;
     199: ifnonnull     258
     202: aload_3
     203: invokevirtual #31                 // Method org/jboss/as/ejb3/component/entity/EntityBeanComponentInstance.isRemoved:()Z
     206: ifne          216
     209: aload_3
     210: invokevirtual #32                 // Method org/jboss/as/ejb3/component/entity/EntityBeanComponentInstance.isDiscarded:()Z
     213: ifeq          258
     216: aload_1
     217: getstatic     #33                 // Field org/jboss/as/ejb3/component/entity/EntityBeanComponent.PRIMARY_KEY_CONTEXT_KEY:Ljava/lang/Object;
     220: invokevirtual #34                 // Method org/jboss/invocation/InterceptorContext.getPrivateData:(Ljava/lang/Object;)Ljava/lang/Object;
     223: astore        9
     225: aload_2
     226: invokevirtual #35                 // Method org/jboss/as/ejb3/component/entity/EntityBeanComponent.getCache:()Lorg/jboss/as/ejb3/component/entity/entitycache/ReadyEntityCache;
     229: aload_3
     230: iconst_1
     231: invokeinterface #36,  3           // InterfaceMethod org/jboss/as/ejb3/component/entity/entitycache/ReadyEntityCache.release:(Lorg/jboss/as/ejb3/component/entity/EntityBeanComponentInstance;Z)V
     236: aload         4
     238: aload         6
     240: invokevirtual #37                 // Method org/jboss/as/ejb3/tx/OwnableReentrantLock.unlock:(Ljava/lang/Object;)V
     243: getstatic     #13                 // Field org/jboss/as/ejb3/logging/EjbLogger.ROOT_LOGGER:Lorg/jboss/as/ejb3/logging/EjbLogger;
     246: aload_2
     247: invokevirtual #38                 // Method org/jboss/as/ejb3/component/entity/EntityBeanComponent.getComponentName:()Ljava/lang/String;
     250: aload         9
     252: invokeinterface #39,  3           // InterfaceMethod org/jboss/as/ejb3/logging/EjbLogger.instanceWasRemoved:(Ljava/lang/String;Ljava/lang/Object;)Ljavax/ejb/NoSuchEntityException;
     257: athrow
     258: aconst_null
     259: astore        9
     261: aload         5
     263: invokeinterface #40,  1           // InterfaceMethod javax/transaction/TransactionSynchronizationRegistry.getTransactionKey:()Ljava/lang/Object;
     268: astore        9
     270: aload_3
     271: invokevirtual #41                 // Method org/jboss/as/ejb3/component/entity/EntityBeanComponentInstance.isSynchronizeRegistered:()Z
     274: ifne          370
     277: aload         9
     279: ifnull        365
     282: new           #42                 // class org/jboss/as/ejb3/component/entity/interceptors/EntityBeanSynchronizationInterceptor$EntityBeanSynchronization
     285: dup
     286: aload_0
     287: aload_3
     288: aload         6
     290: invokespecial #43                 // Method org/jboss/as/ejb3/component/entity/interceptors/EntityBeanSynchronizationInterceptor$EntityBeanSynchronization."<init>":(Lorg/jboss/as/ejb3/component/entity/interceptors/EntityBeanSynchronizationInterceptor;Lorg/jboss/as/ejb3/component/entity/EntityBeanComponentInstance;Ljava/lang/Object;)V
     293: astore        10
     295: aload         5
     297: aload         10
     299: invokeinterface #44,  2           // InterfaceMethod javax/transaction/TransactionSynchronizationRegistry.registerInterposedSynchronization:(Ljavax/transaction/Synchronization;)V
     304: iconst_1
     305: istore        7
     307: getstatic     #13                 // Field org/jboss/as/ejb3/logging/EjbLogger.ROOT_LOGGER:Lorg/jboss/as/ejb3/logging/EjbLogger;
     310: invokeinterface #14,  1           // InterfaceMethod org/jboss/as/ejb3/logging/EjbLogger.isTraceEnabled:()Z
     315: ifeq          365
     318: getstatic     #13                 // Field org/jboss/as/ejb3/logging/EjbLogger.ROOT_LOGGER:Lorg/jboss/as/ejb3/logging/EjbLogger;
     321: new           #15                 // class java/lang/StringBuilder
     324: dup
     325: invokespecial #16                 // Method java/lang/StringBuilder."<init>":()V
     328: ldc           #45                 // String Registered tx synchronization:
     330: invokevirtual #18                 // Method java/lang/StringBuilder.append:(Ljava/lang/String;)Ljava/lang/StringBuilder;
     333: aload         10
     335: invokevirtual #19                 // Method java/lang/StringBuilder.append:(Ljava/lang/Object;)Ljava/lang/StringBuilder;
     338: ldc           #46                 // String  for tx:
     340: invokevirtual #18                 // Method java/lang/StringBuilder.append:(Ljava/lang/String;)Ljava/lang/StringBuilder;
     343: aload         9
     345: invokevirtual #19                 // Method java/lang/StringBuilder.append:(Ljava/lang/Object;)Ljava/lang/StringBuilder;
     348: ldc           #47                 // String  associated with stateful component instance:
     350: invokevirtual #18                 // Method java/lang/StringBuilder.append:(Ljava/lang/String;)Ljava/lang/StringBuilder;
     353: aload_3
     354: invokevirtual #19                 // Method java/lang/StringBuilder.append:(Ljava/lang/Object;)Ljava/lang/StringBuilder;
     357: invokevirtual #22                 // Method java/lang/StringBuilder.toString:()Ljava/lang/String;
     360: invokeinterface #23,  2           // InterfaceMethod org/jboss/as/ejb3/logging/EjbLogger.trace:(Ljava/lang/Object;)V
     365: aload_3
     366: iconst_1
     367: invokevirtual #48                 // Method org/jboss/as/ejb3/component/entity/EntityBeanComponentInstance.setSynchronizationRegistered:(Z)V
     370: aload_1
     371: invokevirtual #11                 // Method org/jboss/invocation/InterceptorContext.proceed:()Ljava/lang/Object;
     374: astore        10
     376: aload         9
     378: ifnonnull     394
     381: aload_3
     382: invokevirtual #49                 // Method org/jboss/as/ejb3/component/entity/EntityBeanComponentInstance.store:()V
     385: aload_0
     386: aload_3
     387: iconst_1
     388: invokespecial #2                  // Method releaseInstance:(Lorg/jboss/as/ejb3/component/entity/EntityBeanComponentInstance;Z)V
     391: goto          417
     394: iload         7
     396: ifne          417
     399: aload_2
     400: invokevirtual #35                 // Method org/jboss/as/ejb3/component/entity/EntityBeanComponent.getCache:()Lorg/jboss/as/ejb3/component/entity/entitycache/ReadyEntityCache;
     403: aload_3
     404: iconst_1
     405: invokeinterface #36,  3           // InterfaceMethod org/jboss/as/ejb3/component/entity/entitycache/ReadyEntityCache.release:(Lorg/jboss/as/ejb3/component/entity/EntityBeanComponentInstance;Z)V
     410: aload         4
     412: aload         6
     414: invokevirtual #37                 // Method org/jboss/as/ejb3/tx/OwnableReentrantLock.unlock:(Ljava/lang/Object;)V
     417: aload         8
     419: monitorexit
     420: aload         10
     422: areturn
     423: astore        11
     425: aload         9
     427: ifnonnull     443
     430: aload_3
     431: invokevirtual #49                 // Method org/jboss/as/ejb3/component/entity/EntityBeanComponentInstance.store:()V
     434: aload_0
     435: aload_3
     436: iconst_1
     437: invokespecial #2                  // Method releaseInstance:(Lorg/jboss/as/ejb3/component/entity/EntityBeanComponentInstance;Z)V
     440: goto          466
     443: iload         7
     445: ifne          466
     448: aload_2
     449: invokevirtual #35                 // Method org/jboss/as/ejb3/component/entity/EntityBeanComponent.getCache:()Lorg/jboss/as/ejb3/component/entity/entitycache/ReadyEntityCache;
     452: aload_3
     453: iconst_1
     454: invokeinterface #36,  3           // InterfaceMethod org/jboss/as/ejb3/component/entity/entitycache/ReadyEntityCache.release:(Lorg/jboss/as/ejb3/component/entity/EntityBeanComponentInstance;Z)V
     459: aload         4
     461: aload         6
     463: invokevirtual #37                 // Method org/jboss/as/ejb3/tx/OwnableReentrantLock.unlock:(Ljava/lang/Object;)V
     466: aload         11
     468: athrow
     469: astore        12
     471: aload         8
     473: monitorexit
     474: aload         12
     476: athrow
    Exception table:
       from    to  target type
         261   376   423   any
         423   425   423   any
         125   420   469   any
         423   474   469   any

  private void releaseInstance(org.jboss.as.ejb3.component.entity.EntityBeanComponentInstance, boolean);
    Code:
       0: aload_1
       1: invokevirtual #50                 // Method org/jboss/as/ejb3/component/entity/EntityBeanComponentInstance.getComponent:()Lorg/jboss/as/ejb3/component/entity/EntityBeanComponent;
       4: invokevirtual #35                 // Method org/jboss/as/ejb3/component/entity/EntityBeanComponent.getCache:()Lorg/jboss/as/ejb3/component/entity/entitycache/ReadyEntityCache;
       7: aload_1
       8: iload_2
       9: invokeinterface #36,  3           // InterfaceMethod org/jboss/as/ejb3/component/entity/entitycache/ReadyEntityCache.release:(Lorg/jboss/as/ejb3/component/entity/EntityBeanComponentInstance;Z)V
      14: aload_1
      15: iconst_0
      16: invokevirtual #48                 // Method org/jboss/as/ejb3/component/entity/EntityBeanComponentInstance.setSynchronizationRegistered:(Z)V
      19: aload_0
      20: aload_1
      21: invokespecial #1                  // Method releaseLock:(Lorg/jboss/as/ejb3/component/entity/EntityBeanComponentInstance;)V
      24: goto          40
      27: astore_3
      28: aload_1
      29: iconst_0
      30: invokevirtual #48                 // Method org/jboss/as/ejb3/component/entity/EntityBeanComponentInstance.setSynchronizationRegistered:(Z)V
      33: aload_0
      34: aload_1
      35: invokespecial #1                  // Method releaseLock:(Lorg/jboss/as/ejb3/component/entity/EntityBeanComponentInstance;)V
      38: aload_3
      39: athrow
      40: return
    Exception table:
       from    to  target type
           0    14    27   any

  private void releaseLock(org.jboss.as.ejb3.component.entity.EntityBeanComponentInstance);
    Code:
       0: aload_1
       1: invokevirtual #9                  // Method org/jboss/as/ejb3/component/entity/EntityBeanComponentInstance.getLock:()Lorg/jboss/as/ejb3/tx/OwnableReentrantLock;
       4: aload_0
       5: aload_1
       6: invokevirtual #50                 // Method org/jboss/as/ejb3/component/entity/EntityBeanComponentInstance.getComponent:()Lorg/jboss/as/ejb3/component/entity/EntityBeanComponent;
       9: invokevirtual #12                 // Method org/jboss/as/ejb3/component/entity/EntityBeanComponent.getTransactionSynchronizationRegistry:()Ljavax/transaction/TransactionSynchronizationRegistry;
      12: invokespecial #24                 // Method getLockOwner:(Ljavax/transaction/TransactionSynchronizationRegistry;)Ljava/lang/Object;
      15: invokevirtual #37                 // Method org/jboss/as/ejb3/tx/OwnableReentrantLock.unlock:(Ljava/lang/Object;)V
      18: getstatic     #13                 // Field org/jboss/as/ejb3/logging/EjbLogger.ROOT_LOGGER:Lorg/jboss/as/ejb3/logging/EjbLogger;
      21: invokeinterface #14,  1           // InterfaceMethod org/jboss/as/ejb3/logging/EjbLogger.isTraceEnabled:()Z
      26: ifeq          43
      29: getstatic     #13                 // Field org/jboss/as/ejb3/logging/EjbLogger.ROOT_LOGGER:Lorg/jboss/as/ejb3/logging/EjbLogger;
      32: ldc           #51                 // String Released lock: %s
      34: aload_1
      35: invokevirtual #9                  // Method org/jboss/as/ejb3/component/entity/EntityBeanComponentInstance.getLock:()Lorg/jboss/as/ejb3/tx/OwnableReentrantLock;
      38: invokeinterface #52,  3           // InterfaceMethod org/jboss/as/ejb3/logging/EjbLogger.tracef:(Ljava/lang/String;Ljava/lang/Object;)V
      43: return

  private java.lang.Object getLockOwner(javax.transaction.TransactionSynchronizationRegistry);
    Code:
       0: aload_1
       1: invokeinterface #40,  1           // InterfaceMethod javax/transaction/TransactionSynchronizationRegistry.getTransactionKey:()Ljava/lang/Object;
       6: astore_2
       7: aload_2
       8: ifnull        15
      11: aload_2
      12: goto          18
      15: invokestatic  #53                 // Method java/lang/Thread.currentThread:()Ljava/lang/Thread;
      18: areturn

  static void access$000(org.jboss.as.ejb3.component.entity.interceptors.EntityBeanSynchronizationInterceptor, org.jboss.as.ejb3.component.entity.EntityBeanComponentInstance, boolean);
    Code:
       0: aload_0
       1: aload_1
       2: iload_2
       3: invokespecial #2                  // Method releaseInstance:(Lorg/jboss/as/ejb3/component/entity/EntityBeanComponentInstance;Z)V
       6: return

  static void access$100(org.jboss.as.ejb3.component.entity.interceptors.EntityBeanSynchronizationInterceptor, org.jboss.as.ejb3.component.entity.EntityBeanComponentInstance);
    Code:
       0: aload_0
       1: aload_1
       2: invokespecial #1                  // Method releaseLock:(Lorg/jboss/as/ejb3/component/entity/EntityBeanComponentInstance;)V
       5: return

  static {};
    Code:
       0: new           #54                 // class org/jboss/as/ejb3/component/entity/interceptors/EntityBeanSynchronizationInterceptor$1
       3: dup
       4: invokespecial #55                 // Method org/jboss/as/ejb3/component/entity/interceptors/EntityBeanSynchronizationInterceptor$1."<init>":()V
       7: putstatic     #56                 // Field FACTORY:Lorg/jboss/invocation/InterceptorFactory;
      10: return
}
