Compiled from "EntityBeanHomeFinderInterceptorFactory.java"
class org.jboss.as.ejb3.component.entity.interceptors.EntityBeanHomeFinderInterceptorFactory$2 implements java.util.Enumeration<java.lang.Object> {
  final java.util.Iterator val$iterator;

  final org.jboss.as.ejb3.component.entity.interceptors.EntityBeanHomeFinderInterceptorFactory this$0;

  org.jboss.as.ejb3.component.entity.interceptors.EntityBeanHomeFinderInterceptorFactory$2(org.jboss.as.ejb3.component.entity.interceptors.EntityBeanHomeFinderInterceptorFactory, java.util.Iterator);
    Code:
       0: aload_0
       1: aload_1
       2: putfield      #1                  // Field this$0:Lorg/jboss/as/ejb3/component/entity/interceptors/EntityBeanHomeFinderInterceptorFactory;
       5: aload_0
       6: aload_2
       7: putfield      #2                  // Field val$iterator:Ljava/util/Iterator;
      10: aload_0
      11: invokespecial #3                  // Method java/lang/Object."<init>":()V
      14: return

  public boolean hasMoreElements();
    Code:
       0: aload_0
       1: getfield      #2                  // Field val$iterator:Ljava/util/Iterator;
       4: invokeinterface #4,  1            // InterfaceMethod java/util/Iterator.hasNext:()Z
       9: ireturn

  public java.lang.Object nextElement();
    Code:
       0: aload_0
       1: getfield      #2                  // Field val$iterator:Ljava/util/Iterator;
       4: invokeinterface #5,  1            // InterfaceMethod java/util/Iterator.next:()Ljava/lang/Object;
       9: areturn
}
