Compiled from "ImpersonatedCredentials.java"
public class com.google.auth.oauth2.ImpersonatedCredentials extends com.google.auth.oauth2.GoogleCredentials implements com.google.auth.ServiceAccountSigner,com.google.auth.oauth2.IdTokenProvider {
  private static final long serialVersionUID;

  private static final java.lang.String RFC3339;

  private static final int ONE_HOUR_IN_SECONDS;

  private static final java.lang.String CLOUD_PLATFORM_SCOPE;

  private static final java.lang.String IAM_ACCESS_TOKEN_ENDPOINT;

  private static final java.lang.String SCOPE_EMPTY_ERROR;

  private static final java.lang.String LIFETIME_EXCEEDED_ERROR;

  private com.google.auth.oauth2.GoogleCredentials sourceCredentials;

  private java.lang.String targetPrincipal;

  private java.util.List<java.lang.String> delegates;

  private java.util.List<java.lang.String> scopes;

  private int lifetime;

  private final java.lang.String transportFactoryClassName;

  private transient com.google.auth.http.HttpTransportFactory transportFactory;

  public static com.google.auth.oauth2.ImpersonatedCredentials create(com.google.auth.oauth2.GoogleCredentials, java.lang.String, java.util.List<java.lang.String>, java.util.List<java.lang.String>, int, com.google.auth.http.HttpTransportFactory);
    Code:
       0: invokestatic  #2                  // Method newBuilder:()Lcom/google/auth/oauth2/ImpersonatedCredentials$Builder;
       3: aload_0
       4: invokevirtual #3                  // Method com/google/auth/oauth2/ImpersonatedCredentials$Builder.setSourceCredentials:(Lcom/google/auth/oauth2/GoogleCredentials;)Lcom/google/auth/oauth2/ImpersonatedCredentials$Builder;
       7: aload_1
       8: invokevirtual #4                  // Method com/google/auth/oauth2/ImpersonatedCredentials$Builder.setTargetPrincipal:(Ljava/lang/String;)Lcom/google/auth/oauth2/ImpersonatedCredentials$Builder;
      11: aload_2
      12: invokevirtual #5                  // Method com/google/auth/oauth2/ImpersonatedCredentials$Builder.setDelegates:(Ljava/util/List;)Lcom/google/auth/oauth2/ImpersonatedCredentials$Builder;
      15: aload_3
      16: invokevirtual #6                  // Method com/google/auth/oauth2/ImpersonatedCredentials$Builder.setScopes:(Ljava/util/List;)Lcom/google/auth/oauth2/ImpersonatedCredentials$Builder;
      19: iload         4
      21: invokevirtual #7                  // Method com/google/auth/oauth2/ImpersonatedCredentials$Builder.setLifetime:(I)Lcom/google/auth/oauth2/ImpersonatedCredentials$Builder;
      24: aload         5
      26: invokevirtual #8                  // Method com/google/auth/oauth2/ImpersonatedCredentials$Builder.setHttpTransportFactory:(Lcom/google/auth/http/HttpTransportFactory;)Lcom/google/auth/oauth2/ImpersonatedCredentials$Builder;
      29: invokevirtual #9                  // Method com/google/auth/oauth2/ImpersonatedCredentials$Builder.build:()Lcom/google/auth/oauth2/ImpersonatedCredentials;
      32: areturn

  public static com.google.auth.oauth2.ImpersonatedCredentials create(com.google.auth.oauth2.GoogleCredentials, java.lang.String, java.util.List<java.lang.String>, java.util.List<java.lang.String>, int);
    Code:
       0: invokestatic  #2                  // Method newBuilder:()Lcom/google/auth/oauth2/ImpersonatedCredentials$Builder;
       3: aload_0
       4: invokevirtual #3                  // Method com/google/auth/oauth2/ImpersonatedCredentials$Builder.setSourceCredentials:(Lcom/google/auth/oauth2/GoogleCredentials;)Lcom/google/auth/oauth2/ImpersonatedCredentials$Builder;
       7: aload_1
       8: invokevirtual #4                  // Method com/google/auth/oauth2/ImpersonatedCredentials$Builder.setTargetPrincipal:(Ljava/lang/String;)Lcom/google/auth/oauth2/ImpersonatedCredentials$Builder;
      11: aload_2
      12: invokevirtual #5                  // Method com/google/auth/oauth2/ImpersonatedCredentials$Builder.setDelegates:(Ljava/util/List;)Lcom/google/auth/oauth2/ImpersonatedCredentials$Builder;
      15: aload_3
      16: invokevirtual #6                  // Method com/google/auth/oauth2/ImpersonatedCredentials$Builder.setScopes:(Ljava/util/List;)Lcom/google/auth/oauth2/ImpersonatedCredentials$Builder;
      19: iload         4
      21: invokevirtual #7                  // Method com/google/auth/oauth2/ImpersonatedCredentials$Builder.setLifetime:(I)Lcom/google/auth/oauth2/ImpersonatedCredentials$Builder;
      24: invokevirtual #9                  // Method com/google/auth/oauth2/ImpersonatedCredentials$Builder.build:()Lcom/google/auth/oauth2/ImpersonatedCredentials;
      27: areturn

  public java.lang.String getAccount();
    Code:
       0: aload_0
       1: getfield      #10                 // Field targetPrincipal:Ljava/lang/String;
       4: areturn

  public byte[] sign(byte[]);
    Code:
       0: aload_0
       1: invokevirtual #11                 // Method getAccount:()Ljava/lang/String;
       4: aload_0
       5: getfield      #12                 // Field sourceCredentials:Lcom/google/auth/oauth2/GoogleCredentials;
       8: aload_0
       9: getfield      #13                 // Field transportFactory:Lcom/google/auth/http/HttpTransportFactory;
      12: invokeinterface #14,  1           // InterfaceMethod com/google/auth/http/HttpTransportFactory.create:()Lcom/google/api/client/http/HttpTransport;
      17: aload_1
      18: ldc           #15                 // String delegates
      20: aload_0
      21: getfield      #16                 // Field delegates:Ljava/util/List;
      24: invokestatic  #17                 // Method com/google/common/collect/ImmutableMap.of:(Ljava/lang/Object;Ljava/lang/Object;)Lcom/google/common/collect/ImmutableMap;
      27: invokestatic  #18                 // Method com/google/auth/oauth2/IamUtils.sign:(Ljava/lang/String;Lcom/google/auth/Credentials;Lcom/google/api/client/http/HttpTransport;[BLjava/util/Map;)[B
      30: areturn

  private com.google.auth.oauth2.ImpersonatedCredentials(com.google.auth.oauth2.ImpersonatedCredentials$Builder);
    Code:
       0: aload_0
       1: invokespecial #19                 // Method com/google/auth/oauth2/GoogleCredentials."<init>":()V
       4: aload_0
       5: aload_1
       6: invokevirtual #20                 // Method com/google/auth/oauth2/ImpersonatedCredentials$Builder.getSourceCredentials:()Lcom/google/auth/oauth2/GoogleCredentials;
       9: putfield      #12                 // Field sourceCredentials:Lcom/google/auth/oauth2/GoogleCredentials;
      12: aload_0
      13: aload_1
      14: invokevirtual #21                 // Method com/google/auth/oauth2/ImpersonatedCredentials$Builder.getTargetPrincipal:()Ljava/lang/String;
      17: putfield      #10                 // Field targetPrincipal:Ljava/lang/String;
      20: aload_0
      21: aload_1
      22: invokevirtual #22                 // Method com/google/auth/oauth2/ImpersonatedCredentials$Builder.getDelegates:()Ljava/util/List;
      25: putfield      #16                 // Field delegates:Ljava/util/List;
      28: aload_0
      29: aload_1
      30: invokevirtual #23                 // Method com/google/auth/oauth2/ImpersonatedCredentials$Builder.getScopes:()Ljava/util/List;
      33: putfield      #24                 // Field scopes:Ljava/util/List;
      36: aload_0
      37: aload_1
      38: invokevirtual #25                 // Method com/google/auth/oauth2/ImpersonatedCredentials$Builder.getLifetime:()I
      41: putfield      #26                 // Field lifetime:I
      44: aload_0
      45: aload_1
      46: invokevirtual #27                 // Method com/google/auth/oauth2/ImpersonatedCredentials$Builder.getHttpTransportFactory:()Lcom/google/auth/http/HttpTransportFactory;
      49: ldc           #28                 // class com/google/auth/http/HttpTransportFactory
      51: getstatic     #29                 // Field com/google/auth/oauth2/OAuth2Utils.HTTP_TRANSPORT_FACTORY:Lcom/google/auth/http/HttpTransportFactory;
      54: invokestatic  #30                 // Method getFromServiceLoader:(Ljava/lang/Class;Ljava/lang/Object;)Ljava/lang/Object;
      57: invokestatic  #31                 // Method com/google/common/base/MoreObjects.firstNonNull:(Ljava/lang/Object;Ljava/lang/Object;)Ljava/lang/Object;
      60: checkcast     #28                 // class com/google/auth/http/HttpTransportFactory
      63: putfield      #13                 // Field transportFactory:Lcom/google/auth/http/HttpTransportFactory;
      66: aload_0
      67: aload_0
      68: getfield      #13                 // Field transportFactory:Lcom/google/auth/http/HttpTransportFactory;
      71: invokevirtual #32                 // Method java/lang/Object.getClass:()Ljava/lang/Class;
      74: invokevirtual #33                 // Method java/lang/Class.getName:()Ljava/lang/String;
      77: putfield      #34                 // Field transportFactoryClassName:Ljava/lang/String;
      80: aload_0
      81: getfield      #16                 // Field delegates:Ljava/util/List;
      84: ifnonnull     98
      87: aload_0
      88: new           #35                 // class java/util/ArrayList
      91: dup
      92: invokespecial #36                 // Method java/util/ArrayList."<init>":()V
      95: putfield      #16                 // Field delegates:Ljava/util/List;
      98: aload_0
      99: getfield      #24                 // Field scopes:Ljava/util/List;
     102: ifnonnull     115
     105: new           #37                 // class java/lang/IllegalStateException
     108: dup
     109: ldc           #39                 // String Scopes cannot be null
     111: invokespecial #40                 // Method java/lang/IllegalStateException."<init>":(Ljava/lang/String;)V
     114: athrow
     115: return

  public com.google.auth.oauth2.AccessToken refreshAccessToken() throws java.io.IOException;
    Code:
       0: aload_0
       1: getfield      #12                 // Field sourceCredentials:Lcom/google/auth/oauth2/GoogleCredentials;
       4: invokevirtual #41                 // Method com/google/auth/oauth2/GoogleCredentials.getAccessToken:()Lcom/google/auth/oauth2/AccessToken;
       7: ifnonnull     33
      10: aload_0
      11: aload_0
      12: getfield      #12                 // Field sourceCredentials:Lcom/google/auth/oauth2/GoogleCredentials;
      15: iconst_1
      16: anewarray     #42                 // class java/lang/String
      19: dup
      20: iconst_0
      21: ldc           #43                 // String https://www.googleapis.com/auth/cloud-platform
      23: aastore
      24: invokestatic  #44                 // Method java/util/Arrays.asList:([Ljava/lang/Object;)Ljava/util/List;
      27: invokevirtual #45                 // Method com/google/auth/oauth2/GoogleCredentials.createScoped:(Ljava/util/Collection;)Lcom/google/auth/oauth2/GoogleCredentials;
      30: putfield      #12                 // Field sourceCredentials:Lcom/google/auth/oauth2/GoogleCredentials;
      33: aload_0
      34: getfield      #12                 // Field sourceCredentials:Lcom/google/auth/oauth2/GoogleCredentials;
      37: invokevirtual #46                 // Method com/google/auth/oauth2/GoogleCredentials.refreshIfExpired:()V
      40: goto          55
      43: astore_1
      44: new           #47                 // class java/io/IOException
      47: dup
      48: ldc           #48                 // String Unable to refresh sourceCredentials
      50: aload_1
      51: invokespecial #49                 // Method java/io/IOException."<init>":(Ljava/lang/String;Ljava/lang/Throwable;)V
      54: athrow
      55: aload_0
      56: getfield      #13                 // Field transportFactory:Lcom/google/auth/http/HttpTransportFactory;
      59: invokeinterface #14,  1           // InterfaceMethod com/google/auth/http/HttpTransportFactory.create:()Lcom/google/api/client/http/HttpTransport;
      64: astore_1
      65: new           #50                 // class com/google/api/client/json/JsonObjectParser
      68: dup
      69: getstatic     #51                 // Field com/google/auth/oauth2/OAuth2Utils.JSON_FACTORY:Lcom/google/api/client/json/JsonFactory;
      72: invokespecial #52                 // Method com/google/api/client/json/JsonObjectParser."<init>":(Lcom/google/api/client/json/JsonFactory;)V
      75: astore_2
      76: new           #53                 // class com/google/auth/http/HttpCredentialsAdapter
      79: dup
      80: aload_0
      81: getfield      #12                 // Field sourceCredentials:Lcom/google/auth/oauth2/GoogleCredentials;
      84: invokespecial #54                 // Method com/google/auth/http/HttpCredentialsAdapter."<init>":(Lcom/google/auth/Credentials;)V
      87: astore_3
      88: aload_1
      89: invokevirtual #55                 // Method com/google/api/client/http/HttpTransport.createRequestFactory:()Lcom/google/api/client/http/HttpRequestFactory;
      92: astore        4
      94: ldc           #56                 // String https://iamcredentials.googleapis.com/v1/projects/-/serviceAccounts/%s:generateAccessToken
      96: iconst_1
      97: anewarray     #57                 // class java/lang/Object
     100: dup
     101: iconst_0
     102: aload_0
     103: getfield      #10                 // Field targetPrincipal:Ljava/lang/String;
     106: aastore
     107: invokestatic  #58                 // Method java/lang/String.format:(Ljava/lang/String;[Ljava/lang/Object;)Ljava/lang/String;
     110: astore        5
     112: new           #59                 // class com/google/api/client/http/GenericUrl
     115: dup
     116: aload         5
     118: invokespecial #60                 // Method com/google/api/client/http/GenericUrl."<init>":(Ljava/lang/String;)V
     121: astore        6
     123: ldc           #15                 // String delegates
     125: aload_0
     126: getfield      #16                 // Field delegates:Ljava/util/List;
     129: ldc           #61                 // String scope
     131: aload_0
     132: getfield      #24                 // Field scopes:Ljava/util/List;
     135: ldc           #62                 // String lifetime
     137: new           #63                 // class java/lang/StringBuilder
     140: dup
     141: invokespecial #64                 // Method java/lang/StringBuilder."<init>":()V
     144: aload_0
     145: getfield      #26                 // Field lifetime:I
     148: invokevirtual #65                 // Method java/lang/StringBuilder.append:(I)Ljava/lang/StringBuilder;
     151: ldc           #66                 // String s
     153: invokevirtual #67                 // Method java/lang/StringBuilder.append:(Ljava/lang/String;)Ljava/lang/StringBuilder;
     156: invokevirtual #68                 // Method java/lang/StringBuilder.toString:()Ljava/lang/String;
     159: invokestatic  #69                 // Method com/google/common/collect/ImmutableMap.of:(Ljava/lang/Object;Ljava/lang/Object;Ljava/lang/Object;Ljava/lang/Object;Ljava/lang/Object;Ljava/lang/Object;)Lcom/google/common/collect/ImmutableMap;
     162: astore        7
     164: new           #70                 // class com/google/api/client/http/json/JsonHttpContent
     167: dup
     168: aload_2
     169: invokevirtual #71                 // Method com/google/api/client/json/JsonObjectParser.getJsonFactory:()Lcom/google/api/client/json/JsonFactory;
     172: aload         7
     174: invokespecial #72                 // Method com/google/api/client/http/json/JsonHttpContent."<init>":(Lcom/google/api/client/json/JsonFactory;Ljava/lang/Object;)V
     177: astore        8
     179: aload         4
     181: aload         6
     183: aload         8
     185: invokevirtual #73                 // Method com/google/api/client/http/HttpRequestFactory.buildPostRequest:(Lcom/google/api/client/http/GenericUrl;Lcom/google/api/client/http/HttpContent;)Lcom/google/api/client/http/HttpRequest;
     188: astore        9
     190: aload_3
     191: aload         9
     193: invokevirtual #74                 // Method com/google/auth/http/HttpCredentialsAdapter.initialize:(Lcom/google/api/client/http/HttpRequest;)V
     196: aload         9
     198: aload_2
     199: invokevirtual #75                 // Method com/google/api/client/http/HttpRequest.setParser:(Lcom/google/api/client/util/ObjectParser;)Lcom/google/api/client/http/HttpRequest;
     202: pop
     203: aconst_null
     204: astore        10
     206: aload         9
     208: invokevirtual #76                 // Method com/google/api/client/http/HttpRequest.execute:()Lcom/google/api/client/http/HttpResponse;
     211: astore        10
     213: goto          230
     216: astore        11
     218: new           #47                 // class java/io/IOException
     221: dup
     222: ldc           #77                 // String Error requesting access token
     224: aload         11
     226: invokespecial #49                 // Method java/io/IOException."<init>":(Ljava/lang/String;Ljava/lang/Throwable;)V
     229: athrow
     230: aload         10
     232: ldc           #78                 // class com/google/api/client/util/GenericData
     234: invokevirtual #79                 // Method com/google/api/client/http/HttpResponse.parseAs:(Ljava/lang/Class;)Ljava/lang/Object;
     237: checkcast     #78                 // class com/google/api/client/util/GenericData
     240: astore        11
     242: aload         10
     244: invokevirtual #80                 // Method com/google/api/client/http/HttpResponse.disconnect:()V
     247: aload         11
     249: ldc           #81                 // String accessToken
     251: ldc           #82                 // String Expected to find an accessToken
     253: invokestatic  #83                 // Method com/google/auth/oauth2/OAuth2Utils.validateString:(Ljava/util/Map;Ljava/lang/String;Ljava/lang/String;)Ljava/lang/String;
     256: astore        12
     258: aload         11
     260: ldc           #84                 // String expireTime
     262: ldc           #85                 // String Expected to find an expireTime
     264: invokestatic  #83                 // Method com/google/auth/oauth2/OAuth2Utils.validateString:(Ljava/util/Map;Ljava/lang/String;Ljava/lang/String;)Ljava/lang/String;
     267: astore        13
     269: new           #86                 // class java/text/SimpleDateFormat
     272: dup
     273: ldc           #87                 // String yyyy-MM-dd\'T\'HH:mm:ss\'Z\'
     275: invokespecial #88                 // Method java/text/SimpleDateFormat."<init>":(Ljava/lang/String;)V
     278: astore        14
     280: aload         14
     282: aload         13
     284: invokevirtual #89                 // Method java/text/DateFormat.parse:(Ljava/lang/String;)Ljava/util/Date;
     287: astore        15
     289: goto          325
     292: astore        16
     294: new           #47                 // class java/io/IOException
     297: dup
     298: new           #63                 // class java/lang/StringBuilder
     301: dup
     302: invokespecial #64                 // Method java/lang/StringBuilder."<init>":()V
     305: ldc           #91                 // String Error parsing expireTime:
     307: invokevirtual #67                 // Method java/lang/StringBuilder.append:(Ljava/lang/String;)Ljava/lang/StringBuilder;
     310: aload         16
     312: invokevirtual #92                 // Method java/text/ParseException.getMessage:()Ljava/lang/String;
     315: invokevirtual #67                 // Method java/lang/StringBuilder.append:(Ljava/lang/String;)Ljava/lang/StringBuilder;
     318: invokevirtual #68                 // Method java/lang/StringBuilder.toString:()Ljava/lang/String;
     321: invokespecial #93                 // Method java/io/IOException."<init>":(Ljava/lang/String;)V
     324: athrow
     325: new           #94                 // class com/google/auth/oauth2/AccessToken
     328: dup
     329: aload         12
     331: aload         15
     333: invokespecial #95                 // Method com/google/auth/oauth2/AccessToken."<init>":(Ljava/lang/String;Ljava/util/Date;)V
     336: areturn
    Exception table:
       from    to  target type
          33    40    43   Class java/io/IOException
         206   213   216   Class java/io/IOException
         280   289   292   Class java/text/ParseException

  public com.google.auth.oauth2.IdToken idTokenWithAudience(java.lang.String, java.util.List<com.google.auth.oauth2.IdTokenProvider$Option>) throws java.io.IOException;
    Code:
       0: aload_2
       1: ifnull        20
       4: aload_2
       5: getstatic     #96                 // Field com/google/auth/oauth2/IdTokenProvider$Option.INCLUDE_EMAIL:Lcom/google/auth/oauth2/IdTokenProvider$Option;
       8: invokeinterface #97,  2           // InterfaceMethod java/util/List.contains:(Ljava/lang/Object;)Z
      13: ifeq          20
      16: iconst_1
      17: goto          21
      20: iconst_0
      21: istore_3
      22: aload_0
      23: invokevirtual #11                 // Method getAccount:()Ljava/lang/String;
      26: aload_0
      27: getfield      #12                 // Field sourceCredentials:Lcom/google/auth/oauth2/GoogleCredentials;
      30: aload_0
      31: getfield      #13                 // Field transportFactory:Lcom/google/auth/http/HttpTransportFactory;
      34: invokeinterface #14,  1           // InterfaceMethod com/google/auth/http/HttpTransportFactory.create:()Lcom/google/api/client/http/HttpTransport;
      39: aload_1
      40: iload_3
      41: ldc           #15                 // String delegates
      43: aload_0
      44: getfield      #16                 // Field delegates:Ljava/util/List;
      47: invokestatic  #17                 // Method com/google/common/collect/ImmutableMap.of:(Ljava/lang/Object;Ljava/lang/Object;)Lcom/google/common/collect/ImmutableMap;
      50: invokestatic  #98                 // Method com/google/auth/oauth2/IamUtils.getIdToken:(Ljava/lang/String;Lcom/google/auth/Credentials;Lcom/google/api/client/http/HttpTransport;Ljava/lang/String;ZLjava/util/Map;)Lcom/google/auth/oauth2/IdToken;
      53: areturn

  public int hashCode();
    Code:
       0: iconst_5
       1: anewarray     #57                 // class java/lang/Object
       4: dup
       5: iconst_0
       6: aload_0
       7: getfield      #12                 // Field sourceCredentials:Lcom/google/auth/oauth2/GoogleCredentials;
      10: aastore
      11: dup
      12: iconst_1
      13: aload_0
      14: getfield      #10                 // Field targetPrincipal:Ljava/lang/String;
      17: aastore
      18: dup
      19: iconst_2
      20: aload_0
      21: getfield      #16                 // Field delegates:Ljava/util/List;
      24: aastore
      25: dup
      26: iconst_3
      27: aload_0
      28: getfield      #24                 // Field scopes:Ljava/util/List;
      31: aastore
      32: dup
      33: iconst_4
      34: aload_0
      35: getfield      #26                 // Field lifetime:I
      38: invokestatic  #99                 // Method java/lang/Integer.valueOf:(I)Ljava/lang/Integer;
      41: aastore
      42: invokestatic  #100                // Method java/util/Objects.hash:([Ljava/lang/Object;)I
      45: ireturn

  public java.lang.String toString();
    Code:
       0: aload_0
       1: invokestatic  #101                // Method com/google/common/base/MoreObjects.toStringHelper:(Ljava/lang/Object;)Lcom/google/common/base/MoreObjects$ToStringHelper;
       4: ldc           #102                // String sourceCredentials
       6: aload_0
       7: getfield      #12                 // Field sourceCredentials:Lcom/google/auth/oauth2/GoogleCredentials;
      10: invokevirtual #103                // Method com/google/common/base/MoreObjects$ToStringHelper.add:(Ljava/lang/String;Ljava/lang/Object;)Lcom/google/common/base/MoreObjects$ToStringHelper;
      13: ldc           #104                // String targetPrincipal
      15: aload_0
      16: getfield      #10                 // Field targetPrincipal:Ljava/lang/String;
      19: invokevirtual #103                // Method com/google/common/base/MoreObjects$ToStringHelper.add:(Ljava/lang/String;Ljava/lang/Object;)Lcom/google/common/base/MoreObjects$ToStringHelper;
      22: ldc           #15                 // String delegates
      24: aload_0
      25: getfield      #16                 // Field delegates:Ljava/util/List;
      28: invokevirtual #103                // Method com/google/common/base/MoreObjects$ToStringHelper.add:(Ljava/lang/String;Ljava/lang/Object;)Lcom/google/common/base/MoreObjects$ToStringHelper;
      31: ldc           #105                // String scopes
      33: aload_0
      34: getfield      #24                 // Field scopes:Ljava/util/List;
      37: invokevirtual #103                // Method com/google/common/base/MoreObjects$ToStringHelper.add:(Ljava/lang/String;Ljava/lang/Object;)Lcom/google/common/base/MoreObjects$ToStringHelper;
      40: ldc           #62                 // String lifetime
      42: aload_0
      43: getfield      #26                 // Field lifetime:I
      46: invokevirtual #106                // Method com/google/common/base/MoreObjects$ToStringHelper.add:(Ljava/lang/String;I)Lcom/google/common/base/MoreObjects$ToStringHelper;
      49: ldc           #107                // String transportFactoryClassName
      51: aload_0
      52: getfield      #34                 // Field transportFactoryClassName:Ljava/lang/String;
      55: invokevirtual #103                // Method com/google/common/base/MoreObjects$ToStringHelper.add:(Ljava/lang/String;Ljava/lang/Object;)Lcom/google/common/base/MoreObjects$ToStringHelper;
      58: invokevirtual #108                // Method com/google/common/base/MoreObjects$ToStringHelper.toString:()Ljava/lang/String;
      61: areturn

  public boolean equals(java.lang.Object);
    Code:
       0: aload_1
       1: instanceof    #38                 // class com/google/auth/oauth2/ImpersonatedCredentials
       4: ifne          9
       7: iconst_0
       8: ireturn
       9: aload_1
      10: checkcast     #38                 // class com/google/auth/oauth2/ImpersonatedCredentials
      13: astore_2
      14: aload_0
      15: getfield      #12                 // Field sourceCredentials:Lcom/google/auth/oauth2/GoogleCredentials;
      18: aload_2
      19: getfield      #12                 // Field sourceCredentials:Lcom/google/auth/oauth2/GoogleCredentials;
      22: invokestatic  #109                // Method java/util/Objects.equals:(Ljava/lang/Object;Ljava/lang/Object;)Z
      25: ifeq          108
      28: aload_0
      29: getfield      #10                 // Field targetPrincipal:Ljava/lang/String;
      32: aload_2
      33: getfield      #10                 // Field targetPrincipal:Ljava/lang/String;
      36: invokestatic  #109                // Method java/util/Objects.equals:(Ljava/lang/Object;Ljava/lang/Object;)Z
      39: ifeq          108
      42: aload_0
      43: getfield      #16                 // Field delegates:Ljava/util/List;
      46: aload_2
      47: getfield      #16                 // Field delegates:Ljava/util/List;
      50: invokestatic  #109                // Method java/util/Objects.equals:(Ljava/lang/Object;Ljava/lang/Object;)Z
      53: ifeq          108
      56: aload_0
      57: getfield      #24                 // Field scopes:Ljava/util/List;
      60: aload_2
      61: getfield      #24                 // Field scopes:Ljava/util/List;
      64: invokestatic  #109                // Method java/util/Objects.equals:(Ljava/lang/Object;Ljava/lang/Object;)Z
      67: ifeq          108
      70: aload_0
      71: getfield      #26                 // Field lifetime:I
      74: invokestatic  #99                 // Method java/lang/Integer.valueOf:(I)Ljava/lang/Integer;
      77: aload_2
      78: getfield      #26                 // Field lifetime:I
      81: invokestatic  #99                 // Method java/lang/Integer.valueOf:(I)Ljava/lang/Integer;
      84: invokestatic  #109                // Method java/util/Objects.equals:(Ljava/lang/Object;Ljava/lang/Object;)Z
      87: ifeq          108
      90: aload_0
      91: getfield      #34                 // Field transportFactoryClassName:Ljava/lang/String;
      94: aload_2
      95: getfield      #34                 // Field transportFactoryClassName:Ljava/lang/String;
      98: invokestatic  #109                // Method java/util/Objects.equals:(Ljava/lang/Object;Ljava/lang/Object;)Z
     101: ifeq          108
     104: iconst_1
     105: goto          109
     108: iconst_0
     109: ireturn

  public com.google.auth.oauth2.ImpersonatedCredentials$Builder toBuilder();
    Code:
       0: new           #110                // class com/google/auth/oauth2/ImpersonatedCredentials$Builder
       3: dup
       4: aload_0
       5: getfield      #12                 // Field sourceCredentials:Lcom/google/auth/oauth2/GoogleCredentials;
       8: aload_0
       9: getfield      #10                 // Field targetPrincipal:Ljava/lang/String;
      12: invokespecial #111                // Method com/google/auth/oauth2/ImpersonatedCredentials$Builder."<init>":(Lcom/google/auth/oauth2/GoogleCredentials;Ljava/lang/String;)V
      15: areturn

  public static com.google.auth.oauth2.ImpersonatedCredentials$Builder newBuilder();
    Code:
       0: new           #110                // class com/google/auth/oauth2/ImpersonatedCredentials$Builder
       3: dup
       4: invokespecial #112                // Method com/google/auth/oauth2/ImpersonatedCredentials$Builder."<init>":()V
       7: areturn

  public com.google.auth.oauth2.GoogleCredentials$Builder toBuilder();
    Code:
       0: aload_0
       1: invokevirtual #113                // Method toBuilder:()Lcom/google/auth/oauth2/ImpersonatedCredentials$Builder;
       4: areturn

  public com.google.auth.oauth2.OAuth2Credentials$Builder toBuilder();
    Code:
       0: aload_0
       1: invokevirtual #113                // Method toBuilder:()Lcom/google/auth/oauth2/ImpersonatedCredentials$Builder;
       4: areturn

  com.google.auth.oauth2.ImpersonatedCredentials(com.google.auth.oauth2.ImpersonatedCredentials$Builder, com.google.auth.oauth2.ImpersonatedCredentials$1);
    Code:
       0: aload_0
       1: aload_1
       2: invokespecial #1                  // Method "<init>":(Lcom/google/auth/oauth2/ImpersonatedCredentials$Builder;)V
       5: return
}
