Compiled from "JwtCredentials.java"
public class com.google.auth.oauth2.JwtCredentials$Builder {
  private java.security.PrivateKey privateKey;

  private java.lang.String privateKeyId;

  private com.google.auth.oauth2.JwtClaims jwtClaims;

  private com.google.api.client.util.Clock clock;

  private java.lang.Long lifeSpanSeconds;

  protected com.google.auth.oauth2.JwtCredentials$Builder();
    Code:
       0: aload_0
       1: invokespecial #1                  // Method java/lang/Object."<init>":()V
       4: aload_0
       5: getstatic     #2                  // Field com/google/api/client/util/Clock.SYSTEM:Lcom/google/api/client/util/Clock;
       8: putfield      #3                  // Field clock:Lcom/google/api/client/util/Clock;
      11: aload_0
      12: getstatic     #4                  // Field java/util/concurrent/TimeUnit.HOURS:Ljava/util/concurrent/TimeUnit;
      15: lconst_1
      16: invokevirtual #5                  // Method java/util/concurrent/TimeUnit.toSeconds:(J)J
      19: invokestatic  #6                  // Method java/lang/Long.valueOf:(J)Ljava/lang/Long;
      22: putfield      #7                  // Field lifeSpanSeconds:Ljava/lang/Long;
      25: return

  public com.google.auth.oauth2.JwtCredentials$Builder setPrivateKey(java.security.PrivateKey);
    Code:
       0: aload_0
       1: aload_1
       2: invokestatic  #8                  // Method com/google/common/base/Preconditions.checkNotNull:(Ljava/lang/Object;)Ljava/lang/Object;
       5: checkcast     #9                  // class java/security/PrivateKey
       8: putfield      #10                 // Field privateKey:Ljava/security/PrivateKey;
      11: aload_0
      12: areturn

  public java.security.PrivateKey getPrivateKey();
    Code:
       0: aload_0
       1: getfield      #10                 // Field privateKey:Ljava/security/PrivateKey;
       4: areturn

  public com.google.auth.oauth2.JwtCredentials$Builder setPrivateKeyId(java.lang.String);
    Code:
       0: aload_0
       1: aload_1
       2: putfield      #11                 // Field privateKeyId:Ljava/lang/String;
       5: aload_0
       6: areturn

  public java.lang.String getPrivateKeyId();
    Code:
       0: aload_0
       1: getfield      #11                 // Field privateKeyId:Ljava/lang/String;
       4: areturn

  public com.google.auth.oauth2.JwtCredentials$Builder setJwtClaims(com.google.auth.oauth2.JwtClaims);
    Code:
       0: aload_0
       1: aload_1
       2: invokestatic  #8                  // Method com/google/common/base/Preconditions.checkNotNull:(Ljava/lang/Object;)Ljava/lang/Object;
       5: checkcast     #12                 // class com/google/auth/oauth2/JwtClaims
       8: putfield      #13                 // Field jwtClaims:Lcom/google/auth/oauth2/JwtClaims;
      11: aload_0
      12: areturn

  public com.google.auth.oauth2.JwtClaims getJwtClaims();
    Code:
       0: aload_0
       1: getfield      #13                 // Field jwtClaims:Lcom/google/auth/oauth2/JwtClaims;
       4: areturn

  public com.google.auth.oauth2.JwtCredentials$Builder setLifeSpanSeconds(java.lang.Long);
    Code:
       0: aload_0
       1: aload_1
       2: invokestatic  #8                  // Method com/google/common/base/Preconditions.checkNotNull:(Ljava/lang/Object;)Ljava/lang/Object;
       5: checkcast     #14                 // class java/lang/Long
       8: putfield      #7                  // Field lifeSpanSeconds:Ljava/lang/Long;
      11: aload_0
      12: areturn

  public java.lang.Long getLifeSpanSeconds();
    Code:
       0: aload_0
       1: getfield      #7                  // Field lifeSpanSeconds:Ljava/lang/Long;
       4: areturn

  com.google.auth.oauth2.JwtCredentials$Builder setClock(com.google.api.client.util.Clock);
    Code:
       0: aload_0
       1: aload_1
       2: invokestatic  #8                  // Method com/google/common/base/Preconditions.checkNotNull:(Ljava/lang/Object;)Ljava/lang/Object;
       5: checkcast     #15                 // class com/google/api/client/util/Clock
       8: putfield      #3                  // Field clock:Lcom/google/api/client/util/Clock;
      11: aload_0
      12: areturn

  com.google.api.client.util.Clock getClock();
    Code:
       0: aload_0
       1: getfield      #3                  // Field clock:Lcom/google/api/client/util/Clock;
       4: areturn

  public com.google.auth.oauth2.JwtCredentials build();
    Code:
       0: new           #16                 // class com/google/auth/oauth2/JwtCredentials
       3: dup
       4: aload_0
       5: aconst_null
       6: invokespecial #17                 // Method com/google/auth/oauth2/JwtCredentials."<init>":(Lcom/google/auth/oauth2/JwtCredentials$Builder;Lcom/google/auth/oauth2/JwtCredentials$1;)V
       9: areturn
}
