Compiled from "ServiceAccountJwtAccessCredentials.java"
class com.google.auth.oauth2.ServiceAccountJwtAccessCredentials$1 extends com.google.common.cache.CacheLoader<com.google.auth.oauth2.JwtClaims, com.google.auth.oauth2.JwtCredentials> {
  final com.google.auth.oauth2.ServiceAccountJwtAccessCredentials this$0;

  com.google.auth.oauth2.ServiceAccountJwtAccessCredentials$1(com.google.auth.oauth2.ServiceAccountJwtAccessCredentials);
    Code:
       0: aload_0
       1: aload_1
       2: putfield      #1                  // Field this$0:Lcom/google/auth/oauth2/ServiceAccountJwtAccessCredentials;
       5: aload_0
       6: invokespecial #2                  // Method com/google/common/cache/CacheLoader."<init>":()V
       9: return

  public com.google.auth.oauth2.JwtCredentials load(com.google.auth.oauth2.JwtClaims) throws java.lang.Exception;
    Code:
       0: invokestatic  #3                  // Method com/google/auth/oauth2/JwtCredentials.newBuilder:()Lcom/google/auth/oauth2/JwtCredentials$Builder;
       3: aload_0
       4: getfield      #1                  // Field this$0:Lcom/google/auth/oauth2/ServiceAccountJwtAccessCredentials;
       7: invokestatic  #4                  // Method com/google/auth/oauth2/ServiceAccountJwtAccessCredentials.access$100:(Lcom/google/auth/oauth2/ServiceAccountJwtAccessCredentials;)Ljava/security/PrivateKey;
      10: invokevirtual #5                  // Method com/google/auth/oauth2/JwtCredentials$Builder.setPrivateKey:(Ljava/security/PrivateKey;)Lcom/google/auth/oauth2/JwtCredentials$Builder;
      13: aload_0
      14: getfield      #1                  // Field this$0:Lcom/google/auth/oauth2/ServiceAccountJwtAccessCredentials;
      17: invokestatic  #6                  // Method com/google/auth/oauth2/ServiceAccountJwtAccessCredentials.access$000:(Lcom/google/auth/oauth2/ServiceAccountJwtAccessCredentials;)Ljava/lang/String;
      20: invokevirtual #7                  // Method com/google/auth/oauth2/JwtCredentials$Builder.setPrivateKeyId:(Ljava/lang/String;)Lcom/google/auth/oauth2/JwtCredentials$Builder;
      23: aload_1
      24: invokevirtual #8                  // Method com/google/auth/oauth2/JwtCredentials$Builder.setJwtClaims:(Lcom/google/auth/oauth2/JwtClaims;)Lcom/google/auth/oauth2/JwtCredentials$Builder;
      27: getstatic     #9                  // Field com/google/auth/oauth2/ServiceAccountJwtAccessCredentials.LIFE_SPAN_SECS:J
      30: invokestatic  #10                 // Method java/lang/Long.valueOf:(J)Ljava/lang/Long;
      33: invokevirtual #11                 // Method com/google/auth/oauth2/JwtCredentials$Builder.setLifeSpanSeconds:(Ljava/lang/Long;)Lcom/google/auth/oauth2/JwtCredentials$Builder;
      36: aload_0
      37: getfield      #1                  // Field this$0:Lcom/google/auth/oauth2/ServiceAccountJwtAccessCredentials;
      40: getfield      #12                 // Field com/google/auth/oauth2/ServiceAccountJwtAccessCredentials.clock:Lcom/google/api/client/util/Clock;
      43: invokevirtual #13                 // Method com/google/auth/oauth2/JwtCredentials$Builder.setClock:(Lcom/google/api/client/util/Clock;)Lcom/google/auth/oauth2/JwtCredentials$Builder;
      46: invokevirtual #14                 // Method com/google/auth/oauth2/JwtCredentials$Builder.build:()Lcom/google/auth/oauth2/JwtCredentials;
      49: areturn

  public java.lang.Object load(java.lang.Object) throws java.lang.Exception;
    Code:
       0: aload_0
       1: aload_1
       2: checkcast     #15                 // class com/google/auth/oauth2/JwtClaims
       5: invokevirtual #16                 // Method load:(Lcom/google/auth/oauth2/JwtClaims;)Lcom/google/auth/oauth2/JwtCredentials;
       8: areturn
}
