Compiled from "UserCredentials.java"
public class com.google.auth.oauth2.UserCredentials extends com.google.auth.oauth2.GoogleCredentials implements com.google.auth.oauth2.QuotaProjectIdProvider {
  private static final java.lang.String GRANT_TYPE;

  private static final java.lang.String PARSE_ERROR_PREFIX;

  private static final long serialVersionUID;

  private final java.lang.String clientId;

  private final java.lang.String clientSecret;

  private final java.lang.String refreshToken;

  private final java.net.URI tokenServerUri;

  private final java.lang.String transportFactoryClassName;

  private final java.lang.String quotaProjectId;

  private transient com.google.auth.http.HttpTransportFactory transportFactory;

  private com.google.auth.oauth2.UserCredentials(java.lang.String, java.lang.String, java.lang.String, com.google.auth.oauth2.AccessToken, com.google.auth.http.HttpTransportFactory, java.net.URI, java.lang.String);
    Code:
       0: aload_0
       1: aload         4
       3: invokespecial #8                  // Method com/google/auth/oauth2/GoogleCredentials."<init>":(Lcom/google/auth/oauth2/AccessToken;)V
       6: aload_0
       7: aload_1
       8: invokestatic  #9                  // Method com/google/api/client/util/Preconditions.checkNotNull:(Ljava/lang/Object;)Ljava/lang/Object;
      11: checkcast     #10                 // class java/lang/String
      14: putfield      #7                  // Field clientId:Ljava/lang/String;
      17: aload_0
      18: aload_2
      19: invokestatic  #9                  // Method com/google/api/client/util/Preconditions.checkNotNull:(Ljava/lang/Object;)Ljava/lang/Object;
      22: checkcast     #10                 // class java/lang/String
      25: putfield      #6                  // Field clientSecret:Ljava/lang/String;
      28: aload_0
      29: aload_3
      30: putfield      #5                  // Field refreshToken:Ljava/lang/String;
      33: aload_0
      34: aload         5
      36: ldc           #11                 // class com/google/auth/http/HttpTransportFactory
      38: getstatic     #12                 // Field com/google/auth/oauth2/OAuth2Utils.HTTP_TRANSPORT_FACTORY:Lcom/google/auth/http/HttpTransportFactory;
      41: invokestatic  #13                 // Method getFromServiceLoader:(Ljava/lang/Class;Ljava/lang/Object;)Ljava/lang/Object;
      44: invokestatic  #14                 // Method com/google/common/base/MoreObjects.firstNonNull:(Ljava/lang/Object;Ljava/lang/Object;)Ljava/lang/Object;
      47: checkcast     #11                 // class com/google/auth/http/HttpTransportFactory
      50: putfield      #4                  // Field transportFactory:Lcom/google/auth/http/HttpTransportFactory;
      53: aload_0
      54: aload         6
      56: ifnonnull     65
      59: getstatic     #15                 // Field com/google/auth/oauth2/OAuth2Utils.TOKEN_SERVER_URI:Ljava/net/URI;
      62: goto          67
      65: aload         6
      67: putfield      #3                  // Field tokenServerUri:Ljava/net/URI;
      70: aload_0
      71: aload_0
      72: getfield      #4                  // Field transportFactory:Lcom/google/auth/http/HttpTransportFactory;
      75: invokevirtual #16                 // Method java/lang/Object.getClass:()Ljava/lang/Class;
      78: invokevirtual #17                 // Method java/lang/Class.getName:()Ljava/lang/String;
      81: putfield      #18                 // Field transportFactoryClassName:Ljava/lang/String;
      84: aload_0
      85: aload         7
      87: putfield      #2                  // Field quotaProjectId:Ljava/lang/String;
      90: aload         4
      92: ifnonnull     99
      95: aload_3
      96: ifnull        103
      99: iconst_1
     100: goto          104
     103: iconst_0
     104: ldc           #19                 // String Either accessToken or refreshToken must not be null
     106: invokestatic  #20                 // Method com/google/api/client/util/Preconditions.checkState:(ZLjava/lang/Object;)V
     109: return

  static com.google.auth.oauth2.UserCredentials fromJson(java.util.Map<java.lang.String, java.lang.Object>, com.google.auth.http.HttpTransportFactory) throws java.io.IOException;
    Code:
       0: aload_0
       1: ldc           #21                 // String client_id
       3: invokeinterface #22,  2           // InterfaceMethod java/util/Map.get:(Ljava/lang/Object;)Ljava/lang/Object;
       8: checkcast     #10                 // class java/lang/String
      11: astore_2
      12: aload_0
      13: ldc           #23                 // String client_secret
      15: invokeinterface #22,  2           // InterfaceMethod java/util/Map.get:(Ljava/lang/Object;)Ljava/lang/Object;
      20: checkcast     #10                 // class java/lang/String
      23: astore_3
      24: aload_0
      25: ldc           #24                 // String refresh_token
      27: invokeinterface #22,  2           // InterfaceMethod java/util/Map.get:(Ljava/lang/Object;)Ljava/lang/Object;
      32: checkcast     #10                 // class java/lang/String
      35: astore        4
      37: aload_0
      38: ldc           #25                 // String quota_project_id
      40: invokeinterface #22,  2           // InterfaceMethod java/util/Map.get:(Ljava/lang/Object;)Ljava/lang/Object;
      45: checkcast     #10                 // class java/lang/String
      48: astore        5
      50: aload_2
      51: ifnull        63
      54: aload_3
      55: ifnull        63
      58: aload         4
      60: ifnonnull     73
      63: new           #26                 // class java/io/IOException
      66: dup
      67: ldc           #27                 // String Error reading user credential from JSON,  expecting \'client_id\', \'client_secret\' and \'refresh_token\'.
      69: invokespecial #28                 // Method java/io/IOException."<init>":(Ljava/lang/String;)V
      72: athrow
      73: invokestatic  #29                 // Method newBuilder:()Lcom/google/auth/oauth2/UserCredentials$Builder;
      76: aload_2
      77: invokevirtual #30                 // Method com/google/auth/oauth2/UserCredentials$Builder.setClientId:(Ljava/lang/String;)Lcom/google/auth/oauth2/UserCredentials$Builder;
      80: aload_3
      81: invokevirtual #31                 // Method com/google/auth/oauth2/UserCredentials$Builder.setClientSecret:(Ljava/lang/String;)Lcom/google/auth/oauth2/UserCredentials$Builder;
      84: aload         4
      86: invokevirtual #32                 // Method com/google/auth/oauth2/UserCredentials$Builder.setRefreshToken:(Ljava/lang/String;)Lcom/google/auth/oauth2/UserCredentials$Builder;
      89: aconst_null
      90: invokevirtual #33                 // Method com/google/auth/oauth2/UserCredentials$Builder.setAccessToken:(Lcom/google/auth/oauth2/AccessToken;)Lcom/google/auth/oauth2/UserCredentials$Builder;
      93: aload_1
      94: invokevirtual #34                 // Method com/google/auth/oauth2/UserCredentials$Builder.setHttpTransportFactory:(Lcom/google/auth/http/HttpTransportFactory;)Lcom/google/auth/oauth2/UserCredentials$Builder;
      97: aconst_null
      98: invokevirtual #35                 // Method com/google/auth/oauth2/UserCredentials$Builder.setTokenServerUri:(Ljava/net/URI;)Lcom/google/auth/oauth2/UserCredentials$Builder;
     101: aload         5
     103: invokevirtual #36                 // Method com/google/auth/oauth2/UserCredentials$Builder.setQuotaProjectId:(Ljava/lang/String;)Lcom/google/auth/oauth2/UserCredentials$Builder;
     106: invokevirtual #37                 // Method com/google/auth/oauth2/UserCredentials$Builder.build:()Lcom/google/auth/oauth2/UserCredentials;
     109: areturn

  public static com.google.auth.oauth2.UserCredentials fromStream(java.io.InputStream) throws java.io.IOException;
    Code:
       0: aload_0
       1: getstatic     #12                 // Field com/google/auth/oauth2/OAuth2Utils.HTTP_TRANSPORT_FACTORY:Lcom/google/auth/http/HttpTransportFactory;
       4: invokestatic  #38                 // Method fromStream:(Ljava/io/InputStream;Lcom/google/auth/http/HttpTransportFactory;)Lcom/google/auth/oauth2/UserCredentials;
       7: areturn

  public static com.google.auth.oauth2.UserCredentials fromStream(java.io.InputStream, com.google.auth.http.HttpTransportFactory) throws java.io.IOException;
    Code:
       0: aload_0
       1: invokestatic  #9                  // Method com/google/api/client/util/Preconditions.checkNotNull:(Ljava/lang/Object;)Ljava/lang/Object;
       4: pop
       5: aload_1
       6: invokestatic  #9                  // Method com/google/api/client/util/Preconditions.checkNotNull:(Ljava/lang/Object;)Ljava/lang/Object;
       9: pop
      10: getstatic     #39                 // Field com/google/auth/oauth2/OAuth2Utils.JSON_FACTORY:Lcom/google/api/client/json/JsonFactory;
      13: astore_2
      14: new           #40                 // class com/google/api/client/json/JsonObjectParser
      17: dup
      18: aload_2
      19: invokespecial #41                 // Method com/google/api/client/json/JsonObjectParser."<init>":(Lcom/google/api/client/json/JsonFactory;)V
      22: astore_3
      23: aload_3
      24: aload_0
      25: getstatic     #42                 // Field com/google/auth/oauth2/OAuth2Utils.UTF_8:Ljava/nio/charset/Charset;
      28: ldc           #43                 // class com/google/api/client/json/GenericJson
      30: invokevirtual #44                 // Method com/google/api/client/json/JsonObjectParser.parseAndClose:(Ljava/io/InputStream;Ljava/nio/charset/Charset;Ljava/lang/Class;)Ljava/lang/Object;
      33: checkcast     #43                 // class com/google/api/client/json/GenericJson
      36: astore        4
      38: aload         4
      40: ldc           #45                 // String type
      42: invokevirtual #46                 // Method com/google/api/client/json/GenericJson.get:(Ljava/lang/Object;)Ljava/lang/Object;
      45: checkcast     #10                 // class java/lang/String
      48: astore        5
      50: aload         5
      52: ifnonnull     65
      55: new           #26                 // class java/io/IOException
      58: dup
      59: ldc           #47                 // String Error reading credentials from stream, \'type\' field not specified.
      61: invokespecial #28                 // Method java/io/IOException."<init>":(Ljava/lang/String;)V
      64: athrow
      65: ldc           #49                 // String authorized_user
      67: aload         5
      69: invokevirtual #50                 // Method java/lang/String.equals:(Ljava/lang/Object;)Z
      72: ifeq          82
      75: aload         4
      77: aload_1
      78: invokestatic  #51                 // Method fromJson:(Ljava/util/Map;Lcom/google/auth/http/HttpTransportFactory;)Lcom/google/auth/oauth2/UserCredentials;
      81: areturn
      82: new           #26                 // class java/io/IOException
      85: dup
      86: ldc           #52                 // String Error reading credentials from stream, \'type\' value \'%s\' not recognized. Expecting \'%s\'.
      88: iconst_2
      89: anewarray     #53                 // class java/lang/Object
      92: dup
      93: iconst_0
      94: aload         5
      96: aastore
      97: dup
      98: iconst_1
      99: ldc           #49                 // String authorized_user
     101: aastore
     102: invokestatic  #54                 // Method java/lang/String.format:(Ljava/lang/String;[Ljava/lang/Object;)Ljava/lang/String;
     105: invokespecial #28                 // Method java/io/IOException."<init>":(Ljava/lang/String;)V
     108: athrow

  public com.google.auth.oauth2.AccessToken refreshAccessToken() throws java.io.IOException;
    Code:
       0: aload_0
       1: getfield      #5                  // Field refreshToken:Ljava/lang/String;
       4: ifnonnull     17
       7: new           #55                 // class java/lang/IllegalStateException
      10: dup
      11: ldc           #56                 // String UserCredentials instance cannot refresh because there is no refresh token.
      13: invokespecial #57                 // Method java/lang/IllegalStateException."<init>":(Ljava/lang/String;)V
      16: athrow
      17: new           #58                 // class com/google/api/client/util/GenericData
      20: dup
      21: invokespecial #59                 // Method com/google/api/client/util/GenericData."<init>":()V
      24: astore_1
      25: aload_1
      26: ldc           #21                 // String client_id
      28: aload_0
      29: getfield      #7                  // Field clientId:Ljava/lang/String;
      32: invokevirtual #60                 // Method com/google/api/client/util/GenericData.set:(Ljava/lang/String;Ljava/lang/Object;)Lcom/google/api/client/util/GenericData;
      35: pop
      36: aload_1
      37: ldc           #23                 // String client_secret
      39: aload_0
      40: getfield      #6                  // Field clientSecret:Ljava/lang/String;
      43: invokevirtual #60                 // Method com/google/api/client/util/GenericData.set:(Ljava/lang/String;Ljava/lang/Object;)Lcom/google/api/client/util/GenericData;
      46: pop
      47: aload_1
      48: ldc           #24                 // String refresh_token
      50: aload_0
      51: getfield      #5                  // Field refreshToken:Ljava/lang/String;
      54: invokevirtual #60                 // Method com/google/api/client/util/GenericData.set:(Ljava/lang/String;Ljava/lang/Object;)Lcom/google/api/client/util/GenericData;
      57: pop
      58: aload_1
      59: ldc           #61                 // String grant_type
      61: ldc           #24                 // String refresh_token
      63: invokevirtual #60                 // Method com/google/api/client/util/GenericData.set:(Ljava/lang/String;Ljava/lang/Object;)Lcom/google/api/client/util/GenericData;
      66: pop
      67: new           #63                 // class com/google/api/client/http/UrlEncodedContent
      70: dup
      71: aload_1
      72: invokespecial #64                 // Method com/google/api/client/http/UrlEncodedContent."<init>":(Ljava/lang/Object;)V
      75: astore_2
      76: aload_0
      77: getfield      #4                  // Field transportFactory:Lcom/google/auth/http/HttpTransportFactory;
      80: invokeinterface #65,  1           // InterfaceMethod com/google/auth/http/HttpTransportFactory.create:()Lcom/google/api/client/http/HttpTransport;
      85: invokevirtual #66                 // Method com/google/api/client/http/HttpTransport.createRequestFactory:()Lcom/google/api/client/http/HttpRequestFactory;
      88: astore_3
      89: aload_3
      90: new           #67                 // class com/google/api/client/http/GenericUrl
      93: dup
      94: aload_0
      95: getfield      #3                  // Field tokenServerUri:Ljava/net/URI;
      98: invokespecial #68                 // Method com/google/api/client/http/GenericUrl."<init>":(Ljava/net/URI;)V
     101: aload_2
     102: invokevirtual #69                 // Method com/google/api/client/http/HttpRequestFactory.buildPostRequest:(Lcom/google/api/client/http/GenericUrl;Lcom/google/api/client/http/HttpContent;)Lcom/google/api/client/http/HttpRequest;
     105: astore        4
     107: aload         4
     109: new           #40                 // class com/google/api/client/json/JsonObjectParser
     112: dup
     113: getstatic     #39                 // Field com/google/auth/oauth2/OAuth2Utils.JSON_FACTORY:Lcom/google/api/client/json/JsonFactory;
     116: invokespecial #41                 // Method com/google/api/client/json/JsonObjectParser."<init>":(Lcom/google/api/client/json/JsonFactory;)V
     119: invokevirtual #70                 // Method com/google/api/client/http/HttpRequest.setParser:(Lcom/google/api/client/util/ObjectParser;)Lcom/google/api/client/http/HttpRequest;
     122: pop
     123: aload         4
     125: invokevirtual #71                 // Method com/google/api/client/http/HttpRequest.execute:()Lcom/google/api/client/http/HttpResponse;
     128: astore        5
     130: aload         5
     132: ldc           #58                 // class com/google/api/client/util/GenericData
     134: invokevirtual #72                 // Method com/google/api/client/http/HttpResponse.parseAs:(Ljava/lang/Class;)Ljava/lang/Object;
     137: checkcast     #58                 // class com/google/api/client/util/GenericData
     140: astore        6
     142: aload         6
     144: ldc           #73                 // String access_token
     146: ldc           #74                 // String Error parsing token refresh response.
     148: invokestatic  #75                 // Method com/google/auth/oauth2/OAuth2Utils.validateString:(Ljava/util/Map;Ljava/lang/String;Ljava/lang/String;)Ljava/lang/String;
     151: astore        7
     153: aload         6
     155: ldc           #76                 // String expires_in
     157: ldc           #74                 // String Error parsing token refresh response.
     159: invokestatic  #77                 // Method com/google/auth/oauth2/OAuth2Utils.validateInt32:(Ljava/util/Map;Ljava/lang/String;Ljava/lang/String;)I
     162: istore        8
     164: aload_0
     165: getfield      #78                 // Field clock:Lcom/google/api/client/util/Clock;
     168: invokeinterface #79,  1           // InterfaceMethod com/google/api/client/util/Clock.currentTimeMillis:()J
     173: iload         8
     175: sipush        1000
     178: imul
     179: i2l
     180: ladd
     181: lstore        9
     183: new           #80                 // class com/google/auth/oauth2/AccessToken
     186: dup
     187: aload         7
     189: new           #81                 // class java/util/Date
     192: dup
     193: lload         9
     195: invokespecial #82                 // Method java/util/Date."<init>":(J)V
     198: invokespecial #83                 // Method com/google/auth/oauth2/AccessToken."<init>":(Ljava/lang/String;Ljava/util/Date;)V
     201: areturn

  public final java.lang.String getClientId();
    Code:
       0: aload_0
       1: getfield      #7                  // Field clientId:Ljava/lang/String;
       4: areturn

  public final java.lang.String getClientSecret();
    Code:
       0: aload_0
       1: getfield      #6                  // Field clientSecret:Ljava/lang/String;
       4: areturn

  public final java.lang.String getRefreshToken();
    Code:
       0: aload_0
       1: getfield      #5                  // Field refreshToken:Ljava/lang/String;
       4: areturn

  private java.io.InputStream getUserCredentialsStream() throws java.io.IOException;
    Code:
       0: new           #43                 // class com/google/api/client/json/GenericJson
       3: dup
       4: invokespecial #84                 // Method com/google/api/client/json/GenericJson."<init>":()V
       7: astore_1
       8: aload_1
       9: ldc           #45                 // String type
      11: ldc           #49                 // String authorized_user
      13: invokevirtual #85                 // Method com/google/api/client/json/GenericJson.put:(Ljava/lang/String;Ljava/lang/Object;)Ljava/lang/Object;
      16: pop
      17: aload_0
      18: getfield      #5                  // Field refreshToken:Ljava/lang/String;
      21: ifnull        35
      24: aload_1
      25: ldc           #24                 // String refresh_token
      27: aload_0
      28: getfield      #5                  // Field refreshToken:Ljava/lang/String;
      31: invokevirtual #85                 // Method com/google/api/client/json/GenericJson.put:(Ljava/lang/String;Ljava/lang/Object;)Ljava/lang/Object;
      34: pop
      35: aload_0
      36: getfield      #3                  // Field tokenServerUri:Ljava/net/URI;
      39: ifnull        53
      42: aload_1
      43: ldc           #86                 // String token_server_uri
      45: aload_0
      46: getfield      #3                  // Field tokenServerUri:Ljava/net/URI;
      49: invokevirtual #85                 // Method com/google/api/client/json/GenericJson.put:(Ljava/lang/String;Ljava/lang/Object;)Ljava/lang/Object;
      52: pop
      53: aload_0
      54: getfield      #7                  // Field clientId:Ljava/lang/String;
      57: ifnull        71
      60: aload_1
      61: ldc           #21                 // String client_id
      63: aload_0
      64: getfield      #7                  // Field clientId:Ljava/lang/String;
      67: invokevirtual #85                 // Method com/google/api/client/json/GenericJson.put:(Ljava/lang/String;Ljava/lang/Object;)Ljava/lang/Object;
      70: pop
      71: aload_0
      72: getfield      #6                  // Field clientSecret:Ljava/lang/String;
      75: ifnull        89
      78: aload_1
      79: ldc           #23                 // String client_secret
      81: aload_0
      82: getfield      #6                  // Field clientSecret:Ljava/lang/String;
      85: invokevirtual #85                 // Method com/google/api/client/json/GenericJson.put:(Ljava/lang/String;Ljava/lang/Object;)Ljava/lang/Object;
      88: pop
      89: aload_0
      90: getfield      #2                  // Field quotaProjectId:Ljava/lang/String;
      93: ifnull        107
      96: aload_1
      97: ldc           #87                 // String quota_project
      99: aload_0
     100: getfield      #6                  // Field clientSecret:Ljava/lang/String;
     103: invokevirtual #85                 // Method com/google/api/client/json/GenericJson.put:(Ljava/lang/String;Ljava/lang/Object;)Ljava/lang/Object;
     106: pop
     107: aload_1
     108: getstatic     #39                 // Field com/google/auth/oauth2/OAuth2Utils.JSON_FACTORY:Lcom/google/api/client/json/JsonFactory;
     111: invokevirtual #88                 // Method com/google/api/client/json/GenericJson.setFactory:(Lcom/google/api/client/json/JsonFactory;)V
     114: aload_1
     115: invokevirtual #89                 // Method com/google/api/client/json/GenericJson.toPrettyString:()Ljava/lang/String;
     118: astore_2
     119: new           #90                 // class java/io/ByteArrayInputStream
     122: dup
     123: aload_2
     124: getstatic     #42                 // Field com/google/auth/oauth2/OAuth2Utils.UTF_8:Ljava/nio/charset/Charset;
     127: invokevirtual #91                 // Method java/lang/String.getBytes:(Ljava/nio/charset/Charset;)[B
     130: invokespecial #92                 // Method java/io/ByteArrayInputStream."<init>":([B)V
     133: areturn

  public void save(java.lang.String) throws java.io.IOException;
    Code:
       0: aload_0
       1: invokespecial #93                 // Method getUserCredentialsStream:()Ljava/io/InputStream;
       4: aload_1
       5: invokestatic  #94                 // Method com/google/auth/oauth2/OAuth2Utils.writeInputStreamToFile:(Ljava/io/InputStream;Ljava/lang/String;)V
       8: return

  protected java.util.Map<java.lang.String, java.util.List<java.lang.String>> getAdditionalHeaders();
    Code:
       0: aload_0
       1: invokespecial #95                 // Method com/google/auth/oauth2/GoogleCredentials.getAdditionalHeaders:()Ljava/util/Map;
       4: astore_1
       5: aload_0
       6: getfield      #2                  // Field quotaProjectId:Ljava/lang/String;
       9: ifnull        21
      12: aload_0
      13: getfield      #2                  // Field quotaProjectId:Ljava/lang/String;
      16: aload_1
      17: invokestatic  #96                 // Method addQuotaProjectIdToRequestMetadata:(Ljava/lang/String;Ljava/util/Map;)Ljava/util/Map;
      20: areturn
      21: aload_1
      22: areturn

  public int hashCode();
    Code:
       0: bipush        7
       2: anewarray     #53                 // class java/lang/Object
       5: dup
       6: iconst_0
       7: aload_0
       8: invokespecial #97                 // Method com/google/auth/oauth2/GoogleCredentials.hashCode:()I
      11: invokestatic  #98                 // Method java/lang/Integer.valueOf:(I)Ljava/lang/Integer;
      14: aastore
      15: dup
      16: iconst_1
      17: aload_0
      18: getfield      #7                  // Field clientId:Ljava/lang/String;
      21: aastore
      22: dup
      23: iconst_2
      24: aload_0
      25: getfield      #6                  // Field clientSecret:Ljava/lang/String;
      28: aastore
      29: dup
      30: iconst_3
      31: aload_0
      32: getfield      #5                  // Field refreshToken:Ljava/lang/String;
      35: aastore
      36: dup
      37: iconst_4
      38: aload_0
      39: getfield      #3                  // Field tokenServerUri:Ljava/net/URI;
      42: aastore
      43: dup
      44: iconst_5
      45: aload_0
      46: getfield      #18                 // Field transportFactoryClassName:Ljava/lang/String;
      49: aastore
      50: dup
      51: bipush        6
      53: aload_0
      54: getfield      #2                  // Field quotaProjectId:Ljava/lang/String;
      57: aastore
      58: invokestatic  #99                 // Method java/util/Objects.hash:([Ljava/lang/Object;)I
      61: ireturn

  public java.lang.String toString();
    Code:
       0: aload_0
       1: invokestatic  #100                // Method com/google/common/base/MoreObjects.toStringHelper:(Ljava/lang/Object;)Lcom/google/common/base/MoreObjects$ToStringHelper;
       4: ldc           #101                // String requestMetadata
       6: aload_0
       7: invokevirtual #102                // Method getRequestMetadataInternal:()Ljava/util/Map;
      10: invokevirtual #103                // Method com/google/common/base/MoreObjects$ToStringHelper.add:(Ljava/lang/String;Ljava/lang/Object;)Lcom/google/common/base/MoreObjects$ToStringHelper;
      13: ldc           #104                // String temporaryAccess
      15: aload_0
      16: invokevirtual #105                // Method getAccessToken:()Lcom/google/auth/oauth2/AccessToken;
      19: invokevirtual #103                // Method com/google/common/base/MoreObjects$ToStringHelper.add:(Ljava/lang/String;Ljava/lang/Object;)Lcom/google/common/base/MoreObjects$ToStringHelper;
      22: ldc           #106                // String clientId
      24: aload_0
      25: getfield      #7                  // Field clientId:Ljava/lang/String;
      28: invokevirtual #103                // Method com/google/common/base/MoreObjects$ToStringHelper.add:(Ljava/lang/String;Ljava/lang/Object;)Lcom/google/common/base/MoreObjects$ToStringHelper;
      31: ldc           #107                // String refreshToken
      33: aload_0
      34: getfield      #5                  // Field refreshToken:Ljava/lang/String;
      37: invokevirtual #103                // Method com/google/common/base/MoreObjects$ToStringHelper.add:(Ljava/lang/String;Ljava/lang/Object;)Lcom/google/common/base/MoreObjects$ToStringHelper;
      40: ldc           #108                // String tokenServerUri
      42: aload_0
      43: getfield      #3                  // Field tokenServerUri:Ljava/net/URI;
      46: invokevirtual #103                // Method com/google/common/base/MoreObjects$ToStringHelper.add:(Ljava/lang/String;Ljava/lang/Object;)Lcom/google/common/base/MoreObjects$ToStringHelper;
      49: ldc           #109                // String transportFactoryClassName
      51: aload_0
      52: getfield      #18                 // Field transportFactoryClassName:Ljava/lang/String;
      55: invokevirtual #103                // Method com/google/common/base/MoreObjects$ToStringHelper.add:(Ljava/lang/String;Ljava/lang/Object;)Lcom/google/common/base/MoreObjects$ToStringHelper;
      58: ldc           #110                // String quotaProjectId
      60: aload_0
      61: getfield      #2                  // Field quotaProjectId:Ljava/lang/String;
      64: invokevirtual #103                // Method com/google/common/base/MoreObjects$ToStringHelper.add:(Ljava/lang/String;Ljava/lang/Object;)Lcom/google/common/base/MoreObjects$ToStringHelper;
      67: invokevirtual #111                // Method com/google/common/base/MoreObjects$ToStringHelper.toString:()Ljava/lang/String;
      70: areturn

  public boolean equals(java.lang.Object);
    Code:
       0: aload_1
       1: instanceof    #62                 // class com/google/auth/oauth2/UserCredentials
       4: ifne          9
       7: iconst_0
       8: ireturn
       9: aload_1
      10: checkcast     #62                 // class com/google/auth/oauth2/UserCredentials
      13: astore_2
      14: aload_0
      15: aload_2
      16: invokespecial #112                // Method com/google/auth/oauth2/GoogleCredentials.equals:(Ljava/lang/Object;)Z
      19: ifeq          110
      22: aload_0
      23: getfield      #7                  // Field clientId:Ljava/lang/String;
      26: aload_2
      27: getfield      #7                  // Field clientId:Ljava/lang/String;
      30: invokestatic  #113                // Method java/util/Objects.equals:(Ljava/lang/Object;Ljava/lang/Object;)Z
      33: ifeq          110
      36: aload_0
      37: getfield      #6                  // Field clientSecret:Ljava/lang/String;
      40: aload_2
      41: getfield      #6                  // Field clientSecret:Ljava/lang/String;
      44: invokestatic  #113                // Method java/util/Objects.equals:(Ljava/lang/Object;Ljava/lang/Object;)Z
      47: ifeq          110
      50: aload_0
      51: getfield      #5                  // Field refreshToken:Ljava/lang/String;
      54: aload_2
      55: getfield      #5                  // Field refreshToken:Ljava/lang/String;
      58: invokestatic  #113                // Method java/util/Objects.equals:(Ljava/lang/Object;Ljava/lang/Object;)Z
      61: ifeq          110
      64: aload_0
      65: getfield      #3                  // Field tokenServerUri:Ljava/net/URI;
      68: aload_2
      69: getfield      #3                  // Field tokenServerUri:Ljava/net/URI;
      72: invokestatic  #113                // Method java/util/Objects.equals:(Ljava/lang/Object;Ljava/lang/Object;)Z
      75: ifeq          110
      78: aload_0
      79: getfield      #18                 // Field transportFactoryClassName:Ljava/lang/String;
      82: aload_2
      83: getfield      #18                 // Field transportFactoryClassName:Ljava/lang/String;
      86: invokestatic  #113                // Method java/util/Objects.equals:(Ljava/lang/Object;Ljava/lang/Object;)Z
      89: ifeq          110
      92: aload_0
      93: getfield      #2                  // Field quotaProjectId:Ljava/lang/String;
      96: aload_2
      97: getfield      #2                  // Field quotaProjectId:Ljava/lang/String;
     100: invokestatic  #113                // Method java/util/Objects.equals:(Ljava/lang/Object;Ljava/lang/Object;)Z
     103: ifeq          110
     106: iconst_1
     107: goto          111
     110: iconst_0
     111: ireturn

  private void readObject(java.io.ObjectInputStream) throws java.io.IOException, java.lang.ClassNotFoundException;
    Code:
       0: aload_1
       1: invokevirtual #114                // Method java/io/ObjectInputStream.defaultReadObject:()V
       4: aload_0
       5: aload_0
       6: getfield      #18                 // Field transportFactoryClassName:Ljava/lang/String;
       9: invokestatic  #115                // Method newInstance:(Ljava/lang/String;)Ljava/lang/Object;
      12: checkcast     #11                 // class com/google/auth/http/HttpTransportFactory
      15: putfield      #4                  // Field transportFactory:Lcom/google/auth/http/HttpTransportFactory;
      18: return

  public static com.google.auth.oauth2.UserCredentials$Builder newBuilder();
    Code:
       0: new           #116                // class com/google/auth/oauth2/UserCredentials$Builder
       3: dup
       4: invokespecial #117                // Method com/google/auth/oauth2/UserCredentials$Builder."<init>":()V
       7: areturn

  public com.google.auth.oauth2.UserCredentials$Builder toBuilder();
    Code:
       0: new           #116                // class com/google/auth/oauth2/UserCredentials$Builder
       3: dup
       4: aload_0
       5: invokespecial #118                // Method com/google/auth/oauth2/UserCredentials$Builder."<init>":(Lcom/google/auth/oauth2/UserCredentials;)V
       8: areturn

  public java.lang.String getQuotaProjectId();
    Code:
       0: aload_0
       1: getfield      #2                  // Field quotaProjectId:Ljava/lang/String;
       4: areturn

  public com.google.auth.oauth2.GoogleCredentials$Builder toBuilder();
    Code:
       0: aload_0
       1: invokevirtual #119                // Method toBuilder:()Lcom/google/auth/oauth2/UserCredentials$Builder;
       4: areturn

  public com.google.auth.oauth2.OAuth2Credentials$Builder toBuilder();
    Code:
       0: aload_0
       1: invokevirtual #119                // Method toBuilder:()Lcom/google/auth/oauth2/UserCredentials$Builder;
       4: areturn

  static java.lang.String access$000(com.google.auth.oauth2.UserCredentials);
    Code:
       0: aload_0
       1: getfield      #7                  // Field clientId:Ljava/lang/String;
       4: areturn

  static java.lang.String access$100(com.google.auth.oauth2.UserCredentials);
    Code:
       0: aload_0
       1: getfield      #6                  // Field clientSecret:Ljava/lang/String;
       4: areturn

  static java.lang.String access$200(com.google.auth.oauth2.UserCredentials);
    Code:
       0: aload_0
       1: getfield      #5                  // Field refreshToken:Ljava/lang/String;
       4: areturn

  static com.google.auth.http.HttpTransportFactory access$300(com.google.auth.oauth2.UserCredentials);
    Code:
       0: aload_0
       1: getfield      #4                  // Field transportFactory:Lcom/google/auth/http/HttpTransportFactory;
       4: areturn

  static java.net.URI access$400(com.google.auth.oauth2.UserCredentials);
    Code:
       0: aload_0
       1: getfield      #3                  // Field tokenServerUri:Ljava/net/URI;
       4: areturn

  static java.lang.String access$500(com.google.auth.oauth2.UserCredentials);
    Code:
       0: aload_0
       1: getfield      #2                  // Field quotaProjectId:Ljava/lang/String;
       4: areturn

  com.google.auth.oauth2.UserCredentials(java.lang.String, java.lang.String, java.lang.String, com.google.auth.oauth2.AccessToken, com.google.auth.http.HttpTransportFactory, java.net.URI, java.lang.String, com.google.auth.oauth2.UserCredentials$1);
    Code:
       0: aload_0
       1: aload_1
       2: aload_2
       3: aload_3
       4: aload         4
       6: aload         5
       8: aload         6
      10: aload         7
      12: invokespecial #1                  // Method "<init>":(Ljava/lang/String;Ljava/lang/String;Ljava/lang/String;Lcom/google/auth/oauth2/AccessToken;Lcom/google/auth/http/HttpTransportFactory;Ljava/net/URI;Ljava/lang/String;)V
      15: return
}
