Compiled from "RelationRole.java"
public final class com.cloudera.nav.sdk.model.relations.RelationRole extends java.lang.Enum<com.cloudera.nav.sdk.model.relations.RelationRole> {
  public static final com.cloudera.nav.sdk.model.relations.RelationRole SOURCE;

  public static final com.cloudera.nav.sdk.model.relations.RelationRole TARGET;

  public static final com.cloudera.nav.sdk.model.relations.RelationRole PARENT;

  public static final com.cloudera.nav.sdk.model.relations.RelationRole CHILD;

  public static final com.cloudera.nav.sdk.model.relations.RelationRole LOGICAL;

  public static final com.cloudera.nav.sdk.model.relations.RelationRole PHYSICAL;

  public static final com.cloudera.nav.sdk.model.relations.RelationRole TEMPLATE;

  public static final com.cloudera.nav.sdk.model.relations.RelationRole INSTANCE;

  public static final com.cloudera.nav.sdk.model.relations.RelationRole ENDPOINT1;

  public static final com.cloudera.nav.sdk.model.relations.RelationRole ENDPOINT2;

  private final com.cloudera.nav.sdk.model.relations.RelationRole$EndPoint endPoint;

  private static final com.cloudera.nav.sdk.model.relations.RelationRole[] $VALUES;

  public static com.cloudera.nav.sdk.model.relations.RelationRole[] values();
    Code:
       0: getstatic     #1                  // Field $VALUES:[Lcom/cloudera/nav/sdk/model/relations/RelationRole;
       3: invokevirtual #2                  // Method "[Lcom/cloudera/nav/sdk/model/relations/RelationRole;".clone:()Ljava/lang/Object;
       6: checkcast     #3                  // class "[Lcom/cloudera/nav/sdk/model/relations/RelationRole;"
       9: areturn

  public static com.cloudera.nav.sdk.model.relations.RelationRole valueOf(java.lang.String);
    Code:
       0: ldc_w         #4                  // class com/cloudera/nav/sdk/model/relations/RelationRole
       3: aload_0
       4: invokestatic  #5                  // Method java/lang/Enum.valueOf:(Ljava/lang/Class;Ljava/lang/String;)Ljava/lang/Enum;
       7: checkcast     #4                  // class com/cloudera/nav/sdk/model/relations/RelationRole
      10: areturn

  private com.cloudera.nav.sdk.model.relations.RelationRole(com.cloudera.nav.sdk.model.relations.RelationRole$EndPoint);
    Code:
       0: aload_0
       1: aload_1
       2: iload_2
       3: invokespecial #6                  // Method java/lang/Enum."<init>":(Ljava/lang/String;I)V
       6: aload_0
       7: aload_3
       8: putfield      #7                  // Field endPoint:Lcom/cloudera/nav/sdk/model/relations/RelationRole$EndPoint;
      11: return

  public com.cloudera.nav.sdk.model.relations.RelationRole$EndPoint getEndPoint();
    Code:
       0: aload_0
       1: getfield      #7                  // Field endPoint:Lcom/cloudera/nav/sdk/model/relations/RelationRole$EndPoint;
       4: areturn

  public com.cloudera.nav.sdk.model.relations.RelationRole getInverseRole();
    Code:
       0: getstatic     #8                  // Field com/cloudera/nav/sdk/model/relations/RelationRole$1.$SwitchMap$com$cloudera$nav$sdk$model$relations$RelationRole:[I
       3: aload_0
       4: invokevirtual #9                  // Method ordinal:()I
       7: iaload
       8: tableswitch   { // 1 to 10
                     1: 64
                     2: 68
                     3: 72
                     4: 76
                     5: 80
                     6: 84
                     7: 88
                     8: 92
                     9: 96
                    10: 100
               default: 104
          }
      64: getstatic     #10                 // Field TARGET:Lcom/cloudera/nav/sdk/model/relations/RelationRole;
      67: areturn
      68: getstatic     #11                 // Field SOURCE:Lcom/cloudera/nav/sdk/model/relations/RelationRole;
      71: areturn
      72: getstatic     #12                 // Field CHILD:Lcom/cloudera/nav/sdk/model/relations/RelationRole;
      75: areturn
      76: getstatic     #13                 // Field PARENT:Lcom/cloudera/nav/sdk/model/relations/RelationRole;
      79: areturn
      80: getstatic     #14                 // Field LOGICAL:Lcom/cloudera/nav/sdk/model/relations/RelationRole;
      83: areturn
      84: getstatic     #15                 // Field PHYSICAL:Lcom/cloudera/nav/sdk/model/relations/RelationRole;
      87: areturn
      88: getstatic     #16                 // Field INSTANCE:Lcom/cloudera/nav/sdk/model/relations/RelationRole;
      91: areturn
      92: getstatic     #17                 // Field TEMPLATE:Lcom/cloudera/nav/sdk/model/relations/RelationRole;
      95: areturn
      96: getstatic     #18                 // Field ENDPOINT2:Lcom/cloudera/nav/sdk/model/relations/RelationRole;
      99: areturn
     100: getstatic     #19                 // Field ENDPOINT1:Lcom/cloudera/nav/sdk/model/relations/RelationRole;
     103: areturn
     104: new           #20                 // class java/lang/IllegalArgumentException
     107: dup
     108: new           #21                 // class java/lang/StringBuilder
     111: dup
     112: invokespecial #22                 // Method java/lang/StringBuilder."<init>":()V
     115: ldc           #23                 // String Unknown role
     117: invokevirtual #24                 // Method java/lang/StringBuilder.append:(Ljava/lang/String;)Ljava/lang/StringBuilder;
     120: aload_0
     121: invokestatic  #25                 // Method java/lang/String.valueOf:(Ljava/lang/Object;)Ljava/lang/String;
     124: invokevirtual #24                 // Method java/lang/StringBuilder.append:(Ljava/lang/String;)Ljava/lang/StringBuilder;
     127: invokevirtual #26                 // Method java/lang/StringBuilder.toString:()Ljava/lang/String;
     130: invokespecial #27                 // Method java/lang/IllegalArgumentException."<init>":(Ljava/lang/String;)V
     133: athrow

  static {};
    Code:
       0: new           #4                  // class com/cloudera/nav/sdk/model/relations/RelationRole
       3: dup
       4: ldc           #28                 // String SOURCE
       6: iconst_0
       7: getstatic     #29                 // Field com/cloudera/nav/sdk/model/relations/RelationRole$EndPoint.ENDPOINT1:Lcom/cloudera/nav/sdk/model/relations/RelationRole$EndPoint;
      10: invokespecial #30                 // Method "<init>":(Ljava/lang/String;ILcom/cloudera/nav/sdk/model/relations/RelationRole$EndPoint;)V
      13: putstatic     #11                 // Field SOURCE:Lcom/cloudera/nav/sdk/model/relations/RelationRole;
      16: new           #4                  // class com/cloudera/nav/sdk/model/relations/RelationRole
      19: dup
      20: ldc           #31                 // String TARGET
      22: iconst_1
      23: getstatic     #32                 // Field com/cloudera/nav/sdk/model/relations/RelationRole$EndPoint.ENDPOINT2:Lcom/cloudera/nav/sdk/model/relations/RelationRole$EndPoint;
      26: invokespecial #30                 // Method "<init>":(Ljava/lang/String;ILcom/cloudera/nav/sdk/model/relations/RelationRole$EndPoint;)V
      29: putstatic     #10                 // Field TARGET:Lcom/cloudera/nav/sdk/model/relations/RelationRole;
      32: new           #4                  // class com/cloudera/nav/sdk/model/relations/RelationRole
      35: dup
      36: ldc           #33                 // String PARENT
      38: iconst_2
      39: getstatic     #29                 // Field com/cloudera/nav/sdk/model/relations/RelationRole$EndPoint.ENDPOINT1:Lcom/cloudera/nav/sdk/model/relations/RelationRole$EndPoint;
      42: invokespecial #30                 // Method "<init>":(Ljava/lang/String;ILcom/cloudera/nav/sdk/model/relations/RelationRole$EndPoint;)V
      45: putstatic     #13                 // Field PARENT:Lcom/cloudera/nav/sdk/model/relations/RelationRole;
      48: new           #4                  // class com/cloudera/nav/sdk/model/relations/RelationRole
      51: dup
      52: ldc           #34                 // String CHILD
      54: iconst_3
      55: getstatic     #32                 // Field com/cloudera/nav/sdk/model/relations/RelationRole$EndPoint.ENDPOINT2:Lcom/cloudera/nav/sdk/model/relations/RelationRole$EndPoint;
      58: invokespecial #30                 // Method "<init>":(Ljava/lang/String;ILcom/cloudera/nav/sdk/model/relations/RelationRole$EndPoint;)V
      61: putstatic     #12                 // Field CHILD:Lcom/cloudera/nav/sdk/model/relations/RelationRole;
      64: new           #4                  // class com/cloudera/nav/sdk/model/relations/RelationRole
      67: dup
      68: ldc           #35                 // String LOGICAL
      70: iconst_4
      71: getstatic     #29                 // Field com/cloudera/nav/sdk/model/relations/RelationRole$EndPoint.ENDPOINT1:Lcom/cloudera/nav/sdk/model/relations/RelationRole$EndPoint;
      74: invokespecial #30                 // Method "<init>":(Ljava/lang/String;ILcom/cloudera/nav/sdk/model/relations/RelationRole$EndPoint;)V
      77: putstatic     #14                 // Field LOGICAL:Lcom/cloudera/nav/sdk/model/relations/RelationRole;
      80: new           #4                  // class com/cloudera/nav/sdk/model/relations/RelationRole
      83: dup
      84: ldc           #36                 // String PHYSICAL
      86: iconst_5
      87: getstatic     #32                 // Field com/cloudera/nav/sdk/model/relations/RelationRole$EndPoint.ENDPOINT2:Lcom/cloudera/nav/sdk/model/relations/RelationRole$EndPoint;
      90: invokespecial #30                 // Method "<init>":(Ljava/lang/String;ILcom/cloudera/nav/sdk/model/relations/RelationRole$EndPoint;)V
      93: putstatic     #15                 // Field PHYSICAL:Lcom/cloudera/nav/sdk/model/relations/RelationRole;
      96: new           #4                  // class com/cloudera/nav/sdk/model/relations/RelationRole
      99: dup
     100: ldc           #37                 // String TEMPLATE
     102: bipush        6
     104: getstatic     #29                 // Field com/cloudera/nav/sdk/model/relations/RelationRole$EndPoint.ENDPOINT1:Lcom/cloudera/nav/sdk/model/relations/RelationRole$EndPoint;
     107: invokespecial #30                 // Method "<init>":(Ljava/lang/String;ILcom/cloudera/nav/sdk/model/relations/RelationRole$EndPoint;)V
     110: putstatic     #17                 // Field TEMPLATE:Lcom/cloudera/nav/sdk/model/relations/RelationRole;
     113: new           #4                  // class com/cloudera/nav/sdk/model/relations/RelationRole
     116: dup
     117: ldc           #38                 // String INSTANCE
     119: bipush        7
     121: getstatic     #32                 // Field com/cloudera/nav/sdk/model/relations/RelationRole$EndPoint.ENDPOINT2:Lcom/cloudera/nav/sdk/model/relations/RelationRole$EndPoint;
     124: invokespecial #30                 // Method "<init>":(Ljava/lang/String;ILcom/cloudera/nav/sdk/model/relations/RelationRole$EndPoint;)V
     127: putstatic     #16                 // Field INSTANCE:Lcom/cloudera/nav/sdk/model/relations/RelationRole;
     130: new           #4                  // class com/cloudera/nav/sdk/model/relations/RelationRole
     133: dup
     134: ldc           #39                 // String ENDPOINT1
     136: bipush        8
     138: getstatic     #29                 // Field com/cloudera/nav/sdk/model/relations/RelationRole$EndPoint.ENDPOINT1:Lcom/cloudera/nav/sdk/model/relations/RelationRole$EndPoint;
     141: invokespecial #30                 // Method "<init>":(Ljava/lang/String;ILcom/cloudera/nav/sdk/model/relations/RelationRole$EndPoint;)V
     144: putstatic     #19                 // Field ENDPOINT1:Lcom/cloudera/nav/sdk/model/relations/RelationRole;
     147: new           #4                  // class com/cloudera/nav/sdk/model/relations/RelationRole
     150: dup
     151: ldc           #40                 // String ENDPOINT2
     153: bipush        9
     155: getstatic     #32                 // Field com/cloudera/nav/sdk/model/relations/RelationRole$EndPoint.ENDPOINT2:Lcom/cloudera/nav/sdk/model/relations/RelationRole$EndPoint;
     158: invokespecial #30                 // Method "<init>":(Ljava/lang/String;ILcom/cloudera/nav/sdk/model/relations/RelationRole$EndPoint;)V
     161: putstatic     #18                 // Field ENDPOINT2:Lcom/cloudera/nav/sdk/model/relations/RelationRole;
     164: bipush        10
     166: anewarray     #4                  // class com/cloudera/nav/sdk/model/relations/RelationRole
     169: dup
     170: iconst_0
     171: getstatic     #11                 // Field SOURCE:Lcom/cloudera/nav/sdk/model/relations/RelationRole;
     174: aastore
     175: dup
     176: iconst_1
     177: getstatic     #10                 // Field TARGET:Lcom/cloudera/nav/sdk/model/relations/RelationRole;
     180: aastore
     181: dup
     182: iconst_2
     183: getstatic     #13                 // Field PARENT:Lcom/cloudera/nav/sdk/model/relations/RelationRole;
     186: aastore
     187: dup
     188: iconst_3
     189: getstatic     #12                 // Field CHILD:Lcom/cloudera/nav/sdk/model/relations/RelationRole;
     192: aastore
     193: dup
     194: iconst_4
     195: getstatic     #14                 // Field LOGICAL:Lcom/cloudera/nav/sdk/model/relations/RelationRole;
     198: aastore
     199: dup
     200: iconst_5
     201: getstatic     #15                 // Field PHYSICAL:Lcom/cloudera/nav/sdk/model/relations/RelationRole;
     204: aastore
     205: dup
     206: bipush        6
     208: getstatic     #17                 // Field TEMPLATE:Lcom/cloudera/nav/sdk/model/relations/RelationRole;
     211: aastore
     212: dup
     213: bipush        7
     215: getstatic     #16                 // Field INSTANCE:Lcom/cloudera/nav/sdk/model/relations/RelationRole;
     218: aastore
     219: dup
     220: bipush        8
     222: getstatic     #19                 // Field ENDPOINT1:Lcom/cloudera/nav/sdk/model/relations/RelationRole;
     225: aastore
     226: dup
     227: bipush        9
     229: getstatic     #18                 // Field ENDPOINT2:Lcom/cloudera/nav/sdk/model/relations/RelationRole;
     232: aastore
     233: putstatic     #1                  // Field $VALUES:[Lcom/cloudera/nav/sdk/model/relations/RelationRole;
     236: return
}
