Compiled from "Relation.java"
public abstract class com.cloudera.nav.sdk.model.relations.Relation$Builder<T extends com.cloudera.nav.sdk.model.relations.Relation$Builder<T>> {
  private final com.cloudera.nav.sdk.model.relations.RelationType type;

  private java.lang.String namespace;

  private java.lang.String identity;

  private java.util.Collection<java.lang.String> ep1Ids;

  private com.cloudera.nav.sdk.model.entities.EntityType ep1Type;

  private com.cloudera.nav.sdk.model.SourceType ep1SourceType;

  private java.lang.String ep1SourceId;

  private java.util.Collection<java.lang.String> ep2Ids;

  private com.cloudera.nav.sdk.model.entities.EntityType ep2Type;

  private com.cloudera.nav.sdk.model.SourceType ep2SourceType;

  private java.lang.String ep2SourceId;

  private boolean userSpecified;

  private com.cloudera.nav.sdk.model.relations.RelationIdGenerator idGenerator;

  protected com.cloudera.nav.sdk.model.relations.Relation$Builder(com.cloudera.nav.sdk.model.relations.RelationType);
    Code:
       0: aload_0
       1: invokespecial #14                 // Method java/lang/Object."<init>":()V
       4: aload_0
       5: aload_1
       6: putfield      #7                  // Field type:Lcom/cloudera/nav/sdk/model/relations/RelationType;
       9: return

  protected abstract T self();

  public T namespace(java.lang.String);
    Code:
       0: aload_0
       1: aload_1
       2: putfield      #6                  // Field namespace:Ljava/lang/String;
       5: aload_0
       6: invokevirtual #15                 // Method self:()Lcom/cloudera/nav/sdk/model/relations/Relation$Builder;
       9: areturn

  public T identity(java.lang.String);
    Code:
       0: aload_0
       1: aload_1
       2: putfield      #13                 // Field identity:Ljava/lang/String;
       5: aload_0
       6: invokevirtual #15                 // Method self:()Lcom/cloudera/nav/sdk/model/relations/Relation$Builder;
       9: areturn

  public T idGenerator(com.cloudera.nav.sdk.model.relations.RelationIdGenerator);
    Code:
       0: aload_0
       1: aload_1
       2: putfield      #12                 // Field idGenerator:Lcom/cloudera/nav/sdk/model/relations/RelationIdGenerator;
       5: aload_0
       6: invokevirtual #15                 // Method self:()Lcom/cloudera/nav/sdk/model/relations/Relation$Builder;
       9: areturn

  public T ep1Ids(java.util.Collection<java.lang.String>);
    Code:
       0: aload_0
       1: aload_1
       2: putfield      #11                 // Field ep1Ids:Ljava/util/Collection;
       5: aload_0
       6: invokevirtual #15                 // Method self:()Lcom/cloudera/nav/sdk/model/relations/Relation$Builder;
       9: areturn

  public T ep1Type(com.cloudera.nav.sdk.model.entities.EntityType);
    Code:
       0: aload_0
       1: aload_1
       2: putfield      #5                  // Field ep1Type:Lcom/cloudera/nav/sdk/model/entities/EntityType;
       5: aload_0
       6: invokevirtual #15                 // Method self:()Lcom/cloudera/nav/sdk/model/relations/Relation$Builder;
       9: areturn

  public T ep2Ids(java.util.Collection<java.lang.String>);
    Code:
       0: aload_0
       1: aload_1
       2: putfield      #9                  // Field ep2Ids:Ljava/util/Collection;
       5: aload_0
       6: invokevirtual #15                 // Method self:()Lcom/cloudera/nav/sdk/model/relations/Relation$Builder;
       9: areturn

  public T ep2Type(com.cloudera.nav.sdk.model.entities.EntityType);
    Code:
       0: aload_0
       1: aload_1
       2: putfield      #3                  // Field ep2Type:Lcom/cloudera/nav/sdk/model/entities/EntityType;
       5: aload_0
       6: invokevirtual #15                 // Method self:()Lcom/cloudera/nav/sdk/model/relations/Relation$Builder;
       9: areturn

  public T ep1SourceType(com.cloudera.nav.sdk.model.SourceType);
    Code:
       0: aload_0
       1: aload_1
       2: putfield      #10                 // Field ep1SourceType:Lcom/cloudera/nav/sdk/model/SourceType;
       5: aload_0
       6: invokevirtual #15                 // Method self:()Lcom/cloudera/nav/sdk/model/relations/Relation$Builder;
       9: areturn

  public T ep1SourceId(java.lang.String);
    Code:
       0: aload_0
       1: aload_1
       2: putfield      #4                  // Field ep1SourceId:Ljava/lang/String;
       5: aload_0
       6: invokevirtual #15                 // Method self:()Lcom/cloudera/nav/sdk/model/relations/Relation$Builder;
       9: areturn

  public T ep2SourceType(com.cloudera.nav.sdk.model.SourceType);
    Code:
       0: aload_0
       1: aload_1
       2: putfield      #8                  // Field ep2SourceType:Lcom/cloudera/nav/sdk/model/SourceType;
       5: aload_0
       6: invokevirtual #15                 // Method self:()Lcom/cloudera/nav/sdk/model/relations/Relation$Builder;
       9: areturn

  public T ep2SourceId(java.lang.String);
    Code:
       0: aload_0
       1: aload_1
       2: putfield      #2                  // Field ep2SourceId:Ljava/lang/String;
       5: aload_0
       6: invokevirtual #15                 // Method self:()Lcom/cloudera/nav/sdk/model/relations/Relation$Builder;
       9: areturn

  public T userSpecified(boolean);
    Code:
       0: aload_0
       1: iload_1
       2: putfield      #1                  // Field userSpecified:Z
       5: aload_0
       6: invokevirtual #15                 // Method self:()Lcom/cloudera/nav/sdk/model/relations/Relation$Builder;
       9: areturn

  public T ep1(java.util.Collection<com.cloudera.nav.sdk.model.entities.Entity>);
    Code:
       0: aload_0
       1: aload_1
       2: invokespecial #16                 // Method prepEndpoint:(Ljava/util/Collection;)Ljava/util/Collection;
       5: astore_2
       6: aload_1
       7: aconst_null
       8: invokestatic  #17                 // Method com/google/common/collect/Iterables.getFirst:(Ljava/lang/Iterable;Ljava/lang/Object;)Ljava/lang/Object;
      11: checkcast     #18                 // class com/cloudera/nav/sdk/model/entities/Entity
      14: astore_3
      15: aload_3
      16: invokestatic  #19                 // Method com/google/common/base/Preconditions.checkNotNull:(Ljava/lang/Object;)Ljava/lang/Object;
      19: pop
      20: aload_0
      21: aload_2
      22: invokevirtual #20                 // Method ep1Ids:(Ljava/util/Collection;)Lcom/cloudera/nav/sdk/model/relations/Relation$Builder;
      25: aload_3
      26: invokevirtual #21                 // Method com/cloudera/nav/sdk/model/entities/Entity.getSourceType:()Lcom/cloudera/nav/sdk/model/SourceType;
      29: invokevirtual #22                 // Method ep1SourceType:(Lcom/cloudera/nav/sdk/model/SourceType;)Lcom/cloudera/nav/sdk/model/relations/Relation$Builder;
      32: aload_3
      33: invokevirtual #23                 // Method com/cloudera/nav/sdk/model/entities/Entity.getEntityType:()Lcom/cloudera/nav/sdk/model/entities/EntityType;
      36: invokevirtual #24                 // Method ep1Type:(Lcom/cloudera/nav/sdk/model/entities/EntityType;)Lcom/cloudera/nav/sdk/model/relations/Relation$Builder;
      39: aload_3
      40: invokevirtual #25                 // Method com/cloudera/nav/sdk/model/entities/Entity.getSourceId:()Ljava/lang/String;
      43: invokevirtual #26                 // Method ep1SourceId:(Ljava/lang/String;)Lcom/cloudera/nav/sdk/model/relations/Relation$Builder;
      46: areturn

  public T ep2(java.util.Collection<com.cloudera.nav.sdk.model.entities.Entity>);
    Code:
       0: aload_0
       1: aload_1
       2: invokespecial #16                 // Method prepEndpoint:(Ljava/util/Collection;)Ljava/util/Collection;
       5: astore_2
       6: aload_1
       7: aconst_null
       8: invokestatic  #17                 // Method com/google/common/collect/Iterables.getFirst:(Ljava/lang/Iterable;Ljava/lang/Object;)Ljava/lang/Object;
      11: checkcast     #18                 // class com/cloudera/nav/sdk/model/entities/Entity
      14: astore_3
      15: aload_3
      16: invokestatic  #19                 // Method com/google/common/base/Preconditions.checkNotNull:(Ljava/lang/Object;)Ljava/lang/Object;
      19: pop
      20: aload_0
      21: aload_2
      22: invokevirtual #27                 // Method ep2Ids:(Ljava/util/Collection;)Lcom/cloudera/nav/sdk/model/relations/Relation$Builder;
      25: aload_3
      26: invokevirtual #21                 // Method com/cloudera/nav/sdk/model/entities/Entity.getSourceType:()Lcom/cloudera/nav/sdk/model/SourceType;
      29: invokevirtual #28                 // Method ep2SourceType:(Lcom/cloudera/nav/sdk/model/SourceType;)Lcom/cloudera/nav/sdk/model/relations/Relation$Builder;
      32: aload_3
      33: invokevirtual #23                 // Method com/cloudera/nav/sdk/model/entities/Entity.getEntityType:()Lcom/cloudera/nav/sdk/model/entities/EntityType;
      36: invokevirtual #29                 // Method ep2Type:(Lcom/cloudera/nav/sdk/model/entities/EntityType;)Lcom/cloudera/nav/sdk/model/relations/Relation$Builder;
      39: aload_3
      40: invokevirtual #25                 // Method com/cloudera/nav/sdk/model/entities/Entity.getSourceId:()Ljava/lang/String;
      43: invokevirtual #30                 // Method ep2SourceId:(Ljava/lang/String;)Lcom/cloudera/nav/sdk/model/relations/Relation$Builder;
      46: areturn

  private java.util.Collection<java.lang.String> prepEndpoint(java.util.Collection<com.cloudera.nav.sdk.model.entities.Entity>);
    Code:
       0: aload_1
       1: invokestatic  #31                 // Method org/apache/commons/collections/CollectionUtils.isEmpty:(Ljava/util/Collection;)Z
       4: ifne          11
       7: iconst_1
       8: goto          12
      11: iconst_0
      12: invokestatic  #32                 // Method com/google/common/base/Preconditions.checkArgument:(Z)V
      15: invokestatic  #33                 // Method com/google/common/collect/Lists.newArrayList:()Ljava/util/ArrayList;
      18: astore_2
      19: aconst_null
      20: astore_3
      21: aload_1
      22: invokeinterface #34,  1           // InterfaceMethod java/util/Collection.iterator:()Ljava/util/Iterator;
      27: astore        4
      29: aload         4
      31: invokeinterface #35,  1           // InterfaceMethod java/util/Iterator.hasNext:()Z
      36: ifeq          123
      39: aload         4
      41: invokeinterface #36,  1           // InterfaceMethod java/util/Iterator.next:()Ljava/lang/Object;
      46: checkcast     #18                 // class com/cloudera/nav/sdk/model/entities/Entity
      49: astore        5
      51: aload_2
      52: aload         5
      54: invokevirtual #37                 // Method com/cloudera/nav/sdk/model/entities/Entity.getIdentity:()Ljava/lang/String;
      57: invokeinterface #38,  2           // InterfaceMethod java/util/Collection.add:(Ljava/lang/Object;)Z
      62: pop
      63: aload_3
      64: ifnonnull     73
      67: aload         5
      69: astore_3
      70: goto          120
      73: aload_3
      74: invokevirtual #25                 // Method com/cloudera/nav/sdk/model/entities/Entity.getSourceId:()Ljava/lang/String;
      77: aload         5
      79: invokevirtual #25                 // Method com/cloudera/nav/sdk/model/entities/Entity.getSourceId:()Ljava/lang/String;
      82: invokestatic  #39                 // Method org/apache/commons/lang/StringUtils.equals:(Ljava/lang/String;Ljava/lang/String;)Z
      85: ifeq          116
      88: aload_3
      89: invokevirtual #21                 // Method com/cloudera/nav/sdk/model/entities/Entity.getSourceType:()Lcom/cloudera/nav/sdk/model/SourceType;
      92: aload         5
      94: invokevirtual #21                 // Method com/cloudera/nav/sdk/model/entities/Entity.getSourceType:()Lcom/cloudera/nav/sdk/model/SourceType;
      97: if_acmpne     116
     100: aload_3
     101: invokevirtual #23                 // Method com/cloudera/nav/sdk/model/entities/Entity.getEntityType:()Lcom/cloudera/nav/sdk/model/entities/EntityType;
     104: aload         5
     106: invokevirtual #23                 // Method com/cloudera/nav/sdk/model/entities/Entity.getEntityType:()Lcom/cloudera/nav/sdk/model/entities/EntityType;
     109: if_acmpne     116
     112: iconst_1
     113: goto          117
     116: iconst_0
     117: invokestatic  #32                 // Method com/google/common/base/Preconditions.checkArgument:(Z)V
     120: goto          29
     123: aload_2
     124: areturn

  public abstract com.cloudera.nav.sdk.model.relations.Relation build();

  static java.lang.String access$000(com.cloudera.nav.sdk.model.relations.Relation$Builder);
    Code:
       0: aload_0
       1: getfield      #13                 // Field identity:Ljava/lang/String;
       4: areturn

  static com.cloudera.nav.sdk.model.relations.RelationIdGenerator access$100(com.cloudera.nav.sdk.model.relations.Relation$Builder);
    Code:
       0: aload_0
       1: getfield      #12                 // Field idGenerator:Lcom/cloudera/nav/sdk/model/relations/RelationIdGenerator;
       4: areturn

  static java.util.Collection access$200(com.cloudera.nav.sdk.model.relations.Relation$Builder);
    Code:
       0: aload_0
       1: getfield      #11                 // Field ep1Ids:Ljava/util/Collection;
       4: areturn

  static com.cloudera.nav.sdk.model.SourceType access$300(com.cloudera.nav.sdk.model.relations.Relation$Builder);
    Code:
       0: aload_0
       1: getfield      #10                 // Field ep1SourceType:Lcom/cloudera/nav/sdk/model/SourceType;
       4: areturn

  static java.util.Collection access$400(com.cloudera.nav.sdk.model.relations.Relation$Builder);
    Code:
       0: aload_0
       1: getfield      #9                  // Field ep2Ids:Ljava/util/Collection;
       4: areturn

  static com.cloudera.nav.sdk.model.SourceType access$500(com.cloudera.nav.sdk.model.relations.Relation$Builder);
    Code:
       0: aload_0
       1: getfield      #8                  // Field ep2SourceType:Lcom/cloudera/nav/sdk/model/SourceType;
       4: areturn

  static com.cloudera.nav.sdk.model.relations.RelationType access$600(com.cloudera.nav.sdk.model.relations.Relation$Builder);
    Code:
       0: aload_0
       1: getfield      #7                  // Field type:Lcom/cloudera/nav/sdk/model/relations/RelationType;
       4: areturn

  static java.lang.String access$700(com.cloudera.nav.sdk.model.relations.Relation$Builder);
    Code:
       0: aload_0
       1: getfield      #6                  // Field namespace:Ljava/lang/String;
       4: areturn

  static com.cloudera.nav.sdk.model.entities.EntityType access$800(com.cloudera.nav.sdk.model.relations.Relation$Builder);
    Code:
       0: aload_0
       1: getfield      #5                  // Field ep1Type:Lcom/cloudera/nav/sdk/model/entities/EntityType;
       4: areturn

  static java.lang.String access$900(com.cloudera.nav.sdk.model.relations.Relation$Builder);
    Code:
       0: aload_0
       1: getfield      #4                  // Field ep1SourceId:Ljava/lang/String;
       4: areturn

  static com.cloudera.nav.sdk.model.entities.EntityType access$1000(com.cloudera.nav.sdk.model.relations.Relation$Builder);
    Code:
       0: aload_0
       1: getfield      #3                  // Field ep2Type:Lcom/cloudera/nav/sdk/model/entities/EntityType;
       4: areturn

  static java.lang.String access$1100(com.cloudera.nav.sdk.model.relations.Relation$Builder);
    Code:
       0: aload_0
       1: getfield      #2                  // Field ep2SourceId:Ljava/lang/String;
       4: areturn

  static boolean access$1200(com.cloudera.nav.sdk.model.relations.Relation$Builder);
    Code:
       0: aload_0
       1: getfield      #1                  // Field userSpecified:Z
       4: ireturn
}
