Compiled from "NamespaceContextCorrectingXMLStreamWriterWrapper.java"
class org.apache.axiom.util.stax.dialect.NamespaceContextCorrectingXMLStreamWriterWrapper extends org.apache.axiom.util.stax.AbstractXMLStreamWriter {
  private final javax.xml.stream.XMLStreamWriter parent;

  public org.apache.axiom.util.stax.dialect.NamespaceContextCorrectingXMLStreamWriterWrapper(javax.xml.stream.XMLStreamWriter);
    Code:
       0: aload_0
       1: invokespecial #1                  // Method org/apache/axiom/util/stax/AbstractXMLStreamWriter."<init>":()V
       4: aload_0
       5: aload_1
       6: putfield      #2                  // Field parent:Ljavax/xml/stream/XMLStreamWriter;
       9: return

  protected void doWriteAttribute(java.lang.String, java.lang.String, java.lang.String, java.lang.String) throws javax.xml.stream.XMLStreamException;
    Code:
       0: aload_0
       1: getfield      #2                  // Field parent:Ljavax/xml/stream/XMLStreamWriter;
       4: aload_1
       5: aload_2
       6: aload_3
       7: aload         4
       9: invokeinterface #3,  5            // InterfaceMethod javax/xml/stream/XMLStreamWriter.writeAttribute:(Ljava/lang/String;Ljava/lang/String;Ljava/lang/String;Ljava/lang/String;)V
      14: return

  protected void doWriteAttribute(java.lang.String, java.lang.String) throws javax.xml.stream.XMLStreamException;
    Code:
       0: aload_0
       1: getfield      #2                  // Field parent:Ljavax/xml/stream/XMLStreamWriter;
       4: aload_1
       5: aload_2
       6: invokeinterface #4,  3            // InterfaceMethod javax/xml/stream/XMLStreamWriter.writeAttribute:(Ljava/lang/String;Ljava/lang/String;)V
      11: return

  protected void doWriteCData(java.lang.String) throws javax.xml.stream.XMLStreamException;
    Code:
       0: aload_0
       1: getfield      #2                  // Field parent:Ljavax/xml/stream/XMLStreamWriter;
       4: aload_1
       5: invokeinterface #5,  2            // InterfaceMethod javax/xml/stream/XMLStreamWriter.writeCData:(Ljava/lang/String;)V
      10: return

  protected void doWriteCharacters(char[], int, int) throws javax.xml.stream.XMLStreamException;
    Code:
       0: aload_0
       1: getfield      #2                  // Field parent:Ljavax/xml/stream/XMLStreamWriter;
       4: aload_1
       5: iload_2
       6: iload_3
       7: invokeinterface #6,  4            // InterfaceMethod javax/xml/stream/XMLStreamWriter.writeCharacters:([CII)V
      12: return

  protected void doWriteCharacters(java.lang.String) throws javax.xml.stream.XMLStreamException;
    Code:
       0: aload_0
       1: getfield      #2                  // Field parent:Ljavax/xml/stream/XMLStreamWriter;
       4: aload_1
       5: invokeinterface #7,  2            // InterfaceMethod javax/xml/stream/XMLStreamWriter.writeCharacters:(Ljava/lang/String;)V
      10: return

  protected void doWriteComment(java.lang.String) throws javax.xml.stream.XMLStreamException;
    Code:
       0: aload_0
       1: getfield      #2                  // Field parent:Ljavax/xml/stream/XMLStreamWriter;
       4: aload_1
       5: invokeinterface #8,  2            // InterfaceMethod javax/xml/stream/XMLStreamWriter.writeComment:(Ljava/lang/String;)V
      10: return

  protected void doWriteDefaultNamespace(java.lang.String) throws javax.xml.stream.XMLStreamException;
    Code:
       0: aload_0
       1: getfield      #2                  // Field parent:Ljavax/xml/stream/XMLStreamWriter;
       4: aload_1
       5: invokeinterface #9,  2            // InterfaceMethod javax/xml/stream/XMLStreamWriter.writeDefaultNamespace:(Ljava/lang/String;)V
      10: return

  protected void doWriteDTD(java.lang.String) throws javax.xml.stream.XMLStreamException;
    Code:
       0: aload_0
       1: getfield      #2                  // Field parent:Ljavax/xml/stream/XMLStreamWriter;
       4: aload_1
       5: invokeinterface #10,  2           // InterfaceMethod javax/xml/stream/XMLStreamWriter.writeDTD:(Ljava/lang/String;)V
      10: return

  protected void doWriteEmptyElement(java.lang.String, java.lang.String, java.lang.String) throws javax.xml.stream.XMLStreamException;
    Code:
       0: aload_0
       1: getfield      #2                  // Field parent:Ljavax/xml/stream/XMLStreamWriter;
       4: aload_1
       5: aload_2
       6: aload_3
       7: invokeinterface #11,  4           // InterfaceMethod javax/xml/stream/XMLStreamWriter.writeEmptyElement:(Ljava/lang/String;Ljava/lang/String;Ljava/lang/String;)V
      12: return

  protected void doWriteEmptyElement(java.lang.String) throws javax.xml.stream.XMLStreamException;
    Code:
       0: aload_0
       1: getfield      #2                  // Field parent:Ljavax/xml/stream/XMLStreamWriter;
       4: aload_1
       5: invokeinterface #12,  2           // InterfaceMethod javax/xml/stream/XMLStreamWriter.writeEmptyElement:(Ljava/lang/String;)V
      10: return

  protected void doWriteEndDocument() throws javax.xml.stream.XMLStreamException;
    Code:
       0: aload_0
       1: getfield      #2                  // Field parent:Ljavax/xml/stream/XMLStreamWriter;
       4: invokeinterface #13,  1           // InterfaceMethod javax/xml/stream/XMLStreamWriter.writeEndDocument:()V
       9: return

  protected void doWriteEndElement() throws javax.xml.stream.XMLStreamException;
    Code:
       0: aload_0
       1: getfield      #2                  // Field parent:Ljavax/xml/stream/XMLStreamWriter;
       4: invokeinterface #14,  1           // InterfaceMethod javax/xml/stream/XMLStreamWriter.writeEndElement:()V
       9: return

  protected void doWriteEntityRef(java.lang.String) throws javax.xml.stream.XMLStreamException;
    Code:
       0: aload_0
       1: getfield      #2                  // Field parent:Ljavax/xml/stream/XMLStreamWriter;
       4: aload_1
       5: invokeinterface #15,  2           // InterfaceMethod javax/xml/stream/XMLStreamWriter.writeEntityRef:(Ljava/lang/String;)V
      10: return

  protected void doWriteNamespace(java.lang.String, java.lang.String) throws javax.xml.stream.XMLStreamException;
    Code:
       0: aload_0
       1: getfield      #2                  // Field parent:Ljavax/xml/stream/XMLStreamWriter;
       4: aload_1
       5: aload_2
       6: invokeinterface #16,  3           // InterfaceMethod javax/xml/stream/XMLStreamWriter.writeNamespace:(Ljava/lang/String;Ljava/lang/String;)V
      11: return

  protected void doWriteProcessingInstruction(java.lang.String, java.lang.String) throws javax.xml.stream.XMLStreamException;
    Code:
       0: aload_0
       1: getfield      #2                  // Field parent:Ljavax/xml/stream/XMLStreamWriter;
       4: aload_1
       5: aload_2
       6: invokeinterface #17,  3           // InterfaceMethod javax/xml/stream/XMLStreamWriter.writeProcessingInstruction:(Ljava/lang/String;Ljava/lang/String;)V
      11: return

  protected void doWriteProcessingInstruction(java.lang.String) throws javax.xml.stream.XMLStreamException;
    Code:
       0: aload_0
       1: getfield      #2                  // Field parent:Ljavax/xml/stream/XMLStreamWriter;
       4: aload_1
       5: invokeinterface #18,  2           // InterfaceMethod javax/xml/stream/XMLStreamWriter.writeProcessingInstruction:(Ljava/lang/String;)V
      10: return

  protected void doWriteStartDocument() throws javax.xml.stream.XMLStreamException;
    Code:
       0: aload_0
       1: getfield      #2                  // Field parent:Ljavax/xml/stream/XMLStreamWriter;
       4: invokeinterface #19,  1           // InterfaceMethod javax/xml/stream/XMLStreamWriter.writeStartDocument:()V
       9: return

  protected void doWriteStartDocument(java.lang.String, java.lang.String) throws javax.xml.stream.XMLStreamException;
    Code:
       0: aload_0
       1: getfield      #2                  // Field parent:Ljavax/xml/stream/XMLStreamWriter;
       4: aload_1
       5: aload_2
       6: invokeinterface #20,  3           // InterfaceMethod javax/xml/stream/XMLStreamWriter.writeStartDocument:(Ljava/lang/String;Ljava/lang/String;)V
      11: return

  protected void doWriteStartDocument(java.lang.String) throws javax.xml.stream.XMLStreamException;
    Code:
       0: aload_0
       1: getfield      #2                  // Field parent:Ljavax/xml/stream/XMLStreamWriter;
       4: aload_1
       5: invokeinterface #21,  2           // InterfaceMethod javax/xml/stream/XMLStreamWriter.writeStartDocument:(Ljava/lang/String;)V
      10: return

  protected void doWriteStartElement(java.lang.String, java.lang.String, java.lang.String) throws javax.xml.stream.XMLStreamException;
    Code:
       0: aload_0
       1: getfield      #2                  // Field parent:Ljavax/xml/stream/XMLStreamWriter;
       4: aload_1
       5: aload_2
       6: aload_3
       7: invokeinterface #22,  4           // InterfaceMethod javax/xml/stream/XMLStreamWriter.writeStartElement:(Ljava/lang/String;Ljava/lang/String;Ljava/lang/String;)V
      12: return

  protected void doWriteStartElement(java.lang.String) throws javax.xml.stream.XMLStreamException;
    Code:
       0: aload_0
       1: getfield      #2                  // Field parent:Ljavax/xml/stream/XMLStreamWriter;
       4: aload_1
       5: invokeinterface #23,  2           // InterfaceMethod javax/xml/stream/XMLStreamWriter.writeStartElement:(Ljava/lang/String;)V
      10: return

  public void close() throws javax.xml.stream.XMLStreamException;
    Code:
       0: aload_0
       1: getfield      #2                  // Field parent:Ljavax/xml/stream/XMLStreamWriter;
       4: invokeinterface #24,  1           // InterfaceMethod javax/xml/stream/XMLStreamWriter.close:()V
       9: return

  public void flush() throws javax.xml.stream.XMLStreamException;
    Code:
       0: aload_0
       1: getfield      #2                  // Field parent:Ljavax/xml/stream/XMLStreamWriter;
       4: invokeinterface #25,  1           // InterfaceMethod javax/xml/stream/XMLStreamWriter.flush:()V
       9: return

  public java.lang.Object getProperty(java.lang.String) throws java.lang.IllegalArgumentException;
    Code:
       0: aload_0
       1: getfield      #2                  // Field parent:Ljavax/xml/stream/XMLStreamWriter;
       4: aload_1
       5: invokeinterface #26,  2           // InterfaceMethod javax/xml/stream/XMLStreamWriter.getProperty:(Ljava/lang/String;)Ljava/lang/Object;
      10: areturn
}
