Compiled from "SJSXPNamespaceContextWrapper.java"
class org.apache.axiom.util.stax.dialect.SJSXPNamespaceContextWrapper implements javax.xml.namespace.NamespaceContext {
  private final javax.xml.namespace.NamespaceContext parent;

  public org.apache.axiom.util.stax.dialect.SJSXPNamespaceContextWrapper(javax.xml.namespace.NamespaceContext);
    Code:
       0: aload_0
       1: invokespecial #1                  // Method java/lang/Object."<init>":()V
       4: aload_0
       5: aload_1
       6: putfield      #2                  // Field parent:Ljavax/xml/namespace/NamespaceContext;
       9: return

  public java.lang.String getNamespaceURI(java.lang.String);
    Code:
       0: aload_0
       1: getfield      #2                  // Field parent:Ljavax/xml/namespace/NamespaceContext;
       4: aload_1
       5: invokeinterface #3,  2            // InterfaceMethod javax/xml/namespace/NamespaceContext.getNamespaceURI:(Ljava/lang/String;)Ljava/lang/String;
      10: astore_2
      11: aload_2
      12: ifnonnull     20
      15: ldc           #5                  // String
      17: goto          21
      20: aload_2
      21: areturn

  public java.lang.String getPrefix(java.lang.String);
    Code:
       0: aload_0
       1: getfield      #2                  // Field parent:Ljavax/xml/namespace/NamespaceContext;
       4: aload_1
       5: invokeinterface #6,  2            // InterfaceMethod javax/xml/namespace/NamespaceContext.getPrefix:(Ljava/lang/String;)Ljava/lang/String;
      10: areturn

  public java.util.Iterator getPrefixes(java.lang.String);
    Code:
       0: new           #7                  // class java/util/ArrayList
       3: dup
       4: iconst_5
       5: invokespecial #8                  // Method java/util/ArrayList."<init>":(I)V
       8: astore_2
       9: aload_0
      10: getfield      #2                  // Field parent:Ljavax/xml/namespace/NamespaceContext;
      13: aload_1
      14: invokeinterface #9,  2            // InterfaceMethod javax/xml/namespace/NamespaceContext.getPrefixes:(Ljava/lang/String;)Ljava/util/Iterator;
      19: astore_3
      20: aload_3
      21: invokeinterface #10,  1           // InterfaceMethod java/util/Iterator.hasNext:()Z
      26: ifeq          84
      29: aload_3
      30: invokeinterface #11,  1           // InterfaceMethod java/util/Iterator.next:()Ljava/lang/Object;
      35: checkcast     #12                 // class java/lang/String
      38: astore        4
      40: aload_0
      41: getfield      #2                  // Field parent:Ljavax/xml/namespace/NamespaceContext;
      44: aload         4
      46: invokeinterface #3,  2            // InterfaceMethod javax/xml/namespace/NamespaceContext.getNamespaceURI:(Ljava/lang/String;)Ljava/lang/String;
      51: astore        5
      53: aload_1
      54: aload         5
      56: if_acmpeq     72
      59: aload_1
      60: ifnull        81
      63: aload_1
      64: aload         5
      66: invokevirtual #13                 // Method java/lang/String.equals:(Ljava/lang/Object;)Z
      69: ifeq          81
      72: aload_2
      73: aload         4
      75: invokeinterface #14,  2           // InterfaceMethod java/util/List.add:(Ljava/lang/Object;)Z
      80: pop
      81: goto          20
      84: aload_2
      85: invokeinterface #15,  1           // InterfaceMethod java/util/List.iterator:()Ljava/util/Iterator;
      90: areturn
}
