Compiled from "Certificates.java"
public class io.undertow.util.Certificates {
  public static final java.lang.String BEGIN_CERT;

  public static final java.lang.String END_CERT;

  public static java.lang.String toPem(javax.security.cert.X509Certificate) throws javax.security.cert.CertificateEncodingException;
    Code:
       0: aload_0
       1: invokevirtual #1                  // Method javax/security/cert/X509Certificate.getEncoded:()[B
       4: invokestatic  #2                  // Method toPem:([B)Ljava/lang/String;
       7: areturn

  public static java.lang.String toPem(java.security.cert.Certificate) throws java.security.cert.CertificateEncodingException;
    Code:
       0: aload_0
       1: invokevirtual #3                  // Method java/security/cert/Certificate.getEncoded:()[B
       4: invokestatic  #2                  // Method toPem:([B)Ljava/lang/String;
       7: areturn

  private static java.lang.String toPem(byte[]);
    Code:
       0: new           #4                  // class java/lang/StringBuilder
       3: dup
       4: invokespecial #5                  // Method java/lang/StringBuilder."<init>":()V
       7: astore_1
       8: aload_1
       9: ldc           #7                  // String -----BEGIN CERTIFICATE-----
      11: invokevirtual #8                  // Method java/lang/StringBuilder.append:(Ljava/lang/String;)Ljava/lang/StringBuilder;
      14: pop
      15: aload_1
      16: bipush        10
      18: invokevirtual #9                  // Method java/lang/StringBuilder.append:(C)Ljava/lang/StringBuilder;
      21: pop
      22: aload_1
      23: aload_0
      24: iconst_1
      25: invokestatic  #10                 // Method io/undertow/util/FlexBase64.encodeString:([BZ)Ljava/lang/String;
      28: invokevirtual #8                  // Method java/lang/StringBuilder.append:(Ljava/lang/String;)Ljava/lang/StringBuilder;
      31: pop
      32: aload_1
      33: bipush        10
      35: invokevirtual #9                  // Method java/lang/StringBuilder.append:(C)Ljava/lang/StringBuilder;
      38: pop
      39: aload_1
      40: ldc           #11                 // String -----END CERTIFICATE-----
      42: invokevirtual #8                  // Method java/lang/StringBuilder.append:(Ljava/lang/String;)Ljava/lang/StringBuilder;
      45: pop
      46: aload_1
      47: invokevirtual #12                 // Method java/lang/StringBuilder.toString:()Ljava/lang/String;
      50: areturn

  private io.undertow.util.Certificates();
    Code:
       0: aload_0
       1: invokespecial #13                 // Method java/lang/Object."<init>":()V
       4: return
}
