Compiled from "HeaderTokenParser.java"
class io.undertow.util.HeaderTokenParser$1 {
  static final int[] $SwitchMap$io$undertow$util$HeaderTokenParser$SearchingFor;

  static {};
    Code:
       0: invokestatic  #1                  // Method io/undertow/util/HeaderTokenParser$SearchingFor.values:()[Lio/undertow/util/HeaderTokenParser$SearchingFor;
       3: arraylength
       4: newarray       int
       6: putstatic     #2                  // Field $SwitchMap$io$undertow$util$HeaderTokenParser$SearchingFor:[I
       9: getstatic     #2                  // Field $SwitchMap$io$undertow$util$HeaderTokenParser$SearchingFor:[I
      12: getstatic     #3                  // Field io/undertow/util/HeaderTokenParser$SearchingFor.START_OF_NAME:Lio/undertow/util/HeaderTokenParser$SearchingFor;
      15: invokevirtual #4                  // Method io/undertow/util/HeaderTokenParser$SearchingFor.ordinal:()I
      18: iconst_1
      19: iastore
      20: goto          24
      23: astore_0
      24: getstatic     #2                  // Field $SwitchMap$io$undertow$util$HeaderTokenParser$SearchingFor:[I
      27: getstatic     #6                  // Field io/undertow/util/HeaderTokenParser$SearchingFor.EQUALS_SIGN:Lio/undertow/util/HeaderTokenParser$SearchingFor;
      30: invokevirtual #4                  // Method io/undertow/util/HeaderTokenParser$SearchingFor.ordinal:()I
      33: iconst_2
      34: iastore
      35: goto          39
      38: astore_0
      39: getstatic     #2                  // Field $SwitchMap$io$undertow$util$HeaderTokenParser$SearchingFor:[I
      42: getstatic     #7                  // Field io/undertow/util/HeaderTokenParser$SearchingFor.START_OF_VALUE:Lio/undertow/util/HeaderTokenParser$SearchingFor;
      45: invokevirtual #4                  // Method io/undertow/util/HeaderTokenParser$SearchingFor.ordinal:()I
      48: iconst_3
      49: iastore
      50: goto          54
      53: astore_0
      54: getstatic     #2                  // Field $SwitchMap$io$undertow$util$HeaderTokenParser$SearchingFor:[I
      57: getstatic     #8                  // Field io/undertow/util/HeaderTokenParser$SearchingFor.LAST_QUOTE:Lio/undertow/util/HeaderTokenParser$SearchingFor;
      60: invokevirtual #4                  // Method io/undertow/util/HeaderTokenParser$SearchingFor.ordinal:()I
      63: iconst_4
      64: iastore
      65: goto          69
      68: astore_0
      69: getstatic     #2                  // Field $SwitchMap$io$undertow$util$HeaderTokenParser$SearchingFor:[I
      72: getstatic     #9                  // Field io/undertow/util/HeaderTokenParser$SearchingFor.END_OF_VALUE:Lio/undertow/util/HeaderTokenParser$SearchingFor;
      75: invokevirtual #4                  // Method io/undertow/util/HeaderTokenParser$SearchingFor.ordinal:()I
      78: iconst_5
      79: iastore
      80: goto          84
      83: astore_0
      84: return
    Exception table:
       from    to  target type
           9    20    23   Class java/lang/NoSuchFieldError
          24    35    38   Class java/lang/NoSuchFieldError
          39    50    53   Class java/lang/NoSuchFieldError
          54    65    68   Class java/lang/NoSuchFieldError
          69    80    83   Class java/lang/NoSuchFieldError
}
