Compiled from "ImmediatePooled.java"
public class io.undertow.util.ImmediatePooled<T> implements org.xnio.Pooled<T> {
  private final T value;

  public io.undertow.util.ImmediatePooled(T);
    Code:
       0: aload_0
       1: invokespecial #1                  // Method java/lang/Object."<init>":()V
       4: aload_0
       5: aload_1
       6: putfield      #2                  // Field value:Ljava/lang/Object;
       9: return

  public void discard();
    Code:
       0: return

  public void free();
    Code:
       0: return

  public T getResource() throws java.lang.IllegalStateException;
    Code:
       0: aload_0
       1: getfield      #2                  // Field value:Ljava/lang/Object;
       4: areturn

  public void close();
    Code:
       0: return
}
