Compiled from "SimpleObjectPool.java"
public class io.undertow.util.SimpleObjectPool<T> implements io.undertow.util.ObjectPool {
  private final java.util.function.Supplier<T> supplier;

  private final java.util.function.Consumer<T> recycler;

  private final java.util.function.Consumer<T> consumer;

  private final java.util.concurrent.LinkedBlockingDeque<T> pool;

  public io.undertow.util.SimpleObjectPool(int, java.util.function.Supplier<T>, java.util.function.Consumer<T>, java.util.function.Consumer<T>);
    Code:
       0: aload_0
       1: invokespecial #1                  // Method java/lang/Object."<init>":()V
       4: aload_0
       5: aload_2
       6: putfield      #2                  // Field supplier:Ljava/util/function/Supplier;
       9: aload_0
      10: aload_3
      11: putfield      #3                  // Field recycler:Ljava/util/function/Consumer;
      14: aload_0
      15: aload         4
      17: putfield      #4                  // Field consumer:Ljava/util/function/Consumer;
      20: aload_0
      21: new           #5                  // class java/util/concurrent/LinkedBlockingDeque
      24: dup
      25: iload_1
      26: invokespecial #6                  // Method java/util/concurrent/LinkedBlockingDeque."<init>":(I)V
      29: putfield      #7                  // Field pool:Ljava/util/concurrent/LinkedBlockingDeque;
      32: return

  public io.undertow.util.SimpleObjectPool(int, java.util.function.Supplier<T>, java.util.function.Consumer<T>);
    Code:
       0: aload_0
       1: iload_1
       2: aload_2
       3: invokedynamic #8,  0              // InvokeDynamic #0:accept:()Ljava/util/function/Consumer;
       8: aload_3
       9: invokespecial #9                  // Method "<init>":(ILjava/util/function/Supplier;Ljava/util/function/Consumer;Ljava/util/function/Consumer;)V
      12: return

  public io.undertow.util.PooledObject<T> allocate();
    Code:
       0: aload_0
       1: getfield      #7                  // Field pool:Ljava/util/concurrent/LinkedBlockingDeque;
       4: invokevirtual #10                 // Method java/util/concurrent/LinkedBlockingDeque.poll:()Ljava/lang/Object;
       7: astore_1
       8: aload_1
       9: ifnonnull     22
      12: aload_0
      13: getfield      #2                  // Field supplier:Ljava/util/function/Supplier;
      16: invokeinterface #11,  1           // InterfaceMethod java/util/function/Supplier.get:()Ljava/lang/Object;
      21: astore_1
      22: new           #12                 // class io/undertow/util/SimpleObjectPool$SimplePooledObject
      25: dup
      26: aload_1
      27: aload_0
      28: invokespecial #13                 // Method io/undertow/util/SimpleObjectPool$SimplePooledObject."<init>":(Ljava/lang/Object;Lio/undertow/util/SimpleObjectPool;)V
      31: areturn

  private static void lambda$new$0(java.lang.Object);
    Code:
       0: return
}
