Compiled from "PoolAnnotationInformationFactory.java"
public class org.jboss.as.ejb3.deployment.processors.annotation.PoolAnnotationInformationFactory extends org.jboss.as.ee.metadata.ClassAnnotationInformationFactory<org.jboss.ejb3.annotation.Pool, java.lang.String> {
  public org.jboss.as.ejb3.deployment.processors.annotation.PoolAnnotationInformationFactory();
    Code:
       0: aload_0
       1: ldc           #1                  // class org/jboss/ejb3/annotation/Pool
       3: aconst_null
       4: invokespecial #2                  // Method org/jboss/as/ee/metadata/ClassAnnotationInformationFactory."<init>":(Ljava/lang/Class;Ljava/lang/Class;)V
       7: return

  protected java.lang.String fromAnnotation(org.jboss.jandex.AnnotationInstance, org.jboss.metadata.property.PropertyReplacer);
    Code:
       0: aload_1
       1: invokevirtual #3                  // Method org/jboss/jandex/AnnotationInstance.value:()Lorg/jboss/jandex/AnnotationValue;
       4: astore_3
       5: aload_3
       6: ifnull        19
       9: aload_3
      10: invokevirtual #4                  // Method org/jboss/jandex/AnnotationValue.asString:()Ljava/lang/String;
      13: invokevirtual #5                  // Method java/lang/String.isEmpty:()Z
      16: ifeq          32
      19: getstatic     #6                  // Field org/jboss/as/ee/logging/EeLogger.ROOT_LOGGER:Lorg/jboss/as/ee/logging/EeLogger;
      22: ldc           #7                  // String @Pool
      24: ldc           #8                  // String value
      26: invokeinterface #9,  3            // InterfaceMethod org/jboss/as/ee/logging/EeLogger.annotationAttributeMissing:(Ljava/lang/String;Ljava/lang/String;)Ljava/lang/IllegalArgumentException;
      31: athrow
      32: aload_2
      33: aload_3
      34: invokevirtual #4                  // Method org/jboss/jandex/AnnotationValue.asString:()Ljava/lang/String;
      37: invokeinterface #10,  2           // InterfaceMethod org/jboss/metadata/property/PropertyReplacer.replaceProperties:(Ljava/lang/String;)Ljava/lang/String;
      42: areturn

  protected java.lang.Object fromAnnotation(org.jboss.jandex.AnnotationInstance, org.jboss.metadata.property.PropertyReplacer);
    Code:
       0: aload_0
       1: aload_1
       2: aload_2
       3: invokevirtual #11                 // Method fromAnnotation:(Lorg/jboss/jandex/AnnotationInstance;Lorg/jboss/metadata/property/PropertyReplacer;)Ljava/lang/String;
       6: areturn
}
