Compiled from "OnErrorEvaluator.java"
public class ch.qos.logback.classic.boolex.OnErrorEvaluator extends ch.qos.logback.core.boolex.EventEvaluatorBase<ch.qos.logback.classic.spi.ILoggingEvent> {
  public ch.qos.logback.classic.boolex.OnErrorEvaluator();
    Code:
       0: aload_0
       1: invokespecial #1                  // Method ch/qos/logback/core/boolex/EventEvaluatorBase."<init>":()V
       4: return

  public boolean evaluate(ch.qos.logback.classic.spi.ILoggingEvent) throws java.lang.NullPointerException, ch.qos.logback.core.boolex.EvaluationException;
    Code:
       0: aload_1
       1: invokeinterface #2,  1            // InterfaceMethod ch/qos/logback/classic/spi/ILoggingEvent.getLevel:()Lch/qos/logback/classic/Level;
       6: getfield      #3                  // Field ch/qos/logback/classic/Level.levelInt:I
       9: ldc           #4                  // int 40000
      11: if_icmplt     18
      14: iconst_1
      15: goto          19
      18: iconst_0
      19: ireturn

  public boolean evaluate(java.lang.Object) throws java.lang.NullPointerException, ch.qos.logback.core.boolex.EvaluationException;
    Code:
       0: aload_0
       1: aload_1
       2: checkcast     #5                  // class ch/qos/logback/classic/spi/ILoggingEvent
       5: invokevirtual #6                  // Method evaluate:(Lch/qos/logback/classic/spi/ILoggingEvent;)Z
       8: ireturn
}
