Compiled from "ToStringHelper.java"
public class org.slf4j.instrumentation.ToStringHelper {
  private static final java.lang.String ARRAY_PREFIX;

  private static final java.lang.String ARRAY_SUFFIX;

  private static final java.lang.String ELEMENT_SEPARATOR;

  static final java.util.Map<java.lang.Class<?>, java.lang.Object> unrenderableClasses;

  public org.slf4j.instrumentation.ToStringHelper();
    Code:
       0: aload_0
       1: invokespecial #1                  // Method java/lang/Object."<init>":()V
       4: return

  public static java.lang.String render(java.lang.Object);
    Code:
       0: aload_0
       1: ifnonnull     9
       4: aload_0
       5: invokestatic  #2                  // Method java/lang/String.valueOf:(Ljava/lang/Object;)Ljava/lang/String;
       8: areturn
       9: aload_0
      10: invokevirtual #3                  // Method java/lang/Object.getClass:()Ljava/lang/Class;
      13: astore_1
      14: getstatic     #4                  // Field unrenderableClasses:Ljava/util/Map;
      17: aload_1
      18: invokeinterface #5,  2            // InterfaceMethod java/util/Map.containsKey:(Ljava/lang/Object;)Z
      23: ifne          110
      26: aload_1
      27: invokevirtual #6                  // Method java/lang/Class.isArray:()Z
      30: ifeq          42
      33: aload_0
      34: aload_1
      35: invokestatic  #7                  // Method renderArray:(Ljava/lang/Object;Ljava/lang/Class;)Ljava/lang/StringBuffer;
      38: invokevirtual #8                  // Method java/lang/StringBuffer.toString:()Ljava/lang/String;
      41: areturn
      42: aload_0
      43: invokevirtual #9                  // Method java/lang/Object.toString:()Ljava/lang/String;
      46: areturn
      47: astore_2
      48: new           #11                 // class java/lang/Long
      51: dup
      52: invokestatic  #12                 // Method java/lang/System.currentTimeMillis:()J
      55: invokespecial #13                 // Method java/lang/Long."<init>":(J)V
      58: astore_3
      59: getstatic     #14                 // Field java/lang/System.err:Ljava/io/PrintStream;
      62: new           #15                 // class java/lang/StringBuilder
      65: dup
      66: invokespecial #16                 // Method java/lang/StringBuilder."<init>":()V
      69: ldc           #17                 // String Disabling exception throwing class
      71: invokevirtual #18                 // Method java/lang/StringBuilder.append:(Ljava/lang/String;)Ljava/lang/StringBuilder;
      74: aload_1
      75: invokevirtual #19                 // Method java/lang/Class.getName:()Ljava/lang/String;
      78: invokevirtual #18                 // Method java/lang/StringBuilder.append:(Ljava/lang/String;)Ljava/lang/StringBuilder;
      81: ldc           #20                 // String ,
      83: invokevirtual #18                 // Method java/lang/StringBuilder.append:(Ljava/lang/String;)Ljava/lang/StringBuilder;
      86: aload_2
      87: invokevirtual #21                 // Method java/lang/Exception.getMessage:()Ljava/lang/String;
      90: invokevirtual #18                 // Method java/lang/StringBuilder.append:(Ljava/lang/String;)Ljava/lang/StringBuilder;
      93: invokevirtual #22                 // Method java/lang/StringBuilder.toString:()Ljava/lang/String;
      96: invokevirtual #23                 // Method java/io/PrintStream.println:(Ljava/lang/String;)V
      99: getstatic     #4                  // Field unrenderableClasses:Ljava/util/Map;
     102: aload_1
     103: aload_3
     104: invokeinterface #24,  3           // InterfaceMethod java/util/Map.put:(Ljava/lang/Object;Ljava/lang/Object;)Ljava/lang/Object;
     109: pop
     110: aload_0
     111: invokevirtual #3                  // Method java/lang/Object.getClass:()Ljava/lang/Class;
     114: invokevirtual #19                 // Method java/lang/Class.getName:()Ljava/lang/String;
     117: astore_2
     118: new           #15                 // class java/lang/StringBuilder
     121: dup
     122: invokespecial #16                 // Method java/lang/StringBuilder."<init>":()V
     125: aload_2
     126: invokevirtual #18                 // Method java/lang/StringBuilder.append:(Ljava/lang/String;)Ljava/lang/StringBuilder;
     129: ldc           #25                 // String @
     131: invokevirtual #18                 // Method java/lang/StringBuilder.append:(Ljava/lang/String;)Ljava/lang/StringBuilder;
     134: aload_0
     135: invokevirtual #26                 // Method java/lang/Object.hashCode:()I
     138: invokestatic  #27                 // Method java/lang/Integer.toHexString:(I)Ljava/lang/String;
     141: invokevirtual #18                 // Method java/lang/StringBuilder.append:(Ljava/lang/String;)Ljava/lang/StringBuilder;
     144: invokevirtual #22                 // Method java/lang/StringBuilder.toString:()Ljava/lang/String;
     147: areturn
    Exception table:
       from    to  target type
          26    41    47   Class java/lang/Exception
          42    46    47   Class java/lang/Exception

  private static java.lang.StringBuffer renderArray(java.lang.Object, java.lang.Class<?>);
    Code:
       0: aload_1
       1: invokevirtual #28                 // Method java/lang/Class.getComponentType:()Ljava/lang/Class;
       4: astore_2
       5: new           #29                 // class java/lang/StringBuffer
       8: dup
       9: ldc           #30                 // String [
      11: invokespecial #31                 // Method java/lang/StringBuffer."<init>":(Ljava/lang/String;)V
      14: astore_3
      15: aload_2
      16: invokevirtual #32                 // Method java/lang/Class.isPrimitive:()Z
      19: ifne          76
      22: aload_0
      23: checkcast     #33                 // class "[Ljava/lang/Object;"
      26: checkcast     #33                 // class "[Ljava/lang/Object;"
      29: astore        4
      31: iconst_0
      32: istore        5
      34: iload         5
      36: aload         4
      38: arraylength
      39: if_icmpge     73
      42: iload         5
      44: ifle          54
      47: aload_3
      48: ldc           #20                 // String ,
      50: invokevirtual #34                 // Method java/lang/StringBuffer.append:(Ljava/lang/String;)Ljava/lang/StringBuffer;
      53: pop
      54: aload_3
      55: aload         4
      57: iload         5
      59: aaload
      60: invokestatic  #35                 // Method render:(Ljava/lang/Object;)Ljava/lang/String;
      63: invokevirtual #34                 // Method java/lang/StringBuffer.append:(Ljava/lang/String;)Ljava/lang/StringBuffer;
      66: pop
      67: iinc          5, 1
      70: goto          34
      73: goto          561
      76: getstatic     #36                 // Field java/lang/Boolean.TYPE:Ljava/lang/Class;
      79: aload_2
      80: invokevirtual #37                 // Method java/lang/Object.equals:(Ljava/lang/Object;)Z
      83: ifeq          137
      86: aload_0
      87: checkcast     #38                 // class "[Z"
      90: checkcast     #38                 // class "[Z"
      93: astore        4
      95: iconst_0
      96: istore        5
      98: iload         5
     100: aload         4
     102: arraylength
     103: if_icmpge     134
     106: iload         5
     108: ifle          118
     111: aload_3
     112: ldc           #20                 // String ,
     114: invokevirtual #34                 // Method java/lang/StringBuffer.append:(Ljava/lang/String;)Ljava/lang/StringBuffer;
     117: pop
     118: aload_3
     119: aload         4
     121: iload         5
     123: baload
     124: invokevirtual #39                 // Method java/lang/StringBuffer.append:(Z)Ljava/lang/StringBuffer;
     127: pop
     128: iinc          5, 1
     131: goto          98
     134: goto          561
     137: getstatic     #40                 // Field java/lang/Integer.TYPE:Ljava/lang/Class;
     140: aload_2
     141: invokevirtual #37                 // Method java/lang/Object.equals:(Ljava/lang/Object;)Z
     144: ifeq          198
     147: aload_0
     148: checkcast     #41                 // class "[I"
     151: checkcast     #41                 // class "[I"
     154: astore        4
     156: iconst_0
     157: istore        5
     159: iload         5
     161: aload         4
     163: arraylength
     164: if_icmpge     195
     167: iload         5
     169: ifle          179
     172: aload_3
     173: ldc           #20                 // String ,
     175: invokevirtual #34                 // Method java/lang/StringBuffer.append:(Ljava/lang/String;)Ljava/lang/StringBuffer;
     178: pop
     179: aload_3
     180: aload         4
     182: iload         5
     184: iaload
     185: invokevirtual #42                 // Method java/lang/StringBuffer.append:(I)Ljava/lang/StringBuffer;
     188: pop
     189: iinc          5, 1
     192: goto          159
     195: goto          561
     198: getstatic     #43                 // Field java/lang/Long.TYPE:Ljava/lang/Class;
     201: aload_2
     202: invokevirtual #37                 // Method java/lang/Object.equals:(Ljava/lang/Object;)Z
     205: ifeq          259
     208: aload_0
     209: checkcast     #44                 // class "[J"
     212: checkcast     #44                 // class "[J"
     215: astore        4
     217: iconst_0
     218: istore        5
     220: iload         5
     222: aload         4
     224: arraylength
     225: if_icmpge     256
     228: iload         5
     230: ifle          240
     233: aload_3
     234: ldc           #20                 // String ,
     236: invokevirtual #34                 // Method java/lang/StringBuffer.append:(Ljava/lang/String;)Ljava/lang/StringBuffer;
     239: pop
     240: aload_3
     241: aload         4
     243: iload         5
     245: laload
     246: invokevirtual #45                 // Method java/lang/StringBuffer.append:(J)Ljava/lang/StringBuffer;
     249: pop
     250: iinc          5, 1
     253: goto          220
     256: goto          561
     259: getstatic     #46                 // Field java/lang/Double.TYPE:Ljava/lang/Class;
     262: aload_2
     263: invokevirtual #37                 // Method java/lang/Object.equals:(Ljava/lang/Object;)Z
     266: ifeq          320
     269: aload_0
     270: checkcast     #47                 // class "[D"
     273: checkcast     #47                 // class "[D"
     276: astore        4
     278: iconst_0
     279: istore        5
     281: iload         5
     283: aload         4
     285: arraylength
     286: if_icmpge     317
     289: iload         5
     291: ifle          301
     294: aload_3
     295: ldc           #20                 // String ,
     297: invokevirtual #34                 // Method java/lang/StringBuffer.append:(Ljava/lang/String;)Ljava/lang/StringBuffer;
     300: pop
     301: aload_3
     302: aload         4
     304: iload         5
     306: daload
     307: invokevirtual #48                 // Method java/lang/StringBuffer.append:(D)Ljava/lang/StringBuffer;
     310: pop
     311: iinc          5, 1
     314: goto          281
     317: goto          561
     320: getstatic     #49                 // Field java/lang/Float.TYPE:Ljava/lang/Class;
     323: aload_2
     324: invokevirtual #37                 // Method java/lang/Object.equals:(Ljava/lang/Object;)Z
     327: ifeq          381
     330: aload_0
     331: checkcast     #50                 // class "[F"
     334: checkcast     #50                 // class "[F"
     337: astore        4
     339: iconst_0
     340: istore        5
     342: iload         5
     344: aload         4
     346: arraylength
     347: if_icmpge     378
     350: iload         5
     352: ifle          362
     355: aload_3
     356: ldc           #20                 // String ,
     358: invokevirtual #34                 // Method java/lang/StringBuffer.append:(Ljava/lang/String;)Ljava/lang/StringBuffer;
     361: pop
     362: aload_3
     363: aload         4
     365: iload         5
     367: faload
     368: invokevirtual #51                 // Method java/lang/StringBuffer.append:(F)Ljava/lang/StringBuffer;
     371: pop
     372: iinc          5, 1
     375: goto          342
     378: goto          561
     381: getstatic     #52                 // Field java/lang/Character.TYPE:Ljava/lang/Class;
     384: aload_2
     385: invokevirtual #37                 // Method java/lang/Object.equals:(Ljava/lang/Object;)Z
     388: ifeq          442
     391: aload_0
     392: checkcast     #53                 // class "[C"
     395: checkcast     #53                 // class "[C"
     398: astore        4
     400: iconst_0
     401: istore        5
     403: iload         5
     405: aload         4
     407: arraylength
     408: if_icmpge     439
     411: iload         5
     413: ifle          423
     416: aload_3
     417: ldc           #20                 // String ,
     419: invokevirtual #34                 // Method java/lang/StringBuffer.append:(Ljava/lang/String;)Ljava/lang/StringBuffer;
     422: pop
     423: aload_3
     424: aload         4
     426: iload         5
     428: caload
     429: invokevirtual #54                 // Method java/lang/StringBuffer.append:(C)Ljava/lang/StringBuffer;
     432: pop
     433: iinc          5, 1
     436: goto          403
     439: goto          561
     442: getstatic     #55                 // Field java/lang/Short.TYPE:Ljava/lang/Class;
     445: aload_2
     446: invokevirtual #37                 // Method java/lang/Object.equals:(Ljava/lang/Object;)Z
     449: ifeq          503
     452: aload_0
     453: checkcast     #56                 // class "[S"
     456: checkcast     #56                 // class "[S"
     459: astore        4
     461: iconst_0
     462: istore        5
     464: iload         5
     466: aload         4
     468: arraylength
     469: if_icmpge     500
     472: iload         5
     474: ifle          484
     477: aload_3
     478: ldc           #20                 // String ,
     480: invokevirtual #34                 // Method java/lang/StringBuffer.append:(Ljava/lang/String;)Ljava/lang/StringBuffer;
     483: pop
     484: aload_3
     485: aload         4
     487: iload         5
     489: saload
     490: invokevirtual #42                 // Method java/lang/StringBuffer.append:(I)Ljava/lang/StringBuffer;
     493: pop
     494: iinc          5, 1
     497: goto          464
     500: goto          561
     503: getstatic     #57                 // Field java/lang/Byte.TYPE:Ljava/lang/Class;
     506: aload_2
     507: invokevirtual #37                 // Method java/lang/Object.equals:(Ljava/lang/Object;)Z
     510: ifeq          561
     513: aload_0
     514: checkcast     #58                 // class "[B"
     517: checkcast     #58                 // class "[B"
     520: astore        4
     522: iconst_0
     523: istore        5
     525: iload         5
     527: aload         4
     529: arraylength
     530: if_icmpge     561
     533: iload         5
     535: ifle          545
     538: aload_3
     539: ldc           #20                 // String ,
     541: invokevirtual #34                 // Method java/lang/StringBuffer.append:(Ljava/lang/String;)Ljava/lang/StringBuffer;
     544: pop
     545: aload_3
     546: aload         4
     548: iload         5
     550: baload
     551: invokevirtual #42                 // Method java/lang/StringBuffer.append:(I)Ljava/lang/StringBuffer;
     554: pop
     555: iinc          5, 1
     558: goto          525
     561: aload_3
     562: ldc           #59                 // String ]
     564: invokevirtual #34                 // Method java/lang/StringBuffer.append:(Ljava/lang/String;)Ljava/lang/StringBuffer;
     567: pop
     568: aload_3
     569: areturn

  static {};
    Code:
       0: new           #60                 // class java/util/WeakHashMap
       3: dup
       4: invokespecial #61                 // Method java/util/WeakHashMap."<init>":()V
       7: putstatic     #4                  // Field unrenderableClasses:Ljava/util/Map;
      10: return
}
