Compiled from "CamelContextStartupFailureEvent.java"
public class org.apache.camel.management.event.CamelContextStartupFailureEvent extends java.util.EventObject {
  private static final long serialVersionUID;

  private org.apache.camel.CamelContext context;

  private java.lang.Throwable cause;

  public org.apache.camel.management.event.CamelContextStartupFailureEvent(org.apache.camel.CamelContext, java.lang.Throwable);
    Code:
       0: aload_0
       1: aload_1
       2: invokespecial #18                 // Method java/util/EventObject."<init>":(Ljava/lang/Object;)V
       5: aload_0
       6: aload_1
       7: putfield      #20                 // Field context:Lorg/apache/camel/CamelContext;
      10: aload_0
      11: aload_2
      12: putfield      #22                 // Field cause:Ljava/lang/Throwable;
      15: return

  public org.apache.camel.CamelContext getContext();
    Code:
       0: aload_0
       1: getfield      #20                 // Field context:Lorg/apache/camel/CamelContext;
       4: areturn

  public java.lang.Throwable getCause();
    Code:
       0: aload_0
       1: getfield      #22                 // Field cause:Ljava/lang/Throwable;
       4: areturn

  public java.lang.String toString();
    Code:
       0: new           #32                 // class java/lang/StringBuilder
       3: dup
       4: invokespecial #35                 // Method java/lang/StringBuilder."<init>":()V
       7: ldc           #37                 // String Failed to start Camel:
       9: invokevirtual #41                 // Method java/lang/StringBuilder.append:(Ljava/lang/String;)Ljava/lang/StringBuilder;
      12: aload_0
      13: getfield      #20                 // Field context:Lorg/apache/camel/CamelContext;
      16: invokeinterface #46,  1           // InterfaceMethod org/apache/camel/CamelContext.getName:()Ljava/lang/String;
      21: invokevirtual #41                 // Method java/lang/StringBuilder.append:(Ljava/lang/String;)Ljava/lang/StringBuilder;
      24: ldc           #48                 // String  due to
      26: invokevirtual #41                 // Method java/lang/StringBuilder.append:(Ljava/lang/String;)Ljava/lang/StringBuilder;
      29: aload_0
      30: getfield      #22                 // Field cause:Ljava/lang/Throwable;
      33: invokevirtual #53                 // Method java/lang/Throwable.getMessage:()Ljava/lang/String;
      36: invokevirtual #41                 // Method java/lang/StringBuilder.append:(Ljava/lang/String;)Ljava/lang/StringBuilder;
      39: invokevirtual #55                 // Method java/lang/StringBuilder.toString:()Ljava/lang/String;
      42: areturn
}
