Compiled from "SMTPAppenderBase.java"
class ch.qos.logback.core.net.SMTPAppenderBase$SenderRunnable implements java.lang.Runnable {
  final ch.qos.logback.core.helpers.CyclicBuffer<E> cyclicBuffer;

  final E e;

  final ch.qos.logback.core.net.SMTPAppenderBase this$0;

  ch.qos.logback.core.net.SMTPAppenderBase$SenderRunnable(ch.qos.logback.core.helpers.CyclicBuffer<E>, E);
    Code:
       0: aload_0
       1: aload_1
       2: putfield      #1                  // Field this$0:Lch/qos/logback/core/net/SMTPAppenderBase;
       5: aload_0
       6: invokespecial #2                  // Method java/lang/Object."<init>":()V
       9: aload_0
      10: aload_2
      11: putfield      #3                  // Field cyclicBuffer:Lch/qos/logback/core/helpers/CyclicBuffer;
      14: aload_0
      15: aload_3
      16: putfield      #4                  // Field e:Ljava/lang/Object;
      19: return

  public void run();
    Code:
       0: aload_0
       1: getfield      #1                  // Field this$0:Lch/qos/logback/core/net/SMTPAppenderBase;
       4: aload_0
       5: getfield      #3                  // Field cyclicBuffer:Lch/qos/logback/core/helpers/CyclicBuffer;
       8: aload_0
       9: getfield      #4                  // Field e:Ljava/lang/Object;
      12: invokevirtual #5                  // Method ch/qos/logback/core/net/SMTPAppenderBase.sendBuffer:(Lch/qos/logback/core/helpers/CyclicBuffer;Ljava/lang/Object;)V
      15: return
}
