Compiled from "HealthEndpointWebExtension.java"
public class org.springframework.boot.actuate.health.HealthEndpointWebExtension {
  private final org.springframework.boot.actuate.health.HealthEndpoint delegate;

  private final org.springframework.boot.actuate.health.HealthWebEndpointResponseMapper responseMapper;

  public org.springframework.boot.actuate.health.HealthEndpointWebExtension(org.springframework.boot.actuate.health.HealthEndpoint, org.springframework.boot.actuate.health.HealthWebEndpointResponseMapper);
    Code:
       0: aload_0
       1: invokespecial #1                  // Method java/lang/Object."<init>":()V
       4: aload_0
       5: aload_1
       6: putfield      #2                  // Field delegate:Lorg/springframework/boot/actuate/health/HealthEndpoint;
       9: aload_0
      10: aload_2
      11: putfield      #3                  // Field responseMapper:Lorg/springframework/boot/actuate/health/HealthWebEndpointResponseMapper;
      14: return

  public org.springframework.boot.actuate.endpoint.web.WebEndpointResponse<org.springframework.boot.actuate.health.Health> health(org.springframework.boot.actuate.endpoint.SecurityContext);
    Code:
       0: aload_0
       1: getfield      #3                  // Field responseMapper:Lorg/springframework/boot/actuate/health/HealthWebEndpointResponseMapper;
       4: aload_0
       5: getfield      #2                  // Field delegate:Lorg/springframework/boot/actuate/health/HealthEndpoint;
       8: invokevirtual #4                  // Method org/springframework/boot/actuate/health/HealthEndpoint.health:()Lorg/springframework/boot/actuate/health/Health;
      11: aload_1
      12: invokevirtual #5                  // Method org/springframework/boot/actuate/health/HealthWebEndpointResponseMapper.map:(Lorg/springframework/boot/actuate/health/Health;Lorg/springframework/boot/actuate/endpoint/SecurityContext;)Lorg/springframework/boot/actuate/endpoint/web/WebEndpointResponse;
      15: areturn

  public org.springframework.boot.actuate.endpoint.web.WebEndpointResponse<org.springframework.boot.actuate.health.Health> healthForComponent(org.springframework.boot.actuate.endpoint.SecurityContext, java.lang.String);
    Code:
       0: aload_0
       1: aload_2
       2: invokedynamic #6,  0              // InvokeDynamic #0:get:(Lorg/springframework/boot/actuate/health/HealthEndpointWebExtension;Ljava/lang/String;)Ljava/util/function/Supplier;
       7: astore_3
       8: aload_0
       9: getfield      #3                  // Field responseMapper:Lorg/springframework/boot/actuate/health/HealthWebEndpointResponseMapper;
      12: aload_3
      13: aload_1
      14: invokevirtual #7                  // Method org/springframework/boot/actuate/health/HealthWebEndpointResponseMapper.mapDetails:(Ljava/util/function/Supplier;Lorg/springframework/boot/actuate/endpoint/SecurityContext;)Lorg/springframework/boot/actuate/endpoint/web/WebEndpointResponse;
      17: areturn

  public org.springframework.boot.actuate.endpoint.web.WebEndpointResponse<org.springframework.boot.actuate.health.Health> healthForComponentInstance(org.springframework.boot.actuate.endpoint.SecurityContext, java.lang.String, java.lang.String);
    Code:
       0: aload_0
       1: aload_2
       2: aload_3
       3: invokedynamic #8,  0              // InvokeDynamic #1:get:(Lorg/springframework/boot/actuate/health/HealthEndpointWebExtension;Ljava/lang/String;Ljava/lang/String;)Ljava/util/function/Supplier;
       8: astore        4
      10: aload_0
      11: getfield      #3                  // Field responseMapper:Lorg/springframework/boot/actuate/health/HealthWebEndpointResponseMapper;
      14: aload         4
      16: aload_1
      17: invokevirtual #7                  // Method org/springframework/boot/actuate/health/HealthWebEndpointResponseMapper.mapDetails:(Ljava/util/function/Supplier;Lorg/springframework/boot/actuate/endpoint/SecurityContext;)Lorg/springframework/boot/actuate/endpoint/web/WebEndpointResponse;
      20: areturn

  public org.springframework.boot.actuate.endpoint.web.WebEndpointResponse<org.springframework.boot.actuate.health.Health> getHealth(org.springframework.boot.actuate.endpoint.SecurityContext, org.springframework.boot.actuate.health.ShowDetails);
    Code:
       0: aload_0
       1: getfield      #3                  // Field responseMapper:Lorg/springframework/boot/actuate/health/HealthWebEndpointResponseMapper;
       4: aload_0
       5: getfield      #2                  // Field delegate:Lorg/springframework/boot/actuate/health/HealthEndpoint;
       8: invokevirtual #4                  // Method org/springframework/boot/actuate/health/HealthEndpoint.health:()Lorg/springframework/boot/actuate/health/Health;
      11: aload_1
      12: aload_2
      13: invokevirtual #9                  // Method org/springframework/boot/actuate/health/HealthWebEndpointResponseMapper.map:(Lorg/springframework/boot/actuate/health/Health;Lorg/springframework/boot/actuate/endpoint/SecurityContext;Lorg/springframework/boot/actuate/health/ShowDetails;)Lorg/springframework/boot/actuate/endpoint/web/WebEndpointResponse;
      16: areturn

  private org.springframework.boot.actuate.health.Health lambda$healthForComponentInstance$1(java.lang.String, java.lang.String);
    Code:
       0: aload_0
       1: getfield      #2                  // Field delegate:Lorg/springframework/boot/actuate/health/HealthEndpoint;
       4: aload_1
       5: aload_2
       6: invokevirtual #10                 // Method org/springframework/boot/actuate/health/HealthEndpoint.healthForComponentInstance:(Ljava/lang/String;Ljava/lang/String;)Lorg/springframework/boot/actuate/health/Health;
       9: areturn

  private org.springframework.boot.actuate.health.Health lambda$healthForComponent$0(java.lang.String);
    Code:
       0: aload_0
       1: getfield      #2                  // Field delegate:Lorg/springframework/boot/actuate/health/HealthEndpoint;
       4: aload_1
       5: invokevirtual #11                 // Method org/springframework/boot/actuate/health/HealthEndpoint.healthForComponent:(Ljava/lang/String;)Lorg/springframework/boot/actuate/health/Health;
       8: areturn
}
