Compiled from "HealthIndicatorRegistryFactory.java"
public class org.springframework.boot.actuate.health.HealthIndicatorRegistryFactory {
  private final java.util.function.Function<java.lang.String, java.lang.String> healthIndicatorNameFactory;

  public org.springframework.boot.actuate.health.HealthIndicatorRegistryFactory(java.util.function.Function<java.lang.String, java.lang.String>);
    Code:
       0: aload_0
       1: invokespecial #1                  // Method java/lang/Object."<init>":()V
       4: aload_0
       5: aload_1
       6: putfield      #2                  // Field healthIndicatorNameFactory:Ljava/util/function/Function;
       9: return

  public org.springframework.boot.actuate.health.HealthIndicatorRegistryFactory();
    Code:
       0: aload_0
       1: new           #3                  // class org/springframework/boot/actuate/health/HealthIndicatorNameFactory
       4: dup
       5: invokespecial #4                  // Method org/springframework/boot/actuate/health/HealthIndicatorNameFactory."<init>":()V
       8: invokespecial #5                  // Method "<init>":(Ljava/util/function/Function;)V
      11: return

  public org.springframework.boot.actuate.health.HealthIndicatorRegistry createHealthIndicatorRegistry(java.util.Map<java.lang.String, org.springframework.boot.actuate.health.HealthIndicator>);
    Code:
       0: aload_1
       1: ldc           #6                  // String HealthIndicators must not be null
       3: invokestatic  #7                  // Method org/springframework/util/Assert.notNull:(Ljava/lang/Object;Ljava/lang/String;)V
       6: aload_0
       7: new           #8                  // class org/springframework/boot/actuate/health/DefaultHealthIndicatorRegistry
      10: dup
      11: invokespecial #9                  // Method org/springframework/boot/actuate/health/DefaultHealthIndicatorRegistry."<init>":()V
      14: aload_1
      15: invokevirtual #10                 // Method initialize:(Lorg/springframework/boot/actuate/health/HealthIndicatorRegistry;Ljava/util/Map;)Lorg/springframework/boot/actuate/health/HealthIndicatorRegistry;
      18: areturn

  protected <T extends org.springframework.boot.actuate.health.HealthIndicatorRegistry> T initialize(T, java.util.Map<java.lang.String, org.springframework.boot.actuate.health.HealthIndicator>);
    Code:
       0: aload_2
       1: invokeinterface #11,  1           // InterfaceMethod java/util/Map.entrySet:()Ljava/util/Set;
       6: invokeinterface #12,  1           // InterfaceMethod java/util/Set.iterator:()Ljava/util/Iterator;
      11: astore_3
      12: aload_3
      13: invokeinterface #13,  1           // InterfaceMethod java/util/Iterator.hasNext:()Z
      18: ifeq          74
      21: aload_3
      22: invokeinterface #14,  1           // InterfaceMethod java/util/Iterator.next:()Ljava/lang/Object;
      27: checkcast     #15                 // class java/util/Map$Entry
      30: astore        4
      32: aload_0
      33: getfield      #2                  // Field healthIndicatorNameFactory:Ljava/util/function/Function;
      36: aload         4
      38: invokeinterface #16,  1           // InterfaceMethod java/util/Map$Entry.getKey:()Ljava/lang/Object;
      43: invokeinterface #17,  2           // InterfaceMethod java/util/function/Function.apply:(Ljava/lang/Object;)Ljava/lang/Object;
      48: checkcast     #18                 // class java/lang/String
      51: astore        5
      53: aload_1
      54: aload         5
      56: aload         4
      58: invokeinterface #19,  1           // InterfaceMethod java/util/Map$Entry.getValue:()Ljava/lang/Object;
      63: checkcast     #20                 // class org/springframework/boot/actuate/health/HealthIndicator
      66: invokeinterface #21,  3           // InterfaceMethod org/springframework/boot/actuate/health/HealthIndicatorRegistry.register:(Ljava/lang/String;Lorg/springframework/boot/actuate/health/HealthIndicator;)V
      71: goto          12
      74: aload_1
      75: areturn
}
