Compiled from "SourceConfigUtils.java"
public class org.apache.pulsar.functions.utils.SourceConfigUtils {
  private static final org.slf4j.Logger log;

  public org.apache.pulsar.functions.utils.SourceConfigUtils();
    Code:
       0: aload_0
       1: invokespecial #1                  // Method java/lang/Object."<init>":()V
       4: return

  public static org.apache.pulsar.functions.proto.Function$FunctionDetails convert(org.apache.pulsar.common.io.SourceConfig, org.apache.pulsar.functions.utils.SourceConfigUtils$ExtractedSourceDetails) throws java.lang.IllegalArgumentException;
    Code:
       0: invokestatic  #2                  // Method org/apache/pulsar/functions/proto/Function$FunctionDetails.newBuilder:()Lorg/apache/pulsar/functions/proto/Function$FunctionDetails$Builder;
       3: astore_2
       4: aload_0
       5: invokevirtual #3                  // Method org/apache/pulsar/common/io/SourceConfig.getArchive:()Ljava/lang/String;
       8: invokestatic  #4                  // Method org/apache/commons/lang3/StringUtils.isEmpty:(Ljava/lang/CharSequence;)Z
      11: ifne          30
      14: aload_0
      15: invokevirtual #3                  // Method org/apache/pulsar/common/io/SourceConfig.getArchive:()Ljava/lang/String;
      18: ldc           #6                  // String builtin
      20: invokevirtual #7                  // Method java/lang/String.startsWith:(Ljava/lang/String;)Z
      23: ifeq          30
      26: iconst_1
      27: goto          31
      30: iconst_0
      31: istore_3
      32: aload_0
      33: invokevirtual #8                  // Method org/apache/pulsar/common/io/SourceConfig.getTenant:()Ljava/lang/String;
      36: ifnull        48
      39: aload_2
      40: aload_0
      41: invokevirtual #8                  // Method org/apache/pulsar/common/io/SourceConfig.getTenant:()Ljava/lang/String;
      44: invokevirtual #9                  // Method org/apache/pulsar/functions/proto/Function$FunctionDetails$Builder.setTenant:(Ljava/lang/String;)Lorg/apache/pulsar/functions/proto/Function$FunctionDetails$Builder;
      47: pop
      48: aload_0
      49: invokevirtual #10                 // Method org/apache/pulsar/common/io/SourceConfig.getNamespace:()Ljava/lang/String;
      52: ifnull        64
      55: aload_2
      56: aload_0
      57: invokevirtual #10                 // Method org/apache/pulsar/common/io/SourceConfig.getNamespace:()Ljava/lang/String;
      60: invokevirtual #11                 // Method org/apache/pulsar/functions/proto/Function$FunctionDetails$Builder.setNamespace:(Ljava/lang/String;)Lorg/apache/pulsar/functions/proto/Function$FunctionDetails$Builder;
      63: pop
      64: aload_0
      65: invokevirtual #12                 // Method org/apache/pulsar/common/io/SourceConfig.getName:()Ljava/lang/String;
      68: ifnull        80
      71: aload_2
      72: aload_0
      73: invokevirtual #12                 // Method org/apache/pulsar/common/io/SourceConfig.getName:()Ljava/lang/String;
      76: invokevirtual #13                 // Method org/apache/pulsar/functions/proto/Function$FunctionDetails$Builder.setName:(Ljava/lang/String;)Lorg/apache/pulsar/functions/proto/Function$FunctionDetails$Builder;
      79: pop
      80: aload_2
      81: getstatic     #14                 // Field org/apache/pulsar/functions/proto/Function$FunctionDetails$Runtime.JAVA:Lorg/apache/pulsar/functions/proto/Function$FunctionDetails$Runtime;
      84: invokevirtual #15                 // Method org/apache/pulsar/functions/proto/Function$FunctionDetails$Builder.setRuntime:(Lorg/apache/pulsar/functions/proto/Function$FunctionDetails$Runtime;)Lorg/apache/pulsar/functions/proto/Function$FunctionDetails$Builder;
      87: pop
      88: aload_0
      89: invokevirtual #16                 // Method org/apache/pulsar/common/io/SourceConfig.getParallelism:()Ljava/lang/Integer;
      92: ifnull        110
      95: aload_2
      96: aload_0
      97: invokevirtual #16                 // Method org/apache/pulsar/common/io/SourceConfig.getParallelism:()Ljava/lang/Integer;
     100: invokevirtual #17                 // Method java/lang/Integer.intValue:()I
     103: invokevirtual #18                 // Method org/apache/pulsar/functions/proto/Function$FunctionDetails$Builder.setParallelism:(I)Lorg/apache/pulsar/functions/proto/Function$FunctionDetails$Builder;
     106: pop
     107: goto          116
     110: aload_2
     111: iconst_1
     112: invokevirtual #18                 // Method org/apache/pulsar/functions/proto/Function$FunctionDetails$Builder.setParallelism:(I)Lorg/apache/pulsar/functions/proto/Function$FunctionDetails$Builder;
     115: pop
     116: aload_2
     117: ldc           #19                 // class org/apache/pulsar/functions/api/utils/IdentityFunction
     119: invokevirtual #20                 // Method java/lang/Class.getName:()Ljava/lang/String;
     122: invokevirtual #21                 // Method org/apache/pulsar/functions/proto/Function$FunctionDetails$Builder.setClassName:(Ljava/lang/String;)Lorg/apache/pulsar/functions/proto/Function$FunctionDetails$Builder;
     125: pop
     126: aload_2
     127: iconst_1
     128: invokevirtual #22                 // Method org/apache/pulsar/functions/proto/Function$FunctionDetails$Builder.setAutoAck:(Z)Lorg/apache/pulsar/functions/proto/Function$FunctionDetails$Builder;
     131: pop
     132: aload_0
     133: invokevirtual #23                 // Method org/apache/pulsar/common/io/SourceConfig.getProcessingGuarantees:()Lorg/apache/pulsar/common/functions/FunctionConfig$ProcessingGuarantees;
     136: ifnull        151
     139: aload_2
     140: aload_0
     141: invokevirtual #23                 // Method org/apache/pulsar/common/io/SourceConfig.getProcessingGuarantees:()Lorg/apache/pulsar/common/functions/FunctionConfig$ProcessingGuarantees;
     144: invokestatic  #24                 // Method org/apache/pulsar/functions/utils/FunctionCommon.convertProcessingGuarantee:(Lorg/apache/pulsar/common/functions/FunctionConfig$ProcessingGuarantees;)Lorg/apache/pulsar/functions/proto/Function$ProcessingGuarantees;
     147: invokevirtual #25                 // Method org/apache/pulsar/functions/proto/Function$FunctionDetails$Builder.setProcessingGuarantees:(Lorg/apache/pulsar/functions/proto/Function$ProcessingGuarantees;)Lorg/apache/pulsar/functions/proto/Function$FunctionDetails$Builder;
     150: pop
     151: invokestatic  #26                 // Method org/apache/pulsar/functions/proto/Function$SourceSpec.newBuilder:()Lorg/apache/pulsar/functions/proto/Function$SourceSpec$Builder;
     154: astore        4
     156: aload_1
     157: invokevirtual #27                 // Method org/apache/pulsar/functions/utils/SourceConfigUtils$ExtractedSourceDetails.getSourceClassName:()Ljava/lang/String;
     160: ifnull        173
     163: aload         4
     165: aload_1
     166: invokevirtual #27                 // Method org/apache/pulsar/functions/utils/SourceConfigUtils$ExtractedSourceDetails.getSourceClassName:()Ljava/lang/String;
     169: invokevirtual #28                 // Method org/apache/pulsar/functions/proto/Function$SourceSpec$Builder.setClassName:(Ljava/lang/String;)Lorg/apache/pulsar/functions/proto/Function$SourceSpec$Builder;
     172: pop
     173: iload_3
     174: ifeq          198
     177: aload_0
     178: invokevirtual #3                  // Method org/apache/pulsar/common/io/SourceConfig.getArchive:()Ljava/lang/String;
     181: ldc           #29                 // String ^builtin://
     183: ldc           #30                 // String
     185: invokevirtual #31                 // Method java/lang/String.replaceFirst:(Ljava/lang/String;Ljava/lang/String;)Ljava/lang/String;
     188: astore        5
     190: aload         4
     192: aload         5
     194: invokevirtual #32                 // Method org/apache/pulsar/functions/proto/Function$SourceSpec$Builder.setBuiltin:(Ljava/lang/String;)Lorg/apache/pulsar/functions/proto/Function$SourceSpec$Builder;
     197: pop
     198: new           #33                 // class java/util/HashMap
     201: dup
     202: invokespecial #34                 // Method java/util/HashMap."<init>":()V
     205: astore        5
     207: aload_0
     208: invokevirtual #35                 // Method org/apache/pulsar/common/io/SourceConfig.getConfigs:()Ljava/util/Map;
     211: ifnull        225
     214: aload         5
     216: aload_0
     217: invokevirtual #35                 // Method org/apache/pulsar/common/io/SourceConfig.getConfigs:()Ljava/util/Map;
     220: invokeinterface #36,  2           // InterfaceMethod java/util/Map.putAll:(Ljava/util/Map;)V
     225: aload_0
     226: invokevirtual #37                 // Method org/apache/pulsar/common/io/SourceConfig.getBatchSourceConfig:()Lorg/apache/pulsar/common/io/BatchSourceConfig;
     229: ifnull        279
     232: aload         5
     234: ldc           #39                 // String __BATCHSOURCECONFIGS__
     236: new           #40                 // class com/google/gson/Gson
     239: dup
     240: invokespecial #41                 // Method com/google/gson/Gson."<init>":()V
     243: aload_0
     244: invokevirtual #37                 // Method org/apache/pulsar/common/io/SourceConfig.getBatchSourceConfig:()Lorg/apache/pulsar/common/io/BatchSourceConfig;
     247: invokevirtual #42                 // Method com/google/gson/Gson.toJson:(Ljava/lang/Object;)Ljava/lang/String;
     250: invokeinterface #43,  3           // InterfaceMethod java/util/Map.put:(Ljava/lang/Object;Ljava/lang/Object;)Ljava/lang/Object;
     255: pop
     256: aload         5
     258: ldc           #44                 // String __BATCHSOURCECLASSNAME__
     260: aload         4
     262: invokevirtual #45                 // Method org/apache/pulsar/functions/proto/Function$SourceSpec$Builder.getClassName:()Ljava/lang/String;
     265: invokeinterface #43,  3           // InterfaceMethod java/util/Map.put:(Ljava/lang/Object;Ljava/lang/Object;)Ljava/lang/Object;
     270: pop
     271: aload         4
     273: ldc           #46                 // String org.apache.pulsar.functions.source.batch.BatchSourceExecutor
     275: invokevirtual #28                 // Method org/apache/pulsar/functions/proto/Function$SourceSpec$Builder.setClassName:(Ljava/lang/String;)Lorg/apache/pulsar/functions/proto/Function$SourceSpec$Builder;
     278: pop
     279: aload         4
     281: new           #40                 // class com/google/gson/Gson
     284: dup
     285: invokespecial #41                 // Method com/google/gson/Gson."<init>":()V
     288: aload         5
     290: invokevirtual #42                 // Method com/google/gson/Gson.toJson:(Ljava/lang/Object;)Ljava/lang/String;
     293: invokevirtual #47                 // Method org/apache/pulsar/functions/proto/Function$SourceSpec$Builder.setConfigs:(Ljava/lang/String;)Lorg/apache/pulsar/functions/proto/Function$SourceSpec$Builder;
     296: pop
     297: aload_0
     298: invokevirtual #48                 // Method org/apache/pulsar/common/io/SourceConfig.getSecrets:()Ljava/util/Map;
     301: ifnull        335
     304: aload_0
     305: invokevirtual #48                 // Method org/apache/pulsar/common/io/SourceConfig.getSecrets:()Ljava/util/Map;
     308: invokeinterface #49,  1           // InterfaceMethod java/util/Map.isEmpty:()Z
     313: ifne          335
     316: aload_2
     317: new           #40                 // class com/google/gson/Gson
     320: dup
     321: invokespecial #41                 // Method com/google/gson/Gson."<init>":()V
     324: aload_0
     325: invokevirtual #48                 // Method org/apache/pulsar/common/io/SourceConfig.getSecrets:()Ljava/util/Map;
     328: invokevirtual #42                 // Method com/google/gson/Gson.toJson:(Ljava/lang/Object;)Ljava/lang/String;
     331: invokevirtual #50                 // Method org/apache/pulsar/functions/proto/Function$FunctionDetails$Builder.setSecretsMap:(Ljava/lang/String;)Lorg/apache/pulsar/functions/proto/Function$FunctionDetails$Builder;
     334: pop
     335: aload_1
     336: invokevirtual #51                 // Method org/apache/pulsar/functions/utils/SourceConfigUtils$ExtractedSourceDetails.getTypeArg:()Ljava/lang/String;
     339: ifnull        352
     342: aload         4
     344: aload_1
     345: invokevirtual #51                 // Method org/apache/pulsar/functions/utils/SourceConfigUtils$ExtractedSourceDetails.getTypeArg:()Ljava/lang/String;
     348: invokevirtual #52                 // Method org/apache/pulsar/functions/proto/Function$SourceSpec$Builder.setTypeClassName:(Ljava/lang/String;)Lorg/apache/pulsar/functions/proto/Function$SourceSpec$Builder;
     351: pop
     352: aload_2
     353: aload         4
     355: invokevirtual #53                 // Method org/apache/pulsar/functions/proto/Function$FunctionDetails$Builder.setSource:(Lorg/apache/pulsar/functions/proto/Function$SourceSpec$Builder;)Lorg/apache/pulsar/functions/proto/Function$FunctionDetails$Builder;
     358: pop
     359: invokestatic  #54                 // Method org/apache/pulsar/functions/proto/Function$SinkSpec.newBuilder:()Lorg/apache/pulsar/functions/proto/Function$SinkSpec$Builder;
     362: astore        6
     364: aload_0
     365: invokevirtual #55                 // Method org/apache/pulsar/common/io/SourceConfig.getSchemaType:()Ljava/lang/String;
     368: invokestatic  #4                  // Method org/apache/commons/lang3/StringUtils.isEmpty:(Ljava/lang/CharSequence;)Z
     371: ifne          384
     374: aload         6
     376: aload_0
     377: invokevirtual #55                 // Method org/apache/pulsar/common/io/SourceConfig.getSchemaType:()Ljava/lang/String;
     380: invokevirtual #56                 // Method org/apache/pulsar/functions/proto/Function$SinkSpec$Builder.setSchemaType:(Ljava/lang/String;)Lorg/apache/pulsar/functions/proto/Function$SinkSpec$Builder;
     383: pop
     384: aload_0
     385: invokevirtual #57                 // Method org/apache/pulsar/common/io/SourceConfig.getSerdeClassName:()Ljava/lang/String;
     388: invokestatic  #4                  // Method org/apache/commons/lang3/StringUtils.isEmpty:(Ljava/lang/CharSequence;)Z
     391: ifne          404
     394: aload         6
     396: aload_0
     397: invokevirtual #57                 // Method org/apache/pulsar/common/io/SourceConfig.getSerdeClassName:()Ljava/lang/String;
     400: invokevirtual #58                 // Method org/apache/pulsar/functions/proto/Function$SinkSpec$Builder.setSerDeClassName:(Ljava/lang/String;)Lorg/apache/pulsar/functions/proto/Function$SinkSpec$Builder;
     403: pop
     404: aload         6
     406: aload_0
     407: invokevirtual #59                 // Method org/apache/pulsar/common/io/SourceConfig.getTopicName:()Ljava/lang/String;
     410: invokevirtual #60                 // Method org/apache/pulsar/functions/proto/Function$SinkSpec$Builder.setTopic:(Ljava/lang/String;)Lorg/apache/pulsar/functions/proto/Function$SinkSpec$Builder;
     413: pop
     414: aload_1
     415: invokevirtual #51                 // Method org/apache/pulsar/functions/utils/SourceConfigUtils$ExtractedSourceDetails.getTypeArg:()Ljava/lang/String;
     418: ifnull        431
     421: aload         6
     423: aload_1
     424: invokevirtual #51                 // Method org/apache/pulsar/functions/utils/SourceConfigUtils$ExtractedSourceDetails.getTypeArg:()Ljava/lang/String;
     427: invokevirtual #61                 // Method org/apache/pulsar/functions/proto/Function$SinkSpec$Builder.setTypeClassName:(Ljava/lang/String;)Lorg/apache/pulsar/functions/proto/Function$SinkSpec$Builder;
     430: pop
     431: aload_0
     432: invokevirtual #62                 // Method org/apache/pulsar/common/io/SourceConfig.getProducerConfig:()Lorg/apache/pulsar/common/functions/ProducerConfig;
     435: ifnull        567
     438: aload_0
     439: invokevirtual #62                 // Method org/apache/pulsar/common/io/SourceConfig.getProducerConfig:()Lorg/apache/pulsar/common/functions/ProducerConfig;
     442: astore        7
     444: invokestatic  #63                 // Method org/apache/pulsar/functions/proto/Function$ProducerSpec.newBuilder:()Lorg/apache/pulsar/functions/proto/Function$ProducerSpec$Builder;
     447: astore        8
     449: aload         7
     451: invokevirtual #64                 // Method org/apache/pulsar/common/functions/ProducerConfig.getMaxPendingMessages:()Ljava/lang/Integer;
     454: ifnull        471
     457: aload         8
     459: aload         7
     461: invokevirtual #64                 // Method org/apache/pulsar/common/functions/ProducerConfig.getMaxPendingMessages:()Ljava/lang/Integer;
     464: invokevirtual #17                 // Method java/lang/Integer.intValue:()I
     467: invokevirtual #65                 // Method org/apache/pulsar/functions/proto/Function$ProducerSpec$Builder.setMaxPendingMessages:(I)Lorg/apache/pulsar/functions/proto/Function$ProducerSpec$Builder;
     470: pop
     471: aload         7
     473: invokevirtual #66                 // Method org/apache/pulsar/common/functions/ProducerConfig.getMaxPendingMessagesAcrossPartitions:()Ljava/lang/Integer;
     476: ifnull        493
     479: aload         8
     481: aload         7
     483: invokevirtual #66                 // Method org/apache/pulsar/common/functions/ProducerConfig.getMaxPendingMessagesAcrossPartitions:()Ljava/lang/Integer;
     486: invokevirtual #17                 // Method java/lang/Integer.intValue:()I
     489: invokevirtual #67                 // Method org/apache/pulsar/functions/proto/Function$ProducerSpec$Builder.setMaxPendingMessagesAcrossPartitions:(I)Lorg/apache/pulsar/functions/proto/Function$ProducerSpec$Builder;
     492: pop
     493: aload         7
     495: invokevirtual #68                 // Method org/apache/pulsar/common/functions/ProducerConfig.getUseThreadLocalProducers:()Ljava/lang/Boolean;
     498: ifnull        515
     501: aload         8
     503: aload         7
     505: invokevirtual #68                 // Method org/apache/pulsar/common/functions/ProducerConfig.getUseThreadLocalProducers:()Ljava/lang/Boolean;
     508: invokevirtual #69                 // Method java/lang/Boolean.booleanValue:()Z
     511: invokevirtual #70                 // Method org/apache/pulsar/functions/proto/Function$ProducerSpec$Builder.setUseThreadLocalProducers:(Z)Lorg/apache/pulsar/functions/proto/Function$ProducerSpec$Builder;
     514: pop
     515: aload         7
     517: invokevirtual #71                 // Method org/apache/pulsar/common/functions/ProducerConfig.getCryptoConfig:()Lorg/apache/pulsar/common/functions/CryptoConfig;
     520: ifnull        537
     523: aload         8
     525: aload         7
     527: invokevirtual #71                 // Method org/apache/pulsar/common/functions/ProducerConfig.getCryptoConfig:()Lorg/apache/pulsar/common/functions/CryptoConfig;
     530: invokestatic  #72                 // Method org/apache/pulsar/functions/utils/CryptoUtils.convert:(Lorg/apache/pulsar/common/functions/CryptoConfig;)Lorg/apache/pulsar/functions/proto/Function$CryptoSpec;
     533: invokevirtual #73                 // Method org/apache/pulsar/functions/proto/Function$ProducerSpec$Builder.setCryptoSpec:(Lorg/apache/pulsar/functions/proto/Function$CryptoSpec;)Lorg/apache/pulsar/functions/proto/Function$ProducerSpec$Builder;
     536: pop
     537: aload         7
     539: invokevirtual #74                 // Method org/apache/pulsar/common/functions/ProducerConfig.getBatchBuilder:()Ljava/lang/String;
     542: ifnull        556
     545: aload         8
     547: aload         7
     549: invokevirtual #74                 // Method org/apache/pulsar/common/functions/ProducerConfig.getBatchBuilder:()Ljava/lang/String;
     552: invokevirtual #75                 // Method org/apache/pulsar/functions/proto/Function$ProducerSpec$Builder.setBatchBuilder:(Ljava/lang/String;)Lorg/apache/pulsar/functions/proto/Function$ProducerSpec$Builder;
     555: pop
     556: aload         6
     558: aload         8
     560: invokevirtual #76                 // Method org/apache/pulsar/functions/proto/Function$ProducerSpec$Builder.build:()Lorg/apache/pulsar/functions/proto/Function$ProducerSpec;
     563: invokevirtual #77                 // Method org/apache/pulsar/functions/proto/Function$SinkSpec$Builder.setProducerSpec:(Lorg/apache/pulsar/functions/proto/Function$ProducerSpec;)Lorg/apache/pulsar/functions/proto/Function$SinkSpec$Builder;
     566: pop
     567: aload_0
     568: invokevirtual #78                 // Method org/apache/pulsar/common/io/SourceConfig.getBatchBuilder:()Ljava/lang/String;
     571: ifnull        616
     574: aload         6
     576: invokevirtual #79                 // Method org/apache/pulsar/functions/proto/Function$SinkSpec$Builder.getProducerSpec:()Lorg/apache/pulsar/functions/proto/Function$ProducerSpec;
     579: ifnull        593
     582: aload         6
     584: invokevirtual #79                 // Method org/apache/pulsar/functions/proto/Function$SinkSpec$Builder.getProducerSpec:()Lorg/apache/pulsar/functions/proto/Function$ProducerSpec;
     587: invokevirtual #80                 // Method org/apache/pulsar/functions/proto/Function$ProducerSpec.toBuilder:()Lorg/apache/pulsar/functions/proto/Function$ProducerSpec$Builder;
     590: goto          596
     593: invokestatic  #63                 // Method org/apache/pulsar/functions/proto/Function$ProducerSpec.newBuilder:()Lorg/apache/pulsar/functions/proto/Function$ProducerSpec$Builder;
     596: astore        7
     598: aload         6
     600: aload         7
     602: aload_0
     603: invokevirtual #78                 // Method org/apache/pulsar/common/io/SourceConfig.getBatchBuilder:()Ljava/lang/String;
     606: invokevirtual #75                 // Method org/apache/pulsar/functions/proto/Function$ProducerSpec$Builder.setBatchBuilder:(Ljava/lang/String;)Lorg/apache/pulsar/functions/proto/Function$ProducerSpec$Builder;
     609: invokevirtual #76                 // Method org/apache/pulsar/functions/proto/Function$ProducerSpec$Builder.build:()Lorg/apache/pulsar/functions/proto/Function$ProducerSpec;
     612: invokevirtual #77                 // Method org/apache/pulsar/functions/proto/Function$SinkSpec$Builder.setProducerSpec:(Lorg/apache/pulsar/functions/proto/Function$ProducerSpec;)Lorg/apache/pulsar/functions/proto/Function$SinkSpec$Builder;
     615: pop
     616: aload         6
     618: iconst_1
     619: invokevirtual #81                 // Method org/apache/pulsar/functions/proto/Function$SinkSpec$Builder.setForwardSourceMessageProperty:(Z)Lorg/apache/pulsar/functions/proto/Function$SinkSpec$Builder;
     622: pop
     623: aload_2
     624: aload         6
     626: invokevirtual #82                 // Method org/apache/pulsar/functions/proto/Function$FunctionDetails$Builder.setSink:(Lorg/apache/pulsar/functions/proto/Function$SinkSpec$Builder;)Lorg/apache/pulsar/functions/proto/Function$FunctionDetails$Builder;
     629: pop
     630: aload_0
     631: invokevirtual #83                 // Method org/apache/pulsar/common/io/SourceConfig.getResources:()Lorg/apache/pulsar/common/functions/Resources;
     634: invokestatic  #84                 // Method org/apache/pulsar/common/functions/Resources.mergeWithDefault:(Lorg/apache/pulsar/common/functions/Resources;)Lorg/apache/pulsar/common/functions/Resources;
     637: astore        7
     639: invokestatic  #85                 // Method org/apache/pulsar/functions/proto/Function$Resources.newBuilder:()Lorg/apache/pulsar/functions/proto/Function$Resources$Builder;
     642: astore        8
     644: aload         8
     646: aload         7
     648: invokevirtual #86                 // Method org/apache/pulsar/common/functions/Resources.getCpu:()Ljava/lang/Double;
     651: invokevirtual #87                 // Method java/lang/Double.doubleValue:()D
     654: invokevirtual #88                 // Method org/apache/pulsar/functions/proto/Function$Resources$Builder.setCpu:(D)Lorg/apache/pulsar/functions/proto/Function$Resources$Builder;
     657: pop
     658: aload         8
     660: aload         7
     662: invokevirtual #89                 // Method org/apache/pulsar/common/functions/Resources.getRam:()Ljava/lang/Long;
     665: invokevirtual #90                 // Method java/lang/Long.longValue:()J
     668: invokevirtual #91                 // Method org/apache/pulsar/functions/proto/Function$Resources$Builder.setRam:(J)Lorg/apache/pulsar/functions/proto/Function$Resources$Builder;
     671: pop
     672: aload         8
     674: aload         7
     676: invokevirtual #92                 // Method org/apache/pulsar/common/functions/Resources.getDisk:()Ljava/lang/Long;
     679: invokevirtual #90                 // Method java/lang/Long.longValue:()J
     682: invokevirtual #93                 // Method org/apache/pulsar/functions/proto/Function$Resources$Builder.setDisk:(J)Lorg/apache/pulsar/functions/proto/Function$Resources$Builder;
     685: pop
     686: aload_2
     687: aload         8
     689: invokevirtual #94                 // Method org/apache/pulsar/functions/proto/Function$FunctionDetails$Builder.setResources:(Lorg/apache/pulsar/functions/proto/Function$Resources$Builder;)Lorg/apache/pulsar/functions/proto/Function$FunctionDetails$Builder;
     692: pop
     693: aload_0
     694: invokevirtual #95                 // Method org/apache/pulsar/common/io/SourceConfig.getRuntimeFlags:()Ljava/lang/String;
     697: invokestatic  #4                  // Method org/apache/commons/lang3/StringUtils.isEmpty:(Ljava/lang/CharSequence;)Z
     700: ifne          712
     703: aload_2
     704: aload_0
     705: invokevirtual #95                 // Method org/apache/pulsar/common/io/SourceConfig.getRuntimeFlags:()Ljava/lang/String;
     708: invokevirtual #96                 // Method org/apache/pulsar/functions/proto/Function$FunctionDetails$Builder.setRuntimeFlags:(Ljava/lang/String;)Lorg/apache/pulsar/functions/proto/Function$FunctionDetails$Builder;
     711: pop
     712: aload_2
     713: getstatic     #97                 // Field org/apache/pulsar/functions/proto/Function$FunctionDetails$ComponentType.SOURCE:Lorg/apache/pulsar/functions/proto/Function$FunctionDetails$ComponentType;
     716: invokevirtual #98                 // Method org/apache/pulsar/functions/proto/Function$FunctionDetails$Builder.setComponentType:(Lorg/apache/pulsar/functions/proto/Function$FunctionDetails$ComponentType;)Lorg/apache/pulsar/functions/proto/Function$FunctionDetails$Builder;
     719: pop
     720: aload_0
     721: invokevirtual #99                 // Method org/apache/pulsar/common/io/SourceConfig.getCustomRuntimeOptions:()Ljava/lang/String;
     724: invokestatic  #4                  // Method org/apache/commons/lang3/StringUtils.isEmpty:(Ljava/lang/CharSequence;)Z
     727: ifne          739
     730: aload_2
     731: aload_0
     732: invokevirtual #99                 // Method org/apache/pulsar/common/io/SourceConfig.getCustomRuntimeOptions:()Ljava/lang/String;
     735: invokevirtual #100                // Method org/apache/pulsar/functions/proto/Function$FunctionDetails$Builder.setCustomRuntimeOptions:(Ljava/lang/String;)Lorg/apache/pulsar/functions/proto/Function$FunctionDetails$Builder;
     738: pop
     739: aload_2
     740: invokevirtual #101                // Method org/apache/pulsar/functions/proto/Function$FunctionDetails$Builder.build:()Lorg/apache/pulsar/functions/proto/Function$FunctionDetails;
     743: areturn

  public static org.apache.pulsar.common.io.SourceConfig convertFromDetails(org.apache.pulsar.functions.proto.Function$FunctionDetails);
    Code:
       0: new           #355                // class org/apache/pulsar/common/io/SourceConfig
       3: dup
       4: invokespecial #103                // Method org/apache/pulsar/common/io/SourceConfig."<init>":()V
       7: astore_1
       8: aload_1
       9: aload_0
      10: invokevirtual #104                // Method org/apache/pulsar/functions/proto/Function$FunctionDetails.getTenant:()Ljava/lang/String;
      13: invokevirtual #105                // Method org/apache/pulsar/common/io/SourceConfig.setTenant:(Ljava/lang/String;)V
      16: aload_1
      17: aload_0
      18: invokevirtual #106                // Method org/apache/pulsar/functions/proto/Function$FunctionDetails.getNamespace:()Ljava/lang/String;
      21: invokevirtual #107                // Method org/apache/pulsar/common/io/SourceConfig.setNamespace:(Ljava/lang/String;)V
      24: aload_1
      25: aload_0
      26: invokevirtual #108                // Method org/apache/pulsar/functions/proto/Function$FunctionDetails.getName:()Ljava/lang/String;
      29: invokevirtual #109                // Method org/apache/pulsar/common/io/SourceConfig.setName:(Ljava/lang/String;)V
      32: aload_1
      33: aload_0
      34: invokevirtual #110                // Method org/apache/pulsar/functions/proto/Function$FunctionDetails.getParallelism:()I
      37: invokestatic  #111                // Method java/lang/Integer.valueOf:(I)Ljava/lang/Integer;
      40: invokevirtual #112                // Method org/apache/pulsar/common/io/SourceConfig.setParallelism:(Ljava/lang/Integer;)V
      43: aload_1
      44: aload_0
      45: invokevirtual #113                // Method org/apache/pulsar/functions/proto/Function$FunctionDetails.getProcessingGuarantees:()Lorg/apache/pulsar/functions/proto/Function$ProcessingGuarantees;
      48: invokestatic  #114                // Method org/apache/pulsar/functions/utils/FunctionCommon.convertProcessingGuarantee:(Lorg/apache/pulsar/functions/proto/Function$ProcessingGuarantees;)Lorg/apache/pulsar/common/functions/FunctionConfig$ProcessingGuarantees;
      51: invokevirtual #115                // Method org/apache/pulsar/common/io/SourceConfig.setProcessingGuarantees:(Lorg/apache/pulsar/common/functions/FunctionConfig$ProcessingGuarantees;)V
      54: aload_0
      55: invokevirtual #116                // Method org/apache/pulsar/functions/proto/Function$FunctionDetails.getSource:()Lorg/apache/pulsar/functions/proto/Function$SourceSpec;
      58: astore_2
      59: aload_2
      60: invokevirtual #117                // Method org/apache/pulsar/functions/proto/Function$SourceSpec.getClassName:()Ljava/lang/String;
      63: invokestatic  #4                  // Method org/apache/commons/lang3/StringUtils.isEmpty:(Ljava/lang/CharSequence;)Z
      66: ifne          77
      69: aload_1
      70: aload_2
      71: invokevirtual #117                // Method org/apache/pulsar/functions/proto/Function$SourceSpec.getClassName:()Ljava/lang/String;
      74: invokevirtual #118                // Method org/apache/pulsar/common/io/SourceConfig.setClassName:(Ljava/lang/String;)V
      77: aload_2
      78: invokevirtual #119                // Method org/apache/pulsar/functions/proto/Function$SourceSpec.getBuiltin:()Ljava/lang/String;
      81: invokestatic  #4                  // Method org/apache/commons/lang3/StringUtils.isEmpty:(Ljava/lang/CharSequence;)Z
      84: ifne          113
      87: aload_1
      88: new           #120                // class java/lang/StringBuilder
      91: dup
      92: invokespecial #121                // Method java/lang/StringBuilder."<init>":()V
      95: ldc           #122                // String builtin://
      97: invokevirtual #123                // Method java/lang/StringBuilder.append:(Ljava/lang/String;)Ljava/lang/StringBuilder;
     100: aload_2
     101: invokevirtual #119                // Method org/apache/pulsar/functions/proto/Function$SourceSpec.getBuiltin:()Ljava/lang/String;
     104: invokevirtual #123                // Method java/lang/StringBuilder.append:(Ljava/lang/String;)Ljava/lang/StringBuilder;
     107: invokevirtual #124                // Method java/lang/StringBuilder.toString:()Ljava/lang/String;
     110: invokevirtual #125                // Method org/apache/pulsar/common/io/SourceConfig.setArchive:(Ljava/lang/String;)V
     113: aload_2
     114: aload_0
     115: invokestatic  #126                // Method org/apache/pulsar/functions/utils/FunctionCommon.getFullyQualifiedName:(Lorg/apache/pulsar/functions/proto/Function$FunctionDetails;)Ljava/lang/String;
     118: invokestatic  #127                // Method extractSourceConfig:(Lorg/apache/pulsar/functions/proto/Function$SourceSpec;Ljava/lang/String;)Ljava/util/Map;
     121: astore_3
     122: aload_3
     123: ifnull        217
     126: aload_3
     127: invokestatic  #128                // Method extractBatchSourceConfig:(Ljava/util/Map;)Lorg/apache/pulsar/common/io/BatchSourceConfig;
     130: astore        4
     132: aload         4
     134: ifnull        194
     137: aload_1
     138: aload         4
     140: invokevirtual #129                // Method org/apache/pulsar/common/io/SourceConfig.setBatchSourceConfig:(Lorg/apache/pulsar/common/io/BatchSourceConfig;)V
     143: aload_3
     144: ldc           #44                 // String __BATCHSOURCECLASSNAME__
     146: invokeinterface #130,  2          // InterfaceMethod java/util/Map.containsKey:(Ljava/lang/Object;)Z
     151: ifeq          194
     154: aload_3
     155: ldc           #44                 // String __BATCHSOURCECLASSNAME__
     157: invokeinterface #131,  2          // InterfaceMethod java/util/Map.get:(Ljava/lang/Object;)Ljava/lang/Object;
     162: checkcast     #374                // class java/lang/String
     165: invokestatic  #4                  // Method org/apache/commons/lang3/StringUtils.isEmpty:(Ljava/lang/CharSequence;)Z
     168: ifne          189
     171: aload_1
     172: aload_3
     173: ldc           #44                 // String __BATCHSOURCECLASSNAME__
     175: invokeinterface #131,  2          // InterfaceMethod java/util/Map.get:(Ljava/lang/Object;)Ljava/lang/Object;
     180: checkcast     #374                // class java/lang/String
     183: invokevirtual #118                // Method org/apache/pulsar/common/io/SourceConfig.setClassName:(Ljava/lang/String;)V
     186: goto          194
     189: aload_1
     190: aconst_null
     191: invokevirtual #118                // Method org/apache/pulsar/common/io/SourceConfig.setClassName:(Ljava/lang/String;)V
     194: aload_3
     195: ldc           #39                 // String __BATCHSOURCECONFIGS__
     197: invokeinterface #133,  2          // InterfaceMethod java/util/Map.remove:(Ljava/lang/Object;)Ljava/lang/Object;
     202: pop
     203: aload_3
     204: ldc           #44                 // String __BATCHSOURCECLASSNAME__
     206: invokeinterface #133,  2          // InterfaceMethod java/util/Map.remove:(Ljava/lang/Object;)Ljava/lang/Object;
     211: pop
     212: aload_1
     213: aload_3
     214: invokevirtual #134                // Method org/apache/pulsar/common/io/SourceConfig.setConfigs:(Ljava/util/Map;)V
     217: aload_0
     218: invokevirtual #135                // Method org/apache/pulsar/functions/proto/Function$FunctionDetails.getSecretsMap:()Ljava/lang/String;
     221: invokestatic  #4                  // Method org/apache/commons/lang3/StringUtils.isEmpty:(Ljava/lang/CharSequence;)Z
     224: ifne          266
     227: new           #136                // class org/apache/pulsar/functions/utils/SourceConfigUtils$1
     230: dup
     231: invokespecial #137                // Method org/apache/pulsar/functions/utils/SourceConfigUtils$1."<init>":()V
     234: invokevirtual #138                // Method org/apache/pulsar/functions/utils/SourceConfigUtils$1.getType:()Ljava/lang/reflect/Type;
     237: astore        4
     239: new           #40                 // class com/google/gson/Gson
     242: dup
     243: invokespecial #41                 // Method com/google/gson/Gson."<init>":()V
     246: aload_0
     247: invokevirtual #135                // Method org/apache/pulsar/functions/proto/Function$FunctionDetails.getSecretsMap:()Ljava/lang/String;
     250: aload         4
     252: invokevirtual #139                // Method com/google/gson/Gson.fromJson:(Ljava/lang/String;Ljava/lang/reflect/Type;)Ljava/lang/Object;
     255: checkcast     #330                // class java/util/Map
     258: astore        5
     260: aload_1
     261: aload         5
     263: invokevirtual #141                // Method org/apache/pulsar/common/io/SourceConfig.setSecrets:(Ljava/util/Map;)V
     266: aload_0
     267: invokevirtual #142                // Method org/apache/pulsar/functions/proto/Function$FunctionDetails.getSink:()Lorg/apache/pulsar/functions/proto/Function$SinkSpec;
     270: astore        4
     272: aload_1
     273: aload         4
     275: invokevirtual #143                // Method org/apache/pulsar/functions/proto/Function$SinkSpec.getTopic:()Ljava/lang/String;
     278: invokevirtual #144                // Method org/apache/pulsar/common/io/SourceConfig.setTopicName:(Ljava/lang/String;)V
     281: aload         4
     283: invokevirtual #145                // Method org/apache/pulsar/functions/proto/Function$SinkSpec.getSchemaType:()Ljava/lang/String;
     286: invokestatic  #4                  // Method org/apache/commons/lang3/StringUtils.isEmpty:(Ljava/lang/CharSequence;)Z
     289: ifne          301
     292: aload_1
     293: aload         4
     295: invokevirtual #145                // Method org/apache/pulsar/functions/proto/Function$SinkSpec.getSchemaType:()Ljava/lang/String;
     298: invokevirtual #146                // Method org/apache/pulsar/common/io/SourceConfig.setSchemaType:(Ljava/lang/String;)V
     301: aload         4
     303: invokevirtual #147                // Method org/apache/pulsar/functions/proto/Function$SinkSpec.getSerDeClassName:()Ljava/lang/String;
     306: invokestatic  #4                  // Method org/apache/commons/lang3/StringUtils.isEmpty:(Ljava/lang/CharSequence;)Z
     309: ifne          321
     312: aload_1
     313: aload         4
     315: invokevirtual #147                // Method org/apache/pulsar/functions/proto/Function$SinkSpec.getSerDeClassName:()Ljava/lang/String;
     318: invokevirtual #148                // Method org/apache/pulsar/common/io/SourceConfig.setSerdeClassName:(Ljava/lang/String;)V
     321: aload         4
     323: invokevirtual #149                // Method org/apache/pulsar/functions/proto/Function$SinkSpec.getProducerSpec:()Lorg/apache/pulsar/functions/proto/Function$ProducerSpec;
     326: ifnull        445
     329: aload         4
     331: invokevirtual #149                // Method org/apache/pulsar/functions/proto/Function$SinkSpec.getProducerSpec:()Lorg/apache/pulsar/functions/proto/Function$ProducerSpec;
     334: astore        5
     336: new           #332                // class org/apache/pulsar/common/functions/ProducerConfig
     339: dup
     340: invokespecial #151                // Method org/apache/pulsar/common/functions/ProducerConfig."<init>":()V
     343: astore        6
     345: aload         5
     347: invokevirtual #152                // Method org/apache/pulsar/functions/proto/Function$ProducerSpec.getMaxPendingMessages:()I
     350: ifeq          366
     353: aload         6
     355: aload         5
     357: invokevirtual #152                // Method org/apache/pulsar/functions/proto/Function$ProducerSpec.getMaxPendingMessages:()I
     360: invokestatic  #111                // Method java/lang/Integer.valueOf:(I)Ljava/lang/Integer;
     363: invokevirtual #153                // Method org/apache/pulsar/common/functions/ProducerConfig.setMaxPendingMessages:(Ljava/lang/Integer;)V
     366: aload         5
     368: invokevirtual #154                // Method org/apache/pulsar/functions/proto/Function$ProducerSpec.getMaxPendingMessagesAcrossPartitions:()I
     371: ifeq          387
     374: aload         6
     376: aload         5
     378: invokevirtual #154                // Method org/apache/pulsar/functions/proto/Function$ProducerSpec.getMaxPendingMessagesAcrossPartitions:()I
     381: invokestatic  #111                // Method java/lang/Integer.valueOf:(I)Ljava/lang/Integer;
     384: invokevirtual #155                // Method org/apache/pulsar/common/functions/ProducerConfig.setMaxPendingMessagesAcrossPartitions:(Ljava/lang/Integer;)V
     387: aload         5
     389: invokevirtual #156                // Method org/apache/pulsar/functions/proto/Function$ProducerSpec.hasCryptoSpec:()Z
     392: ifeq          408
     395: aload         6
     397: aload         5
     399: invokevirtual #157                // Method org/apache/pulsar/functions/proto/Function$ProducerSpec.getCryptoSpec:()Lorg/apache/pulsar/functions/proto/Function$CryptoSpec;
     402: invokestatic  #158                // Method org/apache/pulsar/functions/utils/CryptoUtils.convertFromSpec:(Lorg/apache/pulsar/functions/proto/Function$CryptoSpec;)Lorg/apache/pulsar/common/functions/CryptoConfig;
     405: invokevirtual #159                // Method org/apache/pulsar/common/functions/ProducerConfig.setCryptoConfig:(Lorg/apache/pulsar/common/functions/CryptoConfig;)V
     408: aload         5
     410: invokevirtual #160                // Method org/apache/pulsar/functions/proto/Function$ProducerSpec.getBatchBuilder:()Ljava/lang/String;
     413: ifnull        426
     416: aload         6
     418: aload         5
     420: invokevirtual #160                // Method org/apache/pulsar/functions/proto/Function$ProducerSpec.getBatchBuilder:()Ljava/lang/String;
     423: invokevirtual #161                // Method org/apache/pulsar/common/functions/ProducerConfig.setBatchBuilder:(Ljava/lang/String;)V
     426: aload         6
     428: aload         5
     430: invokevirtual #162                // Method org/apache/pulsar/functions/proto/Function$ProducerSpec.getUseThreadLocalProducers:()Z
     433: invokestatic  #163                // Method java/lang/Boolean.valueOf:(Z)Ljava/lang/Boolean;
     436: invokevirtual #164                // Method org/apache/pulsar/common/functions/ProducerConfig.setUseThreadLocalProducers:(Ljava/lang/Boolean;)V
     439: aload_1
     440: aload         6
     442: invokevirtual #165                // Method org/apache/pulsar/common/io/SourceConfig.setProducerConfig:(Lorg/apache/pulsar/common/functions/ProducerConfig;)V
     445: aload_0
     446: invokevirtual #166                // Method org/apache/pulsar/functions/proto/Function$FunctionDetails.hasResources:()Z
     449: ifeq          512
     452: new           #334                // class org/apache/pulsar/common/functions/Resources
     455: dup
     456: invokespecial #168                // Method org/apache/pulsar/common/functions/Resources."<init>":()V
     459: astore        5
     461: aload         5
     463: aload_0
     464: invokevirtual #169                // Method org/apache/pulsar/functions/proto/Function$FunctionDetails.getResources:()Lorg/apache/pulsar/functions/proto/Function$Resources;
     467: invokevirtual #170                // Method org/apache/pulsar/functions/proto/Function$Resources.getCpu:()D
     470: invokestatic  #171                // Method java/lang/Double.valueOf:(D)Ljava/lang/Double;
     473: invokevirtual #172                // Method org/apache/pulsar/common/functions/Resources.setCpu:(Ljava/lang/Double;)V
     476: aload         5
     478: aload_0
     479: invokevirtual #169                // Method org/apache/pulsar/functions/proto/Function$FunctionDetails.getResources:()Lorg/apache/pulsar/functions/proto/Function$Resources;
     482: invokevirtual #173                // Method org/apache/pulsar/functions/proto/Function$Resources.getRam:()J
     485: invokestatic  #174                // Method java/lang/Long.valueOf:(J)Ljava/lang/Long;
     488: invokevirtual #175                // Method org/apache/pulsar/common/functions/Resources.setRam:(Ljava/lang/Long;)V
     491: aload         5
     493: aload_0
     494: invokevirtual #169                // Method org/apache/pulsar/functions/proto/Function$FunctionDetails.getResources:()Lorg/apache/pulsar/functions/proto/Function$Resources;
     497: invokevirtual #176                // Method org/apache/pulsar/functions/proto/Function$Resources.getDisk:()J
     500: invokestatic  #174                // Method java/lang/Long.valueOf:(J)Ljava/lang/Long;
     503: invokevirtual #177                // Method org/apache/pulsar/common/functions/Resources.setDisk:(Ljava/lang/Long;)V
     506: aload_1
     507: aload         5
     509: invokevirtual #178                // Method org/apache/pulsar/common/io/SourceConfig.setResources:(Lorg/apache/pulsar/common/functions/Resources;)V
     512: aload_0
     513: invokevirtual #179                // Method org/apache/pulsar/functions/proto/Function$FunctionDetails.getRuntimeFlags:()Ljava/lang/String;
     516: invokestatic  #4                  // Method org/apache/commons/lang3/StringUtils.isEmpty:(Ljava/lang/CharSequence;)Z
     519: ifne          530
     522: aload_1
     523: aload_0
     524: invokevirtual #179                // Method org/apache/pulsar/functions/proto/Function$FunctionDetails.getRuntimeFlags:()Ljava/lang/String;
     527: invokevirtual #180                // Method org/apache/pulsar/common/io/SourceConfig.setRuntimeFlags:(Ljava/lang/String;)V
     530: aload_0
     531: invokevirtual #181                // Method org/apache/pulsar/functions/proto/Function$FunctionDetails.getCustomRuntimeOptions:()Ljava/lang/String;
     534: invokestatic  #4                  // Method org/apache/commons/lang3/StringUtils.isEmpty:(Ljava/lang/CharSequence;)Z
     537: ifne          548
     540: aload_1
     541: aload_0
     542: invokevirtual #181                // Method org/apache/pulsar/functions/proto/Function$FunctionDetails.getCustomRuntimeOptions:()Ljava/lang/String;
     545: invokevirtual #182                // Method org/apache/pulsar/common/io/SourceConfig.setCustomRuntimeOptions:(Ljava/lang/String;)V
     548: aload_1
     549: areturn

  public static org.apache.pulsar.functions.utils.SourceConfigUtils$ExtractedSourceDetails validateAndExtractDetails(org.apache.pulsar.common.io.SourceConfig, java.lang.ClassLoader, boolean);
    Code:
       0: aload_0
       1: invokevirtual #8                  // Method org/apache/pulsar/common/io/SourceConfig.getTenant:()Ljava/lang/String;
       4: invokestatic  #4                  // Method org/apache/commons/lang3/StringUtils.isEmpty:(Ljava/lang/CharSequence;)Z
       7: ifeq          20
      10: new           #431                // class java/lang/IllegalArgumentException
      13: dup
      14: ldc           #184                // String Source tenant cannot be null
      16: invokespecial #185                // Method java/lang/IllegalArgumentException."<init>":(Ljava/lang/String;)V
      19: athrow
      20: aload_0
      21: invokevirtual #10                 // Method org/apache/pulsar/common/io/SourceConfig.getNamespace:()Ljava/lang/String;
      24: invokestatic  #4                  // Method org/apache/commons/lang3/StringUtils.isEmpty:(Ljava/lang/CharSequence;)Z
      27: ifeq          40
      30: new           #431                // class java/lang/IllegalArgumentException
      33: dup
      34: ldc           #186                // String Source namespace cannot be null
      36: invokespecial #185                // Method java/lang/IllegalArgumentException."<init>":(Ljava/lang/String;)V
      39: athrow
      40: aload_0
      41: invokevirtual #12                 // Method org/apache/pulsar/common/io/SourceConfig.getName:()Ljava/lang/String;
      44: invokestatic  #4                  // Method org/apache/commons/lang3/StringUtils.isEmpty:(Ljava/lang/CharSequence;)Z
      47: ifeq          60
      50: new           #431                // class java/lang/IllegalArgumentException
      53: dup
      54: ldc           #187                // String Source name cannot be null
      56: invokespecial #185                // Method java/lang/IllegalArgumentException."<init>":(Ljava/lang/String;)V
      59: athrow
      60: aload_0
      61: invokevirtual #59                 // Method org/apache/pulsar/common/io/SourceConfig.getTopicName:()Ljava/lang/String;
      64: invokestatic  #4                  // Method org/apache/commons/lang3/StringUtils.isEmpty:(Ljava/lang/CharSequence;)Z
      67: ifeq          80
      70: new           #431                // class java/lang/IllegalArgumentException
      73: dup
      74: ldc           #188                // String Topic name cannot be null
      76: invokespecial #185                // Method java/lang/IllegalArgumentException."<init>":(Ljava/lang/String;)V
      79: athrow
      80: aload_0
      81: invokevirtual #59                 // Method org/apache/pulsar/common/io/SourceConfig.getTopicName:()Ljava/lang/String;
      84: invokestatic  #189                // Method org/apache/pulsar/common/naming/TopicName.isValid:(Ljava/lang/String;)Z
      87: ifne          100
      90: new           #431                // class java/lang/IllegalArgumentException
      93: dup
      94: ldc           #190                // String Topic name is invalid
      96: invokespecial #185                // Method java/lang/IllegalArgumentException."<init>":(Ljava/lang/String;)V
      99: athrow
     100: aload_0
     101: invokevirtual #16                 // Method org/apache/pulsar/common/io/SourceConfig.getParallelism:()Ljava/lang/Integer;
     104: ifnull        127
     107: aload_0
     108: invokevirtual #16                 // Method org/apache/pulsar/common/io/SourceConfig.getParallelism:()Ljava/lang/Integer;
     111: invokevirtual #17                 // Method java/lang/Integer.intValue:()I
     114: ifgt          127
     117: new           #431                // class java/lang/IllegalArgumentException
     120: dup
     121: ldc           #191                // String Source parallelism must be a positive number
     123: invokespecial #185                // Method java/lang/IllegalArgumentException."<init>":(Ljava/lang/String;)V
     126: athrow
     127: aload_0
     128: invokevirtual #83                 // Method org/apache/pulsar/common/io/SourceConfig.getResources:()Lorg/apache/pulsar/common/functions/Resources;
     131: ifnull        141
     134: aload_0
     135: invokevirtual #83                 // Method org/apache/pulsar/common/io/SourceConfig.getResources:()Lorg/apache/pulsar/common/functions/Resources;
     138: invokestatic  #192                // Method org/apache/pulsar/functions/utils/ResourceConfigUtils.validate:(Lorg/apache/pulsar/common/functions/Resources;)V
     141: aload_0
     142: invokevirtual #193                // Method org/apache/pulsar/common/io/SourceConfig.getClassName:()Ljava/lang/String;
     145: astore_3
     146: aload_3
     147: ifnonnull     175
     150: aload_1
     151: checkcast     #194                // class org/apache/pulsar/common/nar/NarClassLoader
     154: invokestatic  #195                // Method org/apache/pulsar/functions/utils/io/ConnectorUtils.getIOSourceClass:(Lorg/apache/pulsar/common/nar/NarClassLoader;)Ljava/lang/String;
     157: astore_3
     158: goto          175
     161: astore        4
     163: new           #431                // class java/lang/IllegalArgumentException
     166: dup
     167: ldc           #197                // String Failed to extract source class from archive
     169: aload         4
     171: invokespecial #198                // Method java/lang/IllegalArgumentException."<init>":(Ljava/lang/String;Ljava/lang/Throwable;)V
     174: athrow
     175: aload_1
     176: aload_3
     177: invokevirtual #199                // Method java/lang/ClassLoader.loadClass:(Ljava/lang/String;)Ljava/lang/Class;
     180: astore        4
     182: goto          210
     185: astore        5
     187: new           #431                // class java/lang/IllegalArgumentException
     190: dup
     191: ldc           #201                // String Source class %s not found in class loader
     193: iconst_1
     194: anewarray     #202                // class java/lang/Object
     197: dup
     198: iconst_0
     199: aload_3
     200: aastore
     201: invokestatic  #203                // Method java/lang/String.format:(Ljava/lang/String;[Ljava/lang/Object;)Ljava/lang/String;
     204: aload         5
     206: invokespecial #198                // Method java/lang/IllegalArgumentException."<init>":(Ljava/lang/String;Ljava/lang/Throwable;)V
     209: athrow
     210: ldc           #204                // class org/apache/pulsar/io/core/Source
     212: aload         4
     214: invokevirtual #205                // Method java/lang/Class.isAssignableFrom:(Ljava/lang/Class;)Z
     217: ifne          255
     220: ldc           #206                // class org/apache/pulsar/io/core/BatchSource
     222: aload         4
     224: invokevirtual #205                // Method java/lang/Class.isAssignableFrom:(Ljava/lang/Class;)Z
     227: ifne          255
     230: new           #431                // class java/lang/IllegalArgumentException
     233: dup
     234: ldc           #207                // String Source class %s does not implement the correct interface
     236: iconst_1
     237: anewarray     #202                // class java/lang/Object
     240: dup
     241: iconst_0
     242: aload         4
     244: invokevirtual #20                 // Method java/lang/Class.getName:()Ljava/lang/String;
     247: aastore
     248: invokestatic  #203                // Method java/lang/String.format:(Ljava/lang/String;[Ljava/lang/Object;)Ljava/lang/String;
     251: invokespecial #185                // Method java/lang/IllegalArgumentException."<init>":(Ljava/lang/String;)V
     254: athrow
     255: ldc           #206                // class org/apache/pulsar/io/core/BatchSource
     257: aload         4
     259: invokevirtual #205                // Method java/lang/Class.isAssignableFrom:(Ljava/lang/Class;)Z
     262: ifeq          315
     265: aload_0
     266: invokevirtual #37                 // Method org/apache/pulsar/common/io/SourceConfig.getBatchSourceConfig:()Lorg/apache/pulsar/common/io/BatchSourceConfig;
     269: ifnull        282
     272: aload_0
     273: invokevirtual #37                 // Method org/apache/pulsar/common/io/SourceConfig.getBatchSourceConfig:()Lorg/apache/pulsar/common/io/BatchSourceConfig;
     276: invokestatic  #208                // Method validateBatchSourceConfig:(Lorg/apache/pulsar/common/io/BatchSourceConfig;)V
     279: goto          315
     282: new           #431                // class java/lang/IllegalArgumentException
     285: dup
     286: ldc           #209                // String Source class %s implements %s but batch source source config is not specified
     288: iconst_2
     289: anewarray     #202                // class java/lang/Object
     292: dup
     293: iconst_0
     294: aload         4
     296: invokevirtual #20                 // Method java/lang/Class.getName:()Ljava/lang/String;
     299: aastore
     300: dup
     301: iconst_1
     302: ldc           #206                // class org/apache/pulsar/io/core/BatchSource
     304: invokevirtual #20                 // Method java/lang/Class.getName:()Ljava/lang/String;
     307: aastore
     308: invokestatic  #203                // Method java/lang/String.format:(Ljava/lang/String;[Ljava/lang/Object;)Ljava/lang/String;
     311: invokespecial #185                // Method java/lang/IllegalArgumentException."<init>":(Ljava/lang/String;)V
     314: athrow
     315: aload         4
     317: invokestatic  #210                // Method org/apache/pulsar/functions/utils/FunctionCommon.getSourceType:(Ljava/lang/Class;)Ljava/lang/Class;
     320: astore        5
     322: aload_0
     323: invokevirtual #57                 // Method org/apache/pulsar/common/io/SourceConfig.getSerdeClassName:()Ljava/lang/String;
     326: invokestatic  #4                  // Method org/apache/commons/lang3/StringUtils.isEmpty:(Ljava/lang/CharSequence;)Z
     329: ifne          352
     332: aload_0
     333: invokevirtual #55                 // Method org/apache/pulsar/common/io/SourceConfig.getSchemaType:()Ljava/lang/String;
     336: invokestatic  #4                  // Method org/apache/commons/lang3/StringUtils.isEmpty:(Ljava/lang/CharSequence;)Z
     339: ifne          352
     342: new           #431                // class java/lang/IllegalArgumentException
     345: dup
     346: ldc           #211                // String Only one of serdeClassName or schemaType should be set
     348: invokespecial #185                // Method java/lang/IllegalArgumentException."<init>":(Ljava/lang/String;)V
     351: athrow
     352: aload_0
     353: invokevirtual #57                 // Method org/apache/pulsar/common/io/SourceConfig.getSerdeClassName:()Ljava/lang/String;
     356: invokestatic  #4                  // Method org/apache/commons/lang3/StringUtils.isEmpty:(Ljava/lang/CharSequence;)Z
     359: ifne          373
     362: aload_0
     363: invokevirtual #57                 // Method org/apache/pulsar/common/io/SourceConfig.getSerdeClassName:()Ljava/lang/String;
     366: aload         5
     368: aload_1
     369: iconst_0
     370: invokestatic  #212                // Method org/apache/pulsar/functions/utils/ValidatorUtils.validateSerde:(Ljava/lang/String;Ljava/lang/Class;Ljava/lang/ClassLoader;Z)V
     373: aload_0
     374: invokevirtual #55                 // Method org/apache/pulsar/common/io/SourceConfig.getSchemaType:()Ljava/lang/String;
     377: invokestatic  #4                  // Method org/apache/commons/lang3/StringUtils.isEmpty:(Ljava/lang/CharSequence;)Z
     380: ifne          394
     383: aload_0
     384: invokevirtual #55                 // Method org/apache/pulsar/common/io/SourceConfig.getSchemaType:()Ljava/lang/String;
     387: aload         5
     389: aload_1
     390: iconst_0
     391: invokestatic  #213                // Method org/apache/pulsar/functions/utils/ValidatorUtils.validateSchema:(Ljava/lang/String;Ljava/lang/Class;Ljava/lang/ClassLoader;Z)V
     394: aload_0
     395: invokevirtual #62                 // Method org/apache/pulsar/common/io/SourceConfig.getProducerConfig:()Lorg/apache/pulsar/common/functions/ProducerConfig;
     398: ifnull        423
     401: aload_0
     402: invokevirtual #62                 // Method org/apache/pulsar/common/io/SourceConfig.getProducerConfig:()Lorg/apache/pulsar/common/functions/ProducerConfig;
     405: invokevirtual #71                 // Method org/apache/pulsar/common/functions/ProducerConfig.getCryptoConfig:()Lorg/apache/pulsar/common/functions/CryptoConfig;
     408: ifnull        423
     411: aload_0
     412: invokevirtual #62                 // Method org/apache/pulsar/common/io/SourceConfig.getProducerConfig:()Lorg/apache/pulsar/common/functions/ProducerConfig;
     415: invokevirtual #71                 // Method org/apache/pulsar/common/functions/ProducerConfig.getCryptoConfig:()Lorg/apache/pulsar/common/functions/CryptoConfig;
     418: aload_1
     419: iconst_1
     420: invokestatic  #214                // Method org/apache/pulsar/functions/utils/ValidatorUtils.validateCryptoKeyReader:(Lorg/apache/pulsar/common/functions/CryptoConfig;Ljava/lang/ClassLoader;Z)V
     423: aload         5
     425: ldc           #215                // class net/jodah/typetools/TypeResolver$Unknown
     427: invokevirtual #216                // Method java/lang/Object.equals:(Ljava/lang/Object;)Z
     430: ifeq          454
     433: new           #431                // class java/lang/IllegalArgumentException
     436: dup
     437: ldc           #217                // String Failed to resolve type for Source class %s
     439: iconst_1
     440: anewarray     #202                // class java/lang/Object
     443: dup
     444: iconst_0
     445: aload_3
     446: aastore
     447: invokestatic  #203                // Method java/lang/String.format:(Ljava/lang/String;[Ljava/lang/Object;)Ljava/lang/String;
     450: invokespecial #185                // Method java/lang/IllegalArgumentException."<init>":(Ljava/lang/String;)V
     453: athrow
     454: iload_2
     455: ifeq          473
     458: aload_1
     459: instanceof    #194                // class org/apache/pulsar/common/nar/NarClassLoader
     462: ifeq          473
     465: aload_0
     466: aload_1
     467: checkcast     #194                // class org/apache/pulsar/common/nar/NarClassLoader
     470: invokestatic  #218                // Method validateSourceConfig:(Lorg/apache/pulsar/common/io/SourceConfig;Lorg/apache/pulsar/common/nar/NarClassLoader;)V
     473: new           #219                // class org/apache/pulsar/functions/utils/SourceConfigUtils$ExtractedSourceDetails
     476: dup
     477: aload_3
     478: aload         5
     480: invokevirtual #20                 // Method java/lang/Class.getName:()Ljava/lang/String;
     483: invokespecial #220                // Method org/apache/pulsar/functions/utils/SourceConfigUtils$ExtractedSourceDetails."<init>":(Ljava/lang/String;Ljava/lang/String;)V
     486: areturn
    Exception table:
       from    to  target type
         150   158   161   Class java/io/IOException
         175   182   185   Class java/lang/ClassNotFoundException

  public static org.apache.pulsar.common.io.SourceConfig clone(org.apache.pulsar.common.io.SourceConfig);
    Code:
       0: invokestatic  #221                // Method org/apache/pulsar/common/util/ObjectMapperFactory.getThreadLocal:()Lcom/fasterxml/jackson/databind/ObjectMapper;
       3: invokestatic  #221                // Method org/apache/pulsar/common/util/ObjectMapperFactory.getThreadLocal:()Lcom/fasterxml/jackson/databind/ObjectMapper;
       6: aload_0
       7: invokevirtual #222                // Method com/fasterxml/jackson/databind/ObjectMapper.writeValueAsBytes:(Ljava/lang/Object;)[B
      10: ldc_w         #355                // class org/apache/pulsar/common/io/SourceConfig
      13: invokevirtual #223                // Method com/fasterxml/jackson/databind/ObjectMapper.readValue:([BLjava/lang/Class;)Ljava/lang/Object;
      16: checkcast     #355                // class org/apache/pulsar/common/io/SourceConfig
      19: areturn
      20: astore_1
      21: aload_1
      22: athrow
    Exception table:
       from    to  target type
           0    19    20   Class java/lang/Throwable

  public static org.apache.pulsar.common.io.SourceConfig validateUpdate(org.apache.pulsar.common.io.SourceConfig, org.apache.pulsar.common.io.SourceConfig);
    Code:
       0: aload_0
       1: invokestatic  #226                // Method clone:(Lorg/apache/pulsar/common/io/SourceConfig;)Lorg/apache/pulsar/common/io/SourceConfig;
       4: astore_2
       5: aload_0
       6: invokevirtual #8                  // Method org/apache/pulsar/common/io/SourceConfig.getTenant:()Ljava/lang/String;
       9: aload_1
      10: invokevirtual #8                  // Method org/apache/pulsar/common/io/SourceConfig.getTenant:()Ljava/lang/String;
      13: invokevirtual #227                // Method java/lang/String.equals:(Ljava/lang/Object;)Z
      16: ifne          29
      19: new           #431                // class java/lang/IllegalArgumentException
      22: dup
      23: ldc           #228                // String Tenants differ
      25: invokespecial #185                // Method java/lang/IllegalArgumentException."<init>":(Ljava/lang/String;)V
      28: athrow
      29: aload_0
      30: invokevirtual #10                 // Method org/apache/pulsar/common/io/SourceConfig.getNamespace:()Ljava/lang/String;
      33: aload_1
      34: invokevirtual #10                 // Method org/apache/pulsar/common/io/SourceConfig.getNamespace:()Ljava/lang/String;
      37: invokevirtual #227                // Method java/lang/String.equals:(Ljava/lang/Object;)Z
      40: ifne          53
      43: new           #431                // class java/lang/IllegalArgumentException
      46: dup
      47: ldc           #229                // String Namespaces differ
      49: invokespecial #185                // Method java/lang/IllegalArgumentException."<init>":(Ljava/lang/String;)V
      52: athrow
      53: aload_0
      54: invokevirtual #12                 // Method org/apache/pulsar/common/io/SourceConfig.getName:()Ljava/lang/String;
      57: aload_1
      58: invokevirtual #12                 // Method org/apache/pulsar/common/io/SourceConfig.getName:()Ljava/lang/String;
      61: invokevirtual #227                // Method java/lang/String.equals:(Ljava/lang/Object;)Z
      64: ifne          77
      67: new           #431                // class java/lang/IllegalArgumentException
      70: dup
      71: ldc           #230                // String Function Names differ
      73: invokespecial #185                // Method java/lang/IllegalArgumentException."<init>":(Ljava/lang/String;)V
      76: athrow
      77: aload_1
      78: invokevirtual #193                // Method org/apache/pulsar/common/io/SourceConfig.getClassName:()Ljava/lang/String;
      81: invokestatic  #4                  // Method org/apache/commons/lang3/StringUtils.isEmpty:(Ljava/lang/CharSequence;)Z
      84: ifne          95
      87: aload_2
      88: aload_1
      89: invokevirtual #193                // Method org/apache/pulsar/common/io/SourceConfig.getClassName:()Ljava/lang/String;
      92: invokevirtual #118                // Method org/apache/pulsar/common/io/SourceConfig.setClassName:(Ljava/lang/String;)V
      95: aload_1
      96: invokevirtual #59                 // Method org/apache/pulsar/common/io/SourceConfig.getTopicName:()Ljava/lang/String;
      99: invokestatic  #4                  // Method org/apache/commons/lang3/StringUtils.isEmpty:(Ljava/lang/CharSequence;)Z
     102: ifne          113
     105: aload_2
     106: aload_1
     107: invokevirtual #59                 // Method org/apache/pulsar/common/io/SourceConfig.getTopicName:()Ljava/lang/String;
     110: invokevirtual #144                // Method org/apache/pulsar/common/io/SourceConfig.setTopicName:(Ljava/lang/String;)V
     113: aload_1
     114: invokevirtual #57                 // Method org/apache/pulsar/common/io/SourceConfig.getSerdeClassName:()Ljava/lang/String;
     117: invokestatic  #4                  // Method org/apache/commons/lang3/StringUtils.isEmpty:(Ljava/lang/CharSequence;)Z
     120: ifne          131
     123: aload_2
     124: aload_1
     125: invokevirtual #57                 // Method org/apache/pulsar/common/io/SourceConfig.getSerdeClassName:()Ljava/lang/String;
     128: invokevirtual #148                // Method org/apache/pulsar/common/io/SourceConfig.setSerdeClassName:(Ljava/lang/String;)V
     131: aload_1
     132: invokevirtual #55                 // Method org/apache/pulsar/common/io/SourceConfig.getSchemaType:()Ljava/lang/String;
     135: invokestatic  #4                  // Method org/apache/commons/lang3/StringUtils.isEmpty:(Ljava/lang/CharSequence;)Z
     138: ifne          149
     141: aload_2
     142: aload_1
     143: invokevirtual #55                 // Method org/apache/pulsar/common/io/SourceConfig.getSchemaType:()Ljava/lang/String;
     146: invokevirtual #146                // Method org/apache/pulsar/common/io/SourceConfig.setSchemaType:(Ljava/lang/String;)V
     149: aload_1
     150: invokevirtual #35                 // Method org/apache/pulsar/common/io/SourceConfig.getConfigs:()Ljava/util/Map;
     153: ifnull        164
     156: aload_2
     157: aload_1
     158: invokevirtual #35                 // Method org/apache/pulsar/common/io/SourceConfig.getConfigs:()Ljava/util/Map;
     161: invokevirtual #134                // Method org/apache/pulsar/common/io/SourceConfig.setConfigs:(Ljava/util/Map;)V
     164: aload_1
     165: invokevirtual #48                 // Method org/apache/pulsar/common/io/SourceConfig.getSecrets:()Ljava/util/Map;
     168: ifnull        179
     171: aload_2
     172: aload_1
     173: invokevirtual #48                 // Method org/apache/pulsar/common/io/SourceConfig.getSecrets:()Ljava/util/Map;
     176: invokevirtual #141                // Method org/apache/pulsar/common/io/SourceConfig.setSecrets:(Ljava/util/Map;)V
     179: aload_1
     180: invokevirtual #23                 // Method org/apache/pulsar/common/io/SourceConfig.getProcessingGuarantees:()Lorg/apache/pulsar/common/functions/FunctionConfig$ProcessingGuarantees;
     183: ifnull        210
     186: aload_1
     187: invokevirtual #23                 // Method org/apache/pulsar/common/io/SourceConfig.getProcessingGuarantees:()Lorg/apache/pulsar/common/functions/FunctionConfig$ProcessingGuarantees;
     190: aload_0
     191: invokevirtual #23                 // Method org/apache/pulsar/common/io/SourceConfig.getProcessingGuarantees:()Lorg/apache/pulsar/common/functions/FunctionConfig$ProcessingGuarantees;
     194: invokevirtual #231                // Method org/apache/pulsar/common/functions/FunctionConfig$ProcessingGuarantees.equals:(Ljava/lang/Object;)Z
     197: ifne          210
     200: new           #431                // class java/lang/IllegalArgumentException
     203: dup
     204: ldc           #232                // String Processing Guarantees cannot be altered
     206: invokespecial #185                // Method java/lang/IllegalArgumentException."<init>":(Ljava/lang/String;)V
     209: athrow
     210: aload_1
     211: invokevirtual #16                 // Method org/apache/pulsar/common/io/SourceConfig.getParallelism:()Ljava/lang/Integer;
     214: ifnull        225
     217: aload_2
     218: aload_1
     219: invokevirtual #16                 // Method org/apache/pulsar/common/io/SourceConfig.getParallelism:()Ljava/lang/Integer;
     222: invokevirtual #112                // Method org/apache/pulsar/common/io/SourceConfig.setParallelism:(Ljava/lang/Integer;)V
     225: aload_1
     226: invokevirtual #83                 // Method org/apache/pulsar/common/io/SourceConfig.getResources:()Lorg/apache/pulsar/common/functions/Resources;
     229: ifnull        247
     232: aload_2
     233: aload_0
     234: invokevirtual #83                 // Method org/apache/pulsar/common/io/SourceConfig.getResources:()Lorg/apache/pulsar/common/functions/Resources;
     237: aload_1
     238: invokevirtual #83                 // Method org/apache/pulsar/common/io/SourceConfig.getResources:()Lorg/apache/pulsar/common/functions/Resources;
     241: invokestatic  #233                // Method org/apache/pulsar/functions/utils/ResourceConfigUtils.merge:(Lorg/apache/pulsar/common/functions/Resources;Lorg/apache/pulsar/common/functions/Resources;)Lorg/apache/pulsar/common/functions/Resources;
     244: invokevirtual #178                // Method org/apache/pulsar/common/io/SourceConfig.setResources:(Lorg/apache/pulsar/common/functions/Resources;)V
     247: aload_1
     248: invokevirtual #3                  // Method org/apache/pulsar/common/io/SourceConfig.getArchive:()Ljava/lang/String;
     251: invokestatic  #4                  // Method org/apache/commons/lang3/StringUtils.isEmpty:(Ljava/lang/CharSequence;)Z
     254: ifne          265
     257: aload_2
     258: aload_1
     259: invokevirtual #3                  // Method org/apache/pulsar/common/io/SourceConfig.getArchive:()Ljava/lang/String;
     262: invokevirtual #125                // Method org/apache/pulsar/common/io/SourceConfig.setArchive:(Ljava/lang/String;)V
     265: aload_1
     266: invokevirtual #95                 // Method org/apache/pulsar/common/io/SourceConfig.getRuntimeFlags:()Ljava/lang/String;
     269: invokestatic  #4                  // Method org/apache/commons/lang3/StringUtils.isEmpty:(Ljava/lang/CharSequence;)Z
     272: ifne          283
     275: aload_2
     276: aload_1
     277: invokevirtual #95                 // Method org/apache/pulsar/common/io/SourceConfig.getRuntimeFlags:()Ljava/lang/String;
     280: invokevirtual #180                // Method org/apache/pulsar/common/io/SourceConfig.setRuntimeFlags:(Ljava/lang/String;)V
     283: aload_1
     284: invokevirtual #99                 // Method org/apache/pulsar/common/io/SourceConfig.getCustomRuntimeOptions:()Ljava/lang/String;
     287: invokestatic  #4                  // Method org/apache/commons/lang3/StringUtils.isEmpty:(Ljava/lang/CharSequence;)Z
     290: ifne          301
     293: aload_2
     294: aload_1
     295: invokevirtual #99                 // Method org/apache/pulsar/common/io/SourceConfig.getCustomRuntimeOptions:()Ljava/lang/String;
     298: invokevirtual #182                // Method org/apache/pulsar/common/io/SourceConfig.setCustomRuntimeOptions:(Ljava/lang/String;)V
     301: aload_0
     302: invokestatic  #234                // Method isBatchSource:(Lorg/apache/pulsar/common/io/SourceConfig;)Z
     305: aload_1
     306: invokestatic  #234                // Method isBatchSource:(Lorg/apache/pulsar/common/io/SourceConfig;)Z
     309: if_icmpeq     322
     312: new           #431                // class java/lang/IllegalArgumentException
     315: dup
     316: ldc           #235                // String Sources cannot be update between regular sources and batchsource
     318: invokespecial #185                // Method java/lang/IllegalArgumentException."<init>":(Ljava/lang/String;)V
     321: athrow
     322: aload_1
     323: invokevirtual #37                 // Method org/apache/pulsar/common/io/SourceConfig.getBatchSourceConfig:()Lorg/apache/pulsar/common/io/BatchSourceConfig;
     326: ifnull        348
     329: aload_0
     330: invokevirtual #37                 // Method org/apache/pulsar/common/io/SourceConfig.getBatchSourceConfig:()Lorg/apache/pulsar/common/io/BatchSourceConfig;
     333: aload_1
     334: invokevirtual #37                 // Method org/apache/pulsar/common/io/SourceConfig.getBatchSourceConfig:()Lorg/apache/pulsar/common/io/BatchSourceConfig;
     337: invokestatic  #236                // Method validateBatchSourceConfigUpdate:(Lorg/apache/pulsar/common/io/BatchSourceConfig;Lorg/apache/pulsar/common/io/BatchSourceConfig;)V
     340: aload_2
     341: aload_1
     342: invokevirtual #37                 // Method org/apache/pulsar/common/io/SourceConfig.getBatchSourceConfig:()Lorg/apache/pulsar/common/io/BatchSourceConfig;
     345: invokevirtual #129                // Method org/apache/pulsar/common/io/SourceConfig.setBatchSourceConfig:(Lorg/apache/pulsar/common/io/BatchSourceConfig;)V
     348: aload_2
     349: areturn

  public static void validateBatchSourceConfig(org.apache.pulsar.common.io.BatchSourceConfig) throws java.lang.IllegalArgumentException;
    Code:
       0: aload_0
       1: invokevirtual #237                // Method org/apache/pulsar/common/io/BatchSourceConfig.getDiscoveryTriggererClassName:()Ljava/lang/String;
       4: invokestatic  #4                  // Method org/apache/commons/lang3/StringUtils.isEmpty:(Ljava/lang/CharSequence;)Z
       7: ifeq          30
      10: getstatic     #238                // Field log:Lorg/slf4j/Logger;
      13: ldc           #239                // String BatchSourceConfig does not specify Discovery Trigger ClassName
      15: invokeinterface #240,  2          // InterfaceMethod org/slf4j/Logger.error:(Ljava/lang/String;)V
      20: new           #431                // class java/lang/IllegalArgumentException
      23: dup
      24: ldc           #239                // String BatchSourceConfig does not specify Discovery Trigger ClassName
      26: invokespecial #185                // Method java/lang/IllegalArgumentException."<init>":(Ljava/lang/String;)V
      29: athrow
      30: return

  public static java.util.Map<java.lang.String, java.lang.Object> extractSourceConfig(org.apache.pulsar.functions.proto.Function$SourceSpec, java.lang.String);
    Code:
       0: aload_0
       1: invokevirtual #241                // Method org/apache/pulsar/functions/proto/Function$SourceSpec.getConfigs:()Ljava/lang/String;
       4: invokestatic  #4                  // Method org/apache/commons/lang3/StringUtils.isEmpty:(Ljava/lang/CharSequence;)Z
       7: ifne          55
      10: new           #242                // class org/apache/pulsar/functions/utils/SourceConfigUtils$2
      13: dup
      14: invokespecial #243                // Method org/apache/pulsar/functions/utils/SourceConfigUtils$2."<init>":()V
      17: astore_2
      18: invokestatic  #221                // Method org/apache/pulsar/common/util/ObjectMapperFactory.getThreadLocal:()Lcom/fasterxml/jackson/databind/ObjectMapper;
      21: aload_0
      22: invokevirtual #241                // Method org/apache/pulsar/functions/proto/Function$SourceSpec.getConfigs:()Ljava/lang/String;
      25: aload_2
      26: invokevirtual #244                // Method com/fasterxml/jackson/databind/ObjectMapper.readValue:(Ljava/lang/String;Lcom/fasterxml/jackson/core/type/TypeReference;)Ljava/lang/Object;
      29: checkcast     #330                // class java/util/Map
      32: areturn
      33: astore_3
      34: getstatic     #238                // Field log:Lorg/slf4j/Logger;
      37: ldc           #245                // String Failed to read configs for source {}
      39: aload_1
      40: aload_3
      41: invokeinterface #246,  4          // InterfaceMethod org/slf4j/Logger.error:(Ljava/lang/String;Ljava/lang/Object;Ljava/lang/Object;)V
      46: new           #247                // class java/lang/RuntimeException
      49: dup
      50: aload_3
      51: invokespecial #248                // Method java/lang/RuntimeException."<init>":(Ljava/lang/Throwable;)V
      54: athrow
      55: aconst_null
      56: areturn
    Exception table:
       from    to  target type
          18    32    33   Class java/io/IOException

  public static org.apache.pulsar.common.io.BatchSourceConfig extractBatchSourceConfig(java.util.Map<java.lang.String, java.lang.Object>);
    Code:
       0: aload_0
       1: ldc           #39                 // String __BATCHSOURCECONFIGS__
       3: invokeinterface #130,  2          // InterfaceMethod java/util/Map.containsKey:(Ljava/lang/Object;)Z
       8: ifeq          41
      11: aload_0
      12: ldc           #39                 // String __BATCHSOURCECONFIGS__
      14: invokeinterface #131,  2          // InterfaceMethod java/util/Map.get:(Ljava/lang/Object;)Ljava/lang/Object;
      19: checkcast     #374                // class java/lang/String
      22: astore_1
      23: new           #40                 // class com/google/gson/Gson
      26: dup
      27: invokespecial #41                 // Method com/google/gson/Gson."<init>":()V
      30: aload_1
      31: ldc_w         #357                // class org/apache/pulsar/common/io/BatchSourceConfig
      34: invokevirtual #249                // Method com/google/gson/Gson.fromJson:(Ljava/lang/String;Ljava/lang/Class;)Ljava/lang/Object;
      37: checkcast     #357                // class org/apache/pulsar/common/io/BatchSourceConfig
      40: areturn
      41: aconst_null
      42: areturn

  public static java.util.Map<java.lang.String, java.lang.String> computeBatchSourceIntermediateTopicSubscriptions(org.apache.pulsar.functions.proto.Function$FunctionDetails, java.lang.String);
    Code:
       0: aload_0
       1: invokevirtual #116                // Method org/apache/pulsar/functions/proto/Function$FunctionDetails.getSource:()Lorg/apache/pulsar/functions/proto/Function$SourceSpec;
       4: aload_1
       5: invokestatic  #127                // Method extractSourceConfig:(Lorg/apache/pulsar/functions/proto/Function$SourceSpec;Ljava/lang/String;)Ljava/util/Map;
       8: astore_2
       9: aload_2
      10: ifnull        79
      13: aload_2
      14: invokestatic  #128                // Method extractBatchSourceConfig:(Ljava/util/Map;)Lorg/apache/pulsar/common/io/BatchSourceConfig;
      17: astore_3
      18: aload_0
      19: invokevirtual #104                // Method org/apache/pulsar/functions/proto/Function$FunctionDetails.getTenant:()Ljava/lang/String;
      22: aload_0
      23: invokevirtual #106                // Method org/apache/pulsar/functions/proto/Function$FunctionDetails.getNamespace:()Ljava/lang/String;
      26: aload_0
      27: invokevirtual #108                // Method org/apache/pulsar/functions/proto/Function$FunctionDetails.getName:()Ljava/lang/String;
      30: invokestatic  #250                // Method computeBatchSourceIntermediateTopicName:(Ljava/lang/String;Ljava/lang/String;Ljava/lang/String;)Lorg/apache/pulsar/common/naming/TopicName;
      33: invokevirtual #251                // Method org/apache/pulsar/common/naming/TopicName.toString:()Ljava/lang/String;
      36: astore        4
      38: aload_3
      39: ifnull        79
      42: new           #33                 // class java/util/HashMap
      45: dup
      46: invokespecial #34                 // Method java/util/HashMap."<init>":()V
      49: astore        5
      51: aload         5
      53: aload         4
      55: aload_0
      56: invokevirtual #104                // Method org/apache/pulsar/functions/proto/Function$FunctionDetails.getTenant:()Ljava/lang/String;
      59: aload_0
      60: invokevirtual #106                // Method org/apache/pulsar/functions/proto/Function$FunctionDetails.getNamespace:()Ljava/lang/String;
      63: aload_0
      64: invokevirtual #108                // Method org/apache/pulsar/functions/proto/Function$FunctionDetails.getName:()Ljava/lang/String;
      67: invokestatic  #252                // Method computeBatchSourceInstanceSubscriptionName:(Ljava/lang/String;Ljava/lang/String;Ljava/lang/String;)Ljava/lang/String;
      70: invokeinterface #43,  3           // InterfaceMethod java/util/Map.put:(Ljava/lang/Object;Ljava/lang/Object;)Ljava/lang/Object;
      75: pop
      76: aload         5
      78: areturn
      79: aconst_null
      80: areturn

  public static java.lang.String computeBatchSourceInstanceSubscriptionName(java.lang.String, java.lang.String, java.lang.String);
    Code:
       0: new           #120                // class java/lang/StringBuilder
       3: dup
       4: invokespecial #121                // Method java/lang/StringBuilder."<init>":()V
       7: ldc           #253                // String BatchSourceExecutor-
       9: invokevirtual #123                // Method java/lang/StringBuilder.append:(Ljava/lang/String;)Ljava/lang/StringBuilder;
      12: aload_0
      13: invokevirtual #123                // Method java/lang/StringBuilder.append:(Ljava/lang/String;)Ljava/lang/StringBuilder;
      16: ldc           #254                // String /
      18: invokevirtual #123                // Method java/lang/StringBuilder.append:(Ljava/lang/String;)Ljava/lang/StringBuilder;
      21: aload_1
      22: invokevirtual #123                // Method java/lang/StringBuilder.append:(Ljava/lang/String;)Ljava/lang/StringBuilder;
      25: ldc           #254                // String /
      27: invokevirtual #123                // Method java/lang/StringBuilder.append:(Ljava/lang/String;)Ljava/lang/StringBuilder;
      30: aload_2
      31: invokevirtual #123                // Method java/lang/StringBuilder.append:(Ljava/lang/String;)Ljava/lang/StringBuilder;
      34: invokevirtual #124                // Method java/lang/StringBuilder.toString:()Ljava/lang/String;
      37: areturn

  public static org.apache.pulsar.common.naming.TopicName computeBatchSourceIntermediateTopicName(java.lang.String, java.lang.String, java.lang.String);
    Code:
       0: getstatic     #255                // Field org/apache/pulsar/common/naming/TopicDomain.persistent:Lorg/apache/pulsar/common/naming/TopicDomain;
       3: invokevirtual #256                // Method org/apache/pulsar/common/naming/TopicDomain.name:()Ljava/lang/String;
       6: aload_0
       7: aload_1
       8: new           #120                // class java/lang/StringBuilder
      11: dup
      12: invokespecial #121                // Method java/lang/StringBuilder."<init>":()V
      15: aload_2
      16: invokevirtual #123                // Method java/lang/StringBuilder.append:(Ljava/lang/String;)Ljava/lang/StringBuilder;
      19: ldc_w         #257                // String -intermediate
      22: invokevirtual #123                // Method java/lang/StringBuilder.append:(Ljava/lang/String;)Ljava/lang/StringBuilder;
      25: invokevirtual #124                // Method java/lang/StringBuilder.toString:()Ljava/lang/String;
      28: invokestatic  #258                // Method org/apache/pulsar/common/naming/TopicName.get:(Ljava/lang/String;Ljava/lang/String;Ljava/lang/String;Ljava/lang/String;)Lorg/apache/pulsar/common/naming/TopicName;
      31: areturn

  public static boolean isBatchSource(org.apache.pulsar.common.io.SourceConfig);
    Code:
       0: aload_0
       1: invokevirtual #37                 // Method org/apache/pulsar/common/io/SourceConfig.getBatchSourceConfig:()Lorg/apache/pulsar/common/io/BatchSourceConfig;
       4: ifnull        11
       7: iconst_1
       8: goto          12
      11: iconst_0
      12: ireturn

  public static void validateBatchSourceConfigUpdate(org.apache.pulsar.common.io.BatchSourceConfig, org.apache.pulsar.common.io.BatchSourceConfig);
    Code:
       0: aload_0
       1: invokevirtual #237                // Method org/apache/pulsar/common/io/BatchSourceConfig.getDiscoveryTriggererClassName:()Ljava/lang/String;
       4: aload_1
       5: invokevirtual #237                // Method org/apache/pulsar/common/io/BatchSourceConfig.getDiscoveryTriggererClassName:()Ljava/lang/String;
       8: invokevirtual #227                // Method java/lang/String.equals:(Ljava/lang/Object;)Z
      11: ifne          25
      14: new           #431                // class java/lang/IllegalArgumentException
      17: dup
      18: ldc_w         #259                // String DiscoverTriggerer class cannot be updated for batchsources
      21: invokespecial #185                // Method java/lang/IllegalArgumentException."<init>":(Ljava/lang/String;)V
      24: athrow
      25: return

  public static void validateSourceConfig(org.apache.pulsar.common.io.SourceConfig, org.apache.pulsar.common.nar.NarClassLoader);
    Code:
       0: aload_1
       1: invokestatic  #260                // Method org/apache/pulsar/functions/utils/io/ConnectorUtils.getConnectorDefinition:(Lorg/apache/pulsar/common/nar/NarClassLoader;)Lorg/apache/pulsar/common/io/ConnectorDefinition;
       4: astore_2
       5: aload_2
       6: invokevirtual #261                // Method org/apache/pulsar/common/io/ConnectorDefinition.getSourceConfigClass:()Ljava/lang/String;
       9: ifnull        45
      12: aload_2
      13: invokevirtual #261                // Method org/apache/pulsar/common/io/ConnectorDefinition.getSourceConfigClass:()Ljava/lang/String;
      16: iconst_1
      17: aload_1
      18: invokestatic  #262                // Method java/lang/Class.forName:(Ljava/lang/String;ZLjava/lang/ClassLoader;)Ljava/lang/Class;
      21: astore_3
      22: invokestatic  #221                // Method org/apache/pulsar/common/util/ObjectMapperFactory.getThreadLocal:()Lcom/fasterxml/jackson/databind/ObjectMapper;
      25: aload_0
      26: invokevirtual #35                 // Method org/apache/pulsar/common/io/SourceConfig.getConfigs:()Ljava/util/Map;
      29: aload_3
      30: invokevirtual #263                // Method com/fasterxml/jackson/databind/ObjectMapper.convertValue:(Ljava/lang/Object;Ljava/lang/Class;)Ljava/lang/Object;
      33: astore        4
      35: aload         4
      37: ifnull        45
      40: aload         4
      42: invokestatic  #264                // Method org/apache/pulsar/config/validation/ConfigValidation.validateConfig:(Ljava/lang/Object;)V
      45: goto          105
      48: astore_2
      49: new           #431                // class java/lang/IllegalArgumentException
      52: dup
      53: ldc_w         #265                // String Error validating source config
      56: aload_2
      57: invokespecial #198                // Method java/lang/IllegalArgumentException."<init>":(Ljava/lang/String;Ljava/lang/Throwable;)V
      60: athrow
      61: astore_2
      62: new           #431                // class java/lang/IllegalArgumentException
      65: dup
      66: ldc_w         #266                // String Could not find source config class
      69: invokespecial #185                // Method java/lang/IllegalArgumentException."<init>":(Ljava/lang/String;)V
      72: athrow
      73: astore_2
      74: new           #431                // class java/lang/IllegalArgumentException
      77: dup
      78: new           #120                // class java/lang/StringBuilder
      81: dup
      82: invokespecial #121                // Method java/lang/StringBuilder."<init>":()V
      85: ldc_w         #267                // String Could not validate source config:
      88: invokevirtual #123                // Method java/lang/StringBuilder.append:(Ljava/lang/String;)Ljava/lang/StringBuilder;
      91: aload_2
      92: invokevirtual #268                // Method java/lang/IllegalArgumentException.getMessage:()Ljava/lang/String;
      95: invokevirtual #123                // Method java/lang/StringBuilder.append:(Ljava/lang/String;)Ljava/lang/StringBuilder;
      98: invokevirtual #124                // Method java/lang/StringBuilder.toString:()Ljava/lang/String;
     101: invokespecial #185                // Method java/lang/IllegalArgumentException."<init>":(Ljava/lang/String;)V
     104: athrow
     105: return
    Exception table:
       from    to  target type
           0    45    48   Class java/io/IOException
           0    45    61   Class java/lang/ClassNotFoundException
           0    45    73   Class java/lang/IllegalArgumentException

  static {};
    Code:
       0: ldc_w         #269                // class org/apache/pulsar/functions/utils/SourceConfigUtils
       3: invokestatic  #270                // Method org/slf4j/LoggerFactory.getLogger:(Ljava/lang/Class;)Lorg/slf4j/Logger;
       6: putstatic     #238                // Field log:Lorg/slf4j/Logger;
       9: return
}
