Compiled from "Main.java"
public class hudson.Main {
  public hudson.Main();
    Code:
       0: aload_0
       1: invokespecial #1                  // Method java/lang/Object."<init>":()V
       4: return

  public static void main(java.lang.String[]);
    Code:
       0: aload_0
       1: invokestatic  #2                  // Method run:([Ljava/lang/String;)I
       4: invokestatic  #3                  // Method java/lang/System.exit:(I)V
       7: goto          19
      10: astore_1
      11: aload_1
      12: invokevirtual #5                  // Method java/lang/Exception.printStackTrace:()V
      15: iconst_m1
      16: invokestatic  #3                  // Method java/lang/System.exit:(I)V
      19: return
    Exception table:
       from    to  target type
           0     7    10   Class java/lang/Exception

  public static int run(java.lang.String[]) throws java.lang.Exception;
    Code:
       0: invokestatic  #6                  // Method getHudsonHome:()Ljava/lang/String;
       3: astore_1
       4: aload_1
       5: ifnonnull     18
       8: getstatic     #7                  // Field java/lang/System.err:Ljava/io/PrintStream;
      11: ldc           #8                  // String HUDSON_HOME is not set.
      13: invokevirtual #9                  // Method java/io/PrintStream.println:(Ljava/lang/String;)V
      16: iconst_m1
      17: ireturn
      18: aload_0
      19: invokestatic  #10                 // Method remotePost:([Ljava/lang/String;)I
      22: ireturn

  private static java.lang.String getHudsonHome();
    Code:
       0: getstatic     #11                 // Field hudson/EnvVars.masterEnvVars:Ljava/util/Map;
       3: ldc           #12                 // String HUDSON_HOME
       5: invokeinterface #13,  2           // InterfaceMethod java/util/Map.get:(Ljava/lang/Object;)Ljava/lang/Object;
      10: checkcast     #14                 // class java/lang/String
      13: areturn

  public static int remotePost(java.lang.String[]) throws java.lang.Exception;
    Code:
       0: aload_0
       1: iconst_0
       2: aaload
       3: astore_1
       4: invokestatic  #6                  // Method getHudsonHome:()Ljava/lang/String;
       7: astore_2
       8: aload_2
       9: ldc           #15                 // String /
      11: invokevirtual #16                 // Method java/lang/String.endsWith:(Ljava/lang/String;)Z
      14: ifne          37
      17: new           #17                 // class java/lang/StringBuilder
      20: dup
      21: invokespecial #18                 // Method java/lang/StringBuilder."<init>":()V
      24: aload_2
      25: invokevirtual #19                 // Method java/lang/StringBuilder.append:(Ljava/lang/String;)Ljava/lang/StringBuilder;
      28: bipush        47
      30: invokevirtual #20                 // Method java/lang/StringBuilder.append:(C)Ljava/lang/StringBuilder;
      33: invokevirtual #21                 // Method java/lang/StringBuilder.toString:()Ljava/lang/String;
      36: astore_2
      37: new           #22                 // class java/net/URL
      40: dup
      41: aload_2
      42: invokespecial #23                 // Method java/net/URL."<init>":(Ljava/lang/String;)V
      45: invokevirtual #24                 // Method java/net/URL.openConnection:()Ljava/net/URLConnection;
      48: checkcast     #25                 // class java/net/HttpURLConnection
      51: astore_3
      52: aload_3
      53: invokevirtual #26                 // Method java/net/HttpURLConnection.connect:()V
      56: aload_3
      57: invokevirtual #27                 // Method java/net/HttpURLConnection.getResponseCode:()I
      60: sipush        200
      63: if_icmpne     75
      66: aload_3
      67: ldc           #28                 // String X-Hudson
      69: invokevirtual #29                 // Method java/net/HttpURLConnection.getHeaderField:(Ljava/lang/String;)Ljava/lang/String;
      72: ifnonnull     114
      75: getstatic     #7                  // Field java/lang/System.err:Ljava/io/PrintStream;
      78: new           #17                 // class java/lang/StringBuilder
      81: dup
      82: invokespecial #18                 // Method java/lang/StringBuilder."<init>":()V
      85: aload_2
      86: invokevirtual #19                 // Method java/lang/StringBuilder.append:(Ljava/lang/String;)Ljava/lang/StringBuilder;
      89: ldc           #30                 // String  is not Hudson (
      91: invokevirtual #19                 // Method java/lang/StringBuilder.append:(Ljava/lang/String;)Ljava/lang/StringBuilder;
      94: aload_3
      95: invokevirtual #31                 // Method java/net/HttpURLConnection.getResponseMessage:()Ljava/lang/String;
      98: invokevirtual #19                 // Method java/lang/StringBuilder.append:(Ljava/lang/String;)Ljava/lang/StringBuilder;
     101: ldc           #32                 // String )
     103: invokevirtual #19                 // Method java/lang/StringBuilder.append:(Ljava/lang/String;)Ljava/lang/StringBuilder;
     106: invokevirtual #21                 // Method java/lang/StringBuilder.toString:()Ljava/lang/String;
     109: invokevirtual #9                  // Method java/io/PrintStream.println:(Ljava/lang/String;)V
     112: iconst_m1
     113: ireturn
     114: aload_1
     115: ldc           #33                 // String UTF-8
     117: invokestatic  #34                 // Method java/net/URLEncoder.encode:(Ljava/lang/String;Ljava/lang/String;)Ljava/lang/String;
     120: ldc           #35                 // String \\+
     122: ldc           #36                 // String %20
     124: invokevirtual #37                 // Method java/lang/String.replaceAll:(Ljava/lang/String;Ljava/lang/String;)Ljava/lang/String;
     127: astore_3
     128: new           #22                 // class java/net/URL
     131: dup
     132: new           #17                 // class java/lang/StringBuilder
     135: dup
     136: invokespecial #18                 // Method java/lang/StringBuilder."<init>":()V
     139: aload_2
     140: invokevirtual #19                 // Method java/lang/StringBuilder.append:(Ljava/lang/String;)Ljava/lang/StringBuilder;
     143: ldc           #38                 // String job/
     145: invokevirtual #19                 // Method java/lang/StringBuilder.append:(Ljava/lang/String;)Ljava/lang/StringBuilder;
     148: aload_3
     149: invokevirtual #19                 // Method java/lang/StringBuilder.append:(Ljava/lang/String;)Ljava/lang/StringBuilder;
     152: ldc           #39                 // String /acceptBuildResult
     154: invokevirtual #19                 // Method java/lang/StringBuilder.append:(Ljava/lang/String;)Ljava/lang/StringBuilder;
     157: invokevirtual #21                 // Method java/lang/StringBuilder.toString:()Ljava/lang/String;
     160: invokespecial #23                 // Method java/net/URL."<init>":(Ljava/lang/String;)V
     163: invokevirtual #24                 // Method java/net/URL.openConnection:()Ljava/net/URLConnection;
     166: checkcast     #25                 // class java/net/HttpURLConnection
     169: astore        4
     171: aload         4
     173: invokevirtual #26                 // Method java/net/HttpURLConnection.connect:()V
     176: aload         4
     178: invokevirtual #27                 // Method java/net/HttpURLConnection.getResponseCode:()I
     181: sipush        200
     184: if_icmpeq     236
     187: getstatic     #7                  // Field java/lang/System.err:Ljava/io/PrintStream;
     190: new           #17                 // class java/lang/StringBuilder
     193: dup
     194: invokespecial #18                 // Method java/lang/StringBuilder."<init>":()V
     197: aload_1
     198: invokevirtual #19                 // Method java/lang/StringBuilder.append:(Ljava/lang/String;)Ljava/lang/StringBuilder;
     201: ldc           #40                 // String  is not a valid job name on
     203: invokevirtual #19                 // Method java/lang/StringBuilder.append:(Ljava/lang/String;)Ljava/lang/StringBuilder;
     206: aload_2
     207: invokevirtual #19                 // Method java/lang/StringBuilder.append:(Ljava/lang/String;)Ljava/lang/StringBuilder;
     210: ldc           #41                 // String  (
     212: invokevirtual #19                 // Method java/lang/StringBuilder.append:(Ljava/lang/String;)Ljava/lang/StringBuilder;
     215: aload         4
     217: invokevirtual #31                 // Method java/net/HttpURLConnection.getResponseMessage:()Ljava/lang/String;
     220: invokevirtual #19                 // Method java/lang/StringBuilder.append:(Ljava/lang/String;)Ljava/lang/StringBuilder;
     223: ldc           #32                 // String )
     225: invokevirtual #19                 // Method java/lang/StringBuilder.append:(Ljava/lang/String;)Ljava/lang/StringBuilder;
     228: invokevirtual #21                 // Method java/lang/StringBuilder.toString:()Ljava/lang/String;
     231: invokevirtual #9                  // Method java/io/PrintStream.println:(Ljava/lang/String;)V
     234: iconst_m1
     235: ireturn
     236: ldc           #42                 // String hudson
     238: ldc           #43                 // String log
     240: invokestatic  #44                 // Method java/io/File.createTempFile:(Ljava/lang/String;Ljava/lang/String;)Ljava/io/File;
     243: astore        4
     245: aload         4
     247: invokevirtual #45                 // Method java/io/File.deleteOnExit:()V
     250: new           #46                 // class java/io/FileOutputStream
     253: dup
     254: aload         4
     256: invokespecial #47                 // Method java/io/FileOutputStream."<init>":(Ljava/io/File;)V
     259: astore        5
     261: new           #48                 // class java/io/OutputStreamWriter
     264: dup
     265: aload         5
     267: ldc           #33                 // String UTF-8
     269: invokespecial #49                 // Method java/io/OutputStreamWriter."<init>":(Ljava/io/OutputStream;Ljava/lang/String;)V
     272: astore        6
     274: aload         6
     276: ldc           #50                 // String <?xml version=\'1.0\' encoding=\'UTF-8\'?>
     278: invokevirtual #51                 // Method java/io/Writer.write:(Ljava/lang/String;)V
     281: aload         6
     283: ldc           #52                 // String <run><log encoding=\'hexBinary\'>
     285: invokevirtual #51                 // Method java/io/Writer.write:(Ljava/lang/String;)V
     288: aload         6
     290: invokevirtual #53                 // Method java/io/Writer.flush:()V
     293: invokestatic  #54                 // Method java/lang/System.currentTimeMillis:()J
     296: lstore        7
     298: new           #55                 // class java/util/ArrayList
     301: dup
     302: invokespecial #56                 // Method java/util/ArrayList."<init>":()V
     305: astore        9
     307: iconst_1
     308: istore        10
     310: iload         10
     312: aload_0
     313: arraylength
     314: if_icmpge     335
     317: aload         9
     319: aload_0
     320: iload         10
     322: aaload
     323: invokeinterface #57,  2           // InterfaceMethod java/util/List.add:(Ljava/lang/Object;)Z
     328: pop
     329: iinc          10, 1
     332: goto          310
     335: new           #58                 // class hudson/Proc$LocalProc
     338: dup
     339: aload         9
     341: iconst_0
     342: anewarray     #14                 // class java/lang/String
     345: invokeinterface #59,  2           // InterfaceMethod java/util/List.toArray:([Ljava/lang/Object;)[Ljava/lang/Object;
     350: checkcast     #60                 // class "[Ljava/lang/String;"
     353: aconst_null
     354: checkcast     #60                 // class "[Ljava/lang/String;"
     357: getstatic     #61                 // Field java/lang/System.in:Ljava/io/InputStream;
     360: new           #62                 // class hudson/util/DualOutputStream
     363: dup
     364: getstatic     #63                 // Field java/lang/System.out:Ljava/io/PrintStream;
     367: new           #64                 // class hudson/util/EncodingStream
     370: dup
     371: aload         5
     373: invokespecial #65                 // Method hudson/util/EncodingStream."<init>":(Ljava/io/OutputStream;)V
     376: invokespecial #66                 // Method hudson/util/DualOutputStream."<init>":(Ljava/io/OutputStream;Ljava/io/OutputStream;)V
     379: invokespecial #67                 // Method hudson/Proc$LocalProc."<init>":([Ljava/lang/String;[Ljava/lang/String;Ljava/io/InputStream;Ljava/io/OutputStream;)V
     382: astore        10
     384: aload         10
     386: invokevirtual #68                 // Method hudson/Proc.join:()I
     389: istore        11
     391: aload         6
     393: new           #17                 // class java/lang/StringBuilder
     396: dup
     397: invokespecial #18                 // Method java/lang/StringBuilder."<init>":()V
     400: ldc           #69                 // String </log><result>
     402: invokevirtual #19                 // Method java/lang/StringBuilder.append:(Ljava/lang/String;)Ljava/lang/StringBuilder;
     405: iload         11
     407: invokevirtual #70                 // Method java/lang/StringBuilder.append:(I)Ljava/lang/StringBuilder;
     410: ldc           #71                 // String </result><duration>
     412: invokevirtual #19                 // Method java/lang/StringBuilder.append:(Ljava/lang/String;)Ljava/lang/StringBuilder;
     415: invokestatic  #54                 // Method java/lang/System.currentTimeMillis:()J
     418: lload         7
     420: lsub
     421: invokevirtual #72                 // Method java/lang/StringBuilder.append:(J)Ljava/lang/StringBuilder;
     424: ldc           #73                 // String </duration></run>
     426: invokevirtual #19                 // Method java/lang/StringBuilder.append:(Ljava/lang/String;)Ljava/lang/StringBuilder;
     429: invokevirtual #21                 // Method java/lang/StringBuilder.toString:()Ljava/lang/String;
     432: invokevirtual #51                 // Method java/io/Writer.write:(Ljava/lang/String;)V
     435: aload         6
     437: invokevirtual #74                 // Method java/io/Writer.close:()V
     440: new           #17                 // class java/lang/StringBuilder
     443: dup
     444: invokespecial #18                 // Method java/lang/StringBuilder."<init>":()V
     447: aload_2
     448: invokevirtual #19                 // Method java/lang/StringBuilder.append:(Ljava/lang/String;)Ljava/lang/StringBuilder;
     451: ldc           #38                 // String job/
     453: invokevirtual #19                 // Method java/lang/StringBuilder.append:(Ljava/lang/String;)Ljava/lang/StringBuilder;
     456: aload_3
     457: invokevirtual #19                 // Method java/lang/StringBuilder.append:(Ljava/lang/String;)Ljava/lang/StringBuilder;
     460: ldc           #75                 // String /postBuildResult
     462: invokevirtual #19                 // Method java/lang/StringBuilder.append:(Ljava/lang/String;)Ljava/lang/StringBuilder;
     465: invokevirtual #21                 // Method java/lang/StringBuilder.toString:()Ljava/lang/String;
     468: astore        12
     470: new           #22                 // class java/net/URL
     473: dup
     474: aload         12
     476: invokespecial #23                 // Method java/net/URL."<init>":(Ljava/lang/String;)V
     479: invokevirtual #24                 // Method java/net/URL.openConnection:()Ljava/net/URLConnection;
     482: checkcast     #25                 // class java/net/HttpURLConnection
     485: astore        13
     487: aload         13
     489: iconst_1
     490: invokevirtual #76                 // Method java/net/HttpURLConnection.setDoOutput:(Z)V
     493: aload         13
     495: aload         4
     497: invokevirtual #77                 // Method java/io/File.length:()J
     500: l2i
     501: invokevirtual #78                 // Method java/net/HttpURLConnection.setFixedLengthStreamingMode:(I)V
     504: aload         13
     506: invokevirtual #26                 // Method java/net/HttpURLConnection.connect:()V
     509: new           #79                 // class java/io/FileInputStream
     512: dup
     513: aload         4
     515: invokespecial #80                 // Method java/io/FileInputStream."<init>":(Ljava/io/File;)V
     518: astore        14
     520: aload         14
     522: aload         13
     524: invokevirtual #81                 // Method java/net/HttpURLConnection.getOutputStream:()Ljava/io/OutputStream;
     527: invokestatic  #82                 // Method hudson/Util.copyStream:(Ljava/io/InputStream;Ljava/io/OutputStream;)V
     530: aload         14
     532: invokevirtual #83                 // Method java/io/FileInputStream.close:()V
     535: aload         13
     537: invokevirtual #27                 // Method java/net/HttpURLConnection.getResponseCode:()I
     540: sipush        200
     543: if_icmpeq     557
     546: aload         13
     548: invokevirtual #84                 // Method java/net/HttpURLConnection.getErrorStream:()Ljava/io/InputStream;
     551: getstatic     #7                  // Field java/lang/System.err:Ljava/io/PrintStream;
     554: invokestatic  #82                 // Method hudson/Util.copyStream:(Ljava/io/InputStream;Ljava/io/OutputStream;)V
     557: iload         11
     559: ireturn
     560: astore        13
     562: aload         13
     564: invokevirtual #86                 // Method java/net/HttpRetryException.getLocation:()Ljava/lang/String;
     567: ifnull        580
     570: aload         13
     572: invokevirtual #86                 // Method java/net/HttpRetryException.getLocation:()Ljava/lang/String;
     575: astore        12
     577: goto          470
     580: aload         13
     582: athrow
    Exception table:
       from    to  target type
         470   559   560   Class java/net/HttpRetryException
}
