Compiled from "XmlFile.java"
class hudson.XmlFile$1Eureka extends org.xml.sax.SAXException {
  final java.lang.String encoding;

  final hudson.XmlFile this$0;

  public hudson.XmlFile$1Eureka(hudson.XmlFile, java.lang.String);
    Code:
       0: aload_0
       1: aload_1
       2: putfield      #1                  // Field this$0:Lhudson/XmlFile;
       5: aload_0
       6: invokespecial #2                  // Method org/xml/sax/SAXException."<init>":()V
       9: aload_0
      10: aload_2
      11: putfield      #3                  // Field encoding:Ljava/lang/String;
      14: return
}
