Compiled from "DescribeVpcEndpointsResponse.java"
final class software.amazon.awssdk.services.opensearch.model.DescribeVpcEndpointsResponse$BuilderImpl extends software.amazon.awssdk.services.opensearch.model.OpenSearchResponse$BuilderImpl implements software.amazon.awssdk.services.opensearch.model.DescribeVpcEndpointsResponse$Builder {
  private java.util.List<software.amazon.awssdk.services.opensearch.model.VpcEndpoint> vpcEndpoints;

  private java.util.List<software.amazon.awssdk.services.opensearch.model.VpcEndpointError> vpcEndpointErrors;

  private software.amazon.awssdk.services.opensearch.model.DescribeVpcEndpointsResponse$BuilderImpl();
    Code:
       0: aload_0
       1: invokespecial #5                  // Method software/amazon/awssdk/services/opensearch/model/OpenSearchResponse$BuilderImpl."<init>":()V
       4: aload_0
       5: invokestatic  #6                  // Method software/amazon/awssdk/core/util/DefaultSdkAutoConstructList.getInstance:()Lsoftware/amazon/awssdk/core/util/DefaultSdkAutoConstructList;
       8: putfield      #4                  // Field vpcEndpoints:Ljava/util/List;
      11: aload_0
      12: invokestatic  #6                  // Method software/amazon/awssdk/core/util/DefaultSdkAutoConstructList.getInstance:()Lsoftware/amazon/awssdk/core/util/DefaultSdkAutoConstructList;
      15: putfield      #3                  // Field vpcEndpointErrors:Ljava/util/List;
      18: return

  private software.amazon.awssdk.services.opensearch.model.DescribeVpcEndpointsResponse$BuilderImpl(software.amazon.awssdk.services.opensearch.model.DescribeVpcEndpointsResponse);
    Code:
       0: aload_0
       1: aload_1
       2: invokespecial #7                  // Method software/amazon/awssdk/services/opensearch/model/OpenSearchResponse$BuilderImpl."<init>":(Lsoftware/amazon/awssdk/services/opensearch/model/OpenSearchResponse;)V
       5: aload_0
       6: invokestatic  #6                  // Method software/amazon/awssdk/core/util/DefaultSdkAutoConstructList.getInstance:()Lsoftware/amazon/awssdk/core/util/DefaultSdkAutoConstructList;
       9: putfield      #4                  // Field vpcEndpoints:Ljava/util/List;
      12: aload_0
      13: invokestatic  #6                  // Method software/amazon/awssdk/core/util/DefaultSdkAutoConstructList.getInstance:()Lsoftware/amazon/awssdk/core/util/DefaultSdkAutoConstructList;
      16: putfield      #3                  // Field vpcEndpointErrors:Ljava/util/List;
      19: aload_0
      20: aload_1
      21: invokestatic  #8                  // Method software/amazon/awssdk/services/opensearch/model/DescribeVpcEndpointsResponse.access$400:(Lsoftware/amazon/awssdk/services/opensearch/model/DescribeVpcEndpointsResponse;)Ljava/util/List;
      24: invokevirtual #9                  // Method vpcEndpoints:(Ljava/util/Collection;)Lsoftware/amazon/awssdk/services/opensearch/model/DescribeVpcEndpointsResponse$Builder;
      27: pop
      28: aload_0
      29: aload_1
      30: invokestatic  #10                 // Method software/amazon/awssdk/services/opensearch/model/DescribeVpcEndpointsResponse.access$500:(Lsoftware/amazon/awssdk/services/opensearch/model/DescribeVpcEndpointsResponse;)Ljava/util/List;
      33: invokevirtual #11                 // Method vpcEndpointErrors:(Ljava/util/Collection;)Lsoftware/amazon/awssdk/services/opensearch/model/DescribeVpcEndpointsResponse$Builder;
      36: pop
      37: return

  public final java.util.List<software.amazon.awssdk.services.opensearch.model.VpcEndpoint$Builder> getVpcEndpoints();
    Code:
       0: aload_0
       1: getfield      #4                  // Field vpcEndpoints:Ljava/util/List;
       4: invokestatic  #12                 // Method software/amazon/awssdk/services/opensearch/model/VpcEndpointsCopier.copyToBuilder:(Ljava/util/Collection;)Ljava/util/List;
       7: astore_1
       8: aload_1
       9: instanceof    #13                 // class software/amazon/awssdk/core/util/SdkAutoConstructList
      12: ifeq          17
      15: aconst_null
      16: areturn
      17: aload_1
      18: areturn

  public final void setVpcEndpoints(java.util.Collection<software.amazon.awssdk.services.opensearch.model.VpcEndpoint$BuilderImpl>);
    Code:
       0: aload_0
       1: aload_1
       2: invokestatic  #14                 // Method software/amazon/awssdk/services/opensearch/model/VpcEndpointsCopier.copyFromBuilder:(Ljava/util/Collection;)Ljava/util/List;
       5: putfield      #4                  // Field vpcEndpoints:Ljava/util/List;
       8: return

  public final software.amazon.awssdk.services.opensearch.model.DescribeVpcEndpointsResponse$Builder vpcEndpoints(java.util.Collection<software.amazon.awssdk.services.opensearch.model.VpcEndpoint>);
    Code:
       0: aload_0
       1: aload_1
       2: invokestatic  #15                 // Method software/amazon/awssdk/services/opensearch/model/VpcEndpointsCopier.copy:(Ljava/util/Collection;)Ljava/util/List;
       5: putfield      #4                  // Field vpcEndpoints:Ljava/util/List;
       8: aload_0
       9: areturn

  public final software.amazon.awssdk.services.opensearch.model.DescribeVpcEndpointsResponse$Builder vpcEndpoints(software.amazon.awssdk.services.opensearch.model.VpcEndpoint...);
    Code:
       0: aload_0
       1: aload_1
       2: invokestatic  #16                 // Method java/util/Arrays.asList:([Ljava/lang/Object;)Ljava/util/List;
       5: invokevirtual #9                  // Method vpcEndpoints:(Ljava/util/Collection;)Lsoftware/amazon/awssdk/services/opensearch/model/DescribeVpcEndpointsResponse$Builder;
       8: pop
       9: aload_0
      10: areturn

  public final software.amazon.awssdk.services.opensearch.model.DescribeVpcEndpointsResponse$Builder vpcEndpoints(java.util.function.Consumer<software.amazon.awssdk.services.opensearch.model.VpcEndpoint$Builder>...);
    Code:
       0: aload_0
       1: aload_1
       2: invokestatic  #17                 // InterfaceMethod java/util/stream/Stream.of:([Ljava/lang/Object;)Ljava/util/stream/Stream;
       5: invokedynamic #18,  0             // InvokeDynamic #0:apply:()Ljava/util/function/Function;
      10: invokeinterface #19,  2           // InterfaceMethod java/util/stream/Stream.map:(Ljava/util/function/Function;)Ljava/util/stream/Stream;
      15: invokestatic  #20                 // Method java/util/stream/Collectors.toList:()Ljava/util/stream/Collector;
      18: invokeinterface #21,  2           // InterfaceMethod java/util/stream/Stream.collect:(Ljava/util/stream/Collector;)Ljava/lang/Object;
      23: checkcast     #22                 // class java/util/Collection
      26: invokevirtual #9                  // Method vpcEndpoints:(Ljava/util/Collection;)Lsoftware/amazon/awssdk/services/opensearch/model/DescribeVpcEndpointsResponse$Builder;
      29: pop
      30: aload_0
      31: areturn

  public final java.util.List<software.amazon.awssdk.services.opensearch.model.VpcEndpointError$Builder> getVpcEndpointErrors();
    Code:
       0: aload_0
       1: getfield      #3                  // Field vpcEndpointErrors:Ljava/util/List;
       4: invokestatic  #23                 // Method software/amazon/awssdk/services/opensearch/model/VpcEndpointErrorListCopier.copyToBuilder:(Ljava/util/Collection;)Ljava/util/List;
       7: astore_1
       8: aload_1
       9: instanceof    #13                 // class software/amazon/awssdk/core/util/SdkAutoConstructList
      12: ifeq          17
      15: aconst_null
      16: areturn
      17: aload_1
      18: areturn

  public final void setVpcEndpointErrors(java.util.Collection<software.amazon.awssdk.services.opensearch.model.VpcEndpointError$BuilderImpl>);
    Code:
       0: aload_0
       1: aload_1
       2: invokestatic  #24                 // Method software/amazon/awssdk/services/opensearch/model/VpcEndpointErrorListCopier.copyFromBuilder:(Ljava/util/Collection;)Ljava/util/List;
       5: putfield      #3                  // Field vpcEndpointErrors:Ljava/util/List;
       8: return

  public final software.amazon.awssdk.services.opensearch.model.DescribeVpcEndpointsResponse$Builder vpcEndpointErrors(java.util.Collection<software.amazon.awssdk.services.opensearch.model.VpcEndpointError>);
    Code:
       0: aload_0
       1: aload_1
       2: invokestatic  #25                 // Method software/amazon/awssdk/services/opensearch/model/VpcEndpointErrorListCopier.copy:(Ljava/util/Collection;)Ljava/util/List;
       5: putfield      #3                  // Field vpcEndpointErrors:Ljava/util/List;
       8: aload_0
       9: areturn

  public final software.amazon.awssdk.services.opensearch.model.DescribeVpcEndpointsResponse$Builder vpcEndpointErrors(software.amazon.awssdk.services.opensearch.model.VpcEndpointError...);
    Code:
       0: aload_0
       1: aload_1
       2: invokestatic  #16                 // Method java/util/Arrays.asList:([Ljava/lang/Object;)Ljava/util/List;
       5: invokevirtual #11                 // Method vpcEndpointErrors:(Ljava/util/Collection;)Lsoftware/amazon/awssdk/services/opensearch/model/DescribeVpcEndpointsResponse$Builder;
       8: pop
       9: aload_0
      10: areturn

  public final software.amazon.awssdk.services.opensearch.model.DescribeVpcEndpointsResponse$Builder vpcEndpointErrors(java.util.function.Consumer<software.amazon.awssdk.services.opensearch.model.VpcEndpointError$Builder>...);
    Code:
       0: aload_0
       1: aload_1
       2: invokestatic  #17                 // InterfaceMethod java/util/stream/Stream.of:([Ljava/lang/Object;)Ljava/util/stream/Stream;
       5: invokedynamic #26,  0             // InvokeDynamic #1:apply:()Ljava/util/function/Function;
      10: invokeinterface #19,  2           // InterfaceMethod java/util/stream/Stream.map:(Ljava/util/function/Function;)Ljava/util/stream/Stream;
      15: invokestatic  #20                 // Method java/util/stream/Collectors.toList:()Ljava/util/stream/Collector;
      18: invokeinterface #21,  2           // InterfaceMethod java/util/stream/Stream.collect:(Ljava/util/stream/Collector;)Ljava/lang/Object;
      23: checkcast     #22                 // class java/util/Collection
      26: invokevirtual #11                 // Method vpcEndpointErrors:(Ljava/util/Collection;)Lsoftware/amazon/awssdk/services/opensearch/model/DescribeVpcEndpointsResponse$Builder;
      29: pop
      30: aload_0
      31: areturn

  public software.amazon.awssdk.services.opensearch.model.DescribeVpcEndpointsResponse build();
    Code:
       0: new           #27                 // class software/amazon/awssdk/services/opensearch/model/DescribeVpcEndpointsResponse
       3: dup
       4: aload_0
       5: aconst_null
       6: invokespecial #28                 // Method software/amazon/awssdk/services/opensearch/model/DescribeVpcEndpointsResponse."<init>":(Lsoftware/amazon/awssdk/services/opensearch/model/DescribeVpcEndpointsResponse$BuilderImpl;Lsoftware/amazon/awssdk/services/opensearch/model/DescribeVpcEndpointsResponse$1;)V
       9: areturn

  public java.util.List<software.amazon.awssdk.core.SdkField<?>> sdkFields();
    Code:
       0: invokestatic  #29                 // Method software/amazon/awssdk/services/opensearch/model/DescribeVpcEndpointsResponse.access$700:()Ljava/util/List;
       3: areturn

  public software.amazon.awssdk.services.opensearch.model.OpenSearchResponse build();
    Code:
       0: aload_0
       1: invokevirtual #30                 // Method build:()Lsoftware/amazon/awssdk/services/opensearch/model/DescribeVpcEndpointsResponse;
       4: areturn

  public software.amazon.awssdk.awscore.AwsResponse build();
    Code:
       0: aload_0
       1: invokevirtual #30                 // Method build:()Lsoftware/amazon/awssdk/services/opensearch/model/DescribeVpcEndpointsResponse;
       4: areturn

  public software.amazon.awssdk.core.SdkResponse build();
    Code:
       0: aload_0
       1: invokevirtual #30                 // Method build:()Lsoftware/amazon/awssdk/services/opensearch/model/DescribeVpcEndpointsResponse;
       4: areturn

  public java.lang.Object build();
    Code:
       0: aload_0
       1: invokevirtual #30                 // Method build:()Lsoftware/amazon/awssdk/services/opensearch/model/DescribeVpcEndpointsResponse;
       4: areturn

  private static software.amazon.awssdk.services.opensearch.model.VpcEndpointError lambda$vpcEndpointErrors$1(java.util.function.Consumer);
    Code:
       0: invokestatic  #31                 // Method software/amazon/awssdk/services/opensearch/model/VpcEndpointError.builder:()Lsoftware/amazon/awssdk/services/opensearch/model/VpcEndpointError$Builder;
       3: aload_0
       4: invokeinterface #32,  2           // InterfaceMethod software/amazon/awssdk/services/opensearch/model/VpcEndpointError$Builder.applyMutation:(Ljava/util/function/Consumer;)Lsoftware/amazon/awssdk/utils/builder/SdkBuilder;
       9: checkcast     #33                 // class software/amazon/awssdk/services/opensearch/model/VpcEndpointError$Builder
      12: invokeinterface #34,  1           // InterfaceMethod software/amazon/awssdk/services/opensearch/model/VpcEndpointError$Builder.build:()Ljava/lang/Object;
      17: checkcast     #35                 // class software/amazon/awssdk/services/opensearch/model/VpcEndpointError
      20: areturn

  private static software.amazon.awssdk.services.opensearch.model.VpcEndpoint lambda$vpcEndpoints$0(java.util.function.Consumer);
    Code:
       0: invokestatic  #36                 // Method software/amazon/awssdk/services/opensearch/model/VpcEndpoint.builder:()Lsoftware/amazon/awssdk/services/opensearch/model/VpcEndpoint$Builder;
       3: aload_0
       4: invokeinterface #37,  2           // InterfaceMethod software/amazon/awssdk/services/opensearch/model/VpcEndpoint$Builder.applyMutation:(Ljava/util/function/Consumer;)Lsoftware/amazon/awssdk/utils/builder/SdkBuilder;
       9: checkcast     #38                 // class software/amazon/awssdk/services/opensearch/model/VpcEndpoint$Builder
      12: invokeinterface #39,  1           // InterfaceMethod software/amazon/awssdk/services/opensearch/model/VpcEndpoint$Builder.build:()Ljava/lang/Object;
      17: checkcast     #40                 // class software/amazon/awssdk/services/opensearch/model/VpcEndpoint
      20: areturn

  static java.util.List access$000(software.amazon.awssdk.services.opensearch.model.DescribeVpcEndpointsResponse$BuilderImpl);
    Code:
       0: aload_0
       1: getfield      #4                  // Field vpcEndpoints:Ljava/util/List;
       4: areturn

  static java.util.List access$100(software.amazon.awssdk.services.opensearch.model.DescribeVpcEndpointsResponse$BuilderImpl);
    Code:
       0: aload_0
       1: getfield      #3                  // Field vpcEndpointErrors:Ljava/util/List;
       4: areturn

  software.amazon.awssdk.services.opensearch.model.DescribeVpcEndpointsResponse$BuilderImpl(software.amazon.awssdk.services.opensearch.model.DescribeVpcEndpointsResponse, software.amazon.awssdk.services.opensearch.model.DescribeVpcEndpointsResponse$1);
    Code:
       0: aload_0
       1: aload_1
       2: invokespecial #2                  // Method "<init>":(Lsoftware/amazon/awssdk/services/opensearch/model/DescribeVpcEndpointsResponse;)V
       5: return

  software.amazon.awssdk.services.opensearch.model.DescribeVpcEndpointsResponse$BuilderImpl(software.amazon.awssdk.services.opensearch.model.DescribeVpcEndpointsResponse$1);
    Code:
       0: aload_0
       1: invokespecial #1                  // Method "<init>":()V
       4: return
}
