Compiled from "AdamsBashforthFieldIntegrator.java"
public class org.apache.commons.math3.ode.nonstiff.AdamsBashforthFieldIntegrator<T extends org.apache.commons.math3.RealFieldElement<T>> extends org.apache.commons.math3.ode.nonstiff.AdamsFieldIntegrator<T> {
  private static final java.lang.String METHOD_NAME;

  public org.apache.commons.math3.ode.nonstiff.AdamsBashforthFieldIntegrator(org.apache.commons.math3.Field<T>, int, double, double, double, double) throws org.apache.commons.math3.exception.NumberIsTooSmallException;
    Code:
       0: aload_0
       1: aload_1
       2: ldc           #1                  // String Adams-Bashforth
       4: iload_2
       5: iload_2
       6: dload_3
       7: dload         5
       9: dload         7
      11: dload         9
      13: invokespecial #2                  // Method org/apache/commons/math3/ode/nonstiff/AdamsFieldIntegrator."<init>":(Lorg/apache/commons/math3/Field;Ljava/lang/String;IIDDDD)V
      16: return

  public org.apache.commons.math3.ode.nonstiff.AdamsBashforthFieldIntegrator(org.apache.commons.math3.Field<T>, int, double, double, double[], double[]) throws java.lang.IllegalArgumentException;
    Code:
       0: aload_0
       1: aload_1
       2: ldc           #1                  // String Adams-Bashforth
       4: iload_2
       5: iload_2
       6: dload_3
       7: dload         5
       9: aload         7
      11: aload         8
      13: invokespecial #3                  // Method org/apache/commons/math3/ode/nonstiff/AdamsFieldIntegrator."<init>":(Lorg/apache/commons/math3/Field;Ljava/lang/String;IIDD[D[D)V
      16: return

  private T errorEstimation(T[], T[], T[], org.apache.commons.math3.linear.FieldMatrix<T>);
    Code:
       0: aload_0
       1: invokevirtual #4                  // Method getField:()Lorg/apache/commons/math3/Field;
       4: invokeinterface #5,  1            // InterfaceMethod org/apache/commons/math3/Field.getZero:()Ljava/lang/Object;
       9: checkcast     #6                  // class org/apache/commons/math3/RealFieldElement
      12: astore        5
      14: iconst_0
      15: istore        6
      17: iload         6
      19: aload_0
      20: getfield      #7                  // Field mainSetDimension:I
      23: if_icmpge     284
      26: aload_2
      27: iload         6
      29: aaload
      30: invokeinterface #8,  1            // InterfaceMethod org/apache/commons/math3/RealFieldElement.abs:()Ljava/lang/Object;
      35: checkcast     #6                  // class org/apache/commons/math3/RealFieldElement
      38: astore        7
      40: aload_0
      41: getfield      #9                  // Field vecAbsoluteTolerance:[D
      44: ifnonnull     76
      47: aload         7
      49: aload_0
      50: getfield      #10                 // Field scalRelativeTolerance:D
      53: invokeinterface #11,  3           // InterfaceMethod org/apache/commons/math3/RealFieldElement.multiply:(D)Ljava/lang/Object;
      58: checkcast     #6                  // class org/apache/commons/math3/RealFieldElement
      61: aload_0
      62: getfield      #12                 // Field scalAbsoluteTolerance:D
      65: invokeinterface #13,  3           // InterfaceMethod org/apache/commons/math3/RealFieldElement.add:(D)Ljava/lang/Object;
      70: checkcast     #6                  // class org/apache/commons/math3/RealFieldElement
      73: goto          108
      76: aload         7
      78: aload_0
      79: getfield      #14                 // Field vecRelativeTolerance:[D
      82: iload         6
      84: daload
      85: invokeinterface #11,  3           // InterfaceMethod org/apache/commons/math3/RealFieldElement.multiply:(D)Ljava/lang/Object;
      90: checkcast     #6                  // class org/apache/commons/math3/RealFieldElement
      93: aload_0
      94: getfield      #9                  // Field vecAbsoluteTolerance:[D
      97: iload         6
      99: daload
     100: invokeinterface #13,  3           // InterfaceMethod org/apache/commons/math3/RealFieldElement.add:(D)Ljava/lang/Object;
     105: checkcast     #6                  // class org/apache/commons/math3/RealFieldElement
     108: astore        8
     110: aload_0
     111: invokevirtual #4                  // Method getField:()Lorg/apache/commons/math3/Field;
     114: invokeinterface #5,  1            // InterfaceMethod org/apache/commons/math3/Field.getZero:()Ljava/lang/Object;
     119: checkcast     #6                  // class org/apache/commons/math3/RealFieldElement
     122: astore        9
     124: aload         4
     126: invokeinterface #15,  1           // InterfaceMethod org/apache/commons/math3/linear/FieldMatrix.getRowDimension:()I
     131: iconst_2
     132: irem
     133: ifne          140
     136: iconst_m1
     137: goto          141
     140: iconst_1
     141: istore        10
     143: aload         4
     145: invokeinterface #15,  1           // InterfaceMethod org/apache/commons/math3/linear/FieldMatrix.getRowDimension:()I
     150: iconst_1
     151: isub
     152: istore        11
     154: iload         11
     156: iflt          203
     159: aload         9
     161: aload         4
     163: iload         11
     165: iload         6
     167: invokeinterface #16,  3           // InterfaceMethod org/apache/commons/math3/linear/FieldMatrix.getEntry:(II)Lorg/apache/commons/math3/FieldElement;
     172: checkcast     #6                  // class org/apache/commons/math3/RealFieldElement
     175: iload         10
     177: invokeinterface #17,  2           // InterfaceMethod org/apache/commons/math3/RealFieldElement.multiply:(I)Ljava/lang/Object;
     182: invokeinterface #18,  2           // InterfaceMethod org/apache/commons/math3/RealFieldElement.add:(Ljava/lang/Object;)Ljava/lang/Object;
     187: checkcast     #6                  // class org/apache/commons/math3/RealFieldElement
     190: astore        9
     192: iload         10
     194: ineg
     195: istore        10
     197: iinc          11, -1
     200: goto          154
     203: aload         9
     205: aload_3
     206: iload         6
     208: aaload
     209: invokeinterface #19,  2           // InterfaceMethod org/apache/commons/math3/RealFieldElement.subtract:(Ljava/lang/Object;)Ljava/lang/Object;
     214: checkcast     #6                  // class org/apache/commons/math3/RealFieldElement
     217: astore        9
     219: aload_2
     220: iload         6
     222: aaload
     223: aload_1
     224: iload         6
     226: aaload
     227: invokeinterface #19,  2           // InterfaceMethod org/apache/commons/math3/RealFieldElement.subtract:(Ljava/lang/Object;)Ljava/lang/Object;
     232: checkcast     #6                  // class org/apache/commons/math3/RealFieldElement
     235: aload         9
     237: invokeinterface #18,  2           // InterfaceMethod org/apache/commons/math3/RealFieldElement.add:(Ljava/lang/Object;)Ljava/lang/Object;
     242: checkcast     #6                  // class org/apache/commons/math3/RealFieldElement
     245: aload         8
     247: invokeinterface #20,  2           // InterfaceMethod org/apache/commons/math3/RealFieldElement.divide:(Ljava/lang/Object;)Ljava/lang/Object;
     252: checkcast     #6                  // class org/apache/commons/math3/RealFieldElement
     255: astore        11
     257: aload         5
     259: aload         11
     261: aload         11
     263: invokeinterface #21,  2           // InterfaceMethod org/apache/commons/math3/RealFieldElement.multiply:(Ljava/lang/Object;)Ljava/lang/Object;
     268: invokeinterface #18,  2           // InterfaceMethod org/apache/commons/math3/RealFieldElement.add:(Ljava/lang/Object;)Ljava/lang/Object;
     273: checkcast     #6                  // class org/apache/commons/math3/RealFieldElement
     276: astore        5
     278: iinc          6, 1
     281: goto          17
     284: aload         5
     286: aload_0
     287: getfield      #7                  // Field mainSetDimension:I
     290: i2d
     291: invokeinterface #22,  3           // InterfaceMethod org/apache/commons/math3/RealFieldElement.divide:(D)Ljava/lang/Object;
     296: checkcast     #6                  // class org/apache/commons/math3/RealFieldElement
     299: invokeinterface #23,  1           // InterfaceMethod org/apache/commons/math3/RealFieldElement.sqrt:()Ljava/lang/Object;
     304: checkcast     #6                  // class org/apache/commons/math3/RealFieldElement
     307: areturn

  public org.apache.commons.math3.ode.FieldODEStateAndDerivative<T> integrate(org.apache.commons.math3.ode.FieldExpandableODE<T>, org.apache.commons.math3.ode.FieldODEState<T>, T) throws org.apache.commons.math3.exception.NumberIsTooSmallException, org.apache.commons.math3.exception.DimensionMismatchException, org.apache.commons.math3.exception.MaxCountExceededException, org.apache.commons.math3.exception.NoBracketingException;
    Code:
       0: aload_0
       1: aload_2
       2: aload_3
       3: invokevirtual #24                 // Method sanityChecks:(Lorg/apache/commons/math3/ode/FieldODEState;Lorg/apache/commons/math3/RealFieldElement;)V
       6: aload_2
       7: invokevirtual #25                 // Method org/apache/commons/math3/ode/FieldODEState.getTime:()Lorg/apache/commons/math3/RealFieldElement;
      10: astore        4
      12: aload_1
      13: invokevirtual #26                 // Method org/apache/commons/math3/ode/FieldExpandableODE.getMapper:()Lorg/apache/commons/math3/ode/FieldEquationsMapper;
      16: aload_2
      17: invokevirtual #27                 // Method org/apache/commons/math3/ode/FieldEquationsMapper.mapState:(Lorg/apache/commons/math3/ode/FieldODEState;)[Lorg/apache/commons/math3/RealFieldElement;
      20: astore        5
      22: aload_0
      23: aload_0
      24: aload_1
      25: aload         4
      27: aload         5
      29: aload_3
      30: invokevirtual #28                 // Method initIntegration:(Lorg/apache/commons/math3/ode/FieldExpandableODE;Lorg/apache/commons/math3/RealFieldElement;[Lorg/apache/commons/math3/RealFieldElement;Lorg/apache/commons/math3/RealFieldElement;)Lorg/apache/commons/math3/ode/FieldODEStateAndDerivative;
      33: invokevirtual #29                 // Method setStepStart:(Lorg/apache/commons/math3/ode/FieldODEStateAndDerivative;)V
      36: aload_3
      37: aload_2
      38: invokevirtual #25                 // Method org/apache/commons/math3/ode/FieldODEState.getTime:()Lorg/apache/commons/math3/RealFieldElement;
      41: invokeinterface #19,  2           // InterfaceMethod org/apache/commons/math3/RealFieldElement.subtract:(Ljava/lang/Object;)Ljava/lang/Object;
      46: checkcast     #6                  // class org/apache/commons/math3/RealFieldElement
      49: invokeinterface #30,  1           // InterfaceMethod org/apache/commons/math3/RealFieldElement.getReal:()D
      54: dconst_0
      55: dcmpl
      56: ifle          63
      59: iconst_1
      60: goto          64
      63: iconst_0
      64: istore        6
      66: aload_0
      67: aload_1
      68: aload_0
      69: invokevirtual #31                 // Method getStepStart:()Lorg/apache/commons/math3/ode/FieldODEStateAndDerivative;
      72: aload_3
      73: invokevirtual #32                 // Method start:(Lorg/apache/commons/math3/ode/FieldExpandableODE;Lorg/apache/commons/math3/ode/FieldODEState;Lorg/apache/commons/math3/RealFieldElement;)V
      76: aload_0
      77: invokevirtual #31                 // Method getStepStart:()Lorg/apache/commons/math3/ode/FieldODEStateAndDerivative;
      80: astore        7
      82: aload         7
      84: aload         7
      86: invokevirtual #33                 // Method org/apache/commons/math3/ode/FieldODEStateAndDerivative.getTime:()Lorg/apache/commons/math3/RealFieldElement;
      89: aload_0
      90: invokevirtual #34                 // Method getStepSize:()Lorg/apache/commons/math3/RealFieldElement;
      93: invokeinterface #18,  2           // InterfaceMethod org/apache/commons/math3/RealFieldElement.add:(Ljava/lang/Object;)Ljava/lang/Object;
      98: checkcast     #6                  // class org/apache/commons/math3/RealFieldElement
     101: aload_0
     102: invokevirtual #34                 // Method getStepSize:()Lorg/apache/commons/math3/RealFieldElement;
     105: aload_0
     106: getfield      #35                 // Field scaled:[Lorg/apache/commons/math3/RealFieldElement;
     109: aload_0
     110: getfield      #36                 // Field nordsieck:Lorg/apache/commons/math3/linear/Array2DRowFieldMatrix;
     113: invokestatic  #37                 // Method org/apache/commons/math3/ode/nonstiff/AdamsFieldStepInterpolator.taylor:(Lorg/apache/commons/math3/ode/FieldODEStateAndDerivative;Lorg/apache/commons/math3/RealFieldElement;Lorg/apache/commons/math3/RealFieldElement;[Lorg/apache/commons/math3/RealFieldElement;Lorg/apache/commons/math3/linear/Array2DRowFieldMatrix;)Lorg/apache/commons/math3/ode/FieldODEStateAndDerivative;
     116: astore        8
     118: aload_0
     119: iconst_0
     120: invokevirtual #38                 // Method setIsLastStep:(Z)V
     123: aconst_null
     124: astore        9
     126: aload_0
     127: invokevirtual #4                  // Method getField:()Lorg/apache/commons/math3/Field;
     130: aload         5
     132: arraylength
     133: invokestatic  #39                 // Method org/apache/commons/math3/util/MathArrays.buildArray:(Lorg/apache/commons/math3/Field;I)[Ljava/lang/Object;
     136: checkcast     #40                 // class "[Lorg/apache/commons/math3/RealFieldElement;"
     139: astore        10
     141: aconst_null
     142: astore        11
     144: aload_0
     145: invokevirtual #4                  // Method getField:()Lorg/apache/commons/math3/Field;
     148: invokeinterface #5,  1            // InterfaceMethod org/apache/commons/math3/Field.getZero:()Ljava/lang/Object;
     153: checkcast     #6                  // class org/apache/commons/math3/RealFieldElement
     156: ldc2_w        #41                 // double 10.0d
     159: invokeinterface #13,  3           // InterfaceMethod org/apache/commons/math3/RealFieldElement.add:(D)Ljava/lang/Object;
     164: checkcast     #6                  // class org/apache/commons/math3/RealFieldElement
     167: astore        12
     169: aload         12
     171: dconst_1
     172: invokeinterface #43,  3           // InterfaceMethod org/apache/commons/math3/RealFieldElement.subtract:(D)Ljava/lang/Object;
     177: checkcast     #6                  // class org/apache/commons/math3/RealFieldElement
     180: invokeinterface #30,  1           // InterfaceMethod org/apache/commons/math3/RealFieldElement.getReal:()D
     185: dconst_0
     186: dcmpl
     187: iflt          382
     190: aload         8
     192: invokevirtual #44                 // Method org/apache/commons/math3/ode/FieldODEStateAndDerivative.getState:()[Lorg/apache/commons/math3/RealFieldElement;
     195: astore        9
     197: aload_0
     198: aload         8
     200: invokevirtual #33                 // Method org/apache/commons/math3/ode/FieldODEStateAndDerivative.getTime:()Lorg/apache/commons/math3/RealFieldElement;
     203: aload         9
     205: invokevirtual #45                 // Method computeDerivatives:(Lorg/apache/commons/math3/RealFieldElement;[Lorg/apache/commons/math3/RealFieldElement;)[Lorg/apache/commons/math3/RealFieldElement;
     208: astore        13
     210: iconst_0
     211: istore        14
     213: iload         14
     215: aload         10
     217: arraylength
     218: if_icmpge     249
     221: aload         10
     223: iload         14
     225: aload_0
     226: invokevirtual #34                 // Method getStepSize:()Lorg/apache/commons/math3/RealFieldElement;
     229: aload         13
     231: iload         14
     233: aaload
     234: invokeinterface #21,  2           // InterfaceMethod org/apache/commons/math3/RealFieldElement.multiply:(Ljava/lang/Object;)Ljava/lang/Object;
     239: checkcast     #6                  // class org/apache/commons/math3/RealFieldElement
     242: aastore
     243: iinc          14, 1
     246: goto          213
     249: aload_0
     250: aload_0
     251: getfield      #36                 // Field nordsieck:Lorg/apache/commons/math3/linear/Array2DRowFieldMatrix;
     254: invokevirtual #46                 // Method updateHighOrderDerivativesPhase1:(Lorg/apache/commons/math3/linear/Array2DRowFieldMatrix;)Lorg/apache/commons/math3/linear/Array2DRowFieldMatrix;
     257: astore        11
     259: aload_0
     260: aload_0
     261: getfield      #35                 // Field scaled:[Lorg/apache/commons/math3/RealFieldElement;
     264: aload         10
     266: aload         11
     268: invokevirtual #47                 // Method updateHighOrderDerivativesPhase2:([Lorg/apache/commons/math3/RealFieldElement;[Lorg/apache/commons/math3/RealFieldElement;Lorg/apache/commons/math3/linear/Array2DRowFieldMatrix;)V
     271: aload_0
     272: aload         5
     274: aload         9
     276: aload         10
     278: aload         11
     280: invokespecial #48                 // Method errorEstimation:([Lorg/apache/commons/math3/RealFieldElement;[Lorg/apache/commons/math3/RealFieldElement;[Lorg/apache/commons/math3/RealFieldElement;Lorg/apache/commons/math3/linear/FieldMatrix;)Lorg/apache/commons/math3/RealFieldElement;
     283: astore        12
     285: aload         12
     287: dconst_1
     288: invokeinterface #43,  3           // InterfaceMethod org/apache/commons/math3/RealFieldElement.subtract:(D)Ljava/lang/Object;
     293: checkcast     #6                  // class org/apache/commons/math3/RealFieldElement
     296: invokeinterface #30,  1           // InterfaceMethod org/apache/commons/math3/RealFieldElement.getReal:()D
     301: dconst_0
     302: dcmpl
     303: iflt          379
     306: aload_0
     307: aload         12
     309: invokevirtual #49                 // Method computeStepGrowShrinkFactor:(Lorg/apache/commons/math3/RealFieldElement;)Lorg/apache/commons/math3/RealFieldElement;
     312: astore        14
     314: aload_0
     315: aload_0
     316: aload_0
     317: invokevirtual #34                 // Method getStepSize:()Lorg/apache/commons/math3/RealFieldElement;
     320: aload         14
     322: invokeinterface #21,  2           // InterfaceMethod org/apache/commons/math3/RealFieldElement.multiply:(Ljava/lang/Object;)Ljava/lang/Object;
     327: checkcast     #6                  // class org/apache/commons/math3/RealFieldElement
     330: iload         6
     332: iconst_0
     333: invokevirtual #50                 // Method filterStep:(Lorg/apache/commons/math3/RealFieldElement;ZZ)Lorg/apache/commons/math3/RealFieldElement;
     336: invokevirtual #51                 // Method rescale:(Lorg/apache/commons/math3/RealFieldElement;)V
     339: aload_0
     340: invokevirtual #31                 // Method getStepStart:()Lorg/apache/commons/math3/ode/FieldODEStateAndDerivative;
     343: aload_0
     344: invokevirtual #31                 // Method getStepStart:()Lorg/apache/commons/math3/ode/FieldODEStateAndDerivative;
     347: invokevirtual #33                 // Method org/apache/commons/math3/ode/FieldODEStateAndDerivative.getTime:()Lorg/apache/commons/math3/RealFieldElement;
     350: aload_0
     351: invokevirtual #34                 // Method getStepSize:()Lorg/apache/commons/math3/RealFieldElement;
     354: invokeinterface #18,  2           // InterfaceMethod org/apache/commons/math3/RealFieldElement.add:(Ljava/lang/Object;)Ljava/lang/Object;
     359: checkcast     #6                  // class org/apache/commons/math3/RealFieldElement
     362: aload_0
     363: invokevirtual #34                 // Method getStepSize:()Lorg/apache/commons/math3/RealFieldElement;
     366: aload_0
     367: getfield      #35                 // Field scaled:[Lorg/apache/commons/math3/RealFieldElement;
     370: aload_0
     371: getfield      #36                 // Field nordsieck:Lorg/apache/commons/math3/linear/Array2DRowFieldMatrix;
     374: invokestatic  #37                 // Method org/apache/commons/math3/ode/nonstiff/AdamsFieldStepInterpolator.taylor:(Lorg/apache/commons/math3/ode/FieldODEStateAndDerivative;Lorg/apache/commons/math3/RealFieldElement;Lorg/apache/commons/math3/RealFieldElement;[Lorg/apache/commons/math3/RealFieldElement;Lorg/apache/commons/math3/linear/Array2DRowFieldMatrix;)Lorg/apache/commons/math3/ode/FieldODEStateAndDerivative;
     377: astore        8
     379: goto          169
     382: aload_0
     383: aload_0
     384: new           #52                 // class org/apache/commons/math3/ode/nonstiff/AdamsFieldStepInterpolator
     387: dup
     388: aload_0
     389: invokevirtual #34                 // Method getStepSize:()Lorg/apache/commons/math3/RealFieldElement;
     392: aload         8
     394: aload         10
     396: aload         11
     398: iload         6
     400: aload_0
     401: invokevirtual #31                 // Method getStepStart:()Lorg/apache/commons/math3/ode/FieldODEStateAndDerivative;
     404: aload         8
     406: aload_1
     407: invokevirtual #26                 // Method org/apache/commons/math3/ode/FieldExpandableODE.getMapper:()Lorg/apache/commons/math3/ode/FieldEquationsMapper;
     410: invokespecial #53                 // Method org/apache/commons/math3/ode/nonstiff/AdamsFieldStepInterpolator."<init>":(Lorg/apache/commons/math3/RealFieldElement;Lorg/apache/commons/math3/ode/FieldODEStateAndDerivative;[Lorg/apache/commons/math3/RealFieldElement;Lorg/apache/commons/math3/linear/Array2DRowFieldMatrix;ZLorg/apache/commons/math3/ode/FieldODEStateAndDerivative;Lorg/apache/commons/math3/ode/FieldODEStateAndDerivative;Lorg/apache/commons/math3/ode/FieldEquationsMapper;)V
     413: aload_3
     414: invokevirtual #54                 // Method acceptStep:(Lorg/apache/commons/math3/ode/sampling/AbstractFieldStepInterpolator;Lorg/apache/commons/math3/RealFieldElement;)Lorg/apache/commons/math3/ode/FieldODEStateAndDerivative;
     417: invokevirtual #29                 // Method setStepStart:(Lorg/apache/commons/math3/ode/FieldODEStateAndDerivative;)V
     420: aload_0
     421: aload         10
     423: putfield      #35                 // Field scaled:[Lorg/apache/commons/math3/RealFieldElement;
     426: aload_0
     427: aload         11
     429: putfield      #36                 // Field nordsieck:Lorg/apache/commons/math3/linear/Array2DRowFieldMatrix;
     432: aload_0
     433: invokevirtual #55                 // Method isLastStep:()Z
     436: ifne          735
     439: aload         9
     441: iconst_0
     442: aload         5
     444: iconst_0
     445: aload         5
     447: arraylength
     448: invokestatic  #56                 // Method java/lang/System.arraycopy:(Ljava/lang/Object;ILjava/lang/Object;II)V
     451: aload_0
     452: invokevirtual #57                 // Method resetOccurred:()Z
     455: ifeq          468
     458: aload_0
     459: aload_1
     460: aload_0
     461: invokevirtual #31                 // Method getStepStart:()Lorg/apache/commons/math3/ode/FieldODEStateAndDerivative;
     464: aload_3
     465: invokevirtual #32                 // Method start:(Lorg/apache/commons/math3/ode/FieldExpandableODE;Lorg/apache/commons/math3/ode/FieldODEState;Lorg/apache/commons/math3/RealFieldElement;)V
     468: aload_0
     469: aload         12
     471: invokevirtual #49                 // Method computeStepGrowShrinkFactor:(Lorg/apache/commons/math3/RealFieldElement;)Lorg/apache/commons/math3/RealFieldElement;
     474: astore        13
     476: aload_0
     477: invokevirtual #34                 // Method getStepSize:()Lorg/apache/commons/math3/RealFieldElement;
     480: aload         13
     482: invokeinterface #21,  2           // InterfaceMethod org/apache/commons/math3/RealFieldElement.multiply:(Ljava/lang/Object;)Ljava/lang/Object;
     487: checkcast     #6                  // class org/apache/commons/math3/RealFieldElement
     490: astore        14
     492: aload_0
     493: invokevirtual #31                 // Method getStepStart:()Lorg/apache/commons/math3/ode/FieldODEStateAndDerivative;
     496: invokevirtual #33                 // Method org/apache/commons/math3/ode/FieldODEStateAndDerivative.getTime:()Lorg/apache/commons/math3/RealFieldElement;
     499: aload         14
     501: invokeinterface #18,  2           // InterfaceMethod org/apache/commons/math3/RealFieldElement.add:(Ljava/lang/Object;)Ljava/lang/Object;
     506: checkcast     #6                  // class org/apache/commons/math3/RealFieldElement
     509: astore        15
     511: iload         6
     513: ifeq          545
     516: aload         15
     518: aload_3
     519: invokeinterface #19,  2           // InterfaceMethod org/apache/commons/math3/RealFieldElement.subtract:(Ljava/lang/Object;)Ljava/lang/Object;
     524: checkcast     #6                  // class org/apache/commons/math3/RealFieldElement
     527: invokeinterface #30,  1           // InterfaceMethod org/apache/commons/math3/RealFieldElement.getReal:()D
     532: dconst_0
     533: dcmpl
     534: iflt          541
     537: iconst_1
     538: goto          571
     541: iconst_0
     542: goto          571
     545: aload         15
     547: aload_3
     548: invokeinterface #19,  2           // InterfaceMethod org/apache/commons/math3/RealFieldElement.subtract:(Ljava/lang/Object;)Ljava/lang/Object;
     553: checkcast     #6                  // class org/apache/commons/math3/RealFieldElement
     556: invokeinterface #30,  1           // InterfaceMethod org/apache/commons/math3/RealFieldElement.getReal:()D
     561: dconst_0
     562: dcmpg
     563: ifgt          570
     566: iconst_1
     567: goto          571
     570: iconst_0
     571: istore        16
     573: aload_0
     574: aload         14
     576: iload         6
     578: iload         16
     580: invokevirtual #50                 // Method filterStep:(Lorg/apache/commons/math3/RealFieldElement;ZZ)Lorg/apache/commons/math3/RealFieldElement;
     583: astore        17
     585: aload_0
     586: invokevirtual #31                 // Method getStepStart:()Lorg/apache/commons/math3/ode/FieldODEStateAndDerivative;
     589: invokevirtual #33                 // Method org/apache/commons/math3/ode/FieldODEStateAndDerivative.getTime:()Lorg/apache/commons/math3/RealFieldElement;
     592: aload         17
     594: invokeinterface #18,  2           // InterfaceMethod org/apache/commons/math3/RealFieldElement.add:(Ljava/lang/Object;)Ljava/lang/Object;
     599: checkcast     #6                  // class org/apache/commons/math3/RealFieldElement
     602: astore        18
     604: iload         6
     606: ifeq          638
     609: aload         18
     611: aload_3
     612: invokeinterface #19,  2           // InterfaceMethod org/apache/commons/math3/RealFieldElement.subtract:(Ljava/lang/Object;)Ljava/lang/Object;
     617: checkcast     #6                  // class org/apache/commons/math3/RealFieldElement
     620: invokeinterface #30,  1           // InterfaceMethod org/apache/commons/math3/RealFieldElement.getReal:()D
     625: dconst_0
     626: dcmpl
     627: iflt          634
     630: iconst_1
     631: goto          664
     634: iconst_0
     635: goto          664
     638: aload         18
     640: aload_3
     641: invokeinterface #19,  2           // InterfaceMethod org/apache/commons/math3/RealFieldElement.subtract:(Ljava/lang/Object;)Ljava/lang/Object;
     646: checkcast     #6                  // class org/apache/commons/math3/RealFieldElement
     649: invokeinterface #30,  1           // InterfaceMethod org/apache/commons/math3/RealFieldElement.getReal:()D
     654: dconst_0
     655: dcmpg
     656: ifgt          663
     659: iconst_1
     660: goto          664
     663: iconst_0
     664: istore        19
     666: iload         19
     668: ifeq          689
     671: aload_3
     672: aload_0
     673: invokevirtual #31                 // Method getStepStart:()Lorg/apache/commons/math3/ode/FieldODEStateAndDerivative;
     676: invokevirtual #33                 // Method org/apache/commons/math3/ode/FieldODEStateAndDerivative.getTime:()Lorg/apache/commons/math3/RealFieldElement;
     679: invokeinterface #19,  2           // InterfaceMethod org/apache/commons/math3/RealFieldElement.subtract:(Ljava/lang/Object;)Ljava/lang/Object;
     684: checkcast     #6                  // class org/apache/commons/math3/RealFieldElement
     687: astore        17
     689: aload_0
     690: aload         17
     692: invokevirtual #51                 // Method rescale:(Lorg/apache/commons/math3/RealFieldElement;)V
     695: aload_0
     696: invokevirtual #31                 // Method getStepStart:()Lorg/apache/commons/math3/ode/FieldODEStateAndDerivative;
     699: aload_0
     700: invokevirtual #31                 // Method getStepStart:()Lorg/apache/commons/math3/ode/FieldODEStateAndDerivative;
     703: invokevirtual #33                 // Method org/apache/commons/math3/ode/FieldODEStateAndDerivative.getTime:()Lorg/apache/commons/math3/RealFieldElement;
     706: aload_0
     707: invokevirtual #34                 // Method getStepSize:()Lorg/apache/commons/math3/RealFieldElement;
     710: invokeinterface #18,  2           // InterfaceMethod org/apache/commons/math3/RealFieldElement.add:(Ljava/lang/Object;)Ljava/lang/Object;
     715: checkcast     #6                  // class org/apache/commons/math3/RealFieldElement
     718: aload_0
     719: invokevirtual #34                 // Method getStepSize:()Lorg/apache/commons/math3/RealFieldElement;
     722: aload_0
     723: getfield      #35                 // Field scaled:[Lorg/apache/commons/math3/RealFieldElement;
     726: aload_0
     727: getfield      #36                 // Field nordsieck:Lorg/apache/commons/math3/linear/Array2DRowFieldMatrix;
     730: invokestatic  #37                 // Method org/apache/commons/math3/ode/nonstiff/AdamsFieldStepInterpolator.taylor:(Lorg/apache/commons/math3/ode/FieldODEStateAndDerivative;Lorg/apache/commons/math3/RealFieldElement;Lorg/apache/commons/math3/RealFieldElement;[Lorg/apache/commons/math3/RealFieldElement;Lorg/apache/commons/math3/linear/Array2DRowFieldMatrix;)Lorg/apache/commons/math3/ode/FieldODEStateAndDerivative;
     733: astore        8
     735: aload_0
     736: invokevirtual #55                 // Method isLastStep:()Z
     739: ifeq          123
     742: aload_0
     743: invokevirtual #31                 // Method getStepStart:()Lorg/apache/commons/math3/ode/FieldODEStateAndDerivative;
     746: astore        9
     748: aload_0
     749: aconst_null
     750: invokevirtual #29                 // Method setStepStart:(Lorg/apache/commons/math3/ode/FieldODEStateAndDerivative;)V
     753: aload_0
     754: aconst_null
     755: invokevirtual #58                 // Method setStepSize:(Lorg/apache/commons/math3/RealFieldElement;)V
     758: aload         9
     760: areturn
}
