Compiled from "DefaultUnitOfWork.java"
public class org.apache.camel.impl.DefaultUnitOfWork implements org.apache.camel.spi.UnitOfWork,org.apache.camel.Service {
  private static final org.slf4j.Logger LOG;

  private org.apache.camel.spi.UnitOfWork parent;

  private java.lang.String id;

  private org.apache.camel.CamelContext context;

  private java.util.List<org.apache.camel.spi.Synchronization> synchronizations;

  private org.apache.camel.Message originalInMessage;

  private final org.apache.camel.spi.TracedRouteNodes tracedRouteNodes;

  private java.util.Set<java.lang.Object> transactedBy;

  private final java.util.Stack<org.apache.camel.spi.RouteContext> routeContextStack;

  private java.util.Stack<org.apache.camel.impl.DefaultSubUnitOfWork> subUnitOfWorks;

  private final transient org.slf4j.Logger log;

  public org.apache.camel.impl.DefaultUnitOfWork(org.apache.camel.Exchange);
    Code:
       0: aload_0
       1: aload_1
       2: getstatic     #37                 // Field LOG:Lorg/slf4j/Logger;
       5: invokespecial #40                 // Method "<init>":(Lorg/apache/camel/Exchange;Lorg/slf4j/Logger;)V
       8: return

  protected org.apache.camel.impl.DefaultUnitOfWork(org.apache.camel.Exchange, org.slf4j.Logger);
    Code:
       0: aload_0
       1: invokespecial #49                 // Method java/lang/Object."<init>":()V
       4: aload_0
       5: new           #51                 // class java/util/Stack
       8: dup
       9: invokespecial #52                 // Method java/util/Stack."<init>":()V
      12: putfield      #54                 // Field routeContextStack:Ljava/util/Stack;
      15: aload_0
      16: aload_2
      17: putfield      #56                 // Field log:Lorg/slf4j/Logger;
      20: aload_0
      21: getfield      #56                 // Field log:Lorg/slf4j/Logger;
      24: invokeinterface #62,  1           // InterfaceMethod org/slf4j/Logger.isTraceEnabled:()Z
      29: ifeq          50
      32: aload_0
      33: getfield      #56                 // Field log:Lorg/slf4j/Logger;
      36: ldc           #64                 // String UnitOfWork created for ExchangeId: {} with {}
      38: aload_1
      39: invokeinterface #70,  1           // InterfaceMethod org/apache/camel/Exchange.getExchangeId:()Ljava/lang/String;
      44: aload_1
      45: invokeinterface #74,  4           // InterfaceMethod org/slf4j/Logger.trace:(Ljava/lang/String;Ljava/lang/Object;Ljava/lang/Object;)V
      50: aload_0
      51: new           #76                 // class org/apache/camel/impl/DefaultTracedRouteNodes
      54: dup
      55: invokespecial #77                 // Method org/apache/camel/impl/DefaultTracedRouteNodes."<init>":()V
      58: putfield      #79                 // Field tracedRouteNodes:Lorg/apache/camel/spi/TracedRouteNodes;
      61: aload_0
      62: aload_1
      63: invokeinterface #83,  1           // InterfaceMethod org/apache/camel/Exchange.getContext:()Lorg/apache/camel/CamelContext;
      68: putfield      #85                 // Field context:Lorg/apache/camel/CamelContext;
      71: aload_1
      72: invokeinterface #89,  1           // InterfaceMethod org/apache/camel/Exchange.getIn:()Lorg/apache/camel/Message;
      77: invokevirtual #93                 // Method java/lang/Object.getClass:()Ljava/lang/Class;
      80: invokevirtual #98                 // Method java/lang/Class.getName:()Ljava/lang/String;
      83: ldc           #100                // String org.apache.camel.component.jms.JmsMessage
      85: invokevirtual #106                // Method java/lang/String.equals:(Ljava/lang/Object;)Z
      88: ifeq          150
      91: aload_0
      92: new           #108                // class org/apache/camel/impl/DefaultMessage
      95: dup
      96: invokespecial #109                // Method org/apache/camel/impl/DefaultMessage."<init>":()V
      99: putfield      #111                // Field originalInMessage:Lorg/apache/camel/Message;
     102: aload_0
     103: getfield      #111                // Field originalInMessage:Lorg/apache/camel/Message;
     106: aload_1
     107: invokeinterface #89,  1           // InterfaceMethod org/apache/camel/Exchange.getIn:()Lorg/apache/camel/Message;
     112: invokeinterface #117,  1          // InterfaceMethod org/apache/camel/Message.getBody:()Ljava/lang/Object;
     117: invokeinterface #121,  2          // InterfaceMethod org/apache/camel/Message.setBody:(Ljava/lang/Object;)V
     122: aload_0
     123: getfield      #111                // Field originalInMessage:Lorg/apache/camel/Message;
     126: invokeinterface #125,  1          // InterfaceMethod org/apache/camel/Message.getHeaders:()Ljava/util/Map;
     131: aload_1
     132: invokeinterface #89,  1           // InterfaceMethod org/apache/camel/Exchange.getIn:()Lorg/apache/camel/Message;
     137: invokeinterface #125,  1          // InterfaceMethod org/apache/camel/Message.getHeaders:()Ljava/util/Map;
     142: invokeinterface #131,  2          // InterfaceMethod java/util/Map.putAll:(Ljava/util/Map;)V
     147: goto          165
     150: aload_0
     151: aload_1
     152: invokeinterface #89,  1           // InterfaceMethod org/apache/camel/Exchange.getIn:()Lorg/apache/camel/Message;
     157: invokeinterface #134,  1          // InterfaceMethod org/apache/camel/Message.copy:()Lorg/apache/camel/Message;
     162: putfield      #111                // Field originalInMessage:Lorg/apache/camel/Message;
     165: aload_1
     166: ldc           #136                // String CamelCreatedTimestamp
     168: invokeinterface #140,  2          // InterfaceMethod org/apache/camel/Exchange.getProperty:(Ljava/lang/String;)Ljava/lang/Object;
     173: ifnonnull     191
     176: aload_1
     177: ldc           #136                // String CamelCreatedTimestamp
     179: new           #142                // class java/util/Date
     182: dup
     183: invokespecial #143                // Method java/util/Date."<init>":()V
     186: invokeinterface #147,  3          // InterfaceMethod org/apache/camel/Exchange.setProperty:(Ljava/lang/String;Ljava/lang/Object;)V
     191: aload_1
     192: invokeinterface #83,  1           // InterfaceMethod org/apache/camel/Exchange.getContext:()Lorg/apache/camel/CamelContext;
     197: invokeinterface #153,  1          // InterfaceMethod org/apache/camel/CamelContext.isUseBreadcrumb:()Ljava/lang/Boolean;
     202: invokevirtual #158                // Method java/lang/Boolean.booleanValue:()Z
     205: ifeq          257
     208: aload_1
     209: invokeinterface #89,  1           // InterfaceMethod org/apache/camel/Exchange.getIn:()Lorg/apache/camel/Message;
     214: ldc           #160                // String breadcrumbId
     216: ldc           #102                // class java/lang/String
     218: invokeinterface #164,  3          // InterfaceMethod org/apache/camel/Message.getHeader:(Ljava/lang/String;Ljava/lang/Class;)Ljava/lang/Object;
     223: checkcast     #102                // class java/lang/String
     226: astore_3
     227: aload_3
     228: ifnonnull     257
     231: aload_1
     232: invokeinterface #89,  1           // InterfaceMethod org/apache/camel/Exchange.getIn:()Lorg/apache/camel/Message;
     237: invokeinterface #167,  1          // InterfaceMethod org/apache/camel/Message.getMessageId:()Ljava/lang/String;
     242: astore_3
     243: aload_1
     244: invokeinterface #89,  1           // InterfaceMethod org/apache/camel/Exchange.getIn:()Lorg/apache/camel/Message;
     249: ldc           #160                // String breadcrumbId
     251: aload_3
     252: invokeinterface #170,  3          // InterfaceMethod org/apache/camel/Message.setHeader:(Ljava/lang/String;Ljava/lang/Object;)V
     257: aload_1
     258: ldc           #172                // String CamelExternalRedelivered
     260: invokeinterface #140,  2          // InterfaceMethod org/apache/camel/Exchange.getProperty:(Ljava/lang/String;)Ljava/lang/Object;
     265: ifnonnull     282
     268: aload_1
     269: ldc           #172                // String CamelExternalRedelivered
     271: aload_1
     272: invokeinterface #175,  1          // InterfaceMethod org/apache/camel/Exchange.isExternalRedelivered:()Ljava/lang/Boolean;
     277: invokeinterface #147,  3          // InterfaceMethod org/apache/camel/Exchange.setProperty:(Ljava/lang/String;Ljava/lang/Object;)V
     282: aload_1
     283: invokeinterface #83,  1           // InterfaceMethod org/apache/camel/Exchange.getContext:()Lorg/apache/camel/CamelContext;
     288: aload_1
     289: invokestatic  #181                // Method org/apache/camel/util/EventHelper.notifyExchangeCreated:(Lorg/apache/camel/CamelContext;Lorg/apache/camel/Exchange;)V
     292: goto          308
     295: astore_3
     296: aload_0
     297: getfield      #56                 // Field log:Lorg/slf4j/Logger;
     300: ldc           #183                // String Exception occurred during event notification. This exception will be ignored.
     302: aload_3
     303: invokeinterface #187,  3          // InterfaceMethod org/slf4j/Logger.warn:(Ljava/lang/String;Ljava/lang/Throwable;)V
     308: aload_1
     309: invokeinterface #83,  1           // InterfaceMethod org/apache/camel/Exchange.getContext:()Lorg/apache/camel/CamelContext;
     314: ifnull        334
     317: aload_1
     318: invokeinterface #83,  1           // InterfaceMethod org/apache/camel/Exchange.getContext:()Lorg/apache/camel/CamelContext;
     323: invokeinterface #191,  1          // InterfaceMethod org/apache/camel/CamelContext.getInflightRepository:()Lorg/apache/camel/spi/InflightRepository;
     328: aload_1
     329: invokeinterface #196,  2          // InterfaceMethod org/apache/camel/spi/InflightRepository.add:(Lorg/apache/camel/Exchange;)V
     334: return
    Exception table:
       from    to  target type
         282   292   295   Class java/lang/Throwable

  org.apache.camel.spi.UnitOfWork newInstance(org.apache.camel.Exchange);
    Code:
       0: new           #2                  // class org/apache/camel/impl/DefaultUnitOfWork
       3: dup
       4: aload_1
       5: invokespecial #203                // Method "<init>":(Lorg/apache/camel/Exchange;)V
       8: areturn

  public void setParentUnitOfWork(org.apache.camel.spi.UnitOfWork);
    Code:
       0: aload_0
       1: aload_1
       2: putfield      #207                // Field parent:Lorg/apache/camel/spi/UnitOfWork;
       5: return

  public org.apache.camel.spi.UnitOfWork createChildUnitOfWork(org.apache.camel.Exchange);
    Code:
       0: aload_0
       1: aload_1
       2: invokevirtual #211                // Method newInstance:(Lorg/apache/camel/Exchange;)Lorg/apache/camel/spi/UnitOfWork;
       5: astore_2
       6: aload_2
       7: aload_0
       8: invokeinterface #213,  2          // InterfaceMethod org/apache/camel/spi/UnitOfWork.setParentUnitOfWork:(Lorg/apache/camel/spi/UnitOfWork;)V
      13: aload_2
      14: areturn

  public void start() throws java.lang.Exception;
    Code:
       0: aload_0
       1: aconst_null
       2: putfield      #220                // Field id:Ljava/lang/String;
       5: return

  public void stop() throws java.lang.Exception;
    Code:
       0: aload_0
       1: getfield      #223                // Field synchronizations:Ljava/util/List;
       4: ifnull        16
       7: aload_0
       8: getfield      #223                // Field synchronizations:Ljava/util/List;
      11: invokeinterface #228,  1          // InterfaceMethod java/util/List.clear:()V
      16: aload_0
      17: getfield      #79                 // Field tracedRouteNodes:Lorg/apache/camel/spi/TracedRouteNodes;
      20: ifnull        32
      23: aload_0
      24: getfield      #79                 // Field tracedRouteNodes:Lorg/apache/camel/spi/TracedRouteNodes;
      27: invokeinterface #231,  1          // InterfaceMethod org/apache/camel/spi/TracedRouteNodes.clear:()V
      32: aload_0
      33: getfield      #233                // Field transactedBy:Ljava/util/Set;
      36: ifnull        48
      39: aload_0
      40: getfield      #233                // Field transactedBy:Ljava/util/Set;
      43: invokeinterface #236,  1          // InterfaceMethod java/util/Set.clear:()V
      48: aload_0
      49: getfield      #54                 // Field routeContextStack:Ljava/util/Stack;
      52: dup
      53: astore_1
      54: monitorenter
      55: aload_0
      56: getfield      #54                 // Field routeContextStack:Ljava/util/Stack;
      59: invokevirtual #239                // Method java/util/Stack.isEmpty:()Z
      62: ifne          72
      65: aload_0
      66: getfield      #54                 // Field routeContextStack:Ljava/util/Stack;
      69: invokevirtual #240                // Method java/util/Stack.clear:()V
      72: aload_1
      73: monitorexit
      74: goto          82
      77: astore_2
      78: aload_1
      79: monitorexit
      80: aload_2
      81: athrow
      82: aload_0
      83: getfield      #242                // Field subUnitOfWorks:Ljava/util/Stack;
      86: ifnull        96
      89: aload_0
      90: getfield      #242                // Field subUnitOfWorks:Ljava/util/Stack;
      93: invokevirtual #240                // Method java/util/Stack.clear:()V
      96: aload_0
      97: aconst_null
      98: putfield      #111                // Field originalInMessage:Lorg/apache/camel/Message;
     101: aload_0
     102: aconst_null
     103: putfield      #207                // Field parent:Lorg/apache/camel/spi/UnitOfWork;
     106: aload_0
     107: aconst_null
     108: putfield      #220                // Field id:Ljava/lang/String;
     111: return
    Exception table:
       from    to  target type
          55    74    77   any
          77    80    77   any

  public synchronized void addSynchronization(org.apache.camel.spi.Synchronization);
    Code:
       0: aload_0
       1: getfield      #223                // Field synchronizations:Ljava/util/List;
       4: ifnonnull     18
       7: aload_0
       8: new           #246                // class java/util/ArrayList
      11: dup
      12: invokespecial #247                // Method java/util/ArrayList."<init>":()V
      15: putfield      #223                // Field synchronizations:Ljava/util/List;
      18: aload_0
      19: getfield      #56                 // Field log:Lorg/slf4j/Logger;
      22: ldc           #249                // String Adding synchronization {}
      24: aload_1
      25: invokeinterface #251,  3          // InterfaceMethod org/slf4j/Logger.trace:(Ljava/lang/String;Ljava/lang/Object;)V
      30: aload_0
      31: getfield      #223                // Field synchronizations:Ljava/util/List;
      34: aload_1
      35: invokeinterface #253,  2          // InterfaceMethod java/util/List.add:(Ljava/lang/Object;)Z
      40: pop
      41: return

  public synchronized void removeSynchronization(org.apache.camel.spi.Synchronization);
    Code:
       0: aload_0
       1: getfield      #223                // Field synchronizations:Ljava/util/List;
       4: ifnull        18
       7: aload_0
       8: getfield      #223                // Field synchronizations:Ljava/util/List;
      11: aload_1
      12: invokeinterface #259,  2          // InterfaceMethod java/util/List.remove:(Ljava/lang/Object;)Z
      17: pop
      18: return

  public synchronized boolean containsSynchronization(org.apache.camel.spi.Synchronization);
    Code:
       0: aload_0
       1: getfield      #223                // Field synchronizations:Ljava/util/List;
       4: ifnull        24
       7: aload_0
       8: getfield      #223                // Field synchronizations:Ljava/util/List;
      11: aload_1
      12: invokeinterface #264,  2          // InterfaceMethod java/util/List.contains:(Ljava/lang/Object;)Z
      17: ifeq          24
      20: iconst_1
      21: goto          25
      24: iconst_0
      25: ireturn

  public void handoverSynchronization(org.apache.camel.Exchange);
    Code:
       0: aload_0
       1: getfield      #223                // Field synchronizations:Ljava/util/List;
       4: ifnull        19
       7: aload_0
       8: getfield      #223                // Field synchronizations:Ljava/util/List;
      11: invokeinterface #266,  1          // InterfaceMethod java/util/List.isEmpty:()Z
      16: ifeq          20
      19: return
      20: aload_0
      21: getfield      #223                // Field synchronizations:Ljava/util/List;
      24: invokeinterface #270,  1          // InterfaceMethod java/util/List.iterator:()Ljava/util/Iterator;
      29: astore_2
      30: aload_2
      31: invokeinterface #275,  1          // InterfaceMethod java/util/Iterator.hasNext:()Z
      36: ifeq          125
      39: aload_2
      40: invokeinterface #278,  1          // InterfaceMethod java/util/Iterator.next:()Ljava/lang/Object;
      45: checkcast     #280                // class org/apache/camel/spi/Synchronization
      48: astore_3
      49: iconst_1
      50: istore        4
      52: aload_3
      53: instanceof    #282                // class org/apache/camel/spi/SynchronizationVetoable
      56: ifeq          74
      59: aload_3
      60: checkcast     #282                // class org/apache/camel/spi/SynchronizationVetoable
      63: astore        5
      65: aload         5
      67: invokeinterface #285,  1          // InterfaceMethod org/apache/camel/spi/SynchronizationVetoable.allowHandover:()Z
      72: istore        4
      74: iload         4
      76: ifeq          109
      79: aload_0
      80: getfield      #56                 // Field log:Lorg/slf4j/Logger;
      83: ldc_w         #287                // String Handover synchronization {} to: {}
      86: aload_3
      87: aload_1
      88: invokeinterface #74,  4           // InterfaceMethod org/slf4j/Logger.trace:(Ljava/lang/String;Ljava/lang/Object;Ljava/lang/Object;)V
      93: aload_1
      94: aload_3
      95: invokeinterface #290,  2          // InterfaceMethod org/apache/camel/Exchange.addOnCompletion:(Lorg/apache/camel/spi/Synchronization;)V
     100: aload_2
     101: invokeinterface #292,  1          // InterfaceMethod java/util/Iterator.remove:()V
     106: goto          122
     109: aload_0
     110: getfield      #56                 // Field log:Lorg/slf4j/Logger;
     113: ldc_w         #294                // String Handover not allow for synchronization {}
     116: aload_3
     117: invokeinterface #251,  3          // InterfaceMethod org/slf4j/Logger.trace:(Ljava/lang/String;Ljava/lang/Object;)V
     122: goto          30
     125: return

  public void done(org.apache.camel.Exchange);
    Code:
       0: aload_0
       1: getfield      #56                 // Field log:Lorg/slf4j/Logger;
       4: ldc_w         #305                // String UnitOfWork done for ExchangeId: {} with {}
       7: aload_1
       8: invokeinterface #70,  1           // InterfaceMethod org/apache/camel/Exchange.getExchangeId:()Ljava/lang/String;
      13: aload_1
      14: invokeinterface #74,  4           // InterfaceMethod org/slf4j/Logger.trace:(Ljava/lang/String;Ljava/lang/Object;Ljava/lang/Object;)V
      19: aload_1
      20: invokeinterface #308,  1          // InterfaceMethod org/apache/camel/Exchange.isFailed:()Z
      25: istore_2
      26: aload_1
      27: aload_0
      28: getfield      #223                // Field synchronizations:Ljava/util/List;
      31: aload_0
      32: getfield      #56                 // Field log:Lorg/slf4j/Logger;
      35: invokestatic  #314                // Method org/apache/camel/util/UnitOfWorkHelper.doneSynchronizations:(Lorg/apache/camel/Exchange;Ljava/util/List;Lorg/slf4j/Logger;)V
      38: aload_0
      39: invokevirtual #318                // Method getSubUnitOfWorkCallback:()Lorg/apache/camel/spi/SubUnitOfWorkCallback;
      42: astore_3
      43: aload_3
      44: ifnull        54
      47: aload_3
      48: aload_1
      49: invokeinterface #323,  2          // InterfaceMethod org/apache/camel/spi/SubUnitOfWorkCallback.onDone:(Lorg/apache/camel/Exchange;)V
      54: goto          71
      57: astore_3
      58: aload_0
      59: getfield      #56                 // Field log:Lorg/slf4j/Logger;
      62: ldc_w         #325                // String Exception occurred during savepoint onDone. This exception will be ignored.
      65: aload_3
      66: invokeinterface #187,  3          // InterfaceMethod org/slf4j/Logger.warn:(Ljava/lang/String;Ljava/lang/Throwable;)V
      71: aload_1
      72: invokeinterface #83,  1           // InterfaceMethod org/apache/camel/Exchange.getContext:()Lorg/apache/camel/CamelContext;
      77: ifnull        97
      80: aload_1
      81: invokeinterface #83,  1           // InterfaceMethod org/apache/camel/Exchange.getContext:()Lorg/apache/camel/CamelContext;
      86: invokeinterface #191,  1          // InterfaceMethod org/apache/camel/CamelContext.getInflightRepository:()Lorg/apache/camel/spi/InflightRepository;
      91: aload_1
      92: invokeinterface #327,  2          // InterfaceMethod org/apache/camel/spi/InflightRepository.remove:(Lorg/apache/camel/Exchange;)V
      97: iload_2
      98: ifeq          114
     101: aload_1
     102: invokeinterface #83,  1           // InterfaceMethod org/apache/camel/Exchange.getContext:()Lorg/apache/camel/CamelContext;
     107: aload_1
     108: invokestatic  #330                // Method org/apache/camel/util/EventHelper.notifyExchangeFailed:(Lorg/apache/camel/CamelContext;Lorg/apache/camel/Exchange;)V
     111: goto          124
     114: aload_1
     115: invokeinterface #83,  1           // InterfaceMethod org/apache/camel/Exchange.getContext:()Lorg/apache/camel/CamelContext;
     120: aload_1
     121: invokestatic  #333                // Method org/apache/camel/util/EventHelper.notifyExchangeDone:(Lorg/apache/camel/CamelContext;Lorg/apache/camel/Exchange;)V
     124: goto          140
     127: astore_3
     128: aload_0
     129: getfield      #56                 // Field log:Lorg/slf4j/Logger;
     132: ldc           #183                // String Exception occurred during event notification. This exception will be ignored.
     134: aload_3
     135: invokeinterface #187,  3          // InterfaceMethod org/slf4j/Logger.warn:(Ljava/lang/String;Ljava/lang/Throwable;)V
     140: return
    Exception table:
       from    to  target type
          38    54    57   Class java/lang/Throwable
          97   124   127   Class java/lang/Throwable

  public java.lang.String getId();
    Code:
       0: aload_0
       1: getfield      #220                // Field id:Ljava/lang/String;
       4: ifnonnull     25
       7: aload_0
       8: aload_0
       9: getfield      #85                 // Field context:Lorg/apache/camel/CamelContext;
      12: invokeinterface #341,  1          // InterfaceMethod org/apache/camel/CamelContext.getUuidGenerator:()Lorg/apache/camel/spi/UuidGenerator;
      17: invokeinterface #346,  1          // InterfaceMethod org/apache/camel/spi/UuidGenerator.generateUuid:()Ljava/lang/String;
      22: putfield      #220                // Field id:Ljava/lang/String;
      25: aload_0
      26: getfield      #220                // Field id:Ljava/lang/String;
      29: areturn

  public org.apache.camel.Message getOriginalInMessage();
    Code:
       0: aload_0
       1: getfield      #111                // Field originalInMessage:Lorg/apache/camel/Message;
       4: areturn

  public org.apache.camel.spi.TracedRouteNodes getTracedRouteNodes();
    Code:
       0: aload_0
       1: getfield      #79                 // Field tracedRouteNodes:Lorg/apache/camel/spi/TracedRouteNodes;
       4: areturn

  public boolean isTransacted();
    Code:
       0: aload_0
       1: getfield      #233                // Field transactedBy:Ljava/util/Set;
       4: ifnull        23
       7: aload_0
       8: getfield      #233                // Field transactedBy:Ljava/util/Set;
      11: invokeinterface #351,  1          // InterfaceMethod java/util/Set.isEmpty:()Z
      16: ifne          23
      19: iconst_1
      20: goto          24
      23: iconst_0
      24: ireturn

  public boolean isTransactedBy(java.lang.Object);
    Code:
       0: aload_0
       1: invokespecial #356                // Method getTransactedBy:()Ljava/util/Set;
       4: aload_1
       5: invokeinterface #357,  2          // InterfaceMethod java/util/Set.contains:(Ljava/lang/Object;)Z
      10: ireturn

  public void beginTransactedBy(java.lang.Object);
    Code:
       0: aload_0
       1: invokespecial #356                // Method getTransactedBy:()Ljava/util/Set;
       4: aload_1
       5: invokeinterface #361,  2          // InterfaceMethod java/util/Set.add:(Ljava/lang/Object;)Z
      10: pop
      11: return

  public void endTransactedBy(java.lang.Object);
    Code:
       0: aload_0
       1: invokespecial #356                // Method getTransactedBy:()Ljava/util/Set;
       4: aload_1
       5: invokeinterface #363,  2          // InterfaceMethod java/util/Set.remove:(Ljava/lang/Object;)Z
      10: pop
      11: return

  public org.apache.camel.spi.RouteContext getRouteContext();
    Code:
       0: aload_0
       1: getfield      #54                 // Field routeContextStack:Ljava/util/Stack;
       4: dup
       5: astore_1
       6: monitorenter
       7: aload_0
       8: getfield      #54                 // Field routeContextStack:Ljava/util/Stack;
      11: invokevirtual #239                // Method java/util/Stack.isEmpty:()Z
      14: ifeq          21
      17: aconst_null
      18: aload_1
      19: monitorexit
      20: areturn
      21: aload_0
      22: getfield      #54                 // Field routeContextStack:Ljava/util/Stack;
      25: invokevirtual #368                // Method java/util/Stack.peek:()Ljava/lang/Object;
      28: checkcast     #370                // class org/apache/camel/spi/RouteContext
      31: aload_1
      32: monitorexit
      33: areturn
      34: astore_2
      35: aload_1
      36: monitorexit
      37: aload_2
      38: athrow
    Exception table:
       from    to  target type
           7    20    34   any
          21    33    34   any
          34    37    34   any

  public void pushRouteContext(org.apache.camel.spi.RouteContext);
    Code:
       0: aload_0
       1: getfield      #54                 // Field routeContextStack:Ljava/util/Stack;
       4: dup
       5: astore_2
       6: monitorenter
       7: aload_0
       8: getfield      #54                 // Field routeContextStack:Ljava/util/Stack;
      11: aload_1
      12: invokevirtual #373                // Method java/util/Stack.add:(Ljava/lang/Object;)Z
      15: pop
      16: aload_2
      17: monitorexit
      18: goto          26
      21: astore_3
      22: aload_2
      23: monitorexit
      24: aload_3
      25: athrow
      26: return
    Exception table:
       from    to  target type
           7    18    21   any
          21    24    21   any

  public org.apache.camel.spi.RouteContext popRouteContext();
    Code:
       0: aload_0
       1: getfield      #54                 // Field routeContextStack:Ljava/util/Stack;
       4: dup
       5: astore_1
       6: monitorenter
       7: aload_0
       8: getfield      #54                 // Field routeContextStack:Ljava/util/Stack;
      11: invokevirtual #239                // Method java/util/Stack.isEmpty:()Z
      14: ifeq          21
      17: aconst_null
      18: aload_1
      19: monitorexit
      20: areturn
      21: aload_0
      22: getfield      #54                 // Field routeContextStack:Ljava/util/Stack;
      25: invokevirtual #379                // Method java/util/Stack.pop:()Ljava/lang/Object;
      28: checkcast     #370                // class org/apache/camel/spi/RouteContext
      31: aload_1
      32: monitorexit
      33: areturn
      34: astore_2
      35: aload_1
      36: monitorexit
      37: aload_2
      38: athrow
    Exception table:
       from    to  target type
           7    20    34   any
          21    33    34   any
          34    37    34   any

  public org.apache.camel.AsyncCallback beforeProcess(org.apache.camel.Processor, org.apache.camel.Exchange, org.apache.camel.AsyncCallback);
    Code:
       0: aload_3
       1: areturn

  public void afterProcess(org.apache.camel.Processor, org.apache.camel.Exchange, org.apache.camel.AsyncCallback, boolean);
    Code:
       0: return

  public void beginSubUnitOfWork(org.apache.camel.Exchange);
    Code:
       0: aload_0
       1: getfield      #56                 // Field log:Lorg/slf4j/Logger;
       4: invokeinterface #62,  1           // InterfaceMethod org/slf4j/Logger.isTraceEnabled:()Z
       9: ifeq          30
      12: aload_0
      13: getfield      #56                 // Field log:Lorg/slf4j/Logger;
      16: ldc_w         #391                // String beginSubUnitOfWork exchangeId: {}
      19: aload_1
      20: invokeinterface #70,  1           // InterfaceMethod org/apache/camel/Exchange.getExchangeId:()Ljava/lang/String;
      25: invokeinterface #251,  3          // InterfaceMethod org/slf4j/Logger.trace:(Ljava/lang/String;Ljava/lang/Object;)V
      30: aload_0
      31: getfield      #242                // Field subUnitOfWorks:Ljava/util/Stack;
      34: ifnonnull     48
      37: aload_0
      38: new           #51                 // class java/util/Stack
      41: dup
      42: invokespecial #52                 // Method java/util/Stack."<init>":()V
      45: putfield      #242                // Field subUnitOfWorks:Ljava/util/Stack;
      48: aload_0
      49: getfield      #242                // Field subUnitOfWorks:Ljava/util/Stack;
      52: new           #393                // class org/apache/camel/impl/DefaultSubUnitOfWork
      55: dup
      56: invokespecial #394                // Method org/apache/camel/impl/DefaultSubUnitOfWork."<init>":()V
      59: invokevirtual #398                // Method java/util/Stack.push:(Ljava/lang/Object;)Ljava/lang/Object;
      62: pop
      63: return

  public void endSubUnitOfWork(org.apache.camel.Exchange);
    Code:
       0: aload_0
       1: getfield      #56                 // Field log:Lorg/slf4j/Logger;
       4: invokeinterface #62,  1           // InterfaceMethod org/slf4j/Logger.isTraceEnabled:()Z
       9: ifeq          30
      12: aload_0
      13: getfield      #56                 // Field log:Lorg/slf4j/Logger;
      16: ldc_w         #401                // String endSubUnitOfWork exchangeId: {}
      19: aload_1
      20: invokeinterface #70,  1           // InterfaceMethod org/apache/camel/Exchange.getExchangeId:()Ljava/lang/String;
      25: invokeinterface #251,  3          // InterfaceMethod org/slf4j/Logger.trace:(Ljava/lang/String;Ljava/lang/Object;)V
      30: aload_0
      31: getfield      #242                // Field subUnitOfWorks:Ljava/util/Stack;
      34: ifnull        47
      37: aload_0
      38: getfield      #242                // Field subUnitOfWorks:Ljava/util/Stack;
      41: invokevirtual #239                // Method java/util/Stack.isEmpty:()Z
      44: ifeq          48
      47: return
      48: aload_0
      49: getfield      #242                // Field subUnitOfWorks:Ljava/util/Stack;
      52: invokevirtual #379                // Method java/util/Stack.pop:()Ljava/lang/Object;
      55: checkcast     #403                // class org/apache/camel/spi/SubUnitOfWork
      58: astore_2
      59: aload_2
      60: invokeinterface #404,  1          // InterfaceMethod org/apache/camel/spi/SubUnitOfWork.isFailed:()Z
      65: ifeq          216
      68: aload_2
      69: invokeinterface #408,  1          // InterfaceMethod org/apache/camel/spi/SubUnitOfWork.getExceptions:()Ljava/util/List;
      74: astore_3
      75: aload_3
      76: ifnull        123
      79: aload_3
      80: invokeinterface #412,  1          // InterfaceMethod java/util/List.size:()I
      85: iconst_1
      86: if_icmpne     104
      89: aload_3
      90: iconst_0
      91: invokeinterface #416,  2          // InterfaceMethod java/util/List.get:(I)Ljava/lang/Object;
      96: checkcast     #218                // class java/lang/Exception
      99: astore        4
     101: goto          115
     104: new           #418                // class org/apache/camel/CamelUnitOfWorkException
     107: dup
     108: aload_1
     109: aload_3
     110: invokespecial #421                // Method org/apache/camel/CamelUnitOfWorkException."<init>":(Lorg/apache/camel/Exchange;Ljava/util/List;)V
     113: astore        4
     115: aload_1
     116: aload         4
     118: invokeinterface #425,  2          // InterfaceMethod org/apache/camel/Exchange.setException:(Ljava/lang/Throwable;)V
     123: aload_1
     124: ldc_w         #427                // String CamelRollbackOnly
     127: iconst_1
     128: invokestatic  #431                // Method java/lang/Boolean.valueOf:(Z)Ljava/lang/Boolean;
     131: invokeinterface #147,  3          // InterfaceMethod org/apache/camel/Exchange.setProperty:(Ljava/lang/String;Ljava/lang/Object;)V
     136: aload_1
     137: ldc_w         #433                // String CamelUnitOfWorkExhausted
     140: iconst_1
     141: invokestatic  #431                // Method java/lang/Boolean.valueOf:(Z)Ljava/lang/Boolean;
     144: invokeinterface #147,  3          // InterfaceMethod org/apache/camel/Exchange.setProperty:(Ljava/lang/String;Ljava/lang/Object;)V
     149: aload_1
     150: ldc_w         #435                // String CamelErrorHandlerHandled
     153: aconst_null
     154: invokeinterface #147,  3          // InterfaceMethod org/apache/camel/Exchange.setProperty:(Ljava/lang/String;Ljava/lang/Object;)V
     159: aload_1
     160: ldc_w         #437                // String CamelFailureHandled
     163: aconst_null
     164: invokeinterface #147,  3          // InterfaceMethod org/apache/camel/Exchange.setProperty:(Ljava/lang/String;Ljava/lang/Object;)V
     169: aload_0
     170: getfield      #56                 // Field log:Lorg/slf4j/Logger;
     173: invokeinterface #62,  1           // InterfaceMethod org/slf4j/Logger.isTraceEnabled:()Z
     178: ifeq          216
     181: aload_0
     182: getfield      #56                 // Field log:Lorg/slf4j/Logger;
     185: ldc_w         #439                // String endSubUnitOfWork exchangeId: {} with {} caused exceptions.
     188: aload_1
     189: invokeinterface #70,  1           // InterfaceMethod org/apache/camel/Exchange.getExchangeId:()Ljava/lang/String;
     194: aload_3
     195: ifnull        207
     198: aload_3
     199: invokeinterface #412,  1          // InterfaceMethod java/util/List.size:()I
     204: goto          208
     207: iconst_0
     208: invokestatic  #444                // Method java/lang/Integer.valueOf:(I)Ljava/lang/Integer;
     211: invokeinterface #74,  4           // InterfaceMethod org/slf4j/Logger.trace:(Ljava/lang/String;Ljava/lang/Object;Ljava/lang/Object;)V
     216: return

  public org.apache.camel.spi.SubUnitOfWorkCallback getSubUnitOfWorkCallback();
    Code:
       0: aload_0
       1: getfield      #207                // Field parent:Lorg/apache/camel/spi/UnitOfWork;
       4: ifnull        17
       7: aload_0
       8: getfield      #207                // Field parent:Lorg/apache/camel/spi/UnitOfWork;
      11: invokeinterface #451,  1          // InterfaceMethod org/apache/camel/spi/UnitOfWork.getSubUnitOfWorkCallback:()Lorg/apache/camel/spi/SubUnitOfWorkCallback;
      16: areturn
      17: aload_0
      18: getfield      #242                // Field subUnitOfWorks:Ljava/util/Stack;
      21: ifnull        34
      24: aload_0
      25: getfield      #242                // Field subUnitOfWorks:Ljava/util/Stack;
      28: invokevirtual #239                // Method java/util/Stack.isEmpty:()Z
      31: ifeq          36
      34: aconst_null
      35: areturn
      36: aload_0
      37: getfield      #242                // Field subUnitOfWorks:Ljava/util/Stack;
      40: invokevirtual #368                // Method java/util/Stack.peek:()Ljava/lang/Object;
      43: checkcast     #320                // class org/apache/camel/spi/SubUnitOfWorkCallback
      46: areturn

  private java.util.Set<java.lang.Object> getTransactedBy();
    Code:
       0: aload_0
       1: getfield      #233                // Field transactedBy:Ljava/util/Set;
       4: ifnonnull     18
       7: aload_0
       8: new           #453                // class java/util/LinkedHashSet
      11: dup
      12: invokespecial #454                // Method java/util/LinkedHashSet."<init>":()V
      15: putfield      #233                // Field transactedBy:Ljava/util/Set;
      18: aload_0
      19: getfield      #233                // Field transactedBy:Ljava/util/Set;
      22: areturn

  public java.lang.String toString();
    Code:
       0: ldc_w         #457                // String DefaultUnitOfWork
       3: areturn

  static {};
    Code:
       0: ldc           #2                  // class org/apache/camel/impl/DefaultUnitOfWork
       2: invokestatic  #464                // Method org/slf4j/LoggerFactory.getLogger:(Ljava/lang/Class;)Lorg/slf4j/Logger;
       5: putstatic     #37                 // Field LOG:Lorg/slf4j/Logger;
       8: return
}
