Compiled from "DefaultCamelContextNameStrategy.java"
public class org.apache.camel.impl.DefaultCamelContextNameStrategy implements org.apache.camel.spi.CamelContextNameStrategy {
  private static final java.util.concurrent.atomic.AtomicInteger CONTEXT_COUNTER;

  private final java.lang.String prefix;

  private java.lang.String name;

  public org.apache.camel.impl.DefaultCamelContextNameStrategy();
    Code:
       0: aload_0
       1: ldc           #16                 // String camel
       3: invokespecial #19                 // Method "<init>":(Ljava/lang/String;)V
       6: return

  public org.apache.camel.impl.DefaultCamelContextNameStrategy(java.lang.String);
    Code:
       0: aload_0
       1: invokespecial #23                 // Method java/lang/Object."<init>":()V
       4: aload_0
       5: aload_1
       6: putfield      #25                 // Field prefix:Ljava/lang/String;
       9: aload_0
      10: aload_0
      11: invokevirtual #29                 // Method getNextName:()Ljava/lang/String;
      14: putfield      #31                 // Field name:Ljava/lang/String;
      17: return

  public java.lang.String getName();
    Code:
       0: aload_0
       1: getfield      #31                 // Field name:Ljava/lang/String;
       4: ifnonnull     15
       7: aload_0
       8: aload_0
       9: invokevirtual #29                 // Method getNextName:()Ljava/lang/String;
      12: putfield      #31                 // Field name:Ljava/lang/String;
      15: aload_0
      16: getfield      #31                 // Field name:Ljava/lang/String;
      19: areturn

  public java.lang.String getNextName();
    Code:
       0: new           #34                 // class java/lang/StringBuilder
       3: dup
       4: invokespecial #35                 // Method java/lang/StringBuilder."<init>":()V
       7: aload_0
       8: getfield      #25                 // Field prefix:Ljava/lang/String;
      11: invokevirtual #39                 // Method java/lang/StringBuilder.append:(Ljava/lang/String;)Ljava/lang/StringBuilder;
      14: ldc           #41                 // String -
      16: invokevirtual #39                 // Method java/lang/StringBuilder.append:(Ljava/lang/String;)Ljava/lang/StringBuilder;
      19: invokestatic  #45                 // Method getNextCounter:()I
      22: invokevirtual #48                 // Method java/lang/StringBuilder.append:(I)Ljava/lang/StringBuilder;
      25: invokevirtual #51                 // Method java/lang/StringBuilder.toString:()Ljava/lang/String;
      28: areturn

  public boolean isFixedName();
    Code:
       0: iconst_0
       1: ireturn

  public static int getNextCounter();
    Code:
       0: getstatic     #55                 // Field CONTEXT_COUNTER:Ljava/util/concurrent/atomic/AtomicInteger;
       3: invokevirtual #60                 // Method java/util/concurrent/atomic/AtomicInteger.incrementAndGet:()I
       6: ireturn

  public static void setCounter(int);
    Code:
       0: getstatic     #55                 // Field CONTEXT_COUNTER:Ljava/util/concurrent/atomic/AtomicInteger;
       3: iload_0
       4: invokevirtual #65                 // Method java/util/concurrent/atomic/AtomicInteger.set:(I)V
       7: return

  static {};
    Code:
       0: new           #57                 // class java/util/concurrent/atomic/AtomicInteger
       3: dup
       4: iconst_0
       5: invokespecial #70                 // Method java/util/concurrent/atomic/AtomicInteger."<init>":(I)V
       8: putstatic     #55                 // Field CONTEXT_COUNTER:Ljava/util/concurrent/atomic/AtomicInteger;
      11: return
}
