Compiled from "DefaultDataFormatResolver.java"
public class org.apache.camel.impl.DefaultDataFormatResolver implements org.apache.camel.spi.DataFormatResolver {
  public static final java.lang.String DATAFORMAT_RESOURCE_PATH;

  protected org.apache.camel.spi.FactoryFinder dataformatFactory;

  public org.apache.camel.impl.DefaultDataFormatResolver();
    Code:
       0: aload_0
       1: invokespecial #17                 // Method java/lang/Object."<init>":()V
       4: return

  public org.apache.camel.spi.DataFormat resolveDataFormat(java.lang.String, org.apache.camel.CamelContext);
    Code:
       0: aload_2
       1: aload_1
       2: ldc           #27                 // class org/apache/camel/spi/DataFormat
       4: invokestatic  #31                 // Method lookup:(Lorg/apache/camel/CamelContext;Ljava/lang/String;Ljava/lang/Class;)Ljava/lang/Object;
       7: checkcast     #27                 // class org/apache/camel/spi/DataFormat
      10: astore_3
      11: aload_3
      12: ifnonnull     182
      15: aconst_null
      16: astore        4
      18: aload_0
      19: getfield      #33                 // Field dataformatFactory:Lorg/apache/camel/spi/FactoryFinder;
      22: ifnonnull     37
      25: aload_0
      26: aload_2
      27: ldc           #11                 // String META-INF/services/org/apache/camel/dataformat/
      29: invokeinterface #39,  2           // InterfaceMethod org/apache/camel/CamelContext.getFactoryFinder:(Ljava/lang/String;)Lorg/apache/camel/spi/FactoryFinder;
      34: putfield      #33                 // Field dataformatFactory:Lorg/apache/camel/spi/FactoryFinder;
      37: aload_0
      38: getfield      #33                 // Field dataformatFactory:Lorg/apache/camel/spi/FactoryFinder;
      41: aload_1
      42: invokeinterface #47,  2           // InterfaceMethod org/apache/camel/spi/FactoryFinder.findClass:(Ljava/lang/String;)Ljava/lang/Class;
      47: astore        4
      49: goto          88
      52: astore        5
      54: goto          88
      57: astore        5
      59: new           #49                 // class java/lang/IllegalArgumentException
      62: dup
      63: new           #51                 // class java/lang/StringBuilder
      66: dup
      67: invokespecial #52                 // Method java/lang/StringBuilder."<init>":()V
      70: ldc           #54                 // String Invalid URI, no DataFormat registered for scheme:
      72: invokevirtual #58                 // Method java/lang/StringBuilder.append:(Ljava/lang/String;)Ljava/lang/StringBuilder;
      75: aload_1
      76: invokevirtual #58                 // Method java/lang/StringBuilder.append:(Ljava/lang/String;)Ljava/lang/StringBuilder;
      79: invokevirtual #62                 // Method java/lang/StringBuilder.toString:()Ljava/lang/String;
      82: aload         5
      84: invokespecial #65                 // Method java/lang/IllegalArgumentException."<init>":(Ljava/lang/String;Ljava/lang/Throwable;)V
      87: athrow
      88: aload         4
      90: ifnonnull     107
      93: aload_2
      94: invokeinterface #69,  1           // InterfaceMethod org/apache/camel/CamelContext.getClassResolver:()Lorg/apache/camel/spi/ClassResolver;
      99: aload_1
     100: invokeinterface #74,  2           // InterfaceMethod org/apache/camel/spi/ClassResolver.resolveClass:(Ljava/lang/String;)Ljava/lang/Class;
     105: astore        4
     107: aload         4
     109: ifnull        182
     112: ldc           #27                 // class org/apache/camel/spi/DataFormat
     114: aload         4
     116: invokevirtual #78                 // Method java/lang/Class.isAssignableFrom:(Ljava/lang/Class;)Z
     119: ifeq          142
     122: aload_2
     123: invokeinterface #82,  1           // InterfaceMethod org/apache/camel/CamelContext.getInjector:()Lorg/apache/camel/spi/Injector;
     128: aload         4
     130: invokeinterface #88,  2           // InterfaceMethod org/apache/camel/spi/Injector.newInstance:(Ljava/lang/Class;)Ljava/lang/Object;
     135: checkcast     #27                 // class org/apache/camel/spi/DataFormat
     138: astore_3
     139: goto          182
     142: new           #49                 // class java/lang/IllegalArgumentException
     145: dup
     146: new           #51                 // class java/lang/StringBuilder
     149: dup
     150: invokespecial #52                 // Method java/lang/StringBuilder."<init>":()V
     153: ldc           #90                 // String Resolving dataformat:
     155: invokevirtual #58                 // Method java/lang/StringBuilder.append:(Ljava/lang/String;)Ljava/lang/StringBuilder;
     158: aload_1
     159: invokevirtual #58                 // Method java/lang/StringBuilder.append:(Ljava/lang/String;)Ljava/lang/StringBuilder;
     162: ldc           #92                 // String  detected type conflict: Not a DataFormat implementation. Found:
     164: invokevirtual #58                 // Method java/lang/StringBuilder.append:(Ljava/lang/String;)Ljava/lang/StringBuilder;
     167: aload         4
     169: invokevirtual #95                 // Method java/lang/Class.getName:()Ljava/lang/String;
     172: invokevirtual #58                 // Method java/lang/StringBuilder.append:(Ljava/lang/String;)Ljava/lang/StringBuilder;
     175: invokevirtual #62                 // Method java/lang/StringBuilder.toString:()Ljava/lang/String;
     178: invokespecial #98                 // Method java/lang/IllegalArgumentException."<init>":(Ljava/lang/String;)V
     181: athrow
     182: aload_3
     183: areturn
    Exception table:
       from    to  target type
          18    49    52   Class org/apache/camel/NoFactoryAvailableException
          18    49    57   Class java/lang/Exception

  private static <T> T lookup(org.apache.camel.CamelContext, java.lang.String, java.lang.Class<T>);
    Code:
       0: aload_0
       1: invokeinterface #113,  1          // InterfaceMethod org/apache/camel/CamelContext.getRegistry:()Lorg/apache/camel/spi/Registry;
       6: aload_1
       7: aload_2
       8: invokeinterface #119,  3          // InterfaceMethod org/apache/camel/spi/Registry.lookupByNameAndType:(Ljava/lang/String;Ljava/lang/Class;)Ljava/lang/Object;
      13: areturn
      14: astore_3
      15: aconst_null
      16: areturn
    Exception table:
       from    to  target type
           0    13    14   Class java/lang/Exception
}
