Compiled from "AbstractMultiValuedMap.java"
class org.apache.commons.collections4.multimap.AbstractMultiValuedMap$MultiValuedMapEntry extends org.apache.commons.collections4.keyvalue.AbstractMapEntry<K, V> {
  final org.apache.commons.collections4.multimap.AbstractMultiValuedMap this$0;

  public org.apache.commons.collections4.multimap.AbstractMultiValuedMap$MultiValuedMapEntry(K, V);
    Code:
       0: aload_0
       1: aload_1
       2: putfield      #1                  // Field this$0:Lorg/apache/commons/collections4/multimap/AbstractMultiValuedMap;
       5: aload_0
       6: aload_2
       7: aload_3
       8: invokespecial #2                  // Method org/apache/commons/collections4/keyvalue/AbstractMapEntry."<init>":(Ljava/lang/Object;Ljava/lang/Object;)V
      11: return

  public V setValue(V);
    Code:
       0: new           #3                  // class java/lang/UnsupportedOperationException
       3: dup
       4: invokespecial #4                  // Method java/lang/UnsupportedOperationException."<init>":()V
       7: athrow
}
