Compiled from "SimpleDnsCache.scala"
public class akka.io.SimpleDnsCache$Cache {
  private final scala.collection.immutable.SortedSet<akka.io.SimpleDnsCache$ExpiryEntry> queue;

  private final scala.collection.immutable.Map<java.lang.String, akka.io.SimpleDnsCache$CacheEntry> cache;

  public final scala.Function0<java.lang.Object> akka$io$SimpleDnsCache$Cache$$clock;

  public scala.Option<akka.io.Dns$Resolved> get(java.lang.String);
    Code:
       0: aload_0
       1: getfield      #18                 // Field cache:Lscala/collection/immutable/Map;
       4: aload_1
       5: invokeinterface #23,  2           // InterfaceMethod scala/collection/immutable/Map.get:(Ljava/lang/Object;)Lscala/Option;
      10: new           #25                 // class akka/io/SimpleDnsCache$Cache$$anonfun$get$1
      13: dup
      14: aload_0
      15: invokespecial #29                 // Method akka/io/SimpleDnsCache$Cache$$anonfun$get$1."<init>":(Lakka/io/SimpleDnsCache$Cache;)V
      18: invokevirtual #35                 // Method scala/Option.withFilter:(Lscala/Function1;)Lscala/Option$WithFilter;
      21: new           #37                 // class akka/io/SimpleDnsCache$Cache$$anonfun$get$2
      24: dup
      25: aload_0
      26: invokespecial #38                 // Method akka/io/SimpleDnsCache$Cache$$anonfun$get$2."<init>":(Lakka/io/SimpleDnsCache$Cache;)V
      29: invokevirtual #44                 // Method scala/Option$WithFilter.map:(Lscala/Function1;)Lscala/Option;
      32: areturn

  public akka.io.SimpleDnsCache$Cache put(akka.io.Dns$Resolved, long);
    Code:
       0: aload_0
       1: getfield      #52                 // Field akka$io$SimpleDnsCache$Cache$$clock:Lscala/Function0;
       4: invokeinterface #58,  1           // InterfaceMethod scala/Function0.apply$mcJ$sp:()J
       9: lload_2
      10: ladd
      11: lstore        4
      13: new           #2                  // class akka/io/SimpleDnsCache$Cache
      16: dup
      17: aload_0
      18: getfield      #60                 // Field queue:Lscala/collection/immutable/SortedSet;
      21: new           #62                 // class akka/io/SimpleDnsCache$ExpiryEntry
      24: dup
      25: aload_1
      26: invokevirtual #67                 // Method akka/io/Dns$Resolved.name:()Ljava/lang/String;
      29: lload         4
      31: invokespecial #70                 // Method akka/io/SimpleDnsCache$ExpiryEntry."<init>":(Ljava/lang/String;J)V
      34: invokeinterface #76,  2           // InterfaceMethod scala/collection/immutable/SortedSet.$plus:(Ljava/lang/Object;)Lscala/collection/Set;
      39: checkcast     #72                 // class scala/collection/immutable/SortedSet
      42: aload_0
      43: getfield      #18                 // Field cache:Lscala/collection/immutable/Map;
      46: getstatic     #82                 // Field scala/Predef$ArrowAssoc$.MODULE$:Lscala/Predef$ArrowAssoc$;
      49: getstatic     #87                 // Field scala/Predef$.MODULE$:Lscala/Predef$;
      52: aload_1
      53: invokevirtual #67                 // Method akka/io/Dns$Resolved.name:()Ljava/lang/String;
      56: invokevirtual #91                 // Method scala/Predef$.ArrowAssoc:(Ljava/lang/Object;)Ljava/lang/Object;
      59: new           #93                 // class akka/io/SimpleDnsCache$CacheEntry
      62: dup
      63: aload_1
      64: lload         4
      66: invokespecial #96                 // Method akka/io/SimpleDnsCache$CacheEntry."<init>":(Lakka/io/Dns$Resolved;J)V
      69: invokevirtual #100                // Method scala/Predef$ArrowAssoc$.$u2192$extension:(Ljava/lang/Object;Ljava/lang/Object;)Lscala/Tuple2;
      72: invokeinterface #103,  2          // InterfaceMethod scala/collection/immutable/Map.$plus:(Lscala/Tuple2;)Lscala/collection/immutable/Map;
      77: aload_0
      78: getfield      #52                 // Field akka$io$SimpleDnsCache$Cache$$clock:Lscala/Function0;
      81: invokespecial #106                // Method "<init>":(Lscala/collection/immutable/SortedSet;Lscala/collection/immutable/Map;Lscala/Function0;)V
      84: areturn

  public akka.io.SimpleDnsCache$Cache cleanup();
    Code:
       0: aload_0
       1: getfield      #52                 // Field akka$io$SimpleDnsCache$Cache$$clock:Lscala/Function0;
       4: invokeinterface #58,  1           // InterfaceMethod scala/Function0.apply$mcJ$sp:()J
       9: lstore_1
      10: aload_0
      11: getfield      #60                 // Field queue:Lscala/collection/immutable/SortedSet;
      14: astore_3
      15: aload_0
      16: getfield      #18                 // Field cache:Lscala/collection/immutable/Map;
      19: astore        4
      21: aload_3
      22: invokeinterface #117,  1          // InterfaceMethod scala/collection/immutable/SortedSet.nonEmpty:()Z
      27: ifeq          120
      30: aload_3
      31: invokeinterface #121,  1          // InterfaceMethod scala/collection/immutable/SortedSet.head:()Ljava/lang/Object;
      36: checkcast     #62                 // class akka/io/SimpleDnsCache$ExpiryEntry
      39: lload_1
      40: invokevirtual #125                // Method akka/io/SimpleDnsCache$ExpiryEntry.isValid:(J)Z
      43: ifne          120
      46: aload_3
      47: invokeinterface #121,  1          // InterfaceMethod scala/collection/immutable/SortedSet.head:()Ljava/lang/Object;
      52: checkcast     #62                 // class akka/io/SimpleDnsCache$ExpiryEntry
      55: astore        5
      57: aload         5
      59: invokevirtual #126                // Method akka/io/SimpleDnsCache$ExpiryEntry.name:()Ljava/lang/String;
      62: astore        6
      64: aload_3
      65: aload         5
      67: invokeinterface #129,  2          // InterfaceMethod scala/collection/immutable/SortedSet.$minus:(Ljava/lang/Object;)Lscala/collection/Set;
      72: checkcast     #72                 // class scala/collection/immutable/SortedSet
      75: astore_3
      76: aload         4
      78: aload         6
      80: invokeinterface #23,  2           // InterfaceMethod scala/collection/immutable/Map.get:(Ljava/lang/Object;)Lscala/Option;
      85: new           #131                // class akka/io/SimpleDnsCache$Cache$$anonfun$cleanup$1
      88: dup
      89: aload_0
      90: lload_1
      91: invokespecial #134                // Method akka/io/SimpleDnsCache$Cache$$anonfun$cleanup$1."<init>":(Lakka/io/SimpleDnsCache$Cache;J)V
      94: invokevirtual #137                // Method scala/Option.filterNot:(Lscala/Function1;)Lscala/Option;
      97: invokevirtual #140                // Method scala/Option.isDefined:()Z
     100: ifeq          21
     103: aload         4
     105: aload         6
     107: invokeinterface #143,  2          // InterfaceMethod scala/collection/immutable/Map.$minus:(Ljava/lang/Object;)Lscala/collection/Map;
     112: checkcast     #20                 // class scala/collection/immutable/Map
     115: astore        4
     117: goto          21
     120: new           #2                  // class akka/io/SimpleDnsCache$Cache
     123: dup
     124: aload_3
     125: aload         4
     127: aload_0
     128: getfield      #52                 // Field akka$io$SimpleDnsCache$Cache$$clock:Lscala/Function0;
     131: invokespecial #106                // Method "<init>":(Lscala/collection/immutable/SortedSet;Lscala/collection/immutable/Map;Lscala/Function0;)V
     134: areturn

  public akka.io.SimpleDnsCache$Cache(scala.collection.immutable.SortedSet<akka.io.SimpleDnsCache$ExpiryEntry>, scala.collection.immutable.Map<java.lang.String, akka.io.SimpleDnsCache$CacheEntry>, scala.Function0<java.lang.Object>);
    Code:
       0: aload_0
       1: aload_1
       2: putfield      #60                 // Field queue:Lscala/collection/immutable/SortedSet;
       5: aload_0
       6: aload_2
       7: putfield      #18                 // Field cache:Lscala/collection/immutable/Map;
      10: aload_0
      11: aload_3
      12: putfield      #52                 // Field akka$io$SimpleDnsCache$Cache$$clock:Lscala/Function0;
      15: aload_0
      16: invokespecial #151                // Method java/lang/Object."<init>":()V
      19: return
}
