Compiled from "TcpConnection.scala"
public class akka.io.TcpConnection$EmptyPendingWrite$ extends akka.io.TcpConnection$PendingWrite {
  public static final akka.io.TcpConnection$EmptyPendingWrite$ MODULE$;

  public static {};
    Code:
       0: new           #2                  // class akka/io/TcpConnection$EmptyPendingWrite$
       3: invokespecial #12                 // Method "<init>":()V
       6: return

  public akka.actor.ActorRef commander();
    Code:
       0: new           #16                 // class java/lang/IllegalStateException
       3: dup
       4: invokespecial #17                 // Method java/lang/IllegalStateException."<init>":()V
       7: athrow

  public akka.io.TcpConnection$PendingWrite doWrite(akka.io.TcpConnection$ConnectionInfo);
    Code:
       0: new           #16                 // class java/lang/IllegalStateException
       3: dup
       4: invokespecial #17                 // Method java/lang/IllegalStateException."<init>":()V
       7: athrow

  public void release();
    Code:
       0: new           #16                 // class java/lang/IllegalStateException
       3: dup
       4: invokespecial #17                 // Method java/lang/IllegalStateException."<init>":()V
       7: athrow

  public akka.io.TcpConnection$EmptyPendingWrite$();
    Code:
       0: aload_0
       1: invokespecial #24                 // Method akka/io/TcpConnection$PendingWrite."<init>":()V
       4: aload_0
       5: putstatic     #26                 // Field MODULE$:Lakka/io/TcpConnection$EmptyPendingWrite$;
       8: return
}
