Compiled from "ClusterSingletonMessageSerializer.scala"
public final class akka.cluster.singleton.protobuf.ClusterSingletonMessageSerializer$$anonfun$1 extends scala.runtime.AbstractFunction1<byte[], akka.cluster.singleton.ClusterSingletonManager$Internal$HandOverToMe$> implements scala.Serializable {
  public static final long serialVersionUID;

  public final akka.cluster.singleton.ClusterSingletonManager$Internal$HandOverToMe$ apply(byte[]);
    Code:
       0: getstatic     #22                 // Field akka/cluster/singleton/ClusterSingletonManager$Internal$HandOverToMe$.MODULE$:Lakka/cluster/singleton/ClusterSingletonManager$Internal$HandOverToMe$;
       3: areturn

  public final java.lang.Object apply(java.lang.Object);
    Code:
       0: aload_0
       1: aload_1
       2: checkcast     #28                 // class "[B"
       5: invokevirtual #30                 // Method apply:([B)Lakka/cluster/singleton/ClusterSingletonManager$Internal$HandOverToMe$;
       8: areturn

  public akka.cluster.singleton.protobuf.ClusterSingletonMessageSerializer$$anonfun$1(akka.cluster.singleton.protobuf.ClusterSingletonMessageSerializer);
    Code:
       0: aload_0
       1: invokespecial #37                 // Method scala/runtime/AbstractFunction1."<init>":()V
       4: return
}
