Compiled from "JRegexFactory.java"
public class juzu.impl.router.regex.JRegexFactory$JRegex extends juzu.impl.router.regex.RE {
  private final jregex.Pattern pattern;

  public juzu.impl.router.regex.JRegexFactory$JRegex(java.lang.String);
    Code:
       0: aload_0
       1: invokespecial #2                  // Method juzu/impl/router/regex/RE."<init>":()V
       4: aload_0
       5: new           #3                  // class jregex/Pattern
       8: dup
       9: aload_1
      10: invokespecial #4                  // Method jregex/Pattern."<init>":(Ljava/lang/String;)V
      13: putfield      #1                  // Field pattern:Ljregex/Pattern;
      16: return

  public juzu.impl.router.regex.RE$Matcher matcher();
    Code:
       0: new           #5                  // class juzu/impl/router/regex/JRegexFactory$JRegex$1
       3: dup
       4: aload_0
       5: invokespecial #6                  // Method juzu/impl/router/regex/JRegexFactory$JRegex$1."<init>":(Ljuzu/impl/router/regex/JRegexFactory$JRegex;)V
       8: areturn

  public java.lang.String getPattern();
    Code:
       0: aload_0
       1: getfield      #1                  // Field pattern:Ljregex/Pattern;
       4: invokevirtual #7                  // Method jregex/Pattern.toString:()Ljava/lang/String;
       7: areturn

  static jregex.Pattern access$000(juzu.impl.router.regex.JRegexFactory$JRegex);
    Code:
       0: aload_0
       1: getfield      #1                  // Field pattern:Ljregex/Pattern;
       4: areturn
}
