Compiled from "CdiValidatorFactoryService.java"
public class org.jboss.as.weld.CdiValidatorFactoryService implements org.jboss.msc.service.Service<org.jboss.as.weld.CdiValidatorFactoryService> {
  public static final org.jboss.msc.service.ServiceName SERVICE_NAME;

  private final org.jboss.msc.value.InjectedValue<org.jboss.as.weld.WeldBootstrapService> weldContainer;

  private final java.lang.ClassLoader classLoader;

  private final org.jboss.as.server.deployment.DeploymentUnit deploymentUnit;

  public org.jboss.as.weld.CdiValidatorFactoryService(org.jboss.as.server.deployment.DeploymentUnit);
    Code:
       0: aload_0
       1: invokespecial #1                  // Method java/lang/Object."<init>":()V
       4: aload_0
       5: new           #2                  // class org/jboss/msc/value/InjectedValue
       8: dup
       9: invokespecial #3                  // Method org/jboss/msc/value/InjectedValue."<init>":()V
      12: putfield      #4                  // Field weldContainer:Lorg/jboss/msc/value/InjectedValue;
      15: aload_0
      16: aload_1
      17: putfield      #5                  // Field deploymentUnit:Lorg/jboss/as/server/deployment/DeploymentUnit;
      20: aload_0
      21: getfield      #5                  // Field deploymentUnit:Lorg/jboss/as/server/deployment/DeploymentUnit;
      24: getstatic     #6                  // Field org/jboss/as/server/deployment/Attachments.MODULE:Lorg/jboss/as/server/deployment/AttachmentKey;
      27: invokeinterface #7,  2            // InterfaceMethod org/jboss/as/server/deployment/DeploymentUnit.getAttachment:(Lorg/jboss/as/server/deployment/AttachmentKey;)Ljava/lang/Object;
      32: checkcast     #8                  // class org/jboss/modules/Module
      35: astore_2
      36: aload_0
      37: aload_2
      38: invokevirtual #9                  // Method org/jboss/modules/Module.getClassLoader:()Lorg/jboss/modules/ModuleClassLoader;
      41: putfield      #10                 // Field classLoader:Ljava/lang/ClassLoader;
      44: return

  public void start(org.jboss.msc.service.StartContext) throws org.jboss.msc.service.StartException;
    Code:
       0: invokestatic  #11                 // Method org/wildfly/security/manager/WildFlySecurityManager.getCurrentContextClassLoaderPrivileged:()Ljava/lang/ClassLoader;
       3: astore_2
       4: aload_0
       5: getfield      #10                 // Field classLoader:Ljava/lang/ClassLoader;
       8: invokestatic  #12                 // Method org/wildfly/security/manager/WildFlySecurityManager.setCurrentContextClassLoaderPrivileged:(Ljava/lang/ClassLoader;)Ljava/lang/ClassLoader;
      11: pop
      12: aload_0
      13: getfield      #4                  // Field weldContainer:Lorg/jboss/msc/value/InjectedValue;
      16: invokevirtual #13                 // Method org/jboss/msc/value/InjectedValue.getValue:()Ljava/lang/Object;
      19: checkcast     #14                 // class org/jboss/as/weld/WeldBootstrapService
      22: invokevirtual #15                 // Method org/jboss/as/weld/WeldBootstrapService.getBeanManager:()Lorg/jboss/weld/manager/BeanManagerImpl;
      25: astore_3
      26: aload_0
      27: ldc           #16                 // class javax/validation/ValidatorFactory
      29: aload_3
      30: invokespecial #17                 // Method getReference:(Ljava/lang/Class;Ljavax/enterprise/inject/spi/BeanManager;)Ljava/lang/Object;
      33: checkcast     #16                 // class javax/validation/ValidatorFactory
      36: astore        4
      38: aload_0
      39: getfield      #5                  // Field deploymentUnit:Lorg/jboss/as/server/deployment/DeploymentUnit;
      42: getstatic     #18                 // Field org/jboss/as/ee/beanvalidation/BeanValidationAttachments.VALIDATOR_FACTORY:Lorg/jboss/as/server/deployment/AttachmentKey;
      45: invokeinterface #7,  2            // InterfaceMethod org/jboss/as/server/deployment/DeploymentUnit.getAttachment:(Lorg/jboss/as/server/deployment/AttachmentKey;)Ljava/lang/Object;
      50: checkcast     #19                 // class org/jboss/as/ee/beanvalidation/LazyValidatorFactory
      53: checkcast     #19                 // class org/jboss/as/ee/beanvalidation/LazyValidatorFactory
      56: astore        5
      58: aload         5
      60: aload         4
      62: invokevirtual #20                 // Method org/jboss/as/ee/beanvalidation/LazyValidatorFactory.replaceDelegate:(Ljavax/validation/ValidatorFactory;)V
      65: aload_2
      66: invokestatic  #12                 // Method org/wildfly/security/manager/WildFlySecurityManager.setCurrentContextClassLoaderPrivileged:(Ljava/lang/ClassLoader;)Ljava/lang/ClassLoader;
      69: pop
      70: goto          83
      73: astore        6
      75: aload_2
      76: invokestatic  #12                 // Method org/wildfly/security/manager/WildFlySecurityManager.setCurrentContextClassLoaderPrivileged:(Ljava/lang/ClassLoader;)Ljava/lang/ClassLoader;
      79: pop
      80: aload         6
      82: athrow
      83: return
    Exception table:
       from    to  target type
           4    65    73   any
          73    75    73   any

  public void stop(org.jboss.msc.service.StopContext);
    Code:
       0: invokestatic  #11                 // Method org/wildfly/security/manager/WildFlySecurityManager.getCurrentContextClassLoaderPrivileged:()Ljava/lang/ClassLoader;
       3: astore_2
       4: aload_0
       5: getfield      #10                 // Field classLoader:Ljava/lang/ClassLoader;
       8: invokestatic  #12                 // Method org/wildfly/security/manager/WildFlySecurityManager.setCurrentContextClassLoaderPrivileged:(Ljava/lang/ClassLoader;)Ljava/lang/ClassLoader;
      11: pop
      12: aload_0
      13: getfield      #5                  // Field deploymentUnit:Lorg/jboss/as/server/deployment/DeploymentUnit;
      16: getstatic     #18                 // Field org/jboss/as/ee/beanvalidation/BeanValidationAttachments.VALIDATOR_FACTORY:Lorg/jboss/as/server/deployment/AttachmentKey;
      19: invokeinterface #7,  2            // InterfaceMethod org/jboss/as/server/deployment/DeploymentUnit.getAttachment:(Lorg/jboss/as/server/deployment/AttachmentKey;)Ljava/lang/Object;
      24: checkcast     #16                 // class javax/validation/ValidatorFactory
      27: astore_3
      28: aload_3
      29: ifnull        38
      32: aload_3
      33: invokeinterface #21,  1           // InterfaceMethod javax/validation/ValidatorFactory.close:()V
      38: aload_2
      39: invokestatic  #12                 // Method org/wildfly/security/manager/WildFlySecurityManager.setCurrentContextClassLoaderPrivileged:(Ljava/lang/ClassLoader;)Ljava/lang/ClassLoader;
      42: pop
      43: goto          56
      46: astore        4
      48: aload_2
      49: invokestatic  #12                 // Method org/wildfly/security/manager/WildFlySecurityManager.setCurrentContextClassLoaderPrivileged:(Ljava/lang/ClassLoader;)Ljava/lang/ClassLoader;
      52: pop
      53: aload         4
      55: athrow
      56: return
    Exception table:
       from    to  target type
           4    38    46   any
          46    48    46   any

  public org.jboss.as.weld.CdiValidatorFactoryService getValue() throws java.lang.IllegalStateException, java.lang.IllegalArgumentException;
    Code:
       0: aload_0
       1: areturn

  private <T> T getReference(java.lang.Class<T>, javax.enterprise.inject.spi.BeanManager);
    Code:
       0: aload_2
       1: aload_1
       2: iconst_1
       3: anewarray     #22                 // class java/lang/annotation/Annotation
       6: dup
       7: iconst_0
       8: new           #23                 // class org/jboss/as/weld/CdiValidatorFactoryService$1
      11: dup
      12: aload_0
      13: invokespecial #24                 // Method org/jboss/as/weld/CdiValidatorFactoryService$1."<init>":(Lorg/jboss/as/weld/CdiValidatorFactoryService;)V
      16: aastore
      17: invokeinterface #25,  3           // InterfaceMethod javax/enterprise/inject/spi/BeanManager.getBeans:(Ljava/lang/reflect/Type;[Ljava/lang/annotation/Annotation;)Ljava/util/Set;
      22: astore_3
      23: aload_3
      24: invokeinterface #26,  1           // InterfaceMethod java/util/Set.iterator:()Ljava/util/Iterator;
      29: astore        4
      31: aload         4
      33: invokeinterface #27,  1           // InterfaceMethod java/util/Iterator.hasNext:()Z
      38: ifne          43
      41: aconst_null
      42: areturn
      43: aload         4
      45: invokeinterface #28,  1           // InterfaceMethod java/util/Iterator.next:()Ljava/lang/Object;
      50: checkcast     #29                 // class javax/enterprise/inject/spi/Bean
      53: astore        5
      55: aload_2
      56: aload         5
      58: invokeinterface #30,  2           // InterfaceMethod javax/enterprise/inject/spi/BeanManager.createCreationalContext:(Ljavax/enterprise/context/spi/Contextual;)Ljavax/enterprise/context/spi/CreationalContext;
      63: astore        6
      65: aload_2
      66: aload         5
      68: aload_1
      69: aload         6
      71: invokeinterface #31,  4           // InterfaceMethod javax/enterprise/inject/spi/BeanManager.getReference:(Ljavax/enterprise/inject/spi/Bean;Ljava/lang/reflect/Type;Ljavax/enterprise/context/spi/CreationalContext;)Ljava/lang/Object;
      76: areturn

  public org.jboss.msc.value.InjectedValue<org.jboss.as.weld.WeldBootstrapService> getWeldContainer();
    Code:
       0: aload_0
       1: getfield      #4                  // Field weldContainer:Lorg/jboss/msc/value/InjectedValue;
       4: areturn

  public java.lang.Object getValue() throws java.lang.IllegalStateException, java.lang.IllegalArgumentException;
    Code:
       0: aload_0
       1: invokevirtual #32                 // Method getValue:()Lorg/jboss/as/weld/CdiValidatorFactoryService;
       4: areturn

  static {};
    Code:
       0: iconst_1
       1: anewarray     #33                 // class java/lang/String
       4: dup
       5: iconst_0
       6: ldc           #34                 // String CdiValidatorFactoryService
       8: aastore
       9: invokestatic  #35                 // Method org/jboss/msc/service/ServiceName.of:([Ljava/lang/String;)Lorg/jboss/msc/service/ServiceName;
      12: putstatic     #36                 // Field SERVICE_NAME:Lorg/jboss/msc/service/ServiceName;
      15: return
}
