Compiled from "BaseXMLWriter.java"
public abstract class org.apache.jena.rdfxml.xmloutput.impl.BaseXMLWriter implements org.apache.jena.rdfxml.xmloutput.RDFXMLWriterI {
  private static final java.lang.String newline;

  private static final java.lang.String DEFAULT_NS_ENTITY_NAME;

  private static final java.lang.String DEFAULT_NS_ENTITY_NAME_ALT;

  private java.lang.String defaultNSEntityName;

  private static org.slf4j.Logger xlogger;

  protected static org.apache.jena.rdfxml.xmloutput.impl.SimpleLogger logger;

  private static java.util.Set<java.lang.String> badRDF;

  private int jenaPrefixCount;

  static java.lang.String RDFNS;

  private static java.util.regex.Pattern jenaNamespace;

  java.lang.String xmlBase;

  private org.apache.jena.iri.IRI baseURI;

  boolean longId;

  private boolean demandGoodURIs;

  int tabSize;

  int width;

  java.util.HashMap<org.apache.jena.rdf.model.AnonId, java.lang.String> anonMap;

  int anonCount;

  private static org.apache.jena.rdf.model.impl.RDFDefaultErrorHandler defaultErrorHandler;

  org.apache.jena.rdf.model.RDFErrorHandler errorHandler;

  java.lang.Boolean showXmlDeclaration;

  protected java.lang.Boolean showDoctypeDeclaration;

  private boolean writingAllModelPrefixNamespaces;

  private org.apache.jena.rdfxml.xmloutput.impl.Relation<java.lang.String> nameSpaces;

  private java.util.Map<java.lang.String, java.lang.String> ns;

  private org.apache.jena.shared.PrefixMapping modelPrefixMapping;

  private java.util.Set<java.lang.String> namespacesNeeded;

  private static final int FAST;

  private static final int START;

  private static final int END;

  private static final int ATTR;

  private static final int FASTATTR;

  public static boolean dbg;

  static org.apache.jena.iri.IRIFactory factory;

  protected static final java.util.regex.Pattern predefinedEntityNames;

  private java.lang.String attributeQuoteChar;

  private static final char ESCAPE;

  static final char[] hexchar;

  private org.apache.jena.rdf.model.Resource[] blockedRules;

  private int relativeFlags;

  public org.apache.jena.rdfxml.xmloutput.impl.BaseXMLWriter();
    Code:
       0: aload_0
       1: invokespecial #2                  // Method java/lang/Object."<init>":()V
       4: aload_0
       5: ldc           #3                  // String UNSET
       7: putfield      #4                  // Field defaultNSEntityName:Ljava/lang/String;
      10: aload_0
      11: aconst_null
      12: putfield      #5                  // Field xmlBase:Ljava/lang/String;
      15: aload_0
      16: iconst_0
      17: putfield      #6                  // Field longId:Z
      20: aload_0
      21: iconst_1
      22: putfield      #7                  // Field demandGoodURIs:Z
      25: aload_0
      26: iconst_2
      27: putfield      #8                  // Field tabSize:I
      30: aload_0
      31: bipush        60
      33: putfield      #9                  // Field width:I
      36: aload_0
      37: new           #10                 // class java/util/HashMap
      40: dup
      41: invokespecial #11                 // Method java/util/HashMap."<init>":()V
      44: putfield      #12                 // Field anonMap:Ljava/util/HashMap;
      47: aload_0
      48: iconst_0
      49: putfield      #13                 // Field anonCount:I
      52: aload_0
      53: getstatic     #14                 // Field defaultErrorHandler:Lorg/apache/jena/rdf/model/impl/RDFDefaultErrorHandler;
      56: putfield      #15                 // Field errorHandler:Lorg/apache/jena/rdf/model/RDFErrorHandler;
      59: aload_0
      60: aconst_null
      61: putfield      #16                 // Field showXmlDeclaration:Ljava/lang/Boolean;
      64: aload_0
      65: getstatic     #17                 // Field java/lang/Boolean.FALSE:Ljava/lang/Boolean;
      68: putfield      #18                 // Field showDoctypeDeclaration:Ljava/lang/Boolean;
      71: aload_0
      72: iconst_1
      73: putfield      #19                 // Field writingAllModelPrefixNamespaces:Z
      76: aload_0
      77: new           #20                 // class org/apache/jena/rdfxml/xmloutput/impl/Relation
      80: dup
      81: invokespecial #21                 // Method org/apache/jena/rdfxml/xmloutput/impl/Relation."<init>":()V
      84: putfield      #22                 // Field nameSpaces:Lorg/apache/jena/rdfxml/xmloutput/impl/Relation;
      87: aload_0
      88: ldc           #23                 // String \"
      90: putfield      #24                 // Field attributeQuoteChar:Ljava/lang/String;
      93: aload_0
      94: iconst_1
      95: anewarray     #25                 // class org/apache/jena/rdf/model/Resource
      98: dup
      99: iconst_0
     100: getstatic     #26                 // Field org/apache/jena/vocabulary/RDFSyntax.propertyAttr:Lorg/apache/jena/rdf/model/Resource;
     103: aastore
     104: putfield      #27                 // Field blockedRules:[Lorg/apache/jena/rdf/model/Resource;
     107: aload_0
     108: bipush        29
     110: putfield      #29                 // Field relativeFlags:I
     113: aload_0
     114: invokevirtual #30                 // Method setupMaps:()V
     117: return

  public static org.apache.jena.rdfxml.xmloutput.impl.SimpleLogger setLogger(org.apache.jena.rdfxml.xmloutput.impl.SimpleLogger);
    Code:
       0: getstatic     #31                 // Field logger:Lorg/apache/jena/rdfxml/xmloutput/impl/SimpleLogger;
       3: astore_1
       4: aload_0
       5: putstatic     #31                 // Field logger:Lorg/apache/jena/rdfxml/xmloutput/impl/SimpleLogger;
       8: aload_1
       9: areturn

  protected abstract void unblockAll();

  protected abstract void blockRule(org.apache.jena.rdf.model.Resource);

  protected abstract void writeBody(org.apache.jena.rdf.model.Model, java.io.PrintWriter, java.lang.String, boolean);

  java.lang.String anonId(org.apache.jena.rdf.model.Resource);
    Code:
       0: aload_0
       1: getfield      #6                  // Field longId:Z
       4: ifeq          15
       7: aload_0
       8: aload_1
       9: invokespecial #32                 // Method longAnonId:(Lorg/apache/jena/rdf/model/Resource;)Ljava/lang/String;
      12: goto          20
      15: aload_0
      16: aload_1
      17: invokespecial #33                 // Method shortAnonId:(Lorg/apache/jena/rdf/model/Resource;)Ljava/lang/String;
      20: areturn

  private java.lang.String shortAnonId(org.apache.jena.rdf.model.Resource);
    Code:
       0: aload_0
       1: getfield      #12                 // Field anonMap:Ljava/util/HashMap;
       4: aload_1
       5: invokeinterface #34,  1           // InterfaceMethod org/apache/jena/rdf/model/Resource.getId:()Lorg/apache/jena/rdf/model/AnonId;
      10: invokevirtual #35                 // Method java/util/HashMap.get:(Ljava/lang/Object;)Ljava/lang/Object;
      13: checkcast     #36                 // class java/lang/String
      16: astore_2
      17: aload_2
      18: ifnonnull     69
      21: new           #37                 // class java/lang/StringBuilder
      24: dup
      25: invokespecial #38                 // Method java/lang/StringBuilder."<init>":()V
      28: ldc           #39                 // String A
      30: invokevirtual #40                 // Method java/lang/StringBuilder.append:(Ljava/lang/String;)Ljava/lang/StringBuilder;
      33: aload_0
      34: dup
      35: getfield      #13                 // Field anonCount:I
      38: dup_x1
      39: iconst_1
      40: iadd
      41: putfield      #13                 // Field anonCount:I
      44: invokestatic  #41                 // Method java/lang/Integer.toString:(I)Ljava/lang/String;
      47: invokevirtual #40                 // Method java/lang/StringBuilder.append:(Ljava/lang/String;)Ljava/lang/StringBuilder;
      50: invokevirtual #42                 // Method java/lang/StringBuilder.toString:()Ljava/lang/String;
      53: astore_2
      54: aload_0
      55: getfield      #12                 // Field anonMap:Ljava/util/HashMap;
      58: aload_1
      59: invokeinterface #34,  1           // InterfaceMethod org/apache/jena/rdf/model/Resource.getId:()Lorg/apache/jena/rdf/model/AnonId;
      64: aload_2
      65: invokevirtual #43                 // Method java/util/HashMap.put:(Ljava/lang/Object;Ljava/lang/Object;)Ljava/lang/Object;
      68: pop
      69: aload_2
      70: areturn

  private java.lang.String longAnonId(org.apache.jena.rdf.model.Resource);
    Code:
       0: aload_1
       1: invokeinterface #34,  1           // InterfaceMethod org/apache/jena/rdf/model/Resource.getId:()Lorg/apache/jena/rdf/model/AnonId;
       6: invokevirtual #44                 // Method org/apache/jena/rdf/model/AnonId.toString:()Ljava/lang/String;
       9: astore_2
      10: aload_2
      11: invokestatic  #45                 // Method org/apache/xerces/util/XMLChar.isValidNCName:(Ljava/lang/String;)Z
      14: ifeq          21
      17: aload_2
      18: goto          25
      21: aload_2
      22: invokestatic  #46                 // Method escapedId:(Ljava/lang/String;)Ljava/lang/String;
      25: areturn

  void addNameSpace(java.lang.String);
    Code:
       0: aload_0
       1: getfield      #47                 // Field namespacesNeeded:Ljava/util/Set;
       4: aload_1
       5: invokeinterface #48,  2           // InterfaceMethod java/util/Set.add:(Ljava/lang/Object;)Z
      10: pop
      11: return

  boolean isDefaultNamespace(java.lang.String);
    Code:
       0: ldc           #49                 // String
       2: aload_0
       3: getfield      #50                 // Field ns:Ljava/util/Map;
       6: aload_1
       7: invokeinterface #51,  2           // InterfaceMethod java/util/Map.get:(Ljava/lang/Object;)Ljava/lang/Object;
      12: invokevirtual #52                 // Method java/lang/String.equals:(Ljava/lang/Object;)Z
      15: ireturn

  private void addNameSpaces(org.apache.jena.rdf.model.Model);
    Code:
       0: aload_1
       1: invokeinterface #53,  1           // InterfaceMethod org/apache/jena/rdf/model/Model.listNameSpaces:()Lorg/apache/jena/rdf/model/NsIterator;
       6: astore_2
       7: aload_2
       8: invokeinterface #54,  1           // InterfaceMethod org/apache/jena/rdf/model/NsIterator.hasNext:()Z
      13: ifeq          29
      16: aload_0
      17: aload_2
      18: invokeinterface #55,  1           // InterfaceMethod org/apache/jena/rdf/model/NsIterator.nextNs:()Ljava/lang/String;
      23: invokevirtual #56                 // Method addNameSpace:(Ljava/lang/String;)V
      26: goto          7
      29: return

  private void primeNamespace(org.apache.jena.rdf.model.Model);
    Code:
       0: aload_1
       1: invokeinterface #57,  1           // InterfaceMethod org/apache/jena/rdf/model/Model.getNsPrefixMap:()Ljava/util/Map;
       6: astore_2
       7: aload_2
       8: invokeinterface #58,  1           // InterfaceMethod java/util/Map.entrySet:()Ljava/util/Set;
      13: invokeinterface #59,  1           // InterfaceMethod java/util/Set.iterator:()Ljava/util/Iterator;
      18: astore_3
      19: aload_3
      20: invokeinterface #60,  1           // InterfaceMethod java/util/Iterator.hasNext:()Z
      25: ifeq          94
      28: aload_3
      29: invokeinterface #61,  1           // InterfaceMethod java/util/Iterator.next:()Ljava/lang/Object;
      34: checkcast     #62                 // class java/util/Map$Entry
      37: astore        4
      39: aload         4
      41: invokeinterface #63,  1           // InterfaceMethod java/util/Map$Entry.getValue:()Ljava/lang/Object;
      46: checkcast     #36                 // class java/lang/String
      49: astore        5
      51: aload_0
      52: aload         5
      54: invokevirtual #64                 // Method getPrefixFor:(Ljava/lang/String;)Ljava/lang/String;
      57: astore        6
      59: aload         6
      61: ifnonnull     91
      64: aload_0
      65: aload_1
      66: aload         5
      68: invokeinterface #65,  2           // InterfaceMethod org/apache/jena/rdf/model/Model.getNsURIPrefix:(Ljava/lang/String;)Ljava/lang/String;
      73: aload         5
      75: invokevirtual #66                 // Method setNsPrefix:(Ljava/lang/String;Ljava/lang/String;)V
      78: aload_0
      79: getfield      #19                 // Field writingAllModelPrefixNamespaces:Z
      82: ifeq          91
      85: aload_0
      86: aload         5
      88: invokevirtual #56                 // Method addNameSpace:(Ljava/lang/String;)V
      91: goto          19
      94: aload_1
      95: ldc           #49                 // String
      97: invokestatic  #67                 // Method usesPrefix:(Lorg/apache/jena/rdf/model/Model;Ljava/lang/String;)Z
     100: ifeq          160
     103: ldc           #69                 // String this
     105: astore_3
     106: aload_1
     107: aload_3
     108: invokestatic  #67                 // Method usesPrefix:(Lorg/apache/jena/rdf/model/Model;Ljava/lang/String;)Z
     111: ifeq          117
     114: ldc           #70                 // String here
     116: astore_3
     117: iconst_0
     118: istore        4
     120: aload_1
     121: aload_3
     122: invokestatic  #67                 // Method usesPrefix:(Lorg/apache/jena/rdf/model/Model;Ljava/lang/String;)Z
     125: ifeq          155
     128: new           #37                 // class java/lang/StringBuilder
     131: dup
     132: invokespecial #38                 // Method java/lang/StringBuilder."<init>":()V
     135: ldc           #71                 // String here.
     137: invokevirtual #40                 // Method java/lang/StringBuilder.append:(Ljava/lang/String;)Ljava/lang/StringBuilder;
     140: iload         4
     142: invokevirtual #72                 // Method java/lang/StringBuilder.append:(I)Ljava/lang/StringBuilder;
     145: invokevirtual #42                 // Method java/lang/StringBuilder.toString:()Ljava/lang/String;
     148: astore_3
     149: iinc          4, 1
     152: goto          120
     155: aload_0
     156: aload_3
     157: putfield      #4                  // Field defaultNSEntityName:Ljava/lang/String;
     160: return

  void setupMaps();
    Code:
       0: aload_0
       1: getfield      #22                 // Field nameSpaces:Lorg/apache/jena/rdfxml/xmloutput/impl/Relation;
       4: invokestatic  #73                 // Method org/apache/jena/vocabulary/RDF.getURI:()Ljava/lang/String;
       7: ldc           #74                 // String rdf
       9: invokevirtual #75                 // Method org/apache/jena/rdfxml/xmloutput/impl/Relation.set11:(Ljava/lang/Object;Ljava/lang/Object;)V
      12: aload_0
      13: getfield      #22                 // Field nameSpaces:Lorg/apache/jena/rdfxml/xmloutput/impl/Relation;
      16: invokestatic  #76                 // Method org/apache/jena/vocabulary/RDFS.getURI:()Ljava/lang/String;
      19: ldc           #77                 // String rdfs
      21: invokevirtual #75                 // Method org/apache/jena/rdfxml/xmloutput/impl/Relation.set11:(Ljava/lang/Object;Ljava/lang/Object;)V
      24: aload_0
      25: getfield      #22                 // Field nameSpaces:Lorg/apache/jena/rdfxml/xmloutput/impl/Relation;
      28: invokestatic  #78                 // Method org/apache/jena/vocabulary/DC.getURI:()Ljava/lang/String;
      31: ldc           #79                 // String dc
      33: invokevirtual #75                 // Method org/apache/jena/rdfxml/xmloutput/impl/Relation.set11:(Ljava/lang/Object;Ljava/lang/Object;)V
      36: aload_0
      37: getfield      #22                 // Field nameSpaces:Lorg/apache/jena/rdfxml/xmloutput/impl/Relation;
      40: invokestatic  #80                 // Method org/apache/jena/vocabulary/RSS.getURI:()Ljava/lang/String;
      43: ldc           #81                 // String rss
      45: invokevirtual #75                 // Method org/apache/jena/rdfxml/xmloutput/impl/Relation.set11:(Ljava/lang/Object;Ljava/lang/Object;)V
      48: aload_0
      49: getfield      #22                 // Field nameSpaces:Lorg/apache/jena/rdfxml/xmloutput/impl/Relation;
      52: ldc           #82                 // String http://www.daml.org/2001/03/daml+oil.daml#
      54: ldc           #83                 // String daml
      56: invokevirtual #75                 // Method org/apache/jena/rdfxml/xmloutput/impl/Relation.set11:(Ljava/lang/Object;Ljava/lang/Object;)V
      59: aload_0
      60: getfield      #22                 // Field nameSpaces:Lorg/apache/jena/rdfxml/xmloutput/impl/Relation;
      63: invokestatic  #84                 // Method org/apache/jena/vocabulary/VCARD.getURI:()Ljava/lang/String;
      66: ldc           #85                 // String vcard
      68: invokevirtual #75                 // Method org/apache/jena/rdfxml/xmloutput/impl/Relation.set11:(Ljava/lang/Object;Ljava/lang/Object;)V
      71: aload_0
      72: getfield      #22                 // Field nameSpaces:Lorg/apache/jena/rdfxml/xmloutput/impl/Relation;
      75: ldc           #86                 // String http://www.w3.org/2002/07/owl#
      77: ldc           #87                 // String owl
      79: invokevirtual #75                 // Method org/apache/jena/rdfxml/xmloutput/impl/Relation.set11:(Ljava/lang/Object;Ljava/lang/Object;)V
      82: return

  void workOutNamespaces();
    Code:
       0: aload_0
       1: getfield      #50                 // Field ns:Ljava/util/Map;
       4: ifnonnull     44
       7: aload_0
       8: new           #10                 // class java/util/HashMap
      11: dup
      12: invokespecial #11                 // Method java/util/HashMap."<init>":()V
      15: putfield      #50                 // Field ns:Ljava/util/Map;
      18: new           #88                 // class java/util/HashSet
      21: dup
      22: invokespecial #89                 // Method java/util/HashSet."<init>":()V
      25: astore_1
      26: aload_0
      27: aload_0
      28: getfield      #50                 // Field ns:Ljava/util/Map;
      31: aload_1
      32: invokespecial #90                 // Method setFromWriterSystemProperties:(Ljava/util/Map;Ljava/util/Set;)V
      35: aload_0
      36: aload_0
      37: getfield      #50                 // Field ns:Ljava/util/Map;
      40: aload_1
      41: invokespecial #91                 // Method setFromGivenNamespaces:(Ljava/util/Map;Ljava/util/Set;)V
      44: return

  private void setFromWriterSystemProperties(java.util.Map<java.lang.String, java.lang.String>, java.util.Set<java.lang.String>);
    Code:
       0: aload_0
       1: getfield      #47                 // Field namespacesNeeded:Ljava/util/Set;
       4: invokeinterface #59,  1           // InterfaceMethod java/util/Set.iterator:()Ljava/util/Iterator;
       9: astore_3
      10: aload_3
      11: invokeinterface #60,  1           // InterfaceMethod java/util/Iterator.hasNext:()Z
      16: ifeq          103
      19: aload_3
      20: invokeinterface #61,  1           // InterfaceMethod java/util/Iterator.next:()Ljava/lang/Object;
      25: checkcast     #36                 // class java/lang/String
      28: astore        4
      30: new           #37                 // class java/lang/StringBuilder
      33: dup
      34: invokespecial #38                 // Method java/lang/StringBuilder."<init>":()V
      37: ldc           #93                 // String org.apache.jena.nsprefix.
      39: invokevirtual #40                 // Method java/lang/StringBuilder.append:(Ljava/lang/String;)Ljava/lang/StringBuilder;
      42: aload         4
      44: invokevirtual #40                 // Method java/lang/StringBuilder.append:(Ljava/lang/String;)Ljava/lang/StringBuilder;
      47: invokevirtual #42                 // Method java/lang/StringBuilder.toString:()Ljava/lang/String;
      50: invokestatic  #94                 // Method org/apache/jena/JenaRuntime.getSystemProperty:(Ljava/lang/String;)Ljava/lang/String;
      53: astore        5
      55: aload         5
      57: ifnull        100
      60: aload_0
      61: aload         5
      63: invokespecial #95                 // Method checkLegalPrefix:(Ljava/lang/String;)Z
      66: ifeq          100
      69: aload_2
      70: aload         5
      72: invokeinterface #96,  2           // InterfaceMethod java/util/Set.contains:(Ljava/lang/Object;)Z
      77: ifne          100
      80: aload_1
      81: aload         4
      83: aload         5
      85: invokeinterface #97,  3           // InterfaceMethod java/util/Map.put:(Ljava/lang/Object;Ljava/lang/Object;)Ljava/lang/Object;
      90: pop
      91: aload_2
      92: aload         5
      94: invokeinterface #48,  2           // InterfaceMethod java/util/Set.add:(Ljava/lang/Object;)Z
      99: pop
     100: goto          10
     103: return

  private void setFromGivenNamespaces(java.util.Map<java.lang.String, java.lang.String>, java.util.Set<java.lang.String>);
    Code:
       0: aload_0
       1: getfield      #47                 // Field namespacesNeeded:Ljava/util/Set;
       4: invokeinterface #59,  1           // InterfaceMethod java/util/Set.iterator:()Ljava/util/Iterator;
       9: astore_3
      10: aload_3
      11: invokeinterface #60,  1           // InterfaceMethod java/util/Iterator.hasNext:()Z
      16: ifeq          178
      19: aload_3
      20: invokeinterface #61,  1           // InterfaceMethod java/util/Iterator.next:()Ljava/lang/Object;
      25: checkcast     #36                 // class java/lang/String
      28: astore        4
      30: aload_1
      31: aload         4
      33: invokeinterface #98,  2           // InterfaceMethod java/util/Map.containsKey:(Ljava/lang/Object;)Z
      38: ifeq          44
      41: goto          10
      44: aconst_null
      45: astore        5
      47: aload_0
      48: getfield      #22                 // Field nameSpaces:Lorg/apache/jena/rdfxml/xmloutput/impl/Relation;
      51: aload         4
      53: invokevirtual #99                 // Method org/apache/jena/rdfxml/xmloutput/impl/Relation.forward:(Ljava/lang/Object;)Ljava/util/Set;
      56: astore        6
      58: aload         6
      60: ifnull        108
      63: aload         6
      65: invokeinterface #59,  1           // InterfaceMethod java/util/Set.iterator:()Ljava/util/Iterator;
      70: astore        7
      72: aload         7
      74: invokeinterface #60,  1           // InterfaceMethod java/util/Iterator.hasNext:()Z
      79: ifeq          94
      82: aload         7
      84: invokeinterface #61,  1           // InterfaceMethod java/util/Iterator.next:()Ljava/lang/Object;
      89: checkcast     #36                 // class java/lang/String
      92: astore        5
      94: aload_2
      95: aload         5
      97: invokeinterface #96,  2           // InterfaceMethod java/util/Set.contains:(Ljava/lang/Object;)Z
     102: ifeq          108
     105: aconst_null
     106: astore        5
     108: aload         5
     110: ifnonnull     155
     113: new           #37                 // class java/lang/StringBuilder
     116: dup
     117: invokespecial #38                 // Method java/lang/StringBuilder."<init>":()V
     120: ldc           #100                // String j.
     122: invokevirtual #40                 // Method java/lang/StringBuilder.append:(Ljava/lang/String;)Ljava/lang/StringBuilder;
     125: aload_0
     126: dup
     127: getfield      #101                // Field jenaPrefixCount:I
     130: dup_x1
     131: iconst_1
     132: iadd
     133: putfield      #101                // Field jenaPrefixCount:I
     136: invokevirtual #72                 // Method java/lang/StringBuilder.append:(I)Ljava/lang/StringBuilder;
     139: invokevirtual #42                 // Method java/lang/StringBuilder.toString:()Ljava/lang/String;
     142: astore        5
     144: aload_2
     145: aload         5
     147: invokeinterface #96,  2           // InterfaceMethod java/util/Set.contains:(Ljava/lang/Object;)Z
     152: ifne          113
     155: aload_1
     156: aload         4
     158: aload         5
     160: invokeinterface #97,  3           // InterfaceMethod java/util/Map.put:(Ljava/lang/Object;Ljava/lang/Object;)Ljava/lang/Object;
     165: pop
     166: aload_2
     167: aload         5
     169: invokeinterface #48,  2           // InterfaceMethod java/util/Set.add:(Ljava/lang/Object;)Z
     174: pop
     175: goto          10
     178: return

  public final synchronized void setNsPrefix(java.lang.String, java.lang.String);
    Code:
       0: aload_0
       1: aload_1
       2: invokespecial #95                 // Method checkLegalPrefix:(Ljava/lang/String;)Z
       5: ifeq          17
       8: aload_0
       9: getfield      #22                 // Field nameSpaces:Lorg/apache/jena/rdfxml/xmloutput/impl/Relation;
      12: aload_2
      13: aload_1
      14: invokevirtual #75                 // Method org/apache/jena/rdfxml/xmloutput/impl/Relation.set11:(Ljava/lang/Object;Ljava/lang/Object;)V
      17: return

  public final java.lang.String getPrefixFor(java.lang.String);
    Code:
       0: ldc           #102                // String http://www.w3.org/XML/1998/namespace
       2: aload_1
       3: invokevirtual #52                 // Method java/lang/String.equals:(Ljava/lang/Object;)Z
       6: ifeq          12
       9: ldc           #103                // String xml
      11: areturn
      12: ldc           #104                // String http://www.w3.org/2000/xmlns/
      14: aload_1
      15: invokevirtual #52                 // Method java/lang/String.equals:(Ljava/lang/Object;)Z
      18: ifeq          24
      21: ldc           #105                // String xmlns
      23: areturn
      24: aload_0
      25: getfield      #22                 // Field nameSpaces:Lorg/apache/jena/rdfxml/xmloutput/impl/Relation;
      28: aload_1
      29: invokevirtual #106                // Method org/apache/jena/rdfxml/xmloutput/impl/Relation.backward:(Ljava/lang/Object;)Ljava/util/Set;
      32: astore_2
      33: aload_2
      34: ifnull        62
      37: aload_2
      38: invokeinterface #107,  1          // InterfaceMethod java/util/Set.size:()I
      43: iconst_1
      44: if_icmpne     62
      47: aload_2
      48: invokeinterface #59,  1           // InterfaceMethod java/util/Set.iterator:()Ljava/util/Iterator;
      53: invokeinterface #61,  1           // InterfaceMethod java/util/Iterator.next:()Ljava/lang/Object;
      58: checkcast     #36                 // class java/lang/String
      61: areturn
      62: aconst_null
      63: areturn

  java.lang.String xmlnsDecl();
    Code:
       0: aload_0
       1: invokevirtual #108                // Method workOutNamespaces:()V
       4: new           #37                 // class java/lang/StringBuilder
       7: dup
       8: invokespecial #38                 // Method java/lang/StringBuilder."<init>":()V
      11: astore_1
      12: aload_0
      13: getfield      #50                 // Field ns:Ljava/util/Map;
      16: invokeinterface #58,  1           // InterfaceMethod java/util/Map.entrySet:()Ljava/util/Set;
      21: invokeinterface #59,  1           // InterfaceMethod java/util/Set.iterator:()Ljava/util/Iterator;
      26: astore_2
      27: aload_2
      28: invokeinterface #60,  1           // InterfaceMethod java/util/Iterator.hasNext:()Z
      33: ifeq          124
      36: aload_2
      37: invokeinterface #61,  1           // InterfaceMethod java/util/Iterator.next:()Ljava/lang/Object;
      42: checkcast     #62                 // class java/util/Map$Entry
      45: astore_3
      46: aload_3
      47: invokeinterface #63,  1           // InterfaceMethod java/util/Map$Entry.getValue:()Ljava/lang/Object;
      52: checkcast     #36                 // class java/lang/String
      55: astore        4
      57: aload_3
      58: invokeinterface #109,  1          // InterfaceMethod java/util/Map$Entry.getKey:()Ljava/lang/Object;
      63: checkcast     #36                 // class java/lang/String
      66: astore        5
      68: aload_1
      69: getstatic     #110                // Field newline:Ljava/lang/String;
      72: invokevirtual #40                 // Method java/lang/StringBuilder.append:(Ljava/lang/String;)Ljava/lang/StringBuilder;
      75: ldc           #111                // String     xmlns
      77: invokevirtual #40                 // Method java/lang/StringBuilder.append:(Ljava/lang/String;)Ljava/lang/StringBuilder;
      80: pop
      81: aload         4
      83: invokevirtual #112                // Method java/lang/String.length:()I
      86: ifle          101
      89: aload_1
      90: bipush        58
      92: invokevirtual #113                // Method java/lang/StringBuilder.append:(C)Ljava/lang/StringBuilder;
      95: aload         4
      97: invokevirtual #40                 // Method java/lang/StringBuilder.append:(Ljava/lang/String;)Ljava/lang/StringBuilder;
     100: pop
     101: aload_1
     102: bipush        61
     104: invokevirtual #113                // Method java/lang/StringBuilder.append:(C)Ljava/lang/StringBuilder;
     107: aload_0
     108: aload_0
     109: aload         5
     111: invokespecial #114                // Method checkURI:(Ljava/lang/String;)Ljava/lang/String;
     114: invokevirtual #115                // Method substitutedAttribute:(Ljava/lang/String;)Ljava/lang/String;
     117: invokevirtual #40                 // Method java/lang/StringBuilder.append:(Ljava/lang/String;)Ljava/lang/StringBuilder;
     120: pop
     121: goto          27
     124: aload_1
     125: invokevirtual #42                 // Method java/lang/StringBuilder.toString:()Ljava/lang/String;
     128: areturn

  java.lang.String rdfEl(java.lang.String);
    Code:
       0: aload_0
       1: getstatic     #116                // Field RDFNS:Ljava/lang/String;
       4: aload_1
       5: iconst_1
       6: iconst_1
       7: invokevirtual #117                // Method tag:(Ljava/lang/String;Ljava/lang/String;IZ)Ljava/lang/String;
      10: areturn

  java.lang.String startElementTag(java.lang.String, java.lang.String);
    Code:
       0: aload_0
       1: aload_1
       2: aload_2
       3: iconst_2
       4: iconst_0
       5: invokevirtual #117                // Method tag:(Ljava/lang/String;Ljava/lang/String;IZ)Ljava/lang/String;
       8: areturn

  protected java.lang.String startElementTag(java.lang.String);
    Code:
       0: aload_0
       1: aload_1
       2: iconst_2
       3: invokevirtual #118                // Method splitTag:(Ljava/lang/String;I)Ljava/lang/String;
       6: areturn

  java.lang.String attributeTag(java.lang.String);
    Code:
       0: aload_0
       1: aload_1
       2: iconst_4
       3: invokevirtual #118                // Method splitTag:(Ljava/lang/String;I)Ljava/lang/String;
       6: areturn

  java.lang.String attributeTag(java.lang.String, java.lang.String);
    Code:
       0: aload_0
       1: aload_1
       2: aload_2
       3: iconst_4
       4: iconst_0
       5: invokevirtual #117                // Method tag:(Ljava/lang/String;Ljava/lang/String;IZ)Ljava/lang/String;
       8: areturn

  java.lang.String rdfAt(java.lang.String);
    Code:
       0: aload_0
       1: getstatic     #116                // Field RDFNS:Ljava/lang/String;
       4: aload_1
       5: iconst_5
       6: iconst_1
       7: invokevirtual #117                // Method tag:(Ljava/lang/String;Ljava/lang/String;IZ)Ljava/lang/String;
      10: areturn

  java.lang.String endElementTag(java.lang.String, java.lang.String);
    Code:
       0: aload_0
       1: aload_1
       2: aload_2
       3: iconst_3
       4: iconst_0
       5: invokevirtual #117                // Method tag:(Ljava/lang/String;Ljava/lang/String;IZ)Ljava/lang/String;
       8: areturn

  protected java.lang.String endElementTag(java.lang.String);
    Code:
       0: aload_0
       1: aload_1
       2: iconst_3
       3: invokevirtual #118                // Method splitTag:(Ljava/lang/String;I)Ljava/lang/String;
       6: areturn

  java.lang.String splitTag(java.lang.String, int);
    Code:
       0: aload_1
       1: invokestatic  #119                // Method org/apache/jena/rdf/model/impl/Util.splitNamespaceXML:(Ljava/lang/String;)I
       4: istore_3
       5: iload_3
       6: aload_1
       7: invokevirtual #112                // Method java/lang/String.length:()I
      10: if_icmpne     22
      13: new           #120                // class org/apache/jena/shared/InvalidPropertyURIException
      16: dup
      17: aload_1
      18: invokespecial #121                // Method org/apache/jena/shared/InvalidPropertyURIException."<init>":(Ljava/lang/String;)V
      21: athrow
      22: aload_0
      23: aload_1
      24: iconst_0
      25: iload_3
      26: invokevirtual #122                // Method java/lang/String.substring:(II)Ljava/lang/String;
      29: aload_1
      30: iload_3
      31: invokevirtual #123                // Method java/lang/String.substring:(I)Ljava/lang/String;
      34: iload_2
      35: iconst_1
      36: invokevirtual #117                // Method tag:(Ljava/lang/String;Ljava/lang/String;IZ)Ljava/lang/String;
      39: areturn

  java.lang.String tag(java.lang.String, java.lang.String, int, boolean);
    Code:
       0: getstatic     #124                // Field dbg:Z
       3: ifeq          35
       6: getstatic     #125                // Field java/lang/System.err:Ljava/io/PrintStream;
       9: new           #37                 // class java/lang/StringBuilder
      12: dup
      13: invokespecial #38                 // Method java/lang/StringBuilder."<init>":()V
      16: aload_1
      17: invokevirtual #40                 // Method java/lang/StringBuilder.append:(Ljava/lang/String;)Ljava/lang/StringBuilder;
      20: ldc           #126                // String  -
      22: invokevirtual #40                 // Method java/lang/StringBuilder.append:(Ljava/lang/String;)Ljava/lang/StringBuilder;
      25: aload_2
      26: invokevirtual #40                 // Method java/lang/StringBuilder.append:(Ljava/lang/String;)Ljava/lang/StringBuilder;
      29: invokevirtual #42                 // Method java/lang/StringBuilder.toString:()Ljava/lang/String;
      32: invokevirtual #127                // Method java/io/PrintStream.println:(Ljava/lang/String;)V
      35: aload_0
      36: getfield      #50                 // Field ns:Ljava/util/Map;
      39: aload_1
      40: invokeinterface #51,  2           // InterfaceMethod java/util/Map.get:(Ljava/lang/Object;)Ljava/lang/Object;
      45: checkcast     #36                 // class java/lang/String
      48: astore        5
      50: iload_3
      51: iconst_1
      52: if_icmpeq     177
      55: iload_3
      56: iconst_5
      57: if_icmpeq     177
      60: iload         4
      62: ifne          96
      65: aload_2
      66: invokestatic  #45                 // Method org/apache/xerces/util/XMLChar.isValidNCName:(Ljava/lang/String;)Z
      69: ifne          96
      72: aload_0
      73: new           #37                 // class java/lang/StringBuilder
      76: dup
      77: invokespecial #38                 // Method java/lang/StringBuilder."<init>":()V
      80: aload_1
      81: invokevirtual #40                 // Method java/lang/StringBuilder.append:(Ljava/lang/String;)Ljava/lang/StringBuilder;
      84: aload_2
      85: invokevirtual #40                 // Method java/lang/StringBuilder.append:(Ljava/lang/String;)Ljava/lang/StringBuilder;
      88: invokevirtual #42                 // Method java/lang/StringBuilder.toString:()Ljava/lang/String;
      91: iload_3
      92: invokevirtual #118                // Method splitTag:(Ljava/lang/String;I)Ljava/lang/String;
      95: areturn
      96: aload_1
      97: getstatic     #116                // Field RDFNS:Ljava/lang/String;
     100: invokevirtual #52                 // Method java/lang/String.equals:(Ljava/lang/Object;)Z
     103: ifeq          177
     106: getstatic     #128                // Field badRDF:Ljava/util/Set;
     109: aload_2
     110: invokeinterface #96,  2           // InterfaceMethod java/util/Set.contains:(Ljava/lang/Object;)Z
     115: ifeq          177
     118: getstatic     #31                 // Field logger:Lorg/apache/jena/rdfxml/xmloutput/impl/SimpleLogger;
     121: new           #37                 // class java/lang/StringBuilder
     124: dup
     125: invokespecial #38                 // Method java/lang/StringBuilder."<init>":()V
     128: ldc           #129                // String The URI rdf:
     130: invokevirtual #40                 // Method java/lang/StringBuilder.append:(Ljava/lang/String;)Ljava/lang/StringBuilder;
     133: aload_2
     134: invokevirtual #40                 // Method java/lang/StringBuilder.append:(Ljava/lang/String;)Ljava/lang/StringBuilder;
     137: ldc           #130                // String  cannot be serialized in RDF/XML.
     139: invokevirtual #40                 // Method java/lang/StringBuilder.append:(Ljava/lang/String;)Ljava/lang/StringBuilder;
     142: invokevirtual #42                 // Method java/lang/StringBuilder.toString:()Ljava/lang/String;
     145: invokeinterface #131,  2          // InterfaceMethod org/apache/jena/rdfxml/xmloutput/impl/SimpleLogger.warn:(Ljava/lang/String;)V
     150: new           #120                // class org/apache/jena/shared/InvalidPropertyURIException
     153: dup
     154: new           #37                 // class java/lang/StringBuilder
     157: dup
     158: invokespecial #38                 // Method java/lang/StringBuilder."<init>":()V
     161: ldc           #132                // String rdf:
     163: invokevirtual #40                 // Method java/lang/StringBuilder.append:(Ljava/lang/String;)Ljava/lang/StringBuilder;
     166: aload_2
     167: invokevirtual #40                 // Method java/lang/StringBuilder.append:(Ljava/lang/String;)Ljava/lang/StringBuilder;
     170: invokevirtual #42                 // Method java/lang/StringBuilder.toString:()Ljava/lang/String;
     173: invokespecial #121                // Method org/apache/jena/shared/InvalidPropertyURIException."<init>":(Ljava/lang/String;)V
     176: athrow
     177: iconst_0
     178: istore        6
     180: aload         5
     182: ifnonnull     255
     185: aload_0
     186: aload_1
     187: invokespecial #114                // Method checkURI:(Ljava/lang/String;)Ljava/lang/String;
     190: pop
     191: getstatic     #31                 // Field logger:Lorg/apache/jena/rdfxml/xmloutput/impl/SimpleLogger;
     194: new           #37                 // class java/lang/StringBuilder
     197: dup
     198: invokespecial #38                 // Method java/lang/StringBuilder."<init>":()V
     201: ldc           #133                // String Internal error: unexpected QName URI: <
     203: invokevirtual #40                 // Method java/lang/StringBuilder.append:(Ljava/lang/String;)Ljava/lang/StringBuilder;
     206: aload_1
     207: invokevirtual #40                 // Method java/lang/StringBuilder.append:(Ljava/lang/String;)Ljava/lang/StringBuilder;
     210: ldc           #134                // String >.  Fixing up with j.cook.up code.
     212: invokevirtual #40                 // Method java/lang/StringBuilder.append:(Ljava/lang/String;)Ljava/lang/StringBuilder;
     215: invokevirtual #42                 // Method java/lang/StringBuilder.toString:()Ljava/lang/String;
     218: new           #135                // class org/apache/jena/shared/BrokenException
     221: dup
     222: new           #37                 // class java/lang/StringBuilder
     225: dup
     226: invokespecial #38                 // Method java/lang/StringBuilder."<init>":()V
     229: ldc           #136                // String unexpected QName URI
     231: invokevirtual #40                 // Method java/lang/StringBuilder.append:(Ljava/lang/String;)Ljava/lang/StringBuilder;
     234: aload_1
     235: invokevirtual #40                 // Method java/lang/StringBuilder.append:(Ljava/lang/String;)Ljava/lang/StringBuilder;
     238: invokevirtual #42                 // Method java/lang/StringBuilder.toString:()Ljava/lang/String;
     241: invokespecial #137                // Method org/apache/jena/shared/BrokenException."<init>":(Ljava/lang/String;)V
     244: invokeinterface #138,  3          // InterfaceMethod org/apache/jena/rdfxml/xmloutput/impl/SimpleLogger.warn:(Ljava/lang/String;Ljava/lang/Exception;)V
     249: iconst_1
     250: istore        6
     252: goto          281
     255: aload         5
     257: invokevirtual #112                // Method java/lang/String.length:()I
     260: ifne          281
     263: iload_3
     264: iconst_4
     265: if_icmpeq     273
     268: iload_3
     269: iconst_5
     270: if_icmpne     279
     273: iconst_1
     274: istore        6
     276: goto          281
     279: aload_2
     280: areturn
     281: iload         6
     283: ifeq          294
     286: aload_0
     287: iload_3
     288: aload_1
     289: aload_2
     290: invokespecial #139                // Method cookUpAttribution:(ILjava/lang/String;Ljava/lang/String;)Ljava/lang/String;
     293: areturn
     294: new           #37                 // class java/lang/StringBuilder
     297: dup
     298: invokespecial #38                 // Method java/lang/StringBuilder."<init>":()V
     301: aload         5
     303: invokevirtual #40                 // Method java/lang/StringBuilder.append:(Ljava/lang/String;)Ljava/lang/StringBuilder;
     306: ldc           #140                // String :
     308: invokevirtual #40                 // Method java/lang/StringBuilder.append:(Ljava/lang/String;)Ljava/lang/StringBuilder;
     311: aload_2
     312: invokevirtual #40                 // Method java/lang/StringBuilder.append:(Ljava/lang/String;)Ljava/lang/StringBuilder;
     315: invokevirtual #42                 // Method java/lang/StringBuilder.toString:()Ljava/lang/String;
     318: areturn

  private java.lang.String cookUpAttribution(int, java.lang.String, java.lang.String);
    Code:
       0: ldc           #141                // String j.cook.up
       2: astore        4
       4: iload_1
       5: tableswitch   { // 1 to 5
                     1: 166
                     2: 93
                     3: 141
                     4: 40
                     5: 40
               default: 141
          }
      40: new           #37                 // class java/lang/StringBuilder
      43: dup
      44: invokespecial #38                 // Method java/lang/StringBuilder."<init>":()V
      47: ldc           #142                // String xmlns:
      49: invokevirtual #40                 // Method java/lang/StringBuilder.append:(Ljava/lang/String;)Ljava/lang/StringBuilder;
      52: aload         4
      54: invokevirtual #40                 // Method java/lang/StringBuilder.append:(Ljava/lang/String;)Ljava/lang/StringBuilder;
      57: ldc           #143                // String =
      59: invokevirtual #40                 // Method java/lang/StringBuilder.append:(Ljava/lang/String;)Ljava/lang/StringBuilder;
      62: aload_0
      63: aload_2
      64: invokevirtual #115                // Method substitutedAttribute:(Ljava/lang/String;)Ljava/lang/String;
      67: invokevirtual #40                 // Method java/lang/StringBuilder.append:(Ljava/lang/String;)Ljava/lang/StringBuilder;
      70: ldc           #144                // String
      72: invokevirtual #40                 // Method java/lang/StringBuilder.append:(Ljava/lang/String;)Ljava/lang/StringBuilder;
      75: aload         4
      77: invokevirtual #40                 // Method java/lang/StringBuilder.append:(Ljava/lang/String;)Ljava/lang/StringBuilder;
      80: ldc           #140                // String :
      82: invokevirtual #40                 // Method java/lang/StringBuilder.append:(Ljava/lang/String;)Ljava/lang/StringBuilder;
      85: aload_3
      86: invokevirtual #40                 // Method java/lang/StringBuilder.append:(Ljava/lang/String;)Ljava/lang/StringBuilder;
      89: invokevirtual #42                 // Method java/lang/StringBuilder.toString:()Ljava/lang/String;
      92: areturn
      93: new           #37                 // class java/lang/StringBuilder
      96: dup
      97: invokespecial #38                 // Method java/lang/StringBuilder."<init>":()V
     100: aload         4
     102: invokevirtual #40                 // Method java/lang/StringBuilder.append:(Ljava/lang/String;)Ljava/lang/StringBuilder;
     105: ldc           #140                // String :
     107: invokevirtual #40                 // Method java/lang/StringBuilder.append:(Ljava/lang/String;)Ljava/lang/StringBuilder;
     110: aload_3
     111: invokevirtual #40                 // Method java/lang/StringBuilder.append:(Ljava/lang/String;)Ljava/lang/StringBuilder;
     114: ldc           #145                // String  xmlns:
     116: invokevirtual #40                 // Method java/lang/StringBuilder.append:(Ljava/lang/String;)Ljava/lang/StringBuilder;
     119: aload         4
     121: invokevirtual #40                 // Method java/lang/StringBuilder.append:(Ljava/lang/String;)Ljava/lang/StringBuilder;
     124: ldc           #143                // String =
     126: invokevirtual #40                 // Method java/lang/StringBuilder.append:(Ljava/lang/String;)Ljava/lang/StringBuilder;
     129: aload_0
     130: aload_2
     131: invokevirtual #115                // Method substitutedAttribute:(Ljava/lang/String;)Ljava/lang/String;
     134: invokevirtual #40                 // Method java/lang/StringBuilder.append:(Ljava/lang/String;)Ljava/lang/StringBuilder;
     137: invokevirtual #42                 // Method java/lang/StringBuilder.toString:()Ljava/lang/String;
     140: areturn
     141: new           #37                 // class java/lang/StringBuilder
     144: dup
     145: invokespecial #38                 // Method java/lang/StringBuilder."<init>":()V
     148: aload         4
     150: invokevirtual #40                 // Method java/lang/StringBuilder.append:(Ljava/lang/String;)Ljava/lang/StringBuilder;
     153: ldc           #140                // String :
     155: invokevirtual #40                 // Method java/lang/StringBuilder.append:(Ljava/lang/String;)Ljava/lang/StringBuilder;
     158: aload_3
     159: invokevirtual #40                 // Method java/lang/StringBuilder.append:(Ljava/lang/String;)Ljava/lang/StringBuilder;
     162: invokevirtual #42                 // Method java/lang/StringBuilder.toString:()Ljava/lang/String;
     165: areturn
     166: new           #135                // class org/apache/jena/shared/BrokenException
     169: dup
     170: ldc           #146                // String cookup reached final FAST
     172: invokespecial #137                // Method org/apache/jena/shared/BrokenException."<init>":(Ljava/lang/String;)V
     175: athrow

  public final void write(org.apache.jena.rdf.model.Model, java.io.OutputStream, java.lang.String);
    Code:
       0: aload_0
       1: aload_1
       2: aload_2
       3: invokestatic  #147                // Method org/apache/jena/util/FileUtils.asUTF8:(Ljava/io/OutputStream;)Ljava/io/Writer;
       6: aload_3
       7: invokevirtual #148                // Method write:(Lorg/apache/jena/rdf/model/Model;Ljava/io/Writer;Ljava/lang/String;)V
      10: return

  public synchronized void write(org.apache.jena.rdf.model.Model, java.io.Writer, java.lang.String);
    Code:
       0: aload_0
       1: aload_1
       2: invokespecial #149                // Method setupNamespaces:(Lorg/apache/jena/rdf/model/Model;)V
       5: aload_2
       6: instanceof    #150                // class java/io/PrintWriter
       9: ifeq          19
      12: aload_2
      13: checkcast     #150                // class java/io/PrintWriter
      16: goto          27
      19: new           #150                // class java/io/PrintWriter
      22: dup
      23: aload_2
      24: invokespecial #151                // Method java/io/PrintWriter."<init>":(Ljava/io/Writer;)V
      27: astore        4
      29: getstatic     #17                 // Field java/lang/Boolean.FALSE:Ljava/lang/Boolean;
      32: aload_0
      33: getfield      #16                 // Field showXmlDeclaration:Ljava/lang/Boolean;
      36: invokevirtual #152                // Method java/lang/Boolean.equals:(Ljava/lang/Object;)Z
      39: ifne          49
      42: aload_0
      43: aload_2
      44: aload         4
      46: invokespecial #153                // Method writeXMLDeclaration:(Ljava/io/Writer;Ljava/io/PrintWriter;)V
      49: aload_0
      50: aload_1
      51: aload         4
      53: aload_3
      54: invokespecial #154                // Method writeXMLBody:(Lorg/apache/jena/rdf/model/Model;Ljava/io/PrintWriter;Ljava/lang/String;)V
      57: aload         4
      59: invokevirtual #155                // Method java/io/PrintWriter.flush:()V
      62: return

  private void setupNamespaces(org.apache.jena.rdf.model.Model);
    Code:
       0: aload_0
       1: new           #88                 // class java/util/HashSet
       4: dup
       5: invokespecial #89                 // Method java/util/HashSet."<init>":()V
       8: putfield      #47                 // Field namespacesNeeded:Ljava/util/Set;
      11: aload_0
      12: aconst_null
      13: putfield      #50                 // Field ns:Ljava/util/Map;
      16: aload_0
      17: aload_1
      18: putfield      #156                // Field modelPrefixMapping:Lorg/apache/jena/shared/PrefixMapping;
      21: aload_0
      22: aload_1
      23: invokespecial #157                // Method primeNamespace:(Lorg/apache/jena/rdf/model/Model;)V
      26: aload_0
      27: invokestatic  #73                 // Method org/apache/jena/vocabulary/RDF.getURI:()Ljava/lang/String;
      30: invokevirtual #56                 // Method addNameSpace:(Ljava/lang/String;)V
      33: aload_0
      34: aload_1
      35: invokespecial #158                // Method addNameSpaces:(Lorg/apache/jena/rdf/model/Model;)V
      38: aload_0
      39: iconst_0
      40: putfield      #101                // Field jenaPrefixCount:I
      43: return

  private void writeXMLBody(org.apache.jena.rdf.model.Model, java.io.PrintWriter, java.lang.String);
    Code:
       0: aload_0
       1: getfield      #18                 // Field showDoctypeDeclaration:Ljava/lang/Boolean;
       4: invokevirtual #159                // Method java/lang/Boolean.booleanValue:()Z
       7: ifeq          16
      10: aload_0
      11: aload_1
      12: aload_2
      13: invokespecial #160                // Method generateDoctypeDeclaration:(Lorg/apache/jena/rdf/model/Model;Ljava/io/PrintWriter;)V
      16: aload_0
      17: getfield      #5                  // Field xmlBase:Ljava/lang/String;
      20: ifnonnull     60
      23: aload_0
      24: aload_3
      25: ifnull        35
      28: aload_3
      29: invokevirtual #112                // Method java/lang/String.length:()I
      32: ifne          39
      35: aconst_null
      36: goto          46
      39: getstatic     #161                // Field factory:Lorg/apache/jena/iri/IRIFactory;
      42: aload_3
      43: invokevirtual #162                // Method org/apache/jena/iri/IRIFactory.create:(Ljava/lang/String;)Lorg/apache/jena/iri/IRI;
      46: putfield      #163                // Field baseURI:Lorg/apache/jena/iri/IRI;
      49: aload_0
      50: aload_1
      51: aload_2
      52: aload_3
      53: iconst_0
      54: invokevirtual #164                // Method writeBody:(Lorg/apache/jena/rdf/model/Model;Ljava/io/PrintWriter;Ljava/lang/String;Z)V
      57: goto          99
      60: aload_0
      61: aload_0
      62: getfield      #5                  // Field xmlBase:Ljava/lang/String;
      65: invokevirtual #112                // Method java/lang/String.length:()I
      68: ifne          75
      71: aconst_null
      72: goto          85
      75: getstatic     #161                // Field factory:Lorg/apache/jena/iri/IRIFactory;
      78: aload_0
      79: getfield      #5                  // Field xmlBase:Ljava/lang/String;
      82: invokevirtual #162                // Method org/apache/jena/iri/IRIFactory.create:(Ljava/lang/String;)Lorg/apache/jena/iri/IRI;
      85: putfield      #163                // Field baseURI:Lorg/apache/jena/iri/IRI;
      88: aload_0
      89: aload_1
      90: aload_2
      91: aload_0
      92: getfield      #5                  // Field xmlBase:Ljava/lang/String;
      95: iconst_1
      96: invokevirtual #164                // Method writeBody:(Lorg/apache/jena/rdf/model/Model;Ljava/io/PrintWriter;Ljava/lang/String;Z)V
      99: return

  public boolean isPredefinedEntityName(java.lang.String);
    Code:
       0: getstatic     #165                // Field predefinedEntityNames:Ljava/util/regex/Pattern;
       3: aload_1
       4: invokevirtual #166                // Method java/util/regex/Pattern.matcher:(Ljava/lang/CharSequence;)Ljava/util/regex/Matcher;
       7: invokevirtual #167                // Method java/util/regex/Matcher.matches:()Z
      10: ireturn

  protected java.lang.String attributeQuoted(java.lang.String);
    Code:
       0: new           #37                 // class java/lang/StringBuilder
       3: dup
       4: invokespecial #38                 // Method java/lang/StringBuilder."<init>":()V
       7: aload_0
       8: getfield      #24                 // Field attributeQuoteChar:Ljava/lang/String;
      11: invokevirtual #40                 // Method java/lang/StringBuilder.append:(Ljava/lang/String;)Ljava/lang/StringBuilder;
      14: aload_1
      15: invokevirtual #40                 // Method java/lang/StringBuilder.append:(Ljava/lang/String;)Ljava/lang/StringBuilder;
      18: aload_0
      19: getfield      #24                 // Field attributeQuoteChar:Ljava/lang/String;
      22: invokevirtual #40                 // Method java/lang/StringBuilder.append:(Ljava/lang/String;)Ljava/lang/StringBuilder;
      25: invokevirtual #42                 // Method java/lang/StringBuilder.toString:()Ljava/lang/String;
      28: areturn

  protected java.lang.String substitutedAttribute(java.lang.String);
    Code:
       0: aload_1
       1: invokestatic  #168                // Method org/apache/jena/rdf/model/impl/Util.substituteStandardEntities:(Ljava/lang/String;)Ljava/lang/String;
       4: astore_2
       5: aload_0
       6: getfield      #18                 // Field showDoctypeDeclaration:Ljava/lang/Boolean;
       9: invokevirtual #159                // Method java/lang/Boolean.booleanValue:()Z
      12: ifne          21
      15: aload_0
      16: aload_2
      17: invokevirtual #169                // Method attributeQuoted:(Ljava/lang/String;)Ljava/lang/String;
      20: areturn
      21: aload_2
      22: invokestatic  #119                // Method org/apache/jena/rdf/model/impl/Util.splitNamespaceXML:(Ljava/lang/String;)I
      25: istore_3
      26: aload_2
      27: iconst_0
      28: iload_3
      29: invokevirtual #122                // Method java/lang/String.substring:(II)Ljava/lang/String;
      32: astore        4
      34: aload_0
      35: getfield      #156                // Field modelPrefixMapping:Lorg/apache/jena/shared/PrefixMapping;
      38: aload         4
      40: invokeinterface #170,  2          // InterfaceMethod org/apache/jena/shared/PrefixMapping.getNsURIPrefix:(Ljava/lang/String;)Ljava/lang/String;
      45: astore        5
      47: aload         5
      49: ifnull        61
      52: aload_0
      53: aload         5
      55: invokevirtual #171                // Method isPredefinedEntityName:(Ljava/lang/String;)Z
      58: ifeq          69
      61: aload_0
      62: aload_2
      63: invokevirtual #169                // Method attributeQuoted:(Ljava/lang/String;)Ljava/lang/String;
      66: goto          110
      69: aload_0
      70: new           #37                 // class java/lang/StringBuilder
      73: dup
      74: invokespecial #38                 // Method java/lang/StringBuilder."<init>":()V
      77: ldc           #172                // String &
      79: invokevirtual #40                 // Method java/lang/StringBuilder.append:(Ljava/lang/String;)Ljava/lang/StringBuilder;
      82: aload_0
      83: aload         5
      85: invokespecial #173                // Method strForPrefix:(Ljava/lang/String;)Ljava/lang/String;
      88: invokevirtual #40                 // Method java/lang/StringBuilder.append:(Ljava/lang/String;)Ljava/lang/StringBuilder;
      91: ldc           #174                // String ;
      93: invokevirtual #40                 // Method java/lang/StringBuilder.append:(Ljava/lang/String;)Ljava/lang/StringBuilder;
      96: aload_2
      97: iload_3
      98: invokevirtual #123                // Method java/lang/String.substring:(I)Ljava/lang/String;
     101: invokevirtual #40                 // Method java/lang/StringBuilder.append:(Ljava/lang/String;)Ljava/lang/StringBuilder;
     104: invokevirtual #42                 // Method java/lang/StringBuilder.toString:()Ljava/lang/String;
     107: invokevirtual #169                // Method attributeQuoted:(Ljava/lang/String;)Ljava/lang/String;
     110: areturn

  private void generateDoctypeDeclaration(org.apache.jena.rdf.model.Model, java.io.PrintWriter);
    Code:
       0: invokestatic  #73                 // Method org/apache/jena/vocabulary/RDF.getURI:()Ljava/lang/String;
       3: astore_3
       4: aload_1
       5: new           #37                 // class java/lang/StringBuilder
       8: dup
       9: invokespecial #38                 // Method java/lang/StringBuilder."<init>":()V
      12: aload_3
      13: invokevirtual #40                 // Method java/lang/StringBuilder.append:(Ljava/lang/String;)Ljava/lang/StringBuilder;
      16: ldc           #175                // String RDF
      18: invokevirtual #40                 // Method java/lang/StringBuilder.append:(Ljava/lang/String;)Ljava/lang/StringBuilder;
      21: invokevirtual #42                 // Method java/lang/StringBuilder.toString:()Ljava/lang/String;
      24: invokeinterface #176,  2          // InterfaceMethod org/apache/jena/rdf/model/Model.qnameFor:(Ljava/lang/String;)Ljava/lang/String;
      29: astore        4
      31: aload         4
      33: ifnonnull     50
      36: aload_1
      37: ldc           #74                 // String rdf
      39: aload_3
      40: invokeinterface #177,  3          // InterfaceMethod org/apache/jena/rdf/model/Model.setNsPrefix:(Ljava/lang/String;Ljava/lang/String;)Lorg/apache/jena/shared/PrefixMapping;
      45: pop
      46: ldc           #178                // String rdf:RDF
      48: astore        4
      50: aload_1
      51: invokeinterface #57,  1           // InterfaceMethod org/apache/jena/rdf/model/Model.getNsPrefixMap:()Ljava/util/Map;
      56: astore        5
      58: aload_2
      59: new           #37                 // class java/lang/StringBuilder
      62: dup
      63: invokespecial #38                 // Method java/lang/StringBuilder."<init>":()V
      66: ldc           #179                // String <!DOCTYPE
      68: invokevirtual #40                 // Method java/lang/StringBuilder.append:(Ljava/lang/String;)Ljava/lang/StringBuilder;
      71: aload         4
      73: invokevirtual #40                 // Method java/lang/StringBuilder.append:(Ljava/lang/String;)Ljava/lang/StringBuilder;
      76: ldc           #180                // String  [
      78: invokevirtual #40                 // Method java/lang/StringBuilder.append:(Ljava/lang/String;)Ljava/lang/StringBuilder;
      81: invokevirtual #42                 // Method java/lang/StringBuilder.toString:()Ljava/lang/String;
      84: invokevirtual #181                // Method java/io/PrintWriter.print:(Ljava/lang/String;)V
      87: aload         5
      89: invokeinterface #182,  1          // InterfaceMethod java/util/Map.keySet:()Ljava/util/Set;
      94: invokeinterface #59,  1           // InterfaceMethod java/util/Set.iterator:()Ljava/util/Iterator;
      99: astore        6
     101: aload         6
     103: invokeinterface #60,  1           // InterfaceMethod java/util/Iterator.hasNext:()Z
     108: ifeq          200
     111: aload         6
     113: invokeinterface #61,  1           // InterfaceMethod java/util/Iterator.next:()Ljava/lang/Object;
     118: checkcast     #36                 // class java/lang/String
     121: astore        7
     123: aload_0
     124: aload         7
     126: invokevirtual #171                // Method isPredefinedEntityName:(Ljava/lang/String;)Z
     129: ifeq          135
     132: goto          101
     135: aload_2
     136: new           #37                 // class java/lang/StringBuilder
     139: dup
     140: invokespecial #38                 // Method java/lang/StringBuilder."<init>":()V
     143: getstatic     #110                // Field newline:Ljava/lang/String;
     146: invokevirtual #40                 // Method java/lang/StringBuilder.append:(Ljava/lang/String;)Ljava/lang/StringBuilder;
     149: ldc           #183                // String   <!ENTITY
     151: invokevirtual #40                 // Method java/lang/StringBuilder.append:(Ljava/lang/String;)Ljava/lang/StringBuilder;
     154: aload_0
     155: aload         7
     157: invokespecial #173                // Method strForPrefix:(Ljava/lang/String;)Ljava/lang/String;
     160: invokevirtual #40                 // Method java/lang/StringBuilder.append:(Ljava/lang/String;)Ljava/lang/StringBuilder;
     163: ldc           #184                // String  \'
     165: invokevirtual #40                 // Method java/lang/StringBuilder.append:(Ljava/lang/String;)Ljava/lang/StringBuilder;
     168: aload         5
     170: aload         7
     172: invokeinterface #51,  2           // InterfaceMethod java/util/Map.get:(Ljava/lang/Object;)Ljava/lang/Object;
     177: checkcast     #36                 // class java/lang/String
     180: invokestatic  #185                // Method org/apache/jena/rdf/model/impl/Util.substituteEntitiesInEntityValue:(Ljava/lang/String;)Ljava/lang/String;
     183: invokevirtual #40                 // Method java/lang/StringBuilder.append:(Ljava/lang/String;)Ljava/lang/StringBuilder;
     186: ldc           #186                // String \'>
     188: invokevirtual #40                 // Method java/lang/StringBuilder.append:(Ljava/lang/String;)Ljava/lang/StringBuilder;
     191: invokevirtual #42                 // Method java/lang/StringBuilder.toString:()Ljava/lang/String;
     194: invokevirtual #181                // Method java/io/PrintWriter.print:(Ljava/lang/String;)V
     197: goto          101
     200: aload_2
     201: new           #37                 // class java/lang/StringBuilder
     204: dup
     205: invokespecial #38                 // Method java/lang/StringBuilder."<init>":()V
     208: ldc           #187                // String ]>
     210: invokevirtual #40                 // Method java/lang/StringBuilder.append:(Ljava/lang/String;)Ljava/lang/StringBuilder;
     213: getstatic     #110                // Field newline:Ljava/lang/String;
     216: invokevirtual #40                 // Method java/lang/StringBuilder.append:(Ljava/lang/String;)Ljava/lang/StringBuilder;
     219: invokevirtual #42                 // Method java/lang/StringBuilder.toString:()Ljava/lang/String;
     222: invokevirtual #181                // Method java/io/PrintWriter.print:(Ljava/lang/String;)V
     225: return

  private java.lang.String strForPrefix(java.lang.String);
    Code:
       0: aload_1
       1: invokevirtual #112                // Method java/lang/String.length:()I
       4: ifne          12
       7: aload_0
       8: getfield      #4                  // Field defaultNSEntityName:Ljava/lang/String;
      11: areturn
      12: aload_1
      13: areturn

  private static boolean usesPrefix(org.apache.jena.rdf.model.Model, java.lang.String);
    Code:
       0: aload_0
       1: aload_1
       2: invokeinterface #188,  2          // InterfaceMethod org/apache/jena/rdf/model/Model.getNsPrefixURI:(Ljava/lang/String;)Ljava/lang/String;
       7: ifnull        14
      10: iconst_1
      11: goto          15
      14: iconst_0
      15: ireturn

  private void writeXMLDeclaration(java.io.Writer, java.io.PrintWriter);
    Code:
       0: aconst_null
       1: astore_3
       2: aload_1
       3: instanceof    #189                // class java/io/OutputStreamWriter
       6: ifeq          135
       9: aload_1
      10: checkcast     #189                // class java/io/OutputStreamWriter
      13: invokevirtual #190                // Method java/io/OutputStreamWriter.getEncoding:()Ljava/lang/String;
      16: astore        4
      18: aload         4
      20: ldc           #191                // String UTF8
      22: invokevirtual #52                 // Method java/lang/String.equals:(Ljava/lang/Object;)Z
      25: ifne          135
      28: aload         4
      30: ldc           #192                // String UTF-16
      32: invokevirtual #52                 // Method java/lang/String.equals:(Ljava/lang/Object;)Z
      35: ifne          135
      38: aload         4
      40: invokestatic  #193                // Method org/apache/jena/util/CharEncoding.create:(Ljava/lang/String;)Lorg/apache/jena/util/CharEncoding;
      43: astore        5
      45: aload         5
      47: invokevirtual #194                // Method org/apache/jena/util/CharEncoding.name:()Ljava/lang/String;
      50: astore        6
      52: new           #37                 // class java/lang/StringBuilder
      55: dup
      56: invokespecial #38                 // Method java/lang/StringBuilder."<init>":()V
      59: ldc           #195                // String <?xml version=
      61: invokevirtual #40                 // Method java/lang/StringBuilder.append:(Ljava/lang/String;)Ljava/lang/StringBuilder;
      64: aload_0
      65: ldc           #196                // String 1.0
      67: invokevirtual #169                // Method attributeQuoted:(Ljava/lang/String;)Ljava/lang/String;
      70: invokevirtual #40                 // Method java/lang/StringBuilder.append:(Ljava/lang/String;)Ljava/lang/StringBuilder;
      73: ldc           #197                // String  encoding=
      75: invokevirtual #40                 // Method java/lang/StringBuilder.append:(Ljava/lang/String;)Ljava/lang/StringBuilder;
      78: aload_0
      79: aload         6
      81: invokevirtual #169                // Method attributeQuoted:(Ljava/lang/String;)Ljava/lang/String;
      84: invokevirtual #40                 // Method java/lang/StringBuilder.append:(Ljava/lang/String;)Ljava/lang/StringBuilder;
      87: ldc           #198                // String ?>
      89: invokevirtual #40                 // Method java/lang/StringBuilder.append:(Ljava/lang/String;)Ljava/lang/StringBuilder;
      92: invokevirtual #42                 // Method java/lang/StringBuilder.toString:()Ljava/lang/String;
      95: astore_3
      96: aload         5
      98: invokevirtual #199                // Method org/apache/jena/util/CharEncoding.isIANA:()Z
     101: ifne          135
     104: getstatic     #31                 // Field logger:Lorg/apache/jena/rdfxml/xmloutput/impl/SimpleLogger;
     107: new           #37                 // class java/lang/StringBuilder
     110: dup
     111: invokespecial #38                 // Method java/lang/StringBuilder."<init>":()V
     114: aload         5
     116: invokevirtual #200                // Method org/apache/jena/util/CharEncoding.warningMessage:()Ljava/lang/String;
     119: invokevirtual #40                 // Method java/lang/StringBuilder.append:(Ljava/lang/String;)Ljava/lang/StringBuilder;
     122: ldc           #201                // String \n   It is better to use a FileOutputStream, in place of a FileWriter.
     124: invokevirtual #40                 // Method java/lang/StringBuilder.append:(Ljava/lang/String;)Ljava/lang/StringBuilder;
     127: invokevirtual #42                 // Method java/lang/StringBuilder.toString:()Ljava/lang/String;
     130: invokeinterface #131,  2          // InterfaceMethod org/apache/jena/rdfxml/xmloutput/impl/SimpleLogger.warn:(Ljava/lang/String;)V
     135: aload_3
     136: ifnonnull     176
     139: aload_0
     140: getfield      #16                 // Field showXmlDeclaration:Ljava/lang/Boolean;
     143: ifnull        176
     146: new           #37                 // class java/lang/StringBuilder
     149: dup
     150: invokespecial #38                 // Method java/lang/StringBuilder."<init>":()V
     153: ldc           #195                // String <?xml version=
     155: invokevirtual #40                 // Method java/lang/StringBuilder.append:(Ljava/lang/String;)Ljava/lang/StringBuilder;
     158: aload_0
     159: ldc           #196                // String 1.0
     161: invokevirtual #169                // Method attributeQuoted:(Ljava/lang/String;)Ljava/lang/String;
     164: invokevirtual #40                 // Method java/lang/StringBuilder.append:(Ljava/lang/String;)Ljava/lang/StringBuilder;
     167: ldc           #198                // String ?>
     169: invokevirtual #40                 // Method java/lang/StringBuilder.append:(Ljava/lang/String;)Ljava/lang/StringBuilder;
     172: invokevirtual #42                 // Method java/lang/StringBuilder.toString:()Ljava/lang/String;
     175: astore_3
     176: aload_3
     177: ifnull        185
     180: aload_2
     181: aload_3
     182: invokevirtual #202                // Method java/io/PrintWriter.println:(Ljava/lang/String;)V
     185: return

  public synchronized org.apache.jena.rdf.model.RDFErrorHandler setErrorHandler(org.apache.jena.rdf.model.RDFErrorHandler);
    Code:
       0: aload_0
       1: getfield      #15                 // Field errorHandler:Lorg/apache/jena/rdf/model/RDFErrorHandler;
       4: astore_2
       5: aload_2
       6: getstatic     #14                 // Field defaultErrorHandler:Lorg/apache/jena/rdf/model/impl/RDFDefaultErrorHandler;
       9: if_acmpne     14
      12: aconst_null
      13: astore_2
      14: aload_0
      15: aload_1
      16: ifnonnull     25
      19: getstatic     #14                 // Field defaultErrorHandler:Lorg/apache/jena/rdf/model/impl/RDFDefaultErrorHandler;
      22: goto          26
      25: aload_1
      26: putfield      #15                 // Field errorHandler:Lorg/apache/jena/rdf/model/RDFErrorHandler;
      29: aload_2
      30: areturn

  private static java.lang.String escapedId(java.lang.String);
    Code:
       0: new           #203                // class java/lang/StringBuffer
       3: dup
       4: invokespecial #204                // Method java/lang/StringBuffer."<init>":()V
       7: astore_1
       8: iconst_0
       9: istore_2
      10: iload_2
      11: aload_0
      12: invokevirtual #112                // Method java/lang/String.length:()I
      15: if_icmpge     71
      18: aload_0
      19: iload_2
      20: invokevirtual #205                // Method java/lang/String.charAt:(I)C
      23: istore_3
      24: iload_3
      25: bipush        88
      27: if_icmpeq     60
      30: iload_2
      31: ifne          44
      34: iload_3
      35: invokestatic  #206                // Method org/apache/xerces/util/XMLChar.isNCNameStart:(I)Z
      38: ifeq          60
      41: goto          51
      44: iload_3
      45: invokestatic  #207                // Method org/apache/xerces/util/XMLChar.isNCName:(I)Z
      48: ifeq          60
      51: aload_1
      52: iload_3
      53: invokevirtual #208                // Method java/lang/StringBuffer.append:(C)Ljava/lang/StringBuffer;
      56: pop
      57: goto          65
      60: aload_1
      61: iload_3
      62: invokestatic  #209                // Method escape:(Ljava/lang/StringBuffer;C)V
      65: iinc          2, 1
      68: goto          10
      71: aload_1
      72: invokevirtual #210                // Method java/lang/StringBuffer.toString:()Ljava/lang/String;
      75: areturn

  private static void escape(java.lang.StringBuffer, char);
    Code:
       0: aload_0
       1: bipush        88
       3: invokevirtual #208                // Method java/lang/StringBuffer.append:(C)Ljava/lang/StringBuffer;
       6: pop
       7: iload_1
       8: istore_2
       9: aload_0
      10: getstatic     #211                // Field hexchar:[C
      13: iload_2
      14: bipush        15
      16: iand
      17: caload
      18: invokevirtual #208                // Method java/lang/StringBuffer.append:(C)Ljava/lang/StringBuffer;
      21: pop
      22: iload_2
      23: iconst_4
      24: ishr
      25: istore_2
      26: iload_2
      27: ifne          9
      30: aload_0
      31: bipush        88
      33: invokevirtual #208                // Method java/lang/StringBuffer.append:(C)Ljava/lang/StringBuffer;
      36: pop
      37: return

  public final synchronized java.lang.Object setProperty(java.lang.String, java.lang.Object);
    Code:
       0: aload_1
       1: ldc           #212                // String showXmlDeclaration
       3: invokevirtual #213                // Method java/lang/String.equalsIgnoreCase:(Ljava/lang/String;)Z
       6: ifeq          15
       9: aload_0
      10: aload_2
      11: invokespecial #214                // Method setShowXmlDeclaration:(Ljava/lang/Object;)Ljava/lang/String;
      14: areturn
      15: aload_1
      16: ldc           #215                // String showDoctypeDeclaration
      18: invokevirtual #213                // Method java/lang/String.equalsIgnoreCase:(Ljava/lang/String;)Z
      21: ifeq          30
      24: aload_0
      25: aload_2
      26: invokespecial #216                // Method setShowDoctypeDeclaration:(Ljava/lang/Object;)Ljava/lang/String;
      29: areturn
      30: aload_1
      31: ldc           #217                // String minimalPrefixes
      33: invokevirtual #213                // Method java/lang/String.equalsIgnoreCase:(Ljava/lang/String;)Z
      36: ifeq          98
      39: new           #218                // class java/lang/Boolean
      42: dup
      43: aload_0
      44: getfield      #19                 // Field writingAllModelPrefixNamespaces:Z
      47: ifne          54
      50: iconst_1
      51: goto          55
      54: iconst_0
      55: invokespecial #219                // Method java/lang/Boolean."<init>":(Z)V
      58: astore_3
      59: aload_0
      60: aload_2
      61: invokestatic  #220                // Method getBoolean:(Ljava/lang/Object;)Z
      64: ifne          71
      67: iconst_1
      68: goto          72
      71: iconst_0
      72: putfield      #19                 // Field writingAllModelPrefixNamespaces:Z
      75: aload_3
      76: areturn
      77: astore        4
      79: aload_0
      80: aload_2
      81: invokestatic  #220                // Method getBoolean:(Ljava/lang/Object;)Z
      84: ifne          91
      87: iconst_1
      88: goto          92
      91: iconst_0
      92: putfield      #19                 // Field writingAllModelPrefixNamespaces:Z
      95: aload         4
      97: athrow
      98: aload_1
      99: ldc           #221                // String xmlbase
     101: invokevirtual #213                // Method java/lang/String.equalsIgnoreCase:(Ljava/lang/String;)Z
     104: ifeq          122
     107: aload_0
     108: getfield      #5                  // Field xmlBase:Ljava/lang/String;
     111: astore_3
     112: aload_0
     113: aload_2
     114: checkcast     #36                 // class java/lang/String
     117: putfield      #5                  // Field xmlBase:Ljava/lang/String;
     120: aload_3
     121: areturn
     122: aload_1
     123: ldc           #222                // String tab
     125: invokevirtual #213                // Method java/lang/String.equalsIgnoreCase:(Ljava/lang/String;)Z
     128: ifeq          137
     131: aload_0
     132: aload_2
     133: invokespecial #223                // Method setTab:(Ljava/lang/Object;)Ljava/lang/Integer;
     136: areturn
     137: aload_1
     138: ldc           #224                // String width
     140: invokevirtual #213                // Method java/lang/String.equalsIgnoreCase:(Ljava/lang/String;)Z
     143: ifeq          152
     146: aload_0
     147: aload_2
     148: invokespecial #225                // Method setWidth:(Ljava/lang/Object;)Ljava/lang/Integer;
     151: areturn
     152: aload_1
     153: ldc           #226                // String longid
     155: invokevirtual #213                // Method java/lang/String.equalsIgnoreCase:(Ljava/lang/String;)Z
     158: ifeq          183
     161: new           #218                // class java/lang/Boolean
     164: dup
     165: aload_0
     166: getfield      #6                  // Field longId:Z
     169: invokespecial #219                // Method java/lang/Boolean."<init>":(Z)V
     172: astore_3
     173: aload_0
     174: aload_2
     175: invokestatic  #220                // Method getBoolean:(Ljava/lang/Object;)Z
     178: putfield      #6                  // Field longId:Z
     181: aload_3
     182: areturn
     183: aload_1
     184: ldc           #227                // String attributeQuoteChar
     186: invokevirtual #213                // Method java/lang/String.equalsIgnoreCase:(Ljava/lang/String;)Z
     189: ifeq          198
     192: aload_0
     193: aload_2
     194: invokespecial #228                // Method setAttributeQuoteChar:(Ljava/lang/Object;)Ljava/lang/String;
     197: areturn
     198: aload_1
     199: ldc           #229                // String allowBadURIs
     201: invokevirtual #213                // Method java/lang/String.equalsIgnoreCase:(Ljava/lang/String;)Z
     204: ifeq          245
     207: new           #218                // class java/lang/Boolean
     210: dup
     211: aload_0
     212: getfield      #7                  // Field demandGoodURIs:Z
     215: ifne          222
     218: iconst_1
     219: goto          223
     222: iconst_0
     223: invokespecial #219                // Method java/lang/Boolean."<init>":(Z)V
     226: astore_3
     227: aload_0
     228: aload_2
     229: invokestatic  #220                // Method getBoolean:(Ljava/lang/Object;)Z
     232: ifne          239
     235: iconst_1
     236: goto          240
     239: iconst_0
     240: putfield      #7                  // Field demandGoodURIs:Z
     243: aload_3
     244: areturn
     245: aload_1
     246: ldc           #230                // String prettyTypes
     248: invokevirtual #213                // Method java/lang/String.equalsIgnoreCase:(Ljava/lang/String;)Z
     251: ifeq          266
     254: aload_0
     255: aload_2
     256: checkcast     #231                // class "[Lorg/apache/jena/rdf/model/Resource;"
     259: checkcast     #231                // class "[Lorg/apache/jena/rdf/model/Resource;"
     262: invokevirtual #232                // Method setTypes:([Lorg/apache/jena/rdf/model/Resource;)[Lorg/apache/jena/rdf/model/Resource;
     265: areturn
     266: aload_1
     267: ldc           #233                // String relativeURIs
     269: invokevirtual #213                // Method java/lang/String.equalsIgnoreCase:(Ljava/lang/String;)Z
     272: ifeq          296
     275: aload_0
     276: getfield      #29                 // Field relativeFlags:I
     279: istore_3
     280: aload_0
     281: aload_2
     282: checkcast     #36                 // class java/lang/String
     285: invokestatic  #234                // Method str2flags:(Ljava/lang/String;)I
     288: putfield      #29                 // Field relativeFlags:I
     291: iload_3
     292: invokestatic  #235                // Method flags2str:(I)Ljava/lang/String;
     295: areturn
     296: aload_1
     297: ldc           #236                // String blockRules
     299: invokevirtual #213                // Method java/lang/String.equalsIgnoreCase:(Ljava/lang/String;)Z
     302: ifeq          311
     305: aload_0
     306: aload_2
     307: invokevirtual #237                // Method setBlockRules:(Ljava/lang/Object;)[Lorg/apache/jena/rdf/model/Resource;
     310: areturn
     311: getstatic     #31                 // Field logger:Lorg/apache/jena/rdfxml/xmloutput/impl/SimpleLogger;
     314: new           #37                 // class java/lang/StringBuilder
     317: dup
     318: invokespecial #38                 // Method java/lang/StringBuilder."<init>":()V
     321: ldc           #238                // String Unsupported property:
     323: invokevirtual #40                 // Method java/lang/StringBuilder.append:(Ljava/lang/String;)Ljava/lang/StringBuilder;
     326: aload_1
     327: invokevirtual #40                 // Method java/lang/StringBuilder.append:(Ljava/lang/String;)Ljava/lang/StringBuilder;
     330: invokevirtual #42                 // Method java/lang/StringBuilder.toString:()Ljava/lang/String;
     333: invokeinterface #131,  2          // InterfaceMethod org/apache/jena/rdfxml/xmloutput/impl/SimpleLogger.warn:(Ljava/lang/String;)V
     338: aconst_null
     339: areturn
    Exception table:
       from    to  target type
          39    59    77   any
          77    79    77   any

  private java.lang.String setAttributeQuoteChar(java.lang.Object);
    Code:
       0: aload_0
       1: getfield      #24                 // Field attributeQuoteChar:Ljava/lang/String;
       4: astore_2
       5: ldc           #23                 // String \"
       7: aload_1
       8: invokevirtual #52                 // Method java/lang/String.equals:(Ljava/lang/Object;)Z
      11: ifne          23
      14: ldc           #239                // String \'
      16: aload_1
      17: invokevirtual #52                 // Method java/lang/String.equals:(Ljava/lang/Object;)Z
      20: ifeq          34
      23: aload_0
      24: aload_1
      25: checkcast     #36                 // class java/lang/String
      28: putfield      #24                 // Field attributeQuoteChar:Ljava/lang/String;
      31: goto          66
      34: getstatic     #31                 // Field logger:Lorg/apache/jena/rdfxml/xmloutput/impl/SimpleLogger;
      37: new           #37                 // class java/lang/StringBuilder
      40: dup
      41: invokespecial #38                 // Method java/lang/StringBuilder."<init>":()V
      44: ldc           #240                // String attributeQutpeChar must be either \"\\\"\" or \', not \"
      46: invokevirtual #40                 // Method java/lang/StringBuilder.append:(Ljava/lang/String;)Ljava/lang/StringBuilder;
      49: aload_1
      50: invokevirtual #241                // Method java/lang/StringBuilder.append:(Ljava/lang/Object;)Ljava/lang/StringBuilder;
      53: ldc           #23                 // String \"
      55: invokevirtual #40                 // Method java/lang/StringBuilder.append:(Ljava/lang/String;)Ljava/lang/StringBuilder;
      58: invokevirtual #42                 // Method java/lang/StringBuilder.toString:()Ljava/lang/String;
      61: invokeinterface #131,  2          // InterfaceMethod org/apache/jena/rdfxml/xmloutput/impl/SimpleLogger.warn:(Ljava/lang/String;)V
      66: aload_2
      67: areturn

  private java.lang.Integer setWidth(java.lang.Object);
    Code:
       0: new           #242                // class java/lang/Integer
       3: dup
       4: aload_0
       5: getfield      #9                  // Field width:I
       8: invokespecial #243                // Method java/lang/Integer."<init>":(I)V
      11: astore_2
      12: aload_1
      13: instanceof    #242                // class java/lang/Integer
      16: ifeq          33
      19: aload_0
      20: aload_1
      21: checkcast     #242                // class java/lang/Integer
      24: invokevirtual #244                // Method java/lang/Integer.intValue:()I
      27: putfield      #9                  // Field width:I
      30: goto          92
      33: aload_0
      34: aload_1
      35: checkcast     #36                 // class java/lang/String
      38: invokestatic  #245                // Method java/lang/Integer.parseInt:(Ljava/lang/String;)I
      41: putfield      #9                  // Field width:I
      44: goto          92
      47: astore_3
      48: getstatic     #31                 // Field logger:Lorg/apache/jena/rdfxml/xmloutput/impl/SimpleLogger;
      51: new           #37                 // class java/lang/StringBuilder
      54: dup
      55: invokespecial #38                 // Method java/lang/StringBuilder."<init>":()V
      58: ldc           #247                // String Bad value for width: \'
      60: invokevirtual #40                 // Method java/lang/StringBuilder.append:(Ljava/lang/String;)Ljava/lang/StringBuilder;
      63: aload_1
      64: invokevirtual #241                // Method java/lang/StringBuilder.append:(Ljava/lang/Object;)Ljava/lang/StringBuilder;
      67: ldc           #248                // String \' [
      69: invokevirtual #40                 // Method java/lang/StringBuilder.append:(Ljava/lang/String;)Ljava/lang/StringBuilder;
      72: aload_3
      73: invokevirtual #249                // Method java/lang/Exception.getMessage:()Ljava/lang/String;
      76: invokevirtual #40                 // Method java/lang/StringBuilder.append:(Ljava/lang/String;)Ljava/lang/StringBuilder;
      79: ldc           #250                // String ]
      81: invokevirtual #40                 // Method java/lang/StringBuilder.append:(Ljava/lang/String;)Ljava/lang/StringBuilder;
      84: invokevirtual #42                 // Method java/lang/StringBuilder.toString:()Ljava/lang/String;
      87: invokeinterface #131,  2          // InterfaceMethod org/apache/jena/rdfxml/xmloutput/impl/SimpleLogger.warn:(Ljava/lang/String;)V
      92: aload_2
      93: areturn
    Exception table:
       from    to  target type
          33    44    47   Class java/lang/Exception

  private java.lang.Integer setTab(java.lang.Object);
    Code:
       0: new           #242                // class java/lang/Integer
       3: dup
       4: aload_0
       5: getfield      #8                  // Field tabSize:I
       8: invokespecial #243                // Method java/lang/Integer."<init>":(I)V
      11: astore_2
      12: aload_1
      13: instanceof    #242                // class java/lang/Integer
      16: ifeq          33
      19: aload_0
      20: aload_1
      21: checkcast     #242                // class java/lang/Integer
      24: invokevirtual #244                // Method java/lang/Integer.intValue:()I
      27: putfield      #8                  // Field tabSize:I
      30: goto          92
      33: aload_0
      34: aload_1
      35: checkcast     #36                 // class java/lang/String
      38: invokestatic  #245                // Method java/lang/Integer.parseInt:(Ljava/lang/String;)I
      41: putfield      #8                  // Field tabSize:I
      44: goto          92
      47: astore_3
      48: getstatic     #31                 // Field logger:Lorg/apache/jena/rdfxml/xmloutput/impl/SimpleLogger;
      51: new           #37                 // class java/lang/StringBuilder
      54: dup
      55: invokespecial #38                 // Method java/lang/StringBuilder."<init>":()V
      58: ldc           #251                // String Bad value for tab: \'
      60: invokevirtual #40                 // Method java/lang/StringBuilder.append:(Ljava/lang/String;)Ljava/lang/StringBuilder;
      63: aload_1
      64: invokevirtual #241                // Method java/lang/StringBuilder.append:(Ljava/lang/Object;)Ljava/lang/StringBuilder;
      67: ldc           #248                // String \' [
      69: invokevirtual #40                 // Method java/lang/StringBuilder.append:(Ljava/lang/String;)Ljava/lang/StringBuilder;
      72: aload_3
      73: invokevirtual #249                // Method java/lang/Exception.getMessage:()Ljava/lang/String;
      76: invokevirtual #40                 // Method java/lang/StringBuilder.append:(Ljava/lang/String;)Ljava/lang/StringBuilder;
      79: ldc           #250                // String ]
      81: invokevirtual #40                 // Method java/lang/StringBuilder.append:(Ljava/lang/String;)Ljava/lang/StringBuilder;
      84: invokevirtual #42                 // Method java/lang/StringBuilder.toString:()Ljava/lang/String;
      87: invokeinterface #131,  2          // InterfaceMethod org/apache/jena/rdfxml/xmloutput/impl/SimpleLogger.warn:(Ljava/lang/String;)V
      92: aload_2
      93: areturn
    Exception table:
       from    to  target type
          33    44    47   Class java/lang/Exception

  private java.lang.String setShowDoctypeDeclaration(java.lang.Object);
    Code:
       0: aload_0
       1: getfield      #18                 // Field showDoctypeDeclaration:Ljava/lang/Boolean;
       4: invokevirtual #252                // Method java/lang/Boolean.toString:()Ljava/lang/String;
       7: astore_2
       8: aload_0
       9: aload_1
      10: getstatic     #17                 // Field java/lang/Boolean.FALSE:Ljava/lang/Boolean;
      13: invokestatic  #253                // Method getBooleanValue:(Ljava/lang/Object;Ljava/lang/Boolean;)Ljava/lang/Boolean;
      16: putfield      #18                 // Field showDoctypeDeclaration:Ljava/lang/Boolean;
      19: aload_2
      20: areturn

  private java.lang.String setShowXmlDeclaration(java.lang.Object);
    Code:
       0: aload_0
       1: getfield      #16                 // Field showXmlDeclaration:Ljava/lang/Boolean;
       4: ifnonnull     11
       7: aconst_null
       8: goto          18
      11: aload_0
      12: getfield      #16                 // Field showXmlDeclaration:Ljava/lang/Boolean;
      15: invokevirtual #252                // Method java/lang/Boolean.toString:()Ljava/lang/String;
      18: astore_2
      19: aload_0
      20: aload_1
      21: aconst_null
      22: invokestatic  #253                // Method getBooleanValue:(Ljava/lang/Object;Ljava/lang/Boolean;)Ljava/lang/Boolean;
      25: putfield      #16                 // Field showXmlDeclaration:Ljava/lang/Boolean;
      28: aload_2
      29: areturn

  private static boolean getBoolean(java.lang.Object);
    Code:
       0: aload_0
       1: getstatic     #17                 // Field java/lang/Boolean.FALSE:Ljava/lang/Boolean;
       4: invokestatic  #253                // Method getBooleanValue:(Ljava/lang/Object;Ljava/lang/Boolean;)Ljava/lang/Boolean;
       7: invokevirtual #159                // Method java/lang/Boolean.booleanValue:()Z
      10: ireturn

  private static java.lang.Boolean getBooleanValue(java.lang.Object, java.lang.Boolean);
    Code:
       0: aload_0
       1: ifnonnull     6
       4: aload_1
       5: areturn
       6: aload_0
       7: instanceof    #218                // class java/lang/Boolean
      10: ifeq          18
      13: aload_0
      14: checkcast     #218                // class java/lang/Boolean
      17: areturn
      18: aload_0
      19: instanceof    #36                 // class java/lang/String
      22: ifeq          34
      25: aload_0
      26: checkcast     #36                 // class java/lang/String
      29: aload_1
      30: invokestatic  #254                // Method stringToBoolean:(Ljava/lang/String;Ljava/lang/Boolean;)Ljava/lang/Boolean;
      33: areturn
      34: new           #255                // class org/apache/jena/shared/JenaException
      37: dup
      38: new           #37                 // class java/lang/StringBuilder
      41: dup
      42: invokespecial #38                 // Method java/lang/StringBuilder."<init>":()V
      45: ldc_w         #256                // String cannot treat as boolean:
      48: invokevirtual #40                 // Method java/lang/StringBuilder.append:(Ljava/lang/String;)Ljava/lang/StringBuilder;
      51: aload_0
      52: invokevirtual #241                // Method java/lang/StringBuilder.append:(Ljava/lang/Object;)Ljava/lang/StringBuilder;
      55: invokevirtual #42                 // Method java/lang/StringBuilder.toString:()Ljava/lang/String;
      58: invokespecial #257                // Method org/apache/jena/shared/JenaException."<init>":(Ljava/lang/String;)V
      61: athrow

  private static java.lang.Boolean stringToBoolean(java.lang.String, java.lang.Boolean);
    Code:
       0: aload_0
       1: ldc_w         #258                // String default
       4: invokevirtual #52                 // Method java/lang/String.equals:(Ljava/lang/Object;)Z
       7: ifeq          12
      10: aload_1
      11: areturn
      12: aload_0
      13: ldc_w         #259                // String true
      16: invokevirtual #213                // Method java/lang/String.equalsIgnoreCase:(Ljava/lang/String;)Z
      19: ifeq          26
      22: getstatic     #260                // Field java/lang/Boolean.TRUE:Ljava/lang/Boolean;
      25: areturn
      26: aload_0
      27: ldc_w         #261                // String false
      30: invokevirtual #213                // Method java/lang/String.equalsIgnoreCase:(Ljava/lang/String;)Z
      33: ifeq          40
      36: getstatic     #17                 // Field java/lang/Boolean.FALSE:Ljava/lang/Boolean;
      39: areturn
      40: new           #262                // class org/apache/jena/shared/BadBooleanException
      43: dup
      44: aload_0
      45: invokespecial #263                // Method org/apache/jena/shared/BadBooleanException."<init>":(Ljava/lang/String;)V
      48: athrow

  org.apache.jena.rdf.model.Resource[] setTypes(org.apache.jena.rdf.model.Resource[]);
    Code:
       0: getstatic     #31                 // Field logger:Lorg/apache/jena/rdfxml/xmloutput/impl/SimpleLogger;
       3: ldc_w         #264                // String prettyTypes is not a property on the Basic RDF/XML writer.
       6: invokeinterface #131,  2          // InterfaceMethod org/apache/jena/rdfxml/xmloutput/impl/SimpleLogger.warn:(Ljava/lang/String;)V
      11: aconst_null
      12: areturn

  org.apache.jena.rdf.model.Resource[] setBlockRules(java.lang.Object);
    Code:
       0: aload_0
       1: getfield      #27                 // Field blockedRules:[Lorg/apache/jena/rdf/model/Resource;
       4: astore_2
       5: aload_0
       6: invokevirtual #265                // Method unblockAll:()V
       9: aload_1
      10: instanceof    #231                // class "[Lorg/apache/jena/rdf/model/Resource;"
      13: ifeq          30
      16: aload_0
      17: aload_1
      18: checkcast     #231                // class "[Lorg/apache/jena/rdf/model/Resource;"
      21: checkcast     #231                // class "[Lorg/apache/jena/rdf/model/Resource;"
      24: putfield      #27                 // Field blockedRules:[Lorg/apache/jena/rdf/model/Resource;
      27: goto          125
      30: new           #266                // class java/util/StringTokenizer
      33: dup
      34: aload_1
      35: checkcast     #36                 // class java/lang/String
      38: ldc_w         #267                // String ,
      41: invokespecial #268                // Method java/util/StringTokenizer."<init>":(Ljava/lang/String;Ljava/lang/String;)V
      44: astore_3
      45: new           #269                // class java/util/Vector
      48: dup
      49: invokespecial #270                // Method java/util/Vector."<init>":()V
      52: astore        4
      54: aload_3
      55: invokevirtual #271                // Method java/util/StringTokenizer.hasMoreElements:()Z
      58: ifeq          104
      61: aload_3
      62: invokevirtual #272                // Method java/util/StringTokenizer.nextToken:()Ljava/lang/String;
      65: astore        5
      67: aload         4
      69: new           #273                // class org/apache/jena/rdf/model/impl/ResourceImpl
      72: dup
      73: new           #37                 // class java/lang/StringBuilder
      76: dup
      77: invokespecial #38                 // Method java/lang/StringBuilder."<init>":()V
      80: invokestatic  #274                // Method org/apache/jena/vocabulary/RDFSyntax.getURI:()Ljava/lang/String;
      83: invokevirtual #40                 // Method java/lang/StringBuilder.append:(Ljava/lang/String;)Ljava/lang/StringBuilder;
      86: aload         5
      88: invokevirtual #40                 // Method java/lang/StringBuilder.append:(Ljava/lang/String;)Ljava/lang/StringBuilder;
      91: invokevirtual #42                 // Method java/lang/StringBuilder.toString:()Ljava/lang/String;
      94: invokespecial #275                // Method org/apache/jena/rdf/model/impl/ResourceImpl."<init>":(Ljava/lang/String;)V
      97: invokevirtual #276                // Method java/util/Vector.add:(Ljava/lang/Object;)Z
     100: pop
     101: goto          54
     104: aload_0
     105: aload         4
     107: invokevirtual #277                // Method java/util/Vector.size:()I
     110: anewarray     #25                 // class org/apache/jena/rdf/model/Resource
     113: putfield      #27                 // Field blockedRules:[Lorg/apache/jena/rdf/model/Resource;
     116: aload         4
     118: aload_0
     119: getfield      #27                 // Field blockedRules:[Lorg/apache/jena/rdf/model/Resource;
     122: invokevirtual #278                // Method java/util/Vector.copyInto:([Ljava/lang/Object;)V
     125: aload_0
     126: getfield      #27                 // Field blockedRules:[Lorg/apache/jena/rdf/model/Resource;
     129: astore_3
     130: aload_3
     131: arraylength
     132: istore        4
     134: iconst_0
     135: istore        5
     137: iload         5
     139: iload         4
     141: if_icmpge     162
     144: aload_3
     145: iload         5
     147: aaload
     148: astore        6
     150: aload_0
     151: aload         6
     153: invokevirtual #279                // Method blockRule:(Lorg/apache/jena/rdf/model/Resource;)V
     156: iinc          5, 1
     159: goto          137
     162: aload_2
     163: areturn

  protected java.lang.String relativize(java.lang.String);
    Code:
       0: aload_0
       1: getfield      #29                 // Field relativeFlags:I
       4: ifeq          26
       7: aload_0
       8: getfield      #163                // Field baseURI:Lorg/apache/jena/iri/IRI;
      11: ifnull        26
      14: aload_0
      15: aload_0
      16: getfield      #163                // Field baseURI:Lorg/apache/jena/iri/IRI;
      19: aload_1
      20: invokespecial #280                // Method relativize:(Lorg/apache/jena/iri/IRI;Ljava/lang/String;)Ljava/lang/String;
      23: goto          31
      26: aload_0
      27: aload_1
      28: invokespecial #114                // Method checkURI:(Ljava/lang/String;)Ljava/lang/String;
      31: areturn

  private java.lang.String relativize(org.apache.jena.iri.IRI, java.lang.String);
    Code:
       0: aload_1
       1: aload_2
       2: aload_0
       3: getfield      #29                 // Field relativeFlags:I
       6: invokevirtual #281                // Method org/apache/jena/iri/IRI.relativize:(Ljava/lang/String;I)Lorg/apache/jena/iri/IRI;
       9: invokevirtual #282                // Method org/apache/jena/iri/IRI.toString:()Ljava/lang/String;
      12: areturn

  private java.lang.String checkURI(java.lang.String);
    Code:
       0: aload_0
       1: getfield      #7                  // Field demandGoodURIs:Z
       4: ifeq          66
       7: getstatic     #161                // Field factory:Lorg/apache/jena/iri/IRIFactory;
      10: aload_1
      11: invokevirtual #162                // Method org/apache/jena/iri/IRIFactory.create:(Ljava/lang/String;)Lorg/apache/jena/iri/IRI;
      14: astore_2
      15: aload_2
      16: iconst_0
      17: invokevirtual #283                // Method org/apache/jena/iri/IRI.hasViolation:(Z)Z
      20: ifeq          66
      23: new           #284                // class org/apache/jena/shared/BadURIException
      26: dup
      27: new           #37                 // class java/lang/StringBuilder
      30: dup
      31: invokespecial #38                 // Method java/lang/StringBuilder."<init>":()V
      34: ldc_w         #285                // String Only well-formed absolute URIrefs can be included in RDF/XML output:
      37: invokevirtual #40                 // Method java/lang/StringBuilder.append:(Ljava/lang/String;)Ljava/lang/StringBuilder;
      40: aload_2
      41: iconst_0
      42: invokevirtual #286                // Method org/apache/jena/iri/IRI.violations:(Z)Ljava/util/Iterator;
      45: invokeinterface #61,  1           // InterfaceMethod java/util/Iterator.next:()Ljava/lang/Object;
      50: checkcast     #287                // class org/apache/jena/iri/Violation
      53: invokevirtual #288                // Method org/apache/jena/iri/Violation.getShortMessage:()Ljava/lang/String;
      56: invokevirtual #40                 // Method java/lang/StringBuilder.append:(Ljava/lang/String;)Ljava/lang/StringBuilder;
      59: invokevirtual #42                 // Method java/lang/StringBuilder.toString:()Ljava/lang/String;
      62: invokespecial #289                // Method org/apache/jena/shared/BadURIException."<init>":(Ljava/lang/String;)V
      65: athrow
      66: aload_1
      67: areturn

  private boolean checkLegalPrefix(java.lang.String);
    Code:
       0: aload_1
       1: ldc           #49                 // String
       3: invokevirtual #52                 // Method java/lang/String.equals:(Ljava/lang/Object;)Z
       6: ifeq          11
       9: iconst_1
      10: ireturn
      11: aload_1
      12: invokevirtual #290                // Method java/lang/String.toLowerCase:()Ljava/lang/String;
      15: ldc           #103                // String xml
      17: invokevirtual #291                // Method java/lang/String.startsWith:(Ljava/lang/String;)Z
      20: ifeq          60
      23: getstatic     #31                 // Field logger:Lorg/apache/jena/rdfxml/xmloutput/impl/SimpleLogger;
      26: new           #37                 // class java/lang/StringBuilder
      29: dup
      30: invokespecial #38                 // Method java/lang/StringBuilder."<init>":()V
      33: ldc_w         #292                // String Namespace prefix \'
      36: invokevirtual #40                 // Method java/lang/StringBuilder.append:(Ljava/lang/String;)Ljava/lang/StringBuilder;
      39: aload_1
      40: invokevirtual #40                 // Method java/lang/StringBuilder.append:(Ljava/lang/String;)Ljava/lang/StringBuilder;
      43: ldc_w         #293                // String \' is reserved by XML.
      46: invokevirtual #40                 // Method java/lang/StringBuilder.append:(Ljava/lang/String;)Ljava/lang/StringBuilder;
      49: invokevirtual #42                 // Method java/lang/StringBuilder.toString:()Ljava/lang/String;
      52: invokeinterface #131,  2          // InterfaceMethod org/apache/jena/rdfxml/xmloutput/impl/SimpleLogger.warn:(Ljava/lang/String;)V
      57: goto          155
      60: aload_1
      61: invokestatic  #45                 // Method org/apache/xerces/util/XMLChar.isValidNCName:(Ljava/lang/String;)Z
      64: ifne          103
      67: getstatic     #31                 // Field logger:Lorg/apache/jena/rdfxml/xmloutput/impl/SimpleLogger;
      70: new           #37                 // class java/lang/StringBuilder
      73: dup
      74: invokespecial #38                 // Method java/lang/StringBuilder."<init>":()V
      77: ldc           #239                // String \'
      79: invokevirtual #40                 // Method java/lang/StringBuilder.append:(Ljava/lang/String;)Ljava/lang/StringBuilder;
      82: aload_1
      83: invokevirtual #40                 // Method java/lang/StringBuilder.append:(Ljava/lang/String;)Ljava/lang/StringBuilder;
      86: ldc_w         #294                // String \' is not a legal namespace prefix.
      89: invokevirtual #40                 // Method java/lang/StringBuilder.append:(Ljava/lang/String;)Ljava/lang/StringBuilder;
      92: invokevirtual #42                 // Method java/lang/StringBuilder.toString:()Ljava/lang/String;
      95: invokeinterface #131,  2          // InterfaceMethod org/apache/jena/rdfxml/xmloutput/impl/SimpleLogger.warn:(Ljava/lang/String;)V
     100: goto          155
     103: getstatic     #295                // Field jenaNamespace:Ljava/util/regex/Pattern;
     106: aload_1
     107: invokevirtual #166                // Method java/util/regex/Pattern.matcher:(Ljava/lang/CharSequence;)Ljava/util/regex/Matcher;
     110: invokevirtual #167                // Method java/util/regex/Matcher.matches:()Z
     113: ifeq          153
     116: getstatic     #31                 // Field logger:Lorg/apache/jena/rdfxml/xmloutput/impl/SimpleLogger;
     119: new           #37                 // class java/lang/StringBuilder
     122: dup
     123: invokespecial #38                 // Method java/lang/StringBuilder."<init>":()V
     126: ldc_w         #292                // String Namespace prefix \'
     129: invokevirtual #40                 // Method java/lang/StringBuilder.append:(Ljava/lang/String;)Ljava/lang/StringBuilder;
     132: aload_1
     133: invokevirtual #40                 // Method java/lang/StringBuilder.append:(Ljava/lang/String;)Ljava/lang/StringBuilder;
     136: ldc_w         #296                // String \' is reserved by Jena.
     139: invokevirtual #40                 // Method java/lang/StringBuilder.append:(Ljava/lang/String;)Ljava/lang/StringBuilder;
     142: invokevirtual #42                 // Method java/lang/StringBuilder.toString:()Ljava/lang/String;
     145: invokeinterface #131,  2          // InterfaceMethod org/apache/jena/rdfxml/xmloutput/impl/SimpleLogger.warn:(Ljava/lang/String;)V
     150: goto          155
     153: iconst_1
     154: ireturn
     155: iconst_0
     156: ireturn

  private static java.lang.String flags2str(int);
    Code:
       0: new           #203                // class java/lang/StringBuffer
       3: dup
       4: bipush        64
       6: invokespecial #297                // Method java/lang/StringBuffer."<init>":(I)V
       9: astore_1
      10: iload_0
      11: iconst_1
      12: iand
      13: ifeq          24
      16: aload_1
      17: ldc_w         #298                // String same-document,
      20: invokevirtual #299                // Method java/lang/StringBuffer.append:(Ljava/lang/String;)Ljava/lang/StringBuffer;
      23: pop
      24: iload_0
      25: iconst_2
      26: iand
      27: ifeq          38
      30: aload_1
      31: ldc_w         #300                // String network,
      34: invokevirtual #299                // Method java/lang/StringBuffer.append:(Ljava/lang/String;)Ljava/lang/StringBuffer;
      37: pop
      38: iload_0
      39: iconst_4
      40: iand
      41: ifeq          52
      44: aload_1
      45: ldc_w         #301                // String absolute,
      48: invokevirtual #299                // Method java/lang/StringBuffer.append:(Ljava/lang/String;)Ljava/lang/StringBuffer;
      51: pop
      52: iload_0
      53: bipush        8
      55: iand
      56: ifeq          67
      59: aload_1
      60: ldc_w         #302                // String relative,
      63: invokevirtual #299                // Method java/lang/StringBuffer.append:(Ljava/lang/String;)Ljava/lang/StringBuffer;
      66: pop
      67: iload_0
      68: bipush        16
      70: iand
      71: ifeq          82
      74: aload_1
      75: ldc_w         #303                // String parent,
      78: invokevirtual #299                // Method java/lang/StringBuffer.append:(Ljava/lang/String;)Ljava/lang/StringBuffer;
      81: pop
      82: iload_0
      83: bipush        32
      85: iand
      86: ifeq          97
      89: aload_1
      90: ldc_w         #304                // String grandparent,
      93: invokevirtual #299                // Method java/lang/StringBuffer.append:(Ljava/lang/String;)Ljava/lang/StringBuffer;
      96: pop
      97: aload_1
      98: invokevirtual #305                // Method java/lang/StringBuffer.length:()I
     101: ifle          114
     104: aload_1
     105: aload_1
     106: invokevirtual #305                // Method java/lang/StringBuffer.length:()I
     109: iconst_2
     110: isub
     111: invokevirtual #306                // Method java/lang/StringBuffer.setLength:(I)V
     114: aload_1
     115: invokevirtual #210                // Method java/lang/StringBuffer.toString:()Ljava/lang/String;
     118: areturn

  public static int str2flags(java.lang.String);
    Code:
       0: new           #266                // class java/util/StringTokenizer
       3: dup
       4: aload_0
       5: ldc_w         #267                // String ,
       8: invokespecial #268                // Method java/util/StringTokenizer."<init>":(Ljava/lang/String;Ljava/lang/String;)V
      11: astore_1
      12: iconst_0
      13: istore_2
      14: aload_1
      15: invokevirtual #271                // Method java/util/StringTokenizer.hasMoreElements:()Z
      18: ifeq          162
      21: aload_1
      22: invokevirtual #272                // Method java/util/StringTokenizer.nextToken:()Ljava/lang/String;
      25: astore_3
      26: aload_3
      27: ldc_w         #307                // String same-document
      30: invokevirtual #52                 // Method java/lang/String.equals:(Ljava/lang/Object;)Z
      33: ifeq          43
      36: iload_2
      37: iconst_1
      38: ior
      39: istore_2
      40: goto          159
      43: aload_3
      44: ldc_w         #308                // String network
      47: invokevirtual #52                 // Method java/lang/String.equals:(Ljava/lang/Object;)Z
      50: ifeq          60
      53: iload_2
      54: iconst_2
      55: ior
      56: istore_2
      57: goto          159
      60: aload_3
      61: ldc_w         #309                // String absolute
      64: invokevirtual #52                 // Method java/lang/String.equals:(Ljava/lang/Object;)Z
      67: ifeq          77
      70: iload_2
      71: iconst_4
      72: ior
      73: istore_2
      74: goto          159
      77: aload_3
      78: ldc_w         #310                // String relative
      81: invokevirtual #52                 // Method java/lang/String.equals:(Ljava/lang/Object;)Z
      84: ifeq          95
      87: iload_2
      88: bipush        8
      90: ior
      91: istore_2
      92: goto          159
      95: aload_3
      96: ldc_w         #311                // String parent
      99: invokevirtual #52                 // Method java/lang/String.equals:(Ljava/lang/Object;)Z
     102: ifeq          113
     105: iload_2
     106: bipush        16
     108: ior
     109: istore_2
     110: goto          159
     113: aload_3
     114: ldc_w         #312                // String grandparent
     117: invokevirtual #52                 // Method java/lang/String.equals:(Ljava/lang/Object;)Z
     120: ifeq          131
     123: iload_2
     124: bipush        32
     126: ior
     127: istore_2
     128: goto          159
     131: getstatic     #31                 // Field logger:Lorg/apache/jena/rdfxml/xmloutput/impl/SimpleLogger;
     134: new           #37                 // class java/lang/StringBuilder
     137: dup
     138: invokespecial #38                 // Method java/lang/StringBuilder."<init>":()V
     141: ldc_w         #313                // String Incorrect property value for relativeURIs:
     144: invokevirtual #40                 // Method java/lang/StringBuilder.append:(Ljava/lang/String;)Ljava/lang/StringBuilder;
     147: aload_3
     148: invokevirtual #40                 // Method java/lang/StringBuilder.append:(Ljava/lang/String;)Ljava/lang/StringBuilder;
     151: invokevirtual #42                 // Method java/lang/StringBuilder.toString:()Ljava/lang/String;
     154: invokeinterface #131,  2          // InterfaceMethod org/apache/jena/rdfxml/xmloutput/impl/SimpleLogger.warn:(Ljava/lang/String;)V
     159: goto          14
     162: iload_2
     163: ireturn

  static org.slf4j.Logger access$000();
    Code:
       0: getstatic     #1                  // Field xlogger:Lorg/slf4j/Logger;
       3: areturn

  static {};
    Code:
       0: ldc_w         #314                // String line.separator
       3: invokestatic  #94                 // Method org/apache/jena/JenaRuntime.getSystemProperty:(Ljava/lang/String;)Ljava/lang/String;
       6: putstatic     #110                // Field newline:Ljava/lang/String;
       9: ldc           #68                 // class org/apache/jena/rdfxml/xmloutput/impl/BaseXMLWriter
      11: invokestatic  #315                // Method org/slf4j/LoggerFactory.getLogger:(Ljava/lang/Class;)Lorg/slf4j/Logger;
      14: putstatic     #1                  // Field xlogger:Lorg/slf4j/Logger;
      17: new           #316                // class org/apache/jena/rdfxml/xmloutput/impl/BaseXMLWriter$1
      20: dup
      21: invokespecial #317                // Method org/apache/jena/rdfxml/xmloutput/impl/BaseXMLWriter$1."<init>":()V
      24: putstatic     #31                 // Field logger:Lorg/apache/jena/rdfxml/xmloutput/impl/SimpleLogger;
      27: new           #88                 // class java/util/HashSet
      30: dup
      31: invokespecial #89                 // Method java/util/HashSet."<init>":()V
      34: putstatic     #128                // Field badRDF:Ljava/util/Set;
      37: invokestatic  #73                 // Method org/apache/jena/vocabulary/RDF.getURI:()Ljava/lang/String;
      40: putstatic     #116                // Field RDFNS:Ljava/lang/String;
      43: ldc_w         #318                // String j\\.([1-9][0-9]*|cook\\.up)
      46: invokestatic  #319                // Method java/util/regex/Pattern.compile:(Ljava/lang/String;)Ljava/util/regex/Pattern;
      49: putstatic     #295                // Field jenaNamespace:Ljava/util/regex/Pattern;
      52: getstatic     #128                // Field badRDF:Ljava/util/Set;
      55: ldc           #175                // String RDF
      57: invokeinterface #48,  2           // InterfaceMethod java/util/Set.add:(Ljava/lang/Object;)Z
      62: pop
      63: getstatic     #128                // Field badRDF:Ljava/util/Set;
      66: ldc_w         #320                // String Description
      69: invokeinterface #48,  2           // InterfaceMethod java/util/Set.add:(Ljava/lang/Object;)Z
      74: pop
      75: getstatic     #128                // Field badRDF:Ljava/util/Set;
      78: ldc_w         #321                // String li
      81: invokeinterface #48,  2           // InterfaceMethod java/util/Set.add:(Ljava/lang/Object;)Z
      86: pop
      87: getstatic     #128                // Field badRDF:Ljava/util/Set;
      90: ldc_w         #322                // String about
      93: invokeinterface #48,  2           // InterfaceMethod java/util/Set.add:(Ljava/lang/Object;)Z
      98: pop
      99: getstatic     #128                // Field badRDF:Ljava/util/Set;
     102: ldc_w         #323                // String aboutEach
     105: invokeinterface #48,  2           // InterfaceMethod java/util/Set.add:(Ljava/lang/Object;)Z
     110: pop
     111: getstatic     #128                // Field badRDF:Ljava/util/Set;
     114: ldc_w         #324                // String aboutEachPrefix
     117: invokeinterface #48,  2           // InterfaceMethod java/util/Set.add:(Ljava/lang/Object;)Z
     122: pop
     123: getstatic     #128                // Field badRDF:Ljava/util/Set;
     126: ldc_w         #325                // String ID
     129: invokeinterface #48,  2           // InterfaceMethod java/util/Set.add:(Ljava/lang/Object;)Z
     134: pop
     135: getstatic     #128                // Field badRDF:Ljava/util/Set;
     138: ldc_w         #326                // String nodeID
     141: invokeinterface #48,  2           // InterfaceMethod java/util/Set.add:(Ljava/lang/Object;)Z
     146: pop
     147: getstatic     #128                // Field badRDF:Ljava/util/Set;
     150: ldc_w         #327                // String parseType
     153: invokeinterface #48,  2           // InterfaceMethod java/util/Set.add:(Ljava/lang/Object;)Z
     158: pop
     159: getstatic     #128                // Field badRDF:Ljava/util/Set;
     162: ldc_w         #328                // String datatype
     165: invokeinterface #48,  2           // InterfaceMethod java/util/Set.add:(Ljava/lang/Object;)Z
     170: pop
     171: getstatic     #128                // Field badRDF:Ljava/util/Set;
     174: ldc_w         #329                // String bagID
     177: invokeinterface #48,  2           // InterfaceMethod java/util/Set.add:(Ljava/lang/Object;)Z
     182: pop
     183: getstatic     #128                // Field badRDF:Ljava/util/Set;
     186: ldc_w         #330                // String resource
     189: invokeinterface #48,  2           // InterfaceMethod java/util/Set.add:(Ljava/lang/Object;)Z
     194: pop
     195: new           #331                // class org/apache/jena/rdf/model/impl/RDFDefaultErrorHandler
     198: dup
     199: invokespecial #332                // Method org/apache/jena/rdf/model/impl/RDFDefaultErrorHandler."<init>":()V
     202: putstatic     #14                 // Field defaultErrorHandler:Lorg/apache/jena/rdf/model/impl/RDFDefaultErrorHandler;
     205: iconst_0
     206: putstatic     #124                // Field dbg:Z
     209: invokestatic  #333                // Method org/apache/jena/iri/IRIFactory.jenaImplementation:()Lorg/apache/jena/iri/IRIFactory;
     212: putstatic     #161                // Field factory:Lorg/apache/jena/iri/IRIFactory;
     215: ldc_w         #334                // String amp|lt|gt|apos|quot
     218: invokestatic  #319                // Method java/util/regex/Pattern.compile:(Ljava/lang/String;)Ljava/util/regex/Pattern;
     221: putstatic     #165                // Field predefinedEntityNames:Ljava/util/regex/Pattern;
     224: ldc_w         #335                // String 0123456789abcdef
     227: invokevirtual #336                // Method java/lang/String.toCharArray:()[C
     230: putstatic     #211                // Field hexchar:[C
     233: return
}
