Compiled from "AnnotatedFieldInjector.java"
class org.picocontainer.injectors.AnnotatedFieldInjector$1 implements java.security.PrivilegedAction<java.lang.reflect.Field[]> {
  final java.lang.Class val$clazz;

  final org.picocontainer.injectors.AnnotatedFieldInjector this$0;

  org.picocontainer.injectors.AnnotatedFieldInjector$1(org.picocontainer.injectors.AnnotatedFieldInjector, java.lang.Class);
    Code:
       0: aload_0
       1: aload_1
       2: putfield      #21                 // Field this$0:Lorg/picocontainer/injectors/AnnotatedFieldInjector;
       5: aload_0
       6: aload_2
       7: putfield      #23                 // Field val$clazz:Ljava/lang/Class;
      10: aload_0
      11: invokespecial #26                 // Method java/lang/Object."<init>":()V
      14: return

  public java.lang.reflect.Field[] run();
    Code:
       0: aload_0
       1: getfield      #23                 // Field val$clazz:Ljava/lang/Class;
       4: invokevirtual #36                 // Method java/lang/Class.getDeclaredFields:()[Ljava/lang/reflect/Field;
       7: areturn

  public java.lang.Object run();
    Code:
       0: aload_0
       1: invokevirtual #39                 // Method run:()[Ljava/lang/reflect/Field;
       4: areturn
}
