Compiled from "IndexedSeqView.scala"
public abstract class scala.collection.mutable.IndexedSeqView$class {
  public static scala.collection.mutable.IndexedSeqView$Transformed newFiltered(scala.collection.mutable.IndexedSeqView, scala.Function1);
    Code:
       0: new           #9                  // class scala/collection/mutable/IndexedSeqView$$anon$1
       3: dup
       4: aload_0
       5: aload_1
       6: invokespecial #13                 // Method scala/collection/mutable/IndexedSeqView$$anon$1."<init>":(Lscala/collection/mutable/IndexedSeqView;Lscala/Function1;)V
       9: areturn

  public static scala.collection.mutable.IndexedSeqView$Transformed newSliced(scala.collection.mutable.IndexedSeqView, scala.collection.generic.SliceInterval);
    Code:
       0: new           #21                 // class scala/collection/mutable/IndexedSeqView$$anon$2
       3: dup
       4: aload_0
       5: aload_1
       6: invokespecial #24                 // Method scala/collection/mutable/IndexedSeqView$$anon$2."<init>":(Lscala/collection/mutable/IndexedSeqView;Lscala/collection/generic/SliceInterval;)V
       9: areturn

  public static scala.collection.mutable.IndexedSeqView$Transformed newDroppedWhile(scala.collection.mutable.IndexedSeqView, scala.Function1);
    Code:
       0: new           #29                 // class scala/collection/mutable/IndexedSeqView$$anon$3
       3: dup
       4: aload_0
       5: aload_1
       6: invokespecial #30                 // Method scala/collection/mutable/IndexedSeqView$$anon$3."<init>":(Lscala/collection/mutable/IndexedSeqView;Lscala/Function1;)V
       9: areturn

  public static scala.collection.mutable.IndexedSeqView$Transformed newTakenWhile(scala.collection.mutable.IndexedSeqView, scala.Function1);
    Code:
       0: new           #33                 // class scala/collection/mutable/IndexedSeqView$$anon$4
       3: dup
       4: aload_0
       5: aload_1
       6: invokespecial #34                 // Method scala/collection/mutable/IndexedSeqView$$anon$4."<init>":(Lscala/collection/mutable/IndexedSeqView;Lscala/Function1;)V
       9: areturn

  public static scala.collection.mutable.IndexedSeqView$Transformed newReversed(scala.collection.mutable.IndexedSeqView);
    Code:
       0: new           #38                 // class scala/collection/mutable/IndexedSeqView$$anon$5
       3: dup
       4: aload_0
       5: invokespecial #41                 // Method scala/collection/mutable/IndexedSeqView$$anon$5."<init>":(Lscala/collection/mutable/IndexedSeqView;)V
       8: areturn

  public static scala.collection.mutable.IndexedSeqView filter(scala.collection.mutable.IndexedSeqView, scala.Function1);
    Code:
       0: aload_0
       1: aload_1
       2: invokeinterface #48,  2           // InterfaceMethod scala/collection/mutable/IndexedSeqView.newFiltered:(Lscala/Function1;)Lscala/collection/mutable/IndexedSeqView$Transformed;
       7: areturn

  public static scala.collection.mutable.IndexedSeqView init(scala.collection.mutable.IndexedSeqView);
    Code:
       0: aload_0
       1: getstatic     #56                 // Field scala/collection/generic/SliceInterval$.MODULE$:Lscala/collection/generic/SliceInterval$;
       4: iconst_0
       5: aload_0
       6: invokeinterface #60,  1           // InterfaceMethod scala/collection/mutable/IndexedSeqView.length:()I
      11: iconst_1
      12: isub
      13: invokevirtual #64                 // Method scala/collection/generic/SliceInterval$.apply:(II)Lscala/collection/generic/SliceInterval;
      16: invokeinterface #67,  2           // InterfaceMethod scala/collection/mutable/IndexedSeqView.newSliced:(Lscala/collection/generic/SliceInterval;)Lscala/collection/mutable/IndexedSeqView$Transformed;
      21: areturn

  public static scala.collection.mutable.IndexedSeqView drop(scala.collection.mutable.IndexedSeqView, int);
    Code:
       0: aload_0
       1: getstatic     #56                 // Field scala/collection/generic/SliceInterval$.MODULE$:Lscala/collection/generic/SliceInterval$;
       4: iload_1
       5: aload_0
       6: invokeinterface #60,  1           // InterfaceMethod scala/collection/mutable/IndexedSeqView.length:()I
      11: invokevirtual #64                 // Method scala/collection/generic/SliceInterval$.apply:(II)Lscala/collection/generic/SliceInterval;
      14: invokeinterface #67,  2           // InterfaceMethod scala/collection/mutable/IndexedSeqView.newSliced:(Lscala/collection/generic/SliceInterval;)Lscala/collection/mutable/IndexedSeqView$Transformed;
      19: areturn

  public static scala.collection.mutable.IndexedSeqView take(scala.collection.mutable.IndexedSeqView, int);
    Code:
       0: aload_0
       1: getstatic     #56                 // Field scala/collection/generic/SliceInterval$.MODULE$:Lscala/collection/generic/SliceInterval$;
       4: iconst_0
       5: getstatic     #77                 // Field scala/runtime/RichInt$.MODULE$:Lscala/runtime/RichInt$;
       8: getstatic     #82                 // Field scala/Predef$.MODULE$:Lscala/Predef$;
      11: astore_2
      12: iload_1
      13: aload_0
      14: invokeinterface #60,  1           // InterfaceMethod scala/collection/mutable/IndexedSeqView.length:()I
      19: invokevirtual #86                 // Method scala/runtime/RichInt$.min$extension:(II)I
      22: invokevirtual #64                 // Method scala/collection/generic/SliceInterval$.apply:(II)Lscala/collection/generic/SliceInterval;
      25: invokeinterface #67,  2           // InterfaceMethod scala/collection/mutable/IndexedSeqView.newSliced:(Lscala/collection/generic/SliceInterval;)Lscala/collection/mutable/IndexedSeqView$Transformed;
      30: areturn

  public static scala.collection.mutable.IndexedSeqView slice(scala.collection.mutable.IndexedSeqView, int, int);
    Code:
       0: aload_0
       1: getstatic     #56                 // Field scala/collection/generic/SliceInterval$.MODULE$:Lscala/collection/generic/SliceInterval$;
       4: iload_1
       5: getstatic     #77                 // Field scala/runtime/RichInt$.MODULE$:Lscala/runtime/RichInt$;
       8: getstatic     #82                 // Field scala/Predef$.MODULE$:Lscala/Predef$;
      11: astore_3
      12: iload_2
      13: aload_0
      14: invokeinterface #60,  1           // InterfaceMethod scala/collection/mutable/IndexedSeqView.length:()I
      19: invokevirtual #86                 // Method scala/runtime/RichInt$.min$extension:(II)I
      22: invokevirtual #64                 // Method scala/collection/generic/SliceInterval$.apply:(II)Lscala/collection/generic/SliceInterval;
      25: invokeinterface #67,  2           // InterfaceMethod scala/collection/mutable/IndexedSeqView.newSliced:(Lscala/collection/generic/SliceInterval;)Lscala/collection/mutable/IndexedSeqView$Transformed;
      30: areturn

  public static scala.collection.mutable.IndexedSeqView dropWhile(scala.collection.mutable.IndexedSeqView, scala.Function1);
    Code:
       0: aload_0
       1: aload_1
       2: invokeinterface #93,  2           // InterfaceMethod scala/collection/mutable/IndexedSeqView.newDroppedWhile:(Lscala/Function1;)Lscala/collection/mutable/IndexedSeqView$Transformed;
       7: areturn

  public static scala.collection.mutable.IndexedSeqView takeWhile(scala.collection.mutable.IndexedSeqView, scala.Function1);
    Code:
       0: aload_0
       1: aload_1
       2: invokeinterface #96,  2           // InterfaceMethod scala/collection/mutable/IndexedSeqView.newTakenWhile:(Lscala/Function1;)Lscala/collection/mutable/IndexedSeqView$Transformed;
       7: areturn

  public static scala.Tuple2 span(scala.collection.mutable.IndexedSeqView, scala.Function1);
    Code:
       0: new           #100                // class scala/Tuple2
       3: dup
       4: aload_0
       5: aload_1
       6: invokeinterface #96,  2           // InterfaceMethod scala/collection/mutable/IndexedSeqView.newTakenWhile:(Lscala/Function1;)Lscala/collection/mutable/IndexedSeqView$Transformed;
      11: aload_0
      12: aload_1
      13: invokeinterface #93,  2           // InterfaceMethod scala/collection/mutable/IndexedSeqView.newDroppedWhile:(Lscala/Function1;)Lscala/collection/mutable/IndexedSeqView$Transformed;
      18: invokespecial #103                // Method scala/Tuple2."<init>":(Ljava/lang/Object;Ljava/lang/Object;)V
      21: areturn

  public static scala.Tuple2 splitAt(scala.collection.mutable.IndexedSeqView, int);
    Code:
       0: new           #100                // class scala/Tuple2
       3: dup
       4: aload_0
       5: iload_1
       6: invokeinterface #108,  2          // InterfaceMethod scala/collection/mutable/IndexedSeqView.take:(I)Lscala/collection/mutable/IndexedSeqView;
      11: aload_0
      12: iload_1
      13: invokeinterface #110,  2          // InterfaceMethod scala/collection/mutable/IndexedSeqView.drop:(I)Lscala/collection/mutable/IndexedSeqView;
      18: invokespecial #103                // Method scala/Tuple2."<init>":(Ljava/lang/Object;Ljava/lang/Object;)V
      21: areturn

  public static scala.collection.mutable.IndexedSeqView reverse(scala.collection.mutable.IndexedSeqView);
    Code:
       0: aload_0
       1: invokeinterface #114,  1          // InterfaceMethod scala/collection/mutable/IndexedSeqView.newReversed:()Lscala/collection/mutable/IndexedSeqView$Transformed;
       6: areturn

  public static scala.collection.mutable.IndexedSeqView tail(scala.collection.mutable.IndexedSeqView);
    Code:
       0: aload_0
       1: invokeinterface #119,  1          // InterfaceMethod scala/collection/mutable/IndexedSeqView.isEmpty:()Z
       6: ifeq          18
       9: aload_0
      10: invokeinterface #123,  1          // InterfaceMethod scala/collection/mutable/IndexedSeqView.scala$collection$mutable$IndexedSeqView$$super$tail:()Lscala/collection/mutable/IndexedSeqView;
      15: goto          31
      18: aload_0
      19: iconst_1
      20: aload_0
      21: invokeinterface #60,  1           // InterfaceMethod scala/collection/mutable/IndexedSeqView.length:()I
      26: invokeinterface #126,  3          // InterfaceMethod scala/collection/mutable/IndexedSeqView.slice:(II)Lscala/collection/mutable/IndexedSeqView;
      31: areturn

  public static void $init$(scala.collection.mutable.IndexedSeqView);
    Code:
       0: return
}
