Compiled from "RethrowErrorService.java"
public class org.glassfish.hk2.utilities.RethrowErrorService implements org.glassfish.hk2.api.ErrorService {
  public org.glassfish.hk2.utilities.RethrowErrorService();
    Code:
       0: aload_0
       1: invokespecial #1                  // Method java/lang/Object."<init>":()V
       4: return

  public void onFailure(org.glassfish.hk2.api.ErrorInformation) throws org.glassfish.hk2.api.MultiException;
    Code:
       0: getstatic     #2                  // Field org/glassfish/hk2/api/ErrorType.FAILURE_TO_REIFY:Lorg/glassfish/hk2/api/ErrorType;
       3: aload_1
       4: invokeinterface #3,  1            // InterfaceMethod org/glassfish/hk2/api/ErrorInformation.getErrorType:()Lorg/glassfish/hk2/api/ErrorType;
       9: invokevirtual #4                  // Method org/glassfish/hk2/api/ErrorType.equals:(Ljava/lang/Object;)Z
      12: ifeq          29
      15: aload_1
      16: invokeinterface #5,  1            // InterfaceMethod org/glassfish/hk2/api/ErrorInformation.getAssociatedException:()Lorg/glassfish/hk2/api/MultiException;
      21: astore_2
      22: aload_2
      23: ifnonnull     27
      26: return
      27: aload_2
      28: athrow
      29: return
}
