Compiled from "HandleAndService.java"
public class org.glassfish.hk2.internal.HandleAndService {
  private final org.glassfish.hk2.api.ServiceHandle<?> handle;

  private final java.lang.Object service;

  public org.glassfish.hk2.internal.HandleAndService(org.glassfish.hk2.api.ServiceHandle<?>, java.lang.Object);
    Code:
       0: aload_0
       1: invokespecial #1                  // Method java/lang/Object."<init>":()V
       4: aload_0
       5: aload_1
       6: putfield      #2                  // Field handle:Lorg/glassfish/hk2/api/ServiceHandle;
       9: aload_0
      10: aload_2
      11: putfield      #3                  // Field service:Ljava/lang/Object;
      14: return

  public org.glassfish.hk2.api.ServiceHandle<?> getHandle();
    Code:
       0: aload_0
       1: getfield      #2                  // Field handle:Lorg/glassfish/hk2/api/ServiceHandle;
       4: areturn

  public java.lang.Object getService();
    Code:
       0: aload_0
       1: getfield      #3                  // Field service:Ljava/lang/Object;
       4: areturn
}
