Compiled from "ServiceLocatorFactoryImpl.java"
public class org.glassfish.hk2.internal.ServiceLocatorFactoryImpl extends org.glassfish.hk2.api.ServiceLocatorFactory {
  private static final java.lang.String DEBUG_SERVICE_LOCATOR_PROPERTY;

  private static final boolean DEBUG_SERVICE_LOCATOR_LIFECYCLE;

  private static final java.lang.Object sLock;

  private static int name_count;

  private static final java.lang.String GENERATED_NAME_PREFIX;

  private final java.lang.Object lock;

  private final java.util.HashMap<java.lang.String, org.glassfish.hk2.api.ServiceLocator> serviceLocators;

  private final java.util.HashSet<org.glassfish.hk2.api.ServiceLocatorListener> listeners;

  private static org.glassfish.hk2.extension.ServiceLocatorGenerator getGeneratorSecure();
    Code:
       0: new           #3                  // class org/glassfish/hk2/internal/ServiceLocatorFactoryImpl$2
       3: dup
       4: invokespecial #4                  // Method org/glassfish/hk2/internal/ServiceLocatorFactoryImpl$2."<init>":()V
       7: invokestatic  #5                  // Method java/security/AccessController.doPrivileged:(Ljava/security/PrivilegedAction;)Ljava/lang/Object;
      10: checkcast     #6                  // class org/glassfish/hk2/extension/ServiceLocatorGenerator
      13: areturn

  public org.glassfish.hk2.internal.ServiceLocatorFactoryImpl();
    Code:
       0: aload_0
       1: invokespecial #7                  // Method org/glassfish/hk2/api/ServiceLocatorFactory."<init>":()V
       4: aload_0
       5: new           #8                  // class java/lang/Object
       8: dup
       9: invokespecial #9                  // Method java/lang/Object."<init>":()V
      12: putfield      #10                 // Field lock:Ljava/lang/Object;
      15: aload_0
      16: new           #11                 // class java/util/HashMap
      19: dup
      20: invokespecial #12                 // Method java/util/HashMap."<init>":()V
      23: putfield      #13                 // Field serviceLocators:Ljava/util/HashMap;
      26: aload_0
      27: new           #14                 // class java/util/HashSet
      30: dup
      31: invokespecial #15                 // Method java/util/HashSet."<init>":()V
      34: putfield      #16                 // Field listeners:Ljava/util/HashSet;
      37: return

  private static java.lang.Iterable<? extends org.glassfish.hk2.extension.ServiceLocatorGenerator> getOSGiSafeGenerators();
    Code:
       0: ldc           #6                  // class org/glassfish/hk2/extension/ServiceLocatorGenerator
       2: invokestatic  #17                 // Method org/glassfish/hk2/osgiresourcelocator/ServiceLoader.lookupProviderInstances:(Ljava/lang/Class;)Ljava/lang/Iterable;
       5: areturn
       6: astore_0
       7: aconst_null
       8: areturn
    Exception table:
       from    to  target type
           0     5     6   Class java/lang/Throwable

  private static org.glassfish.hk2.extension.ServiceLocatorGenerator getGenerator();
    Code:
       0: invokestatic  #19                 // Method getOSGiSafeGenerators:()Ljava/lang/Iterable;
       3: astore_0
       4: aload_0
       5: ifnull        38
       8: aload_0
       9: invokeinterface #20,  1           // InterfaceMethod java/lang/Iterable.iterator:()Ljava/util/Iterator;
      14: astore_1
      15: aload_1
      16: invokeinterface #21,  1           // InterfaceMethod java/util/Iterator.hasNext:()Z
      21: ifeq          36
      24: aload_1
      25: invokeinterface #22,  1           // InterfaceMethod java/util/Iterator.next:()Ljava/lang/Object;
      30: checkcast     #6                  // class org/glassfish/hk2/extension/ServiceLocatorGenerator
      33: goto          37
      36: aconst_null
      37: areturn
      38: ldc           #23                 // class org/glassfish/hk2/internal/ServiceLocatorFactoryImpl
      40: invokevirtual #24                 // Method java/lang/Class.getClassLoader:()Ljava/lang/ClassLoader;
      43: astore_1
      44: ldc           #6                  // class org/glassfish/hk2/extension/ServiceLocatorGenerator
      46: aload_1
      47: invokestatic  #25                 // Method java/util/ServiceLoader.load:(Ljava/lang/Class;Ljava/lang/ClassLoader;)Ljava/util/ServiceLoader;
      50: invokevirtual #26                 // Method java/util/ServiceLoader.iterator:()Ljava/util/Iterator;
      53: astore_2
      54: aload_2
      55: invokeinterface #21,  1           // InterfaceMethod java/util/Iterator.hasNext:()Z
      60: ifeq          88
      63: aload_2
      64: invokeinterface #22,  1           // InterfaceMethod java/util/Iterator.next:()Ljava/lang/Object;
      69: checkcast     #6                  // class org/glassfish/hk2/extension/ServiceLocatorGenerator
      72: areturn
      73: astore_3
      74: invokestatic  #28                 // Method org/glassfish/hk2/utilities/reflection/Logger.getLogger:()Lorg/glassfish/hk2/utilities/reflection/Logger;
      77: ldc           #29                 // String ServiceLocatorFactoryImpl
      79: ldc           #30                 // String getGenerator
      81: aload_3
      82: invokevirtual #31                 // Method org/glassfish/hk2/utilities/reflection/Logger.debug:(Ljava/lang/String;Ljava/lang/String;Ljava/lang/Throwable;)V
      85: goto          54
      88: invokestatic  #28                 // Method org/glassfish/hk2/utilities/reflection/Logger.getLogger:()Lorg/glassfish/hk2/utilities/reflection/Logger;
      91: ldc           #32                 // String Cannot find a default implementation of the HK2 ServiceLocatorGenerator
      93: invokevirtual #33                 // Method org/glassfish/hk2/utilities/reflection/Logger.warning:(Ljava/lang/String;)V
      96: aconst_null
      97: areturn
    Exception table:
       from    to  target type
          63    72    73   Class java/util/ServiceConfigurationError

  public org.glassfish.hk2.api.ServiceLocator create(java.lang.String);
    Code:
       0: aload_0
       1: aload_1
       2: aconst_null
       3: aconst_null
       4: getstatic     #34                 // Field org/glassfish/hk2/api/ServiceLocatorFactory$CreatePolicy.RETURN:Lorg/glassfish/hk2/api/ServiceLocatorFactory$CreatePolicy;
       7: invokevirtual #35                 // Method create:(Ljava/lang/String;Lorg/glassfish/hk2/api/ServiceLocator;Lorg/glassfish/hk2/extension/ServiceLocatorGenerator;Lorg/glassfish/hk2/api/ServiceLocatorFactory$CreatePolicy;)Lorg/glassfish/hk2/api/ServiceLocator;
      10: areturn

  public org.glassfish.hk2.api.ServiceLocator find(java.lang.String);
    Code:
       0: aload_0
       1: getfield      #10                 // Field lock:Ljava/lang/Object;
       4: dup
       5: astore_2
       6: monitorenter
       7: aload_0
       8: getfield      #13                 // Field serviceLocators:Ljava/util/HashMap;
      11: aload_1
      12: invokevirtual #36                 // Method java/util/HashMap.get:(Ljava/lang/Object;)Ljava/lang/Object;
      15: checkcast     #37                 // class org/glassfish/hk2/api/ServiceLocator
      18: aload_2
      19: monitorexit
      20: areturn
      21: astore_3
      22: aload_2
      23: monitorexit
      24: aload_3
      25: athrow
    Exception table:
       from    to  target type
           7    20    21   any
          21    24    21   any

  public void destroy(java.lang.String);
    Code:
       0: aload_0
       1: aload_1
       2: aconst_null
       3: invokespecial #38                 // Method destroy:(Ljava/lang/String;Lorg/glassfish/hk2/api/ServiceLocator;)V
       6: return

  private void destroy(java.lang.String, org.glassfish.hk2.api.ServiceLocator);
    Code:
       0: aconst_null
       1: astore_3
       2: aload_0
       3: getfield      #10                 // Field lock:Ljava/lang/Object;
       6: dup
       7: astore        4
       9: monitorenter
      10: aload_1
      11: ifnull        26
      14: aload_0
      15: getfield      #13                 // Field serviceLocators:Ljava/util/HashMap;
      18: aload_1
      19: invokevirtual #39                 // Method java/util/HashMap.remove:(Ljava/lang/Object;)Ljava/lang/Object;
      22: checkcast     #37                 // class org/glassfish/hk2/api/ServiceLocator
      25: astore_3
      26: getstatic     #40                 // Field DEBUG_SERVICE_LOCATOR_LIFECYCLE:Z
      29: ifeq          82
      32: invokestatic  #28                 // Method org/glassfish/hk2/utilities/reflection/Logger.getLogger:()Lorg/glassfish/hk2/utilities/reflection/Logger;
      35: new           #41                 // class java/lang/StringBuilder
      38: dup
      39: invokespecial #42                 // Method java/lang/StringBuilder."<init>":()V
      42: ldc           #43                 // String ServiceFactoryImpl destroying locator with name
      44: invokevirtual #44                 // Method java/lang/StringBuilder.append:(Ljava/lang/String;)Ljava/lang/StringBuilder;
      47: aload_1
      48: invokevirtual #44                 // Method java/lang/StringBuilder.append:(Ljava/lang/String;)Ljava/lang/StringBuilder;
      51: ldc           #45                 // String  and locator
      53: invokevirtual #44                 // Method java/lang/StringBuilder.append:(Ljava/lang/String;)Ljava/lang/StringBuilder;
      56: aload_2
      57: invokevirtual #46                 // Method java/lang/StringBuilder.append:(Ljava/lang/Object;)Ljava/lang/StringBuilder;
      60: ldc           #47                 // String  with found locator
      62: invokevirtual #44                 // Method java/lang/StringBuilder.append:(Ljava/lang/String;)Ljava/lang/StringBuilder;
      65: aload_3
      66: invokevirtual #46                 // Method java/lang/StringBuilder.append:(Ljava/lang/Object;)Ljava/lang/StringBuilder;
      69: invokevirtual #48                 // Method java/lang/StringBuilder.toString:()Ljava/lang/String;
      72: new           #18                 // class java/lang/Throwable
      75: dup
      76: invokespecial #49                 // Method java/lang/Throwable."<init>":()V
      79: invokevirtual #50                 // Method org/glassfish/hk2/utilities/reflection/Logger.debug:(Ljava/lang/String;Ljava/lang/Throwable;)V
      82: aload_3
      83: ifnonnull     88
      86: aload_2
      87: astore_3
      88: aload_3
      89: ifnull        174
      92: aload_0
      93: getfield      #16                 // Field listeners:Ljava/util/HashSet;
      96: invokevirtual #51                 // Method java/util/HashSet.iterator:()Ljava/util/Iterator;
      99: astore        5
     101: aload         5
     103: invokeinterface #21,  1           // InterfaceMethod java/util/Iterator.hasNext:()Z
     108: ifeq          174
     111: aload         5
     113: invokeinterface #22,  1           // InterfaceMethod java/util/Iterator.next:()Ljava/lang/Object;
     118: checkcast     #52                 // class org/glassfish/hk2/api/ServiceLocatorListener
     121: astore        6
     123: aload         6
     125: aload_3
     126: invokeinterface #53,  2           // InterfaceMethod org/glassfish/hk2/api/ServiceLocatorListener.locatorDestroyed:(Lorg/glassfish/hk2/api/ServiceLocator;)V
     131: goto          171
     134: astore        7
     136: invokestatic  #28                 // Method org/glassfish/hk2/utilities/reflection/Logger.getLogger:()Lorg/glassfish/hk2/utilities/reflection/Logger;
     139: aload_0
     140: invokevirtual #54                 // Method java/lang/Object.getClass:()Ljava/lang/Class;
     143: invokevirtual #55                 // Method java/lang/Class.getName:()Ljava/lang/String;
     146: new           #41                 // class java/lang/StringBuilder
     149: dup
     150: invokespecial #42                 // Method java/lang/StringBuilder."<init>":()V
     153: ldc           #56                 // String destroy
     155: invokevirtual #44                 // Method java/lang/StringBuilder.append:(Ljava/lang/String;)Ljava/lang/StringBuilder;
     158: aload         6
     160: invokevirtual #46                 // Method java/lang/StringBuilder.append:(Ljava/lang/Object;)Ljava/lang/StringBuilder;
     163: invokevirtual #48                 // Method java/lang/StringBuilder.toString:()Ljava/lang/String;
     166: aload         7
     168: invokevirtual #31                 // Method org/glassfish/hk2/utilities/reflection/Logger.debug:(Ljava/lang/String;Ljava/lang/String;Ljava/lang/Throwable;)V
     171: goto          101
     174: aload         4
     176: monitorexit
     177: goto          188
     180: astore        8
     182: aload         4
     184: monitorexit
     185: aload         8
     187: athrow
     188: aload_3
     189: ifnull        198
     192: aload_3
     193: invokeinterface #57,  1           // InterfaceMethod org/glassfish/hk2/api/ServiceLocator.shutdown:()V
     198: return
    Exception table:
       from    to  target type
         123   131   134   Class java/lang/Throwable
          10   177   180   any
         180   185   180   any

  public void destroy(org.glassfish.hk2.api.ServiceLocator);
    Code:
       0: aload_1
       1: ifnonnull     5
       4: return
       5: aload_0
       6: aload_1
       7: invokeinterface #58,  1           // InterfaceMethod org/glassfish/hk2/api/ServiceLocator.getName:()Ljava/lang/String;
      12: aload_1
      13: invokespecial #38                 // Method destroy:(Ljava/lang/String;Lorg/glassfish/hk2/api/ServiceLocator;)V
      16: return

  public org.glassfish.hk2.api.ServiceLocator create(java.lang.String, org.glassfish.hk2.api.ServiceLocator);
    Code:
       0: aload_0
       1: aload_1
       2: aload_2
       3: aconst_null
       4: getstatic     #34                 // Field org/glassfish/hk2/api/ServiceLocatorFactory$CreatePolicy.RETURN:Lorg/glassfish/hk2/api/ServiceLocatorFactory$CreatePolicy;
       7: invokevirtual #35                 // Method create:(Ljava/lang/String;Lorg/glassfish/hk2/api/ServiceLocator;Lorg/glassfish/hk2/extension/ServiceLocatorGenerator;Lorg/glassfish/hk2/api/ServiceLocatorFactory$CreatePolicy;)Lorg/glassfish/hk2/api/ServiceLocator;
      10: areturn

  private static java.lang.String getGeneratedName();
    Code:
       0: getstatic     #59                 // Field sLock:Ljava/lang/Object;
       3: dup
       4: astore_0
       5: monitorenter
       6: new           #41                 // class java/lang/StringBuilder
       9: dup
      10: invokespecial #42                 // Method java/lang/StringBuilder."<init>":()V
      13: ldc           #60                 // String __HK2_Generated_
      15: invokevirtual #44                 // Method java/lang/StringBuilder.append:(Ljava/lang/String;)Ljava/lang/StringBuilder;
      18: getstatic     #61                 // Field name_count:I
      21: dup
      22: iconst_1
      23: iadd
      24: putstatic     #61                 // Field name_count:I
      27: invokevirtual #62                 // Method java/lang/StringBuilder.append:(I)Ljava/lang/StringBuilder;
      30: invokevirtual #48                 // Method java/lang/StringBuilder.toString:()Ljava/lang/String;
      33: aload_0
      34: monitorexit
      35: areturn
      36: astore_1
      37: aload_0
      38: monitorexit
      39: aload_1
      40: athrow
    Exception table:
       from    to  target type
           6    35    36   any
          36    39    36   any

  public org.glassfish.hk2.api.ServiceLocator create(java.lang.String, org.glassfish.hk2.api.ServiceLocator, org.glassfish.hk2.extension.ServiceLocatorGenerator);
    Code:
       0: aload_0
       1: aload_1
       2: aload_2
       3: aload_3
       4: getstatic     #34                 // Field org/glassfish/hk2/api/ServiceLocatorFactory$CreatePolicy.RETURN:Lorg/glassfish/hk2/api/ServiceLocatorFactory$CreatePolicy;
       7: invokevirtual #35                 // Method create:(Ljava/lang/String;Lorg/glassfish/hk2/api/ServiceLocator;Lorg/glassfish/hk2/extension/ServiceLocatorGenerator;Lorg/glassfish/hk2/api/ServiceLocatorFactory$CreatePolicy;)Lorg/glassfish/hk2/api/ServiceLocator;
      10: areturn

  private void callListenerAdded(org.glassfish.hk2.api.ServiceLocator);
    Code:
       0: aload_0
       1: getfield      #16                 // Field listeners:Ljava/util/HashSet;
       4: invokevirtual #51                 // Method java/util/HashSet.iterator:()Ljava/util/Iterator;
       7: astore_2
       8: aload_2
       9: invokeinterface #21,  1           // InterfaceMethod java/util/Iterator.hasNext:()Z
      14: ifeq          76
      17: aload_2
      18: invokeinterface #22,  1           // InterfaceMethod java/util/Iterator.next:()Ljava/lang/Object;
      23: checkcast     #52                 // class org/glassfish/hk2/api/ServiceLocatorListener
      26: astore_3
      27: aload_3
      28: aload_1
      29: invokeinterface #63,  2           // InterfaceMethod org/glassfish/hk2/api/ServiceLocatorListener.locatorAdded:(Lorg/glassfish/hk2/api/ServiceLocator;)V
      34: goto          73
      37: astore        4
      39: invokestatic  #28                 // Method org/glassfish/hk2/utilities/reflection/Logger.getLogger:()Lorg/glassfish/hk2/utilities/reflection/Logger;
      42: aload_0
      43: invokevirtual #54                 // Method java/lang/Object.getClass:()Ljava/lang/Class;
      46: invokevirtual #55                 // Method java/lang/Class.getName:()Ljava/lang/String;
      49: new           #41                 // class java/lang/StringBuilder
      52: dup
      53: invokespecial #42                 // Method java/lang/StringBuilder."<init>":()V
      56: ldc           #64                 // String create
      58: invokevirtual #44                 // Method java/lang/StringBuilder.append:(Ljava/lang/String;)Ljava/lang/StringBuilder;
      61: aload_3
      62: invokevirtual #46                 // Method java/lang/StringBuilder.append:(Ljava/lang/Object;)Ljava/lang/StringBuilder;
      65: invokevirtual #48                 // Method java/lang/StringBuilder.toString:()Ljava/lang/String;
      68: aload         4
      70: invokevirtual #31                 // Method org/glassfish/hk2/utilities/reflection/Logger.debug:(Ljava/lang/String;Ljava/lang/String;Ljava/lang/Throwable;)V
      73: goto          8
      76: return
    Exception table:
       from    to  target type
          27    34    37   Class java/lang/Throwable

  public org.glassfish.hk2.api.ServiceLocator create(java.lang.String, org.glassfish.hk2.api.ServiceLocator, org.glassfish.hk2.extension.ServiceLocatorGenerator, org.glassfish.hk2.api.ServiceLocatorFactory$CreatePolicy);
    Code:
       0: getstatic     #40                 // Field DEBUG_SERVICE_LOCATOR_LIFECYCLE:Z
       3: ifeq          66
       6: invokestatic  #28                 // Method org/glassfish/hk2/utilities/reflection/Logger.getLogger:()Lorg/glassfish/hk2/utilities/reflection/Logger;
       9: new           #41                 // class java/lang/StringBuilder
      12: dup
      13: invokespecial #42                 // Method java/lang/StringBuilder."<init>":()V
      16: ldc           #65                 // String ServiceFactoryImpl given create of
      18: invokevirtual #44                 // Method java/lang/StringBuilder.append:(Ljava/lang/String;)Ljava/lang/StringBuilder;
      21: aload_1
      22: invokevirtual #44                 // Method java/lang/StringBuilder.append:(Ljava/lang/String;)Ljava/lang/StringBuilder;
      25: ldc           #66                 // String  with parent
      27: invokevirtual #44                 // Method java/lang/StringBuilder.append:(Ljava/lang/String;)Ljava/lang/StringBuilder;
      30: aload_2
      31: invokevirtual #46                 // Method java/lang/StringBuilder.append:(Ljava/lang/Object;)Ljava/lang/StringBuilder;
      34: ldc           #67                 // String  with generator
      36: invokevirtual #44                 // Method java/lang/StringBuilder.append:(Ljava/lang/String;)Ljava/lang/StringBuilder;
      39: aload_3
      40: invokevirtual #46                 // Method java/lang/StringBuilder.append:(Ljava/lang/Object;)Ljava/lang/StringBuilder;
      43: ldc           #68                 // String  and policy
      45: invokevirtual #44                 // Method java/lang/StringBuilder.append:(Ljava/lang/String;)Ljava/lang/StringBuilder;
      48: aload         4
      50: invokevirtual #46                 // Method java/lang/StringBuilder.append:(Ljava/lang/Object;)Ljava/lang/StringBuilder;
      53: invokevirtual #48                 // Method java/lang/StringBuilder.toString:()Ljava/lang/String;
      56: new           #18                 // class java/lang/Throwable
      59: dup
      60: invokespecial #49                 // Method java/lang/Throwable."<init>":()V
      63: invokevirtual #50                 // Method org/glassfish/hk2/utilities/reflection/Logger.debug:(Ljava/lang/String;Ljava/lang/Throwable;)V
      66: aload_0
      67: getfield      #10                 // Field lock:Ljava/lang/Object;
      70: dup
      71: astore        5
      73: monitorenter
      74: aload_1
      75: ifnonnull     135
      78: invokestatic  #69                 // Method getGeneratedName:()Ljava/lang/String;
      81: astore_1
      82: aload_0
      83: aload_1
      84: aload_2
      85: aload_3
      86: invokespecial #70                 // Method internalCreate:(Ljava/lang/String;Lorg/glassfish/hk2/api/ServiceLocator;Lorg/glassfish/hk2/extension/ServiceLocatorGenerator;)Lorg/glassfish/hk2/api/ServiceLocator;
      89: astore        7
      91: aload_0
      92: aload         7
      94: invokespecial #71                 // Method callListenerAdded:(Lorg/glassfish/hk2/api/ServiceLocator;)V
      97: getstatic     #40                 // Field DEBUG_SERVICE_LOCATOR_LIFECYCLE:Z
     100: ifeq          129
     103: invokestatic  #28                 // Method org/glassfish/hk2/utilities/reflection/Logger.getLogger:()Lorg/glassfish/hk2/utilities/reflection/Logger;
     106: new           #41                 // class java/lang/StringBuilder
     109: dup
     110: invokespecial #42                 // Method java/lang/StringBuilder."<init>":()V
     113: ldc           #72                 // String ServiceFactoryImpl added untracked listener
     115: invokevirtual #44                 // Method java/lang/StringBuilder.append:(Ljava/lang/String;)Ljava/lang/StringBuilder;
     118: aload         7
     120: invokevirtual #46                 // Method java/lang/StringBuilder.append:(Ljava/lang/Object;)Ljava/lang/StringBuilder;
     123: invokevirtual #48                 // Method java/lang/StringBuilder.toString:()Ljava/lang/String;
     126: invokevirtual #73                 // Method org/glassfish/hk2/utilities/reflection/Logger.debug:(Ljava/lang/String;)V
     129: aload         7
     131: aload         5
     133: monitorexit
     134: areturn
     135: aload_0
     136: getfield      #13                 // Field serviceLocators:Ljava/util/HashMap;
     139: aload_1
     140: invokevirtual #36                 // Method java/util/HashMap.get:(Ljava/lang/Object;)Ljava/lang/Object;
     143: checkcast     #37                 // class org/glassfish/hk2/api/ServiceLocator
     146: astore        6
     148: aload         6
     150: ifnull        259
     153: aload         4
     155: ifnull        169
     158: getstatic     #34                 // Field org/glassfish/hk2/api/ServiceLocatorFactory$CreatePolicy.RETURN:Lorg/glassfish/hk2/api/ServiceLocatorFactory$CreatePolicy;
     161: aload         4
     163: invokevirtual #74                 // Method org/glassfish/hk2/api/ServiceLocatorFactory$CreatePolicy.equals:(Ljava/lang/Object;)Z
     166: ifeq          207
     169: getstatic     #40                 // Field DEBUG_SERVICE_LOCATOR_LIFECYCLE:Z
     172: ifeq          201
     175: invokestatic  #28                 // Method org/glassfish/hk2/utilities/reflection/Logger.getLogger:()Lorg/glassfish/hk2/utilities/reflection/Logger;
     178: new           #41                 // class java/lang/StringBuilder
     181: dup
     182: invokespecial #42                 // Method java/lang/StringBuilder."<init>":()V
     185: ldc           #75                 // String ServiceFactoryImpl added found listener under RETURN policy of
     187: invokevirtual #44                 // Method java/lang/StringBuilder.append:(Ljava/lang/String;)Ljava/lang/StringBuilder;
     190: aload         6
     192: invokevirtual #46                 // Method java/lang/StringBuilder.append:(Ljava/lang/Object;)Ljava/lang/StringBuilder;
     195: invokevirtual #48                 // Method java/lang/StringBuilder.toString:()Ljava/lang/String;
     198: invokevirtual #73                 // Method org/glassfish/hk2/utilities/reflection/Logger.debug:(Ljava/lang/String;)V
     201: aload         6
     203: aload         5
     205: monitorexit
     206: areturn
     207: aload         4
     209: getstatic     #76                 // Field org/glassfish/hk2/api/ServiceLocatorFactory$CreatePolicy.DESTROY:Lorg/glassfish/hk2/api/ServiceLocatorFactory$CreatePolicy;
     212: invokevirtual #74                 // Method org/glassfish/hk2/api/ServiceLocatorFactory$CreatePolicy.equals:(Ljava/lang/Object;)Z
     215: ifeq          227
     218: aload_0
     219: aload         6
     221: invokevirtual #77                 // Method destroy:(Lorg/glassfish/hk2/api/ServiceLocator;)V
     224: goto          259
     227: new           #78                 // class java/lang/IllegalStateException
     230: dup
     231: new           #41                 // class java/lang/StringBuilder
     234: dup
     235: invokespecial #42                 // Method java/lang/StringBuilder."<init>":()V
     238: ldc           #79                 // String A ServiceLocator named
     240: invokevirtual #44                 // Method java/lang/StringBuilder.append:(Ljava/lang/String;)Ljava/lang/StringBuilder;
     243: aload_1
     244: invokevirtual #44                 // Method java/lang/StringBuilder.append:(Ljava/lang/String;)Ljava/lang/StringBuilder;
     247: ldc           #80                 // String  already exists
     249: invokevirtual #44                 // Method java/lang/StringBuilder.append:(Ljava/lang/String;)Ljava/lang/StringBuilder;
     252: invokevirtual #48                 // Method java/lang/StringBuilder.toString:()Ljava/lang/String;
     255: invokespecial #81                 // Method java/lang/IllegalStateException."<init>":(Ljava/lang/String;)V
     258: athrow
     259: aload_0
     260: aload_1
     261: aload_2
     262: aload_3
     263: invokespecial #70                 // Method internalCreate:(Ljava/lang/String;Lorg/glassfish/hk2/api/ServiceLocator;Lorg/glassfish/hk2/extension/ServiceLocatorGenerator;)Lorg/glassfish/hk2/api/ServiceLocator;
     266: astore        6
     268: aload_0
     269: getfield      #13                 // Field serviceLocators:Ljava/util/HashMap;
     272: aload_1
     273: aload         6
     275: invokevirtual #82                 // Method java/util/HashMap.put:(Ljava/lang/Object;Ljava/lang/Object;)Ljava/lang/Object;
     278: pop
     279: aload_0
     280: aload         6
     282: invokespecial #71                 // Method callListenerAdded:(Lorg/glassfish/hk2/api/ServiceLocator;)V
     285: getstatic     #40                 // Field DEBUG_SERVICE_LOCATOR_LIFECYCLE:Z
     288: ifeq          317
     291: invokestatic  #28                 // Method org/glassfish/hk2/utilities/reflection/Logger.getLogger:()Lorg/glassfish/hk2/utilities/reflection/Logger;
     294: new           #41                 // class java/lang/StringBuilder
     297: dup
     298: invokespecial #42                 // Method java/lang/StringBuilder."<init>":()V
     301: ldc           #83                 // String ServiceFactoryImpl created locator
     303: invokevirtual #44                 // Method java/lang/StringBuilder.append:(Ljava/lang/String;)Ljava/lang/StringBuilder;
     306: aload         6
     308: invokevirtual #46                 // Method java/lang/StringBuilder.append:(Ljava/lang/Object;)Ljava/lang/StringBuilder;
     311: invokevirtual #48                 // Method java/lang/StringBuilder.toString:()Ljava/lang/String;
     314: invokevirtual #73                 // Method org/glassfish/hk2/utilities/reflection/Logger.debug:(Ljava/lang/String;)V
     317: aload         6
     319: aload         5
     321: monitorexit
     322: areturn
     323: astore        8
     325: aload         5
     327: monitorexit
     328: aload         8
     330: athrow
    Exception table:
       from    to  target type
          74   134   323   any
         135   206   323   any
         207   322   323   any
         323   328   323   any

  private org.glassfish.hk2.api.ServiceLocator internalCreate(java.lang.String, org.glassfish.hk2.api.ServiceLocator, org.glassfish.hk2.extension.ServiceLocatorGenerator);
    Code:
       0: aload_3
       1: ifnonnull     24
       4: invokestatic  #84                 // Method org/glassfish/hk2/internal/ServiceLocatorFactoryImpl$DefaultGeneratorInitializer.access$200:()Lorg/glassfish/hk2/extension/ServiceLocatorGenerator;
       7: ifnonnull     20
      10: new           #78                 // class java/lang/IllegalStateException
      13: dup
      14: ldc           #85                 // String No generator was provided and there is no default generator registered
      16: invokespecial #81                 // Method java/lang/IllegalStateException."<init>":(Ljava/lang/String;)V
      19: athrow
      20: invokestatic  #84                 // Method org/glassfish/hk2/internal/ServiceLocatorFactoryImpl$DefaultGeneratorInitializer.access$200:()Lorg/glassfish/hk2/extension/ServiceLocatorGenerator;
      23: astore_3
      24: aload_3
      25: aload_1
      26: aload_2
      27: invokeinterface #86,  3           // InterfaceMethod org/glassfish/hk2/extension/ServiceLocatorGenerator.create:(Ljava/lang/String;Lorg/glassfish/hk2/api/ServiceLocator;)Lorg/glassfish/hk2/api/ServiceLocator;
      32: areturn

  public void addListener(org.glassfish.hk2.api.ServiceLocatorListener);
    Code:
       0: aload_1
       1: ifnonnull     12
       4: new           #87                 // class java/lang/IllegalArgumentException
       7: dup
       8: invokespecial #88                 // Method java/lang/IllegalArgumentException."<init>":()V
      11: athrow
      12: aload_0
      13: getfield      #10                 // Field lock:Ljava/lang/Object;
      16: dup
      17: astore_2
      18: monitorenter
      19: aload_0
      20: getfield      #16                 // Field listeners:Ljava/util/HashSet;
      23: aload_1
      24: invokevirtual #89                 // Method java/util/HashSet.contains:(Ljava/lang/Object;)Z
      27: ifeq          33
      30: aload_2
      31: monitorexit
      32: return
      33: new           #14                 // class java/util/HashSet
      36: dup
      37: aload_0
      38: getfield      #13                 // Field serviceLocators:Ljava/util/HashMap;
      41: invokevirtual #90                 // Method java/util/HashMap.values:()Ljava/util/Collection;
      44: invokespecial #91                 // Method java/util/HashSet."<init>":(Ljava/util/Collection;)V
      47: astore_3
      48: aload_1
      49: aload_3
      50: invokestatic  #92                 // Method java/util/Collections.unmodifiableSet:(Ljava/util/Set;)Ljava/util/Set;
      53: invokeinterface #93,  2           // InterfaceMethod org/glassfish/hk2/api/ServiceLocatorListener.initialize:(Ljava/util/Set;)V
      58: goto          98
      61: astore_3
      62: invokestatic  #28                 // Method org/glassfish/hk2/utilities/reflection/Logger.getLogger:()Lorg/glassfish/hk2/utilities/reflection/Logger;
      65: aload_0
      66: invokevirtual #54                 // Method java/lang/Object.getClass:()Ljava/lang/Class;
      69: invokevirtual #55                 // Method java/lang/Class.getName:()Ljava/lang/String;
      72: new           #41                 // class java/lang/StringBuilder
      75: dup
      76: invokespecial #42                 // Method java/lang/StringBuilder."<init>":()V
      79: ldc           #94                 // String addListener
      81: invokevirtual #44                 // Method java/lang/StringBuilder.append:(Ljava/lang/String;)Ljava/lang/StringBuilder;
      84: aload_1
      85: invokevirtual #46                 // Method java/lang/StringBuilder.append:(Ljava/lang/Object;)Ljava/lang/StringBuilder;
      88: invokevirtual #48                 // Method java/lang/StringBuilder.toString:()Ljava/lang/String;
      91: aload_3
      92: invokevirtual #31                 // Method org/glassfish/hk2/utilities/reflection/Logger.debug:(Ljava/lang/String;Ljava/lang/String;Ljava/lang/Throwable;)V
      95: aload_2
      96: monitorexit
      97: return
      98: aload_0
      99: getfield      #16                 // Field listeners:Ljava/util/HashSet;
     102: aload_1
     103: invokevirtual #95                 // Method java/util/HashSet.add:(Ljava/lang/Object;)Z
     106: pop
     107: aload_2
     108: monitorexit
     109: goto          119
     112: astore        4
     114: aload_2
     115: monitorexit
     116: aload         4
     118: athrow
     119: return
    Exception table:
       from    to  target type
          33    58    61   Class java/lang/Throwable
          19    32   112   any
          33    97   112   any
          98   109   112   any
         112   116   112   any

  public void removeListener(org.glassfish.hk2.api.ServiceLocatorListener);
    Code:
       0: aload_1
       1: ifnonnull     12
       4: new           #87                 // class java/lang/IllegalArgumentException
       7: dup
       8: invokespecial #88                 // Method java/lang/IllegalArgumentException."<init>":()V
      11: athrow
      12: aload_0
      13: getfield      #10                 // Field lock:Ljava/lang/Object;
      16: dup
      17: astore_2
      18: monitorenter
      19: aload_0
      20: getfield      #16                 // Field listeners:Ljava/util/HashSet;
      23: aload_1
      24: invokevirtual #96                 // Method java/util/HashSet.remove:(Ljava/lang/Object;)Z
      27: pop
      28: aload_2
      29: monitorexit
      30: goto          38
      33: astore_3
      34: aload_2
      35: monitorexit
      36: aload_3
      37: athrow
      38: return
    Exception table:
       from    to  target type
          19    30    33   any
          33    36    33   any

  static org.glassfish.hk2.extension.ServiceLocatorGenerator access$000();
    Code:
       0: invokestatic  #2                  // Method getGeneratorSecure:()Lorg/glassfish/hk2/extension/ServiceLocatorGenerator;
       3: areturn

  static org.glassfish.hk2.extension.ServiceLocatorGenerator access$100();
    Code:
       0: invokestatic  #1                  // Method getGenerator:()Lorg/glassfish/hk2/extension/ServiceLocatorGenerator;
       3: areturn

  static {};
    Code:
       0: new           #97                 // class org/glassfish/hk2/internal/ServiceLocatorFactoryImpl$1
       3: dup
       4: invokespecial #98                 // Method org/glassfish/hk2/internal/ServiceLocatorFactoryImpl$1."<init>":()V
       7: invokestatic  #5                  // Method java/security/AccessController.doPrivileged:(Ljava/security/PrivilegedAction;)Ljava/lang/Object;
      10: checkcast     #99                 // class java/lang/Boolean
      13: invokevirtual #100                // Method java/lang/Boolean.booleanValue:()Z
      16: putstatic     #40                 // Field DEBUG_SERVICE_LOCATOR_LIFECYCLE:Z
      19: new           #8                  // class java/lang/Object
      22: dup
      23: invokespecial #9                  // Method java/lang/Object."<init>":()V
      26: putstatic     #59                 // Field sLock:Ljava/lang/Object;
      29: iconst_0
      30: putstatic     #61                 // Field name_count:I
      33: return
}
