Compiled from "IntConverter.java"
public class com.thoughtworks.xstream.converters.basic.IntConverter extends com.thoughtworks.xstream.converters.basic.AbstractSingleValueConverter {
  public com.thoughtworks.xstream.converters.basic.IntConverter();
    Code:
       0: aload_0
       1: invokespecial #1                  // Method com/thoughtworks/xstream/converters/basic/AbstractSingleValueConverter."<init>":()V
       4: return

  public boolean canConvert(java.lang.Class);
    Code:
       0: aload_1
       1: getstatic     #2                  // Field java/lang/Integer.TYPE:Ljava/lang/Class;
       4: invokevirtual #3                  // Method java/lang/Object.equals:(Ljava/lang/Object;)Z
       7: ifne          20
      10: aload_1
      11: ldc_w         #4                  // class java/lang/Integer
      14: invokevirtual #3                  // Method java/lang/Object.equals:(Ljava/lang/Object;)Z
      17: ifeq          24
      20: iconst_1
      21: goto          25
      24: iconst_0
      25: ireturn

  public java.lang.Object fromString(java.lang.String);
    Code:
       0: aload_1
       1: invokestatic  #5                  // Method java/lang/Long.decode:(Ljava/lang/String;)Ljava/lang/Long;
       4: invokevirtual #6                  // Method java/lang/Long.longValue:()J
       7: lstore_2
       8: lload_2
       9: ldc2_w        #7                  // long -2147483648l
      12: lcmp
      13: iflt          24
      16: lload_2
      17: ldc2_w        #9                  // long 4294967295l
      20: lcmp
      21: ifle          56
      24: new           #11                 // class java/lang/NumberFormatException
      27: dup
      28: new           #12                 // class java/lang/StringBuilder
      31: dup
      32: invokespecial #13                 // Method java/lang/StringBuilder."<init>":()V
      35: ldc           #14                 // String For input string: \"
      37: invokevirtual #15                 // Method java/lang/StringBuilder.append:(Ljava/lang/String;)Ljava/lang/StringBuilder;
      40: aload_1
      41: invokevirtual #15                 // Method java/lang/StringBuilder.append:(Ljava/lang/String;)Ljava/lang/StringBuilder;
      44: bipush        34
      46: invokevirtual #16                 // Method java/lang/StringBuilder.append:(C)Ljava/lang/StringBuilder;
      49: invokevirtual #17                 // Method java/lang/StringBuilder.toString:()Ljava/lang/String;
      52: invokespecial #18                 // Method java/lang/NumberFormatException."<init>":(Ljava/lang/String;)V
      55: athrow
      56: new           #4                  // class java/lang/Integer
      59: dup
      60: lload_2
      61: l2i
      62: invokespecial #19                 // Method java/lang/Integer."<init>":(I)V
      65: areturn
}
