Compiled from "AccordionBehavior.java"
final class org.wicketstuff.jwicket.ui.accordion.AccordionBehavior$EventType extends java.lang.Enum<org.wicketstuff.jwicket.ui.accordion.AccordionBehavior$EventType> implements java.io.Serializable {
  public static final org.wicketstuff.jwicket.ui.accordion.AccordionBehavior$EventType UNKNOWN;

  public static final org.wicketstuff.jwicket.ui.accordion.AccordionBehavior$EventType CHANGE;

  public static final org.wicketstuff.jwicket.ui.accordion.AccordionBehavior$EventType CHANGE_START;

  public static final java.lang.String IDENTIFIER;

  private final java.lang.String eventName;

  private static final org.wicketstuff.jwicket.ui.accordion.AccordionBehavior$EventType[] $VALUES;

  public static org.wicketstuff.jwicket.ui.accordion.AccordionBehavior$EventType[] values();
    Code:
       0: getstatic     #2                  // Field $VALUES:[Lorg/wicketstuff/jwicket/ui/accordion/AccordionBehavior$EventType;
       3: invokevirtual #3                  // Method "[Lorg/wicketstuff/jwicket/ui/accordion/AccordionBehavior$EventType;".clone:()Ljava/lang/Object;
       6: checkcast     #4                  // class "[Lorg/wicketstuff/jwicket/ui/accordion/AccordionBehavior$EventType;"
       9: areturn

  public static org.wicketstuff.jwicket.ui.accordion.AccordionBehavior$EventType valueOf(java.lang.String);
    Code:
       0: ldc_w         #5                  // class org/wicketstuff/jwicket/ui/accordion/AccordionBehavior$EventType
       3: aload_0
       4: invokestatic  #6                  // Method java/lang/Enum.valueOf:(Ljava/lang/Class;Ljava/lang/String;)Ljava/lang/Enum;
       7: checkcast     #5                  // class org/wicketstuff/jwicket/ui/accordion/AccordionBehavior$EventType
      10: areturn

  private org.wicketstuff.jwicket.ui.accordion.AccordionBehavior$EventType(java.lang.String);
    Code:
       0: aload_0
       1: aload_1
       2: iload_2
       3: invokespecial #7                  // Method java/lang/Enum."<init>":(Ljava/lang/String;I)V
       6: aload_0
       7: aload_3
       8: putfield      #1                  // Field eventName:Ljava/lang/String;
      11: return

  public java.lang.String getEventName();
    Code:
       0: aload_0
       1: getfield      #1                  // Field eventName:Ljava/lang/String;
       4: areturn

  public static org.wicketstuff.jwicket.ui.accordion.AccordionBehavior$EventType stringToType(java.lang.String);
    Code:
       0: invokestatic  #8                  // Method values:()[Lorg/wicketstuff/jwicket/ui/accordion/AccordionBehavior$EventType;
       3: astore_1
       4: aload_1
       5: arraylength
       6: istore_2
       7: iconst_0
       8: istore_3
       9: iload_3
      10: iload_2
      11: if_icmpge     40
      14: aload_1
      15: iload_3
      16: aaload
      17: astore        4
      19: aload         4
      21: invokevirtual #9                  // Method getEventName:()Ljava/lang/String;
      24: aload_0
      25: invokevirtual #10                 // Method java/lang/String.equals:(Ljava/lang/Object;)Z
      28: ifeq          34
      31: aload         4
      33: areturn
      34: iinc          3, 1
      37: goto          9
      40: getstatic     #11                 // Field UNKNOWN:Lorg/wicketstuff/jwicket/ui/accordion/AccordionBehavior$EventType;
      43: areturn

  public java.lang.String toString();
    Code:
       0: aload_0
       1: getfield      #1                  // Field eventName:Ljava/lang/String;
       4: areturn

  static java.lang.String access$000(org.wicketstuff.jwicket.ui.accordion.AccordionBehavior$EventType);
    Code:
       0: aload_0
       1: getfield      #1                  // Field eventName:Ljava/lang/String;
       4: areturn

  static {};
    Code:
       0: new           #5                  // class org/wicketstuff/jwicket/ui/accordion/AccordionBehavior$EventType
       3: dup
       4: ldc           #12                 // String UNKNOWN
       6: iconst_0
       7: ldc           #13                 // String *
       9: invokespecial #14                 // Method "<init>":(Ljava/lang/String;ILjava/lang/String;)V
      12: putstatic     #11                 // Field UNKNOWN:Lorg/wicketstuff/jwicket/ui/accordion/AccordionBehavior$EventType;
      15: new           #5                  // class org/wicketstuff/jwicket/ui/accordion/AccordionBehavior$EventType
      18: dup
      19: ldc           #15                 // String CHANGE
      21: iconst_1
      22: ldc           #16                 // String change
      24: invokespecial #14                 // Method "<init>":(Ljava/lang/String;ILjava/lang/String;)V
      27: putstatic     #17                 // Field CHANGE:Lorg/wicketstuff/jwicket/ui/accordion/AccordionBehavior$EventType;
      30: new           #5                  // class org/wicketstuff/jwicket/ui/accordion/AccordionBehavior$EventType
      33: dup
      34: ldc           #18                 // String CHANGE_START
      36: iconst_2
      37: ldc           #19                 // String changestart
      39: invokespecial #14                 // Method "<init>":(Ljava/lang/String;ILjava/lang/String;)V
      42: putstatic     #20                 // Field CHANGE_START:Lorg/wicketstuff/jwicket/ui/accordion/AccordionBehavior$EventType;
      45: iconst_3
      46: anewarray     #5                  // class org/wicketstuff/jwicket/ui/accordion/AccordionBehavior$EventType
      49: dup
      50: iconst_0
      51: getstatic     #11                 // Field UNKNOWN:Lorg/wicketstuff/jwicket/ui/accordion/AccordionBehavior$EventType;
      54: aastore
      55: dup
      56: iconst_1
      57: getstatic     #17                 // Field CHANGE:Lorg/wicketstuff/jwicket/ui/accordion/AccordionBehavior$EventType;
      60: aastore
      61: dup
      62: iconst_2
      63: getstatic     #20                 // Field CHANGE_START:Lorg/wicketstuff/jwicket/ui/accordion/AccordionBehavior$EventType;
      66: aastore
      67: putstatic     #2                  // Field $VALUES:[Lorg/wicketstuff/jwicket/ui/accordion/AccordionBehavior$EventType;
      70: return
}
