Compiled from "LazyAccordion.java"
class org.wicketstuff.jwicket.ui.accordion.LazyAccordion$ModelParkingLot extends org.apache.wicket.markup.html.WebMarkupContainer {
  private static final long serialVersionUID;

  final org.wicketstuff.jwicket.ui.accordion.LazyAccordion this$0;

  public org.wicketstuff.jwicket.ui.accordion.LazyAccordion$ModelParkingLot(java.lang.String, org.apache.wicket.model.IModel<T>);
    Code:
       0: aload_0
       1: aload_1
       2: putfield      #1                  // Field this$0:Lorg/wicketstuff/jwicket/ui/accordion/LazyAccordion;
       5: aload_0
       6: aload_2
       7: aload_3
       8: invokespecial #2                  // Method org/apache/wicket/markup/html/WebMarkupContainer."<init>":(Ljava/lang/String;Lorg/apache/wicket/model/IModel;)V
      11: return

  public org.apache.wicket.model.IModel<T> getModel();
    Code:
       0: aload_0
       1: invokevirtual #3                  // Method getDefaultModel:()Lorg/apache/wicket/model/IModel;
       4: areturn
}
