Compiled from "WriteTimeoutHandler.java"
public class org.jboss.netty.handler.timeout.WriteTimeoutHandler extends org.jboss.netty.channel.SimpleChannelDownstreamHandler implements org.jboss.netty.util.ExternalResourceReleasable {
  static final org.jboss.netty.handler.timeout.WriteTimeoutException EXCEPTION;

  private final org.jboss.netty.util.Timer timer;

  private final long timeoutMillis;

  public org.jboss.netty.handler.timeout.WriteTimeoutHandler(org.jboss.netty.util.Timer, int);
    Code:
       0: aload_0
       1: aload_1
       2: iload_2
       3: i2l
       4: getstatic     #1                  // Field java/util/concurrent/TimeUnit.SECONDS:Ljava/util/concurrent/TimeUnit;
       7: invokespecial #2                  // Method "<init>":(Lorg/jboss/netty/util/Timer;JLjava/util/concurrent/TimeUnit;)V
      10: return

  public org.jboss.netty.handler.timeout.WriteTimeoutHandler(org.jboss.netty.util.Timer, long, java.util.concurrent.TimeUnit);
    Code:
       0: aload_0
       1: invokespecial #3                  // Method org/jboss/netty/channel/SimpleChannelDownstreamHandler."<init>":()V
       4: aload_1
       5: ifnonnull     18
       8: new           #4                  // class java/lang/NullPointerException
      11: dup
      12: ldc           #5                  // String timer
      14: invokespecial #6                  // Method java/lang/NullPointerException."<init>":(Ljava/lang/String;)V
      17: athrow
      18: aload         4
      20: ifnonnull     33
      23: new           #4                  // class java/lang/NullPointerException
      26: dup
      27: ldc           #7                  // String unit
      29: invokespecial #6                  // Method java/lang/NullPointerException."<init>":(Ljava/lang/String;)V
      32: athrow
      33: aload_0
      34: aload_1
      35: putfield      #8                  // Field timer:Lorg/jboss/netty/util/Timer;
      38: lload_2
      39: lconst_0
      40: lcmp
      41: ifgt          52
      44: aload_0
      45: lconst_0
      46: putfield      #9                  // Field timeoutMillis:J
      49: goto          66
      52: aload_0
      53: aload         4
      55: lload_2
      56: invokevirtual #10                 // Method java/util/concurrent/TimeUnit.toMillis:(J)J
      59: lconst_1
      60: invokestatic  #11                 // Method java/lang/Math.max:(JJ)J
      63: putfield      #9                  // Field timeoutMillis:J
      66: return

  public void releaseExternalResources();
    Code:
       0: aload_0
       1: getfield      #8                  // Field timer:Lorg/jboss/netty/util/Timer;
       4: invokeinterface #12,  1           // InterfaceMethod org/jboss/netty/util/Timer.stop:()Ljava/util/Set;
       9: pop
      10: return

  protected long getTimeoutMillis(org.jboss.netty.channel.MessageEvent);
    Code:
       0: aload_0
       1: getfield      #9                  // Field timeoutMillis:J
       4: lreturn

  public void writeRequested(org.jboss.netty.channel.ChannelHandlerContext, org.jboss.netty.channel.MessageEvent) throws java.lang.Exception;
    Code:
       0: aload_0
       1: aload_2
       2: invokevirtual #13                 // Method getTimeoutMillis:(Lorg/jboss/netty/channel/MessageEvent;)J
       5: lstore_3
       6: lload_3
       7: lconst_0
       8: lcmp
       9: ifle          62
      12: aload_2
      13: invokeinterface #14,  1           // InterfaceMethod org/jboss/netty/channel/MessageEvent.getFuture:()Lorg/jboss/netty/channel/ChannelFuture;
      18: astore        5
      20: aload_0
      21: getfield      #8                  // Field timer:Lorg/jboss/netty/util/Timer;
      24: new           #15                 // class org/jboss/netty/handler/timeout/WriteTimeoutHandler$WriteTimeoutTask
      27: dup
      28: aload_0
      29: aload_1
      30: aload         5
      32: invokespecial #16                 // Method org/jboss/netty/handler/timeout/WriteTimeoutHandler$WriteTimeoutTask."<init>":(Lorg/jboss/netty/handler/timeout/WriteTimeoutHandler;Lorg/jboss/netty/channel/ChannelHandlerContext;Lorg/jboss/netty/channel/ChannelFuture;)V
      35: lload_3
      36: getstatic     #17                 // Field java/util/concurrent/TimeUnit.MILLISECONDS:Ljava/util/concurrent/TimeUnit;
      39: invokeinterface #18,  5           // InterfaceMethod org/jboss/netty/util/Timer.newTimeout:(Lorg/jboss/netty/util/TimerTask;JLjava/util/concurrent/TimeUnit;)Lorg/jboss/netty/util/Timeout;
      44: astore        6
      46: aload         5
      48: new           #19                 // class org/jboss/netty/handler/timeout/WriteTimeoutHandler$TimeoutCanceller
      51: dup
      52: aload         6
      54: invokespecial #20                 // Method org/jboss/netty/handler/timeout/WriteTimeoutHandler$TimeoutCanceller."<init>":(Lorg/jboss/netty/util/Timeout;)V
      57: invokeinterface #21,  2           // InterfaceMethod org/jboss/netty/channel/ChannelFuture.addListener:(Lorg/jboss/netty/channel/ChannelFutureListener;)V
      62: aload_0
      63: aload_1
      64: aload_2
      65: invokespecial #22                 // Method org/jboss/netty/channel/SimpleChannelDownstreamHandler.writeRequested:(Lorg/jboss/netty/channel/ChannelHandlerContext;Lorg/jboss/netty/channel/MessageEvent;)V
      68: return

  protected void writeTimedOut(org.jboss.netty.channel.ChannelHandlerContext) throws java.lang.Exception;
    Code:
       0: aload_1
       1: getstatic     #23                 // Field EXCEPTION:Lorg/jboss/netty/handler/timeout/WriteTimeoutException;
       4: invokestatic  #24                 // Method org/jboss/netty/channel/Channels.fireExceptionCaught:(Lorg/jboss/netty/channel/ChannelHandlerContext;Ljava/lang/Throwable;)V
       7: return

  static {};
    Code:
       0: new           #25                 // class org/jboss/netty/handler/timeout/WriteTimeoutException
       3: dup
       4: invokespecial #26                 // Method org/jboss/netty/handler/timeout/WriteTimeoutException."<init>":()V
       7: putstatic     #23                 // Field EXCEPTION:Lorg/jboss/netty/handler/timeout/WriteTimeoutException;
      10: return
}
