Compiled from "$AutoValue_DatabaseStats_DataFileVersion.java"
abstract class org.graylog2.system.stats.mongo.$AutoValue_DatabaseStats_DataFileVersion extends org.graylog2.system.stats.mongo.DatabaseStats$DataFileVersion {
  private final int major;

  private final int minor;

  org.graylog2.system.stats.mongo.$AutoValue_DatabaseStats_DataFileVersion(int, int);
    Code:
       0: aload_0
       1: invokespecial #1                  // Method org/graylog2/system/stats/mongo/DatabaseStats$DataFileVersion."<init>":()V
       4: aload_0
       5: iload_1
       6: putfield      #2                  // Field major:I
       9: aload_0
      10: iload_2
      11: putfield      #3                  // Field minor:I
      14: return

  public int major();
    Code:
       0: aload_0
       1: getfield      #2                  // Field major:I
       4: ireturn

  public int minor();
    Code:
       0: aload_0
       1: getfield      #3                  // Field minor:I
       4: ireturn

  public java.lang.String toString();
    Code:
       0: new           #4                  // class java/lang/StringBuilder
       3: dup
       4: invokespecial #5                  // Method java/lang/StringBuilder."<init>":()V
       7: ldc           #6                  // String DataFileVersion{major=
       9: invokevirtual #7                  // Method java/lang/StringBuilder.append:(Ljava/lang/String;)Ljava/lang/StringBuilder;
      12: aload_0
      13: getfield      #2                  // Field major:I
      16: invokevirtual #8                  // Method java/lang/StringBuilder.append:(I)Ljava/lang/StringBuilder;
      19: ldc           #9                  // String , minor=
      21: invokevirtual #7                  // Method java/lang/StringBuilder.append:(Ljava/lang/String;)Ljava/lang/StringBuilder;
      24: aload_0
      25: getfield      #3                  // Field minor:I
      28: invokevirtual #8                  // Method java/lang/StringBuilder.append:(I)Ljava/lang/StringBuilder;
      31: ldc           #10                 // String }
      33: invokevirtual #7                  // Method java/lang/StringBuilder.append:(Ljava/lang/String;)Ljava/lang/StringBuilder;
      36: invokevirtual #11                 // Method java/lang/StringBuilder.toString:()Ljava/lang/String;
      39: areturn

  public boolean equals(java.lang.Object);
    Code:
       0: aload_1
       1: aload_0
       2: if_acmpne     7
       5: iconst_1
       6: ireturn
       7: aload_1
       8: instanceof    #12                 // class org/graylog2/system/stats/mongo/DatabaseStats$DataFileVersion
      11: ifeq          47
      14: aload_1
      15: checkcast     #12                 // class org/graylog2/system/stats/mongo/DatabaseStats$DataFileVersion
      18: astore_2
      19: aload_0
      20: getfield      #2                  // Field major:I
      23: aload_2
      24: invokevirtual #13                 // Method org/graylog2/system/stats/mongo/DatabaseStats$DataFileVersion.major:()I
      27: if_icmpne     45
      30: aload_0
      31: getfield      #3                  // Field minor:I
      34: aload_2
      35: invokevirtual #14                 // Method org/graylog2/system/stats/mongo/DatabaseStats$DataFileVersion.minor:()I
      38: if_icmpne     45
      41: iconst_1
      42: goto          46
      45: iconst_0
      46: ireturn
      47: iconst_0
      48: ireturn

  public int hashCode();
    Code:
       0: iconst_1
       1: istore_1
       2: iload_1
       3: ldc           #15                 // int 1000003
       5: imul
       6: istore_1
       7: iload_1
       8: aload_0
       9: getfield      #2                  // Field major:I
      12: ixor
      13: istore_1
      14: iload_1
      15: ldc           #15                 // int 1000003
      17: imul
      18: istore_1
      19: iload_1
      20: aload_0
      21: getfield      #3                  // Field minor:I
      24: ixor
      25: istore_1
      26: iload_1
      27: ireturn
}
