Compiled from "AutoValue_DatabaseStats_ExtentFreeList.java"
final class org.graylog2.system.stats.mongo.AutoValue_DatabaseStats_ExtentFreeList extends org.graylog2.system.stats.mongo.$AutoValue_DatabaseStats_ExtentFreeList {
  org.graylog2.system.stats.mongo.AutoValue_DatabaseStats_ExtentFreeList(int, int);
    Code:
       0: aload_0
       1: iload_1
       2: iload_2
       3: invokespecial #1                  // Method org/graylog2/system/stats/mongo/$AutoValue_DatabaseStats_ExtentFreeList."<init>":(II)V
       6: return

  public final int getNum();
    Code:
       0: aload_0
       1: invokevirtual #2                  // Method num:()I
       4: ireturn

  public final int getTotalSize();
    Code:
       0: aload_0
       1: invokevirtual #3                  // Method totalSize:()I
       4: ireturn
}
