Compiled from "MessageBodyFactory.java"
final class org.glassfish.jersey.message.internal.MessageBodyFactory$2 implements java.util.Comparator<org.glassfish.jersey.message.AbstractEntityProviderModel<?>> {
  org.glassfish.jersey.message.internal.MessageBodyFactory$2();
    Code:
       0: aload_0
       1: invokespecial #1                  // Method java/lang/Object."<init>":()V
       4: return

  public int compare(org.glassfish.jersey.message.AbstractEntityProviderModel<?>, org.glassfish.jersey.message.AbstractEntityProviderModel<?>);
    Code:
       0: aload_1
       1: invokevirtual #2                  // Method org/glassfish/jersey/message/AbstractEntityProviderModel.providedType:()Ljava/lang/Class;
       4: astore_3
       5: aload_2
       6: invokevirtual #2                  // Method org/glassfish/jersey/message/AbstractEntityProviderModel.providedType:()Ljava/lang/Class;
       9: astore        4
      11: aload_3
      12: aload         4
      14: if_acmpne     30
      17: aload_0
      18: aload_2
      19: invokevirtual #3                  // Method org/glassfish/jersey/message/AbstractEntityProviderModel.declaredTypes:()Ljava/util/List;
      22: aload_1
      23: invokevirtual #3                  // Method org/glassfish/jersey/message/AbstractEntityProviderModel.declaredTypes:()Ljava/util/List;
      26: invokespecial #4                  // Method compare:(Ljava/util/List;Ljava/util/List;)I
      29: ireturn
      30: aload_3
      31: aload         4
      33: invokevirtual #5                  // Method java/lang/Class.isAssignableFrom:(Ljava/lang/Class;)Z
      36: ifeq          41
      39: iconst_1
      40: ireturn
      41: aload         4
      43: aload_3
      44: invokevirtual #5                  // Method java/lang/Class.isAssignableFrom:(Ljava/lang/Class;)Z
      47: ifeq          52
      50: iconst_m1
      51: ireturn
      52: invokestatic  #6                  // Method org/glassfish/jersey/message/internal/MessageBodyFactory.access$000:()Ljava/util/Comparator;
      55: aload_3
      56: aload         4
      58: invokeinterface #7,  3            // InterfaceMethod java/util/Comparator.compare:(Ljava/lang/Object;Ljava/lang/Object;)I
      63: ireturn

  private int compare(java.util.List<javax.ws.rs.core.MediaType>, java.util.List<javax.ws.rs.core.MediaType>);
    Code:
       0: aload_1
       1: invokeinterface #8,  1            // InterfaceMethod java/util/List.isEmpty:()Z
       6: ifeq          15
       9: getstatic     #9                  // Field org/glassfish/jersey/message/internal/MediaTypes.WILDCARD_TYPE_SINGLETON_LIST:Ljava/util/List;
      12: goto          16
      15: aload_1
      16: astore_1
      17: aload_2
      18: invokeinterface #8,  1            // InterfaceMethod java/util/List.isEmpty:()Z
      23: ifeq          32
      26: getstatic     #9                  // Field org/glassfish/jersey/message/internal/MediaTypes.WILDCARD_TYPE_SINGLETON_LIST:Ljava/util/List;
      29: goto          33
      32: aload_2
      33: astore_2
      34: getstatic     #10                 // Field org/glassfish/jersey/message/internal/MediaTypes.MEDIA_TYPE_LIST_COMPARATOR:Ljava/util/Comparator;
      37: aload_2
      38: aload_1
      39: invokeinterface #7,  3            // InterfaceMethod java/util/Comparator.compare:(Ljava/lang/Object;Ljava/lang/Object;)I
      44: ireturn

  public int compare(java.lang.Object, java.lang.Object);
    Code:
       0: aload_0
       1: aload_1
       2: checkcast     #11                 // class org/glassfish/jersey/message/AbstractEntityProviderModel
       5: aload_2
       6: checkcast     #11                 // class org/glassfish/jersey/message/AbstractEntityProviderModel
       9: invokevirtual #12                 // Method compare:(Lorg/glassfish/jersey/message/AbstractEntityProviderModel;Lorg/glassfish/jersey/message/AbstractEntityProviderModel;)I
      12: ireturn
}
