Compiled from "Utils.java"
final class org.glassfish.jersey.message.internal.Utils$1 implements java.security.PrivilegedAction<java.io.File> {
  final java.util.concurrent.atomic.AtomicReference val$exceptionReference;

  org.glassfish.jersey.message.internal.Utils$1(java.util.concurrent.atomic.AtomicReference);
    Code:
       0: aload_0
       1: aload_1
       2: putfield      #1                  // Field val$exceptionReference:Ljava/util/concurrent/atomic/AtomicReference;
       5: aload_0
       6: invokespecial #2                  // Method java/lang/Object."<init>":()V
       9: return

  public java.io.File run();
    Code:
       0: aconst_null
       1: astore_1
       2: ldc           #3                  // String rep
       4: ldc           #4                  // String tmp
       6: iconst_0
       7: anewarray     #5                  // class java/nio/file/attribute/FileAttribute
      10: invokestatic  #6                  // Method java/nio/file/Files.createTempFile:(Ljava/lang/String;Ljava/lang/String;[Ljava/nio/file/attribute/FileAttribute;)Ljava/nio/file/Path;
      13: invokeinterface #7,  1            // InterfaceMethod java/nio/file/Path.toFile:()Ljava/io/File;
      18: astore_1
      19: aload_1
      20: invokevirtual #8                  // Method java/io/File.deleteOnExit:()V
      23: goto          35
      26: astore_2
      27: aload_0
      28: getfield      #1                  // Field val$exceptionReference:Ljava/util/concurrent/atomic/AtomicReference;
      31: aload_2
      32: invokevirtual #10                 // Method java/util/concurrent/atomic/AtomicReference.set:(Ljava/lang/Object;)V
      35: aload_1
      36: areturn
    Exception table:
       from    to  target type
           2    23    26   Class java/io/IOException

  public java.lang.Object run();
    Code:
       0: aload_0
       1: invokevirtual #11                 // Method run:()Ljava/io/File;
       4: areturn
}
