Compiled from "ExtendedRiverMarshaller.java"
public class org.infinispan.commons.marshall.jboss.ExtendedRiverMarshaller extends org.jboss.marshalling.river.RiverMarshaller {
  private org.infinispan.commons.marshall.jboss.RiverCloseListener listener;

  public org.infinispan.commons.marshall.jboss.ExtendedRiverMarshaller(org.jboss.marshalling.river.RiverMarshallerFactory, org.jboss.marshalling.reflect.SerializableClassRegistry, org.jboss.marshalling.MarshallingConfiguration) throws java.io.IOException;
    Code:
       0: aload_0
       1: aload_1
       2: aload_2
       3: aload_3
       4: invokespecial #1                  // Method org/jboss/marshalling/river/RiverMarshaller."<init>":(Lorg/jboss/marshalling/river/RiverMarshallerFactory;Lorg/jboss/marshalling/reflect/SerializableClassRegistry;Lorg/jboss/marshalling/MarshallingConfiguration;)V
       7: return

  public void finish() throws java.io.IOException;
    Code:
       0: aload_0
       1: invokespecial #2                  // Method org/jboss/marshalling/river/RiverMarshaller.finish:()V
       4: aload_0
       5: getfield      #3                  // Field listener:Lorg/infinispan/commons/marshall/jboss/RiverCloseListener;
       8: ifnull        20
      11: aload_0
      12: getfield      #3                  // Field listener:Lorg/infinispan/commons/marshall/jboss/RiverCloseListener;
      15: invokeinterface #4,  1            // InterfaceMethod org/infinispan/commons/marshall/jboss/RiverCloseListener.closeMarshaller:()V
      20: return

  void setCloseListener(org.infinispan.commons.marshall.jboss.RiverCloseListener);
    Code:
       0: aload_0
       1: aload_1
       2: putfield      #3                  // Field listener:Lorg/infinispan/commons/marshall/jboss/RiverCloseListener;
       5: return
}
