Compiled from "PrometheusMetricsExportAutoConfiguration.java"
public class org.springframework.boot.actuate.autoconfigure.metrics.export.prometheus.PrometheusMetricsExportAutoConfiguration {
  public org.springframework.boot.actuate.autoconfigure.metrics.export.prometheus.PrometheusMetricsExportAutoConfiguration();
    Code:
       0: aload_0
       1: invokespecial #1                  // Method java/lang/Object."<init>":()V
       4: return

  public io.micrometer.prometheus.PrometheusConfig prometheusConfig(org.springframework.boot.actuate.autoconfigure.metrics.export.prometheus.PrometheusProperties);
    Code:
       0: new           #2                  // class org/springframework/boot/actuate/autoconfigure/metrics/export/prometheus/PrometheusPropertiesConfigAdapter
       3: dup
       4: aload_1
       5: invokespecial #3                  // Method org/springframework/boot/actuate/autoconfigure/metrics/export/prometheus/PrometheusPropertiesConfigAdapter."<init>":(Lorg/springframework/boot/actuate/autoconfigure/metrics/export/prometheus/PrometheusProperties;)V
       8: areturn

  public io.micrometer.prometheus.PrometheusMeterRegistry prometheusMeterRegistry(io.micrometer.prometheus.PrometheusConfig, io.prometheus.client.CollectorRegistry, io.micrometer.core.instrument.Clock);
    Code:
       0: new           #4                  // class io/micrometer/prometheus/PrometheusMeterRegistry
       3: dup
       4: aload_1
       5: aload_2
       6: aload_3
       7: invokespecial #5                  // Method io/micrometer/prometheus/PrometheusMeterRegistry."<init>":(Lio/micrometer/prometheus/PrometheusConfig;Lio/prometheus/client/CollectorRegistry;Lio/micrometer/core/instrument/Clock;)V
      10: areturn

  public io.prometheus.client.CollectorRegistry collectorRegistry();
    Code:
       0: new           #6                  // class io/prometheus/client/CollectorRegistry
       3: dup
       4: iconst_1
       5: invokespecial #7                  // Method io/prometheus/client/CollectorRegistry."<init>":(Z)V
       8: areturn
}
