Compiled from "JCacheCache.java"
public class org.springframework.cache.jcache.JCacheCache extends org.springframework.cache.support.AbstractValueAdaptingCache {
  private final javax.cache.Cache<java.lang.Object, java.lang.Object> cache;

  public org.springframework.cache.jcache.JCacheCache(javax.cache.Cache<java.lang.Object, java.lang.Object>);
    Code:
       0: aload_0
       1: aload_1
       2: iconst_1
       3: invokespecial #3                  // Method "<init>":(Ljavax/cache/Cache;Z)V
       6: return

  public org.springframework.cache.jcache.JCacheCache(javax.cache.Cache<java.lang.Object, java.lang.Object>, boolean);
    Code:
       0: aload_0
       1: iload_2
       2: invokespecial #4                  // Method org/springframework/cache/support/AbstractValueAdaptingCache."<init>":(Z)V
       5: aload_1
       6: ldc           #5                  // String Cache must not be null
       8: invokestatic  #6                  // Method org/springframework/util/Assert.notNull:(Ljava/lang/Object;Ljava/lang/String;)V
      11: aload_0
      12: aload_1
      13: putfield      #7                  // Field cache:Ljavax/cache/Cache;
      16: return

  public final java.lang.String getName();
    Code:
       0: aload_0
       1: getfield      #7                  // Field cache:Ljavax/cache/Cache;
       4: invokeinterface #8,  1            // InterfaceMethod javax/cache/Cache.getName:()Ljava/lang/String;
       9: areturn

  public final javax.cache.Cache<java.lang.Object, java.lang.Object> getNativeCache();
    Code:
       0: aload_0
       1: getfield      #7                  // Field cache:Ljavax/cache/Cache;
       4: areturn

  protected java.lang.Object lookup(java.lang.Object);
    Code:
       0: aload_0
       1: getfield      #7                  // Field cache:Ljavax/cache/Cache;
       4: aload_1
       5: invokeinterface #9,  2            // InterfaceMethod javax/cache/Cache.get:(Ljava/lang/Object;)Ljava/lang/Object;
      10: areturn

  public <T> T get(java.lang.Object, java.util.concurrent.Callable<T>);
    Code:
       0: aload_0
       1: getfield      #7                  // Field cache:Ljavax/cache/Cache;
       4: aload_1
       5: new           #10                 // class org/springframework/cache/jcache/JCacheCache$ValueLoaderEntryProcessor
       8: dup
       9: aload_0
      10: aconst_null
      11: invokespecial #11                 // Method org/springframework/cache/jcache/JCacheCache$ValueLoaderEntryProcessor."<init>":(Lorg/springframework/cache/jcache/JCacheCache;Lorg/springframework/cache/jcache/JCacheCache$1;)V
      14: iconst_1
      15: anewarray     #12                 // class java/lang/Object
      18: dup
      19: iconst_0
      20: aload_2
      21: aastore
      22: invokeinterface #13,  4           // InterfaceMethod javax/cache/Cache.invoke:(Ljava/lang/Object;Ljavax/cache/processor/EntryProcessor;[Ljava/lang/Object;)Ljava/lang/Object;
      27: areturn
      28: astore_3
      29: new           #15                 // class org/springframework/cache/Cache$ValueRetrievalException
      32: dup
      33: aload_1
      34: aload_2
      35: aload_3
      36: invokevirtual #16                 // Method javax/cache/processor/EntryProcessorException.getCause:()Ljava/lang/Throwable;
      39: invokespecial #17                 // Method org/springframework/cache/Cache$ValueRetrievalException."<init>":(Ljava/lang/Object;Ljava/util/concurrent/Callable;Ljava/lang/Throwable;)V
      42: athrow
    Exception table:
       from    to  target type
           0    27    28   Class javax/cache/processor/EntryProcessorException

  public void put(java.lang.Object, java.lang.Object);
    Code:
       0: aload_0
       1: getfield      #7                  // Field cache:Ljavax/cache/Cache;
       4: aload_1
       5: aload_0
       6: aload_2
       7: invokevirtual #1                  // Method toStoreValue:(Ljava/lang/Object;)Ljava/lang/Object;
      10: invokeinterface #18,  3           // InterfaceMethod javax/cache/Cache.put:(Ljava/lang/Object;Ljava/lang/Object;)V
      15: return

  public org.springframework.cache.Cache$ValueWrapper putIfAbsent(java.lang.Object, java.lang.Object);
    Code:
       0: aload_0
       1: getfield      #7                  // Field cache:Ljavax/cache/Cache;
       4: aload_1
       5: aload_0
       6: aload_2
       7: invokevirtual #1                  // Method toStoreValue:(Ljava/lang/Object;)Ljava/lang/Object;
      10: invokeinterface #19,  3           // InterfaceMethod javax/cache/Cache.putIfAbsent:(Ljava/lang/Object;Ljava/lang/Object;)Z
      15: istore_3
      16: iload_3
      17: ifeq          24
      20: aconst_null
      21: goto          29
      24: aload_0
      25: aload_1
      26: invokevirtual #20                 // Method get:(Ljava/lang/Object;)Lorg/springframework/cache/Cache$ValueWrapper;
      29: areturn

  public void evict(java.lang.Object);
    Code:
       0: aload_0
       1: getfield      #7                  // Field cache:Ljavax/cache/Cache;
       4: aload_1
       5: invokeinterface #21,  2           // InterfaceMethod javax/cache/Cache.remove:(Ljava/lang/Object;)Z
      10: pop
      11: return

  public void clear();
    Code:
       0: aload_0
       1: getfield      #7                  // Field cache:Ljavax/cache/Cache;
       4: invokeinterface #22,  1           // InterfaceMethod javax/cache/Cache.removeAll:()V
       9: return

  public java.lang.Object getNativeCache();
    Code:
       0: aload_0
       1: invokevirtual #23                 // Method getNativeCache:()Ljavax/cache/Cache;
       4: areturn

  static java.lang.Object access$100(org.springframework.cache.jcache.JCacheCache, java.lang.Object);
    Code:
       0: aload_0
       1: aload_1
       2: invokevirtual #2                  // Method fromStoreValue:(Ljava/lang/Object;)Ljava/lang/Object;
       5: areturn

  static java.lang.Object access$200(org.springframework.cache.jcache.JCacheCache, java.lang.Object);
    Code:
       0: aload_0
       1: aload_1
       2: invokevirtual #1                  // Method toStoreValue:(Ljava/lang/Object;)Ljava/lang/Object;
       5: areturn
}
