Compiled from "SignatureData.java"
public class de.uni_koblenz.aggrimm.icp.crypto.sign.graph.SignatureData {
  private java.math.BigInteger hash;

  private java.lang.String signature;

  private java.security.MessageDigest digestGen;

  private java.lang.String canonicalizationMethod;

  private java.lang.String graphDigestMethod;

  private java.lang.String serializationMethod;

  private java.lang.String signatureMethod;

  private java.lang.String verificationCertificate;

  public de.uni_koblenz.aggrimm.icp.crypto.sign.graph.SignatureData();
    Code:
       0: aload_0
       1: invokespecial #1                  // Method java/lang/Object."<init>":()V
       4: return

  public java.math.BigInteger getHash();
    Code:
       0: aload_0
       1: getfield      #2                  // Field hash:Ljava/math/BigInteger;
       4: areturn

  public void setHash(java.math.BigInteger);
    Code:
       0: aload_0
       1: aload_1
       2: putfield      #2                  // Field hash:Ljava/math/BigInteger;
       5: return

  public java.lang.String getSignature();
    Code:
       0: aload_0
       1: getfield      #3                  // Field signature:Ljava/lang/String;
       4: areturn

  public void setSignature(java.lang.String);
    Code:
       0: aload_0
       1: aload_1
       2: putfield      #3                  // Field signature:Ljava/lang/String;
       5: return

  public java.security.MessageDigest getDigestGen();
    Code:
       0: aload_0
       1: getfield      #4                  // Field digestGen:Ljava/security/MessageDigest;
       4: areturn

  public void setDigestGen(java.security.MessageDigest);
    Code:
       0: aload_0
       1: aload_1
       2: putfield      #4                  // Field digestGen:Ljava/security/MessageDigest;
       5: return

  public java.lang.String getCanonicalizationMethod();
    Code:
       0: aload_0
       1: getfield      #5                  // Field canonicalizationMethod:Ljava/lang/String;
       4: areturn

  public void setCanonicalizationMethod(java.lang.String);
    Code:
       0: aload_0
       1: aload_1
       2: putfield      #5                  // Field canonicalizationMethod:Ljava/lang/String;
       5: return

  public java.lang.String getGraphDigestMethod();
    Code:
       0: aload_0
       1: getfield      #6                  // Field graphDigestMethod:Ljava/lang/String;
       4: areturn

  public void setGraphDigestMethod(java.lang.String);
    Code:
       0: aload_0
       1: aload_1
       2: putfield      #6                  // Field graphDigestMethod:Ljava/lang/String;
       5: return

  public java.lang.String getSerializationMethod();
    Code:
       0: aload_0
       1: getfield      #7                  // Field serializationMethod:Ljava/lang/String;
       4: areturn

  public void setSerializationMethod(java.lang.String);
    Code:
       0: aload_0
       1: aload_1
       2: putfield      #7                  // Field serializationMethod:Ljava/lang/String;
       5: return

  public java.lang.String getSignatureMethod();
    Code:
       0: aload_0
       1: getfield      #8                  // Field signatureMethod:Ljava/lang/String;
       4: areturn

  public void setSignatureMethod(java.lang.String);
    Code:
       0: aload_0
       1: aload_1
       2: putfield      #8                  // Field signatureMethod:Ljava/lang/String;
       5: return

  public java.lang.String getVerificationCertificate();
    Code:
       0: aload_0
       1: getfield      #9                  // Field verificationCertificate:Ljava/lang/String;
       4: areturn

  public void setVerificationCertificate(java.lang.String);
    Code:
       0: aload_0
       1: aload_1
       2: putfield      #9                  // Field verificationCertificate:Ljava/lang/String;
       5: return
}
