Compiled from "ByteString.scala"
public final class akka.util.ByteString$Companion$$anonfun$2 extends scala.runtime.AbstractFunction1<java.lang.Object, scala.runtime.Nothing$> implements scala.Serializable {
  public static final long serialVersionUID;

  public final scala.runtime.Nothing$ apply(byte);
    Code:
       0: new           #18                 // class java/lang/IllegalArgumentException
       3: dup
       4: new           #20                 // class scala/collection/mutable/StringBuilder
       7: dup
       8: invokespecial #24                 // Method scala/collection/mutable/StringBuilder."<init>":()V
      11: ldc           #26                 // String Invalid serialization id
      13: invokevirtual #30                 // Method scala/collection/mutable/StringBuilder.append:(Ljava/lang/Object;)Lscala/collection/mutable/StringBuilder;
      16: iload_1
      17: invokestatic  #36                 // Method scala/runtime/BoxesRunTime.boxToByte:(B)Ljava/lang/Byte;
      20: invokevirtual #30                 // Method scala/collection/mutable/StringBuilder.append:(Ljava/lang/Object;)Lscala/collection/mutable/StringBuilder;
      23: invokevirtual #40                 // Method scala/collection/mutable/StringBuilder.toString:()Ljava/lang/String;
      26: invokespecial #43                 // Method java/lang/IllegalArgumentException."<init>":(Ljava/lang/String;)V
      29: athrow

  public final java.lang.Object apply(java.lang.Object);
    Code:
       0: aload_0
       1: aload_1
       2: invokestatic  #52                 // Method scala/runtime/BoxesRunTime.unboxToByte:(Ljava/lang/Object;)B
       5: invokevirtual #54                 // Method apply:(B)Lscala/runtime/Nothing$;
       8: athrow

  public akka.util.ByteString$Companion$$anonfun$2();
    Code:
       0: aload_0
       1: invokespecial #57                 // Method scala/runtime/AbstractFunction1."<init>":()V
       4: return
}
