Compiled from "ByteString.scala"
public abstract class akka.util.ByteString implements scala.collection.immutable.IndexedSeq<java.lang.Object>, scala.collection.IndexedSeqOptimized<java.lang.Object, akka.util.ByteString> {
  public static akka.util.ByteString fromInts(int...);
    Code:
       0: getstatic     #21                 // Field akka/util/ByteString$.MODULE$:Lakka/util/ByteString$;
       3: aload_0
       4: invokevirtual #23                 // Method akka/util/ByteString$.fromInts:([I)Lakka/util/ByteString;
       7: areturn

  public static scala.collection.generic.CanBuildFrom<scala.collection.TraversableOnce<java.lang.Object>, java.lang.Object, akka.util.ByteString> canBuildFrom();
    Code:
       0: getstatic     #21                 // Field akka/util/ByteString$.MODULE$:Lakka/util/ByteString$;
       3: invokevirtual #27                 // Method akka/util/ByteString$.canBuildFrom:()Lscala/collection/generic/CanBuildFrom;
       6: areturn

  public static akka.util.ByteStringBuilder createBuilder();
    Code:
       0: getstatic     #21                 // Field akka/util/ByteString$.MODULE$:Lakka/util/ByteString$;
       3: invokevirtual #31                 // Method akka/util/ByteString$.createBuilder:()Lakka/util/ByteStringBuilder;
       6: areturn

  public static akka.util.ByteString empty();
    Code:
       0: getstatic     #21                 // Field akka/util/ByteString$.MODULE$:Lakka/util/ByteString$;
       3: invokevirtual #35                 // Method akka/util/ByteString$.empty:()Lakka/util/ByteString;
       6: areturn

  public static akka.util.ByteString fromByteBuffer(java.nio.ByteBuffer);
    Code:
       0: getstatic     #21                 // Field akka/util/ByteString$.MODULE$:Lakka/util/ByteString$;
       3: aload_0
       4: invokevirtual #39                 // Method akka/util/ByteString$.fromByteBuffer:(Ljava/nio/ByteBuffer;)Lakka/util/ByteString;
       7: areturn

  public static java.lang.String UTF_8();
    Code:
       0: getstatic     #21                 // Field akka/util/ByteString$.MODULE$:Lakka/util/ByteString$;
       3: invokevirtual #43                 // Method akka/util/ByteString$.UTF_8:()Ljava/lang/String;
       6: areturn

  public static akka.util.ByteString fromString(java.lang.String, java.lang.String);
    Code:
       0: getstatic     #21                 // Field akka/util/ByteString$.MODULE$:Lakka/util/ByteString$;
       3: aload_0
       4: aload_1
       5: invokevirtual #47                 // Method akka/util/ByteString$.fromString:(Ljava/lang/String;Ljava/lang/String;)Lakka/util/ByteString;
       8: areturn

  public static akka.util.ByteString fromString(java.lang.String);
    Code:
       0: getstatic     #21                 // Field akka/util/ByteString$.MODULE$:Lakka/util/ByteString$;
       3: aload_0
       4: invokevirtual #50                 // Method akka/util/ByteString$.fromString:(Ljava/lang/String;)Lakka/util/ByteString;
       7: areturn

  public static akka.util.ByteString fromInts(scala.collection.Seq<java.lang.Object>);
    Code:
       0: getstatic     #21                 // Field akka/util/ByteString$.MODULE$:Lakka/util/ByteString$;
       3: aload_0
       4: invokevirtual #53                 // Method akka/util/ByteString$.fromInts:(Lscala/collection/Seq;)Lakka/util/ByteString;
       7: areturn

  public static akka.util.ByteString fromArray(byte[], int, int);
    Code:
       0: getstatic     #21                 // Field akka/util/ByteString$.MODULE$:Lakka/util/ByteString$;
       3: aload_0
       4: iload_1
       5: iload_2
       6: invokevirtual #57                 // Method akka/util/ByteString$.fromArray:([BII)Lakka/util/ByteString;
       9: areturn

  public static akka.util.ByteString fromArray(byte[]);
    Code:
       0: getstatic     #21                 // Field akka/util/ByteString$.MODULE$:Lakka/util/ByteString$;
       3: aload_0
       4: invokevirtual #60                 // Method akka/util/ByteString$.fromArray:([B)Lakka/util/ByteString;
       7: areturn

  public java.lang.Object scala$collection$IndexedSeqOptimized$$super$reduceLeft(scala.Function2);
    Code:
       0: aload_0
       1: aload_1
       2: invokestatic  #68                 // Method scala/collection/TraversableOnce$class.reduceLeft:(Lscala/collection/TraversableOnce;Lscala/Function2;)Ljava/lang/Object;
       5: areturn

  public java.lang.Object scala$collection$IndexedSeqOptimized$$super$reduceRight(scala.Function2);
    Code:
       0: aload_0
       1: aload_1
       2: invokestatic  #79                 // Method scala/collection/IterableLike$class.reduceRight:(Lscala/collection/IterableLike;Lscala/Function2;)Ljava/lang/Object;
       5: areturn

  public java.lang.Object scala$collection$IndexedSeqOptimized$$super$zip(scala.collection.GenIterable, scala.collection.generic.CanBuildFrom);
    Code:
       0: aload_0
       1: aload_1
       2: aload_2
       3: invokestatic  #85                 // Method scala/collection/IterableLike$class.zip:(Lscala/collection/IterableLike;Lscala/collection/GenIterable;Lscala/collection/generic/CanBuildFrom;)Ljava/lang/Object;
       6: areturn

  public java.lang.Object scala$collection$IndexedSeqOptimized$$super$head();
    Code:
       0: aload_0
       1: invokestatic  #95                 // Method scala/collection/IterableLike$class.head:(Lscala/collection/IterableLike;)Ljava/lang/Object;
       4: areturn

  public java.lang.Object scala$collection$IndexedSeqOptimized$$super$tail();
    Code:
       0: aload_0
       1: invokestatic  #102                // Method scala/collection/TraversableLike$class.tail:(Lscala/collection/TraversableLike;)Ljava/lang/Object;
       4: areturn

  public java.lang.Object scala$collection$IndexedSeqOptimized$$super$last();
    Code:
       0: aload_0
       1: invokestatic  #106                // Method scala/collection/TraversableLike$class.last:(Lscala/collection/TraversableLike;)Ljava/lang/Object;
       4: areturn

  public java.lang.Object scala$collection$IndexedSeqOptimized$$super$init();
    Code:
       0: aload_0
       1: invokestatic  #110                // Method scala/collection/TraversableLike$class.init:(Lscala/collection/TraversableLike;)Ljava/lang/Object;
       4: areturn

  public boolean scala$collection$IndexedSeqOptimized$$super$sameElements(scala.collection.GenIterable);
    Code:
       0: aload_0
       1: aload_1
       2: invokestatic  #116                // Method scala/collection/IterableLike$class.sameElements:(Lscala/collection/IterableLike;Lscala/collection/GenIterable;)Z
       5: ireturn

  public boolean scala$collection$IndexedSeqOptimized$$super$endsWith(scala.collection.GenSeq);
    Code:
       0: aload_0
       1: aload_1
       2: invokestatic  #124                // Method scala/collection/SeqLike$class.endsWith:(Lscala/collection/SeqLike;Lscala/collection/GenSeq;)Z
       5: ireturn

  public boolean isEmpty();
    Code:
       0: aload_0
       1: invokestatic  #132                // Method scala/collection/IndexedSeqOptimized$class.isEmpty:(Lscala/collection/IndexedSeqOptimized;)Z
       4: ireturn

  public boolean forall(scala.Function1<java.lang.Object, java.lang.Object>);
    Code:
       0: aload_0
       1: aload_1
       2: invokestatic  #137                // Method scala/collection/IndexedSeqOptimized$class.forall:(Lscala/collection/IndexedSeqOptimized;Lscala/Function1;)Z
       5: ireturn

  public boolean exists(scala.Function1<java.lang.Object, java.lang.Object>);
    Code:
       0: aload_0
       1: aload_1
       2: invokestatic  #142                // Method scala/collection/IndexedSeqOptimized$class.exists:(Lscala/collection/IndexedSeqOptimized;Lscala/Function1;)Z
       5: ireturn

  public scala.Option<java.lang.Object> find(scala.Function1<java.lang.Object, java.lang.Object>);
    Code:
       0: aload_0
       1: aload_1
       2: invokestatic  #147                // Method scala/collection/IndexedSeqOptimized$class.find:(Lscala/collection/IndexedSeqOptimized;Lscala/Function1;)Lscala/Option;
       5: areturn

  public <B> B foldLeft(B, scala.Function2<B, java.lang.Object, B>);
    Code:
       0: aload_0
       1: aload_1
       2: aload_2
       3: invokestatic  #152                // Method scala/collection/IndexedSeqOptimized$class.foldLeft:(Lscala/collection/IndexedSeqOptimized;Ljava/lang/Object;Lscala/Function2;)Ljava/lang/Object;
       6: areturn

  public <B> B foldRight(B, scala.Function2<java.lang.Object, B, B>);
    Code:
       0: aload_0
       1: aload_1
       2: aload_2
       3: invokestatic  #157                // Method scala/collection/IndexedSeqOptimized$class.foldRight:(Lscala/collection/IndexedSeqOptimized;Ljava/lang/Object;Lscala/Function2;)Ljava/lang/Object;
       6: areturn

  public <B> B reduceLeft(scala.Function2<B, java.lang.Object, B>);
    Code:
       0: aload_0
       1: aload_1
       2: invokestatic  #160                // Method scala/collection/IndexedSeqOptimized$class.reduceLeft:(Lscala/collection/IndexedSeqOptimized;Lscala/Function2;)Ljava/lang/Object;
       5: areturn

  public <B> B reduceRight(scala.Function2<java.lang.Object, B, B>);
    Code:
       0: aload_0
       1: aload_1
       2: invokestatic  #162                // Method scala/collection/IndexedSeqOptimized$class.reduceRight:(Lscala/collection/IndexedSeqOptimized;Lscala/Function2;)Ljava/lang/Object;
       5: areturn

  public <A1, B, That> That zip(scala.collection.GenIterable<B>, scala.collection.generic.CanBuildFrom<akka.util.ByteString, scala.Tuple2<A1, B>, That>);
    Code:
       0: aload_0
       1: aload_1
       2: aload_2
       3: invokestatic  #165                // Method scala/collection/IndexedSeqOptimized$class.zip:(Lscala/collection/IndexedSeqOptimized;Lscala/collection/GenIterable;Lscala/collection/generic/CanBuildFrom;)Ljava/lang/Object;
       6: areturn

  public <A1, That> That zipWithIndex(scala.collection.generic.CanBuildFrom<akka.util.ByteString, scala.Tuple2<A1, java.lang.Object>, That>);
    Code:
       0: aload_0
       1: aload_1
       2: invokestatic  #170                // Method scala/collection/IndexedSeqOptimized$class.zipWithIndex:(Lscala/collection/IndexedSeqOptimized;Lscala/collection/generic/CanBuildFrom;)Ljava/lang/Object;
       5: areturn

  public <B> boolean sameElements(scala.collection.GenIterable<B>);
    Code:
       0: aload_0
       1: aload_1
       2: invokestatic  #173                // Method scala/collection/IndexedSeqOptimized$class.sameElements:(Lscala/collection/IndexedSeqOptimized;Lscala/collection/GenIterable;)Z
       5: ireturn

  public int lengthCompare(int);
    Code:
       0: aload_0
       1: iload_1
       2: invokestatic  #178                // Method scala/collection/IndexedSeqOptimized$class.lengthCompare:(Lscala/collection/IndexedSeqOptimized;I)I
       5: ireturn

  public int segmentLength(scala.Function1<java.lang.Object, java.lang.Object>, int);
    Code:
       0: aload_0
       1: aload_1
       2: iload_2
       3: invokestatic  #185                // Method scala/collection/IndexedSeqOptimized$class.segmentLength:(Lscala/collection/IndexedSeqOptimized;Lscala/Function1;I)I
       6: ireturn

  public int indexWhere(scala.Function1<java.lang.Object, java.lang.Object>, int);
    Code:
       0: aload_0
       1: aload_1
       2: iload_2
       3: invokestatic  #189                // Method scala/collection/IndexedSeqOptimized$class.indexWhere:(Lscala/collection/IndexedSeqOptimized;Lscala/Function1;I)I
       6: ireturn

  public int lastIndexWhere(scala.Function1<java.lang.Object, java.lang.Object>, int);
    Code:
       0: aload_0
       1: aload_1
       2: iload_2
       3: invokestatic  #192                // Method scala/collection/IndexedSeqOptimized$class.lastIndexWhere:(Lscala/collection/IndexedSeqOptimized;Lscala/Function1;I)I
       6: ireturn

  public java.lang.Object reverse();
    Code:
       0: aload_0
       1: invokestatic  #197                // Method scala/collection/IndexedSeqOptimized$class.reverse:(Lscala/collection/IndexedSeqOptimized;)Ljava/lang/Object;
       4: areturn

  public scala.collection.Iterator<java.lang.Object> reverseIterator();
    Code:
       0: aload_0
       1: invokestatic  #202                // Method scala/collection/IndexedSeqOptimized$class.reverseIterator:(Lscala/collection/IndexedSeqOptimized;)Lscala/collection/Iterator;
       4: areturn

  public <B> boolean startsWith(scala.collection.GenSeq<B>, int);
    Code:
       0: aload_0
       1: aload_1
       2: iload_2
       3: invokestatic  #207                // Method scala/collection/IndexedSeqOptimized$class.startsWith:(Lscala/collection/IndexedSeqOptimized;Lscala/collection/GenSeq;I)Z
       6: ireturn

  public <B> boolean endsWith(scala.collection.GenSeq<B>);
    Code:
       0: aload_0
       1: aload_1
       2: invokestatic  #211                // Method scala/collection/IndexedSeqOptimized$class.endsWith:(Lscala/collection/IndexedSeqOptimized;Lscala/collection/GenSeq;)Z
       5: ireturn

  public scala.collection.generic.GenericCompanion<scala.collection.immutable.IndexedSeq> companion();
    Code:
       0: aload_0
       1: invokestatic  #218                // Method scala/collection/immutable/IndexedSeq$class.companion:(Lscala/collection/immutable/IndexedSeq;)Lscala/collection/generic/GenericCompanion;
       4: areturn

  public scala.collection.immutable.IndexedSeq<java.lang.Object> toIndexedSeq();
    Code:
       0: aload_0
       1: invokestatic  #223                // Method scala/collection/immutable/IndexedSeq$class.toIndexedSeq:(Lscala/collection/immutable/IndexedSeq;)Lscala/collection/immutable/IndexedSeq;
       4: areturn

  public scala.collection.immutable.IndexedSeq<java.lang.Object> seq();
    Code:
       0: aload_0
       1: invokestatic  #226                // Method scala/collection/immutable/IndexedSeq$class.seq:(Lscala/collection/immutable/IndexedSeq;)Lscala/collection/immutable/IndexedSeq;
       4: areturn

  public int hashCode();
    Code:
       0: aload_0
       1: invokestatic  #233                // Method scala/collection/IndexedSeqLike$class.hashCode:(Lscala/collection/IndexedSeqLike;)I
       4: ireturn

  public scala.collection.IndexedSeq<java.lang.Object> thisCollection();
    Code:
       0: aload_0
       1: invokestatic  #238                // Method scala/collection/IndexedSeqLike$class.thisCollection:(Lscala/collection/IndexedSeqLike;)Lscala/collection/IndexedSeq;
       4: areturn

  public scala.collection.IndexedSeq toCollection(java.lang.Object);
    Code:
       0: aload_0
       1: aload_1
       2: invokestatic  #243                // Method scala/collection/IndexedSeqLike$class.toCollection:(Lscala/collection/IndexedSeqLike;Ljava/lang/Object;)Lscala/collection/IndexedSeq;
       5: areturn

  public <A1> scala.collection.mutable.Buffer<A1> toBuffer();
    Code:
       0: aload_0
       1: invokestatic  #249                // Method scala/collection/IndexedSeqLike$class.toBuffer:(Lscala/collection/IndexedSeqLike;)Lscala/collection/mutable/Buffer;
       4: areturn

  public scala.collection.immutable.Seq<java.lang.Object> toSeq();
    Code:
       0: aload_0
       1: invokestatic  #256                // Method scala/collection/immutable/Seq$class.toSeq:(Lscala/collection/immutable/Seq;)Lscala/collection/immutable/Seq;
       4: areturn

  public scala.collection.parallel.Combiner<java.lang.Object, scala.collection.parallel.immutable.ParSeq<java.lang.Object>> parCombiner();
    Code:
       0: aload_0
       1: invokestatic  #261                // Method scala/collection/immutable/Seq$class.parCombiner:(Lscala/collection/immutable/Seq;)Lscala/collection/parallel/Combiner;
       4: areturn

  public int size();
    Code:
       0: aload_0
       1: invokestatic  #265                // Method scala/collection/SeqLike$class.size:(Lscala/collection/SeqLike;)I
       4: ireturn

  public scala.collection.Iterator<akka.util.ByteString> permutations();
    Code:
       0: aload_0
       1: invokestatic  #269                // Method scala/collection/SeqLike$class.permutations:(Lscala/collection/SeqLike;)Lscala/collection/Iterator;
       4: areturn

  public scala.collection.Iterator<akka.util.ByteString> combinations(int);
    Code:
       0: aload_0
       1: iload_1
       2: invokestatic  #274                // Method scala/collection/SeqLike$class.combinations:(Lscala/collection/SeqLike;I)Lscala/collection/Iterator;
       5: areturn

  public <B, That> That reverseMap(scala.Function1<java.lang.Object, B>, scala.collection.generic.CanBuildFrom<akka.util.ByteString, B, That>);
    Code:
       0: aload_0
       1: aload_1
       2: aload_2
       3: invokestatic  #280                // Method scala/collection/SeqLike$class.reverseMap:(Lscala/collection/SeqLike;Lscala/Function1;Lscala/collection/generic/CanBuildFrom;)Ljava/lang/Object;
       6: areturn

  public <B> int indexOfSlice(scala.collection.GenSeq<B>);
    Code:
       0: aload_0
       1: aload_1
       2: invokestatic  #286                // Method scala/collection/SeqLike$class.indexOfSlice:(Lscala/collection/SeqLike;Lscala/collection/GenSeq;)I
       5: ireturn

  public <B> int indexOfSlice(scala.collection.GenSeq<B>, int);
    Code:
       0: aload_0
       1: aload_1
       2: iload_2
       3: invokestatic  #290                // Method scala/collection/SeqLike$class.indexOfSlice:(Lscala/collection/SeqLike;Lscala/collection/GenSeq;I)I
       6: ireturn

  public <B> int lastIndexOfSlice(scala.collection.GenSeq<B>);
    Code:
       0: aload_0
       1: aload_1
       2: invokestatic  #293                // Method scala/collection/SeqLike$class.lastIndexOfSlice:(Lscala/collection/SeqLike;Lscala/collection/GenSeq;)I
       5: ireturn

  public <B> int lastIndexOfSlice(scala.collection.GenSeq<B>, int);
    Code:
       0: aload_0
       1: aload_1
       2: iload_2
       3: invokestatic  #295                // Method scala/collection/SeqLike$class.lastIndexOfSlice:(Lscala/collection/SeqLike;Lscala/collection/GenSeq;I)I
       6: ireturn

  public <B> boolean containsSlice(scala.collection.GenSeq<B>);
    Code:
       0: aload_0
       1: aload_1
       2: invokestatic  #298                // Method scala/collection/SeqLike$class.containsSlice:(Lscala/collection/SeqLike;Lscala/collection/GenSeq;)Z
       5: ireturn

  public <A1> boolean contains(A1);
    Code:
       0: aload_0
       1: aload_1
       2: invokestatic  #303                // Method scala/collection/SeqLike$class.contains:(Lscala/collection/SeqLike;Ljava/lang/Object;)Z
       5: ireturn

  public <B, That> That union(scala.collection.GenSeq<B>, scala.collection.generic.CanBuildFrom<akka.util.ByteString, B, That>);
    Code:
       0: aload_0
       1: aload_1
       2: aload_2
       3: invokestatic  #309                // Method scala/collection/SeqLike$class.union:(Lscala/collection/SeqLike;Lscala/collection/GenSeq;Lscala/collection/generic/CanBuildFrom;)Ljava/lang/Object;
       6: areturn

  public java.lang.Object diff(scala.collection.GenSeq);
    Code:
       0: aload_0
       1: aload_1
       2: invokestatic  #314                // Method scala/collection/SeqLike$class.diff:(Lscala/collection/SeqLike;Lscala/collection/GenSeq;)Ljava/lang/Object;
       5: areturn

  public java.lang.Object intersect(scala.collection.GenSeq);
    Code:
       0: aload_0
       1: aload_1
       2: invokestatic  #317                // Method scala/collection/SeqLike$class.intersect:(Lscala/collection/SeqLike;Lscala/collection/GenSeq;)Ljava/lang/Object;
       5: areturn

  public java.lang.Object distinct();
    Code:
       0: aload_0
       1: invokestatic  #321                // Method scala/collection/SeqLike$class.distinct:(Lscala/collection/SeqLike;)Ljava/lang/Object;
       4: areturn

  public <B, That> That patch(int, scala.collection.GenSeq<B>, int, scala.collection.generic.CanBuildFrom<akka.util.ByteString, B, That>);
    Code:
       0: aload_0
       1: iload_1
       2: aload_2
       3: iload_3
       4: aload         4
       6: invokestatic  #326                // Method scala/collection/SeqLike$class.patch:(Lscala/collection/SeqLike;ILscala/collection/GenSeq;ILscala/collection/generic/CanBuildFrom;)Ljava/lang/Object;
       9: areturn

  public <B, That> That updated(int, B, scala.collection.generic.CanBuildFrom<akka.util.ByteString, B, That>);
    Code:
       0: aload_0
       1: iload_1
       2: aload_2
       3: aload_3
       4: invokestatic  #332                // Method scala/collection/SeqLike$class.updated:(Lscala/collection/SeqLike;ILjava/lang/Object;Lscala/collection/generic/CanBuildFrom;)Ljava/lang/Object;
       7: areturn

  public <B, That> That $plus$colon(B, scala.collection.generic.CanBuildFrom<akka.util.ByteString, B, That>);
    Code:
       0: aload_0
       1: aload_1
       2: aload_2
       3: invokestatic  #338                // Method scala/collection/SeqLike$class.$plus$colon:(Lscala/collection/SeqLike;Ljava/lang/Object;Lscala/collection/generic/CanBuildFrom;)Ljava/lang/Object;
       6: areturn

  public <B, That> That $colon$plus(B, scala.collection.generic.CanBuildFrom<akka.util.ByteString, B, That>);
    Code:
       0: aload_0
       1: aload_1
       2: aload_2
       3: invokestatic  #341                // Method scala/collection/SeqLike$class.$colon$plus:(Lscala/collection/SeqLike;Ljava/lang/Object;Lscala/collection/generic/CanBuildFrom;)Ljava/lang/Object;
       6: areturn

  public <B, That> That padTo(int, B, scala.collection.generic.CanBuildFrom<akka.util.ByteString, B, That>);
    Code:
       0: aload_0
       1: iload_1
       2: aload_2
       3: aload_3
       4: invokestatic  #344                // Method scala/collection/SeqLike$class.padTo:(Lscala/collection/SeqLike;ILjava/lang/Object;Lscala/collection/generic/CanBuildFrom;)Ljava/lang/Object;
       7: areturn

  public <B> boolean corresponds(scala.collection.GenSeq<B>, scala.Function2<java.lang.Object, B, java.lang.Object>);
    Code:
       0: aload_0
       1: aload_1
       2: aload_2
       3: invokestatic  #349                // Method scala/collection/SeqLike$class.corresponds:(Lscala/collection/SeqLike;Lscala/collection/GenSeq;Lscala/Function2;)Z
       6: ireturn

  public java.lang.Object sortWith(scala.Function2);
    Code:
       0: aload_0
       1: aload_1
       2: invokestatic  #353                // Method scala/collection/SeqLike$class.sortWith:(Lscala/collection/SeqLike;Lscala/Function2;)Ljava/lang/Object;
       5: areturn

  public java.lang.Object sortBy(scala.Function1, scala.math.Ordering);
    Code:
       0: aload_0
       1: aload_1
       2: aload_2
       3: invokestatic  #359                // Method scala/collection/SeqLike$class.sortBy:(Lscala/collection/SeqLike;Lscala/Function1;Lscala/math/Ordering;)Ljava/lang/Object;
       6: areturn

  public java.lang.Object sorted(scala.math.Ordering);
    Code:
       0: aload_0
       1: aload_1
       2: invokestatic  #366                // Method scala/collection/SeqLike$class.sorted:(Lscala/collection/SeqLike;Lscala/math/Ordering;)Ljava/lang/Object;
       5: areturn

  public scala.collection.immutable.Range indices();
    Code:
       0: aload_0
       1: invokestatic  #371                // Method scala/collection/SeqLike$class.indices:(Lscala/collection/SeqLike;)Lscala/collection/immutable/Range;
       4: areturn

  public java.lang.Object view();
    Code:
       0: aload_0
       1: invokestatic  #376                // Method scala/collection/SeqLike$class.view:(Lscala/collection/SeqLike;)Lscala/collection/SeqView;
       4: areturn

  public scala.collection.SeqView<java.lang.Object, akka.util.ByteString> view(int, int);
    Code:
       0: aload_0
       1: iload_1
       2: iload_2
       3: invokestatic  #380                // Method scala/collection/SeqLike$class.view:(Lscala/collection/SeqLike;II)Lscala/collection/SeqView;
       6: areturn

  public boolean isDefinedAt(int);
    Code:
       0: aload_0
       1: iload_1
       2: invokestatic  #388                // Method scala/collection/GenSeqLike$class.isDefinedAt:(Lscala/collection/GenSeqLike;I)Z
       5: ireturn

  public int prefixLength(scala.Function1<java.lang.Object, java.lang.Object>);
    Code:
       0: aload_0
       1: aload_1
       2: invokestatic  #394                // Method scala/collection/GenSeqLike$class.prefixLength:(Lscala/collection/GenSeqLike;Lscala/Function1;)I
       5: ireturn

  public <B> int indexOf(B, int);
    Code:
       0: aload_0
       1: aload_1
       2: iload_2
       3: invokestatic  #399                // Method scala/collection/GenSeqLike$class.indexOf:(Lscala/collection/GenSeqLike;Ljava/lang/Object;I)I
       6: ireturn

  public <B> int lastIndexOf(B);
    Code:
       0: aload_0
       1: aload_1
       2: invokestatic  #404                // Method scala/collection/GenSeqLike$class.lastIndexOf:(Lscala/collection/GenSeqLike;Ljava/lang/Object;)I
       5: ireturn

  public <B> int lastIndexOf(B, int);
    Code:
       0: aload_0
       1: aload_1
       2: iload_2
       3: invokestatic  #406                // Method scala/collection/GenSeqLike$class.lastIndexOf:(Lscala/collection/GenSeqLike;Ljava/lang/Object;I)I
       6: ireturn

  public int lastIndexWhere(scala.Function1<java.lang.Object, java.lang.Object>);
    Code:
       0: aload_0
       1: aload_1
       2: invokestatic  #408                // Method scala/collection/GenSeqLike$class.lastIndexWhere:(Lscala/collection/GenSeqLike;Lscala/Function1;)I
       5: ireturn

  public <B> boolean startsWith(scala.collection.GenSeq<B>);
    Code:
       0: aload_0
       1: aload_1
       2: invokestatic  #411                // Method scala/collection/GenSeqLike$class.startsWith:(Lscala/collection/GenSeqLike;Lscala/collection/GenSeq;)Z
       5: ireturn

  public boolean equals(java.lang.Object);
    Code:
       0: aload_0
       1: aload_1
       2: invokestatic  #415                // Method scala/collection/GenSeqLike$class.equals:(Lscala/collection/GenSeqLike;Ljava/lang/Object;)Z
       5: ireturn

  public <A1, B1> scala.PartialFunction<A1, B1> orElse(scala.PartialFunction<A1, B1>);
    Code:
       0: aload_0
       1: aload_1
       2: invokestatic  #422                // Method scala/PartialFunction$class.orElse:(Lscala/PartialFunction;Lscala/PartialFunction;)Lscala/PartialFunction;
       5: areturn

  public <C> scala.PartialFunction<java.lang.Object, C> andThen(scala.Function1<java.lang.Object, C>);
    Code:
       0: aload_0
       1: aload_1
       2: invokestatic  #428                // Method scala/PartialFunction$class.andThen:(Lscala/PartialFunction;Lscala/Function1;)Lscala/PartialFunction;
       5: areturn

  public scala.Function1<java.lang.Object, scala.Option<java.lang.Object>> lift();
    Code:
       0: aload_0
       1: invokestatic  #434                // Method scala/PartialFunction$class.lift:(Lscala/PartialFunction;)Lscala/Function1;
       4: areturn

  public java.lang.Object applyOrElse(java.lang.Object, scala.Function1);
    Code:
       0: aload_0
       1: aload_1
       2: aload_2
       3: invokestatic  #439                // Method scala/PartialFunction$class.applyOrElse:(Lscala/PartialFunction;Ljava/lang/Object;Lscala/Function1;)Ljava/lang/Object;
       6: areturn

  public <U> scala.Function1<java.lang.Object, java.lang.Object> runWith(scala.Function1<java.lang.Object, U>);
    Code:
       0: aload_0
       1: aload_1
       2: invokestatic  #446                // Method scala/PartialFunction$class.runWith:(Lscala/PartialFunction;Lscala/Function1;)Lscala/Function1;
       5: areturn

  public boolean apply$mcZD$sp(double);
    Code:
       0: aload_0
       1: dload_1
       2: invokestatic  #454                // Method scala/Function1$class.apply$mcZD$sp:(Lscala/Function1;D)Z
       5: ireturn

  public double apply$mcDD$sp(double);
    Code:
       0: aload_0
       1: dload_1
       2: invokestatic  #461                // Method scala/Function1$class.apply$mcDD$sp:(Lscala/Function1;D)D
       5: dreturn

  public float apply$mcFD$sp(double);
    Code:
       0: aload_0
       1: dload_1
       2: invokestatic  #466                // Method scala/Function1$class.apply$mcFD$sp:(Lscala/Function1;D)F
       5: freturn

  public int apply$mcID$sp(double);
    Code:
       0: aload_0
       1: dload_1
       2: invokestatic  #471                // Method scala/Function1$class.apply$mcID$sp:(Lscala/Function1;D)I
       5: ireturn

  public long apply$mcJD$sp(double);
    Code:
       0: aload_0
       1: dload_1
       2: invokestatic  #476                // Method scala/Function1$class.apply$mcJD$sp:(Lscala/Function1;D)J
       5: lreturn

  public void apply$mcVD$sp(double);
    Code:
       0: aload_0
       1: dload_1
       2: invokestatic  #481                // Method scala/Function1$class.apply$mcVD$sp:(Lscala/Function1;D)V
       5: return

  public boolean apply$mcZF$sp(float);
    Code:
       0: aload_0
       1: fload_1
       2: invokestatic  #486                // Method scala/Function1$class.apply$mcZF$sp:(Lscala/Function1;F)Z
       5: ireturn

  public double apply$mcDF$sp(float);
    Code:
       0: aload_0
       1: fload_1
       2: invokestatic  #492                // Method scala/Function1$class.apply$mcDF$sp:(Lscala/Function1;F)D
       5: dreturn

  public float apply$mcFF$sp(float);
    Code:
       0: aload_0
       1: fload_1
       2: invokestatic  #497                // Method scala/Function1$class.apply$mcFF$sp:(Lscala/Function1;F)F
       5: freturn

  public int apply$mcIF$sp(float);
    Code:
       0: aload_0
       1: fload_1
       2: invokestatic  #502                // Method scala/Function1$class.apply$mcIF$sp:(Lscala/Function1;F)I
       5: ireturn

  public long apply$mcJF$sp(float);
    Code:
       0: aload_0
       1: fload_1
       2: invokestatic  #507                // Method scala/Function1$class.apply$mcJF$sp:(Lscala/Function1;F)J
       5: lreturn

  public void apply$mcVF$sp(float);
    Code:
       0: aload_0
       1: fload_1
       2: invokestatic  #512                // Method scala/Function1$class.apply$mcVF$sp:(Lscala/Function1;F)V
       5: return

  public boolean apply$mcZI$sp(int);
    Code:
       0: aload_0
       1: iload_1
       2: invokestatic  #516                // Method scala/Function1$class.apply$mcZI$sp:(Lscala/Function1;I)Z
       5: ireturn

  public double apply$mcDI$sp(int);
    Code:
       0: aload_0
       1: iload_1
       2: invokestatic  #521                // Method scala/Function1$class.apply$mcDI$sp:(Lscala/Function1;I)D
       5: dreturn

  public float apply$mcFI$sp(int);
    Code:
       0: aload_0
       1: iload_1
       2: invokestatic  #526                // Method scala/Function1$class.apply$mcFI$sp:(Lscala/Function1;I)F
       5: freturn

  public int apply$mcII$sp(int);
    Code:
       0: aload_0
       1: iload_1
       2: invokestatic  #529                // Method scala/Function1$class.apply$mcII$sp:(Lscala/Function1;I)I
       5: ireturn

  public long apply$mcJI$sp(int);
    Code:
       0: aload_0
       1: iload_1
       2: invokestatic  #534                // Method scala/Function1$class.apply$mcJI$sp:(Lscala/Function1;I)J
       5: lreturn

  public void apply$mcVI$sp(int);
    Code:
       0: aload_0
       1: iload_1
       2: invokestatic  #539                // Method scala/Function1$class.apply$mcVI$sp:(Lscala/Function1;I)V
       5: return

  public boolean apply$mcZJ$sp(long);
    Code:
       0: aload_0
       1: lload_1
       2: invokestatic  #544                // Method scala/Function1$class.apply$mcZJ$sp:(Lscala/Function1;J)Z
       5: ireturn

  public double apply$mcDJ$sp(long);
    Code:
       0: aload_0
       1: lload_1
       2: invokestatic  #550                // Method scala/Function1$class.apply$mcDJ$sp:(Lscala/Function1;J)D
       5: dreturn

  public float apply$mcFJ$sp(long);
    Code:
       0: aload_0
       1: lload_1
       2: invokestatic  #555                // Method scala/Function1$class.apply$mcFJ$sp:(Lscala/Function1;J)F
       5: freturn

  public int apply$mcIJ$sp(long);
    Code:
       0: aload_0
       1: lload_1
       2: invokestatic  #560                // Method scala/Function1$class.apply$mcIJ$sp:(Lscala/Function1;J)I
       5: ireturn

  public long apply$mcJJ$sp(long);
    Code:
       0: aload_0
       1: lload_1
       2: invokestatic  #565                // Method scala/Function1$class.apply$mcJJ$sp:(Lscala/Function1;J)J
       5: lreturn

  public void apply$mcVJ$sp(long);
    Code:
       0: aload_0
       1: lload_1
       2: invokestatic  #570                // Method scala/Function1$class.apply$mcVJ$sp:(Lscala/Function1;J)V
       5: return

  public <A> scala.Function1<A, java.lang.Object> compose(scala.Function1<A, java.lang.Object>);
    Code:
       0: aload_0
       1: aload_1
       2: invokestatic  #574                // Method scala/Function1$class.compose:(Lscala/Function1;Lscala/Function1;)Lscala/Function1;
       5: areturn

  public scala.collection.Iterable<java.lang.Object> toIterable();
    Code:
       0: aload_0
       1: invokestatic  #580                // Method scala/collection/IterableLike$class.toIterable:(Lscala/collection/IterableLike;)Lscala/collection/Iterable;
       4: areturn

  public scala.collection.Iterator<java.lang.Object> toIterator();
    Code:
       0: aload_0
       1: invokestatic  #584                // Method scala/collection/IterableLike$class.toIterator:(Lscala/collection/IterableLike;)Lscala/collection/Iterator;
       4: areturn

  public scala.collection.Iterator<akka.util.ByteString> grouped(int);
    Code:
       0: aload_0
       1: iload_1
       2: invokestatic  #588                // Method scala/collection/IterableLike$class.grouped:(Lscala/collection/IterableLike;I)Lscala/collection/Iterator;
       5: areturn

  public scala.collection.Iterator<akka.util.ByteString> sliding(int);
    Code:
       0: aload_0
       1: iload_1
       2: invokestatic  #591                // Method scala/collection/IterableLike$class.sliding:(Lscala/collection/IterableLike;I)Lscala/collection/Iterator;
       5: areturn

  public scala.collection.Iterator<akka.util.ByteString> sliding(int, int);
    Code:
       0: aload_0
       1: iload_1
       2: iload_2
       3: invokestatic  #595                // Method scala/collection/IterableLike$class.sliding:(Lscala/collection/IterableLike;II)Lscala/collection/Iterator;
       6: areturn

  public <B, A1, That> That zipAll(scala.collection.GenIterable<B>, A1, B, scala.collection.generic.CanBuildFrom<akka.util.ByteString, scala.Tuple2<A1, B>, That>);
    Code:
       0: aload_0
       1: aload_1
       2: aload_2
       3: aload_3
       4: aload         4
       6: invokestatic  #601                // Method scala/collection/IterableLike$class.zipAll:(Lscala/collection/IterableLike;Lscala/collection/GenIterable;Ljava/lang/Object;Ljava/lang/Object;Lscala/collection/generic/CanBuildFrom;)Ljava/lang/Object;
       9: areturn

  public scala.collection.immutable.Stream<java.lang.Object> toStream();
    Code:
       0: aload_0
       1: invokestatic  #608                // Method scala/collection/IterableLike$class.toStream:(Lscala/collection/IterableLike;)Lscala/collection/immutable/Stream;
       4: areturn

  public boolean canEqual(java.lang.Object);
    Code:
       0: aload_0
       1: aload_1
       2: invokestatic  #612                // Method scala/collection/IterableLike$class.canEqual:(Lscala/collection/IterableLike;Ljava/lang/Object;)Z
       5: ireturn

  public <B> scala.collection.mutable.Builder<B, scala.collection.immutable.IndexedSeq<B>> genericBuilder();
    Code:
       0: aload_0
       1: invokestatic  #619                // Method scala/collection/generic/GenericTraversableTemplate$class.genericBuilder:(Lscala/collection/generic/GenericTraversableTemplate;)Lscala/collection/mutable/Builder;
       4: areturn

  public <A1, A2> scala.Tuple2<scala.collection.immutable.IndexedSeq<A1>, scala.collection.immutable.IndexedSeq<A2>> unzip(scala.Function1<java.lang.Object, scala.Tuple2<A1, A2>>);
    Code:
       0: aload_0
       1: aload_1
       2: invokestatic  #624                // Method scala/collection/generic/GenericTraversableTemplate$class.unzip:(Lscala/collection/generic/GenericTraversableTemplate;Lscala/Function1;)Lscala/Tuple2;
       5: areturn

  public <A1, A2, A3> scala.Tuple3<scala.collection.immutable.IndexedSeq<A1>, scala.collection.immutable.IndexedSeq<A2>, scala.collection.immutable.IndexedSeq<A3>> unzip3(scala.Function1<java.lang.Object, scala.Tuple3<A1, A2, A3>>);
    Code:
       0: aload_0
       1: aload_1
       2: invokestatic  #630                // Method scala/collection/generic/GenericTraversableTemplate$class.unzip3:(Lscala/collection/generic/GenericTraversableTemplate;Lscala/Function1;)Lscala/Tuple3;
       5: areturn

  public scala.collection.GenTraversable flatten(scala.Function1);
    Code:
       0: aload_0
       1: aload_1
       2: invokestatic  #636                // Method scala/collection/generic/GenericTraversableTemplate$class.flatten:(Lscala/collection/generic/GenericTraversableTemplate;Lscala/Function1;)Lscala/collection/GenTraversable;
       5: areturn

  public scala.collection.GenTraversable transpose(scala.Function1);
    Code:
       0: aload_0
       1: aload_1
       2: invokestatic  #640                // Method scala/collection/generic/GenericTraversableTemplate$class.transpose:(Lscala/collection/generic/GenericTraversableTemplate;Lscala/Function1;)Lscala/collection/GenTraversable;
       5: areturn

  public java.lang.Object repr();
    Code:
       0: aload_0
       1: invokestatic  #642                // Method scala/collection/TraversableLike$class.repr:(Lscala/collection/TraversableLike;)Ljava/lang/Object;
       4: areturn

  public final boolean isTraversableAgain();
    Code:
       0: aload_0
       1: invokestatic  #646                // Method scala/collection/TraversableLike$class.isTraversableAgain:(Lscala/collection/TraversableLike;)Z
       4: ireturn

  public boolean hasDefiniteSize();
    Code:
       0: aload_0
       1: invokestatic  #649                // Method scala/collection/TraversableLike$class.hasDefiniteSize:(Lscala/collection/TraversableLike;)Z
       4: ireturn

  public <B, That> That $plus$plus(scala.collection.GenTraversableOnce<B>, scala.collection.generic.CanBuildFrom<akka.util.ByteString, B, That>);
    Code:
       0: aload_0
       1: aload_1
       2: aload_2
       3: invokestatic  #654                // Method scala/collection/TraversableLike$class.$plus$plus:(Lscala/collection/TraversableLike;Lscala/collection/GenTraversableOnce;Lscala/collection/generic/CanBuildFrom;)Ljava/lang/Object;
       6: areturn

  public <B, That> That $plus$plus$colon(scala.collection.TraversableOnce<B>, scala.collection.generic.CanBuildFrom<akka.util.ByteString, B, That>);
    Code:
       0: aload_0
       1: aload_1
       2: aload_2
       3: invokestatic  #660                // Method scala/collection/TraversableLike$class.$plus$plus$colon:(Lscala/collection/TraversableLike;Lscala/collection/TraversableOnce;Lscala/collection/generic/CanBuildFrom;)Ljava/lang/Object;
       6: areturn

  public <B, That> That $plus$plus$colon(scala.collection.Traversable<B>, scala.collection.generic.CanBuildFrom<akka.util.ByteString, B, That>);
    Code:
       0: aload_0
       1: aload_1
       2: aload_2
       3: invokestatic  #665                // Method scala/collection/TraversableLike$class.$plus$plus$colon:(Lscala/collection/TraversableLike;Lscala/collection/Traversable;Lscala/collection/generic/CanBuildFrom;)Ljava/lang/Object;
       6: areturn

  public <B, That> That map(scala.Function1<java.lang.Object, B>, scala.collection.generic.CanBuildFrom<akka.util.ByteString, B, That>);
    Code:
       0: aload_0
       1: aload_1
       2: aload_2
       3: invokestatic  #670                // Method scala/collection/TraversableLike$class.map:(Lscala/collection/TraversableLike;Lscala/Function1;Lscala/collection/generic/CanBuildFrom;)Ljava/lang/Object;
       6: areturn

  public <B, That> That flatMap(scala.Function1<java.lang.Object, scala.collection.GenTraversableOnce<B>>, scala.collection.generic.CanBuildFrom<akka.util.ByteString, B, That>);
    Code:
       0: aload_0
       1: aload_1
       2: aload_2
       3: invokestatic  #673                // Method scala/collection/TraversableLike$class.flatMap:(Lscala/collection/TraversableLike;Lscala/Function1;Lscala/collection/generic/CanBuildFrom;)Ljava/lang/Object;
       6: areturn

  public java.lang.Object filter(scala.Function1);
    Code:
       0: aload_0
       1: aload_1
       2: invokestatic  #678                // Method scala/collection/TraversableLike$class.filter:(Lscala/collection/TraversableLike;Lscala/Function1;)Ljava/lang/Object;
       5: areturn

  public java.lang.Object filterNot(scala.Function1);
    Code:
       0: aload_0
       1: aload_1
       2: invokestatic  #681                // Method scala/collection/TraversableLike$class.filterNot:(Lscala/collection/TraversableLike;Lscala/Function1;)Ljava/lang/Object;
       5: areturn

  public <B, That> That collect(scala.PartialFunction<java.lang.Object, B>, scala.collection.generic.CanBuildFrom<akka.util.ByteString, B, That>);
    Code:
       0: aload_0
       1: aload_1
       2: aload_2
       3: invokestatic  #686                // Method scala/collection/TraversableLike$class.collect:(Lscala/collection/TraversableLike;Lscala/PartialFunction;Lscala/collection/generic/CanBuildFrom;)Ljava/lang/Object;
       6: areturn

  public scala.Tuple2<akka.util.ByteString, akka.util.ByteString> partition(scala.Function1<java.lang.Object, java.lang.Object>);
    Code:
       0: aload_0
       1: aload_1
       2: invokestatic  #691                // Method scala/collection/TraversableLike$class.partition:(Lscala/collection/TraversableLike;Lscala/Function1;)Lscala/Tuple2;
       5: areturn

  public <K> scala.collection.immutable.Map<K, akka.util.ByteString> groupBy(scala.Function1<java.lang.Object, K>);
    Code:
       0: aload_0
       1: aload_1
       2: invokestatic  #696                // Method scala/collection/TraversableLike$class.groupBy:(Lscala/collection/TraversableLike;Lscala/Function1;)Lscala/collection/immutable/Map;
       5: areturn

  public <B, That> That scan(B, scala.Function2<B, B, B>, scala.collection.generic.CanBuildFrom<akka.util.ByteString, B, That>);
    Code:
       0: aload_0
       1: aload_1
       2: aload_2
       3: aload_3
       4: invokestatic  #701                // Method scala/collection/TraversableLike$class.scan:(Lscala/collection/TraversableLike;Ljava/lang/Object;Lscala/Function2;Lscala/collection/generic/CanBuildFrom;)Ljava/lang/Object;
       7: areturn

  public <B, That> That scanLeft(B, scala.Function2<B, java.lang.Object, B>, scala.collection.generic.CanBuildFrom<akka.util.ByteString, B, That>);
    Code:
       0: aload_0
       1: aload_1
       2: aload_2
       3: aload_3
       4: invokestatic  #705                // Method scala/collection/TraversableLike$class.scanLeft:(Lscala/collection/TraversableLike;Ljava/lang/Object;Lscala/Function2;Lscala/collection/generic/CanBuildFrom;)Ljava/lang/Object;
       7: areturn

  public <B, That> That scanRight(B, scala.Function2<java.lang.Object, B, B>, scala.collection.generic.CanBuildFrom<akka.util.ByteString, B, That>);
    Code:
       0: aload_0
       1: aload_1
       2: aload_2
       3: aload_3
       4: invokestatic  #708                // Method scala/collection/TraversableLike$class.scanRight:(Lscala/collection/TraversableLike;Ljava/lang/Object;Lscala/Function2;Lscala/collection/generic/CanBuildFrom;)Ljava/lang/Object;
       7: areturn

  public scala.Option<java.lang.Object> headOption();
    Code:
       0: aload_0
       1: invokestatic  #713                // Method scala/collection/TraversableLike$class.headOption:(Lscala/collection/TraversableLike;)Lscala/Option;
       4: areturn

  public scala.Option<java.lang.Object> lastOption();
    Code:
       0: aload_0
       1: invokestatic  #716                // Method scala/collection/TraversableLike$class.lastOption:(Lscala/collection/TraversableLike;)Lscala/Option;
       4: areturn

  public java.lang.Object sliceWithKnownDelta(int, int, int);
    Code:
       0: aload_0
       1: iload_1
       2: iload_2
       3: iload_3
       4: invokestatic  #721                // Method scala/collection/TraversableLike$class.sliceWithKnownDelta:(Lscala/collection/TraversableLike;III)Ljava/lang/Object;
       7: areturn

  public java.lang.Object sliceWithKnownBound(int, int);
    Code:
       0: aload_0
       1: iload_1
       2: iload_2
       3: invokestatic  #727                // Method scala/collection/TraversableLike$class.sliceWithKnownBound:(Lscala/collection/TraversableLike;II)Ljava/lang/Object;
       6: areturn

  public scala.collection.Iterator<akka.util.ByteString> tails();
    Code:
       0: aload_0
       1: invokestatic  #731                // Method scala/collection/TraversableLike$class.tails:(Lscala/collection/TraversableLike;)Lscala/collection/Iterator;
       4: areturn

  public scala.collection.Iterator<akka.util.ByteString> inits();
    Code:
       0: aload_0
       1: invokestatic  #734                // Method scala/collection/TraversableLike$class.inits:(Lscala/collection/TraversableLike;)Lscala/collection/Iterator;
       4: areturn

  public scala.collection.Traversable<java.lang.Object> toTraversable();
    Code:
       0: aload_0
       1: invokestatic  #739                // Method scala/collection/TraversableLike$class.toTraversable:(Lscala/collection/TraversableLike;)Lscala/collection/Traversable;
       4: areturn

  public <Col> Col to(scala.collection.generic.CanBuildFrom<scala.runtime.Nothing$, java.lang.Object, Col>);
    Code:
       0: aload_0
       1: aload_1
       2: invokestatic  #743                // Method scala/collection/TraversableLike$class.to:(Lscala/collection/TraversableLike;Lscala/collection/generic/CanBuildFrom;)Ljava/lang/Object;
       5: areturn

  public java.lang.String stringPrefix();
    Code:
       0: aload_0
       1: invokestatic  #747                // Method scala/collection/TraversableLike$class.stringPrefix:(Lscala/collection/TraversableLike;)Ljava/lang/String;
       4: areturn

  public scala.collection.generic.FilterMonadic<java.lang.Object, akka.util.ByteString> withFilter(scala.Function1<java.lang.Object, java.lang.Object>);
    Code:
       0: aload_0
       1: aload_1
       2: invokestatic  #752                // Method scala/collection/TraversableLike$class.withFilter:(Lscala/collection/TraversableLike;Lscala/Function1;)Lscala/collection/generic/FilterMonadic;
       5: areturn

  public scala.collection.Parallel par();
    Code:
       0: aload_0
       1: invokestatic  #759                // Method scala/collection/Parallelizable$class.par:(Lscala/collection/Parallelizable;)Lscala/collection/Parallel;
       4: areturn

  public scala.collection.immutable.List<java.lang.Object> reversed();
    Code:
       0: aload_0
       1: invokestatic  #764                // Method scala/collection/TraversableOnce$class.reversed:(Lscala/collection/TraversableOnce;)Lscala/collection/immutable/List;
       4: areturn

  public boolean nonEmpty();
    Code:
       0: aload_0
       1: invokestatic  #768                // Method scala/collection/TraversableOnce$class.nonEmpty:(Lscala/collection/TraversableOnce;)Z
       4: ireturn

  public int count(scala.Function1<java.lang.Object, java.lang.Object>);
    Code:
       0: aload_0
       1: aload_1
       2: invokestatic  #772                // Method scala/collection/TraversableOnce$class.count:(Lscala/collection/TraversableOnce;Lscala/Function1;)I
       5: ireturn

  public <B> scala.Option<B> collectFirst(scala.PartialFunction<java.lang.Object, B>);
    Code:
       0: aload_0
       1: aload_1
       2: invokestatic  #777                // Method scala/collection/TraversableOnce$class.collectFirst:(Lscala/collection/TraversableOnce;Lscala/PartialFunction;)Lscala/Option;
       5: areturn

  public <B> B $div$colon(B, scala.Function2<B, java.lang.Object, B>);
    Code:
       0: aload_0
       1: aload_1
       2: aload_2
       3: invokestatic  #781                // Method scala/collection/TraversableOnce$class.$div$colon:(Lscala/collection/TraversableOnce;Ljava/lang/Object;Lscala/Function2;)Ljava/lang/Object;
       6: areturn

  public <B> B $colon$bslash(B, scala.Function2<java.lang.Object, B, B>);
    Code:
       0: aload_0
       1: aload_1
       2: aload_2
       3: invokestatic  #784                // Method scala/collection/TraversableOnce$class.$colon$bslash:(Lscala/collection/TraversableOnce;Ljava/lang/Object;Lscala/Function2;)Ljava/lang/Object;
       6: areturn

  public <B> scala.Option<B> reduceLeftOption(scala.Function2<B, java.lang.Object, B>);
    Code:
       0: aload_0
       1: aload_1
       2: invokestatic  #789                // Method scala/collection/TraversableOnce$class.reduceLeftOption:(Lscala/collection/TraversableOnce;Lscala/Function2;)Lscala/Option;
       5: areturn

  public <B> scala.Option<B> reduceRightOption(scala.Function2<java.lang.Object, B, B>);
    Code:
       0: aload_0
       1: aload_1
       2: invokestatic  #792                // Method scala/collection/TraversableOnce$class.reduceRightOption:(Lscala/collection/TraversableOnce;Lscala/Function2;)Lscala/Option;
       5: areturn

  public <A1> A1 reduce(scala.Function2<A1, A1, A1>);
    Code:
       0: aload_0
       1: aload_1
       2: invokestatic  #795                // Method scala/collection/TraversableOnce$class.reduce:(Lscala/collection/TraversableOnce;Lscala/Function2;)Ljava/lang/Object;
       5: areturn

  public <A1> scala.Option<A1> reduceOption(scala.Function2<A1, A1, A1>);
    Code:
       0: aload_0
       1: aload_1
       2: invokestatic  #798                // Method scala/collection/TraversableOnce$class.reduceOption:(Lscala/collection/TraversableOnce;Lscala/Function2;)Lscala/Option;
       5: areturn

  public <A1> A1 fold(A1, scala.Function2<A1, A1, A1>);
    Code:
       0: aload_0
       1: aload_1
       2: aload_2
       3: invokestatic  #801                // Method scala/collection/TraversableOnce$class.fold:(Lscala/collection/TraversableOnce;Ljava/lang/Object;Lscala/Function2;)Ljava/lang/Object;
       6: areturn

  public <B> B aggregate(scala.Function0<B>, scala.Function2<B, java.lang.Object, B>, scala.Function2<B, B, B>);
    Code:
       0: aload_0
       1: aload_1
       2: aload_2
       3: aload_3
       4: invokestatic  #806                // Method scala/collection/TraversableOnce$class.aggregate:(Lscala/collection/TraversableOnce;Lscala/Function0;Lscala/Function2;Lscala/Function2;)Ljava/lang/Object;
       7: areturn

  public <B> B sum(scala.math.Numeric<B>);
    Code:
       0: aload_0
       1: aload_1
       2: invokestatic  #814                // Method scala/collection/TraversableOnce$class.sum:(Lscala/collection/TraversableOnce;Lscala/math/Numeric;)Ljava/lang/Object;
       5: areturn

  public <B> B product(scala.math.Numeric<B>);
    Code:
       0: aload_0
       1: aload_1
       2: invokestatic  #819                // Method scala/collection/TraversableOnce$class.product:(Lscala/collection/TraversableOnce;Lscala/math/Numeric;)Ljava/lang/Object;
       5: areturn

  public java.lang.Object min(scala.math.Ordering);
    Code:
       0: aload_0
       1: aload_1
       2: invokestatic  #823                // Method scala/collection/TraversableOnce$class.min:(Lscala/collection/TraversableOnce;Lscala/math/Ordering;)Ljava/lang/Object;
       5: areturn

  public java.lang.Object max(scala.math.Ordering);
    Code:
       0: aload_0
       1: aload_1
       2: invokestatic  #827                // Method scala/collection/TraversableOnce$class.max:(Lscala/collection/TraversableOnce;Lscala/math/Ordering;)Ljava/lang/Object;
       5: areturn

  public java.lang.Object maxBy(scala.Function1, scala.math.Ordering);
    Code:
       0: aload_0
       1: aload_1
       2: aload_2
       3: invokestatic  #831                // Method scala/collection/TraversableOnce$class.maxBy:(Lscala/collection/TraversableOnce;Lscala/Function1;Lscala/math/Ordering;)Ljava/lang/Object;
       6: areturn

  public java.lang.Object minBy(scala.Function1, scala.math.Ordering);
    Code:
       0: aload_0
       1: aload_1
       2: aload_2
       3: invokestatic  #834                // Method scala/collection/TraversableOnce$class.minBy:(Lscala/collection/TraversableOnce;Lscala/Function1;Lscala/math/Ordering;)Ljava/lang/Object;
       6: areturn

  public <B> void copyToBuffer(scala.collection.mutable.Buffer<B>);
    Code:
       0: aload_0
       1: aload_1
       2: invokestatic  #839                // Method scala/collection/TraversableOnce$class.copyToBuffer:(Lscala/collection/TraversableOnce;Lscala/collection/mutable/Buffer;)V
       5: return

  public <B> void copyToArray(java.lang.Object, int);
    Code:
       0: aload_0
       1: aload_1
       2: iload_2
       3: invokestatic  #846                // Method scala/collection/TraversableOnce$class.copyToArray:(Lscala/collection/TraversableOnce;Ljava/lang/Object;I)V
       6: return

  public <B> void copyToArray(java.lang.Object);
    Code:
       0: aload_0
       1: aload_1
       2: invokestatic  #852                // Method scala/collection/TraversableOnce$class.copyToArray:(Lscala/collection/TraversableOnce;Ljava/lang/Object;)V
       5: return

  public scala.collection.immutable.List<java.lang.Object> toList();
    Code:
       0: aload_0
       1: invokestatic  #855                // Method scala/collection/TraversableOnce$class.toList:(Lscala/collection/TraversableOnce;)Lscala/collection/immutable/List;
       4: areturn

  public <B> scala.collection.immutable.Set<B> toSet();
    Code:
       0: aload_0
       1: invokestatic  #860                // Method scala/collection/TraversableOnce$class.toSet:(Lscala/collection/TraversableOnce;)Lscala/collection/immutable/Set;
       4: areturn

  public scala.collection.immutable.Vector<java.lang.Object> toVector();
    Code:
       0: aload_0
       1: invokestatic  #865                // Method scala/collection/TraversableOnce$class.toVector:(Lscala/collection/TraversableOnce;)Lscala/collection/immutable/Vector;
       4: areturn

  public <T, U> scala.collection.immutable.Map<T, U> toMap(scala.Predef$$less$colon$less<java.lang.Object, scala.Tuple2<T, U>>);
    Code:
       0: aload_0
       1: aload_1
       2: invokestatic  #870                // Method scala/collection/TraversableOnce$class.toMap:(Lscala/collection/TraversableOnce;Lscala/Predef$$less$colon$less;)Lscala/collection/immutable/Map;
       5: areturn

  public java.lang.String mkString(java.lang.String, java.lang.String, java.lang.String);
    Code:
       0: aload_0
       1: aload_1
       2: aload_2
       3: aload_3
       4: invokestatic  #877                // Method scala/collection/TraversableOnce$class.mkString:(Lscala/collection/TraversableOnce;Ljava/lang/String;Ljava/lang/String;Ljava/lang/String;)Ljava/lang/String;
       7: areturn

  public java.lang.String mkString(java.lang.String);
    Code:
       0: aload_0
       1: aload_1
       2: invokestatic  #883                // Method scala/collection/TraversableOnce$class.mkString:(Lscala/collection/TraversableOnce;Ljava/lang/String;)Ljava/lang/String;
       5: areturn

  public java.lang.String mkString();
    Code:
       0: aload_0
       1: invokestatic  #886                // Method scala/collection/TraversableOnce$class.mkString:(Lscala/collection/TraversableOnce;)Ljava/lang/String;
       4: areturn

  public scala.collection.mutable.StringBuilder addString(scala.collection.mutable.StringBuilder, java.lang.String, java.lang.String, java.lang.String);
    Code:
       0: aload_0
       1: aload_1
       2: aload_2
       3: aload_3
       4: aload         4
       6: invokestatic  #891                // Method scala/collection/TraversableOnce$class.addString:(Lscala/collection/TraversableOnce;Lscala/collection/mutable/StringBuilder;Ljava/lang/String;Ljava/lang/String;Ljava/lang/String;)Lscala/collection/mutable/StringBuilder;
       9: areturn

  public scala.collection.mutable.StringBuilder addString(scala.collection.mutable.StringBuilder, java.lang.String);
    Code:
       0: aload_0
       1: aload_1
       2: aload_2
       3: invokestatic  #897                // Method scala/collection/TraversableOnce$class.addString:(Lscala/collection/TraversableOnce;Lscala/collection/mutable/StringBuilder;Ljava/lang/String;)Lscala/collection/mutable/StringBuilder;
       6: areturn

  public scala.collection.mutable.StringBuilder addString(scala.collection.mutable.StringBuilder);
    Code:
       0: aload_0
       1: aload_1
       2: invokestatic  #901                // Method scala/collection/TraversableOnce$class.addString:(Lscala/collection/TraversableOnce;Lscala/collection/mutable/StringBuilder;)Lscala/collection/mutable/StringBuilder;
       5: areturn

  public abstract byte apply(int);

  public abstract akka.util.ByteString$Companion byteStringCompanion();

  public akka.util.ByteStringBuilder newBuilder();
    Code:
       0: getstatic     #21                 // Field akka/util/ByteString$.MODULE$:Lakka/util/ByteString$;
       3: invokevirtual #908                // Method akka/util/ByteString$.newBuilder:()Lakka/util/ByteStringBuilder;
       6: areturn

  public akka.util.ByteIterator iterator();
    Code:
       0: new           #912                // class java/lang/UnsupportedOperationException
       3: dup
       4: ldc_w         #914                // String Method iterator is not implemented in ByteString
       7: invokespecial #918                // Method java/lang/UnsupportedOperationException."<init>":(Ljava/lang/String;)V
      10: athrow

  public byte head();
    Code:
       0: aload_0
       1: iconst_0
       2: invokevirtual #921                // Method apply:(I)B
       5: ireturn

  public akka.util.ByteString tail();
    Code:
       0: aload_0
       1: iconst_1
       2: invokevirtual #925                // Method drop:(I)Lakka/util/ByteString;
       5: areturn

  public byte last();
    Code:
       0: aload_0
       1: aload_0
       2: invokevirtual #928                // Method length:()I
       5: iconst_1
       6: isub
       7: invokevirtual #921                // Method apply:(I)B
      10: ireturn

  public akka.util.ByteString init();
    Code:
       0: aload_0
       1: iconst_1
       2: invokevirtual #931                // Method dropRight:(I)Lakka/util/ByteString;
       5: areturn

  public akka.util.ByteString take(int);
    Code:
       0: new           #912                // class java/lang/UnsupportedOperationException
       3: dup
       4: ldc_w         #934                // String Method take is not implemented in ByteString
       7: invokespecial #918                // Method java/lang/UnsupportedOperationException."<init>":(Ljava/lang/String;)V
      10: athrow

  public akka.util.ByteString takeRight(int);
    Code:
       0: aload_0
       1: aload_0
       2: invokevirtual #928                // Method length:()I
       5: iload_1
       6: isub
       7: aload_0
       8: invokevirtual #928                // Method length:()I
      11: invokevirtual #939                // Method slice:(II)Lakka/util/ByteString;
      14: areturn

  public akka.util.ByteString slice(int, int);
    Code:
       0: new           #912                // class java/lang/UnsupportedOperationException
       3: dup
       4: ldc_w         #941                // String Method slice is not implemented in ByteString
       7: invokespecial #918                // Method java/lang/UnsupportedOperationException."<init>":(Ljava/lang/String;)V
      10: athrow

  public akka.util.ByteString drop(int);
    Code:
       0: new           #912                // class java/lang/UnsupportedOperationException
       3: dup
       4: ldc_w         #943                // String Method drop is not implemented in ByteString
       7: invokespecial #918                // Method java/lang/UnsupportedOperationException."<init>":(Ljava/lang/String;)V
      10: athrow

  public akka.util.ByteString dropRight(int);
    Code:
       0: new           #912                // class java/lang/UnsupportedOperationException
       3: dup
       4: ldc_w         #945                // String Method dropRight is not implemented in ByteString
       7: invokespecial #918                // Method java/lang/UnsupportedOperationException."<init>":(Ljava/lang/String;)V
      10: athrow

  public akka.util.ByteString takeWhile(scala.Function1<java.lang.Object, java.lang.Object>);
    Code:
       0: aload_0
       1: invokevirtual #949                // Method iterator:()Lakka/util/ByteIterator;
       4: aload_1
       5: invokevirtual #954                // Method akka/util/ByteIterator.takeWhile:(Lscala/Function1;)Lakka/util/ByteIterator;
       8: invokevirtual #957                // Method akka/util/ByteIterator.toByteString:()Lakka/util/ByteString;
      11: areturn

  public akka.util.ByteString dropWhile(scala.Function1<java.lang.Object, java.lang.Object>);
    Code:
       0: aload_0
       1: invokevirtual #949                // Method iterator:()Lakka/util/ByteIterator;
       4: aload_1
       5: invokevirtual #960                // Method akka/util/ByteIterator.dropWhile:(Lscala/Function1;)Lakka/util/ByteIterator;
       8: invokevirtual #957                // Method akka/util/ByteIterator.toByteString:()Lakka/util/ByteString;
      11: areturn

  public scala.Tuple2<akka.util.ByteString, akka.util.ByteString> span(scala.Function1<java.lang.Object, java.lang.Object>);
    Code:
       0: aload_0
       1: invokevirtual #949                // Method iterator:()Lakka/util/ByteIterator;
       4: aload_1
       5: invokevirtual #963                // Method akka/util/ByteIterator.span:(Lscala/Function1;)Lscala/Tuple2;
       8: astore_3
       9: aload_3
      10: ifnull        83
      13: aload_3
      14: invokevirtual #968                // Method scala/Tuple2._1:()Ljava/lang/Object;
      17: checkcast     #951                // class akka/util/ByteIterator
      20: astore        4
      22: aload_3
      23: invokevirtual #971                // Method scala/Tuple2._2:()Ljava/lang/Object;
      26: checkcast     #951                // class akka/util/ByteIterator
      29: astore        5
      31: new           #965                // class scala/Tuple2
      34: dup
      35: aload         4
      37: aload         5
      39: invokespecial #974                // Method scala/Tuple2."<init>":(Ljava/lang/Object;Ljava/lang/Object;)V
      42: astore        6
      44: aload         6
      46: astore_2
      47: aload_2
      48: invokevirtual #968                // Method scala/Tuple2._1:()Ljava/lang/Object;
      51: checkcast     #951                // class akka/util/ByteIterator
      54: astore        7
      56: aload_2
      57: invokevirtual #971                // Method scala/Tuple2._2:()Ljava/lang/Object;
      60: checkcast     #951                // class akka/util/ByteIterator
      63: astore        8
      65: new           #965                // class scala/Tuple2
      68: dup
      69: aload         7
      71: invokevirtual #957                // Method akka/util/ByteIterator.toByteString:()Lakka/util/ByteString;
      74: aload         8
      76: invokevirtual #957                // Method akka/util/ByteIterator.toByteString:()Lakka/util/ByteString;
      79: invokespecial #974                // Method scala/Tuple2."<init>":(Ljava/lang/Object;Ljava/lang/Object;)V
      82: areturn
      83: new           #976                // class scala/MatchError
      86: dup
      87: aload_3
      88: invokespecial #978                // Method scala/MatchError."<init>":(Ljava/lang/Object;)V
      91: athrow

  public scala.Tuple2<akka.util.ByteString, akka.util.ByteString> splitAt(int);
    Code:
       0: new           #965                // class scala/Tuple2
       3: dup
       4: aload_0
       5: iload_1
       6: invokevirtual #984                // Method take:(I)Lakka/util/ByteString;
       9: aload_0
      10: iload_1
      11: invokevirtual #925                // Method drop:(I)Lakka/util/ByteString;
      14: invokespecial #974                // Method scala/Tuple2."<init>":(Ljava/lang/Object;Ljava/lang/Object;)V
      17: areturn

  public int indexWhere(scala.Function1<java.lang.Object, java.lang.Object>);
    Code:
       0: aload_0
       1: invokevirtual #949                // Method iterator:()Lakka/util/ByteIterator;
       4: aload_1
       5: invokevirtual #986                // Method akka/util/ByteIterator.indexWhere:(Lscala/Function1;)I
       8: ireturn

  public <B> int indexOf(B);
    Code:
       0: aload_0
       1: invokevirtual #949                // Method iterator:()Lakka/util/ByteIterator;
       4: aload_1
       5: invokevirtual #988                // Method akka/util/ByteIterator.indexOf:(Ljava/lang/Object;)I
       8: ireturn

  public java.lang.String toString();
    Code:
       0: bipush        100
       2: istore_1
       3: aload_0
       4: invokevirtual #991                // Method size:()I
       7: iload_1
       8: if_icmple     95
      11: new           #993                // class scala/collection/mutable/StringBuilder
      14: dup
      15: invokespecial #996                // Method scala/collection/mutable/StringBuilder."<init>":()V
      18: aload_0
      19: iload_1
      20: invokevirtual #984                // Method take:(I)Lakka/util/ByteString;
      23: invokevirtual #998                // Method toString:()Ljava/lang/String;
      26: invokevirtual #1002               // Method scala/collection/mutable/StringBuilder.append:(Ljava/lang/Object;)Lscala/collection/mutable/StringBuilder;
      29: new           #1004               // class scala/StringContext
      32: dup
      33: getstatic     #1009               // Field scala/Predef$.MODULE$:Lscala/Predef$;
      36: iconst_2
      37: anewarray     #1011               // class java/lang/String
      40: dup
      41: iconst_0
      42: ldc_w         #1013               // String ... and [
      45: aastore
      46: dup
      47: iconst_1
      48: ldc_w         #1015               // String ] more
      51: aastore
      52: checkcast     #1017               // class "[Ljava/lang/Object;"
      55: invokevirtual #1021               // Method scala/Predef$.wrapRefArray:([Ljava/lang/Object;)Lscala/collection/mutable/WrappedArray;
      58: invokespecial #1024               // Method scala/StringContext."<init>":(Lscala/collection/Seq;)V
      61: getstatic     #1009               // Field scala/Predef$.MODULE$:Lscala/Predef$;
      64: iconst_1
      65: anewarray     #5                  // class java/lang/Object
      68: dup
      69: iconst_0
      70: aload_0
      71: invokevirtual #991                // Method size:()I
      74: iload_1
      75: isub
      76: invokestatic  #1030               // Method scala/runtime/BoxesRunTime.boxToInteger:(I)Ljava/lang/Integer;
      79: aastore
      80: invokevirtual #1034               // Method scala/Predef$.genericWrapArray:(Ljava/lang/Object;)Lscala/collection/mutable/WrappedArray;
      83: invokevirtual #1038               // Method scala/StringContext.s:(Lscala/collection/Seq;)Ljava/lang/String;
      86: invokevirtual #1002               // Method scala/collection/mutable/StringBuilder.append:(Ljava/lang/Object;)Lscala/collection/mutable/StringBuilder;
      89: invokevirtual #1039               // Method scala/collection/mutable/StringBuilder.toString:()Ljava/lang/String;
      92: goto          99
      95: aload_0
      96: invokestatic  #1042               // Method scala/collection/SeqLike$class.toString:(Lscala/collection/SeqLike;)Ljava/lang/String;
      99: areturn

  public byte[] toArray();
    Code:
       0: aload_0
       1: getstatic     #1050               // Field scala/reflect/ClassTag$.MODULE$:Lscala/reflect/ClassTag$;
       4: invokevirtual #1054               // Method scala/reflect/ClassTag$.Byte:()Lscala/reflect/ClassTag;
       7: invokevirtual #1057               // Method toArray:(Lscala/reflect/ClassTag;)Ljava/lang/Object;
      10: checkcast     #1059               // class "[B"
      13: areturn

  public <B> java.lang.Object toArray(scala.reflect.ClassTag<B>);
    Code:
       0: aload_0
       1: invokevirtual #949                // Method iterator:()Lakka/util/ByteIterator;
       4: aload_1
       5: invokevirtual #1060               // Method akka/util/ByteIterator.toArray:(Lscala/reflect/ClassTag;)Ljava/lang/Object;
       8: areturn

  public <B> void copyToArray(java.lang.Object, int, int);
    Code:
       0: aload_0
       1: invokevirtual #949                // Method iterator:()Lakka/util/ByteIterator;
       4: aload_1
       5: iload_2
       6: iload_3
       7: invokevirtual #1065               // Method akka/util/ByteIterator.copyToArray:(Ljava/lang/Object;II)V
      10: return

  public <U> void foreach(scala.Function1<java.lang.Object, U>);
    Code:
       0: aload_0
       1: invokevirtual #949                // Method iterator:()Lakka/util/ByteIterator;
       4: aload_1
       5: invokevirtual #1069               // Method akka/util/ByteIterator.foreach:(Lscala/Function1;)V
       8: return

  public abstract void writeToOutputStream(java.io.ObjectOutputStream);

  public abstract akka.util.ByteString $plus$plus(akka.util.ByteString);

  public akka.util.ByteString concat(akka.util.ByteString);
    Code:
       0: aload_0
       1: aload_1
       2: invokevirtual #1075               // Method $plus$plus:(Lakka/util/ByteString;)Lakka/util/ByteString;
       5: areturn

  public int copyToBuffer(java.nio.ByteBuffer);
    Code:
       0: new           #912                // class java/lang/UnsupportedOperationException
       3: dup
       4: ldc_w         #1078               // String Method copyToBuffer is not implemented in ByteString
       7: invokespecial #918                // Method java/lang/UnsupportedOperationException."<init>":(Ljava/lang/String;)V
      10: athrow

  public abstract akka.util.CompactByteString compact();

  public abstract boolean isCompact();

  public abstract java.nio.ByteBuffer asByteBuffer();

  public abstract scala.collection.immutable.Iterable<java.nio.ByteBuffer> asByteBuffers();

  public java.lang.Iterable<java.nio.ByteBuffer> getByteBuffers();
    Code:
       0: getstatic     #1094               // Field scala/collection/JavaConverters$.MODULE$:Lscala/collection/JavaConverters$;
       3: aload_0
       4: invokevirtual #1096               // Method asByteBuffers:()Lscala/collection/immutable/Iterable;
       7: invokevirtual #1100               // Method scala/collection/JavaConverters$.asJavaIterableConverter:(Lscala/collection/Iterable;)Lscala/collection/convert/Decorators$AsJava;
      10: invokevirtual #1105               // Method scala/collection/convert/Decorators$AsJava.asJava:()Ljava/lang/Object;
      13: checkcast     #1107               // class java/lang/Iterable
      16: areturn

  public java.nio.ByteBuffer toByteBuffer();
    Code:
       0: aload_0
       1: invokevirtual #1110               // Method toArray:()[B
       4: invokestatic  #1116               // Method java/nio/ByteBuffer.wrap:([B)Ljava/nio/ByteBuffer;
       7: areturn

  public final java.lang.String utf8String();
    Code:
       0: aload_0
       1: getstatic     #21                 // Field akka/util/ByteString$.MODULE$:Lakka/util/ByteString$;
       4: invokevirtual #43                 // Method akka/util/ByteString$.UTF_8:()Ljava/lang/String;
       7: invokevirtual #1120               // Method decodeString:(Ljava/lang/String;)Ljava/lang/String;
      10: areturn

  public abstract java.lang.String decodeString(java.lang.String);

  public abstract java.lang.String decodeString(java.nio.charset.Charset);

  public final akka.util.ByteString mapI(scala.Function1<java.lang.Object, java.lang.Object>);
    Code:
       0: aload_0
       1: aload_1
       2: new           #1124               // class akka/util/ByteString$$anonfun$mapI$1
       5: dup
       6: aload_0
       7: invokespecial #1127               // Method akka/util/ByteString$$anonfun$mapI$1."<init>":(Lakka/util/ByteString;)V
      10: invokeinterface #1131,  2         // InterfaceMethod scala/Function1.andThen:(Lscala/Function1;)Lscala/Function1;
      15: getstatic     #21                 // Field akka/util/ByteString$.MODULE$:Lakka/util/ByteString$;
      18: invokevirtual #27                 // Method akka/util/ByteString$.canBuildFrom:()Lscala/collection/generic/CanBuildFrom;
      21: invokevirtual #1133               // Method map:(Lscala/Function1;Lscala/collection/generic/CanBuildFrom;)Ljava/lang/Object;
      24: checkcast     #2                  // class akka/util/ByteString
      27: areturn

  public void foreach$mZc$sp(scala.Function1<java.lang.Object, java.lang.Object>);
    Code:
       0: aload_0
       1: invokevirtual #949                // Method iterator:()Lakka/util/ByteIterator;
       4: aload_1
       5: invokevirtual #1136               // Method akka/util/ByteIterator.foreach$mZc$sp:(Lscala/Function1;)V
       8: return

  public void foreach$mBc$sp(scala.Function1<java.lang.Object, java.lang.Object>);
    Code:
       0: aload_0
       1: invokevirtual #949                // Method iterator:()Lakka/util/ByteIterator;
       4: aload_1
       5: invokevirtual #1139               // Method akka/util/ByteIterator.foreach$mBc$sp:(Lscala/Function1;)V
       8: return

  public void foreach$mCc$sp(scala.Function1<java.lang.Object, java.lang.Object>);
    Code:
       0: aload_0
       1: invokevirtual #949                // Method iterator:()Lakka/util/ByteIterator;
       4: aload_1
       5: invokevirtual #1142               // Method akka/util/ByteIterator.foreach$mCc$sp:(Lscala/Function1;)V
       8: return

  public void foreach$mDc$sp(scala.Function1<java.lang.Object, java.lang.Object>);
    Code:
       0: aload_0
       1: invokevirtual #949                // Method iterator:()Lakka/util/ByteIterator;
       4: aload_1
       5: invokevirtual #1145               // Method akka/util/ByteIterator.foreach$mDc$sp:(Lscala/Function1;)V
       8: return

  public void foreach$mFc$sp(scala.Function1<java.lang.Object, java.lang.Object>);
    Code:
       0: aload_0
       1: invokevirtual #949                // Method iterator:()Lakka/util/ByteIterator;
       4: aload_1
       5: invokevirtual #1148               // Method akka/util/ByteIterator.foreach$mFc$sp:(Lscala/Function1;)V
       8: return

  public void foreach$mIc$sp(scala.Function1<java.lang.Object, java.lang.Object>);
    Code:
       0: aload_0
       1: invokevirtual #949                // Method iterator:()Lakka/util/ByteIterator;
       4: aload_1
       5: invokevirtual #1151               // Method akka/util/ByteIterator.foreach$mIc$sp:(Lscala/Function1;)V
       8: return

  public void foreach$mJc$sp(scala.Function1<java.lang.Object, java.lang.Object>);
    Code:
       0: aload_0
       1: invokevirtual #949                // Method iterator:()Lakka/util/ByteIterator;
       4: aload_1
       5: invokevirtual #1154               // Method akka/util/ByteIterator.foreach$mJc$sp:(Lscala/Function1;)V
       8: return

  public void foreach$mSc$sp(scala.Function1<java.lang.Object, java.lang.Object>);
    Code:
       0: aload_0
       1: invokevirtual #949                // Method iterator:()Lakka/util/ByteIterator;
       4: aload_1
       5: invokevirtual #1157               // Method akka/util/ByteIterator.foreach$mSc$sp:(Lscala/Function1;)V
       8: return

  public void foreach$mVc$sp(scala.Function1<java.lang.Object, scala.runtime.BoxedUnit>);
    Code:
       0: aload_0
       1: invokevirtual #949                // Method iterator:()Lakka/util/ByteIterator;
       4: aload_1
       5: invokevirtual #1160               // Method akka/util/ByteIterator.foreach$mVc$sp:(Lscala/Function1;)V
       8: return

  public scala.collection.GenMap toMap(scala.Predef$$less$colon$less);
    Code:
       0: aload_0
       1: aload_1
       2: invokevirtual #1163               // Method toMap:(Lscala/Predef$$less$colon$less;)Lscala/collection/immutable/Map;
       5: areturn

  public scala.collection.GenSet toSet();
    Code:
       0: aload_0
       1: invokevirtual #1166               // Method toSet:()Lscala/collection/immutable/Set;
       4: areturn

  public scala.collection.GenTraversable toTraversable();
    Code:
       0: aload_0
       1: invokevirtual #1169               // Method toTraversable:()Lscala/collection/Traversable;
       4: areturn

  public scala.collection.GenMap groupBy(scala.Function1);
    Code:
       0: aload_0
       1: aload_1
       2: invokevirtual #1172               // Method groupBy:(Lscala/Function1;)Lscala/collection/immutable/Map;
       5: areturn

  public scala.collection.GenIterable toIterable();
    Code:
       0: aload_0
       1: invokevirtual #1175               // Method toIterable:()Lscala/collection/Iterable;
       4: areturn

  public scala.Function1 andThen(scala.Function1);
    Code:
       0: aload_0
       1: aload_1
       2: invokevirtual #1177               // Method andThen:(Lscala/Function1;)Lscala/PartialFunction;
       5: areturn

  public boolean isDefinedAt(java.lang.Object);
    Code:
       0: aload_0
       1: aload_1
       2: invokestatic  #1180               // Method scala/runtime/BoxesRunTime.unboxToInt:(Ljava/lang/Object;)I
       5: invokevirtual #1182               // Method isDefinedAt:(I)Z
       8: ireturn

  public scala.collection.TraversableView view(int, int);
    Code:
       0: aload_0
       1: iload_1
       2: iload_2
       3: invokevirtual #1185               // Method view:(II)Lscala/collection/SeqView;
       6: areturn

  public scala.collection.IterableView view(int, int);
    Code:
       0: aload_0
       1: iload_1
       2: iload_2
       3: invokevirtual #1185               // Method view:(II)Lscala/collection/SeqView;
       6: areturn

  public scala.collection.TraversableView view();
    Code:
       0: aload_0
       1: invokevirtual #1189               // Method view:()Lscala/collection/SeqView;
       4: areturn

  public scala.collection.IterableView view();
    Code:
       0: aload_0
       1: invokevirtual #1189               // Method view:()Lscala/collection/SeqView;
       4: areturn

  public scala.collection.GenSeq toSeq();
    Code:
       0: aload_0
       1: invokevirtual #1193               // Method toSeq:()Lscala/collection/immutable/Seq;
       4: areturn

  public scala.collection.Seq toSeq();
    Code:
       0: aload_0
       1: invokevirtual #1193               // Method toSeq:()Lscala/collection/immutable/Seq;
       4: areturn

  public scala.collection.Traversable toCollection(java.lang.Object);
    Code:
       0: aload_0
       1: aload_1
       2: invokevirtual #1197               // Method toCollection:(Ljava/lang/Object;)Lscala/collection/IndexedSeq;
       5: areturn

  public scala.collection.Iterable toCollection(java.lang.Object);
    Code:
       0: aload_0
       1: aload_1
       2: invokevirtual #1197               // Method toCollection:(Ljava/lang/Object;)Lscala/collection/IndexedSeq;
       5: areturn

  public scala.collection.Seq toCollection(java.lang.Object);
    Code:
       0: aload_0
       1: aload_1
       2: invokevirtual #1197               // Method toCollection:(Ljava/lang/Object;)Lscala/collection/IndexedSeq;
       5: areturn

  public scala.collection.Traversable thisCollection();
    Code:
       0: aload_0
       1: invokevirtual #1201               // Method thisCollection:()Lscala/collection/IndexedSeq;
       4: areturn

  public scala.collection.Iterable thisCollection();
    Code:
       0: aload_0
       1: invokevirtual #1201               // Method thisCollection:()Lscala/collection/IndexedSeq;
       4: areturn

  public scala.collection.Seq thisCollection();
    Code:
       0: aload_0
       1: invokevirtual #1201               // Method thisCollection:()Lscala/collection/IndexedSeq;
       4: areturn

  public scala.collection.TraversableOnce seq();
    Code:
       0: aload_0
       1: invokevirtual #1204               // Method seq:()Lscala/collection/immutable/IndexedSeq;
       4: areturn

  public scala.collection.Traversable seq();
    Code:
       0: aload_0
       1: invokevirtual #1204               // Method seq:()Lscala/collection/immutable/IndexedSeq;
       4: areturn

  public scala.collection.immutable.Traversable seq();
    Code:
       0: aload_0
       1: invokevirtual #1204               // Method seq:()Lscala/collection/immutable/IndexedSeq;
       4: areturn

  public scala.collection.Iterable seq();
    Code:
       0: aload_0
       1: invokevirtual #1204               // Method seq:()Lscala/collection/immutable/IndexedSeq;
       4: areturn

  public scala.collection.immutable.Iterable seq();
    Code:
       0: aload_0
       1: invokevirtual #1204               // Method seq:()Lscala/collection/immutable/IndexedSeq;
       4: areturn

  public scala.collection.Seq seq();
    Code:
       0: aload_0
       1: invokevirtual #1204               // Method seq:()Lscala/collection/immutable/IndexedSeq;
       4: areturn

  public scala.collection.immutable.Seq seq();
    Code:
       0: aload_0
       1: invokevirtual #1204               // Method seq:()Lscala/collection/immutable/IndexedSeq;
       4: areturn

  public scala.collection.IndexedSeq seq();
    Code:
       0: aload_0
       1: invokevirtual #1204               // Method seq:()Lscala/collection/immutable/IndexedSeq;
       4: areturn

  public java.lang.Object dropWhile(scala.Function1);
    Code:
       0: aload_0
       1: aload_1
       2: invokevirtual #1207               // Method dropWhile:(Lscala/Function1;)Lakka/util/ByteString;
       5: areturn

  public java.lang.Object takeWhile(scala.Function1);
    Code:
       0: aload_0
       1: aload_1
       2: invokevirtual #1209               // Method takeWhile:(Lscala/Function1;)Lakka/util/ByteString;
       5: areturn

  public java.lang.Object dropRight(int);
    Code:
       0: aload_0
       1: iload_1
       2: invokevirtual #931                // Method dropRight:(I)Lakka/util/ByteString;
       5: areturn

  public java.lang.Object drop(int);
    Code:
       0: aload_0
       1: iload_1
       2: invokevirtual #925                // Method drop:(I)Lakka/util/ByteString;
       5: areturn

  public java.lang.Object slice(int, int);
    Code:
       0: aload_0
       1: iload_1
       2: iload_2
       3: invokevirtual #939                // Method slice:(II)Lakka/util/ByteString;
       6: areturn

  public java.lang.Object takeRight(int);
    Code:
       0: aload_0
       1: iload_1
       2: invokevirtual #1212               // Method takeRight:(I)Lakka/util/ByteString;
       5: areturn

  public java.lang.Object take(int);
    Code:
       0: aload_0
       1: iload_1
       2: invokevirtual #984                // Method take:(I)Lakka/util/ByteString;
       5: areturn

  public java.lang.Object init();
    Code:
       0: aload_0
       1: invokevirtual #1214               // Method init:()Lakka/util/ByteString;
       4: areturn

  public java.lang.Object last();
    Code:
       0: aload_0
       1: invokevirtual #1216               // Method last:()B
       4: invokestatic  #1220               // Method scala/runtime/BoxesRunTime.boxToByte:(B)Ljava/lang/Byte;
       7: areturn

  public java.lang.Object tail();
    Code:
       0: aload_0
       1: invokevirtual #1222               // Method tail:()Lakka/util/ByteString;
       4: areturn

  public java.lang.Object head();
    Code:
       0: aload_0
       1: invokevirtual #1224               // Method head:()B
       4: invokestatic  #1220               // Method scala/runtime/BoxesRunTime.boxToByte:(B)Ljava/lang/Byte;
       7: areturn

  public scala.collection.Iterator iterator();
    Code:
       0: aload_0
       1: invokevirtual #949                // Method iterator:()Lakka/util/ByteIterator;
       4: areturn

  public scala.collection.mutable.Builder newBuilder();
    Code:
       0: aload_0
       1: invokevirtual #1225               // Method newBuilder:()Lakka/util/ByteStringBuilder;
       4: areturn

  public akka.util.ByteString();
    Code:
       0: aload_0
       1: invokespecial #1226               // Method java/lang/Object."<init>":()V
       4: aload_0
       5: invokestatic  #1230               // Method scala/collection/TraversableOnce$class.$init$:(Lscala/collection/TraversableOnce;)V
       8: aload_0
       9: invokestatic  #1233               // Method scala/collection/Parallelizable$class.$init$:(Lscala/collection/Parallelizable;)V
      12: aload_0
      13: invokestatic  #1236               // Method scala/collection/TraversableLike$class.$init$:(Lscala/collection/TraversableLike;)V
      16: aload_0
      17: invokestatic  #1239               // Method scala/collection/generic/GenericTraversableTemplate$class.$init$:(Lscala/collection/generic/GenericTraversableTemplate;)V
      20: aload_0
      21: invokestatic  #1244               // Method scala/collection/GenTraversable$class.$init$:(Lscala/collection/GenTraversable;)V
      24: aload_0
      25: invokestatic  #1249               // Method scala/collection/Traversable$class.$init$:(Lscala/collection/Traversable;)V
      28: aload_0
      29: invokestatic  #1254               // Method scala/collection/immutable/Traversable$class.$init$:(Lscala/collection/immutable/Traversable;)V
      32: aload_0
      33: invokestatic  #1259               // Method scala/collection/GenIterable$class.$init$:(Lscala/collection/GenIterable;)V
      36: aload_0
      37: invokestatic  #1262               // Method scala/collection/IterableLike$class.$init$:(Lscala/collection/IterableLike;)V
      40: aload_0
      41: invokestatic  #1267               // Method scala/collection/Iterable$class.$init$:(Lscala/collection/Iterable;)V
      44: aload_0
      45: invokestatic  #1272               // Method scala/collection/immutable/Iterable$class.$init$:(Lscala/collection/immutable/Iterable;)V
      48: aload_0
      49: invokestatic  #1274               // Method scala/Function1$class.$init$:(Lscala/Function1;)V
      52: aload_0
      53: invokestatic  #1277               // Method scala/PartialFunction$class.$init$:(Lscala/PartialFunction;)V
      56: aload_0
      57: invokestatic  #1280               // Method scala/collection/GenSeqLike$class.$init$:(Lscala/collection/GenSeqLike;)V
      60: aload_0
      61: invokestatic  #1285               // Method scala/collection/GenSeq$class.$init$:(Lscala/collection/GenSeq;)V
      64: aload_0
      65: invokestatic  #1288               // Method scala/collection/SeqLike$class.$init$:(Lscala/collection/SeqLike;)V
      68: aload_0
      69: invokestatic  #1292               // Method scala/collection/Seq$class.$init$:(Lscala/collection/Seq;)V
      72: aload_0
      73: invokestatic  #1295               // Method scala/collection/immutable/Seq$class.$init$:(Lscala/collection/immutable/Seq;)V
      76: aload_0
      77: invokestatic  #1298               // Method scala/collection/IndexedSeqLike$class.$init$:(Lscala/collection/IndexedSeqLike;)V
      80: aload_0
      81: invokestatic  #1303               // Method scala/collection/IndexedSeq$class.$init$:(Lscala/collection/IndexedSeq;)V
      84: aload_0
      85: invokestatic  #1306               // Method scala/collection/immutable/IndexedSeq$class.$init$:(Lscala/collection/immutable/IndexedSeq;)V
      88: aload_0
      89: invokestatic  #1309               // Method scala/collection/IndexedSeqOptimized$class.$init$:(Lscala/collection/IndexedSeqOptimized;)V
      92: return
}
