Compiled from "Crypt.scala"
public final class akka.util.Crypt {
  public static java.lang.String hexify(byte[]);
    Code:
       0: getstatic     #16                 // Field akka/util/Crypt$.MODULE$:Lakka/util/Crypt$;
       3: aload_0
       4: invokevirtual #18                 // Method akka/util/Crypt$.hexify:([B)Ljava/lang/String;
       7: areturn

  public static java.lang.String digest(byte[], java.security.MessageDigest);
    Code:
       0: getstatic     #16                 // Field akka/util/Crypt$.MODULE$:Lakka/util/Crypt$;
       3: aload_0
       4: aload_1
       5: invokevirtual #22                 // Method akka/util/Crypt$.digest:([BLjava/security/MessageDigest;)Ljava/lang/String;
       8: areturn

  public static java.lang.String generateSecureCookie();
    Code:
       0: getstatic     #16                 // Field akka/util/Crypt$.MODULE$:Lakka/util/Crypt$;
       3: invokevirtual #26                 // Method akka/util/Crypt$.generateSecureCookie:()Ljava/lang/String;
       6: areturn

  public static java.lang.String sha1(byte[]);
    Code:
       0: getstatic     #16                 // Field akka/util/Crypt$.MODULE$:Lakka/util/Crypt$;
       3: aload_0
       4: invokevirtual #29                 // Method akka/util/Crypt$.sha1:([B)Ljava/lang/String;
       7: areturn

  public static java.lang.String sha1(java.lang.String);
    Code:
       0: getstatic     #16                 // Field akka/util/Crypt$.MODULE$:Lakka/util/Crypt$;
       3: aload_0
       4: invokevirtual #32                 // Method akka/util/Crypt$.sha1:(Ljava/lang/String;)Ljava/lang/String;
       7: areturn

  public static java.lang.String md5(byte[]);
    Code:
       0: getstatic     #16                 // Field akka/util/Crypt$.MODULE$:Lakka/util/Crypt$;
       3: aload_0
       4: invokevirtual #35                 // Method akka/util/Crypt$.md5:([B)Ljava/lang/String;
       7: areturn

  public static java.lang.String md5(java.lang.String);
    Code:
       0: getstatic     #16                 // Field akka/util/Crypt$.MODULE$:Lakka/util/Crypt$;
       3: aload_0
       4: invokevirtual #37                 // Method akka/util/Crypt$.md5:(Ljava/lang/String;)Ljava/lang/String;
       7: areturn

  public static java.security.SecureRandom random();
    Code:
       0: getstatic     #16                 // Field akka/util/Crypt$.MODULE$:Lakka/util/Crypt$;
       3: invokevirtual #41                 // Method akka/util/Crypt$.random:()Ljava/security/SecureRandom;
       6: areturn

  public static java.lang.String lineSeparator();
    Code:
       0: getstatic     #16                 // Field akka/util/Crypt$.MODULE$:Lakka/util/Crypt$;
       3: invokevirtual #44                 // Method akka/util/Crypt$.lineSeparator:()Ljava/lang/String;
       6: areturn

  public static java.lang.String hex();
    Code:
       0: getstatic     #16                 // Field akka/util/Crypt$.MODULE$:Lakka/util/Crypt$;
       3: invokevirtual #47                 // Method akka/util/Crypt$.hex:()Ljava/lang/String;
       6: areturn
}
