Compiled from "PrettyByteString.scala"
public final class akka.util.PrettyByteString$$anonfun$1 extends scala.runtime.AbstractFunction1<java.lang.Object, java.lang.String> implements scala.Serializable {
  public static final long serialVersionUID;

  public final java.lang.String apply(byte);
    Code:
       0: getstatic     #23                 // Field akka/util/PrettyByteString$.MODULE$:Lakka/util/PrettyByteString$;
       3: iload_1
       4: invokevirtual #26                 // Method akka/util/PrettyByteString$.akka$util$PrettyByteString$$asHex$1:(B)Ljava/lang/String;
       7: areturn

  public final java.lang.Object apply(java.lang.Object);
    Code:
       0: aload_0
       1: aload_1
       2: invokestatic  #37                 // Method scala/runtime/BoxesRunTime.unboxToByte:(Ljava/lang/Object;)B
       5: invokevirtual #39                 // Method apply:(B)Ljava/lang/String;
       8: areturn

  public akka.util.PrettyByteString$$anonfun$1();
    Code:
       0: aload_0
       1: invokespecial #45                 // Method scala/runtime/AbstractFunction1."<init>":()V
       4: return
}
