Compiled from "XOPDecodingStreamReader.java"
class org.apache.axiom.util.stax.xop.XOPDecodingStreamReader$DataHandlerProviderImpl implements org.apache.axiom.ext.stax.datahandler.DataHandlerProvider {
  private final org.apache.axiom.util.stax.xop.MimePartProvider mimePartProvider;

  private final java.lang.String contentID;

  public org.apache.axiom.util.stax.xop.XOPDecodingStreamReader$DataHandlerProviderImpl(org.apache.axiom.util.stax.xop.MimePartProvider, java.lang.String);
    Code:
       0: aload_0
       1: invokespecial #1                  // Method java/lang/Object."<init>":()V
       4: aload_0
       5: aload_1
       6: putfield      #2                  // Field mimePartProvider:Lorg/apache/axiom/util/stax/xop/MimePartProvider;
       9: aload_0
      10: aload_2
      11: putfield      #3                  // Field contentID:Ljava/lang/String;
      14: return

  public java.lang.String getContentID();
    Code:
       0: aload_0
       1: getfield      #3                  // Field contentID:Ljava/lang/String;
       4: areturn

  public boolean isLoaded();
    Code:
       0: aload_0
       1: getfield      #2                  // Field mimePartProvider:Lorg/apache/axiom/util/stax/xop/MimePartProvider;
       4: aload_0
       5: getfield      #3                  // Field contentID:Ljava/lang/String;
       8: invokeinterface #4,  2            // InterfaceMethod org/apache/axiom/util/stax/xop/MimePartProvider.isLoaded:(Ljava/lang/String;)Z
      13: ireturn

  public javax.activation.DataHandler getDataHandler() throws java.io.IOException;
    Code:
       0: aload_0
       1: getfield      #2                  // Field mimePartProvider:Lorg/apache/axiom/util/stax/xop/MimePartProvider;
       4: aload_0
       5: getfield      #3                  // Field contentID:Ljava/lang/String;
       8: invokeinterface #5,  2            // InterfaceMethod org/apache/axiom/util/stax/xop/MimePartProvider.getDataHandler:(Ljava/lang/String;)Ljavax/activation/DataHandler;
      13: areturn
}
