Compiled from "ServletWebServerFactoryConfiguration.java"
class org.springframework.boot.autoconfigure.web.servlet.ServletWebServerFactoryConfiguration$EmbeddedUndertow {
  org.springframework.boot.autoconfigure.web.servlet.ServletWebServerFactoryConfiguration$EmbeddedUndertow();
    Code:
       0: aload_0
       1: invokespecial #1                  // Method java/lang/Object."<init>":()V
       4: return

  org.springframework.boot.web.embedded.undertow.UndertowServletWebServerFactory undertowServletWebServerFactory(org.springframework.beans.factory.ObjectProvider<org.springframework.boot.web.embedded.undertow.UndertowDeploymentInfoCustomizer>, org.springframework.beans.factory.ObjectProvider<org.springframework.boot.web.embedded.undertow.UndertowBuilderCustomizer>);
    Code:
       0: new           #2                  // class org/springframework/boot/web/embedded/undertow/UndertowServletWebServerFactory
       3: dup
       4: invokespecial #3                  // Method org/springframework/boot/web/embedded/undertow/UndertowServletWebServerFactory."<init>":()V
       7: astore_3
       8: aload_3
       9: invokevirtual #4                  // Method org/springframework/boot/web/embedded/undertow/UndertowServletWebServerFactory.getDeploymentInfoCustomizers:()Ljava/util/Collection;
      12: aload_1
      13: invokeinterface #5,  1            // InterfaceMethod org/springframework/beans/factory/ObjectProvider.orderedStream:()Ljava/util/stream/Stream;
      18: invokestatic  #6                  // Method java/util/stream/Collectors.toList:()Ljava/util/stream/Collector;
      21: invokeinterface #7,  2            // InterfaceMethod java/util/stream/Stream.collect:(Ljava/util/stream/Collector;)Ljava/lang/Object;
      26: checkcast     #8                  // class java/util/Collection
      29: invokeinterface #9,  2            // InterfaceMethod java/util/Collection.addAll:(Ljava/util/Collection;)Z
      34: pop
      35: aload_3
      36: invokevirtual #10                 // Method org/springframework/boot/web/embedded/undertow/UndertowServletWebServerFactory.getBuilderCustomizers:()Ljava/util/Collection;
      39: aload_2
      40: invokeinterface #5,  1            // InterfaceMethod org/springframework/beans/factory/ObjectProvider.orderedStream:()Ljava/util/stream/Stream;
      45: invokestatic  #6                  // Method java/util/stream/Collectors.toList:()Ljava/util/stream/Collector;
      48: invokeinterface #7,  2            // InterfaceMethod java/util/stream/Stream.collect:(Ljava/util/stream/Collector;)Ljava/lang/Object;
      53: checkcast     #8                  // class java/util/Collection
      56: invokeinterface #9,  2            // InterfaceMethod java/util/Collection.addAll:(Ljava/util/Collection;)Z
      61: pop
      62: aload_3
      63: areturn
}
