Compiled from "WebMvcAutoConfiguration.java"
public class org.springframework.boot.autoconfigure.web.servlet.WebMvcAutoConfiguration {
  public static final java.lang.String DEFAULT_PREFIX;

  public static final java.lang.String DEFAULT_SUFFIX;

  private static final java.lang.String[] SERVLET_LOCATIONS;

  public org.springframework.boot.autoconfigure.web.servlet.WebMvcAutoConfiguration();
    Code:
       0: aload_0
       1: invokespecial #1                  // Method java/lang/Object."<init>":()V
       4: return

  public org.springframework.boot.web.servlet.filter.OrderedHiddenHttpMethodFilter hiddenHttpMethodFilter();
    Code:
       0: new           #2                  // class org/springframework/boot/web/servlet/filter/OrderedHiddenHttpMethodFilter
       3: dup
       4: invokespecial #3                  // Method org/springframework/boot/web/servlet/filter/OrderedHiddenHttpMethodFilter."<init>":()V
       7: areturn

  public org.springframework.boot.web.servlet.filter.OrderedFormContentFilter formContentFilter();
    Code:
       0: new           #4                  // class org/springframework/boot/web/servlet/filter/OrderedFormContentFilter
       3: dup
       4: invokespecial #5                  // Method org/springframework/boot/web/servlet/filter/OrderedFormContentFilter."<init>":()V
       7: areturn

  static java.lang.String[] getResourceLocations(java.lang.String[]);
    Code:
       0: aload_0
       1: arraylength
       2: getstatic     #6                  // Field SERVLET_LOCATIONS:[Ljava/lang/String;
       5: arraylength
       6: iadd
       7: anewarray     #7                  // class java/lang/String
      10: astore_1
      11: aload_0
      12: iconst_0
      13: aload_1
      14: iconst_0
      15: aload_0
      16: arraylength
      17: invokestatic  #8                  // Method java/lang/System.arraycopy:(Ljava/lang/Object;ILjava/lang/Object;II)V
      20: getstatic     #6                  // Field SERVLET_LOCATIONS:[Ljava/lang/String;
      23: iconst_0
      24: aload_1
      25: aload_0
      26: arraylength
      27: getstatic     #6                  // Field SERVLET_LOCATIONS:[Ljava/lang/String;
      30: arraylength
      31: invokestatic  #8                  // Method java/lang/System.arraycopy:(Ljava/lang/Object;ILjava/lang/Object;II)V
      34: aload_1
      35: areturn

  static {};
    Code:
       0: iconst_1
       1: anewarray     #7                  // class java/lang/String
       4: dup
       5: iconst_0
       6: ldc           #9                  // String /
       8: aastore
       9: putstatic     #6                  // Field SERVLET_LOCATIONS:[Ljava/lang/String;
      12: return
}
