Compiled from "TypedXMLStreamException.java"
public class org.codehaus.stax2.typed.TypedXMLStreamException extends javax.xml.stream.XMLStreamException {
  private static final long serialVersionUID;

  protected java.lang.String mLexical;

  public org.codehaus.stax2.typed.TypedXMLStreamException(java.lang.String, java.lang.String);
    Code:
       0: aload_0
       1: aload_2
       2: invokespecial #1                  // Method javax/xml/stream/XMLStreamException."<init>":(Ljava/lang/String;)V
       5: aload_0
       6: aload_1
       7: putfield      #2                  // Field mLexical:Ljava/lang/String;
      10: return

  public org.codehaus.stax2.typed.TypedXMLStreamException(java.lang.String, java.lang.IllegalArgumentException);
    Code:
       0: aload_0
       1: aload_2
       2: invokespecial #3                  // Method javax/xml/stream/XMLStreamException."<init>":(Ljava/lang/Throwable;)V
       5: aload_0
       6: aload_1
       7: putfield      #2                  // Field mLexical:Ljava/lang/String;
      10: return

  public org.codehaus.stax2.typed.TypedXMLStreamException(java.lang.String, java.lang.String, java.lang.IllegalArgumentException);
    Code:
       0: aload_0
       1: aload_2
       2: aload_3
       3: invokespecial #4                  // Method javax/xml/stream/XMLStreamException."<init>":(Ljava/lang/String;Ljava/lang/Throwable;)V
       6: aload_0
       7: aload_1
       8: putfield      #2                  // Field mLexical:Ljava/lang/String;
      11: return

  public org.codehaus.stax2.typed.TypedXMLStreamException(java.lang.String, java.lang.String, javax.xml.stream.Location, java.lang.IllegalArgumentException);
    Code:
       0: aload_0
       1: aload_2
       2: aload_3
       3: aload         4
       5: invokespecial #5                  // Method javax/xml/stream/XMLStreamException."<init>":(Ljava/lang/String;Ljavax/xml/stream/Location;Ljava/lang/Throwable;)V
       8: aload_0
       9: aload_1
      10: putfield      #2                  // Field mLexical:Ljava/lang/String;
      13: return

  public org.codehaus.stax2.typed.TypedXMLStreamException(java.lang.String, java.lang.String, javax.xml.stream.Location);
    Code:
       0: aload_0
       1: aload_2
       2: aload_3
       3: invokespecial #6                  // Method javax/xml/stream/XMLStreamException."<init>":(Ljava/lang/String;Ljavax/xml/stream/Location;)V
       6: aload_0
       7: aload_1
       8: putfield      #2                  // Field mLexical:Ljava/lang/String;
      11: return

  public java.lang.String getLexical();
    Code:
       0: aload_0
       1: getfield      #2                  // Field mLexical:Ljava/lang/String;
       4: areturn
}
