Compiled from "NamedBootstrapContext.java"
public class org.jboss.as.connector.services.bootstrap.NamedBootstrapContext extends org.jboss.jca.core.bootstrapcontext.BaseCloneableBootstrapContext {
  public static final java.lang.String DEFAULT_NAME;

  private java.lang.String name;

  public org.jboss.as.connector.services.bootstrap.NamedBootstrapContext(java.lang.String);
    Code:
       0: aload_0
       1: invokespecial #1                  // Method org/jboss/jca/core/bootstrapcontext/BaseCloneableBootstrapContext."<init>":()V
       4: aload_0
       5: aload_1
       6: invokevirtual #2                  // Method setName:(Ljava/lang/String;)V
       9: return

  public java.lang.String getName();
    Code:
       0: aload_0
       1: getfield      #3                  // Field name:Ljava/lang/String;
       4: areturn

  public void setName(java.lang.String);
    Code:
       0: aload_0
       1: aload_1
       2: putfield      #3                  // Field name:Ljava/lang/String;
       5: return

  public org.jboss.jca.core.api.bootstrap.CloneableBootstrapContext clone() throws java.lang.CloneNotSupportedException;
    Code:
       0: aload_0
       1: invokespecial #4                  // Method org/jboss/jca/core/bootstrapcontext/BaseCloneableBootstrapContext.clone:()Lorg/jboss/jca/core/api/bootstrap/CloneableBootstrapContext;
       4: checkcast     #5                  // class org/jboss/as/connector/services/bootstrap/NamedBootstrapContext
       7: astore_1
       8: aload_1
       9: aload_0
      10: invokevirtual #6                  // Method getName:()Ljava/lang/String;
      13: invokevirtual #2                  // Method setName:(Ljava/lang/String;)V
      16: aload_1
      17: areturn

  public java.lang.Object clone() throws java.lang.CloneNotSupportedException;
    Code:
       0: aload_0
       1: invokevirtual #7                  // Method clone:()Lorg/jboss/jca/core/api/bootstrap/CloneableBootstrapContext;
       4: areturn
}
