Compiled from "SourceType.java"
public class org.apache.cxf.aegis.type.xml.SourceType extends org.apache.cxf.aegis.type.AegisType {
  public org.apache.cxf.aegis.type.xml.SourceType();
    Code:
       0: aload_0
       1: invokespecial #1                  // Method org/apache/cxf/aegis/type/AegisType."<init>":()V
       4: aload_0
       5: ldc_w         #2                  // class javax/xml/transform/Source
       8: invokevirtual #3                  // Method setTypeClass:(Ljava/lang/reflect/Type;)V
      11: aload_0
      12: iconst_0
      13: invokevirtual #4                  // Method setWriteOuter:(Z)V
      16: return

  public java.lang.Object readObject(org.apache.cxf.aegis.xml.MessageReader, org.apache.cxf.aegis.Context) throws org.apache.cxf.aegis.DatabindingException;
    Code:
       0: aload_0
       1: invokevirtual #5                  // Method getTypeMapping:()Lorg/apache/cxf/aegis/type/TypeMapping;
       4: ldc_w         #6                  // class org/w3c/dom/Document
       7: invokeinterface #7,  2            // InterfaceMethod org/apache/cxf/aegis/type/TypeMapping.getType:(Ljava/lang/reflect/Type;)Lorg/apache/cxf/aegis/type/AegisType;
      12: checkcast     #8                  // class org/apache/cxf/aegis/type/xml/DocumentType
      15: astore_3
      16: new           #9                  // class javax/xml/transform/dom/DOMSource
      19: dup
      20: aload_3
      21: aload_1
      22: aload_2
      23: invokevirtual #10                 // Method org/apache/cxf/aegis/type/xml/DocumentType.readObject:(Lorg/apache/cxf/aegis/xml/MessageReader;Lorg/apache/cxf/aegis/Context;)Ljava/lang/Object;
      26: checkcast     #6                  // class org/w3c/dom/Document
      29: invokespecial #11                 // Method javax/xml/transform/dom/DOMSource."<init>":(Lorg/w3c/dom/Node;)V
      32: areturn

  public void writeObject(java.lang.Object, org.apache.cxf.aegis.xml.MessageWriter, org.apache.cxf.aegis.Context) throws org.apache.cxf.aegis.DatabindingException;
    Code:
       0: aload_1
       1: ifnonnull     5
       4: return
       5: aload_0
       6: aload_1
       7: checkcast     #2                  // class javax/xml/transform/Source
      10: aload_2
      11: checkcast     #12                 // class org/apache/cxf/aegis/xml/stax/ElementWriter
      14: invokevirtual #13                 // Method org/apache/cxf/aegis/xml/stax/ElementWriter.getXMLStreamWriter:()Ljavax/xml/stream/XMLStreamWriter;
      17: invokevirtual #14                 // Method write:(Ljavax/xml/transform/Source;Ljavax/xml/stream/XMLStreamWriter;)V
      20: goto          37
      23: astore        4
      25: new           #16                 // class org/apache/cxf/aegis/DatabindingException
      28: dup
      29: ldc           #17                 // String Could not write xml.
      31: aload         4
      33: invokespecial #18                 // Method org/apache/cxf/aegis/DatabindingException."<init>":(Ljava/lang/String;Ljava/lang/Throwable;)V
      36: athrow
      37: return
    Exception table:
       from    to  target type
           0     4    23   Class javax/xml/stream/XMLStreamException
           5    20    23   Class javax/xml/stream/XMLStreamException

  protected void write(javax.xml.transform.Source, javax.xml.stream.XMLStreamWriter) throws javax.xml.stream.FactoryConfigurationError, javax.xml.stream.XMLStreamException, org.apache.cxf.aegis.DatabindingException;
    Code:
       0: aload_1
       1: ifnonnull     5
       4: return
       5: aload_1
       6: instanceof    #9                  // class javax/xml/transform/dom/DOMSource
       9: ifeq          117
      12: aload_1
      13: checkcast     #9                  // class javax/xml/transform/dom/DOMSource
      16: astore_3
      17: aconst_null
      18: astore        4
      20: aload_3
      21: invokevirtual #19                 // Method javax/xml/transform/dom/DOMSource.getNode:()Lorg/w3c/dom/Node;
      24: instanceof    #20                 // class org/w3c/dom/Element
      27: ifeq          42
      30: aload_3
      31: invokevirtual #19                 // Method javax/xml/transform/dom/DOMSource.getNode:()Lorg/w3c/dom/Node;
      34: checkcast     #20                 // class org/w3c/dom/Element
      37: astore        4
      39: goto          107
      42: aload_3
      43: invokevirtual #19                 // Method javax/xml/transform/dom/DOMSource.getNode:()Lorg/w3c/dom/Node;
      46: instanceof    #6                  // class org/w3c/dom/Document
      49: ifeq          69
      52: aload_3
      53: invokevirtual #19                 // Method javax/xml/transform/dom/DOMSource.getNode:()Lorg/w3c/dom/Node;
      56: checkcast     #6                  // class org/w3c/dom/Document
      59: invokeinterface #21,  1           // InterfaceMethod org/w3c/dom/Document.getDocumentElement:()Lorg/w3c/dom/Element;
      64: astore        4
      66: goto          107
      69: new           #16                 // class org/apache/cxf/aegis/DatabindingException
      72: dup
      73: new           #22                 // class java/lang/StringBuilder
      76: dup
      77: invokespecial #23                 // Method java/lang/StringBuilder."<init>":()V
      80: ldc           #24                 // String Node type
      82: invokevirtual #25                 // Method java/lang/StringBuilder.append:(Ljava/lang/String;)Ljava/lang/StringBuilder;
      85: aload_3
      86: invokevirtual #19                 // Method javax/xml/transform/dom/DOMSource.getNode:()Lorg/w3c/dom/Node;
      89: invokevirtual #26                 // Method java/lang/Object.getClass:()Ljava/lang/Class;
      92: invokevirtual #27                 // Method java/lang/StringBuilder.append:(Ljava/lang/Object;)Ljava/lang/StringBuilder;
      95: ldc           #28                 // String  was not understood.
      97: invokevirtual #25                 // Method java/lang/StringBuilder.append:(Ljava/lang/String;)Ljava/lang/StringBuilder;
     100: invokevirtual #29                 // Method java/lang/StringBuilder.toString:()Ljava/lang/String;
     103: invokespecial #30                 // Method org/apache/cxf/aegis/DatabindingException."<init>":(Ljava/lang/String;)V
     106: athrow
     107: aload         4
     109: aload_2
     110: iconst_0
     111: invokestatic  #31                 // Method org/apache/cxf/staxutils/StaxUtils.writeElement:(Lorg/w3c/dom/Element;Ljavax/xml/stream/XMLStreamWriter;Z)V
     114: goto          122
     117: aload_1
     118: aload_2
     119: invokestatic  #32                 // Method org/apache/cxf/staxutils/StaxUtils.copy:(Ljavax/xml/transform/Source;Ljavax/xml/stream/XMLStreamWriter;)V
     122: return

  protected org.xml.sax.XMLReader createXMLReader() throws org.xml.sax.SAXException;
    Code:
       0: invokestatic  #33                 // Method org/xml/sax/helpers/XMLReaderFactory.createXMLReader:()Lorg/xml/sax/XMLReader;
       3: areturn
       4: astore_1
       5: ldc           #35                 // String org.apache.xerces.parsers.SAXParser
       7: invokestatic  #36                 // Method org/xml/sax/helpers/XMLReaderFactory.createXMLReader:(Ljava/lang/String;)Lorg/xml/sax/XMLReader;
      10: areturn
    Exception table:
       from    to  target type
           0     3     4   Class java/lang/Exception
}
