Compiled from "AbstractMessageSourceConduit.java"
public abstract class org.xnio.conduits.AbstractMessageSourceConduit<D extends org.xnio.conduits.MessageSourceConduit> extends org.xnio.conduits.AbstractSourceConduit<D> implements org.xnio.conduits.MessageSourceConduit {
  protected org.xnio.conduits.AbstractMessageSourceConduit(D);
    Code:
       0: aload_0
       1: aload_1
       2: invokespecial #14                 // Method org/xnio/conduits/AbstractSourceConduit."<init>":(Lorg/xnio/conduits/SourceConduit;)V
       5: return

  public int receive(java.nio.ByteBuffer) throws java.io.IOException;
    Code:
       0: aload_0
       1: getfield      #27                 // Field next:Lorg/xnio/conduits/Conduit;
       4: checkcast     #7                  // class org/xnio/conduits/MessageSourceConduit
       7: aload_1
       8: invokeinterface #29,  2           // InterfaceMethod org/xnio/conduits/MessageSourceConduit.receive:(Ljava/nio/ByteBuffer;)I
      13: ireturn

  public long receive(java.nio.ByteBuffer[], int, int) throws java.io.IOException;
    Code:
       0: aload_0
       1: getfield      #27                 // Field next:Lorg/xnio/conduits/Conduit;
       4: checkcast     #7                  // class org/xnio/conduits/MessageSourceConduit
       7: aload_1
       8: iload_2
       9: iload_3
      10: invokeinterface #34,  4           // InterfaceMethod org/xnio/conduits/MessageSourceConduit.receive:([Ljava/nio/ByteBuffer;II)J
      15: lreturn
}
