Compiled from "AbstractMessageSinkConduit.java"
public abstract class org.xnio.conduits.AbstractMessageSinkConduit<D extends org.xnio.conduits.MessageSinkConduit> extends org.xnio.conduits.AbstractSinkConduit<D> implements org.xnio.conduits.MessageSinkConduit {
  protected org.xnio.conduits.AbstractMessageSinkConduit(D);
    Code:
       0: aload_0
       1: aload_1
       2: invokespecial #14                 // Method org/xnio/conduits/AbstractSinkConduit."<init>":(Lorg/xnio/conduits/SinkConduit;)V
       5: return

  public boolean send(java.nio.ByteBuffer) throws java.io.IOException;
    Code:
       0: aload_0
       1: getfield      #27                 // Field next:Lorg/xnio/conduits/Conduit;
       4: checkcast     #7                  // class org/xnio/conduits/MessageSinkConduit
       7: aload_1
       8: invokeinterface #29,  2           // InterfaceMethod org/xnio/conduits/MessageSinkConduit.send:(Ljava/nio/ByteBuffer;)Z
      13: ireturn

  public boolean send(java.nio.ByteBuffer[], int, int) throws java.io.IOException;
    Code:
       0: aload_0
       1: getfield      #27                 // Field next:Lorg/xnio/conduits/Conduit;
       4: checkcast     #7                  // class org/xnio/conduits/MessageSinkConduit
       7: aload_1
       8: iload_2
       9: iload_3
      10: invokeinterface #34,  4           // InterfaceMethod org/xnio/conduits/MessageSinkConduit.send:([Ljava/nio/ByteBuffer;II)Z
      15: ireturn

  public boolean sendFinal(java.nio.ByteBuffer[], int, int) throws java.io.IOException;
    Code:
       0: aload_0
       1: getfield      #27                 // Field next:Lorg/xnio/conduits/Conduit;
       4: checkcast     #7                  // class org/xnio/conduits/MessageSinkConduit
       7: aload_1
       8: iload_2
       9: iload_3
      10: invokeinterface #42,  4           // InterfaceMethod org/xnio/conduits/MessageSinkConduit.sendFinal:([Ljava/nio/ByteBuffer;II)Z
      15: ireturn

  public boolean sendFinal(java.nio.ByteBuffer) throws java.io.IOException;
    Code:
       0: aload_0
       1: getfield      #27                 // Field next:Lorg/xnio/conduits/Conduit;
       4: checkcast     #7                  // class org/xnio/conduits/MessageSinkConduit
       7: aload_1
       8: invokeinterface #44,  2           // InterfaceMethod org/xnio/conduits/MessageSinkConduit.sendFinal:(Ljava/nio/ByteBuffer;)Z
      13: ireturn
}
