Compiled from "TracingCallback.java"
class brave.kafka.clients.TracingCallback$FinishSpan implements org.apache.kafka.clients.producer.Callback {
  final brave.Span span;

  brave.kafka.clients.TracingCallback$FinishSpan(brave.Span);
    Code:
       0: aload_0
       1: invokespecial #1                  // Method java/lang/Object."<init>":()V
       4: aload_0
       5: aload_1
       6: putfield      #2                  // Field span:Lbrave/Span;
       9: return

  public void onCompletion(org.apache.kafka.clients.producer.RecordMetadata, java.lang.Exception);
    Code:
       0: aload_2
       1: ifnull        13
       4: aload_0
       5: getfield      #2                  // Field span:Lbrave/Span;
       8: aload_2
       9: invokevirtual #3                  // Method brave/Span.error:(Ljava/lang/Throwable;)Lbrave/Span;
      12: pop
      13: aload_0
      14: getfield      #2                  // Field span:Lbrave/Span;
      17: invokevirtual #4                  // Method brave/Span.finish:()V
      20: return
}
