Compiled from "FactoryBeanListenerManager.java"
public class org.apache.cxf.service.factory.FactoryBeanListenerManager {
  org.apache.cxf.Bus bus;

  java.util.concurrent.CopyOnWriteArrayList<org.apache.cxf.service.factory.FactoryBeanListener> listeners;

  public org.apache.cxf.service.factory.FactoryBeanListenerManager();
    Code:
       0: aload_0
       1: invokespecial #1                  // Method java/lang/Object."<init>":()V
       4: aload_0
       5: new           #2                  // class java/util/concurrent/CopyOnWriteArrayList
       8: dup
       9: invokespecial #3                  // Method java/util/concurrent/CopyOnWriteArrayList."<init>":()V
      12: putfield      #4                  // Field listeners:Ljava/util/concurrent/CopyOnWriteArrayList;
      15: aload_0
      16: getfield      #4                  // Field listeners:Ljava/util/concurrent/CopyOnWriteArrayList;
      19: new           #5                  // class org/apache/cxf/service/factory/AnnotationsFactoryBeanListener
      22: dup
      23: invokespecial #6                  // Method org/apache/cxf/service/factory/AnnotationsFactoryBeanListener."<init>":()V
      26: invokevirtual #7                  // Method java/util/concurrent/CopyOnWriteArrayList.add:(Ljava/lang/Object;)Z
      29: pop
      30: return

  public org.apache.cxf.service.factory.FactoryBeanListenerManager(org.apache.cxf.Bus);
    Code:
       0: aload_0
       1: invokespecial #8                  // Method "<init>":()V
       4: aload_0
       5: aload_1
       6: invokevirtual #9                  // Method setBus:(Lorg/apache/cxf/Bus;)V
       9: return

  public final void setBus(org.apache.cxf.Bus);
    Code:
       0: aload_0
       1: aload_1
       2: putfield      #10                 // Field bus:Lorg/apache/cxf/Bus;
       5: aload_0
       6: getfield      #10                 // Field bus:Lorg/apache/cxf/Bus;
       9: aload_0
      10: ldc_w         #11                 // class org/apache/cxf/service/factory/FactoryBeanListenerManager
      13: invokeinterface #12,  3           // InterfaceMethod org/apache/cxf/Bus.setExtension:(Ljava/lang/Object;Ljava/lang/Class;)V
      18: aload_1
      19: ldc_w         #13                 // class org/apache/cxf/configuration/ConfiguredBeanLocator
      22: invokeinterface #14,  2           // InterfaceMethod org/apache/cxf/Bus.getExtension:(Ljava/lang/Class;)Ljava/lang/Object;
      27: checkcast     #13                 // class org/apache/cxf/configuration/ConfiguredBeanLocator
      30: astore_2
      31: aload_2
      32: ifnull        83
      35: aload_2
      36: ldc_w         #15                 // class org/apache/cxf/service/factory/FactoryBeanListener
      39: invokeinterface #16,  2           // InterfaceMethod org/apache/cxf/configuration/ConfiguredBeanLocator.getBeansOfType:(Ljava/lang/Class;)Ljava/util/Collection;
      44: invokeinterface #17,  1           // InterfaceMethod java/util/Collection.iterator:()Ljava/util/Iterator;
      49: astore_3
      50: aload_3
      51: invokeinterface #18,  1           // InterfaceMethod java/util/Iterator.hasNext:()Z
      56: ifeq          83
      59: aload_3
      60: invokeinterface #19,  1           // InterfaceMethod java/util/Iterator.next:()Ljava/lang/Object;
      65: checkcast     #15                 // class org/apache/cxf/service/factory/FactoryBeanListener
      68: astore        4
      70: aload_0
      71: getfield      #4                  // Field listeners:Ljava/util/concurrent/CopyOnWriteArrayList;
      74: aload         4
      76: invokevirtual #20                 // Method java/util/concurrent/CopyOnWriteArrayList.addIfAbsent:(Ljava/lang/Object;)Z
      79: pop
      80: goto          50
      83: return

  public java.util.List<org.apache.cxf.service.factory.FactoryBeanListener> getListeners();
    Code:
       0: aload_0
       1: getfield      #4                  // Field listeners:Ljava/util/concurrent/CopyOnWriteArrayList;
       4: areturn

  public void addListener(org.apache.cxf.service.factory.FactoryBeanListener);
    Code:
       0: aload_0
       1: getfield      #4                  // Field listeners:Ljava/util/concurrent/CopyOnWriteArrayList;
       4: aload_1
       5: invokevirtual #20                 // Method java/util/concurrent/CopyOnWriteArrayList.addIfAbsent:(Ljava/lang/Object;)Z
       8: pop
       9: return

  public void removeListener(org.apache.cxf.service.factory.FactoryBeanListener);
    Code:
       0: aload_0
       1: getfield      #4                  // Field listeners:Ljava/util/concurrent/CopyOnWriteArrayList;
       4: aload_1
       5: invokevirtual #21                 // Method java/util/concurrent/CopyOnWriteArrayList.remove:(Ljava/lang/Object;)Z
       8: pop
       9: return
}
