Compiled from "Parser.java"
public abstract class org.apache.commons.cli.Parser implements org.apache.commons.cli.CommandLineParser {
  protected org.apache.commons.cli.CommandLine cmd;

  private org.apache.commons.cli.Options options;

  private java.util.List requiredOptions;

  public org.apache.commons.cli.Parser();
    Code:
       0: aload_0
       1: invokespecial #1                  // Method java/lang/Object."<init>":()V
       4: return

  protected void checkRequiredOptions() throws org.apache.commons.cli.MissingOptionException;
    Code:
       0: aload_0
       1: invokevirtual #2                  // Method getRequiredOptions:()Ljava/util/List;
       4: invokeinterface #3,  1            // InterfaceMethod java/util/List.isEmpty:()Z
       9: ifne          24
      12: new           #4                  // class org/apache/commons/cli/MissingOptionException
      15: dup
      16: aload_0
      17: invokevirtual #2                  // Method getRequiredOptions:()Ljava/util/List;
      20: invokespecial #5                  // Method org/apache/commons/cli/MissingOptionException."<init>":(Ljava/util/List;)V
      23: athrow
      24: return

  protected abstract java.lang.String[] flatten(org.apache.commons.cli.Options, java.lang.String[], boolean) throws org.apache.commons.cli.ParseException;

  protected org.apache.commons.cli.Options getOptions();
    Code:
       0: aload_0
       1: getfield      #6                  // Field options:Lorg/apache/commons/cli/Options;
       4: areturn

  protected java.util.List getRequiredOptions();
    Code:
       0: aload_0
       1: getfield      #7                  // Field requiredOptions:Ljava/util/List;
       4: areturn

  public org.apache.commons.cli.CommandLine parse(org.apache.commons.cli.Options, java.lang.String[]) throws org.apache.commons.cli.ParseException;
    Code:
       0: aload_0
       1: aload_1
       2: aload_2
       3: aconst_null
       4: iconst_0
       5: invokevirtual #8                  // Method parse:(Lorg/apache/commons/cli/Options;[Ljava/lang/String;Ljava/util/Properties;Z)Lorg/apache/commons/cli/CommandLine;
       8: areturn

  public org.apache.commons.cli.CommandLine parse(org.apache.commons.cli.Options, java.lang.String[], boolean) throws org.apache.commons.cli.ParseException;
    Code:
       0: aload_0
       1: aload_1
       2: aload_2
       3: aconst_null
       4: iload_3
       5: invokevirtual #8                  // Method parse:(Lorg/apache/commons/cli/Options;[Ljava/lang/String;Ljava/util/Properties;Z)Lorg/apache/commons/cli/CommandLine;
       8: areturn

  public org.apache.commons.cli.CommandLine parse(org.apache.commons.cli.Options, java.lang.String[], java.util.Properties) throws org.apache.commons.cli.ParseException;
    Code:
       0: aload_0
       1: aload_1
       2: aload_2
       3: aload_3
       4: iconst_0
       5: invokevirtual #8                  // Method parse:(Lorg/apache/commons/cli/Options;[Ljava/lang/String;Ljava/util/Properties;Z)Lorg/apache/commons/cli/CommandLine;
       8: areturn

  public org.apache.commons.cli.CommandLine parse(org.apache.commons.cli.Options, java.lang.String[], java.util.Properties, boolean) throws org.apache.commons.cli.ParseException;
    Code:
       0: aload_1
       1: invokevirtual #9                  // Method org/apache/commons/cli/Options.helpOptions:()Ljava/util/List;
       4: invokeinterface #10,  1           // InterfaceMethod java/util/List.iterator:()Ljava/util/Iterator;
       9: astore        5
      11: aload         5
      13: invokeinterface #11,  1           // InterfaceMethod java/util/Iterator.hasNext:()Z
      18: ifeq          41
      21: aload         5
      23: invokeinterface #12,  1           // InterfaceMethod java/util/Iterator.next:()Ljava/lang/Object;
      28: checkcast     #13                 // class org/apache/commons/cli/Option
      31: astore        6
      33: aload         6
      35: invokevirtual #14                 // Method org/apache/commons/cli/Option.clearValues:()V
      38: goto          11
      41: aload_1
      42: invokevirtual #15                 // Method org/apache/commons/cli/Options.getOptionGroups:()Ljava/util/Collection;
      45: invokeinterface #16,  1           // InterfaceMethod java/util/Collection.iterator:()Ljava/util/Iterator;
      50: astore        5
      52: aload         5
      54: invokeinterface #11,  1           // InterfaceMethod java/util/Iterator.hasNext:()Z
      59: ifeq          83
      62: aload         5
      64: invokeinterface #12,  1           // InterfaceMethod java/util/Iterator.next:()Ljava/lang/Object;
      69: checkcast     #17                 // class org/apache/commons/cli/OptionGroup
      72: astore        6
      74: aload         6
      76: aconst_null
      77: invokevirtual #18                 // Method org/apache/commons/cli/OptionGroup.setSelected:(Lorg/apache/commons/cli/Option;)V
      80: goto          52
      83: aload_0
      84: aload_1
      85: invokevirtual #19                 // Method setOptions:(Lorg/apache/commons/cli/Options;)V
      88: aload_0
      89: new           #20                 // class org/apache/commons/cli/CommandLine
      92: dup
      93: invokespecial #21                 // Method org/apache/commons/cli/CommandLine."<init>":()V
      96: putfield      #22                 // Field cmd:Lorg/apache/commons/cli/CommandLine;
      99: iconst_0
     100: istore        5
     102: aload_2
     103: ifnonnull     111
     106: iconst_0
     107: anewarray     #23                 // class java/lang/String
     110: astore_2
     111: aload_0
     112: aload_0
     113: invokevirtual #24                 // Method getOptions:()Lorg/apache/commons/cli/Options;
     116: aload_2
     117: iload         4
     119: invokevirtual #25                 // Method flatten:(Lorg/apache/commons/cli/Options;[Ljava/lang/String;Z)[Ljava/lang/String;
     122: invokestatic  #26                 // Method java/util/Arrays.asList:([Ljava/lang/Object;)Ljava/util/List;
     125: astore        6
     127: aload         6
     129: invokeinterface #27,  1           // InterfaceMethod java/util/List.listIterator:()Ljava/util/ListIterator;
     134: astore        7
     136: aload         7
     138: invokeinterface #28,  1           // InterfaceMethod java/util/ListIterator.hasNext:()Z
     143: ifeq          329
     146: aload         7
     148: invokeinterface #29,  1           // InterfaceMethod java/util/ListIterator.next:()Ljava/lang/Object;
     153: checkcast     #23                 // class java/lang/String
     156: astore        8
     158: ldc           #30                 // String --
     160: aload         8
     162: invokevirtual #31                 // Method java/lang/String.equals:(Ljava/lang/Object;)Z
     165: ifeq          174
     168: iconst_1
     169: istore        5
     171: goto          277
     174: ldc           #32                 // String -
     176: aload         8
     178: invokevirtual #31                 // Method java/lang/String.equals:(Ljava/lang/Object;)Z
     181: ifeq          207
     184: iload         4
     186: ifeq          195
     189: iconst_1
     190: istore        5
     192: goto          277
     195: aload_0
     196: getfield      #22                 // Field cmd:Lorg/apache/commons/cli/CommandLine;
     199: aload         8
     201: invokevirtual #33                 // Method org/apache/commons/cli/CommandLine.addArg:(Ljava/lang/String;)V
     204: goto          277
     207: aload         8
     209: ldc           #32                 // String -
     211: invokevirtual #34                 // Method java/lang/String.startsWith:(Ljava/lang/String;)Z
     214: ifeq          260
     217: iload         4
     219: ifeq          249
     222: aload_0
     223: invokevirtual #24                 // Method getOptions:()Lorg/apache/commons/cli/Options;
     226: aload         8
     228: invokevirtual #35                 // Method org/apache/commons/cli/Options.hasOption:(Ljava/lang/String;)Z
     231: ifne          249
     234: iconst_1
     235: istore        5
     237: aload_0
     238: getfield      #22                 // Field cmd:Lorg/apache/commons/cli/CommandLine;
     241: aload         8
     243: invokevirtual #33                 // Method org/apache/commons/cli/CommandLine.addArg:(Ljava/lang/String;)V
     246: goto          277
     249: aload_0
     250: aload         8
     252: aload         7
     254: invokevirtual #36                 // Method processOption:(Ljava/lang/String;Ljava/util/ListIterator;)V
     257: goto          277
     260: aload_0
     261: getfield      #22                 // Field cmd:Lorg/apache/commons/cli/CommandLine;
     264: aload         8
     266: invokevirtual #33                 // Method org/apache/commons/cli/CommandLine.addArg:(Ljava/lang/String;)V
     269: iload         4
     271: ifeq          277
     274: iconst_1
     275: istore        5
     277: iload         5
     279: ifeq          326
     282: aload         7
     284: invokeinterface #28,  1           // InterfaceMethod java/util/ListIterator.hasNext:()Z
     289: ifeq          326
     292: aload         7
     294: invokeinterface #29,  1           // InterfaceMethod java/util/ListIterator.next:()Ljava/lang/Object;
     299: checkcast     #23                 // class java/lang/String
     302: astore        9
     304: ldc           #30                 // String --
     306: aload         9
     308: invokevirtual #31                 // Method java/lang/String.equals:(Ljava/lang/Object;)Z
     311: ifne          323
     314: aload_0
     315: getfield      #22                 // Field cmd:Lorg/apache/commons/cli/CommandLine;
     318: aload         9
     320: invokevirtual #33                 // Method org/apache/commons/cli/CommandLine.addArg:(Ljava/lang/String;)V
     323: goto          282
     326: goto          136
     329: aload_0
     330: aload_3
     331: invokevirtual #37                 // Method processProperties:(Ljava/util/Properties;)V
     334: aload_0
     335: invokevirtual #38                 // Method checkRequiredOptions:()V
     338: aload_0
     339: getfield      #22                 // Field cmd:Lorg/apache/commons/cli/CommandLine;
     342: areturn

  public void processArgs(org.apache.commons.cli.Option, java.util.ListIterator<java.lang.String>) throws org.apache.commons.cli.ParseException;
    Code:
       0: aload_2
       1: invokeinterface #28,  1           // InterfaceMethod java/util/ListIterator.hasNext:()Z
       6: ifeq          75
       9: aload_2
      10: invokeinterface #29,  1           // InterfaceMethod java/util/ListIterator.next:()Ljava/lang/Object;
      15: checkcast     #23                 // class java/lang/String
      18: astore_3
      19: aload_0
      20: invokevirtual #24                 // Method getOptions:()Lorg/apache/commons/cli/Options;
      23: aload_3
      24: invokevirtual #35                 // Method org/apache/commons/cli/Options.hasOption:(Ljava/lang/String;)Z
      27: ifeq          49
      30: aload_3
      31: ldc           #32                 // String -
      33: invokevirtual #34                 // Method java/lang/String.startsWith:(Ljava/lang/String;)Z
      36: ifeq          49
      39: aload_2
      40: invokeinterface #39,  1           // InterfaceMethod java/util/ListIterator.previous:()Ljava/lang/Object;
      45: pop
      46: goto          75
      49: aload_1
      50: aload_3
      51: invokestatic  #40                 // Method org/apache/commons/cli/Util.stripLeadingAndTrailingQuotes:(Ljava/lang/String;)Ljava/lang/String;
      54: invokevirtual #41                 // Method org/apache/commons/cli/Option.addValueForProcessing:(Ljava/lang/String;)V
      57: goto          72
      60: astore        4
      62: aload_2
      63: invokeinterface #39,  1           // InterfaceMethod java/util/ListIterator.previous:()Ljava/lang/Object;
      68: pop
      69: goto          75
      72: goto          0
      75: aload_1
      76: invokevirtual #43                 // Method org/apache/commons/cli/Option.getValues:()[Ljava/lang/String;
      79: ifnonnull     98
      82: aload_1
      83: invokevirtual #44                 // Method org/apache/commons/cli/Option.hasOptionalArg:()Z
      86: ifne          98
      89: new           #45                 // class org/apache/commons/cli/MissingArgumentException
      92: dup
      93: aload_1
      94: invokespecial #46                 // Method org/apache/commons/cli/MissingArgumentException."<init>":(Lorg/apache/commons/cli/Option;)V
      97: athrow
      98: return
    Exception table:
       from    to  target type
          49    57    60   Class java/lang/RuntimeException

  protected void processOption(java.lang.String, java.util.ListIterator<java.lang.String>) throws org.apache.commons.cli.ParseException;
    Code:
       0: aload_0
       1: invokevirtual #24                 // Method getOptions:()Lorg/apache/commons/cli/Options;
       4: aload_1
       5: invokevirtual #35                 // Method org/apache/commons/cli/Options.hasOption:(Ljava/lang/String;)Z
       8: istore_3
       9: iload_3
      10: ifne          41
      13: new           #47                 // class org/apache/commons/cli/UnrecognizedOptionException
      16: dup
      17: new           #48                 // class java/lang/StringBuilder
      20: dup
      21: invokespecial #49                 // Method java/lang/StringBuilder."<init>":()V
      24: ldc           #50                 // String Unrecognized option:
      26: invokevirtual #51                 // Method java/lang/StringBuilder.append:(Ljava/lang/String;)Ljava/lang/StringBuilder;
      29: aload_1
      30: invokevirtual #51                 // Method java/lang/StringBuilder.append:(Ljava/lang/String;)Ljava/lang/StringBuilder;
      33: invokevirtual #52                 // Method java/lang/StringBuilder.toString:()Ljava/lang/String;
      36: aload_1
      37: invokespecial #53                 // Method org/apache/commons/cli/UnrecognizedOptionException."<init>":(Ljava/lang/String;Ljava/lang/String;)V
      40: athrow
      41: aload_0
      42: invokevirtual #24                 // Method getOptions:()Lorg/apache/commons/cli/Options;
      45: aload_1
      46: invokevirtual #54                 // Method org/apache/commons/cli/Options.getOption:(Ljava/lang/String;)Lorg/apache/commons/cli/Option;
      49: invokevirtual #55                 // Method org/apache/commons/cli/Option.clone:()Ljava/lang/Object;
      52: checkcast     #13                 // class org/apache/commons/cli/Option
      55: astore        4
      57: aload_0
      58: aload         4
      60: invokespecial #56                 // Method updateRequiredOptions:(Lorg/apache/commons/cli/Option;)V
      63: aload         4
      65: invokevirtual #57                 // Method org/apache/commons/cli/Option.hasArg:()Z
      68: ifeq          78
      71: aload_0
      72: aload         4
      74: aload_2
      75: invokevirtual #58                 // Method processArgs:(Lorg/apache/commons/cli/Option;Ljava/util/ListIterator;)V
      78: aload_0
      79: getfield      #22                 // Field cmd:Lorg/apache/commons/cli/CommandLine;
      82: aload         4
      84: invokevirtual #59                 // Method org/apache/commons/cli/CommandLine.addOption:(Lorg/apache/commons/cli/Option;)V
      87: return

  protected void processProperties(java.util.Properties) throws org.apache.commons.cli.ParseException;
    Code:
       0: aload_1
       1: ifnonnull     5
       4: return
       5: aload_1
       6: invokevirtual #60                 // Method java/util/Properties.propertyNames:()Ljava/util/Enumeration;
       9: astore_2
      10: aload_2
      11: invokeinterface #61,  1           // InterfaceMethod java/util/Enumeration.hasMoreElements:()Z
      16: ifeq          200
      19: aload_2
      20: invokeinterface #62,  1           // InterfaceMethod java/util/Enumeration.nextElement:()Ljava/lang/Object;
      25: invokevirtual #63                 // Method java/lang/Object.toString:()Ljava/lang/String;
      28: astore_3
      29: aload_0
      30: getfield      #6                  // Field options:Lorg/apache/commons/cli/Options;
      33: aload_3
      34: invokevirtual #54                 // Method org/apache/commons/cli/Options.getOption:(Ljava/lang/String;)Lorg/apache/commons/cli/Option;
      37: astore        4
      39: aload         4
      41: ifnonnull     55
      44: new           #47                 // class org/apache/commons/cli/UnrecognizedOptionException
      47: dup
      48: ldc           #64                 // String Default option wasn\'t defined
      50: aload_3
      51: invokespecial #53                 // Method org/apache/commons/cli/UnrecognizedOptionException."<init>":(Ljava/lang/String;Ljava/lang/String;)V
      54: athrow
      55: aload_0
      56: getfield      #6                  // Field options:Lorg/apache/commons/cli/Options;
      59: aload         4
      61: invokevirtual #65                 // Method org/apache/commons/cli/Options.getOptionGroup:(Lorg/apache/commons/cli/Option;)Lorg/apache/commons/cli/OptionGroup;
      64: astore        5
      66: aload         5
      68: ifnull        83
      71: aload         5
      73: invokevirtual #66                 // Method org/apache/commons/cli/OptionGroup.getSelected:()Ljava/lang/String;
      76: ifnull        83
      79: iconst_1
      80: goto          84
      83: iconst_0
      84: istore        6
      86: aload_0
      87: getfield      #22                 // Field cmd:Lorg/apache/commons/cli/CommandLine;
      90: aload_3
      91: invokevirtual #67                 // Method org/apache/commons/cli/CommandLine.hasOption:(Ljava/lang/String;)Z
      94: ifne          197
      97: iload         6
      99: ifne          197
     102: aload_1
     103: aload_3
     104: invokevirtual #68                 // Method java/util/Properties.getProperty:(Ljava/lang/String;)Ljava/lang/String;
     107: astore        7
     109: aload         4
     111: invokevirtual #57                 // Method org/apache/commons/cli/Option.hasArg:()Z
     114: ifeq          149
     117: aload         4
     119: invokevirtual #43                 // Method org/apache/commons/cli/Option.getValues:()[Ljava/lang/String;
     122: ifnull        134
     125: aload         4
     127: invokevirtual #43                 // Method org/apache/commons/cli/Option.getValues:()[Ljava/lang/String;
     130: arraylength
     131: ifne          182
     134: aload         4
     136: aload         7
     138: invokevirtual #41                 // Method org/apache/commons/cli/Option.addValueForProcessing:(Ljava/lang/String;)V
     141: goto          182
     144: astore        8
     146: goto          182
     149: ldc           #69                 // String yes
     151: aload         7
     153: invokevirtual #70                 // Method java/lang/String.equalsIgnoreCase:(Ljava/lang/String;)Z
     156: ifne          182
     159: ldc           #71                 // String true
     161: aload         7
     163: invokevirtual #70                 // Method java/lang/String.equalsIgnoreCase:(Ljava/lang/String;)Z
     166: ifne          182
     169: ldc           #72                 // String 1
     171: aload         7
     173: invokevirtual #70                 // Method java/lang/String.equalsIgnoreCase:(Ljava/lang/String;)Z
     176: ifne          182
     179: goto          10
     182: aload_0
     183: getfield      #22                 // Field cmd:Lorg/apache/commons/cli/CommandLine;
     186: aload         4
     188: invokevirtual #59                 // Method org/apache/commons/cli/CommandLine.addOption:(Lorg/apache/commons/cli/Option;)V
     191: aload_0
     192: aload         4
     194: invokespecial #56                 // Method updateRequiredOptions:(Lorg/apache/commons/cli/Option;)V
     197: goto          10
     200: return
    Exception table:
       from    to  target type
         134   141   144   Class java/lang/RuntimeException

  protected void setOptions(org.apache.commons.cli.Options);
    Code:
       0: aload_0
       1: aload_1
       2: putfield      #6                  // Field options:Lorg/apache/commons/cli/Options;
       5: aload_0
       6: new           #73                 // class java/util/ArrayList
       9: dup
      10: aload_1
      11: invokevirtual #74                 // Method org/apache/commons/cli/Options.getRequiredOptions:()Ljava/util/List;
      14: invokespecial #75                 // Method java/util/ArrayList."<init>":(Ljava/util/Collection;)V
      17: putfield      #7                  // Field requiredOptions:Ljava/util/List;
      20: return

  private void updateRequiredOptions(org.apache.commons.cli.Option) throws org.apache.commons.cli.ParseException;
    Code:
       0: aload_1
       1: invokevirtual #76                 // Method org/apache/commons/cli/Option.isRequired:()Z
       4: ifeq          21
       7: aload_0
       8: invokevirtual #2                  // Method getRequiredOptions:()Ljava/util/List;
      11: aload_1
      12: invokevirtual #77                 // Method org/apache/commons/cli/Option.getKey:()Ljava/lang/String;
      15: invokeinterface #78,  2           // InterfaceMethod java/util/List.remove:(Ljava/lang/Object;)Z
      20: pop
      21: aload_0
      22: invokevirtual #24                 // Method getOptions:()Lorg/apache/commons/cli/Options;
      25: aload_1
      26: invokevirtual #65                 // Method org/apache/commons/cli/Options.getOptionGroup:(Lorg/apache/commons/cli/Option;)Lorg/apache/commons/cli/OptionGroup;
      29: ifnull        64
      32: aload_0
      33: invokevirtual #24                 // Method getOptions:()Lorg/apache/commons/cli/Options;
      36: aload_1
      37: invokevirtual #65                 // Method org/apache/commons/cli/Options.getOptionGroup:(Lorg/apache/commons/cli/Option;)Lorg/apache/commons/cli/OptionGroup;
      40: astore_2
      41: aload_2
      42: invokevirtual #79                 // Method org/apache/commons/cli/OptionGroup.isRequired:()Z
      45: ifeq          59
      48: aload_0
      49: invokevirtual #2                  // Method getRequiredOptions:()Ljava/util/List;
      52: aload_2
      53: invokeinterface #78,  2           // InterfaceMethod java/util/List.remove:(Ljava/lang/Object;)Z
      58: pop
      59: aload_2
      60: aload_1
      61: invokevirtual #18                 // Method org/apache/commons/cli/OptionGroup.setSelected:(Lorg/apache/commons/cli/Option;)V
      64: return
}
