Compiled from "ApplicationMappingMatch.java"
public final class org.apache.catalina.core.ApplicationMappingMatch extends java.lang.Enum<org.apache.catalina.core.ApplicationMappingMatch> {
  public static final org.apache.catalina.core.ApplicationMappingMatch CONTEXT_ROOT;

  public static final org.apache.catalina.core.ApplicationMappingMatch DEFAULT;

  public static final org.apache.catalina.core.ApplicationMappingMatch EXACT;

  public static final org.apache.catalina.core.ApplicationMappingMatch EXTENSION;

  public static final org.apache.catalina.core.ApplicationMappingMatch PATH;

  private static final org.apache.catalina.core.ApplicationMappingMatch[] $VALUES;

  public static org.apache.catalina.core.ApplicationMappingMatch[] values();
    Code:
       0: getstatic     #1                  // Field $VALUES:[Lorg/apache/catalina/core/ApplicationMappingMatch;
       3: invokevirtual #2                  // Method "[Lorg/apache/catalina/core/ApplicationMappingMatch;".clone:()Ljava/lang/Object;
       6: checkcast     #3                  // class "[Lorg/apache/catalina/core/ApplicationMappingMatch;"
       9: areturn

  public static org.apache.catalina.core.ApplicationMappingMatch valueOf(java.lang.String);
    Code:
       0: ldc_w         #4                  // class org/apache/catalina/core/ApplicationMappingMatch
       3: aload_0
       4: invokestatic  #5                  // Method java/lang/Enum.valueOf:(Ljava/lang/Class;Ljava/lang/String;)Ljava/lang/Enum;
       7: checkcast     #4                  // class org/apache/catalina/core/ApplicationMappingMatch
      10: areturn

  private org.apache.catalina.core.ApplicationMappingMatch();
    Code:
       0: aload_0
       1: aload_1
       2: iload_2
       3: invokespecial #6                  // Method java/lang/Enum."<init>":(Ljava/lang/String;I)V
       6: return

  static {};
    Code:
       0: new           #4                  // class org/apache/catalina/core/ApplicationMappingMatch
       3: dup
       4: ldc           #7                  // String CONTEXT_ROOT
       6: iconst_0
       7: invokespecial #8                  // Method "<init>":(Ljava/lang/String;I)V
      10: putstatic     #9                  // Field CONTEXT_ROOT:Lorg/apache/catalina/core/ApplicationMappingMatch;
      13: new           #4                  // class org/apache/catalina/core/ApplicationMappingMatch
      16: dup
      17: ldc           #10                 // String DEFAULT
      19: iconst_1
      20: invokespecial #8                  // Method "<init>":(Ljava/lang/String;I)V
      23: putstatic     #11                 // Field DEFAULT:Lorg/apache/catalina/core/ApplicationMappingMatch;
      26: new           #4                  // class org/apache/catalina/core/ApplicationMappingMatch
      29: dup
      30: ldc           #12                 // String EXACT
      32: iconst_2
      33: invokespecial #8                  // Method "<init>":(Ljava/lang/String;I)V
      36: putstatic     #13                 // Field EXACT:Lorg/apache/catalina/core/ApplicationMappingMatch;
      39: new           #4                  // class org/apache/catalina/core/ApplicationMappingMatch
      42: dup
      43: ldc           #14                 // String EXTENSION
      45: iconst_3
      46: invokespecial #8                  // Method "<init>":(Ljava/lang/String;I)V
      49: putstatic     #15                 // Field EXTENSION:Lorg/apache/catalina/core/ApplicationMappingMatch;
      52: new           #4                  // class org/apache/catalina/core/ApplicationMappingMatch
      55: dup
      56: ldc           #16                 // String PATH
      58: iconst_4
      59: invokespecial #8                  // Method "<init>":(Ljava/lang/String;I)V
      62: putstatic     #17                 // Field PATH:Lorg/apache/catalina/core/ApplicationMappingMatch;
      65: iconst_5
      66: anewarray     #4                  // class org/apache/catalina/core/ApplicationMappingMatch
      69: dup
      70: iconst_0
      71: getstatic     #9                  // Field CONTEXT_ROOT:Lorg/apache/catalina/core/ApplicationMappingMatch;
      74: aastore
      75: dup
      76: iconst_1
      77: getstatic     #11                 // Field DEFAULT:Lorg/apache/catalina/core/ApplicationMappingMatch;
      80: aastore
      81: dup
      82: iconst_2
      83: getstatic     #13                 // Field EXACT:Lorg/apache/catalina/core/ApplicationMappingMatch;
      86: aastore
      87: dup
      88: iconst_3
      89: getstatic     #15                 // Field EXTENSION:Lorg/apache/catalina/core/ApplicationMappingMatch;
      92: aastore
      93: dup
      94: iconst_4
      95: getstatic     #17                 // Field PATH:Lorg/apache/catalina/core/ApplicationMappingMatch;
      98: aastore
      99: putstatic     #1                  // Field $VALUES:[Lorg/apache/catalina/core/ApplicationMappingMatch;
     102: return
}
