Compiled from "ContainerNode.java"
public class org.elasticsearch.hadoop.thirdparty.codehaus.jackson.node.ContainerNode$NoStringsIterator implements java.util.Iterator<java.lang.String> {
  static final org.elasticsearch.hadoop.thirdparty.codehaus.jackson.node.ContainerNode$NoStringsIterator instance;

  private org.elasticsearch.hadoop.thirdparty.codehaus.jackson.node.ContainerNode$NoStringsIterator();
    Code:
       0: aload_0
       1: invokespecial #17                 // Method java/lang/Object."<init>":()V
       4: return

  public static org.elasticsearch.hadoop.thirdparty.codehaus.jackson.node.ContainerNode$NoStringsIterator instance();
    Code:
       0: getstatic     #21                 // Field instance:Lorg/elasticsearch/hadoop/thirdparty/codehaus/jackson/node/ContainerNode$NoStringsIterator;
       3: areturn

  public boolean hasNext();
    Code:
       0: iconst_0
       1: ireturn

  public java.lang.String next();
    Code:
       0: new           #27                 // class java/util/NoSuchElementException
       3: dup
       4: invokespecial #28                 // Method java/util/NoSuchElementException."<init>":()V
       7: athrow

  public void remove();
    Code:
       0: new           #31                 // class java/lang/IllegalStateException
       3: dup
       4: invokespecial #32                 // Method java/lang/IllegalStateException."<init>":()V
       7: athrow

  public java.lang.Object next();
    Code:
       0: aload_0
       1: invokevirtual #35                 // Method next:()Ljava/lang/String;
       4: areturn

  static {};
    Code:
       0: new           #2                  // class org/elasticsearch/hadoop/thirdparty/codehaus/jackson/node/ContainerNode$NoStringsIterator
       3: dup
       4: invokespecial #37                 // Method "<init>":()V
       7: putstatic     #21                 // Field instance:Lorg/elasticsearch/hadoop/thirdparty/codehaus/jackson/node/ContainerNode$NoStringsIterator;
      10: return
}
