Compiled from "KeyValueOutput.java"
public class io.lettuce.core.output.KeyValueOutput<K, V> extends io.lettuce.core.output.CommandOutput<K, V, io.lettuce.core.KeyValue<K, V>> {
  private K key;

  public io.lettuce.core.output.KeyValueOutput(io.lettuce.core.codec.RedisCodec<K, V>);
    Code:
       0: aload_0
       1: aload_1
       2: aconst_null
       3: invokespecial #1                  // Method io/lettuce/core/output/CommandOutput."<init>":(Lio/lettuce/core/codec/RedisCodec;Ljava/lang/Object;)V
       6: return

  public void set(java.nio.ByteBuffer);
    Code:
       0: aload_1
       1: ifnull        51
       4: aload_0
       5: getfield      #2                  // Field key:Ljava/lang/Object;
       8: ifnonnull     28
      11: aload_0
      12: aload_0
      13: getfield      #3                  // Field codec:Lio/lettuce/core/codec/RedisCodec;
      16: aload_1
      17: invokeinterface #4,  2            // InterfaceMethod io/lettuce/core/codec/RedisCodec.decodeKey:(Ljava/nio/ByteBuffer;)Ljava/lang/Object;
      22: putfield      #2                  // Field key:Ljava/lang/Object;
      25: goto          51
      28: aload_0
      29: getfield      #3                  // Field codec:Lio/lettuce/core/codec/RedisCodec;
      32: aload_1
      33: invokeinterface #5,  2            // InterfaceMethod io/lettuce/core/codec/RedisCodec.decodeValue:(Ljava/nio/ByteBuffer;)Ljava/lang/Object;
      38: astore_2
      39: aload_0
      40: aload_0
      41: getfield      #2                  // Field key:Ljava/lang/Object;
      44: aload_2
      45: invokestatic  #6                  // Method io/lettuce/core/KeyValue.fromNullable:(Ljava/lang/Object;Ljava/lang/Object;)Lio/lettuce/core/KeyValue;
      48: putfield      #7                  // Field output:Ljava/lang/Object;
      51: return
}
