Compiled from "PolicyBasedWSS4JOutInterceptor.java"
public class org.apache.cxf.ws.security.wss4j.PolicyBasedWSS4JOutInterceptor extends org.apache.cxf.phase.AbstractPhaseInterceptor<org.apache.cxf.binding.soap.SoapMessage> {
  public static final java.lang.String SECURITY_PROCESSED;

  public static final org.apache.cxf.ws.security.wss4j.PolicyBasedWSS4JOutInterceptor INSTANCE;

  private static final java.util.logging.Logger LOG;

  private org.apache.cxf.ws.security.wss4j.PolicyBasedWSS4JOutInterceptor$PolicyBasedWSS4JOutInterceptorInternal ending;

  private org.apache.cxf.binding.soap.saaj.SAAJOutInterceptor saajOut;

  public org.apache.cxf.ws.security.wss4j.PolicyBasedWSS4JOutInterceptor();
    Code:
       0: aload_0
       1: ldc           #3                  // String pre-protocol
       3: invokespecial #4                  // Method org/apache/cxf/phase/AbstractPhaseInterceptor."<init>":(Ljava/lang/String;)V
       6: aload_0
       7: new           #5                  // class org/apache/cxf/binding/soap/saaj/SAAJOutInterceptor
      10: dup
      11: invokespecial #6                  // Method org/apache/cxf/binding/soap/saaj/SAAJOutInterceptor."<init>":()V
      14: putfield      #7                  // Field saajOut:Lorg/apache/cxf/binding/soap/saaj/SAAJOutInterceptor;
      17: aload_0
      18: invokevirtual #8                  // Method getAfter:()Ljava/util/Set;
      21: ldc_w         #5                  // class org/apache/cxf/binding/soap/saaj/SAAJOutInterceptor
      24: invokevirtual #9                  // Method java/lang/Class.getName:()Ljava/lang/String;
      27: invokeinterface #10,  2           // InterfaceMethod java/util/Set.add:(Ljava/lang/Object;)Z
      32: pop
      33: aload_0
      34: aload_0
      35: invokevirtual #11                 // Method createEndingInterceptor:()Lorg/apache/cxf/ws/security/wss4j/PolicyBasedWSS4JOutInterceptor$PolicyBasedWSS4JOutInterceptorInternal;
      38: putfield      #12                 // Field ending:Lorg/apache/cxf/ws/security/wss4j/PolicyBasedWSS4JOutInterceptor$PolicyBasedWSS4JOutInterceptorInternal;
      41: return

  public void handleMessage(org.apache.cxf.binding.soap.SoapMessage) throws org.apache.cxf.interceptor.Fault;
    Code:
       0: aload_1
       1: ldc           #13                 // String ws-security.enable.streaming
       3: invokevirtual #14                 // Method org/apache/cxf/binding/soap/SoapMessage.getContextualProperty:(Ljava/lang/String;)Ljava/lang/Object;
       6: invokestatic  #15                 // Method org/apache/cxf/message/MessageUtils.isTrue:(Ljava/lang/Object;)Z
       9: istore_2
      10: iload_2
      11: ifne          56
      14: aload_1
      15: ldc_w         #16                 // class javax/xml/soap/SOAPMessage
      18: invokevirtual #17                 // Method org/apache/cxf/binding/soap/SoapMessage.getContent:(Ljava/lang/Class;)Ljava/lang/Object;
      21: ifnonnull     32
      24: aload_0
      25: getfield      #7                  // Field saajOut:Lorg/apache/cxf/binding/soap/saaj/SAAJOutInterceptor;
      28: aload_1
      29: invokevirtual #18                 // Method org/apache/cxf/binding/soap/saaj/SAAJOutInterceptor.handleMessage:(Lorg/apache/cxf/binding/soap/SoapMessage;)V
      32: aload_1
      33: getstatic     #19                 // Field SECURITY_PROCESSED:Ljava/lang/String;
      36: getstatic     #20                 // Field java/lang/Boolean.TRUE:Ljava/lang/Boolean;
      39: invokevirtual #21                 // Method org/apache/cxf/binding/soap/SoapMessage.put:(Ljava/lang/String;Ljava/lang/Object;)Ljava/lang/Object;
      42: pop
      43: aload_1
      44: invokevirtual #22                 // Method org/apache/cxf/binding/soap/SoapMessage.getInterceptorChain:()Lorg/apache/cxf/interceptor/InterceptorChain;
      47: aload_0
      48: getfield      #12                 // Field ending:Lorg/apache/cxf/ws/security/wss4j/PolicyBasedWSS4JOutInterceptor$PolicyBasedWSS4JOutInterceptorInternal;
      51: invokeinterface #23,  2           // InterfaceMethod org/apache/cxf/interceptor/InterceptorChain.add:(Lorg/apache/cxf/interceptor/Interceptor;)V
      56: return

  public void handleFault(org.apache.cxf.binding.soap.SoapMessage);
    Code:
       0: aload_0
       1: getfield      #7                  // Field saajOut:Lorg/apache/cxf/binding/soap/saaj/SAAJOutInterceptor;
       4: aload_1
       5: invokevirtual #24                 // Method org/apache/cxf/binding/soap/saaj/SAAJOutInterceptor.handleFault:(Lorg/apache/cxf/binding/soap/SoapMessage;)V
       8: return

  public final org.apache.cxf.ws.security.wss4j.PolicyBasedWSS4JOutInterceptor$PolicyBasedWSS4JOutInterceptorInternal createEndingInterceptor();
    Code:
       0: new           #25                 // class org/apache/cxf/ws/security/wss4j/PolicyBasedWSS4JOutInterceptor$PolicyBasedWSS4JOutInterceptorInternal
       3: dup
       4: aload_0
       5: invokespecial #26                 // Method org/apache/cxf/ws/security/wss4j/PolicyBasedWSS4JOutInterceptor$PolicyBasedWSS4JOutInterceptorInternal."<init>":(Lorg/apache/cxf/ws/security/wss4j/PolicyBasedWSS4JOutInterceptor;)V
       8: areturn

  public void handleFault(org.apache.cxf.message.Message);
    Code:
       0: aload_0
       1: aload_1
       2: checkcast     #27                 // class org/apache/cxf/binding/soap/SoapMessage
       5: invokevirtual #28                 // Method handleFault:(Lorg/apache/cxf/binding/soap/SoapMessage;)V
       8: return

  public void handleMessage(org.apache.cxf.message.Message) throws org.apache.cxf.interceptor.Fault;
    Code:
       0: aload_0
       1: aload_1
       2: checkcast     #27                 // class org/apache/cxf/binding/soap/SoapMessage
       5: invokevirtual #29                 // Method handleMessage:(Lorg/apache/cxf/binding/soap/SoapMessage;)V
       8: return

  static java.util.logging.Logger access$000();
    Code:
       0: getstatic     #2                  // Field LOG:Ljava/util/logging/Logger;
       3: areturn

  static boolean access$100(org.apache.cxf.ws.security.wss4j.PolicyBasedWSS4JOutInterceptor, org.apache.cxf.message.Message);
    Code:
       0: aload_0
       1: aload_1
       2: invokevirtual #1                  // Method isRequestor:(Lorg/apache/cxf/message/Message;)Z
       5: ireturn

  static {};
    Code:
       0: new           #30                 // class java/lang/StringBuilder
       3: dup
       4: invokespecial #31                 // Method java/lang/StringBuilder."<init>":()V
       7: ldc_w         #32                 // class org/apache/cxf/ws/security/wss4j/PolicyBasedWSS4JOutInterceptor
      10: invokevirtual #9                  // Method java/lang/Class.getName:()Ljava/lang/String;
      13: invokevirtual #33                 // Method java/lang/StringBuilder.append:(Ljava/lang/String;)Ljava/lang/StringBuilder;
      16: ldc           #34                 // String .DONE
      18: invokevirtual #33                 // Method java/lang/StringBuilder.append:(Ljava/lang/String;)Ljava/lang/StringBuilder;
      21: invokevirtual #35                 // Method java/lang/StringBuilder.toString:()Ljava/lang/String;
      24: putstatic     #19                 // Field SECURITY_PROCESSED:Ljava/lang/String;
      27: new           #32                 // class org/apache/cxf/ws/security/wss4j/PolicyBasedWSS4JOutInterceptor
      30: dup
      31: invokespecial #36                 // Method "<init>":()V
      34: putstatic     #37                 // Field INSTANCE:Lorg/apache/cxf/ws/security/wss4j/PolicyBasedWSS4JOutInterceptor;
      37: ldc_w         #32                 // class org/apache/cxf/ws/security/wss4j/PolicyBasedWSS4JOutInterceptor
      40: invokestatic  #38                 // Method org/apache/cxf/common/logging/LogUtils.getL7dLogger:(Ljava/lang/Class;)Ljava/util/logging/Logger;
      43: putstatic     #2                  // Field LOG:Ljava/util/logging/Logger;
      46: return
}
