Compiled from "GitBuildValidationIT.kt"
public class net.nemerosa.ontrack.extension.git.service.GitBuildValidationIT extends net.nemerosa.ontrack.extension.git.AbstractGitTestSupport {
  public net.nemerosa.ontrack.extension.git.service.GitBuildValidationIT();
    Code:
       0: aload_0
       1: invokespecial #8                  // Method net/nemerosa/ontrack/extension/git/AbstractGitTestSupport."<init>":()V
       4: return

  public void Build validation OK without branch config();
    Code:
       0: aload_0
       1: checkcast     #14                 // class net/nemerosa/ontrack/it/AbstractDSLTestJUnit4Support
       4: aconst_null
       5: new           #16                 // class "net/nemerosa/ontrack/extension/git/service/GitBuildValidationIT$Build validation OK without branch config$1"
       8: dup
       9: aload_0
      10: invokespecial #19                 // Method "net/nemerosa/ontrack/extension/git/service/GitBuildValidationIT$Build validation OK without branch config$1"."<init>":(Lnet/nemerosa/ontrack/extension/git/service/GitBuildValidationIT;)V
      13: checkcast     #21                 // class kotlin/jvm/functions/Function1
      16: iconst_1
      17: aconst_null
      18: invokestatic  #25                 // Method net/nemerosa/ontrack/it/AbstractDSLTestJUnit4Support.project$default:(Lnet/nemerosa/ontrack/it/AbstractDSLTestJUnit4Support;Lnet/nemerosa/ontrack/model/structure/NameDescription;Lkotlin/jvm/functions/Function1;ILjava/lang/Object;)Lnet/nemerosa/ontrack/model/structure/Project;
      21: pop
      22: return

  public void Build validation OK with tag pattern();
    Code:
       0: aload_0
       1: new           #28                 // class "net/nemerosa/ontrack/extension/git/service/GitBuildValidationIT$Build validation OK with tag pattern$1"
       4: dup
       5: aload_0
       6: invokespecial #29                 // Method "net/nemerosa/ontrack/extension/git/service/GitBuildValidationIT$Build validation OK with tag pattern$1"."<init>":(Lnet/nemerosa/ontrack/extension/git/service/GitBuildValidationIT;)V
       9: checkcast     #21                 // class kotlin/jvm/functions/Function1
      12: invokevirtual #33                 // Method withRepo:(Lkotlin/jvm/functions/Function1;)V
      15: return

  public void Build validation not OK with tag pattern();
    Code:
       0: aload_0
       1: new           #38                 // class "net/nemerosa/ontrack/extension/git/service/GitBuildValidationIT$Build validation not OK with tag pattern$1"
       4: dup
       5: aload_0
       6: invokespecial #39                 // Method "net/nemerosa/ontrack/extension/git/service/GitBuildValidationIT$Build validation not OK with tag pattern$1"."<init>":(Lnet/nemerosa/ontrack/extension/git/service/GitBuildValidationIT;)V
       9: checkcast     #21                 // class kotlin/jvm/functions/Function1
      12: invokevirtual #33                 // Method withRepo:(Lkotlin/jvm/functions/Function1;)V
      15: return

  public void Build validation not OK on rename();
    Code:
       0: aload_0
       1: new           #42                 // class "net/nemerosa/ontrack/extension/git/service/GitBuildValidationIT$Build validation not OK on rename$1"
       4: dup
       5: aload_0
       6: invokespecial #43                 // Method "net/nemerosa/ontrack/extension/git/service/GitBuildValidationIT$Build validation not OK on rename$1"."<init>":(Lnet/nemerosa/ontrack/extension/git/service/GitBuildValidationIT;)V
       9: checkcast     #21                 // class kotlin/jvm/functions/Function1
      12: invokevirtual #33                 // Method withRepo:(Lkotlin/jvm/functions/Function1;)V
      15: return

  public static final net.nemerosa.ontrack.extension.git.model.ConfiguredBuildGitCommitLink access$tagPatternBuildName(net.nemerosa.ontrack.extension.git.service.GitBuildValidationIT, java.lang.String);
    Code:
       0: aload_0
       1: aload_1
       2: invokevirtual #49                 // Method tagPatternBuildName:(Ljava/lang/String;)Lnet/nemerosa/ontrack/extension/git/model/ConfiguredBuildGitCommitLink;
       5: areturn

  public static final net.nemerosa.ontrack.it.AbstractServiceTestJUnit4Support$UserCall access$asUser(net.nemerosa.ontrack.extension.git.service.GitBuildValidationIT);
    Code:
       0: aload_0
       1: invokevirtual #58                 // Method asUser:()Lnet/nemerosa/ontrack/it/AbstractServiceTestJUnit4Support$UserCall;
       4: areturn

  public static final net.nemerosa.ontrack.model.structure.StructureService access$getStructureService(net.nemerosa.ontrack.extension.git.service.GitBuildValidationIT);
    Code:
       0: aload_0
       1: invokevirtual #64                 // Method getStructureService:()Lnet/nemerosa/ontrack/model/structure/StructureService;
       4: areturn

  public static final net.nemerosa.ontrack.model.security.SecurityService access$getSecurityService(net.nemerosa.ontrack.extension.git.service.GitBuildValidationIT);
    Code:
       0: aload_0
       1: invokevirtual #70                 // Method getSecurityService:()Lnet/nemerosa/ontrack/model/security/SecurityService;
       4: areturn
}
