Compiled from "GitDiffIT.kt"
final class net.nemerosa.ontrack.extension.git.service.GitDiffIT$changeLog$1 extends kotlin.jvm.internal.Lambda implements kotlin.jvm.functions.Function1<net.nemerosa.ontrack.git.support.GitRepo, java.util.Map<java.lang.Integer, ? extends java.lang.String>> {
  public static final net.nemerosa.ontrack.extension.git.service.GitDiffIT$changeLog$1 INSTANCE;

  net.nemerosa.ontrack.extension.git.service.GitDiffIT$changeLog$1();
    Code:
       0: aload_0
       1: iconst_1
       2: invokespecial #12                 // Method kotlin/jvm/internal/Lambda."<init>":(I)V
       5: return

  public final java.util.Map<java.lang.Integer, java.lang.String> invoke(net.nemerosa.ontrack.git.support.GitRepo);
    Code:
       0: aload_1
       1: ldc           #20                 // String $this$createRepo
       3: invokestatic  #26                 // Method kotlin/jvm/internal/Intrinsics.checkNotNullParameter:(Ljava/lang/Object;Ljava/lang/String;)V
       6: aload_1
       7: ldc           #28                 // String file1
       9: ldc           #30                 // String Line 1\n
      11: iconst_0
      12: iconst_4
      13: aconst_null
      14: invokestatic  #36                 // Method net/nemerosa/ontrack/git/support/GitRepo.file$default:(Lnet/nemerosa/ontrack/git/support/GitRepo;Ljava/lang/String;Ljava/lang/String;ZILjava/lang/Object;)V
      17: aload_1
      18: ldc           #38                 // String file2
      20: ldc           #30                 // String Line 1\n
      22: iconst_0
      23: iconst_4
      24: aconst_null
      25: invokestatic  #36                 // Method net/nemerosa/ontrack/git/support/GitRepo.file$default:(Lnet/nemerosa/ontrack/git/support/GitRepo;Ljava/lang/String;Ljava/lang/String;ZILjava/lang/Object;)V
      28: aload_1
      29: ldc           #40                 // String file4
      31: ldc           #30                 // String Line 1\n
      33: iconst_0
      34: iconst_4
      35: aconst_null
      36: invokestatic  #36                 // Method net/nemerosa/ontrack/git/support/GitRepo.file$default:(Lnet/nemerosa/ontrack/git/support/GitRepo;Ljava/lang/String;Ljava/lang/String;ZILjava/lang/Object;)V
      39: aload_1
      40: iconst_3
      41: anewarray     #42                 // class java/lang/String
      44: astore_2
      45: aload_2
      46: iconst_0
      47: ldc           #44                 // String commit
      49: aastore
      50: aload_2
      51: iconst_1
      52: ldc           #46                 // String -m
      54: aastore
      55: aload_2
      56: iconst_2
      57: ldc           #48                 // String Commit 1
      59: aastore
      60: aload_2
      61: invokevirtual #52                 // Method net/nemerosa/ontrack/git/support/GitRepo.git:([Ljava/lang/String;)Ljava/lang/String;
      64: pop
      65: aload_1
      66: ldc           #28                 // String file1
      68: ldc           #54                 // String Line 1\nLine 2\n
      70: iconst_0
      71: iconst_4
      72: aconst_null
      73: invokestatic  #36                 // Method net/nemerosa/ontrack/git/support/GitRepo.file$default:(Lnet/nemerosa/ontrack/git/support/GitRepo;Ljava/lang/String;Ljava/lang/String;ZILjava/lang/Object;)V
      76: aload_1
      77: ldc           #38                 // String file2
      79: ldc           #30                 // String Line 1\n
      81: iconst_0
      82: iconst_4
      83: aconst_null
      84: invokestatic  #36                 // Method net/nemerosa/ontrack/git/support/GitRepo.file$default:(Lnet/nemerosa/ontrack/git/support/GitRepo;Ljava/lang/String;Ljava/lang/String;ZILjava/lang/Object;)V
      87: aload_1
      88: iconst_3
      89: anewarray     #42                 // class java/lang/String
      92: astore_2
      93: aload_2
      94: iconst_0
      95: ldc           #44                 // String commit
      97: aastore
      98: aload_2
      99: iconst_1
     100: ldc           #46                 // String -m
     102: aastore
     103: aload_2
     104: iconst_2
     105: ldc           #56                 // String Commit 2
     107: aastore
     108: aload_2
     109: invokevirtual #52                 // Method net/nemerosa/ontrack/git/support/GitRepo.git:([Ljava/lang/String;)Ljava/lang/String;
     112: pop
     113: aload_1
     114: ldc           #28                 // String file1
     116: ldc           #58                 // String Line 1\nLine 2\nLine 3\n
     118: iconst_0
     119: iconst_4
     120: aconst_null
     121: invokestatic  #36                 // Method net/nemerosa/ontrack/git/support/GitRepo.file$default:(Lnet/nemerosa/ontrack/git/support/GitRepo;Ljava/lang/String;Ljava/lang/String;ZILjava/lang/Object;)V
     124: aload_1
     125: ldc           #38                 // String file2
     127: ldc           #54                 // String Line 1\nLine 2\n
     129: iconst_0
     130: iconst_4
     131: aconst_null
     132: invokestatic  #36                 // Method net/nemerosa/ontrack/git/support/GitRepo.file$default:(Lnet/nemerosa/ontrack/git/support/GitRepo;Ljava/lang/String;Ljava/lang/String;ZILjava/lang/Object;)V
     135: aload_1
     136: ldc           #60                 // String file3
     138: ldc           #54                 // String Line 1\nLine 2\n
     140: iconst_0
     141: iconst_4
     142: aconst_null
     143: invokestatic  #36                 // Method net/nemerosa/ontrack/git/support/GitRepo.file$default:(Lnet/nemerosa/ontrack/git/support/GitRepo;Ljava/lang/String;Ljava/lang/String;ZILjava/lang/Object;)V
     146: aload_1
     147: ldc           #40                 // String file4
     149: invokevirtual #64                 // Method net/nemerosa/ontrack/git/support/GitRepo.delete:(Ljava/lang/String;)V
     152: aload_1
     153: iconst_3
     154: anewarray     #42                 // class java/lang/String
     157: astore_2
     158: aload_2
     159: iconst_0
     160: ldc           #44                 // String commit
     162: aastore
     163: aload_2
     164: iconst_1
     165: ldc           #46                 // String -m
     167: aastore
     168: aload_2
     169: iconst_2
     170: ldc           #66                 // String Commit 3
     172: aastore
     173: aload_2
     174: invokevirtual #52                 // Method net/nemerosa/ontrack/git/support/GitRepo.git:([Ljava/lang/String;)Ljava/lang/String;
     177: pop
     178: new           #68                 // class kotlin/ranges/IntRange
     181: dup
     182: iconst_1
     183: iconst_3
     184: invokespecial #71                 // Method kotlin/ranges/IntRange."<init>":(II)V
     187: checkcast     #73                 // class java/lang/Iterable
     190: astore_2
     191: iconst_0
     192: istore_3
     193: aload_2
     194: bipush        10
     196: invokestatic  #79                 // Method kotlin/collections/CollectionsKt.collectionSizeOrDefault:(Ljava/lang/Iterable;I)I
     199: invokestatic  #85                 // Method kotlin/collections/MapsKt.mapCapacity:(I)I
     202: bipush        16
     204: invokestatic  #91                 // Method kotlin/ranges/RangesKt.coerceAtLeast:(II)I
     207: istore        4
     209: aload_2
     210: astore        5
     212: new           #93                 // class java/util/LinkedHashMap
     215: dup
     216: iload         4
     218: invokespecial #94                 // Method java/util/LinkedHashMap."<init>":(I)V
     221: checkcast     #96                 // class java/util/Map
     224: astore        6
     226: iconst_0
     227: istore        7
     229: aload         5
     231: invokeinterface #100,  1          // InterfaceMethod java/lang/Iterable.iterator:()Ljava/util/Iterator;
     236: astore        8
     238: aload         8
     240: invokeinterface #106,  1          // InterfaceMethod java/util/Iterator.hasNext:()Z
     245: ifeq          314
     248: aload         8
     250: checkcast     #108                // class kotlin/collections/IntIterator
     253: invokevirtual #112                // Method kotlin/collections/IntIterator.nextInt:()I
     256: istore        9
     258: aload         6
     260: astore        10
     262: iload         9
     264: istore        11
     266: iconst_0
     267: istore        12
     269: iload         11
     271: invokestatic  #118                // Method java/lang/Integer.valueOf:(I)Ljava/lang/Integer;
     274: aload_1
     275: iload         11
     277: invokedynamic #130,  0            // InvokeDynamic #0:makeConcatWithConstants:(I)Ljava/lang/String;
     282: iconst_0
     283: iconst_2
     284: aconst_null
     285: invokestatic  #134                // Method net/nemerosa/ontrack/git/support/GitRepo.commitLookup$default:(Lnet/nemerosa/ontrack/git/support/GitRepo;Ljava/lang/String;ZILjava/lang/Object;)Ljava/lang/String;
     288: invokestatic  #140                // Method kotlin/TuplesKt.to:(Ljava/lang/Object;Ljava/lang/Object;)Lkotlin/Pair;
     291: astore        11
     293: aload         10
     295: aload         11
     297: invokevirtual #146                // Method kotlin/Pair.getFirst:()Ljava/lang/Object;
     300: aload         11
     302: invokevirtual #149                // Method kotlin/Pair.getSecond:()Ljava/lang/Object;
     305: invokeinterface #153,  3          // InterfaceMethod java/util/Map.put:(Ljava/lang/Object;Ljava/lang/Object;)Ljava/lang/Object;
     310: pop
     311: goto          238
     314: aload         6
     316: nop
     317: areturn

  public java.lang.Object invoke(java.lang.Object);
    Code:
       0: aload_0
       1: aload_1
       2: checkcast     #32                 // class net/nemerosa/ontrack/git/support/GitRepo
       5: invokevirtual #169                // Method invoke:(Lnet/nemerosa/ontrack/git/support/GitRepo;)Ljava/util/Map;
       8: areturn

  static {};
    Code:
       0: new           #2                  // class net/nemerosa/ontrack/extension/git/service/GitDiffIT$changeLog$1
       3: dup
       4: invokespecial #174                // Method "<init>":()V
       7: putstatic     #177                // Field INSTANCE:Lnet/nemerosa/ontrack/extension/git/service/GitDiffIT$changeLog$1;
      10: return
}
