Compiled from "OWLExpressionParserException.java"
public class org.protege.editor.owl.model.classexpression.OWLExpressionParserException extends org.semanticweb.owlapi.model.OWLException {
  private int startIndex;

  private int endIndex;

  private boolean owlClassExpected;

  private boolean owlObjectPropertyExpected;

  private boolean owlDataPropertyExpected;

  private boolean owlIndividualExpected;

  private boolean owlDatatypeExpected;

  private boolean owlAnnotationPropertyExpected;

  private java.util.Set<java.lang.String> expectedKeyWords;

  public org.protege.editor.owl.model.classexpression.OWLExpressionParserException(java.lang.String, int, int, boolean, boolean, boolean, boolean, boolean, boolean, java.util.Set<java.lang.String>);
    Code:
       0: aload_0
       1: aload_1
       2: invokespecial #1                  // Method org/semanticweb/owlapi/model/OWLException."<init>":(Ljava/lang/String;)V
       5: aload_0
       6: iload_2
       7: putfield      #2                  // Field startIndex:I
      10: aload_0
      11: iload_3
      12: putfield      #3                  // Field endIndex:I
      15: aload_0
      16: iload         4
      18: putfield      #4                  // Field owlClassExpected:Z
      21: aload_0
      22: iload         5
      24: putfield      #5                  // Field owlObjectPropertyExpected:Z
      27: aload_0
      28: iload         6
      30: putfield      #6                  // Field owlDataPropertyExpected:Z
      33: aload_0
      34: iload         7
      36: putfield      #7                  // Field owlIndividualExpected:Z
      39: aload_0
      40: iload         8
      42: putfield      #8                  // Field owlDatatypeExpected:Z
      45: aload_0
      46: iload         9
      48: putfield      #9                  // Field owlAnnotationPropertyExpected:Z
      51: aload_0
      52: aload         10
      54: putfield      #10                 // Field expectedKeyWords:Ljava/util/Set;
      57: return

  public org.protege.editor.owl.model.classexpression.OWLExpressionParserException(java.lang.Throwable);
    Code:
       0: aload_0
       1: aload_1
       2: invokespecial #11                 // Method org/semanticweb/owlapi/model/OWLException."<init>":(Ljava/lang/Throwable;)V
       5: return

  public int getStartIndex();
    Code:
       0: aload_0
       1: getfield      #2                  // Field startIndex:I
       4: ireturn

  public int getEndIndex();
    Code:
       0: aload_0
       1: getfield      #3                  // Field endIndex:I
       4: ireturn

  public boolean isOWLClassExpected();
    Code:
       0: aload_0
       1: getfield      #4                  // Field owlClassExpected:Z
       4: ireturn

  public boolean isOWLObjectPropertyExpected();
    Code:
       0: aload_0
       1: getfield      #5                  // Field owlObjectPropertyExpected:Z
       4: ireturn

  public boolean isOWLDataPropertyExpected();
    Code:
       0: aload_0
       1: getfield      #6                  // Field owlDataPropertyExpected:Z
       4: ireturn

  public boolean isOWLIndividualExpected();
    Code:
       0: aload_0
       1: getfield      #7                  // Field owlIndividualExpected:Z
       4: ireturn

  public boolean isDatatypeExpected();
    Code:
       0: aload_0
       1: getfield      #8                  // Field owlDatatypeExpected:Z
       4: ireturn

  public boolean isAnnotationPropertyExpected();
    Code:
       0: aload_0
       1: getfield      #9                  // Field owlAnnotationPropertyExpected:Z
       4: ireturn

  public java.util.Set<java.lang.String> getExpectedKeyWords();
    Code:
       0: aload_0
       1: getfield      #10                 // Field expectedKeyWords:Ljava/util/Set;
       4: areturn
}
