Compiled from "BodyPart.java"
public class org.glassfish.jersey.media.multipart.BodyPart {
  protected org.glassfish.jersey.media.multipart.ContentDisposition contentDisposition;

  private java.lang.Object entity;

  private final javax.ws.rs.core.MultivaluedMap<java.lang.String, java.lang.String> headers;

  private javax.ws.rs.core.MediaType mediaType;

  public org.glassfish.jersey.message.MessageBodyWorkers messageBodyWorkers;

  private org.glassfish.jersey.media.multipart.MultiPart parent;

  private javax.ws.rs.ext.Providers providers;

  public org.glassfish.jersey.media.multipart.BodyPart();
    Code:
       0: aload_0
       1: getstatic     #1                  // Field javax/ws/rs/core/MediaType.TEXT_PLAIN_TYPE:Ljavax/ws/rs/core/MediaType;
       4: invokespecial #2                  // Method "<init>":(Ljavax/ws/rs/core/MediaType;)V
       7: return

  public org.glassfish.jersey.media.multipart.BodyPart(javax.ws.rs.core.MediaType);
    Code:
       0: aload_0
       1: invokespecial #3                  // Method java/lang/Object."<init>":()V
       4: aload_0
       5: aconst_null
       6: putfield      #4                  // Field contentDisposition:Lorg/glassfish/jersey/media/multipart/ContentDisposition;
       9: aload_0
      10: invokestatic  #5                  // Method org/glassfish/jersey/message/internal/HeaderUtils.createInbound:()Ljavax/ws/rs/core/AbstractMultivaluedMap;
      13: putfield      #6                  // Field headers:Ljavax/ws/rs/core/MultivaluedMap;
      16: aload_0
      17: aconst_null
      18: putfield      #7                  // Field mediaType:Ljavax/ws/rs/core/MediaType;
      21: aload_0
      22: aconst_null
      23: putfield      #8                  // Field parent:Lorg/glassfish/jersey/media/multipart/MultiPart;
      26: aload_0
      27: aconst_null
      28: putfield      #9                  // Field providers:Ljavax/ws/rs/ext/Providers;
      31: aload_0
      32: aload_1
      33: invokevirtual #10                 // Method setMediaType:(Ljavax/ws/rs/core/MediaType;)V
      36: return

  public org.glassfish.jersey.media.multipart.BodyPart(java.lang.Object, javax.ws.rs.core.MediaType);
    Code:
       0: aload_0
       1: invokespecial #3                  // Method java/lang/Object."<init>":()V
       4: aload_0
       5: aconst_null
       6: putfield      #4                  // Field contentDisposition:Lorg/glassfish/jersey/media/multipart/ContentDisposition;
       9: aload_0
      10: invokestatic  #5                  // Method org/glassfish/jersey/message/internal/HeaderUtils.createInbound:()Ljavax/ws/rs/core/AbstractMultivaluedMap;
      13: putfield      #6                  // Field headers:Ljavax/ws/rs/core/MultivaluedMap;
      16: aload_0
      17: aconst_null
      18: putfield      #7                  // Field mediaType:Ljavax/ws/rs/core/MediaType;
      21: aload_0
      22: aconst_null
      23: putfield      #8                  // Field parent:Lorg/glassfish/jersey/media/multipart/MultiPart;
      26: aload_0
      27: aconst_null
      28: putfield      #9                  // Field providers:Ljavax/ws/rs/ext/Providers;
      31: aload_0
      32: aload_1
      33: invokevirtual #11                 // Method setEntity:(Ljava/lang/Object;)V
      36: aload_0
      37: aload_2
      38: invokevirtual #10                 // Method setMediaType:(Ljavax/ws/rs/core/MediaType;)V
      41: return

  public java.lang.Object getEntity();
    Code:
       0: aload_0
       1: getfield      #12                 // Field entity:Ljava/lang/Object;
       4: areturn

  public void setEntity(java.lang.Object);
    Code:
       0: aload_0
       1: aload_1
       2: putfield      #12                 // Field entity:Ljava/lang/Object;
       5: return

  public javax.ws.rs.core.MultivaluedMap<java.lang.String, java.lang.String> getHeaders();
    Code:
       0: aload_0
       1: getfield      #6                  // Field headers:Ljavax/ws/rs/core/MultivaluedMap;
       4: areturn

  public javax.ws.rs.core.MultivaluedMap<java.lang.String, org.glassfish.jersey.message.internal.ParameterizedHeader> getParameterizedHeaders() throws java.text.ParseException;
    Code:
       0: new           #13                 // class org/glassfish/jersey/internal/util/collection/ImmutableMultivaluedMap
       3: dup
       4: new           #14                 // class org/glassfish/jersey/media/multipart/ParameterizedHeadersMap
       7: dup
       8: aload_0
       9: getfield      #6                  // Field headers:Ljavax/ws/rs/core/MultivaluedMap;
      12: invokespecial #15                 // Method org/glassfish/jersey/media/multipart/ParameterizedHeadersMap."<init>":(Ljavax/ws/rs/core/MultivaluedMap;)V
      15: invokespecial #16                 // Method org/glassfish/jersey/internal/util/collection/ImmutableMultivaluedMap."<init>":(Ljavax/ws/rs/core/MultivaluedMap;)V
      18: areturn

  public org.glassfish.jersey.media.multipart.ContentDisposition getContentDisposition();
    Code:
       0: aload_0
       1: getfield      #4                  // Field contentDisposition:Lorg/glassfish/jersey/media/multipart/ContentDisposition;
       4: ifnonnull     70
       7: aload_0
       8: getfield      #6                  // Field headers:Ljavax/ws/rs/core/MultivaluedMap;
      11: ldc           #17                 // String Content-Disposition
      13: invokeinterface #18,  2           // InterfaceMethod javax/ws/rs/core/MultivaluedMap.getFirst:(Ljava/lang/Object;)Ljava/lang/Object;
      18: checkcast     #19                 // class java/lang/String
      21: astore_1
      22: aload_1
      23: ifnull        70
      26: aload_0
      27: new           #20                 // class org/glassfish/jersey/media/multipart/ContentDisposition
      30: dup
      31: aload_1
      32: invokespecial #21                 // Method org/glassfish/jersey/media/multipart/ContentDisposition."<init>":(Ljava/lang/String;)V
      35: putfield      #4                  // Field contentDisposition:Lorg/glassfish/jersey/media/multipart/ContentDisposition;
      38: goto          70
      41: astore_2
      42: new           #23                 // class java/lang/IllegalArgumentException
      45: dup
      46: new           #24                 // class java/lang/StringBuilder
      49: dup
      50: invokespecial #25                 // Method java/lang/StringBuilder."<init>":()V
      53: ldc           #26                 // String Error parsing content disposition:
      55: invokevirtual #27                 // Method java/lang/StringBuilder.append:(Ljava/lang/String;)Ljava/lang/StringBuilder;
      58: aload_1
      59: invokevirtual #27                 // Method java/lang/StringBuilder.append:(Ljava/lang/String;)Ljava/lang/StringBuilder;
      62: invokevirtual #28                 // Method java/lang/StringBuilder.toString:()Ljava/lang/String;
      65: aload_2
      66: invokespecial #29                 // Method java/lang/IllegalArgumentException."<init>":(Ljava/lang/String;Ljava/lang/Throwable;)V
      69: athrow
      70: aload_0
      71: getfield      #4                  // Field contentDisposition:Lorg/glassfish/jersey/media/multipart/ContentDisposition;
      74: areturn
    Exception table:
       from    to  target type
          26    38    41   Class java/text/ParseException

  public void setContentDisposition(org.glassfish.jersey.media.multipart.ContentDisposition);
    Code:
       0: aload_0
       1: aload_1
       2: putfield      #4                  // Field contentDisposition:Lorg/glassfish/jersey/media/multipart/ContentDisposition;
       5: aload_0
       6: getfield      #6                  // Field headers:Ljavax/ws/rs/core/MultivaluedMap;
       9: ldc           #17                 // String Content-Disposition
      11: invokeinterface #30,  2           // InterfaceMethod javax/ws/rs/core/MultivaluedMap.remove:(Ljava/lang/Object;)Ljava/lang/Object;
      16: pop
      17: return

  public javax.ws.rs.core.MediaType getMediaType();
    Code:
       0: aload_0
       1: getfield      #7                  // Field mediaType:Ljavax/ws/rs/core/MediaType;
       4: areturn

  public void setMediaType(javax.ws.rs.core.MediaType);
    Code:
       0: aload_1
       1: ifnonnull     14
       4: new           #23                 // class java/lang/IllegalArgumentException
       7: dup
       8: ldc           #31                 // String mediaType cannot be null
      10: invokespecial #32                 // Method java/lang/IllegalArgumentException."<init>":(Ljava/lang/String;)V
      13: athrow
      14: aload_0
      15: aload_1
      16: putfield      #7                  // Field mediaType:Ljavax/ws/rs/core/MediaType;
      19: return

  public org.glassfish.jersey.media.multipart.MultiPart getParent();
    Code:
       0: aload_0
       1: getfield      #8                  // Field parent:Lorg/glassfish/jersey/media/multipart/MultiPart;
       4: areturn

  public void setParent(org.glassfish.jersey.media.multipart.MultiPart);
    Code:
       0: aload_0
       1: aload_1
       2: putfield      #8                  // Field parent:Lorg/glassfish/jersey/media/multipart/MultiPart;
       5: return

  public javax.ws.rs.ext.Providers getProviders();
    Code:
       0: aload_0
       1: getfield      #9                  // Field providers:Ljavax/ws/rs/ext/Providers;
       4: areturn

  public void setProviders(javax.ws.rs.ext.Providers);
    Code:
       0: aload_0
       1: aload_1
       2: putfield      #9                  // Field providers:Ljavax/ws/rs/ext/Providers;
       5: return

  public void cleanup();
    Code:
       0: aload_0
       1: invokevirtual #33                 // Method getEntity:()Ljava/lang/Object;
       4: ifnull        27
       7: aload_0
       8: invokevirtual #33                 // Method getEntity:()Ljava/lang/Object;
      11: instanceof    #34                 // class org/glassfish/jersey/media/multipart/BodyPartEntity
      14: ifeq          27
      17: aload_0
      18: invokevirtual #33                 // Method getEntity:()Ljava/lang/Object;
      21: checkcast     #34                 // class org/glassfish/jersey/media/multipart/BodyPartEntity
      24: invokevirtual #35                 // Method org/glassfish/jersey/media/multipart/BodyPartEntity.cleanup:()V
      27: return

  public org.glassfish.jersey.media.multipart.BodyPart entity(java.lang.Object);
    Code:
       0: aload_0
       1: aload_1
       2: invokevirtual #11                 // Method setEntity:(Ljava/lang/Object;)V
       5: aload_0
       6: areturn

  public <T> T getEntityAs(java.lang.Class<T>);
    Code:
       0: aload_0
       1: getfield      #12                 // Field entity:Ljava/lang/Object;
       4: ifnull        17
       7: aload_0
       8: getfield      #12                 // Field entity:Ljava/lang/Object;
      11: instanceof    #34                 // class org/glassfish/jersey/media/multipart/BodyPartEntity
      14: ifne          28
      17: new           #36                 // class java/lang/IllegalStateException
      20: dup
      21: invokestatic  #37                 // Method org/glassfish/jersey/media/multipart/internal/LocalizationMessages.ENTITY_HAS_WRONG_TYPE:()Ljava/lang/String;
      24: invokespecial #38                 // Method java/lang/IllegalStateException."<init>":(Ljava/lang/String;)V
      27: athrow
      28: aload_1
      29: ldc           #34                 // class org/glassfish/jersey/media/multipart/BodyPartEntity
      31: if_acmpne     43
      34: aload_1
      35: aload_0
      36: getfield      #12                 // Field entity:Ljava/lang/Object;
      39: invokevirtual #39                 // Method java/lang/Class.cast:(Ljava/lang/Object;)Ljava/lang/Object;
      42: areturn
      43: iconst_0
      44: anewarray     #40                 // class java/lang/annotation/Annotation
      47: astore_2
      48: aload_0
      49: getfield      #41                 // Field messageBodyWorkers:Lorg/glassfish/jersey/message/MessageBodyWorkers;
      52: aload_1
      53: aload_1
      54: aload_2
      55: aload_0
      56: getfield      #7                  // Field mediaType:Ljavax/ws/rs/core/MediaType;
      59: invokeinterface #42,  5           // InterfaceMethod org/glassfish/jersey/message/MessageBodyWorkers.getMessageBodyReader:(Ljava/lang/Class;Ljava/lang/reflect/Type;[Ljava/lang/annotation/Annotation;Ljavax/ws/rs/core/MediaType;)Ljavax/ws/rs/ext/MessageBodyReader;
      64: astore_3
      65: aload_3
      66: ifnonnull     85
      69: new           #23                 // class java/lang/IllegalArgumentException
      72: dup
      73: aload_1
      74: aload_0
      75: getfield      #7                  // Field mediaType:Ljavax/ws/rs/core/MediaType;
      78: invokestatic  #43                 // Method org/glassfish/jersey/media/multipart/internal/LocalizationMessages.NO_AVAILABLE_MBR:(Ljava/lang/Object;Ljava/lang/Object;)Ljava/lang/String;
      81: invokespecial #32                 // Method java/lang/IllegalArgumentException."<init>":(Ljava/lang/String;)V
      84: athrow
      85: aload_3
      86: aload_1
      87: aload_1
      88: aload_2
      89: aload_0
      90: getfield      #7                  // Field mediaType:Ljavax/ws/rs/core/MediaType;
      93: aload_0
      94: getfield      #6                  // Field headers:Ljavax/ws/rs/core/MultivaluedMap;
      97: aload_0
      98: getfield      #12                 // Field entity:Ljava/lang/Object;
     101: checkcast     #34                 // class org/glassfish/jersey/media/multipart/BodyPartEntity
     104: invokevirtual #44                 // Method org/glassfish/jersey/media/multipart/BodyPartEntity.getInputStream:()Ljava/io/InputStream;
     107: invokeinterface #45,  7           // InterfaceMethod javax/ws/rs/ext/MessageBodyReader.readFrom:(Ljava/lang/Class;Ljava/lang/reflect/Type;[Ljava/lang/annotation/Annotation;Ljavax/ws/rs/core/MediaType;Ljavax/ws/rs/core/MultivaluedMap;Ljava/io/InputStream;)Ljava/lang/Object;
     112: areturn
     113: astore        4
     115: new           #47                 // class javax/ws/rs/ProcessingException
     118: dup
     119: ldc           #19                 // class java/lang/String
     121: invokestatic  #48                 // Method org/glassfish/jersey/media/multipart/internal/LocalizationMessages.ERROR_READING_ENTITY:(Ljava/lang/Object;)Ljava/lang/String;
     124: aload         4
     126: invokespecial #49                 // Method javax/ws/rs/ProcessingException."<init>":(Ljava/lang/String;Ljava/lang/Throwable;)V
     129: athrow
    Exception table:
       from    to  target type
          85   112   113   Class java/io/IOException

  public org.glassfish.jersey.media.multipart.BodyPart type(javax.ws.rs.core.MediaType);
    Code:
       0: aload_0
       1: aload_1
       2: invokevirtual #10                 // Method setMediaType:(Ljavax/ws/rs/core/MediaType;)V
       5: aload_0
       6: areturn

  public org.glassfish.jersey.media.multipart.BodyPart contentDisposition(org.glassfish.jersey.media.multipart.ContentDisposition);
    Code:
       0: aload_0
       1: aload_1
       2: invokevirtual #50                 // Method setContentDisposition:(Lorg/glassfish/jersey/media/multipart/ContentDisposition;)V
       5: aload_0
       6: areturn

  public void setMessageBodyWorkers(org.glassfish.jersey.message.MessageBodyWorkers);
    Code:
       0: aload_0
       1: aload_1
       2: putfield      #41                 // Field messageBodyWorkers:Lorg/glassfish/jersey/message/MessageBodyWorkers;
       5: return
}
