Compiled from "FormDataMultiPart.java"
public class org.glassfish.jersey.media.multipart.FormDataMultiPart extends org.glassfish.jersey.media.multipart.MultiPart {
  public org.glassfish.jersey.media.multipart.FormDataMultiPart();
    Code:
       0: aload_0
       1: getstatic     #1                  // Field javax/ws/rs/core/MediaType.MULTIPART_FORM_DATA_TYPE:Ljavax/ws/rs/core/MediaType;
       4: invokespecial #2                  // Method org/glassfish/jersey/media/multipart/MultiPart."<init>":(Ljavax/ws/rs/core/MediaType;)V
       7: return

  public org.glassfish.jersey.media.multipart.FormDataMultiPart field(java.lang.String, java.lang.String);
    Code:
       0: aload_0
       1: invokevirtual #3                  // Method getBodyParts:()Ljava/util/List;
       4: new           #4                  // class org/glassfish/jersey/media/multipart/FormDataBodyPart
       7: dup
       8: aload_1
       9: aload_2
      10: invokespecial #5                  // Method org/glassfish/jersey/media/multipart/FormDataBodyPart."<init>":(Ljava/lang/String;Ljava/lang/String;)V
      13: invokeinterface #6,  2            // InterfaceMethod java/util/List.add:(Ljava/lang/Object;)Z
      18: pop
      19: aload_0
      20: areturn

  public org.glassfish.jersey.media.multipart.FormDataMultiPart field(java.lang.String, java.lang.Object, javax.ws.rs.core.MediaType);
    Code:
       0: aload_0
       1: invokevirtual #3                  // Method getBodyParts:()Ljava/util/List;
       4: new           #4                  // class org/glassfish/jersey/media/multipart/FormDataBodyPart
       7: dup
       8: aload_1
       9: aload_2
      10: aload_3
      11: invokespecial #7                  // Method org/glassfish/jersey/media/multipart/FormDataBodyPart."<init>":(Ljava/lang/String;Ljava/lang/Object;Ljavax/ws/rs/core/MediaType;)V
      14: invokeinterface #6,  2            // InterfaceMethod java/util/List.add:(Ljava/lang/Object;)Z
      19: pop
      20: aload_0
      21: areturn

  public org.glassfish.jersey.media.multipart.FormDataBodyPart getField(java.lang.String);
    Code:
       0: aconst_null
       1: astore_2
       2: aload_0
       3: invokevirtual #3                  // Method getBodyParts:()Ljava/util/List;
       6: invokeinterface #8,  1            // InterfaceMethod java/util/List.iterator:()Ljava/util/Iterator;
      11: astore_3
      12: aload_3
      13: invokeinterface #9,  1            // InterfaceMethod java/util/Iterator.hasNext:()Z
      18: ifeq          70
      21: aload_3
      22: invokeinterface #10,  1           // InterfaceMethod java/util/Iterator.next:()Ljava/lang/Object;
      27: checkcast     #11                 // class org/glassfish/jersey/media/multipart/BodyPart
      30: astore        4
      32: aload         4
      34: instanceof    #4                  // class org/glassfish/jersey/media/multipart/FormDataBodyPart
      37: ifne          43
      40: goto          12
      43: aload_1
      44: aload         4
      46: checkcast     #4                  // class org/glassfish/jersey/media/multipart/FormDataBodyPart
      49: invokevirtual #12                 // Method org/glassfish/jersey/media/multipart/FormDataBodyPart.getName:()Ljava/lang/String;
      52: invokevirtual #13                 // Method java/lang/String.equals:(Ljava/lang/Object;)Z
      55: ifeq          67
      58: aload         4
      60: checkcast     #4                  // class org/glassfish/jersey/media/multipart/FormDataBodyPart
      63: astore_2
      64: goto          70
      67: goto          12
      70: aload_2
      71: areturn

  public java.util.List<org.glassfish.jersey.media.multipart.FormDataBodyPart> getFields(java.lang.String);
    Code:
       0: aconst_null
       1: astore_2
       2: aload_0
       3: invokevirtual #3                  // Method getBodyParts:()Ljava/util/List;
       6: invokeinterface #8,  1            // InterfaceMethod java/util/List.iterator:()Ljava/util/Iterator;
      11: astore_3
      12: aload_3
      13: invokeinterface #9,  1            // InterfaceMethod java/util/Iterator.hasNext:()Z
      18: ifeq          86
      21: aload_3
      22: invokeinterface #10,  1           // InterfaceMethod java/util/Iterator.next:()Ljava/lang/Object;
      27: checkcast     #11                 // class org/glassfish/jersey/media/multipart/BodyPart
      30: astore        4
      32: aload         4
      34: instanceof    #4                  // class org/glassfish/jersey/media/multipart/FormDataBodyPart
      37: ifne          43
      40: goto          12
      43: aload_1
      44: aload         4
      46: checkcast     #4                  // class org/glassfish/jersey/media/multipart/FormDataBodyPart
      49: invokevirtual #12                 // Method org/glassfish/jersey/media/multipart/FormDataBodyPart.getName:()Ljava/lang/String;
      52: invokevirtual #13                 // Method java/lang/String.equals:(Ljava/lang/Object;)Z
      55: ifeq          83
      58: aload_2
      59: ifnonnull     71
      62: new           #14                 // class java/util/ArrayList
      65: dup
      66: iconst_1
      67: invokespecial #15                 // Method java/util/ArrayList."<init>":(I)V
      70: astore_2
      71: aload_2
      72: aload         4
      74: checkcast     #4                  // class org/glassfish/jersey/media/multipart/FormDataBodyPart
      77: invokeinterface #6,  2            // InterfaceMethod java/util/List.add:(Ljava/lang/Object;)Z
      82: pop
      83: goto          12
      86: aload_2
      87: areturn

  public java.util.Map<java.lang.String, java.util.List<org.glassfish.jersey.media.multipart.FormDataBodyPart>> getFields();
    Code:
       0: new           #16                 // class java/util/HashMap
       3: dup
       4: invokespecial #17                 // Method java/util/HashMap."<init>":()V
       7: astore_1
       8: aload_0
       9: invokevirtual #3                  // Method getBodyParts:()Ljava/util/List;
      12: invokeinterface #8,  1            // InterfaceMethod java/util/List.iterator:()Ljava/util/Iterator;
      17: astore_2
      18: aload_2
      19: invokeinterface #9,  1            // InterfaceMethod java/util/Iterator.hasNext:()Z
      24: ifeq          111
      27: aload_2
      28: invokeinterface #10,  1           // InterfaceMethod java/util/Iterator.next:()Ljava/lang/Object;
      33: checkcast     #11                 // class org/glassfish/jersey/media/multipart/BodyPart
      36: astore_3
      37: aload_3
      38: instanceof    #4                  // class org/glassfish/jersey/media/multipart/FormDataBodyPart
      41: ifne          47
      44: goto          18
      47: aload_3
      48: checkcast     #4                  // class org/glassfish/jersey/media/multipart/FormDataBodyPart
      51: astore        4
      53: aload_1
      54: aload         4
      56: invokevirtual #12                 // Method org/glassfish/jersey/media/multipart/FormDataBodyPart.getName:()Ljava/lang/String;
      59: invokeinterface #18,  2           // InterfaceMethod java/util/Map.get:(Ljava/lang/Object;)Ljava/lang/Object;
      64: checkcast     #19                 // class java/util/List
      67: astore        5
      69: aload         5
      71: ifnonnull     98
      74: new           #14                 // class java/util/ArrayList
      77: dup
      78: iconst_1
      79: invokespecial #15                 // Method java/util/ArrayList."<init>":(I)V
      82: astore        5
      84: aload_1
      85: aload         4
      87: invokevirtual #12                 // Method org/glassfish/jersey/media/multipart/FormDataBodyPart.getName:()Ljava/lang/String;
      90: aload         5
      92: invokeinterface #20,  3           // InterfaceMethod java/util/Map.put:(Ljava/lang/Object;Ljava/lang/Object;)Ljava/lang/Object;
      97: pop
      98: aload         5
     100: aload         4
     102: invokeinterface #6,  2            // InterfaceMethod java/util/List.add:(Ljava/lang/Object;)Z
     107: pop
     108: goto          18
     111: aload_1
     112: areturn

  public void setMediaType(javax.ws.rs.core.MediaType);
    Code:
       0: aload_1
       1: getstatic     #1                  // Field javax/ws/rs/core/MediaType.MULTIPART_FORM_DATA_TYPE:Ljavax/ws/rs/core/MediaType;
       4: invokestatic  #21                 // Method org/glassfish/jersey/message/internal/MediaTypes.typeEqual:(Ljavax/ws/rs/core/MediaType;Ljavax/ws/rs/core/MediaType;)Z
       7: ifne          21
      10: new           #22                 // class java/lang/IllegalArgumentException
      13: dup
      14: invokestatic  #23                 // Method org/glassfish/jersey/media/multipart/internal/LocalizationMessages.FORM_DATA_MULTIPART_CANNOT_CHANGE_MEDIATYPE:()Ljava/lang/String;
      17: invokespecial #24                 // Method java/lang/IllegalArgumentException."<init>":(Ljava/lang/String;)V
      20: athrow
      21: aload_0
      22: aload_1
      23: invokespecial #25                 // Method org/glassfish/jersey/media/multipart/MultiPart.setMediaType:(Ljavax/ws/rs/core/MediaType;)V
      26: return
}
