Compiled from "BasicNIOConnFactory.java"
public class org.apache.http.impl.nio.pool.BasicNIOConnFactory implements org.apache.http.nio.pool.NIOConnFactory<org.apache.http.HttpHost, org.apache.http.nio.NHttpClientConnection> {
  private final org.apache.http.nio.NHttpConnectionFactory<? extends org.apache.http.nio.NHttpClientConnection> plainFactory;

  private final org.apache.http.nio.NHttpConnectionFactory<? extends org.apache.http.nio.NHttpClientConnection> sslFactory;

  public org.apache.http.impl.nio.pool.BasicNIOConnFactory(org.apache.http.nio.NHttpConnectionFactory<? extends org.apache.http.nio.NHttpClientConnection>, org.apache.http.nio.NHttpConnectionFactory<? extends org.apache.http.nio.NHttpClientConnection>);
    Code:
       0: aload_0
       1: invokespecial #1                  // Method java/lang/Object."<init>":()V
       4: aload_1
       5: ldc           #2                  // String Plain HTTP client connection factory
       7: invokestatic  #3                  // Method org/apache/http/util/Args.notNull:(Ljava/lang/Object;Ljava/lang/String;)Ljava/lang/Object;
      10: pop
      11: aload_0
      12: aload_1
      13: putfield      #4                  // Field plainFactory:Lorg/apache/http/nio/NHttpConnectionFactory;
      16: aload_0
      17: aload_2
      18: putfield      #5                  // Field sslFactory:Lorg/apache/http/nio/NHttpConnectionFactory;
      21: return

  public org.apache.http.impl.nio.pool.BasicNIOConnFactory(org.apache.http.nio.NHttpConnectionFactory<? extends org.apache.http.nio.NHttpClientConnection>);
    Code:
       0: aload_0
       1: aload_1
       2: aconst_null
       3: invokespecial #6                  // Method "<init>":(Lorg/apache/http/nio/NHttpConnectionFactory;Lorg/apache/http/nio/NHttpConnectionFactory;)V
       6: return

  public org.apache.http.impl.nio.pool.BasicNIOConnFactory(javax.net.ssl.SSLContext, org.apache.http.nio.reactor.ssl.SSLSetupHandler, org.apache.http.HttpResponseFactory, org.apache.http.nio.util.ByteBufferAllocator, org.apache.http.params.HttpParams);
    Code:
       0: aload_0
       1: new           #7                  // class org/apache/http/impl/nio/DefaultNHttpClientConnectionFactory
       4: dup
       5: aload_3
       6: aload         4
       8: aload         5
      10: invokespecial #8                  // Method org/apache/http/impl/nio/DefaultNHttpClientConnectionFactory."<init>":(Lorg/apache/http/HttpResponseFactory;Lorg/apache/http/nio/util/ByteBufferAllocator;Lorg/apache/http/params/HttpParams;)V
      13: new           #9                  // class org/apache/http/impl/nio/SSLNHttpClientConnectionFactory
      16: dup
      17: aload_1
      18: aload_2
      19: aload_3
      20: aload         4
      22: aload         5
      24: invokespecial #10                 // Method org/apache/http/impl/nio/SSLNHttpClientConnectionFactory."<init>":(Ljavax/net/ssl/SSLContext;Lorg/apache/http/nio/reactor/ssl/SSLSetupHandler;Lorg/apache/http/HttpResponseFactory;Lorg/apache/http/nio/util/ByteBufferAllocator;Lorg/apache/http/params/HttpParams;)V
      27: invokespecial #6                  // Method "<init>":(Lorg/apache/http/nio/NHttpConnectionFactory;Lorg/apache/http/nio/NHttpConnectionFactory;)V
      30: return

  public org.apache.http.impl.nio.pool.BasicNIOConnFactory(javax.net.ssl.SSLContext, org.apache.http.nio.reactor.ssl.SSLSetupHandler, org.apache.http.params.HttpParams);
    Code:
       0: aload_0
       1: aload_1
       2: aload_2
       3: getstatic     #11                 // Field org/apache/http/impl/DefaultHttpResponseFactory.INSTANCE:Lorg/apache/http/impl/DefaultHttpResponseFactory;
       6: getstatic     #12                 // Field org/apache/http/nio/util/HeapByteBufferAllocator.INSTANCE:Lorg/apache/http/nio/util/HeapByteBufferAllocator;
       9: aload_3
      10: invokespecial #13                 // Method "<init>":(Ljavax/net/ssl/SSLContext;Lorg/apache/http/nio/reactor/ssl/SSLSetupHandler;Lorg/apache/http/HttpResponseFactory;Lorg/apache/http/nio/util/ByteBufferAllocator;Lorg/apache/http/params/HttpParams;)V
      13: return

  public org.apache.http.impl.nio.pool.BasicNIOConnFactory(org.apache.http.params.HttpParams);
    Code:
       0: aload_0
       1: aconst_null
       2: aconst_null
       3: aload_1
       4: invokespecial #14                 // Method "<init>":(Ljavax/net/ssl/SSLContext;Lorg/apache/http/nio/reactor/ssl/SSLSetupHandler;Lorg/apache/http/params/HttpParams;)V
       7: return

  public org.apache.http.impl.nio.pool.BasicNIOConnFactory(javax.net.ssl.SSLContext, org.apache.http.nio.reactor.ssl.SSLSetupHandler, org.apache.http.nio.NHttpMessageParserFactory<org.apache.http.HttpResponse>, org.apache.http.nio.NHttpMessageWriterFactory<org.apache.http.HttpRequest>, org.apache.http.nio.util.ByteBufferAllocator, org.apache.http.config.ConnectionConfig);
    Code:
       0: aload_0
       1: new           #7                  // class org/apache/http/impl/nio/DefaultNHttpClientConnectionFactory
       4: dup
       5: aload_3
       6: aload         4
       8: aload         5
      10: aload         6
      12: invokespecial #15                 // Method org/apache/http/impl/nio/DefaultNHttpClientConnectionFactory."<init>":(Lorg/apache/http/nio/NHttpMessageParserFactory;Lorg/apache/http/nio/NHttpMessageWriterFactory;Lorg/apache/http/nio/util/ByteBufferAllocator;Lorg/apache/http/config/ConnectionConfig;)V
      15: new           #9                  // class org/apache/http/impl/nio/SSLNHttpClientConnectionFactory
      18: dup
      19: aload_1
      20: aload_2
      21: aload_3
      22: aload         4
      24: aload         5
      26: aload         6
      28: invokespecial #16                 // Method org/apache/http/impl/nio/SSLNHttpClientConnectionFactory."<init>":(Ljavax/net/ssl/SSLContext;Lorg/apache/http/nio/reactor/ssl/SSLSetupHandler;Lorg/apache/http/nio/NHttpMessageParserFactory;Lorg/apache/http/nio/NHttpMessageWriterFactory;Lorg/apache/http/nio/util/ByteBufferAllocator;Lorg/apache/http/config/ConnectionConfig;)V
      31: invokespecial #6                  // Method "<init>":(Lorg/apache/http/nio/NHttpConnectionFactory;Lorg/apache/http/nio/NHttpConnectionFactory;)V
      34: return

  public org.apache.http.impl.nio.pool.BasicNIOConnFactory(javax.net.ssl.SSLContext, org.apache.http.nio.reactor.ssl.SSLSetupHandler, org.apache.http.config.ConnectionConfig);
    Code:
       0: aload_0
       1: aload_1
       2: aload_2
       3: aconst_null
       4: aconst_null
       5: aconst_null
       6: aload_3
       7: invokespecial #17                 // Method "<init>":(Ljavax/net/ssl/SSLContext;Lorg/apache/http/nio/reactor/ssl/SSLSetupHandler;Lorg/apache/http/nio/NHttpMessageParserFactory;Lorg/apache/http/nio/NHttpMessageWriterFactory;Lorg/apache/http/nio/util/ByteBufferAllocator;Lorg/apache/http/config/ConnectionConfig;)V
      10: return

  public org.apache.http.impl.nio.pool.BasicNIOConnFactory(org.apache.http.config.ConnectionConfig);
    Code:
       0: aload_0
       1: new           #7                  // class org/apache/http/impl/nio/DefaultNHttpClientConnectionFactory
       4: dup
       5: aload_1
       6: invokespecial #18                 // Method org/apache/http/impl/nio/DefaultNHttpClientConnectionFactory."<init>":(Lorg/apache/http/config/ConnectionConfig;)V
       9: aconst_null
      10: invokespecial #6                  // Method "<init>":(Lorg/apache/http/nio/NHttpConnectionFactory;Lorg/apache/http/nio/NHttpConnectionFactory;)V
      13: return

  public org.apache.http.nio.NHttpClientConnection create(org.apache.http.HttpHost, org.apache.http.nio.reactor.IOSession) throws java.io.IOException;
    Code:
       0: aload_1
       1: invokevirtual #19                 // Method org/apache/http/HttpHost.getSchemeName:()Ljava/lang/String;
       4: ldc           #20                 // String https
       6: invokevirtual #21                 // Method java/lang/String.equalsIgnoreCase:(Ljava/lang/String;)Z
       9: ifeq          46
      12: aload_0
      13: getfield      #5                  // Field sslFactory:Lorg/apache/http/nio/NHttpConnectionFactory;
      16: ifnonnull     29
      19: new           #22                 // class java/io/IOException
      22: dup
      23: ldc           #23                 // String SSL not supported
      25: invokespecial #24                 // Method java/io/IOException."<init>":(Ljava/lang/String;)V
      28: athrow
      29: aload_0
      30: getfield      #5                  // Field sslFactory:Lorg/apache/http/nio/NHttpConnectionFactory;
      33: aload_2
      34: invokeinterface #25,  2           // InterfaceMethod org/apache/http/nio/NHttpConnectionFactory.createConnection:(Lorg/apache/http/nio/reactor/IOSession;)Lorg/apache/http/nio/NHttpConnection;
      39: checkcast     #26                 // class org/apache/http/nio/NHttpClientConnection
      42: astore_3
      43: goto          60
      46: aload_0
      47: getfield      #4                  // Field plainFactory:Lorg/apache/http/nio/NHttpConnectionFactory;
      50: aload_2
      51: invokeinterface #25,  2           // InterfaceMethod org/apache/http/nio/NHttpConnectionFactory.createConnection:(Lorg/apache/http/nio/reactor/IOSession;)Lorg/apache/http/nio/NHttpConnection;
      56: checkcast     #26                 // class org/apache/http/nio/NHttpClientConnection
      59: astore_3
      60: aload_2
      61: ldc           #27                 // String http.connection
      63: aload_3
      64: invokeinterface #28,  3           // InterfaceMethod org/apache/http/nio/reactor/IOSession.setAttribute:(Ljava/lang/String;Ljava/lang/Object;)V
      69: aload_3
      70: areturn

  public java.lang.Object create(java.lang.Object, org.apache.http.nio.reactor.IOSession) throws java.io.IOException;
    Code:
       0: aload_0
       1: aload_1
       2: checkcast     #29                 // class org/apache/http/HttpHost
       5: aload_2
       6: invokevirtual #30                 // Method create:(Lorg/apache/http/HttpHost;Lorg/apache/http/nio/reactor/IOSession;)Lorg/apache/http/nio/NHttpClientConnection;
       9: areturn
}
