Compiled from "TraceWebClientAutoConfiguration.java"
final class org.springframework.cloud.sleuth.instrument.web.client.TracingHttpClientInstrumentation$1 implements brave.propagation.Propagation$Setter<io.netty.handler.codec.http.HttpHeaders, java.lang.String> {
  org.springframework.cloud.sleuth.instrument.web.client.TracingHttpClientInstrumentation$1();
    Code:
       0: aload_0
       1: invokespecial #1                  // Method java/lang/Object."<init>":()V
       4: return

  public void put(io.netty.handler.codec.http.HttpHeaders, java.lang.String, java.lang.String);
    Code:
       0: aload_1
       1: aload_2
       2: invokevirtual #2                  // Method io/netty/handler/codec/http/HttpHeaders.contains:(Ljava/lang/String;)Z
       5: ifne          15
       8: aload_1
       9: aload_2
      10: aload_3
      11: invokevirtual #3                  // Method io/netty/handler/codec/http/HttpHeaders.add:(Ljava/lang/String;Ljava/lang/Object;)Lio/netty/handler/codec/http/HttpHeaders;
      14: pop
      15: return

  public java.lang.String toString();
    Code:
       0: ldc           #4                  // String HttpHeaders::add
       2: areturn

  public void put(java.lang.Object, java.lang.Object, java.lang.String);
    Code:
       0: aload_0
       1: aload_1
       2: checkcast     #5                  // class io/netty/handler/codec/http/HttpHeaders
       5: aload_2
       6: checkcast     #6                  // class java/lang/String
       9: aload_3
      10: invokevirtual #7                  // Method put:(Lio/netty/handler/codec/http/HttpHeaders;Ljava/lang/String;Ljava/lang/String;)V
      13: return
}
