Compiled from "Junit5SnapshotTestContextProvider.java"
final class de.skuzzle.test.snapshots.junit5.Junit5SnapshotTestContextProvider {
  private static final org.junit.jupiter.api.extension.ExtensionContext$Namespace NAMESPACE;

  private static final java.lang.String KEY_SELF;

  de.skuzzle.test.snapshots.junit5.Junit5SnapshotTestContextProvider();
    Code:
       0: aload_0
       1: invokespecial #1                  // Method java/lang/Object."<init>":()V
       4: return

  public static de.skuzzle.test.snapshots.impl.SnapshotTestContext fromExtensionContext(org.junit.jupiter.api.extension.ExtensionContext);
    Code:
       0: aload_0
       1: invokestatic  #2                  // Method searchParents:(Lorg/junit/jupiter/api/extension/ExtensionContext;)Ljava/util/Optional;
       4: invokedynamic #3,  0              // InvokeDynamic #0:get:()Ljava/util/function/Supplier;
       9: invokevirtual #4                  // Method java/util/Optional.orElseThrow:(Ljava/util/function/Supplier;)Ljava/lang/Object;
      12: checkcast     #5                  // class de/skuzzle/test/snapshots/impl/SnapshotTestContext
      15: areturn

  public static de.skuzzle.test.snapshots.impl.SnapshotTestContext create(org.junit.jupiter.api.extension.ExtensionContext);
    Code:
       0: aload_0
       1: invokeinterface #6,  1            // InterfaceMethod org/junit/jupiter/api/extension/ExtensionContext.getRequiredTestClass:()Ljava/lang/Class;
       6: astore_1
       7: aload_1
       8: invokestatic  #7                  // InterfaceMethod de/skuzzle/test/snapshots/impl/SnapshotConfiguration.defaultConfigurationFor:(Ljava/lang/Class;)Lde/skuzzle/test/snapshots/impl/SnapshotConfiguration;
      11: astore_2
      12: aload_2
      13: invokestatic  #8                  // Method de/skuzzle/test/snapshots/impl/SnapshotTestContext.forConfiguration:(Lde/skuzzle/test/snapshots/impl/SnapshotConfiguration;)Lde/skuzzle/test/snapshots/impl/SnapshotTestContext;
      16: astore_3
      17: aload_0
      18: getstatic     #9                  // Field NAMESPACE:Lorg/junit/jupiter/api/extension/ExtensionContext$Namespace;
      21: invokeinterface #10,  2           // InterfaceMethod org/junit/jupiter/api/extension/ExtensionContext.getStore:(Lorg/junit/jupiter/api/extension/ExtensionContext$Namespace;)Lorg/junit/jupiter/api/extension/ExtensionContext$Store;
      26: ldc           #12                 // String SNAPSHOT_CONTEXT
      28: aload_3
      29: invokeinterface #13,  3           // InterfaceMethod org/junit/jupiter/api/extension/ExtensionContext$Store.put:(Ljava/lang/Object;Ljava/lang/Object;)V
      34: aload_3
      35: areturn

  public static de.skuzzle.test.snapshots.impl.SnapshotTestContext createLegacy(org.junit.jupiter.api.extension.ExtensionContext);
    Code:
       0: aload_0
       1: invokeinterface #6,  1            // InterfaceMethod org/junit/jupiter/api/extension/ExtensionContext.getRequiredTestClass:()Ljava/lang/Class;
       6: astore_1
       7: aload_1
       8: invokestatic  #14                 // InterfaceMethod de/skuzzle/test/snapshots/impl/SnapshotConfiguration.legacyConfigurationFor:(Ljava/lang/Class;)Lde/skuzzle/test/snapshots/impl/SnapshotConfiguration;
      11: astore_2
      12: aload_2
      13: invokestatic  #8                  // Method de/skuzzle/test/snapshots/impl/SnapshotTestContext.forConfiguration:(Lde/skuzzle/test/snapshots/impl/SnapshotConfiguration;)Lde/skuzzle/test/snapshots/impl/SnapshotTestContext;
      16: astore_3
      17: aload_0
      18: getstatic     #9                  // Field NAMESPACE:Lorg/junit/jupiter/api/extension/ExtensionContext$Namespace;
      21: invokeinterface #10,  2           // InterfaceMethod org/junit/jupiter/api/extension/ExtensionContext.getStore:(Lorg/junit/jupiter/api/extension/ExtensionContext$Namespace;)Lorg/junit/jupiter/api/extension/ExtensionContext$Store;
      26: ldc           #12                 // String SNAPSHOT_CONTEXT
      28: aload_3
      29: invokeinterface #13,  3           // InterfaceMethod org/junit/jupiter/api/extension/ExtensionContext$Store.put:(Ljava/lang/Object;Ljava/lang/Object;)V
      34: aload_3
      35: areturn

  private static java.util.Optional<de.skuzzle.test.snapshots.impl.SnapshotTestContext> searchParents(org.junit.jupiter.api.extension.ExtensionContext);
    Code:
       0: aload_0
       1: astore_1
       2: aload_1
       3: ifnull        54
       6: aload_1
       7: getstatic     #9                  // Field NAMESPACE:Lorg/junit/jupiter/api/extension/ExtensionContext$Namespace;
      10: invokeinterface #10,  2           // InterfaceMethod org/junit/jupiter/api/extension/ExtensionContext.getStore:(Lorg/junit/jupiter/api/extension/ExtensionContext$Namespace;)Lorg/junit/jupiter/api/extension/ExtensionContext$Store;
      15: ldc           #12                 // String SNAPSHOT_CONTEXT
      17: ldc           #5                  // class de/skuzzle/test/snapshots/impl/SnapshotTestContext
      19: invokeinterface #15,  3           // InterfaceMethod org/junit/jupiter/api/extension/ExtensionContext$Store.get:(Ljava/lang/Object;Ljava/lang/Class;)Ljava/lang/Object;
      24: checkcast     #5                  // class de/skuzzle/test/snapshots/impl/SnapshotTestContext
      27: astore_2
      28: aload_2
      29: ifnull        37
      32: aload_2
      33: invokestatic  #16                 // Method java/util/Optional.of:(Ljava/lang/Object;)Ljava/util/Optional;
      36: areturn
      37: aload_1
      38: invokeinterface #17,  1           // InterfaceMethod org/junit/jupiter/api/extension/ExtensionContext.getParent:()Ljava/util/Optional;
      43: aconst_null
      44: invokevirtual #18                 // Method java/util/Optional.orElse:(Ljava/lang/Object;)Ljava/lang/Object;
      47: checkcast     #19                 // class org/junit/jupiter/api/extension/ExtensionContext
      50: astore_1
      51: goto          2
      54: invokestatic  #20                 // Method java/util/Optional.empty:()Ljava/util/Optional;
      57: areturn

  private static java.lang.IllegalStateException lambda$fromExtensionContext$0();
    Code:
       0: new           #21                 // class java/lang/IllegalStateException
       3: dup
       4: ldc           #22                 // String SnapshotTestContext not found on given ExtensionContext or any of its parents
       6: invokespecial #23                 // Method java/lang/IllegalStateException."<init>":(Ljava/lang/String;)V
       9: areturn

  static {};
    Code:
       0: iconst_1
       1: anewarray     #24                 // class java/lang/Object
       4: dup
       5: iconst_0
       6: ldc           #25                 // class de/skuzzle/test/snapshots/junit5/JUnit5SnapshotExtension
       8: aastore
       9: invokestatic  #26                 // Method org/junit/jupiter/api/extension/ExtensionContext$Namespace.create:([Ljava/lang/Object;)Lorg/junit/jupiter/api/extension/ExtensionContext$Namespace;
      12: putstatic     #9                  // Field NAMESPACE:Lorg/junit/jupiter/api/extension/ExtensionContext$Namespace;
      15: return
}
