Compiled from "ElasticsearchExceptionMapper.java"
public class org.graylog2.rest.ElasticsearchExceptionMapper implements javax.ws.rs.ext.ExceptionMapper<org.graylog2.indexer.ElasticsearchException> {
  public org.graylog2.rest.ElasticsearchExceptionMapper();
    Code:
       0: aload_0
       1: invokespecial #1                  // Method java/lang/Object."<init>":()V
       4: return

  public javax.ws.rs.core.Response toResponse(org.graylog2.indexer.ElasticsearchException);
    Code:
       0: aload_1
       1: invokevirtual #2                  // Method org/graylog2/indexer/ElasticsearchException.getMessage:()Ljava/lang/String;
       4: aload_1
       5: invokevirtual #3                  // Method org/graylog2/indexer/ElasticsearchException.getErrorDetails:()Ljava/util/List;
       8: invokestatic  #4                  // Method org/graylog2/rest/resources/search/responses/SearchError.create:(Ljava/lang/String;Ljava/util/Collection;)Lorg/graylog2/rest/resources/search/responses/SearchError;
      11: astore_2
      12: getstatic     #5                  // Field javax/ws/rs/core/Response$Status.INTERNAL_SERVER_ERROR:Ljavax/ws/rs/core/Response$Status;
      15: invokestatic  #6                  // Method javax/ws/rs/core/Response.status:(Ljavax/ws/rs/core/Response$Status;)Ljavax/ws/rs/core/Response$ResponseBuilder;
      18: aload_2
      19: invokevirtual #7                  // Method javax/ws/rs/core/Response$ResponseBuilder.entity:(Ljava/lang/Object;)Ljavax/ws/rs/core/Response$ResponseBuilder;
      22: invokevirtual #8                  // Method javax/ws/rs/core/Response$ResponseBuilder.build:()Ljavax/ws/rs/core/Response;
      25: areturn

  public javax.ws.rs.core.Response toResponse(java.lang.Throwable);
    Code:
       0: aload_0
       1: aload_1
       2: checkcast     #9                  // class org/graylog2/indexer/ElasticsearchException
       5: invokevirtual #10                 // Method toResponse:(Lorg/graylog2/indexer/ElasticsearchException;)Ljavax/ws/rs/core/Response;
       8: areturn
}
