Compiled from "NicInterfaceCriteria.java"
public class org.jboss.as.controller.interfaces.NicInterfaceCriteria extends org.jboss.as.controller.interfaces.AbstractInterfaceCriteria {
  private static final long serialVersionUID;

  private final java.lang.String name;

  public org.jboss.as.controller.interfaces.NicInterfaceCriteria(java.lang.String);
    Code:
       0: aload_0
       1: invokespecial #1                  // Method org/jboss/as/controller/interfaces/AbstractInterfaceCriteria."<init>":()V
       4: aload_1
       5: ifnonnull     19
       8: getstatic     #2                  // Field org/jboss/as/controller/logging/ControllerLogger.ROOT_LOGGER:Lorg/jboss/as/controller/logging/ControllerLogger;
      11: ldc           #3                  // String name
      13: invokeinterface #4,  2            // InterfaceMethod org/jboss/as/controller/logging/ControllerLogger.nullVar:(Ljava/lang/String;)Ljava/lang/IllegalArgumentException;
      18: athrow
      19: aload_0
      20: aload_1
      21: putfield      #5                  // Field name:Ljava/lang/String;
      24: return

  public java.lang.String getAcceptableName();
    Code:
       0: aload_0
       1: getfield      #5                  // Field name:Ljava/lang/String;
       4: areturn

  protected java.net.InetAddress isAcceptable(java.net.NetworkInterface, java.net.InetAddress) throws java.net.SocketException;
    Code:
       0: aload_0
       1: getfield      #5                  // Field name:Ljava/lang/String;
       4: aload_1
       5: invokevirtual #6                  // Method java/net/NetworkInterface.getName:()Ljava/lang/String;
       8: invokevirtual #7                  // Method java/lang/String.equals:(Ljava/lang/Object;)Z
      11: ifeq          16
      14: aload_2
      15: areturn
      16: aconst_null
      17: areturn

  public int hashCode();
    Code:
       0: aload_0
       1: getfield      #5                  // Field name:Ljava/lang/String;
       4: invokevirtual #8                  // Method java/lang/String.hashCode:()I
       7: ireturn

  public boolean equals(java.lang.Object);
    Code:
       0: aload_1
       1: instanceof    #9                  // class org/jboss/as/controller/interfaces/NicInterfaceCriteria
       4: ifeq          28
       7: aload_0
       8: getfield      #5                  // Field name:Ljava/lang/String;
      11: aload_1
      12: checkcast     #9                  // class org/jboss/as/controller/interfaces/NicInterfaceCriteria
      15: getfield      #5                  // Field name:Ljava/lang/String;
      18: invokevirtual #7                  // Method java/lang/String.equals:(Ljava/lang/Object;)Z
      21: ifeq          28
      24: iconst_1
      25: goto          29
      28: iconst_0
      29: ireturn
}
