Compiled from "SystemFunctions.java"
final class info.archinnov.achilles.generated.function.SystemFunctions$36 extends info.archinnov.achilles.generated.function.ByteBuffer_Type {
  final java.util.List val$params;

  info.archinnov.achilles.generated.function.SystemFunctions$36(java.util.Optional, java.util.List);
    Code:
       0: aload_0
       1: aload_2
       2: putfield      #1                  // Field val$params:Ljava/util/List;
       5: aload_0
       6: aload_1
       7: invokespecial #2                  // Method info/archinnov/achilles/generated/function/ByteBuffer_Type."<init>":(Ljava/util/Optional;)V
      10: return

  public boolean isFunctionCall();
    Code:
       0: iconst_1
       1: ireturn

  public java.lang.String functionName();
    Code:
       0: ldc           #3                  // String doubleAsBlob
       2: areturn

  public java.util.List<java.lang.Object> parameters();
    Code:
       0: aload_0
       1: getfield      #1                  // Field val$params:Ljava/util/List;
       4: areturn
}
