Compiled from "Configuration.java"
public final class org.modelmapper.config.Configuration$AccessLevel extends java.lang.Enum<org.modelmapper.config.Configuration$AccessLevel> {
  public static final org.modelmapper.config.Configuration$AccessLevel PUBLIC;

  public static final org.modelmapper.config.Configuration$AccessLevel PROTECTED;

  public static final org.modelmapper.config.Configuration$AccessLevel PACKAGE_PRIVATE;

  public static final org.modelmapper.config.Configuration$AccessLevel PRIVATE;

  private static final org.modelmapper.config.Configuration$AccessLevel[] $VALUES;

  public static org.modelmapper.config.Configuration$AccessLevel[] values();
    Code:
       0: getstatic     #20                 // Field $VALUES:[Lorg/modelmapper/config/Configuration$AccessLevel;
       3: invokevirtual #25                 // Method "[Lorg/modelmapper/config/Configuration$AccessLevel;".clone:()Ljava/lang/Object;
       6: checkcast     #21                 // class "[Lorg/modelmapper/config/Configuration$AccessLevel;"
       9: areturn

  public static org.modelmapper.config.Configuration$AccessLevel valueOf(java.lang.String);
    Code:
       0: ldc           #2                  // class org/modelmapper/config/Configuration$AccessLevel
       2: aload_0
       3: invokestatic  #30                 // Method java/lang/Enum.valueOf:(Ljava/lang/Class;Ljava/lang/String;)Ljava/lang/Enum;
       6: checkcast     #2                  // class org/modelmapper/config/Configuration$AccessLevel
       9: areturn

  private org.modelmapper.config.Configuration$AccessLevel();
    Code:
       0: aload_0
       1: aload_1
       2: iload_2
       3: invokespecial #36                 // Method java/lang/Enum."<init>":(Ljava/lang/String;I)V
       6: return

  static {};
    Code:
       0: new           #2                  // class org/modelmapper/config/Configuration$AccessLevel
       3: dup
       4: ldc           #40                 // String PUBLIC
       6: iconst_0
       7: invokespecial #41                 // Method "<init>":(Ljava/lang/String;I)V
      10: putstatic     #43                 // Field PUBLIC:Lorg/modelmapper/config/Configuration$AccessLevel;
      13: new           #2                  // class org/modelmapper/config/Configuration$AccessLevel
      16: dup
      17: ldc           #44                 // String PROTECTED
      19: iconst_1
      20: invokespecial #41                 // Method "<init>":(Ljava/lang/String;I)V
      23: putstatic     #46                 // Field PROTECTED:Lorg/modelmapper/config/Configuration$AccessLevel;
      26: new           #2                  // class org/modelmapper/config/Configuration$AccessLevel
      29: dup
      30: ldc           #47                 // String PACKAGE_PRIVATE
      32: iconst_2
      33: invokespecial #41                 // Method "<init>":(Ljava/lang/String;I)V
      36: putstatic     #49                 // Field PACKAGE_PRIVATE:Lorg/modelmapper/config/Configuration$AccessLevel;
      39: new           #2                  // class org/modelmapper/config/Configuration$AccessLevel
      42: dup
      43: ldc           #50                 // String PRIVATE
      45: iconst_3
      46: invokespecial #41                 // Method "<init>":(Ljava/lang/String;I)V
      49: putstatic     #52                 // Field PRIVATE:Lorg/modelmapper/config/Configuration$AccessLevel;
      52: iconst_4
      53: anewarray     #2                  // class org/modelmapper/config/Configuration$AccessLevel
      56: dup
      57: iconst_0
      58: getstatic     #43                 // Field PUBLIC:Lorg/modelmapper/config/Configuration$AccessLevel;
      61: aastore
      62: dup
      63: iconst_1
      64: getstatic     #46                 // Field PROTECTED:Lorg/modelmapper/config/Configuration$AccessLevel;
      67: aastore
      68: dup
      69: iconst_2
      70: getstatic     #49                 // Field PACKAGE_PRIVATE:Lorg/modelmapper/config/Configuration$AccessLevel;
      73: aastore
      74: dup
      75: iconst_3
      76: getstatic     #52                 // Field PRIVATE:Lorg/modelmapper/config/Configuration$AccessLevel;
      79: aastore
      80: putstatic     #20                 // Field $VALUES:[Lorg/modelmapper/config/Configuration$AccessLevel;
      83: return
}
