Compiled from "Policy.java"
public class com.amazonaws.auth.policy.Policy {
  private static final java.lang.String DEFAULT_POLICY_VERSION;

  private java.lang.String id;

  private java.lang.String version;

  private java.util.List<com.amazonaws.auth.policy.Statement> statements;

  public com.amazonaws.auth.policy.Policy();
    Code:
       0: aload_0
       1: invokespecial #1                  // Method java/lang/Object."<init>":()V
       4: aload_0
       5: ldc           #3                  // String 2012-10-17
       7: putfield      #4                  // Field version:Ljava/lang/String;
      10: aload_0
      11: new           #5                  // class java/util/ArrayList
      14: dup
      15: invokespecial #6                  // Method java/util/ArrayList."<init>":()V
      18: putfield      #7                  // Field statements:Ljava/util/List;
      21: return

  public com.amazonaws.auth.policy.Policy(java.lang.String);
    Code:
       0: aload_0
       1: invokespecial #1                  // Method java/lang/Object."<init>":()V
       4: aload_0
       5: ldc           #3                  // String 2012-10-17
       7: putfield      #4                  // Field version:Ljava/lang/String;
      10: aload_0
      11: new           #5                  // class java/util/ArrayList
      14: dup
      15: invokespecial #6                  // Method java/util/ArrayList."<init>":()V
      18: putfield      #7                  // Field statements:Ljava/util/List;
      21: aload_0
      22: aload_1
      23: putfield      #8                  // Field id:Ljava/lang/String;
      26: return

  public com.amazonaws.auth.policy.Policy(java.lang.String, java.util.Collection<com.amazonaws.auth.policy.Statement>);
    Code:
       0: aload_0
       1: aload_1
       2: invokespecial #9                  // Method "<init>":(Ljava/lang/String;)V
       5: aload_0
       6: aload_2
       7: invokevirtual #10                 // Method setStatements:(Ljava/util/Collection;)V
      10: return

  public java.lang.String getId();
    Code:
       0: aload_0
       1: getfield      #8                  // Field id:Ljava/lang/String;
       4: areturn

  public void setId(java.lang.String);
    Code:
       0: aload_0
       1: aload_1
       2: putfield      #8                  // Field id:Ljava/lang/String;
       5: return

  public com.amazonaws.auth.policy.Policy withId(java.lang.String);
    Code:
       0: aload_0
       1: aload_1
       2: invokevirtual #11                 // Method setId:(Ljava/lang/String;)V
       5: aload_0
       6: areturn

  public java.lang.String getVersion();
    Code:
       0: aload_0
       1: getfield      #4                  // Field version:Ljava/lang/String;
       4: areturn

  public java.util.Collection<com.amazonaws.auth.policy.Statement> getStatements();
    Code:
       0: aload_0
       1: getfield      #7                  // Field statements:Ljava/util/List;
       4: areturn

  public void setStatements(java.util.Collection<com.amazonaws.auth.policy.Statement>);
    Code:
       0: aload_0
       1: new           #5                  // class java/util/ArrayList
       4: dup
       5: aload_1
       6: invokespecial #12                 // Method java/util/ArrayList."<init>":(Ljava/util/Collection;)V
       9: putfield      #7                  // Field statements:Ljava/util/List;
      12: aload_0
      13: invokespecial #13                 // Method assignUniqueStatementIds:()V
      16: return

  public com.amazonaws.auth.policy.Policy withStatements(com.amazonaws.auth.policy.Statement...);
    Code:
       0: aload_0
       1: aload_1
       2: invokestatic  #14                 // Method java/util/Arrays.asList:([Ljava/lang/Object;)Ljava/util/List;
       5: invokevirtual #10                 // Method setStatements:(Ljava/util/Collection;)V
       8: aload_0
       9: areturn

  public java.lang.String toJson();
    Code:
       0: new           #15                 // class com/amazonaws/auth/policy/internal/JsonPolicyWriter
       3: dup
       4: invokespecial #16                 // Method com/amazonaws/auth/policy/internal/JsonPolicyWriter."<init>":()V
       7: aload_0
       8: invokevirtual #17                 // Method com/amazonaws/auth/policy/internal/JsonPolicyWriter.writePolicyToString:(Lcom/amazonaws/auth/policy/Policy;)Ljava/lang/String;
      11: areturn

  public static com.amazonaws.auth.policy.Policy fromJson(java.lang.String);
    Code:
       0: new           #18                 // class com/amazonaws/auth/policy/internal/JsonPolicyReader
       3: dup
       4: invokespecial #19                 // Method com/amazonaws/auth/policy/internal/JsonPolicyReader."<init>":()V
       7: aload_0
       8: invokevirtual #20                 // Method com/amazonaws/auth/policy/internal/JsonPolicyReader.createPolicyFromJsonString:(Ljava/lang/String;)Lcom/amazonaws/auth/policy/Policy;
      11: areturn

  private void assignUniqueStatementIds();
    Code:
       0: new           #21                 // class java/util/HashSet
       3: dup
       4: invokespecial #22                 // Method java/util/HashSet."<init>":()V
       7: astore_1
       8: aload_0
       9: getfield      #7                  // Field statements:Ljava/util/List;
      12: invokeinterface #23,  1           // InterfaceMethod java/util/List.iterator:()Ljava/util/Iterator;
      17: astore_2
      18: aload_2
      19: invokeinterface #24,  1           // InterfaceMethod java/util/Iterator.hasNext:()Z
      24: ifeq          58
      27: aload_2
      28: invokeinterface #25,  1           // InterfaceMethod java/util/Iterator.next:()Ljava/lang/Object;
      33: checkcast     #26                 // class com/amazonaws/auth/policy/Statement
      36: astore_3
      37: aload_3
      38: invokevirtual #27                 // Method com/amazonaws/auth/policy/Statement.getId:()Ljava/lang/String;
      41: ifnull        55
      44: aload_1
      45: aload_3
      46: invokevirtual #27                 // Method com/amazonaws/auth/policy/Statement.getId:()Ljava/lang/String;
      49: invokeinterface #28,  2           // InterfaceMethod java/util/Set.add:(Ljava/lang/Object;)Z
      54: pop
      55: goto          18
      58: iconst_0
      59: istore_2
      60: aload_0
      61: getfield      #7                  // Field statements:Ljava/util/List;
      64: invokeinterface #23,  1           // InterfaceMethod java/util/List.iterator:()Ljava/util/Iterator;
      69: astore_3
      70: aload_3
      71: invokeinterface #24,  1           // InterfaceMethod java/util/Iterator.hasNext:()Z
      76: ifeq          132
      79: aload_3
      80: invokeinterface #25,  1           // InterfaceMethod java/util/Iterator.next:()Ljava/lang/Object;
      85: checkcast     #26                 // class com/amazonaws/auth/policy/Statement
      88: astore        4
      90: aload         4
      92: invokevirtual #27                 // Method com/amazonaws/auth/policy/Statement.getId:()Ljava/lang/String;
      95: ifnull        101
      98: goto          70
     101: aload_1
     102: iinc          2, 1
     105: iload_2
     106: invokestatic  #29                 // Method java/lang/Integer.toString:(I)Ljava/lang/String;
     109: invokeinterface #30,  2           // InterfaceMethod java/util/Set.contains:(Ljava/lang/Object;)Z
     114: ifeq          120
     117: goto          101
     120: aload         4
     122: iload_2
     123: invokestatic  #29                 // Method java/lang/Integer.toString:(I)Ljava/lang/String;
     126: invokevirtual #31                 // Method com/amazonaws/auth/policy/Statement.setId:(Ljava/lang/String;)V
     129: goto          70
     132: return
}
