Compiled from "EnumType.java"
public class org.hibernate.type.EnumType<T extends java.lang.Enum> implements org.hibernate.usertype.EnhancedUserType, org.hibernate.usertype.DynamicParameterizedType, org.hibernate.usertype.LoggableUserType, org.hibernate.type.spi.TypeConfigurationAware, java.io.Serializable {
  private static final org.jboss.logging.Logger LOG;

  public static final java.lang.String ENUM;

  public static final java.lang.String NAMED;

  public static final java.lang.String TYPE;

  private java.lang.Class enumClass;

  private org.hibernate.metamodel.model.convert.spi.EnumValueConverter enumValueConverter;

  private org.hibernate.type.spi.TypeConfiguration typeConfiguration;

  public org.hibernate.type.EnumType();
    Code:
       0: aload_0
       1: invokespecial #1                  // Method java/lang/Object."<init>":()V
       4: return

  public void setParameterValues(java.util.Properties);
    Code:
       0: aload_1
       1: ldc           #3                  // String org.hibernate.type.ParameterType
       3: invokevirtual #4                  // Method java/util/Properties.get:(Ljava/lang/Object;)Ljava/lang/Object;
       6: checkcast     #5                  // class org/hibernate/usertype/DynamicParameterizedType$ParameterType
       9: astore_2
      10: aload_2
      11: ifnull        161
      14: aload_0
      15: aload_2
      16: invokeinterface #6,  1            // InterfaceMethod org/hibernate/usertype/DynamicParameterizedType$ParameterType.getReturnedClass:()Ljava/lang/Class;
      21: ldc           #7                  // class java/lang/Enum
      23: invokevirtual #8                  // Method java/lang/Class.asSubclass:(Ljava/lang/Class;)Ljava/lang/Class;
      26: putfield      #9                  // Field enumClass:Ljava/lang/Class;
      29: aload_0
      30: aload_2
      31: invokespecial #10                 // Method getEnumType:(Lorg/hibernate/usertype/DynamicParameterizedType$ParameterType;)Ljavax/persistence/EnumType;
      34: astore        4
      36: aload         4
      38: ifnonnull     46
      41: iconst_1
      42: istore_3
      43: goto          106
      46: getstatic     #11                 // Field javax/persistence/EnumType.ORDINAL:Ljavax/persistence/EnumType;
      49: aload         4
      51: invokevirtual #12                 // Method javax/persistence/EnumType.equals:(Ljava/lang/Object;)Z
      54: ifeq          62
      57: iconst_1
      58: istore_3
      59: goto          106
      62: getstatic     #13                 // Field javax/persistence/EnumType.STRING:Ljavax/persistence/EnumType;
      65: aload         4
      67: invokevirtual #12                 // Method javax/persistence/EnumType.equals:(Ljava/lang/Object;)Z
      70: ifeq          78
      73: iconst_0
      74: istore_3
      75: goto          106
      78: new           #14                 // class org/hibernate/AssertionFailure
      81: dup
      82: new           #15                 // class java/lang/StringBuilder
      85: dup
      86: invokespecial #16                 // Method java/lang/StringBuilder."<init>":()V
      89: ldc           #17                 // String Unknown EnumType:
      91: invokevirtual #18                 // Method java/lang/StringBuilder.append:(Ljava/lang/String;)Ljava/lang/StringBuilder;
      94: aload         4
      96: invokevirtual #19                 // Method java/lang/StringBuilder.append:(Ljava/lang/Object;)Ljava/lang/StringBuilder;
      99: invokevirtual #20                 // Method java/lang/StringBuilder.toString:()Ljava/lang/String;
     102: invokespecial #21                 // Method org/hibernate/AssertionFailure."<init>":(Ljava/lang/String;)V
     105: athrow
     106: aload_0
     107: getfield      #22                 // Field typeConfiguration:Lorg/hibernate/type/spi/TypeConfiguration;
     110: invokevirtual #23                 // Method org/hibernate/type/spi/TypeConfiguration.getJavaTypeDescriptorRegistry:()Lorg/hibernate/type/descriptor/java/spi/JavaTypeDescriptorRegistry;
     113: aload_0
     114: getfield      #9                  // Field enumClass:Ljava/lang/Class;
     117: invokevirtual #24                 // Method org/hibernate/type/descriptor/java/spi/JavaTypeDescriptorRegistry.getDescriptor:(Ljava/lang/Class;)Lorg/hibernate/type/descriptor/java/JavaTypeDescriptor;
     120: checkcast     #25                 // class org/hibernate/type/descriptor/java/EnumJavaTypeDescriptor
     123: astore        5
     125: iload_3
     126: ifeq          145
     129: aload_0
     130: new           #26                 // class org/hibernate/metamodel/model/convert/internal/OrdinalEnumValueConverter
     133: dup
     134: aload         5
     136: invokespecial #27                 // Method org/hibernate/metamodel/model/convert/internal/OrdinalEnumValueConverter."<init>":(Lorg/hibernate/type/descriptor/java/EnumJavaTypeDescriptor;)V
     139: putfield      #28                 // Field enumValueConverter:Lorg/hibernate/metamodel/model/convert/spi/EnumValueConverter;
     142: goto          158
     145: aload_0
     146: new           #29                 // class org/hibernate/metamodel/model/convert/internal/NamedEnumValueConverter
     149: dup
     150: aload         5
     152: invokespecial #30                 // Method org/hibernate/metamodel/model/convert/internal/NamedEnumValueConverter."<init>":(Lorg/hibernate/type/descriptor/java/EnumJavaTypeDescriptor;)V
     155: putfield      #28                 // Field enumValueConverter:Lorg/hibernate/metamodel/model/convert/spi/EnumValueConverter;
     158: goto          231
     161: aload_1
     162: ldc           #32                 // String enumClass
     164: invokevirtual #4                  // Method java/util/Properties.get:(Ljava/lang/Object;)Ljava/lang/Object;
     167: checkcast     #33                 // class java/lang/String
     170: astore_3
     171: aload_0
     172: aload_3
     173: aload_0
     174: invokevirtual #34                 // Method java/lang/Object.getClass:()Ljava/lang/Class;
     177: invokestatic  #35                 // Method org/hibernate/internal/util/ReflectHelper.classForName:(Ljava/lang/String;Ljava/lang/Class;)Ljava/lang/Class;
     180: ldc           #7                  // class java/lang/Enum
     182: invokevirtual #8                  // Method java/lang/Class.asSubclass:(Ljava/lang/Class;)Ljava/lang/Class;
     185: putfield      #9                  // Field enumClass:Ljava/lang/Class;
     188: goto          222
     191: astore        4
     193: new           #37                 // class org/hibernate/HibernateException
     196: dup
     197: new           #15                 // class java/lang/StringBuilder
     200: dup
     201: invokespecial #16                 // Method java/lang/StringBuilder."<init>":()V
     204: ldc           #38                 // String Enum class not found:
     206: invokevirtual #18                 // Method java/lang/StringBuilder.append:(Ljava/lang/String;)Ljava/lang/StringBuilder;
     209: aload_3
     210: invokevirtual #18                 // Method java/lang/StringBuilder.append:(Ljava/lang/String;)Ljava/lang/StringBuilder;
     213: invokevirtual #20                 // Method java/lang/StringBuilder.toString:()Ljava/lang/String;
     216: aload         4
     218: invokespecial #39                 // Method org/hibernate/HibernateException."<init>":(Ljava/lang/String;Ljava/lang/Throwable;)V
     221: athrow
     222: aload_0
     223: aload_0
     224: aload_1
     225: invokespecial #40                 // Method interpretParameters:(Ljava/util/Properties;)Lorg/hibernate/metamodel/model/convert/spi/EnumValueConverter;
     228: putfield      #28                 // Field enumValueConverter:Lorg/hibernate/metamodel/model/convert/spi/EnumValueConverter;
     231: getstatic     #41                 // Field LOG:Lorg/jboss/logging/Logger;
     234: ldc           #42                 // String Using %s-based conversion for Enum %s
     236: aload_0
     237: invokevirtual #43                 // Method isOrdinal:()Z
     240: ifeq          248
     243: ldc           #44                 // String ORDINAL
     245: goto          250
     248: ldc           #45                 // String NAMED
     250: aload_0
     251: getfield      #9                  // Field enumClass:Ljava/lang/Class;
     254: invokevirtual #46                 // Method java/lang/Class.getName:()Ljava/lang/String;
     257: invokevirtual #47                 // Method org/jboss/logging/Logger.debugf:(Ljava/lang/String;Ljava/lang/Object;Ljava/lang/Object;)V
     260: return
    Exception table:
       from    to  target type
         171   188   191   Class java/lang/ClassNotFoundException

  private javax.persistence.EnumType getEnumType(org.hibernate.usertype.DynamicParameterizedType$ParameterType);
    Code:
       0: aconst_null
       1: astore_2
       2: aload_1
       3: invokeinterface #48,  1           // InterfaceMethod org/hibernate/usertype/DynamicParameterizedType$ParameterType.isPrimaryKey:()Z
       8: ifeq          41
      11: aload_0
      12: aload_1
      13: invokeinterface #49,  1           // InterfaceMethod org/hibernate/usertype/DynamicParameterizedType$ParameterType.getAnnotationsMethod:()[Ljava/lang/annotation/Annotation;
      18: ldc           #50                 // class javax/persistence/MapKeyEnumerated
      20: invokespecial #51                 // Method getAnnotation:([Ljava/lang/annotation/Annotation;Ljava/lang/Class;)Ljava/lang/annotation/Annotation;
      23: checkcast     #50                 // class javax/persistence/MapKeyEnumerated
      26: astore_3
      27: aload_3
      28: ifnull        38
      31: aload_3
      32: invokeinterface #52,  1           // InterfaceMethod javax/persistence/MapKeyEnumerated.value:()Ljavax/persistence/EnumType;
      37: astore_2
      38: goto          68
      41: aload_0
      42: aload_1
      43: invokeinterface #49,  1           // InterfaceMethod org/hibernate/usertype/DynamicParameterizedType$ParameterType.getAnnotationsMethod:()[Ljava/lang/annotation/Annotation;
      48: ldc           #53                 // class javax/persistence/Enumerated
      50: invokespecial #51                 // Method getAnnotation:([Ljava/lang/annotation/Annotation;Ljava/lang/Class;)Ljava/lang/annotation/Annotation;
      53: checkcast     #53                 // class javax/persistence/Enumerated
      56: astore_3
      57: aload_3
      58: ifnull        68
      61: aload_3
      62: invokeinterface #54,  1           // InterfaceMethod javax/persistence/Enumerated.value:()Ljavax/persistence/EnumType;
      67: astore_2
      68: aload_2
      69: areturn

  private <A extends java.lang.annotation.Annotation> A getAnnotation(java.lang.annotation.Annotation[], java.lang.Class<A>);
    Code:
       0: aload_1
       1: astore_3
       2: aload_3
       3: arraylength
       4: istore        4
       6: iconst_0
       7: istore        5
       9: iload         5
      11: iload         4
      13: if_icmpge     40
      16: aload_3
      17: iload         5
      19: aaload
      20: astore        6
      22: aload_2
      23: aload         6
      25: invokevirtual #55                 // Method java/lang/Class.isInstance:(Ljava/lang/Object;)Z
      28: ifeq          34
      31: aload         6
      33: areturn
      34: iinc          5, 1
      37: goto          9
      40: aconst_null
      41: areturn

  private org.hibernate.metamodel.model.convert.spi.EnumValueConverter interpretParameters(java.util.Properties);
    Code:
       0: aload_0
       1: getfield      #22                 // Field typeConfiguration:Lorg/hibernate/type/spi/TypeConfiguration;
       4: invokevirtual #23                 // Method org/hibernate/type/spi/TypeConfiguration.getJavaTypeDescriptorRegistry:()Lorg/hibernate/type/descriptor/java/spi/JavaTypeDescriptorRegistry;
       7: aload_0
       8: getfield      #9                  // Field enumClass:Ljava/lang/Class;
      11: invokevirtual #24                 // Method org/hibernate/type/descriptor/java/spi/JavaTypeDescriptorRegistry.getDescriptor:(Ljava/lang/Class;)Lorg/hibernate/type/descriptor/java/JavaTypeDescriptor;
      14: checkcast     #25                 // class org/hibernate/type/descriptor/java/EnumJavaTypeDescriptor
      17: astore_2
      18: aload_1
      19: ldc           #56                 // String useNamed
      21: invokevirtual #57                 // Method java/util/Properties.containsKey:(Ljava/lang/Object;)Z
      24: ifeq          56
      27: ldc           #56                 // String useNamed
      29: aload_1
      30: invokestatic  #58                 // Method org/hibernate/internal/util/config/ConfigurationHelper.getBoolean:(Ljava/lang/String;Ljava/util/Map;)Z
      33: istore_3
      34: iload_3
      35: ifeq          47
      38: new           #29                 // class org/hibernate/metamodel/model/convert/internal/NamedEnumValueConverter
      41: dup
      42: aload_2
      43: invokespecial #30                 // Method org/hibernate/metamodel/model/convert/internal/NamedEnumValueConverter."<init>":(Lorg/hibernate/type/descriptor/java/EnumJavaTypeDescriptor;)V
      46: areturn
      47: new           #26                 // class org/hibernate/metamodel/model/convert/internal/OrdinalEnumValueConverter
      50: dup
      51: aload_2
      52: invokespecial #27                 // Method org/hibernate/metamodel/model/convert/internal/OrdinalEnumValueConverter."<init>":(Lorg/hibernate/type/descriptor/java/EnumJavaTypeDescriptor;)V
      55: areturn
      56: aload_1
      57: ldc           #59                 // String type
      59: invokevirtual #57                 // Method java/util/Properties.containsKey:(Ljava/lang/Object;)Z
      62: ifeq          142
      65: aload_1
      66: ldc           #59                 // String type
      68: invokevirtual #4                  // Method java/util/Properties.get:(Ljava/lang/Object;)Ljava/lang/Object;
      71: checkcast     #33                 // class java/lang/String
      74: invokestatic  #60                 // Method java/lang/Integer.decode:(Ljava/lang/String;)Ljava/lang/Integer;
      77: invokevirtual #61                 // Method java/lang/Integer.intValue:()I
      80: istore_3
      81: aload_0
      82: iload_3
      83: invokespecial #62                 // Method isNumericType:(I)Z
      86: ifeq          98
      89: new           #26                 // class org/hibernate/metamodel/model/convert/internal/OrdinalEnumValueConverter
      92: dup
      93: aload_2
      94: invokespecial #27                 // Method org/hibernate/metamodel/model/convert/internal/OrdinalEnumValueConverter."<init>":(Lorg/hibernate/type/descriptor/java/EnumJavaTypeDescriptor;)V
      97: areturn
      98: aload_0
      99: iload_3
     100: invokespecial #63                 // Method isCharacterType:(I)Z
     103: ifeq          115
     106: new           #29                 // class org/hibernate/metamodel/model/convert/internal/NamedEnumValueConverter
     109: dup
     110: aload_2
     111: invokespecial #30                 // Method org/hibernate/metamodel/model/convert/internal/NamedEnumValueConverter."<init>":(Lorg/hibernate/type/descriptor/java/EnumJavaTypeDescriptor;)V
     114: areturn
     115: new           #37                 // class org/hibernate/HibernateException
     118: dup
     119: getstatic     #64                 // Field java/util/Locale.ENGLISH:Ljava/util/Locale;
     122: ldc           #65                 // String Passed JDBC type code [%s] not recognized as numeric nor character
     124: iconst_1
     125: anewarray     #66                 // class java/lang/Object
     128: dup
     129: iconst_0
     130: iload_3
     131: invokestatic  #67                 // Method java/lang/Integer.valueOf:(I)Ljava/lang/Integer;
     134: aastore
     135: invokestatic  #68                 // Method java/lang/String.format:(Ljava/util/Locale;Ljava/lang/String;[Ljava/lang/Object;)Ljava/lang/String;
     138: invokespecial #69                 // Method org/hibernate/HibernateException."<init>":(Ljava/lang/String;)V
     141: athrow
     142: new           #26                 // class org/hibernate/metamodel/model/convert/internal/OrdinalEnumValueConverter
     145: dup
     146: aload_2
     147: invokespecial #27                 // Method org/hibernate/metamodel/model/convert/internal/OrdinalEnumValueConverter."<init>":(Lorg/hibernate/type/descriptor/java/EnumJavaTypeDescriptor;)V
     150: areturn

  private boolean isCharacterType(int);
    Code:
       0: iload_1
       1: lookupswitch  { // 3
                    -1: 36
                     1: 36
                    12: 36
               default: 38
          }
      36: iconst_1
      37: ireturn
      38: iconst_0
      39: ireturn

  private boolean isNumericType(int);
    Code:
       0: iload_1
       1: tableswitch   { // -6 to 8
                    -6: 76
                    -5: 76
                    -4: 78
                    -3: 78
                    -2: 78
                    -1: 78
                     0: 78
                     1: 78
                     2: 76
                     3: 76
                     4: 76
                     5: 76
                     6: 76
                     7: 78
                     8: 76
               default: 78
          }
      76: iconst_1
      77: ireturn
      78: iconst_0
      79: ireturn

  public int[] sqlTypes();
    Code:
       0: aload_0
       1: invokespecial #70                 // Method verifyConfigured:()V
       4: iconst_1
       5: newarray       int
       7: dup
       8: iconst_0
       9: aload_0
      10: getfield      #28                 // Field enumValueConverter:Lorg/hibernate/metamodel/model/convert/spi/EnumValueConverter;
      13: invokeinterface #71,  1           // InterfaceMethod org/hibernate/metamodel/model/convert/spi/EnumValueConverter.getJdbcTypeCode:()I
      18: iastore
      19: areturn

  public java.lang.Class<? extends java.lang.Enum> returnedClass();
    Code:
       0: aload_0
       1: getfield      #9                  // Field enumClass:Ljava/lang/Class;
       4: areturn

  public boolean equals(java.lang.Object, java.lang.Object) throws org.hibernate.HibernateException;
    Code:
       0: aload_1
       1: aload_2
       2: if_acmpne     9
       5: iconst_1
       6: goto          10
       9: iconst_0
      10: ireturn

  public int hashCode(java.lang.Object) throws org.hibernate.HibernateException;
    Code:
       0: aload_1
       1: ifnonnull     8
       4: iconst_0
       5: goto          12
       8: aload_1
       9: invokevirtual #72                 // Method java/lang/Object.hashCode:()I
      12: ireturn

  public java.lang.Object nullSafeGet(java.sql.ResultSet, java.lang.String[], org.hibernate.engine.spi.SharedSessionContractImplementor, java.lang.Object) throws java.sql.SQLException;
    Code:
       0: aload_0
       1: invokespecial #70                 // Method verifyConfigured:()V
       4: aload_0
       5: getfield      #28                 // Field enumValueConverter:Lorg/hibernate/metamodel/model/convert/spi/EnumValueConverter;
       8: aload_1
       9: aload_2
      10: iconst_0
      11: aaload
      12: invokeinterface #73,  3           // InterfaceMethod org/hibernate/metamodel/model/convert/spi/EnumValueConverter.readValue:(Ljava/sql/ResultSet;Ljava/lang/String;)Ljava/lang/Enum;
      17: areturn

  private void verifyConfigured();
    Code:
       0: aload_0
       1: getfield      #28                 // Field enumValueConverter:Lorg/hibernate/metamodel/model/convert/spi/EnumValueConverter;
       4: ifnonnull     45
       7: new           #14                 // class org/hibernate/AssertionFailure
      10: dup
      11: new           #15                 // class java/lang/StringBuilder
      14: dup
      15: invokespecial #16                 // Method java/lang/StringBuilder."<init>":()V
      18: ldc           #74                 // String EnumType (
      20: invokevirtual #18                 // Method java/lang/StringBuilder.append:(Ljava/lang/String;)Ljava/lang/StringBuilder;
      23: aload_0
      24: getfield      #9                  // Field enumClass:Ljava/lang/Class;
      27: invokevirtual #46                 // Method java/lang/Class.getName:()Ljava/lang/String;
      30: invokevirtual #18                 // Method java/lang/StringBuilder.append:(Ljava/lang/String;)Ljava/lang/StringBuilder;
      33: ldc           #75                 // String ) not properly, fully configured
      35: invokevirtual #18                 // Method java/lang/StringBuilder.append:(Ljava/lang/String;)Ljava/lang/StringBuilder;
      38: invokevirtual #20                 // Method java/lang/StringBuilder.toString:()Ljava/lang/String;
      41: invokespecial #21                 // Method org/hibernate/AssertionFailure."<init>":(Ljava/lang/String;)V
      44: athrow
      45: return

  public void nullSafeSet(java.sql.PreparedStatement, java.lang.Object, int, org.hibernate.engine.spi.SharedSessionContractImplementor) throws org.hibernate.HibernateException, java.sql.SQLException;
    Code:
       0: aload_0
       1: invokespecial #70                 // Method verifyConfigured:()V
       4: aload_0
       5: getfield      #28                 // Field enumValueConverter:Lorg/hibernate/metamodel/model/convert/spi/EnumValueConverter;
       8: aload_1
       9: aload_2
      10: checkcast     #7                  // class java/lang/Enum
      13: iload_3
      14: invokeinterface #76,  4           // InterfaceMethod org/hibernate/metamodel/model/convert/spi/EnumValueConverter.writeValue:(Ljava/sql/PreparedStatement;Ljava/lang/Enum;I)V
      19: return

  public java.lang.Object deepCopy(java.lang.Object) throws org.hibernate.HibernateException;
    Code:
       0: aload_1
       1: areturn

  public boolean isMutable();
    Code:
       0: iconst_0
       1: ireturn

  public java.io.Serializable disassemble(java.lang.Object) throws org.hibernate.HibernateException;
    Code:
       0: aload_1
       1: checkcast     #77                 // class java/io/Serializable
       4: areturn

  public java.lang.Object assemble(java.io.Serializable, java.lang.Object) throws org.hibernate.HibernateException;
    Code:
       0: aload_1
       1: areturn

  public java.lang.Object replace(java.lang.Object, java.lang.Object, java.lang.Object) throws org.hibernate.HibernateException;
    Code:
       0: aload_1
       1: areturn

  public org.hibernate.type.spi.TypeConfiguration getTypeConfiguration();
    Code:
       0: aload_0
       1: getfield      #22                 // Field typeConfiguration:Lorg/hibernate/type/spi/TypeConfiguration;
       4: areturn

  public void setTypeConfiguration(org.hibernate.type.spi.TypeConfiguration);
    Code:
       0: aload_0
       1: aload_1
       2: putfield      #22                 // Field typeConfiguration:Lorg/hibernate/type/spi/TypeConfiguration;
       5: return

  public java.lang.String objectToSQLString(java.lang.Object);
    Code:
       0: aload_0
       1: invokespecial #70                 // Method verifyConfigured:()V
       4: aload_0
       5: getfield      #28                 // Field enumValueConverter:Lorg/hibernate/metamodel/model/convert/spi/EnumValueConverter;
       8: aload_1
       9: invokeinterface #78,  2           // InterfaceMethod org/hibernate/metamodel/model/convert/spi/EnumValueConverter.toSqlLiteral:(Ljava/lang/Object;)Ljava/lang/String;
      14: areturn

  public java.lang.String toXMLString(java.lang.Object);
    Code:
       0: aload_0
       1: invokespecial #70                 // Method verifyConfigured:()V
       4: aload_0
       5: getfield      #28                 // Field enumValueConverter:Lorg/hibernate/metamodel/model/convert/spi/EnumValueConverter;
       8: invokeinterface #79,  1           // InterfaceMethod org/hibernate/metamodel/model/convert/spi/EnumValueConverter.getJavaDescriptor:()Lorg/hibernate/type/descriptor/java/EnumJavaTypeDescriptor;
      13: aload_1
      14: checkcast     #7                  // class java/lang/Enum
      17: ldc           #33                 // class java/lang/String
      19: aconst_null
      20: invokevirtual #80                 // Method org/hibernate/type/descriptor/java/EnumJavaTypeDescriptor.unwrap:(Ljava/lang/Enum;Ljava/lang/Class;Lorg/hibernate/type/descriptor/WrapperOptions;)Ljava/lang/Object;
      23: checkcast     #33                 // class java/lang/String
      26: areturn

  public java.lang.Object fromXMLString(java.lang.String);
    Code:
       0: aload_0
       1: invokespecial #70                 // Method verifyConfigured:()V
       4: aload_0
       5: getfield      #28                 // Field enumValueConverter:Lorg/hibernate/metamodel/model/convert/spi/EnumValueConverter;
       8: invokeinterface #79,  1           // InterfaceMethod org/hibernate/metamodel/model/convert/spi/EnumValueConverter.getJavaDescriptor:()Lorg/hibernate/type/descriptor/java/EnumJavaTypeDescriptor;
      13: aload_1
      14: aconst_null
      15: invokevirtual #81                 // Method org/hibernate/type/descriptor/java/EnumJavaTypeDescriptor.wrap:(Ljava/lang/Object;Lorg/hibernate/type/descriptor/WrapperOptions;)Ljava/lang/Enum;
      18: areturn

  public java.lang.String toLoggableString(java.lang.Object, org.hibernate.engine.spi.SessionFactoryImplementor);
    Code:
       0: aload_0
       1: invokespecial #70                 // Method verifyConfigured:()V
       4: aload_0
       5: getfield      #28                 // Field enumValueConverter:Lorg/hibernate/metamodel/model/convert/spi/EnumValueConverter;
       8: invokeinterface #79,  1           // InterfaceMethod org/hibernate/metamodel/model/convert/spi/EnumValueConverter.getJavaDescriptor:()Lorg/hibernate/type/descriptor/java/EnumJavaTypeDescriptor;
      13: aload_1
      14: checkcast     #7                  // class java/lang/Enum
      17: invokevirtual #82                 // Method org/hibernate/type/descriptor/java/EnumJavaTypeDescriptor.toString:(Ljava/lang/Enum;)Ljava/lang/String;
      20: areturn

  public boolean isOrdinal();
    Code:
       0: aload_0
       1: invokespecial #70                 // Method verifyConfigured:()V
       4: aload_0
       5: getfield      #28                 // Field enumValueConverter:Lorg/hibernate/metamodel/model/convert/spi/EnumValueConverter;
       8: instanceof    #26                 // class org/hibernate/metamodel/model/convert/internal/OrdinalEnumValueConverter
      11: ireturn

  static {};
    Code:
       0: ldc           #31                 // class org/hibernate/type/EnumType
       2: invokestatic  #83                 // Method org/hibernate/internal/CoreLogging.logger:(Ljava/lang/Class;)Lorg/jboss/logging/Logger;
       5: putstatic     #41                 // Field LOG:Lorg/jboss/logging/Logger;
       8: return
}
