Compiled from "TypeHelper.java"
public class org.hibernate.type.TypeHelper {
  private org.hibernate.type.TypeHelper();
    Code:
       0: aload_0
       1: invokespecial #1                  // Method java/lang/Object."<init>":()V
       4: return

  public static void deepCopy(java.lang.Object[], org.hibernate.type.Type[], boolean[], java.lang.Object[], org.hibernate.engine.spi.SharedSessionContractImplementor);
    Code:
       0: iconst_0
       1: istore        5
       3: iload         5
       5: aload_1
       6: arraylength
       7: if_icmpge     78
      10: aload_2
      11: iload         5
      13: baload
      14: ifeq          72
      17: aload_0
      18: iload         5
      20: aaload
      21: getstatic     #2                  // Field org/hibernate/bytecode/enhance/spi/LazyPropertyInitializer.UNFETCHED_PROPERTY:Ljava/io/Serializable;
      24: if_acmpeq     37
      27: aload_0
      28: iload         5
      30: aaload
      31: getstatic     #3                  // Field org/hibernate/property/access/internal/PropertyAccessStrategyBackRefImpl.UNKNOWN:Ljava/io/Serializable;
      34: if_acmpne     48
      37: aload_3
      38: iload         5
      40: aload_0
      41: iload         5
      43: aaload
      44: aastore
      45: goto          72
      48: aload_3
      49: iload         5
      51: aload_1
      52: iload         5
      54: aaload
      55: aload_0
      56: iload         5
      58: aaload
      59: aload         4
      61: invokeinterface #4,  1            // InterfaceMethod org/hibernate/engine/spi/SharedSessionContractImplementor.getFactory:()Lorg/hibernate/engine/spi/SessionFactoryImplementor;
      66: invokeinterface #5,  3            // InterfaceMethod org/hibernate/type/Type.deepCopy:(Ljava/lang/Object;Lorg/hibernate/engine/spi/SessionFactoryImplementor;)Ljava/lang/Object;
      71: aastore
      72: iinc          5, 1
      75: goto          3
      78: return

  public static void beforeAssemble(java.io.Serializable[], org.hibernate.type.Type[], org.hibernate.engine.spi.SharedSessionContractImplementor);
    Code:
       0: iconst_0
       1: istore_3
       2: iload_3
       3: aload_1
       4: arraylength
       5: if_icmpge     44
       8: aload_0
       9: iload_3
      10: aaload
      11: getstatic     #2                  // Field org/hibernate/bytecode/enhance/spi/LazyPropertyInitializer.UNFETCHED_PROPERTY:Ljava/io/Serializable;
      14: if_acmpeq     38
      17: aload_0
      18: iload_3
      19: aaload
      20: getstatic     #3                  // Field org/hibernate/property/access/internal/PropertyAccessStrategyBackRefImpl.UNKNOWN:Ljava/io/Serializable;
      23: if_acmpeq     38
      26: aload_1
      27: iload_3
      28: aaload
      29: aload_0
      30: iload_3
      31: aaload
      32: aload_2
      33: invokeinterface #6,  3            // InterfaceMethod org/hibernate/type/Type.beforeAssemble:(Ljava/io/Serializable;Lorg/hibernate/engine/spi/SharedSessionContractImplementor;)V
      38: iinc          3, 1
      41: goto          2
      44: return

  public static java.lang.Object[] assemble(java.io.Serializable[], org.hibernate.type.Type[], org.hibernate.engine.spi.SharedSessionContractImplementor, java.lang.Object);
    Code:
       0: aload_0
       1: arraylength
       2: anewarray     #7                  // class java/lang/Object
       5: astore        4
       7: iconst_0
       8: istore        5
      10: iload         5
      12: aload_1
      13: arraylength
      14: if_icmpge     75
      17: aload_0
      18: iload         5
      20: aaload
      21: getstatic     #2                  // Field org/hibernate/bytecode/enhance/spi/LazyPropertyInitializer.UNFETCHED_PROPERTY:Ljava/io/Serializable;
      24: if_acmpeq     37
      27: aload_0
      28: iload         5
      30: aaload
      31: getstatic     #3                  // Field org/hibernate/property/access/internal/PropertyAccessStrategyBackRefImpl.UNKNOWN:Ljava/io/Serializable;
      34: if_acmpne     49
      37: aload         4
      39: iload         5
      41: aload_0
      42: iload         5
      44: aaload
      45: aastore
      46: goto          69
      49: aload         4
      51: iload         5
      53: aload_1
      54: iload         5
      56: aaload
      57: aload_0
      58: iload         5
      60: aaload
      61: aload_2
      62: aload_3
      63: invokeinterface #8,  4            // InterfaceMethod org/hibernate/type/Type.assemble:(Ljava/io/Serializable;Lorg/hibernate/engine/spi/SharedSessionContractImplementor;Ljava/lang/Object;)Ljava/lang/Object;
      68: aastore
      69: iinc          5, 1
      72: goto          10
      75: aload         4
      77: areturn

  public static java.io.Serializable[] disassemble(java.lang.Object[], org.hibernate.type.Type[], boolean[], org.hibernate.engine.spi.SharedSessionContractImplementor, java.lang.Object);
    Code:
       0: aload_0
       1: arraylength
       2: anewarray     #9                  // class java/io/Serializable
       5: astore        5
       7: iconst_0
       8: istore        6
      10: iload         6
      12: aload_0
      13: arraylength
      14: if_icmpge     101
      17: aload_2
      18: ifnull        39
      21: aload_2
      22: iload         6
      24: baload
      25: ifeq          39
      28: aload         5
      30: iload         6
      32: getstatic     #2                  // Field org/hibernate/bytecode/enhance/spi/LazyPropertyInitializer.UNFETCHED_PROPERTY:Ljava/io/Serializable;
      35: aastore
      36: goto          95
      39: aload_0
      40: iload         6
      42: aaload
      43: getstatic     #2                  // Field org/hibernate/bytecode/enhance/spi/LazyPropertyInitializer.UNFETCHED_PROPERTY:Ljava/io/Serializable;
      46: if_acmpeq     59
      49: aload_0
      50: iload         6
      52: aaload
      53: getstatic     #3                  // Field org/hibernate/property/access/internal/PropertyAccessStrategyBackRefImpl.UNKNOWN:Ljava/io/Serializable;
      56: if_acmpne     74
      59: aload         5
      61: iload         6
      63: aload_0
      64: iload         6
      66: aaload
      67: checkcast     #9                  // class java/io/Serializable
      70: aastore
      71: goto          95
      74: aload         5
      76: iload         6
      78: aload_1
      79: iload         6
      81: aaload
      82: aload_0
      83: iload         6
      85: aaload
      86: aload_3
      87: aload         4
      89: invokeinterface #10,  4           // InterfaceMethod org/hibernate/type/Type.disassemble:(Ljava/lang/Object;Lorg/hibernate/engine/spi/SharedSessionContractImplementor;Ljava/lang/Object;)Ljava/io/Serializable;
      94: aastore
      95: iinc          6, 1
      98: goto          10
     101: aload         5
     103: areturn

  public static java.lang.Object[] replace(java.lang.Object[], java.lang.Object[], org.hibernate.type.Type[], org.hibernate.engine.spi.SharedSessionContractImplementor, java.lang.Object, java.util.Map);
    Code:
       0: aload_0
       1: arraylength
       2: anewarray     #7                  // class java/lang/Object
       5: astore        6
       7: iconst_0
       8: istore        7
      10: iload         7
      12: aload_2
      13: arraylength
      14: if_icmpge     119
      17: aload_0
      18: iload         7
      20: aaload
      21: getstatic     #2                  // Field org/hibernate/bytecode/enhance/spi/LazyPropertyInitializer.UNFETCHED_PROPERTY:Ljava/io/Serializable;
      24: if_acmpeq     37
      27: aload_0
      28: iload         7
      30: aaload
      31: getstatic     #3                  // Field org/hibernate/property/access/internal/PropertyAccessStrategyBackRefImpl.UNKNOWN:Ljava/io/Serializable;
      34: if_acmpne     49
      37: aload         6
      39: iload         7
      41: aload_1
      42: iload         7
      44: aaload
      45: aastore
      46: goto          113
      49: aload_1
      50: iload         7
      52: aaload
      53: getstatic     #2                  // Field org/hibernate/bytecode/enhance/spi/LazyPropertyInitializer.UNFETCHED_PROPERTY:Ljava/io/Serializable;
      56: if_acmpne     86
      59: aload         6
      61: iload         7
      63: aload_2
      64: iload         7
      66: aaload
      67: aload_0
      68: iload         7
      70: aaload
      71: aconst_null
      72: aload_3
      73: aload         4
      75: aload         5
      77: invokeinterface #11,  6           // InterfaceMethod org/hibernate/type/Type.replace:(Ljava/lang/Object;Ljava/lang/Object;Lorg/hibernate/engine/spi/SharedSessionContractImplementor;Ljava/lang/Object;Ljava/util/Map;)Ljava/lang/Object;
      82: aastore
      83: goto          113
      86: aload         6
      88: iload         7
      90: aload_2
      91: iload         7
      93: aaload
      94: aload_0
      95: iload         7
      97: aaload
      98: aload_1
      99: iload         7
     101: aaload
     102: aload_3
     103: aload         4
     105: aload         5
     107: invokeinterface #11,  6           // InterfaceMethod org/hibernate/type/Type.replace:(Ljava/lang/Object;Ljava/lang/Object;Lorg/hibernate/engine/spi/SharedSessionContractImplementor;Ljava/lang/Object;Ljava/util/Map;)Ljava/lang/Object;
     112: aastore
     113: iinc          7, 1
     116: goto          10
     119: aload         6
     121: areturn

  public static java.lang.Object[] replace(java.lang.Object[], java.lang.Object[], org.hibernate.type.Type[], org.hibernate.engine.spi.SharedSessionContractImplementor, java.lang.Object, java.util.Map, org.hibernate.type.ForeignKeyDirection);
    Code:
       0: aload_0
       1: arraylength
       2: anewarray     #7                  // class java/lang/Object
       5: astore        7
       7: iconst_0
       8: istore        8
      10: iload         8
      12: aload_2
      13: arraylength
      14: if_icmpge     123
      17: aload_0
      18: iload         8
      20: aaload
      21: getstatic     #2                  // Field org/hibernate/bytecode/enhance/spi/LazyPropertyInitializer.UNFETCHED_PROPERTY:Ljava/io/Serializable;
      24: if_acmpeq     37
      27: aload_0
      28: iload         8
      30: aaload
      31: getstatic     #3                  // Field org/hibernate/property/access/internal/PropertyAccessStrategyBackRefImpl.UNKNOWN:Ljava/io/Serializable;
      34: if_acmpne     49
      37: aload         7
      39: iload         8
      41: aload_1
      42: iload         8
      44: aaload
      45: aastore
      46: goto          117
      49: aload_1
      50: iload         8
      52: aaload
      53: getstatic     #2                  // Field org/hibernate/bytecode/enhance/spi/LazyPropertyInitializer.UNFETCHED_PROPERTY:Ljava/io/Serializable;
      56: if_acmpne     88
      59: aload         7
      61: iload         8
      63: aload_2
      64: iload         8
      66: aaload
      67: aload_0
      68: iload         8
      70: aaload
      71: aconst_null
      72: aload_3
      73: aload         4
      75: aload         5
      77: aload         6
      79: invokeinterface #12,  7           // InterfaceMethod org/hibernate/type/Type.replace:(Ljava/lang/Object;Ljava/lang/Object;Lorg/hibernate/engine/spi/SharedSessionContractImplementor;Ljava/lang/Object;Ljava/util/Map;Lorg/hibernate/type/ForeignKeyDirection;)Ljava/lang/Object;
      84: aastore
      85: goto          117
      88: aload         7
      90: iload         8
      92: aload_2
      93: iload         8
      95: aaload
      96: aload_0
      97: iload         8
      99: aaload
     100: aload_1
     101: iload         8
     103: aaload
     104: aload_3
     105: aload         4
     107: aload         5
     109: aload         6
     111: invokeinterface #12,  7           // InterfaceMethod org/hibernate/type/Type.replace:(Ljava/lang/Object;Ljava/lang/Object;Lorg/hibernate/engine/spi/SharedSessionContractImplementor;Ljava/lang/Object;Ljava/util/Map;Lorg/hibernate/type/ForeignKeyDirection;)Ljava/lang/Object;
     116: aastore
     117: iinc          8, 1
     120: goto          10
     123: aload         7
     125: areturn

  public static java.lang.Object[] replaceAssociations(java.lang.Object[], java.lang.Object[], org.hibernate.type.Type[], org.hibernate.engine.spi.SharedSessionContractImplementor, java.lang.Object, java.util.Map, org.hibernate.type.ForeignKeyDirection);
    Code:
       0: aload_0
       1: arraylength
       2: anewarray     #7                  // class java/lang/Object
       5: astore        7
       7: iconst_0
       8: istore        8
      10: iload         8
      12: aload_2
      13: arraylength
      14: if_icmpge     226
      17: aload_0
      18: iload         8
      20: aaload
      21: getstatic     #2                  // Field org/hibernate/bytecode/enhance/spi/LazyPropertyInitializer.UNFETCHED_PROPERTY:Ljava/io/Serializable;
      24: if_acmpeq     37
      27: aload_0
      28: iload         8
      30: aaload
      31: getstatic     #3                  // Field org/hibernate/property/access/internal/PropertyAccessStrategyBackRefImpl.UNKNOWN:Ljava/io/Serializable;
      34: if_acmpne     49
      37: aload         7
      39: iload         8
      41: aload_1
      42: iload         8
      44: aaload
      45: aastore
      46: goto          220
      49: aload_2
      50: iload         8
      52: aaload
      53: invokeinterface #13,  1           // InterfaceMethod org/hibernate/type/Type.isComponentType:()Z
      58: ifeq          167
      61: aload_2
      62: iload         8
      64: aaload
      65: checkcast     #14                 // class org/hibernate/type/CompositeType
      68: astore        9
      70: aload         9
      72: invokeinterface #15,  1           // InterfaceMethod org/hibernate/type/CompositeType.getSubtypes:()[Lorg/hibernate/type/Type;
      77: astore        10
      79: aload_0
      80: iload         8
      82: aaload
      83: ifnonnull     95
      86: aload         10
      88: arraylength
      89: anewarray     #7                  // class java/lang/Object
      92: goto          107
      95: aload         9
      97: aload_0
      98: iload         8
     100: aaload
     101: aload_3
     102: invokeinterface #16,  3           // InterfaceMethod org/hibernate/type/CompositeType.getPropertyValues:(Ljava/lang/Object;Lorg/hibernate/engine/spi/SharedSessionContractImplementor;)[Ljava/lang/Object;
     107: astore        11
     109: aload_1
     110: iload         8
     112: aaload
     113: ifnonnull     125
     116: aload         10
     118: arraylength
     119: anewarray     #7                  // class java/lang/Object
     122: goto          137
     125: aload         9
     127: aload_1
     128: iload         8
     130: aaload
     131: aload_3
     132: invokeinterface #16,  3           // InterfaceMethod org/hibernate/type/CompositeType.getPropertyValues:(Ljava/lang/Object;Lorg/hibernate/engine/spi/SharedSessionContractImplementor;)[Ljava/lang/Object;
     137: astore        12
     139: aload         11
     141: aload         12
     143: aload         10
     145: aload_3
     146: aconst_null
     147: aload         5
     149: aload         6
     151: invokestatic  #17                 // Method replaceAssociations:([Ljava/lang/Object;[Ljava/lang/Object;[Lorg/hibernate/type/Type;Lorg/hibernate/engine/spi/SharedSessionContractImplementor;Ljava/lang/Object;Ljava/util/Map;Lorg/hibernate/type/ForeignKeyDirection;)[Ljava/lang/Object;
     154: pop
     155: aload         7
     157: iload         8
     159: aload_1
     160: iload         8
     162: aaload
     163: aastore
     164: goto          220
     167: aload_2
     168: iload         8
     170: aaload
     171: invokeinterface #18,  1           // InterfaceMethod org/hibernate/type/Type.isAssociationType:()Z
     176: ifne          191
     179: aload         7
     181: iload         8
     183: aload_1
     184: iload         8
     186: aaload
     187: aastore
     188: goto          220
     191: aload         7
     193: iload         8
     195: aload_2
     196: iload         8
     198: aaload
     199: aload_0
     200: iload         8
     202: aaload
     203: aload_1
     204: iload         8
     206: aaload
     207: aload_3
     208: aload         4
     210: aload         5
     212: aload         6
     214: invokeinterface #12,  7           // InterfaceMethod org/hibernate/type/Type.replace:(Ljava/lang/Object;Ljava/lang/Object;Lorg/hibernate/engine/spi/SharedSessionContractImplementor;Ljava/lang/Object;Ljava/util/Map;Lorg/hibernate/type/ForeignKeyDirection;)Ljava/lang/Object;
     219: aastore
     220: iinc          8, 1
     223: goto          10
     226: aload         7
     228: areturn

  public static int[] findDirty(org.hibernate.tuple.NonIdentifierAttribute[], java.lang.Object[], java.lang.Object[], boolean[][], boolean, org.hibernate.engine.spi.SharedSessionContractImplementor);
    Code:
       0: aload_0
       1: aload_1
       2: aload_2
       3: aload_3
       4: aload         5
       6: invokestatic  #19                 // Method findDirty:([Lorg/hibernate/tuple/NonIdentifierAttribute;[Ljava/lang/Object;[Ljava/lang/Object;[[ZLorg/hibernate/engine/spi/SharedSessionContractImplementor;)[I
       9: areturn

  public static int[] findDirty(org.hibernate.tuple.NonIdentifierAttribute[], java.lang.Object[], java.lang.Object[], boolean[][], org.hibernate.engine.spi.SharedSessionContractImplementor);
    Code:
       0: aconst_null
       1: astore        5
       3: iconst_0
       4: istore        6
       6: aload_0
       7: arraylength
       8: istore        7
      10: iconst_0
      11: istore        8
      13: iload         8
      15: iload         7
      17: if_icmpge     122
      20: aload_1
      21: iload         8
      23: aaload
      24: getstatic     #2                  // Field org/hibernate/bytecode/enhance/spi/LazyPropertyInitializer.UNFETCHED_PROPERTY:Ljava/io/Serializable;
      27: if_acmpeq     87
      30: aload_2
      31: iload         8
      33: aaload
      34: getstatic     #2                  // Field org/hibernate/bytecode/enhance/spi/LazyPropertyInitializer.UNFETCHED_PROPERTY:Ljava/io/Serializable;
      37: if_acmpeq     83
      40: aload_0
      41: iload         8
      43: aaload
      44: invokeinterface #20,  1           // InterfaceMethod org/hibernate/tuple/NonIdentifierAttribute.isDirtyCheckable:()Z
      49: ifeq          87
      52: aload_0
      53: iload         8
      55: aaload
      56: invokeinterface #21,  1           // InterfaceMethod org/hibernate/tuple/NonIdentifierAttribute.getType:()Lorg/hibernate/type/Type;
      61: aload_2
      62: iload         8
      64: aaload
      65: aload_1
      66: iload         8
      68: aaload
      69: aload_3
      70: iload         8
      72: aaload
      73: aload         4
      75: invokeinterface #22,  5           // InterfaceMethod org/hibernate/type/Type.isDirty:(Ljava/lang/Object;Ljava/lang/Object;[ZLorg/hibernate/engine/spi/SharedSessionContractImplementor;)Z
      80: ifeq          87
      83: iconst_1
      84: goto          88
      87: iconst_0
      88: istore        9
      90: iload         9
      92: ifeq          116
      95: aload         5
      97: ifnonnull     106
     100: iload         7
     102: newarray       int
     104: astore        5
     106: aload         5
     108: iload         6
     110: iinc          6, 1
     113: iload         8
     115: iastore
     116: iinc          8, 1
     119: goto          13
     122: iload         6
     124: ifne          129
     127: aconst_null
     128: areturn
     129: iload         6
     131: newarray       int
     133: astore        8
     135: aload         5
     137: iconst_0
     138: aload         8
     140: iconst_0
     141: iload         6
     143: invokestatic  #23                 // Method java/lang/System.arraycopy:(Ljava/lang/Object;ILjava/lang/Object;II)V
     146: aload         8
     148: areturn

  public static int[] findModified(org.hibernate.tuple.NonIdentifierAttribute[], java.lang.Object[], java.lang.Object[], boolean[][], boolean[], boolean, org.hibernate.engine.spi.SharedSessionContractImplementor);
    Code:
       0: aload_0
       1: aload_1
       2: aload_2
       3: aload_3
       4: aload         4
       6: aload         6
       8: invokestatic  #24                 // Method findModified:([Lorg/hibernate/tuple/NonIdentifierAttribute;[Ljava/lang/Object;[Ljava/lang/Object;[[Z[ZLorg/hibernate/engine/spi/SharedSessionContractImplementor;)[I
      11: areturn

  public static int[] findModified(org.hibernate.tuple.NonIdentifierAttribute[], java.lang.Object[], java.lang.Object[], boolean[][], boolean[], org.hibernate.engine.spi.SharedSessionContractImplementor);
    Code:
       0: aconst_null
       1: astore        6
       3: iconst_0
       4: istore        7
       6: aload_0
       7: arraylength
       8: istore        8
      10: iconst_0
      11: istore        9
      13: iload         9
      15: iload         8
      17: if_icmpge     120
      20: aload_1
      21: iload         9
      23: aaload
      24: getstatic     #2                  // Field org/hibernate/bytecode/enhance/spi/LazyPropertyInitializer.UNFETCHED_PROPERTY:Ljava/io/Serializable;
      27: if_acmpeq     85
      30: aload         4
      32: iload         9
      34: baload
      35: ifeq          85
      38: aload_0
      39: iload         9
      41: aaload
      42: invokeinterface #20,  1           // InterfaceMethod org/hibernate/tuple/NonIdentifierAttribute.isDirtyCheckable:()Z
      47: ifeq          85
      50: aload_0
      51: iload         9
      53: aaload
      54: invokeinterface #21,  1           // InterfaceMethod org/hibernate/tuple/NonIdentifierAttribute.getType:()Lorg/hibernate/type/Type;
      59: aload_2
      60: iload         9
      62: aaload
      63: aload_1
      64: iload         9
      66: aaload
      67: aload_3
      68: iload         9
      70: aaload
      71: aload         5
      73: invokeinterface #25,  5           // InterfaceMethod org/hibernate/type/Type.isModified:(Ljava/lang/Object;Ljava/lang/Object;[ZLorg/hibernate/engine/spi/SharedSessionContractImplementor;)Z
      78: ifeq          85
      81: iconst_1
      82: goto          86
      85: iconst_0
      86: istore        10
      88: iload         10
      90: ifeq          114
      93: aload         6
      95: ifnonnull     104
      98: iload         8
     100: newarray       int
     102: astore        6
     104: aload         6
     106: iload         7
     108: iinc          7, 1
     111: iload         9
     113: iastore
     114: iinc          9, 1
     117: goto          13
     120: iload         7
     122: ifne          127
     125: aconst_null
     126: areturn
     127: iload         7
     129: newarray       int
     131: astore        9
     133: aload         6
     135: iconst_0
     136: aload         9
     138: iconst_0
     139: iload         7
     141: invokestatic  #23                 // Method java/lang/System.arraycopy:(Ljava/lang/Object;ILjava/lang/Object;II)V
     144: aload         9
     146: areturn
}
