Compiled from "InternalLoggerFactory.java"
public abstract class io.micrometer.core.util.internal.logging.InternalLoggerFactory {
  private static volatile io.micrometer.core.util.internal.logging.InternalLoggerFactory defaultFactory;

  public io.micrometer.core.util.internal.logging.InternalLoggerFactory();
    Code:
       0: aload_0
       1: invokespecial #1                  // Method java/lang/Object."<init>":()V
       4: return

  private static io.micrometer.core.util.internal.logging.InternalLoggerFactory newDefaultFactory(java.lang.String);
    Code:
       0: getstatic     #7                  // Field io/micrometer/core/util/internal/logging/Slf4JLoggerFactory.INSTANCE:Lio/micrometer/core/util/internal/logging/InternalLoggerFactory;
       3: astore_1
       4: aload_1
       5: aload_0
       6: invokevirtual #13                 // Method newInstance:(Ljava/lang/String;)Lio/micrometer/core/util/internal/logging/InternalLogger;
       9: ldc           #19                 // String Using SLF4J as the default logging framework
      11: invokeinterface #21,  2           // InterfaceMethod io/micrometer/core/util/internal/logging/InternalLogger.debug:(Ljava/lang/String;)V
      16: goto          36
      19: astore_2
      20: getstatic     #29                 // Field io/micrometer/core/util/internal/logging/JdkLoggerFactory.INSTANCE:Lio/micrometer/core/util/internal/logging/InternalLoggerFactory;
      23: astore_1
      24: aload_1
      25: aload_0
      26: invokevirtual #13                 // Method newInstance:(Ljava/lang/String;)Lio/micrometer/core/util/internal/logging/InternalLogger;
      29: ldc           #32                 // String Using java.util.logging as the default logging framework
      31: invokeinterface #21,  2           // InterfaceMethod io/micrometer/core/util/internal/logging/InternalLogger.debug:(Ljava/lang/String;)V
      36: aload_1
      37: areturn
    Exception table:
       from    to  target type
           0    16    19   Class java/lang/Throwable

  public static io.micrometer.core.util.internal.logging.InternalLoggerFactory getDefaultFactory();
    Code:
       0: getstatic     #34                 // Field defaultFactory:Lio/micrometer/core/util/internal/logging/InternalLoggerFactory;
       3: ifnonnull     17
       6: ldc           #14                 // class io/micrometer/core/util/internal/logging/InternalLoggerFactory
       8: invokevirtual #37                 // Method java/lang/Class.getName:()Ljava/lang/String;
      11: invokestatic  #43                 // Method newDefaultFactory:(Ljava/lang/String;)Lio/micrometer/core/util/internal/logging/InternalLoggerFactory;
      14: putstatic     #34                 // Field defaultFactory:Lio/micrometer/core/util/internal/logging/InternalLoggerFactory;
      17: getstatic     #34                 // Field defaultFactory:Lio/micrometer/core/util/internal/logging/InternalLoggerFactory;
      20: areturn

  public static void setDefaultFactory(io.micrometer.core.util.internal.logging.InternalLoggerFactory);
    Code:
       0: aload_0
       1: ldc           #47                 // String defaultFactory
       3: invokestatic  #48                 // Method java/util/Objects.requireNonNull:(Ljava/lang/Object;Ljava/lang/String;)Ljava/lang/Object;
       6: pop
       7: aload_0
       8: putstatic     #34                 // Field defaultFactory:Lio/micrometer/core/util/internal/logging/InternalLoggerFactory;
      11: return

  public static io.micrometer.core.util.internal.logging.InternalLogger getInstance(java.lang.Class<?>);
    Code:
       0: aload_0
       1: invokevirtual #37                 // Method java/lang/Class.getName:()Ljava/lang/String;
       4: invokestatic  #54                 // Method getInstance:(Ljava/lang/String;)Lio/micrometer/core/util/internal/logging/InternalLogger;
       7: areturn

  public static io.micrometer.core.util.internal.logging.InternalLogger getInstance(java.lang.String);
    Code:
       0: invokestatic  #57                 // Method getDefaultFactory:()Lio/micrometer/core/util/internal/logging/InternalLoggerFactory;
       3: aload_0
       4: invokevirtual #13                 // Method newInstance:(Ljava/lang/String;)Lio/micrometer/core/util/internal/logging/InternalLogger;
       7: areturn

  protected abstract io.micrometer.core.util.internal.logging.InternalLogger newInstance(java.lang.String);
}
