Compiled from "Slf4JLoggerFactory.java"
public class io.micrometer.core.util.internal.logging.Slf4JLoggerFactory extends io.micrometer.core.util.internal.logging.InternalLoggerFactory {
  public static final io.micrometer.core.util.internal.logging.InternalLoggerFactory INSTANCE;

  private io.micrometer.core.util.internal.logging.Slf4JLoggerFactory();
    Code:
       0: aload_0
       1: invokespecial #1                  // Method io/micrometer/core/util/internal/logging/InternalLoggerFactory."<init>":()V
       4: invokestatic  #7                  // Method org/slf4j/LoggerFactory.getILoggerFactory:()Lorg/slf4j/ILoggerFactory;
       7: instanceof    #13                 // class org/slf4j/helpers/NOPLoggerFactory
      10: ifeq          23
      13: new           #15                 // class java/lang/NoClassDefFoundError
      16: dup
      17: ldc           #17                 // String NOPLoggerFactory not supported
      19: invokespecial #19                 // Method java/lang/NoClassDefFoundError."<init>":(Ljava/lang/String;)V
      22: athrow
      23: return

  public io.micrometer.core.util.internal.logging.InternalLogger newInstance(java.lang.String);
    Code:
       0: aload_1
       1: invokestatic  #22                 // Method org/slf4j/LoggerFactory.getLogger:(Ljava/lang/String;)Lorg/slf4j/Logger;
       4: invokestatic  #26                 // Method wrapLogger:(Lorg/slf4j/Logger;)Lio/micrometer/core/util/internal/logging/InternalLogger;
       7: areturn

  static io.micrometer.core.util.internal.logging.InternalLogger wrapLogger(org.slf4j.Logger);
    Code:
       0: aload_0
       1: instanceof    #32                 // class org/slf4j/spi/LocationAwareLogger
       4: ifeq          21
       7: new           #34                 // class io/micrometer/core/util/internal/logging/LocationAwareSlf4JLogger
      10: dup
      11: aload_0
      12: checkcast     #32                 // class org/slf4j/spi/LocationAwareLogger
      15: invokespecial #36                 // Method io/micrometer/core/util/internal/logging/LocationAwareSlf4JLogger."<init>":(Lorg/slf4j/spi/LocationAwareLogger;)V
      18: goto          29
      21: new           #39                 // class io/micrometer/core/util/internal/logging/Slf4JLogger
      24: dup
      25: aload_0
      26: invokespecial #41                 // Method io/micrometer/core/util/internal/logging/Slf4JLogger."<init>":(Lorg/slf4j/Logger;)V
      29: areturn

  static {};
    Code:
       0: new           #27                 // class io/micrometer/core/util/internal/logging/Slf4JLoggerFactory
       3: dup
       4: invokespecial #44                 // Method "<init>":()V
       7: putstatic     #45                 // Field INSTANCE:Lio/micrometer/core/util/internal/logging/InternalLoggerFactory;
      10: return
}
