Compiled from "AbstractPatriciaTrie.java"
class org.apache.commons.collections4.trie.AbstractPatriciaTrie$Reference<E> {
  private E item;

  private org.apache.commons.collections4.trie.AbstractPatriciaTrie$Reference();
    Code:
       0: aload_0
       1: invokespecial #2                  // Method java/lang/Object."<init>":()V
       4: return

  public void set(E);
    Code:
       0: aload_0
       1: aload_1
       2: putfield      #3                  // Field item:Ljava/lang/Object;
       5: return

  public E get();
    Code:
       0: aload_0
       1: getfield      #3                  // Field item:Ljava/lang/Object;
       4: areturn

  org.apache.commons.collections4.trie.AbstractPatriciaTrie$Reference(org.apache.commons.collections4.trie.AbstractPatriciaTrie$1);
    Code:
       0: aload_0
       1: invokespecial #1                  // Method "<init>":()V
       4: return
}
