Compiled from "DoneableDaemonSetUpdateStrategy.java"
public class io.fabric8.kubernetes.api.model.extensions.DoneableDaemonSetUpdateStrategy extends io.fabric8.kubernetes.api.model.extensions.DaemonSetUpdateStrategyFluentImpl<io.fabric8.kubernetes.api.model.extensions.DoneableDaemonSetUpdateStrategy> implements io.fabric8.kubernetes.api.model.Doneable<io.fabric8.kubernetes.api.model.extensions.DaemonSetUpdateStrategy> {
  private final io.fabric8.kubernetes.api.model.extensions.DaemonSetUpdateStrategyBuilder builder;

  private final io.fabric8.kubernetes.api.builder.Function<io.fabric8.kubernetes.api.model.extensions.DaemonSetUpdateStrategy, io.fabric8.kubernetes.api.model.extensions.DaemonSetUpdateStrategy> function;

  public io.fabric8.kubernetes.api.model.extensions.DoneableDaemonSetUpdateStrategy(io.fabric8.kubernetes.api.builder.Function<io.fabric8.kubernetes.api.model.extensions.DaemonSetUpdateStrategy, io.fabric8.kubernetes.api.model.extensions.DaemonSetUpdateStrategy>);
    Code:
       0: aload_0
       1: invokespecial #1                  // Method io/fabric8/kubernetes/api/model/extensions/DaemonSetUpdateStrategyFluentImpl."<init>":()V
       4: aload_0
       5: new           #2                  // class io/fabric8/kubernetes/api/model/extensions/DaemonSetUpdateStrategyBuilder
       8: dup
       9: aload_0
      10: invokespecial #3                  // Method io/fabric8/kubernetes/api/model/extensions/DaemonSetUpdateStrategyBuilder."<init>":(Lio/fabric8/kubernetes/api/model/extensions/DaemonSetUpdateStrategyFluent;)V
      13: putfield      #4                  // Field builder:Lio/fabric8/kubernetes/api/model/extensions/DaemonSetUpdateStrategyBuilder;
      16: aload_0
      17: aload_1
      18: putfield      #5                  // Field function:Lio/fabric8/kubernetes/api/builder/Function;
      21: return

  public io.fabric8.kubernetes.api.model.extensions.DoneableDaemonSetUpdateStrategy(io.fabric8.kubernetes.api.model.extensions.DaemonSetUpdateStrategy, io.fabric8.kubernetes.api.builder.Function<io.fabric8.kubernetes.api.model.extensions.DaemonSetUpdateStrategy, io.fabric8.kubernetes.api.model.extensions.DaemonSetUpdateStrategy>);
    Code:
       0: aload_0
       1: aload_1
       2: invokespecial #6                  // Method io/fabric8/kubernetes/api/model/extensions/DaemonSetUpdateStrategyFluentImpl."<init>":(Lio/fabric8/kubernetes/api/model/extensions/DaemonSetUpdateStrategy;)V
       5: aload_0
       6: new           #2                  // class io/fabric8/kubernetes/api/model/extensions/DaemonSetUpdateStrategyBuilder
       9: dup
      10: aload_0
      11: aload_1
      12: invokespecial #7                  // Method io/fabric8/kubernetes/api/model/extensions/DaemonSetUpdateStrategyBuilder."<init>":(Lio/fabric8/kubernetes/api/model/extensions/DaemonSetUpdateStrategyFluent;Lio/fabric8/kubernetes/api/model/extensions/DaemonSetUpdateStrategy;)V
      15: putfield      #4                  // Field builder:Lio/fabric8/kubernetes/api/model/extensions/DaemonSetUpdateStrategyBuilder;
      18: aload_0
      19: aload_2
      20: putfield      #5                  // Field function:Lio/fabric8/kubernetes/api/builder/Function;
      23: return

  public io.fabric8.kubernetes.api.model.extensions.DoneableDaemonSetUpdateStrategy(io.fabric8.kubernetes.api.model.extensions.DaemonSetUpdateStrategy);
    Code:
       0: aload_0
       1: aload_1
       2: invokespecial #6                  // Method io/fabric8/kubernetes/api/model/extensions/DaemonSetUpdateStrategyFluentImpl."<init>":(Lio/fabric8/kubernetes/api/model/extensions/DaemonSetUpdateStrategy;)V
       5: aload_0
       6: new           #2                  // class io/fabric8/kubernetes/api/model/extensions/DaemonSetUpdateStrategyBuilder
       9: dup
      10: aload_0
      11: aload_1
      12: invokespecial #7                  // Method io/fabric8/kubernetes/api/model/extensions/DaemonSetUpdateStrategyBuilder."<init>":(Lio/fabric8/kubernetes/api/model/extensions/DaemonSetUpdateStrategyFluent;Lio/fabric8/kubernetes/api/model/extensions/DaemonSetUpdateStrategy;)V
      15: putfield      #4                  // Field builder:Lio/fabric8/kubernetes/api/model/extensions/DaemonSetUpdateStrategyBuilder;
      18: aload_0
      19: new           #8                  // class io/fabric8/kubernetes/api/model/extensions/DoneableDaemonSetUpdateStrategy$1
      22: dup
      23: aload_0
      24: invokespecial #9                  // Method io/fabric8/kubernetes/api/model/extensions/DoneableDaemonSetUpdateStrategy$1."<init>":(Lio/fabric8/kubernetes/api/model/extensions/DoneableDaemonSetUpdateStrategy;)V
      27: putfield      #5                  // Field function:Lio/fabric8/kubernetes/api/builder/Function;
      30: return

  public io.fabric8.kubernetes.api.model.extensions.DaemonSetUpdateStrategy done();
    Code:
       0: aload_0
       1: getfield      #5                  // Field function:Lio/fabric8/kubernetes/api/builder/Function;
       4: aload_0
       5: getfield      #4                  // Field builder:Lio/fabric8/kubernetes/api/model/extensions/DaemonSetUpdateStrategyBuilder;
       8: invokevirtual #10                 // Method io/fabric8/kubernetes/api/model/extensions/DaemonSetUpdateStrategyBuilder.build:()Lio/fabric8/kubernetes/api/model/extensions/DaemonSetUpdateStrategy;
      11: invokeinterface #11,  2           // InterfaceMethod io/fabric8/kubernetes/api/builder/Function.apply:(Ljava/lang/Object;)Ljava/lang/Object;
      16: checkcast     #12                 // class io/fabric8/kubernetes/api/model/extensions/DaemonSetUpdateStrategy
      19: areturn

  public java.lang.Object done();
    Code:
       0: aload_0
       1: invokevirtual #13                 // Method done:()Lio/fabric8/kubernetes/api/model/extensions/DaemonSetUpdateStrategy;
       4: areturn
}
