Compiled from "TypeDeclarationsIRFactory.java"
final class com.google.javascript.jscomp.parsing.TypeDeclarationsIRFactory$1 implements com.google.common.base.Function<com.google.javascript.rhino.Node, com.google.javascript.rhino.Node$TypeDeclarationNode> {
  com.google.javascript.jscomp.parsing.TypeDeclarationsIRFactory$1();
    Code:
       0: aload_0
       1: invokespecial #1                  // Method java/lang/Object."<init>":()V
       4: return

  public com.google.javascript.rhino.Node$TypeDeclarationNode apply(com.google.javascript.rhino.Node);
    Code:
       0: aload_1
       1: invokestatic  #2                  // Method com/google/javascript/jscomp/parsing/TypeDeclarationsIRFactory.convertTypeNodeAST:(Lcom/google/javascript/rhino/Node;)Lcom/google/javascript/rhino/Node$TypeDeclarationNode;
       4: areturn

  public java.lang.Object apply(java.lang.Object);
    Code:
       0: aload_0
       1: aload_1
       2: checkcast     #3                  // class com/google/javascript/rhino/Node
       5: invokevirtual #4                  // Method apply:(Lcom/google/javascript/rhino/Node;)Lcom/google/javascript/rhino/Node$TypeDeclarationNode;
       8: areturn
}
