Compiled from "ConnectorStatistics.java"
public class org.apache.activemq.broker.region.ConnectorStatistics extends org.apache.activemq.management.StatsImpl {
  protected org.apache.activemq.management.CountStatisticImpl enqueues;

  protected org.apache.activemq.management.CountStatisticImpl dequeues;

  protected org.apache.activemq.management.CountStatisticImpl consumers;

  protected org.apache.activemq.management.CountStatisticImpl messages;

  protected org.apache.activemq.management.PollCountStatisticImpl messagesCached;

  public org.apache.activemq.broker.region.ConnectorStatistics();
    Code:
       0: aload_0
       1: invokespecial #1                  // Method org/apache/activemq/management/StatsImpl."<init>":()V
       4: aload_0
       5: new           #2                  // class org/apache/activemq/management/CountStatisticImpl
       8: dup
       9: ldc           #3                  // String enqueues
      11: ldc           #4                  // String The number of messages that have been sent to the destination
      13: invokespecial #5                  // Method org/apache/activemq/management/CountStatisticImpl."<init>":(Ljava/lang/String;Ljava/lang/String;)V
      16: putfield      #6                  // Field enqueues:Lorg/apache/activemq/management/CountStatisticImpl;
      19: aload_0
      20: new           #2                  // class org/apache/activemq/management/CountStatisticImpl
      23: dup
      24: ldc           #7                  // String dequeues
      26: ldc           #8                  // String The number of messages that have been dispatched from the destination
      28: invokespecial #5                  // Method org/apache/activemq/management/CountStatisticImpl."<init>":(Ljava/lang/String;Ljava/lang/String;)V
      31: putfield      #9                  // Field dequeues:Lorg/apache/activemq/management/CountStatisticImpl;
      34: aload_0
      35: new           #2                  // class org/apache/activemq/management/CountStatisticImpl
      38: dup
      39: ldc           #10                 // String consumers
      41: ldc           #11                 // String The number of consumers that that are subscribing to messages from the destination
      43: invokespecial #5                  // Method org/apache/activemq/management/CountStatisticImpl."<init>":(Ljava/lang/String;Ljava/lang/String;)V
      46: putfield      #12                 // Field consumers:Lorg/apache/activemq/management/CountStatisticImpl;
      49: aload_0
      50: new           #2                  // class org/apache/activemq/management/CountStatisticImpl
      53: dup
      54: ldc           #13                 // String messages
      56: ldc           #14                 // String The number of messages that that are being held by the destination
      58: invokespecial #5                  // Method org/apache/activemq/management/CountStatisticImpl."<init>":(Ljava/lang/String;Ljava/lang/String;)V
      61: putfield      #15                 // Field messages:Lorg/apache/activemq/management/CountStatisticImpl;
      64: aload_0
      65: new           #16                 // class org/apache/activemq/management/PollCountStatisticImpl
      68: dup
      69: ldc           #17                 // String messagesCached
      71: ldc           #18                 // String The number of messages that are held in the destination\'s memory cache
      73: invokespecial #19                 // Method org/apache/activemq/management/PollCountStatisticImpl."<init>":(Ljava/lang/String;Ljava/lang/String;)V
      76: putfield      #20                 // Field messagesCached:Lorg/apache/activemq/management/PollCountStatisticImpl;
      79: aload_0
      80: ldc           #3                  // String enqueues
      82: aload_0
      83: getfield      #6                  // Field enqueues:Lorg/apache/activemq/management/CountStatisticImpl;
      86: invokevirtual #21                 // Method addStatistic:(Ljava/lang/String;Lorg/apache/activemq/management/StatisticImpl;)V
      89: aload_0
      90: ldc           #7                  // String dequeues
      92: aload_0
      93: getfield      #9                  // Field dequeues:Lorg/apache/activemq/management/CountStatisticImpl;
      96: invokevirtual #21                 // Method addStatistic:(Ljava/lang/String;Lorg/apache/activemq/management/StatisticImpl;)V
      99: aload_0
     100: ldc           #10                 // String consumers
     102: aload_0
     103: getfield      #12                 // Field consumers:Lorg/apache/activemq/management/CountStatisticImpl;
     106: invokevirtual #21                 // Method addStatistic:(Ljava/lang/String;Lorg/apache/activemq/management/StatisticImpl;)V
     109: aload_0
     110: ldc           #13                 // String messages
     112: aload_0
     113: getfield      #15                 // Field messages:Lorg/apache/activemq/management/CountStatisticImpl;
     116: invokevirtual #21                 // Method addStatistic:(Ljava/lang/String;Lorg/apache/activemq/management/StatisticImpl;)V
     119: aload_0
     120: ldc           #17                 // String messagesCached
     122: aload_0
     123: getfield      #20                 // Field messagesCached:Lorg/apache/activemq/management/PollCountStatisticImpl;
     126: invokevirtual #21                 // Method addStatistic:(Ljava/lang/String;Lorg/apache/activemq/management/StatisticImpl;)V
     129: return

  public org.apache.activemq.management.CountStatisticImpl getEnqueues();
    Code:
       0: aload_0
       1: getfield      #6                  // Field enqueues:Lorg/apache/activemq/management/CountStatisticImpl;
       4: areturn

  public org.apache.activemq.management.CountStatisticImpl getDequeues();
    Code:
       0: aload_0
       1: getfield      #9                  // Field dequeues:Lorg/apache/activemq/management/CountStatisticImpl;
       4: areturn

  public org.apache.activemq.management.CountStatisticImpl getConsumers();
    Code:
       0: aload_0
       1: getfield      #12                 // Field consumers:Lorg/apache/activemq/management/CountStatisticImpl;
       4: areturn

  public org.apache.activemq.management.PollCountStatisticImpl getMessagesCached();
    Code:
       0: aload_0
       1: getfield      #20                 // Field messagesCached:Lorg/apache/activemq/management/PollCountStatisticImpl;
       4: areturn

  public org.apache.activemq.management.CountStatisticImpl getMessages();
    Code:
       0: aload_0
       1: getfield      #15                 // Field messages:Lorg/apache/activemq/management/CountStatisticImpl;
       4: areturn

  public void reset();
    Code:
       0: aload_0
       1: invokespecial #22                 // Method org/apache/activemq/management/StatsImpl.reset:()V
       4: aload_0
       5: getfield      #6                  // Field enqueues:Lorg/apache/activemq/management/CountStatisticImpl;
       8: invokevirtual #23                 // Method org/apache/activemq/management/CountStatisticImpl.reset:()V
      11: aload_0
      12: getfield      #9                  // Field dequeues:Lorg/apache/activemq/management/CountStatisticImpl;
      15: invokevirtual #23                 // Method org/apache/activemq/management/CountStatisticImpl.reset:()V
      18: return

  public void setEnabled(boolean);
    Code:
       0: aload_0
       1: iload_1
       2: invokespecial #24                 // Method org/apache/activemq/management/StatsImpl.setEnabled:(Z)V
       5: aload_0
       6: getfield      #6                  // Field enqueues:Lorg/apache/activemq/management/CountStatisticImpl;
       9: iload_1
      10: invokevirtual #25                 // Method org/apache/activemq/management/CountStatisticImpl.setEnabled:(Z)V
      13: aload_0
      14: getfield      #9                  // Field dequeues:Lorg/apache/activemq/management/CountStatisticImpl;
      17: iload_1
      18: invokevirtual #25                 // Method org/apache/activemq/management/CountStatisticImpl.setEnabled:(Z)V
      21: aload_0
      22: getfield      #12                 // Field consumers:Lorg/apache/activemq/management/CountStatisticImpl;
      25: iload_1
      26: invokevirtual #25                 // Method org/apache/activemq/management/CountStatisticImpl.setEnabled:(Z)V
      29: aload_0
      30: getfield      #15                 // Field messages:Lorg/apache/activemq/management/CountStatisticImpl;
      33: iload_1
      34: invokevirtual #25                 // Method org/apache/activemq/management/CountStatisticImpl.setEnabled:(Z)V
      37: aload_0
      38: getfield      #20                 // Field messagesCached:Lorg/apache/activemq/management/PollCountStatisticImpl;
      41: iload_1
      42: invokevirtual #26                 // Method org/apache/activemq/management/PollCountStatisticImpl.setEnabled:(Z)V
      45: return

  public void setParent(org.apache.activemq.broker.region.ConnectorStatistics);
    Code:
       0: aload_1
       1: ifnull        62
       4: aload_0
       5: getfield      #6                  // Field enqueues:Lorg/apache/activemq/management/CountStatisticImpl;
       8: aload_1
       9: getfield      #6                  // Field enqueues:Lorg/apache/activemq/management/CountStatisticImpl;
      12: invokevirtual #27                 // Method org/apache/activemq/management/CountStatisticImpl.setParent:(Lorg/apache/activemq/management/CountStatisticImpl;)V
      15: aload_0
      16: getfield      #9                  // Field dequeues:Lorg/apache/activemq/management/CountStatisticImpl;
      19: aload_1
      20: getfield      #9                  // Field dequeues:Lorg/apache/activemq/management/CountStatisticImpl;
      23: invokevirtual #27                 // Method org/apache/activemq/management/CountStatisticImpl.setParent:(Lorg/apache/activemq/management/CountStatisticImpl;)V
      26: aload_0
      27: getfield      #12                 // Field consumers:Lorg/apache/activemq/management/CountStatisticImpl;
      30: aload_1
      31: getfield      #12                 // Field consumers:Lorg/apache/activemq/management/CountStatisticImpl;
      34: invokevirtual #27                 // Method org/apache/activemq/management/CountStatisticImpl.setParent:(Lorg/apache/activemq/management/CountStatisticImpl;)V
      37: aload_0
      38: getfield      #20                 // Field messagesCached:Lorg/apache/activemq/management/PollCountStatisticImpl;
      41: aload_1
      42: getfield      #20                 // Field messagesCached:Lorg/apache/activemq/management/PollCountStatisticImpl;
      45: invokevirtual #28                 // Method org/apache/activemq/management/PollCountStatisticImpl.setParent:(Lorg/apache/activemq/management/PollCountStatisticImpl;)V
      48: aload_0
      49: getfield      #15                 // Field messages:Lorg/apache/activemq/management/CountStatisticImpl;
      52: aload_1
      53: getfield      #15                 // Field messages:Lorg/apache/activemq/management/CountStatisticImpl;
      56: invokevirtual #27                 // Method org/apache/activemq/management/CountStatisticImpl.setParent:(Lorg/apache/activemq/management/CountStatisticImpl;)V
      59: goto          102
      62: aload_0
      63: getfield      #6                  // Field enqueues:Lorg/apache/activemq/management/CountStatisticImpl;
      66: aconst_null
      67: invokevirtual #27                 // Method org/apache/activemq/management/CountStatisticImpl.setParent:(Lorg/apache/activemq/management/CountStatisticImpl;)V
      70: aload_0
      71: getfield      #9                  // Field dequeues:Lorg/apache/activemq/management/CountStatisticImpl;
      74: aconst_null
      75: invokevirtual #27                 // Method org/apache/activemq/management/CountStatisticImpl.setParent:(Lorg/apache/activemq/management/CountStatisticImpl;)V
      78: aload_0
      79: getfield      #12                 // Field consumers:Lorg/apache/activemq/management/CountStatisticImpl;
      82: aconst_null
      83: invokevirtual #27                 // Method org/apache/activemq/management/CountStatisticImpl.setParent:(Lorg/apache/activemq/management/CountStatisticImpl;)V
      86: aload_0
      87: getfield      #20                 // Field messagesCached:Lorg/apache/activemq/management/PollCountStatisticImpl;
      90: aconst_null
      91: invokevirtual #28                 // Method org/apache/activemq/management/PollCountStatisticImpl.setParent:(Lorg/apache/activemq/management/PollCountStatisticImpl;)V
      94: aload_0
      95: getfield      #15                 // Field messages:Lorg/apache/activemq/management/CountStatisticImpl;
      98: aconst_null
      99: invokevirtual #27                 // Method org/apache/activemq/management/CountStatisticImpl.setParent:(Lorg/apache/activemq/management/CountStatisticImpl;)V
     102: return

  public void setMessagesCached(org.apache.activemq.management.PollCountStatisticImpl);
    Code:
       0: aload_0
       1: aload_1
       2: putfield      #20                 // Field messagesCached:Lorg/apache/activemq/management/PollCountStatisticImpl;
       5: return
}
