Compiled from "TopicSubscription.java"
class org.apache.activemq.broker.region.TopicSubscription$1 extends org.apache.activemq.transaction.Synchronization {
  final org.apache.activemq.command.MessageAck val$ack;

  final org.apache.activemq.broker.region.TopicSubscription this$0;

  org.apache.activemq.broker.region.TopicSubscription$1(org.apache.activemq.broker.region.TopicSubscription, org.apache.activemq.command.MessageAck);
    Code:
       0: aload_0
       1: aload_1
       2: putfield      #1                  // Field this$0:Lorg/apache/activemq/broker/region/TopicSubscription;
       5: aload_0
       6: aload_2
       7: putfield      #2                  // Field val$ack:Lorg/apache/activemq/command/MessageAck;
      10: aload_0
      11: invokespecial #3                  // Method org/apache/activemq/transaction/Synchronization."<init>":()V
      14: return

  public void afterCommit() throws java.lang.Exception;
    Code:
       0: aload_0
       1: getfield      #1                  // Field this$0:Lorg/apache/activemq/broker/region/TopicSubscription;
       4: dup
       5: astore_1
       6: monitorenter
       7: aload_0
       8: getfield      #1                  // Field this$0:Lorg/apache/activemq/broker/region/TopicSubscription;
      11: getfield      #4                  // Field org/apache/activemq/broker/region/TopicSubscription.singleDestination:Z
      14: ifeq          53
      17: aload_0
      18: getfield      #1                  // Field this$0:Lorg/apache/activemq/broker/region/TopicSubscription;
      21: getfield      #5                  // Field org/apache/activemq/broker/region/TopicSubscription.destination:Lorg/apache/activemq/broker/region/Destination;
      24: ifnull        53
      27: aload_0
      28: getfield      #1                  // Field this$0:Lorg/apache/activemq/broker/region/TopicSubscription;
      31: getfield      #5                  // Field org/apache/activemq/broker/region/TopicSubscription.destination:Lorg/apache/activemq/broker/region/Destination;
      34: invokeinterface #6,  1            // InterfaceMethod org/apache/activemq/broker/region/Destination.getDestinationStatistics:()Lorg/apache/activemq/broker/region/DestinationStatistics;
      39: invokevirtual #7                  // Method org/apache/activemq/broker/region/DestinationStatistics.getDequeues:()Lorg/apache/activemq/management/CountStatisticImpl;
      42: aload_0
      43: getfield      #2                  // Field val$ack:Lorg/apache/activemq/command/MessageAck;
      46: invokevirtual #8                  // Method org/apache/activemq/command/MessageAck.getMessageCount:()I
      49: i2l
      50: invokevirtual #9                  // Method org/apache/activemq/management/CountStatisticImpl.add:(J)V
      53: aload_1
      54: monitorexit
      55: goto          63
      58: astore_2
      59: aload_1
      60: monitorexit
      61: aload_2
      62: athrow
      63: aload_0
      64: getfield      #1                  // Field this$0:Lorg/apache/activemq/broker/region/TopicSubscription;
      67: invokestatic  #10                 // Method org/apache/activemq/broker/region/TopicSubscription.access$000:(Lorg/apache/activemq/broker/region/TopicSubscription;)Ljava/util/concurrent/atomic/AtomicLong;
      70: aload_0
      71: getfield      #2                  // Field val$ack:Lorg/apache/activemq/command/MessageAck;
      74: invokevirtual #8                  // Method org/apache/activemq/command/MessageAck.getMessageCount:()I
      77: i2l
      78: invokevirtual #11                 // Method java/util/concurrent/atomic/AtomicLong.addAndGet:(J)J
      81: pop2
      82: aload_0
      83: getfield      #1                  // Field this$0:Lorg/apache/activemq/broker/region/TopicSubscription;
      86: invokestatic  #12                 // Method org/apache/activemq/broker/region/TopicSubscription.access$100:(Lorg/apache/activemq/broker/region/TopicSubscription;)V
      89: return
    Exception table:
       from    to  target type
           7    55    58   any
          58    61    58   any
}
