Compiled from "TopicRegion.java"
class org.apache.activemq.broker.region.TopicRegion$1 extends java.util.TimerTask {
  final org.apache.activemq.broker.region.TopicRegion this$0;

  org.apache.activemq.broker.region.TopicRegion$1(org.apache.activemq.broker.region.TopicRegion);
    Code:
       0: aload_0
       1: aload_1
       2: putfield      #1                  // Field this$0:Lorg/apache/activemq/broker/region/TopicRegion;
       5: aload_0
       6: invokespecial #2                  // Method java/util/TimerTask."<init>":()V
       9: return

  public void run();
    Code:
       0: aload_0
       1: getfield      #1                  // Field this$0:Lorg/apache/activemq/broker/region/TopicRegion;
       4: invokevirtual #3                  // Method org/apache/activemq/broker/region/TopicRegion.doCleanup:()V
       7: return
}
