Compiled from "I18nConversionCategory.java"
public final class org.checkerframework.checker.i18nformatter.qual.I18nConversionCategory extends java.lang.Enum<org.checkerframework.checker.i18nformatter.qual.I18nConversionCategory> {
  public static final org.checkerframework.checker.i18nformatter.qual.I18nConversionCategory UNUSED;

  public static final org.checkerframework.checker.i18nformatter.qual.I18nConversionCategory GENERAL;

  public static final org.checkerframework.checker.i18nformatter.qual.I18nConversionCategory DATE;

  public static final org.checkerframework.checker.i18nformatter.qual.I18nConversionCategory NUMBER;

  public final java.lang.Class<? extends java.lang.Object>[] types;

  public final java.lang.String[] strings;

  static org.checkerframework.checker.i18nformatter.qual.I18nConversionCategory[] namedCategories;

  private static final org.checkerframework.checker.i18nformatter.qual.I18nConversionCategory[] $VALUES;

  public static org.checkerframework.checker.i18nformatter.qual.I18nConversionCategory[] values();
    Code:
       0: getstatic     #1                  // Field $VALUES:[Lorg/checkerframework/checker/i18nformatter/qual/I18nConversionCategory;
       3: invokevirtual #2                  // Method "[Lorg/checkerframework/checker/i18nformatter/qual/I18nConversionCategory;".clone:()Ljava/lang/Object;
       6: checkcast     #3                  // class "[Lorg/checkerframework/checker/i18nformatter/qual/I18nConversionCategory;"
       9: areturn

  public static org.checkerframework.checker.i18nformatter.qual.I18nConversionCategory valueOf(java.lang.String);
    Code:
       0: ldc           #4                  // class org/checkerframework/checker/i18nformatter/qual/I18nConversionCategory
       2: aload_0
       3: invokestatic  #5                  // Method java/lang/Enum.valueOf:(Ljava/lang/Class;Ljava/lang/String;)Ljava/lang/Enum;
       6: checkcast     #4                  // class org/checkerframework/checker/i18nformatter/qual/I18nConversionCategory
       9: areturn

  private org.checkerframework.checker.i18nformatter.qual.I18nConversionCategory(java.lang.Class<? extends java.lang.Object>[], java.lang.String[]);
    Code:
       0: aload_0
       1: aload_1
       2: iload_2
       3: invokespecial #6                  // Method java/lang/Enum."<init>":(Ljava/lang/String;I)V
       6: aload_0
       7: aload_3
       8: putfield      #7                  // Field types:[Ljava/lang/Class;
      11: aload_0
      12: aload         4
      14: putfield      #8                  // Field strings:[Ljava/lang/String;
      17: return

  public static org.checkerframework.checker.i18nformatter.qual.I18nConversionCategory stringToI18nConversionCategory(java.lang.String);
    Code:
       0: aload_0
       1: invokevirtual #9                  // Method java/lang/String.toLowerCase:()Ljava/lang/String;
       4: astore_0
       5: getstatic     #10                 // Field namedCategories:[Lorg/checkerframework/checker/i18nformatter/qual/I18nConversionCategory;
       8: astore_1
       9: aload_1
      10: arraylength
      11: istore_2
      12: iconst_0
      13: istore_3
      14: iload_3
      15: iload_2
      16: if_icmpge     77
      19: aload_1
      20: iload_3
      21: aaload
      22: astore        4
      24: aload         4
      26: getfield      #8                  // Field strings:[Ljava/lang/String;
      29: astore        5
      31: aload         5
      33: arraylength
      34: istore        6
      36: iconst_0
      37: istore        7
      39: iload         7
      41: iload         6
      43: if_icmpge     71
      46: aload         5
      48: iload         7
      50: aaload
      51: astore        8
      53: aload         8
      55: aload_0
      56: invokevirtual #11                 // Method java/lang/String.equals:(Ljava/lang/Object;)Z
      59: ifeq          65
      62: aload         4
      64: areturn
      65: iinc          7, 1
      68: goto          39
      71: iinc          3, 1
      74: goto          14
      77: new           #12                 // class java/lang/IllegalArgumentException
      80: dup
      81: new           #13                 // class java/lang/StringBuilder
      84: dup
      85: invokespecial #14                 // Method java/lang/StringBuilder."<init>":()V
      88: ldc           #15                 // String Invalid format type
      90: invokevirtual #16                 // Method java/lang/StringBuilder.append:(Ljava/lang/String;)Ljava/lang/StringBuilder;
      93: aload_0
      94: invokevirtual #16                 // Method java/lang/StringBuilder.append:(Ljava/lang/String;)Ljava/lang/StringBuilder;
      97: invokevirtual #17                 // Method java/lang/StringBuilder.toString:()Ljava/lang/String;
     100: invokespecial #18                 // Method java/lang/IllegalArgumentException."<init>":(Ljava/lang/String;)V
     103: athrow

  private static <E> java.util.Set<E> arrayToSet(E[]);
    Code:
       0: new           #19                 // class java/util/HashSet
       3: dup
       4: aload_0
       5: invokestatic  #20                 // Method java/util/Arrays.asList:([Ljava/lang/Object;)Ljava/util/List;
       8: invokespecial #21                 // Method java/util/HashSet."<init>":(Ljava/util/Collection;)V
      11: areturn

  public static boolean isSubsetOf(org.checkerframework.checker.i18nformatter.qual.I18nConversionCategory, org.checkerframework.checker.i18nformatter.qual.I18nConversionCategory);
    Code:
       0: aload_0
       1: aload_1
       2: invokestatic  #22                 // Method intersect:(Lorg/checkerframework/checker/i18nformatter/qual/I18nConversionCategory;Lorg/checkerframework/checker/i18nformatter/qual/I18nConversionCategory;)Lorg/checkerframework/checker/i18nformatter/qual/I18nConversionCategory;
       5: aload_0
       6: if_acmpne     13
       9: iconst_1
      10: goto          14
      13: iconst_0
      14: ireturn

  public static org.checkerframework.checker.i18nformatter.qual.I18nConversionCategory intersect(org.checkerframework.checker.i18nformatter.qual.I18nConversionCategory, org.checkerframework.checker.i18nformatter.qual.I18nConversionCategory);
    Code:
       0: aload_0
       1: getstatic     #23                 // Field UNUSED:Lorg/checkerframework/checker/i18nformatter/qual/I18nConversionCategory;
       4: if_acmpne     9
       7: aload_1
       8: areturn
       9: aload_1
      10: getstatic     #23                 // Field UNUSED:Lorg/checkerframework/checker/i18nformatter/qual/I18nConversionCategory;
      13: if_acmpne     18
      16: aload_0
      17: areturn
      18: aload_0
      19: getstatic     #24                 // Field GENERAL:Lorg/checkerframework/checker/i18nformatter/qual/I18nConversionCategory;
      22: if_acmpne     27
      25: aload_1
      26: areturn
      27: aload_1
      28: getstatic     #24                 // Field GENERAL:Lorg/checkerframework/checker/i18nformatter/qual/I18nConversionCategory;
      31: if_acmpne     36
      34: aload_0
      35: areturn
      36: aload_0
      37: getfield      #7                  // Field types:[Ljava/lang/Class;
      40: invokestatic  #25                 // Method arrayToSet:([Ljava/lang/Object;)Ljava/util/Set;
      43: astore_2
      44: aload_1
      45: getfield      #7                  // Field types:[Ljava/lang/Class;
      48: invokestatic  #25                 // Method arrayToSet:([Ljava/lang/Object;)Ljava/util/Set;
      51: astore_3
      52: aload_2
      53: aload_3
      54: invokeinterface #26,  2           // InterfaceMethod java/util/Set.retainAll:(Ljava/util/Collection;)Z
      59: pop
      60: iconst_2
      61: anewarray     #4                  // class org/checkerframework/checker/i18nformatter/qual/I18nConversionCategory
      64: dup
      65: iconst_0
      66: getstatic     #27                 // Field DATE:Lorg/checkerframework/checker/i18nformatter/qual/I18nConversionCategory;
      69: aastore
      70: dup
      71: iconst_1
      72: getstatic     #28                 // Field NUMBER:Lorg/checkerframework/checker/i18nformatter/qual/I18nConversionCategory;
      75: aastore
      76: astore        4
      78: aload         4
      80: arraylength
      81: istore        5
      83: iconst_0
      84: istore        6
      86: iload         6
      88: iload         5
      90: if_icmpge     130
      93: aload         4
      95: iload         6
      97: aaload
      98: astore        7
     100: aload         7
     102: getfield      #7                  // Field types:[Ljava/lang/Class;
     105: invokestatic  #25                 // Method arrayToSet:([Ljava/lang/Object;)Ljava/util/Set;
     108: astore        8
     110: aload         8
     112: aload_2
     113: invokeinterface #29,  2           // InterfaceMethod java/util/Set.equals:(Ljava/lang/Object;)Z
     118: ifeq          124
     121: aload         7
     123: areturn
     124: iinc          6, 1
     127: goto          86
     130: new           #30                 // class java/lang/RuntimeException
     133: dup
     134: invokespecial #31                 // Method java/lang/RuntimeException."<init>":()V
     137: athrow

  public static org.checkerframework.checker.i18nformatter.qual.I18nConversionCategory union(org.checkerframework.checker.i18nformatter.qual.I18nConversionCategory, org.checkerframework.checker.i18nformatter.qual.I18nConversionCategory);
    Code:
       0: aload_0
       1: getstatic     #23                 // Field UNUSED:Lorg/checkerframework/checker/i18nformatter/qual/I18nConversionCategory;
       4: if_acmpeq     14
       7: aload_1
       8: getstatic     #23                 // Field UNUSED:Lorg/checkerframework/checker/i18nformatter/qual/I18nConversionCategory;
      11: if_acmpne     18
      14: getstatic     #23                 // Field UNUSED:Lorg/checkerframework/checker/i18nformatter/qual/I18nConversionCategory;
      17: areturn
      18: aload_0
      19: getstatic     #24                 // Field GENERAL:Lorg/checkerframework/checker/i18nformatter/qual/I18nConversionCategory;
      22: if_acmpeq     32
      25: aload_1
      26: getstatic     #24                 // Field GENERAL:Lorg/checkerframework/checker/i18nformatter/qual/I18nConversionCategory;
      29: if_acmpne     36
      32: getstatic     #24                 // Field GENERAL:Lorg/checkerframework/checker/i18nformatter/qual/I18nConversionCategory;
      35: areturn
      36: aload_0
      37: getstatic     #27                 // Field DATE:Lorg/checkerframework/checker/i18nformatter/qual/I18nConversionCategory;
      40: if_acmpeq     50
      43: aload_1
      44: getstatic     #27                 // Field DATE:Lorg/checkerframework/checker/i18nformatter/qual/I18nConversionCategory;
      47: if_acmpne     54
      50: getstatic     #27                 // Field DATE:Lorg/checkerframework/checker/i18nformatter/qual/I18nConversionCategory;
      53: areturn
      54: getstatic     #28                 // Field NUMBER:Lorg/checkerframework/checker/i18nformatter/qual/I18nConversionCategory;
      57: areturn

  public java.lang.String toString();
    Code:
       0: new           #13                 // class java/lang/StringBuilder
       3: dup
       4: aload_0
       5: invokevirtual #32                 // Method name:()Ljava/lang/String;
       8: invokespecial #33                 // Method java/lang/StringBuilder."<init>":(Ljava/lang/String;)V
      11: astore_1
      12: aload_0
      13: getfield      #7                  // Field types:[Ljava/lang/Class;
      16: ifnonnull     29
      19: aload_1
      20: ldc           #34                 // String  conversion category (all types)
      22: invokevirtual #16                 // Method java/lang/StringBuilder.append:(Ljava/lang/String;)Ljava/lang/StringBuilder;
      25: pop
      26: goto          99
      29: aload_1
      30: ldc           #35                 // String  conversion category (one of:
      32: invokevirtual #16                 // Method java/lang/StringBuilder.append:(Ljava/lang/String;)Ljava/lang/StringBuilder;
      35: pop
      36: iconst_1
      37: istore_2
      38: aload_0
      39: getfield      #7                  // Field types:[Ljava/lang/Class;
      42: astore_3
      43: aload_3
      44: arraylength
      45: istore        4
      47: iconst_0
      48: istore        5
      50: iload         5
      52: iload         4
      54: if_icmpge     92
      57: aload_3
      58: iload         5
      60: aaload
      61: astore        6
      63: iload_2
      64: ifne          74
      67: aload_1
      68: ldc           #36                 // String ,
      70: invokevirtual #16                 // Method java/lang/StringBuilder.append:(Ljava/lang/String;)Ljava/lang/StringBuilder;
      73: pop
      74: aload_1
      75: aload         6
      77: invokevirtual #37                 // Method java/lang/Class.getCanonicalName:()Ljava/lang/String;
      80: invokevirtual #16                 // Method java/lang/StringBuilder.append:(Ljava/lang/String;)Ljava/lang/StringBuilder;
      83: pop
      84: iconst_0
      85: istore_2
      86: iinc          5, 1
      89: goto          50
      92: aload_1
      93: ldc           #38                 // String )
      95: invokevirtual #16                 // Method java/lang/StringBuilder.append:(Ljava/lang/String;)Ljava/lang/StringBuilder;
      98: pop
      99: aload_1
     100: invokevirtual #17                 // Method java/lang/StringBuilder.toString:()Ljava/lang/String;
     103: areturn

  static {};
    Code:
       0: new           #4                  // class org/checkerframework/checker/i18nformatter/qual/I18nConversionCategory
       3: dup
       4: ldc           #39                 // String UNUSED
       6: iconst_0
       7: aconst_null
       8: aconst_null
       9: invokespecial #40                 // Method "<init>":(Ljava/lang/String;I[Ljava/lang/Class;[Ljava/lang/String;)V
      12: putstatic     #23                 // Field UNUSED:Lorg/checkerframework/checker/i18nformatter/qual/I18nConversionCategory;
      15: new           #4                  // class org/checkerframework/checker/i18nformatter/qual/I18nConversionCategory
      18: dup
      19: ldc           #41                 // String GENERAL
      21: iconst_1
      22: aconst_null
      23: aconst_null
      24: invokespecial #40                 // Method "<init>":(Ljava/lang/String;I[Ljava/lang/Class;[Ljava/lang/String;)V
      27: putstatic     #24                 // Field GENERAL:Lorg/checkerframework/checker/i18nformatter/qual/I18nConversionCategory;
      30: new           #4                  // class org/checkerframework/checker/i18nformatter/qual/I18nConversionCategory
      33: dup
      34: ldc           #42                 // String DATE
      36: iconst_2
      37: iconst_2
      38: anewarray     #43                 // class java/lang/Class
      41: dup
      42: iconst_0
      43: ldc           #44                 // class java/util/Date
      45: aastore
      46: dup
      47: iconst_1
      48: ldc           #45                 // class java/lang/Number
      50: aastore
      51: iconst_2
      52: anewarray     #46                 // class java/lang/String
      55: dup
      56: iconst_0
      57: ldc           #47                 // String date
      59: aastore
      60: dup
      61: iconst_1
      62: ldc           #48                 // String time
      64: aastore
      65: invokespecial #40                 // Method "<init>":(Ljava/lang/String;I[Ljava/lang/Class;[Ljava/lang/String;)V
      68: putstatic     #27                 // Field DATE:Lorg/checkerframework/checker/i18nformatter/qual/I18nConversionCategory;
      71: new           #4                  // class org/checkerframework/checker/i18nformatter/qual/I18nConversionCategory
      74: dup
      75: ldc           #49                 // String NUMBER
      77: iconst_3
      78: iconst_1
      79: anewarray     #43                 // class java/lang/Class
      82: dup
      83: iconst_0
      84: ldc           #45                 // class java/lang/Number
      86: aastore
      87: iconst_2
      88: anewarray     #46                 // class java/lang/String
      91: dup
      92: iconst_0
      93: ldc           #50                 // String number
      95: aastore
      96: dup
      97: iconst_1
      98: ldc           #51                 // String choice
     100: aastore
     101: invokespecial #40                 // Method "<init>":(Ljava/lang/String;I[Ljava/lang/Class;[Ljava/lang/String;)V
     104: putstatic     #28                 // Field NUMBER:Lorg/checkerframework/checker/i18nformatter/qual/I18nConversionCategory;
     107: iconst_4
     108: anewarray     #4                  // class org/checkerframework/checker/i18nformatter/qual/I18nConversionCategory
     111: dup
     112: iconst_0
     113: getstatic     #23                 // Field UNUSED:Lorg/checkerframework/checker/i18nformatter/qual/I18nConversionCategory;
     116: aastore
     117: dup
     118: iconst_1
     119: getstatic     #24                 // Field GENERAL:Lorg/checkerframework/checker/i18nformatter/qual/I18nConversionCategory;
     122: aastore
     123: dup
     124: iconst_2
     125: getstatic     #27                 // Field DATE:Lorg/checkerframework/checker/i18nformatter/qual/I18nConversionCategory;
     128: aastore
     129: dup
     130: iconst_3
     131: getstatic     #28                 // Field NUMBER:Lorg/checkerframework/checker/i18nformatter/qual/I18nConversionCategory;
     134: aastore
     135: putstatic     #1                  // Field $VALUES:[Lorg/checkerframework/checker/i18nformatter/qual/I18nConversionCategory;
     138: iconst_2
     139: anewarray     #4                  // class org/checkerframework/checker/i18nformatter/qual/I18nConversionCategory
     142: dup
     143: iconst_0
     144: getstatic     #27                 // Field DATE:Lorg/checkerframework/checker/i18nformatter/qual/I18nConversionCategory;
     147: aastore
     148: dup
     149: iconst_1
     150: getstatic     #28                 // Field NUMBER:Lorg/checkerframework/checker/i18nformatter/qual/I18nConversionCategory;
     153: aastore
     154: putstatic     #10                 // Field namedCategories:[Lorg/checkerframework/checker/i18nformatter/qual/I18nConversionCategory;
     157: return
}
