Compiled from "AnnotationConfiguration.java"
public class com.fasterxml.classmate.AnnotationConfiguration$StdConfiguration extends com.fasterxml.classmate.AnnotationConfiguration implements java.io.Serializable {
  protected final com.fasterxml.classmate.AnnotationInclusion _defaultInclusion;

  protected final java.util.HashMap<com.fasterxml.classmate.util.ClassKey, com.fasterxml.classmate.AnnotationInclusion> _inclusions;

  public com.fasterxml.classmate.AnnotationConfiguration$StdConfiguration(com.fasterxml.classmate.AnnotationInclusion);
    Code:
       0: aload_0
       1: invokespecial #1                  // Method com/fasterxml/classmate/AnnotationConfiguration."<init>":()V
       4: aload_0
       5: new           #2                  // class java/util/HashMap
       8: dup
       9: invokespecial #3                  // Method java/util/HashMap."<init>":()V
      12: putfield      #4                  // Field _inclusions:Ljava/util/HashMap;
      15: aload_0
      16: aload_1
      17: putfield      #5                  // Field _defaultInclusion:Lcom/fasterxml/classmate/AnnotationInclusion;
      20: return

  public com.fasterxml.classmate.AnnotationInclusion getInclusionForClass(java.lang.Class<? extends java.lang.annotation.Annotation>);
    Code:
       0: aload_0
       1: aload_1
       2: invokevirtual #6                  // Method _inclusionFor:(Ljava/lang/Class;)Lcom/fasterxml/classmate/AnnotationInclusion;
       5: areturn

  public com.fasterxml.classmate.AnnotationInclusion getInclusionForConstructor(java.lang.Class<? extends java.lang.annotation.Annotation>);
    Code:
       0: aload_0
       1: aload_1
       2: invokevirtual #6                  // Method _inclusionFor:(Ljava/lang/Class;)Lcom/fasterxml/classmate/AnnotationInclusion;
       5: areturn

  public com.fasterxml.classmate.AnnotationInclusion getInclusionForField(java.lang.Class<? extends java.lang.annotation.Annotation>);
    Code:
       0: aload_0
       1: aload_1
       2: invokevirtual #7                  // Method getInclusionForClass:(Ljava/lang/Class;)Lcom/fasterxml/classmate/AnnotationInclusion;
       5: areturn

  public com.fasterxml.classmate.AnnotationInclusion getInclusionForMethod(java.lang.Class<? extends java.lang.annotation.Annotation>);
    Code:
       0: aload_0
       1: aload_1
       2: invokevirtual #7                  // Method getInclusionForClass:(Ljava/lang/Class;)Lcom/fasterxml/classmate/AnnotationInclusion;
       5: areturn

  public com.fasterxml.classmate.AnnotationInclusion getInclusionForParameter(java.lang.Class<? extends java.lang.annotation.Annotation>);
    Code:
       0: aload_0
       1: aload_1
       2: invokevirtual #7                  // Method getInclusionForClass:(Ljava/lang/Class;)Lcom/fasterxml/classmate/AnnotationInclusion;
       5: areturn

  public void setInclusion(java.lang.Class<? extends java.lang.annotation.Annotation>, com.fasterxml.classmate.AnnotationInclusion);
    Code:
       0: aload_0
       1: getfield      #4                  // Field _inclusions:Ljava/util/HashMap;
       4: new           #8                  // class com/fasterxml/classmate/util/ClassKey
       7: dup
       8: aload_1
       9: invokespecial #9                  // Method com/fasterxml/classmate/util/ClassKey."<init>":(Ljava/lang/Class;)V
      12: aload_2
      13: invokevirtual #10                 // Method java/util/HashMap.put:(Ljava/lang/Object;Ljava/lang/Object;)Ljava/lang/Object;
      16: pop
      17: return

  protected com.fasterxml.classmate.AnnotationInclusion _inclusionFor(java.lang.Class<? extends java.lang.annotation.Annotation>);
    Code:
       0: new           #8                  // class com/fasterxml/classmate/util/ClassKey
       3: dup
       4: aload_1
       5: invokespecial #9                  // Method com/fasterxml/classmate/util/ClassKey."<init>":(Ljava/lang/Class;)V
       8: astore_2
       9: aload_0
      10: getfield      #4                  // Field _inclusions:Ljava/util/HashMap;
      13: aload_2
      14: invokevirtual #11                 // Method java/util/HashMap.get:(Ljava/lang/Object;)Ljava/lang/Object;
      17: checkcast     #12                 // class com/fasterxml/classmate/AnnotationInclusion
      20: astore_3
      21: aload_3
      22: ifnonnull     32
      25: aload_0
      26: getfield      #5                  // Field _defaultInclusion:Lcom/fasterxml/classmate/AnnotationInclusion;
      29: goto          33
      32: aload_3
      33: areturn
}
