Compiled from "OperationPolicy.java"
public class org.apache.wss4j.policy.stax.OperationPolicy {
  private javax.xml.namespace.QName operationName;

  private java.lang.String operationAction;

  private org.apache.neethi.Policy policy;

  private java.lang.String soapMessageVersionNamespace;

  public org.apache.wss4j.policy.stax.OperationPolicy(javax.xml.namespace.QName);
    Code:
       0: aload_0
       1: invokespecial #1                  // Method java/lang/Object."<init>":()V
       4: aload_0
       5: aload_1
       6: putfield      #2                  // Field operationName:Ljavax/xml/namespace/QName;
       9: return

  public javax.xml.namespace.QName getOperationName();
    Code:
       0: aload_0
       1: getfield      #2                  // Field operationName:Ljavax/xml/namespace/QName;
       4: areturn

  public void setOperationName(javax.xml.namespace.QName);
    Code:
       0: aload_0
       1: aload_1
       2: putfield      #2                  // Field operationName:Ljavax/xml/namespace/QName;
       5: return

  public java.lang.String getOperationAction();
    Code:
       0: aload_0
       1: getfield      #3                  // Field operationAction:Ljava/lang/String;
       4: areturn

  public void setOperationAction(java.lang.String);
    Code:
       0: aload_0
       1: aload_1
       2: putfield      #3                  // Field operationAction:Ljava/lang/String;
       5: return

  public org.apache.neethi.Policy getPolicy();
    Code:
       0: aload_0
       1: getfield      #4                  // Field policy:Lorg/apache/neethi/Policy;
       4: areturn

  public void setPolicy(org.apache.neethi.Policy);
    Code:
       0: aload_0
       1: aload_1
       2: putfield      #4                  // Field policy:Lorg/apache/neethi/Policy;
       5: return

  public java.lang.String getSoapMessageVersionNamespace();
    Code:
       0: aload_0
       1: getfield      #5                  // Field soapMessageVersionNamespace:Ljava/lang/String;
       4: areturn

  public void setSoapMessageVersionNamespace(java.lang.String);
    Code:
       0: aload_0
       1: aload_1
       2: putfield      #5                  // Field soapMessageVersionNamespace:Ljava/lang/String;
       5: return

  public boolean equals(java.lang.Object);
    Code:
       0: aload_1
       1: instanceof    #6                  // class org/apache/wss4j/policy/stax/OperationPolicy
       4: ifne          9
       7: iconst_0
       8: ireturn
       9: aload_1
      10: checkcast     #6                  // class org/apache/wss4j/policy/stax/OperationPolicy
      13: astore_2
      14: aload_0
      15: invokevirtual #7                  // Method getOperationName:()Ljavax/xml/namespace/QName;
      18: aload_2
      19: invokevirtual #7                  // Method getOperationName:()Ljavax/xml/namespace/QName;
      22: invokevirtual #8                  // Method javax/xml/namespace/QName.equals:(Ljava/lang/Object;)Z
      25: ireturn

  public int hashCode();
    Code:
       0: bipush        17
       2: istore_1
       3: aload_0
       4: invokevirtual #7                  // Method getOperationName:()Ljavax/xml/namespace/QName;
       7: ifnull        23
      10: iload_1
      11: bipush        31
      13: aload_0
      14: invokevirtual #7                  // Method getOperationName:()Ljavax/xml/namespace/QName;
      17: invokevirtual #9                  // Method javax/xml/namespace/QName.hashCode:()I
      20: imul
      21: imul
      22: istore_1
      23: iload_1
      24: ireturn
}
