Compiled from "CompilingClassLoader.java"
public class com.google.common.truth.codegen.CompilingClassLoader extends java.lang.ClassLoader {
  private final java.util.Map<java.lang.String, java.io.ByteArrayOutputStream> byteCodeForClasses;

  private static final java.net.URI EMPTY_URI;

  public com.google.common.truth.codegen.CompilingClassLoader(java.lang.ClassLoader, java.lang.String, java.lang.String, javax.tools.DiagnosticListener<javax.tools.JavaFileObject>) throws com.google.common.truth.codegen.CompilingClassLoader$CompilerException;
    Code:
       0: aload_0
       1: aload_1
       2: invokespecial #3                  // Method java/lang/ClassLoader."<init>":(Ljava/lang/ClassLoader;)V
       5: aload_0
       6: new           #4                  // class java/util/HashMap
       9: dup
      10: invokespecial #5                  // Method java/util/HashMap."<init>":()V
      13: putfield      #1                  // Field byteCodeForClasses:Ljava/util/Map;
      16: aload_0
      17: aload_2
      18: aload_3
      19: aload         4
      21: invokespecial #6                  // Method compileSourceCodeToByteCode:(Ljava/lang/String;Ljava/lang/String;Ljavax/tools/DiagnosticListener;)Z
      24: ifne          54
      27: new           #7                  // class com/google/common/truth/codegen/CompilingClassLoader$CompilerException
      30: dup
      31: new           #8                  // class java/lang/StringBuilder
      34: dup
      35: invokespecial #9                  // Method java/lang/StringBuilder."<init>":()V
      38: ldc           #10                 // String Could not compile
      40: invokevirtual #11                 // Method java/lang/StringBuilder.append:(Ljava/lang/String;)Ljava/lang/StringBuilder;
      43: aload_2
      44: invokevirtual #11                 // Method java/lang/StringBuilder.append:(Ljava/lang/String;)Ljava/lang/StringBuilder;
      47: invokevirtual #12                 // Method java/lang/StringBuilder.toString:()Ljava/lang/String;
      50: invokespecial #13                 // Method com/google/common/truth/codegen/CompilingClassLoader$CompilerException."<init>":(Ljava/lang/String;)V
      53: athrow
      54: return

  public java.lang.Class<?> findClass(java.lang.String) throws java.lang.ClassNotFoundException;
    Code:
       0: aload_0
       1: getfield      #1                  // Field byteCodeForClasses:Ljava/util/Map;
       4: aload_1
       5: invokeinterface #14,  2           // InterfaceMethod java/util/Map.get:(Ljava/lang/Object;)Ljava/lang/Object;
      10: checkcast     #15                 // class java/io/ByteArrayOutputStream
      13: astore_2
      14: aload_2
      15: ifnonnull     27
      18: new           #16                 // class java/lang/ClassNotFoundException
      21: dup
      22: aload_1
      23: invokespecial #17                 // Method java/lang/ClassNotFoundException."<init>":(Ljava/lang/String;)V
      26: athrow
      27: aload_0
      28: aload_1
      29: aload_2
      30: invokevirtual #18                 // Method java/io/ByteArrayOutputStream.toByteArray:()[B
      33: iconst_0
      34: aload_2
      35: invokevirtual #19                 // Method java/io/ByteArrayOutputStream.size:()I
      38: invokevirtual #20                 // Method defineClass:(Ljava/lang/String;[BII)Ljava/lang/Class;
      41: areturn

  private boolean compileSourceCodeToByteCode(java.lang.String, java.lang.String, javax.tools.DiagnosticListener<javax.tools.JavaFileObject>);
    Code:
       0: invokestatic  #21                 // Method javax/tools/ToolProvider.getSystemJavaCompiler:()Ljavax/tools/JavaCompiler;
       3: astore        4
       5: new           #22                 // class com/google/common/truth/codegen/CompilingClassLoader$InMemoryFileManager
       8: dup
       9: aload_0
      10: aload         4
      12: aconst_null
      13: aconst_null
      14: aconst_null
      15: invokeinterface #23,  4           // InterfaceMethod javax/tools/JavaCompiler.getStandardFileManager:(Ljavax/tools/DiagnosticListener;Ljava/util/Locale;Ljava/nio/charset/Charset;)Ljavax/tools/StandardJavaFileManager;
      20: invokespecial #24                 // Method com/google/common/truth/codegen/CompilingClassLoader$InMemoryFileManager."<init>":(Lcom/google/common/truth/codegen/CompilingClassLoader;Ljavax/tools/JavaFileManager;)V
      23: astore        5
      25: new           #25                 // class com/google/common/truth/codegen/CompilingClassLoader$InMemoryJavaFile
      28: dup
      29: aload_1
      30: aload_2
      31: invokespecial #26                 // Method com/google/common/truth/codegen/CompilingClassLoader$InMemoryJavaFile."<init>":(Ljava/lang/String;Ljava/lang/String;)V
      34: astore        6
      36: ldc           #27                 // String useJavaUtilZip
      38: ldc           #28                 // String true
      40: invokestatic  #29                 // Method java/lang/System.setProperty:(Ljava/lang/String;Ljava/lang/String;)Ljava/lang/String;
      43: pop
      44: new           #30                 // class java/util/LinkedList
      47: dup
      48: invokespecial #31                 // Method java/util/LinkedList."<init>":()V
      51: astore        7
      53: aload         7
      55: ldc           #32                 // String -XDuseJavaUtilZip
      57: invokeinterface #33,  2           // InterfaceMethod java/util/List.add:(Ljava/lang/Object;)Z
      62: pop
      63: aload         4
      65: aconst_null
      66: aload         5
      68: aload_3
      69: aload         7
      71: aconst_null
      72: aload         6
      74: invokestatic  #34                 // Method java/util/Collections.singleton:(Ljava/lang/Object;)Ljava/util/Set;
      77: invokeinterface #35,  7           // InterfaceMethod javax/tools/JavaCompiler.getTask:(Ljava/io/Writer;Ljavax/tools/JavaFileManager;Ljavax/tools/DiagnosticListener;Ljava/lang/Iterable;Ljava/lang/Iterable;Ljava/lang/Iterable;)Ljavax/tools/JavaCompiler$CompilationTask;
      82: astore        8
      84: aload         8
      86: invokeinterface #36,  1           // InterfaceMethod javax/tools/JavaCompiler$CompilationTask.call:()Ljava/lang/Boolean;
      91: invokevirtual #37                 // Method java/lang/Boolean.booleanValue:()Z
      94: ireturn

  static java.net.URI access$000();
    Code:
       0: getstatic     #2                  // Field EMPTY_URI:Ljava/net/URI;
       3: areturn

  static java.util.Map access$100(com.google.common.truth.codegen.CompilingClassLoader);
    Code:
       0: aload_0
       1: getfield      #1                  // Field byteCodeForClasses:Ljava/util/Map;
       4: areturn

  static {};
    Code:
       0: new           #38                 // class java/net/URI
       3: dup
       4: ldc           #39                 // String
       6: invokespecial #40                 // Method java/net/URI."<init>":(Ljava/lang/String;)V
       9: putstatic     #2                  // Field EMPTY_URI:Ljava/net/URI;
      12: goto          25
      15: astore_0
      16: new           #42                 // class java/lang/Error
      19: dup
      20: aload_0
      21: invokespecial #43                 // Method java/lang/Error."<init>":(Ljava/lang/Throwable;)V
      24: athrow
      25: return
    Exception table:
       from    to  target type
           0    12    15   Class java/net/URISyntaxException
}
