Compiled from "LiteralKind.java"
public final class org.checkerframework.framework.qual.LiteralKind extends java.lang.Enum<org.checkerframework.framework.qual.LiteralKind> {
  public static final org.checkerframework.framework.qual.LiteralKind NULL;

  public static final org.checkerframework.framework.qual.LiteralKind INT;

  public static final org.checkerframework.framework.qual.LiteralKind LONG;

  public static final org.checkerframework.framework.qual.LiteralKind FLOAT;

  public static final org.checkerframework.framework.qual.LiteralKind DOUBLE;

  public static final org.checkerframework.framework.qual.LiteralKind BOOLEAN;

  public static final org.checkerframework.framework.qual.LiteralKind CHAR;

  public static final org.checkerframework.framework.qual.LiteralKind STRING;

  public static final org.checkerframework.framework.qual.LiteralKind ALL;

  public static final org.checkerframework.framework.qual.LiteralKind PRIMITIVE;

  private static final org.checkerframework.framework.qual.LiteralKind[] $VALUES;

  public static org.checkerframework.framework.qual.LiteralKind[] values();
    Code:
       0: getstatic     #1                  // Field $VALUES:[Lorg/checkerframework/framework/qual/LiteralKind;
       3: invokevirtual #2                  // Method "[Lorg/checkerframework/framework/qual/LiteralKind;".clone:()Ljava/lang/Object;
       6: checkcast     #3                  // class "[Lorg/checkerframework/framework/qual/LiteralKind;"
       9: areturn

  public static org.checkerframework.framework.qual.LiteralKind valueOf(java.lang.String);
    Code:
       0: ldc           #4                  // class org/checkerframework/framework/qual/LiteralKind
       2: aload_0
       3: invokestatic  #5                  // Method java/lang/Enum.valueOf:(Ljava/lang/Class;Ljava/lang/String;)Ljava/lang/Enum;
       6: checkcast     #4                  // class org/checkerframework/framework/qual/LiteralKind
       9: areturn

  private org.checkerframework.framework.qual.LiteralKind();
    Code:
       0: aload_0
       1: aload_1
       2: iload_2
       3: invokespecial #6                  // Method java/lang/Enum."<init>":(Ljava/lang/String;I)V
       6: return

  public static java.util.List<org.checkerframework.framework.qual.LiteralKind> allLiteralKinds();
    Code:
       0: new           #7                  // class java/util/ArrayList
       3: dup
       4: invokestatic  #8                  // Method values:()[Lorg/checkerframework/framework/qual/LiteralKind;
       7: invokestatic  #9                  // Method java/util/Arrays.asList:([Ljava/lang/Object;)Ljava/util/List;
      10: invokespecial #10                 // Method java/util/ArrayList."<init>":(Ljava/util/Collection;)V
      13: astore_0
      14: aload_0
      15: getstatic     #11                 // Field ALL:Lorg/checkerframework/framework/qual/LiteralKind;
      18: invokeinterface #12,  2           // InterfaceMethod java/util/List.remove:(Ljava/lang/Object;)Z
      23: pop
      24: aload_0
      25: getstatic     #13                 // Field PRIMITIVE:Lorg/checkerframework/framework/qual/LiteralKind;
      28: invokeinterface #12,  2           // InterfaceMethod java/util/List.remove:(Ljava/lang/Object;)Z
      33: pop
      34: aload_0
      35: areturn

  public static java.util.List<org.checkerframework.framework.qual.LiteralKind> primitiveLiteralKinds();
    Code:
       0: bipush        6
       2: anewarray     #4                  // class org/checkerframework/framework/qual/LiteralKind
       5: dup
       6: iconst_0
       7: getstatic     #14                 // Field INT:Lorg/checkerframework/framework/qual/LiteralKind;
      10: aastore
      11: dup
      12: iconst_1
      13: getstatic     #15                 // Field LONG:Lorg/checkerframework/framework/qual/LiteralKind;
      16: aastore
      17: dup
      18: iconst_2
      19: getstatic     #16                 // Field FLOAT:Lorg/checkerframework/framework/qual/LiteralKind;
      22: aastore
      23: dup
      24: iconst_3
      25: getstatic     #17                 // Field DOUBLE:Lorg/checkerframework/framework/qual/LiteralKind;
      28: aastore
      29: dup
      30: iconst_4
      31: getstatic     #18                 // Field BOOLEAN:Lorg/checkerframework/framework/qual/LiteralKind;
      34: aastore
      35: dup
      36: iconst_5
      37: getstatic     #19                 // Field CHAR:Lorg/checkerframework/framework/qual/LiteralKind;
      40: aastore
      41: invokestatic  #9                  // Method java/util/Arrays.asList:([Ljava/lang/Object;)Ljava/util/List;
      44: areturn

  static {};
    Code:
       0: new           #4                  // class org/checkerframework/framework/qual/LiteralKind
       3: dup
       4: ldc           #20                 // String NULL
       6: iconst_0
       7: invokespecial #21                 // Method "<init>":(Ljava/lang/String;I)V
      10: putstatic     #22                 // Field NULL:Lorg/checkerframework/framework/qual/LiteralKind;
      13: new           #4                  // class org/checkerframework/framework/qual/LiteralKind
      16: dup
      17: ldc           #23                 // String INT
      19: iconst_1
      20: invokespecial #21                 // Method "<init>":(Ljava/lang/String;I)V
      23: putstatic     #14                 // Field INT:Lorg/checkerframework/framework/qual/LiteralKind;
      26: new           #4                  // class org/checkerframework/framework/qual/LiteralKind
      29: dup
      30: ldc           #24                 // String LONG
      32: iconst_2
      33: invokespecial #21                 // Method "<init>":(Ljava/lang/String;I)V
      36: putstatic     #15                 // Field LONG:Lorg/checkerframework/framework/qual/LiteralKind;
      39: new           #4                  // class org/checkerframework/framework/qual/LiteralKind
      42: dup
      43: ldc           #25                 // String FLOAT
      45: iconst_3
      46: invokespecial #21                 // Method "<init>":(Ljava/lang/String;I)V
      49: putstatic     #16                 // Field FLOAT:Lorg/checkerframework/framework/qual/LiteralKind;
      52: new           #4                  // class org/checkerframework/framework/qual/LiteralKind
      55: dup
      56: ldc           #26                 // String DOUBLE
      58: iconst_4
      59: invokespecial #21                 // Method "<init>":(Ljava/lang/String;I)V
      62: putstatic     #17                 // Field DOUBLE:Lorg/checkerframework/framework/qual/LiteralKind;
      65: new           #4                  // class org/checkerframework/framework/qual/LiteralKind
      68: dup
      69: ldc           #27                 // String BOOLEAN
      71: iconst_5
      72: invokespecial #21                 // Method "<init>":(Ljava/lang/String;I)V
      75: putstatic     #18                 // Field BOOLEAN:Lorg/checkerframework/framework/qual/LiteralKind;
      78: new           #4                  // class org/checkerframework/framework/qual/LiteralKind
      81: dup
      82: ldc           #28                 // String CHAR
      84: bipush        6
      86: invokespecial #21                 // Method "<init>":(Ljava/lang/String;I)V
      89: putstatic     #19                 // Field CHAR:Lorg/checkerframework/framework/qual/LiteralKind;
      92: new           #4                  // class org/checkerframework/framework/qual/LiteralKind
      95: dup
      96: ldc           #29                 // String STRING
      98: bipush        7
     100: invokespecial #21                 // Method "<init>":(Ljava/lang/String;I)V
     103: putstatic     #30                 // Field STRING:Lorg/checkerframework/framework/qual/LiteralKind;
     106: new           #4                  // class org/checkerframework/framework/qual/LiteralKind
     109: dup
     110: ldc           #31                 // String ALL
     112: bipush        8
     114: invokespecial #21                 // Method "<init>":(Ljava/lang/String;I)V
     117: putstatic     #11                 // Field ALL:Lorg/checkerframework/framework/qual/LiteralKind;
     120: new           #4                  // class org/checkerframework/framework/qual/LiteralKind
     123: dup
     124: ldc           #32                 // String PRIMITIVE
     126: bipush        9
     128: invokespecial #21                 // Method "<init>":(Ljava/lang/String;I)V
     131: putstatic     #13                 // Field PRIMITIVE:Lorg/checkerframework/framework/qual/LiteralKind;
     134: bipush        10
     136: anewarray     #4                  // class org/checkerframework/framework/qual/LiteralKind
     139: dup
     140: iconst_0
     141: getstatic     #22                 // Field NULL:Lorg/checkerframework/framework/qual/LiteralKind;
     144: aastore
     145: dup
     146: iconst_1
     147: getstatic     #14                 // Field INT:Lorg/checkerframework/framework/qual/LiteralKind;
     150: aastore
     151: dup
     152: iconst_2
     153: getstatic     #15                 // Field LONG:Lorg/checkerframework/framework/qual/LiteralKind;
     156: aastore
     157: dup
     158: iconst_3
     159: getstatic     #16                 // Field FLOAT:Lorg/checkerframework/framework/qual/LiteralKind;
     162: aastore
     163: dup
     164: iconst_4
     165: getstatic     #17                 // Field DOUBLE:Lorg/checkerframework/framework/qual/LiteralKind;
     168: aastore
     169: dup
     170: iconst_5
     171: getstatic     #18                 // Field BOOLEAN:Lorg/checkerframework/framework/qual/LiteralKind;
     174: aastore
     175: dup
     176: bipush        6
     178: getstatic     #19                 // Field CHAR:Lorg/checkerframework/framework/qual/LiteralKind;
     181: aastore
     182: dup
     183: bipush        7
     185: getstatic     #30                 // Field STRING:Lorg/checkerframework/framework/qual/LiteralKind;
     188: aastore
     189: dup
     190: bipush        8
     192: getstatic     #11                 // Field ALL:Lorg/checkerframework/framework/qual/LiteralKind;
     195: aastore
     196: dup
     197: bipush        9
     199: getstatic     #13                 // Field PRIMITIVE:Lorg/checkerframework/framework/qual/LiteralKind;
     202: aastore
     203: putstatic     #1                  // Field $VALUES:[Lorg/checkerframework/framework/qual/LiteralKind;
     206: return
}
