Compiled from "ASTNode.java"
public abstract class org.eclipse.jdt.internal.compiler.ast.ASTNode implements org.eclipse.jdt.internal.compiler.lookup.TypeConstants,org.eclipse.jdt.internal.compiler.lookup.TypeIds {
  public int sourceStart;

  public int sourceEnd;

  public static final int Bit1;

  public static final int Bit2;

  public static final int Bit3;

  public static final int Bit4;

  public static final int Bit5;

  public static final int Bit6;

  public static final int Bit7;

  public static final int Bit8;

  public static final int Bit9;

  public static final int Bit10;

  public static final int Bit11;

  public static final int Bit12;

  public static final int Bit13;

  public static final int Bit14;

  public static final int Bit15;

  public static final int Bit16;

  public static final int Bit17;

  public static final int Bit18;

  public static final int Bit19;

  public static final int Bit20;

  public static final int Bit21;

  public static final int Bit22;

  public static final int Bit23;

  public static final int Bit24;

  public static final int Bit25;

  public static final int Bit26;

  public static final int Bit27;

  public static final int Bit28;

  public static final int Bit29;

  public static final int Bit30;

  public static final int Bit31;

  public static final int Bit32;

  public static final long Bit32L;

  public static final long Bit33L;

  public static final long Bit34L;

  public static final long Bit35L;

  public static final long Bit36L;

  public static final long Bit37L;

  public static final long Bit38L;

  public static final long Bit39L;

  public static final long Bit40L;

  public static final long Bit41L;

  public static final long Bit42L;

  public static final long Bit43L;

  public static final long Bit44L;

  public static final long Bit45L;

  public static final long Bit46L;

  public static final long Bit47L;

  public static final long Bit48L;

  public static final long Bit49L;

  public static final long Bit50L;

  public static final long Bit51L;

  public static final long Bit52L;

  public static final long Bit53L;

  public static final long Bit54L;

  public static final long Bit55L;

  public static final long Bit56L;

  public static final long Bit57L;

  public static final long Bit58L;

  public static final long Bit59L;

  public static final long Bit60L;

  public static final long Bit61L;

  public static final long Bit62L;

  public static final long Bit63L;

  public static final long Bit64L;

  public int bits;

  public static final int ReturnTypeIDMASK;

  public static final int OperatorSHIFT;

  public static final int OperatorMASK;

  public static final int IsReturnedValue;

  public static final int UnnecessaryCast;

  public static final int DisableUnnecessaryCastCheck;

  public static final int GenerateCheckcast;

  public static final int UnsafeCast;

  public static final int RestrictiveFlagMASK;

  public static final int IsTypeElided;

  public static final int IsArgument;

  public static final int IsLocalDeclarationReachable;

  public static final int IsForeachElementVariable;

  public static final int ShadowsOuterLocal;

  public static final int FirstAssignmentToLocal;

  public static final int NeedReceiverGenericCast;

  public static final int IsImplicitThis;

  public static final int DepthSHIFT;

  public static final int DepthMASK;

  public static final int IsCapturedOuterLocal;

  public static final int IsReachable;

  public static final int LabelUsed;

  public static final int DocumentedFallthrough;

  public static final int DocumentedCasesOmitted;

  public static final int IsSubRoutineEscaping;

  public static final int IsTryBlockExiting;

  public static final int ContainsAssertion;

  public static final int IsLocalType;

  public static final int IsAnonymousType;

  public static final int IsMemberType;

  public static final int HasAbstractMethods;

  public static final int IsSecondaryType;

  public static final int HasBeenGenerated;

  public static final int HasLocalType;

  public static final int HasBeenResolved;

  public static final int ParenthesizedSHIFT;

  public static final int ParenthesizedMASK;

  public static final int IgnoreNoEffectAssignCheck;

  public static final int IsStrictlyAssigned;

  public static final int IsCompoundAssigned;

  public static final int DiscardEnclosingInstance;

  public static final int Unchecked;

  public static final int ResolveJavadoc;

  public static final int IsUsefulEmptyStatement;

  public static final int UndocumentedEmptyBlock;

  public static final int OverridingMethodWithSupercall;

  public static final int CanBeStatic;

  public static final int ErrorInSignature;

  public static final int NeedFreeReturn;

  public static final int IsDefaultConstructor;

  public static final int HasAllMethodBodies;

  public static final int IsImplicitUnit;

  public static final int InsideJavadoc;

  public static final int SuperAccess;

  public static final int Empty;

  public static final int IsElseIfStatement;

  public static final int ThenExit;

  public static final int IsElseStatementUnreachable;

  public static final int IsThenStatementUnreachable;

  public static final int IsSuperType;

  public static final int IsVarArgs;

  public static final int IgnoreRawTypeCheck;

  public static final int IsAnnotationDefaultValue;

  public static final int IsNonNull;

  public static final int NeededScope;

  public static final int OnDemand;

  public static final int Used;

  public static final int DidResolve;

  public static final int IsAnySubRoutineEscaping;

  public static final int IsSynchronized;

  public static final int BlockExit;

  public static final int IsRecovered;

  public static final int HasSyntaxErrors;

  public static final int INVOCATION_ARGUMENT_OK;

  public static final int INVOCATION_ARGUMENT_UNCHECKED;

  public static final int INVOCATION_ARGUMENT_WILDCARD;

  public static final int HasTypeAnnotations;

  public static final int IsUnionType;

  public static final int IsDiamond;

  public static final int InsideExpressionStatement;

  public static final int IsSynthetic;

  public static final int HasFunctionalInterfaceTypes;

  public static final org.eclipse.jdt.internal.compiler.ast.Argument[] NO_ARGUMENTS;

  static {};
    Code:
       0: iconst_0
       1: anewarray     #274                // class org/eclipse/jdt/internal/compiler/ast/Argument
       4: putstatic     #276                // Field NO_ARGUMENTS:[Lorg/eclipse/jdt/internal/compiler/ast/Argument;
       7: return

  public org.eclipse.jdt.internal.compiler.ast.ASTNode();
    Code:
       0: aload_0
       1: invokespecial #281                // Method java/lang/Object."<init>":()V
       4: aload_0
       5: ldc           #76                 // int -2147483648
       7: putfield      #283                // Field bits:I
      10: return

  private static int checkInvocationArgument(org.eclipse.jdt.internal.compiler.lookup.BlockScope, org.eclipse.jdt.internal.compiler.ast.Expression, org.eclipse.jdt.internal.compiler.lookup.TypeBinding, org.eclipse.jdt.internal.compiler.lookup.TypeBinding, org.eclipse.jdt.internal.compiler.lookup.TypeBinding);
    Code:
       0: aload_1
       1: aload_0
       2: aload_2
       3: aload_3
       4: invokevirtual #289                // Method org/eclipse/jdt/internal/compiler/ast/Expression.computeConversion:(Lorg/eclipse/jdt/internal/compiler/lookup/Scope;Lorg/eclipse/jdt/internal/compiler/lookup/TypeBinding;Lorg/eclipse/jdt/internal/compiler/lookup/TypeBinding;)V
       7: aload_3
       8: getstatic     #295                // Field org/eclipse/jdt/internal/compiler/lookup/TypeBinding.NULL:Lorg/eclipse/jdt/internal/compiler/lookup/NullTypeBinding;
      11: if_acmpeq     41
      14: aload_2
      15: invokevirtual #301                // Method org/eclipse/jdt/internal/compiler/lookup/TypeBinding.kind:()I
      18: sipush        516
      21: if_icmpne     41
      24: aload_2
      25: checkcast     #305                // class org/eclipse/jdt/internal/compiler/lookup/WildcardBinding
      28: astore        5
      30: aload         5
      32: getfield      #307                // Field org/eclipse/jdt/internal/compiler/lookup/WildcardBinding.boundKind:I
      35: iconst_2
      36: if_icmpeq     41
      39: iconst_2
      40: ireturn
      41: aload_2
      42: astore        5
      44: aload_3
      45: aload         5
      47: invokestatic  #310                // Method org/eclipse/jdt/internal/compiler/lookup/TypeBinding.notEquals:(Lorg/eclipse/jdt/internal/compiler/lookup/TypeBinding;Lorg/eclipse/jdt/internal/compiler/lookup/TypeBinding;)Z
      50: ifeq          75
      53: aload_3
      54: aload         5
      56: invokevirtual #314                // Method org/eclipse/jdt/internal/compiler/lookup/TypeBinding.needsUncheckedConversion:(Lorg/eclipse/jdt/internal/compiler/lookup/TypeBinding;)Z
      59: ifeq          75
      62: aload_0
      63: invokevirtual #318                // Method org/eclipse/jdt/internal/compiler/lookup/BlockScope.problemReporter:()Lorg/eclipse/jdt/internal/compiler/problem/ProblemReporter;
      66: aload_1
      67: aload_3
      68: aload         5
      70: invokevirtual #324                // Method org/eclipse/jdt/internal/compiler/problem/ProblemReporter.unsafeTypeConversion:(Lorg/eclipse/jdt/internal/compiler/ast/Expression;Lorg/eclipse/jdt/internal/compiler/lookup/TypeBinding;Lorg/eclipse/jdt/internal/compiler/lookup/TypeBinding;)V
      73: iconst_1
      74: ireturn
      75: iconst_0
      76: ireturn

  public static boolean checkInvocationArguments(org.eclipse.jdt.internal.compiler.lookup.BlockScope, org.eclipse.jdt.internal.compiler.ast.Expression, org.eclipse.jdt.internal.compiler.lookup.TypeBinding, org.eclipse.jdt.internal.compiler.lookup.MethodBinding, org.eclipse.jdt.internal.compiler.ast.Expression[], org.eclipse.jdt.internal.compiler.lookup.TypeBinding[], boolean, org.eclipse.jdt.internal.compiler.lookup.InvocationSite);
    Code:
       0: aload_0
       1: invokevirtual #344                // Method org/eclipse/jdt/internal/compiler/lookup/BlockScope.compilerOptions:()Lorg/eclipse/jdt/internal/compiler/impl/CompilerOptions;
       4: getfield      #348                // Field org/eclipse/jdt/internal/compiler/impl/CompilerOptions.sourceLevel:J
       7: ldc2_w        #353                // long 3342336l
      10: lcmp
      11: iflt          18
      14: iconst_1
      15: goto          19
      18: iconst_0
      19: istore        8
      21: iload         8
      23: ifeq          35
      26: aload_3
      27: invokevirtual #355                // Method org/eclipse/jdt/internal/compiler/lookup/MethodBinding.isPolymorphic:()Z
      30: ifeq          35
      33: iconst_0
      34: ireturn
      35: aload_3
      36: getfield      #361                // Field org/eclipse/jdt/internal/compiler/lookup/MethodBinding.parameters:[Lorg/eclipse/jdt/internal/compiler/lookup/TypeBinding;
      39: astore        9
      41: aload         9
      43: arraylength
      44: istore        10
      46: aload_3
      47: invokevirtual #365                // Method org/eclipse/jdt/internal/compiler/lookup/MethodBinding.isStatic:()Z
      50: ifne          81
      53: aload_2
      54: invokevirtual #368                // Method org/eclipse/jdt/internal/compiler/lookup/TypeBinding.isUnboundWildcard:()Z
      57: ifne          81
      60: aload_3
      61: getfield      #371                // Field org/eclipse/jdt/internal/compiler/lookup/MethodBinding.declaringClass:Lorg/eclipse/jdt/internal/compiler/lookup/ReferenceBinding;
      64: invokevirtual #375                // Method org/eclipse/jdt/internal/compiler/lookup/ReferenceBinding.isRawType:()Z
      67: ifeq          81
      70: aload_3
      71: invokevirtual #380                // Method org/eclipse/jdt/internal/compiler/lookup/MethodBinding.hasSubstitutedParameters:()Z
      74: ifeq          81
      77: iconst_1
      78: goto          82
      81: iconst_0
      82: istore        11
      84: aload_3
      85: getfield      #383                // Field org/eclipse/jdt/internal/compiler/lookup/MethodBinding.tagBits:J
      88: ldc2_w        #386                // long 256l
      91: land
      92: lconst_0
      93: lcmp
      94: ifeq          101
      97: iconst_1
      98: goto          102
     101: iconst_0
     102: istore        12
     104: aconst_null
     105: astore        13
     107: iload         11
     109: ifne          146
     112: aload_3
     113: instanceof    #388                // class org/eclipse/jdt/internal/compiler/lookup/ParameterizedGenericMethodBinding
     116: ifeq          146
     119: aload_3
     120: checkcast     #388                // class org/eclipse/jdt/internal/compiler/lookup/ParameterizedGenericMethodBinding
     123: astore        14
     125: aload         14
     127: getfield      #390                // Field org/eclipse/jdt/internal/compiler/lookup/ParameterizedGenericMethodBinding.isRaw:Z
     130: ifeq          146
     133: aload_3
     134: invokevirtual #380                // Method org/eclipse/jdt/internal/compiler/lookup/MethodBinding.hasSubstitutedParameters:()Z
     137: ifeq          146
     140: aload_3
     141: invokevirtual #394                // Method org/eclipse/jdt/internal/compiler/lookup/MethodBinding.original:()Lorg/eclipse/jdt/internal/compiler/lookup/MethodBinding;
     144: astore        13
     146: iconst_0
     147: istore        14
     149: aload         4
     151: ifnonnull     219
     154: aload_3
     155: invokevirtual #398                // Method org/eclipse/jdt/internal/compiler/lookup/MethodBinding.isVarargs:()Z
     158: ifeq          740
     161: aload         9
     163: iload         10
     165: iconst_1
     166: isub
     167: aaload
     168: checkcast     #401                // class org/eclipse/jdt/internal/compiler/lookup/ArrayBinding
     171: invokevirtual #403                // Method org/eclipse/jdt/internal/compiler/lookup/ArrayBinding.elementsType:()Lorg/eclipse/jdt/internal/compiler/lookup/TypeBinding;
     174: astore        15
     176: aload         15
     178: invokevirtual #407                // Method org/eclipse/jdt/internal/compiler/lookup/TypeBinding.isReifiable:()Z
     181: ifne          740
     184: iload         8
     186: ifeq          202
     189: aload_3
     190: getfield      #383                // Field org/eclipse/jdt/internal/compiler/lookup/MethodBinding.tagBits:J
     193: ldc2_w        #139                // long 2251799813685248l
     196: land
     197: lconst_0
     198: lcmp
     199: ifne          740
     202: aload_0
     203: invokevirtual #318                // Method org/eclipse/jdt/internal/compiler/lookup/BlockScope.problemReporter:()Lorg/eclipse/jdt/internal/compiler/problem/ProblemReporter;
     206: aload         15
     208: aload         7
     210: checkcast     #1                  // class org/eclipse/jdt/internal/compiler/ast/ASTNode
     213: invokevirtual #410                // Method org/eclipse/jdt/internal/compiler/problem/ProblemReporter.unsafeGenericArrayForVarargs:(Lorg/eclipse/jdt/internal/compiler/lookup/TypeBinding;Lorg/eclipse/jdt/internal/compiler/ast/ASTNode;)V
     216: goto          740
     219: aload_3
     220: invokevirtual #398                // Method org/eclipse/jdt/internal/compiler/lookup/MethodBinding.isVarargs:()Z
     223: ifeq          661
     226: iload         10
     228: iconst_1
     229: isub
     230: istore        15
     232: iconst_0
     233: istore        16
     235: goto          286
     238: aload         13
     240: ifnonnull     247
     243: aconst_null
     244: goto          255
     247: aload         13
     249: getfield      #361                // Field org/eclipse/jdt/internal/compiler/lookup/MethodBinding.parameters:[Lorg/eclipse/jdt/internal/compiler/lookup/TypeBinding;
     252: iload         16
     254: aaload
     255: astore        17
     257: iload         14
     259: aload_0
     260: aload         4
     262: iload         16
     264: aaload
     265: aload         9
     267: iload         16
     269: aaload
     270: aload         5
     272: iload         16
     274: aaload
     275: aload         17
     277: invokestatic  #414                // Method checkInvocationArgument:(Lorg/eclipse/jdt/internal/compiler/lookup/BlockScope;Lorg/eclipse/jdt/internal/compiler/ast/Expression;Lorg/eclipse/jdt/internal/compiler/lookup/TypeBinding;Lorg/eclipse/jdt/internal/compiler/lookup/TypeBinding;Lorg/eclipse/jdt/internal/compiler/lookup/TypeBinding;)I
     280: ior
     281: istore        14
     283: iinc          16, 1
     286: iload         16
     288: iload         15
     290: if_icmplt     238
     293: aload         4
     295: arraylength
     296: istore        16
     298: iload         15
     300: iload         16
     302: if_icmpgt     453
     305: aload         9
     307: iload         15
     309: aaload
     310: astore        17
     312: aconst_null
     313: astore        18
     315: iload         10
     317: iload         16
     319: if_icmpne     338
     322: aload         17
     324: invokevirtual #416                // Method org/eclipse/jdt/internal/compiler/lookup/TypeBinding.dimensions:()I
     327: aload         5
     329: iload         15
     331: aaload
     332: invokevirtual #416                // Method org/eclipse/jdt/internal/compiler/lookup/TypeBinding.dimensions:()I
     335: if_icmpeq     413
     338: aload         17
     340: checkcast     #401                // class org/eclipse/jdt/internal/compiler/lookup/ArrayBinding
     343: invokevirtual #403                // Method org/eclipse/jdt/internal/compiler/lookup/ArrayBinding.elementsType:()Lorg/eclipse/jdt/internal/compiler/lookup/TypeBinding;
     346: astore        17
     348: aload         17
     350: invokevirtual #407                // Method org/eclipse/jdt/internal/compiler/lookup/TypeBinding.isReifiable:()Z
     353: ifne          388
     356: iload         8
     358: ifeq          374
     361: aload_3
     362: getfield      #383                // Field org/eclipse/jdt/internal/compiler/lookup/MethodBinding.tagBits:J
     365: ldc2_w        #139                // long 2251799813685248l
     368: land
     369: lconst_0
     370: lcmp
     371: ifne          388
     374: aload_0
     375: invokevirtual #318                // Method org/eclipse/jdt/internal/compiler/lookup/BlockScope.problemReporter:()Lorg/eclipse/jdt/internal/compiler/problem/ProblemReporter;
     378: aload         17
     380: aload         7
     382: checkcast     #1                  // class org/eclipse/jdt/internal/compiler/ast/ASTNode
     385: invokevirtual #410                // Method org/eclipse/jdt/internal/compiler/problem/ProblemReporter.unsafeGenericArrayForVarargs:(Lorg/eclipse/jdt/internal/compiler/lookup/TypeBinding;Lorg/eclipse/jdt/internal/compiler/ast/ASTNode;)V
     388: aload         13
     390: ifnonnull     397
     393: aconst_null
     394: goto          411
     397: aload         13
     399: getfield      #361                // Field org/eclipse/jdt/internal/compiler/lookup/MethodBinding.parameters:[Lorg/eclipse/jdt/internal/compiler/lookup/TypeBinding;
     402: iload         15
     404: aaload
     405: checkcast     #401                // class org/eclipse/jdt/internal/compiler/lookup/ArrayBinding
     408: invokevirtual #403                // Method org/eclipse/jdt/internal/compiler/lookup/ArrayBinding.elementsType:()Lorg/eclipse/jdt/internal/compiler/lookup/TypeBinding;
     411: astore        18
     413: iload         15
     415: istore        19
     417: goto          446
     420: iload         14
     422: aload_0
     423: aload         4
     425: iload         19
     427: aaload
     428: aload         17
     430: aload         5
     432: iload         19
     434: aaload
     435: aload         18
     437: invokestatic  #414                // Method checkInvocationArgument:(Lorg/eclipse/jdt/internal/compiler/lookup/BlockScope;Lorg/eclipse/jdt/internal/compiler/ast/Expression;Lorg/eclipse/jdt/internal/compiler/lookup/TypeBinding;Lorg/eclipse/jdt/internal/compiler/lookup/TypeBinding;Lorg/eclipse/jdt/internal/compiler/lookup/TypeBinding;)I
     440: ior
     441: istore        14
     443: iinc          19, 1
     446: iload         19
     448: iload         16
     450: if_icmplt     420
     453: iload         10
     455: iload         16
     457: if_icmpne     722
     460: iload         10
     462: iconst_1
     463: isub
     464: istore        17
     466: aload         9
     468: iload         17
     470: aaload
     471: checkcast     #401                // class org/eclipse/jdt/internal/compiler/lookup/ArrayBinding
     474: astore        18
     476: aload         5
     478: iload         17
     480: aaload
     481: astore        19
     483: aload         19
     485: getstatic     #295                // Field org/eclipse/jdt/internal/compiler/lookup/TypeBinding.NULL:Lorg/eclipse/jdt/internal/compiler/lookup/NullTypeBinding;
     488: if_acmpne     526
     491: aload         18
     493: invokevirtual #419                // Method org/eclipse/jdt/internal/compiler/lookup/ArrayBinding.leafComponentType:()Lorg/eclipse/jdt/internal/compiler/lookup/TypeBinding;
     496: invokevirtual #422                // Method org/eclipse/jdt/internal/compiler/lookup/TypeBinding.isBaseType:()Z
     499: ifeq          511
     502: aload         18
     504: invokevirtual #425                // Method org/eclipse/jdt/internal/compiler/lookup/ArrayBinding.dimensions:()I
     507: iconst_1
     508: if_icmpeq     722
     511: aload_0
     512: invokevirtual #318                // Method org/eclipse/jdt/internal/compiler/lookup/BlockScope.problemReporter:()Lorg/eclipse/jdt/internal/compiler/problem/ProblemReporter;
     515: aload_3
     516: aload         19
     518: aload         7
     520: invokevirtual #426                // Method org/eclipse/jdt/internal/compiler/problem/ProblemReporter.varargsArgumentNeedCast:(Lorg/eclipse/jdt/internal/compiler/lookup/MethodBinding;Lorg/eclipse/jdt/internal/compiler/lookup/TypeBinding;Lorg/eclipse/jdt/internal/compiler/lookup/InvocationSite;)V
     523: goto          722
     526: aload         18
     528: getfield      #430                // Field org/eclipse/jdt/internal/compiler/lookup/ArrayBinding.dimensions:I
     531: aload         19
     533: invokevirtual #416                // Method org/eclipse/jdt/internal/compiler/lookup/TypeBinding.dimensions:()I
     536: dup
     537: istore        20
     539: if_icmpgt     722
     542: aload         19
     544: invokevirtual #432                // Method org/eclipse/jdt/internal/compiler/lookup/TypeBinding.leafComponentType:()Lorg/eclipse/jdt/internal/compiler/lookup/TypeBinding;
     547: invokevirtual #422                // Method org/eclipse/jdt/internal/compiler/lookup/TypeBinding.isBaseType:()Z
     550: ifeq          556
     553: iinc          20, -1
     556: aload         18
     558: getfield      #430                // Field org/eclipse/jdt/internal/compiler/lookup/ArrayBinding.dimensions:I
     561: iload         20
     563: if_icmpge     581
     566: aload_0
     567: invokevirtual #318                // Method org/eclipse/jdt/internal/compiler/lookup/BlockScope.problemReporter:()Lorg/eclipse/jdt/internal/compiler/problem/ProblemReporter;
     570: aload_3
     571: aload         19
     573: aload         7
     575: invokevirtual #426                // Method org/eclipse/jdt/internal/compiler/problem/ProblemReporter.varargsArgumentNeedCast:(Lorg/eclipse/jdt/internal/compiler/lookup/MethodBinding;Lorg/eclipse/jdt/internal/compiler/lookup/TypeBinding;Lorg/eclipse/jdt/internal/compiler/lookup/InvocationSite;)V
     578: goto          722
     581: aload         18
     583: getfield      #430                // Field org/eclipse/jdt/internal/compiler/lookup/ArrayBinding.dimensions:I
     586: iload         20
     588: if_icmpne     722
     591: aload         19
     593: aload         18
     595: invokestatic  #310                // Method org/eclipse/jdt/internal/compiler/lookup/TypeBinding.notEquals:(Lorg/eclipse/jdt/internal/compiler/lookup/TypeBinding;Lorg/eclipse/jdt/internal/compiler/lookup/TypeBinding;)Z
     598: ifeq          722
     601: aload         19
     603: invokevirtual #432                // Method org/eclipse/jdt/internal/compiler/lookup/TypeBinding.leafComponentType:()Lorg/eclipse/jdt/internal/compiler/lookup/TypeBinding;
     606: invokevirtual #433                // Method org/eclipse/jdt/internal/compiler/lookup/TypeBinding.erasure:()Lorg/eclipse/jdt/internal/compiler/lookup/TypeBinding;
     609: aload         18
     611: getfield      #436                // Field org/eclipse/jdt/internal/compiler/lookup/ArrayBinding.leafComponentType:Lorg/eclipse/jdt/internal/compiler/lookup/TypeBinding;
     614: invokevirtual #433                // Method org/eclipse/jdt/internal/compiler/lookup/TypeBinding.erasure:()Lorg/eclipse/jdt/internal/compiler/lookup/TypeBinding;
     617: invokestatic  #310                // Method org/eclipse/jdt/internal/compiler/lookup/TypeBinding.notEquals:(Lorg/eclipse/jdt/internal/compiler/lookup/TypeBinding;Lorg/eclipse/jdt/internal/compiler/lookup/TypeBinding;)Z
     620: ifeq          722
     623: aload         19
     625: aload         18
     627: invokevirtual #403                // Method org/eclipse/jdt/internal/compiler/lookup/ArrayBinding.elementsType:()Lorg/eclipse/jdt/internal/compiler/lookup/TypeBinding;
     630: invokevirtual #438                // Method org/eclipse/jdt/internal/compiler/lookup/TypeBinding.isCompatibleWith:(Lorg/eclipse/jdt/internal/compiler/lookup/TypeBinding;)Z
     633: ifeq          722
     636: aload         19
     638: aload         18
     640: invokevirtual #438                // Method org/eclipse/jdt/internal/compiler/lookup/TypeBinding.isCompatibleWith:(Lorg/eclipse/jdt/internal/compiler/lookup/TypeBinding;)Z
     643: ifeq          722
     646: aload_0
     647: invokevirtual #318                // Method org/eclipse/jdt/internal/compiler/lookup/BlockScope.problemReporter:()Lorg/eclipse/jdt/internal/compiler/problem/ProblemReporter;
     650: aload_3
     651: aload         19
     653: aload         7
     655: invokevirtual #426                // Method org/eclipse/jdt/internal/compiler/problem/ProblemReporter.varargsArgumentNeedCast:(Lorg/eclipse/jdt/internal/compiler/lookup/MethodBinding;Lorg/eclipse/jdt/internal/compiler/lookup/TypeBinding;Lorg/eclipse/jdt/internal/compiler/lookup/InvocationSite;)V
     658: goto          722
     661: iconst_0
     662: istore        15
     664: goto          715
     667: aload         13
     669: ifnonnull     676
     672: aconst_null
     673: goto          684
     676: aload         13
     678: getfield      #361                // Field org/eclipse/jdt/internal/compiler/lookup/MethodBinding.parameters:[Lorg/eclipse/jdt/internal/compiler/lookup/TypeBinding;
     681: iload         15
     683: aaload
     684: astore        16
     686: iload         14
     688: aload_0
     689: aload         4
     691: iload         15
     693: aaload
     694: aload         9
     696: iload         15
     698: aaload
     699: aload         5
     701: iload         15
     703: aaload
     704: aload         16
     706: invokestatic  #414                // Method checkInvocationArgument:(Lorg/eclipse/jdt/internal/compiler/lookup/BlockScope;Lorg/eclipse/jdt/internal/compiler/ast/Expression;Lorg/eclipse/jdt/internal/compiler/lookup/TypeBinding;Lorg/eclipse/jdt/internal/compiler/lookup/TypeBinding;Lorg/eclipse/jdt/internal/compiler/lookup/TypeBinding;)I
     709: ior
     710: istore        14
     712: iinc          15, 1
     715: iload         15
     717: iload         10
     719: if_icmplt     667
     722: iload         6
     724: ifeq          740
     727: aload_0
     728: aload_1
     729: aload_2
     730: aload_3
     731: aload         4
     733: aload         5
     735: aload         7
     737: invokestatic  #441                // Method org/eclipse/jdt/internal/compiler/ast/CastExpression.checkNeedForArgumentCasts:(Lorg/eclipse/jdt/internal/compiler/lookup/BlockScope;Lorg/eclipse/jdt/internal/compiler/ast/Expression;Lorg/eclipse/jdt/internal/compiler/lookup/TypeBinding;Lorg/eclipse/jdt/internal/compiler/lookup/MethodBinding;[Lorg/eclipse/jdt/internal/compiler/ast/Expression;[Lorg/eclipse/jdt/internal/compiler/lookup/TypeBinding;Lorg/eclipse/jdt/internal/compiler/lookup/InvocationSite;)V
     740: iload         14
     742: iconst_2
     743: iand
     744: ifeq          766
     747: aload_0
     748: invokevirtual #318                // Method org/eclipse/jdt/internal/compiler/lookup/BlockScope.problemReporter:()Lorg/eclipse/jdt/internal/compiler/problem/ProblemReporter;
     751: aload         7
     753: checkcast     #1                  // class org/eclipse/jdt/internal/compiler/ast/ASTNode
     756: aload_2
     757: aload_3
     758: aload         5
     760: invokevirtual #447                // Method org/eclipse/jdt/internal/compiler/problem/ProblemReporter.wildcardInvocation:(Lorg/eclipse/jdt/internal/compiler/ast/ASTNode;Lorg/eclipse/jdt/internal/compiler/lookup/TypeBinding;Lorg/eclipse/jdt/internal/compiler/lookup/MethodBinding;[Lorg/eclipse/jdt/internal/compiler/lookup/TypeBinding;)V
     763: goto          879
     766: aload_3
     767: invokevirtual #365                // Method org/eclipse/jdt/internal/compiler/lookup/MethodBinding.isStatic:()Z
     770: ifne          838
     773: aload_2
     774: invokevirtual #368                // Method org/eclipse/jdt/internal/compiler/lookup/TypeBinding.isUnboundWildcard:()Z
     777: ifne          838
     780: aload_3
     781: getfield      #371                // Field org/eclipse/jdt/internal/compiler/lookup/MethodBinding.declaringClass:Lorg/eclipse/jdt/internal/compiler/lookup/ReferenceBinding;
     784: invokevirtual #375                // Method org/eclipse/jdt/internal/compiler/lookup/ReferenceBinding.isRawType:()Z
     787: ifeq          838
     790: aload_3
     791: invokevirtual #380                // Method org/eclipse/jdt/internal/compiler/lookup/MethodBinding.hasSubstitutedParameters:()Z
     794: ifeq          838
     797: aload_0
     798: invokevirtual #344                // Method org/eclipse/jdt/internal/compiler/lookup/BlockScope.compilerOptions:()Lorg/eclipse/jdt/internal/compiler/impl/CompilerOptions;
     801: getfield      #451                // Field org/eclipse/jdt/internal/compiler/impl/CompilerOptions.reportUnavoidableGenericTypeProblems:Z
     804: ifne          822
     807: aload_1
     808: ifnull        822
     811: aload_1
     812: aload_0
     813: invokevirtual #454                // Method org/eclipse/jdt/internal/compiler/lookup/BlockScope.referenceContext:()Lorg/eclipse/jdt/internal/compiler/impl/ReferenceContext;
     816: invokevirtual #458                // Method org/eclipse/jdt/internal/compiler/ast/Expression.forcedToBeRaw:(Lorg/eclipse/jdt/internal/compiler/impl/ReferenceContext;)Z
     819: ifne          879
     822: aload_0
     823: invokevirtual #318                // Method org/eclipse/jdt/internal/compiler/lookup/BlockScope.problemReporter:()Lorg/eclipse/jdt/internal/compiler/problem/ProblemReporter;
     826: aload         7
     828: checkcast     #1                  // class org/eclipse/jdt/internal/compiler/ast/ASTNode
     831: aload_3
     832: invokevirtual #462                // Method org/eclipse/jdt/internal/compiler/problem/ProblemReporter.unsafeRawInvocation:(Lorg/eclipse/jdt/internal/compiler/ast/ASTNode;Lorg/eclipse/jdt/internal/compiler/lookup/MethodBinding;)V
     835: goto          879
     838: aload         13
     840: ifnonnull     862
     843: iload         12
     845: ifne          862
     848: iload         14
     850: iconst_1
     851: iand
     852: ifeq          879
     855: aload_3
     856: instanceof    #388                // class org/eclipse/jdt/internal/compiler/lookup/ParameterizedGenericMethodBinding
     859: ifeq          879
     862: aload_0
     863: invokevirtual #318                // Method org/eclipse/jdt/internal/compiler/lookup/BlockScope.problemReporter:()Lorg/eclipse/jdt/internal/compiler/problem/ProblemReporter;
     866: aload         7
     868: checkcast     #1                  // class org/eclipse/jdt/internal/compiler/ast/ASTNode
     871: aload_3
     872: aload         5
     874: invokevirtual #466                // Method org/eclipse/jdt/internal/compiler/problem/ProblemReporter.unsafeRawGenericMethodInvocation:(Lorg/eclipse/jdt/internal/compiler/ast/ASTNode;Lorg/eclipse/jdt/internal/compiler/lookup/MethodBinding;[Lorg/eclipse/jdt/internal/compiler/lookup/TypeBinding;)V
     877: iconst_1
     878: ireturn
     879: iconst_0
     880: ireturn

  public org.eclipse.jdt.internal.compiler.ast.ASTNode concreteStatement();
    Code:
       0: aload_0
       1: areturn

  public final boolean isFieldUseDeprecated(org.eclipse.jdt.internal.compiler.lookup.FieldBinding, org.eclipse.jdt.internal.compiler.lookup.Scope, int);
    Code:
       0: aload_0
       1: getfield      #283                // Field bits:I
       4: ldc           #44                 // int 32768
       6: iand
       7: ifne          70
      10: iload_3
      11: sipush        8192
      14: iand
      15: ifne          70
      18: aload_1
      19: invokevirtual #505                // Method org/eclipse/jdt/internal/compiler/lookup/FieldBinding.isOrEnclosedByPrivateType:()Z
      22: ifeq          70
      25: aload_2
      26: aload_1
      27: invokevirtual #510                // Method org/eclipse/jdt/internal/compiler/lookup/Scope.isDefinedInField:(Lorg/eclipse/jdt/internal/compiler/lookup/FieldBinding;)Z
      30: ifne          70
      33: iload_3
      34: ldc           #46                 // int 65536
      36: iand
      37: ifeq          56
      40: aload_1
      41: invokevirtual #516                // Method org/eclipse/jdt/internal/compiler/lookup/FieldBinding.original:()Lorg/eclipse/jdt/internal/compiler/lookup/FieldBinding;
      44: dup
      45: getfield      #519                // Field org/eclipse/jdt/internal/compiler/lookup/FieldBinding.compoundUseFlag:I
      48: iconst_1
      49: iadd
      50: putfield      #519                // Field org/eclipse/jdt/internal/compiler/lookup/FieldBinding.compoundUseFlag:I
      53: goto          70
      56: aload_1
      57: invokevirtual #516                // Method org/eclipse/jdt/internal/compiler/lookup/FieldBinding.original:()Lorg/eclipse/jdt/internal/compiler/lookup/FieldBinding;
      60: dup
      61: getfield      #522                // Field org/eclipse/jdt/internal/compiler/lookup/FieldBinding.modifiers:I
      64: ldc           #68                 // int 134217728
      66: ior
      67: putfield      #522                // Field org/eclipse/jdt/internal/compiler/lookup/FieldBinding.modifiers:I
      70: aload_1
      71: getfield      #522                // Field org/eclipse/jdt/internal/compiler/lookup/FieldBinding.modifiers:I
      74: ldc           #50                 // int 262144
      76: iand
      77: ifeq          125
      80: aload_2
      81: invokevirtual #525                // Method org/eclipse/jdt/internal/compiler/lookup/Scope.environment:()Lorg/eclipse/jdt/internal/compiler/lookup/LookupEnvironment;
      84: aload_1
      85: getfield      #529                // Field org/eclipse/jdt/internal/compiler/lookup/FieldBinding.declaringClass:Lorg/eclipse/jdt/internal/compiler/lookup/ReferenceBinding;
      88: invokevirtual #530                // Method org/eclipse/jdt/internal/compiler/lookup/ReferenceBinding.erasure:()Lorg/eclipse/jdt/internal/compiler/lookup/TypeBinding;
      91: invokevirtual #531                // Method org/eclipse/jdt/internal/compiler/lookup/LookupEnvironment.getAccessRestriction:(Lorg/eclipse/jdt/internal/compiler/lookup/TypeBinding;)Lorg/eclipse/jdt/internal/compiler/env/AccessRestriction;
      94: astore        4
      96: aload         4
      98: ifnull        125
     101: aload_2
     102: invokevirtual #537                // Method org/eclipse/jdt/internal/compiler/lookup/Scope.problemReporter:()Lorg/eclipse/jdt/internal/compiler/problem/ProblemReporter;
     105: aload_1
     106: aload_0
     107: aload         4
     109: getfield      #538                // Field org/eclipse/jdt/internal/compiler/env/AccessRestriction.classpathEntryType:B
     112: aload         4
     114: getfield      #544                // Field org/eclipse/jdt/internal/compiler/env/AccessRestriction.classpathEntryName:Ljava/lang/String;
     117: aload         4
     119: invokevirtual #548                // Method org/eclipse/jdt/internal/compiler/env/AccessRestriction.getProblemId:()I
     122: invokevirtual #551                // Method org/eclipse/jdt/internal/compiler/problem/ProblemReporter.forbiddenReference:(Lorg/eclipse/jdt/internal/compiler/lookup/FieldBinding;Lorg/eclipse/jdt/internal/compiler/ast/ASTNode;BLjava/lang/String;I)V
     125: aload_1
     126: invokevirtual #555                // Method org/eclipse/jdt/internal/compiler/lookup/FieldBinding.isViewedAsDeprecated:()Z
     129: ifne          134
     132: iconst_0
     133: ireturn
     134: aload_2
     135: aload_1
     136: getfield      #529                // Field org/eclipse/jdt/internal/compiler/lookup/FieldBinding.declaringClass:Lorg/eclipse/jdt/internal/compiler/lookup/ReferenceBinding;
     139: invokevirtual #558                // Method org/eclipse/jdt/internal/compiler/lookup/Scope.isDefinedInSameUnit:(Lorg/eclipse/jdt/internal/compiler/lookup/ReferenceBinding;)Z
     142: ifeq          147
     145: iconst_0
     146: ireturn
     147: aload_2
     148: invokevirtual #562                // Method org/eclipse/jdt/internal/compiler/lookup/Scope.compilerOptions:()Lorg/eclipse/jdt/internal/compiler/impl/CompilerOptions;
     151: getfield      #563                // Field org/eclipse/jdt/internal/compiler/impl/CompilerOptions.reportDeprecationInsideDeprecatedCode:Z
     154: ifne          166
     157: aload_2
     158: invokevirtual #566                // Method org/eclipse/jdt/internal/compiler/lookup/Scope.isInsideDeprecatedCode:()Z
     161: ifeq          166
     164: iconst_0
     165: ireturn
     166: iconst_1
     167: ireturn

  public boolean isImplicitThis();
    Code:
       0: iconst_0
       1: ireturn

  public boolean receiverIsImplicitThis();
    Code:
       0: iconst_0
       1: ireturn

  public final boolean isMethodUseDeprecated(org.eclipse.jdt.internal.compiler.lookup.MethodBinding, org.eclipse.jdt.internal.compiler.lookup.Scope, boolean);
    Code:
       0: aload_0
       1: getfield      #283                // Field bits:I
       4: ldc           #44                 // int 32768
       6: iand
       7: ifne          39
      10: aload_1
      11: invokevirtual #579                // Method org/eclipse/jdt/internal/compiler/lookup/MethodBinding.isOrEnclosedByPrivateType:()Z
      14: ifeq          39
      17: aload_2
      18: aload_1
      19: invokevirtual #580                // Method org/eclipse/jdt/internal/compiler/lookup/Scope.isDefinedInMethod:(Lorg/eclipse/jdt/internal/compiler/lookup/MethodBinding;)Z
      22: ifne          39
      25: aload_1
      26: invokevirtual #394                // Method org/eclipse/jdt/internal/compiler/lookup/MethodBinding.original:()Lorg/eclipse/jdt/internal/compiler/lookup/MethodBinding;
      29: dup
      30: getfield      #584                // Field org/eclipse/jdt/internal/compiler/lookup/MethodBinding.modifiers:I
      33: ldc           #68                 // int 134217728
      35: ior
      36: putfield      #584                // Field org/eclipse/jdt/internal/compiler/lookup/MethodBinding.modifiers:I
      39: iload_3
      40: ifeq          98
      43: aload_1
      44: getfield      #584                // Field org/eclipse/jdt/internal/compiler/lookup/MethodBinding.modifiers:I
      47: ldc           #50                 // int 262144
      49: iand
      50: ifeq          98
      53: aload_2
      54: invokevirtual #525                // Method org/eclipse/jdt/internal/compiler/lookup/Scope.environment:()Lorg/eclipse/jdt/internal/compiler/lookup/LookupEnvironment;
      57: aload_1
      58: getfield      #371                // Field org/eclipse/jdt/internal/compiler/lookup/MethodBinding.declaringClass:Lorg/eclipse/jdt/internal/compiler/lookup/ReferenceBinding;
      61: invokevirtual #530                // Method org/eclipse/jdt/internal/compiler/lookup/ReferenceBinding.erasure:()Lorg/eclipse/jdt/internal/compiler/lookup/TypeBinding;
      64: invokevirtual #531                // Method org/eclipse/jdt/internal/compiler/lookup/LookupEnvironment.getAccessRestriction:(Lorg/eclipse/jdt/internal/compiler/lookup/TypeBinding;)Lorg/eclipse/jdt/internal/compiler/env/AccessRestriction;
      67: astore        4
      69: aload         4
      71: ifnull        98
      74: aload_2
      75: invokevirtual #537                // Method org/eclipse/jdt/internal/compiler/lookup/Scope.problemReporter:()Lorg/eclipse/jdt/internal/compiler/problem/ProblemReporter;
      78: aload_1
      79: aload_0
      80: aload         4
      82: getfield      #538                // Field org/eclipse/jdt/internal/compiler/env/AccessRestriction.classpathEntryType:B
      85: aload         4
      87: getfield      #544                // Field org/eclipse/jdt/internal/compiler/env/AccessRestriction.classpathEntryName:Ljava/lang/String;
      90: aload         4
      92: invokevirtual #548                // Method org/eclipse/jdt/internal/compiler/env/AccessRestriction.getProblemId:()I
      95: invokevirtual #585                // Method org/eclipse/jdt/internal/compiler/problem/ProblemReporter.forbiddenReference:(Lorg/eclipse/jdt/internal/compiler/lookup/MethodBinding;Lorg/eclipse/jdt/internal/compiler/ast/ASTNode;BLjava/lang/String;I)V
      98: aload_1
      99: invokevirtual #588                // Method org/eclipse/jdt/internal/compiler/lookup/MethodBinding.isViewedAsDeprecated:()Z
     102: ifne          107
     105: iconst_0
     106: ireturn
     107: aload_2
     108: aload_1
     109: getfield      #371                // Field org/eclipse/jdt/internal/compiler/lookup/MethodBinding.declaringClass:Lorg/eclipse/jdt/internal/compiler/lookup/ReferenceBinding;
     112: invokevirtual #558                // Method org/eclipse/jdt/internal/compiler/lookup/Scope.isDefinedInSameUnit:(Lorg/eclipse/jdt/internal/compiler/lookup/ReferenceBinding;)Z
     115: ifeq          120
     118: iconst_0
     119: ireturn
     120: iload_3
     121: ifne          136
     124: aload_1
     125: getfield      #584                // Field org/eclipse/jdt/internal/compiler/lookup/MethodBinding.modifiers:I
     128: ldc           #54                 // int 1048576
     130: iand
     131: ifne          136
     134: iconst_0
     135: ireturn
     136: aload_2
     137: invokevirtual #562                // Method org/eclipse/jdt/internal/compiler/lookup/Scope.compilerOptions:()Lorg/eclipse/jdt/internal/compiler/impl/CompilerOptions;
     140: getfield      #563                // Field org/eclipse/jdt/internal/compiler/impl/CompilerOptions.reportDeprecationInsideDeprecatedCode:Z
     143: ifne          155
     146: aload_2
     147: invokevirtual #566                // Method org/eclipse/jdt/internal/compiler/lookup/Scope.isInsideDeprecatedCode:()Z
     150: ifeq          155
     153: iconst_0
     154: ireturn
     155: iconst_1
     156: ireturn

  public boolean isSuper();
    Code:
       0: iconst_0
       1: ireturn

  public boolean isThis();
    Code:
       0: iconst_0
       1: ireturn

  public boolean isUnqualifiedSuper();
    Code:
       0: iconst_0
       1: ireturn

  public final boolean isTypeUseDeprecated(org.eclipse.jdt.internal.compiler.lookup.TypeBinding, org.eclipse.jdt.internal.compiler.lookup.Scope);
    Code:
       0: aload_1
       1: invokevirtual #595                // Method org/eclipse/jdt/internal/compiler/lookup/TypeBinding.isArrayType:()Z
       4: ifeq          15
       7: aload_1
       8: checkcast     #401                // class org/eclipse/jdt/internal/compiler/lookup/ArrayBinding
      11: getfield      #436                // Field org/eclipse/jdt/internal/compiler/lookup/ArrayBinding.leafComponentType:Lorg/eclipse/jdt/internal/compiler/lookup/TypeBinding;
      14: astore_1
      15: aload_1
      16: invokevirtual #422                // Method org/eclipse/jdt/internal/compiler/lookup/TypeBinding.isBaseType:()Z
      19: ifeq          24
      22: iconst_0
      23: ireturn
      24: aload_1
      25: checkcast     #376                // class org/eclipse/jdt/internal/compiler/lookup/ReferenceBinding
      28: astore_3
      29: aload_0
      30: getfield      #283                // Field bits:I
      33: ldc           #44                 // int 32768
      35: iand
      36: ifne          57
      39: aload_3
      40: instanceof    #598                // class org/eclipse/jdt/internal/compiler/lookup/TypeVariableBinding
      43: ifeq          57
      46: aload_3
      47: dup
      48: getfield      #600                // Field org/eclipse/jdt/internal/compiler/lookup/ReferenceBinding.modifiers:I
      51: ldc           #68                 // int 134217728
      53: ior
      54: putfield      #600                // Field org/eclipse/jdt/internal/compiler/lookup/ReferenceBinding.modifiers:I
      57: aload_0
      58: getfield      #283                // Field bits:I
      61: ldc           #44                 // int 32768
      63: iand
      64: ifne          99
      67: aload_3
      68: invokevirtual #601                // Method org/eclipse/jdt/internal/compiler/lookup/ReferenceBinding.isOrEnclosedByPrivateType:()Z
      71: ifeq          99
      74: aload_2
      75: aload_3
      76: invokevirtual #602                // Method org/eclipse/jdt/internal/compiler/lookup/Scope.isDefinedInType:(Lorg/eclipse/jdt/internal/compiler/lookup/ReferenceBinding;)Z
      79: ifne          99
      82: aload_3
      83: invokevirtual #530                // Method org/eclipse/jdt/internal/compiler/lookup/ReferenceBinding.erasure:()Lorg/eclipse/jdt/internal/compiler/lookup/TypeBinding;
      86: checkcast     #376                // class org/eclipse/jdt/internal/compiler/lookup/ReferenceBinding
      89: dup
      90: getfield      #600                // Field org/eclipse/jdt/internal/compiler/lookup/ReferenceBinding.modifiers:I
      93: ldc           #68                 // int 134217728
      95: ior
      96: putfield      #600                // Field org/eclipse/jdt/internal/compiler/lookup/ReferenceBinding.modifiers:I
      99: aload_3
     100: invokevirtual #605                // Method org/eclipse/jdt/internal/compiler/lookup/ReferenceBinding.hasRestrictedAccess:()Z
     103: ifeq          148
     106: aload_2
     107: invokevirtual #525                // Method org/eclipse/jdt/internal/compiler/lookup/Scope.environment:()Lorg/eclipse/jdt/internal/compiler/lookup/LookupEnvironment;
     110: aload_1
     111: invokevirtual #433                // Method org/eclipse/jdt/internal/compiler/lookup/TypeBinding.erasure:()Lorg/eclipse/jdt/internal/compiler/lookup/TypeBinding;
     114: invokevirtual #531                // Method org/eclipse/jdt/internal/compiler/lookup/LookupEnvironment.getAccessRestriction:(Lorg/eclipse/jdt/internal/compiler/lookup/TypeBinding;)Lorg/eclipse/jdt/internal/compiler/env/AccessRestriction;
     117: astore        4
     119: aload         4
     121: ifnull        148
     124: aload_2
     125: invokevirtual #537                // Method org/eclipse/jdt/internal/compiler/lookup/Scope.problemReporter:()Lorg/eclipse/jdt/internal/compiler/problem/ProblemReporter;
     128: aload_1
     129: aload_0
     130: aload         4
     132: getfield      #538                // Field org/eclipse/jdt/internal/compiler/env/AccessRestriction.classpathEntryType:B
     135: aload         4
     137: getfield      #544                // Field org/eclipse/jdt/internal/compiler/env/AccessRestriction.classpathEntryName:Ljava/lang/String;
     140: aload         4
     142: invokevirtual #548                // Method org/eclipse/jdt/internal/compiler/env/AccessRestriction.getProblemId:()I
     145: invokevirtual #608                // Method org/eclipse/jdt/internal/compiler/problem/ProblemReporter.forbiddenReference:(Lorg/eclipse/jdt/internal/compiler/lookup/TypeBinding;Lorg/eclipse/jdt/internal/compiler/ast/ASTNode;BLjava/lang/String;I)V
     148: aload_3
     149: invokevirtual #611                // Method org/eclipse/jdt/internal/compiler/lookup/ReferenceBinding.initializeDeprecatedAnnotationTagBits:()V
     152: aload_3
     153: invokevirtual #614                // Method org/eclipse/jdt/internal/compiler/lookup/ReferenceBinding.isViewedAsDeprecated:()Z
     156: ifne          161
     159: iconst_0
     160: ireturn
     161: aload_2
     162: aload_3
     163: invokevirtual #558                // Method org/eclipse/jdt/internal/compiler/lookup/Scope.isDefinedInSameUnit:(Lorg/eclipse/jdt/internal/compiler/lookup/ReferenceBinding;)Z
     166: ifeq          171
     169: iconst_0
     170: ireturn
     171: aload_2
     172: invokevirtual #562                // Method org/eclipse/jdt/internal/compiler/lookup/Scope.compilerOptions:()Lorg/eclipse/jdt/internal/compiler/impl/CompilerOptions;
     175: getfield      #563                // Field org/eclipse/jdt/internal/compiler/impl/CompilerOptions.reportDeprecationInsideDeprecatedCode:Z
     178: ifne          190
     181: aload_2
     182: invokevirtual #566                // Method org/eclipse/jdt/internal/compiler/lookup/Scope.isInsideDeprecatedCode:()Z
     185: ifeq          190
     188: iconst_0
     189: ireturn
     190: iconst_1
     191: ireturn

  public abstract java.lang.StringBuffer print(int, java.lang.StringBuffer);

  public static java.lang.StringBuffer printAnnotations(org.eclipse.jdt.internal.compiler.ast.Annotation[], java.lang.StringBuffer);
    Code:
       0: aload_0
       1: arraylength
       2: istore_2
       3: iconst_0
       4: istore_3
       5: goto          51
       8: iload_3
       9: ifle          20
      12: aload_1
      13: ldc_w         #621                // String
      16: invokevirtual #623                // Method java/lang/StringBuffer.append:(Ljava/lang/String;)Ljava/lang/StringBuffer;
      19: pop
      20: aload_0
      21: iload_3
      22: aaload
      23: astore        4
      25: aload         4
      27: ifnull        41
      30: aload         4
      32: iconst_0
      33: aload_1
      34: invokevirtual #629                // Method org/eclipse/jdt/internal/compiler/ast/Annotation.print:(ILjava/lang/StringBuffer;)Ljava/lang/StringBuffer;
      37: pop
      38: goto          48
      41: aload_1
      42: bipush        63
      44: invokevirtual #633                // Method java/lang/StringBuffer.append:(C)Ljava/lang/StringBuffer;
      47: pop
      48: iinc          3, 1
      51: iload_3
      52: iload_2
      53: if_icmplt     8
      56: aload_1
      57: areturn

  public static java.lang.StringBuffer printIndent(int, java.lang.StringBuffer);
    Code:
       0: iload_0
       1: istore_2
       2: goto          16
       5: aload_1
       6: ldc_w         #644                // String
       9: invokevirtual #623                // Method java/lang/StringBuffer.append:(Ljava/lang/String;)Ljava/lang/StringBuffer;
      12: pop
      13: iinc          2, -1
      16: iload_2
      17: ifgt          5
      20: aload_1
      21: areturn

  public static java.lang.StringBuffer printModifiers(int, java.lang.StringBuffer);
    Code:
       0: iload_0
       1: iconst_1
       2: iand
       3: ifeq          14
       6: aload_1
       7: ldc_w         #648                // String public
      10: invokevirtual #623                // Method java/lang/StringBuffer.append:(Ljava/lang/String;)Ljava/lang/StringBuffer;
      13: pop
      14: iload_0
      15: iconst_2
      16: iand
      17: ifeq          28
      20: aload_1
      21: ldc_w         #650                // String private
      24: invokevirtual #623                // Method java/lang/StringBuffer.append:(Ljava/lang/String;)Ljava/lang/StringBuffer;
      27: pop
      28: iload_0
      29: iconst_4
      30: iand
      31: ifeq          42
      34: aload_1
      35: ldc_w         #652                // String protected
      38: invokevirtual #623                // Method java/lang/StringBuffer.append:(Ljava/lang/String;)Ljava/lang/StringBuffer;
      41: pop
      42: iload_0
      43: bipush        8
      45: iand
      46: ifeq          57
      49: aload_1
      50: ldc_w         #654                // String static
      53: invokevirtual #623                // Method java/lang/StringBuffer.append:(Ljava/lang/String;)Ljava/lang/StringBuffer;
      56: pop
      57: iload_0
      58: bipush        16
      60: iand
      61: ifeq          72
      64: aload_1
      65: ldc_w         #656                // String final
      68: invokevirtual #623                // Method java/lang/StringBuffer.append:(Ljava/lang/String;)Ljava/lang/StringBuffer;
      71: pop
      72: iload_0
      73: bipush        32
      75: iand
      76: ifeq          87
      79: aload_1
      80: ldc_w         #658                // String synchronized
      83: invokevirtual #623                // Method java/lang/StringBuffer.append:(Ljava/lang/String;)Ljava/lang/StringBuffer;
      86: pop
      87: iload_0
      88: bipush        64
      90: iand
      91: ifeq          102
      94: aload_1
      95: ldc_w         #660                // String volatile
      98: invokevirtual #623                // Method java/lang/StringBuffer.append:(Ljava/lang/String;)Ljava/lang/StringBuffer;
     101: pop
     102: iload_0
     103: sipush        128
     106: iand
     107: ifeq          118
     110: aload_1
     111: ldc_w         #662                // String transient
     114: invokevirtual #623                // Method java/lang/StringBuffer.append:(Ljava/lang/String;)Ljava/lang/StringBuffer;
     117: pop
     118: iload_0
     119: sipush        256
     122: iand
     123: ifeq          134
     126: aload_1
     127: ldc_w         #664                // String native
     130: invokevirtual #623                // Method java/lang/StringBuffer.append:(Ljava/lang/String;)Ljava/lang/StringBuffer;
     133: pop
     134: iload_0
     135: sipush        1024
     138: iand
     139: ifeq          150
     142: aload_1
     143: ldc_w         #666                // String abstract
     146: invokevirtual #623                // Method java/lang/StringBuffer.append:(Ljava/lang/String;)Ljava/lang/StringBuffer;
     149: pop
     150: iload_0
     151: ldc           #46                 // int 65536
     153: iand
     154: ifeq          165
     157: aload_1
     158: ldc_w         #668                // String default
     161: invokevirtual #623                // Method java/lang/StringBuffer.append:(Ljava/lang/String;)Ljava/lang/StringBuffer;
     164: pop
     165: aload_1
     166: areturn

  public static void resolvePolyExpressionArguments(org.eclipse.jdt.internal.compiler.ast.Invocation, org.eclipse.jdt.internal.compiler.lookup.MethodBinding, org.eclipse.jdt.internal.compiler.lookup.TypeBinding[], org.eclipse.jdt.internal.compiler.lookup.Scope);
    Code:
       0: aload_0
       1: invokeinterface #672,  1          // InterfaceMethod org/eclipse/jdt/internal/compiler/ast/Invocation.innersNeedUpdate:()Z
       6: ifne          10
       9: return
      10: iconst_0
      11: istore        4
      13: aload_1
      14: invokevirtual #677                // Method org/eclipse/jdt/internal/compiler/lookup/MethodBinding.isValidBinding:()Z
      17: ifeq          26
      20: aload_1
      21: astore        5
      23: goto          54
      26: aload_1
      27: instanceof    #680                // class org/eclipse/jdt/internal/compiler/lookup/ProblemMethodBinding
      30: ifeq          51
      33: aload_1
      34: invokevirtual #682                // Method org/eclipse/jdt/internal/compiler/lookup/MethodBinding.problemId:()I
      37: istore        4
      39: aload_1
      40: checkcast     #680                // class org/eclipse/jdt/internal/compiler/lookup/ProblemMethodBinding
      43: getfield      #685                // Field org/eclipse/jdt/internal/compiler/lookup/ProblemMethodBinding.closestMatch:Lorg/eclipse/jdt/internal/compiler/lookup/MethodBinding;
      46: astore        5
      48: goto          54
      51: aconst_null
      52: astore        5
      54: aload         5
      56: ifnull        516
      59: aload         5
      61: invokevirtual #398                // Method org/eclipse/jdt/internal/compiler/lookup/MethodBinding.isVarargs:()Z
      64: istore        6
      66: aconst_null
      67: astore        7
      69: aload         5
      71: instanceof    #688                // class org/eclipse/jdt/internal/compiler/lookup/ParameterizedMethodBinding
      74: ifeq          118
      77: aload_0
      78: aload         5
      80: checkcast     #688                // class org/eclipse/jdt/internal/compiler/lookup/ParameterizedMethodBinding
      83: invokeinterface #690,  2          // InterfaceMethod org/eclipse/jdt/internal/compiler/ast/Invocation.getInferenceContext:(Lorg/eclipse/jdt/internal/compiler/lookup/ParameterizedMethodBinding;)Lorg/eclipse/jdt/internal/compiler/lookup/InferenceContext18;
      88: astore        7
      90: aload         7
      92: ifnull        136
      95: aload         7
      97: getfield      #694                // Field org/eclipse/jdt/internal/compiler/lookup/InferenceContext18.stepCompleted:I
     100: iconst_2
     101: if_icmpeq     105
     104: return
     105: iload         6
     107: aload         7
     109: invokevirtual #699                // Method org/eclipse/jdt/internal/compiler/lookup/InferenceContext18.isVarArgs:()Z
     112: iand
     113: istore        6
     115: goto          136
     118: aload_0
     119: instanceof    #702                // class org/eclipse/jdt/internal/compiler/ast/AllocationExpression
     122: ifeq          136
     125: aload_0
     126: checkcast     #702                // class org/eclipse/jdt/internal/compiler/ast/AllocationExpression
     129: getfield      #704                // Field org/eclipse/jdt/internal/compiler/ast/AllocationExpression.suspendedResolutionState:Lorg/eclipse/jdt/internal/compiler/ast/AllocationExpression$ResolutionState;
     132: ifnull        136
     135: return
     136: aload         5
     138: getfield      #361                // Field org/eclipse/jdt/internal/compiler/lookup/MethodBinding.parameters:[Lorg/eclipse/jdt/internal/compiler/lookup/TypeBinding;
     141: astore        8
     143: aload_0
     144: invokeinterface #708,  1          // InterfaceMethod org/eclipse/jdt/internal/compiler/ast/Invocation.arguments:()[Lorg/eclipse/jdt/internal/compiler/ast/Expression;
     149: astore        9
     151: aload         9
     153: astore        10
     155: aload         7
     157: ifnonnull     213
     160: iload         6
     162: ifeq          213
     165: aload         10
     167: ifnull        213
     170: aload         8
     172: arraylength
     173: aload         10
     175: arraylength
     176: if_icmpne     213
     179: aload         8
     181: aload         8
     183: arraylength
     184: iconst_1
     185: isub
     186: aaload
     187: astore        11
     189: aload         10
     191: aload         10
     193: arraylength
     194: iconst_1
     195: isub
     196: aaload
     197: astore        12
     199: aload         12
     201: aload         11
     203: aconst_null
     204: invokevirtual #711                // Method org/eclipse/jdt/internal/compiler/ast/Expression.isCompatibleWith:(Lorg/eclipse/jdt/internal/compiler/lookup/TypeBinding;Lorg/eclipse/jdt/internal/compiler/lookup/Scope;)Z
     207: ifeq          213
     210: iconst_0
     211: istore        6
     213: iconst_0
     214: istore        11
     216: aload         10
     218: ifnonnull     225
     221: iconst_0
     222: goto          228
     225: aload         10
     227: arraylength
     228: istore        12
     230: goto          509
     233: aload         10
     235: iload         11
     237: aaload
     238: astore        13
     240: aconst_null
     241: astore        14
     243: aload         8
     245: iload         11
     247: iload         6
     249: invokestatic  #713                // Method org/eclipse/jdt/internal/compiler/lookup/InferenceContext18.getParameter:([Lorg/eclipse/jdt/internal/compiler/lookup/TypeBinding;IZ)Lorg/eclipse/jdt/internal/compiler/lookup/TypeBinding;
     252: astore        15
     254: aload         15
     256: ifnonnull     267
     259: iload         4
     261: ifeq          267
     264: goto          506
     267: aload         13
     269: instanceof    #717                // class org/eclipse/jdt/internal/compiler/ast/LambdaExpression
     272: ifeq          289
     275: aload         13
     277: checkcast     #717                // class org/eclipse/jdt/internal/compiler/ast/LambdaExpression
     280: invokevirtual #719                // Method org/eclipse/jdt/internal/compiler/ast/LambdaExpression.hasErrors:()Z
     283: ifeq          289
     286: goto          506
     289: aload         13
     291: instanceof    #673                // class org/eclipse/jdt/internal/compiler/ast/Invocation
     294: ifeq          440
     297: aload         13
     299: checkcast     #673                // class org/eclipse/jdt/internal/compiler/ast/Invocation
     302: astore        16
     304: aload         16
     306: aload         15
     308: iconst_1
     309: aload_3
     310: invokeinterface #722,  4          // InterfaceMethod org/eclipse/jdt/internal/compiler/ast/Invocation.binding:(Lorg/eclipse/jdt/internal/compiler/lookup/TypeBinding;ZLorg/eclipse/jdt/internal/compiler/lookup/Scope;)Lorg/eclipse/jdt/internal/compiler/lookup/MethodBinding;
     315: astore        17
     317: aload         17
     319: instanceof    #388                // class org/eclipse/jdt/internal/compiler/lookup/ParameterizedGenericMethodBinding
     322: ifeq          440
     325: aload         17
     327: checkcast     #388                // class org/eclipse/jdt/internal/compiler/lookup/ParameterizedGenericMethodBinding
     330: astore        18
     332: aload         16
     334: aload         18
     336: invokeinterface #690,  2          // InterfaceMethod org/eclipse/jdt/internal/compiler/ast/Invocation.getInferenceContext:(Lorg/eclipse/jdt/internal/compiler/lookup/ParameterizedMethodBinding;)Lorg/eclipse/jdt/internal/compiler/lookup/InferenceContext18;
     341: astore        19
     343: aload         19
     345: ifnull        506
     348: aload         19
     350: aload         15
     352: invokevirtual #726                // Method org/eclipse/jdt/internal/compiler/lookup/InferenceContext18.hasResultFor:(Lorg/eclipse/jdt/internal/compiler/lookup/TypeBinding;)Z
     355: ifne          418
     358: aload         13
     360: aload         15
     362: invokevirtual #729                // Method org/eclipse/jdt/internal/compiler/ast/Expression.setExpectedType:(Lorg/eclipse/jdt/internal/compiler/lookup/TypeBinding;)V
     365: aload         19
     367: aload         16
     369: aload         18
     371: invokevirtual #733                // Method org/eclipse/jdt/internal/compiler/lookup/InferenceContext18.inferInvocationType:(Lorg/eclipse/jdt/internal/compiler/ast/Invocation;Lorg/eclipse/jdt/internal/compiler/lookup/ParameterizedGenericMethodBinding;)Lorg/eclipse/jdt/internal/compiler/lookup/MethodBinding;
     374: astore        20
     376: aload         20
     378: invokevirtual #677                // Method org/eclipse/jdt/internal/compiler/lookup/MethodBinding.isValidBinding:()Z
     381: ifne          393
     384: aload         19
     386: aload         16
     388: aload         20
     390: invokevirtual #737                // Method org/eclipse/jdt/internal/compiler/lookup/InferenceContext18.reportInvalidInvocation:(Lorg/eclipse/jdt/internal/compiler/ast/Invocation;Lorg/eclipse/jdt/internal/compiler/lookup/MethodBinding;)V
     393: aload         16
     395: aload         20
     397: aload         15
     399: invokeinterface #741,  3          // InterfaceMethod org/eclipse/jdt/internal/compiler/ast/Invocation.updateBindings:(Lorg/eclipse/jdt/internal/compiler/lookup/MethodBinding;Lorg/eclipse/jdt/internal/compiler/lookup/TypeBinding;)Z
     404: ifeq          506
     407: aload         16
     409: aload         20
     411: aload_3
     412: invokestatic  #745                // Method resolvePolyExpressionArguments:(Lorg/eclipse/jdt/internal/compiler/ast/Invocation;Lorg/eclipse/jdt/internal/compiler/lookup/MethodBinding;Lorg/eclipse/jdt/internal/compiler/lookup/Scope;)V
     415: goto          506
     418: aload         19
     420: getfield      #694                // Field org/eclipse/jdt/internal/compiler/lookup/InferenceContext18.stepCompleted:I
     423: iconst_3
     424: if_icmpge     506
     427: aload         19
     429: aload         18
     431: aload         16
     433: invokevirtual #748                // Method org/eclipse/jdt/internal/compiler/lookup/InferenceContext18.rebindInnerPolies:(Lorg/eclipse/jdt/internal/compiler/lookup/MethodBinding;Lorg/eclipse/jdt/internal/compiler/lookup/InvocationSite;)Z
     436: pop
     437: goto          506
     440: aload         13
     442: invokevirtual #752                // Method org/eclipse/jdt/internal/compiler/ast/Expression.isPolyExpression:()Z
     445: ifeq          506
     448: aload         7
     450: ifnull        472
     453: aload         7
     455: getfield      #694                // Field org/eclipse/jdt/internal/compiler/lookup/InferenceContext18.stepCompleted:I
     458: iconst_3
     459: if_icmpne     472
     462: aload         13
     464: getfield      #755                // Field org/eclipse/jdt/internal/compiler/ast/Expression.resolvedType:Lorg/eclipse/jdt/internal/compiler/lookup/TypeBinding;
     467: astore        14
     469: goto          482
     472: aload         13
     474: aload         15
     476: aload_3
     477: invokevirtual #758                // Method org/eclipse/jdt/internal/compiler/ast/Expression.checkAgainstFinalTargetType:(Lorg/eclipse/jdt/internal/compiler/lookup/TypeBinding;Lorg/eclipse/jdt/internal/compiler/lookup/Scope;)Lorg/eclipse/jdt/internal/compiler/lookup/TypeBinding;
     480: astore        14
     482: iload         4
     484: ifne          506
     487: aload         14
     489: ifnull        506
     492: aload         14
     494: instanceof    #762                // class org/eclipse/jdt/internal/compiler/lookup/PolyTypeBinding
     497: ifne          506
     500: aload_2
     501: iload         11
     503: aload         14
     505: aastore
     506: iinc          11, 1
     509: iload         11
     511: iload         12
     513: if_icmplt     233
     516: aload_0
     517: invokeinterface #764,  1          // InterfaceMethod org/eclipse/jdt/internal/compiler/ast/Invocation.innerUpdateDone:()V
     522: return

  public static void resolvePolyExpressionArguments(org.eclipse.jdt.internal.compiler.ast.Invocation, org.eclipse.jdt.internal.compiler.lookup.MethodBinding, org.eclipse.jdt.internal.compiler.lookup.Scope);
    Code:
       0: aconst_null
       1: astore_3
       2: aload_0
       3: invokeinterface #708,  1          // InterfaceMethod org/eclipse/jdt/internal/compiler/ast/Invocation.arguments:()[Lorg/eclipse/jdt/internal/compiler/ast/Expression;
       8: astore        4
      10: aload         4
      12: ifnull        51
      15: aload         4
      17: arraylength
      18: anewarray     #296                // class org/eclipse/jdt/internal/compiler/lookup/TypeBinding
      21: astore_3
      22: iconst_0
      23: istore        5
      25: goto          43
      28: aload_3
      29: iload         5
      31: aload         4
      33: iload         5
      35: aaload
      36: getfield      #755                // Field org/eclipse/jdt/internal/compiler/ast/Expression.resolvedType:Lorg/eclipse/jdt/internal/compiler/lookup/TypeBinding;
      39: aastore
      40: iinc          5, 1
      43: iload         5
      45: aload         4
      47: arraylength
      48: if_icmplt     28
      51: aload_0
      52: aload_1
      53: aload_3
      54: aload_2
      55: invokestatic  #783                // Method resolvePolyExpressionArguments:(Lorg/eclipse/jdt/internal/compiler/ast/Invocation;Lorg/eclipse/jdt/internal/compiler/lookup/MethodBinding;[Lorg/eclipse/jdt/internal/compiler/lookup/TypeBinding;Lorg/eclipse/jdt/internal/compiler/lookup/Scope;)V
      58: return

  public static void resolveAnnotations(org.eclipse.jdt.internal.compiler.lookup.BlockScope, org.eclipse.jdt.internal.compiler.ast.Annotation[], org.eclipse.jdt.internal.compiler.lookup.Binding);
    Code:
       0: aload_0
       1: aload_1
       2: aload_2
       3: iconst_0
       4: invokestatic  #787                // Method resolveAnnotations:(Lorg/eclipse/jdt/internal/compiler/lookup/BlockScope;[Lorg/eclipse/jdt/internal/compiler/ast/Annotation;Lorg/eclipse/jdt/internal/compiler/lookup/Binding;Z)[Lorg/eclipse/jdt/internal/compiler/lookup/AnnotationBinding;
       7: pop
       8: return

  public static org.eclipse.jdt.internal.compiler.lookup.AnnotationBinding[] resolveAnnotations(org.eclipse.jdt.internal.compiler.lookup.BlockScope, org.eclipse.jdt.internal.compiler.ast.Annotation[], org.eclipse.jdt.internal.compiler.lookup.Binding, boolean);
    Code:
       0: aconst_null
       1: astore        4
       3: aload_1
       4: ifnonnull     11
       7: iconst_0
       8: goto          13
      11: aload_1
      12: arraylength
      13: istore        5
      15: aload_2
      16: ifnull        381
      19: aload_2
      20: invokevirtual #793                // Method org/eclipse/jdt/internal/compiler/lookup/Binding.kind:()I
      23: lookupswitch  { // 8
                     1: 251
                     2: 309
                     4: 135
                     8: 193
                    16: 96
                  2052: 135
                  4100: 368
                 16388: 368
               default: 378
          }
      96: aload_2
      97: checkcast     #796                // class org/eclipse/jdt/internal/compiler/lookup/PackageBinding
     100: astore        6
     102: aload         6
     104: getfield      #798                // Field org/eclipse/jdt/internal/compiler/lookup/PackageBinding.tagBits:J
     107: ldc2_w        #85                 // long 8589934592l
     110: land
     111: lconst_0
     112: lcmp
     113: ifeq          119
     116: aload         4
     118: areturn
     119: aload         6
     121: dup
     122: getfield      #798                // Field org/eclipse/jdt/internal/compiler/lookup/PackageBinding.tagBits:J
     125: ldc2_w        #799                // long 25769803776l
     128: lor
     129: putfield      #798                // Field org/eclipse/jdt/internal/compiler/lookup/PackageBinding.tagBits:J
     132: goto          381
     135: aload_2
     136: checkcast     #376                // class org/eclipse/jdt/internal/compiler/lookup/ReferenceBinding
     139: astore        7
     141: aload         7
     143: getfield      #801                // Field org/eclipse/jdt/internal/compiler/lookup/ReferenceBinding.tagBits:J
     146: ldc2_w        #85                 // long 8589934592l
     149: land
     150: lconst_0
     151: lcmp
     152: ifeq          158
     155: aload         4
     157: areturn
     158: aload         7
     160: dup
     161: getfield      #801                // Field org/eclipse/jdt/internal/compiler/lookup/ReferenceBinding.tagBits:J
     164: ldc2_w        #799                // long 25769803776l
     167: lor
     168: putfield      #801                // Field org/eclipse/jdt/internal/compiler/lookup/ReferenceBinding.tagBits:J
     171: iload         5
     173: ifle          381
     176: iload         5
     178: anewarray     #802                // class org/eclipse/jdt/internal/compiler/lookup/AnnotationBinding
     181: astore        4
     183: aload         7
     185: aload         4
     187: invokevirtual #804                // Method org/eclipse/jdt/internal/compiler/lookup/ReferenceBinding.setAnnotations:([Lorg/eclipse/jdt/internal/compiler/lookup/AnnotationBinding;)V
     190: goto          381
     193: aload_2
     194: checkcast     #356                // class org/eclipse/jdt/internal/compiler/lookup/MethodBinding
     197: astore        8
     199: aload         8
     201: getfield      #383                // Field org/eclipse/jdt/internal/compiler/lookup/MethodBinding.tagBits:J
     204: ldc2_w        #85                 // long 8589934592l
     207: land
     208: lconst_0
     209: lcmp
     210: ifeq          216
     213: aload         4
     215: areturn
     216: aload         8
     218: dup
     219: getfield      #383                // Field org/eclipse/jdt/internal/compiler/lookup/MethodBinding.tagBits:J
     222: ldc2_w        #799                // long 25769803776l
     225: lor
     226: putfield      #383                // Field org/eclipse/jdt/internal/compiler/lookup/MethodBinding.tagBits:J
     229: iload         5
     231: ifle          381
     234: iload         5
     236: anewarray     #802                // class org/eclipse/jdt/internal/compiler/lookup/AnnotationBinding
     239: astore        4
     241: aload         8
     243: aload         4
     245: invokevirtual #808                // Method org/eclipse/jdt/internal/compiler/lookup/MethodBinding.setAnnotations:([Lorg/eclipse/jdt/internal/compiler/lookup/AnnotationBinding;)V
     248: goto          381
     251: aload_2
     252: checkcast     #506                // class org/eclipse/jdt/internal/compiler/lookup/FieldBinding
     255: astore        9
     257: aload         9
     259: getfield      #809                // Field org/eclipse/jdt/internal/compiler/lookup/FieldBinding.tagBits:J
     262: ldc2_w        #85                 // long 8589934592l
     265: land
     266: lconst_0
     267: lcmp
     268: ifeq          274
     271: aload         4
     273: areturn
     274: aload         9
     276: dup
     277: getfield      #809                // Field org/eclipse/jdt/internal/compiler/lookup/FieldBinding.tagBits:J
     280: ldc2_w        #799                // long 25769803776l
     283: lor
     284: putfield      #809                // Field org/eclipse/jdt/internal/compiler/lookup/FieldBinding.tagBits:J
     287: iload         5
     289: ifle          381
     292: iload         5
     294: anewarray     #802                // class org/eclipse/jdt/internal/compiler/lookup/AnnotationBinding
     297: astore        4
     299: aload         9
     301: aload         4
     303: invokevirtual #810                // Method org/eclipse/jdt/internal/compiler/lookup/FieldBinding.setAnnotations:([Lorg/eclipse/jdt/internal/compiler/lookup/AnnotationBinding;)V
     306: goto          381
     309: aload_2
     310: checkcast     #811                // class org/eclipse/jdt/internal/compiler/lookup/LocalVariableBinding
     313: astore        10
     315: aload         10
     317: getfield      #813                // Field org/eclipse/jdt/internal/compiler/lookup/LocalVariableBinding.tagBits:J
     320: ldc2_w        #85                 // long 8589934592l
     323: land
     324: lconst_0
     325: lcmp
     326: ifeq          332
     329: aload         4
     331: areturn
     332: aload         10
     334: dup
     335: getfield      #813                // Field org/eclipse/jdt/internal/compiler/lookup/LocalVariableBinding.tagBits:J
     338: ldc2_w        #799                // long 25769803776l
     341: lor
     342: putfield      #813                // Field org/eclipse/jdt/internal/compiler/lookup/LocalVariableBinding.tagBits:J
     345: iload         5
     347: ifle          381
     350: iload         5
     352: anewarray     #802                // class org/eclipse/jdt/internal/compiler/lookup/AnnotationBinding
     355: astore        4
     357: aload         10
     359: aload         4
     361: aload_0
     362: invokevirtual #814                // Method org/eclipse/jdt/internal/compiler/lookup/LocalVariableBinding.setAnnotations:([Lorg/eclipse/jdt/internal/compiler/lookup/AnnotationBinding;Lorg/eclipse/jdt/internal/compiler/lookup/Scope;)V
     365: goto          381
     368: iload         5
     370: anewarray     #802                // class org/eclipse/jdt/internal/compiler/lookup/AnnotationBinding
     373: astore        4
     375: goto          381
     378: aload         4
     380: areturn
     381: aload_1
     382: ifnonnull     388
     385: aload         4
     387: areturn
     388: iconst_0
     389: istore        6
     391: goto          765
     394: aload_1
     395: iload         6
     397: aaload
     398: astore        7
     400: aload         7
     402: getfield      #817                // Field org/eclipse/jdt/internal/compiler/ast/Annotation.recipient:Lorg/eclipse/jdt/internal/compiler/lookup/Binding;
     405: astore        8
     407: aload         8
     409: ifnull        734
     412: aload_2
     413: ifnull        734
     416: aload_2
     417: invokevirtual #793                // Method org/eclipse/jdt/internal/compiler/lookup/Binding.kind:()I
     420: lookupswitch  { // 3
                     1: 492
                     2: 551
                 16388: 456
               default: 731
          }
     456: aload         4
     458: ifnull        731
     461: iconst_0
     462: istore        9
     464: goto          482
     467: aload         4
     469: iload         9
     471: aload_1
     472: iload         9
     474: aaload
     475: invokevirtual #819                // Method org/eclipse/jdt/internal/compiler/ast/Annotation.getCompilerAnnotation:()Lorg/eclipse/jdt/internal/compiler/lookup/AnnotationBinding;
     478: aastore
     479: iinc          9, 1
     482: iload         9
     484: iload         5
     486: if_icmplt     467
     489: goto          731
     492: aload_2
     493: checkcast     #506                // class org/eclipse/jdt/internal/compiler/lookup/FieldBinding
     496: astore        9
     498: aload         9
     500: aload         8
     502: checkcast     #506                // class org/eclipse/jdt/internal/compiler/lookup/FieldBinding
     505: getfield      #809                // Field org/eclipse/jdt/internal/compiler/lookup/FieldBinding.tagBits:J
     508: putfield      #809                // Field org/eclipse/jdt/internal/compiler/lookup/FieldBinding.tagBits:J
     511: aload         4
     513: ifnull        731
     516: iconst_0
     517: istore        10
     519: goto          541
     522: aload_1
     523: iload         10
     525: aaload
     526: astore        11
     528: aload         4
     530: iload         10
     532: aload         11
     534: invokevirtual #819                // Method org/eclipse/jdt/internal/compiler/ast/Annotation.getCompilerAnnotation:()Lorg/eclipse/jdt/internal/compiler/lookup/AnnotationBinding;
     537: aastore
     538: iinc          10, 1
     541: iload         10
     543: iload         5
     545: if_icmplt     522
     548: goto          731
     551: aload_2
     552: checkcast     #811                // class org/eclipse/jdt/internal/compiler/lookup/LocalVariableBinding
     555: astore        10
     557: aload         8
     559: checkcast     #811                // class org/eclipse/jdt/internal/compiler/lookup/LocalVariableBinding
     562: getfield      #813                // Field org/eclipse/jdt/internal/compiler/lookup/LocalVariableBinding.tagBits:J
     565: lstore        11
     567: aload         10
     569: lload         11
     571: putfield      #813                // Field org/eclipse/jdt/internal/compiler/lookup/LocalVariableBinding.tagBits:J
     574: lload         11
     576: ldc2_w        #136                // long 1125899906842624l
     579: land
     580: lconst_0
     581: lcmp
     582: ifne          625
     585: aload         4
     587: ifnull        731
     590: iconst_0
     591: istore        13
     593: goto          615
     596: aload_1
     597: iload         13
     599: aaload
     600: astore        14
     602: aload         4
     604: iload         13
     606: aload         14
     608: invokevirtual #819                // Method org/eclipse/jdt/internal/compiler/ast/Annotation.getCompilerAnnotation:()Lorg/eclipse/jdt/internal/compiler/lookup/AnnotationBinding;
     611: aastore
     612: iinc          13, 1
     615: iload         13
     617: iload         5
     619: if_icmplt     596
     622: goto          731
     625: aload         4
     627: ifnull        731
     630: aload         10
     632: getfield      #823                // Field org/eclipse/jdt/internal/compiler/lookup/LocalVariableBinding.declaration:Lorg/eclipse/jdt/internal/compiler/ast/LocalDeclaration;
     635: astore        13
     637: aload         13
     639: getfield      #827                // Field org/eclipse/jdt/internal/compiler/ast/LocalDeclaration.declarationSourceEnd:I
     642: istore        14
     644: aload         13
     646: getfield      #832                // Field org/eclipse/jdt/internal/compiler/ast/LocalDeclaration.declarationSourceStart:I
     649: istore        15
     651: iconst_0
     652: istore        16
     654: goto          724
     657: aload_1
     658: iload         16
     660: aaload
     661: astore        17
     663: aload         17
     665: invokevirtual #819                // Method org/eclipse/jdt/internal/compiler/ast/Annotation.getCompilerAnnotation:()Lorg/eclipse/jdt/internal/compiler/lookup/AnnotationBinding;
     668: astore        18
     670: aload         4
     672: iload         16
     674: aload         18
     676: aastore
     677: aload         18
     679: ifnull        721
     682: aload         18
     684: invokevirtual #835                // Method org/eclipse/jdt/internal/compiler/lookup/AnnotationBinding.getAnnotationType:()Lorg/eclipse/jdt/internal/compiler/lookup/ReferenceBinding;
     687: astore        19
     689: aload         19
     691: ifnull        721
     694: aload         19
     696: getfield      #839                // Field org/eclipse/jdt/internal/compiler/lookup/ReferenceBinding.id:I
     699: bipush        49
     701: if_icmpne     721
     704: aload         17
     706: aload_0
     707: iload         15
     709: iload         14
     711: aload_0
     712: invokevirtual #344                // Method org/eclipse/jdt/internal/compiler/lookup/BlockScope.compilerOptions:()Lorg/eclipse/jdt/internal/compiler/impl/CompilerOptions;
     715: getfield      #842                // Field org/eclipse/jdt/internal/compiler/impl/CompilerOptions.suppressWarnings:Z
     718: invokevirtual #845                // Method org/eclipse/jdt/internal/compiler/ast/Annotation.recordSuppressWarnings:(Lorg/eclipse/jdt/internal/compiler/lookup/Scope;IIZ)V
     721: iinc          16, 1
     724: iload         16
     726: iload         5
     728: if_icmplt     657
     731: aload         4
     733: areturn
     734: aload         7
     736: aload_2
     737: putfield      #817                // Field org/eclipse/jdt/internal/compiler/ast/Annotation.recipient:Lorg/eclipse/jdt/internal/compiler/lookup/Binding;
     740: aload         7
     742: aload_0
     743: invokevirtual #849                // Method org/eclipse/jdt/internal/compiler/ast/Annotation.resolveType:(Lorg/eclipse/jdt/internal/compiler/lookup/BlockScope;)Lorg/eclipse/jdt/internal/compiler/lookup/TypeBinding;
     746: pop
     747: aload         4
     749: ifnull        762
     752: aload         4
     754: iload         6
     756: aload         7
     758: invokevirtual #819                // Method org/eclipse/jdt/internal/compiler/ast/Annotation.getCompilerAnnotation:()Lorg/eclipse/jdt/internal/compiler/lookup/AnnotationBinding;
     761: aastore
     762: iinc          6, 1
     765: iload         6
     767: iload         5
     769: if_icmplt     394
     772: aload_2
     773: ifnull        848
     776: aload_2
     777: invokevirtual #853                // Method org/eclipse/jdt/internal/compiler/lookup/Binding.isTaggedRepeatable:()Z
     780: ifeq          848
     783: iconst_0
     784: istore        6
     786: goto          841
     789: aload_1
     790: iload         6
     792: aaload
     793: astore        7
     795: aload         4
     797: iload         6
     799: aaload
     800: ifnull        814
     803: aload         4
     805: iload         6
     807: aaload
     808: invokevirtual #835                // Method org/eclipse/jdt/internal/compiler/lookup/AnnotationBinding.getAnnotationType:()Lorg/eclipse/jdt/internal/compiler/lookup/ReferenceBinding;
     811: goto          815
     814: aconst_null
     815: astore        8
     817: aload         8
     819: ifnull        838
     822: aload         8
     824: getfield      #839                // Field org/eclipse/jdt/internal/compiler/lookup/ReferenceBinding.id:I
     827: bipush        90
     829: if_icmpne     838
     832: aload         7
     834: aload_0
     835: invokevirtual #856                // Method org/eclipse/jdt/internal/compiler/ast/Annotation.checkRepeatableMetaAnnotation:(Lorg/eclipse/jdt/internal/compiler/lookup/BlockScope;)V
     838: iinc          6, 1
     841: iload         6
     843: iload         5
     845: if_icmplt     789
     848: aload         4
     850: ifnull        1232
     853: iload         5
     855: iconst_1
     856: if_icmple     1232
     859: aload         4
     861: astore        6
     863: aconst_null
     864: astore        7
     866: iconst_0
     867: istore        8
     869: goto          1144
     872: aload         6
     874: iload         8
     876: aaload
     877: astore        9
     879: aload         9
     881: ifnonnull     887
     884: goto          1141
     887: aload         9
     889: invokevirtual #835                // Method org/eclipse/jdt/internal/compiler/lookup/AnnotationBinding.getAnnotationType:()Lorg/eclipse/jdt/internal/compiler/lookup/ReferenceBinding;
     892: astore        10
     894: iconst_0
     895: istore        11
     897: aconst_null
     898: astore        12
     900: iload         8
     902: iconst_1
     903: iadd
     904: istore        13
     906: goto          1099
     909: aload         6
     911: iload         13
     913: aaload
     914: astore        14
     916: aload         14
     918: ifnonnull     924
     921: goto          1096
     924: aload         14
     926: invokevirtual #835                // Method org/eclipse/jdt/internal/compiler/lookup/AnnotationBinding.getAnnotationType:()Lorg/eclipse/jdt/internal/compiler/lookup/ReferenceBinding;
     929: aload         10
     931: invokestatic  #860                // Method org/eclipse/jdt/internal/compiler/lookup/TypeBinding.equalsEquals:(Lorg/eclipse/jdt/internal/compiler/lookup/TypeBinding;Lorg/eclipse/jdt/internal/compiler/lookup/TypeBinding;)Z
     934: ifeq          1096
     937: aload         6
     939: aload         4
     941: if_acmpne     961
     944: aload         6
     946: iconst_0
     947: iload         5
     949: anewarray     #802                // class org/eclipse/jdt/internal/compiler/lookup/AnnotationBinding
     952: dup
     953: astore        6
     955: iconst_0
     956: iload         5
     958: invokestatic  #863                // Method java/lang/System.arraycopy:(Ljava/lang/Object;ILjava/lang/Object;II)V
     961: aload         6
     963: iload         13
     965: aconst_null
     966: aastore
     967: aload         10
     969: invokevirtual #869                // Method org/eclipse/jdt/internal/compiler/lookup/ReferenceBinding.isRepeatableAnnotationType:()Z
     972: ifeq          1075
     975: aload_1
     976: iload         8
     978: aaload
     979: invokevirtual #872                // Method org/eclipse/jdt/internal/compiler/ast/Annotation.getPersistibleAnnotation:()Lorg/eclipse/jdt/internal/compiler/ast/Annotation;
     982: astore        15
     984: aload         15
     986: instanceof    #876                // class org/eclipse/jdt/internal/compiler/ast/ContainerAnnotation
     989: ifeq          999
     992: aload         15
     994: checkcast     #876                // class org/eclipse/jdt/internal/compiler/ast/ContainerAnnotation
     997: astore        12
     999: aload         12
    1001: ifnonnull     1063
    1004: aload         10
    1006: invokevirtual #878                // Method org/eclipse/jdt/internal/compiler/lookup/ReferenceBinding.containerAnnotationType:()Lorg/eclipse/jdt/internal/compiler/lookup/ReferenceBinding;
    1009: astore        16
    1011: new           #876                // class org/eclipse/jdt/internal/compiler/ast/ContainerAnnotation
    1014: dup
    1015: aload_1
    1016: iload         8
    1018: aaload
    1019: aload         16
    1021: aload_0
    1022: invokespecial #881                // Method org/eclipse/jdt/internal/compiler/ast/ContainerAnnotation."<init>":(Lorg/eclipse/jdt/internal/compiler/ast/Annotation;Lorg/eclipse/jdt/internal/compiler/lookup/ReferenceBinding;Lorg/eclipse/jdt/internal/compiler/lookup/BlockScope;)V
    1025: astore        12
    1027: aload         7
    1029: ifnonnull     1042
    1032: new           #884                // class java/util/HashMap
    1035: dup
    1036: iconst_3
    1037: invokespecial #886                // Method java/util/HashMap."<init>":(I)V
    1040: astore        7
    1042: aload         7
    1044: aload         16
    1046: aload_1
    1047: iload         8
    1049: aaload
    1050: invokeinterface #889,  3          // InterfaceMethod java/util/Map.put:(Ljava/lang/Object;Ljava/lang/Object;)Ljava/lang/Object;
    1055: pop
    1056: aload_0
    1057: aload         10
    1059: aload_1
    1060: invokestatic  #895                // Method org/eclipse/jdt/internal/compiler/ast/Annotation.checkForInstancesOfRepeatableWithRepeatingContainerAnnotation:(Lorg/eclipse/jdt/internal/compiler/lookup/BlockScope;Lorg/eclipse/jdt/internal/compiler/lookup/ReferenceBinding;[Lorg/eclipse/jdt/internal/compiler/ast/Annotation;)V
    1063: aload         12
    1065: aload_1
    1066: iload         13
    1068: aaload
    1069: invokevirtual #899                // Method org/eclipse/jdt/internal/compiler/ast/ContainerAnnotation.addContainee:(Lorg/eclipse/jdt/internal/compiler/ast/Annotation;)V
    1072: goto          1096
    1075: iconst_1
    1076: istore        11
    1078: aload_0
    1079: invokevirtual #318                // Method org/eclipse/jdt/internal/compiler/lookup/BlockScope.problemReporter:()Lorg/eclipse/jdt/internal/compiler/problem/ProblemReporter;
    1082: aload_1
    1083: iload         13
    1085: aaload
    1086: aload_0
    1087: invokevirtual #344                // Method org/eclipse/jdt/internal/compiler/lookup/BlockScope.compilerOptions:()Lorg/eclipse/jdt/internal/compiler/impl/CompilerOptions;
    1090: getfield      #348                // Field org/eclipse/jdt/internal/compiler/impl/CompilerOptions.sourceLevel:J
    1093: invokevirtual #903                // Method org/eclipse/jdt/internal/compiler/problem/ProblemReporter.duplicateAnnotation:(Lorg/eclipse/jdt/internal/compiler/ast/Annotation;J)V
    1096: iinc          13, 1
    1099: iload         13
    1101: iload         5
    1103: if_icmplt     909
    1106: aload         12
    1108: ifnull        1118
    1111: aload         12
    1113: aload_0
    1114: invokevirtual #907                // Method org/eclipse/jdt/internal/compiler/ast/ContainerAnnotation.resolveType:(Lorg/eclipse/jdt/internal/compiler/lookup/BlockScope;)Lorg/eclipse/jdt/internal/compiler/lookup/TypeBinding;
    1117: pop
    1118: iload         11
    1120: ifeq          1141
    1123: aload_0
    1124: invokevirtual #318                // Method org/eclipse/jdt/internal/compiler/lookup/BlockScope.problemReporter:()Lorg/eclipse/jdt/internal/compiler/problem/ProblemReporter;
    1127: aload_1
    1128: iload         8
    1130: aaload
    1131: aload_0
    1132: invokevirtual #344                // Method org/eclipse/jdt/internal/compiler/lookup/BlockScope.compilerOptions:()Lorg/eclipse/jdt/internal/compiler/impl/CompilerOptions;
    1135: getfield      #348                // Field org/eclipse/jdt/internal/compiler/impl/CompilerOptions.sourceLevel:J
    1138: invokevirtual #903                // Method org/eclipse/jdt/internal/compiler/problem/ProblemReporter.duplicateAnnotation:(Lorg/eclipse/jdt/internal/compiler/ast/Annotation;J)V
    1141: iinc          8, 1
    1144: iload         8
    1146: iload         5
    1148: if_icmplt     872
    1151: aload         7
    1153: ifnull        1232
    1156: iconst_0
    1157: istore        8
    1159: goto          1225
    1162: aload         6
    1164: iload         8
    1166: aaload
    1167: ifnonnull     1173
    1170: goto          1222
    1173: aload_1
    1174: iload         8
    1176: aaload
    1177: astore        9
    1179: aload         6
    1181: iload         8
    1183: aaload
    1184: invokevirtual #835                // Method org/eclipse/jdt/internal/compiler/lookup/AnnotationBinding.getAnnotationType:()Lorg/eclipse/jdt/internal/compiler/lookup/ReferenceBinding;
    1187: astore        10
    1189: aload         7
    1191: aload         10
    1193: invokeinterface #908,  2          // InterfaceMethod java/util/Map.containsKey:(Ljava/lang/Object;)Z
    1198: ifeq          1222
    1201: aload_0
    1202: invokevirtual #318                // Method org/eclipse/jdt/internal/compiler/lookup/BlockScope.problemReporter:()Lorg/eclipse/jdt/internal/compiler/problem/ProblemReporter;
    1205: aload         7
    1207: aload         10
    1209: invokeinterface #912,  2          // InterfaceMethod java/util/Map.get:(Ljava/lang/Object;)Ljava/lang/Object;
    1214: checkcast     #630                // class org/eclipse/jdt/internal/compiler/ast/Annotation
    1217: aload         9
    1219: invokevirtual #916                // Method org/eclipse/jdt/internal/compiler/problem/ProblemReporter.repeatedAnnotationWithContainer:(Lorg/eclipse/jdt/internal/compiler/ast/Annotation;Lorg/eclipse/jdt/internal/compiler/ast/Annotation;)V
    1222: iinc          8, 1
    1225: iload         8
    1227: iload         5
    1229: if_icmplt     1162
    1232: iload_3
    1233: ifeq          1243
    1236: aload_0
    1237: aload_2
    1238: aload_1
    1239: iconst_1
    1240: invokestatic  #920                // Method copySE8AnnotationsToType:(Lorg/eclipse/jdt/internal/compiler/lookup/BlockScope;Lorg/eclipse/jdt/internal/compiler/lookup/Binding;[Lorg/eclipse/jdt/internal/compiler/ast/Annotation;Z)V
    1243: aload         4
    1245: areturn

  public static org.eclipse.jdt.internal.compiler.lookup.TypeBinding resolveAnnotations(org.eclipse.jdt.internal.compiler.lookup.BlockScope, org.eclipse.jdt.internal.compiler.ast.Annotation[][], org.eclipse.jdt.internal.compiler.lookup.TypeBinding);
    Code:
       0: aload_1
       1: ifnonnull     8
       4: iconst_0
       5: goto          10
       8: aload_1
       9: arraylength
      10: istore_3
      11: aload_2
      12: ifnull        19
      15: iload_3
      16: ifne          21
      19: aload_2
      20: areturn
      21: iload_3
      22: anewarray     #946                // class "[Lorg/eclipse/jdt/internal/compiler/lookup/AnnotationBinding;"
      25: astore        4
      27: iconst_0
      28: istore        5
      30: goto          68
      33: aload_1
      34: iload         5
      36: aaload
      37: astore        6
      39: aload         6
      41: ifnull        65
      44: aload         6
      46: arraylength
      47: ifle          65
      50: aload         4
      52: iload         5
      54: aload_0
      55: aload         6
      57: getstatic     #949                // Field org/eclipse/jdt/internal/compiler/lookup/TypeBinding.TYPE_USE_BINDING:Lorg/eclipse/jdt/internal/compiler/lookup/ReferenceBinding;
      60: iconst_0
      61: invokestatic  #787                // Method resolveAnnotations:(Lorg/eclipse/jdt/internal/compiler/lookup/BlockScope;[Lorg/eclipse/jdt/internal/compiler/ast/Annotation;Lorg/eclipse/jdt/internal/compiler/lookup/Binding;Z)[Lorg/eclipse/jdt/internal/compiler/lookup/AnnotationBinding;
      64: aastore
      65: iinc          5, 1
      68: iload         5
      70: iload_3
      71: if_icmplt     33
      74: aload_0
      75: invokevirtual #952                // Method org/eclipse/jdt/internal/compiler/lookup/BlockScope.environment:()Lorg/eclipse/jdt/internal/compiler/lookup/LookupEnvironment;
      78: aload_2
      79: aload         4
      81: invokevirtual #953                // Method org/eclipse/jdt/internal/compiler/lookup/LookupEnvironment.createAnnotatedType:(Lorg/eclipse/jdt/internal/compiler/lookup/TypeBinding;[[Lorg/eclipse/jdt/internal/compiler/lookup/AnnotationBinding;)Lorg/eclipse/jdt/internal/compiler/lookup/TypeBinding;
      84: areturn

  public static void copySE8AnnotationsToType(org.eclipse.jdt.internal.compiler.lookup.BlockScope, org.eclipse.jdt.internal.compiler.lookup.Binding, org.eclipse.jdt.internal.compiler.ast.Annotation[], boolean);
    Code:
       0: aload_2
       1: ifnull        13
       4: aload_2
       5: arraylength
       6: ifeq          13
       9: aload_1
      10: ifnonnull     14
      13: return
      14: lconst_0
      15: lstore        4
      17: aload_1
      18: invokevirtual #793                // Method org/eclipse/jdt/internal/compiler/lookup/Binding.kind:()I
      21: lookupswitch  { // 3
                     1: 77
                     2: 56
                     8: 85
               default: 93
          }
      56: aload_1
      57: invokevirtual #962                // Method org/eclipse/jdt/internal/compiler/lookup/Binding.isParameter:()Z
      60: ifeq          69
      63: ldc2_w        #103                // long 549755813888l
      66: goto          72
      69: ldc2_w        #109                // long 2199023255552l
      72: lstore        4
      74: goto          94
      77: ldc2_w        #97                 // long 137438953472l
      80: lstore        4
      82: goto          94
      85: ldc2_w        #100                // long 274877906944l
      88: lstore        4
      90: goto          94
      93: return
      94: aconst_null
      95: astore        6
      97: iconst_0
      98: istore        7
     100: lconst_0
     101: lstore        8
     103: aconst_null
     104: astore        10
     106: iconst_m1
     107: istore        11
     109: iconst_0
     110: istore        12
     112: iconst_0
     113: istore        13
     115: aload_2
     116: arraylength
     117: istore        14
     119: goto          277
     122: aload_2
     123: iload         13
     125: aaload
     126: invokevirtual #819                // Method org/eclipse/jdt/internal/compiler/ast/Annotation.getCompilerAnnotation:()Lorg/eclipse/jdt/internal/compiler/lookup/AnnotationBinding;
     129: astore        15
     131: aload         15
     133: ifnonnull     139
     136: goto          274
     139: aload         15
     141: invokevirtual #835                // Method org/eclipse/jdt/internal/compiler/lookup/AnnotationBinding.getAnnotationType:()Lorg/eclipse/jdt/internal/compiler/lookup/ReferenceBinding;
     144: astore        16
     146: aload         16
     148: invokevirtual #965                // Method org/eclipse/jdt/internal/compiler/lookup/ReferenceBinding.getAnnotationTagBits:()J
     151: lstore        17
     153: lload         17
     155: ldc2_w        #145                // long 9007199254740992l
     158: land
     159: lconst_0
     160: lcmp
     161: ifeq          274
     164: iload         11
     166: iconst_m1
     167: if_icmpne     174
     170: iload         13
     172: istore        11
     174: iload         13
     176: istore        12
     178: aload         6
     180: ifnonnull     200
     183: iconst_1
     184: anewarray     #802                // class org/eclipse/jdt/internal/compiler/lookup/AnnotationBinding
     187: dup
     188: iconst_0
     189: aload         15
     191: aastore
     192: astore        6
     194: iconst_1
     195: istore        7
     197: goto          229
     200: aload         6
     202: iconst_0
     203: iload         7
     205: iconst_1
     206: iadd
     207: anewarray     #802                // class org/eclipse/jdt/internal/compiler/lookup/AnnotationBinding
     210: dup
     211: astore        6
     213: iconst_0
     214: iload         7
     216: invokestatic  #863                // Method java/lang/System.arraycopy:(Ljava/lang/Object;ILjava/lang/Object;II)V
     219: aload         6
     221: iload         7
     223: iinc          7, 1
     226: aload         15
     228: aastore
     229: aload         16
     231: getfield      #839                // Field org/eclipse/jdt/internal/compiler/lookup/ReferenceBinding.id:I
     234: bipush        66
     236: if_icmpne     253
     239: ldc2_w        #154                // long 72057594037927936l
     242: lstore        8
     244: aload_2
     245: iload         13
     247: aaload
     248: astore        10
     250: goto          274
     253: aload         16
     255: getfield      #839                // Field org/eclipse/jdt/internal/compiler/lookup/ReferenceBinding.id:I
     258: bipush        65
     260: if_icmpne     274
     263: ldc2_w        #151                // long 36028797018963968l
     266: lstore        8
     268: aload_2
     269: iload         13
     271: aaload
     272: astore        10
     274: iinc          13, 1
     277: iload         13
     279: iload         14
     281: if_icmplt     122
     284: aload         6
     286: ifnull        755
     289: iload_3
     290: ifne          309
     293: aload_0
     294: invokevirtual #318                // Method org/eclipse/jdt/internal/compiler/lookup/BlockScope.problemReporter:()Lorg/eclipse/jdt/internal/compiler/problem/ProblemReporter;
     297: aload_2
     298: iload         11
     300: aaload
     301: aload_2
     302: iload         12
     304: aaload
     305: invokevirtual #969                // Method org/eclipse/jdt/internal/compiler/problem/ProblemReporter.misplacedTypeAnnotations:(Lorg/eclipse/jdt/internal/compiler/ast/Annotation;Lorg/eclipse/jdt/internal/compiler/ast/Annotation;)V
     308: return
     309: aload_1
     310: invokevirtual #793                // Method org/eclipse/jdt/internal/compiler/lookup/Binding.kind:()I
     313: lookupswitch  { // 3
                     1: 425
                     2: 348
                     8: 523
               default: 629
          }
     348: aload_1
     349: checkcast     #811                // class org/eclipse/jdt/internal/compiler/lookup/LocalVariableBinding
     352: astore        13
     354: aload         13
     356: getfield      #823                // Field org/eclipse/jdt/internal/compiler/lookup/LocalVariableBinding.declaration:Lorg/eclipse/jdt/internal/compiler/ast/LocalDeclaration;
     359: getfield      #972                // Field org/eclipse/jdt/internal/compiler/ast/LocalDeclaration.type:Lorg/eclipse/jdt/internal/compiler/ast/TypeReference;
     362: astore        14
     364: aload         14
     366: aload_0
     367: invokestatic  #975                // Method org/eclipse/jdt/internal/compiler/ast/Annotation.isTypeUseCompatible:(Lorg/eclipse/jdt/internal/compiler/ast/TypeReference;Lorg/eclipse/jdt/internal/compiler/lookup/Scope;)Z
     370: ifeq          629
     373: aload         13
     375: getfield      #823                // Field org/eclipse/jdt/internal/compiler/lookup/LocalVariableBinding.declaration:Lorg/eclipse/jdt/internal/compiler/ast/LocalDeclaration;
     378: dup
     379: getfield      #979                // Field org/eclipse/jdt/internal/compiler/ast/LocalDeclaration.bits:I
     382: ldc           #54                 // int 1048576
     384: ior
     385: putfield      #979                // Field org/eclipse/jdt/internal/compiler/ast/LocalDeclaration.bits:I
     388: aload         14
     390: dup
     391: getfield      #980                // Field org/eclipse/jdt/internal/compiler/ast/TypeReference.bits:I
     394: ldc           #54                 // int 1048576
     396: ior
     397: putfield      #980                // Field org/eclipse/jdt/internal/compiler/ast/TypeReference.bits:I
     400: aload         13
     402: aload_0
     403: aload         6
     405: lload         8
     407: aload         10
     409: aload         14
     411: aload         13
     413: getfield      #983                // Field org/eclipse/jdt/internal/compiler/lookup/LocalVariableBinding.type:Lorg/eclipse/jdt/internal/compiler/lookup/TypeBinding;
     416: invokestatic  #985                // Method mergeAnnotationsIntoType:(Lorg/eclipse/jdt/internal/compiler/lookup/BlockScope;[Lorg/eclipse/jdt/internal/compiler/lookup/AnnotationBinding;JLorg/eclipse/jdt/internal/compiler/ast/Annotation;Lorg/eclipse/jdt/internal/compiler/ast/TypeReference;Lorg/eclipse/jdt/internal/compiler/lookup/TypeBinding;)Lorg/eclipse/jdt/internal/compiler/lookup/TypeBinding;
     419: putfield      #983                // Field org/eclipse/jdt/internal/compiler/lookup/LocalVariableBinding.type:Lorg/eclipse/jdt/internal/compiler/lookup/TypeBinding;
     422: goto          629
     425: aload_1
     426: checkcast     #506                // class org/eclipse/jdt/internal/compiler/lookup/FieldBinding
     429: astore        15
     431: aload         15
     433: getfield      #529                // Field org/eclipse/jdt/internal/compiler/lookup/FieldBinding.declaringClass:Lorg/eclipse/jdt/internal/compiler/lookup/ReferenceBinding;
     436: checkcast     #989                // class org/eclipse/jdt/internal/compiler/lookup/SourceTypeBinding
     439: astore        16
     441: aload         16
     443: getfield      #991                // Field org/eclipse/jdt/internal/compiler/lookup/SourceTypeBinding.scope:Lorg/eclipse/jdt/internal/compiler/lookup/ClassScope;
     446: getfield      #994                // Field org/eclipse/jdt/internal/compiler/lookup/ClassScope.referenceContext:Lorg/eclipse/jdt/internal/compiler/ast/TypeDeclaration;
     449: aload         15
     451: invokevirtual #999                // Method org/eclipse/jdt/internal/compiler/ast/TypeDeclaration.declarationOf:(Lorg/eclipse/jdt/internal/compiler/lookup/FieldBinding;)Lorg/eclipse/jdt/internal/compiler/ast/FieldDeclaration;
     454: astore        17
     456: aload         17
     458: getfield      #1005               // Field org/eclipse/jdt/internal/compiler/ast/FieldDeclaration.type:Lorg/eclipse/jdt/internal/compiler/ast/TypeReference;
     461: aload_0
     462: invokestatic  #975                // Method org/eclipse/jdt/internal/compiler/ast/Annotation.isTypeUseCompatible:(Lorg/eclipse/jdt/internal/compiler/ast/TypeReference;Lorg/eclipse/jdt/internal/compiler/lookup/Scope;)Z
     465: ifeq          629
     468: aload         17
     470: dup
     471: getfield      #1008               // Field org/eclipse/jdt/internal/compiler/ast/FieldDeclaration.bits:I
     474: ldc           #54                 // int 1048576
     476: ior
     477: putfield      #1008               // Field org/eclipse/jdt/internal/compiler/ast/FieldDeclaration.bits:I
     480: aload         17
     482: getfield      #1005               // Field org/eclipse/jdt/internal/compiler/ast/FieldDeclaration.type:Lorg/eclipse/jdt/internal/compiler/ast/TypeReference;
     485: dup
     486: getfield      #980                // Field org/eclipse/jdt/internal/compiler/ast/TypeReference.bits:I
     489: ldc           #54                 // int 1048576
     491: ior
     492: putfield      #980                // Field org/eclipse/jdt/internal/compiler/ast/TypeReference.bits:I
     495: aload         15
     497: aload_0
     498: aload         6
     500: lload         8
     502: aload         10
     504: aload         17
     506: getfield      #1005               // Field org/eclipse/jdt/internal/compiler/ast/FieldDeclaration.type:Lorg/eclipse/jdt/internal/compiler/ast/TypeReference;
     509: aload         15
     511: getfield      #1009               // Field org/eclipse/jdt/internal/compiler/lookup/FieldBinding.type:Lorg/eclipse/jdt/internal/compiler/lookup/TypeBinding;
     514: invokestatic  #985                // Method mergeAnnotationsIntoType:(Lorg/eclipse/jdt/internal/compiler/lookup/BlockScope;[Lorg/eclipse/jdt/internal/compiler/lookup/AnnotationBinding;JLorg/eclipse/jdt/internal/compiler/ast/Annotation;Lorg/eclipse/jdt/internal/compiler/ast/TypeReference;Lorg/eclipse/jdt/internal/compiler/lookup/TypeBinding;)Lorg/eclipse/jdt/internal/compiler/lookup/TypeBinding;
     517: putfield      #1009               // Field org/eclipse/jdt/internal/compiler/lookup/FieldBinding.type:Lorg/eclipse/jdt/internal/compiler/lookup/TypeBinding;
     520: goto          629
     523: aload_1
     524: checkcast     #356                // class org/eclipse/jdt/internal/compiler/lookup/MethodBinding
     527: astore        18
     529: aload         18
     531: invokevirtual #1010               // Method org/eclipse/jdt/internal/compiler/lookup/MethodBinding.isConstructor:()Z
     534: ifne          629
     537: aload         18
     539: getfield      #371                // Field org/eclipse/jdt/internal/compiler/lookup/MethodBinding.declaringClass:Lorg/eclipse/jdt/internal/compiler/lookup/ReferenceBinding;
     542: checkcast     #989                // class org/eclipse/jdt/internal/compiler/lookup/SourceTypeBinding
     545: astore        16
     547: aload         16
     549: getfield      #991                // Field org/eclipse/jdt/internal/compiler/lookup/SourceTypeBinding.scope:Lorg/eclipse/jdt/internal/compiler/lookup/ClassScope;
     552: getfield      #994                // Field org/eclipse/jdt/internal/compiler/lookup/ClassScope.referenceContext:Lorg/eclipse/jdt/internal/compiler/ast/TypeDeclaration;
     555: aload         18
     557: invokevirtual #1013               // Method org/eclipse/jdt/internal/compiler/ast/TypeDeclaration.declarationOf:(Lorg/eclipse/jdt/internal/compiler/lookup/MethodBinding;)Lorg/eclipse/jdt/internal/compiler/ast/AbstractMethodDeclaration;
     560: checkcast     #1016               // class org/eclipse/jdt/internal/compiler/ast/MethodDeclaration
     563: astore        19
     565: aload         19
     567: getfield      #1018               // Field org/eclipse/jdt/internal/compiler/ast/MethodDeclaration.returnType:Lorg/eclipse/jdt/internal/compiler/ast/TypeReference;
     570: aload_0
     571: invokestatic  #975                // Method org/eclipse/jdt/internal/compiler/ast/Annotation.isTypeUseCompatible:(Lorg/eclipse/jdt/internal/compiler/ast/TypeReference;Lorg/eclipse/jdt/internal/compiler/lookup/Scope;)Z
     574: ifeq          629
     577: aload         19
     579: dup
     580: getfield      #1021               // Field org/eclipse/jdt/internal/compiler/ast/MethodDeclaration.bits:I
     583: ldc           #54                 // int 1048576
     585: ior
     586: putfield      #1021               // Field org/eclipse/jdt/internal/compiler/ast/MethodDeclaration.bits:I
     589: aload         19
     591: getfield      #1018               // Field org/eclipse/jdt/internal/compiler/ast/MethodDeclaration.returnType:Lorg/eclipse/jdt/internal/compiler/ast/TypeReference;
     594: dup
     595: getfield      #980                // Field org/eclipse/jdt/internal/compiler/ast/TypeReference.bits:I
     598: ldc           #54                 // int 1048576
     600: ior
     601: putfield      #980                // Field org/eclipse/jdt/internal/compiler/ast/TypeReference.bits:I
     604: aload         18
     606: aload_0
     607: aload         6
     609: lload         8
     611: aload         10
     613: aload         19
     615: getfield      #1018               // Field org/eclipse/jdt/internal/compiler/ast/MethodDeclaration.returnType:Lorg/eclipse/jdt/internal/compiler/ast/TypeReference;
     618: aload         18
     620: getfield      #1022               // Field org/eclipse/jdt/internal/compiler/lookup/MethodBinding.returnType:Lorg/eclipse/jdt/internal/compiler/lookup/TypeBinding;
     623: invokestatic  #985                // Method mergeAnnotationsIntoType:(Lorg/eclipse/jdt/internal/compiler/lookup/BlockScope;[Lorg/eclipse/jdt/internal/compiler/lookup/AnnotationBinding;JLorg/eclipse/jdt/internal/compiler/ast/Annotation;Lorg/eclipse/jdt/internal/compiler/ast/TypeReference;Lorg/eclipse/jdt/internal/compiler/lookup/TypeBinding;)Lorg/eclipse/jdt/internal/compiler/lookup/TypeBinding;
     626: putfield      #1022               // Field org/eclipse/jdt/internal/compiler/lookup/MethodBinding.returnType:Lorg/eclipse/jdt/internal/compiler/lookup/TypeBinding;
     629: aload_1
     630: invokevirtual #1024               // Method org/eclipse/jdt/internal/compiler/lookup/Binding.getAnnotations:()[Lorg/eclipse/jdt/internal/compiler/lookup/AnnotationBinding;
     633: astore        13
     635: aload         13
     637: ifnonnull     644
     640: iconst_0
     641: goto          647
     644: aload         13
     646: arraylength
     647: istore        14
     649: iconst_0
     650: istore        15
     652: iconst_0
     653: istore        16
     655: goto          717
     658: aload         13
     660: iload         16
     662: aaload
     663: astore        17
     665: aload         17
     667: ifnonnull     673
     670: goto          714
     673: aload         17
     675: invokevirtual #835                // Method org/eclipse/jdt/internal/compiler/lookup/AnnotationBinding.getAnnotationType:()Lorg/eclipse/jdt/internal/compiler/lookup/ReferenceBinding;
     678: invokevirtual #965                // Method org/eclipse/jdt/internal/compiler/lookup/ReferenceBinding.getAnnotationTagBits:()J
     681: ldc2_w        #1028               // long 27039155590529024l
     684: land
     685: lstore        18
     687: lload         18
     689: lconst_0
     690: lcmp
     691: ifeq          704
     694: lload         18
     696: lload         4
     698: land
     699: lconst_0
     700: lcmp
     701: ifeq          714
     704: aload         13
     706: iload         15
     708: iinc          15, 1
     711: aload         17
     713: aastore
     714: iinc          16, 1
     717: iload         16
     719: iload         14
     721: if_icmplt     658
     724: iload         15
     726: iload         14
     728: if_icmpeq     755
     731: aload         13
     733: iconst_0
     734: iload         15
     736: anewarray     #802                // class org/eclipse/jdt/internal/compiler/lookup/AnnotationBinding
     739: dup
     740: astore        13
     742: iconst_0
     743: iload         15
     745: invokestatic  #863                // Method java/lang/System.arraycopy:(Ljava/lang/Object;ILjava/lang/Object;II)V
     748: aload_1
     749: aload         13
     751: aload_0
     752: invokevirtual #1030               // Method org/eclipse/jdt/internal/compiler/lookup/Binding.setAnnotations:([Lorg/eclipse/jdt/internal/compiler/lookup/AnnotationBinding;Lorg/eclipse/jdt/internal/compiler/lookup/Scope;)V
     755: return

  private static org.eclipse.jdt.internal.compiler.lookup.TypeBinding mergeAnnotationsIntoType(org.eclipse.jdt.internal.compiler.lookup.BlockScope, org.eclipse.jdt.internal.compiler.lookup.AnnotationBinding[], long, org.eclipse.jdt.internal.compiler.ast.Annotation, org.eclipse.jdt.internal.compiler.ast.TypeReference, org.eclipse.jdt.internal.compiler.lookup.TypeBinding);
    Code:
       0: aload         6
       2: ifnull        13
       5: aload         6
       7: invokevirtual #1051               // Method org/eclipse/jdt/internal/compiler/lookup/TypeBinding.isValidBinding:()Z
      10: ifne          16
      13: aload         6
      15: areturn
      16: aload         5
      18: invokevirtual #1052               // Method org/eclipse/jdt/internal/compiler/ast/TypeReference.isUnionType:()Z
      21: ifeq          37
      24: aload         5
      26: checkcast     #1055               // class org/eclipse/jdt/internal/compiler/ast/UnionTypeReference
      29: getfield      #1057               // Field org/eclipse/jdt/internal/compiler/ast/UnionTypeReference.typeReferences:[Lorg/eclipse/jdt/internal/compiler/ast/TypeReference;
      32: iconst_0
      33: aaload
      34: goto          38
      37: aconst_null
      38: astore        7
      40: aload         6
      42: invokevirtual #432                // Method org/eclipse/jdt/internal/compiler/lookup/TypeBinding.leafComponentType:()Lorg/eclipse/jdt/internal/compiler/lookup/TypeBinding;
      45: getfield      #1061               // Field org/eclipse/jdt/internal/compiler/lookup/TypeBinding.tagBits:J
      48: ldc2_w        #1062               // long 108086391056891904l
      51: land
      52: lstore        8
      54: lload_2
      55: lconst_0
      56: lcmp
      57: ifeq          87
      60: lload         8
      62: lload_2
      63: lcmp
      64: ifeq          87
      67: lload         8
      69: lload_2
      70: lor
      71: ldc2_w        #1062               // long 108086391056891904l
      74: lcmp
      75: ifne          87
      78: aload_0
      79: invokevirtual #318                // Method org/eclipse/jdt/internal/compiler/lookup/BlockScope.problemReporter:()Lorg/eclipse/jdt/internal/compiler/problem/ProblemReporter;
      82: aload         4
      84: invokevirtual #1064               // Method org/eclipse/jdt/internal/compiler/problem/ProblemReporter.contradictoryNullAnnotations:(Lorg/eclipse/jdt/internal/compiler/ast/Annotation;)V
      87: aload         7
      89: ifnonnull     100
      92: aload         6
      94: invokevirtual #432                // Method org/eclipse/jdt/internal/compiler/lookup/TypeBinding.leafComponentType:()Lorg/eclipse/jdt/internal/compiler/lookup/TypeBinding;
      97: goto          105
     100: aload         7
     102: getfield      #1067               // Field org/eclipse/jdt/internal/compiler/ast/TypeReference.resolvedType:Lorg/eclipse/jdt/internal/compiler/lookup/TypeBinding;
     105: astore        10
     107: aload         5
     109: invokevirtual #1068               // Method org/eclipse/jdt/internal/compiler/ast/TypeReference.getAnnotatableLevels:()I
     112: anewarray     #946                // class "[Lorg/eclipse/jdt/internal/compiler/lookup/AnnotationBinding;"
     115: astore        11
     117: aload         11
     119: iconst_0
     120: aload_1
     121: aastore
     122: aload_0
     123: invokevirtual #952                // Method org/eclipse/jdt/internal/compiler/lookup/BlockScope.environment:()Lorg/eclipse/jdt/internal/compiler/lookup/LookupEnvironment;
     126: aload         10
     128: aload         11
     130: invokevirtual #953                // Method org/eclipse/jdt/internal/compiler/lookup/LookupEnvironment.createAnnotatedType:(Lorg/eclipse/jdt/internal/compiler/lookup/TypeBinding;[[Lorg/eclipse/jdt/internal/compiler/lookup/AnnotationBinding;)Lorg/eclipse/jdt/internal/compiler/lookup/TypeBinding;
     133: astore        12
     135: aload         7
     137: ifnonnull     180
     140: aload         5
     142: aload         6
     144: invokevirtual #595                // Method org/eclipse/jdt/internal/compiler/lookup/TypeBinding.isArrayType:()Z
     147: ifeq          172
     150: aload_0
     151: invokevirtual #952                // Method org/eclipse/jdt/internal/compiler/lookup/BlockScope.environment:()Lorg/eclipse/jdt/internal/compiler/lookup/LookupEnvironment;
     154: aload         12
     156: aload         6
     158: invokevirtual #416                // Method org/eclipse/jdt/internal/compiler/lookup/TypeBinding.dimensions:()I
     161: aload         6
     163: invokevirtual #1071               // Method org/eclipse/jdt/internal/compiler/lookup/TypeBinding.getTypeAnnotations:()[Lorg/eclipse/jdt/internal/compiler/lookup/AnnotationBinding;
     166: invokevirtual #1074               // Method org/eclipse/jdt/internal/compiler/lookup/LookupEnvironment.createArrayType:(Lorg/eclipse/jdt/internal/compiler/lookup/TypeBinding;I[Lorg/eclipse/jdt/internal/compiler/lookup/AnnotationBinding;)Lorg/eclipse/jdt/internal/compiler/lookup/ArrayBinding;
     169: goto          174
     172: aload         12
     174: putfield      #1067               // Field org/eclipse/jdt/internal/compiler/ast/TypeReference.resolvedType:Lorg/eclipse/jdt/internal/compiler/lookup/TypeBinding;
     177: goto          199
     180: aload         7
     182: aload         12
     184: putfield      #1067               // Field org/eclipse/jdt/internal/compiler/ast/TypeReference.resolvedType:Lorg/eclipse/jdt/internal/compiler/lookup/TypeBinding;
     187: aload         7
     189: dup
     190: getfield      #980                // Field org/eclipse/jdt/internal/compiler/ast/TypeReference.bits:I
     193: ldc           #54                 // int 1048576
     195: ior
     196: putfield      #980                // Field org/eclipse/jdt/internal/compiler/ast/TypeReference.bits:I
     199: aload         5
     201: getfield      #1067               // Field org/eclipse/jdt/internal/compiler/ast/TypeReference.resolvedType:Lorg/eclipse/jdt/internal/compiler/lookup/TypeBinding;
     204: areturn

  public static void resolveDeprecatedAnnotations(org.eclipse.jdt.internal.compiler.lookup.BlockScope, org.eclipse.jdt.internal.compiler.ast.Annotation[], org.eclipse.jdt.internal.compiler.lookup.Binding);
    Code:
       0: aload_2
       1: ifnull        605
       4: aload_2
       5: invokevirtual #793                // Method org/eclipse/jdt/internal/compiler/lookup/Binding.kind:()I
       8: istore_3
       9: aload_1
      10: ifnull        435
      13: aload_1
      14: arraylength
      15: dup
      16: istore        4
      18: iflt          435
      21: iload_3
      22: lookupswitch  { // 6
                     1: 143
                     2: 164
                     4: 101
                     8: 122
                    16: 80
                  2052: 101
               default: 185
          }
      80: aload_2
      81: checkcast     #796                // class org/eclipse/jdt/internal/compiler/lookup/PackageBinding
      84: astore        5
      86: aload         5
      88: getfield      #798                // Field org/eclipse/jdt/internal/compiler/lookup/PackageBinding.tagBits:J
      91: ldc2_w        #88                 // long 17179869184l
      94: land
      95: lconst_0
      96: lcmp
      97: ifeq          186
     100: return
     101: aload_2
     102: checkcast     #376                // class org/eclipse/jdt/internal/compiler/lookup/ReferenceBinding
     105: astore        6
     107: aload         6
     109: getfield      #801                // Field org/eclipse/jdt/internal/compiler/lookup/ReferenceBinding.tagBits:J
     112: ldc2_w        #88                 // long 17179869184l
     115: land
     116: lconst_0
     117: lcmp
     118: ifeq          186
     121: return
     122: aload_2
     123: checkcast     #356                // class org/eclipse/jdt/internal/compiler/lookup/MethodBinding
     126: astore        7
     128: aload         7
     130: getfield      #383                // Field org/eclipse/jdt/internal/compiler/lookup/MethodBinding.tagBits:J
     133: ldc2_w        #88                 // long 17179869184l
     136: land
     137: lconst_0
     138: lcmp
     139: ifeq          186
     142: return
     143: aload_2
     144: checkcast     #506                // class org/eclipse/jdt/internal/compiler/lookup/FieldBinding
     147: astore        8
     149: aload         8
     151: getfield      #809                // Field org/eclipse/jdt/internal/compiler/lookup/FieldBinding.tagBits:J
     154: ldc2_w        #88                 // long 17179869184l
     157: land
     158: lconst_0
     159: lcmp
     160: ifeq          186
     163: return
     164: aload_2
     165: checkcast     #811                // class org/eclipse/jdt/internal/compiler/lookup/LocalVariableBinding
     168: astore        9
     170: aload         9
     172: getfield      #813                // Field org/eclipse/jdt/internal/compiler/lookup/LocalVariableBinding.tagBits:J
     175: ldc2_w        #88                 // long 17179869184l
     178: land
     179: lconst_0
     180: lcmp
     181: ifeq          186
     184: return
     185: return
     186: iconst_0
     187: istore        5
     189: goto          428
     192: aload_1
     193: iload         5
     195: aaload
     196: getfield      #1085               // Field org/eclipse/jdt/internal/compiler/ast/Annotation.type:Lorg/eclipse/jdt/internal/compiler/ast/TypeReference;
     199: astore        6
     201: getstatic     #1086               // Field org/eclipse/jdt/internal/compiler/lookup/TypeConstants.JAVA_LANG_DEPRECATED:[[C
     204: iconst_2
     205: aaload
     206: aload         6
     208: invokevirtual #1090               // Method org/eclipse/jdt/internal/compiler/ast/TypeReference.getLastToken:()[C
     211: invokestatic  #1094               // Method org/eclipse/jdt/core/compiler/CharOperation.equals:([C[C)Z
     214: ifne          220
     217: goto          425
     220: aload_1
     221: iload         5
     223: aaload
     224: getfield      #1085               // Field org/eclipse/jdt/internal/compiler/ast/Annotation.type:Lorg/eclipse/jdt/internal/compiler/ast/TypeReference;
     227: aload_0
     228: invokevirtual #1100               // Method org/eclipse/jdt/internal/compiler/ast/TypeReference.resolveType:(Lorg/eclipse/jdt/internal/compiler/lookup/BlockScope;)Lorg/eclipse/jdt/internal/compiler/lookup/TypeBinding;
     231: astore        7
     233: aload         7
     235: ifnull        425
     238: aload         7
     240: invokevirtual #1051               // Method org/eclipse/jdt/internal/compiler/lookup/TypeBinding.isValidBinding:()Z
     243: ifeq          425
     246: aload         7
     248: getfield      #1101               // Field org/eclipse/jdt/internal/compiler/lookup/TypeBinding.id:I
     251: bipush        44
     253: if_icmpne     425
     256: iload_3
     257: lookupswitch  { // 7
                     1: 384
                     2: 404
                     4: 344
                     8: 364
                    16: 324
                  2052: 344
                  4100: 344
               default: 424
          }
     324: aload_2
     325: checkcast     #796                // class org/eclipse/jdt/internal/compiler/lookup/PackageBinding
     328: astore        8
     330: aload         8
     332: dup
     333: getfield      #798                // Field org/eclipse/jdt/internal/compiler/lookup/PackageBinding.tagBits:J
     336: ldc2_w        #1102               // long 70385924046848l
     339: lor
     340: putfield      #798                // Field org/eclipse/jdt/internal/compiler/lookup/PackageBinding.tagBits:J
     343: return
     344: aload_2
     345: checkcast     #376                // class org/eclipse/jdt/internal/compiler/lookup/ReferenceBinding
     348: astore        9
     350: aload         9
     352: dup
     353: getfield      #801                // Field org/eclipse/jdt/internal/compiler/lookup/ReferenceBinding.tagBits:J
     356: ldc2_w        #1102               // long 70385924046848l
     359: lor
     360: putfield      #801                // Field org/eclipse/jdt/internal/compiler/lookup/ReferenceBinding.tagBits:J
     363: return
     364: aload_2
     365: checkcast     #356                // class org/eclipse/jdt/internal/compiler/lookup/MethodBinding
     368: astore        10
     370: aload         10
     372: dup
     373: getfield      #383                // Field org/eclipse/jdt/internal/compiler/lookup/MethodBinding.tagBits:J
     376: ldc2_w        #1102               // long 70385924046848l
     379: lor
     380: putfield      #383                // Field org/eclipse/jdt/internal/compiler/lookup/MethodBinding.tagBits:J
     383: return
     384: aload_2
     385: checkcast     #506                // class org/eclipse/jdt/internal/compiler/lookup/FieldBinding
     388: astore        11
     390: aload         11
     392: dup
     393: getfield      #809                // Field org/eclipse/jdt/internal/compiler/lookup/FieldBinding.tagBits:J
     396: ldc2_w        #1102               // long 70385924046848l
     399: lor
     400: putfield      #809                // Field org/eclipse/jdt/internal/compiler/lookup/FieldBinding.tagBits:J
     403: return
     404: aload_2
     405: checkcast     #811                // class org/eclipse/jdt/internal/compiler/lookup/LocalVariableBinding
     408: astore        12
     410: aload         12
     412: dup
     413: getfield      #813                // Field org/eclipse/jdt/internal/compiler/lookup/LocalVariableBinding.tagBits:J
     416: ldc2_w        #1102               // long 70385924046848l
     419: lor
     420: putfield      #813                // Field org/eclipse/jdt/internal/compiler/lookup/LocalVariableBinding.tagBits:J
     423: return
     424: return
     425: iinc          5, 1
     428: iload         5
     430: iload         4
     432: if_icmplt     192
     435: iload_3
     436: lookupswitch  { // 7
                     1: 564
                     2: 584
                     4: 524
                     8: 544
                    16: 504
                  2052: 524
                  4100: 524
               default: 604
          }
     504: aload_2
     505: checkcast     #796                // class org/eclipse/jdt/internal/compiler/lookup/PackageBinding
     508: astore        4
     510: aload         4
     512: dup
     513: getfield      #798                // Field org/eclipse/jdt/internal/compiler/lookup/PackageBinding.tagBits:J
     516: ldc2_w        #88                 // long 17179869184l
     519: lor
     520: putfield      #798                // Field org/eclipse/jdt/internal/compiler/lookup/PackageBinding.tagBits:J
     523: return
     524: aload_2
     525: checkcast     #376                // class org/eclipse/jdt/internal/compiler/lookup/ReferenceBinding
     528: astore        5
     530: aload         5
     532: dup
     533: getfield      #801                // Field org/eclipse/jdt/internal/compiler/lookup/ReferenceBinding.tagBits:J
     536: ldc2_w        #88                 // long 17179869184l
     539: lor
     540: putfield      #801                // Field org/eclipse/jdt/internal/compiler/lookup/ReferenceBinding.tagBits:J
     543: return
     544: aload_2
     545: checkcast     #356                // class org/eclipse/jdt/internal/compiler/lookup/MethodBinding
     548: astore        6
     550: aload         6
     552: dup
     553: getfield      #383                // Field org/eclipse/jdt/internal/compiler/lookup/MethodBinding.tagBits:J
     556: ldc2_w        #88                 // long 17179869184l
     559: lor
     560: putfield      #383                // Field org/eclipse/jdt/internal/compiler/lookup/MethodBinding.tagBits:J
     563: return
     564: aload_2
     565: checkcast     #506                // class org/eclipse/jdt/internal/compiler/lookup/FieldBinding
     568: astore        7
     570: aload         7
     572: dup
     573: getfield      #809                // Field org/eclipse/jdt/internal/compiler/lookup/FieldBinding.tagBits:J
     576: ldc2_w        #88                 // long 17179869184l
     579: lor
     580: putfield      #809                // Field org/eclipse/jdt/internal/compiler/lookup/FieldBinding.tagBits:J
     583: return
     584: aload_2
     585: checkcast     #811                // class org/eclipse/jdt/internal/compiler/lookup/LocalVariableBinding
     588: astore        8
     590: aload         8
     592: dup
     593: getfield      #813                // Field org/eclipse/jdt/internal/compiler/lookup/LocalVariableBinding.tagBits:J
     596: ldc2_w        #88                 // long 17179869184l
     599: lor
     600: putfield      #813                // Field org/eclipse/jdt/internal/compiler/lookup/LocalVariableBinding.tagBits:J
     603: return
     604: return
     605: return

  public int sourceStart();
    Code:
       0: aload_0
       1: getfield      #1105               // Field sourceStart:I
       4: ireturn

  public int sourceEnd();
    Code:
       0: aload_0
       1: getfield      #1107               // Field sourceEnd:I
       4: ireturn

  public java.lang.String toString();
    Code:
       0: aload_0
       1: iconst_0
       2: new           #624                // class java/lang/StringBuffer
       5: dup
       6: bipush        30
       8: invokespecial #1111               // Method java/lang/StringBuffer."<init>":(I)V
      11: invokevirtual #1112               // Method print:(ILjava/lang/StringBuffer;)Ljava/lang/StringBuffer;
      14: invokevirtual #1113               // Method java/lang/StringBuffer.toString:()Ljava/lang/String;
      17: areturn

  public void traverse(org.eclipse.jdt.internal.compiler.ASTVisitor, org.eclipse.jdt.internal.compiler.lookup.BlockScope);
    Code:
       0: return
}
