Compiled from "FieldDeclaration.java"
public class org.eclipse.jdt.internal.compiler.ast.FieldDeclaration extends org.eclipse.jdt.internal.compiler.ast.AbstractVariableDeclaration {
  public org.eclipse.jdt.internal.compiler.lookup.FieldBinding binding;

  public org.eclipse.jdt.internal.compiler.ast.Javadoc javadoc;

  public int endPart1Position;

  public int endPart2Position;

  public org.eclipse.jdt.internal.compiler.ast.FieldDeclaration();
    Code:
       0: aload_0
       1: invokespecial #15                 // Method org/eclipse/jdt/internal/compiler/ast/AbstractVariableDeclaration."<init>":()V
       4: return

  public org.eclipse.jdt.internal.compiler.ast.FieldDeclaration(char[], int, int);
    Code:
       0: aload_0
       1: invokespecial #15                 // Method org/eclipse/jdt/internal/compiler/ast/AbstractVariableDeclaration."<init>":()V
       4: aload_0
       5: aload_1
       6: putfield      #22                 // Field name:[C
       9: aload_0
      10: iload_2
      11: putfield      #26                 // Field sourceStart:I
      14: aload_0
      15: iload_3
      16: putfield      #29                 // Field sourceEnd:I
      19: return

  public org.eclipse.jdt.internal.compiler.flow.FlowInfo analyseCode(org.eclipse.jdt.internal.compiler.lookup.MethodScope, org.eclipse.jdt.internal.compiler.flow.FlowContext, org.eclipse.jdt.internal.compiler.flow.FlowInfo);
    Code:
       0: aload_0
       1: getfield      #34                 // Field binding:Lorg/eclipse/jdt/internal/compiler/lookup/FieldBinding;
       4: ifnull        48
       7: aload_0
       8: getfield      #34                 // Field binding:Lorg/eclipse/jdt/internal/compiler/lookup/FieldBinding;
      11: invokevirtual #36                 // Method org/eclipse/jdt/internal/compiler/lookup/FieldBinding.isUsed:()Z
      14: ifne          48
      17: aload_0
      18: getfield      #34                 // Field binding:Lorg/eclipse/jdt/internal/compiler/lookup/FieldBinding;
      21: invokevirtual #42                 // Method org/eclipse/jdt/internal/compiler/lookup/FieldBinding.isOrEnclosedByPrivateType:()Z
      24: ifeq          48
      27: aload_1
      28: invokevirtual #45                 // Method org/eclipse/jdt/internal/compiler/lookup/MethodScope.referenceCompilationUnit:()Lorg/eclipse/jdt/internal/compiler/ast/CompilationUnitDeclaration;
      31: getfield      #51                 // Field org/eclipse/jdt/internal/compiler/ast/CompilationUnitDeclaration.compilationResult:Lorg/eclipse/jdt/internal/compiler/CompilationResult;
      34: getfield      #57                 // Field org/eclipse/jdt/internal/compiler/CompilationResult.hasSyntaxError:Z
      37: ifne          48
      40: aload_1
      41: invokevirtual #63                 // Method org/eclipse/jdt/internal/compiler/lookup/MethodScope.problemReporter:()Lorg/eclipse/jdt/internal/compiler/problem/ProblemReporter;
      44: aload_0
      45: invokevirtual #67                 // Method org/eclipse/jdt/internal/compiler/problem/ProblemReporter.unusedPrivateField:(Lorg/eclipse/jdt/internal/compiler/ast/FieldDeclaration;)V
      48: aload_0
      49: getfield      #34                 // Field binding:Lorg/eclipse/jdt/internal/compiler/lookup/FieldBinding;
      52: ifnull        132
      55: aload_0
      56: getfield      #34                 // Field binding:Lorg/eclipse/jdt/internal/compiler/lookup/FieldBinding;
      59: invokevirtual #73                 // Method org/eclipse/jdt/internal/compiler/lookup/FieldBinding.isValidBinding:()Z
      62: ifeq          132
      65: aload_0
      66: getfield      #34                 // Field binding:Lorg/eclipse/jdt/internal/compiler/lookup/FieldBinding;
      69: invokevirtual #76                 // Method org/eclipse/jdt/internal/compiler/lookup/FieldBinding.isStatic:()Z
      72: ifeq          132
      75: aload_0
      76: getfield      #34                 // Field binding:Lorg/eclipse/jdt/internal/compiler/lookup/FieldBinding;
      79: invokevirtual #79                 // Method org/eclipse/jdt/internal/compiler/lookup/FieldBinding.constant:()Lorg/eclipse/jdt/internal/compiler/impl/Constant;
      82: getstatic     #83                 // Field org/eclipse/jdt/internal/compiler/impl/Constant.NotAConstant:Lorg/eclipse/jdt/internal/compiler/impl/Constant;
      85: if_acmpne     132
      88: aload_0
      89: getfield      #34                 // Field binding:Lorg/eclipse/jdt/internal/compiler/lookup/FieldBinding;
      92: getfield      #89                 // Field org/eclipse/jdt/internal/compiler/lookup/FieldBinding.declaringClass:Lorg/eclipse/jdt/internal/compiler/lookup/ReferenceBinding;
      95: invokevirtual #93                 // Method org/eclipse/jdt/internal/compiler/lookup/ReferenceBinding.isNestedType:()Z
      98: ifeq          132
     101: aload_0
     102: getfield      #34                 // Field binding:Lorg/eclipse/jdt/internal/compiler/lookup/FieldBinding;
     105: getfield      #89                 // Field org/eclipse/jdt/internal/compiler/lookup/FieldBinding.declaringClass:Lorg/eclipse/jdt/internal/compiler/lookup/ReferenceBinding;
     108: invokevirtual #98                 // Method org/eclipse/jdt/internal/compiler/lookup/ReferenceBinding.isStatic:()Z
     111: ifne          132
     114: aload_1
     115: invokevirtual #63                 // Method org/eclipse/jdt/internal/compiler/lookup/MethodScope.problemReporter:()Lorg/eclipse/jdt/internal/compiler/problem/ProblemReporter;
     118: aload_0
     119: getfield      #34                 // Field binding:Lorg/eclipse/jdt/internal/compiler/lookup/FieldBinding;
     122: getfield      #89                 // Field org/eclipse/jdt/internal/compiler/lookup/FieldBinding.declaringClass:Lorg/eclipse/jdt/internal/compiler/lookup/ReferenceBinding;
     125: checkcast     #99                 // class org/eclipse/jdt/internal/compiler/lookup/SourceTypeBinding
     128: aload_0
     129: invokevirtual #101                // Method org/eclipse/jdt/internal/compiler/problem/ProblemReporter.unexpectedStaticModifierForField:(Lorg/eclipse/jdt/internal/compiler/lookup/SourceTypeBinding;Lorg/eclipse/jdt/internal/compiler/ast/FieldDeclaration;)V
     132: aload_0
     133: getfield      #105                // Field initialization:Lorg/eclipse/jdt/internal/compiler/ast/Expression;
     136: ifnull        161
     139: aload_0
     140: getfield      #105                // Field initialization:Lorg/eclipse/jdt/internal/compiler/ast/Expression;
     143: aload_1
     144: aload_2
     145: aload_3
     146: invokevirtual #109                // Method org/eclipse/jdt/internal/compiler/ast/Expression.analyseCode:(Lorg/eclipse/jdt/internal/compiler/lookup/BlockScope;Lorg/eclipse/jdt/internal/compiler/flow/FlowContext;Lorg/eclipse/jdt/internal/compiler/flow/FlowInfo;)Lorg/eclipse/jdt/internal/compiler/flow/FlowInfo;
     149: invokevirtual #114                // Method org/eclipse/jdt/internal/compiler/flow/FlowInfo.unconditionalInits:()Lorg/eclipse/jdt/internal/compiler/flow/UnconditionalFlowInfo;
     152: astore_3
     153: aload_3
     154: aload_0
     155: getfield      #34                 // Field binding:Lorg/eclipse/jdt/internal/compiler/lookup/FieldBinding;
     158: invokevirtual #120                // Method org/eclipse/jdt/internal/compiler/flow/FlowInfo.markAsDefinitelyAssigned:(Lorg/eclipse/jdt/internal/compiler/lookup/FieldBinding;)V
     161: aload_0
     162: getfield      #105                // Field initialization:Lorg/eclipse/jdt/internal/compiler/ast/Expression;
     165: ifnull        255
     168: aload_0
     169: getfield      #34                 // Field binding:Lorg/eclipse/jdt/internal/compiler/lookup/FieldBinding;
     172: ifnull        255
     175: aload_1
     176: invokevirtual #124                // Method org/eclipse/jdt/internal/compiler/lookup/MethodScope.compilerOptions:()Lorg/eclipse/jdt/internal/compiler/impl/CompilerOptions;
     179: astore        4
     181: aload         4
     183: getfield      #128                // Field org/eclipse/jdt/internal/compiler/impl/CompilerOptions.isAnnotationBasedNullAnalysisEnabled:Z
     186: ifeq          245
     189: aload_0
     190: getfield      #34                 // Field binding:Lorg/eclipse/jdt/internal/compiler/lookup/FieldBinding;
     193: invokevirtual #133                // Method org/eclipse/jdt/internal/compiler/lookup/FieldBinding.isNonNull:()Z
     196: ifne          211
     199: aload         4
     201: getfield      #136                // Field org/eclipse/jdt/internal/compiler/impl/CompilerOptions.sourceLevel:J
     204: ldc2_w        #140                // long 3407872l
     207: lcmp
     208: iflt          245
     211: aload_0
     212: getfield      #105                // Field initialization:Lorg/eclipse/jdt/internal/compiler/ast/Expression;
     215: aload_3
     216: aload_2
     217: invokevirtual #142                // Method org/eclipse/jdt/internal/compiler/ast/Expression.nullStatus:(Lorg/eclipse/jdt/internal/compiler/flow/FlowInfo;Lorg/eclipse/jdt/internal/compiler/flow/FlowContext;)I
     220: istore        5
     222: aload_1
     223: aload_2
     224: aload_0
     225: getfield      #34                 // Field binding:Lorg/eclipse/jdt/internal/compiler/lookup/FieldBinding;
     228: iload         5
     230: aload_0
     231: getfield      #105                // Field initialization:Lorg/eclipse/jdt/internal/compiler/ast/Expression;
     234: aload_0
     235: getfield      #105                // Field initialization:Lorg/eclipse/jdt/internal/compiler/ast/Expression;
     238: getfield      #146                // Field org/eclipse/jdt/internal/compiler/ast/Expression.resolvedType:Lorg/eclipse/jdt/internal/compiler/lookup/TypeBinding;
     241: invokestatic  #150                // Method org/eclipse/jdt/internal/compiler/ast/NullAnnotationMatching.checkAssignment:(Lorg/eclipse/jdt/internal/compiler/lookup/BlockScope;Lorg/eclipse/jdt/internal/compiler/flow/FlowContext;Lorg/eclipse/jdt/internal/compiler/lookup/VariableBinding;ILorg/eclipse/jdt/internal/compiler/ast/Expression;Lorg/eclipse/jdt/internal/compiler/lookup/TypeBinding;)I
     244: pop
     245: aload_0
     246: getfield      #105                // Field initialization:Lorg/eclipse/jdt/internal/compiler/ast/Expression;
     249: aload_1
     250: aload_2
     251: aload_3
     252: invokevirtual #156                // Method org/eclipse/jdt/internal/compiler/ast/Expression.checkNPEbyUnboxing:(Lorg/eclipse/jdt/internal/compiler/lookup/BlockScope;Lorg/eclipse/jdt/internal/compiler/flow/FlowContext;Lorg/eclipse/jdt/internal/compiler/flow/FlowInfo;)V
     255: aload_3
     256: areturn

  public void generateCode(org.eclipse.jdt.internal.compiler.lookup.BlockScope, org.eclipse.jdt.internal.compiler.codegen.CodeStream);
    Code:
       0: aload_0
       1: getfield      #171                // Field bits:I
       4: ldc           #174                // int -2147483648
       6: iand
       7: ifne          11
      10: return
      11: aload_2
      12: getfield      #175                // Field org/eclipse/jdt/internal/compiler/codegen/CodeStream.position:I
      15: istore_3
      16: aload_0
      17: getfield      #105                // Field initialization:Lorg/eclipse/jdt/internal/compiler/ast/Expression;
      20: ifnull        98
      23: aload_0
      24: getfield      #34                 // Field binding:Lorg/eclipse/jdt/internal/compiler/lookup/FieldBinding;
      27: invokevirtual #76                 // Method org/eclipse/jdt/internal/compiler/lookup/FieldBinding.isStatic:()Z
      30: dup
      31: istore        4
      33: ifeq          49
      36: aload_0
      37: getfield      #34                 // Field binding:Lorg/eclipse/jdt/internal/compiler/lookup/FieldBinding;
      40: invokevirtual #79                 // Method org/eclipse/jdt/internal/compiler/lookup/FieldBinding.constant:()Lorg/eclipse/jdt/internal/compiler/impl/Constant;
      43: getstatic     #83                 // Field org/eclipse/jdt/internal/compiler/impl/Constant.NotAConstant:Lorg/eclipse/jdt/internal/compiler/impl/Constant;
      46: if_acmpne     98
      49: iload         4
      51: ifne          58
      54: aload_2
      55: invokevirtual #180                // Method org/eclipse/jdt/internal/compiler/codegen/CodeStream.aload_0:()V
      58: aload_0
      59: getfield      #105                // Field initialization:Lorg/eclipse/jdt/internal/compiler/ast/Expression;
      62: aload_1
      63: aload_2
      64: iconst_1
      65: invokevirtual #183                // Method org/eclipse/jdt/internal/compiler/ast/Expression.generateCode:(Lorg/eclipse/jdt/internal/compiler/lookup/BlockScope;Lorg/eclipse/jdt/internal/compiler/codegen/CodeStream;Z)V
      68: iload         4
      70: ifeq          87
      73: aload_2
      74: bipush        -77
      76: aload_0
      77: getfield      #34                 // Field binding:Lorg/eclipse/jdt/internal/compiler/lookup/FieldBinding;
      80: aconst_null
      81: invokevirtual #186                // Method org/eclipse/jdt/internal/compiler/codegen/CodeStream.fieldAccess:(BLorg/eclipse/jdt/internal/compiler/lookup/FieldBinding;Lorg/eclipse/jdt/internal/compiler/lookup/TypeBinding;)V
      84: goto          98
      87: aload_2
      88: bipush        -75
      90: aload_0
      91: getfield      #34                 // Field binding:Lorg/eclipse/jdt/internal/compiler/lookup/FieldBinding;
      94: aconst_null
      95: invokevirtual #186                // Method org/eclipse/jdt/internal/compiler/codegen/CodeStream.fieldAccess:(BLorg/eclipse/jdt/internal/compiler/lookup/FieldBinding;Lorg/eclipse/jdt/internal/compiler/lookup/TypeBinding;)V
      98: aload_2
      99: iload_3
     100: aload_0
     101: getfield      #26                 // Field sourceStart:I
     104: invokevirtual #190                // Method org/eclipse/jdt/internal/compiler/codegen/CodeStream.recordPositionsFrom:(II)V
     107: return

  public void getAllAnnotationContexts(int, java.util.List);
    Code:
       0: new           #201                // class org/eclipse/jdt/internal/compiler/ast/TypeReference$AnnotationCollector
       3: dup
       4: aload_0
       5: getfield      #203                // Field type:Lorg/eclipse/jdt/internal/compiler/ast/TypeReference;
       8: iload_1
       9: aload_2
      10: invokespecial #207                // Method org/eclipse/jdt/internal/compiler/ast/TypeReference$AnnotationCollector."<init>":(Lorg/eclipse/jdt/internal/compiler/ast/TypeReference;ILjava/util/List;)V
      13: astore_3
      14: iconst_0
      15: istore        4
      17: aload_0
      18: getfield      #210                // Field annotations:[Lorg/eclipse/jdt/internal/compiler/ast/Annotation;
      21: arraylength
      22: istore        5
      24: goto          46
      27: aload_0
      28: getfield      #210                // Field annotations:[Lorg/eclipse/jdt/internal/compiler/ast/Annotation;
      31: iload         4
      33: aaload
      34: astore        6
      36: aload         6
      38: aload_3
      39: aconst_null
      40: invokevirtual #214                // Method org/eclipse/jdt/internal/compiler/ast/Annotation.traverse:(Lorg/eclipse/jdt/internal/compiler/ASTVisitor;Lorg/eclipse/jdt/internal/compiler/lookup/BlockScope;)V
      43: iinc          4, 1
      46: iload         4
      48: iload         5
      50: if_icmplt     27
      53: return

  public int getKind();
    Code:
       0: aload_0
       1: getfield      #203                // Field type:Lorg/eclipse/jdt/internal/compiler/ast/TypeReference;
       4: ifnonnull     11
       7: iconst_3
       8: goto          12
      11: iconst_1
      12: ireturn

  public boolean isStatic();
    Code:
       0: aload_0
       1: getfield      #34                 // Field binding:Lorg/eclipse/jdt/internal/compiler/lookup/FieldBinding;
       4: ifnull        15
       7: aload_0
       8: getfield      #34                 // Field binding:Lorg/eclipse/jdt/internal/compiler/lookup/FieldBinding;
      11: invokevirtual #76                 // Method org/eclipse/jdt/internal/compiler/lookup/FieldBinding.isStatic:()Z
      14: ireturn
      15: aload_0
      16: getfield      #231                // Field modifiers:I
      19: bipush        8
      21: iand
      22: ifeq          27
      25: iconst_1
      26: ireturn
      27: iconst_0
      28: ireturn

  public boolean isFinal();
    Code:
       0: aload_0
       1: getfield      #34                 // Field binding:Lorg/eclipse/jdt/internal/compiler/lookup/FieldBinding;
       4: ifnull        15
       7: aload_0
       8: getfield      #34                 // Field binding:Lorg/eclipse/jdt/internal/compiler/lookup/FieldBinding;
      11: invokevirtual #235                // Method org/eclipse/jdt/internal/compiler/lookup/FieldBinding.isFinal:()Z
      14: ireturn
      15: aload_0
      16: getfield      #231                // Field modifiers:I
      19: bipush        16
      21: iand
      22: ifeq          27
      25: iconst_1
      26: ireturn
      27: iconst_0
      28: ireturn

  public java.lang.StringBuffer printStatement(int, java.lang.StringBuffer);
    Code:
       0: aload_0
       1: getfield      #239                // Field javadoc:Lorg/eclipse/jdt/internal/compiler/ast/Javadoc;
       4: ifnull        17
       7: aload_0
       8: getfield      #239                // Field javadoc:Lorg/eclipse/jdt/internal/compiler/ast/Javadoc;
      11: iload_1
      12: aload_2
      13: invokevirtual #241                // Method org/eclipse/jdt/internal/compiler/ast/Javadoc.print:(ILjava/lang/StringBuffer;)Ljava/lang/StringBuffer;
      16: pop
      17: aload_0
      18: iload_1
      19: aload_2
      20: invokespecial #246                // Method org/eclipse/jdt/internal/compiler/ast/AbstractVariableDeclaration.printStatement:(ILjava/lang/StringBuffer;)Ljava/lang/StringBuffer;
      23: areturn

  public void resolve(org.eclipse.jdt.internal.compiler.lookup.MethodScope);
    Code:
       0: aload_0
       1: getfield      #171                // Field bits:I
       4: bipush        16
       6: iand
       7: ifeq          11
      10: return
      11: aload_0
      12: getfield      #34                 // Field binding:Lorg/eclipse/jdt/internal/compiler/lookup/FieldBinding;
      15: ifnull        28
      18: aload_0
      19: getfield      #34                 // Field binding:Lorg/eclipse/jdt/internal/compiler/lookup/FieldBinding;
      22: invokevirtual #73                 // Method org/eclipse/jdt/internal/compiler/lookup/FieldBinding.isValidBinding:()Z
      25: ifne          29
      28: return
      29: aload_0
      30: dup
      31: getfield      #171                // Field bits:I
      34: bipush        16
      36: ior
      37: putfield      #171                // Field bits:I
      40: aload_1
      41: invokevirtual #253                // Method org/eclipse/jdt/internal/compiler/lookup/MethodScope.enclosingClassScope:()Lorg/eclipse/jdt/internal/compiler/lookup/ClassScope;
      44: astore_2
      45: aload_2
      46: ifnull        263
      49: aload_2
      50: invokevirtual #257                // Method org/eclipse/jdt/internal/compiler/lookup/ClassScope.enclosingSourceType:()Lorg/eclipse/jdt/internal/compiler/lookup/SourceTypeBinding;
      53: astore_3
      54: aload_3
      55: getfield      #263                // Field org/eclipse/jdt/internal/compiler/lookup/SourceTypeBinding.superclass:Lorg/eclipse/jdt/internal/compiler/lookup/ReferenceBinding;
      58: ifnonnull     64
      61: goto          142
      64: aload_2
      65: aload_3
      66: getfield      #263                // Field org/eclipse/jdt/internal/compiler/lookup/SourceTypeBinding.superclass:Lorg/eclipse/jdt/internal/compiler/lookup/ReferenceBinding;
      69: aload_0
      70: getfield      #22                 // Field name:[C
      73: aload_0
      74: iconst_0
      75: iconst_1
      76: invokevirtual #266                // Method org/eclipse/jdt/internal/compiler/lookup/ClassScope.findField:(Lorg/eclipse/jdt/internal/compiler/lookup/TypeBinding;[CLorg/eclipse/jdt/internal/compiler/lookup/InvocationSite;ZZ)Lorg/eclipse/jdt/internal/compiler/lookup/FieldBinding;
      79: astore        4
      81: aload         4
      83: ifnonnull     89
      86: goto          142
      89: aload         4
      91: invokevirtual #73                 // Method org/eclipse/jdt/internal/compiler/lookup/FieldBinding.isValidBinding:()Z
      94: ifne          100
      97: goto          142
     100: aload         4
     102: invokevirtual #270                // Method org/eclipse/jdt/internal/compiler/lookup/FieldBinding.original:()Lorg/eclipse/jdt/internal/compiler/lookup/FieldBinding;
     105: aload_0
     106: getfield      #34                 // Field binding:Lorg/eclipse/jdt/internal/compiler/lookup/FieldBinding;
     109: if_acmpne     115
     112: goto          142
     115: aload         4
     117: aload_3
     118: aload_0
     119: aload_1
     120: invokevirtual #274                // Method org/eclipse/jdt/internal/compiler/lookup/FieldBinding.canBeSeenBy:(Lorg/eclipse/jdt/internal/compiler/lookup/TypeBinding;Lorg/eclipse/jdt/internal/compiler/lookup/InvocationSite;Lorg/eclipse/jdt/internal/compiler/lookup/Scope;)Z
     123: ifne          129
     126: goto          142
     129: aload_1
     130: invokevirtual #63                 // Method org/eclipse/jdt/internal/compiler/lookup/MethodScope.problemReporter:()Lorg/eclipse/jdt/internal/compiler/problem/ProblemReporter;
     133: aload_0
     134: aload         4
     136: invokevirtual #278                // Method org/eclipse/jdt/internal/compiler/problem/ProblemReporter.fieldHiding:(Lorg/eclipse/jdt/internal/compiler/ast/FieldDeclaration;Lorg/eclipse/jdt/internal/compiler/lookup/Binding;)V
     139: goto          263
     142: aload_2
     143: getfield      #282                // Field org/eclipse/jdt/internal/compiler/lookup/ClassScope.parent:Lorg/eclipse/jdt/internal/compiler/lookup/Scope;
     146: astore        4
     148: aload         4
     150: getfield      #286                // Field org/eclipse/jdt/internal/compiler/lookup/Scope.kind:I
     153: iconst_4
     154: if_icmpne     160
     157: goto          263
     160: aload         4
     162: aload_0
     163: getfield      #22                 // Field name:[C
     166: iconst_3
     167: aload_0
     168: iconst_0
     169: invokevirtual #291                // Method org/eclipse/jdt/internal/compiler/lookup/Scope.getBinding:([CILorg/eclipse/jdt/internal/compiler/lookup/InvocationSite;Z)Lorg/eclipse/jdt/internal/compiler/lookup/Binding;
     172: astore        5
     174: aload         5
     176: ifnonnull     182
     179: goto          263
     182: aload         5
     184: invokevirtual #295                // Method org/eclipse/jdt/internal/compiler/lookup/Binding.isValidBinding:()Z
     187: ifne          193
     190: goto          263
     193: aload         5
     195: aload_0
     196: getfield      #34                 // Field binding:Lorg/eclipse/jdt/internal/compiler/lookup/FieldBinding;
     199: if_acmpne     205
     202: goto          263
     205: aload         5
     207: instanceof    #37                 // class org/eclipse/jdt/internal/compiler/lookup/FieldBinding
     210: ifeq          253
     213: aload         5
     215: checkcast     #37                 // class org/eclipse/jdt/internal/compiler/lookup/FieldBinding
     218: astore        6
     220: aload         6
     222: invokevirtual #270                // Method org/eclipse/jdt/internal/compiler/lookup/FieldBinding.original:()Lorg/eclipse/jdt/internal/compiler/lookup/FieldBinding;
     225: aload_0
     226: getfield      #34                 // Field binding:Lorg/eclipse/jdt/internal/compiler/lookup/FieldBinding;
     229: if_acmpne     235
     232: goto          263
     235: aload         6
     237: invokevirtual #76                 // Method org/eclipse/jdt/internal/compiler/lookup/FieldBinding.isStatic:()Z
     240: ifne          253
     243: aload_3
     244: invokevirtual #298                // Method org/eclipse/jdt/internal/compiler/lookup/SourceTypeBinding.isStatic:()Z
     247: ifeq          253
     250: goto          263
     253: aload_1
     254: invokevirtual #63                 // Method org/eclipse/jdt/internal/compiler/lookup/MethodScope.problemReporter:()Lorg/eclipse/jdt/internal/compiler/problem/ProblemReporter;
     257: aload_0
     258: aload         5
     260: invokevirtual #278                // Method org/eclipse/jdt/internal/compiler/problem/ProblemReporter.fieldHiding:(Lorg/eclipse/jdt/internal/compiler/ast/FieldDeclaration;Lorg/eclipse/jdt/internal/compiler/lookup/Binding;)V
     263: aload_0
     264: getfield      #203                // Field type:Lorg/eclipse/jdt/internal/compiler/ast/TypeReference;
     267: ifnull        284
     270: aload_0
     271: getfield      #203                // Field type:Lorg/eclipse/jdt/internal/compiler/ast/TypeReference;
     274: aload_0
     275: getfield      #34                 // Field binding:Lorg/eclipse/jdt/internal/compiler/lookup/FieldBinding;
     278: getfield      #299                // Field org/eclipse/jdt/internal/compiler/lookup/FieldBinding.type:Lorg/eclipse/jdt/internal/compiler/lookup/TypeBinding;
     281: putfield      #301                // Field org/eclipse/jdt/internal/compiler/ast/TypeReference.resolvedType:Lorg/eclipse/jdt/internal/compiler/lookup/TypeBinding;
     284: aload_1
     285: getfield      #304                // Field org/eclipse/jdt/internal/compiler/lookup/MethodScope.initializedField:Lorg/eclipse/jdt/internal/compiler/lookup/FieldBinding;
     288: astore_3
     289: aload_1
     290: getfield      #307                // Field org/eclipse/jdt/internal/compiler/lookup/MethodScope.lastVisibleFieldID:I
     293: istore        4
     295: aload_1
     296: aload_0
     297: getfield      #34                 // Field binding:Lorg/eclipse/jdt/internal/compiler/lookup/FieldBinding;
     300: putfield      #304                // Field org/eclipse/jdt/internal/compiler/lookup/MethodScope.initializedField:Lorg/eclipse/jdt/internal/compiler/lookup/FieldBinding;
     303: aload_1
     304: aload_0
     305: getfield      #34                 // Field binding:Lorg/eclipse/jdt/internal/compiler/lookup/FieldBinding;
     308: getfield      #310                // Field org/eclipse/jdt/internal/compiler/lookup/FieldBinding.id:I
     311: putfield      #307                // Field org/eclipse/jdt/internal/compiler/lookup/MethodScope.lastVisibleFieldID:I
     314: aload_1
     315: aload_0
     316: getfield      #210                // Field annotations:[Lorg/eclipse/jdt/internal/compiler/ast/Annotation;
     319: aload_0
     320: getfield      #34                 // Field binding:Lorg/eclipse/jdt/internal/compiler/lookup/FieldBinding;
     323: invokestatic  #313                // Method resolveAnnotations:(Lorg/eclipse/jdt/internal/compiler/lookup/BlockScope;[Lorg/eclipse/jdt/internal/compiler/ast/Annotation;Lorg/eclipse/jdt/internal/compiler/lookup/Binding;)V
     326: aload_0
     327: getfield      #210                // Field annotations:[Lorg/eclipse/jdt/internal/compiler/ast/Annotation;
     330: ifnull        402
     333: iconst_0
     334: istore        5
     336: aload_0
     337: getfield      #210                // Field annotations:[Lorg/eclipse/jdt/internal/compiler/ast/Annotation;
     340: arraylength
     341: istore        6
     343: goto          395
     346: aload_0
     347: getfield      #210                // Field annotations:[Lorg/eclipse/jdt/internal/compiler/ast/Annotation;
     350: iload         5
     352: aaload
     353: getfield      #317                // Field org/eclipse/jdt/internal/compiler/ast/Annotation.resolvedType:Lorg/eclipse/jdt/internal/compiler/lookup/TypeBinding;
     356: astore        7
     358: aload         7
     360: ifnull        392
     363: aload         7
     365: invokevirtual #318                // Method org/eclipse/jdt/internal/compiler/lookup/TypeBinding.getAnnotationTagBits:()J
     368: ldc2_w        #324                // long 9007199254740992l
     371: land
     372: lconst_0
     373: lcmp
     374: ifeq          392
     377: aload_0
     378: dup
     379: getfield      #171                // Field bits:I
     382: ldc_w         #326                // int 1048576
     385: ior
     386: putfield      #171                // Field bits:I
     389: goto          402
     392: iinc          5, 1
     395: iload         5
     397: iload         6
     399: if_icmplt     346
     402: aload_0
     403: getfield      #34                 // Field binding:Lorg/eclipse/jdt/internal/compiler/lookup/FieldBinding;
     406: invokevirtual #327                // Method org/eclipse/jdt/internal/compiler/lookup/FieldBinding.getAnnotationTagBits:()J
     409: ldc2_w        #328                // long 70368744177664l
     412: land
     413: lconst_0
     414: lcmp
     415: ifne          454
     418: aload_0
     419: getfield      #34                 // Field binding:Lorg/eclipse/jdt/internal/compiler/lookup/FieldBinding;
     422: getfield      #330                // Field org/eclipse/jdt/internal/compiler/lookup/FieldBinding.modifiers:I
     425: ldc_w         #326                // int 1048576
     428: iand
     429: ifeq          454
     432: aload_1
     433: invokevirtual #124                // Method org/eclipse/jdt/internal/compiler/lookup/MethodScope.compilerOptions:()Lorg/eclipse/jdt/internal/compiler/impl/CompilerOptions;
     436: getfield      #136                // Field org/eclipse/jdt/internal/compiler/impl/CompilerOptions.sourceLevel:J
     439: ldc2_w        #331                // long 3211264l
     442: lcmp
     443: iflt          454
     446: aload_1
     447: invokevirtual #63                 // Method org/eclipse/jdt/internal/compiler/lookup/MethodScope.problemReporter:()Lorg/eclipse/jdt/internal/compiler/problem/ProblemReporter;
     450: aload_0
     451: invokevirtual #333                // Method org/eclipse/jdt/internal/compiler/problem/ProblemReporter.missingDeprecatedAnnotationForField:(Lorg/eclipse/jdt/internal/compiler/ast/FieldDeclaration;)V
     454: aload_0
     455: getfield      #105                // Field initialization:Lorg/eclipse/jdt/internal/compiler/ast/Expression;
     458: ifnonnull     474
     461: aload_0
     462: getfield      #34                 // Field binding:Lorg/eclipse/jdt/internal/compiler/lookup/FieldBinding;
     465: getstatic     #83                 // Field org/eclipse/jdt/internal/compiler/impl/Constant.NotAConstant:Lorg/eclipse/jdt/internal/compiler/impl/Constant;
     468: invokevirtual #336                // Method org/eclipse/jdt/internal/compiler/lookup/FieldBinding.setConstant:(Lorg/eclipse/jdt/internal/compiler/impl/Constant;)V
     471: goto          892
     474: aload_0
     475: getfield      #34                 // Field binding:Lorg/eclipse/jdt/internal/compiler/lookup/FieldBinding;
     478: getstatic     #83                 // Field org/eclipse/jdt/internal/compiler/impl/Constant.NotAConstant:Lorg/eclipse/jdt/internal/compiler/impl/Constant;
     481: invokevirtual #336                // Method org/eclipse/jdt/internal/compiler/lookup/FieldBinding.setConstant:(Lorg/eclipse/jdt/internal/compiler/impl/Constant;)V
     484: aload_0
     485: getfield      #34                 // Field binding:Lorg/eclipse/jdt/internal/compiler/lookup/FieldBinding;
     488: getfield      #299                // Field org/eclipse/jdt/internal/compiler/lookup/FieldBinding.type:Lorg/eclipse/jdt/internal/compiler/lookup/TypeBinding;
     491: astore        5
     493: aload_0
     494: getfield      #105                // Field initialization:Lorg/eclipse/jdt/internal/compiler/ast/Expression;
     497: getstatic     #340                // Field org/eclipse/jdt/internal/compiler/ast/ExpressionContext.ASSIGNMENT_CONTEXT:Lorg/eclipse/jdt/internal/compiler/ast/ExpressionContext;
     500: invokevirtual #346                // Method org/eclipse/jdt/internal/compiler/ast/Expression.setExpressionContext:(Lorg/eclipse/jdt/internal/compiler/ast/ExpressionContext;)V
     503: aload_0
     504: getfield      #105                // Field initialization:Lorg/eclipse/jdt/internal/compiler/ast/Expression;
     507: aload         5
     509: invokevirtual #350                // Method org/eclipse/jdt/internal/compiler/ast/Expression.setExpectedType:(Lorg/eclipse/jdt/internal/compiler/lookup/TypeBinding;)V
     512: aload_0
     513: getfield      #105                // Field initialization:Lorg/eclipse/jdt/internal/compiler/ast/Expression;
     516: instanceof    #354                // class org/eclipse/jdt/internal/compiler/ast/ArrayInitializer
     519: ifeq          568
     522: aload_0
     523: getfield      #105                // Field initialization:Lorg/eclipse/jdt/internal/compiler/ast/Expression;
     526: aload_1
     527: aload         5
     529: invokevirtual #356                // Method org/eclipse/jdt/internal/compiler/ast/Expression.resolveTypeExpecting:(Lorg/eclipse/jdt/internal/compiler/lookup/BlockScope;Lorg/eclipse/jdt/internal/compiler/lookup/TypeBinding;)Lorg/eclipse/jdt/internal/compiler/lookup/TypeBinding;
     532: dup
     533: astore        6
     535: ifnull        866
     538: aload_0
     539: getfield      #105                // Field initialization:Lorg/eclipse/jdt/internal/compiler/ast/Expression;
     542: checkcast     #354                // class org/eclipse/jdt/internal/compiler/ast/ArrayInitializer
     545: aload         6
     547: checkcast     #360                // class org/eclipse/jdt/internal/compiler/lookup/ArrayBinding
     550: putfield      #362                // Field org/eclipse/jdt/internal/compiler/ast/ArrayInitializer.binding:Lorg/eclipse/jdt/internal/compiler/lookup/ArrayBinding;
     553: aload_0
     554: getfield      #105                // Field initialization:Lorg/eclipse/jdt/internal/compiler/ast/Expression;
     557: aload_1
     558: aload         5
     560: aload         6
     562: invokevirtual #365                // Method org/eclipse/jdt/internal/compiler/ast/Expression.computeConversion:(Lorg/eclipse/jdt/internal/compiler/lookup/Scope;Lorg/eclipse/jdt/internal/compiler/lookup/TypeBinding;Lorg/eclipse/jdt/internal/compiler/lookup/TypeBinding;)V
     565: goto          866
     568: aload_0
     569: getfield      #105                // Field initialization:Lorg/eclipse/jdt/internal/compiler/ast/Expression;
     572: aload_1
     573: invokevirtual #369                // Method org/eclipse/jdt/internal/compiler/ast/Expression.resolveType:(Lorg/eclipse/jdt/internal/compiler/lookup/BlockScope;)Lorg/eclipse/jdt/internal/compiler/lookup/TypeBinding;
     576: dup
     577: astore        6
     579: ifnull        856
     582: aload         5
     584: aload         6
     586: invokestatic  #373                // Method org/eclipse/jdt/internal/compiler/lookup/TypeBinding.notEquals:(Lorg/eclipse/jdt/internal/compiler/lookup/TypeBinding;Lorg/eclipse/jdt/internal/compiler/lookup/TypeBinding;)Z
     589: ifeq          603
     592: aload_1
     593: invokevirtual #377                // Method org/eclipse/jdt/internal/compiler/lookup/MethodScope.compilationUnitScope:()Lorg/eclipse/jdt/internal/compiler/lookup/CompilationUnitScope;
     596: aload         5
     598: aload         6
     600: invokevirtual #381                // Method org/eclipse/jdt/internal/compiler/lookup/CompilationUnitScope.recordTypeConversion:(Lorg/eclipse/jdt/internal/compiler/lookup/TypeBinding;Lorg/eclipse/jdt/internal/compiler/lookup/TypeBinding;)V
     603: aload_0
     604: getfield      #105                // Field initialization:Lorg/eclipse/jdt/internal/compiler/ast/Expression;
     607: aload         6
     609: aload         5
     611: invokevirtual #387                // Method org/eclipse/jdt/internal/compiler/ast/Expression.isConstantValueOfTypeAssignableToType:(Lorg/eclipse/jdt/internal/compiler/lookup/TypeBinding;Lorg/eclipse/jdt/internal/compiler/lookup/TypeBinding;)Z
     614: ifne          628
     617: aload         6
     619: aload         5
     621: aload_2
     622: invokevirtual #390                // Method org/eclipse/jdt/internal/compiler/lookup/TypeBinding.isCompatibleWith:(Lorg/eclipse/jdt/internal/compiler/lookup/TypeBinding;Lorg/eclipse/jdt/internal/compiler/lookup/Scope;)Z
     625: ifeq          705
     628: aload_0
     629: getfield      #105                // Field initialization:Lorg/eclipse/jdt/internal/compiler/ast/Expression;
     632: aload_1
     633: aload         5
     635: aload         6
     637: invokevirtual #365                // Method org/eclipse/jdt/internal/compiler/ast/Expression.computeConversion:(Lorg/eclipse/jdt/internal/compiler/lookup/Scope;Lorg/eclipse/jdt/internal/compiler/lookup/TypeBinding;Lorg/eclipse/jdt/internal/compiler/lookup/TypeBinding;)V
     640: aload         6
     642: aload         5
     644: invokevirtual #394                // Method org/eclipse/jdt/internal/compiler/lookup/TypeBinding.needsUncheckedConversion:(Lorg/eclipse/jdt/internal/compiler/lookup/TypeBinding;)Z
     647: ifeq          665
     650: aload_1
     651: invokevirtual #63                 // Method org/eclipse/jdt/internal/compiler/lookup/MethodScope.problemReporter:()Lorg/eclipse/jdt/internal/compiler/problem/ProblemReporter;
     654: aload_0
     655: getfield      #105                // Field initialization:Lorg/eclipse/jdt/internal/compiler/ast/Expression;
     658: aload         6
     660: aload         5
     662: invokevirtual #398                // Method org/eclipse/jdt/internal/compiler/problem/ProblemReporter.unsafeTypeConversion:(Lorg/eclipse/jdt/internal/compiler/ast/Expression;Lorg/eclipse/jdt/internal/compiler/lookup/TypeBinding;Lorg/eclipse/jdt/internal/compiler/lookup/TypeBinding;)V
     665: aload_0
     666: getfield      #105                // Field initialization:Lorg/eclipse/jdt/internal/compiler/ast/Expression;
     669: instanceof    #402                // class org/eclipse/jdt/internal/compiler/ast/CastExpression
     672: ifeq          803
     675: aload_0
     676: getfield      #105                // Field initialization:Lorg/eclipse/jdt/internal/compiler/ast/Expression;
     679: getfield      #404                // Field org/eclipse/jdt/internal/compiler/ast/Expression.bits:I
     682: sipush        16384
     685: iand
     686: ifne          803
     689: aload_1
     690: aload         5
     692: aload_0
     693: getfield      #105                // Field initialization:Lorg/eclipse/jdt/internal/compiler/ast/Expression;
     696: checkcast     #402                // class org/eclipse/jdt/internal/compiler/ast/CastExpression
     699: invokestatic  #405                // Method org/eclipse/jdt/internal/compiler/ast/CastExpression.checkNeedForAssignedCast:(Lorg/eclipse/jdt/internal/compiler/lookup/BlockScope;Lorg/eclipse/jdt/internal/compiler/lookup/TypeBinding;Lorg/eclipse/jdt/internal/compiler/ast/CastExpression;)V
     702: goto          803
     705: aload_0
     706: aload         6
     708: aload         5
     710: aload_0
     711: getfield      #105                // Field initialization:Lorg/eclipse/jdt/internal/compiler/ast/Expression;
     714: aload_1
     715: invokevirtual #409                // Method isBoxingCompatible:(Lorg/eclipse/jdt/internal/compiler/lookup/TypeBinding;Lorg/eclipse/jdt/internal/compiler/lookup/TypeBinding;Lorg/eclipse/jdt/internal/compiler/ast/Expression;Lorg/eclipse/jdt/internal/compiler/lookup/Scope;)Z
     718: ifeq          773
     721: aload_0
     722: getfield      #105                // Field initialization:Lorg/eclipse/jdt/internal/compiler/ast/Expression;
     725: aload_1
     726: aload         5
     728: aload         6
     730: invokevirtual #365                // Method org/eclipse/jdt/internal/compiler/ast/Expression.computeConversion:(Lorg/eclipse/jdt/internal/compiler/lookup/Scope;Lorg/eclipse/jdt/internal/compiler/lookup/TypeBinding;Lorg/eclipse/jdt/internal/compiler/lookup/TypeBinding;)V
     733: aload_0
     734: getfield      #105                // Field initialization:Lorg/eclipse/jdt/internal/compiler/ast/Expression;
     737: instanceof    #402                // class org/eclipse/jdt/internal/compiler/ast/CastExpression
     740: ifeq          803
     743: aload_0
     744: getfield      #105                // Field initialization:Lorg/eclipse/jdt/internal/compiler/ast/Expression;
     747: getfield      #404                // Field org/eclipse/jdt/internal/compiler/ast/Expression.bits:I
     750: sipush        16384
     753: iand
     754: ifne          803
     757: aload_1
     758: aload         5
     760: aload_0
     761: getfield      #105                // Field initialization:Lorg/eclipse/jdt/internal/compiler/ast/Expression;
     764: checkcast     #402                // class org/eclipse/jdt/internal/compiler/ast/CastExpression
     767: invokestatic  #405                // Method org/eclipse/jdt/internal/compiler/ast/CastExpression.checkNeedForAssignedCast:(Lorg/eclipse/jdt/internal/compiler/lookup/BlockScope;Lorg/eclipse/jdt/internal/compiler/lookup/TypeBinding;Lorg/eclipse/jdt/internal/compiler/ast/CastExpression;)V
     770: goto          803
     773: aload         5
     775: getfield      #413                // Field org/eclipse/jdt/internal/compiler/lookup/TypeBinding.tagBits:J
     778: ldc2_w        #416                // long 128l
     781: land
     782: lconst_0
     783: lcmp
     784: ifne          803
     787: aload_1
     788: invokevirtual #63                 // Method org/eclipse/jdt/internal/compiler/lookup/MethodScope.problemReporter:()Lorg/eclipse/jdt/internal/compiler/problem/ProblemReporter;
     791: aload         6
     793: aload         5
     795: aload_0
     796: getfield      #105                // Field initialization:Lorg/eclipse/jdt/internal/compiler/ast/Expression;
     799: aconst_null
     800: invokevirtual #418                // Method org/eclipse/jdt/internal/compiler/problem/ProblemReporter.typeMismatchError:(Lorg/eclipse/jdt/internal/compiler/lookup/TypeBinding;Lorg/eclipse/jdt/internal/compiler/lookup/TypeBinding;Lorg/eclipse/jdt/internal/compiler/ast/ASTNode;Lorg/eclipse/jdt/internal/compiler/ast/ASTNode;)V
     803: aload_0
     804: getfield      #34                 // Field binding:Lorg/eclipse/jdt/internal/compiler/lookup/FieldBinding;
     807: invokevirtual #235                // Method org/eclipse/jdt/internal/compiler/lookup/FieldBinding.isFinal:()Z
     810: ifeq          866
     813: aload_0
     814: getfield      #34                 // Field binding:Lorg/eclipse/jdt/internal/compiler/lookup/FieldBinding;
     817: aload_0
     818: getfield      #105                // Field initialization:Lorg/eclipse/jdt/internal/compiler/ast/Expression;
     821: getfield      #422                // Field org/eclipse/jdt/internal/compiler/ast/Expression.constant:Lorg/eclipse/jdt/internal/compiler/impl/Constant;
     824: aload_0
     825: getfield      #34                 // Field binding:Lorg/eclipse/jdt/internal/compiler/lookup/FieldBinding;
     828: getfield      #299                // Field org/eclipse/jdt/internal/compiler/lookup/FieldBinding.type:Lorg/eclipse/jdt/internal/compiler/lookup/TypeBinding;
     831: getfield      #424                // Field org/eclipse/jdt/internal/compiler/lookup/TypeBinding.id:I
     834: iconst_4
     835: ishl
     836: aload_0
     837: getfield      #105                // Field initialization:Lorg/eclipse/jdt/internal/compiler/ast/Expression;
     840: getfield      #422                // Field org/eclipse/jdt/internal/compiler/ast/Expression.constant:Lorg/eclipse/jdt/internal/compiler/impl/Constant;
     843: invokevirtual #425                // Method org/eclipse/jdt/internal/compiler/impl/Constant.typeID:()I
     846: iadd
     847: invokevirtual #428                // Method org/eclipse/jdt/internal/compiler/impl/Constant.castTo:(I)Lorg/eclipse/jdt/internal/compiler/impl/Constant;
     850: invokevirtual #336                // Method org/eclipse/jdt/internal/compiler/lookup/FieldBinding.setConstant:(Lorg/eclipse/jdt/internal/compiler/impl/Constant;)V
     853: goto          866
     856: aload_0
     857: getfield      #34                 // Field binding:Lorg/eclipse/jdt/internal/compiler/lookup/FieldBinding;
     860: getstatic     #83                 // Field org/eclipse/jdt/internal/compiler/impl/Constant.NotAConstant:Lorg/eclipse/jdt/internal/compiler/impl/Constant;
     863: invokevirtual #336                // Method org/eclipse/jdt/internal/compiler/lookup/FieldBinding.setConstant:(Lorg/eclipse/jdt/internal/compiler/impl/Constant;)V
     866: aload_0
     867: getfield      #34                 // Field binding:Lorg/eclipse/jdt/internal/compiler/lookup/FieldBinding;
     870: aload_0
     871: getfield      #105                // Field initialization:Lorg/eclipse/jdt/internal/compiler/ast/Expression;
     874: invokestatic  #432                // Method org/eclipse/jdt/internal/compiler/ast/Expression.getDirectBinding:(Lorg/eclipse/jdt/internal/compiler/ast/Expression;)Lorg/eclipse/jdt/internal/compiler/lookup/Binding;
     877: if_acmpne     892
     880: aload_1
     881: invokevirtual #63                 // Method org/eclipse/jdt/internal/compiler/lookup/MethodScope.problemReporter:()Lorg/eclipse/jdt/internal/compiler/problem/ProblemReporter;
     884: aload_0
     885: aload_0
     886: getfield      #22                 // Field name:[C
     889: invokevirtual #436                // Method org/eclipse/jdt/internal/compiler/problem/ProblemReporter.assignmentHasNoEffect:(Lorg/eclipse/jdt/internal/compiler/ast/AbstractVariableDeclaration;[C)V
     892: aload_0
     893: getfield      #239                // Field javadoc:Lorg/eclipse/jdt/internal/compiler/ast/Javadoc;
     896: ifnull        910
     899: aload_0
     900: getfield      #239                // Field javadoc:Lorg/eclipse/jdt/internal/compiler/ast/Javadoc;
     903: aload_1
     904: invokevirtual #440                // Method org/eclipse/jdt/internal/compiler/ast/Javadoc.resolve:(Lorg/eclipse/jdt/internal/compiler/lookup/MethodScope;)V
     907: goto          1062
     910: aload_0
     911: getfield      #34                 // Field binding:Lorg/eclipse/jdt/internal/compiler/lookup/FieldBinding;
     914: ifnull        1062
     917: aload_0
     918: getfield      #34                 // Field binding:Lorg/eclipse/jdt/internal/compiler/lookup/FieldBinding;
     921: getfield      #89                 // Field org/eclipse/jdt/internal/compiler/lookup/FieldBinding.declaringClass:Lorg/eclipse/jdt/internal/compiler/lookup/ReferenceBinding;
     924: ifnull        1062
     927: aload_0
     928: getfield      #34                 // Field binding:Lorg/eclipse/jdt/internal/compiler/lookup/FieldBinding;
     931: getfield      #89                 // Field org/eclipse/jdt/internal/compiler/lookup/FieldBinding.declaringClass:Lorg/eclipse/jdt/internal/compiler/lookup/ReferenceBinding;
     934: invokevirtual #442                // Method org/eclipse/jdt/internal/compiler/lookup/ReferenceBinding.isLocalType:()Z
     937: ifne          1062
     940: aload_0
     941: getfield      #34                 // Field binding:Lorg/eclipse/jdt/internal/compiler/lookup/FieldBinding;
     944: getfield      #330                // Field org/eclipse/jdt/internal/compiler/lookup/FieldBinding.modifiers:I
     947: bipush        7
     949: iand
     950: istore        5
     952: aload_1
     953: invokevirtual #63                 // Method org/eclipse/jdt/internal/compiler/lookup/MethodScope.problemReporter:()Lorg/eclipse/jdt/internal/compiler/problem/ProblemReporter;
     956: astore        6
     958: aload         6
     960: ldc_w         #445                // int -1610612250
     963: invokevirtual #446                // Method org/eclipse/jdt/internal/compiler/problem/ProblemReporter.computeSeverity:(I)I
     966: istore        7
     968: iload         7
     970: sipush        256
     973: if_icmpeq     1062
     976: aload_2
     977: ifnull        991
     980: aload_2
     981: invokevirtual #450                // Method org/eclipse/jdt/internal/compiler/lookup/ClassScope.referenceType:()Lorg/eclipse/jdt/internal/compiler/ast/TypeDeclaration;
     984: iload         5
     986: invokestatic  #454                // Method org/eclipse/jdt/internal/compiler/util/Util.computeOuterMostVisibility:(Lorg/eclipse/jdt/internal/compiler/ast/TypeDeclaration;I)I
     989: istore        5
     991: aload_0
     992: getfield      #34                 // Field binding:Lorg/eclipse/jdt/internal/compiler/lookup/FieldBinding;
     995: getfield      #330                // Field org/eclipse/jdt/internal/compiler/lookup/FieldBinding.modifiers:I
     998: bipush        -8
    1000: iand
    1001: iload         5
    1003: ior
    1004: istore        8
    1006: aload         6
    1008: aload_0
    1009: getfield      #26                 // Field sourceStart:I
    1012: aload_0
    1013: getfield      #29                 // Field sourceEnd:I
    1016: iload         7
    1018: iload         8
    1020: invokevirtual #460                // Method org/eclipse/jdt/internal/compiler/problem/ProblemReporter.javadocMissing:(IIII)V
    1023: goto          1062
    1026: astore        9
    1028: aload_1
    1029: aload_3
    1030: putfield      #304                // Field org/eclipse/jdt/internal/compiler/lookup/MethodScope.initializedField:Lorg/eclipse/jdt/internal/compiler/lookup/FieldBinding;
    1033: aload_1
    1034: iload         4
    1036: putfield      #307                // Field org/eclipse/jdt/internal/compiler/lookup/MethodScope.lastVisibleFieldID:I
    1039: aload_0
    1040: getfield      #34                 // Field binding:Lorg/eclipse/jdt/internal/compiler/lookup/FieldBinding;
    1043: invokevirtual #79                 // Method org/eclipse/jdt/internal/compiler/lookup/FieldBinding.constant:()Lorg/eclipse/jdt/internal/compiler/impl/Constant;
    1046: ifnonnull     1059
    1049: aload_0
    1050: getfield      #34                 // Field binding:Lorg/eclipse/jdt/internal/compiler/lookup/FieldBinding;
    1053: getstatic     #83                 // Field org/eclipse/jdt/internal/compiler/impl/Constant.NotAConstant:Lorg/eclipse/jdt/internal/compiler/impl/Constant;
    1056: invokevirtual #336                // Method org/eclipse/jdt/internal/compiler/lookup/FieldBinding.setConstant:(Lorg/eclipse/jdt/internal/compiler/impl/Constant;)V
    1059: aload         9
    1061: athrow
    1062: aload_1
    1063: aload_3
    1064: putfield      #304                // Field org/eclipse/jdt/internal/compiler/lookup/MethodScope.initializedField:Lorg/eclipse/jdt/internal/compiler/lookup/FieldBinding;
    1067: aload_1
    1068: iload         4
    1070: putfield      #307                // Field org/eclipse/jdt/internal/compiler/lookup/MethodScope.lastVisibleFieldID:I
    1073: aload_0
    1074: getfield      #34                 // Field binding:Lorg/eclipse/jdt/internal/compiler/lookup/FieldBinding;
    1077: invokevirtual #79                 // Method org/eclipse/jdt/internal/compiler/lookup/FieldBinding.constant:()Lorg/eclipse/jdt/internal/compiler/impl/Constant;
    1080: ifnonnull     1093
    1083: aload_0
    1084: getfield      #34                 // Field binding:Lorg/eclipse/jdt/internal/compiler/lookup/FieldBinding;
    1087: getstatic     #83                 // Field org/eclipse/jdt/internal/compiler/impl/Constant.NotAConstant:Lorg/eclipse/jdt/internal/compiler/impl/Constant;
    1090: invokevirtual #336                // Method org/eclipse/jdt/internal/compiler/lookup/FieldBinding.setConstant:(Lorg/eclipse/jdt/internal/compiler/impl/Constant;)V
    1093: return
    Exception table:
       from    to  target type
         295  1026  1026   any

  public void traverse(org.eclipse.jdt.internal.compiler.ASTVisitor, org.eclipse.jdt.internal.compiler.lookup.MethodScope);
    Code:
       0: aload_1
       1: aload_0
       2: aload_2
       3: invokevirtual #485                // Method org/eclipse/jdt/internal/compiler/ASTVisitor.visit:(Lorg/eclipse/jdt/internal/compiler/ast/FieldDeclaration;Lorg/eclipse/jdt/internal/compiler/lookup/MethodScope;)Z
       6: ifeq          97
       9: aload_0
      10: getfield      #239                // Field javadoc:Lorg/eclipse/jdt/internal/compiler/ast/Javadoc;
      13: ifnull        25
      16: aload_0
      17: getfield      #239                // Field javadoc:Lorg/eclipse/jdt/internal/compiler/ast/Javadoc;
      20: aload_1
      21: aload_2
      22: invokevirtual #491                // Method org/eclipse/jdt/internal/compiler/ast/Javadoc.traverse:(Lorg/eclipse/jdt/internal/compiler/ASTVisitor;Lorg/eclipse/jdt/internal/compiler/lookup/BlockScope;)V
      25: aload_0
      26: getfield      #210                // Field annotations:[Lorg/eclipse/jdt/internal/compiler/ast/Annotation;
      29: ifnull        65
      32: aload_0
      33: getfield      #210                // Field annotations:[Lorg/eclipse/jdt/internal/compiler/ast/Annotation;
      36: arraylength
      37: istore_3
      38: iconst_0
      39: istore        4
      41: goto          59
      44: aload_0
      45: getfield      #210                // Field annotations:[Lorg/eclipse/jdt/internal/compiler/ast/Annotation;
      48: iload         4
      50: aaload
      51: aload_1
      52: aload_2
      53: invokevirtual #214                // Method org/eclipse/jdt/internal/compiler/ast/Annotation.traverse:(Lorg/eclipse/jdt/internal/compiler/ASTVisitor;Lorg/eclipse/jdt/internal/compiler/lookup/BlockScope;)V
      56: iinc          4, 1
      59: iload         4
      61: iload_3
      62: if_icmplt     44
      65: aload_0
      66: getfield      #203                // Field type:Lorg/eclipse/jdt/internal/compiler/ast/TypeReference;
      69: ifnull        81
      72: aload_0
      73: getfield      #203                // Field type:Lorg/eclipse/jdt/internal/compiler/ast/TypeReference;
      76: aload_1
      77: aload_2
      78: invokevirtual #492                // Method org/eclipse/jdt/internal/compiler/ast/TypeReference.traverse:(Lorg/eclipse/jdt/internal/compiler/ASTVisitor;Lorg/eclipse/jdt/internal/compiler/lookup/BlockScope;)V
      81: aload_0
      82: getfield      #105                // Field initialization:Lorg/eclipse/jdt/internal/compiler/ast/Expression;
      85: ifnull        97
      88: aload_0
      89: getfield      #105                // Field initialization:Lorg/eclipse/jdt/internal/compiler/ast/Expression;
      92: aload_1
      93: aload_2
      94: invokevirtual #493                // Method org/eclipse/jdt/internal/compiler/ast/Expression.traverse:(Lorg/eclipse/jdt/internal/compiler/ASTVisitor;Lorg/eclipse/jdt/internal/compiler/lookup/BlockScope;)V
      97: aload_1
      98: aload_0
      99: aload_2
     100: invokevirtual #494                // Method org/eclipse/jdt/internal/compiler/ASTVisitor.endVisit:(Lorg/eclipse/jdt/internal/compiler/ast/FieldDeclaration;Lorg/eclipse/jdt/internal/compiler/lookup/MethodScope;)V
     103: return
}
