Compiled from "JavadocArrayQualifiedTypeReference.java"
public class org.eclipse.jdt.internal.compiler.ast.JavadocArrayQualifiedTypeReference extends org.eclipse.jdt.internal.compiler.ast.ArrayQualifiedTypeReference {
  public int tagSourceStart;

  public int tagSourceEnd;

  public org.eclipse.jdt.internal.compiler.ast.JavadocArrayQualifiedTypeReference(org.eclipse.jdt.internal.compiler.ast.JavadocQualifiedTypeReference, int);
    Code:
       0: aload_0
       1: aload_1
       2: getfield      #11                 // Field org/eclipse/jdt/internal/compiler/ast/JavadocQualifiedTypeReference.tokens:[[C
       5: iload_2
       6: aload_1
       7: getfield      #17                 // Field org/eclipse/jdt/internal/compiler/ast/JavadocQualifiedTypeReference.sourcePositions:[J
      10: invokespecial #21                 // Method org/eclipse/jdt/internal/compiler/ast/ArrayQualifiedTypeReference."<init>":([[CI[J)V
      13: return

  protected void reportInvalidType(org.eclipse.jdt.internal.compiler.lookup.Scope);
    Code:
       0: aload_1
       1: invokevirtual #33                 // Method org/eclipse/jdt/internal/compiler/lookup/Scope.problemReporter:()Lorg/eclipse/jdt/internal/compiler/problem/ProblemReporter;
       4: aload_0
       5: aload_0
       6: getfield      #39                 // Field resolvedType:Lorg/eclipse/jdt/internal/compiler/lookup/TypeBinding;
       9: aload_1
      10: invokevirtual #43                 // Method org/eclipse/jdt/internal/compiler/lookup/Scope.getDeclarationModifiers:()I
      13: invokevirtual #47                 // Method org/eclipse/jdt/internal/compiler/problem/ProblemReporter.javadocInvalidType:(Lorg/eclipse/jdt/internal/compiler/ast/ASTNode;Lorg/eclipse/jdt/internal/compiler/lookup/TypeBinding;I)V
      16: return

  protected void reportDeprecatedType(org.eclipse.jdt.internal.compiler.lookup.TypeBinding, org.eclipse.jdt.internal.compiler.lookup.Scope);
    Code:
       0: aload_2
       1: invokevirtual #33                 // Method org/eclipse/jdt/internal/compiler/lookup/Scope.problemReporter:()Lorg/eclipse/jdt/internal/compiler/problem/ProblemReporter;
       4: aload_1
       5: aload_0
       6: aload_2
       7: invokevirtual #43                 // Method org/eclipse/jdt/internal/compiler/lookup/Scope.getDeclarationModifiers:()I
      10: invokevirtual #57                 // Method org/eclipse/jdt/internal/compiler/problem/ProblemReporter.javadocDeprecatedType:(Lorg/eclipse/jdt/internal/compiler/lookup/TypeBinding;Lorg/eclipse/jdt/internal/compiler/ast/ASTNode;I)V
      13: return

  public void traverse(org.eclipse.jdt.internal.compiler.ASTVisitor, org.eclipse.jdt.internal.compiler.lookup.BlockScope);
    Code:
       0: aload_1
       1: aload_0
       2: aload_2
       3: invokevirtual #64                 // Method org/eclipse/jdt/internal/compiler/ASTVisitor.visit:(Lorg/eclipse/jdt/internal/compiler/ast/JavadocArrayQualifiedTypeReference;Lorg/eclipse/jdt/internal/compiler/lookup/BlockScope;)Z
       6: pop
       7: aload_1
       8: aload_0
       9: aload_2
      10: invokevirtual #70                 // Method org/eclipse/jdt/internal/compiler/ASTVisitor.endVisit:(Lorg/eclipse/jdt/internal/compiler/ast/JavadocArrayQualifiedTypeReference;Lorg/eclipse/jdt/internal/compiler/lookup/BlockScope;)V
      13: return

  public void traverse(org.eclipse.jdt.internal.compiler.ASTVisitor, org.eclipse.jdt.internal.compiler.lookup.ClassScope);
    Code:
       0: aload_1
       1: aload_0
       2: aload_2
       3: invokevirtual #78                 // Method org/eclipse/jdt/internal/compiler/ASTVisitor.visit:(Lorg/eclipse/jdt/internal/compiler/ast/JavadocArrayQualifiedTypeReference;Lorg/eclipse/jdt/internal/compiler/lookup/ClassScope;)Z
       6: pop
       7: aload_1
       8: aload_0
       9: aload_2
      10: invokevirtual #81                 // Method org/eclipse/jdt/internal/compiler/ASTVisitor.endVisit:(Lorg/eclipse/jdt/internal/compiler/ast/JavadocArrayQualifiedTypeReference;Lorg/eclipse/jdt/internal/compiler/lookup/ClassScope;)V
      13: return
}
