Compiled from "JavadocSingleTypeReference.java"
public class org.eclipse.jdt.internal.compiler.ast.JavadocSingleTypeReference extends org.eclipse.jdt.internal.compiler.ast.SingleTypeReference {
  public int tagSourceStart;

  public int tagSourceEnd;

  public org.eclipse.jdt.internal.compiler.lookup.PackageBinding packageBinding;

  public org.eclipse.jdt.internal.compiler.ast.JavadocSingleTypeReference(char[], long, int, int);
    Code:
       0: aload_0
       1: aload_1
       2: lload_2
       3: invokespecial #13                 // Method org/eclipse/jdt/internal/compiler/ast/SingleTypeReference."<init>":([CJ)V
       6: aload_0
       7: iload         4
       9: putfield      #16                 // Field tagSourceStart:I
      12: aload_0
      13: iload         5
      15: putfield      #18                 // Field tagSourceEnd:I
      18: aload_0
      19: dup
      20: getfield      #20                 // Field bits:I
      23: ldc           #23                 // int 32768
      25: ior
      26: putfield      #20                 // Field bits:I
      29: return

  protected org.eclipse.jdt.internal.compiler.lookup.TypeBinding internalResolveType(org.eclipse.jdt.internal.compiler.lookup.Scope, int);
    Code:
       0: aload_0
       1: getstatic     #36                 // Field org/eclipse/jdt/internal/compiler/impl/Constant.NotAConstant:Lorg/eclipse/jdt/internal/compiler/impl/Constant;
       4: putfield      #42                 // Field constant:Lorg/eclipse/jdt/internal/compiler/impl/Constant;
       7: aload_0
       8: getfield      #45                 // Field resolvedType:Lorg/eclipse/jdt/internal/compiler/lookup/TypeBinding;
      11: ifnull        84
      14: aload_0
      15: getfield      #45                 // Field resolvedType:Lorg/eclipse/jdt/internal/compiler/lookup/TypeBinding;
      18: invokevirtual #49                 // Method org/eclipse/jdt/internal/compiler/lookup/TypeBinding.isValidBinding:()Z
      21: ifeq          29
      24: aload_0
      25: getfield      #45                 // Field resolvedType:Lorg/eclipse/jdt/internal/compiler/lookup/TypeBinding;
      28: areturn
      29: aload_0
      30: getfield      #45                 // Field resolvedType:Lorg/eclipse/jdt/internal/compiler/lookup/TypeBinding;
      33: invokevirtual #55                 // Method org/eclipse/jdt/internal/compiler/lookup/TypeBinding.problemId:()I
      36: tableswitch   { // 1 to 5
                     1: 72
                     2: 72
                     3: 82
                     4: 82
                     5: 72
               default: 82
          }
      72: aload_0
      73: getfield      #45                 // Field resolvedType:Lorg/eclipse/jdt/internal/compiler/lookup/TypeBinding;
      76: invokevirtual #59                 // Method org/eclipse/jdt/internal/compiler/lookup/TypeBinding.closestMatch:()Lorg/eclipse/jdt/internal/compiler/lookup/TypeBinding;
      79: astore_3
      80: aload_3
      81: areturn
      82: aconst_null
      83: areturn
      84: aload_0
      85: aload_0
      86: aload_1
      87: invokevirtual #63                 // Method getTypeBinding:(Lorg/eclipse/jdt/internal/compiler/lookup/Scope;)Lorg/eclipse/jdt/internal/compiler/lookup/TypeBinding;
      90: putfield      #45                 // Field resolvedType:Lorg/eclipse/jdt/internal/compiler/lookup/TypeBinding;
      93: aload_0
      94: getfield      #45                 // Field resolvedType:Lorg/eclipse/jdt/internal/compiler/lookup/TypeBinding;
      97: ifnonnull     102
     100: aconst_null
     101: areturn
     102: aload_0
     103: getfield      #45                 // Field resolvedType:Lorg/eclipse/jdt/internal/compiler/lookup/TypeBinding;
     106: invokevirtual #49                 // Method org/eclipse/jdt/internal/compiler/lookup/TypeBinding.isValidBinding:()Z
     109: ifne          203
     112: iconst_1
     113: anewarray     #67                 // class "[C"
     116: dup
     117: iconst_0
     118: aload_0
     119: getfield      #68                 // Field token:[C
     122: aastore
     123: astore_3
     124: aload_1
     125: aload_3
     126: invokevirtual #71                 // Method org/eclipse/jdt/internal/compiler/lookup/Scope.getTypeOrPackage:([[C)Lorg/eclipse/jdt/internal/compiler/lookup/Binding;
     129: astore        4
     131: aload         4
     133: instanceof    #77                 // class org/eclipse/jdt/internal/compiler/lookup/PackageBinding
     136: ifeq          151
     139: aload_0
     140: aload         4
     142: checkcast     #77                 // class org/eclipse/jdt/internal/compiler/lookup/PackageBinding
     145: putfield      #79                 // Field packageBinding:Lorg/eclipse/jdt/internal/compiler/lookup/PackageBinding;
     148: goto          201
     151: aload_0
     152: getfield      #45                 // Field resolvedType:Lorg/eclipse/jdt/internal/compiler/lookup/TypeBinding;
     155: invokevirtual #55                 // Method org/eclipse/jdt/internal/compiler/lookup/TypeBinding.problemId:()I
     158: bipush        7
     160: if_icmpne     196
     163: aload_0
     164: getfield      #45                 // Field resolvedType:Lorg/eclipse/jdt/internal/compiler/lookup/TypeBinding;
     167: invokevirtual #59                 // Method org/eclipse/jdt/internal/compiler/lookup/TypeBinding.closestMatch:()Lorg/eclipse/jdt/internal/compiler/lookup/TypeBinding;
     170: astore        5
     172: aload         5
     174: ifnull        196
     177: aload         5
     179: invokevirtual #81                 // Method org/eclipse/jdt/internal/compiler/lookup/TypeBinding.isTypeVariable:()Z
     182: ifeq          196
     185: aload_0
     186: aload         5
     188: putfield      #45                 // Field resolvedType:Lorg/eclipse/jdt/internal/compiler/lookup/TypeBinding;
     191: aload_0
     192: getfield      #45                 // Field resolvedType:Lorg/eclipse/jdt/internal/compiler/lookup/TypeBinding;
     195: areturn
     196: aload_0
     197: aload_1
     198: invokevirtual #84                 // Method reportInvalidType:(Lorg/eclipse/jdt/internal/compiler/lookup/Scope;)V
     201: aconst_null
     202: areturn
     203: aload_0
     204: aload_0
     205: getfield      #45                 // Field resolvedType:Lorg/eclipse/jdt/internal/compiler/lookup/TypeBinding;
     208: aload_1
     209: invokevirtual #88                 // Method isTypeUseDeprecated:(Lorg/eclipse/jdt/internal/compiler/lookup/TypeBinding;Lorg/eclipse/jdt/internal/compiler/lookup/Scope;)Z
     212: ifeq          224
     215: aload_0
     216: aload_0
     217: getfield      #45                 // Field resolvedType:Lorg/eclipse/jdt/internal/compiler/lookup/TypeBinding;
     220: aload_1
     221: invokevirtual #92                 // Method reportDeprecatedType:(Lorg/eclipse/jdt/internal/compiler/lookup/TypeBinding;Lorg/eclipse/jdt/internal/compiler/lookup/Scope;)V
     224: aload_0
     225: getfield      #45                 // Field resolvedType:Lorg/eclipse/jdt/internal/compiler/lookup/TypeBinding;
     228: invokevirtual #96                 // Method org/eclipse/jdt/internal/compiler/lookup/TypeBinding.isGenericType:()Z
     231: ifne          244
     234: aload_0
     235: getfield      #45                 // Field resolvedType:Lorg/eclipse/jdt/internal/compiler/lookup/TypeBinding;
     238: invokevirtual #99                 // Method org/eclipse/jdt/internal/compiler/lookup/TypeBinding.isParameterizedType:()Z
     241: ifeq          260
     244: aload_0
     245: aload_1
     246: invokevirtual #102                // Method org/eclipse/jdt/internal/compiler/lookup/Scope.environment:()Lorg/eclipse/jdt/internal/compiler/lookup/LookupEnvironment;
     249: aload_0
     250: getfield      #45                 // Field resolvedType:Lorg/eclipse/jdt/internal/compiler/lookup/TypeBinding;
     253: iconst_1
     254: invokevirtual #106                // Method org/eclipse/jdt/internal/compiler/lookup/LookupEnvironment.convertToRawType:(Lorg/eclipse/jdt/internal/compiler/lookup/TypeBinding;Z)Lorg/eclipse/jdt/internal/compiler/lookup/TypeBinding;
     257: putfield      #45                 // Field resolvedType:Lorg/eclipse/jdt/internal/compiler/lookup/TypeBinding;
     260: aload_0
     261: getfield      #45                 // Field resolvedType:Lorg/eclipse/jdt/internal/compiler/lookup/TypeBinding;
     264: areturn

  protected void reportDeprecatedType(org.eclipse.jdt.internal.compiler.lookup.TypeBinding, org.eclipse.jdt.internal.compiler.lookup.Scope);
    Code:
       0: aload_2
       1: invokevirtual #124                // Method org/eclipse/jdt/internal/compiler/lookup/Scope.problemReporter:()Lorg/eclipse/jdt/internal/compiler/problem/ProblemReporter;
       4: aload_1
       5: aload_0
       6: aload_2
       7: invokevirtual #128                // Method org/eclipse/jdt/internal/compiler/lookup/Scope.getDeclarationModifiers:()I
      10: invokevirtual #131                // Method org/eclipse/jdt/internal/compiler/problem/ProblemReporter.javadocDeprecatedType:(Lorg/eclipse/jdt/internal/compiler/lookup/TypeBinding;Lorg/eclipse/jdt/internal/compiler/ast/ASTNode;I)V
      13: return

  protected void reportInvalidType(org.eclipse.jdt.internal.compiler.lookup.Scope);
    Code:
       0: aload_1
       1: invokevirtual #124                // Method org/eclipse/jdt/internal/compiler/lookup/Scope.problemReporter:()Lorg/eclipse/jdt/internal/compiler/problem/ProblemReporter;
       4: aload_0
       5: aload_0
       6: getfield      #45                 // Field resolvedType:Lorg/eclipse/jdt/internal/compiler/lookup/TypeBinding;
       9: aload_1
      10: invokevirtual #128                // Method org/eclipse/jdt/internal/compiler/lookup/Scope.getDeclarationModifiers:()I
      13: invokevirtual #137                // Method org/eclipse/jdt/internal/compiler/problem/ProblemReporter.javadocInvalidType:(Lorg/eclipse/jdt/internal/compiler/ast/ASTNode;Lorg/eclipse/jdt/internal/compiler/lookup/TypeBinding;I)V
      16: return

  public void traverse(org.eclipse.jdt.internal.compiler.ASTVisitor, org.eclipse.jdt.internal.compiler.lookup.BlockScope);
    Code:
       0: aload_1
       1: aload_0
       2: aload_2
       3: invokevirtual #143                // Method org/eclipse/jdt/internal/compiler/ASTVisitor.visit:(Lorg/eclipse/jdt/internal/compiler/ast/JavadocSingleTypeReference;Lorg/eclipse/jdt/internal/compiler/lookup/BlockScope;)Z
       6: pop
       7: aload_1
       8: aload_0
       9: aload_2
      10: invokevirtual #149                // Method org/eclipse/jdt/internal/compiler/ASTVisitor.endVisit:(Lorg/eclipse/jdt/internal/compiler/ast/JavadocSingleTypeReference;Lorg/eclipse/jdt/internal/compiler/lookup/BlockScope;)V
      13: return

  public void traverse(org.eclipse.jdt.internal.compiler.ASTVisitor, org.eclipse.jdt.internal.compiler.lookup.ClassScope);
    Code:
       0: aload_1
       1: aload_0
       2: aload_2
       3: invokevirtual #157                // Method org/eclipse/jdt/internal/compiler/ASTVisitor.visit:(Lorg/eclipse/jdt/internal/compiler/ast/JavadocSingleTypeReference;Lorg/eclipse/jdt/internal/compiler/lookup/ClassScope;)Z
       6: pop
       7: aload_1
       8: aload_0
       9: aload_2
      10: invokevirtual #160                // Method org/eclipse/jdt/internal/compiler/ASTVisitor.endVisit:(Lorg/eclipse/jdt/internal/compiler/ast/JavadocSingleTypeReference;Lorg/eclipse/jdt/internal/compiler/lookup/ClassScope;)V
      13: return
}
