Compiled from "LongLiteralMinValue.java"
public class org.eclipse.jdt.internal.compiler.ast.LongLiteralMinValue extends org.eclipse.jdt.internal.compiler.ast.LongLiteral {
  static final char[] CharValue;

  static {};
    Code:
       0: bipush        21
       2: newarray       char
       4: dup
       5: iconst_0
       6: bipush        45
       8: castore
       9: dup
      10: iconst_1
      11: bipush        57
      13: castore
      14: dup
      15: iconst_2
      16: bipush        50
      18: castore
      19: dup
      20: iconst_3
      21: bipush        50
      23: castore
      24: dup
      25: iconst_4
      26: bipush        51
      28: castore
      29: dup
      30: iconst_5
      31: bipush        51
      33: castore
      34: dup
      35: bipush        6
      37: bipush        55
      39: castore
      40: dup
      41: bipush        7
      43: bipush        50
      45: castore
      46: dup
      47: bipush        8
      49: bipush        48
      51: castore
      52: dup
      53: bipush        9
      55: bipush        51
      57: castore
      58: dup
      59: bipush        10
      61: bipush        54
      63: castore
      64: dup
      65: bipush        11
      67: bipush        56
      69: castore
      70: dup
      71: bipush        12
      73: bipush        53
      75: castore
      76: dup
      77: bipush        13
      79: bipush        52
      81: castore
      82: dup
      83: bipush        14
      85: bipush        55
      87: castore
      88: dup
      89: bipush        15
      91: bipush        55
      93: castore
      94: dup
      95: bipush        16
      97: bipush        53
      99: castore
     100: dup
     101: bipush        17
     103: bipush        56
     105: castore
     106: dup
     107: bipush        18
     109: bipush        48
     111: castore
     112: dup
     113: bipush        19
     115: bipush        56
     117: castore
     118: dup
     119: bipush        20
     121: bipush        76
     123: castore
     124: putstatic     #10                 // Field CharValue:[C
     127: return

  public org.eclipse.jdt.internal.compiler.ast.LongLiteralMinValue(char[], char[], int, int);
    Code:
       0: aload_0
       1: aload_1
       2: aload_2
       3: iload_3
       4: iload         4
       6: invokespecial #16                 // Method org/eclipse/jdt/internal/compiler/ast/LongLiteral."<init>":([C[CII)V
       9: aload_0
      10: ldc2_w        #18                 // long -9223372036854775808l
      13: invokestatic  #20                 // Method org/eclipse/jdt/internal/compiler/impl/LongConstant.fromValue:(J)Lorg/eclipse/jdt/internal/compiler/impl/Constant;
      16: putfield      #26                 // Field constant:Lorg/eclipse/jdt/internal/compiler/impl/Constant;
      19: return

  public void computeConstant();
    Code:
       0: return
}
