Compiled from "MemberValuePair.java"
class org.eclipse.jdt.internal.compiler.ast.MemberValuePair$2 implements java.lang.Runnable {
  final org.eclipse.jdt.internal.compiler.ast.MemberValuePair this$0;

  private final org.eclipse.jdt.internal.compiler.lookup.TypeBinding val$valueType;

  private final org.eclipse.jdt.internal.compiler.lookup.TypeBinding val$requiredType;

  private final org.eclipse.jdt.internal.compiler.lookup.TypeBinding val$leafType;

  private final org.eclipse.jdt.internal.compiler.lookup.BlockScope val$scope;

  private final boolean[] val$shouldExit;

  org.eclipse.jdt.internal.compiler.ast.MemberValuePair$2(org.eclipse.jdt.internal.compiler.ast.MemberValuePair, org.eclipse.jdt.internal.compiler.lookup.TypeBinding, org.eclipse.jdt.internal.compiler.lookup.TypeBinding, org.eclipse.jdt.internal.compiler.lookup.TypeBinding, org.eclipse.jdt.internal.compiler.lookup.BlockScope, boolean[]);
    Code:
       0: aload_0
       1: aload_1
       2: putfield      #20                 // Field this$0:Lorg/eclipse/jdt/internal/compiler/ast/MemberValuePair;
       5: aload_0
       6: aload_2
       7: putfield      #22                 // Field val$valueType:Lorg/eclipse/jdt/internal/compiler/lookup/TypeBinding;
      10: aload_0
      11: aload_3
      12: putfield      #24                 // Field val$requiredType:Lorg/eclipse/jdt/internal/compiler/lookup/TypeBinding;
      15: aload_0
      16: aload         4
      18: putfield      #26                 // Field val$leafType:Lorg/eclipse/jdt/internal/compiler/lookup/TypeBinding;
      21: aload_0
      22: aload         5
      24: putfield      #28                 // Field val$scope:Lorg/eclipse/jdt/internal/compiler/lookup/BlockScope;
      27: aload_0
      28: aload         6
      30: putfield      #30                 // Field val$shouldExit:[Z
      33: aload_0
      34: invokespecial #32                 // Method java/lang/Object."<init>":()V
      37: return

  public void run();
    Code:
       0: aload_0
       1: getfield      #20                 // Field this$0:Lorg/eclipse/jdt/internal/compiler/ast/MemberValuePair;
       4: getfield      #40                 // Field org/eclipse/jdt/internal/compiler/ast/MemberValuePair.value:Lorg/eclipse/jdt/internal/compiler/ast/Expression;
       7: aload_0
       8: getfield      #22                 // Field val$valueType:Lorg/eclipse/jdt/internal/compiler/lookup/TypeBinding;
      11: aload_0
      12: getfield      #24                 // Field val$requiredType:Lorg/eclipse/jdt/internal/compiler/lookup/TypeBinding;
      15: invokevirtual #46                 // Method org/eclipse/jdt/internal/compiler/ast/Expression.isConstantValueOfTypeAssignableToType:(Lorg/eclipse/jdt/internal/compiler/lookup/TypeBinding;Lorg/eclipse/jdt/internal/compiler/lookup/TypeBinding;)Z
      18: ifne          188
      21: aload_0
      22: getfield      #22                 // Field val$valueType:Lorg/eclipse/jdt/internal/compiler/lookup/TypeBinding;
      25: aload_0
      26: getfield      #24                 // Field val$requiredType:Lorg/eclipse/jdt/internal/compiler/lookup/TypeBinding;
      29: invokevirtual #52                 // Method org/eclipse/jdt/internal/compiler/lookup/TypeBinding.isCompatibleWith:(Lorg/eclipse/jdt/internal/compiler/lookup/TypeBinding;)Z
      32: ifne          188
      35: aload_0
      36: getfield      #24                 // Field val$requiredType:Lorg/eclipse/jdt/internal/compiler/lookup/TypeBinding;
      39: invokevirtual #58                 // Method org/eclipse/jdt/internal/compiler/lookup/TypeBinding.isArrayType:()Z
      42: ifeq          91
      45: aload_0
      46: getfield      #24                 // Field val$requiredType:Lorg/eclipse/jdt/internal/compiler/lookup/TypeBinding;
      49: invokevirtual #62                 // Method org/eclipse/jdt/internal/compiler/lookup/TypeBinding.dimensions:()I
      52: iconst_1
      53: if_icmpne     91
      56: aload_0
      57: getfield      #20                 // Field this$0:Lorg/eclipse/jdt/internal/compiler/ast/MemberValuePair;
      60: getfield      #40                 // Field org/eclipse/jdt/internal/compiler/ast/MemberValuePair.value:Lorg/eclipse/jdt/internal/compiler/ast/Expression;
      63: aload_0
      64: getfield      #22                 // Field val$valueType:Lorg/eclipse/jdt/internal/compiler/lookup/TypeBinding;
      67: aload_0
      68: getfield      #26                 // Field val$leafType:Lorg/eclipse/jdt/internal/compiler/lookup/TypeBinding;
      71: invokevirtual #46                 // Method org/eclipse/jdt/internal/compiler/ast/Expression.isConstantValueOfTypeAssignableToType:(Lorg/eclipse/jdt/internal/compiler/lookup/TypeBinding;Lorg/eclipse/jdt/internal/compiler/lookup/TypeBinding;)Z
      74: ifne          234
      77: aload_0
      78: getfield      #22                 // Field val$valueType:Lorg/eclipse/jdt/internal/compiler/lookup/TypeBinding;
      81: aload_0
      82: getfield      #26                 // Field val$leafType:Lorg/eclipse/jdt/internal/compiler/lookup/TypeBinding;
      85: invokevirtual #52                 // Method org/eclipse/jdt/internal/compiler/lookup/TypeBinding.isCompatibleWith:(Lorg/eclipse/jdt/internal/compiler/lookup/TypeBinding;)Z
      88: ifne          234
      91: aload_0
      92: getfield      #26                 // Field val$leafType:Lorg/eclipse/jdt/internal/compiler/lookup/TypeBinding;
      95: invokevirtual #66                 // Method org/eclipse/jdt/internal/compiler/lookup/TypeBinding.isAnnotationType:()Z
      98: ifeq          152
     101: aload_0
     102: getfield      #22                 // Field val$valueType:Lorg/eclipse/jdt/internal/compiler/lookup/TypeBinding;
     105: invokevirtual #66                 // Method org/eclipse/jdt/internal/compiler/lookup/TypeBinding.isAnnotationType:()Z
     108: ifne          152
     111: aload_0
     112: getfield      #28                 // Field val$scope:Lorg/eclipse/jdt/internal/compiler/lookup/BlockScope;
     115: invokevirtual #69                 // Method org/eclipse/jdt/internal/compiler/lookup/BlockScope.problemReporter:()Lorg/eclipse/jdt/internal/compiler/problem/ProblemReporter;
     118: aload_0
     119: getfield      #20                 // Field this$0:Lorg/eclipse/jdt/internal/compiler/ast/MemberValuePair;
     122: getfield      #75                 // Field org/eclipse/jdt/internal/compiler/ast/MemberValuePair.binding:Lorg/eclipse/jdt/internal/compiler/lookup/MethodBinding;
     125: getfield      #79                 // Field org/eclipse/jdt/internal/compiler/lookup/MethodBinding.declaringClass:Lorg/eclipse/jdt/internal/compiler/lookup/ReferenceBinding;
     128: aload_0
     129: getfield      #20                 // Field this$0:Lorg/eclipse/jdt/internal/compiler/ast/MemberValuePair;
     132: getfield      #85                 // Field org/eclipse/jdt/internal/compiler/ast/MemberValuePair.name:[C
     135: aload_0
     136: getfield      #20                 // Field this$0:Lorg/eclipse/jdt/internal/compiler/ast/MemberValuePair;
     139: getfield      #40                 // Field org/eclipse/jdt/internal/compiler/ast/MemberValuePair.value:Lorg/eclipse/jdt/internal/compiler/ast/Expression;
     142: aload_0
     143: getfield      #26                 // Field val$leafType:Lorg/eclipse/jdt/internal/compiler/lookup/TypeBinding;
     146: invokevirtual #89                 // Method org/eclipse/jdt/internal/compiler/problem/ProblemReporter.annotationValueMustBeAnnotation:(Lorg/eclipse/jdt/internal/compiler/lookup/TypeBinding;[CLorg/eclipse/jdt/internal/compiler/ast/Expression;Lorg/eclipse/jdt/internal/compiler/lookup/TypeBinding;)V
     149: goto          178
     152: aload_0
     153: getfield      #28                 // Field val$scope:Lorg/eclipse/jdt/internal/compiler/lookup/BlockScope;
     156: invokevirtual #69                 // Method org/eclipse/jdt/internal/compiler/lookup/BlockScope.problemReporter:()Lorg/eclipse/jdt/internal/compiler/problem/ProblemReporter;
     159: aload_0
     160: getfield      #22                 // Field val$valueType:Lorg/eclipse/jdt/internal/compiler/lookup/TypeBinding;
     163: aload_0
     164: getfield      #24                 // Field val$requiredType:Lorg/eclipse/jdt/internal/compiler/lookup/TypeBinding;
     167: aload_0
     168: getfield      #20                 // Field this$0:Lorg/eclipse/jdt/internal/compiler/ast/MemberValuePair;
     171: getfield      #40                 // Field org/eclipse/jdt/internal/compiler/ast/MemberValuePair.value:Lorg/eclipse/jdt/internal/compiler/ast/Expression;
     174: aconst_null
     175: invokevirtual #95                 // Method org/eclipse/jdt/internal/compiler/problem/ProblemReporter.typeMismatchError:(Lorg/eclipse/jdt/internal/compiler/lookup/TypeBinding;Lorg/eclipse/jdt/internal/compiler/lookup/TypeBinding;Lorg/eclipse/jdt/internal/compiler/ast/ASTNode;Lorg/eclipse/jdt/internal/compiler/ast/ASTNode;)V
     178: aload_0
     179: getfield      #30                 // Field val$shouldExit:[Z
     182: iconst_0
     183: iconst_1
     184: bastore
     185: goto          234
     188: aload_0
     189: getfield      #28                 // Field val$scope:Lorg/eclipse/jdt/internal/compiler/lookup/BlockScope;
     192: invokevirtual #99                 // Method org/eclipse/jdt/internal/compiler/lookup/BlockScope.compilationUnitScope:()Lorg/eclipse/jdt/internal/compiler/lookup/CompilationUnitScope;
     195: aload_0
     196: getfield      #24                 // Field val$requiredType:Lorg/eclipse/jdt/internal/compiler/lookup/TypeBinding;
     199: invokevirtual #103                // Method org/eclipse/jdt/internal/compiler/lookup/TypeBinding.leafComponentType:()Lorg/eclipse/jdt/internal/compiler/lookup/TypeBinding;
     202: aload_0
     203: getfield      #22                 // Field val$valueType:Lorg/eclipse/jdt/internal/compiler/lookup/TypeBinding;
     206: invokevirtual #103                // Method org/eclipse/jdt/internal/compiler/lookup/TypeBinding.leafComponentType:()Lorg/eclipse/jdt/internal/compiler/lookup/TypeBinding;
     209: invokevirtual #107                // Method org/eclipse/jdt/internal/compiler/lookup/CompilationUnitScope.recordTypeConversion:(Lorg/eclipse/jdt/internal/compiler/lookup/TypeBinding;Lorg/eclipse/jdt/internal/compiler/lookup/TypeBinding;)V
     212: aload_0
     213: getfield      #20                 // Field this$0:Lorg/eclipse/jdt/internal/compiler/ast/MemberValuePair;
     216: getfield      #40                 // Field org/eclipse/jdt/internal/compiler/ast/MemberValuePair.value:Lorg/eclipse/jdt/internal/compiler/ast/Expression;
     219: aload_0
     220: getfield      #28                 // Field val$scope:Lorg/eclipse/jdt/internal/compiler/lookup/BlockScope;
     223: aload_0
     224: getfield      #24                 // Field val$requiredType:Lorg/eclipse/jdt/internal/compiler/lookup/TypeBinding;
     227: aload_0
     228: getfield      #22                 // Field val$valueType:Lorg/eclipse/jdt/internal/compiler/lookup/TypeBinding;
     231: invokevirtual #113                // Method org/eclipse/jdt/internal/compiler/ast/Expression.computeConversion:(Lorg/eclipse/jdt/internal/compiler/lookup/Scope;Lorg/eclipse/jdt/internal/compiler/lookup/TypeBinding;Lorg/eclipse/jdt/internal/compiler/lookup/TypeBinding;)V
     234: return
}
