Compiled from "AbstractActorCell.java"
final class akka.actor.dungeon.AbstractActorCell {
  static final long mailboxOffset;

  static final long childrenOffset;

  static final long nextNameOffset;

  static final long functionRefsOffset;

  akka.actor.dungeon.AbstractActorCell();
    Code:
       0: aload_0
       1: invokespecial #1                  // Method java/lang/Object."<init>":()V
       4: return

  static {};
    Code:
       0: getstatic     #2                  // Field akka/util/Unsafe.instance:Lsun/misc/Unsafe;
       3: ldc           #3                  // class akka/actor/ActorCell
       5: ldc           #4                  // String akka$actor$dungeon$Dispatch$$_mailboxDoNotCallMeDirectly
       7: invokevirtual #5                  // Method java/lang/Class.getDeclaredField:(Ljava/lang/String;)Ljava/lang/reflect/Field;
      10: invokevirtual #6                  // Method sun/misc/Unsafe.objectFieldOffset:(Ljava/lang/reflect/Field;)J
      13: putstatic     #7                  // Field mailboxOffset:J
      16: getstatic     #2                  // Field akka/util/Unsafe.instance:Lsun/misc/Unsafe;
      19: ldc           #3                  // class akka/actor/ActorCell
      21: ldc           #8                  // String akka$actor$dungeon$Children$$_childrenRefsDoNotCallMeDirectly
      23: invokevirtual #5                  // Method java/lang/Class.getDeclaredField:(Ljava/lang/String;)Ljava/lang/reflect/Field;
      26: invokevirtual #6                  // Method sun/misc/Unsafe.objectFieldOffset:(Ljava/lang/reflect/Field;)J
      29: putstatic     #9                  // Field childrenOffset:J
      32: getstatic     #2                  // Field akka/util/Unsafe.instance:Lsun/misc/Unsafe;
      35: ldc           #3                  // class akka/actor/ActorCell
      37: ldc           #10                 // String akka$actor$dungeon$Children$$_nextNameDoNotCallMeDirectly
      39: invokevirtual #5                  // Method java/lang/Class.getDeclaredField:(Ljava/lang/String;)Ljava/lang/reflect/Field;
      42: invokevirtual #6                  // Method sun/misc/Unsafe.objectFieldOffset:(Ljava/lang/reflect/Field;)J
      45: putstatic     #11                 // Field nextNameOffset:J
      48: getstatic     #2                  // Field akka/util/Unsafe.instance:Lsun/misc/Unsafe;
      51: ldc           #3                  // class akka/actor/ActorCell
      53: ldc           #12                 // String akka$actor$dungeon$Children$$_functionRefsDoNotCallMeDirectly
      55: invokevirtual #5                  // Method java/lang/Class.getDeclaredField:(Ljava/lang/String;)Ljava/lang/reflect/Field;
      58: invokevirtual #6                  // Method sun/misc/Unsafe.objectFieldOffset:(Ljava/lang/reflect/Field;)J
      61: putstatic     #13                 // Field functionRefsOffset:J
      64: goto          77
      67: astore_0
      68: new           #15                 // class java/lang/ExceptionInInitializerError
      71: dup
      72: aload_0
      73: invokespecial #16                 // Method java/lang/ExceptionInInitializerError."<init>":(Ljava/lang/Throwable;)V
      76: athrow
      77: return
    Exception table:
       from    to  target type
           0    64    67   Class java/lang/Throwable
}
