Compiled from "Children.scala"
public final class akka.actor.dungeon.Children$ {
  public static final akka.actor.dungeon.Children$ MODULE$;

  private final scala.Function0<akka.actor.Nobody$> GetNobody;

  public static {};
    Code:
       0: new           #2                  // class akka/actor/dungeon/Children$
       3: invokespecial #12                 // Method "<init>":()V
       6: return

  public scala.Function0<akka.actor.Nobody$> GetNobody();
    Code:
       0: aload_0
       1: getfield      #18                 // Field GetNobody:Lscala/Function0;
       4: areturn

  private akka.actor.dungeon.Children$();
    Code:
       0: aload_0
       1: invokespecial #20                 // Method java/lang/Object."<init>":()V
       4: aload_0
       5: putstatic     #22                 // Field MODULE$:Lakka/actor/dungeon/Children$;
       8: aload_0
       9: new           #24                 // class akka/actor/dungeon/Children$$anonfun$1
      12: dup
      13: invokespecial #25                 // Method akka/actor/dungeon/Children$$anonfun$1."<init>":()V
      16: putfield      #18                 // Field GetNobody:Lscala/Function0;
      19: return
}
