Compiled from "SVGPathfromDString.scala"
public final class edu.psu.sagnik.research.inkscapesvgprocessing.pathparser.impl.SVGPathfromDString$$anonfun$4 extends scala.runtime.AbstractFunction1<java.lang.Object, edu.psu.sagnik.research.inkscapesvgprocessing.pathparser.model.MovePath> implements scala.Serializable {
  public static final long serialVersionUID;

  public final edu.psu.sagnik.research.inkscapesvgprocessing.pathparser.model.MovePath apply(java.lang.Object);
    Code:
       0: aload_1
       1: checkcast     #21                 // class edu/psu/sagnik/research/inkscapesvgprocessing/pathparser/model/MovePath
       4: areturn

  public final java.lang.Object apply(java.lang.Object);
    Code:
       0: aload_0
       1: aload_1
       2: invokevirtual #28                 // Method apply:(Ljava/lang/Object;)Ledu/psu/sagnik/research/inkscapesvgprocessing/pathparser/model/MovePath;
       5: areturn

  public edu.psu.sagnik.research.inkscapesvgprocessing.pathparser.impl.SVGPathfromDString$$anonfun$4();
    Code:
       0: aload_0
       1: invokespecial #33                 // Method scala/runtime/AbstractFunction1."<init>":()V
       4: return
}
