Compiled from "AccessToken.kt"
final class org.http4k.security.BasicAccessToken implements org.http4k.security.AccessToken {
  private final java.lang.String value;

  private final java.lang.String type;

  private final java.lang.Long expiresIn;

  private final java.lang.String scope;

  private final org.http4k.security.oauth.core.RefreshToken refreshToken;

  public org.http4k.security.BasicAccessToken(java.lang.String, java.lang.String, java.lang.Long, java.lang.String, org.http4k.security.oauth.core.RefreshToken);
    Code:
       0: aload_1
       1: ldc           #12                 // String value
       3: invokestatic  #18                 // Method kotlin/jvm/internal/Intrinsics.checkNotNullParameter:(Ljava/lang/Object;Ljava/lang/String;)V
       6: aload_0
       7: invokespecial #21                 // Method java/lang/Object."<init>":()V
      10: aload_0
      11: aload_1
      12: putfield      #24                 // Field value:Ljava/lang/String;
      15: aload_0
      16: aload_2
      17: putfield      #27                 // Field type:Ljava/lang/String;
      20: aload_0
      21: aload_3
      22: putfield      #31                 // Field expiresIn:Ljava/lang/Long;
      25: aload_0
      26: aload         4
      28: putfield      #34                 // Field scope:Ljava/lang/String;
      31: aload_0
      32: aload         5
      34: putfield      #38                 // Field refreshToken:Lorg/http4k/security/oauth/core/RefreshToken;
      37: return

  public java.lang.String getValue();
    Code:
       0: aload_0
       1: getfield      #24                 // Field value:Ljava/lang/String;
       4: areturn

  public java.lang.String getType();
    Code:
       0: aload_0
       1: getfield      #27                 // Field type:Ljava/lang/String;
       4: areturn

  public java.lang.Long getExpiresIn();
    Code:
       0: aload_0
       1: getfield      #31                 // Field expiresIn:Ljava/lang/Long;
       4: areturn

  public java.lang.String getScope();
    Code:
       0: aload_0
       1: getfield      #34                 // Field scope:Ljava/lang/String;
       4: areturn

  public org.http4k.security.oauth.core.RefreshToken getRefreshToken();
    Code:
       0: aload_0
       1: getfield      #38                 // Field refreshToken:Lorg/http4k/security/oauth/core/RefreshToken;
       4: areturn

  public final java.lang.String component1();
    Code:
       0: aload_0
       1: invokevirtual #51                 // Method getValue:()Ljava/lang/String;
       4: areturn

  public final java.lang.String component2();
    Code:
       0: aload_0
       1: invokevirtual #54                 // Method getType:()Ljava/lang/String;
       4: areturn

  public final java.lang.Long component3();
    Code:
       0: aload_0
       1: invokevirtual #57                 // Method getExpiresIn:()Ljava/lang/Long;
       4: areturn

  public final java.lang.String component4();
    Code:
       0: aload_0
       1: invokevirtual #60                 // Method getScope:()Ljava/lang/String;
       4: areturn

  public final org.http4k.security.oauth.core.RefreshToken component5();
    Code:
       0: aload_0
       1: invokevirtual #63                 // Method getRefreshToken:()Lorg/http4k/security/oauth/core/RefreshToken;
       4: areturn

  public final org.http4k.security.BasicAccessToken copy(java.lang.String, java.lang.String, java.lang.Long, java.lang.String, org.http4k.security.oauth.core.RefreshToken);
    Code:
       0: aload_1
       1: ldc           #12                 // String value
       3: invokestatic  #18                 // Method kotlin/jvm/internal/Intrinsics.checkNotNullParameter:(Ljava/lang/Object;Ljava/lang/String;)V
       6: new           #2                  // class org/http4k/security/BasicAccessToken
       9: dup
      10: aload_1
      11: aload_2
      12: aload_3
      13: aload         4
      15: aload         5
      17: invokespecial #67                 // Method "<init>":(Ljava/lang/String;Ljava/lang/String;Ljava/lang/Long;Ljava/lang/String;Lorg/http4k/security/oauth/core/RefreshToken;)V
      20: areturn

  public static org.http4k.security.BasicAccessToken copy$default(org.http4k.security.BasicAccessToken, java.lang.String, java.lang.String, java.lang.Long, java.lang.String, org.http4k.security.oauth.core.RefreshToken, int, java.lang.Object);
    Code:
       0: iload         6
       2: iconst_1
       3: iand
       4: ifeq          12
       7: aload_0
       8: invokevirtual #51                 // Method getValue:()Ljava/lang/String;
      11: astore_1
      12: iload         6
      14: iconst_2
      15: iand
      16: ifeq          24
      19: aload_0
      20: invokevirtual #54                 // Method getType:()Ljava/lang/String;
      23: astore_2
      24: iload         6
      26: iconst_4
      27: iand
      28: ifeq          36
      31: aload_0
      32: invokevirtual #57                 // Method getExpiresIn:()Ljava/lang/Long;
      35: astore_3
      36: iload         6
      38: bipush        8
      40: iand
      41: ifeq          50
      44: aload_0
      45: invokevirtual #60                 // Method getScope:()Ljava/lang/String;
      48: astore        4
      50: iload         6
      52: bipush        16
      54: iand
      55: ifeq          64
      58: aload_0
      59: invokevirtual #63                 // Method getRefreshToken:()Lorg/http4k/security/oauth/core/RefreshToken;
      62: astore        5
      64: aload_0
      65: aload_1
      66: aload_2
      67: aload_3
      68: aload         4
      70: aload         5
      72: invokevirtual #71                 // Method copy:(Ljava/lang/String;Ljava/lang/String;Ljava/lang/Long;Ljava/lang/String;Lorg/http4k/security/oauth/core/RefreshToken;)Lorg/http4k/security/BasicAccessToken;
      75: areturn

  public java.lang.String toString();
    Code:
       0: new           #74                 // class java/lang/StringBuilder
       3: dup
       4: invokespecial #75                 // Method java/lang/StringBuilder."<init>":()V
       7: ldc           #77                 // String BasicAccessToken(value=
       9: invokevirtual #81                 // Method java/lang/StringBuilder.append:(Ljava/lang/String;)Ljava/lang/StringBuilder;
      12: aload_0
      13: invokevirtual #51                 // Method getValue:()Ljava/lang/String;
      16: invokevirtual #81                 // Method java/lang/StringBuilder.append:(Ljava/lang/String;)Ljava/lang/StringBuilder;
      19: ldc           #83                 // String , type=
      21: invokevirtual #81                 // Method java/lang/StringBuilder.append:(Ljava/lang/String;)Ljava/lang/StringBuilder;
      24: aload_0
      25: invokevirtual #54                 // Method getType:()Ljava/lang/String;
      28: invokevirtual #81                 // Method java/lang/StringBuilder.append:(Ljava/lang/String;)Ljava/lang/StringBuilder;
      31: ldc           #85                 // String , expiresIn=
      33: invokevirtual #81                 // Method java/lang/StringBuilder.append:(Ljava/lang/String;)Ljava/lang/StringBuilder;
      36: aload_0
      37: invokevirtual #57                 // Method getExpiresIn:()Ljava/lang/Long;
      40: invokevirtual #88                 // Method java/lang/StringBuilder.append:(Ljava/lang/Object;)Ljava/lang/StringBuilder;
      43: ldc           #90                 // String , scope=
      45: invokevirtual #81                 // Method java/lang/StringBuilder.append:(Ljava/lang/String;)Ljava/lang/StringBuilder;
      48: aload_0
      49: invokevirtual #60                 // Method getScope:()Ljava/lang/String;
      52: invokevirtual #81                 // Method java/lang/StringBuilder.append:(Ljava/lang/String;)Ljava/lang/StringBuilder;
      55: ldc           #92                 // String , refreshToken=
      57: invokevirtual #81                 // Method java/lang/StringBuilder.append:(Ljava/lang/String;)Ljava/lang/StringBuilder;
      60: aload_0
      61: invokevirtual #63                 // Method getRefreshToken:()Lorg/http4k/security/oauth/core/RefreshToken;
      64: invokevirtual #88                 // Method java/lang/StringBuilder.append:(Ljava/lang/Object;)Ljava/lang/StringBuilder;
      67: bipush        41
      69: invokevirtual #95                 // Method java/lang/StringBuilder.append:(C)Ljava/lang/StringBuilder;
      72: invokevirtual #97                 // Method java/lang/StringBuilder.toString:()Ljava/lang/String;
      75: areturn

  public int hashCode();
    Code:
       0: aload_0
       1: invokevirtual #51                 // Method getValue:()Ljava/lang/String;
       4: invokevirtual #103                // Method java/lang/String.hashCode:()I
       7: istore_1
       8: iload_1
       9: bipush        31
      11: imul
      12: aload_0
      13: invokevirtual #54                 // Method getType:()Ljava/lang/String;
      16: ifnonnull     23
      19: iconst_0
      20: goto          30
      23: aload_0
      24: invokevirtual #54                 // Method getType:()Ljava/lang/String;
      27: invokevirtual #103                // Method java/lang/String.hashCode:()I
      30: iadd
      31: istore_1
      32: iload_1
      33: bipush        31
      35: imul
      36: aload_0
      37: invokevirtual #57                 // Method getExpiresIn:()Ljava/lang/Long;
      40: ifnonnull     47
      43: iconst_0
      44: goto          54
      47: aload_0
      48: invokevirtual #57                 // Method getExpiresIn:()Ljava/lang/Long;
      51: invokevirtual #104                // Method java/lang/Object.hashCode:()I
      54: iadd
      55: istore_1
      56: iload_1
      57: bipush        31
      59: imul
      60: aload_0
      61: invokevirtual #60                 // Method getScope:()Ljava/lang/String;
      64: ifnonnull     71
      67: iconst_0
      68: goto          78
      71: aload_0
      72: invokevirtual #60                 // Method getScope:()Ljava/lang/String;
      75: invokevirtual #103                // Method java/lang/String.hashCode:()I
      78: iadd
      79: istore_1
      80: iload_1
      81: bipush        31
      83: imul
      84: aload_0
      85: invokevirtual #63                 // Method getRefreshToken:()Lorg/http4k/security/oauth/core/RefreshToken;
      88: ifnonnull     95
      91: iconst_0
      92: goto          102
      95: aload_0
      96: invokevirtual #63                 // Method getRefreshToken:()Lorg/http4k/security/oauth/core/RefreshToken;
      99: invokevirtual #107                // Method org/http4k/security/oauth/core/RefreshToken.hashCode:()I
     102: iadd
     103: istore_1
     104: iload_1
     105: ireturn

  public boolean equals(java.lang.Object);
    Code:
       0: aload_0
       1: aload_1
       2: if_acmpne     7
       5: iconst_1
       6: ireturn
       7: aload_1
       8: instanceof    #2                  // class org/http4k/security/BasicAccessToken
      11: ifne          16
      14: iconst_0
      15: ireturn
      16: aload_1
      17: checkcast     #2                  // class org/http4k/security/BasicAccessToken
      20: astore_2
      21: aload_0
      22: invokevirtual #51                 // Method getValue:()Ljava/lang/String;
      25: aload_2
      26: invokevirtual #51                 // Method getValue:()Ljava/lang/String;
      29: invokestatic  #115                // Method kotlin/jvm/internal/Intrinsics.areEqual:(Ljava/lang/Object;Ljava/lang/Object;)Z
      32: ifne          37
      35: iconst_0
      36: ireturn
      37: aload_0
      38: invokevirtual #54                 // Method getType:()Ljava/lang/String;
      41: aload_2
      42: invokevirtual #54                 // Method getType:()Ljava/lang/String;
      45: invokestatic  #115                // Method kotlin/jvm/internal/Intrinsics.areEqual:(Ljava/lang/Object;Ljava/lang/Object;)Z
      48: ifne          53
      51: iconst_0
      52: ireturn
      53: aload_0
      54: invokevirtual #57                 // Method getExpiresIn:()Ljava/lang/Long;
      57: aload_2
      58: invokevirtual #57                 // Method getExpiresIn:()Ljava/lang/Long;
      61: invokestatic  #115                // Method kotlin/jvm/internal/Intrinsics.areEqual:(Ljava/lang/Object;Ljava/lang/Object;)Z
      64: ifne          69
      67: iconst_0
      68: ireturn
      69: aload_0
      70: invokevirtual #60                 // Method getScope:()Ljava/lang/String;
      73: aload_2
      74: invokevirtual #60                 // Method getScope:()Ljava/lang/String;
      77: invokestatic  #115                // Method kotlin/jvm/internal/Intrinsics.areEqual:(Ljava/lang/Object;Ljava/lang/Object;)Z
      80: ifne          85
      83: iconst_0
      84: ireturn
      85: aload_0
      86: invokevirtual #63                 // Method getRefreshToken:()Lorg/http4k/security/oauth/core/RefreshToken;
      89: aload_2
      90: invokevirtual #63                 // Method getRefreshToken:()Lorg/http4k/security/oauth/core/RefreshToken;
      93: invokestatic  #115                // Method kotlin/jvm/internal/Intrinsics.areEqual:(Ljava/lang/Object;Ljava/lang/Object;)Z
      96: ifne          101
      99: iconst_0
     100: ireturn
     101: iconst_1
     102: ireturn
}
