Compiled from "OAuthProviderConfig.kt"
public final class org.http4k.security.OAuthProviderConfig {
  private final org.http4k.core.Uri authBase;

  private final java.lang.String authPath;

  private final java.lang.String tokenPath;

  private final org.http4k.core.Credentials credentials;

  private final org.http4k.core.Uri apiBase;

  private final org.http4k.core.Uri authUri;

  private final org.http4k.core.Uri tokenUri;

  public org.http4k.security.OAuthProviderConfig(org.http4k.core.Uri, java.lang.String, java.lang.String, org.http4k.core.Credentials, org.http4k.core.Uri, org.http4k.core.Uri, org.http4k.core.Uri);
    Code:
       0: aload_1
       1: ldc           #9                  // String authBase
       3: invokestatic  #15                 // Method kotlin/jvm/internal/Intrinsics.checkNotNullParameter:(Ljava/lang/Object;Ljava/lang/String;)V
       6: aload_2
       7: ldc           #17                 // String authPath
       9: invokestatic  #15                 // Method kotlin/jvm/internal/Intrinsics.checkNotNullParameter:(Ljava/lang/Object;Ljava/lang/String;)V
      12: aload_3
      13: ldc           #19                 // String tokenPath
      15: invokestatic  #15                 // Method kotlin/jvm/internal/Intrinsics.checkNotNullParameter:(Ljava/lang/Object;Ljava/lang/String;)V
      18: aload         4
      20: ldc           #21                 // String credentials
      22: invokestatic  #15                 // Method kotlin/jvm/internal/Intrinsics.checkNotNullParameter:(Ljava/lang/Object;Ljava/lang/String;)V
      25: aload         5
      27: ldc           #23                 // String apiBase
      29: invokestatic  #15                 // Method kotlin/jvm/internal/Intrinsics.checkNotNullParameter:(Ljava/lang/Object;Ljava/lang/String;)V
      32: aload         6
      34: ldc           #25                 // String authUri
      36: invokestatic  #15                 // Method kotlin/jvm/internal/Intrinsics.checkNotNullParameter:(Ljava/lang/Object;Ljava/lang/String;)V
      39: aload         7
      41: ldc           #27                 // String tokenUri
      43: invokestatic  #15                 // Method kotlin/jvm/internal/Intrinsics.checkNotNullParameter:(Ljava/lang/Object;Ljava/lang/String;)V
      46: aload_0
      47: invokespecial #30                 // Method java/lang/Object."<init>":()V
      50: aload_0
      51: aload_1
      52: putfield      #33                 // Field authBase:Lorg/http4k/core/Uri;
      55: aload_0
      56: aload_2
      57: putfield      #36                 // Field authPath:Ljava/lang/String;
      60: aload_0
      61: aload_3
      62: putfield      #38                 // Field tokenPath:Ljava/lang/String;
      65: aload_0
      66: aload         4
      68: putfield      #41                 // Field credentials:Lorg/http4k/core/Credentials;
      71: aload_0
      72: aload         5
      74: putfield      #43                 // Field apiBase:Lorg/http4k/core/Uri;
      77: aload_0
      78: aload         6
      80: putfield      #45                 // Field authUri:Lorg/http4k/core/Uri;
      83: aload_0
      84: aload         7
      86: putfield      #47                 // Field tokenUri:Lorg/http4k/core/Uri;
      89: return

  public org.http4k.security.OAuthProviderConfig(org.http4k.core.Uri, java.lang.String, java.lang.String, org.http4k.core.Credentials, org.http4k.core.Uri, org.http4k.core.Uri, org.http4k.core.Uri, int, kotlin.jvm.internal.DefaultConstructorMarker);
    Code:
       0: iload         8
       2: bipush        16
       4: iand
       5: ifeq          11
       8: aload_1
       9: astore        5
      11: iload         8
      13: bipush        32
      15: iand
      16: ifeq          32
      19: aload_1
      20: getstatic     #56                 // Field org/http4k/core/Uri.Companion:Lorg/http4k/core/Uri$Companion;
      23: aload_2
      24: invokevirtual #62                 // Method org/http4k/core/Uri$Companion.of:(Ljava/lang/String;)Lorg/http4k/core/Uri;
      27: invokestatic  #68                 // Method org/http4k/core/UriKt.extend:(Lorg/http4k/core/Uri;Lorg/http4k/core/Uri;)Lorg/http4k/core/Uri;
      30: astore        6
      32: iload         8
      34: bipush        64
      36: iand
      37: ifeq          53
      40: aload_1
      41: getstatic     #56                 // Field org/http4k/core/Uri.Companion:Lorg/http4k/core/Uri$Companion;
      44: aload_3
      45: invokevirtual #62                 // Method org/http4k/core/Uri$Companion.of:(Ljava/lang/String;)Lorg/http4k/core/Uri;
      48: invokestatic  #68                 // Method org/http4k/core/UriKt.extend:(Lorg/http4k/core/Uri;Lorg/http4k/core/Uri;)Lorg/http4k/core/Uri;
      51: astore        7
      53: aload_0
      54: aload_1
      55: aload_2
      56: aload_3
      57: aload         4
      59: aload         5
      61: aload         6
      63: aload         7
      65: invokespecial #70                 // Method "<init>":(Lorg/http4k/core/Uri;Ljava/lang/String;Ljava/lang/String;Lorg/http4k/core/Credentials;Lorg/http4k/core/Uri;Lorg/http4k/core/Uri;Lorg/http4k/core/Uri;)V
      68: return

  public final java.lang.String getAuthPath();
    Code:
       0: aload_0
       1: getfield      #36                 // Field authPath:Ljava/lang/String;
       4: areturn

  public final java.lang.String getTokenPath();
    Code:
       0: aload_0
       1: getfield      #38                 // Field tokenPath:Ljava/lang/String;
       4: areturn

  public final org.http4k.core.Credentials getCredentials();
    Code:
       0: aload_0
       1: getfield      #41                 // Field credentials:Lorg/http4k/core/Credentials;
       4: areturn

  public final org.http4k.core.Uri getApiBase();
    Code:
       0: aload_0
       1: getfield      #43                 // Field apiBase:Lorg/http4k/core/Uri;
       4: areturn

  public final org.http4k.core.Uri getAuthUri();
    Code:
       0: aload_0
       1: getfield      #45                 // Field authUri:Lorg/http4k/core/Uri;
       4: areturn

  public final org.http4k.core.Uri getTokenUri();
    Code:
       0: aload_0
       1: getfield      #47                 // Field tokenUri:Lorg/http4k/core/Uri;
       4: areturn

  private final org.http4k.core.Uri component1();
    Code:
       0: aload_0
       1: getfield      #33                 // Field authBase:Lorg/http4k/core/Uri;
       4: areturn

  public final java.lang.String component2();
    Code:
       0: aload_0
       1: getfield      #36                 // Field authPath:Ljava/lang/String;
       4: areturn

  public final java.lang.String component3();
    Code:
       0: aload_0
       1: getfield      #38                 // Field tokenPath:Ljava/lang/String;
       4: areturn

  public final org.http4k.core.Credentials component4();
    Code:
       0: aload_0
       1: getfield      #41                 // Field credentials:Lorg/http4k/core/Credentials;
       4: areturn

  public final org.http4k.core.Uri component5();
    Code:
       0: aload_0
       1: getfield      #43                 // Field apiBase:Lorg/http4k/core/Uri;
       4: areturn

  public final org.http4k.core.Uri component6();
    Code:
       0: aload_0
       1: getfield      #45                 // Field authUri:Lorg/http4k/core/Uri;
       4: areturn

  public final org.http4k.core.Uri component7();
    Code:
       0: aload_0
       1: getfield      #47                 // Field tokenUri:Lorg/http4k/core/Uri;
       4: areturn

  public final org.http4k.security.OAuthProviderConfig copy(org.http4k.core.Uri, java.lang.String, java.lang.String, org.http4k.core.Credentials, org.http4k.core.Uri, org.http4k.core.Uri, org.http4k.core.Uri);
    Code:
       0: aload_1
       1: ldc           #9                  // String authBase
       3: invokestatic  #15                 // Method kotlin/jvm/internal/Intrinsics.checkNotNullParameter:(Ljava/lang/Object;Ljava/lang/String;)V
       6: aload_2
       7: ldc           #17                 // String authPath
       9: invokestatic  #15                 // Method kotlin/jvm/internal/Intrinsics.checkNotNullParameter:(Ljava/lang/Object;Ljava/lang/String;)V
      12: aload_3
      13: ldc           #19                 // String tokenPath
      15: invokestatic  #15                 // Method kotlin/jvm/internal/Intrinsics.checkNotNullParameter:(Ljava/lang/Object;Ljava/lang/String;)V
      18: aload         4
      20: ldc           #21                 // String credentials
      22: invokestatic  #15                 // Method kotlin/jvm/internal/Intrinsics.checkNotNullParameter:(Ljava/lang/Object;Ljava/lang/String;)V
      25: aload         5
      27: ldc           #23                 // String apiBase
      29: invokestatic  #15                 // Method kotlin/jvm/internal/Intrinsics.checkNotNullParameter:(Ljava/lang/Object;Ljava/lang/String;)V
      32: aload         6
      34: ldc           #25                 // String authUri
      36: invokestatic  #15                 // Method kotlin/jvm/internal/Intrinsics.checkNotNullParameter:(Ljava/lang/Object;Ljava/lang/String;)V
      39: aload         7
      41: ldc           #27                 // String tokenUri
      43: invokestatic  #15                 // Method kotlin/jvm/internal/Intrinsics.checkNotNullParameter:(Ljava/lang/Object;Ljava/lang/String;)V
      46: new           #2                  // class org/http4k/security/OAuthProviderConfig
      49: dup
      50: aload_1
      51: aload_2
      52: aload_3
      53: aload         4
      55: aload         5
      57: aload         6
      59: aload         7
      61: invokespecial #70                 // Method "<init>":(Lorg/http4k/core/Uri;Ljava/lang/String;Ljava/lang/String;Lorg/http4k/core/Credentials;Lorg/http4k/core/Uri;Lorg/http4k/core/Uri;Lorg/http4k/core/Uri;)V
      64: areturn

  public static org.http4k.security.OAuthProviderConfig copy$default(org.http4k.security.OAuthProviderConfig, org.http4k.core.Uri, java.lang.String, java.lang.String, org.http4k.core.Credentials, org.http4k.core.Uri, org.http4k.core.Uri, org.http4k.core.Uri, int, java.lang.Object);
    Code:
       0: iload         8
       2: iconst_1
       3: iand
       4: ifeq          12
       7: aload_0
       8: getfield      #33                 // Field authBase:Lorg/http4k/core/Uri;
      11: astore_1
      12: iload         8
      14: iconst_2
      15: iand
      16: ifeq          24
      19: aload_0
      20: getfield      #36                 // Field authPath:Ljava/lang/String;
      23: astore_2
      24: iload         8
      26: iconst_4
      27: iand
      28: ifeq          36
      31: aload_0
      32: getfield      #38                 // Field tokenPath:Ljava/lang/String;
      35: astore_3
      36: iload         8
      38: bipush        8
      40: iand
      41: ifeq          50
      44: aload_0
      45: getfield      #41                 // Field credentials:Lorg/http4k/core/Credentials;
      48: astore        4
      50: iload         8
      52: bipush        16
      54: iand
      55: ifeq          64
      58: aload_0
      59: getfield      #43                 // Field apiBase:Lorg/http4k/core/Uri;
      62: astore        5
      64: iload         8
      66: bipush        32
      68: iand
      69: ifeq          78
      72: aload_0
      73: getfield      #45                 // Field authUri:Lorg/http4k/core/Uri;
      76: astore        6
      78: iload         8
      80: bipush        64
      82: iand
      83: ifeq          92
      86: aload_0
      87: getfield      #47                 // Field tokenUri:Lorg/http4k/core/Uri;
      90: astore        7
      92: aload_0
      93: aload_1
      94: aload_2
      95: aload_3
      96: aload         4
      98: aload         5
     100: aload         6
     102: aload         7
     104: invokevirtual #92                 // Method copy:(Lorg/http4k/core/Uri;Ljava/lang/String;Ljava/lang/String;Lorg/http4k/core/Credentials;Lorg/http4k/core/Uri;Lorg/http4k/core/Uri;Lorg/http4k/core/Uri;)Lorg/http4k/security/OAuthProviderConfig;
     107: areturn

  public java.lang.String toString();
    Code:
       0: new           #95                 // class java/lang/StringBuilder
       3: dup
       4: invokespecial #96                 // Method java/lang/StringBuilder."<init>":()V
       7: ldc           #98                 // String OAuthProviderConfig(authBase=
       9: invokevirtual #102                // Method java/lang/StringBuilder.append:(Ljava/lang/String;)Ljava/lang/StringBuilder;
      12: aload_0
      13: getfield      #33                 // Field authBase:Lorg/http4k/core/Uri;
      16: invokevirtual #105                // Method java/lang/StringBuilder.append:(Ljava/lang/Object;)Ljava/lang/StringBuilder;
      19: ldc           #107                // String , authPath=
      21: invokevirtual #102                // Method java/lang/StringBuilder.append:(Ljava/lang/String;)Ljava/lang/StringBuilder;
      24: aload_0
      25: getfield      #36                 // Field authPath:Ljava/lang/String;
      28: invokevirtual #102                // Method java/lang/StringBuilder.append:(Ljava/lang/String;)Ljava/lang/StringBuilder;
      31: ldc           #109                // String , tokenPath=
      33: invokevirtual #102                // Method java/lang/StringBuilder.append:(Ljava/lang/String;)Ljava/lang/StringBuilder;
      36: aload_0
      37: getfield      #38                 // Field tokenPath:Ljava/lang/String;
      40: invokevirtual #102                // Method java/lang/StringBuilder.append:(Ljava/lang/String;)Ljava/lang/StringBuilder;
      43: ldc           #111                // String , credentials=
      45: invokevirtual #102                // Method java/lang/StringBuilder.append:(Ljava/lang/String;)Ljava/lang/StringBuilder;
      48: aload_0
      49: getfield      #41                 // Field credentials:Lorg/http4k/core/Credentials;
      52: invokevirtual #105                // Method java/lang/StringBuilder.append:(Ljava/lang/Object;)Ljava/lang/StringBuilder;
      55: ldc           #113                // String , apiBase=
      57: invokevirtual #102                // Method java/lang/StringBuilder.append:(Ljava/lang/String;)Ljava/lang/StringBuilder;
      60: aload_0
      61: getfield      #43                 // Field apiBase:Lorg/http4k/core/Uri;
      64: invokevirtual #105                // Method java/lang/StringBuilder.append:(Ljava/lang/Object;)Ljava/lang/StringBuilder;
      67: ldc           #115                // String , authUri=
      69: invokevirtual #102                // Method java/lang/StringBuilder.append:(Ljava/lang/String;)Ljava/lang/StringBuilder;
      72: aload_0
      73: getfield      #45                 // Field authUri:Lorg/http4k/core/Uri;
      76: invokevirtual #105                // Method java/lang/StringBuilder.append:(Ljava/lang/Object;)Ljava/lang/StringBuilder;
      79: ldc           #117                // String , tokenUri=
      81: invokevirtual #102                // Method java/lang/StringBuilder.append:(Ljava/lang/String;)Ljava/lang/StringBuilder;
      84: aload_0
      85: getfield      #47                 // Field tokenUri:Lorg/http4k/core/Uri;
      88: invokevirtual #105                // Method java/lang/StringBuilder.append:(Ljava/lang/Object;)Ljava/lang/StringBuilder;
      91: bipush        41
      93: invokevirtual #120                // Method java/lang/StringBuilder.append:(C)Ljava/lang/StringBuilder;
      96: invokevirtual #122                // Method java/lang/StringBuilder.toString:()Ljava/lang/String;
      99: areturn

  public int hashCode();
    Code:
       0: aload_0
       1: getfield      #33                 // Field authBase:Lorg/http4k/core/Uri;
       4: invokevirtual #126                // Method org/http4k/core/Uri.hashCode:()I
       7: istore_1
       8: iload_1
       9: bipush        31
      11: imul
      12: aload_0
      13: getfield      #36                 // Field authPath:Ljava/lang/String;
      16: invokevirtual #129                // Method java/lang/String.hashCode:()I
      19: iadd
      20: istore_1
      21: iload_1
      22: bipush        31
      24: imul
      25: aload_0
      26: getfield      #38                 // Field tokenPath:Ljava/lang/String;
      29: invokevirtual #129                // Method java/lang/String.hashCode:()I
      32: iadd
      33: istore_1
      34: iload_1
      35: bipush        31
      37: imul
      38: aload_0
      39: getfield      #41                 // Field credentials:Lorg/http4k/core/Credentials;
      42: invokevirtual #132                // Method org/http4k/core/Credentials.hashCode:()I
      45: iadd
      46: istore_1
      47: iload_1
      48: bipush        31
      50: imul
      51: aload_0
      52: getfield      #43                 // Field apiBase:Lorg/http4k/core/Uri;
      55: invokevirtual #126                // Method org/http4k/core/Uri.hashCode:()I
      58: iadd
      59: istore_1
      60: iload_1
      61: bipush        31
      63: imul
      64: aload_0
      65: getfield      #45                 // Field authUri:Lorg/http4k/core/Uri;
      68: invokevirtual #126                // Method org/http4k/core/Uri.hashCode:()I
      71: iadd
      72: istore_1
      73: iload_1
      74: bipush        31
      76: imul
      77: aload_0
      78: getfield      #47                 // Field tokenUri:Lorg/http4k/core/Uri;
      81: invokevirtual #126                // Method org/http4k/core/Uri.hashCode:()I
      84: iadd
      85: istore_1
      86: iload_1
      87: ireturn

  public boolean equals(java.lang.Object);
    Code:
       0: aload_0
       1: aload_1
       2: if_acmpne     7
       5: iconst_1
       6: ireturn
       7: aload_1
       8: instanceof    #2                  // class org/http4k/security/OAuthProviderConfig
      11: ifne          16
      14: iconst_0
      15: ireturn
      16: aload_1
      17: checkcast     #2                  // class org/http4k/security/OAuthProviderConfig
      20: astore_2
      21: aload_0
      22: getfield      #33                 // Field authBase:Lorg/http4k/core/Uri;
      25: aload_2
      26: getfield      #33                 // Field authBase:Lorg/http4k/core/Uri;
      29: invokestatic  #141                // Method kotlin/jvm/internal/Intrinsics.areEqual:(Ljava/lang/Object;Ljava/lang/Object;)Z
      32: ifne          37
      35: iconst_0
      36: ireturn
      37: aload_0
      38: getfield      #36                 // Field authPath:Ljava/lang/String;
      41: aload_2
      42: getfield      #36                 // Field authPath:Ljava/lang/String;
      45: invokestatic  #141                // Method kotlin/jvm/internal/Intrinsics.areEqual:(Ljava/lang/Object;Ljava/lang/Object;)Z
      48: ifne          53
      51: iconst_0
      52: ireturn
      53: aload_0
      54: getfield      #38                 // Field tokenPath:Ljava/lang/String;
      57: aload_2
      58: getfield      #38                 // Field tokenPath:Ljava/lang/String;
      61: invokestatic  #141                // Method kotlin/jvm/internal/Intrinsics.areEqual:(Ljava/lang/Object;Ljava/lang/Object;)Z
      64: ifne          69
      67: iconst_0
      68: ireturn
      69: aload_0
      70: getfield      #41                 // Field credentials:Lorg/http4k/core/Credentials;
      73: aload_2
      74: getfield      #41                 // Field credentials:Lorg/http4k/core/Credentials;
      77: invokestatic  #141                // Method kotlin/jvm/internal/Intrinsics.areEqual:(Ljava/lang/Object;Ljava/lang/Object;)Z
      80: ifne          85
      83: iconst_0
      84: ireturn
      85: aload_0
      86: getfield      #43                 // Field apiBase:Lorg/http4k/core/Uri;
      89: aload_2
      90: getfield      #43                 // Field apiBase:Lorg/http4k/core/Uri;
      93: invokestatic  #141                // Method kotlin/jvm/internal/Intrinsics.areEqual:(Ljava/lang/Object;Ljava/lang/Object;)Z
      96: ifne          101
      99: iconst_0
     100: ireturn
     101: aload_0
     102: getfield      #45                 // Field authUri:Lorg/http4k/core/Uri;
     105: aload_2
     106: getfield      #45                 // Field authUri:Lorg/http4k/core/Uri;
     109: invokestatic  #141                // Method kotlin/jvm/internal/Intrinsics.areEqual:(Ljava/lang/Object;Ljava/lang/Object;)Z
     112: ifne          117
     115: iconst_0
     116: ireturn
     117: aload_0
     118: getfield      #47                 // Field tokenUri:Lorg/http4k/core/Uri;
     121: aload_2
     122: getfield      #47                 // Field tokenUri:Lorg/http4k/core/Uri;
     125: invokestatic  #141                // Method kotlin/jvm/internal/Intrinsics.areEqual:(Ljava/lang/Object;Ljava/lang/Object;)Z
     128: ifne          133
     131: iconst_0
     132: ireturn
     133: iconst_1
     134: ireturn
}
