Compiled from "OAuthCallback.kt"
public final class org.http4k.security.OAuthCallbackError$AuthorizationCodeMissing extends org.http4k.security.OAuthCallbackError {
  public static final org.http4k.security.OAuthCallbackError$AuthorizationCodeMissing INSTANCE;

  private org.http4k.security.OAuthCallbackError$AuthorizationCodeMissing();
    Code:
       0: aload_0
       1: aconst_null
       2: invokespecial #9                  // Method org/http4k/security/OAuthCallbackError."<init>":(Lkotlin/jvm/internal/DefaultConstructorMarker;)V
       5: return

  static {};
    Code:
       0: new           #2                  // class org/http4k/security/OAuthCallbackError$AuthorizationCodeMissing
       3: dup
       4: invokespecial #14                 // Method "<init>":()V
       7: putstatic     #17                 // Field INSTANCE:Lorg/http4k/security/OAuthCallbackError$AuthorizationCodeMissing;
      10: return
}
