Compiled from "DataPatternBuilderImpl.java"
final class org.kohsuke.rngom.digested.DataPatternBuilderImpl implements org.kohsuke.rngom.ast.builder.DataPatternBuilder {
  private final org.kohsuke.rngom.digested.DDataPattern p;

  public org.kohsuke.rngom.digested.DataPatternBuilderImpl(java.lang.String, java.lang.String, org.kohsuke.rngom.ast.om.Location);
    Code:
       0: aload_0
       1: invokespecial #1                  // Method java/lang/Object."<init>":()V
       4: aload_0
       5: new           #2                  // class org/kohsuke/rngom/digested/DDataPattern
       8: dup
       9: invokespecial #3                  // Method org/kohsuke/rngom/digested/DDataPattern."<init>":()V
      12: putfield      #4                  // Field p:Lorg/kohsuke/rngom/digested/DDataPattern;
      15: aload_0
      16: getfield      #4                  // Field p:Lorg/kohsuke/rngom/digested/DDataPattern;
      19: aload_3
      20: checkcast     #5                  // class org/xml/sax/Locator
      23: putfield      #6                  // Field org/kohsuke/rngom/digested/DDataPattern.location:Lorg/xml/sax/Locator;
      26: aload_0
      27: getfield      #4                  // Field p:Lorg/kohsuke/rngom/digested/DDataPattern;
      30: aload_1
      31: putfield      #7                  // Field org/kohsuke/rngom/digested/DDataPattern.datatypeLibrary:Ljava/lang/String;
      34: aload_0
      35: getfield      #4                  // Field p:Lorg/kohsuke/rngom/digested/DDataPattern;
      38: aload_2
      39: putfield      #8                  // Field org/kohsuke/rngom/digested/DDataPattern.type:Ljava/lang/String;
      42: return

  public void addParam(java.lang.String, java.lang.String, org.kohsuke.rngom.parse.Context, java.lang.String, org.kohsuke.rngom.ast.om.Location, org.kohsuke.rngom.ast.builder.Annotations) throws org.kohsuke.rngom.ast.builder.BuildException;
    Code:
       0: aload_0
       1: getfield      #4                  // Field p:Lorg/kohsuke/rngom/digested/DDataPattern;
       4: getfield      #9                  // Field org/kohsuke/rngom/digested/DDataPattern.params:Ljava/util/List;
       7: new           #10                 // class org/kohsuke/rngom/digested/DDataPattern$Param
      10: dup
      11: aload_0
      12: getfield      #4                  // Field p:Lorg/kohsuke/rngom/digested/DDataPattern;
      15: dup
      16: invokevirtual #11                 // Method java/lang/Object.getClass:()Ljava/lang/Class;
      19: pop
      20: aload_1
      21: aload_2
      22: aload_3
      23: invokeinterface #12,  1           // InterfaceMethod org/kohsuke/rngom/parse/Context.copy:()Lorg/kohsuke/rngom/parse/Context;
      28: aload         4
      30: aload         5
      32: aload         6
      34: checkcast     #13                 // class org/kohsuke/rngom/digested/Annotation
      37: invokespecial #14                 // Method org/kohsuke/rngom/digested/DDataPattern$Param."<init>":(Lorg/kohsuke/rngom/digested/DDataPattern;Ljava/lang/String;Ljava/lang/String;Lorg/kohsuke/rngom/parse/Context;Ljava/lang/String;Lorg/kohsuke/rngom/ast/om/Location;Lorg/kohsuke/rngom/digested/Annotation;)V
      40: invokeinterface #15,  2           // InterfaceMethod java/util/List.add:(Ljava/lang/Object;)Z
      45: pop
      46: return

  public void annotation(org.kohsuke.rngom.ast.om.ParsedElementAnnotation);
    Code:
       0: return

  public org.kohsuke.rngom.ast.om.ParsedPattern makePattern(org.kohsuke.rngom.ast.om.Location, org.kohsuke.rngom.ast.builder.Annotations) throws org.kohsuke.rngom.ast.builder.BuildException;
    Code:
       0: aload_0
       1: aconst_null
       2: aload_1
       3: aload_2
       4: invokevirtual #16                 // Method makePattern:(Lorg/kohsuke/rngom/ast/om/ParsedPattern;Lorg/kohsuke/rngom/ast/om/Location;Lorg/kohsuke/rngom/ast/builder/Annotations;)Lorg/kohsuke/rngom/ast/om/ParsedPattern;
       7: areturn

  public org.kohsuke.rngom.ast.om.ParsedPattern makePattern(org.kohsuke.rngom.ast.om.ParsedPattern, org.kohsuke.rngom.ast.om.Location, org.kohsuke.rngom.ast.builder.Annotations) throws org.kohsuke.rngom.ast.builder.BuildException;
    Code:
       0: aload_0
       1: getfield      #4                  // Field p:Lorg/kohsuke/rngom/digested/DDataPattern;
       4: aload_1
       5: checkcast     #17                 // class org/kohsuke/rngom/digested/DPattern
       8: putfield      #18                 // Field org/kohsuke/rngom/digested/DDataPattern.except:Lorg/kohsuke/rngom/digested/DPattern;
      11: aload_3
      12: ifnull        29
      15: aload_0
      16: getfield      #4                  // Field p:Lorg/kohsuke/rngom/digested/DDataPattern;
      19: aload_3
      20: checkcast     #13                 // class org/kohsuke/rngom/digested/Annotation
      23: invokevirtual #19                 // Method org/kohsuke/rngom/digested/Annotation.getResult:()Lorg/kohsuke/rngom/digested/DAnnotation;
      26: putfield      #20                 // Field org/kohsuke/rngom/digested/DDataPattern.annotation:Lorg/kohsuke/rngom/digested/DAnnotation;
      29: aload_0
      30: getfield      #4                  // Field p:Lorg/kohsuke/rngom/digested/DDataPattern;
      33: areturn
}
