Compiled from "StdioContext.java"
abstract class org.jboss.stdio.StdioContext$DelegatingPrintStream extends java.io.PrintStream {
  protected org.jboss.stdio.StdioContext$DelegatingPrintStream();
    Code:
       0: aload_0
       1: invokestatic  #1                  // Method org/jboss/stdio/NullOutputStream.getInstance:()Lorg/jboss/stdio/NullOutputStream;
       4: invokespecial #2                  // Method java/io/PrintStream."<init>":(Ljava/io/OutputStream;)V
       7: return

  abstract java.io.PrintStream getDelegate();

  public void flush();
    Code:
       0: invokestatic  #3                  // Method org/jboss/stdio/StdioContext.access$500:()Ljava/lang/ThreadLocal;
       3: invokevirtual #4                  // Method java/lang/ThreadLocal.get:()Ljava/lang/Object;
       6: ifnull        10
       9: return
      10: invokestatic  #3                  // Method org/jboss/stdio/StdioContext.access$500:()Ljava/lang/ThreadLocal;
      13: getstatic     #5                  // Field java/lang/Boolean.TRUE:Ljava/lang/Boolean;
      16: invokevirtual #6                  // Method java/lang/ThreadLocal.set:(Ljava/lang/Object;)V
      19: aload_0
      20: invokevirtual #7                  // Method getDelegate:()Ljava/io/PrintStream;
      23: invokevirtual #8                  // Method java/io/PrintStream.flush:()V
      26: invokestatic  #3                  // Method org/jboss/stdio/StdioContext.access$500:()Ljava/lang/ThreadLocal;
      29: invokevirtual #9                  // Method java/lang/ThreadLocal.remove:()V
      32: goto          44
      35: astore_1
      36: invokestatic  #3                  // Method org/jboss/stdio/StdioContext.access$500:()Ljava/lang/ThreadLocal;
      39: invokevirtual #9                  // Method java/lang/ThreadLocal.remove:()V
      42: aload_1
      43: athrow
      44: return
    Exception table:
       from    to  target type
          10    26    35   any
          35    36    35   any

  public void close();
    Code:
       0: invokestatic  #3                  // Method org/jboss/stdio/StdioContext.access$500:()Ljava/lang/ThreadLocal;
       3: invokevirtual #4                  // Method java/lang/ThreadLocal.get:()Ljava/lang/Object;
       6: ifnull        10
       9: return
      10: invokestatic  #3                  // Method org/jboss/stdio/StdioContext.access$500:()Ljava/lang/ThreadLocal;
      13: getstatic     #5                  // Field java/lang/Boolean.TRUE:Ljava/lang/Boolean;
      16: invokevirtual #6                  // Method java/lang/ThreadLocal.set:(Ljava/lang/Object;)V
      19: aload_0
      20: invokevirtual #7                  // Method getDelegate:()Ljava/io/PrintStream;
      23: invokevirtual #10                 // Method java/io/PrintStream.close:()V
      26: invokestatic  #3                  // Method org/jboss/stdio/StdioContext.access$500:()Ljava/lang/ThreadLocal;
      29: invokevirtual #9                  // Method java/lang/ThreadLocal.remove:()V
      32: goto          44
      35: astore_1
      36: invokestatic  #3                  // Method org/jboss/stdio/StdioContext.access$500:()Ljava/lang/ThreadLocal;
      39: invokevirtual #9                  // Method java/lang/ThreadLocal.remove:()V
      42: aload_1
      43: athrow
      44: return
    Exception table:
       from    to  target type
          10    26    35   any
          35    36    35   any

  public boolean checkError();
    Code:
       0: invokestatic  #3                  // Method org/jboss/stdio/StdioContext.access$500:()Ljava/lang/ThreadLocal;
       3: invokevirtual #4                  // Method java/lang/ThreadLocal.get:()Ljava/lang/Object;
       6: ifnull        11
       9: iconst_0
      10: ireturn
      11: invokestatic  #3                  // Method org/jboss/stdio/StdioContext.access$500:()Ljava/lang/ThreadLocal;
      14: getstatic     #5                  // Field java/lang/Boolean.TRUE:Ljava/lang/Boolean;
      17: invokevirtual #6                  // Method java/lang/ThreadLocal.set:(Ljava/lang/Object;)V
      20: aload_0
      21: invokevirtual #7                  // Method getDelegate:()Ljava/io/PrintStream;
      24: invokevirtual #11                 // Method java/io/PrintStream.checkError:()Z
      27: istore_1
      28: invokestatic  #3                  // Method org/jboss/stdio/StdioContext.access$500:()Ljava/lang/ThreadLocal;
      31: invokevirtual #9                  // Method java/lang/ThreadLocal.remove:()V
      34: iload_1
      35: ireturn
      36: astore_2
      37: invokestatic  #3                  // Method org/jboss/stdio/StdioContext.access$500:()Ljava/lang/ThreadLocal;
      40: invokevirtual #9                  // Method java/lang/ThreadLocal.remove:()V
      43: aload_2
      44: athrow
    Exception table:
       from    to  target type
          11    28    36   any
          36    37    36   any

  public void write(int);
    Code:
       0: invokestatic  #3                  // Method org/jboss/stdio/StdioContext.access$500:()Ljava/lang/ThreadLocal;
       3: invokevirtual #4                  // Method java/lang/ThreadLocal.get:()Ljava/lang/Object;
       6: ifnull        10
       9: return
      10: invokestatic  #3                  // Method org/jboss/stdio/StdioContext.access$500:()Ljava/lang/ThreadLocal;
      13: getstatic     #5                  // Field java/lang/Boolean.TRUE:Ljava/lang/Boolean;
      16: invokevirtual #6                  // Method java/lang/ThreadLocal.set:(Ljava/lang/Object;)V
      19: aload_0
      20: invokevirtual #7                  // Method getDelegate:()Ljava/io/PrintStream;
      23: iload_1
      24: invokevirtual #12                 // Method java/io/PrintStream.write:(I)V
      27: invokestatic  #3                  // Method org/jboss/stdio/StdioContext.access$500:()Ljava/lang/ThreadLocal;
      30: invokevirtual #9                  // Method java/lang/ThreadLocal.remove:()V
      33: goto          45
      36: astore_2
      37: invokestatic  #3                  // Method org/jboss/stdio/StdioContext.access$500:()Ljava/lang/ThreadLocal;
      40: invokevirtual #9                  // Method java/lang/ThreadLocal.remove:()V
      43: aload_2
      44: athrow
      45: return
    Exception table:
       from    to  target type
          10    27    36   any
          36    37    36   any

  public void write(byte[], int, int);
    Code:
       0: invokestatic  #3                  // Method org/jboss/stdio/StdioContext.access$500:()Ljava/lang/ThreadLocal;
       3: invokevirtual #4                  // Method java/lang/ThreadLocal.get:()Ljava/lang/Object;
       6: ifnull        10
       9: return
      10: invokestatic  #3                  // Method org/jboss/stdio/StdioContext.access$500:()Ljava/lang/ThreadLocal;
      13: getstatic     #5                  // Field java/lang/Boolean.TRUE:Ljava/lang/Boolean;
      16: invokevirtual #6                  // Method java/lang/ThreadLocal.set:(Ljava/lang/Object;)V
      19: aload_0
      20: invokevirtual #7                  // Method getDelegate:()Ljava/io/PrintStream;
      23: aload_1
      24: iload_2
      25: iload_3
      26: invokevirtual #13                 // Method java/io/PrintStream.write:([BII)V
      29: invokestatic  #3                  // Method org/jboss/stdio/StdioContext.access$500:()Ljava/lang/ThreadLocal;
      32: invokevirtual #9                  // Method java/lang/ThreadLocal.remove:()V
      35: goto          49
      38: astore        4
      40: invokestatic  #3                  // Method org/jboss/stdio/StdioContext.access$500:()Ljava/lang/ThreadLocal;
      43: invokevirtual #9                  // Method java/lang/ThreadLocal.remove:()V
      46: aload         4
      48: athrow
      49: return
    Exception table:
       from    to  target type
          10    29    38   any
          38    40    38   any

  public void print(boolean);
    Code:
       0: invokestatic  #3                  // Method org/jboss/stdio/StdioContext.access$500:()Ljava/lang/ThreadLocal;
       3: invokevirtual #4                  // Method java/lang/ThreadLocal.get:()Ljava/lang/Object;
       6: ifnull        10
       9: return
      10: invokestatic  #3                  // Method org/jboss/stdio/StdioContext.access$500:()Ljava/lang/ThreadLocal;
      13: getstatic     #5                  // Field java/lang/Boolean.TRUE:Ljava/lang/Boolean;
      16: invokevirtual #6                  // Method java/lang/ThreadLocal.set:(Ljava/lang/Object;)V
      19: aload_0
      20: invokevirtual #7                  // Method getDelegate:()Ljava/io/PrintStream;
      23: iload_1
      24: invokevirtual #14                 // Method java/io/PrintStream.print:(Z)V
      27: invokestatic  #3                  // Method org/jboss/stdio/StdioContext.access$500:()Ljava/lang/ThreadLocal;
      30: invokevirtual #9                  // Method java/lang/ThreadLocal.remove:()V
      33: goto          45
      36: astore_2
      37: invokestatic  #3                  // Method org/jboss/stdio/StdioContext.access$500:()Ljava/lang/ThreadLocal;
      40: invokevirtual #9                  // Method java/lang/ThreadLocal.remove:()V
      43: aload_2
      44: athrow
      45: return
    Exception table:
       from    to  target type
          10    27    36   any
          36    37    36   any

  public void print(char);
    Code:
       0: invokestatic  #3                  // Method org/jboss/stdio/StdioContext.access$500:()Ljava/lang/ThreadLocal;
       3: invokevirtual #4                  // Method java/lang/ThreadLocal.get:()Ljava/lang/Object;
       6: ifnull        10
       9: return
      10: invokestatic  #3                  // Method org/jboss/stdio/StdioContext.access$500:()Ljava/lang/ThreadLocal;
      13: getstatic     #5                  // Field java/lang/Boolean.TRUE:Ljava/lang/Boolean;
      16: invokevirtual #6                  // Method java/lang/ThreadLocal.set:(Ljava/lang/Object;)V
      19: aload_0
      20: invokevirtual #7                  // Method getDelegate:()Ljava/io/PrintStream;
      23: iload_1
      24: invokevirtual #15                 // Method java/io/PrintStream.print:(C)V
      27: invokestatic  #3                  // Method org/jboss/stdio/StdioContext.access$500:()Ljava/lang/ThreadLocal;
      30: invokevirtual #9                  // Method java/lang/ThreadLocal.remove:()V
      33: goto          45
      36: astore_2
      37: invokestatic  #3                  // Method org/jboss/stdio/StdioContext.access$500:()Ljava/lang/ThreadLocal;
      40: invokevirtual #9                  // Method java/lang/ThreadLocal.remove:()V
      43: aload_2
      44: athrow
      45: return
    Exception table:
       from    to  target type
          10    27    36   any
          36    37    36   any

  public void print(int);
    Code:
       0: invokestatic  #3                  // Method org/jboss/stdio/StdioContext.access$500:()Ljava/lang/ThreadLocal;
       3: invokevirtual #4                  // Method java/lang/ThreadLocal.get:()Ljava/lang/Object;
       6: ifnull        10
       9: return
      10: invokestatic  #3                  // Method org/jboss/stdio/StdioContext.access$500:()Ljava/lang/ThreadLocal;
      13: getstatic     #5                  // Field java/lang/Boolean.TRUE:Ljava/lang/Boolean;
      16: invokevirtual #6                  // Method java/lang/ThreadLocal.set:(Ljava/lang/Object;)V
      19: aload_0
      20: invokevirtual #7                  // Method getDelegate:()Ljava/io/PrintStream;
      23: iload_1
      24: invokevirtual #16                 // Method java/io/PrintStream.print:(I)V
      27: invokestatic  #3                  // Method org/jboss/stdio/StdioContext.access$500:()Ljava/lang/ThreadLocal;
      30: invokevirtual #9                  // Method java/lang/ThreadLocal.remove:()V
      33: goto          45
      36: astore_2
      37: invokestatic  #3                  // Method org/jboss/stdio/StdioContext.access$500:()Ljava/lang/ThreadLocal;
      40: invokevirtual #9                  // Method java/lang/ThreadLocal.remove:()V
      43: aload_2
      44: athrow
      45: return
    Exception table:
       from    to  target type
          10    27    36   any
          36    37    36   any

  public void print(long);
    Code:
       0: invokestatic  #3                  // Method org/jboss/stdio/StdioContext.access$500:()Ljava/lang/ThreadLocal;
       3: invokevirtual #4                  // Method java/lang/ThreadLocal.get:()Ljava/lang/Object;
       6: ifnull        10
       9: return
      10: invokestatic  #3                  // Method org/jboss/stdio/StdioContext.access$500:()Ljava/lang/ThreadLocal;
      13: getstatic     #5                  // Field java/lang/Boolean.TRUE:Ljava/lang/Boolean;
      16: invokevirtual #6                  // Method java/lang/ThreadLocal.set:(Ljava/lang/Object;)V
      19: aload_0
      20: invokevirtual #7                  // Method getDelegate:()Ljava/io/PrintStream;
      23: lload_1
      24: invokevirtual #17                 // Method java/io/PrintStream.print:(J)V
      27: invokestatic  #3                  // Method org/jboss/stdio/StdioContext.access$500:()Ljava/lang/ThreadLocal;
      30: invokevirtual #9                  // Method java/lang/ThreadLocal.remove:()V
      33: goto          45
      36: astore_3
      37: invokestatic  #3                  // Method org/jboss/stdio/StdioContext.access$500:()Ljava/lang/ThreadLocal;
      40: invokevirtual #9                  // Method java/lang/ThreadLocal.remove:()V
      43: aload_3
      44: athrow
      45: return
    Exception table:
       from    to  target type
          10    27    36   any
          36    37    36   any

  public void print(float);
    Code:
       0: invokestatic  #3                  // Method org/jboss/stdio/StdioContext.access$500:()Ljava/lang/ThreadLocal;
       3: invokevirtual #4                  // Method java/lang/ThreadLocal.get:()Ljava/lang/Object;
       6: ifnull        10
       9: return
      10: invokestatic  #3                  // Method org/jboss/stdio/StdioContext.access$500:()Ljava/lang/ThreadLocal;
      13: getstatic     #5                  // Field java/lang/Boolean.TRUE:Ljava/lang/Boolean;
      16: invokevirtual #6                  // Method java/lang/ThreadLocal.set:(Ljava/lang/Object;)V
      19: aload_0
      20: invokevirtual #7                  // Method getDelegate:()Ljava/io/PrintStream;
      23: fload_1
      24: invokevirtual #18                 // Method java/io/PrintStream.print:(F)V
      27: invokestatic  #3                  // Method org/jboss/stdio/StdioContext.access$500:()Ljava/lang/ThreadLocal;
      30: invokevirtual #9                  // Method java/lang/ThreadLocal.remove:()V
      33: goto          45
      36: astore_2
      37: invokestatic  #3                  // Method org/jboss/stdio/StdioContext.access$500:()Ljava/lang/ThreadLocal;
      40: invokevirtual #9                  // Method java/lang/ThreadLocal.remove:()V
      43: aload_2
      44: athrow
      45: return
    Exception table:
       from    to  target type
          10    27    36   any
          36    37    36   any

  public void print(double);
    Code:
       0: invokestatic  #3                  // Method org/jboss/stdio/StdioContext.access$500:()Ljava/lang/ThreadLocal;
       3: invokevirtual #4                  // Method java/lang/ThreadLocal.get:()Ljava/lang/Object;
       6: ifnull        10
       9: return
      10: invokestatic  #3                  // Method org/jboss/stdio/StdioContext.access$500:()Ljava/lang/ThreadLocal;
      13: getstatic     #5                  // Field java/lang/Boolean.TRUE:Ljava/lang/Boolean;
      16: invokevirtual #6                  // Method java/lang/ThreadLocal.set:(Ljava/lang/Object;)V
      19: aload_0
      20: invokevirtual #7                  // Method getDelegate:()Ljava/io/PrintStream;
      23: dload_1
      24: invokevirtual #19                 // Method java/io/PrintStream.print:(D)V
      27: invokestatic  #3                  // Method org/jboss/stdio/StdioContext.access$500:()Ljava/lang/ThreadLocal;
      30: invokevirtual #9                  // Method java/lang/ThreadLocal.remove:()V
      33: goto          45
      36: astore_3
      37: invokestatic  #3                  // Method org/jboss/stdio/StdioContext.access$500:()Ljava/lang/ThreadLocal;
      40: invokevirtual #9                  // Method java/lang/ThreadLocal.remove:()V
      43: aload_3
      44: athrow
      45: return
    Exception table:
       from    to  target type
          10    27    36   any
          36    37    36   any

  public void print(char[]);
    Code:
       0: invokestatic  #3                  // Method org/jboss/stdio/StdioContext.access$500:()Ljava/lang/ThreadLocal;
       3: invokevirtual #4                  // Method java/lang/ThreadLocal.get:()Ljava/lang/Object;
       6: ifnull        10
       9: return
      10: invokestatic  #3                  // Method org/jboss/stdio/StdioContext.access$500:()Ljava/lang/ThreadLocal;
      13: getstatic     #5                  // Field java/lang/Boolean.TRUE:Ljava/lang/Boolean;
      16: invokevirtual #6                  // Method java/lang/ThreadLocal.set:(Ljava/lang/Object;)V
      19: aload_0
      20: invokevirtual #7                  // Method getDelegate:()Ljava/io/PrintStream;
      23: aload_1
      24: invokevirtual #20                 // Method java/io/PrintStream.print:([C)V
      27: invokestatic  #3                  // Method org/jboss/stdio/StdioContext.access$500:()Ljava/lang/ThreadLocal;
      30: invokevirtual #9                  // Method java/lang/ThreadLocal.remove:()V
      33: goto          45
      36: astore_2
      37: invokestatic  #3                  // Method org/jboss/stdio/StdioContext.access$500:()Ljava/lang/ThreadLocal;
      40: invokevirtual #9                  // Method java/lang/ThreadLocal.remove:()V
      43: aload_2
      44: athrow
      45: return
    Exception table:
       from    to  target type
          10    27    36   any
          36    37    36   any

  public void print(java.lang.String);
    Code:
       0: invokestatic  #3                  // Method org/jboss/stdio/StdioContext.access$500:()Ljava/lang/ThreadLocal;
       3: invokevirtual #4                  // Method java/lang/ThreadLocal.get:()Ljava/lang/Object;
       6: ifnull        10
       9: return
      10: invokestatic  #3                  // Method org/jboss/stdio/StdioContext.access$500:()Ljava/lang/ThreadLocal;
      13: getstatic     #5                  // Field java/lang/Boolean.TRUE:Ljava/lang/Boolean;
      16: invokevirtual #6                  // Method java/lang/ThreadLocal.set:(Ljava/lang/Object;)V
      19: aload_0
      20: invokevirtual #7                  // Method getDelegate:()Ljava/io/PrintStream;
      23: aload_1
      24: invokevirtual #21                 // Method java/io/PrintStream.print:(Ljava/lang/String;)V
      27: invokestatic  #3                  // Method org/jboss/stdio/StdioContext.access$500:()Ljava/lang/ThreadLocal;
      30: invokevirtual #9                  // Method java/lang/ThreadLocal.remove:()V
      33: goto          45
      36: astore_2
      37: invokestatic  #3                  // Method org/jboss/stdio/StdioContext.access$500:()Ljava/lang/ThreadLocal;
      40: invokevirtual #9                  // Method java/lang/ThreadLocal.remove:()V
      43: aload_2
      44: athrow
      45: return
    Exception table:
       from    to  target type
          10    27    36   any
          36    37    36   any

  public void print(java.lang.Object);
    Code:
       0: invokestatic  #3                  // Method org/jboss/stdio/StdioContext.access$500:()Ljava/lang/ThreadLocal;
       3: invokevirtual #4                  // Method java/lang/ThreadLocal.get:()Ljava/lang/Object;
       6: ifnull        10
       9: return
      10: invokestatic  #3                  // Method org/jboss/stdio/StdioContext.access$500:()Ljava/lang/ThreadLocal;
      13: getstatic     #5                  // Field java/lang/Boolean.TRUE:Ljava/lang/Boolean;
      16: invokevirtual #6                  // Method java/lang/ThreadLocal.set:(Ljava/lang/Object;)V
      19: aload_0
      20: invokevirtual #7                  // Method getDelegate:()Ljava/io/PrintStream;
      23: aload_1
      24: invokevirtual #22                 // Method java/io/PrintStream.print:(Ljava/lang/Object;)V
      27: invokestatic  #3                  // Method org/jboss/stdio/StdioContext.access$500:()Ljava/lang/ThreadLocal;
      30: invokevirtual #9                  // Method java/lang/ThreadLocal.remove:()V
      33: goto          45
      36: astore_2
      37: invokestatic  #3                  // Method org/jboss/stdio/StdioContext.access$500:()Ljava/lang/ThreadLocal;
      40: invokevirtual #9                  // Method java/lang/ThreadLocal.remove:()V
      43: aload_2
      44: athrow
      45: return
    Exception table:
       from    to  target type
          10    27    36   any
          36    37    36   any

  public void println();
    Code:
       0: invokestatic  #3                  // Method org/jboss/stdio/StdioContext.access$500:()Ljava/lang/ThreadLocal;
       3: getstatic     #5                  // Field java/lang/Boolean.TRUE:Ljava/lang/Boolean;
       6: invokevirtual #6                  // Method java/lang/ThreadLocal.set:(Ljava/lang/Object;)V
       9: aload_0
      10: invokevirtual #7                  // Method getDelegate:()Ljava/io/PrintStream;
      13: invokevirtual #23                 // Method java/io/PrintStream.println:()V
      16: invokestatic  #3                  // Method org/jboss/stdio/StdioContext.access$500:()Ljava/lang/ThreadLocal;
      19: invokevirtual #9                  // Method java/lang/ThreadLocal.remove:()V
      22: goto          34
      25: astore_1
      26: invokestatic  #3                  // Method org/jboss/stdio/StdioContext.access$500:()Ljava/lang/ThreadLocal;
      29: invokevirtual #9                  // Method java/lang/ThreadLocal.remove:()V
      32: aload_1
      33: athrow
      34: return
    Exception table:
       from    to  target type
           0    16    25   any
          25    26    25   any

  public void println(boolean);
    Code:
       0: invokestatic  #3                  // Method org/jboss/stdio/StdioContext.access$500:()Ljava/lang/ThreadLocal;
       3: getstatic     #5                  // Field java/lang/Boolean.TRUE:Ljava/lang/Boolean;
       6: invokevirtual #6                  // Method java/lang/ThreadLocal.set:(Ljava/lang/Object;)V
       9: aload_0
      10: invokevirtual #7                  // Method getDelegate:()Ljava/io/PrintStream;
      13: iload_1
      14: invokevirtual #24                 // Method java/io/PrintStream.println:(Z)V
      17: invokestatic  #3                  // Method org/jboss/stdio/StdioContext.access$500:()Ljava/lang/ThreadLocal;
      20: invokevirtual #9                  // Method java/lang/ThreadLocal.remove:()V
      23: goto          35
      26: astore_2
      27: invokestatic  #3                  // Method org/jboss/stdio/StdioContext.access$500:()Ljava/lang/ThreadLocal;
      30: invokevirtual #9                  // Method java/lang/ThreadLocal.remove:()V
      33: aload_2
      34: athrow
      35: return
    Exception table:
       from    to  target type
           0    17    26   any
          26    27    26   any

  public void println(char);
    Code:
       0: invokestatic  #3                  // Method org/jboss/stdio/StdioContext.access$500:()Ljava/lang/ThreadLocal;
       3: invokevirtual #4                  // Method java/lang/ThreadLocal.get:()Ljava/lang/Object;
       6: ifnull        10
       9: return
      10: invokestatic  #3                  // Method org/jboss/stdio/StdioContext.access$500:()Ljava/lang/ThreadLocal;
      13: getstatic     #5                  // Field java/lang/Boolean.TRUE:Ljava/lang/Boolean;
      16: invokevirtual #6                  // Method java/lang/ThreadLocal.set:(Ljava/lang/Object;)V
      19: aload_0
      20: invokevirtual #7                  // Method getDelegate:()Ljava/io/PrintStream;
      23: iload_1
      24: invokevirtual #25                 // Method java/io/PrintStream.println:(C)V
      27: invokestatic  #3                  // Method org/jboss/stdio/StdioContext.access$500:()Ljava/lang/ThreadLocal;
      30: invokevirtual #9                  // Method java/lang/ThreadLocal.remove:()V
      33: goto          45
      36: astore_2
      37: invokestatic  #3                  // Method org/jboss/stdio/StdioContext.access$500:()Ljava/lang/ThreadLocal;
      40: invokevirtual #9                  // Method java/lang/ThreadLocal.remove:()V
      43: aload_2
      44: athrow
      45: return
    Exception table:
       from    to  target type
          10    27    36   any
          36    37    36   any

  public void println(int);
    Code:
       0: invokestatic  #3                  // Method org/jboss/stdio/StdioContext.access$500:()Ljava/lang/ThreadLocal;
       3: invokevirtual #4                  // Method java/lang/ThreadLocal.get:()Ljava/lang/Object;
       6: ifnull        10
       9: return
      10: invokestatic  #3                  // Method org/jboss/stdio/StdioContext.access$500:()Ljava/lang/ThreadLocal;
      13: getstatic     #5                  // Field java/lang/Boolean.TRUE:Ljava/lang/Boolean;
      16: invokevirtual #6                  // Method java/lang/ThreadLocal.set:(Ljava/lang/Object;)V
      19: aload_0
      20: invokevirtual #7                  // Method getDelegate:()Ljava/io/PrintStream;
      23: iload_1
      24: invokevirtual #26                 // Method java/io/PrintStream.println:(I)V
      27: invokestatic  #3                  // Method org/jboss/stdio/StdioContext.access$500:()Ljava/lang/ThreadLocal;
      30: invokevirtual #9                  // Method java/lang/ThreadLocal.remove:()V
      33: goto          45
      36: astore_2
      37: invokestatic  #3                  // Method org/jboss/stdio/StdioContext.access$500:()Ljava/lang/ThreadLocal;
      40: invokevirtual #9                  // Method java/lang/ThreadLocal.remove:()V
      43: aload_2
      44: athrow
      45: return
    Exception table:
       from    to  target type
          10    27    36   any
          36    37    36   any

  public void println(long);
    Code:
       0: invokestatic  #3                  // Method org/jboss/stdio/StdioContext.access$500:()Ljava/lang/ThreadLocal;
       3: invokevirtual #4                  // Method java/lang/ThreadLocal.get:()Ljava/lang/Object;
       6: ifnull        10
       9: return
      10: invokestatic  #3                  // Method org/jboss/stdio/StdioContext.access$500:()Ljava/lang/ThreadLocal;
      13: getstatic     #5                  // Field java/lang/Boolean.TRUE:Ljava/lang/Boolean;
      16: invokevirtual #6                  // Method java/lang/ThreadLocal.set:(Ljava/lang/Object;)V
      19: aload_0
      20: invokevirtual #7                  // Method getDelegate:()Ljava/io/PrintStream;
      23: lload_1
      24: invokevirtual #27                 // Method java/io/PrintStream.println:(J)V
      27: invokestatic  #3                  // Method org/jboss/stdio/StdioContext.access$500:()Ljava/lang/ThreadLocal;
      30: invokevirtual #9                  // Method java/lang/ThreadLocal.remove:()V
      33: goto          45
      36: astore_3
      37: invokestatic  #3                  // Method org/jboss/stdio/StdioContext.access$500:()Ljava/lang/ThreadLocal;
      40: invokevirtual #9                  // Method java/lang/ThreadLocal.remove:()V
      43: aload_3
      44: athrow
      45: return
    Exception table:
       from    to  target type
          10    27    36   any
          36    37    36   any

  public void println(float);
    Code:
       0: invokestatic  #3                  // Method org/jboss/stdio/StdioContext.access$500:()Ljava/lang/ThreadLocal;
       3: invokevirtual #4                  // Method java/lang/ThreadLocal.get:()Ljava/lang/Object;
       6: ifnull        10
       9: return
      10: invokestatic  #3                  // Method org/jboss/stdio/StdioContext.access$500:()Ljava/lang/ThreadLocal;
      13: getstatic     #5                  // Field java/lang/Boolean.TRUE:Ljava/lang/Boolean;
      16: invokevirtual #6                  // Method java/lang/ThreadLocal.set:(Ljava/lang/Object;)V
      19: aload_0
      20: invokevirtual #7                  // Method getDelegate:()Ljava/io/PrintStream;
      23: fload_1
      24: invokevirtual #28                 // Method java/io/PrintStream.println:(F)V
      27: invokestatic  #3                  // Method org/jboss/stdio/StdioContext.access$500:()Ljava/lang/ThreadLocal;
      30: invokevirtual #9                  // Method java/lang/ThreadLocal.remove:()V
      33: goto          45
      36: astore_2
      37: invokestatic  #3                  // Method org/jboss/stdio/StdioContext.access$500:()Ljava/lang/ThreadLocal;
      40: invokevirtual #9                  // Method java/lang/ThreadLocal.remove:()V
      43: aload_2
      44: athrow
      45: return
    Exception table:
       from    to  target type
          10    27    36   any
          36    37    36   any

  public void println(double);
    Code:
       0: invokestatic  #3                  // Method org/jboss/stdio/StdioContext.access$500:()Ljava/lang/ThreadLocal;
       3: invokevirtual #4                  // Method java/lang/ThreadLocal.get:()Ljava/lang/Object;
       6: ifnull        10
       9: return
      10: invokestatic  #3                  // Method org/jboss/stdio/StdioContext.access$500:()Ljava/lang/ThreadLocal;
      13: getstatic     #5                  // Field java/lang/Boolean.TRUE:Ljava/lang/Boolean;
      16: invokevirtual #6                  // Method java/lang/ThreadLocal.set:(Ljava/lang/Object;)V
      19: aload_0
      20: invokevirtual #7                  // Method getDelegate:()Ljava/io/PrintStream;
      23: dload_1
      24: invokevirtual #29                 // Method java/io/PrintStream.println:(D)V
      27: invokestatic  #3                  // Method org/jboss/stdio/StdioContext.access$500:()Ljava/lang/ThreadLocal;
      30: invokevirtual #9                  // Method java/lang/ThreadLocal.remove:()V
      33: goto          45
      36: astore_3
      37: invokestatic  #3                  // Method org/jboss/stdio/StdioContext.access$500:()Ljava/lang/ThreadLocal;
      40: invokevirtual #9                  // Method java/lang/ThreadLocal.remove:()V
      43: aload_3
      44: athrow
      45: return
    Exception table:
       from    to  target type
          10    27    36   any
          36    37    36   any

  public void println(char[]);
    Code:
       0: invokestatic  #3                  // Method org/jboss/stdio/StdioContext.access$500:()Ljava/lang/ThreadLocal;
       3: invokevirtual #4                  // Method java/lang/ThreadLocal.get:()Ljava/lang/Object;
       6: ifnull        10
       9: return
      10: invokestatic  #3                  // Method org/jboss/stdio/StdioContext.access$500:()Ljava/lang/ThreadLocal;
      13: getstatic     #5                  // Field java/lang/Boolean.TRUE:Ljava/lang/Boolean;
      16: invokevirtual #6                  // Method java/lang/ThreadLocal.set:(Ljava/lang/Object;)V
      19: aload_0
      20: invokevirtual #7                  // Method getDelegate:()Ljava/io/PrintStream;
      23: aload_1
      24: invokevirtual #30                 // Method java/io/PrintStream.println:([C)V
      27: invokestatic  #3                  // Method org/jboss/stdio/StdioContext.access$500:()Ljava/lang/ThreadLocal;
      30: invokevirtual #9                  // Method java/lang/ThreadLocal.remove:()V
      33: goto          45
      36: astore_2
      37: invokestatic  #3                  // Method org/jboss/stdio/StdioContext.access$500:()Ljava/lang/ThreadLocal;
      40: invokevirtual #9                  // Method java/lang/ThreadLocal.remove:()V
      43: aload_2
      44: athrow
      45: return
    Exception table:
       from    to  target type
          10    27    36   any
          36    37    36   any

  public void println(java.lang.String);
    Code:
       0: invokestatic  #3                  // Method org/jboss/stdio/StdioContext.access$500:()Ljava/lang/ThreadLocal;
       3: invokevirtual #4                  // Method java/lang/ThreadLocal.get:()Ljava/lang/Object;
       6: ifnull        10
       9: return
      10: invokestatic  #3                  // Method org/jboss/stdio/StdioContext.access$500:()Ljava/lang/ThreadLocal;
      13: getstatic     #5                  // Field java/lang/Boolean.TRUE:Ljava/lang/Boolean;
      16: invokevirtual #6                  // Method java/lang/ThreadLocal.set:(Ljava/lang/Object;)V
      19: aload_0
      20: invokevirtual #7                  // Method getDelegate:()Ljava/io/PrintStream;
      23: aload_1
      24: invokevirtual #31                 // Method java/io/PrintStream.println:(Ljava/lang/String;)V
      27: invokestatic  #3                  // Method org/jboss/stdio/StdioContext.access$500:()Ljava/lang/ThreadLocal;
      30: invokevirtual #9                  // Method java/lang/ThreadLocal.remove:()V
      33: goto          45
      36: astore_2
      37: invokestatic  #3                  // Method org/jboss/stdio/StdioContext.access$500:()Ljava/lang/ThreadLocal;
      40: invokevirtual #9                  // Method java/lang/ThreadLocal.remove:()V
      43: aload_2
      44: athrow
      45: return
    Exception table:
       from    to  target type
          10    27    36   any
          36    37    36   any

  public void println(java.lang.Object);
    Code:
       0: invokestatic  #3                  // Method org/jboss/stdio/StdioContext.access$500:()Ljava/lang/ThreadLocal;
       3: invokevirtual #4                  // Method java/lang/ThreadLocal.get:()Ljava/lang/Object;
       6: ifnull        10
       9: return
      10: invokestatic  #3                  // Method org/jboss/stdio/StdioContext.access$500:()Ljava/lang/ThreadLocal;
      13: getstatic     #5                  // Field java/lang/Boolean.TRUE:Ljava/lang/Boolean;
      16: invokevirtual #6                  // Method java/lang/ThreadLocal.set:(Ljava/lang/Object;)V
      19: aload_0
      20: invokevirtual #7                  // Method getDelegate:()Ljava/io/PrintStream;
      23: aload_1
      24: invokevirtual #32                 // Method java/io/PrintStream.println:(Ljava/lang/Object;)V
      27: invokestatic  #3                  // Method org/jboss/stdio/StdioContext.access$500:()Ljava/lang/ThreadLocal;
      30: invokevirtual #9                  // Method java/lang/ThreadLocal.remove:()V
      33: goto          45
      36: astore_2
      37: invokestatic  #3                  // Method org/jboss/stdio/StdioContext.access$500:()Ljava/lang/ThreadLocal;
      40: invokevirtual #9                  // Method java/lang/ThreadLocal.remove:()V
      43: aload_2
      44: athrow
      45: return
    Exception table:
       from    to  target type
          10    27    36   any
          36    37    36   any

  public java.io.PrintStream printf(java.lang.String, java.lang.Object...);
    Code:
       0: invokestatic  #3                  // Method org/jboss/stdio/StdioContext.access$500:()Ljava/lang/ThreadLocal;
       3: invokevirtual #4                  // Method java/lang/ThreadLocal.get:()Ljava/lang/Object;
       6: ifnull        11
       9: aload_0
      10: areturn
      11: invokestatic  #3                  // Method org/jboss/stdio/StdioContext.access$500:()Ljava/lang/ThreadLocal;
      14: getstatic     #5                  // Field java/lang/Boolean.TRUE:Ljava/lang/Boolean;
      17: invokevirtual #6                  // Method java/lang/ThreadLocal.set:(Ljava/lang/Object;)V
      20: aload_0
      21: invokevirtual #7                  // Method getDelegate:()Ljava/io/PrintStream;
      24: aload_1
      25: aload_2
      26: invokevirtual #33                 // Method java/io/PrintStream.printf:(Ljava/lang/String;[Ljava/lang/Object;)Ljava/io/PrintStream;
      29: astore_3
      30: invokestatic  #3                  // Method org/jboss/stdio/StdioContext.access$500:()Ljava/lang/ThreadLocal;
      33: invokevirtual #9                  // Method java/lang/ThreadLocal.remove:()V
      36: aload_3
      37: areturn
      38: astore        4
      40: invokestatic  #3                  // Method org/jboss/stdio/StdioContext.access$500:()Ljava/lang/ThreadLocal;
      43: invokevirtual #9                  // Method java/lang/ThreadLocal.remove:()V
      46: aload         4
      48: athrow
    Exception table:
       from    to  target type
          11    30    38   any
          38    40    38   any

  public java.io.PrintStream printf(java.util.Locale, java.lang.String, java.lang.Object...);
    Code:
       0: invokestatic  #3                  // Method org/jboss/stdio/StdioContext.access$500:()Ljava/lang/ThreadLocal;
       3: invokevirtual #4                  // Method java/lang/ThreadLocal.get:()Ljava/lang/Object;
       6: ifnull        11
       9: aload_0
      10: areturn
      11: invokestatic  #3                  // Method org/jboss/stdio/StdioContext.access$500:()Ljava/lang/ThreadLocal;
      14: getstatic     #5                  // Field java/lang/Boolean.TRUE:Ljava/lang/Boolean;
      17: invokevirtual #6                  // Method java/lang/ThreadLocal.set:(Ljava/lang/Object;)V
      20: aload_0
      21: invokevirtual #7                  // Method getDelegate:()Ljava/io/PrintStream;
      24: aload_1
      25: aload_2
      26: aload_3
      27: invokevirtual #34                 // Method java/io/PrintStream.printf:(Ljava/util/Locale;Ljava/lang/String;[Ljava/lang/Object;)Ljava/io/PrintStream;
      30: astore        4
      32: invokestatic  #3                  // Method org/jboss/stdio/StdioContext.access$500:()Ljava/lang/ThreadLocal;
      35: invokevirtual #9                  // Method java/lang/ThreadLocal.remove:()V
      38: aload         4
      40: areturn
      41: astore        5
      43: invokestatic  #3                  // Method org/jboss/stdio/StdioContext.access$500:()Ljava/lang/ThreadLocal;
      46: invokevirtual #9                  // Method java/lang/ThreadLocal.remove:()V
      49: aload         5
      51: athrow
    Exception table:
       from    to  target type
          11    32    41   any
          41    43    41   any

  public java.io.PrintStream format(java.lang.String, java.lang.Object...);
    Code:
       0: invokestatic  #3                  // Method org/jboss/stdio/StdioContext.access$500:()Ljava/lang/ThreadLocal;
       3: invokevirtual #4                  // Method java/lang/ThreadLocal.get:()Ljava/lang/Object;
       6: ifnull        11
       9: aload_0
      10: areturn
      11: invokestatic  #3                  // Method org/jboss/stdio/StdioContext.access$500:()Ljava/lang/ThreadLocal;
      14: getstatic     #5                  // Field java/lang/Boolean.TRUE:Ljava/lang/Boolean;
      17: invokevirtual #6                  // Method java/lang/ThreadLocal.set:(Ljava/lang/Object;)V
      20: aload_0
      21: invokevirtual #7                  // Method getDelegate:()Ljava/io/PrintStream;
      24: aload_1
      25: aload_2
      26: invokevirtual #35                 // Method java/io/PrintStream.format:(Ljava/lang/String;[Ljava/lang/Object;)Ljava/io/PrintStream;
      29: astore_3
      30: invokestatic  #3                  // Method org/jboss/stdio/StdioContext.access$500:()Ljava/lang/ThreadLocal;
      33: invokevirtual #9                  // Method java/lang/ThreadLocal.remove:()V
      36: aload_3
      37: areturn
      38: astore        4
      40: invokestatic  #3                  // Method org/jboss/stdio/StdioContext.access$500:()Ljava/lang/ThreadLocal;
      43: invokevirtual #9                  // Method java/lang/ThreadLocal.remove:()V
      46: aload         4
      48: athrow
    Exception table:
       from    to  target type
          11    30    38   any
          38    40    38   any

  public java.io.PrintStream format(java.util.Locale, java.lang.String, java.lang.Object...);
    Code:
       0: invokestatic  #3                  // Method org/jboss/stdio/StdioContext.access$500:()Ljava/lang/ThreadLocal;
       3: invokevirtual #4                  // Method java/lang/ThreadLocal.get:()Ljava/lang/Object;
       6: ifnull        11
       9: aload_0
      10: areturn
      11: invokestatic  #3                  // Method org/jboss/stdio/StdioContext.access$500:()Ljava/lang/ThreadLocal;
      14: getstatic     #5                  // Field java/lang/Boolean.TRUE:Ljava/lang/Boolean;
      17: invokevirtual #6                  // Method java/lang/ThreadLocal.set:(Ljava/lang/Object;)V
      20: aload_0
      21: invokevirtual #7                  // Method getDelegate:()Ljava/io/PrintStream;
      24: aload_1
      25: aload_2
      26: aload_3
      27: invokevirtual #36                 // Method java/io/PrintStream.format:(Ljava/util/Locale;Ljava/lang/String;[Ljava/lang/Object;)Ljava/io/PrintStream;
      30: astore        4
      32: invokestatic  #3                  // Method org/jboss/stdio/StdioContext.access$500:()Ljava/lang/ThreadLocal;
      35: invokevirtual #9                  // Method java/lang/ThreadLocal.remove:()V
      38: aload         4
      40: areturn
      41: astore        5
      43: invokestatic  #3                  // Method org/jboss/stdio/StdioContext.access$500:()Ljava/lang/ThreadLocal;
      46: invokevirtual #9                  // Method java/lang/ThreadLocal.remove:()V
      49: aload         5
      51: athrow
    Exception table:
       from    to  target type
          11    32    41   any
          41    43    41   any

  public java.io.PrintStream append(java.lang.CharSequence);
    Code:
       0: invokestatic  #3                  // Method org/jboss/stdio/StdioContext.access$500:()Ljava/lang/ThreadLocal;
       3: invokevirtual #4                  // Method java/lang/ThreadLocal.get:()Ljava/lang/Object;
       6: ifnull        11
       9: aload_0
      10: areturn
      11: invokestatic  #3                  // Method org/jboss/stdio/StdioContext.access$500:()Ljava/lang/ThreadLocal;
      14: getstatic     #5                  // Field java/lang/Boolean.TRUE:Ljava/lang/Boolean;
      17: invokevirtual #6                  // Method java/lang/ThreadLocal.set:(Ljava/lang/Object;)V
      20: aload_0
      21: invokevirtual #7                  // Method getDelegate:()Ljava/io/PrintStream;
      24: aload_1
      25: invokevirtual #37                 // Method java/io/PrintStream.append:(Ljava/lang/CharSequence;)Ljava/io/PrintStream;
      28: astore_2
      29: invokestatic  #3                  // Method org/jboss/stdio/StdioContext.access$500:()Ljava/lang/ThreadLocal;
      32: invokevirtual #9                  // Method java/lang/ThreadLocal.remove:()V
      35: aload_2
      36: areturn
      37: astore_3
      38: invokestatic  #3                  // Method org/jboss/stdio/StdioContext.access$500:()Ljava/lang/ThreadLocal;
      41: invokevirtual #9                  // Method java/lang/ThreadLocal.remove:()V
      44: aload_3
      45: athrow
    Exception table:
       from    to  target type
          11    29    37   any
          37    38    37   any

  public java.io.PrintStream append(java.lang.CharSequence, int, int);
    Code:
       0: invokestatic  #3                  // Method org/jboss/stdio/StdioContext.access$500:()Ljava/lang/ThreadLocal;
       3: invokevirtual #4                  // Method java/lang/ThreadLocal.get:()Ljava/lang/Object;
       6: ifnull        11
       9: aload_0
      10: areturn
      11: invokestatic  #3                  // Method org/jboss/stdio/StdioContext.access$500:()Ljava/lang/ThreadLocal;
      14: getstatic     #5                  // Field java/lang/Boolean.TRUE:Ljava/lang/Boolean;
      17: invokevirtual #6                  // Method java/lang/ThreadLocal.set:(Ljava/lang/Object;)V
      20: aload_0
      21: invokevirtual #7                  // Method getDelegate:()Ljava/io/PrintStream;
      24: aload_1
      25: iload_2
      26: iload_3
      27: invokevirtual #38                 // Method java/io/PrintStream.append:(Ljava/lang/CharSequence;II)Ljava/io/PrintStream;
      30: astore        4
      32: invokestatic  #3                  // Method org/jboss/stdio/StdioContext.access$500:()Ljava/lang/ThreadLocal;
      35: invokevirtual #9                  // Method java/lang/ThreadLocal.remove:()V
      38: aload         4
      40: areturn
      41: astore        5
      43: invokestatic  #3                  // Method org/jboss/stdio/StdioContext.access$500:()Ljava/lang/ThreadLocal;
      46: invokevirtual #9                  // Method java/lang/ThreadLocal.remove:()V
      49: aload         5
      51: athrow
    Exception table:
       from    to  target type
          11    32    41   any
          41    43    41   any

  public java.io.PrintStream append(char);
    Code:
       0: invokestatic  #3                  // Method org/jboss/stdio/StdioContext.access$500:()Ljava/lang/ThreadLocal;
       3: invokevirtual #4                  // Method java/lang/ThreadLocal.get:()Ljava/lang/Object;
       6: ifnull        11
       9: aload_0
      10: areturn
      11: invokestatic  #3                  // Method org/jboss/stdio/StdioContext.access$500:()Ljava/lang/ThreadLocal;
      14: getstatic     #5                  // Field java/lang/Boolean.TRUE:Ljava/lang/Boolean;
      17: invokevirtual #6                  // Method java/lang/ThreadLocal.set:(Ljava/lang/Object;)V
      20: aload_0
      21: invokevirtual #7                  // Method getDelegate:()Ljava/io/PrintStream;
      24: iload_1
      25: invokevirtual #39                 // Method java/io/PrintStream.append:(C)Ljava/io/PrintStream;
      28: astore_2
      29: invokestatic  #3                  // Method org/jboss/stdio/StdioContext.access$500:()Ljava/lang/ThreadLocal;
      32: invokevirtual #9                  // Method java/lang/ThreadLocal.remove:()V
      35: aload_2
      36: areturn
      37: astore_3
      38: invokestatic  #3                  // Method org/jboss/stdio/StdioContext.access$500:()Ljava/lang/ThreadLocal;
      41: invokevirtual #9                  // Method java/lang/ThreadLocal.remove:()V
      44: aload_3
      45: athrow
    Exception table:
       from    to  target type
          11    29    37   any
          37    38    37   any

  public java.lang.Appendable append(char) throws java.io.IOException;
    Code:
       0: aload_0
       1: iload_1
       2: invokevirtual #40                 // Method append:(C)Ljava/io/PrintStream;
       5: areturn

  public java.lang.Appendable append(java.lang.CharSequence, int, int) throws java.io.IOException;
    Code:
       0: aload_0
       1: aload_1
       2: iload_2
       3: iload_3
       4: invokevirtual #41                 // Method append:(Ljava/lang/CharSequence;II)Ljava/io/PrintStream;
       7: areturn

  public java.lang.Appendable append(java.lang.CharSequence) throws java.io.IOException;
    Code:
       0: aload_0
       1: aload_1
       2: invokevirtual #42                 // Method append:(Ljava/lang/CharSequence;)Ljava/io/PrintStream;
       5: areturn
}
