Compiled from "StdioContext.java"
public final class org.jboss.stdio.StdioContext {
  private static final org.jboss.stdio.StdioContext SYSTEM_STDIO_CONTEXT;

  private static final java.lang.ThreadLocal<java.lang.Boolean> entered;

  private static final java.security.Permission CREATE_CONTEXT_PERMISSION;

  private static final java.security.Permission SET_CONTEXT_SELECTOR_PERMISSION;

  private static final java.security.Permission INSTALL_PERMISSION;

  private static final java.util.concurrent.atomic.AtomicReference<org.jboss.stdio.StdioContext$State> state;

  private final java.io.InputStream in;

  private final java.io.PrintStream out;

  private final java.io.PrintStream err;

  private static volatile org.jboss.stdio.StdioContextSelector stdioContextSelector;

  org.jboss.stdio.StdioContext(java.io.InputStream, java.io.PrintStream, java.io.PrintStream);
    Code:
       0: aload_0
       1: invokespecial #6                  // Method java/lang/Object."<init>":()V
       4: aload_0
       5: aload_1
       6: putfield      #2                  // Field in:Ljava/io/InputStream;
       9: aload_0
      10: aload_2
      11: putfield      #4                  // Field out:Ljava/io/PrintStream;
      14: aload_0
      15: aload_3
      16: putfield      #3                  // Field err:Ljava/io/PrintStream;
      19: return

  public static org.jboss.stdio.StdioContext create(java.io.InputStream, java.io.PrintStream, java.io.PrintStream) throws java.lang.SecurityException;
    Code:
       0: invokestatic  #7                  // Method java/lang/System.getSecurityManager:()Ljava/lang/SecurityManager;
       3: astore_3
       4: aload_3
       5: ifnull        15
       8: aload_3
       9: getstatic     #8                  // Field CREATE_CONTEXT_PERMISSION:Ljava/security/Permission;
      12: invokevirtual #9                  // Method java/lang/SecurityManager.checkPermission:(Ljava/security/Permission;)V
      15: new           #10                 // class org/jboss/stdio/StdioContext
      18: dup
      19: aload_0
      20: aload_1
      21: aload_2
      22: invokespecial #11                 // Method "<init>":(Ljava/io/InputStream;Ljava/io/PrintStream;Ljava/io/PrintStream;)V
      25: areturn

  public static org.jboss.stdio.StdioContext create(java.io.InputStream, java.io.OutputStream, java.io.OutputStream) throws java.lang.SecurityException;
    Code:
       0: aload_0
       1: new           #12                 // class java/io/PrintStream
       4: dup
       5: aload_1
       6: iconst_1
       7: invokespecial #13                 // Method java/io/PrintStream."<init>":(Ljava/io/OutputStream;Z)V
      10: new           #12                 // class java/io/PrintStream
      13: dup
      14: aload_2
      15: iconst_1
      16: invokespecial #13                 // Method java/io/PrintStream."<init>":(Ljava/io/OutputStream;Z)V
      19: invokestatic  #14                 // Method create:(Ljava/io/InputStream;Ljava/io/PrintStream;Ljava/io/PrintStream;)Lorg/jboss/stdio/StdioContext;
      22: areturn

  public static org.jboss.stdio.StdioContext getStdioContext();
    Code:
       0: getstatic     #5                  // Field stdioContextSelector:Lorg/jboss/stdio/StdioContextSelector;
       3: invokeinterface #15,  1           // InterfaceMethod org/jboss/stdio/StdioContextSelector.getStdioContext:()Lorg/jboss/stdio/StdioContext;
       8: areturn

  public java.io.InputStream getIn();
    Code:
       0: aload_0
       1: getfield      #2                  // Field in:Ljava/io/InputStream;
       4: areturn

  public java.io.PrintStream getOut();
    Code:
       0: aload_0
       1: getfield      #4                  // Field out:Ljava/io/PrintStream;
       4: areturn

  public java.io.PrintStream getErr();
    Code:
       0: aload_0
       1: getfield      #3                  // Field err:Ljava/io/PrintStream;
       4: areturn

  public static void install() throws java.lang.SecurityException, java.lang.IllegalStateException;
    Code:
       0: invokestatic  #7                  // Method java/lang/System.getSecurityManager:()Ljava/lang/SecurityManager;
       3: astore_0
       4: aload_0
       5: ifnull        15
       8: aload_0
       9: getstatic     #16                 // Field INSTALL_PERMISSION:Ljava/security/Permission;
      12: invokevirtual #9                  // Method java/lang/SecurityManager.checkPermission:(Ljava/security/Permission;)V
      15: getstatic     #17                 // Field state:Ljava/util/concurrent/atomic/AtomicReference;
      18: getstatic     #18                 // Field org/jboss/stdio/StdioContext$State.UNINSTALLED:Lorg/jboss/stdio/StdioContext$State;
      21: getstatic     #19                 // Field org/jboss/stdio/StdioContext$State.INSTALLING:Lorg/jboss/stdio/StdioContext$State;
      24: invokevirtual #20                 // Method java/util/concurrent/atomic/AtomicReference.compareAndSet:(Ljava/lang/Object;Ljava/lang/Object;)Z
      27: ifne          40
      30: new           #21                 // class java/lang/IllegalStateException
      33: dup
      34: ldc           #22                 // String Already installed
      36: invokespecial #23                 // Method java/lang/IllegalStateException."<init>":(Ljava/lang/String;)V
      39: athrow
      40: new           #24                 // class org/jboss/stdio/StdioContext$1
      43: dup
      44: invokespecial #25                 // Method org/jboss/stdio/StdioContext$1."<init>":()V
      47: invokestatic  #26                 // Method java/lang/System.setOut:(Ljava/io/PrintStream;)V
      50: new           #27                 // class org/jboss/stdio/StdioContext$2
      53: dup
      54: invokespecial #28                 // Method org/jboss/stdio/StdioContext$2."<init>":()V
      57: invokestatic  #29                 // Method java/lang/System.setErr:(Ljava/io/PrintStream;)V
      60: new           #30                 // class org/jboss/stdio/StdioContext$3
      63: dup
      64: invokespecial #31                 // Method org/jboss/stdio/StdioContext$3."<init>":()V
      67: invokestatic  #32                 // Method java/lang/System.setIn:(Ljava/io/InputStream;)V
      70: getstatic     #17                 // Field state:Ljava/util/concurrent/atomic/AtomicReference;
      73: getstatic     #33                 // Field org/jboss/stdio/StdioContext$State.INSTALLED:Lorg/jboss/stdio/StdioContext$State;
      76: invokevirtual #34                 // Method java/util/concurrent/atomic/AtomicReference.set:(Ljava/lang/Object;)V
      79: return

  public static void uninstall() throws java.lang.SecurityException, java.lang.IllegalStateException;
    Code:
       0: invokestatic  #7                  // Method java/lang/System.getSecurityManager:()Ljava/lang/SecurityManager;
       3: astore_0
       4: aload_0
       5: ifnull        15
       8: aload_0
       9: getstatic     #16                 // Field INSTALL_PERMISSION:Ljava/security/Permission;
      12: invokevirtual #9                  // Method java/lang/SecurityManager.checkPermission:(Ljava/security/Permission;)V
      15: getstatic     #17                 // Field state:Ljava/util/concurrent/atomic/AtomicReference;
      18: getstatic     #33                 // Field org/jboss/stdio/StdioContext$State.INSTALLED:Lorg/jboss/stdio/StdioContext$State;
      21: getstatic     #35                 // Field org/jboss/stdio/StdioContext$State.UNINSTALLING:Lorg/jboss/stdio/StdioContext$State;
      24: invokevirtual #20                 // Method java/util/concurrent/atomic/AtomicReference.compareAndSet:(Ljava/lang/Object;Ljava/lang/Object;)Z
      27: ifne          40
      30: new           #21                 // class java/lang/IllegalStateException
      33: dup
      34: ldc           #36                 // String Already uninstalled
      36: invokespecial #23                 // Method java/lang/IllegalStateException."<init>":(Ljava/lang/String;)V
      39: athrow
      40: getstatic     #37                 // Field SYSTEM_STDIO_CONTEXT:Lorg/jboss/stdio/StdioContext;
      43: getfield      #4                  // Field out:Ljava/io/PrintStream;
      46: invokestatic  #26                 // Method java/lang/System.setOut:(Ljava/io/PrintStream;)V
      49: getstatic     #37                 // Field SYSTEM_STDIO_CONTEXT:Lorg/jboss/stdio/StdioContext;
      52: getfield      #3                  // Field err:Ljava/io/PrintStream;
      55: invokestatic  #29                 // Method java/lang/System.setErr:(Ljava/io/PrintStream;)V
      58: getstatic     #37                 // Field SYSTEM_STDIO_CONTEXT:Lorg/jboss/stdio/StdioContext;
      61: getfield      #2                  // Field in:Ljava/io/InputStream;
      64: invokestatic  #32                 // Method java/lang/System.setIn:(Ljava/io/InputStream;)V
      67: getstatic     #17                 // Field state:Ljava/util/concurrent/atomic/AtomicReference;
      70: getstatic     #18                 // Field org/jboss/stdio/StdioContext$State.UNINSTALLED:Lorg/jboss/stdio/StdioContext$State;
      73: invokevirtual #34                 // Method java/util/concurrent/atomic/AtomicReference.set:(Ljava/lang/Object;)V
      76: return

  public static void setStdioContextSelector(org.jboss.stdio.StdioContextSelector) throws java.lang.SecurityException;
    Code:
       0: aload_0
       1: ifnonnull     14
       4: new           #38                 // class java/lang/NullPointerException
       7: dup
       8: ldc           #39                 // String stdioContextSelector is null
      10: invokespecial #40                 // Method java/lang/NullPointerException."<init>":(Ljava/lang/String;)V
      13: athrow
      14: invokestatic  #7                  // Method java/lang/System.getSecurityManager:()Ljava/lang/SecurityManager;
      17: astore_1
      18: aload_1
      19: ifnull        29
      22: aload_1
      23: getstatic     #41                 // Field SET_CONTEXT_SELECTOR_PERMISSION:Ljava/security/Permission;
      26: invokevirtual #9                  // Method java/lang/SecurityManager.checkPermission:(Ljava/security/Permission;)V
      29: aload_0
      30: putstatic     #5                  // Field stdioContextSelector:Lorg/jboss/stdio/StdioContextSelector;
      33: return

  static org.jboss.stdio.StdioContextSelector access$000();
    Code:
       0: getstatic     #5                  // Field stdioContextSelector:Lorg/jboss/stdio/StdioContextSelector;
       3: areturn

  static java.io.PrintStream access$100(org.jboss.stdio.StdioContext);
    Code:
       0: aload_0
       1: getfield      #4                  // Field out:Ljava/io/PrintStream;
       4: areturn

  static java.io.PrintStream access$200(org.jboss.stdio.StdioContext);
    Code:
       0: aload_0
       1: getfield      #3                  // Field err:Ljava/io/PrintStream;
       4: areturn

  static java.io.InputStream access$400(org.jboss.stdio.StdioContext);
    Code:
       0: aload_0
       1: getfield      #2                  // Field in:Ljava/io/InputStream;
       4: areturn

  static java.lang.ThreadLocal access$500();
    Code:
       0: getstatic     #1                  // Field entered:Ljava/lang/ThreadLocal;
       3: areturn

  static {};
    Code:
       0: new           #10                 // class org/jboss/stdio/StdioContext
       3: dup
       4: getstatic     #42                 // Field java/lang/System.in:Ljava/io/InputStream;
       7: getstatic     #43                 // Field java/lang/System.out:Ljava/io/PrintStream;
      10: getstatic     #44                 // Field java/lang/System.err:Ljava/io/PrintStream;
      13: invokespecial #11                 // Method "<init>":(Ljava/io/InputStream;Ljava/io/PrintStream;Ljava/io/PrintStream;)V
      16: putstatic     #37                 // Field SYSTEM_STDIO_CONTEXT:Lorg/jboss/stdio/StdioContext;
      19: new           #45                 // class java/lang/ThreadLocal
      22: dup
      23: invokespecial #46                 // Method java/lang/ThreadLocal."<init>":()V
      26: putstatic     #1                  // Field entered:Ljava/lang/ThreadLocal;
      29: new           #47                 // class java/lang/RuntimePermission
      32: dup
      33: ldc           #48                 // String createStdioContext
      35: aconst_null
      36: invokespecial #49                 // Method java/lang/RuntimePermission."<init>":(Ljava/lang/String;Ljava/lang/String;)V
      39: putstatic     #8                  // Field CREATE_CONTEXT_PERMISSION:Ljava/security/Permission;
      42: new           #47                 // class java/lang/RuntimePermission
      45: dup
      46: ldc           #50                 // String setStdioContextSelector
      48: aconst_null
      49: invokespecial #49                 // Method java/lang/RuntimePermission."<init>":(Ljava/lang/String;Ljava/lang/String;)V
      52: putstatic     #41                 // Field SET_CONTEXT_SELECTOR_PERMISSION:Ljava/security/Permission;
      55: new           #47                 // class java/lang/RuntimePermission
      58: dup
      59: ldc           #51                 // String installStdioContextSelector
      61: aconst_null
      62: invokespecial #49                 // Method java/lang/RuntimePermission."<init>":(Ljava/lang/String;Ljava/lang/String;)V
      65: putstatic     #16                 // Field INSTALL_PERMISSION:Ljava/security/Permission;
      68: new           #52                 // class java/util/concurrent/atomic/AtomicReference
      71: dup
      72: getstatic     #18                 // Field org/jboss/stdio/StdioContext$State.UNINSTALLED:Lorg/jboss/stdio/StdioContext$State;
      75: invokespecial #53                 // Method java/util/concurrent/atomic/AtomicReference."<init>":(Ljava/lang/Object;)V
      78: putstatic     #17                 // Field state:Ljava/util/concurrent/atomic/AtomicReference;
      81: new           #54                 // class org/jboss/stdio/SimpleStdioContextSelector
      84: dup
      85: getstatic     #37                 // Field SYSTEM_STDIO_CONTEXT:Lorg/jboss/stdio/StdioContext;
      88: invokespecial #55                 // Method org/jboss/stdio/SimpleStdioContextSelector."<init>":(Lorg/jboss/stdio/StdioContext;)V
      91: putstatic     #5                  // Field stdioContextSelector:Lorg/jboss/stdio/StdioContextSelector;
      94: return
}
