Compiled from "AttributeMap.java"
public final class software.amazon.awssdk.utils.AttributeMap$Builder implements software.amazon.awssdk.utils.builder.CopyableBuilder<software.amazon.awssdk.utils.AttributeMap$Builder, software.amazon.awssdk.utils.AttributeMap> {
  private final java.util.Map<software.amazon.awssdk.utils.AttributeMap$Key<?>, java.lang.Object> configuration;

  private software.amazon.awssdk.utils.AttributeMap$Builder();
    Code:
       0: aload_0
       1: invokespecial #2                  // Method java/lang/Object."<init>":()V
       4: aload_0
       5: new           #3                  // class java/util/HashMap
       8: dup
       9: invokespecial #4                  // Method java/util/HashMap."<init>":()V
      12: putfield      #5                  // Field configuration:Ljava/util/Map;
      15: return

  public <T> T get(software.amazon.awssdk.utils.AttributeMap$Key<T>);
    Code:
       0: aload_1
       1: ldc           #6                  // String Key to retrieve must not be null.
       3: iconst_0
       4: anewarray     #7                  // class java/lang/Object
       7: invokestatic  #8                  // Method software/amazon/awssdk/utils/Validate.notNull:(Ljava/lang/Object;Ljava/lang/String;[Ljava/lang/Object;)Ljava/lang/Object;
      10: pop
      11: aload_1
      12: aload_0
      13: getfield      #5                  // Field configuration:Ljava/util/Map;
      16: aload_1
      17: invokeinterface #9,  2            // InterfaceMethod java/util/Map.get:(Ljava/lang/Object;)Ljava/lang/Object;
      22: invokevirtual #10                 // Method software/amazon/awssdk/utils/AttributeMap$Key.convertValue:(Ljava/lang/Object;)Ljava/lang/Object;
      25: areturn

  public <T> software.amazon.awssdk.utils.AttributeMap$Builder put(software.amazon.awssdk.utils.AttributeMap$Key<T>, T);
    Code:
       0: aload_1
       1: ldc           #11                 // String Key to set must not be null.
       3: iconst_0
       4: anewarray     #7                  // class java/lang/Object
       7: invokestatic  #8                  // Method software/amazon/awssdk/utils/Validate.notNull:(Ljava/lang/Object;Ljava/lang/String;[Ljava/lang/Object;)Ljava/lang/Object;
      10: pop
      11: aload_0
      12: getfield      #5                  // Field configuration:Ljava/util/Map;
      15: aload_1
      16: aload_2
      17: invokeinterface #12,  3           // InterfaceMethod java/util/Map.put:(Ljava/lang/Object;Ljava/lang/Object;)Ljava/lang/Object;
      22: pop
      23: aload_0
      24: areturn

  public software.amazon.awssdk.utils.AttributeMap$Builder putAll(java.util.Map<? extends software.amazon.awssdk.utils.AttributeMap$Key<?>, ?>);
    Code:
       0: aload_1
       1: aload_0
       2: invokedynamic #13,  0             // InvokeDynamic #0:accept:(Lsoftware/amazon/awssdk/utils/AttributeMap$Builder;)Ljava/util/function/BiConsumer;
       7: invokeinterface #14,  2           // InterfaceMethod java/util/Map.forEach:(Ljava/util/function/BiConsumer;)V
      12: aload_0
      13: areturn

  public software.amazon.awssdk.utils.AttributeMap build();
    Code:
       0: new           #15                 // class software/amazon/awssdk/utils/AttributeMap
       3: dup
       4: aload_0
       5: getfield      #5                  // Field configuration:Ljava/util/Map;
       8: aconst_null
       9: invokespecial #16                 // Method software/amazon/awssdk/utils/AttributeMap."<init>":(Ljava/util/Map;Lsoftware/amazon/awssdk/utils/AttributeMap$1;)V
      12: areturn

  public java.lang.Object build();
    Code:
       0: aload_0
       1: invokevirtual #17                 // Method build:()Lsoftware/amazon/awssdk/utils/AttributeMap;
       4: areturn

  private void lambda$putAll$0(software.amazon.awssdk.utils.AttributeMap$Key, java.lang.Object);
    Code:
       0: aload_1
       1: aload_2
       2: invokevirtual #18                 // Method software/amazon/awssdk/utils/AttributeMap$Key.validateValue:(Ljava/lang/Object;)V
       5: aload_0
       6: getfield      #5                  // Field configuration:Ljava/util/Map;
       9: aload_1
      10: aload_2
      11: invokeinterface #12,  3           // InterfaceMethod java/util/Map.put:(Ljava/lang/Object;Ljava/lang/Object;)Ljava/lang/Object;
      16: pop
      17: return

  software.amazon.awssdk.utils.AttributeMap$Builder(software.amazon.awssdk.utils.AttributeMap$1);
    Code:
       0: aload_0
       1: invokespecial #1                  // Method "<init>":()V
       4: return
}
