Compiled from "DateUtils.java"
public final class software.amazon.awssdk.utils.DateUtils {
  static final java.time.format.DateTimeFormatter ALTERNATE_ISO_8601_DATE_FORMAT;

  private static final int MILLI_SECOND_PRECISION;

  private software.amazon.awssdk.utils.DateUtils();
    Code:
       0: aload_0
       1: invokespecial #1                  // Method java/lang/Object."<init>":()V
       4: return

  public static java.time.Instant parseIso8601Date(java.lang.String);
    Code:
       0: aload_0
       1: ldc           #2                  // String +0000
       3: invokevirtual #3                  // Method java/lang/String.endsWith:(Ljava/lang/String;)Z
       6: ifeq          26
       9: aload_0
      10: iconst_0
      11: aload_0
      12: invokevirtual #4                  // Method java/lang/String.length:()I
      15: iconst_5
      16: isub
      17: invokevirtual #5                  // Method java/lang/String.substring:(II)Ljava/lang/String;
      20: ldc           #6                  // String Z
      22: invokevirtual #7                  // Method java/lang/String.concat:(Ljava/lang/String;)Ljava/lang/String;
      25: astore_0
      26: aload_0
      27: getstatic     #8                  // Field java/time/format/DateTimeFormatter.ISO_INSTANT:Ljava/time/format/DateTimeFormatter;
      30: invokestatic  #9                  // Method parseInstant:(Ljava/lang/String;Ljava/time/format/DateTimeFormatter;)Ljava/time/Instant;
      33: areturn
      34: astore_1
      35: aload_0
      36: getstatic     #11                 // Field ALTERNATE_ISO_8601_DATE_FORMAT:Ljava/time/format/DateTimeFormatter;
      39: invokestatic  #9                  // Method parseInstant:(Ljava/lang/String;Ljava/time/format/DateTimeFormatter;)Ljava/time/Instant;
      42: areturn
    Exception table:
       from    to  target type
          26    33    34   Class java/time/format/DateTimeParseException

  public static java.lang.String formatIso8601Date(java.time.Instant);
    Code:
       0: getstatic     #8                  // Field java/time/format/DateTimeFormatter.ISO_INSTANT:Ljava/time/format/DateTimeFormatter;
       3: aload_0
       4: invokevirtual #12                 // Method java/time/format/DateTimeFormatter.format:(Ljava/time/temporal/TemporalAccessor;)Ljava/lang/String;
       7: areturn

  public static java.time.Instant parseRfc1123Date(java.lang.String);
    Code:
       0: aload_0
       1: ifnonnull     6
       4: aconst_null
       5: areturn
       6: aload_0
       7: getstatic     #13                 // Field java/time/format/DateTimeFormatter.RFC_1123_DATE_TIME:Ljava/time/format/DateTimeFormatter;
      10: invokestatic  #9                  // Method parseInstant:(Ljava/lang/String;Ljava/time/format/DateTimeFormatter;)Ljava/time/Instant;
      13: areturn

  public static java.lang.String formatRfc1123Date(java.time.Instant);
    Code:
       0: getstatic     #13                 // Field java/time/format/DateTimeFormatter.RFC_1123_DATE_TIME:Ljava/time/format/DateTimeFormatter;
       3: aload_0
       4: getstatic     #14                 // Field java/time/ZoneOffset.UTC:Ljava/time/ZoneOffset;
       7: invokestatic  #15                 // Method java/time/ZonedDateTime.ofInstant:(Ljava/time/Instant;Ljava/time/ZoneId;)Ljava/time/ZonedDateTime;
      10: invokevirtual #12                 // Method java/time/format/DateTimeFormatter.format:(Ljava/time/temporal/TemporalAccessor;)Ljava/lang/String;
      13: areturn

  public static long numberOfDaysSinceEpoch(long);
    Code:
       0: lload_0
       1: invokestatic  #16                 // Method java/time/Duration.ofMillis:(J)Ljava/time/Duration;
       4: invokevirtual #17                 // Method java/time/Duration.toDays:()J
       7: lreturn

  private static java.time.Instant parseInstant(java.lang.String, java.time.format.DateTimeFormatter);
    Code:
       0: aload_1
       1: getstatic     #14                 // Field java/time/ZoneOffset.UTC:Ljava/time/ZoneOffset;
       4: invokevirtual #18                 // Method java/time/format/DateTimeFormatter.withZone:(Ljava/time/ZoneId;)Ljava/time/format/DateTimeFormatter;
       7: aload_0
       8: invokedynamic #19,  0             // InvokeDynamic #0:queryFrom:()Ljava/time/temporal/TemporalQuery;
      13: invokevirtual #20                 // Method java/time/format/DateTimeFormatter.parse:(Ljava/lang/CharSequence;Ljava/time/temporal/TemporalQuery;)Ljava/lang/Object;
      16: checkcast     #21                 // class java/time/Instant
      19: areturn

  public static java.time.Instant parseUnixTimestampInstant(java.lang.String) throws java.lang.NumberFormatException;
    Code:
       0: aload_0
       1: ifnonnull     6
       4: aconst_null
       5: areturn
       6: new           #22                 // class java/math/BigDecimal
       9: dup
      10: aload_0
      11: invokespecial #23                 // Method java/math/BigDecimal."<init>":(Ljava/lang/String;)V
      14: astore_1
      15: aload_1
      16: iconst_3
      17: invokevirtual #25                 // Method java/math/BigDecimal.scaleByPowerOfTen:(I)Ljava/math/BigDecimal;
      20: invokevirtual #26                 // Method java/math/BigDecimal.longValue:()J
      23: invokestatic  #27                 // Method java/time/Instant.ofEpochMilli:(J)Ljava/time/Instant;
      26: areturn

  public static java.time.Instant parseUnixTimestampMillisInstant(java.lang.String) throws java.lang.NumberFormatException;
    Code:
       0: aload_0
       1: ifnonnull     6
       4: aconst_null
       5: areturn
       6: aload_0
       7: invokestatic  #28                 // Method java/lang/Long.parseLong:(Ljava/lang/String;)J
      10: invokestatic  #27                 // Method java/time/Instant.ofEpochMilli:(J)Ljava/time/Instant;
      13: areturn

  public static java.lang.String formatUnixTimestampInstant(java.time.Instant);
    Code:
       0: aload_0
       1: ifnonnull     6
       4: aconst_null
       5: areturn
       6: aload_0
       7: invokevirtual #29                 // Method java/time/Instant.toEpochMilli:()J
      10: invokestatic  #30                 // Method java/math/BigDecimal.valueOf:(J)Ljava/math/BigDecimal;
      13: astore_1
      14: aload_1
      15: bipush        -3
      17: invokevirtual #25                 // Method java/math/BigDecimal.scaleByPowerOfTen:(I)Ljava/math/BigDecimal;
      20: invokevirtual #31                 // Method java/math/BigDecimal.toPlainString:()Ljava/lang/String;
      23: areturn

  static {};
    Code:
       0: new           #32                 // class java/time/format/DateTimeFormatterBuilder
       3: dup
       4: invokespecial #33                 // Method java/time/format/DateTimeFormatterBuilder."<init>":()V
       7: ldc           #34                 // String yyyy-MM-dd\'T\'HH:mm:ss\'Z\'
       9: invokevirtual #35                 // Method java/time/format/DateTimeFormatterBuilder.appendPattern:(Ljava/lang/String;)Ljava/time/format/DateTimeFormatterBuilder;
      12: invokevirtual #36                 // Method java/time/format/DateTimeFormatterBuilder.toFormatter:()Ljava/time/format/DateTimeFormatter;
      15: getstatic     #14                 // Field java/time/ZoneOffset.UTC:Ljava/time/ZoneOffset;
      18: invokevirtual #18                 // Method java/time/format/DateTimeFormatter.withZone:(Ljava/time/ZoneId;)Ljava/time/format/DateTimeFormatter;
      21: putstatic     #11                 // Field ALTERNATE_ISO_8601_DATE_FORMAT:Ljava/time/format/DateTimeFormatter;
      24: return
}
