Compiled from "Logger.java"
public final class software.amazon.awssdk.utils.Logger {
  private final org.slf4j.Logger log;

  software.amazon.awssdk.utils.Logger(org.slf4j.Logger);
    Code:
       0: aload_0
       1: invokespecial #1                  // Method java/lang/Object."<init>":()V
       4: aload_0
       5: aload_1
       6: putfield      #2                  // Field log:Lorg/slf4j/Logger;
       9: return

  public org.slf4j.Logger logger();
    Code:
       0: aload_0
       1: getfield      #2                  // Field log:Lorg/slf4j/Logger;
       4: areturn

  public void info(java.util.function.Supplier<java.lang.String>);
    Code:
       0: aload_0
       1: getfield      #2                  // Field log:Lorg/slf4j/Logger;
       4: invokeinterface #3,  1            // InterfaceMethod org/slf4j/Logger.isInfoEnabled:()Z
       9: ifeq          30
      12: aload_0
      13: getfield      #2                  // Field log:Lorg/slf4j/Logger;
      16: aload_1
      17: invokeinterface #4,  1            // InterfaceMethod java/util/function/Supplier.get:()Ljava/lang/Object;
      22: checkcast     #5                  // class java/lang/String
      25: invokeinterface #6,  2            // InterfaceMethod org/slf4j/Logger.info:(Ljava/lang/String;)V
      30: return

  public void info(java.util.function.Supplier<java.lang.String>, java.lang.Throwable);
    Code:
       0: aload_0
       1: getfield      #2                  // Field log:Lorg/slf4j/Logger;
       4: invokeinterface #3,  1            // InterfaceMethod org/slf4j/Logger.isInfoEnabled:()Z
       9: ifeq          31
      12: aload_0
      13: getfield      #2                  // Field log:Lorg/slf4j/Logger;
      16: aload_1
      17: invokeinterface #4,  1            // InterfaceMethod java/util/function/Supplier.get:()Ljava/lang/Object;
      22: checkcast     #5                  // class java/lang/String
      25: aload_2
      26: invokeinterface #7,  3            // InterfaceMethod org/slf4j/Logger.info:(Ljava/lang/String;Ljava/lang/Throwable;)V
      31: return

  public void error(java.util.function.Supplier<java.lang.String>);
    Code:
       0: aload_0
       1: getfield      #2                  // Field log:Lorg/slf4j/Logger;
       4: invokeinterface #8,  1            // InterfaceMethod org/slf4j/Logger.isErrorEnabled:()Z
       9: ifeq          30
      12: aload_0
      13: getfield      #2                  // Field log:Lorg/slf4j/Logger;
      16: aload_1
      17: invokeinterface #4,  1            // InterfaceMethod java/util/function/Supplier.get:()Ljava/lang/Object;
      22: checkcast     #5                  // class java/lang/String
      25: invokeinterface #9,  2            // InterfaceMethod org/slf4j/Logger.error:(Ljava/lang/String;)V
      30: return

  public void error(java.util.function.Supplier<java.lang.String>, java.lang.Throwable);
    Code:
       0: aload_0
       1: getfield      #2                  // Field log:Lorg/slf4j/Logger;
       4: invokeinterface #8,  1            // InterfaceMethod org/slf4j/Logger.isErrorEnabled:()Z
       9: ifeq          31
      12: aload_0
      13: getfield      #2                  // Field log:Lorg/slf4j/Logger;
      16: aload_1
      17: invokeinterface #4,  1            // InterfaceMethod java/util/function/Supplier.get:()Ljava/lang/Object;
      22: checkcast     #5                  // class java/lang/String
      25: aload_2
      26: invokeinterface #10,  3           // InterfaceMethod org/slf4j/Logger.error:(Ljava/lang/String;Ljava/lang/Throwable;)V
      31: return

  public void debug(java.util.function.Supplier<java.lang.String>);
    Code:
       0: aload_0
       1: getfield      #2                  // Field log:Lorg/slf4j/Logger;
       4: invokeinterface #11,  1           // InterfaceMethod org/slf4j/Logger.isDebugEnabled:()Z
       9: ifeq          30
      12: aload_0
      13: getfield      #2                  // Field log:Lorg/slf4j/Logger;
      16: aload_1
      17: invokeinterface #4,  1            // InterfaceMethod java/util/function/Supplier.get:()Ljava/lang/Object;
      22: checkcast     #5                  // class java/lang/String
      25: invokeinterface #12,  2           // InterfaceMethod org/slf4j/Logger.debug:(Ljava/lang/String;)V
      30: return

  public void debug(java.util.function.Supplier<java.lang.String>, java.lang.Throwable);
    Code:
       0: aload_0
       1: getfield      #2                  // Field log:Lorg/slf4j/Logger;
       4: invokeinterface #11,  1           // InterfaceMethod org/slf4j/Logger.isDebugEnabled:()Z
       9: ifeq          31
      12: aload_0
      13: getfield      #2                  // Field log:Lorg/slf4j/Logger;
      16: aload_1
      17: invokeinterface #4,  1            // InterfaceMethod java/util/function/Supplier.get:()Ljava/lang/Object;
      22: checkcast     #5                  // class java/lang/String
      25: aload_2
      26: invokeinterface #13,  3           // InterfaceMethod org/slf4j/Logger.debug:(Ljava/lang/String;Ljava/lang/Throwable;)V
      31: return

  public void warn(java.util.function.Supplier<java.lang.String>);
    Code:
       0: aload_0
       1: getfield      #2                  // Field log:Lorg/slf4j/Logger;
       4: invokeinterface #14,  1           // InterfaceMethod org/slf4j/Logger.isWarnEnabled:()Z
       9: ifeq          30
      12: aload_0
      13: getfield      #2                  // Field log:Lorg/slf4j/Logger;
      16: aload_1
      17: invokeinterface #4,  1            // InterfaceMethod java/util/function/Supplier.get:()Ljava/lang/Object;
      22: checkcast     #5                  // class java/lang/String
      25: invokeinterface #15,  2           // InterfaceMethod org/slf4j/Logger.warn:(Ljava/lang/String;)V
      30: return

  public void warn(java.util.function.Supplier<java.lang.String>, java.lang.Throwable);
    Code:
       0: aload_0
       1: getfield      #2                  // Field log:Lorg/slf4j/Logger;
       4: invokeinterface #14,  1           // InterfaceMethod org/slf4j/Logger.isWarnEnabled:()Z
       9: ifeq          31
      12: aload_0
      13: getfield      #2                  // Field log:Lorg/slf4j/Logger;
      16: aload_1
      17: invokeinterface #4,  1            // InterfaceMethod java/util/function/Supplier.get:()Ljava/lang/Object;
      22: checkcast     #5                  // class java/lang/String
      25: aload_2
      26: invokeinterface #16,  3           // InterfaceMethod org/slf4j/Logger.warn:(Ljava/lang/String;Ljava/lang/Throwable;)V
      31: return

  public void trace(java.util.function.Supplier<java.lang.String>);
    Code:
       0: aload_0
       1: getfield      #2                  // Field log:Lorg/slf4j/Logger;
       4: invokeinterface #17,  1           // InterfaceMethod org/slf4j/Logger.isTraceEnabled:()Z
       9: ifeq          30
      12: aload_0
      13: getfield      #2                  // Field log:Lorg/slf4j/Logger;
      16: aload_1
      17: invokeinterface #4,  1            // InterfaceMethod java/util/function/Supplier.get:()Ljava/lang/Object;
      22: checkcast     #5                  // class java/lang/String
      25: invokeinterface #18,  2           // InterfaceMethod org/slf4j/Logger.trace:(Ljava/lang/String;)V
      30: return

  public void trace(java.util.function.Supplier<java.lang.String>, java.lang.Throwable);
    Code:
       0: aload_0
       1: getfield      #2                  // Field log:Lorg/slf4j/Logger;
       4: invokeinterface #17,  1           // InterfaceMethod org/slf4j/Logger.isTraceEnabled:()Z
       9: ifeq          31
      12: aload_0
      13: getfield      #2                  // Field log:Lorg/slf4j/Logger;
      16: aload_1
      17: invokeinterface #4,  1            // InterfaceMethod java/util/function/Supplier.get:()Ljava/lang/Object;
      22: checkcast     #5                  // class java/lang/String
      25: aload_2
      26: invokeinterface #19,  3           // InterfaceMethod org/slf4j/Logger.trace:(Ljava/lang/String;Ljava/lang/Throwable;)V
      31: return

  public boolean isLoggingLevelEnabled(java.lang.String);
    Code:
       0: aload_1
       1: invokestatic  #20                 // Method software/amazon/awssdk/utils/StringUtils.lowerCase:(Ljava/lang/String;)Ljava/lang/String;
       4: astore_2
       5: aload_2
       6: astore_3
       7: iconst_m1
       8: istore        4
      10: aload_3
      11: invokevirtual #21                 // Method java/lang/String.hashCode:()I
      14: lookupswitch  { // 5
               3237038: 109
               3641990: 124
              95458899: 64
              96784904: 94
             110620997: 79
               default: 136
          }
      64: aload_3
      65: ldc           #22                 // String debug
      67: invokevirtual #23                 // Method java/lang/String.equals:(Ljava/lang/Object;)Z
      70: ifeq          136
      73: iconst_0
      74: istore        4
      76: goto          136
      79: aload_3
      80: ldc           #24                 // String trace
      82: invokevirtual #23                 // Method java/lang/String.equals:(Ljava/lang/Object;)Z
      85: ifeq          136
      88: iconst_1
      89: istore        4
      91: goto          136
      94: aload_3
      95: ldc           #25                 // String error
      97: invokevirtual #23                 // Method java/lang/String.equals:(Ljava/lang/Object;)Z
     100: ifeq          136
     103: iconst_2
     104: istore        4
     106: goto          136
     109: aload_3
     110: ldc           #26                 // String info
     112: invokevirtual #23                 // Method java/lang/String.equals:(Ljava/lang/Object;)Z
     115: ifeq          136
     118: iconst_3
     119: istore        4
     121: goto          136
     124: aload_3
     125: ldc           #27                 // String warn
     127: invokevirtual #23                 // Method java/lang/String.equals:(Ljava/lang/Object;)Z
     130: ifeq          136
     133: iconst_4
     134: istore        4
     136: iload         4
     138: tableswitch   { // 0 to 4
                     0: 172
                     1: 182
                     2: 192
                     3: 202
                     4: 212
               default: 222
          }
     172: aload_0
     173: getfield      #2                  // Field log:Lorg/slf4j/Logger;
     176: invokeinterface #11,  1           // InterfaceMethod org/slf4j/Logger.isDebugEnabled:()Z
     181: ireturn
     182: aload_0
     183: getfield      #2                  // Field log:Lorg/slf4j/Logger;
     186: invokeinterface #17,  1           // InterfaceMethod org/slf4j/Logger.isTraceEnabled:()Z
     191: ireturn
     192: aload_0
     193: getfield      #2                  // Field log:Lorg/slf4j/Logger;
     196: invokeinterface #8,  1            // InterfaceMethod org/slf4j/Logger.isErrorEnabled:()Z
     201: ireturn
     202: aload_0
     203: getfield      #2                  // Field log:Lorg/slf4j/Logger;
     206: invokeinterface #3,  1            // InterfaceMethod org/slf4j/Logger.isInfoEnabled:()Z
     211: ireturn
     212: aload_0
     213: getfield      #2                  // Field log:Lorg/slf4j/Logger;
     216: invokeinterface #14,  1           // InterfaceMethod org/slf4j/Logger.isWarnEnabled:()Z
     221: ireturn
     222: new           #28                 // class java/lang/IllegalArgumentException
     225: dup
     226: new           #29                 // class java/lang/StringBuilder
     229: dup
     230: invokespecial #30                 // Method java/lang/StringBuilder."<init>":()V
     233: ldc           #31                 // String Unknown log level:
     235: invokevirtual #32                 // Method java/lang/StringBuilder.append:(Ljava/lang/String;)Ljava/lang/StringBuilder;
     238: aload_2
     239: invokevirtual #32                 // Method java/lang/StringBuilder.append:(Ljava/lang/String;)Ljava/lang/StringBuilder;
     242: invokevirtual #33                 // Method java/lang/StringBuilder.toString:()Ljava/lang/String;
     245: invokespecial #34                 // Method java/lang/IllegalArgumentException."<init>":(Ljava/lang/String;)V
     248: athrow

  public static software.amazon.awssdk.utils.Logger loggerFor(java.lang.Class<?>);
    Code:
       0: new           #35                 // class software/amazon/awssdk/utils/Logger
       3: dup
       4: aload_0
       5: invokestatic  #36                 // Method org/slf4j/LoggerFactory.getLogger:(Ljava/lang/Class;)Lorg/slf4j/Logger;
       8: invokespecial #37                 // Method "<init>":(Lorg/slf4j/Logger;)V
      11: areturn

  public static software.amazon.awssdk.utils.Logger loggerFor(java.lang.String);
    Code:
       0: new           #35                 // class software/amazon/awssdk/utils/Logger
       3: dup
       4: aload_0
       5: invokestatic  #38                 // Method org/slf4j/LoggerFactory.getLogger:(Ljava/lang/String;)Lorg/slf4j/Logger;
       8: invokespecial #37                 // Method "<init>":(Lorg/slf4j/Logger;)V
      11: areturn
}
