Compiled from "HttpServerParser.java"
public class brave.http.HttpServerParser extends brave.http.HttpParser {
  public brave.http.HttpServerParser();
    Code:
       0: aload_0
       1: invokespecial #9                  // Method brave/http/HttpParser."<init>":()V
       4: return

  public <Req> void request(brave.http.HttpAdapter<Req, ?>, Req, brave.SpanCustomizer);
    Code:
       0: aload_0
       1: aload_1
       2: aload_2
       3: aload_3
       4: invokespecial #16                 // Method brave/http/HttpParser.request:(Lbrave/http/HttpAdapter;Ljava/lang/Object;Lbrave/SpanCustomizer;)V
       7: return

  public <Resp> void response(brave.http.HttpAdapter<?, Resp>, Resp, java.lang.Throwable, brave.SpanCustomizer);
    Code:
       0: aload_0
       1: aload_1
       2: aload_2
       3: aload_3
       4: aload         4
       6: invokespecial #30                 // Method brave/http/HttpParser.response:(Lbrave/http/HttpAdapter;Ljava/lang/Object;Ljava/lang/Throwable;Lbrave/SpanCustomizer;)V
       9: return
}
