Compiled from "HttpTracing.java"
public final class brave.http.HttpTracing$Builder {
  brave.Tracing tracing;

  brave.http.HttpClientParser clientParser;

  java.lang.String serverName;

  brave.http.HttpServerParser serverParser;

  brave.http.HttpSampler clientSampler;

  brave.http.HttpSampler serverSampler;

  brave.http.HttpTracing$Builder(brave.Tracing);
    Code:
       0: aload_0
       1: invokespecial #28                 // Method java/lang/Object."<init>":()V
       4: aload_1
       5: ifnonnull     18
       8: new           #30                 // class java/lang/NullPointerException
      11: dup
      12: ldc           #32                 // String tracing == null
      14: invokespecial #35                 // Method java/lang/NullPointerException."<init>":(Ljava/lang/String;)V
      17: athrow
      18: aload_1
      19: invokevirtual #41                 // Method brave/Tracing.errorParser:()Lbrave/ErrorParser;
      22: astore_2
      23: aload_0
      24: aload_1
      25: putfield      #43                 // Field tracing:Lbrave/Tracing;
      28: aload_0
      29: ldc           #45                 // String
      31: putfield      #47                 // Field serverName:Ljava/lang/String;
      34: aload_0
      35: new           #12                 // class brave/http/HttpTracing$Builder$1
      38: dup
      39: aload_0
      40: aload_2
      41: invokespecial #50                 // Method brave/http/HttpTracing$Builder$1."<init>":(Lbrave/http/HttpTracing$Builder;Lbrave/ErrorParser;)V
      44: putfield      #52                 // Field clientParser:Lbrave/http/HttpClientParser;
      47: aload_0
      48: new           #10                 // class brave/http/HttpTracing$Builder$2
      51: dup
      52: aload_0
      53: aload_2
      54: invokespecial #53                 // Method brave/http/HttpTracing$Builder$2."<init>":(Lbrave/http/HttpTracing$Builder;Lbrave/ErrorParser;)V
      57: putfield      #55                 // Field serverParser:Lbrave/http/HttpServerParser;
      60: aload_0
      61: getstatic     #60                 // Field brave/http/HttpSampler.TRACE_ID:Lbrave/http/HttpSampler;
      64: putfield      #62                 // Field clientSampler:Lbrave/http/HttpSampler;
      67: aload_0
      68: getstatic     #60                 // Field brave/http/HttpSampler.TRACE_ID:Lbrave/http/HttpSampler;
      71: invokevirtual #65                 // Method serverSampler:(Lbrave/http/HttpSampler;)Lbrave/http/HttpTracing$Builder;
      74: pop
      75: return

  brave.http.HttpTracing$Builder(brave.http.HttpTracing);
    Code:
       0: aload_0
       1: invokespecial #28                 // Method java/lang/Object."<init>":()V
       4: aload_0
       5: aload_1
       6: getfield      #70                 // Field brave/http/HttpTracing.tracing:Lbrave/Tracing;
       9: putfield      #43                 // Field tracing:Lbrave/Tracing;
      12: aload_0
      13: aload_1
      14: getfield      #71                 // Field brave/http/HttpTracing.clientParser:Lbrave/http/HttpClientParser;
      17: putfield      #52                 // Field clientParser:Lbrave/http/HttpClientParser;
      20: aload_0
      21: aload_1
      22: getfield      #72                 // Field brave/http/HttpTracing.serverName:Ljava/lang/String;
      25: putfield      #47                 // Field serverName:Ljava/lang/String;
      28: aload_0
      29: aload_1
      30: getfield      #73                 // Field brave/http/HttpTracing.serverParser:Lbrave/http/HttpServerParser;
      33: putfield      #55                 // Field serverParser:Lbrave/http/HttpServerParser;
      36: aload_0
      37: aload_1
      38: getfield      #74                 // Field brave/http/HttpTracing.clientSampler:Lbrave/http/HttpSampler;
      41: putfield      #62                 // Field clientSampler:Lbrave/http/HttpSampler;
      44: aload_0
      45: aload_1
      46: getfield      #76                 // Field brave/http/HttpTracing.serverSampler:Lbrave/http/HttpSampler;
      49: putfield      #77                 // Field serverSampler:Lbrave/http/HttpSampler;
      52: return

  public brave.http.HttpTracing$Builder tracing(brave.Tracing);
    Code:
       0: aload_1
       1: ifnonnull     14
       4: new           #30                 // class java/lang/NullPointerException
       7: dup
       8: ldc           #32                 // String tracing == null
      10: invokespecial #35                 // Method java/lang/NullPointerException."<init>":(Ljava/lang/String;)V
      13: athrow
      14: aload_0
      15: aload_1
      16: putfield      #43                 // Field tracing:Lbrave/Tracing;
      19: aload_0
      20: areturn

  public brave.http.HttpTracing$Builder clientParser(brave.http.HttpClientParser);
    Code:
       0: aload_1
       1: ifnonnull     14
       4: new           #30                 // class java/lang/NullPointerException
       7: dup
       8: ldc           #83                 // String clientParser == null
      10: invokespecial #35                 // Method java/lang/NullPointerException."<init>":(Ljava/lang/String;)V
      13: athrow
      14: aload_0
      15: aload_1
      16: putfield      #52                 // Field clientParser:Lbrave/http/HttpClientParser;
      19: aload_0
      20: areturn

  brave.http.HttpTracing$Builder serverName(java.lang.String);
    Code:
       0: aload_1
       1: ifnonnull     14
       4: new           #30                 // class java/lang/NullPointerException
       7: dup
       8: ldc           #86                 // String serverName == null
      10: invokespecial #35                 // Method java/lang/NullPointerException."<init>":(Ljava/lang/String;)V
      13: athrow
      14: aload_0
      15: aload_1
      16: putfield      #47                 // Field serverName:Ljava/lang/String;
      19: aload_0
      20: areturn

  public brave.http.HttpTracing$Builder serverParser(brave.http.HttpServerParser);
    Code:
       0: aload_1
       1: ifnonnull     14
       4: new           #30                 // class java/lang/NullPointerException
       7: dup
       8: ldc           #89                 // String serverParser == null
      10: invokespecial #35                 // Method java/lang/NullPointerException."<init>":(Ljava/lang/String;)V
      13: athrow
      14: aload_0
      15: aload_1
      16: putfield      #55                 // Field serverParser:Lbrave/http/HttpServerParser;
      19: aload_0
      20: areturn

  public brave.http.HttpTracing$Builder clientSampler(brave.http.HttpSampler);
    Code:
       0: aload_1
       1: ifnonnull     14
       4: new           #30                 // class java/lang/NullPointerException
       7: dup
       8: ldc           #91                 // String clientSampler == null
      10: invokespecial #35                 // Method java/lang/NullPointerException."<init>":(Ljava/lang/String;)V
      13: athrow
      14: aload_0
      15: aload_1
      16: putfield      #62                 // Field clientSampler:Lbrave/http/HttpSampler;
      19: aload_0
      20: areturn

  public brave.http.HttpTracing$Builder serverSampler(brave.http.HttpSampler);
    Code:
       0: aload_1
       1: ifnonnull     14
       4: new           #30                 // class java/lang/NullPointerException
       7: dup
       8: ldc           #93                 // String serverSampler == null
      10: invokespecial #35                 // Method java/lang/NullPointerException."<init>":(Ljava/lang/String;)V
      13: athrow
      14: aload_0
      15: aload_1
      16: putfield      #77                 // Field serverSampler:Lbrave/http/HttpSampler;
      19: aload_0
      20: areturn

  public brave.http.HttpTracing build();
    Code:
       0: new           #7                  // class brave/http/HttpTracing
       3: dup
       4: aload_0
       5: invokespecial #98                 // Method brave/http/HttpTracing."<init>":(Lbrave/http/HttpTracing$Builder;)V
       8: areturn
}
