Compiled from "Catalog.scala"
public final class wvlet.airframe.sql.catalog.Catalog$ implements java.io.Serializable {
  public static final wvlet.airframe.sql.catalog.Catalog$Database$ Database;

  public static final wvlet.airframe.sql.catalog.Catalog$Table$ Table;

  public static final wvlet.airframe.sql.catalog.Catalog$TableSchema$ TableSchema;

  public static final wvlet.airframe.sql.catalog.Catalog$TableColumn$ TableColumn;

  public static final wvlet.airframe.sql.catalog.Catalog$CreateMode$ CreateMode;

  public static final wvlet.airframe.sql.catalog.Catalog$ MODULE$;

  private wvlet.airframe.sql.catalog.Catalog$();
    Code:
       0: aload_0
       1: invokespecial #50                 // Method java/lang/Object."<init>":()V
       4: return

  public static {};
    Code:
       0: new           #2                  // class wvlet/airframe/sql/catalog/Catalog$
       3: dup
       4: invokespecial #53                 // Method "<init>":()V
       7: putstatic     #55                 // Field MODULE$:Lwvlet/airframe/sql/catalog/Catalog$;
      10: return

  private java.lang.Object writeReplace();
    Code:
       0: new           #59                 // class scala/runtime/ModuleSerializationProxy
       3: dup
       4: ldc           #2                  // class wvlet/airframe/sql/catalog/Catalog$
       6: invokespecial #62                 // Method scala/runtime/ModuleSerializationProxy."<init>":(Ljava/lang/Class;)V
       9: areturn

  public wvlet.airframe.sql.catalog.Catalog$Table newTable(java.lang.String, java.lang.String, wvlet.airframe.sql.catalog.Catalog$TableSchema);
    Code:
       0: getstatic     #69                 // Field wvlet/airframe/sql/catalog/Catalog$Table$.MODULE$:Lwvlet/airframe/sql/catalog/Catalog$Table$;
       3: getstatic     #74                 // Field scala/Some$.MODULE$:Lscala/Some$;
       6: aload_1
       7: invokevirtual #78                 // Method scala/Some$.apply:(Ljava/lang/Object;)Lscala/Some;
      10: aload_2
      11: aload_3
      12: getstatic     #69                 // Field wvlet/airframe/sql/catalog/Catalog$Table$.MODULE$:Lwvlet/airframe/sql/catalog/Catalog$Table$;
      15: invokevirtual #82                 // Method wvlet/airframe/sql/catalog/Catalog$Table$.$lessinit$greater$default$4:()Ljava/lang/String;
      18: getstatic     #69                 // Field wvlet/airframe/sql/catalog/Catalog$Table$.MODULE$:Lwvlet/airframe/sql/catalog/Catalog$Table$;
      21: invokevirtual #86                 // Method wvlet/airframe/sql/catalog/Catalog$Table$.$lessinit$greater$default$5:()Lscala/collection/immutable/Map;
      24: invokevirtual #89                 // Method wvlet/airframe/sql/catalog/Catalog$Table$.apply:(Lscala/Option;Ljava/lang/String;Lwvlet/airframe/sql/catalog/Catalog$TableSchema;Ljava/lang/String;Lscala/collection/immutable/Map;)Lwvlet/airframe/sql/catalog/Catalog$Table;
      27: areturn

  public wvlet.airframe.sql.catalog.Catalog$TableSchema newSchema();
    Code:
       0: getstatic     #95                 // Field wvlet/airframe/sql/catalog/Catalog$TableSchema$.MODULE$:Lwvlet/airframe/sql/catalog/Catalog$TableSchema$;
       3: getstatic     #100                // Field scala/package$.MODULE$:Lscala/package$;
       6: invokevirtual #104                // Method scala/package$.Seq:()Lscala/collection/immutable/Seq$;
       9: invokevirtual #110                // Method scala/collection/immutable/Seq$.empty:()Lscala/collection/SeqOps;
      12: checkcast     #112                // class scala/collection/immutable/Seq
      15: invokevirtual #115                // Method wvlet/airframe/sql/catalog/Catalog$TableSchema$.apply:(Lscala/collection/immutable/Seq;)Lwvlet/airframe/sql/catalog/Catalog$TableSchema;
      18: areturn
}
