Compiled from "Catalog.scala"
public class wvlet.airframe.sql.catalog.Catalog$TableSchema implements scala.Product,java.io.Serializable {
  private final scala.collection.immutable.Seq columns;

  public static wvlet.airframe.sql.catalog.Catalog$TableSchema apply(scala.collection.immutable.Seq<wvlet.airframe.sql.catalog.Catalog$TableColumn>);
    Code:
       0: getstatic     #30                 // Field wvlet/airframe/sql/catalog/Catalog$TableSchema$.MODULE$:Lwvlet/airframe/sql/catalog/Catalog$TableSchema$;
       3: aload_0
       4: invokevirtual #32                 // Method wvlet/airframe/sql/catalog/Catalog$TableSchema$.apply:(Lscala/collection/immutable/Seq;)Lwvlet/airframe/sql/catalog/Catalog$TableSchema;
       7: areturn

  public static wvlet.airframe.sql.catalog.Catalog$TableSchema fromProduct(scala.Product);
    Code:
       0: getstatic     #30                 // Field wvlet/airframe/sql/catalog/Catalog$TableSchema$.MODULE$:Lwvlet/airframe/sql/catalog/Catalog$TableSchema$;
       3: aload_0
       4: invokevirtual #36                 // Method wvlet/airframe/sql/catalog/Catalog$TableSchema$.fromProduct:(Lscala/Product;)Lwvlet/airframe/sql/catalog/Catalog$TableSchema;
       7: areturn

  public static wvlet.airframe.sql.catalog.Catalog$TableSchema unapply(wvlet.airframe.sql.catalog.Catalog$TableSchema);
    Code:
       0: getstatic     #30                 // Field wvlet/airframe/sql/catalog/Catalog$TableSchema$.MODULE$:Lwvlet/airframe/sql/catalog/Catalog$TableSchema$;
       3: aload_0
       4: invokevirtual #40                 // Method wvlet/airframe/sql/catalog/Catalog$TableSchema$.unapply:(Lwvlet/airframe/sql/catalog/Catalog$TableSchema;)Lwvlet/airframe/sql/catalog/Catalog$TableSchema;
       7: areturn

  public wvlet.airframe.sql.catalog.Catalog$TableSchema(scala.collection.immutable.Seq<wvlet.airframe.sql.catalog.Catalog$TableColumn>);
    Code:
       0: aload_0
       1: aload_1
       2: putfield      #45                 // Field columns:Lscala/collection/immutable/Seq;
       5: aload_0
       6: invokespecial #48                 // Method java/lang/Object."<init>":()V
       9: return

  public scala.collection.Iterator productIterator();
    Code:
       0: aload_0
       1: invokestatic  #56                 // InterfaceMethod scala/Product.productIterator$:(Lscala/Product;)Lscala/collection/Iterator;
       4: areturn

  public scala.collection.Iterator productElementNames();
    Code:
       0: aload_0
       1: invokestatic  #60                 // InterfaceMethod scala/Product.productElementNames$:(Lscala/Product;)Lscala/collection/Iterator;
       4: areturn

  public int hashCode();
    Code:
       0: getstatic     #67                 // Field scala/runtime/ScalaRunTime$.MODULE$:Lscala/runtime/ScalaRunTime$;
       3: aload_0
       4: invokevirtual #71                 // Method scala/runtime/ScalaRunTime$._hashCode:(Lscala/Product;)I
       7: ireturn

  public boolean equals(java.lang.Object);
    Code:
       0: aload_0
       1: aload_1
       2: if_acmpeq     73
       5: aload_1
       6: astore_2
       7: aload_2
       8: instanceof    #2                  // class wvlet/airframe/sql/catalog/Catalog$TableSchema
      11: ifeq          66
      14: aload_2
      15: checkcast     #2                  // class wvlet/airframe/sql/catalog/Catalog$TableSchema
      18: astore_3
      19: aload_0
      20: invokevirtual #77                 // Method columns:()Lscala/collection/immutable/Seq;
      23: aload_3
      24: invokevirtual #77                 // Method columns:()Lscala/collection/immutable/Seq;
      27: astore        4
      29: dup
      30: ifnonnull     42
      33: pop
      34: aload         4
      36: ifnull        50
      39: goto          62
      42: aload         4
      44: invokevirtual #79                 // Method java/lang/Object.equals:(Ljava/lang/Object;)Z
      47: ifeq          62
      50: aload_3
      51: aload_0
      52: invokevirtual #82                 // Method canEqual:(Ljava/lang/Object;)Z
      55: ifeq          62
      58: iconst_1
      59: goto          63
      62: iconst_0
      63: goto          70
      66: iconst_0
      67: goto          70
      70: ifeq          77
      73: iconst_1
      74: goto          78
      77: iconst_0
      78: ireturn

  public java.lang.String toString();
    Code:
       0: getstatic     #67                 // Field scala/runtime/ScalaRunTime$.MODULE$:Lscala/runtime/ScalaRunTime$;
       3: aload_0
       4: invokevirtual #91                 // Method scala/runtime/ScalaRunTime$._toString:(Lscala/Product;)Ljava/lang/String;
       7: areturn

  public boolean canEqual(java.lang.Object);
    Code:
       0: aload_1
       1: instanceof    #2                  // class wvlet/airframe/sql/catalog/Catalog$TableSchema
       4: ireturn

  public int productArity();
    Code:
       0: iconst_1
       1: ireturn

  public java.lang.String productPrefix();
    Code:
       0: ldc           #95                 // String TableSchema
       2: areturn

  public java.lang.Object productElement(int);
    Code:
       0: iload_1
       1: istore_2
       2: iconst_0
       3: iload_2
       4: if_icmpne     12
       7: aload_0
       8: invokevirtual #101                // Method _1:()Lscala/collection/immutable/Seq;
      11: areturn
      12: new           #103                // class java/lang/IndexOutOfBoundsException
      15: dup
      16: iload_1
      17: invokestatic  #109                // Method scala/runtime/BoxesRunTime.boxToInteger:(I)Ljava/lang/Integer;
      20: invokevirtual #113                // Method java/lang/Integer.toString:()Ljava/lang/String;
      23: invokespecial #116                // Method java/lang/IndexOutOfBoundsException."<init>":(Ljava/lang/String;)V
      26: athrow

  public java.lang.String productElementName(int);
    Code:
       0: iload_1
       1: istore_2
       2: iconst_0
       3: iload_2
       4: if_icmpne     10
       7: ldc           #120                // String columns
       9: areturn
      10: new           #103                // class java/lang/IndexOutOfBoundsException
      13: dup
      14: iload_1
      15: invokestatic  #109                // Method scala/runtime/BoxesRunTime.boxToInteger:(I)Ljava/lang/Integer;
      18: invokevirtual #113                // Method java/lang/Integer.toString:()Ljava/lang/String;
      21: invokespecial #116                // Method java/lang/IndexOutOfBoundsException."<init>":(Ljava/lang/String;)V
      24: athrow

  public scala.collection.immutable.Seq<wvlet.airframe.sql.catalog.Catalog$TableColumn> columns();
    Code:
       0: aload_0
       1: getfield      #45                 // Field columns:Lscala/collection/immutable/Seq;
       4: areturn

  public wvlet.airframe.sql.catalog.Catalog$TableSchema addColumn(wvlet.airframe.sql.catalog.Catalog$TableColumn);
    Code:
       0: aload_0
       1: aload_0
       2: invokevirtual #77                 // Method columns:()Lscala/collection/immutable/Seq;
       5: aload_1
       6: invokeinterface #128,  2          // InterfaceMethod scala/collection/immutable/Seq.$colon$plus:(Ljava/lang/Object;)Ljava/lang/Object;
      11: checkcast     #85                 // class scala/collection/immutable/Seq
      14: invokevirtual #131                // Method copy:(Lscala/collection/immutable/Seq;)Lwvlet/airframe/sql/catalog/Catalog$TableSchema;
      17: areturn

  public wvlet.airframe.sql.catalog.Catalog$TableSchema addColumn(java.lang.String, wvlet.airframe.sql.catalog.DataType, scala.collection.immutable.Map<java.lang.String, java.lang.Object>);
    Code:
       0: aload_0
       1: aload_0
       2: invokevirtual #77                 // Method columns:()Lscala/collection/immutable/Seq;
       5: getstatic     #140                // Field wvlet/airframe/sql/catalog/Catalog$TableColumn$.MODULE$:Lwvlet/airframe/sql/catalog/Catalog$TableColumn$;
       8: aload_1
       9: aload_2
      10: aload_3
      11: invokevirtual #143                // Method wvlet/airframe/sql/catalog/Catalog$TableColumn$.apply:(Ljava/lang/String;Lwvlet/airframe/sql/catalog/DataType;Lscala/collection/immutable/Map;)Lwvlet/airframe/sql/catalog/Catalog$TableColumn;
      14: invokeinterface #128,  2          // InterfaceMethod scala/collection/immutable/Seq.$colon$plus:(Ljava/lang/Object;)Ljava/lang/Object;
      19: checkcast     #85                 // class scala/collection/immutable/Seq
      22: invokevirtual #131                // Method copy:(Lscala/collection/immutable/Seq;)Lwvlet/airframe/sql/catalog/Catalog$TableSchema;
      25: areturn

  public scala.collection.immutable.Map<java.lang.String, java.lang.Object> addColumn$default$3();
    Code:
       0: getstatic     #154                // Field scala/Predef$.MODULE$:Lscala/Predef$;
       3: invokevirtual #158                // Method scala/Predef$.Map:()Lscala/collection/immutable/Map$;
       6: invokevirtual #163                // Method scala/collection/immutable/Map$.empty:()Lscala/collection/immutable/Map;
       9: areturn

  public wvlet.airframe.sql.catalog.Catalog$TableSchema copy(scala.collection.immutable.Seq<wvlet.airframe.sql.catalog.Catalog$TableColumn>);
    Code:
       0: new           #2                  // class wvlet/airframe/sql/catalog/Catalog$TableSchema
       3: dup
       4: aload_1
       5: invokespecial #165                // Method "<init>":(Lscala/collection/immutable/Seq;)V
       8: areturn

  public scala.collection.immutable.Seq<wvlet.airframe.sql.catalog.Catalog$TableColumn> copy$default$1();
    Code:
       0: aload_0
       1: invokevirtual #77                 // Method columns:()Lscala/collection/immutable/Seq;
       4: areturn

  public scala.collection.immutable.Seq<wvlet.airframe.sql.catalog.Catalog$TableColumn> _1();
    Code:
       0: aload_0
       1: invokevirtual #77                 // Method columns:()Lscala/collection/immutable/Seq;
       4: areturn
}
