Compiled from "DataType.scala"
public class wvlet.airframe.sql.catalog.DataType$RecordType extends wvlet.airframe.sql.catalog.DataType implements scala.Product,java.io.Serializable {
  private final scala.collection.immutable.Seq elems;

  public static wvlet.airframe.sql.catalog.DataType$RecordType apply(scala.collection.immutable.Seq<wvlet.airframe.sql.catalog.DataType>);
    Code:
       0: getstatic     #22                 // Field wvlet/airframe/sql/catalog/DataType$RecordType$.MODULE$:Lwvlet/airframe/sql/catalog/DataType$RecordType$;
       3: aload_0
       4: invokevirtual #24                 // Method wvlet/airframe/sql/catalog/DataType$RecordType$.apply:(Lscala/collection/immutable/Seq;)Lwvlet/airframe/sql/catalog/DataType$RecordType;
       7: areturn

  public static wvlet.airframe.sql.catalog.DataType$RecordType fromProduct(scala.Product);
    Code:
       0: getstatic     #22                 // Field wvlet/airframe/sql/catalog/DataType$RecordType$.MODULE$:Lwvlet/airframe/sql/catalog/DataType$RecordType$;
       3: aload_0
       4: invokevirtual #28                 // Method wvlet/airframe/sql/catalog/DataType$RecordType$.fromProduct:(Lscala/Product;)Lwvlet/airframe/sql/catalog/DataType$RecordType;
       7: areturn

  public static wvlet.airframe.sql.catalog.DataType$RecordType unapply(wvlet.airframe.sql.catalog.DataType$RecordType);
    Code:
       0: getstatic     #22                 // Field wvlet/airframe/sql/catalog/DataType$RecordType$.MODULE$:Lwvlet/airframe/sql/catalog/DataType$RecordType$;
       3: aload_0
       4: invokevirtual #32                 // Method wvlet/airframe/sql/catalog/DataType$RecordType$.unapply:(Lwvlet/airframe/sql/catalog/DataType$RecordType;)Lwvlet/airframe/sql/catalog/DataType$RecordType;
       7: areturn

  public wvlet.airframe.sql.catalog.DataType$RecordType(scala.collection.immutable.Seq<wvlet.airframe.sql.catalog.DataType>);
    Code:
       0: aload_0
       1: aload_1
       2: putfield      #37                 // Field elems:Lscala/collection/immutable/Seq;
       5: aload_0
       6: ldc           #39                 // String record
       8: aload_1
       9: invokespecial #42                 // Method wvlet/airframe/sql/catalog/DataType."<init>":(Ljava/lang/String;Lscala/collection/immutable/Seq;)V
      12: return

  public scala.collection.Iterator productIterator();
    Code:
       0: aload_0
       1: invokestatic  #50                 // InterfaceMethod scala/Product.productIterator$:(Lscala/Product;)Lscala/collection/Iterator;
       4: areturn

  public scala.collection.Iterator productElementNames();
    Code:
       0: aload_0
       1: invokestatic  #54                 // InterfaceMethod scala/Product.productElementNames$:(Lscala/Product;)Lscala/collection/Iterator;
       4: areturn

  public int hashCode();
    Code:
       0: getstatic     #61                 // Field scala/runtime/ScalaRunTime$.MODULE$:Lscala/runtime/ScalaRunTime$;
       3: aload_0
       4: invokevirtual #65                 // Method scala/runtime/ScalaRunTime$._hashCode:(Lscala/Product;)I
       7: ireturn

  public boolean equals(java.lang.Object);
    Code:
       0: aload_0
       1: aload_1
       2: if_acmpeq     73
       5: aload_1
       6: astore_2
       7: aload_2
       8: instanceof    #2                  // class wvlet/airframe/sql/catalog/DataType$RecordType
      11: ifeq          66
      14: aload_2
      15: checkcast     #2                  // class wvlet/airframe/sql/catalog/DataType$RecordType
      18: astore_3
      19: aload_0
      20: invokevirtual #71                 // Method elems:()Lscala/collection/immutable/Seq;
      23: aload_3
      24: invokevirtual #71                 // Method elems:()Lscala/collection/immutable/Seq;
      27: astore        4
      29: dup
      30: ifnonnull     42
      33: pop
      34: aload         4
      36: ifnull        50
      39: goto          62
      42: aload         4
      44: invokevirtual #75                 // Method java/lang/Object.equals:(Ljava/lang/Object;)Z
      47: ifeq          62
      50: aload_3
      51: aload_0
      52: invokevirtual #78                 // Method canEqual:(Ljava/lang/Object;)Z
      55: ifeq          62
      58: iconst_1
      59: goto          63
      62: iconst_0
      63: goto          70
      66: iconst_0
      67: goto          70
      70: ifeq          77
      73: iconst_1
      74: goto          78
      77: iconst_0
      78: ireturn

  public boolean canEqual(java.lang.Object);
    Code:
       0: aload_1
       1: instanceof    #2                  // class wvlet/airframe/sql/catalog/DataType$RecordType
       4: ireturn

  public int productArity();
    Code:
       0: iconst_1
       1: ireturn

  public java.lang.String productPrefix();
    Code:
       0: ldc           #86                 // String RecordType
       2: areturn

  public java.lang.Object productElement(int);
    Code:
       0: iload_1
       1: istore_2
       2: iconst_0
       3: iload_2
       4: if_icmpne     12
       7: aload_0
       8: invokevirtual #92                 // Method _1:()Lscala/collection/immutable/Seq;
      11: areturn
      12: new           #94                 // class java/lang/IndexOutOfBoundsException
      15: dup
      16: iload_1
      17: invokestatic  #100                // Method scala/runtime/BoxesRunTime.boxToInteger:(I)Ljava/lang/Integer;
      20: invokevirtual #105                // Method java/lang/Integer.toString:()Ljava/lang/String;
      23: invokespecial #108                // Method java/lang/IndexOutOfBoundsException."<init>":(Ljava/lang/String;)V
      26: athrow

  public java.lang.String productElementName(int);
    Code:
       0: iload_1
       1: istore_2
       2: iconst_0
       3: iload_2
       4: if_icmpne     10
       7: ldc           #112                // String elems
       9: areturn
      10: new           #94                 // class java/lang/IndexOutOfBoundsException
      13: dup
      14: iload_1
      15: invokestatic  #100                // Method scala/runtime/BoxesRunTime.boxToInteger:(I)Ljava/lang/Integer;
      18: invokevirtual #105                // Method java/lang/Integer.toString:()Ljava/lang/String;
      21: invokespecial #108                // Method java/lang/IndexOutOfBoundsException."<init>":(Ljava/lang/String;)V
      24: athrow

  public scala.collection.immutable.Seq<wvlet.airframe.sql.catalog.DataType> elems();
    Code:
       0: aload_0
       1: getfield      #37                 // Field elems:Lscala/collection/immutable/Seq;
       4: areturn

  public wvlet.airframe.sql.catalog.DataType$RecordType copy(scala.collection.immutable.Seq<wvlet.airframe.sql.catalog.DataType>);
    Code:
       0: new           #2                  // class wvlet/airframe/sql/catalog/DataType$RecordType
       3: dup
       4: aload_1
       5: invokespecial #116                // Method "<init>":(Lscala/collection/immutable/Seq;)V
       8: areturn

  public scala.collection.immutable.Seq<wvlet.airframe.sql.catalog.DataType> copy$default$1();
    Code:
       0: aload_0
       1: invokevirtual #71                 // Method elems:()Lscala/collection/immutable/Seq;
       4: areturn

  public scala.collection.immutable.Seq<wvlet.airframe.sql.catalog.DataType> _1();
    Code:
       0: aload_0
       1: invokevirtual #71                 // Method elems:()Lscala/collection/immutable/Seq;
       4: areturn
}
