Compiled from "JsonValueReader.scala"
public final class org.scalatra.json.JsonValueReader$$anonfun$read$2 extends scala.runtime.AbstractFunction0<scala.util.Right<scala.runtime.Nothing$, scala.Option<org.json4s.JsonAST$JValue>>> implements scala.Serializable {
  public static final long serialVersionUID;

  private final org.scalatra.json.JsonValueReader $outer;

  private final java.lang.String key$1;

  public final scala.util.Right<scala.runtime.Nothing$, scala.Option<org.json4s.JsonAST$JValue>> apply();
    Code:
       0: getstatic     #29                 // Field scala/package$.MODULE$:Lscala/package$;
       3: invokevirtual #33                 // Method scala/package$.Right:()Lscala/util/Right$;
       6: aload_0
       7: getfield      #35                 // Field $outer:Lorg/scalatra/json/JsonValueReader;
      10: aload_0
      11: getfield      #37                 // Field key$1:Ljava/lang/String;
      14: aload_0
      15: getfield      #35                 // Field $outer:Lorg/scalatra/json/JsonValueReader;
      18: invokevirtual #41                 // Method org/scalatra/json/JsonValueReader.readPath$default$2:()Lorg/json4s/JsonAST$JValue;
      21: invokevirtual #45                 // Method org/scalatra/json/JsonValueReader.readPath:(Ljava/lang/String;Lorg/json4s/JsonAST$JValue;)Lscala/Option;
      24: invokevirtual #50                 // Method scala/util/Right$.apply:(Ljava/lang/Object;)Lscala/util/Right;
      27: areturn

  public final java.lang.Object apply();
    Code:
       0: aload_0
       1: invokevirtual #55                 // Method apply:()Lscala/util/Right;
       4: areturn

  public org.scalatra.json.JsonValueReader$$anonfun$read$2(org.scalatra.json.JsonValueReader, java.lang.String);
    Code:
       0: aload_1
       1: ifnonnull     6
       4: aconst_null
       5: athrow
       6: aload_0
       7: aload_1
       8: putfield      #35                 // Field $outer:Lorg/scalatra/json/JsonValueReader;
      11: aload_0
      12: aload_2
      13: putfield      #37                 // Field key$1:Ljava/lang/String;
      16: aload_0
      17: invokespecial #60                 // Method scala/runtime/AbstractFunction0."<init>":()V
      20: return
}
