Compiled from "JValueResult.scala"
public final class org.scalatra.json.JValueResult$$anonfun$org$scalatra$json$JValueResult$$renderToJson$1 extends scala.runtime.AbstractPartialFunction<java.lang.Object, java.lang.Object> implements scala.Serializable {
  public static final long serialVersionUID;

  private final org.scalatra.json.JValueResult $outer;

  public final <A1, B1> B1 applyOrElse(A1, scala.Function1<A1, B1>);
    Code:
       0: iconst_0
       1: istore_3
       2: aconst_null
       3: astore        4
       5: aload_1
       6: astore        5
       8: getstatic     #24                 // Field org/json4s/package$.MODULE$:Lorg/json4s/package$;
      11: invokevirtual #28                 // Method org/json4s/package$.JNothing:()Lorg/json4s/JsonAST$JNothing$;
      14: aload         5
      16: astore        6
      18: dup
      19: ifnonnull     31
      22: pop
      23: aload         6
      25: ifnull        39
      28: goto          47
      31: aload         6
      33: invokevirtual #34                 // Method java/lang/Object.equals:(Ljava/lang/Object;)Z
      36: ifeq          47
      39: getstatic     #40                 // Field scala/runtime/BoxedUnit.UNIT:Lscala/runtime/BoxedUnit;
      42: astore        7
      44: goto          1003
      47: getstatic     #24                 // Field org/json4s/package$.MODULE$:Lorg/json4s/package$;
      50: invokevirtual #44                 // Method org/json4s/package$.JNull:()Lorg/json4s/JsonAST$JNull$;
      53: aload         5
      55: astore        8
      57: dup
      58: ifnonnull     70
      61: pop
      62: aload         8
      64: ifnull        78
      67: goto          112
      70: aload         8
      72: invokevirtual #34                 // Method java/lang/Object.equals:(Ljava/lang/Object;)Z
      75: ifeq          112
      78: aload_0
      79: getfield      #46                 // Field $outer:Lorg/scalatra/json/JValueResult;
      82: aload_0
      83: getfield      #46                 // Field $outer:Lorg/scalatra/json/JValueResult;
      86: invokeinterface #50,  1           // InterfaceMethod org/scalatra/json/JValueResult.response:()Ljavax/servlet/http/HttpServletResponse;
      91: invokeinterface #54,  2           // InterfaceMethod org/scalatra/json/JValueResult.enrichResponse:(Ljavax/servlet/http/HttpServletResponse;)Lorg/scalatra/servlet/RichResponse;
      96: invokevirtual #60                 // Method org/scalatra/servlet/RichResponse.writer:()Ljava/io/PrintWriter;
      99: ldc           #62                 // String null
     101: invokevirtual #68                 // Method java/io/PrintWriter.write:(Ljava/lang/String;)V
     104: getstatic     #40                 // Field scala/runtime/BoxedUnit.UNIT:Lscala/runtime/BoxedUnit;
     107: astore        7
     109: goto          1003
     112: aload         5
     114: instanceof    #70                 // class org/json4s/JsonAST$JValue
     117: ifeq          148
     120: aload         5
     122: checkcast     #70                 // class org/json4s/JsonAST$JValue
     125: astore        9
     127: aload_0
     128: getfield      #46                 // Field $outer:Lorg/scalatra/json/JValueResult;
     131: invokeinterface #74,  1           // InterfaceMethod org/scalatra/json/JValueResult.org$scalatra$json$JValueResult$$super$renderPipeline:()Lscala/PartialFunction;
     136: aload         9
     138: invokeinterface #80,  2           // InterfaceMethod scala/PartialFunction.apply:(Ljava/lang/Object;)Ljava/lang/Object;
     143: astore        7
     145: goto          1003
     148: aload         5
     150: instanceof    #30                 // class java/lang/Object
     153: ifeq          298
     156: aload         5
     158: astore        10
     160: aload_0
     161: getfield      #46                 // Field $outer:Lorg/scalatra/json/JValueResult;
     164: invokestatic  #86                 // Method org/scalatra/json/JValueResult$class.org$scalatra$json$JValueResult$$isJValueResponse:(Lorg/scalatra/json/JValueResult;)Z
     167: ifeq          298
     170: aload_0
     171: getfield      #46                 // Field $outer:Lorg/scalatra/json/JValueResult;
     174: invokestatic  #90                 // Method org/scalatra/json/JValueResult$class.org$scalatra$json$JValueResult$$customSerializer:(Lorg/scalatra/json/JValueResult;)Lscala/PartialFunction;
     177: aload         10
     179: invokeinterface #93,  2           // InterfaceMethod scala/PartialFunction.isDefinedAt:(Ljava/lang/Object;)Z
     184: ifeq          298
     187: aload_0
     188: getfield      #46                 // Field $outer:Lorg/scalatra/json/JValueResult;
     191: invokestatic  #90                 // Method org/scalatra/json/JValueResult$class.org$scalatra$json$JValueResult$$customSerializer:(Lorg/scalatra/json/JValueResult;)Lscala/PartialFunction;
     194: invokeinterface #97,  1           // InterfaceMethod scala/PartialFunction.lift:()Lscala/Function1;
     199: aload         10
     201: invokeinterface #100,  2          // InterfaceMethod scala/Function1.apply:(Ljava/lang/Object;)Ljava/lang/Object;
     206: checkcast     #102                // class scala/Option
     209: astore        11
     211: aload         11
     213: instanceof    #104                // class scala/Some
     216: ifeq          252
     219: aload         11
     221: checkcast     #104                // class scala/Some
     224: astore        12
     226: aload         12
     228: invokevirtual #108                // Method scala/Some.x:()Ljava/lang/Object;
     231: checkcast     #70                 // class org/json4s/JsonAST$JValue
     234: astore        13
     236: aload         13
     238: ifnull        252
     241: aload         13
     243: astore        14
     245: aload         14
     247: astore        15
     249: goto          281
     252: getstatic     #113                // Field scala/None$.MODULE$:Lscala/None$;
     255: aload         11
     257: invokevirtual #34                 // Method java/lang/Object.equals:(Ljava/lang/Object;)Z
     260: ifeq          288
     263: aload_0
     264: getfield      #46                 // Field $outer:Lorg/scalatra/json/JValueResult;
     267: invokeinterface #74,  1           // InterfaceMethod org/scalatra/json/JValueResult.org$scalatra$json$JValueResult$$super$renderPipeline:()Lscala/PartialFunction;
     272: aload         10
     274: invokeinterface #80,  2           // InterfaceMethod scala/PartialFunction.apply:(Ljava/lang/Object;)Ljava/lang/Object;
     279: astore        15
     281: aload         15
     283: astore        7
     285: goto          1003
     288: new           #115                // class scala/MatchError
     291: dup
     292: aload         11
     294: invokespecial #119                // Method scala/MatchError."<init>":(Ljava/lang/Object;)V
     297: athrow
     298: aload         5
     300: instanceof    #121                // class java/lang/Integer
     303: ifeq          337
     306: aload         5
     308: invokestatic  #127                // Method scala/runtime/BoxesRunTime.unboxToInt:(Ljava/lang/Object;)I
     311: istore        16
     313: aload_0
     314: getfield      #46                 // Field $outer:Lorg/scalatra/json/JValueResult;
     317: invokeinterface #74,  1           // InterfaceMethod org/scalatra/json/JValueResult.org$scalatra$json$JValueResult$$super$renderPipeline:()Lscala/PartialFunction;
     322: iload         16
     324: invokestatic  #131                // Method scala/runtime/BoxesRunTime.boxToInteger:(I)Ljava/lang/Integer;
     327: invokeinterface #80,  2           // InterfaceMethod scala/PartialFunction.apply:(Ljava/lang/Object;)Ljava/lang/Object;
     332: astore        7
     334: goto          1003
     337: aload         5
     339: instanceof    #133                // class "[B"
     342: ifeq          373
     345: aload         5
     347: checkcast     #133                // class "[B"
     350: astore        17
     352: aload_0
     353: getfield      #46                 // Field $outer:Lorg/scalatra/json/JValueResult;
     356: invokeinterface #74,  1           // InterfaceMethod org/scalatra/json/JValueResult.org$scalatra$json$JValueResult$$super$renderPipeline:()Lscala/PartialFunction;
     361: aload         17
     363: invokeinterface #80,  2           // InterfaceMethod scala/PartialFunction.apply:(Ljava/lang/Object;)Ljava/lang/Object;
     368: astore        7
     370: goto          1003
     373: aload         5
     375: instanceof    #135                // class java/io/InputStream
     378: ifeq          409
     381: aload         5
     383: checkcast     #135                // class java/io/InputStream
     386: astore        18
     388: aload_0
     389: getfield      #46                 // Field $outer:Lorg/scalatra/json/JValueResult;
     392: invokeinterface #74,  1           // InterfaceMethod org/scalatra/json/JValueResult.org$scalatra$json$JValueResult$$super$renderPipeline:()Lscala/PartialFunction;
     397: aload         18
     399: invokeinterface #80,  2           // InterfaceMethod scala/PartialFunction.apply:(Ljava/lang/Object;)Ljava/lang/Object;
     404: astore        7
     406: goto          1003
     409: aload         5
     411: instanceof    #137                // class java/io/File
     414: ifeq          445
     417: aload         5
     419: checkcast     #137                // class java/io/File
     422: astore        19
     424: aload_0
     425: getfield      #46                 // Field $outer:Lorg/scalatra/json/JValueResult;
     428: invokeinterface #74,  1           // InterfaceMethod org/scalatra/json/JValueResult.org$scalatra$json$JValueResult$$super$renderPipeline:()Lscala/PartialFunction;
     433: aload         19
     435: invokeinterface #80,  2           // InterfaceMethod scala/PartialFunction.apply:(Ljava/lang/Object;)Ljava/lang/Object;
     440: astore        7
     442: goto          1003
     445: aload         5
     447: instanceof    #139                // class org/scalatra/ActionResult
     450: ifeq          481
     453: aload         5
     455: checkcast     #139                // class org/scalatra/ActionResult
     458: astore        20
     460: aload_0
     461: getfield      #46                 // Field $outer:Lorg/scalatra/json/JValueResult;
     464: invokeinterface #74,  1           // InterfaceMethod org/scalatra/json/JValueResult.org$scalatra$json$JValueResult$$super$renderPipeline:()Lscala/PartialFunction;
     469: aload         20
     471: invokeinterface #80,  2           // InterfaceMethod scala/PartialFunction.apply:(Ljava/lang/Object;)Ljava/lang/Object;
     476: astore        7
     478: goto          1003
     481: aload         5
     483: instanceof    #36                 // class scala/runtime/BoxedUnit
     486: ifeq          495
     489: iconst_1
     490: istore        21
     492: goto          526
     495: getstatic     #144                // Field scala/Unit$.MODULE$:Lscala/Unit$;
     498: aload         5
     500: invokevirtual #34                 // Method java/lang/Object.equals:(Ljava/lang/Object;)Z
     503: ifeq          512
     506: iconst_1
     507: istore        21
     509: goto          526
     512: aload         5
     514: ifnonnull     523
     517: iconst_1
     518: istore        21
     520: goto          526
     523: iconst_0
     524: istore        21
     526: iload         21
     528: ifeq          539
     531: getstatic     #40                 // Field scala/runtime/BoxedUnit.UNIT:Lscala/runtime/BoxedUnit;
     534: astore        7
     536: goto          1003
     539: aload         5
     541: instanceof    #146                // class java/lang/String
     544: ifeq          575
     547: aload         5
     549: checkcast     #146                // class java/lang/String
     552: astore        22
     554: aload_0
     555: getfield      #46                 // Field $outer:Lorg/scalatra/json/JValueResult;
     558: invokeinterface #74,  1           // InterfaceMethod org/scalatra/json/JValueResult.org$scalatra$json$JValueResult$$super$renderPipeline:()Lscala/PartialFunction;
     563: aload         22
     565: invokeinterface #80,  2           // InterfaceMethod scala/PartialFunction.apply:(Ljava/lang/Object;)Ljava/lang/Object;
     570: astore        7
     572: goto          1003
     575: aload         5
     577: instanceof    #148                // class scala/xml/Node
     580: ifeq          719
     583: aload         5
     585: checkcast     #148                // class scala/xml/Node
     588: astore        23
     590: aload_0
     591: getfield      #46                 // Field $outer:Lorg/scalatra/json/JValueResult;
     594: checkcast     #150                // class org/scalatra/ApiFormats
     597: aload_0
     598: getfield      #46                 // Field $outer:Lorg/scalatra/json/JValueResult;
     601: invokeinterface #154,  1          // InterfaceMethod org/scalatra/json/JValueResult.request:()Ljavax/servlet/http/HttpServletRequest;
     606: aload_0
     607: getfield      #46                 // Field $outer:Lorg/scalatra/json/JValueResult;
     610: invokeinterface #50,  1           // InterfaceMethod org/scalatra/json/JValueResult.response:()Ljavax/servlet/http/HttpServletResponse;
     615: invokeinterface #158,  3          // InterfaceMethod org/scalatra/ApiFormats.format:(Ljavax/servlet/http/HttpServletRequest;Ljavax/servlet/http/HttpServletResponse;)Ljava/lang/String;
     620: ldc           #160                // String xml
     622: astore        24
     624: dup
     625: ifnonnull     637
     628: pop
     629: aload         24
     631: ifnull        645
     634: goto          719
     637: aload         24
     639: invokevirtual #34                 // Method java/lang/Object.equals:(Ljava/lang/Object;)Z
     642: ifeq          719
     645: aload_0
     646: getfield      #46                 // Field $outer:Lorg/scalatra/json/JValueResult;
     649: aload_0
     650: getfield      #46                 // Field $outer:Lorg/scalatra/json/JValueResult;
     653: checkcast     #150                // class org/scalatra/ApiFormats
     656: invokeinterface #164,  1          // InterfaceMethod org/scalatra/ApiFormats.formats:()Lscala/collection/concurrent/Map;
     661: ldc           #160                // String xml
     663: invokeinterface #167,  2          // InterfaceMethod scala/collection/concurrent/Map.apply:(Ljava/lang/Object;)Ljava/lang/Object;
     668: checkcast     #146                // class java/lang/String
     671: invokeinterface #170,  2          // InterfaceMethod org/scalatra/json/JValueResult.contentType_$eq:(Ljava/lang/String;)V
     676: aload_0
     677: getfield      #46                 // Field $outer:Lorg/scalatra/json/JValueResult;
     680: aload_0
     681: getfield      #46                 // Field $outer:Lorg/scalatra/json/JValueResult;
     684: invokeinterface #50,  1           // InterfaceMethod org/scalatra/json/JValueResult.response:()Ljavax/servlet/http/HttpServletResponse;
     689: invokeinterface #54,  2           // InterfaceMethod org/scalatra/json/JValueResult.enrichResponse:(Ljavax/servlet/http/HttpServletResponse;)Lorg/scalatra/servlet/RichResponse;
     694: invokevirtual #60                 // Method org/scalatra/servlet/RichResponse.writer:()Ljava/io/PrintWriter;
     697: getstatic     #175                // Field scala/xml/Utility$.MODULE$:Lscala/xml/Utility$;
     700: aload         23
     702: invokevirtual #179                // Method scala/xml/Utility$.trim:(Lscala/xml/Node;)Lscala/xml/Node;
     705: invokevirtual #183                // Method scala/xml/Node.toString:()Ljava/lang/String;
     708: invokevirtual #68                 // Method java/io/PrintWriter.write:(Ljava/lang/String;)V
     711: getstatic     #40                 // Field scala/runtime/BoxedUnit.UNIT:Lscala/runtime/BoxedUnit;
     714: astore        7
     716: goto          1003
     719: aload         5
     721: instanceof    #185                // class scala/xml/NodeSeq
     724: ifeq          859
     727: iconst_1
     728: istore_3
     729: aload         5
     731: checkcast     #185                // class scala/xml/NodeSeq
     734: astore        4
     736: aload_0
     737: getfield      #46                 // Field $outer:Lorg/scalatra/json/JValueResult;
     740: checkcast     #150                // class org/scalatra/ApiFormats
     743: aload_0
     744: getfield      #46                 // Field $outer:Lorg/scalatra/json/JValueResult;
     747: invokeinterface #154,  1          // InterfaceMethod org/scalatra/json/JValueResult.request:()Ljavax/servlet/http/HttpServletRequest;
     752: aload_0
     753: getfield      #46                 // Field $outer:Lorg/scalatra/json/JValueResult;
     756: invokeinterface #50,  1           // InterfaceMethod org/scalatra/json/JValueResult.response:()Ljavax/servlet/http/HttpServletResponse;
     761: invokeinterface #158,  3          // InterfaceMethod org/scalatra/ApiFormats.format:(Ljavax/servlet/http/HttpServletRequest;Ljavax/servlet/http/HttpServletResponse;)Ljava/lang/String;
     766: ldc           #160                // String xml
     768: astore        25
     770: dup
     771: ifnonnull     783
     774: pop
     775: aload         25
     777: ifnull        791
     780: goto          859
     783: aload         25
     785: invokevirtual #34                 // Method java/lang/Object.equals:(Ljava/lang/Object;)Z
     788: ifeq          859
     791: aload_0
     792: getfield      #46                 // Field $outer:Lorg/scalatra/json/JValueResult;
     795: aload_0
     796: getfield      #46                 // Field $outer:Lorg/scalatra/json/JValueResult;
     799: checkcast     #150                // class org/scalatra/ApiFormats
     802: invokeinterface #164,  1          // InterfaceMethod org/scalatra/ApiFormats.formats:()Lscala/collection/concurrent/Map;
     807: ldc           #160                // String xml
     809: invokeinterface #167,  2          // InterfaceMethod scala/collection/concurrent/Map.apply:(Ljava/lang/Object;)Ljava/lang/Object;
     814: checkcast     #146                // class java/lang/String
     817: invokeinterface #170,  2          // InterfaceMethod org/scalatra/json/JValueResult.contentType_$eq:(Ljava/lang/String;)V
     822: aload_0
     823: getfield      #46                 // Field $outer:Lorg/scalatra/json/JValueResult;
     826: aload_0
     827: getfield      #46                 // Field $outer:Lorg/scalatra/json/JValueResult;
     830: invokeinterface #50,  1           // InterfaceMethod org/scalatra/json/JValueResult.response:()Ljavax/servlet/http/HttpServletResponse;
     835: invokeinterface #54,  2           // InterfaceMethod org/scalatra/json/JValueResult.enrichResponse:(Ljavax/servlet/http/HttpServletResponse;)Lorg/scalatra/servlet/RichResponse;
     840: invokevirtual #60                 // Method org/scalatra/servlet/RichResponse.writer:()Ljava/io/PrintWriter;
     843: aload         4
     845: invokevirtual #186                // Method scala/xml/NodeSeq.toString:()Ljava/lang/String;
     848: invokevirtual #68                 // Method java/io/PrintWriter.write:(Ljava/lang/String;)V
     851: getstatic     #40                 // Field scala/runtime/BoxedUnit.UNIT:Lscala/runtime/BoxedUnit;
     854: astore        7
     856: goto          1003
     859: iload_3
     860: ifeq          900
     863: aload_0
     864: getfield      #46                 // Field $outer:Lorg/scalatra/json/JValueResult;
     867: aload_0
     868: getfield      #46                 // Field $outer:Lorg/scalatra/json/JValueResult;
     871: invokeinterface #50,  1           // InterfaceMethod org/scalatra/json/JValueResult.response:()Ljavax/servlet/http/HttpServletResponse;
     876: invokeinterface #54,  2           // InterfaceMethod org/scalatra/json/JValueResult.enrichResponse:(Ljavax/servlet/http/HttpServletResponse;)Lorg/scalatra/servlet/RichResponse;
     881: invokevirtual #60                 // Method org/scalatra/servlet/RichResponse.writer:()Ljava/io/PrintWriter;
     884: aload         4
     886: invokevirtual #186                // Method scala/xml/NodeSeq.toString:()Ljava/lang/String;
     889: invokevirtual #68                 // Method java/io/PrintWriter.write:(Ljava/lang/String;)V
     892: getstatic     #40                 // Field scala/runtime/BoxedUnit.UNIT:Lscala/runtime/BoxedUnit;
     895: astore        7
     897: goto          1003
     900: aload         5
     902: instanceof    #188                // class scala/Product
     905: ifeq          947
     908: aload         5
     910: checkcast     #188                // class scala/Product
     913: astore        26
     915: aload_0
     916: getfield      #46                 // Field $outer:Lorg/scalatra/json/JValueResult;
     919: invokestatic  #86                 // Method org/scalatra/json/JValueResult$class.org$scalatra$json$JValueResult$$isJValueResponse:(Lorg/scalatra/json/JValueResult;)Z
     922: ifeq          947
     925: getstatic     #193                // Field org/json4s/Extraction$.MODULE$:Lorg/json4s/Extraction$;
     928: aload         26
     930: aload_0
     931: getfield      #46                 // Field $outer:Lorg/scalatra/json/JValueResult;
     934: invokeinterface #197,  1          // InterfaceMethod org/scalatra/json/JValueResult.jsonFormats:()Lorg/json4s/Formats;
     939: invokevirtual #201                // Method org/json4s/Extraction$.decompose:(Ljava/lang/Object;Lorg/json4s/Formats;)Lorg/json4s/JsonAST$JValue;
     942: astore        7
     944: goto          1003
     947: aload         5
     949: instanceof    #203                // class scala/collection/TraversableOnce
     952: ifeq          994
     955: aload         5
     957: checkcast     #203                // class scala/collection/TraversableOnce
     960: astore        27
     962: aload_0
     963: getfield      #46                 // Field $outer:Lorg/scalatra/json/JValueResult;
     966: invokestatic  #86                 // Method org/scalatra/json/JValueResult$class.org$scalatra$json$JValueResult$$isJValueResponse:(Lorg/scalatra/json/JValueResult;)Z
     969: ifeq          994
     972: getstatic     #193                // Field org/json4s/Extraction$.MODULE$:Lorg/json4s/Extraction$;
     975: aload         27
     977: aload_0
     978: getfield      #46                 // Field $outer:Lorg/scalatra/json/JValueResult;
     981: invokeinterface #197,  1          // InterfaceMethod org/scalatra/json/JValueResult.jsonFormats:()Lorg/json4s/Formats;
     986: invokevirtual #201                // Method org/json4s/Extraction$.decompose:(Ljava/lang/Object;Lorg/json4s/Formats;)Lorg/json4s/JsonAST$JValue;
     989: astore        7
     991: goto          1003
     994: aload_2
     995: aload_1
     996: invokeinterface #100,  2          // InterfaceMethod scala/Function1.apply:(Ljava/lang/Object;)Ljava/lang/Object;
    1001: astore        7
    1003: aload         7
    1005: areturn

  public final boolean isDefinedAt(java.lang.Object);
    Code:
       0: iconst_0
       1: istore_2
       2: aconst_null
       3: astore_3
       4: aload_1
       5: astore        4
       7: getstatic     #24                 // Field org/json4s/package$.MODULE$:Lorg/json4s/package$;
      10: invokevirtual #28                 // Method org/json4s/package$.JNothing:()Lorg/json4s/JsonAST$JNothing$;
      13: aload         4
      15: astore        5
      17: dup
      18: ifnonnull     30
      21: pop
      22: aload         5
      24: ifnull        38
      27: goto          44
      30: aload         5
      32: invokevirtual #34                 // Method java/lang/Object.equals:(Ljava/lang/Object;)Z
      35: ifeq          44
      38: iconst_1
      39: istore        6
      41: goto          487
      44: getstatic     #24                 // Field org/json4s/package$.MODULE$:Lorg/json4s/package$;
      47: invokevirtual #44                 // Method org/json4s/package$.JNull:()Lorg/json4s/JsonAST$JNull$;
      50: aload         4
      52: astore        7
      54: dup
      55: ifnonnull     67
      58: pop
      59: aload         7
      61: ifnull        75
      64: goto          81
      67: aload         7
      69: invokevirtual #34                 // Method java/lang/Object.equals:(Ljava/lang/Object;)Z
      72: ifeq          81
      75: iconst_1
      76: istore        6
      78: goto          487
      81: aload         4
      83: instanceof    #70                 // class org/json4s/JsonAST$JValue
      86: ifeq          95
      89: iconst_1
      90: istore        6
      92: goto          487
      95: aload         4
      97: instanceof    #30                 // class java/lang/Object
     100: ifeq          140
     103: aload         4
     105: astore        8
     107: aload_0
     108: getfield      #46                 // Field $outer:Lorg/scalatra/json/JValueResult;
     111: invokestatic  #86                 // Method org/scalatra/json/JValueResult$class.org$scalatra$json$JValueResult$$isJValueResponse:(Lorg/scalatra/json/JValueResult;)Z
     114: ifeq          140
     117: aload_0
     118: getfield      #46                 // Field $outer:Lorg/scalatra/json/JValueResult;
     121: invokestatic  #90                 // Method org/scalatra/json/JValueResult$class.org$scalatra$json$JValueResult$$customSerializer:(Lorg/scalatra/json/JValueResult;)Lscala/PartialFunction;
     124: aload         8
     126: invokeinterface #93,  2           // InterfaceMethod scala/PartialFunction.isDefinedAt:(Ljava/lang/Object;)Z
     131: ifeq          140
     134: iconst_1
     135: istore        6
     137: goto          487
     140: aload         4
     142: instanceof    #121                // class java/lang/Integer
     145: ifeq          154
     148: iconst_1
     149: istore        6
     151: goto          487
     154: aload         4
     156: instanceof    #133                // class "[B"
     159: ifeq          168
     162: iconst_1
     163: istore        6
     165: goto          487
     168: aload         4
     170: instanceof    #135                // class java/io/InputStream
     173: ifeq          182
     176: iconst_1
     177: istore        6
     179: goto          487
     182: aload         4
     184: instanceof    #137                // class java/io/File
     187: ifeq          196
     190: iconst_1
     191: istore        6
     193: goto          487
     196: aload         4
     198: instanceof    #139                // class org/scalatra/ActionResult
     201: ifeq          210
     204: iconst_1
     205: istore        6
     207: goto          487
     210: aload         4
     212: instanceof    #36                 // class scala/runtime/BoxedUnit
     215: ifeq          224
     218: iconst_1
     219: istore        9
     221: goto          255
     224: getstatic     #144                // Field scala/Unit$.MODULE$:Lscala/Unit$;
     227: aload         4
     229: invokevirtual #34                 // Method java/lang/Object.equals:(Ljava/lang/Object;)Z
     232: ifeq          241
     235: iconst_1
     236: istore        9
     238: goto          255
     241: aload         4
     243: ifnonnull     252
     246: iconst_1
     247: istore        9
     249: goto          255
     252: iconst_0
     253: istore        9
     255: iload         9
     257: ifeq          266
     260: iconst_1
     261: istore        6
     263: goto          487
     266: aload         4
     268: instanceof    #146                // class java/lang/String
     271: ifeq          280
     274: iconst_1
     275: istore        6
     277: goto          487
     280: aload         4
     282: instanceof    #148                // class scala/xml/Node
     285: ifeq          349
     288: aload_0
     289: getfield      #46                 // Field $outer:Lorg/scalatra/json/JValueResult;
     292: checkcast     #150                // class org/scalatra/ApiFormats
     295: aload_0
     296: getfield      #46                 // Field $outer:Lorg/scalatra/json/JValueResult;
     299: invokeinterface #154,  1          // InterfaceMethod org/scalatra/json/JValueResult.request:()Ljavax/servlet/http/HttpServletRequest;
     304: aload_0
     305: getfield      #46                 // Field $outer:Lorg/scalatra/json/JValueResult;
     308: invokeinterface #50,  1           // InterfaceMethod org/scalatra/json/JValueResult.response:()Ljavax/servlet/http/HttpServletResponse;
     313: invokeinterface #158,  3          // InterfaceMethod org/scalatra/ApiFormats.format:(Ljavax/servlet/http/HttpServletRequest;Ljavax/servlet/http/HttpServletResponse;)Ljava/lang/String;
     318: ldc           #160                // String xml
     320: astore        10
     322: dup
     323: ifnonnull     335
     326: pop
     327: aload         10
     329: ifnull        343
     332: goto          349
     335: aload         10
     337: invokevirtual #34                 // Method java/lang/Object.equals:(Ljava/lang/Object;)Z
     340: ifeq          349
     343: iconst_1
     344: istore        6
     346: goto          487
     349: aload         4
     351: instanceof    #185                // class scala/xml/NodeSeq
     354: ifeq          426
     357: iconst_1
     358: istore_2
     359: aload         4
     361: checkcast     #185                // class scala/xml/NodeSeq
     364: astore_3
     365: aload_0
     366: getfield      #46                 // Field $outer:Lorg/scalatra/json/JValueResult;
     369: checkcast     #150                // class org/scalatra/ApiFormats
     372: aload_0
     373: getfield      #46                 // Field $outer:Lorg/scalatra/json/JValueResult;
     376: invokeinterface #154,  1          // InterfaceMethod org/scalatra/json/JValueResult.request:()Ljavax/servlet/http/HttpServletRequest;
     381: aload_0
     382: getfield      #46                 // Field $outer:Lorg/scalatra/json/JValueResult;
     385: invokeinterface #50,  1           // InterfaceMethod org/scalatra/json/JValueResult.response:()Ljavax/servlet/http/HttpServletResponse;
     390: invokeinterface #158,  3          // InterfaceMethod org/scalatra/ApiFormats.format:(Ljavax/servlet/http/HttpServletRequest;Ljavax/servlet/http/HttpServletResponse;)Ljava/lang/String;
     395: ldc           #160                // String xml
     397: astore        11
     399: dup
     400: ifnonnull     412
     403: pop
     404: aload         11
     406: ifnull        420
     409: goto          426
     412: aload         11
     414: invokevirtual #34                 // Method java/lang/Object.equals:(Ljava/lang/Object;)Z
     417: ifeq          426
     420: iconst_1
     421: istore        6
     423: goto          487
     426: iload_2
     427: ifeq          436
     430: iconst_1
     431: istore        6
     433: goto          487
     436: aload         4
     438: instanceof    #188                // class scala/Product
     441: ifeq          460
     444: aload_0
     445: getfield      #46                 // Field $outer:Lorg/scalatra/json/JValueResult;
     448: invokestatic  #86                 // Method org/scalatra/json/JValueResult$class.org$scalatra$json$JValueResult$$isJValueResponse:(Lorg/scalatra/json/JValueResult;)Z
     451: ifeq          460
     454: iconst_1
     455: istore        6
     457: goto          487
     460: aload         4
     462: instanceof    #203                // class scala/collection/TraversableOnce
     465: ifeq          484
     468: aload_0
     469: getfield      #46                 // Field $outer:Lorg/scalatra/json/JValueResult;
     472: invokestatic  #86                 // Method org/scalatra/json/JValueResult$class.org$scalatra$json$JValueResult$$isJValueResponse:(Lorg/scalatra/json/JValueResult;)Z
     475: ifeq          484
     478: iconst_1
     479: istore        6
     481: goto          487
     484: iconst_0
     485: istore        6
     487: iload         6
     489: ireturn

  public org.scalatra.json.JValueResult$$anonfun$org$scalatra$json$JValueResult$$renderToJson$1(org.scalatra.json.JValueResult);
    Code:
       0: aload_1
       1: ifnonnull     6
       4: aconst_null
       5: athrow
       6: aload_0
       7: aload_1
       8: putfield      #46                 // Field $outer:Lorg/scalatra/json/JValueResult;
      11: aload_0
      12: invokespecial #219                // Method scala/runtime/AbstractPartialFunction."<init>":()V
      15: return
}
