Compiled from "SimpleTrustManagerFactory.java"
public abstract class org.jboss.netty.handler.ssl.util.SimpleTrustManagerFactory extends javax.net.ssl.TrustManagerFactory {
  private static final java.security.Provider PROVIDER;

  private static final java.lang.ThreadLocal<org.jboss.netty.handler.ssl.util.SimpleTrustManagerFactory$SimpleTrustManagerFactorySpi> CURRENT_SPI;

  protected org.jboss.netty.handler.ssl.util.SimpleTrustManagerFactory();
    Code:
       0: aload_0
       1: ldc           #1                  // String
       3: invokespecial #2                  // Method "<init>":(Ljava/lang/String;)V
       6: return

  protected org.jboss.netty.handler.ssl.util.SimpleTrustManagerFactory(java.lang.String);
    Code:
       0: aload_0
       1: getstatic     #3                  // Field CURRENT_SPI:Ljava/lang/ThreadLocal;
       4: invokevirtual #4                  // Method java/lang/ThreadLocal.get:()Ljava/lang/Object;
       7: checkcast     #5                  // class javax/net/ssl/TrustManagerFactorySpi
      10: getstatic     #6                  // Field PROVIDER:Ljava/security/Provider;
      13: aload_1
      14: invokespecial #7                  // Method javax/net/ssl/TrustManagerFactory."<init>":(Ljavax/net/ssl/TrustManagerFactorySpi;Ljava/security/Provider;Ljava/lang/String;)V
      17: getstatic     #3                  // Field CURRENT_SPI:Ljava/lang/ThreadLocal;
      20: invokevirtual #4                  // Method java/lang/ThreadLocal.get:()Ljava/lang/Object;
      23: checkcast     #8                  // class org/jboss/netty/handler/ssl/util/SimpleTrustManagerFactory$SimpleTrustManagerFactorySpi
      26: aload_0
      27: invokevirtual #9                  // Method org/jboss/netty/handler/ssl/util/SimpleTrustManagerFactory$SimpleTrustManagerFactorySpi.init:(Lorg/jboss/netty/handler/ssl/util/SimpleTrustManagerFactory;)V
      30: getstatic     #3                  // Field CURRENT_SPI:Ljava/lang/ThreadLocal;
      33: invokevirtual #10                 // Method java/lang/ThreadLocal.remove:()V
      36: aload_1
      37: ifnonnull     50
      40: new           #11                 // class java/lang/NullPointerException
      43: dup
      44: ldc           #12                 // String name
      46: invokespecial #13                 // Method java/lang/NullPointerException."<init>":(Ljava/lang/String;)V
      49: athrow
      50: return

  protected abstract void engineInit(java.security.KeyStore) throws java.lang.Exception;

  protected abstract void engineInit(javax.net.ssl.ManagerFactoryParameters) throws java.lang.Exception;

  protected abstract javax.net.ssl.TrustManager[] engineGetTrustManagers();

  static {};
    Code:
       0: new           #14                 // class org/jboss/netty/handler/ssl/util/SimpleTrustManagerFactory$1
       3: dup
       4: ldc           #1                  // String
       6: dconst_0
       7: ldc           #1                  // String
       9: invokespecial #15                 // Method org/jboss/netty/handler/ssl/util/SimpleTrustManagerFactory$1."<init>":(Ljava/lang/String;DLjava/lang/String;)V
      12: putstatic     #6                  // Field PROVIDER:Ljava/security/Provider;
      15: new           #16                 // class org/jboss/netty/handler/ssl/util/SimpleTrustManagerFactory$2
      18: dup
      19: invokespecial #17                 // Method org/jboss/netty/handler/ssl/util/SimpleTrustManagerFactory$2."<init>":()V
      22: putstatic     #3                  // Field CURRENT_SPI:Ljava/lang/ThreadLocal;
      25: return
}
