Compiled from "ConfigurationsTemplate.scala"
public final class ai.h2o.sparkling.doc.generation.ConfigurationsTemplate$$anonfun$generateTable$1 extends scala.runtime.AbstractFunction1<ai.h2o.sparkling.doc.generation.ConfigurationsTemplate$Option, scala.collection.mutable.StringBuilder> implements scala.Serializable {
  public static final long serialVersionUID;

  private final ai.h2o.sparkling.doc.generation.ConfigurationsTemplate$LineSizes sizes$1;

  private final scala.collection.mutable.StringBuilder builder$1;

  public final scala.collection.mutable.StringBuilder apply(ai.h2o.sparkling.doc.generation.ConfigurationsTemplate$Option);
    Code:
       0: aload_0
       1: getfield      #25                 // Field builder$1:Lscala/collection/mutable/StringBuilder;
       4: getstatic     #29                 // Field ai/h2o/sparkling/doc/generation/ConfigurationsTemplate$.MODULE$:Lai/h2o/sparkling/doc/generation/ConfigurationsTemplate$;
       7: aload_0
       8: getfield      #31                 // Field sizes$1:Lai/h2o/sparkling/doc/generation/ConfigurationsTemplate$LineSizes;
      11: aload_1
      12: invokevirtual #37                 // Method ai/h2o/sparkling/doc/generation/ConfigurationsTemplate$Option.name:()Ljava/lang/String;
      15: aload_1
      16: invokevirtual #40                 // Method ai/h2o/sparkling/doc/generation/ConfigurationsTemplate$Option.value:()Ljava/lang/String;
      19: aload_1
      20: invokevirtual #43                 // Method ai/h2o/sparkling/doc/generation/ConfigurationsTemplate$Option.setters:()Ljava/lang/String;
      23: aload_1
      24: invokevirtual #46                 // Method ai/h2o/sparkling/doc/generation/ConfigurationsTemplate$Option.doc:()Ljava/lang/String;
      27: invokevirtual #50                 // Method ai/h2o/sparkling/doc/generation/ConfigurationsTemplate$.ai$h2o$sparkling$doc$generation$ConfigurationsTemplate$$fillOption:(Lai/h2o/sparkling/doc/generation/ConfigurationsTemplate$LineSizes;Ljava/lang/String;Ljava/lang/String;Ljava/lang/String;Ljava/lang/String;)Ljava/lang/String;
      30: invokevirtual #56                 // Method scala/collection/mutable/StringBuilder.append:(Ljava/lang/String;)Lscala/collection/mutable/StringBuilder;
      33: ldc           #58                 // String \n
      35: invokevirtual #56                 // Method scala/collection/mutable/StringBuilder.append:(Ljava/lang/String;)Lscala/collection/mutable/StringBuilder;
      38: getstatic     #29                 // Field ai/h2o/sparkling/doc/generation/ConfigurationsTemplate$.MODULE$:Lai/h2o/sparkling/doc/generation/ConfigurationsTemplate$;
      41: aload_0
      42: getfield      #31                 // Field sizes$1:Lai/h2o/sparkling/doc/generation/ConfigurationsTemplate$LineSizes;
      45: ldc           #60                 // String -
      47: invokevirtual #64                 // Method ai/h2o/sparkling/doc/generation/ConfigurationsTemplate$.ai$h2o$sparkling$doc$generation$ConfigurationsTemplate$$lineSeparator:(Lai/h2o/sparkling/doc/generation/ConfigurationsTemplate$LineSizes;Ljava/lang/String;)Ljava/lang/String;
      50: invokevirtual #56                 // Method scala/collection/mutable/StringBuilder.append:(Ljava/lang/String;)Lscala/collection/mutable/StringBuilder;
      53: ldc           #58                 // String \n
      55: invokevirtual #56                 // Method scala/collection/mutable/StringBuilder.append:(Ljava/lang/String;)Lscala/collection/mutable/StringBuilder;
      58: areturn

  public final java.lang.Object apply(java.lang.Object);
    Code:
       0: aload_0
       1: aload_1
       2: checkcast     #33                 // class ai/h2o/sparkling/doc/generation/ConfigurationsTemplate$Option
       5: invokevirtual #71                 // Method apply:(Lai/h2o/sparkling/doc/generation/ConfigurationsTemplate$Option;)Lscala/collection/mutable/StringBuilder;
       8: areturn

  public ai.h2o.sparkling.doc.generation.ConfigurationsTemplate$$anonfun$generateTable$1(ai.h2o.sparkling.doc.generation.ConfigurationsTemplate$LineSizes, scala.collection.mutable.StringBuilder);
    Code:
       0: aload_0
       1: aload_1
       2: putfield      #31                 // Field sizes$1:Lai/h2o/sparkling/doc/generation/ConfigurationsTemplate$LineSizes;
       5: aload_0
       6: aload_2
       7: putfield      #25                 // Field builder$1:Lscala/collection/mutable/StringBuilder;
      10: aload_0
      11: invokespecial #78                 // Method scala/runtime/AbstractFunction1."<init>":()V
      14: return
}
