Compiled from "ConfigurationsTemplate.scala"
public final class ai.h2o.sparkling.doc.generation.ConfigurationsTemplate$$anonfun$ai$h2o$sparkling$doc$generation$ConfigurationsTemplate$$fillOption$2 extends scala.runtime.AbstractFunction1<java.lang.Object, scala.collection.mutable.StringBuilder> implements scala.Serializable {
  public static final long serialVersionUID;

  private final ai.h2o.sparkling.doc.generation.ConfigurationsTemplate$LineSizes sizes$2;

  private final scala.collection.mutable.StringBuilder builder$2;

  private final java.lang.String[] setterLines$1;

  private final java.lang.String[] docLines$1;

  private final int setterLinesLen$1;

  private final int docLinesLen$1;

  public final scala.collection.mutable.StringBuilder apply(int);
    Code:
       0: iload_1
       1: aload_0
       2: getfield      #31                 // Field setterLinesLen$1:I
       5: if_icmplt     13
       8: ldc           #33                 // String
      10: goto          98
      13: aload_0
      14: getfield      #35                 // Field setterLines$1:[Ljava/lang/String;
      17: iload_1
      18: aaload
      19: ldc           #33                 // String
      21: astore_3
      22: dup
      23: ifnonnull     34
      26: pop
      27: aload_3
      28: ifnull        41
      31: goto          46
      34: aload_3
      35: invokevirtual #41                 // Method java/lang/Object.equals:(Ljava/lang/Object;)Z
      38: ifeq          46
      41: ldc           #33                 // String
      43: goto          98
      46: new           #43                 // class scala/StringContext
      49: dup
      50: getstatic     #49                 // Field scala/Predef$.MODULE$:Lscala/Predef$;
      53: iconst_2
      54: anewarray     #51                 // class java/lang/String
      57: dup
      58: iconst_0
      59: ldc           #53                 // String ``
      61: aastore
      62: dup
      63: iconst_1
      64: ldc           #53                 // String ``
      66: aastore
      67: checkcast     #55                 // class "[Ljava/lang/Object;"
      70: invokevirtual #59                 // Method scala/Predef$.wrapRefArray:([Ljava/lang/Object;)Lscala/collection/mutable/WrappedArray;
      73: invokespecial #63                 // Method scala/StringContext."<init>":(Lscala/collection/Seq;)V
      76: getstatic     #49                 // Field scala/Predef$.MODULE$:Lscala/Predef$;
      79: iconst_1
      80: anewarray     #37                 // class java/lang/Object
      83: dup
      84: iconst_0
      85: aload_0
      86: getfield      #35                 // Field setterLines$1:[Ljava/lang/String;
      89: iload_1
      90: aaload
      91: aastore
      92: invokevirtual #67                 // Method scala/Predef$.genericWrapArray:(Ljava/lang/Object;)Lscala/collection/mutable/WrappedArray;
      95: invokevirtual #71                 // Method scala/StringContext.s:(Lscala/collection/Seq;)Ljava/lang/String;
      98: astore_2
      99: iload_1
     100: aload_0
     101: getfield      #73                 // Field docLinesLen$1:I
     104: if_icmplt     112
     107: ldc           #33                 // String
     109: goto          118
     112: aload_0
     113: getfield      #75                 // Field docLines$1:[Ljava/lang/String;
     116: iload_1
     117: aaload
     118: astore        4
     120: aload_0
     121: getfield      #77                 // Field builder$2:Lscala/collection/mutable/StringBuilder;
     124: ldc           #79                 // String \n
     126: invokevirtual #85                 // Method scala/collection/mutable/StringBuilder.append:(Ljava/lang/String;)Lscala/collection/mutable/StringBuilder;
     129: ldc           #87                 // String |
     131: invokevirtual #85                 // Method scala/collection/mutable/StringBuilder.append:(Ljava/lang/String;)Lscala/collection/mutable/StringBuilder;
     134: ldc           #89                 // String |
     136: invokevirtual #85                 // Method scala/collection/mutable/StringBuilder.append:(Ljava/lang/String;)Lscala/collection/mutable/StringBuilder;
     139: getstatic     #92                 // Field ai/h2o/sparkling/doc/generation/ConfigurationsTemplate$.MODULE$:Lai/h2o/sparkling/doc/generation/ConfigurationsTemplate$;
     142: aload_0
     143: getfield      #94                 // Field sizes$2:Lai/h2o/sparkling/doc/generation/ConfigurationsTemplate$LineSizes;
     146: invokevirtual #100                // Method ai/h2o/sparkling/doc/generation/ConfigurationsTemplate$LineSizes.nameLength:()I
     149: iconst_4
     150: iadd
     151: ldc           #102                // String
     153: invokevirtual #106                // Method ai/h2o/sparkling/doc/generation/ConfigurationsTemplate$.ai$h2o$sparkling$doc$generation$ConfigurationsTemplate$$repeat:(ILjava/lang/String;)Ljava/lang/String;
     156: invokevirtual #85                 // Method scala/collection/mutable/StringBuilder.append:(Ljava/lang/String;)Lscala/collection/mutable/StringBuilder;
     159: ldc           #108                // String  |
     161: invokevirtual #85                 // Method scala/collection/mutable/StringBuilder.append:(Ljava/lang/String;)Lscala/collection/mutable/StringBuilder;
     164: getstatic     #92                 // Field ai/h2o/sparkling/doc/generation/ConfigurationsTemplate$.MODULE$:Lai/h2o/sparkling/doc/generation/ConfigurationsTemplate$;
     167: aload_0
     168: getfield      #94                 // Field sizes$2:Lai/h2o/sparkling/doc/generation/ConfigurationsTemplate$LineSizes;
     171: invokevirtual #111                // Method ai/h2o/sparkling/doc/generation/ConfigurationsTemplate$LineSizes.valueLength:()I
     174: ldc           #102                // String
     176: invokevirtual #106                // Method ai/h2o/sparkling/doc/generation/ConfigurationsTemplate$.ai$h2o$sparkling$doc$generation$ConfigurationsTemplate$$repeat:(ILjava/lang/String;)Ljava/lang/String;
     179: invokevirtual #85                 // Method scala/collection/mutable/StringBuilder.append:(Ljava/lang/String;)Lscala/collection/mutable/StringBuilder;
     182: ldc           #108                // String  |
     184: invokevirtual #85                 // Method scala/collection/mutable/StringBuilder.append:(Ljava/lang/String;)Lscala/collection/mutable/StringBuilder;
     187: aload_2
     188: invokevirtual #85                 // Method scala/collection/mutable/StringBuilder.append:(Ljava/lang/String;)Lscala/collection/mutable/StringBuilder;
     191: getstatic     #92                 // Field ai/h2o/sparkling/doc/generation/ConfigurationsTemplate$.MODULE$:Lai/h2o/sparkling/doc/generation/ConfigurationsTemplate$;
     194: aload_0
     195: getfield      #94                 // Field sizes$2:Lai/h2o/sparkling/doc/generation/ConfigurationsTemplate$LineSizes;
     198: invokevirtual #114                // Method ai/h2o/sparkling/doc/generation/ConfigurationsTemplate$LineSizes.setterLength:()I
     201: aload_2
     202: invokevirtual #117                // Method java/lang/String.length:()I
     205: isub
     206: iconst_4
     207: iadd
     208: ldc           #102                // String
     210: invokevirtual #106                // Method ai/h2o/sparkling/doc/generation/ConfigurationsTemplate$.ai$h2o$sparkling$doc$generation$ConfigurationsTemplate$$repeat:(ILjava/lang/String;)Ljava/lang/String;
     213: invokevirtual #85                 // Method scala/collection/mutable/StringBuilder.append:(Ljava/lang/String;)Lscala/collection/mutable/StringBuilder;
     216: ldc           #108                // String  |
     218: invokevirtual #85                 // Method scala/collection/mutable/StringBuilder.append:(Ljava/lang/String;)Lscala/collection/mutable/StringBuilder;
     221: aload         4
     223: invokevirtual #85                 // Method scala/collection/mutable/StringBuilder.append:(Ljava/lang/String;)Lscala/collection/mutable/StringBuilder;
     226: getstatic     #92                 // Field ai/h2o/sparkling/doc/generation/ConfigurationsTemplate$.MODULE$:Lai/h2o/sparkling/doc/generation/ConfigurationsTemplate$;
     229: aload_0
     230: getfield      #94                 // Field sizes$2:Lai/h2o/sparkling/doc/generation/ConfigurationsTemplate$LineSizes;
     233: invokevirtual #120                // Method ai/h2o/sparkling/doc/generation/ConfigurationsTemplate$LineSizes.docLength:()I
     236: aload         4
     238: invokevirtual #117                // Method java/lang/String.length:()I
     241: isub
     242: ldc           #102                // String
     244: invokevirtual #106                // Method ai/h2o/sparkling/doc/generation/ConfigurationsTemplate$.ai$h2o$sparkling$doc$generation$ConfigurationsTemplate$$repeat:(ILjava/lang/String;)Ljava/lang/String;
     247: invokevirtual #85                 // Method scala/collection/mutable/StringBuilder.append:(Ljava/lang/String;)Lscala/collection/mutable/StringBuilder;
     250: ldc           #122                // String  |
     252: invokevirtual #85                 // Method scala/collection/mutable/StringBuilder.append:(Ljava/lang/String;)Lscala/collection/mutable/StringBuilder;
     255: areturn

  public final java.lang.Object apply(java.lang.Object);
    Code:
       0: aload_0
       1: aload_1
       2: invokestatic  #135                // Method scala/runtime/BoxesRunTime.unboxToInt:(Ljava/lang/Object;)I
       5: invokevirtual #137                // Method apply:(I)Lscala/collection/mutable/StringBuilder;
       8: areturn

  public ai.h2o.sparkling.doc.generation.ConfigurationsTemplate$$anonfun$ai$h2o$sparkling$doc$generation$ConfigurationsTemplate$$fillOption$2(ai.h2o.sparkling.doc.generation.ConfigurationsTemplate$LineSizes, scala.collection.mutable.StringBuilder, java.lang.String[], java.lang.String[], int, int);
    Code:
       0: aload_0
       1: aload_1
       2: putfield      #94                 // Field sizes$2:Lai/h2o/sparkling/doc/generation/ConfigurationsTemplate$LineSizes;
       5: aload_0
       6: aload_2
       7: putfield      #77                 // Field builder$2:Lscala/collection/mutable/StringBuilder;
      10: aload_0
      11: aload_3
      12: putfield      #35                 // Field setterLines$1:[Ljava/lang/String;
      15: aload_0
      16: aload         4
      18: putfield      #75                 // Field docLines$1:[Ljava/lang/String;
      21: aload_0
      22: iload         5
      24: putfield      #31                 // Field setterLinesLen$1:I
      27: aload_0
      28: iload         6
      30: putfield      #73                 // Field docLinesLen$1:I
      33: aload_0
      34: invokespecial #143                // Method scala/runtime/AbstractFunction1."<init>":()V
      37: return
}
