Compiled from "ParametersTemplate.scala"
public final class ai.h2o.sparkling.doc.generation.ParametersTemplate$$anonfun$getParametersContent$1 extends scala.runtime.AbstractFunction1<org.apache.spark.ml.param.Param<?>, java.lang.String> implements scala.Serializable {
  public static final long serialVersionUID;

  private final org.apache.spark.ml.param.Params algorithmInstance$1;

  private final scala.Option mojoModelInstanceOption$1;

  public final java.lang.String apply(org.apache.spark.ml.param.Param<?>);
    Code:
       0: aload_0
       1: getfield      #25                 // Field algorithmInstance$1:Lorg/apache/spark/ml/param/Params;
       4: aload_1
       5: invokeinterface #31,  2           // InterfaceMethod org/apache/spark/ml/param/Params.getDefault:(Lorg/apache/spark/ml/param/Param;)Lscala/Option;
      10: invokevirtual #37                 // Method scala/Option.isDefined:()Z
      13: ifeq          32
      16: aload_0
      17: getfield      #25                 // Field algorithmInstance$1:Lorg/apache/spark/ml/param/Params;
      20: aload_1
      21: invokeinterface #31,  2           // InterfaceMethod org/apache/spark/ml/param/Params.getDefault:(Lorg/apache/spark/ml/param/Param;)Lscala/Option;
      26: invokevirtual #41                 // Method scala/Option.get:()Ljava/lang/Object;
      29: goto          34
      32: ldc           #43                 // String No default value
      34: astore_2
      35: new           #45                 // class scala/collection/immutable/StringOps
      38: dup
      39: getstatic     #51                 // Field scala/Predef$.MODULE$:Lscala/Predef$;
      42: new           #53                 // class scala/StringContext
      45: dup
      46: getstatic     #51                 // Field scala/Predef$.MODULE$:Lscala/Predef$;
      49: iconst_5
      50: anewarray     #55                 // class java/lang/String
      53: dup
      54: iconst_0
      55: ldc           #57                 // String
      57: aastore
      58: dup
      59: iconst_1
      60: ldc           #59                 // String \n           |
      62: aastore
      63: dup
      64: iconst_2
      65: ldc           #61                 // String \n           |\n           |
      67: aastore
      68: dup
      69: iconst_3
      70: ldc           #59                 // String \n           |
      72: aastore
      73: dup
      74: iconst_4
      75: ldc           #63                 // String \n           |
      77: aastore
      78: checkcast     #65                 // class "[Ljava/lang/Object;"
      81: invokevirtual #69                 // Method scala/Predef$.wrapRefArray:([Ljava/lang/Object;)Lscala/collection/mutable/WrappedArray;
      84: invokespecial #73                 // Method scala/StringContext."<init>":(Lscala/collection/Seq;)V
      87: getstatic     #51                 // Field scala/Predef$.MODULE$:Lscala/Predef$;
      90: iconst_4
      91: anewarray     #75                 // class java/lang/Object
      94: dup
      95: iconst_0
      96: aload_1
      97: invokevirtual #81                 // Method org/apache/spark/ml/param/Param.name:()Ljava/lang/String;
     100: aastore
     101: dup
     102: iconst_1
     103: aload_1
     104: invokevirtual #84                 // Method org/apache/spark/ml/param/Param.doc:()Ljava/lang/String;
     107: ldc           #86                 // String  \n
     109: ldc           #57                 // String
     111: invokevirtual #90                 // Method java/lang/String.replace:(Ljava/lang/CharSequence;Ljava/lang/CharSequence;)Ljava/lang/String;
     114: ldc           #92                 // String \n
     116: ldc           #94                 // String \n\n  -
     118: invokevirtual #90                 // Method java/lang/String.replace:(Ljava/lang/CharSequence;Ljava/lang/CharSequence;)Ljava/lang/String;
     121: aastore
     122: dup
     123: iconst_2
     124: getstatic     #97                 // Field ai/h2o/sparkling/doc/generation/ParametersTemplate$.MODULE$:Lai/h2o/sparkling/doc/generation/ParametersTemplate$;
     127: aload_2
     128: invokevirtual #101                // Method ai/h2o/sparkling/doc/generation/ParametersTemplate$.ai$h2o$sparkling$doc$generation$ParametersTemplate$$generateDefaultValue:(Ljava/lang/Object;)Ljava/lang/String;
     131: aastore
     132: dup
     133: iconst_3
     134: getstatic     #97                 // Field ai/h2o/sparkling/doc/generation/ParametersTemplate$.MODULE$:Lai/h2o/sparkling/doc/generation/ParametersTemplate$;
     137: aload_1
     138: invokevirtual #81                 // Method org/apache/spark/ml/param/Param.name:()Ljava/lang/String;
     141: aload_0
     142: getfield      #103                // Field mojoModelInstanceOption$1:Lscala/Option;
     145: invokevirtual #107                // Method ai/h2o/sparkling/doc/generation/ParametersTemplate$.ai$h2o$sparkling$doc$generation$ParametersTemplate$$generateMOJOComment:(Ljava/lang/String;Lscala/Option;)Ljava/lang/String;
     148: aastore
     149: invokevirtual #111                // Method scala/Predef$.genericWrapArray:(Ljava/lang/Object;)Lscala/collection/mutable/WrappedArray;
     152: invokevirtual #115                // Method scala/StringContext.s:(Lscala/collection/Seq;)Ljava/lang/String;
     155: invokevirtual #119                // Method scala/Predef$.augmentString:(Ljava/lang/String;)Ljava/lang/String;
     158: invokespecial #122                // Method scala/collection/immutable/StringOps."<init>":(Ljava/lang/String;)V
     161: invokevirtual #125                // Method scala/collection/immutable/StringOps.stripMargin:()Ljava/lang/String;
     164: areturn

  public final java.lang.Object apply(java.lang.Object);
    Code:
       0: aload_0
       1: aload_1
       2: checkcast     #77                 // class org/apache/spark/ml/param/Param
       5: invokevirtual #134                // Method apply:(Lorg/apache/spark/ml/param/Param;)Ljava/lang/String;
       8: areturn

  public ai.h2o.sparkling.doc.generation.ParametersTemplate$$anonfun$getParametersContent$1(org.apache.spark.ml.param.Params, scala.Option);
    Code:
       0: aload_0
       1: aload_1
       2: putfield      #25                 // Field algorithmInstance$1:Lorg/apache/spark/ml/param/Params;
       5: aload_0
       6: aload_2
       7: putfield      #103                // Field mojoModelInstanceOption$1:Lscala/Option;
      10: aload_0
      11: invokespecial #139                // Method scala/runtime/AbstractFunction1."<init>":()V
      14: return
}
