public class org.bouncycastle.operator.DefaultDigestAlgorithmIdentifierFinder implements org.bouncycastle.operator.DigestAlgorithmIdentifierFinder {
  private static java.util.Map digestOids;

  private static java.util.Map digestNameToOids;

  private static java.util.Map digestOidToAlgIds;

  public org.bouncycastle.operator.DefaultDigestAlgorithmIdentifierFinder();
    Code:
       0: aload_0
       1: invokespecial #441                // Method java/lang/Object."<init>":()V
       4: return

  private static void addDigestAlgId(org.bouncycastle.asn1.ASN1ObjectIdentifier, boolean);
    Code:
       0: iload_1
       1: ifeq          19
       4: new           #220                // class org/bouncycastle/asn1/x509/AlgorithmIdentifier
       7: dup
       8: aload_0
       9: getstatic     #347                // Field org/bouncycastle/asn1/DERNull.INSTANCE:Lorg/bouncycastle/asn1/DERNull;
      12: invokespecial #451                // Method org/bouncycastle/asn1/x509/AlgorithmIdentifier."<init>":(Lorg/bouncycastle/asn1/ASN1ObjectIdentifier;Lorg/bouncycastle/asn1/ASN1Encodable;)V
      15: astore_2
      16: goto          28
      19: new           #220                // class org/bouncycastle/asn1/x509/AlgorithmIdentifier
      22: dup
      23: aload_0
      24: invokespecial #450                // Method org/bouncycastle/asn1/x509/AlgorithmIdentifier."<init>":(Lorg/bouncycastle/asn1/ASN1ObjectIdentifier;)V
      27: astore_2
      28: getstatic     #438                // Field digestOidToAlgIds:Ljava/util/Map;
      31: aload_0
      32: aload_2
      33: invokeinterface #455,  3          // InterfaceMethod java/util/Map.put:(Ljava/lang/Object;Ljava/lang/Object;)Ljava/lang/Object;
      38: pop
      39: return

  public org.bouncycastle.asn1.x509.AlgorithmIdentifier find(org.bouncycastle.asn1.x509.AlgorithmIdentifier);
    Code:
       0: aload_1
       1: invokevirtual #449                // Method org/bouncycastle/asn1/x509/AlgorithmIdentifier.getAlgorithm:()Lorg/bouncycastle/asn1/ASN1ObjectIdentifier;
       4: astore_2
       5: aload_2
       6: getstatic     #369                // Field org/bouncycastle/asn1/edec/EdECObjectIdentifiers.id_Ed448:Lorg/bouncycastle/asn1/ASN1ObjectIdentifier;
       9: invokevirtual #445                // Method org/bouncycastle/asn1/ASN1ObjectIdentifier.equals:(Lorg/bouncycastle/asn1/ASN1Primitive;)Z
      12: ifeq          36
      15: new           #220                // class org/bouncycastle/asn1/x509/AlgorithmIdentifier
      18: dup
      19: getstatic     #401                // Field org/bouncycastle/asn1/nist/NISTObjectIdentifiers.id_shake256_len:Lorg/bouncycastle/asn1/ASN1ObjectIdentifier;
      22: new           #204                // class org/bouncycastle/asn1/ASN1Integer
      25: dup
      26: ldc2_w        #197                // long 512l
      29: invokespecial #443                // Method org/bouncycastle/asn1/ASN1Integer."<init>":(J)V
      32: invokespecial #451                // Method org/bouncycastle/asn1/x509/AlgorithmIdentifier."<init>":(Lorg/bouncycastle/asn1/ASN1ObjectIdentifier;Lorg/bouncycastle/asn1/ASN1Encodable;)V
      35: areturn
      36: aload_2
      37: getstatic     #407                // Field org/bouncycastle/asn1/pkcs/PKCSObjectIdentifiers.id_RSASSA_PSS:Lorg/bouncycastle/asn1/ASN1ObjectIdentifier;
      40: invokevirtual #445                // Method org/bouncycastle/asn1/ASN1ObjectIdentifier.equals:(Lorg/bouncycastle/asn1/ASN1Primitive;)Z
      43: ifeq          63
      46: aload_1
      47: invokevirtual #448                // Method org/bouncycastle/asn1/x509/AlgorithmIdentifier.getParameters:()Lorg/bouncycastle/asn1/ASN1Encodable;
      50: invokestatic  #447                // Method org/bouncycastle/asn1/pkcs/RSASSAPSSparams.getInstance:(Ljava/lang/Object;)Lorg/bouncycastle/asn1/pkcs/RSASSAPSSparams;
      53: invokevirtual #446                // Method org/bouncycastle/asn1/pkcs/RSASSAPSSparams.getHashAlgorithm:()Lorg/bouncycastle/asn1/x509/AlgorithmIdentifier;
      56: invokevirtual #449                // Method org/bouncycastle/asn1/x509/AlgorithmIdentifier.getAlgorithm:()Lorg/bouncycastle/asn1/ASN1ObjectIdentifier;
      59: astore_3
      60: goto          96
      63: aload_2
      64: getstatic     #368                // Field org/bouncycastle/asn1/edec/EdECObjectIdentifiers.id_Ed25519:Lorg/bouncycastle/asn1/ASN1ObjectIdentifier;
      67: invokevirtual #445                // Method org/bouncycastle/asn1/ASN1ObjectIdentifier.equals:(Lorg/bouncycastle/asn1/ASN1Primitive;)Z
      70: ifeq          80
      73: getstatic     #396                // Field org/bouncycastle/asn1/nist/NISTObjectIdentifiers.id_sha512:Lorg/bouncycastle/asn1/ASN1ObjectIdentifier;
      76: astore_3
      77: goto          96
      80: getstatic     #439                // Field digestOids:Ljava/util/Map;
      83: aload_1
      84: invokevirtual #449                // Method org/bouncycastle/asn1/x509/AlgorithmIdentifier.getAlgorithm:()Lorg/bouncycastle/asn1/ASN1ObjectIdentifier;
      87: invokeinterface #454,  2          // InterfaceMethod java/util/Map.get:(Ljava/lang/Object;)Ljava/lang/Object;
      92: checkcast     #205                // class org/bouncycastle/asn1/ASN1ObjectIdentifier
      95: astore_3
      96: aload_0
      97: aload_3
      98: invokevirtual #453                // Method find:(Lorg/bouncycastle/asn1/ASN1ObjectIdentifier;)Lorg/bouncycastle/asn1/x509/AlgorithmIdentifier;
     101: areturn

  public org.bouncycastle.asn1.x509.AlgorithmIdentifier find(org.bouncycastle.asn1.ASN1ObjectIdentifier);
    Code:
       0: aload_1
       1: ifnonnull     14
       4: new           #200                // class java/lang/NullPointerException
       7: dup
       8: ldc           #33                 // String digest OID is null
      10: invokespecial #440                // Method java/lang/NullPointerException."<init>":(Ljava/lang/String;)V
      13: athrow
      14: getstatic     #438                // Field digestOidToAlgIds:Ljava/util/Map;
      17: aload_1
      18: invokeinterface #454,  2          // InterfaceMethod java/util/Map.get:(Ljava/lang/Object;)Ljava/lang/Object;
      23: checkcast     #220                // class org/bouncycastle/asn1/x509/AlgorithmIdentifier
      26: astore_2
      27: aload_2
      28: ifnonnull     40
      31: new           #220                // class org/bouncycastle/asn1/x509/AlgorithmIdentifier
      34: dup
      35: aload_1
      36: invokespecial #450                // Method org/bouncycastle/asn1/x509/AlgorithmIdentifier."<init>":(Lorg/bouncycastle/asn1/ASN1ObjectIdentifier;)V
      39: areturn
      40: aload_2
      41: areturn

  public org.bouncycastle.asn1.x509.AlgorithmIdentifier find(java.lang.String);
    Code:
       0: getstatic     #437                // Field digestNameToOids:Ljava/util/Map;
       3: aload_1
       4: invokeinterface #454,  2          // InterfaceMethod java/util/Map.get:(Ljava/lang/Object;)Ljava/lang/Object;
       9: checkcast     #205                // class org/bouncycastle/asn1/ASN1ObjectIdentifier
      12: astore_2
      13: aload_2
      14: ifnull        23
      17: aload_0
      18: aload_2
      19: invokevirtual #453                // Method find:(Lorg/bouncycastle/asn1/ASN1ObjectIdentifier;)Lorg/bouncycastle/asn1/x509/AlgorithmIdentifier;
      22: areturn
      23: aload_0
      24: new           #205                // class org/bouncycastle/asn1/ASN1ObjectIdentifier
      27: dup
      28: aload_1
      29: invokespecial #444                // Method org/bouncycastle/asn1/ASN1ObjectIdentifier."<init>":(Ljava/lang/String;)V
      32: invokevirtual #453                // Method find:(Lorg/bouncycastle/asn1/ASN1ObjectIdentifier;)Lorg/bouncycastle/asn1/x509/AlgorithmIdentifier;
      35: areturn
      36: astore_3
      37: aconst_null
      38: areturn
    Exception table:
       from    to  target type
          23    35    36   Class java/lang/IllegalArgumentException

  static {};
    Code:
       0: new           #202                // class java/util/HashMap
       3: dup
       4: invokespecial #442                // Method java/util/HashMap."<init>":()V
       7: putstatic     #439                // Field digestOids:Ljava/util/Map;
      10: new           #202                // class java/util/HashMap
      13: dup
      14: invokespecial #442                // Method java/util/HashMap."<init>":()V
      17: putstatic     #437                // Field digestNameToOids:Ljava/util/Map;
      20: new           #202                // class java/util/HashMap
      23: dup
      24: invokespecial #442                // Method java/util/HashMap."<init>":()V
      27: putstatic     #438                // Field digestOidToAlgIds:Ljava/util/Map;
      30: getstatic     #439                // Field digestOids:Ljava/util/Map;
      33: getstatic     #402                // Field org/bouncycastle/asn1/oiw/OIWObjectIdentifiers.dsaWithSHA1:Lorg/bouncycastle/asn1/ASN1ObjectIdentifier;
      36: getstatic     #403                // Field org/bouncycastle/asn1/oiw/OIWObjectIdentifiers.idSHA1:Lorg/bouncycastle/asn1/ASN1ObjectIdentifier;
      39: invokeinterface #455,  3          // InterfaceMethod java/util/Map.put:(Ljava/lang/Object;Ljava/lang/Object;)Ljava/lang/Object;
      44: pop
      45: getstatic     #439                // Field digestOids:Ljava/util/Map;
      48: getstatic     #405                // Field org/bouncycastle/asn1/oiw/OIWObjectIdentifiers.md4WithRSAEncryption:Lorg/bouncycastle/asn1/ASN1ObjectIdentifier;
      51: getstatic     #410                // Field org/bouncycastle/asn1/pkcs/PKCSObjectIdentifiers.md4:Lorg/bouncycastle/asn1/ASN1ObjectIdentifier;
      54: invokeinterface #455,  3          // InterfaceMethod java/util/Map.put:(Ljava/lang/Object;Ljava/lang/Object;)Ljava/lang/Object;
      59: pop
      60: getstatic     #439                // Field digestOids:Ljava/util/Map;
      63: getstatic     #404                // Field org/bouncycastle/asn1/oiw/OIWObjectIdentifiers.md4WithRSA:Lorg/bouncycastle/asn1/ASN1ObjectIdentifier;
      66: getstatic     #410                // Field org/bouncycastle/asn1/pkcs/PKCSObjectIdentifiers.md4:Lorg/bouncycastle/asn1/ASN1ObjectIdentifier;
      69: invokeinterface #455,  3          // InterfaceMethod java/util/Map.put:(Ljava/lang/Object;Ljava/lang/Object;)Ljava/lang/Object;
      74: pop
      75: getstatic     #439                // Field digestOids:Ljava/util/Map;
      78: getstatic     #406                // Field org/bouncycastle/asn1/oiw/OIWObjectIdentifiers.sha1WithRSA:Lorg/bouncycastle/asn1/ASN1ObjectIdentifier;
      81: getstatic     #403                // Field org/bouncycastle/asn1/oiw/OIWObjectIdentifiers.idSHA1:Lorg/bouncycastle/asn1/ASN1ObjectIdentifier;
      84: invokeinterface #455,  3          // InterfaceMethod java/util/Map.put:(Ljava/lang/Object;Ljava/lang/Object;)Ljava/lang/Object;
      89: pop
      90: getstatic     #439                // Field digestOids:Ljava/util/Map;
      93: getstatic     #415                // Field org/bouncycastle/asn1/pkcs/PKCSObjectIdentifiers.sha224WithRSAEncryption:Lorg/bouncycastle/asn1/ASN1ObjectIdentifier;
      96: getstatic     #389                // Field org/bouncycastle/asn1/nist/NISTObjectIdentifiers.id_sha224:Lorg/bouncycastle/asn1/ASN1ObjectIdentifier;
      99: invokeinterface #455,  3          // InterfaceMethod java/util/Map.put:(Ljava/lang/Object;Ljava/lang/Object;)Ljava/lang/Object;
     104: pop
     105: getstatic     #439                // Field digestOids:Ljava/util/Map;
     108: getstatic     #416                // Field org/bouncycastle/asn1/pkcs/PKCSObjectIdentifiers.sha256WithRSAEncryption:Lorg/bouncycastle/asn1/ASN1ObjectIdentifier;
     111: getstatic     #390                // Field org/bouncycastle/asn1/nist/NISTObjectIdentifiers.id_sha256:Lorg/bouncycastle/asn1/ASN1ObjectIdentifier;
     114: invokeinterface #455,  3          // InterfaceMethod java/util/Map.put:(Ljava/lang/Object;Ljava/lang/Object;)Ljava/lang/Object;
     119: pop
     120: getstatic     #439                // Field digestOids:Ljava/util/Map;
     123: getstatic     #417                // Field org/bouncycastle/asn1/pkcs/PKCSObjectIdentifiers.sha384WithRSAEncryption:Lorg/bouncycastle/asn1/ASN1ObjectIdentifier;
     126: getstatic     #391                // Field org/bouncycastle/asn1/nist/NISTObjectIdentifiers.id_sha384:Lorg/bouncycastle/asn1/ASN1ObjectIdentifier;
     129: invokeinterface #455,  3          // InterfaceMethod java/util/Map.put:(Ljava/lang/Object;Ljava/lang/Object;)Ljava/lang/Object;
     134: pop
     135: getstatic     #439                // Field digestOids:Ljava/util/Map;
     138: getstatic     #418                // Field org/bouncycastle/asn1/pkcs/PKCSObjectIdentifiers.sha512WithRSAEncryption:Lorg/bouncycastle/asn1/ASN1ObjectIdentifier;
     141: getstatic     #396                // Field org/bouncycastle/asn1/nist/NISTObjectIdentifiers.id_sha512:Lorg/bouncycastle/asn1/ASN1ObjectIdentifier;
     144: invokeinterface #455,  3          // InterfaceMethod java/util/Map.put:(Ljava/lang/Object;Ljava/lang/Object;)Ljava/lang/Object;
     149: pop
     150: getstatic     #439                // Field digestOids:Ljava/util/Map;
     153: getstatic     #419                // Field org/bouncycastle/asn1/pkcs/PKCSObjectIdentifiers.sha512_224WithRSAEncryption:Lorg/bouncycastle/asn1/ASN1ObjectIdentifier;
     156: getstatic     #397                // Field org/bouncycastle/asn1/nist/NISTObjectIdentifiers.id_sha512_224:Lorg/bouncycastle/asn1/ASN1ObjectIdentifier;
     159: invokeinterface #455,  3          // InterfaceMethod java/util/Map.put:(Ljava/lang/Object;Ljava/lang/Object;)Ljava/lang/Object;
     164: pop
     165: getstatic     #439                // Field digestOids:Ljava/util/Map;
     168: getstatic     #420                // Field org/bouncycastle/asn1/pkcs/PKCSObjectIdentifiers.sha512_256WithRSAEncryption:Lorg/bouncycastle/asn1/ASN1ObjectIdentifier;
     171: getstatic     #398                // Field org/bouncycastle/asn1/nist/NISTObjectIdentifiers.id_sha512_256:Lorg/bouncycastle/asn1/ASN1ObjectIdentifier;
     174: invokeinterface #455,  3          // InterfaceMethod java/util/Map.put:(Ljava/lang/Object;Ljava/lang/Object;)Ljava/lang/Object;
     179: pop
     180: getstatic     #439                // Field digestOids:Ljava/util/Map;
     183: getstatic     #409                // Field org/bouncycastle/asn1/pkcs/PKCSObjectIdentifiers.md2WithRSAEncryption:Lorg/bouncycastle/asn1/ASN1ObjectIdentifier;
     186: getstatic     #408                // Field org/bouncycastle/asn1/pkcs/PKCSObjectIdentifiers.md2:Lorg/bouncycastle/asn1/ASN1ObjectIdentifier;
     189: invokeinterface #455,  3          // InterfaceMethod java/util/Map.put:(Ljava/lang/Object;Ljava/lang/Object;)Ljava/lang/Object;
     194: pop
     195: getstatic     #439                // Field digestOids:Ljava/util/Map;
     198: getstatic     #411                // Field org/bouncycastle/asn1/pkcs/PKCSObjectIdentifiers.md4WithRSAEncryption:Lorg/bouncycastle/asn1/ASN1ObjectIdentifier;
     201: getstatic     #410                // Field org/bouncycastle/asn1/pkcs/PKCSObjectIdentifiers.md4:Lorg/bouncycastle/asn1/ASN1ObjectIdentifier;
     204: invokeinterface #455,  3          // InterfaceMethod java/util/Map.put:(Ljava/lang/Object;Ljava/lang/Object;)Ljava/lang/Object;
     209: pop
     210: getstatic     #439                // Field digestOids:Ljava/util/Map;
     213: getstatic     #413                // Field org/bouncycastle/asn1/pkcs/PKCSObjectIdentifiers.md5WithRSAEncryption:Lorg/bouncycastle/asn1/ASN1ObjectIdentifier;
     216: getstatic     #412                // Field org/bouncycastle/asn1/pkcs/PKCSObjectIdentifiers.md5:Lorg/bouncycastle/asn1/ASN1ObjectIdentifier;
     219: invokeinterface #455,  3          // InterfaceMethod java/util/Map.put:(Ljava/lang/Object;Ljava/lang/Object;)Ljava/lang/Object;
     224: pop
     225: getstatic     #439                // Field digestOids:Ljava/util/Map;
     228: getstatic     #414                // Field org/bouncycastle/asn1/pkcs/PKCSObjectIdentifiers.sha1WithRSAEncryption:Lorg/bouncycastle/asn1/ASN1ObjectIdentifier;
     231: getstatic     #403                // Field org/bouncycastle/asn1/oiw/OIWObjectIdentifiers.idSHA1:Lorg/bouncycastle/asn1/ASN1ObjectIdentifier;
     234: invokeinterface #455,  3          // InterfaceMethod java/util/Map.put:(Ljava/lang/Object;Ljava/lang/Object;)Ljava/lang/Object;
     239: pop
     240: getstatic     #439                // Field digestOids:Ljava/util/Map;
     243: getstatic     #431                // Field org/bouncycastle/asn1/x9/X9ObjectIdentifiers.ecdsa_with_SHA1:Lorg/bouncycastle/asn1/ASN1ObjectIdentifier;
     246: getstatic     #403                // Field org/bouncycastle/asn1/oiw/OIWObjectIdentifiers.idSHA1:Lorg/bouncycastle/asn1/ASN1ObjectIdentifier;
     249: invokeinterface #455,  3          // InterfaceMethod java/util/Map.put:(Ljava/lang/Object;Ljava/lang/Object;)Ljava/lang/Object;
     254: pop
     255: getstatic     #439                // Field digestOids:Ljava/util/Map;
     258: getstatic     #432                // Field org/bouncycastle/asn1/x9/X9ObjectIdentifiers.ecdsa_with_SHA224:Lorg/bouncycastle/asn1/ASN1ObjectIdentifier;
     261: getstatic     #389                // Field org/bouncycastle/asn1/nist/NISTObjectIdentifiers.id_sha224:Lorg/bouncycastle/asn1/ASN1ObjectIdentifier;
     264: invokeinterface #455,  3          // InterfaceMethod java/util/Map.put:(Ljava/lang/Object;Ljava/lang/Object;)Ljava/lang/Object;
     269: pop
     270: getstatic     #439                // Field digestOids:Ljava/util/Map;
     273: getstatic     #433                // Field org/bouncycastle/asn1/x9/X9ObjectIdentifiers.ecdsa_with_SHA256:Lorg/bouncycastle/asn1/ASN1ObjectIdentifier;
     276: getstatic     #390                // Field org/bouncycastle/asn1/nist/NISTObjectIdentifiers.id_sha256:Lorg/bouncycastle/asn1/ASN1ObjectIdentifier;
     279: invokeinterface #455,  3          // InterfaceMethod java/util/Map.put:(Ljava/lang/Object;Ljava/lang/Object;)Ljava/lang/Object;
     284: pop
     285: getstatic     #439                // Field digestOids:Ljava/util/Map;
     288: getstatic     #434                // Field org/bouncycastle/asn1/x9/X9ObjectIdentifiers.ecdsa_with_SHA384:Lorg/bouncycastle/asn1/ASN1ObjectIdentifier;
     291: getstatic     #391                // Field org/bouncycastle/asn1/nist/NISTObjectIdentifiers.id_sha384:Lorg/bouncycastle/asn1/ASN1ObjectIdentifier;
     294: invokeinterface #455,  3          // InterfaceMethod java/util/Map.put:(Ljava/lang/Object;Ljava/lang/Object;)Ljava/lang/Object;
     299: pop
     300: getstatic     #439                // Field digestOids:Ljava/util/Map;
     303: getstatic     #435                // Field org/bouncycastle/asn1/x9/X9ObjectIdentifiers.ecdsa_with_SHA512:Lorg/bouncycastle/asn1/ASN1ObjectIdentifier;
     306: getstatic     #396                // Field org/bouncycastle/asn1/nist/NISTObjectIdentifiers.id_sha512:Lorg/bouncycastle/asn1/ASN1ObjectIdentifier;
     309: invokeinterface #455,  3          // InterfaceMethod java/util/Map.put:(Ljava/lang/Object;Ljava/lang/Object;)Ljava/lang/Object;
     314: pop
     315: getstatic     #439                // Field digestOids:Ljava/util/Map;
     318: getstatic     #436                // Field org/bouncycastle/asn1/x9/X9ObjectIdentifiers.id_dsa_with_sha1:Lorg/bouncycastle/asn1/ASN1ObjectIdentifier;
     321: getstatic     #403                // Field org/bouncycastle/asn1/oiw/OIWObjectIdentifiers.idSHA1:Lorg/bouncycastle/asn1/ASN1ObjectIdentifier;
     324: invokeinterface #455,  3          // InterfaceMethod java/util/Map.put:(Ljava/lang/Object;Ljava/lang/Object;)Ljava/lang/Object;
     329: pop
     330: getstatic     #439                // Field digestOids:Ljava/util/Map;
     333: getstatic     #351                // Field org/bouncycastle/asn1/bsi/BSIObjectIdentifiers.ecdsa_plain_SHA1:Lorg/bouncycastle/asn1/ASN1ObjectIdentifier;
     336: getstatic     #403                // Field org/bouncycastle/asn1/oiw/OIWObjectIdentifiers.idSHA1:Lorg/bouncycastle/asn1/ASN1ObjectIdentifier;
     339: invokeinterface #455,  3          // InterfaceMethod java/util/Map.put:(Ljava/lang/Object;Ljava/lang/Object;)Ljava/lang/Object;
     344: pop
     345: getstatic     #439                // Field digestOids:Ljava/util/Map;
     348: getstatic     #352                // Field org/bouncycastle/asn1/bsi/BSIObjectIdentifiers.ecdsa_plain_SHA224:Lorg/bouncycastle/asn1/ASN1ObjectIdentifier;
     351: getstatic     #389                // Field org/bouncycastle/asn1/nist/NISTObjectIdentifiers.id_sha224:Lorg/bouncycastle/asn1/ASN1ObjectIdentifier;
     354: invokeinterface #455,  3          // InterfaceMethod java/util/Map.put:(Ljava/lang/Object;Ljava/lang/Object;)Ljava/lang/Object;
     359: pop
     360: getstatic     #439                // Field digestOids:Ljava/util/Map;
     363: getstatic     #353                // Field org/bouncycastle/asn1/bsi/BSIObjectIdentifiers.ecdsa_plain_SHA256:Lorg/bouncycastle/asn1/ASN1ObjectIdentifier;
     366: getstatic     #390                // Field org/bouncycastle/asn1/nist/NISTObjectIdentifiers.id_sha256:Lorg/bouncycastle/asn1/ASN1ObjectIdentifier;
     369: invokeinterface #455,  3          // InterfaceMethod java/util/Map.put:(Ljava/lang/Object;Ljava/lang/Object;)Ljava/lang/Object;
     374: pop
     375: getstatic     #439                // Field digestOids:Ljava/util/Map;
     378: getstatic     #354                // Field org/bouncycastle/asn1/bsi/BSIObjectIdentifiers.ecdsa_plain_SHA384:Lorg/bouncycastle/asn1/ASN1ObjectIdentifier;
     381: getstatic     #391                // Field org/bouncycastle/asn1/nist/NISTObjectIdentifiers.id_sha384:Lorg/bouncycastle/asn1/ASN1ObjectIdentifier;
     384: invokeinterface #455,  3          // InterfaceMethod java/util/Map.put:(Ljava/lang/Object;Ljava/lang/Object;)Ljava/lang/Object;
     389: pop
     390: getstatic     #439                // Field digestOids:Ljava/util/Map;
     393: getstatic     #355                // Field org/bouncycastle/asn1/bsi/BSIObjectIdentifiers.ecdsa_plain_SHA512:Lorg/bouncycastle/asn1/ASN1ObjectIdentifier;
     396: getstatic     #396                // Field org/bouncycastle/asn1/nist/NISTObjectIdentifiers.id_sha512:Lorg/bouncycastle/asn1/ASN1ObjectIdentifier;
     399: invokeinterface #455,  3          // InterfaceMethod java/util/Map.put:(Ljava/lang/Object;Ljava/lang/Object;)Ljava/lang/Object;
     404: pop
     405: getstatic     #439                // Field digestOids:Ljava/util/Map;
     408: getstatic     #350                // Field org/bouncycastle/asn1/bsi/BSIObjectIdentifiers.ecdsa_plain_RIPEMD160:Lorg/bouncycastle/asn1/ASN1ObjectIdentifier;
     411: getstatic     #426                // Field org/bouncycastle/asn1/teletrust/TeleTrusTObjectIdentifiers.ripemd160:Lorg/bouncycastle/asn1/ASN1ObjectIdentifier;
     414: invokeinterface #455,  3          // InterfaceMethod java/util/Map.put:(Ljava/lang/Object;Ljava/lang/Object;)Ljava/lang/Object;
     419: pop
     420: getstatic     #439                // Field digestOids:Ljava/util/Map;
     423: getstatic     #363                // Field org/bouncycastle/asn1/eac/EACObjectIdentifiers.id_TA_ECDSA_SHA_1:Lorg/bouncycastle/asn1/ASN1ObjectIdentifier;
     426: getstatic     #403                // Field org/bouncycastle/asn1/oiw/OIWObjectIdentifiers.idSHA1:Lorg/bouncycastle/asn1/ASN1ObjectIdentifier;
     429: invokeinterface #455,  3          // InterfaceMethod java/util/Map.put:(Ljava/lang/Object;Ljava/lang/Object;)Ljava/lang/Object;
     434: pop
     435: getstatic     #439                // Field digestOids:Ljava/util/Map;
     438: getstatic     #364                // Field org/bouncycastle/asn1/eac/EACObjectIdentifiers.id_TA_ECDSA_SHA_224:Lorg/bouncycastle/asn1/ASN1ObjectIdentifier;
     441: getstatic     #389                // Field org/bouncycastle/asn1/nist/NISTObjectIdentifiers.id_sha224:Lorg/bouncycastle/asn1/ASN1ObjectIdentifier;
     444: invokeinterface #455,  3          // InterfaceMethod java/util/Map.put:(Ljava/lang/Object;Ljava/lang/Object;)Ljava/lang/Object;
     449: pop
     450: getstatic     #439                // Field digestOids:Ljava/util/Map;
     453: getstatic     #365                // Field org/bouncycastle/asn1/eac/EACObjectIdentifiers.id_TA_ECDSA_SHA_256:Lorg/bouncycastle/asn1/ASN1ObjectIdentifier;
     456: getstatic     #390                // Field org/bouncycastle/asn1/nist/NISTObjectIdentifiers.id_sha256:Lorg/bouncycastle/asn1/ASN1ObjectIdentifier;
     459: invokeinterface #455,  3          // InterfaceMethod java/util/Map.put:(Ljava/lang/Object;Ljava/lang/Object;)Ljava/lang/Object;
     464: pop
     465: getstatic     #439                // Field digestOids:Ljava/util/Map;
     468: getstatic     #366                // Field org/bouncycastle/asn1/eac/EACObjectIdentifiers.id_TA_ECDSA_SHA_384:Lorg/bouncycastle/asn1/ASN1ObjectIdentifier;
     471: getstatic     #391                // Field org/bouncycastle/asn1/nist/NISTObjectIdentifiers.id_sha384:Lorg/bouncycastle/asn1/ASN1ObjectIdentifier;
     474: invokeinterface #455,  3          // InterfaceMethod java/util/Map.put:(Ljava/lang/Object;Ljava/lang/Object;)Ljava/lang/Object;
     479: pop
     480: getstatic     #439                // Field digestOids:Ljava/util/Map;
     483: getstatic     #367                // Field org/bouncycastle/asn1/eac/EACObjectIdentifiers.id_TA_ECDSA_SHA_512:Lorg/bouncycastle/asn1/ASN1ObjectIdentifier;
     486: getstatic     #396                // Field org/bouncycastle/asn1/nist/NISTObjectIdentifiers.id_sha512:Lorg/bouncycastle/asn1/ASN1ObjectIdentifier;
     489: invokeinterface #455,  3          // InterfaceMethod java/util/Map.put:(Ljava/lang/Object;Ljava/lang/Object;)Ljava/lang/Object;
     494: pop
     495: getstatic     #439                // Field digestOids:Ljava/util/Map;
     498: getstatic     #373                // Field org/bouncycastle/asn1/nist/NISTObjectIdentifiers.dsa_with_sha224:Lorg/bouncycastle/asn1/ASN1ObjectIdentifier;
     501: getstatic     #389                // Field org/bouncycastle/asn1/nist/NISTObjectIdentifiers.id_sha224:Lorg/bouncycastle/asn1/ASN1ObjectIdentifier;
     504: invokeinterface #455,  3          // InterfaceMethod java/util/Map.put:(Ljava/lang/Object;Ljava/lang/Object;)Ljava/lang/Object;
     509: pop
     510: getstatic     #439                // Field digestOids:Ljava/util/Map;
     513: getstatic     #374                // Field org/bouncycastle/asn1/nist/NISTObjectIdentifiers.dsa_with_sha256:Lorg/bouncycastle/asn1/ASN1ObjectIdentifier;
     516: getstatic     #390                // Field org/bouncycastle/asn1/nist/NISTObjectIdentifiers.id_sha256:Lorg/bouncycastle/asn1/ASN1ObjectIdentifier;
     519: invokeinterface #455,  3          // InterfaceMethod java/util/Map.put:(Ljava/lang/Object;Ljava/lang/Object;)Ljava/lang/Object;
     524: pop
     525: getstatic     #439                // Field digestOids:Ljava/util/Map;
     528: getstatic     #375                // Field org/bouncycastle/asn1/nist/NISTObjectIdentifiers.dsa_with_sha384:Lorg/bouncycastle/asn1/ASN1ObjectIdentifier;
     531: getstatic     #391                // Field org/bouncycastle/asn1/nist/NISTObjectIdentifiers.id_sha384:Lorg/bouncycastle/asn1/ASN1ObjectIdentifier;
     534: invokeinterface #455,  3          // InterfaceMethod java/util/Map.put:(Ljava/lang/Object;Ljava/lang/Object;)Ljava/lang/Object;
     539: pop
     540: getstatic     #439                // Field digestOids:Ljava/util/Map;
     543: getstatic     #376                // Field org/bouncycastle/asn1/nist/NISTObjectIdentifiers.dsa_with_sha512:Lorg/bouncycastle/asn1/ASN1ObjectIdentifier;
     546: getstatic     #396                // Field org/bouncycastle/asn1/nist/NISTObjectIdentifiers.id_sha512:Lorg/bouncycastle/asn1/ASN1ObjectIdentifier;
     549: invokeinterface #455,  3          // InterfaceMethod java/util/Map.put:(Ljava/lang/Object;Ljava/lang/Object;)Ljava/lang/Object;
     554: pop
     555: getstatic     #439                // Field digestOids:Ljava/util/Map;
     558: getstatic     #385                // Field org/bouncycastle/asn1/nist/NISTObjectIdentifiers.id_rsassa_pkcs1_v1_5_with_sha3_224:Lorg/bouncycastle/asn1/ASN1ObjectIdentifier;
     561: getstatic     #392                // Field org/bouncycastle/asn1/nist/NISTObjectIdentifiers.id_sha3_224:Lorg/bouncycastle/asn1/ASN1ObjectIdentifier;
     564: invokeinterface #455,  3          // InterfaceMethod java/util/Map.put:(Ljava/lang/Object;Ljava/lang/Object;)Ljava/lang/Object;
     569: pop
     570: getstatic     #439                // Field digestOids:Ljava/util/Map;
     573: getstatic     #386                // Field org/bouncycastle/asn1/nist/NISTObjectIdentifiers.id_rsassa_pkcs1_v1_5_with_sha3_256:Lorg/bouncycastle/asn1/ASN1ObjectIdentifier;
     576: getstatic     #393                // Field org/bouncycastle/asn1/nist/NISTObjectIdentifiers.id_sha3_256:Lorg/bouncycastle/asn1/ASN1ObjectIdentifier;
     579: invokeinterface #455,  3          // InterfaceMethod java/util/Map.put:(Ljava/lang/Object;Ljava/lang/Object;)Ljava/lang/Object;
     584: pop
     585: getstatic     #439                // Field digestOids:Ljava/util/Map;
     588: getstatic     #387                // Field org/bouncycastle/asn1/nist/NISTObjectIdentifiers.id_rsassa_pkcs1_v1_5_with_sha3_384:Lorg/bouncycastle/asn1/ASN1ObjectIdentifier;
     591: getstatic     #394                // Field org/bouncycastle/asn1/nist/NISTObjectIdentifiers.id_sha3_384:Lorg/bouncycastle/asn1/ASN1ObjectIdentifier;
     594: invokeinterface #455,  3          // InterfaceMethod java/util/Map.put:(Ljava/lang/Object;Ljava/lang/Object;)Ljava/lang/Object;
     599: pop
     600: getstatic     #439                // Field digestOids:Ljava/util/Map;
     603: getstatic     #388                // Field org/bouncycastle/asn1/nist/NISTObjectIdentifiers.id_rsassa_pkcs1_v1_5_with_sha3_512:Lorg/bouncycastle/asn1/ASN1ObjectIdentifier;
     606: getstatic     #395                // Field org/bouncycastle/asn1/nist/NISTObjectIdentifiers.id_sha3_512:Lorg/bouncycastle/asn1/ASN1ObjectIdentifier;
     609: invokeinterface #455,  3          // InterfaceMethod java/util/Map.put:(Ljava/lang/Object;Ljava/lang/Object;)Ljava/lang/Object;
     614: pop
     615: getstatic     #439                // Field digestOids:Ljava/util/Map;
     618: getstatic     #377                // Field org/bouncycastle/asn1/nist/NISTObjectIdentifiers.id_dsa_with_sha3_224:Lorg/bouncycastle/asn1/ASN1ObjectIdentifier;
     621: getstatic     #392                // Field org/bouncycastle/asn1/nist/NISTObjectIdentifiers.id_sha3_224:Lorg/bouncycastle/asn1/ASN1ObjectIdentifier;
     624: invokeinterface #455,  3          // InterfaceMethod java/util/Map.put:(Ljava/lang/Object;Ljava/lang/Object;)Ljava/lang/Object;
     629: pop
     630: getstatic     #439                // Field digestOids:Ljava/util/Map;
     633: getstatic     #378                // Field org/bouncycastle/asn1/nist/NISTObjectIdentifiers.id_dsa_with_sha3_256:Lorg/bouncycastle/asn1/ASN1ObjectIdentifier;
     636: getstatic     #393                // Field org/bouncycastle/asn1/nist/NISTObjectIdentifiers.id_sha3_256:Lorg/bouncycastle/asn1/ASN1ObjectIdentifier;
     639: invokeinterface #455,  3          // InterfaceMethod java/util/Map.put:(Ljava/lang/Object;Ljava/lang/Object;)Ljava/lang/Object;
     644: pop
     645: getstatic     #439                // Field digestOids:Ljava/util/Map;
     648: getstatic     #379                // Field org/bouncycastle/asn1/nist/NISTObjectIdentifiers.id_dsa_with_sha3_384:Lorg/bouncycastle/asn1/ASN1ObjectIdentifier;
     651: getstatic     #394                // Field org/bouncycastle/asn1/nist/NISTObjectIdentifiers.id_sha3_384:Lorg/bouncycastle/asn1/ASN1ObjectIdentifier;
     654: invokeinterface #455,  3          // InterfaceMethod java/util/Map.put:(Ljava/lang/Object;Ljava/lang/Object;)Ljava/lang/Object;
     659: pop
     660: getstatic     #439                // Field digestOids:Ljava/util/Map;
     663: getstatic     #380                // Field org/bouncycastle/asn1/nist/NISTObjectIdentifiers.id_dsa_with_sha3_512:Lorg/bouncycastle/asn1/ASN1ObjectIdentifier;
     666: getstatic     #395                // Field org/bouncycastle/asn1/nist/NISTObjectIdentifiers.id_sha3_512:Lorg/bouncycastle/asn1/ASN1ObjectIdentifier;
     669: invokeinterface #455,  3          // InterfaceMethod java/util/Map.put:(Ljava/lang/Object;Ljava/lang/Object;)Ljava/lang/Object;
     674: pop
     675: getstatic     #439                // Field digestOids:Ljava/util/Map;
     678: getstatic     #381                // Field org/bouncycastle/asn1/nist/NISTObjectIdentifiers.id_ecdsa_with_sha3_224:Lorg/bouncycastle/asn1/ASN1ObjectIdentifier;
     681: getstatic     #392                // Field org/bouncycastle/asn1/nist/NISTObjectIdentifiers.id_sha3_224:Lorg/bouncycastle/asn1/ASN1ObjectIdentifier;
     684: invokeinterface #455,  3          // InterfaceMethod java/util/Map.put:(Ljava/lang/Object;Ljava/lang/Object;)Ljava/lang/Object;
     689: pop
     690: getstatic     #439                // Field digestOids:Ljava/util/Map;
     693: getstatic     #382                // Field org/bouncycastle/asn1/nist/NISTObjectIdentifiers.id_ecdsa_with_sha3_256:Lorg/bouncycastle/asn1/ASN1ObjectIdentifier;
     696: getstatic     #393                // Field org/bouncycastle/asn1/nist/NISTObjectIdentifiers.id_sha3_256:Lorg/bouncycastle/asn1/ASN1ObjectIdentifier;
     699: invokeinterface #455,  3          // InterfaceMethod java/util/Map.put:(Ljava/lang/Object;Ljava/lang/Object;)Ljava/lang/Object;
     704: pop
     705: getstatic     #439                // Field digestOids:Ljava/util/Map;
     708: getstatic     #383                // Field org/bouncycastle/asn1/nist/NISTObjectIdentifiers.id_ecdsa_with_sha3_384:Lorg/bouncycastle/asn1/ASN1ObjectIdentifier;
     711: getstatic     #394                // Field org/bouncycastle/asn1/nist/NISTObjectIdentifiers.id_sha3_384:Lorg/bouncycastle/asn1/ASN1ObjectIdentifier;
     714: invokeinterface #455,  3          // InterfaceMethod java/util/Map.put:(Ljava/lang/Object;Ljava/lang/Object;)Ljava/lang/Object;
     719: pop
     720: getstatic     #439                // Field digestOids:Ljava/util/Map;
     723: getstatic     #384                // Field org/bouncycastle/asn1/nist/NISTObjectIdentifiers.id_ecdsa_with_sha3_512:Lorg/bouncycastle/asn1/ASN1ObjectIdentifier;
     726: getstatic     #395                // Field org/bouncycastle/asn1/nist/NISTObjectIdentifiers.id_sha3_512:Lorg/bouncycastle/asn1/ASN1ObjectIdentifier;
     729: invokeinterface #455,  3          // InterfaceMethod java/util/Map.put:(Ljava/lang/Object;Ljava/lang/Object;)Ljava/lang/Object;
     734: pop
     735: getstatic     #439                // Field digestOids:Ljava/util/Map;
     738: getstatic     #428                // Field org/bouncycastle/asn1/teletrust/TeleTrusTObjectIdentifiers.rsaSignatureWithripemd128:Lorg/bouncycastle/asn1/ASN1ObjectIdentifier;
     741: getstatic     #425                // Field org/bouncycastle/asn1/teletrust/TeleTrusTObjectIdentifiers.ripemd128:Lorg/bouncycastle/asn1/ASN1ObjectIdentifier;
     744: invokeinterface #455,  3          // InterfaceMethod java/util/Map.put:(Ljava/lang/Object;Ljava/lang/Object;)Ljava/lang/Object;
     749: pop
     750: getstatic     #439                // Field digestOids:Ljava/util/Map;
     753: getstatic     #429                // Field org/bouncycastle/asn1/teletrust/TeleTrusTObjectIdentifiers.rsaSignatureWithripemd160:Lorg/bouncycastle/asn1/ASN1ObjectIdentifier;
     756: getstatic     #426                // Field org/bouncycastle/asn1/teletrust/TeleTrusTObjectIdentifiers.ripemd160:Lorg/bouncycastle/asn1/ASN1ObjectIdentifier;
     759: invokeinterface #455,  3          // InterfaceMethod java/util/Map.put:(Ljava/lang/Object;Ljava/lang/Object;)Ljava/lang/Object;
     764: pop
     765: getstatic     #439                // Field digestOids:Ljava/util/Map;
     768: getstatic     #430                // Field org/bouncycastle/asn1/teletrust/TeleTrusTObjectIdentifiers.rsaSignatureWithripemd256:Lorg/bouncycastle/asn1/ASN1ObjectIdentifier;
     771: getstatic     #427                // Field org/bouncycastle/asn1/teletrust/TeleTrusTObjectIdentifiers.ripemd256:Lorg/bouncycastle/asn1/ASN1ObjectIdentifier;
     774: invokeinterface #455,  3          // InterfaceMethod java/util/Map.put:(Ljava/lang/Object;Ljava/lang/Object;)Ljava/lang/Object;
     779: pop
     780: getstatic     #439                // Field digestOids:Ljava/util/Map;
     783: getstatic     #362                // Field org/bouncycastle/asn1/cryptopro/CryptoProObjectIdentifiers.gostR3411_94_with_gostR3410_94:Lorg/bouncycastle/asn1/ASN1ObjectIdentifier;
     786: getstatic     #360                // Field org/bouncycastle/asn1/cryptopro/CryptoProObjectIdentifiers.gostR3411:Lorg/bouncycastle/asn1/ASN1ObjectIdentifier;
     789: invokeinterface #455,  3          // InterfaceMethod java/util/Map.put:(Ljava/lang/Object;Ljava/lang/Object;)Ljava/lang/Object;
     794: pop
     795: getstatic     #439                // Field digestOids:Ljava/util/Map;
     798: getstatic     #361                // Field org/bouncycastle/asn1/cryptopro/CryptoProObjectIdentifiers.gostR3411_94_with_gostR3410_2001:Lorg/bouncycastle/asn1/ASN1ObjectIdentifier;
     801: getstatic     #360                // Field org/bouncycastle/asn1/cryptopro/CryptoProObjectIdentifiers.gostR3411:Lorg/bouncycastle/asn1/ASN1ObjectIdentifier;
     804: invokeinterface #455,  3          // InterfaceMethod java/util/Map.put:(Ljava/lang/Object;Ljava/lang/Object;)Ljava/lang/Object;
     809: pop
     810: getstatic     #439                // Field digestOids:Ljava/util/Map;
     813: getstatic     #423                // Field org/bouncycastle/asn1/rosstandart/RosstandartObjectIdentifiers.id_tc26_signwithdigest_gost_3410_12_256:Lorg/bouncycastle/asn1/ASN1ObjectIdentifier;
     816: getstatic     #421                // Field org/bouncycastle/asn1/rosstandart/RosstandartObjectIdentifiers.id_tc26_gost_3411_12_256:Lorg/bouncycastle/asn1/ASN1ObjectIdentifier;
     819: invokeinterface #455,  3          // InterfaceMethod java/util/Map.put:(Ljava/lang/Object;Ljava/lang/Object;)Ljava/lang/Object;
     824: pop
     825: getstatic     #439                // Field digestOids:Ljava/util/Map;
     828: getstatic     #424                // Field org/bouncycastle/asn1/rosstandart/RosstandartObjectIdentifiers.id_tc26_signwithdigest_gost_3410_12_512:Lorg/bouncycastle/asn1/ASN1ObjectIdentifier;
     831: getstatic     #422                // Field org/bouncycastle/asn1/rosstandart/RosstandartObjectIdentifiers.id_tc26_gost_3411_12_512:Lorg/bouncycastle/asn1/ASN1ObjectIdentifier;
     834: invokeinterface #455,  3          // InterfaceMethod java/util/Map.put:(Ljava/lang/Object;Ljava/lang/Object;)Ljava/lang/Object;
     839: pop
     840: getstatic     #439                // Field digestOids:Ljava/util/Map;
     843: getstatic     #348                // Field org/bouncycastle/asn1/bc/BCObjectIdentifiers.sphincs256_with_SHA3_512:Lorg/bouncycastle/asn1/ASN1ObjectIdentifier;
     846: getstatic     #395                // Field org/bouncycastle/asn1/nist/NISTObjectIdentifiers.id_sha3_512:Lorg/bouncycastle/asn1/ASN1ObjectIdentifier;
     849: invokeinterface #455,  3          // InterfaceMethod java/util/Map.put:(Ljava/lang/Object;Ljava/lang/Object;)Ljava/lang/Object;
     854: pop
     855: getstatic     #439                // Field digestOids:Ljava/util/Map;
     858: getstatic     #349                // Field org/bouncycastle/asn1/bc/BCObjectIdentifiers.sphincs256_with_SHA512:Lorg/bouncycastle/asn1/ASN1ObjectIdentifier;
     861: getstatic     #396                // Field org/bouncycastle/asn1/nist/NISTObjectIdentifiers.id_sha512:Lorg/bouncycastle/asn1/ASN1ObjectIdentifier;
     864: invokeinterface #455,  3          // InterfaceMethod java/util/Map.put:(Ljava/lang/Object;Ljava/lang/Object;)Ljava/lang/Object;
     869: pop
     870: getstatic     #439                // Field digestOids:Ljava/util/Map;
     873: getstatic     #370                // Field org/bouncycastle/asn1/gm/GMObjectIdentifiers.sm2sign_with_sha256:Lorg/bouncycastle/asn1/ASN1ObjectIdentifier;
     876: getstatic     #390                // Field org/bouncycastle/asn1/nist/NISTObjectIdentifiers.id_sha256:Lorg/bouncycastle/asn1/ASN1ObjectIdentifier;
     879: invokeinterface #455,  3          // InterfaceMethod java/util/Map.put:(Ljava/lang/Object;Ljava/lang/Object;)Ljava/lang/Object;
     884: pop
     885: getstatic     #439                // Field digestOids:Ljava/util/Map;
     888: getstatic     #371                // Field org/bouncycastle/asn1/gm/GMObjectIdentifiers.sm2sign_with_sm3:Lorg/bouncycastle/asn1/ASN1ObjectIdentifier;
     891: getstatic     #372                // Field org/bouncycastle/asn1/gm/GMObjectIdentifiers.sm3:Lorg/bouncycastle/asn1/ASN1ObjectIdentifier;
     894: invokeinterface #455,  3          // InterfaceMethod java/util/Map.put:(Ljava/lang/Object;Ljava/lang/Object;)Ljava/lang/Object;
     899: pop
     900: getstatic     #439                // Field digestOids:Ljava/util/Map;
     903: getstatic     #356                // Field org/bouncycastle/asn1/cms/CMSObjectIdentifiers.id_RSASSA_PSS_SHAKE128:Lorg/bouncycastle/asn1/ASN1ObjectIdentifier;
     906: getstatic     #399                // Field org/bouncycastle/asn1/nist/NISTObjectIdentifiers.id_shake128:Lorg/bouncycastle/asn1/ASN1ObjectIdentifier;
     909: invokeinterface #455,  3          // InterfaceMethod java/util/Map.put:(Ljava/lang/Object;Ljava/lang/Object;)Ljava/lang/Object;
     914: pop
     915: getstatic     #439                // Field digestOids:Ljava/util/Map;
     918: getstatic     #357                // Field org/bouncycastle/asn1/cms/CMSObjectIdentifiers.id_RSASSA_PSS_SHAKE256:Lorg/bouncycastle/asn1/ASN1ObjectIdentifier;
     921: getstatic     #400                // Field org/bouncycastle/asn1/nist/NISTObjectIdentifiers.id_shake256:Lorg/bouncycastle/asn1/ASN1ObjectIdentifier;
     924: invokeinterface #455,  3          // InterfaceMethod java/util/Map.put:(Ljava/lang/Object;Ljava/lang/Object;)Ljava/lang/Object;
     929: pop
     930: getstatic     #439                // Field digestOids:Ljava/util/Map;
     933: getstatic     #358                // Field org/bouncycastle/asn1/cms/CMSObjectIdentifiers.id_ecdsa_with_shake128:Lorg/bouncycastle/asn1/ASN1ObjectIdentifier;
     936: getstatic     #399                // Field org/bouncycastle/asn1/nist/NISTObjectIdentifiers.id_shake128:Lorg/bouncycastle/asn1/ASN1ObjectIdentifier;
     939: invokeinterface #455,  3          // InterfaceMethod java/util/Map.put:(Ljava/lang/Object;Ljava/lang/Object;)Ljava/lang/Object;
     944: pop
     945: getstatic     #439                // Field digestOids:Ljava/util/Map;
     948: getstatic     #359                // Field org/bouncycastle/asn1/cms/CMSObjectIdentifiers.id_ecdsa_with_shake256:Lorg/bouncycastle/asn1/ASN1ObjectIdentifier;
     951: getstatic     #400                // Field org/bouncycastle/asn1/nist/NISTObjectIdentifiers.id_shake256:Lorg/bouncycastle/asn1/ASN1ObjectIdentifier;
     954: invokeinterface #455,  3          // InterfaceMethod java/util/Map.put:(Ljava/lang/Object;Ljava/lang/Object;)Ljava/lang/Object;
     959: pop
     960: getstatic     #437                // Field digestNameToOids:Ljava/util/Map;
     963: ldc           #10                 // String SHA-1
     965: getstatic     #403                // Field org/bouncycastle/asn1/oiw/OIWObjectIdentifiers.idSHA1:Lorg/bouncycastle/asn1/ASN1ObjectIdentifier;
     968: invokeinterface #455,  3          // InterfaceMethod java/util/Map.put:(Ljava/lang/Object;Ljava/lang/Object;)Ljava/lang/Object;
     973: pop
     974: getstatic     #437                // Field digestNameToOids:Ljava/util/Map;
     977: ldc           #11                 // String SHA-224
     979: getstatic     #389                // Field org/bouncycastle/asn1/nist/NISTObjectIdentifiers.id_sha224:Lorg/bouncycastle/asn1/ASN1ObjectIdentifier;
     982: invokeinterface #455,  3          // InterfaceMethod java/util/Map.put:(Ljava/lang/Object;Ljava/lang/Object;)Ljava/lang/Object;
     987: pop
     988: getstatic     #437                // Field digestNameToOids:Ljava/util/Map;
     991: ldc           #12                 // String SHA-256
     993: getstatic     #390                // Field org/bouncycastle/asn1/nist/NISTObjectIdentifiers.id_sha256:Lorg/bouncycastle/asn1/ASN1ObjectIdentifier;
     996: invokeinterface #455,  3          // InterfaceMethod java/util/Map.put:(Ljava/lang/Object;Ljava/lang/Object;)Ljava/lang/Object;
    1001: pop
    1002: getstatic     #437                // Field digestNameToOids:Ljava/util/Map;
    1005: ldc           #13                 // String SHA-384
    1007: getstatic     #391                // Field org/bouncycastle/asn1/nist/NISTObjectIdentifiers.id_sha384:Lorg/bouncycastle/asn1/ASN1ObjectIdentifier;
    1010: invokeinterface #455,  3          // InterfaceMethod java/util/Map.put:(Ljava/lang/Object;Ljava/lang/Object;)Ljava/lang/Object;
    1015: pop
    1016: getstatic     #437                // Field digestNameToOids:Ljava/util/Map;
    1019: ldc           #14                 // String SHA-512
    1021: getstatic     #396                // Field org/bouncycastle/asn1/nist/NISTObjectIdentifiers.id_sha512:Lorg/bouncycastle/asn1/ASN1ObjectIdentifier;
    1024: invokeinterface #455,  3          // InterfaceMethod java/util/Map.put:(Ljava/lang/Object;Ljava/lang/Object;)Ljava/lang/Object;
    1029: pop
    1030: getstatic     #437                // Field digestNameToOids:Ljava/util/Map;
    1033: ldc           #15                 // String SHA-512-224
    1035: getstatic     #397                // Field org/bouncycastle/asn1/nist/NISTObjectIdentifiers.id_sha512_224:Lorg/bouncycastle/asn1/ASN1ObjectIdentifier;
    1038: invokeinterface #455,  3          // InterfaceMethod java/util/Map.put:(Ljava/lang/Object;Ljava/lang/Object;)Ljava/lang/Object;
    1043: pop
    1044: getstatic     #437                // Field digestNameToOids:Ljava/util/Map;
    1047: ldc           #16                 // String SHA-512-256
    1049: getstatic     #398                // Field org/bouncycastle/asn1/nist/NISTObjectIdentifiers.id_sha512_256:Lorg/bouncycastle/asn1/ASN1ObjectIdentifier;
    1052: invokeinterface #455,  3          // InterfaceMethod java/util/Map.put:(Ljava/lang/Object;Ljava/lang/Object;)Ljava/lang/Object;
    1057: pop
    1058: getstatic     #437                // Field digestNameToOids:Ljava/util/Map;
    1061: ldc           #17                 // String SHA1
    1063: getstatic     #403                // Field org/bouncycastle/asn1/oiw/OIWObjectIdentifiers.idSHA1:Lorg/bouncycastle/asn1/ASN1ObjectIdentifier;
    1066: invokeinterface #455,  3          // InterfaceMethod java/util/Map.put:(Ljava/lang/Object;Ljava/lang/Object;)Ljava/lang/Object;
    1071: pop
    1072: getstatic     #437                // Field digestNameToOids:Ljava/util/Map;
    1075: ldc           #18                 // String SHA224
    1077: getstatic     #389                // Field org/bouncycastle/asn1/nist/NISTObjectIdentifiers.id_sha224:Lorg/bouncycastle/asn1/ASN1ObjectIdentifier;
    1080: invokeinterface #455,  3          // InterfaceMethod java/util/Map.put:(Ljava/lang/Object;Ljava/lang/Object;)Ljava/lang/Object;
    1085: pop
    1086: getstatic     #437                // Field digestNameToOids:Ljava/util/Map;
    1089: ldc           #19                 // String SHA256
    1091: getstatic     #390                // Field org/bouncycastle/asn1/nist/NISTObjectIdentifiers.id_sha256:Lorg/bouncycastle/asn1/ASN1ObjectIdentifier;
    1094: invokeinterface #455,  3          // InterfaceMethod java/util/Map.put:(Ljava/lang/Object;Ljava/lang/Object;)Ljava/lang/Object;
    1099: pop
    1100: getstatic     #437                // Field digestNameToOids:Ljava/util/Map;
    1103: ldc           #24                 // String SHA384
    1105: getstatic     #391                // Field org/bouncycastle/asn1/nist/NISTObjectIdentifiers.id_sha384:Lorg/bouncycastle/asn1/ASN1ObjectIdentifier;
    1108: invokeinterface #455,  3          // InterfaceMethod java/util/Map.put:(Ljava/lang/Object;Ljava/lang/Object;)Ljava/lang/Object;
    1113: pop
    1114: getstatic     #437                // Field digestNameToOids:Ljava/util/Map;
    1117: ldc           #25                 // String SHA512
    1119: getstatic     #396                // Field org/bouncycastle/asn1/nist/NISTObjectIdentifiers.id_sha512:Lorg/bouncycastle/asn1/ASN1ObjectIdentifier;
    1122: invokeinterface #455,  3          // InterfaceMethod java/util/Map.put:(Ljava/lang/Object;Ljava/lang/Object;)Ljava/lang/Object;
    1127: pop
    1128: getstatic     #437                // Field digestNameToOids:Ljava/util/Map;
    1131: ldc           #26                 // String SHA512-224
    1133: getstatic     #397                // Field org/bouncycastle/asn1/nist/NISTObjectIdentifiers.id_sha512_224:Lorg/bouncycastle/asn1/ASN1ObjectIdentifier;
    1136: invokeinterface #455,  3          // InterfaceMethod java/util/Map.put:(Ljava/lang/Object;Ljava/lang/Object;)Ljava/lang/Object;
    1141: pop
    1142: getstatic     #437                // Field digestNameToOids:Ljava/util/Map;
    1145: ldc           #27                 // String SHA512-256
    1147: getstatic     #398                // Field org/bouncycastle/asn1/nist/NISTObjectIdentifiers.id_sha512_256:Lorg/bouncycastle/asn1/ASN1ObjectIdentifier;
    1150: invokeinterface #455,  3          // InterfaceMethod java/util/Map.put:(Ljava/lang/Object;Ljava/lang/Object;)Ljava/lang/Object;
    1155: pop
    1156: getstatic     #437                // Field digestNameToOids:Ljava/util/Map;
    1159: ldc           #20                 // String SHA3-224
    1161: getstatic     #392                // Field org/bouncycastle/asn1/nist/NISTObjectIdentifiers.id_sha3_224:Lorg/bouncycastle/asn1/ASN1ObjectIdentifier;
    1164: invokeinterface #455,  3          // InterfaceMethod java/util/Map.put:(Ljava/lang/Object;Ljava/lang/Object;)Ljava/lang/Object;
    1169: pop
    1170: getstatic     #437                // Field digestNameToOids:Ljava/util/Map;
    1173: ldc           #21                 // String SHA3-256
    1175: getstatic     #393                // Field org/bouncycastle/asn1/nist/NISTObjectIdentifiers.id_sha3_256:Lorg/bouncycastle/asn1/ASN1ObjectIdentifier;
    1178: invokeinterface #455,  3          // InterfaceMethod java/util/Map.put:(Ljava/lang/Object;Ljava/lang/Object;)Ljava/lang/Object;
    1183: pop
    1184: getstatic     #437                // Field digestNameToOids:Ljava/util/Map;
    1187: ldc           #22                 // String SHA3-384
    1189: getstatic     #394                // Field org/bouncycastle/asn1/nist/NISTObjectIdentifiers.id_sha3_384:Lorg/bouncycastle/asn1/ASN1ObjectIdentifier;
    1192: invokeinterface #455,  3          // InterfaceMethod java/util/Map.put:(Ljava/lang/Object;Ljava/lang/Object;)Ljava/lang/Object;
    1197: pop
    1198: getstatic     #437                // Field digestNameToOids:Ljava/util/Map;
    1201: ldc           #23                 // String SHA3-512
    1203: getstatic     #395                // Field org/bouncycastle/asn1/nist/NISTObjectIdentifiers.id_sha3_512:Lorg/bouncycastle/asn1/ASN1ObjectIdentifier;
    1206: invokeinterface #455,  3          // InterfaceMethod java/util/Map.put:(Ljava/lang/Object;Ljava/lang/Object;)Ljava/lang/Object;
    1211: pop
    1212: getstatic     #437                // Field digestNameToOids:Ljava/util/Map;
    1215: ldc           #30                 // String SHAKE128
    1217: getstatic     #399                // Field org/bouncycastle/asn1/nist/NISTObjectIdentifiers.id_shake128:Lorg/bouncycastle/asn1/ASN1ObjectIdentifier;
    1220: invokeinterface #455,  3          // InterfaceMethod java/util/Map.put:(Ljava/lang/Object;Ljava/lang/Object;)Ljava/lang/Object;
    1225: pop
    1226: getstatic     #437                // Field digestNameToOids:Ljava/util/Map;
    1229: ldc           #31                 // String SHAKE256
    1231: getstatic     #400                // Field org/bouncycastle/asn1/nist/NISTObjectIdentifiers.id_shake256:Lorg/bouncycastle/asn1/ASN1ObjectIdentifier;
    1234: invokeinterface #455,  3          // InterfaceMethod java/util/Map.put:(Ljava/lang/Object;Ljava/lang/Object;)Ljava/lang/Object;
    1239: pop
    1240: getstatic     #437                // Field digestNameToOids:Ljava/util/Map;
    1243: ldc           #28                 // String SHAKE-128
    1245: getstatic     #399                // Field org/bouncycastle/asn1/nist/NISTObjectIdentifiers.id_shake128:Lorg/bouncycastle/asn1/ASN1ObjectIdentifier;
    1248: invokeinterface #455,  3          // InterfaceMethod java/util/Map.put:(Ljava/lang/Object;Ljava/lang/Object;)Ljava/lang/Object;
    1253: pop
    1254: getstatic     #437                // Field digestNameToOids:Ljava/util/Map;
    1257: ldc           #29                 // String SHAKE-256
    1259: getstatic     #400                // Field org/bouncycastle/asn1/nist/NISTObjectIdentifiers.id_shake256:Lorg/bouncycastle/asn1/ASN1ObjectIdentifier;
    1262: invokeinterface #455,  3          // InterfaceMethod java/util/Map.put:(Ljava/lang/Object;Ljava/lang/Object;)Ljava/lang/Object;
    1267: pop
    1268: getstatic     #437                // Field digestNameToOids:Ljava/util/Map;
    1271: ldc           #1                  // String GOST3411
    1273: getstatic     #360                // Field org/bouncycastle/asn1/cryptopro/CryptoProObjectIdentifiers.gostR3411:Lorg/bouncycastle/asn1/ASN1ObjectIdentifier;
    1276: invokeinterface #455,  3          // InterfaceMethod java/util/Map.put:(Ljava/lang/Object;Ljava/lang/Object;)Ljava/lang/Object;
    1281: pop
    1282: getstatic     #437                // Field digestNameToOids:Ljava/util/Map;
    1285: ldc           #2                  // String GOST3411-2012-256
    1287: getstatic     #421                // Field org/bouncycastle/asn1/rosstandart/RosstandartObjectIdentifiers.id_tc26_gost_3411_12_256:Lorg/bouncycastle/asn1/ASN1ObjectIdentifier;
    1290: invokeinterface #455,  3          // InterfaceMethod java/util/Map.put:(Ljava/lang/Object;Ljava/lang/Object;)Ljava/lang/Object;
    1295: pop
    1296: getstatic     #437                // Field digestNameToOids:Ljava/util/Map;
    1299: ldc           #3                  // String GOST3411-2012-512
    1301: getstatic     #422                // Field org/bouncycastle/asn1/rosstandart/RosstandartObjectIdentifiers.id_tc26_gost_3411_12_512:Lorg/bouncycastle/asn1/ASN1ObjectIdentifier;
    1304: invokeinterface #455,  3          // InterfaceMethod java/util/Map.put:(Ljava/lang/Object;Ljava/lang/Object;)Ljava/lang/Object;
    1309: pop
    1310: getstatic     #437                // Field digestNameToOids:Ljava/util/Map;
    1313: ldc           #4                  // String MD2
    1315: getstatic     #408                // Field org/bouncycastle/asn1/pkcs/PKCSObjectIdentifiers.md2:Lorg/bouncycastle/asn1/ASN1ObjectIdentifier;
    1318: invokeinterface #455,  3          // InterfaceMethod java/util/Map.put:(Ljava/lang/Object;Ljava/lang/Object;)Ljava/lang/Object;
    1323: pop
    1324: getstatic     #437                // Field digestNameToOids:Ljava/util/Map;
    1327: ldc           #5                  // String MD4
    1329: getstatic     #410                // Field org/bouncycastle/asn1/pkcs/PKCSObjectIdentifiers.md4:Lorg/bouncycastle/asn1/ASN1ObjectIdentifier;
    1332: invokeinterface #455,  3          // InterfaceMethod java/util/Map.put:(Ljava/lang/Object;Ljava/lang/Object;)Ljava/lang/Object;
    1337: pop
    1338: getstatic     #437                // Field digestNameToOids:Ljava/util/Map;
    1341: ldc           #6                  // String MD5
    1343: getstatic     #412                // Field org/bouncycastle/asn1/pkcs/PKCSObjectIdentifiers.md5:Lorg/bouncycastle/asn1/ASN1ObjectIdentifier;
    1346: invokeinterface #455,  3          // InterfaceMethod java/util/Map.put:(Ljava/lang/Object;Ljava/lang/Object;)Ljava/lang/Object;
    1351: pop
    1352: getstatic     #437                // Field digestNameToOids:Ljava/util/Map;
    1355: ldc           #7                  // String RIPEMD128
    1357: getstatic     #425                // Field org/bouncycastle/asn1/teletrust/TeleTrusTObjectIdentifiers.ripemd128:Lorg/bouncycastle/asn1/ASN1ObjectIdentifier;
    1360: invokeinterface #455,  3          // InterfaceMethod java/util/Map.put:(Ljava/lang/Object;Ljava/lang/Object;)Ljava/lang/Object;
    1365: pop
    1366: getstatic     #437                // Field digestNameToOids:Ljava/util/Map;
    1369: ldc           #8                  // String RIPEMD160
    1371: getstatic     #426                // Field org/bouncycastle/asn1/teletrust/TeleTrusTObjectIdentifiers.ripemd160:Lorg/bouncycastle/asn1/ASN1ObjectIdentifier;
    1374: invokeinterface #455,  3          // InterfaceMethod java/util/Map.put:(Ljava/lang/Object;Ljava/lang/Object;)Ljava/lang/Object;
    1379: pop
    1380: getstatic     #437                // Field digestNameToOids:Ljava/util/Map;
    1383: ldc           #9                  // String RIPEMD256
    1385: getstatic     #427                // Field org/bouncycastle/asn1/teletrust/TeleTrusTObjectIdentifiers.ripemd256:Lorg/bouncycastle/asn1/ASN1ObjectIdentifier;
    1388: invokeinterface #455,  3          // InterfaceMethod java/util/Map.put:(Ljava/lang/Object;Ljava/lang/Object;)Ljava/lang/Object;
    1393: pop
    1394: getstatic     #437                // Field digestNameToOids:Ljava/util/Map;
    1397: ldc           #32                 // String SM3
    1399: getstatic     #372                // Field org/bouncycastle/asn1/gm/GMObjectIdentifiers.sm3:Lorg/bouncycastle/asn1/ASN1ObjectIdentifier;
    1402: invokeinterface #455,  3          // InterfaceMethod java/util/Map.put:(Ljava/lang/Object;Ljava/lang/Object;)Ljava/lang/Object;
    1407: pop
    1408: getstatic     #403                // Field org/bouncycastle/asn1/oiw/OIWObjectIdentifiers.idSHA1:Lorg/bouncycastle/asn1/ASN1ObjectIdentifier;
    1411: iconst_1
    1412: invokestatic  #452                // Method addDigestAlgId:(Lorg/bouncycastle/asn1/ASN1ObjectIdentifier;Z)V
    1415: getstatic     #389                // Field org/bouncycastle/asn1/nist/NISTObjectIdentifiers.id_sha224:Lorg/bouncycastle/asn1/ASN1ObjectIdentifier;
    1418: iconst_0
    1419: invokestatic  #452                // Method addDigestAlgId:(Lorg/bouncycastle/asn1/ASN1ObjectIdentifier;Z)V
    1422: getstatic     #390                // Field org/bouncycastle/asn1/nist/NISTObjectIdentifiers.id_sha256:Lorg/bouncycastle/asn1/ASN1ObjectIdentifier;
    1425: iconst_0
    1426: invokestatic  #452                // Method addDigestAlgId:(Lorg/bouncycastle/asn1/ASN1ObjectIdentifier;Z)V
    1429: getstatic     #391                // Field org/bouncycastle/asn1/nist/NISTObjectIdentifiers.id_sha384:Lorg/bouncycastle/asn1/ASN1ObjectIdentifier;
    1432: iconst_0
    1433: invokestatic  #452                // Method addDigestAlgId:(Lorg/bouncycastle/asn1/ASN1ObjectIdentifier;Z)V
    1436: getstatic     #396                // Field org/bouncycastle/asn1/nist/NISTObjectIdentifiers.id_sha512:Lorg/bouncycastle/asn1/ASN1ObjectIdentifier;
    1439: iconst_0
    1440: invokestatic  #452                // Method addDigestAlgId:(Lorg/bouncycastle/asn1/ASN1ObjectIdentifier;Z)V
    1443: getstatic     #397                // Field org/bouncycastle/asn1/nist/NISTObjectIdentifiers.id_sha512_224:Lorg/bouncycastle/asn1/ASN1ObjectIdentifier;
    1446: iconst_0
    1447: invokestatic  #452                // Method addDigestAlgId:(Lorg/bouncycastle/asn1/ASN1ObjectIdentifier;Z)V
    1450: getstatic     #398                // Field org/bouncycastle/asn1/nist/NISTObjectIdentifiers.id_sha512_256:Lorg/bouncycastle/asn1/ASN1ObjectIdentifier;
    1453: iconst_0
    1454: invokestatic  #452                // Method addDigestAlgId:(Lorg/bouncycastle/asn1/ASN1ObjectIdentifier;Z)V
    1457: getstatic     #392                // Field org/bouncycastle/asn1/nist/NISTObjectIdentifiers.id_sha3_224:Lorg/bouncycastle/asn1/ASN1ObjectIdentifier;
    1460: iconst_0
    1461: invokestatic  #452                // Method addDigestAlgId:(Lorg/bouncycastle/asn1/ASN1ObjectIdentifier;Z)V
    1464: getstatic     #393                // Field org/bouncycastle/asn1/nist/NISTObjectIdentifiers.id_sha3_256:Lorg/bouncycastle/asn1/ASN1ObjectIdentifier;
    1467: iconst_0
    1468: invokestatic  #452                // Method addDigestAlgId:(Lorg/bouncycastle/asn1/ASN1ObjectIdentifier;Z)V
    1471: getstatic     #394                // Field org/bouncycastle/asn1/nist/NISTObjectIdentifiers.id_sha3_384:Lorg/bouncycastle/asn1/ASN1ObjectIdentifier;
    1474: iconst_0
    1475: invokestatic  #452                // Method addDigestAlgId:(Lorg/bouncycastle/asn1/ASN1ObjectIdentifier;Z)V
    1478: getstatic     #395                // Field org/bouncycastle/asn1/nist/NISTObjectIdentifiers.id_sha3_512:Lorg/bouncycastle/asn1/ASN1ObjectIdentifier;
    1481: iconst_0
    1482: invokestatic  #452                // Method addDigestAlgId:(Lorg/bouncycastle/asn1/ASN1ObjectIdentifier;Z)V
    1485: getstatic     #399                // Field org/bouncycastle/asn1/nist/NISTObjectIdentifiers.id_shake128:Lorg/bouncycastle/asn1/ASN1ObjectIdentifier;
    1488: iconst_0
    1489: invokestatic  #452                // Method addDigestAlgId:(Lorg/bouncycastle/asn1/ASN1ObjectIdentifier;Z)V
    1492: getstatic     #400                // Field org/bouncycastle/asn1/nist/NISTObjectIdentifiers.id_shake256:Lorg/bouncycastle/asn1/ASN1ObjectIdentifier;
    1495: iconst_0
    1496: invokestatic  #452                // Method addDigestAlgId:(Lorg/bouncycastle/asn1/ASN1ObjectIdentifier;Z)V
    1499: getstatic     #360                // Field org/bouncycastle/asn1/cryptopro/CryptoProObjectIdentifiers.gostR3411:Lorg/bouncycastle/asn1/ASN1ObjectIdentifier;
    1502: iconst_1
    1503: invokestatic  #452                // Method addDigestAlgId:(Lorg/bouncycastle/asn1/ASN1ObjectIdentifier;Z)V
    1506: getstatic     #421                // Field org/bouncycastle/asn1/rosstandart/RosstandartObjectIdentifiers.id_tc26_gost_3411_12_256:Lorg/bouncycastle/asn1/ASN1ObjectIdentifier;
    1509: iconst_0
    1510: invokestatic  #452                // Method addDigestAlgId:(Lorg/bouncycastle/asn1/ASN1ObjectIdentifier;Z)V
    1513: getstatic     #422                // Field org/bouncycastle/asn1/rosstandart/RosstandartObjectIdentifiers.id_tc26_gost_3411_12_512:Lorg/bouncycastle/asn1/ASN1ObjectIdentifier;
    1516: iconst_0
    1517: invokestatic  #452                // Method addDigestAlgId:(Lorg/bouncycastle/asn1/ASN1ObjectIdentifier;Z)V
    1520: getstatic     #408                // Field org/bouncycastle/asn1/pkcs/PKCSObjectIdentifiers.md2:Lorg/bouncycastle/asn1/ASN1ObjectIdentifier;
    1523: iconst_1
    1524: invokestatic  #452                // Method addDigestAlgId:(Lorg/bouncycastle/asn1/ASN1ObjectIdentifier;Z)V
    1527: getstatic     #410                // Field org/bouncycastle/asn1/pkcs/PKCSObjectIdentifiers.md4:Lorg/bouncycastle/asn1/ASN1ObjectIdentifier;
    1530: iconst_1
    1531: invokestatic  #452                // Method addDigestAlgId:(Lorg/bouncycastle/asn1/ASN1ObjectIdentifier;Z)V
    1534: getstatic     #412                // Field org/bouncycastle/asn1/pkcs/PKCSObjectIdentifiers.md5:Lorg/bouncycastle/asn1/ASN1ObjectIdentifier;
    1537: iconst_1
    1538: invokestatic  #452                // Method addDigestAlgId:(Lorg/bouncycastle/asn1/ASN1ObjectIdentifier;Z)V
    1541: getstatic     #425                // Field org/bouncycastle/asn1/teletrust/TeleTrusTObjectIdentifiers.ripemd128:Lorg/bouncycastle/asn1/ASN1ObjectIdentifier;
    1544: iconst_1
    1545: invokestatic  #452                // Method addDigestAlgId:(Lorg/bouncycastle/asn1/ASN1ObjectIdentifier;Z)V
    1548: getstatic     #426                // Field org/bouncycastle/asn1/teletrust/TeleTrusTObjectIdentifiers.ripemd160:Lorg/bouncycastle/asn1/ASN1ObjectIdentifier;
    1551: iconst_1
    1552: invokestatic  #452                // Method addDigestAlgId:(Lorg/bouncycastle/asn1/ASN1ObjectIdentifier;Z)V
    1555: getstatic     #427                // Field org/bouncycastle/asn1/teletrust/TeleTrusTObjectIdentifiers.ripemd256:Lorg/bouncycastle/asn1/ASN1ObjectIdentifier;
    1558: iconst_1
    1559: invokestatic  #452                // Method addDigestAlgId:(Lorg/bouncycastle/asn1/ASN1ObjectIdentifier;Z)V
    1562: return
}
