public class org.bouncycastle.operator.OperatorCreationException extends org.bouncycastle.operator.OperatorException {
  public org.bouncycastle.operator.OperatorCreationException(java.lang.String, java.lang.Throwable);
    Code:
       0: aload_0
       1: aload_1
       2: aload_2
       3: invokespecial #11                 // Method org/bouncycastle/operator/OperatorException."<init>":(Ljava/lang/String;Ljava/lang/Throwable;)V
       6: return

  public org.bouncycastle.operator.OperatorCreationException(java.lang.String);
    Code:
       0: aload_0
       1: aload_1
       2: invokespecial #10                 // Method org/bouncycastle/operator/OperatorException."<init>":(Ljava/lang/String;)V
       5: return
}
