Compiled from "MarkupTemplateEngine.java"
class groovy.text.markup.MarkupTemplateEngine$1 extends org.codehaus.groovy.control.customizers.CompilationCustomizer {
  final groovy.text.markup.MarkupTemplateEngine this$0;

  groovy.text.markup.MarkupTemplateEngine$1(groovy.text.markup.MarkupTemplateEngine, org.codehaus.groovy.control.CompilePhase);
    Code:
       0: aload_0
       1: aload_1
       2: putfield      #15                 // Field this$0:Lgroovy/text/markup/MarkupTemplateEngine;
       5: aload_0
       6: aload_2
       7: invokespecial #18                 // Method org/codehaus/groovy/control/customizers/CompilationCustomizer."<init>":(Lorg/codehaus/groovy/control/CompilePhase;)V
      10: return

  public void call(org.codehaus.groovy.control.SourceUnit, org.codehaus.groovy.classgen.GeneratorContext, org.codehaus.groovy.ast.ClassNode) throws org.codehaus.groovy.control.CompilationFailedException;
    Code:
       0: new           #28                 // class groovy/text/markup/AutoNewLineTransformer
       3: dup
       4: aload_1
       5: invokespecial #31                 // Method groovy/text/markup/AutoNewLineTransformer."<init>":(Lorg/codehaus/groovy/control/SourceUnit;)V
       8: aload_3
       9: invokevirtual #35                 // Method groovy/text/markup/AutoNewLineTransformer.visitClass:(Lorg/codehaus/groovy/ast/ClassNode;)V
      12: return
}
