Compiled from "MultiClusteringEntity_Update.java"
public final class info.archinnov.achilles.generated.dsl.MultiClusteringEntity_Update$MultiClusteringEntity_UpdateEnd$If_Value {
  final info.archinnov.achilles.generated.dsl.MultiClusteringEntity_Update$MultiClusteringEntity_UpdateEnd this$1;

  public info.archinnov.achilles.generated.dsl.MultiClusteringEntity_Update$MultiClusteringEntity_UpdateEnd$If_Value(info.archinnov.achilles.generated.dsl.MultiClusteringEntity_Update$MultiClusteringEntity_UpdateEnd);
    Code:
       0: aload_0
       1: aload_1
       2: putfield      #1                  // Field this$1:Linfo/archinnov/achilles/generated/dsl/MultiClusteringEntity_Update$MultiClusteringEntity_UpdateEnd;
       5: aload_0
       6: invokespecial #2                  // Method java/lang/Object."<init>":()V
       9: return

  public final info.archinnov.achilles.generated.dsl.MultiClusteringEntity_Update$MultiClusteringEntity_UpdateEnd Eq(java.lang.String);
    Code:
       0: aload_0
       1: getfield      #1                  // Field this$1:Linfo/archinnov/achilles/generated/dsl/MultiClusteringEntity_Update$MultiClusteringEntity_UpdateEnd;
       4: getfield      #3                  // Field info/archinnov/achilles/generated/dsl/MultiClusteringEntity_Update$MultiClusteringEntity_UpdateEnd.this$0:Linfo/archinnov/achilles/generated/dsl/MultiClusteringEntity_Update;
       7: invokestatic  #4                  // Method info/archinnov/achilles/generated/dsl/MultiClusteringEntity_Update.access$7200:(Linfo/archinnov/achilles/generated/dsl/MultiClusteringEntity_Update;)Ljava/util/List;
      10: aload_1
      11: invokeinterface #5,  2            // InterfaceMethod java/util/List.add:(Ljava/lang/Object;)Z
      16: pop
      17: aload_0
      18: getfield      #1                  // Field this$1:Linfo/archinnov/achilles/generated/dsl/MultiClusteringEntity_Update$MultiClusteringEntity_UpdateEnd;
      21: getfield      #3                  // Field info/archinnov/achilles/generated/dsl/MultiClusteringEntity_Update$MultiClusteringEntity_UpdateEnd.this$0:Linfo/archinnov/achilles/generated/dsl/MultiClusteringEntity_Update;
      24: invokestatic  #6                  // Method info/archinnov/achilles/generated/dsl/MultiClusteringEntity_Update.access$7400:(Linfo/archinnov/achilles/generated/dsl/MultiClusteringEntity_Update;)Ljava/util/List;
      27: aload_0
      28: getfield      #1                  // Field this$1:Linfo/archinnov/achilles/generated/dsl/MultiClusteringEntity_Update$MultiClusteringEntity_UpdateEnd;
      31: getfield      #3                  // Field info/archinnov/achilles/generated/dsl/MultiClusteringEntity_Update$MultiClusteringEntity_UpdateEnd.this$0:Linfo/archinnov/achilles/generated/dsl/MultiClusteringEntity_Update;
      34: getfield      #7                  // Field info/archinnov/achilles/generated/dsl/MultiClusteringEntity_Update.meta:Linfo/archinnov/achilles/generated/meta/entity/MultiClusteringEntity_AchillesMeta;
      37: pop
      38: getstatic     #8                  // Field info/archinnov/achilles/generated/meta/entity/MultiClusteringEntity_AchillesMeta.value:Linfo/archinnov/achilles/internals/metamodel/SimpleProperty;
      41: aload_1
      42: aload_0
      43: getfield      #1                  // Field this$1:Linfo/archinnov/achilles/generated/dsl/MultiClusteringEntity_Update$MultiClusteringEntity_UpdateEnd;
      46: invokestatic  #9                  // Method info/archinnov/achilles/generated/dsl/MultiClusteringEntity_Update$MultiClusteringEntity_UpdateEnd.access$7300:(Linfo/archinnov/achilles/generated/dsl/MultiClusteringEntity_Update$MultiClusteringEntity_UpdateEnd;)Linfo/archinnov/achilles/internals/options/CassandraOptions;
      49: invokestatic  #10                 // Method java/util/Optional.of:(Ljava/lang/Object;)Ljava/util/Optional;
      52: invokevirtual #11                 // Method info/archinnov/achilles/internals/metamodel/SimpleProperty.encodeFromJava:(Ljava/lang/Object;Ljava/util/Optional;)Ljava/lang/Object;
      55: invokeinterface #5,  2            // InterfaceMethod java/util/List.add:(Ljava/lang/Object;)Z
      60: pop
      61: aload_0
      62: getfield      #1                  // Field this$1:Linfo/archinnov/achilles/generated/dsl/MultiClusteringEntity_Update$MultiClusteringEntity_UpdateEnd;
      65: invokestatic  #12                 // Method info/archinnov/achilles/generated/dsl/MultiClusteringEntity_Update$MultiClusteringEntity_UpdateEnd.access$7500:(Linfo/archinnov/achilles/generated/dsl/MultiClusteringEntity_Update$MultiClusteringEntity_UpdateEnd;)Lcom/datastax/driver/core/querybuilder/Update$Where;
      68: ldc           #13                 // String value
      70: ldc           #13                 // String value
      72: invokestatic  #14                 // Method com/datastax/driver/core/querybuilder/QueryBuilder.bindMarker:(Ljava/lang/String;)Lcom/datastax/driver/core/querybuilder/BindMarker;
      75: invokestatic  #15                 // Method com/datastax/driver/core/querybuilder/QueryBuilder.eq:(Ljava/lang/String;Ljava/lang/Object;)Lcom/datastax/driver/core/querybuilder/Clause;
      78: invokevirtual #16                 // Method com/datastax/driver/core/querybuilder/Update$Where.onlyIf:(Lcom/datastax/driver/core/querybuilder/Clause;)Lcom/datastax/driver/core/querybuilder/Update$Conditions;
      81: pop
      82: aload_0
      83: getfield      #1                  // Field this$1:Linfo/archinnov/achilles/generated/dsl/MultiClusteringEntity_Update$MultiClusteringEntity_UpdateEnd;
      86: areturn

  public final info.archinnov.achilles.generated.dsl.MultiClusteringEntity_Update$MultiClusteringEntity_UpdateEnd Gt(java.lang.String);
    Code:
       0: aload_0
       1: getfield      #1                  // Field this$1:Linfo/archinnov/achilles/generated/dsl/MultiClusteringEntity_Update$MultiClusteringEntity_UpdateEnd;
       4: getfield      #3                  // Field info/archinnov/achilles/generated/dsl/MultiClusteringEntity_Update$MultiClusteringEntity_UpdateEnd.this$0:Linfo/archinnov/achilles/generated/dsl/MultiClusteringEntity_Update;
       7: invokestatic  #17                 // Method info/archinnov/achilles/generated/dsl/MultiClusteringEntity_Update.access$7600:(Linfo/archinnov/achilles/generated/dsl/MultiClusteringEntity_Update;)Ljava/util/List;
      10: aload_1
      11: invokeinterface #5,  2            // InterfaceMethod java/util/List.add:(Ljava/lang/Object;)Z
      16: pop
      17: aload_0
      18: getfield      #1                  // Field this$1:Linfo/archinnov/achilles/generated/dsl/MultiClusteringEntity_Update$MultiClusteringEntity_UpdateEnd;
      21: getfield      #3                  // Field info/archinnov/achilles/generated/dsl/MultiClusteringEntity_Update$MultiClusteringEntity_UpdateEnd.this$0:Linfo/archinnov/achilles/generated/dsl/MultiClusteringEntity_Update;
      24: invokestatic  #18                 // Method info/archinnov/achilles/generated/dsl/MultiClusteringEntity_Update.access$7800:(Linfo/archinnov/achilles/generated/dsl/MultiClusteringEntity_Update;)Ljava/util/List;
      27: aload_0
      28: getfield      #1                  // Field this$1:Linfo/archinnov/achilles/generated/dsl/MultiClusteringEntity_Update$MultiClusteringEntity_UpdateEnd;
      31: getfield      #3                  // Field info/archinnov/achilles/generated/dsl/MultiClusteringEntity_Update$MultiClusteringEntity_UpdateEnd.this$0:Linfo/archinnov/achilles/generated/dsl/MultiClusteringEntity_Update;
      34: getfield      #7                  // Field info/archinnov/achilles/generated/dsl/MultiClusteringEntity_Update.meta:Linfo/archinnov/achilles/generated/meta/entity/MultiClusteringEntity_AchillesMeta;
      37: pop
      38: getstatic     #8                  // Field info/archinnov/achilles/generated/meta/entity/MultiClusteringEntity_AchillesMeta.value:Linfo/archinnov/achilles/internals/metamodel/SimpleProperty;
      41: aload_1
      42: aload_0
      43: getfield      #1                  // Field this$1:Linfo/archinnov/achilles/generated/dsl/MultiClusteringEntity_Update$MultiClusteringEntity_UpdateEnd;
      46: invokestatic  #19                 // Method info/archinnov/achilles/generated/dsl/MultiClusteringEntity_Update$MultiClusteringEntity_UpdateEnd.access$7700:(Linfo/archinnov/achilles/generated/dsl/MultiClusteringEntity_Update$MultiClusteringEntity_UpdateEnd;)Linfo/archinnov/achilles/internals/options/CassandraOptions;
      49: invokestatic  #10                 // Method java/util/Optional.of:(Ljava/lang/Object;)Ljava/util/Optional;
      52: invokevirtual #11                 // Method info/archinnov/achilles/internals/metamodel/SimpleProperty.encodeFromJava:(Ljava/lang/Object;Ljava/util/Optional;)Ljava/lang/Object;
      55: invokeinterface #5,  2            // InterfaceMethod java/util/List.add:(Ljava/lang/Object;)Z
      60: pop
      61: aload_0
      62: getfield      #1                  // Field this$1:Linfo/archinnov/achilles/generated/dsl/MultiClusteringEntity_Update$MultiClusteringEntity_UpdateEnd;
      65: invokestatic  #20                 // Method info/archinnov/achilles/generated/dsl/MultiClusteringEntity_Update$MultiClusteringEntity_UpdateEnd.access$7900:(Linfo/archinnov/achilles/generated/dsl/MultiClusteringEntity_Update$MultiClusteringEntity_UpdateEnd;)Lcom/datastax/driver/core/querybuilder/Update$Where;
      68: ldc           #13                 // String value
      70: ldc           #13                 // String value
      72: invokestatic  #14                 // Method com/datastax/driver/core/querybuilder/QueryBuilder.bindMarker:(Ljava/lang/String;)Lcom/datastax/driver/core/querybuilder/BindMarker;
      75: invokestatic  #21                 // Method com/datastax/driver/core/querybuilder/QueryBuilder.gt:(Ljava/lang/String;Ljava/lang/Object;)Lcom/datastax/driver/core/querybuilder/Clause;
      78: invokevirtual #16                 // Method com/datastax/driver/core/querybuilder/Update$Where.onlyIf:(Lcom/datastax/driver/core/querybuilder/Clause;)Lcom/datastax/driver/core/querybuilder/Update$Conditions;
      81: pop
      82: aload_0
      83: getfield      #1                  // Field this$1:Linfo/archinnov/achilles/generated/dsl/MultiClusteringEntity_Update$MultiClusteringEntity_UpdateEnd;
      86: areturn

  public final info.archinnov.achilles.generated.dsl.MultiClusteringEntity_Update$MultiClusteringEntity_UpdateEnd Gte(java.lang.String);
    Code:
       0: aload_0
       1: getfield      #1                  // Field this$1:Linfo/archinnov/achilles/generated/dsl/MultiClusteringEntity_Update$MultiClusteringEntity_UpdateEnd;
       4: getfield      #3                  // Field info/archinnov/achilles/generated/dsl/MultiClusteringEntity_Update$MultiClusteringEntity_UpdateEnd.this$0:Linfo/archinnov/achilles/generated/dsl/MultiClusteringEntity_Update;
       7: invokestatic  #22                 // Method info/archinnov/achilles/generated/dsl/MultiClusteringEntity_Update.access$8000:(Linfo/archinnov/achilles/generated/dsl/MultiClusteringEntity_Update;)Ljava/util/List;
      10: aload_1
      11: invokeinterface #5,  2            // InterfaceMethod java/util/List.add:(Ljava/lang/Object;)Z
      16: pop
      17: aload_0
      18: getfield      #1                  // Field this$1:Linfo/archinnov/achilles/generated/dsl/MultiClusteringEntity_Update$MultiClusteringEntity_UpdateEnd;
      21: getfield      #3                  // Field info/archinnov/achilles/generated/dsl/MultiClusteringEntity_Update$MultiClusteringEntity_UpdateEnd.this$0:Linfo/archinnov/achilles/generated/dsl/MultiClusteringEntity_Update;
      24: invokestatic  #23                 // Method info/archinnov/achilles/generated/dsl/MultiClusteringEntity_Update.access$8200:(Linfo/archinnov/achilles/generated/dsl/MultiClusteringEntity_Update;)Ljava/util/List;
      27: aload_0
      28: getfield      #1                  // Field this$1:Linfo/archinnov/achilles/generated/dsl/MultiClusteringEntity_Update$MultiClusteringEntity_UpdateEnd;
      31: getfield      #3                  // Field info/archinnov/achilles/generated/dsl/MultiClusteringEntity_Update$MultiClusteringEntity_UpdateEnd.this$0:Linfo/archinnov/achilles/generated/dsl/MultiClusteringEntity_Update;
      34: getfield      #7                  // Field info/archinnov/achilles/generated/dsl/MultiClusteringEntity_Update.meta:Linfo/archinnov/achilles/generated/meta/entity/MultiClusteringEntity_AchillesMeta;
      37: pop
      38: getstatic     #8                  // Field info/archinnov/achilles/generated/meta/entity/MultiClusteringEntity_AchillesMeta.value:Linfo/archinnov/achilles/internals/metamodel/SimpleProperty;
      41: aload_1
      42: aload_0
      43: getfield      #1                  // Field this$1:Linfo/archinnov/achilles/generated/dsl/MultiClusteringEntity_Update$MultiClusteringEntity_UpdateEnd;
      46: invokestatic  #24                 // Method info/archinnov/achilles/generated/dsl/MultiClusteringEntity_Update$MultiClusteringEntity_UpdateEnd.access$8100:(Linfo/archinnov/achilles/generated/dsl/MultiClusteringEntity_Update$MultiClusteringEntity_UpdateEnd;)Linfo/archinnov/achilles/internals/options/CassandraOptions;
      49: invokestatic  #10                 // Method java/util/Optional.of:(Ljava/lang/Object;)Ljava/util/Optional;
      52: invokevirtual #11                 // Method info/archinnov/achilles/internals/metamodel/SimpleProperty.encodeFromJava:(Ljava/lang/Object;Ljava/util/Optional;)Ljava/lang/Object;
      55: invokeinterface #5,  2            // InterfaceMethod java/util/List.add:(Ljava/lang/Object;)Z
      60: pop
      61: aload_0
      62: getfield      #1                  // Field this$1:Linfo/archinnov/achilles/generated/dsl/MultiClusteringEntity_Update$MultiClusteringEntity_UpdateEnd;
      65: invokestatic  #25                 // Method info/archinnov/achilles/generated/dsl/MultiClusteringEntity_Update$MultiClusteringEntity_UpdateEnd.access$8300:(Linfo/archinnov/achilles/generated/dsl/MultiClusteringEntity_Update$MultiClusteringEntity_UpdateEnd;)Lcom/datastax/driver/core/querybuilder/Update$Where;
      68: ldc           #13                 // String value
      70: ldc           #13                 // String value
      72: invokestatic  #14                 // Method com/datastax/driver/core/querybuilder/QueryBuilder.bindMarker:(Ljava/lang/String;)Lcom/datastax/driver/core/querybuilder/BindMarker;
      75: invokestatic  #26                 // Method com/datastax/driver/core/querybuilder/QueryBuilder.gte:(Ljava/lang/String;Ljava/lang/Object;)Lcom/datastax/driver/core/querybuilder/Clause;
      78: invokevirtual #16                 // Method com/datastax/driver/core/querybuilder/Update$Where.onlyIf:(Lcom/datastax/driver/core/querybuilder/Clause;)Lcom/datastax/driver/core/querybuilder/Update$Conditions;
      81: pop
      82: aload_0
      83: getfield      #1                  // Field this$1:Linfo/archinnov/achilles/generated/dsl/MultiClusteringEntity_Update$MultiClusteringEntity_UpdateEnd;
      86: areturn

  public final info.archinnov.achilles.generated.dsl.MultiClusteringEntity_Update$MultiClusteringEntity_UpdateEnd Lt(java.lang.String);
    Code:
       0: aload_0
       1: getfield      #1                  // Field this$1:Linfo/archinnov/achilles/generated/dsl/MultiClusteringEntity_Update$MultiClusteringEntity_UpdateEnd;
       4: getfield      #3                  // Field info/archinnov/achilles/generated/dsl/MultiClusteringEntity_Update$MultiClusteringEntity_UpdateEnd.this$0:Linfo/archinnov/achilles/generated/dsl/MultiClusteringEntity_Update;
       7: invokestatic  #27                 // Method info/archinnov/achilles/generated/dsl/MultiClusteringEntity_Update.access$8400:(Linfo/archinnov/achilles/generated/dsl/MultiClusteringEntity_Update;)Ljava/util/List;
      10: aload_1
      11: invokeinterface #5,  2            // InterfaceMethod java/util/List.add:(Ljava/lang/Object;)Z
      16: pop
      17: aload_0
      18: getfield      #1                  // Field this$1:Linfo/archinnov/achilles/generated/dsl/MultiClusteringEntity_Update$MultiClusteringEntity_UpdateEnd;
      21: getfield      #3                  // Field info/archinnov/achilles/generated/dsl/MultiClusteringEntity_Update$MultiClusteringEntity_UpdateEnd.this$0:Linfo/archinnov/achilles/generated/dsl/MultiClusteringEntity_Update;
      24: invokestatic  #28                 // Method info/archinnov/achilles/generated/dsl/MultiClusteringEntity_Update.access$8600:(Linfo/archinnov/achilles/generated/dsl/MultiClusteringEntity_Update;)Ljava/util/List;
      27: aload_0
      28: getfield      #1                  // Field this$1:Linfo/archinnov/achilles/generated/dsl/MultiClusteringEntity_Update$MultiClusteringEntity_UpdateEnd;
      31: getfield      #3                  // Field info/archinnov/achilles/generated/dsl/MultiClusteringEntity_Update$MultiClusteringEntity_UpdateEnd.this$0:Linfo/archinnov/achilles/generated/dsl/MultiClusteringEntity_Update;
      34: getfield      #7                  // Field info/archinnov/achilles/generated/dsl/MultiClusteringEntity_Update.meta:Linfo/archinnov/achilles/generated/meta/entity/MultiClusteringEntity_AchillesMeta;
      37: pop
      38: getstatic     #8                  // Field info/archinnov/achilles/generated/meta/entity/MultiClusteringEntity_AchillesMeta.value:Linfo/archinnov/achilles/internals/metamodel/SimpleProperty;
      41: aload_1
      42: aload_0
      43: getfield      #1                  // Field this$1:Linfo/archinnov/achilles/generated/dsl/MultiClusteringEntity_Update$MultiClusteringEntity_UpdateEnd;
      46: invokestatic  #29                 // Method info/archinnov/achilles/generated/dsl/MultiClusteringEntity_Update$MultiClusteringEntity_UpdateEnd.access$8500:(Linfo/archinnov/achilles/generated/dsl/MultiClusteringEntity_Update$MultiClusteringEntity_UpdateEnd;)Linfo/archinnov/achilles/internals/options/CassandraOptions;
      49: invokestatic  #10                 // Method java/util/Optional.of:(Ljava/lang/Object;)Ljava/util/Optional;
      52: invokevirtual #11                 // Method info/archinnov/achilles/internals/metamodel/SimpleProperty.encodeFromJava:(Ljava/lang/Object;Ljava/util/Optional;)Ljava/lang/Object;
      55: invokeinterface #5,  2            // InterfaceMethod java/util/List.add:(Ljava/lang/Object;)Z
      60: pop
      61: aload_0
      62: getfield      #1                  // Field this$1:Linfo/archinnov/achilles/generated/dsl/MultiClusteringEntity_Update$MultiClusteringEntity_UpdateEnd;
      65: invokestatic  #30                 // Method info/archinnov/achilles/generated/dsl/MultiClusteringEntity_Update$MultiClusteringEntity_UpdateEnd.access$8700:(Linfo/archinnov/achilles/generated/dsl/MultiClusteringEntity_Update$MultiClusteringEntity_UpdateEnd;)Lcom/datastax/driver/core/querybuilder/Update$Where;
      68: ldc           #13                 // String value
      70: ldc           #13                 // String value
      72: invokestatic  #14                 // Method com/datastax/driver/core/querybuilder/QueryBuilder.bindMarker:(Ljava/lang/String;)Lcom/datastax/driver/core/querybuilder/BindMarker;
      75: invokestatic  #31                 // Method com/datastax/driver/core/querybuilder/QueryBuilder.lt:(Ljava/lang/String;Ljava/lang/Object;)Lcom/datastax/driver/core/querybuilder/Clause;
      78: invokevirtual #16                 // Method com/datastax/driver/core/querybuilder/Update$Where.onlyIf:(Lcom/datastax/driver/core/querybuilder/Clause;)Lcom/datastax/driver/core/querybuilder/Update$Conditions;
      81: pop
      82: aload_0
      83: getfield      #1                  // Field this$1:Linfo/archinnov/achilles/generated/dsl/MultiClusteringEntity_Update$MultiClusteringEntity_UpdateEnd;
      86: areturn

  public final info.archinnov.achilles.generated.dsl.MultiClusteringEntity_Update$MultiClusteringEntity_UpdateEnd Lte(java.lang.String);
    Code:
       0: aload_0
       1: getfield      #1                  // Field this$1:Linfo/archinnov/achilles/generated/dsl/MultiClusteringEntity_Update$MultiClusteringEntity_UpdateEnd;
       4: getfield      #3                  // Field info/archinnov/achilles/generated/dsl/MultiClusteringEntity_Update$MultiClusteringEntity_UpdateEnd.this$0:Linfo/archinnov/achilles/generated/dsl/MultiClusteringEntity_Update;
       7: invokestatic  #32                 // Method info/archinnov/achilles/generated/dsl/MultiClusteringEntity_Update.access$8800:(Linfo/archinnov/achilles/generated/dsl/MultiClusteringEntity_Update;)Ljava/util/List;
      10: aload_1
      11: invokeinterface #5,  2            // InterfaceMethod java/util/List.add:(Ljava/lang/Object;)Z
      16: pop
      17: aload_0
      18: getfield      #1                  // Field this$1:Linfo/archinnov/achilles/generated/dsl/MultiClusteringEntity_Update$MultiClusteringEntity_UpdateEnd;
      21: getfield      #3                  // Field info/archinnov/achilles/generated/dsl/MultiClusteringEntity_Update$MultiClusteringEntity_UpdateEnd.this$0:Linfo/archinnov/achilles/generated/dsl/MultiClusteringEntity_Update;
      24: invokestatic  #33                 // Method info/archinnov/achilles/generated/dsl/MultiClusteringEntity_Update.access$9000:(Linfo/archinnov/achilles/generated/dsl/MultiClusteringEntity_Update;)Ljava/util/List;
      27: aload_0
      28: getfield      #1                  // Field this$1:Linfo/archinnov/achilles/generated/dsl/MultiClusteringEntity_Update$MultiClusteringEntity_UpdateEnd;
      31: getfield      #3                  // Field info/archinnov/achilles/generated/dsl/MultiClusteringEntity_Update$MultiClusteringEntity_UpdateEnd.this$0:Linfo/archinnov/achilles/generated/dsl/MultiClusteringEntity_Update;
      34: getfield      #7                  // Field info/archinnov/achilles/generated/dsl/MultiClusteringEntity_Update.meta:Linfo/archinnov/achilles/generated/meta/entity/MultiClusteringEntity_AchillesMeta;
      37: pop
      38: getstatic     #8                  // Field info/archinnov/achilles/generated/meta/entity/MultiClusteringEntity_AchillesMeta.value:Linfo/archinnov/achilles/internals/metamodel/SimpleProperty;
      41: aload_1
      42: aload_0
      43: getfield      #1                  // Field this$1:Linfo/archinnov/achilles/generated/dsl/MultiClusteringEntity_Update$MultiClusteringEntity_UpdateEnd;
      46: invokestatic  #34                 // Method info/archinnov/achilles/generated/dsl/MultiClusteringEntity_Update$MultiClusteringEntity_UpdateEnd.access$8900:(Linfo/archinnov/achilles/generated/dsl/MultiClusteringEntity_Update$MultiClusteringEntity_UpdateEnd;)Linfo/archinnov/achilles/internals/options/CassandraOptions;
      49: invokestatic  #10                 // Method java/util/Optional.of:(Ljava/lang/Object;)Ljava/util/Optional;
      52: invokevirtual #11                 // Method info/archinnov/achilles/internals/metamodel/SimpleProperty.encodeFromJava:(Ljava/lang/Object;Ljava/util/Optional;)Ljava/lang/Object;
      55: invokeinterface #5,  2            // InterfaceMethod java/util/List.add:(Ljava/lang/Object;)Z
      60: pop
      61: aload_0
      62: getfield      #1                  // Field this$1:Linfo/archinnov/achilles/generated/dsl/MultiClusteringEntity_Update$MultiClusteringEntity_UpdateEnd;
      65: invokestatic  #35                 // Method info/archinnov/achilles/generated/dsl/MultiClusteringEntity_Update$MultiClusteringEntity_UpdateEnd.access$9100:(Linfo/archinnov/achilles/generated/dsl/MultiClusteringEntity_Update$MultiClusteringEntity_UpdateEnd;)Lcom/datastax/driver/core/querybuilder/Update$Where;
      68: ldc           #13                 // String value
      70: ldc           #13                 // String value
      72: invokestatic  #14                 // Method com/datastax/driver/core/querybuilder/QueryBuilder.bindMarker:(Ljava/lang/String;)Lcom/datastax/driver/core/querybuilder/BindMarker;
      75: invokestatic  #36                 // Method com/datastax/driver/core/querybuilder/QueryBuilder.lte:(Ljava/lang/String;Ljava/lang/Object;)Lcom/datastax/driver/core/querybuilder/Clause;
      78: invokevirtual #16                 // Method com/datastax/driver/core/querybuilder/Update$Where.onlyIf:(Lcom/datastax/driver/core/querybuilder/Clause;)Lcom/datastax/driver/core/querybuilder/Update$Conditions;
      81: pop
      82: aload_0
      83: getfield      #1                  // Field this$1:Linfo/archinnov/achilles/generated/dsl/MultiClusteringEntity_Update$MultiClusteringEntity_UpdateEnd;
      86: areturn

  public final info.archinnov.achilles.generated.dsl.MultiClusteringEntity_Update$MultiClusteringEntity_UpdateEnd NotEq(java.lang.String);
    Code:
       0: aload_0
       1: getfield      #1                  // Field this$1:Linfo/archinnov/achilles/generated/dsl/MultiClusteringEntity_Update$MultiClusteringEntity_UpdateEnd;
       4: getfield      #3                  // Field info/archinnov/achilles/generated/dsl/MultiClusteringEntity_Update$MultiClusteringEntity_UpdateEnd.this$0:Linfo/archinnov/achilles/generated/dsl/MultiClusteringEntity_Update;
       7: invokestatic  #37                 // Method info/archinnov/achilles/generated/dsl/MultiClusteringEntity_Update.access$9200:(Linfo/archinnov/achilles/generated/dsl/MultiClusteringEntity_Update;)Ljava/util/List;
      10: aload_1
      11: invokeinterface #5,  2            // InterfaceMethod java/util/List.add:(Ljava/lang/Object;)Z
      16: pop
      17: aload_0
      18: getfield      #1                  // Field this$1:Linfo/archinnov/achilles/generated/dsl/MultiClusteringEntity_Update$MultiClusteringEntity_UpdateEnd;
      21: getfield      #3                  // Field info/archinnov/achilles/generated/dsl/MultiClusteringEntity_Update$MultiClusteringEntity_UpdateEnd.this$0:Linfo/archinnov/achilles/generated/dsl/MultiClusteringEntity_Update;
      24: invokestatic  #38                 // Method info/archinnov/achilles/generated/dsl/MultiClusteringEntity_Update.access$9400:(Linfo/archinnov/achilles/generated/dsl/MultiClusteringEntity_Update;)Ljava/util/List;
      27: aload_0
      28: getfield      #1                  // Field this$1:Linfo/archinnov/achilles/generated/dsl/MultiClusteringEntity_Update$MultiClusteringEntity_UpdateEnd;
      31: getfield      #3                  // Field info/archinnov/achilles/generated/dsl/MultiClusteringEntity_Update$MultiClusteringEntity_UpdateEnd.this$0:Linfo/archinnov/achilles/generated/dsl/MultiClusteringEntity_Update;
      34: getfield      #7                  // Field info/archinnov/achilles/generated/dsl/MultiClusteringEntity_Update.meta:Linfo/archinnov/achilles/generated/meta/entity/MultiClusteringEntity_AchillesMeta;
      37: pop
      38: getstatic     #8                  // Field info/archinnov/achilles/generated/meta/entity/MultiClusteringEntity_AchillesMeta.value:Linfo/archinnov/achilles/internals/metamodel/SimpleProperty;
      41: aload_1
      42: aload_0
      43: getfield      #1                  // Field this$1:Linfo/archinnov/achilles/generated/dsl/MultiClusteringEntity_Update$MultiClusteringEntity_UpdateEnd;
      46: invokestatic  #39                 // Method info/archinnov/achilles/generated/dsl/MultiClusteringEntity_Update$MultiClusteringEntity_UpdateEnd.access$9300:(Linfo/archinnov/achilles/generated/dsl/MultiClusteringEntity_Update$MultiClusteringEntity_UpdateEnd;)Linfo/archinnov/achilles/internals/options/CassandraOptions;
      49: invokestatic  #10                 // Method java/util/Optional.of:(Ljava/lang/Object;)Ljava/util/Optional;
      52: invokevirtual #11                 // Method info/archinnov/achilles/internals/metamodel/SimpleProperty.encodeFromJava:(Ljava/lang/Object;Ljava/util/Optional;)Ljava/lang/Object;
      55: invokeinterface #5,  2            // InterfaceMethod java/util/List.add:(Ljava/lang/Object;)Z
      60: pop
      61: aload_0
      62: getfield      #1                  // Field this$1:Linfo/archinnov/achilles/generated/dsl/MultiClusteringEntity_Update$MultiClusteringEntity_UpdateEnd;
      65: invokestatic  #40                 // Method info/archinnov/achilles/generated/dsl/MultiClusteringEntity_Update$MultiClusteringEntity_UpdateEnd.access$9500:(Linfo/archinnov/achilles/generated/dsl/MultiClusteringEntity_Update$MultiClusteringEntity_UpdateEnd;)Lcom/datastax/driver/core/querybuilder/Update$Where;
      68: ldc           #13                 // String value
      70: ldc           #13                 // String value
      72: invokestatic  #14                 // Method com/datastax/driver/core/querybuilder/QueryBuilder.bindMarker:(Ljava/lang/String;)Lcom/datastax/driver/core/querybuilder/BindMarker;
      75: invokestatic  #41                 // Method com/datastax/driver/core/querybuilder/NotEq.of:(Ljava/lang/String;Ljava/lang/Object;)Lcom/datastax/driver/core/querybuilder/Clause$SimpleClause;
      78: invokevirtual #16                 // Method com/datastax/driver/core/querybuilder/Update$Where.onlyIf:(Lcom/datastax/driver/core/querybuilder/Clause;)Lcom/datastax/driver/core/querybuilder/Update$Conditions;
      81: pop
      82: aload_0
      83: getfield      #1                  // Field this$1:Linfo/archinnov/achilles/generated/dsl/MultiClusteringEntity_Update$MultiClusteringEntity_UpdateEnd;
      86: areturn

  public final info.archinnov.achilles.generated.dsl.MultiClusteringEntity_Update$MultiClusteringEntity_UpdateEnd Eq_FromJSON(java.lang.String);
    Code:
       0: aload_0
       1: getfield      #1                  // Field this$1:Linfo/archinnov/achilles/generated/dsl/MultiClusteringEntity_Update$MultiClusteringEntity_UpdateEnd;
       4: getfield      #3                  // Field info/archinnov/achilles/generated/dsl/MultiClusteringEntity_Update$MultiClusteringEntity_UpdateEnd.this$0:Linfo/archinnov/achilles/generated/dsl/MultiClusteringEntity_Update;
       7: invokestatic  #42                 // Method info/archinnov/achilles/generated/dsl/MultiClusteringEntity_Update.access$9600:(Linfo/archinnov/achilles/generated/dsl/MultiClusteringEntity_Update;)Ljava/util/List;
      10: aload_1
      11: invokeinterface #5,  2            // InterfaceMethod java/util/List.add:(Ljava/lang/Object;)Z
      16: pop
      17: aload_0
      18: getfield      #1                  // Field this$1:Linfo/archinnov/achilles/generated/dsl/MultiClusteringEntity_Update$MultiClusteringEntity_UpdateEnd;
      21: getfield      #3                  // Field info/archinnov/achilles/generated/dsl/MultiClusteringEntity_Update$MultiClusteringEntity_UpdateEnd.this$0:Linfo/archinnov/achilles/generated/dsl/MultiClusteringEntity_Update;
      24: invokestatic  #43                 // Method info/archinnov/achilles/generated/dsl/MultiClusteringEntity_Update.access$9700:(Linfo/archinnov/achilles/generated/dsl/MultiClusteringEntity_Update;)Ljava/util/List;
      27: aload_1
      28: invokeinterface #5,  2            // InterfaceMethod java/util/List.add:(Ljava/lang/Object;)Z
      33: pop
      34: aload_0
      35: getfield      #1                  // Field this$1:Linfo/archinnov/achilles/generated/dsl/MultiClusteringEntity_Update$MultiClusteringEntity_UpdateEnd;
      38: invokestatic  #44                 // Method info/archinnov/achilles/generated/dsl/MultiClusteringEntity_Update$MultiClusteringEntity_UpdateEnd.access$9800:(Linfo/archinnov/achilles/generated/dsl/MultiClusteringEntity_Update$MultiClusteringEntity_UpdateEnd;)Lcom/datastax/driver/core/querybuilder/Update$Where;
      41: ldc           #13                 // String value
      43: ldc           #13                 // String value
      45: invokestatic  #14                 // Method com/datastax/driver/core/querybuilder/QueryBuilder.bindMarker:(Ljava/lang/String;)Lcom/datastax/driver/core/querybuilder/BindMarker;
      48: invokestatic  #45                 // Method com/datastax/driver/core/querybuilder/QueryBuilder.fromJson:(Ljava/lang/Object;)Ljava/lang/Object;
      51: invokestatic  #15                 // Method com/datastax/driver/core/querybuilder/QueryBuilder.eq:(Ljava/lang/String;Ljava/lang/Object;)Lcom/datastax/driver/core/querybuilder/Clause;
      54: invokevirtual #16                 // Method com/datastax/driver/core/querybuilder/Update$Where.onlyIf:(Lcom/datastax/driver/core/querybuilder/Clause;)Lcom/datastax/driver/core/querybuilder/Update$Conditions;
      57: pop
      58: aload_0
      59: getfield      #1                  // Field this$1:Linfo/archinnov/achilles/generated/dsl/MultiClusteringEntity_Update$MultiClusteringEntity_UpdateEnd;
      62: areturn
}
