Compiled from "ClusterListenerReplicateCallable.java"
public class org.infinispan.notifications.cachelistener.cluster.ClusterListenerReplicateCallable<K, V> implements org.infinispan.distexec.DistributedCallable<K, V, java.lang.Void> {
  private static final org.infinispan.util.logging.Log log;

  private static final boolean trace;

  private transient org.infinispan.manager.EmbeddedCacheManager cacheManager;

  private transient org.infinispan.notifications.cachelistener.CacheNotifier cacheNotifier;

  private transient org.infinispan.notifications.cachemanagerlistener.CacheManagerNotifier cacheManagerNotifier;

  private transient org.infinispan.distexec.DistributedExecutorService distExecutor;

  private transient org.infinispan.remoting.transport.Address ourAddress;

  private transient org.infinispan.notifications.cachelistener.cluster.ClusterEventManager<K, V> eventManager;

  private final java.util.UUID identifier;

  private final org.infinispan.notifications.cachelistener.filter.CacheEventFilter<K, V> filter;

  private final org.infinispan.notifications.cachelistener.filter.CacheEventConverter<K, V, ?> converter;

  private final org.infinispan.remoting.transport.Address origin;

  private final boolean sync;

  public org.infinispan.notifications.cachelistener.cluster.ClusterListenerReplicateCallable(java.util.UUID, org.infinispan.remoting.transport.Address, org.infinispan.notifications.cachelistener.filter.CacheEventFilter<K, V>, org.infinispan.notifications.cachelistener.filter.CacheEventConverter<K, V, ?>, boolean);
    Code:
       0: aload_0
       1: invokespecial #6                  // Method java/lang/Object."<init>":()V
       4: aload_0
       5: aload_1
       6: putfield      #5                  // Field identifier:Ljava/util/UUID;
       9: aload_0
      10: aload_2
      11: putfield      #4                  // Field origin:Lorg/infinispan/remoting/transport/Address;
      14: aload_0
      15: aload_3
      16: putfield      #3                  // Field filter:Lorg/infinispan/notifications/cachelistener/filter/CacheEventFilter;
      19: aload_0
      20: aload         4
      22: putfield      #2                  // Field converter:Lorg/infinispan/notifications/cachelistener/filter/CacheEventConverter;
      25: aload_0
      26: iload         5
      28: putfield      #1                  // Field sync:Z
      31: return

  public void setEnvironment(org.infinispan.Cache<K, V>, java.util.Set<K>);
    Code:
       0: aload_0
       1: aload_1
       2: invokeinterface #7,  1            // InterfaceMethod org/infinispan/Cache.getCacheManager:()Lorg/infinispan/manager/EmbeddedCacheManager;
       7: putfield      #8                  // Field cacheManager:Lorg/infinispan/manager/EmbeddedCacheManager;
      10: aload_1
      11: invokeinterface #9,  1            // InterfaceMethod org/infinispan/Cache.getAdvancedCache:()Lorg/infinispan/AdvancedCache;
      16: invokeinterface #10,  1           // InterfaceMethod org/infinispan/AdvancedCache.getComponentRegistry:()Lorg/infinispan/factories/ComponentRegistry;
      21: astore_3
      22: aload_0
      23: aload_3
      24: ldc           #11                 // class org/infinispan/notifications/cachelistener/CacheNotifier
      26: invokevirtual #12                 // Method org/infinispan/factories/ComponentRegistry.getComponent:(Ljava/lang/Class;)Ljava/lang/Object;
      29: checkcast     #11                 // class org/infinispan/notifications/cachelistener/CacheNotifier
      32: putfield      #13                 // Field cacheNotifier:Lorg/infinispan/notifications/cachelistener/CacheNotifier;
      35: aload_0
      36: aload_1
      37: invokeinterface #7,  1            // InterfaceMethod org/infinispan/Cache.getCacheManager:()Lorg/infinispan/manager/EmbeddedCacheManager;
      42: invokeinterface #14,  1           // InterfaceMethod org/infinispan/manager/EmbeddedCacheManager.getGlobalComponentRegistry:()Lorg/infinispan/factories/GlobalComponentRegistry;
      47: ldc           #15                 // class org/infinispan/notifications/cachemanagerlistener/CacheManagerNotifier
      49: invokevirtual #16                 // Method org/infinispan/factories/GlobalComponentRegistry.getComponent:(Ljava/lang/Class;)Ljava/lang/Object;
      52: checkcast     #15                 // class org/infinispan/notifications/cachemanagerlistener/CacheManagerNotifier
      55: putfield      #17                 // Field cacheManagerNotifier:Lorg/infinispan/notifications/cachemanagerlistener/CacheManagerNotifier;
      58: aload_0
      59: aload_1
      60: invokestatic  #18                 // Method org/infinispan/notifications/cachelistener/cluster/SecurityActions.getDefaultExecutorService:(Lorg/infinispan/Cache;)Lorg/infinispan/distexec/DefaultExecutorService;
      63: putfield      #19                 // Field distExecutor:Lorg/infinispan/distexec/DistributedExecutorService;
      66: aload_0
      67: aload_1
      68: invokeinterface #7,  1            // InterfaceMethod org/infinispan/Cache.getCacheManager:()Lorg/infinispan/manager/EmbeddedCacheManager;
      73: invokeinterface #20,  1           // InterfaceMethod org/infinispan/manager/EmbeddedCacheManager.getAddress:()Lorg/infinispan/remoting/transport/Address;
      78: putfield      #21                 // Field ourAddress:Lorg/infinispan/remoting/transport/Address;
      81: aload_0
      82: aload_3
      83: ldc           #22                 // class org/infinispan/notifications/cachelistener/cluster/ClusterEventManager
      85: invokevirtual #12                 // Method org/infinispan/factories/ComponentRegistry.getComponent:(Ljava/lang/Class;)Ljava/lang/Object;
      88: checkcast     #22                 // class org/infinispan/notifications/cachelistener/cluster/ClusterEventManager
      91: putfield      #23                 // Field eventManager:Lorg/infinispan/notifications/cachelistener/cluster/ClusterEventManager;
      94: aload_0
      95: getfield      #3                  // Field filter:Lorg/infinispan/notifications/cachelistener/filter/CacheEventFilter;
      98: ifnull        109
     101: aload_3
     102: aload_0
     103: getfield      #3                  // Field filter:Lorg/infinispan/notifications/cachelistener/filter/CacheEventFilter;
     106: invokevirtual #24                 // Method org/infinispan/factories/ComponentRegistry.wireDependencies:(Ljava/lang/Object;)V
     109: aload_0
     110: getfield      #2                  // Field converter:Lorg/infinispan/notifications/cachelistener/filter/CacheEventConverter;
     113: ifnull        135
     116: aload_0
     117: getfield      #2                  // Field converter:Lorg/infinispan/notifications/cachelistener/filter/CacheEventConverter;
     120: aload_0
     121: getfield      #3                  // Field filter:Lorg/infinispan/notifications/cachelistener/filter/CacheEventFilter;
     124: if_acmpeq     135
     127: aload_3
     128: aload_0
     129: getfield      #2                  // Field converter:Lorg/infinispan/notifications/cachelistener/filter/CacheEventConverter;
     132: invokevirtual #24                 // Method org/infinispan/factories/ComponentRegistry.wireDependencies:(Ljava/lang/Object;)V
     135: return

  public java.lang.Void call() throws java.lang.Exception;
    Code:
       0: aload_0
       1: getfield      #21                 // Field ourAddress:Lorg/infinispan/remoting/transport/Address;
       4: aload_0
       5: getfield      #4                  // Field origin:Lorg/infinispan/remoting/transport/Address;
       8: invokevirtual #25                 // Method java/lang/Object.equals:(Ljava/lang/Object;)Z
      11: ifne          331
      14: aload_0
      15: getfield      #8                  // Field cacheManager:Lorg/infinispan/manager/EmbeddedCacheManager;
      18: invokeinterface #26,  1           // InterfaceMethod org/infinispan/manager/EmbeddedCacheManager.getMembers:()Ljava/util/List;
      23: aload_0
      24: getfield      #4                  // Field origin:Lorg/infinispan/remoting/transport/Address;
      27: invokeinterface #27,  2           // InterfaceMethod java/util/List.contains:(Ljava/lang/Object;)Z
      32: ifeq          308
      35: aload_0
      36: getfield      #13                 // Field cacheNotifier:Lorg/infinispan/notifications/cachelistener/CacheNotifier;
      39: dup
      40: astore_1
      41: monitorenter
      42: iconst_0
      43: istore_2
      44: aload_0
      45: getfield      #13                 // Field cacheNotifier:Lorg/infinispan/notifications/cachelistener/CacheNotifier;
      48: invokeinterface #28,  1           // InterfaceMethod org/infinispan/notifications/cachelistener/CacheNotifier.getListeners:()Ljava/util/Set;
      53: invokeinterface #29,  1           // InterfaceMethod java/util/Set.iterator:()Ljava/util/Iterator;
      58: astore_3
      59: aload_3
      60: invokeinterface #30,  1           // InterfaceMethod java/util/Iterator.hasNext:()Z
      65: ifeq          110
      68: aload_3
      69: invokeinterface #31,  1           // InterfaceMethod java/util/Iterator.next:()Ljava/lang/Object;
      74: astore        4
      76: aload         4
      78: instanceof    #32                 // class org/infinispan/notifications/cachelistener/cluster/RemoteClusterListener
      81: ifeq          107
      84: aload_0
      85: getfield      #5                  // Field identifier:Ljava/util/UUID;
      88: aload         4
      90: checkcast     #32                 // class org/infinispan/notifications/cachelistener/cluster/RemoteClusterListener
      93: invokevirtual #33                 // Method org/infinispan/notifications/cachelistener/cluster/RemoteClusterListener.getId:()Ljava/util/UUID;
      96: invokevirtual #34                 // Method java/util/UUID.equals:(Ljava/lang/Object;)Z
      99: ifeq          107
     102: iconst_1
     103: istore_2
     104: goto          110
     107: goto          59
     110: iload_2
     111: ifne          269
     114: new           #32                 // class org/infinispan/notifications/cachelistener/cluster/RemoteClusterListener
     117: dup
     118: aload_0
     119: getfield      #5                  // Field identifier:Ljava/util/UUID;
     122: aload_0
     123: getfield      #4                  // Field origin:Lorg/infinispan/remoting/transport/Address;
     126: aload_0
     127: getfield      #19                 // Field distExecutor:Lorg/infinispan/distexec/DistributedExecutorService;
     130: aload_0
     131: getfield      #13                 // Field cacheNotifier:Lorg/infinispan/notifications/cachelistener/CacheNotifier;
     134: aload_0
     135: getfield      #17                 // Field cacheManagerNotifier:Lorg/infinispan/notifications/cachemanagerlistener/CacheManagerNotifier;
     138: aload_0
     139: getfield      #23                 // Field eventManager:Lorg/infinispan/notifications/cachelistener/cluster/ClusterEventManager;
     142: aload_0
     143: getfield      #1                  // Field sync:Z
     146: invokespecial #35                 // Method org/infinispan/notifications/cachelistener/cluster/RemoteClusterListener."<init>":(Ljava/util/UUID;Lorg/infinispan/remoting/transport/Address;Lorg/infinispan/distexec/DistributedExecutorService;Lorg/infinispan/notifications/cachelistener/CacheNotifier;Lorg/infinispan/notifications/cachemanagerlistener/CacheManagerNotifier;Lorg/infinispan/notifications/cachelistener/cluster/ClusterEventManager;Z)V
     149: astore_3
     150: aload_0
     151: getfield      #13                 // Field cacheNotifier:Lorg/infinispan/notifications/cachelistener/CacheNotifier;
     154: aload_3
     155: aload_0
     156: getfield      #3                  // Field filter:Lorg/infinispan/notifications/cachelistener/filter/CacheEventFilter;
     159: aload_0
     160: getfield      #2                  // Field converter:Lorg/infinispan/notifications/cachelistener/filter/CacheEventConverter;
     163: invokeinterface #36,  4           // InterfaceMethod org/infinispan/notifications/cachelistener/CacheNotifier.addListener:(Ljava/lang/Object;Lorg/infinispan/notifications/cachelistener/filter/CacheEventFilter;Lorg/infinispan/notifications/cachelistener/filter/CacheEventConverter;)V
     168: aload_0
     169: getfield      #17                 // Field cacheManagerNotifier:Lorg/infinispan/notifications/cachemanagerlistener/CacheManagerNotifier;
     172: aload_3
     173: invokeinterface #37,  2           // InterfaceMethod org/infinispan/notifications/cachemanagerlistener/CacheManagerNotifier.addListener:(Ljava/lang/Object;)V
     178: aload_0
     179: getfield      #8                  // Field cacheManager:Lorg/infinispan/manager/EmbeddedCacheManager;
     182: invokeinterface #26,  1           // InterfaceMethod org/infinispan/manager/EmbeddedCacheManager.getMembers:()Ljava/util/List;
     187: aload_0
     188: getfield      #4                  // Field origin:Lorg/infinispan/remoting/transport/Address;
     191: invokeinterface #27,  2           // InterfaceMethod java/util/List.contains:(Ljava/lang/Object;)Z
     196: ifne          242
     199: aload_0
     200: getfield      #13                 // Field cacheNotifier:Lorg/infinispan/notifications/cachelistener/CacheNotifier;
     203: aload_3
     204: invokeinterface #38,  2           // InterfaceMethod org/infinispan/notifications/cachelistener/CacheNotifier.removeListener:(Ljava/lang/Object;)V
     209: aload_0
     210: getfield      #17                 // Field cacheManagerNotifier:Lorg/infinispan/notifications/cachemanagerlistener/CacheManagerNotifier;
     213: aload_3
     214: invokeinterface #39,  2           // InterfaceMethod org/infinispan/notifications/cachemanagerlistener/CacheManagerNotifier.removeListener:(Ljava/lang/Object;)V
     219: getstatic     #40                 // Field trace:Z
     222: ifeq          266
     225: getstatic     #41                 // Field log:Lorg/infinispan/util/logging/Log;
     228: ldc           #42                 // String Removing local cluster listener for remote cluster listener that was just registered, as the origin %s went away concurrently
     230: aload_0
     231: getfield      #4                  // Field origin:Lorg/infinispan/remoting/transport/Address;
     234: invokeinterface #43,  3           // InterfaceMethod org/infinispan/util/logging/Log.tracef:(Ljava/lang/String;Ljava/lang/Object;)V
     239: goto          266
     242: getstatic     #40                 // Field trace:Z
     245: ifeq          266
     248: getstatic     #41                 // Field log:Lorg/infinispan/util/logging/Log;
     251: ldc           #44                 // String Registered local cluster listener for remote cluster listener from origin %s with id %s
     253: aload_0
     254: getfield      #4                  // Field origin:Lorg/infinispan/remoting/transport/Address;
     257: aload_0
     258: getfield      #5                  // Field identifier:Ljava/util/UUID;
     261: invokeinterface #45,  4           // InterfaceMethod org/infinispan/util/logging/Log.tracef:(Ljava/lang/String;Ljava/lang/Object;Ljava/lang/Object;)V
     266: goto          293
     269: getstatic     #40                 // Field trace:Z
     272: ifeq          293
     275: getstatic     #41                 // Field log:Lorg/infinispan/util/logging/Log;
     278: ldc           #46                 // String Local cluster listener from origin %s with id %s was already installed, ignoring
     280: aload_0
     281: getfield      #4                  // Field origin:Lorg/infinispan/remoting/transport/Address;
     284: aload_0
     285: getfield      #5                  // Field identifier:Ljava/util/UUID;
     288: invokeinterface #45,  4           // InterfaceMethod org/infinispan/util/logging/Log.tracef:(Ljava/lang/String;Ljava/lang/Object;Ljava/lang/Object;)V
     293: aload_1
     294: monitorexit
     295: goto          305
     298: astore        5
     300: aload_1
     301: monitorexit
     302: aload         5
     304: athrow
     305: goto          347
     308: getstatic     #40                 // Field trace:Z
     311: ifeq          347
     314: getstatic     #41                 // Field log:Lorg/infinispan/util/logging/Log;
     317: ldc           #47                 // String Not registering local cluster listener for remote cluster listener from origin %s, as the origin went away
     319: aload_0
     320: getfield      #4                  // Field origin:Lorg/infinispan/remoting/transport/Address;
     323: invokeinterface #43,  3           // InterfaceMethod org/infinispan/util/logging/Log.tracef:(Ljava/lang/String;Ljava/lang/Object;)V
     328: goto          347
     331: getstatic     #40                 // Field trace:Z
     334: ifeq          347
     337: getstatic     #41                 // Field log:Lorg/infinispan/util/logging/Log;
     340: ldc           #48                 // String Not registering local cluster listener as we are the node who registered the cluster listener
     342: invokeinterface #49,  2           // InterfaceMethod org/infinispan/util/logging/Log.trace:(Ljava/lang/Object;)V
     347: aconst_null
     348: areturn
    Exception table:
       from    to  target type
          42   295   298   any
         298   302   298   any

  public java.lang.Object call() throws java.lang.Exception;
    Code:
       0: aload_0
       1: invokevirtual #50                 // Method call:()Ljava/lang/Void;
       4: areturn

  static java.util.UUID access$000(org.infinispan.notifications.cachelistener.cluster.ClusterListenerReplicateCallable);
    Code:
       0: aload_0
       1: getfield      #5                  // Field identifier:Ljava/util/UUID;
       4: areturn

  static org.infinispan.remoting.transport.Address access$100(org.infinispan.notifications.cachelistener.cluster.ClusterListenerReplicateCallable);
    Code:
       0: aload_0
       1: getfield      #4                  // Field origin:Lorg/infinispan/remoting/transport/Address;
       4: areturn

  static org.infinispan.notifications.cachelistener.filter.CacheEventFilter access$200(org.infinispan.notifications.cachelistener.cluster.ClusterListenerReplicateCallable);
    Code:
       0: aload_0
       1: getfield      #3                  // Field filter:Lorg/infinispan/notifications/cachelistener/filter/CacheEventFilter;
       4: areturn

  static org.infinispan.notifications.cachelistener.filter.CacheEventConverter access$300(org.infinispan.notifications.cachelistener.cluster.ClusterListenerReplicateCallable);
    Code:
       0: aload_0
       1: getfield      #2                  // Field converter:Lorg/infinispan/notifications/cachelistener/filter/CacheEventConverter;
       4: areturn

  static boolean access$400(org.infinispan.notifications.cachelistener.cluster.ClusterListenerReplicateCallable);
    Code:
       0: aload_0
       1: getfield      #1                  // Field sync:Z
       4: ireturn

  static {};
    Code:
       0: ldc           #51                 // class org/infinispan/notifications/cachelistener/cluster/ClusterListenerReplicateCallable
       2: invokestatic  #52                 // Method org/infinispan/util/logging/LogFactory.getLog:(Ljava/lang/Class;)Lorg/infinispan/util/logging/Log;
       5: putstatic     #41                 // Field log:Lorg/infinispan/util/logging/Log;
       8: getstatic     #41                 // Field log:Lorg/infinispan/util/logging/Log;
      11: invokeinterface #53,  1           // InterfaceMethod org/infinispan/util/logging/Log.isTraceEnabled:()Z
      16: putstatic     #40                 // Field trace:Z
      19: return
}
