Compiled from "GraphList.java"
public class org.apache.jena.sparql.util.graph.GraphList {
  private static final org.apache.jena.graph.Node CAR;

  private static final org.apache.jena.graph.Node CDR;

  private static final org.apache.jena.graph.Node NIL;

  public org.apache.jena.sparql.util.graph.GraphList();
    Code:
       0: aload_0
       1: invokespecial #1                  // Method java/lang/Object."<init>":()V
       4: return

  public static java.util.List<org.apache.jena.graph.Node> listFromMember(org.apache.jena.sparql.util.graph.GNode);
    Code:
       0: new           #2                  // class java/util/ArrayList
       3: dup
       4: invokespecial #3                  // Method java/util/ArrayList."<init>":()V
       7: astore_1
       8: aload_0
       9: aload_1
      10: invokestatic  #4                  // Method listFromMember:(Lorg/apache/jena/sparql/util/graph/GNode;Ljava/util/Collection;)V
      13: aload_1
      14: areturn

  public static void listFromMember(org.apache.jena.sparql.util.graph.GNode, java.util.Collection<org.apache.jena.graph.Node>);
    Code:
       0: aload_0
       1: invokestatic  #5                  // Method findCellsWithMember:(Lorg/apache/jena/sparql/util/graph/GNode;)Ljava/util/Set;
       4: astore_2
       5: aload_2
       6: invokeinterface #6,  1            // InterfaceMethod java/util/Set.iterator:()Ljava/util/Iterator;
      11: astore_3
      12: aload_3
      13: invokeinterface #7,  1            // InterfaceMethod java/util/Iterator.hasNext:()Z
      18: ifeq          74
      21: aload_3
      22: invokeinterface #8,  1            // InterfaceMethod java/util/Iterator.next:()Ljava/lang/Object;
      27: checkcast     #9                  // class org/apache/jena/sparql/util/graph/GNode
      30: astore        4
      32: aload         4
      34: ifnull        71
      37: aload         4
      39: invokestatic  #10                 // Method previous:(Lorg/apache/jena/sparql/util/graph/GNode;)Lorg/apache/jena/sparql/util/graph/GNode;
      42: astore        5
      44: aload         5
      46: ifnonnull     64
      49: aload_1
      50: aload         4
      52: getfield      #11                 // Field org/apache/jena/sparql/util/graph/GNode.node:Lorg/apache/jena/graph/Node;
      55: invokeinterface #12,  2           // InterfaceMethod java/util/Collection.add:(Ljava/lang/Object;)Z
      60: pop
      61: goto          71
      64: aload         5
      66: astore        4
      68: goto          32
      71: goto          12
      74: return

  private static java.util.Set<org.apache.jena.sparql.util.graph.GNode> findCellsWithMember(org.apache.jena.sparql.util.graph.GNode);
    Code:
       0: new           #13                 // class java/util/HashSet
       3: dup
       4: invokespecial #14                 // Method java/util/HashSet."<init>":()V
       7: astore_1
       8: aload_0
       9: getfield      #15                 // Field org/apache/jena/sparql/util/graph/GNode.findable:Lorg/apache/jena/sparql/util/graph/Findable;
      12: getstatic     #16                 // Field org/apache/jena/graph/Node.ANY:Lorg/apache/jena/graph/Node;
      15: getstatic     #17                 // Field CAR:Lorg/apache/jena/graph/Node;
      18: aload_0
      19: getfield      #11                 // Field org/apache/jena/sparql/util/graph/GNode.node:Lorg/apache/jena/graph/Node;
      22: invokeinterface #18,  4           // InterfaceMethod org/apache/jena/sparql/util/graph/Findable.find:(Lorg/apache/jena/graph/Node;Lorg/apache/jena/graph/Node;Lorg/apache/jena/graph/Node;)Ljava/util/Iterator;
      27: astore_2
      28: aload_2
      29: invokeinterface #7,  1            // InterfaceMethod java/util/Iterator.hasNext:()Z
      34: ifeq          69
      37: aload_2
      38: invokeinterface #8,  1            // InterfaceMethod java/util/Iterator.next:()Ljava/lang/Object;
      43: checkcast     #19                 // class org/apache/jena/graph/Triple
      46: astore_3
      47: aload_1
      48: new           #9                  // class org/apache/jena/sparql/util/graph/GNode
      51: dup
      52: aload_0
      53: aload_3
      54: invokevirtual #20                 // Method org/apache/jena/graph/Triple.getSubject:()Lorg/apache/jena/graph/Node;
      57: invokespecial #21                 // Method org/apache/jena/sparql/util/graph/GNode."<init>":(Lorg/apache/jena/sparql/util/graph/GNode;Lorg/apache/jena/graph/Node;)V
      60: invokeinterface #22,  2           // InterfaceMethod java/util/Set.add:(Ljava/lang/Object;)Z
      65: pop
      66: goto          28
      69: aload_2
      70: invokestatic  #23                 // Method org/apache/jena/util/iterator/NiceIterator.close:(Ljava/util/Iterator;)V
      73: aload_1
      74: areturn

  private static org.apache.jena.sparql.util.graph.GNode previous(org.apache.jena.sparql.util.graph.GNode);
    Code:
       0: aload_0
       1: getstatic     #24                 // Field CDR:Lorg/apache/jena/graph/Node;
       4: invokestatic  #25                 // Method getNodeReverse:(Lorg/apache/jena/sparql/util/graph/GNode;Lorg/apache/jena/graph/Node;)Lorg/apache/jena/graph/Node;
       7: astore_1
       8: aload_1
       9: ifnonnull     14
      12: aconst_null
      13: areturn
      14: new           #9                  // class org/apache/jena/sparql/util/graph/GNode
      17: dup
      18: aload_0
      19: aload_1
      20: invokespecial #21                 // Method org/apache/jena/sparql/util/graph/GNode."<init>":(Lorg/apache/jena/sparql/util/graph/GNode;Lorg/apache/jena/graph/Node;)V
      23: areturn

  private static org.apache.jena.graph.Node getNodeReverse(org.apache.jena.sparql.util.graph.GNode, org.apache.jena.graph.Node);
    Code:
       0: aload_0
       1: aload_1
       2: invokestatic  #26                 // Method getTripleReverse:(Lorg/apache/jena/sparql/util/graph/GNode;Lorg/apache/jena/graph/Node;)Lorg/apache/jena/graph/Triple;
       5: astore_2
       6: aload_2
       7: ifnonnull     12
      10: aconst_null
      11: areturn
      12: aload_2
      13: invokevirtual #20                 // Method org/apache/jena/graph/Triple.getSubject:()Lorg/apache/jena/graph/Node;
      16: areturn

  private static org.apache.jena.graph.Triple getTripleReverse(org.apache.jena.sparql.util.graph.GNode, org.apache.jena.graph.Node);
    Code:
       0: aload_0
       1: getfield      #15                 // Field org/apache/jena/sparql/util/graph/GNode.findable:Lorg/apache/jena/sparql/util/graph/Findable;
       4: getstatic     #16                 // Field org/apache/jena/graph/Node.ANY:Lorg/apache/jena/graph/Node;
       7: aload_1
       8: aload_0
       9: getfield      #11                 // Field org/apache/jena/sparql/util/graph/GNode.node:Lorg/apache/jena/graph/Node;
      12: invokeinterface #18,  4           // InterfaceMethod org/apache/jena/sparql/util/graph/Findable.find:(Lorg/apache/jena/graph/Node;Lorg/apache/jena/graph/Node;Lorg/apache/jena/graph/Node;)Ljava/util/Iterator;
      17: astore_2
      18: aload_2
      19: invokeinterface #7,  1            // InterfaceMethod java/util/Iterator.hasNext:()Z
      24: ifne          29
      27: aconst_null
      28: areturn
      29: aload_2
      30: invokeinterface #8,  1            // InterfaceMethod java/util/Iterator.next:()Ljava/lang/Object;
      35: checkcast     #19                 // class org/apache/jena/graph/Triple
      38: astore_3
      39: aload_2
      40: invokeinterface #7,  1            // InterfaceMethod java/util/Iterator.hasNext:()Z
      45: ifeq          77
      48: ldc           #27                 // class org/apache/jena/sparql/util/graph/GraphList
      50: new           #28                 // class java/lang/StringBuilder
      53: dup
      54: invokespecial #29                 // Method java/lang/StringBuilder."<init>":()V
      57: ldc           #30                 // String Unusual list: two arcs with same property (
      59: invokevirtual #31                 // Method java/lang/StringBuilder.append:(Ljava/lang/String;)Ljava/lang/StringBuilder;
      62: aload_1
      63: invokevirtual #32                 // Method java/lang/StringBuilder.append:(Ljava/lang/Object;)Ljava/lang/StringBuilder;
      66: ldc           #33                 // String )
      68: invokevirtual #31                 // Method java/lang/StringBuilder.append:(Ljava/lang/String;)Ljava/lang/StringBuilder;
      71: invokevirtual #34                 // Method java/lang/StringBuilder.toString:()Ljava/lang/String;
      74: invokestatic  #35                 // Method org/apache/jena/atlas/logging/Log.warn:(Ljava/lang/Class;Ljava/lang/String;)V
      77: aload_2
      78: invokestatic  #23                 // Method org/apache/jena/util/iterator/NiceIterator.close:(Ljava/util/Iterator;)V
      81: aload_3
      82: areturn

  public static java.util.Iterator<org.apache.jena.graph.Triple> listMember(org.apache.jena.graph.Graph, org.apache.jena.graph.Node, org.apache.jena.graph.Node);
    Code:
       0: aload_1
       1: invokestatic  #36                 // Method isAny:(Lorg/apache/jena/graph/Node;)Z
       4: ifeq          83
       7: aload_0
       8: invokestatic  #37                 // Method findAllLists:(Lorg/apache/jena/graph/Graph;)Ljava/util/Set;
      11: astore_3
      12: new           #38                 // class org/apache/jena/atlas/iterator/IteratorConcat
      15: dup
      16: invokespecial #39                 // Method org/apache/jena/atlas/iterator/IteratorConcat."<init>":()V
      19: astore        4
      21: aload_3
      22: invokeinterface #6,  1            // InterfaceMethod java/util/Set.iterator:()Ljava/util/Iterator;
      27: astore        5
      29: aload         5
      31: invokeinterface #7,  1            // InterfaceMethod java/util/Iterator.hasNext:()Z
      36: ifeq          80
      39: aload         5
      41: invokeinterface #8,  1            // InterfaceMethod java/util/Iterator.next:()Ljava/lang/Object;
      46: checkcast     #40                 // class org/apache/jena/graph/Node
      49: astore        6
      51: aload_0
      52: aload         6
      54: aload_2
      55: invokestatic  #41                 // Method listMember:(Lorg/apache/jena/graph/Graph;Lorg/apache/jena/graph/Node;Lorg/apache/jena/graph/Node;)Ljava/util/Iterator;
      58: astore        7
      60: aload         7
      62: invokeinterface #7,  1            // InterfaceMethod java/util/Iterator.hasNext:()Z
      67: ifeq          77
      70: aload         4
      72: aload         7
      74: invokevirtual #42                 // Method org/apache/jena/atlas/iterator/IteratorConcat.add:(Ljava/util/Iterator;)V
      77: goto          29
      80: aload         4
      82: areturn
      83: new           #9                  // class org/apache/jena/sparql/util/graph/GNode
      86: dup
      87: aload_0
      88: aload_1
      89: invokespecial #43                 // Method org/apache/jena/sparql/util/graph/GNode."<init>":(Lorg/apache/jena/graph/Graph;Lorg/apache/jena/graph/Node;)V
      92: astore_3
      93: aload_2
      94: invokestatic  #36                 // Method isAny:(Lorg/apache/jena/graph/Node;)Z
      97: ifne          124
     100: aload_3
     101: aload_2
     102: invokestatic  #44                 // Method contains:(Lorg/apache/jena/sparql/util/graph/GNode;Lorg/apache/jena/graph/Node;)Z
     105: ifeq          120
     108: aload_1
     109: getstatic     #45                 // Field org/apache/jena/sparql/vocabulary/ListPFunction.nListMember:Lorg/apache/jena/graph/Node;
     112: aload_2
     113: invokestatic  #46                 // Method org/apache/jena/graph/Triple.create:(Lorg/apache/jena/graph/Node;Lorg/apache/jena/graph/Node;Lorg/apache/jena/graph/Node;)Lorg/apache/jena/graph/Triple;
     116: invokestatic  #47                 // Method org/apache/jena/atlas/iterator/Iter.singleton:(Ljava/lang/Object;)Ljava/util/Iterator;
     119: areturn
     120: invokestatic  #48                 // Method org/apache/jena/atlas/iterator/Iter.nullIterator:()Ljava/util/Iterator;
     123: areturn
     124: aload_3
     125: invokestatic  #49                 // Method members:(Lorg/apache/jena/sparql/util/graph/GNode;)Ljava/util/List;
     128: astore        4
     130: aload         4
     132: invokeinterface #50,  1           // InterfaceMethod java/util/List.iterator:()Ljava/util/Iterator;
     137: aload_1
     138: invokedynamic #51,  0             // InvokeDynamic #0:apply:(Lorg/apache/jena/graph/Node;)Ljava/util/function/Function;
     143: invokestatic  #52                 // Method org/apache/jena/atlas/iterator/Iter.map:(Ljava/util/Iterator;Ljava/util/function/Function;)Ljava/util/Iterator;
     146: areturn

  private static boolean isAny(org.apache.jena.graph.Node);
    Code:
       0: aload_0
       1: ifnull        14
       4: getstatic     #16                 // Field org/apache/jena/graph/Node.ANY:Lorg/apache/jena/graph/Node;
       7: aload_0
       8: invokevirtual #53                 // Method org/apache/jena/graph/Node.equals:(Ljava/lang/Object;)Z
      11: ifeq          18
      14: iconst_1
      15: goto          19
      18: iconst_0
      19: ireturn

  public static java.util.List<org.apache.jena.graph.Node> members(org.apache.jena.sparql.util.graph.GNode);
    Code:
       0: new           #2                  // class java/util/ArrayList
       3: dup
       4: invokespecial #3                  // Method java/util/ArrayList."<init>":()V
       7: astore_1
       8: aload_0
       9: aload_1
      10: invokestatic  #54                 // Method members:(Lorg/apache/jena/sparql/util/graph/GNode;Ljava/util/Collection;)V
      13: aload_1
      14: areturn

  public static void members(org.apache.jena.sparql.util.graph.GNode, java.util.Collection<org.apache.jena.graph.Node>);
    Code:
       0: aload_0
       1: invokestatic  #55                 // Method isListNode:(Lorg/apache/jena/sparql/util/graph/GNode;)Z
       4: ifne          8
       7: return
       8: aload_0
       9: invokestatic  #56                 // Method listEnd:(Lorg/apache/jena/sparql/util/graph/GNode;)Z
      12: ifne          40
      15: aload_0
      16: invokestatic  #57                 // Method car:(Lorg/apache/jena/sparql/util/graph/GNode;)Lorg/apache/jena/graph/Node;
      19: astore_2
      20: aload_2
      21: ifnull        32
      24: aload_1
      25: aload_2
      26: invokeinterface #12,  2           // InterfaceMethod java/util/Collection.add:(Ljava/lang/Object;)Z
      31: pop
      32: aload_0
      33: invokestatic  #58                 // Method next:(Lorg/apache/jena/sparql/util/graph/GNode;)Lorg/apache/jena/sparql/util/graph/GNode;
      36: astore_0
      37: goto          8
      40: return

  public static int length(org.apache.jena.sparql.util.graph.GNode);
    Code:
       0: aload_0
       1: invokestatic  #55                 // Method isListNode:(Lorg/apache/jena/sparql/util/graph/GNode;)Z
       4: ifne          9
       7: iconst_m1
       8: ireturn
       9: iconst_0
      10: istore_1
      11: aload_0
      12: invokestatic  #56                 // Method listEnd:(Lorg/apache/jena/sparql/util/graph/GNode;)Z
      15: ifne          29
      18: iinc          1, 1
      21: aload_0
      22: invokestatic  #58                 // Method next:(Lorg/apache/jena/sparql/util/graph/GNode;)Lorg/apache/jena/sparql/util/graph/GNode;
      25: astore_0
      26: goto          11
      29: iload_1
      30: ireturn

  public static int occurs(org.apache.jena.sparql.util.graph.GNode, org.apache.jena.graph.Node);
    Code:
       0: aload_0
       1: aload_1
       2: invokestatic  #59                 // Method indexes:(Lorg/apache/jena/sparql/util/graph/GNode;Lorg/apache/jena/graph/Node;)Ljava/util/List;
       5: invokeinterface #60,  1           // InterfaceMethod java/util/List.size:()I
      10: ireturn

  public static boolean contains(org.apache.jena.sparql.util.graph.GNode, org.apache.jena.graph.Node);
    Code:
       0: aload_0
       1: aload_1
       2: invokestatic  #61                 // Method index:(Lorg/apache/jena/sparql/util/graph/GNode;Lorg/apache/jena/graph/Node;)I
       5: iflt          12
       8: iconst_1
       9: goto          13
      12: iconst_0
      13: ireturn

  public static org.apache.jena.graph.Node get(org.apache.jena.sparql.util.graph.GNode, int);
    Code:
       0: aload_0
       1: invokestatic  #55                 // Method isListNode:(Lorg/apache/jena/sparql/util/graph/GNode;)Z
       4: ifne          9
       7: aconst_null
       8: areturn
       9: aload_0
      10: invokestatic  #56                 // Method listEnd:(Lorg/apache/jena/sparql/util/graph/GNode;)Z
      13: ifne          36
      16: iload_1
      17: ifne          25
      20: aload_0
      21: invokestatic  #57                 // Method car:(Lorg/apache/jena/sparql/util/graph/GNode;)Lorg/apache/jena/graph/Node;
      24: areturn
      25: aload_0
      26: invokestatic  #58                 // Method next:(Lorg/apache/jena/sparql/util/graph/GNode;)Lorg/apache/jena/sparql/util/graph/GNode;
      29: astore_0
      30: iinc          1, -1
      33: goto          9
      36: aconst_null
      37: areturn

  public static int index(org.apache.jena.sparql.util.graph.GNode, org.apache.jena.graph.Node);
    Code:
       0: aload_0
       1: invokestatic  #55                 // Method isListNode:(Lorg/apache/jena/sparql/util/graph/GNode;)Z
       4: ifne          9
       7: iconst_m1
       8: ireturn
       9: iconst_0
      10: istore_2
      11: aload_0
      12: invokestatic  #56                 // Method listEnd:(Lorg/apache/jena/sparql/util/graph/GNode;)Z
      15: ifne          48
      18: aload_0
      19: invokestatic  #57                 // Method car:(Lorg/apache/jena/sparql/util/graph/GNode;)Lorg/apache/jena/graph/Node;
      22: astore_3
      23: aload_3
      24: ifnull        37
      27: aload_3
      28: aload_1
      29: invokevirtual #53                 // Method org/apache/jena/graph/Node.equals:(Ljava/lang/Object;)Z
      32: ifeq          37
      35: iload_2
      36: ireturn
      37: aload_0
      38: invokestatic  #58                 // Method next:(Lorg/apache/jena/sparql/util/graph/GNode;)Lorg/apache/jena/sparql/util/graph/GNode;
      41: astore_0
      42: iinc          2, 1
      45: goto          11
      48: iconst_m1
      49: ireturn

  public static java.util.List<java.lang.Integer> indexes(org.apache.jena.sparql.util.graph.GNode, org.apache.jena.graph.Node);
    Code:
       0: new           #2                  // class java/util/ArrayList
       3: dup
       4: invokespecial #3                  // Method java/util/ArrayList."<init>":()V
       7: astore_2
       8: aload_0
       9: invokestatic  #55                 // Method isListNode:(Lorg/apache/jena/sparql/util/graph/GNode;)Z
      12: ifne          17
      15: aload_2
      16: areturn
      17: iconst_0
      18: istore_3
      19: aload_0
      20: invokestatic  #56                 // Method listEnd:(Lorg/apache/jena/sparql/util/graph/GNode;)Z
      23: ifne          72
      26: aload_0
      27: invokestatic  #57                 // Method car:(Lorg/apache/jena/sparql/util/graph/GNode;)Lorg/apache/jena/graph/Node;
      30: astore        4
      32: aload         4
      34: ifnull        61
      37: aload         4
      39: aload_1
      40: invokevirtual #53                 // Method org/apache/jena/graph/Node.equals:(Ljava/lang/Object;)Z
      43: ifeq          61
      46: aload_2
      47: new           #62                 // class java/lang/Integer
      50: dup
      51: iload_3
      52: invokespecial #63                 // Method java/lang/Integer."<init>":(I)V
      55: invokeinterface #64,  2           // InterfaceMethod java/util/List.add:(Ljava/lang/Object;)Z
      60: pop
      61: aload_0
      62: invokestatic  #58                 // Method next:(Lorg/apache/jena/sparql/util/graph/GNode;)Lorg/apache/jena/sparql/util/graph/GNode;
      65: astore_0
      66: iinc          3, 1
      69: goto          19
      72: aload_2
      73: areturn

  public static void triples(org.apache.jena.sparql.util.graph.GNode, java.util.Collection<org.apache.jena.graph.Triple>);
    Code:
       0: aload_0
       1: invokestatic  #56                 // Method listEnd:(Lorg/apache/jena/sparql/util/graph/GNode;)Z
       4: ifeq          8
       7: return
       8: aconst_null
       9: astore_2
      10: aload_0
      11: getstatic     #17                 // Field CAR:Lorg/apache/jena/graph/Node;
      14: invokestatic  #65                 // Method getTriple:(Lorg/apache/jena/sparql/util/graph/GNode;Lorg/apache/jena/graph/Node;)Lorg/apache/jena/graph/Triple;
      17: astore_2
      18: aload_2
      19: ifnull        30
      22: aload_1
      23: aload_2
      24: invokeinterface #12,  2           // InterfaceMethod java/util/Collection.add:(Ljava/lang/Object;)Z
      29: pop
      30: aload_0
      31: getstatic     #24                 // Field CDR:Lorg/apache/jena/graph/Node;
      34: invokestatic  #65                 // Method getTriple:(Lorg/apache/jena/sparql/util/graph/GNode;Lorg/apache/jena/graph/Node;)Lorg/apache/jena/graph/Triple;
      37: astore_2
      38: aload_2
      39: ifnull        50
      42: aload_1
      43: aload_2
      44: invokeinterface #12,  2           // InterfaceMethod java/util/Collection.add:(Ljava/lang/Object;)Z
      49: pop
      50: return

  public static java.util.List<org.apache.jena.graph.Triple> allTriples(org.apache.jena.sparql.util.graph.GNode);
    Code:
       0: new           #2                  // class java/util/ArrayList
       3: dup
       4: invokespecial #3                  // Method java/util/ArrayList."<init>":()V
       7: astore_1
       8: aload_0
       9: aload_1
      10: invokestatic  #66                 // Method allTriples:(Lorg/apache/jena/sparql/util/graph/GNode;Ljava/util/Collection;)V
      13: aload_1
      14: areturn

  public static void allTriples(org.apache.jena.sparql.util.graph.GNode, java.util.Collection<org.apache.jena.graph.Triple>);
    Code:
       0: aload_0
       1: invokestatic  #55                 // Method isListNode:(Lorg/apache/jena/sparql/util/graph/GNode;)Z
       4: ifne          8
       7: return
       8: aload_0
       9: invokestatic  #56                 // Method listEnd:(Lorg/apache/jena/sparql/util/graph/GNode;)Z
      12: ifne          28
      15: aload_0
      16: aload_1
      17: invokestatic  #67                 // Method triples:(Lorg/apache/jena/sparql/util/graph/GNode;Ljava/util/Collection;)V
      20: aload_0
      21: invokestatic  #58                 // Method next:(Lorg/apache/jena/sparql/util/graph/GNode;)Lorg/apache/jena/sparql/util/graph/GNode;
      24: astore_0
      25: goto          8
      28: return

  public static java.util.Set<org.apache.jena.graph.Node> findAllLists(org.apache.jena.graph.Graph);
    Code:
       0: new           #13                 // class java/util/HashSet
       3: dup
       4: invokespecial #14                 // Method java/util/HashSet."<init>":()V
       7: astore_1
       8: aload_0
       9: getstatic     #16                 // Field org/apache/jena/graph/Node.ANY:Lorg/apache/jena/graph/Node;
      12: getstatic     #24                 // Field CDR:Lorg/apache/jena/graph/Node;
      15: getstatic     #16                 // Field org/apache/jena/graph/Node.ANY:Lorg/apache/jena/graph/Node;
      18: invokeinterface #68,  4           // InterfaceMethod org/apache/jena/graph/Graph.find:(Lorg/apache/jena/graph/Node;Lorg/apache/jena/graph/Node;Lorg/apache/jena/graph/Node;)Lorg/apache/jena/util/iterator/ExtendedIterator;
      23: astore_2
      24: aload_2
      25: invokeinterface #7,  1            // InterfaceMethod java/util/Iterator.hasNext:()Z
      30: ifeq          78
      33: aload_2
      34: invokeinterface #8,  1            // InterfaceMethod java/util/Iterator.next:()Ljava/lang/Object;
      39: checkcast     #19                 // class org/apache/jena/graph/Triple
      42: astore_3
      43: aload_3
      44: invokevirtual #20                 // Method org/apache/jena/graph/Triple.getSubject:()Lorg/apache/jena/graph/Node;
      47: astore        4
      49: aload_0
      50: getstatic     #16                 // Field org/apache/jena/graph/Node.ANY:Lorg/apache/jena/graph/Node;
      53: getstatic     #24                 // Field CDR:Lorg/apache/jena/graph/Node;
      56: aload         4
      58: invokeinterface #69,  4           // InterfaceMethod org/apache/jena/graph/Graph.contains:(Lorg/apache/jena/graph/Node;Lorg/apache/jena/graph/Node;Lorg/apache/jena/graph/Node;)Z
      63: ifne          75
      66: aload_1
      67: aload         4
      69: invokeinterface #22,  2           // InterfaceMethod java/util/Set.add:(Ljava/lang/Object;)Z
      74: pop
      75: goto          24
      78: aload_2
      79: invokestatic  #23                 // Method org/apache/jena/util/iterator/NiceIterator.close:(Ljava/util/Iterator;)V
      82: goto          94
      85: astore        5
      87: aload_2
      88: invokestatic  #23                 // Method org/apache/jena/util/iterator/NiceIterator.close:(Ljava/util/Iterator;)V
      91: aload         5
      93: athrow
      94: aload_0
      95: getstatic     #16                 // Field org/apache/jena/graph/Node.ANY:Lorg/apache/jena/graph/Node;
      98: getstatic     #16                 // Field org/apache/jena/graph/Node.ANY:Lorg/apache/jena/graph/Node;
     101: getstatic     #70                 // Field NIL:Lorg/apache/jena/graph/Node;
     104: invokeinterface #68,  4           // InterfaceMethod org/apache/jena/graph/Graph.find:(Lorg/apache/jena/graph/Node;Lorg/apache/jena/graph/Node;Lorg/apache/jena/graph/Node;)Lorg/apache/jena/util/iterator/ExtendedIterator;
     109: astore_2
     110: aload_2
     111: invokeinterface #7,  1            // InterfaceMethod java/util/Iterator.hasNext:()Z
     116: ifeq          158
     119: aload_2
     120: invokeinterface #8,  1            // InterfaceMethod java/util/Iterator.next:()Ljava/lang/Object;
     125: checkcast     #19                 // class org/apache/jena/graph/Triple
     128: astore_3
     129: aload_3
     130: invokevirtual #71                 // Method org/apache/jena/graph/Triple.getPredicate:()Lorg/apache/jena/graph/Node;
     133: getstatic     #24                 // Field CDR:Lorg/apache/jena/graph/Node;
     136: invokevirtual #53                 // Method org/apache/jena/graph/Node.equals:(Ljava/lang/Object;)Z
     139: ifne          155
     142: aload_1
     143: getstatic     #70                 // Field NIL:Lorg/apache/jena/graph/Node;
     146: invokeinterface #22,  2           // InterfaceMethod java/util/Set.add:(Ljava/lang/Object;)Z
     151: pop
     152: goto          158
     155: goto          110
     158: aload_2
     159: invokestatic  #23                 // Method org/apache/jena/util/iterator/NiceIterator.close:(Ljava/util/Iterator;)V
     162: goto          174
     165: astore        6
     167: aload_2
     168: invokestatic  #23                 // Method org/apache/jena/util/iterator/NiceIterator.close:(Ljava/util/Iterator;)V
     171: aload         6
     173: athrow
     174: aload_0
     175: getstatic     #70                 // Field NIL:Lorg/apache/jena/graph/Node;
     178: getstatic     #16                 // Field org/apache/jena/graph/Node.ANY:Lorg/apache/jena/graph/Node;
     181: getstatic     #16                 // Field org/apache/jena/graph/Node.ANY:Lorg/apache/jena/graph/Node;
     184: invokeinterface #69,  4           // InterfaceMethod org/apache/jena/graph/Graph.contains:(Lorg/apache/jena/graph/Node;Lorg/apache/jena/graph/Node;Lorg/apache/jena/graph/Node;)Z
     189: ifeq          202
     192: aload_1
     193: getstatic     #70                 // Field NIL:Lorg/apache/jena/graph/Node;
     196: invokeinterface #22,  2           // InterfaceMethod java/util/Set.add:(Ljava/lang/Object;)Z
     201: pop
     202: aload_1
     203: areturn
    Exception table:
       from    to  target type
          24    78    85   any
          85    87    85   any
         110   158   165   any
         165   167   165   any

  public static org.apache.jena.graph.Node listToTriples(java.util.List<org.apache.jena.graph.Node>, org.apache.jena.sparql.core.BasicPattern);
    Code:
       0: aload_0
       1: invokeinterface #60,  1           // InterfaceMethod java/util/List.size:()I
       6: ifne          13
       9: getstatic     #72                 // Field org/apache/jena/vocabulary/RDF$Nodes.nil:Lorg/apache/jena/graph/Node;
      12: areturn
      13: invokestatic  #73                 // Method org/apache/jena/graph/NodeFactory.createBlankNode:()Lorg/apache/jena/graph/Node;
      16: astore_2
      17: aload_2
      18: astore_3
      19: aload_0
      20: invokeinterface #50,  1           // InterfaceMethod java/util/List.iterator:()Ljava/util/Iterator;
      25: astore        4
      27: aload         4
      29: invokeinterface #7,  1            // InterfaceMethod java/util/Iterator.hasNext:()Z
      34: ifeq          103
      37: aload         4
      39: invokeinterface #8,  1            // InterfaceMethod java/util/Iterator.next:()Ljava/lang/Object;
      44: checkcast     #40                 // class org/apache/jena/graph/Node
      47: astore        5
      49: invokestatic  #73                 // Method org/apache/jena/graph/NodeFactory.createBlankNode:()Lorg/apache/jena/graph/Node;
      52: astore        6
      54: new           #19                 // class org/apache/jena/graph/Triple
      57: dup
      58: aload_3
      59: getstatic     #74                 // Field org/apache/jena/vocabulary/RDF$Nodes.rest:Lorg/apache/jena/graph/Node;
      62: aload         6
      64: invokespecial #75                 // Method org/apache/jena/graph/Triple."<init>":(Lorg/apache/jena/graph/Node;Lorg/apache/jena/graph/Node;Lorg/apache/jena/graph/Node;)V
      67: astore        7
      69: new           #19                 // class org/apache/jena/graph/Triple
      72: dup
      73: aload         6
      75: getstatic     #76                 // Field org/apache/jena/vocabulary/RDF$Nodes.first:Lorg/apache/jena/graph/Node;
      78: aload         5
      80: invokespecial #75                 // Method org/apache/jena/graph/Triple."<init>":(Lorg/apache/jena/graph/Node;Lorg/apache/jena/graph/Node;Lorg/apache/jena/graph/Node;)V
      83: astore        8
      85: aload         6
      87: astore_3
      88: aload_1
      89: aload         7
      91: invokevirtual #77                 // Method org/apache/jena/sparql/core/BasicPattern.add:(Lorg/apache/jena/graph/Triple;)V
      94: aload_1
      95: aload         8
      97: invokevirtual #77                 // Method org/apache/jena/sparql/core/BasicPattern.add:(Lorg/apache/jena/graph/Triple;)V
     100: goto          27
     103: new           #19                 // class org/apache/jena/graph/Triple
     106: dup
     107: aload_3
     108: getstatic     #74                 // Field org/apache/jena/vocabulary/RDF$Nodes.rest:Lorg/apache/jena/graph/Node;
     111: getstatic     #72                 // Field org/apache/jena/vocabulary/RDF$Nodes.nil:Lorg/apache/jena/graph/Node;
     114: invokespecial #75                 // Method org/apache/jena/graph/Triple."<init>":(Lorg/apache/jena/graph/Node;Lorg/apache/jena/graph/Node;Lorg/apache/jena/graph/Node;)V
     117: astore        4
     119: aload_1
     120: aload         4
     122: invokevirtual #77                 // Method org/apache/jena/sparql/core/BasicPattern.add:(Lorg/apache/jena/graph/Triple;)V
     125: aload_2
     126: areturn

  private static org.apache.jena.sparql.util.graph.GNode next(org.apache.jena.sparql.util.graph.GNode);
    Code:
       0: new           #9                  // class org/apache/jena/sparql/util/graph/GNode
       3: dup
       4: aload_0
       5: aload_0
       6: invokestatic  #78                 // Method cdr:(Lorg/apache/jena/sparql/util/graph/GNode;)Lorg/apache/jena/graph/Node;
       9: invokespecial #21                 // Method org/apache/jena/sparql/util/graph/GNode."<init>":(Lorg/apache/jena/sparql/util/graph/GNode;Lorg/apache/jena/graph/Node;)V
      12: areturn

  public static boolean isListNode(org.apache.jena.sparql.util.graph.GNode);
    Code:
       0: aload_0
       1: getfield      #11                 // Field org/apache/jena/sparql/util/graph/GNode.node:Lorg/apache/jena/graph/Node;
       4: getstatic     #70                 // Field NIL:Lorg/apache/jena/graph/Node;
       7: invokevirtual #53                 // Method org/apache/jena/graph/Node.equals:(Ljava/lang/Object;)Z
      10: ifne          20
      13: aload_0
      14: invokestatic  #79                 // Method isCons:(Lorg/apache/jena/sparql/util/graph/GNode;)Z
      17: ifeq          24
      20: iconst_1
      21: goto          25
      24: iconst_0
      25: ireturn

  private static boolean isCons(org.apache.jena.sparql.util.graph.GNode);
    Code:
       0: aload_0
       1: getfield      #15                 // Field org/apache/jena/sparql/util/graph/GNode.findable:Lorg/apache/jena/sparql/util/graph/Findable;
       4: aload_0
       5: getfield      #11                 // Field org/apache/jena/sparql/util/graph/GNode.node:Lorg/apache/jena/graph/Node;
       8: getstatic     #24                 // Field CDR:Lorg/apache/jena/graph/Node;
      11: aconst_null
      12: invokeinterface #80,  4           // InterfaceMethod org/apache/jena/sparql/util/graph/Findable.contains:(Lorg/apache/jena/graph/Node;Lorg/apache/jena/graph/Node;Lorg/apache/jena/graph/Node;)Z
      17: ireturn

  private static boolean listEnd(org.apache.jena.sparql.util.graph.GNode);
    Code:
       0: aload_0
       1: getfield      #11                 // Field org/apache/jena/sparql/util/graph/GNode.node:Lorg/apache/jena/graph/Node;
       4: ifnull        20
       7: aload_0
       8: getfield      #11                 // Field org/apache/jena/sparql/util/graph/GNode.node:Lorg/apache/jena/graph/Node;
      11: getstatic     #70                 // Field NIL:Lorg/apache/jena/graph/Node;
      14: invokevirtual #53                 // Method org/apache/jena/graph/Node.equals:(Ljava/lang/Object;)Z
      17: ifeq          24
      20: iconst_1
      21: goto          25
      24: iconst_0
      25: ireturn

  private static org.apache.jena.graph.Node car(org.apache.jena.sparql.util.graph.GNode);
    Code:
       0: aload_0
       1: getstatic     #17                 // Field CAR:Lorg/apache/jena/graph/Node;
       4: invokestatic  #81                 // Method getNode:(Lorg/apache/jena/sparql/util/graph/GNode;Lorg/apache/jena/graph/Node;)Lorg/apache/jena/graph/Node;
       7: areturn

  private static org.apache.jena.graph.Node cdr(org.apache.jena.sparql.util.graph.GNode);
    Code:
       0: aload_0
       1: getstatic     #24                 // Field CDR:Lorg/apache/jena/graph/Node;
       4: invokestatic  #81                 // Method getNode:(Lorg/apache/jena/sparql/util/graph/GNode;Lorg/apache/jena/graph/Node;)Lorg/apache/jena/graph/Node;
       7: areturn

  private static org.apache.jena.graph.Node getNode(org.apache.jena.sparql.util.graph.GNode, org.apache.jena.graph.Node);
    Code:
       0: aload_0
       1: invokestatic  #56                 // Method listEnd:(Lorg/apache/jena/sparql/util/graph/GNode;)Z
       4: ifeq          9
       7: aconst_null
       8: areturn
       9: aload_0
      10: aload_1
      11: invokestatic  #65                 // Method getTriple:(Lorg/apache/jena/sparql/util/graph/GNode;Lorg/apache/jena/graph/Node;)Lorg/apache/jena/graph/Triple;
      14: astore_2
      15: aload_2
      16: ifnonnull     21
      19: aconst_null
      20: areturn
      21: aload_2
      22: invokevirtual #82                 // Method org/apache/jena/graph/Triple.getObject:()Lorg/apache/jena/graph/Node;
      25: areturn

  private static org.apache.jena.graph.Triple getTriple(org.apache.jena.sparql.util.graph.GNode, org.apache.jena.graph.Node);
    Code:
       0: aload_0
       1: invokestatic  #56                 // Method listEnd:(Lorg/apache/jena/sparql/util/graph/GNode;)Z
       4: ifeq          9
       7: aconst_null
       8: areturn
       9: aload_0
      10: getfield      #15                 // Field org/apache/jena/sparql/util/graph/GNode.findable:Lorg/apache/jena/sparql/util/graph/Findable;
      13: aload_0
      14: getfield      #11                 // Field org/apache/jena/sparql/util/graph/GNode.node:Lorg/apache/jena/graph/Node;
      17: aload_1
      18: getstatic     #16                 // Field org/apache/jena/graph/Node.ANY:Lorg/apache/jena/graph/Node;
      21: invokeinterface #18,  4           // InterfaceMethod org/apache/jena/sparql/util/graph/Findable.find:(Lorg/apache/jena/graph/Node;Lorg/apache/jena/graph/Node;Lorg/apache/jena/graph/Node;)Ljava/util/Iterator;
      26: astore_2
      27: aload_2
      28: invokeinterface #7,  1            // InterfaceMethod java/util/Iterator.hasNext:()Z
      33: ifne          38
      36: aconst_null
      37: areturn
      38: aload_2
      39: invokeinterface #8,  1            // InterfaceMethod java/util/Iterator.next:()Ljava/lang/Object;
      44: checkcast     #19                 // class org/apache/jena/graph/Triple
      47: astore_3
      48: aload_2
      49: invokeinterface #7,  1            // InterfaceMethod java/util/Iterator.hasNext:()Z
      54: ifeq          86
      57: ldc           #27                 // class org/apache/jena/sparql/util/graph/GraphList
      59: new           #28                 // class java/lang/StringBuilder
      62: dup
      63: invokespecial #29                 // Method java/lang/StringBuilder."<init>":()V
      66: ldc           #30                 // String Unusual list: two arcs with same property (
      68: invokevirtual #31                 // Method java/lang/StringBuilder.append:(Ljava/lang/String;)Ljava/lang/StringBuilder;
      71: aload_1
      72: invokevirtual #32                 // Method java/lang/StringBuilder.append:(Ljava/lang/Object;)Ljava/lang/StringBuilder;
      75: ldc           #33                 // String )
      77: invokevirtual #31                 // Method java/lang/StringBuilder.append:(Ljava/lang/String;)Ljava/lang/StringBuilder;
      80: invokevirtual #34                 // Method java/lang/StringBuilder.toString:()Ljava/lang/String;
      83: invokestatic  #35                 // Method org/apache/jena/atlas/logging/Log.warn:(Ljava/lang/Class;Ljava/lang/String;)V
      86: aload_2
      87: invokestatic  #23                 // Method org/apache/jena/util/iterator/NiceIterator.close:(Ljava/util/Iterator;)V
      90: aload_3
      91: areturn

  private static org.apache.jena.graph.Triple lambda$listMember$0(org.apache.jena.graph.Node, org.apache.jena.graph.Node);
    Code:
       0: aload_0
       1: getstatic     #45                 // Field org/apache/jena/sparql/vocabulary/ListPFunction.nListMember:Lorg/apache/jena/graph/Node;
       4: aload_1
       5: invokestatic  #46                 // Method org/apache/jena/graph/Triple.create:(Lorg/apache/jena/graph/Node;Lorg/apache/jena/graph/Node;Lorg/apache/jena/graph/Node;)Lorg/apache/jena/graph/Triple;
       8: areturn

  static {};
    Code:
       0: getstatic     #83                 // Field org/apache/jena/vocabulary/RDF.first:Lorg/apache/jena/rdf/model/Property;
       3: invokeinterface #84,  1           // InterfaceMethod org/apache/jena/rdf/model/Property.asNode:()Lorg/apache/jena/graph/Node;
       8: putstatic     #17                 // Field CAR:Lorg/apache/jena/graph/Node;
      11: getstatic     #85                 // Field org/apache/jena/vocabulary/RDF.rest:Lorg/apache/jena/rdf/model/Property;
      14: invokeinterface #84,  1           // InterfaceMethod org/apache/jena/rdf/model/Property.asNode:()Lorg/apache/jena/graph/Node;
      19: putstatic     #24                 // Field CDR:Lorg/apache/jena/graph/Node;
      22: getstatic     #86                 // Field org/apache/jena/vocabulary/RDF.nil:Lorg/apache/jena/rdf/model/Resource;
      25: invokeinterface #87,  1           // InterfaceMethod org/apache/jena/rdf/model/Resource.asNode:()Lorg/apache/jena/graph/Node;
      30: putstatic     #70                 // Field NIL:Lorg/apache/jena/graph/Node;
      33: return
}
