Compiled from "TempFileUtils.java"
public final class org.sonar.api.utils.TempFileUtils {
  private org.sonar.api.utils.TempFileUtils();
    Code:
       0: aload_0
       1: invokespecial #10                 // Method java/lang/Object."<init>":()V
       4: return

  public static java.io.File createTempDirectory() throws java.io.IOException;
    Code:
       0: ldc           #18                 // String temp
       2: invokestatic  #21                 // Method createTempDirectory:(Ljava/lang/String;)Ljava/io/File;
       5: areturn

  public static java.io.File createTempDirectory(java.lang.String) throws java.io.IOException;
    Code:
       0: aload_0
       1: iconst_0
       2: anewarray     #23                 // class java/nio/file/attribute/FileAttribute
       5: invokestatic  #28                 // Method java/nio/file/Files.createTempDirectory:(Ljava/lang/String;[Ljava/nio/file/attribute/FileAttribute;)Ljava/nio/file/Path;
       8: astore_1
       9: aload_1
      10: invokeinterface #33,  1           // InterfaceMethod java/nio/file/Path.toFile:()Ljava/io/File;
      15: areturn
}
