Compiled from "JavaTarget.java"
public class org.antlr.v4.codegen.target.JavaTarget$JavaStringRenderer extends org.stringtemplate.v4.StringRenderer {
  protected org.antlr.v4.codegen.target.JavaTarget$JavaStringRenderer();
    Code:
       0: aload_0
       1: invokespecial #1                  // Method org/stringtemplate/v4/StringRenderer."<init>":()V
       4: return

  public java.lang.String toString(java.lang.Object, java.lang.String, java.util.Locale);
    Code:
       0: ldc           #2                  // String java-escape
       2: aload_2
       3: invokevirtual #3                  // Method java/lang/String.equals:(Ljava/lang/Object;)Z
       6: ifeq          21
       9: aload_1
      10: checkcast     #4                  // class java/lang/String
      13: ldc           #5                  // String \\u
      15: ldc           #6                  // String \\u005Cu
      17: invokevirtual #7                  // Method java/lang/String.replace:(Ljava/lang/CharSequence;Ljava/lang/CharSequence;)Ljava/lang/String;
      20: areturn
      21: aload_0
      22: aload_1
      23: aload_2
      24: aload_3
      25: invokespecial #8                  // Method org/stringtemplate/v4/StringRenderer.toString:(Ljava/lang/Object;Ljava/lang/String;Ljava/util/Locale;)Ljava/lang/String;
      28: areturn
}
