Compiled from "DataRowImpl.kt"
final class org.jetbrains.kotlinx.dataframe.impl.DataRowImplKt$namedValues$1 extends kotlin.jvm.internal.Lambda implements kotlin.jvm.functions.Function1<org.jetbrains.kotlinx.dataframe.DataColumn<?>, org.jetbrains.kotlinx.dataframe.aggregation.NamedValue> {
  final org.jetbrains.kotlinx.dataframe.DataRow<?> $this_namedValues;

  org.jetbrains.kotlinx.dataframe.impl.DataRowImplKt$namedValues$1(org.jetbrains.kotlinx.dataframe.DataRow<?>);
    Code:
       0: aload_0
       1: aload_1
       2: putfield      #14                 // Field $this_namedValues:Lorg/jetbrains/kotlinx/dataframe/DataRow;
       5: aload_0
       6: iconst_1
       7: invokespecial #17                 // Method kotlin/jvm/internal/Lambda."<init>":(I)V
      10: return

  public final org.jetbrains.kotlinx.dataframe.aggregation.NamedValue invoke(org.jetbrains.kotlinx.dataframe.DataColumn<?>);
    Code:
       0: aload_1
       1: ldc           #26                 // String it
       3: invokestatic  #32                 // Method kotlin/jvm/internal/Intrinsics.checkNotNullParameter:(Ljava/lang/Object;Ljava/lang/String;)V
       6: getstatic     #38                 // Field org/jetbrains/kotlinx/dataframe/aggregation/NamedValue.Companion:Lorg/jetbrains/kotlinx/dataframe/aggregation/NamedValue$Companion;
       9: aload_1
      10: checkcast     #40                 // class org/jetbrains/kotlinx/dataframe/columns/ColumnReference
      13: invokestatic  #46                 // Method org/jetbrains/kotlinx/dataframe/columns/ColumnReferenceKt.shortPath:(Lorg/jetbrains/kotlinx/dataframe/columns/ColumnReference;)Lorg/jetbrains/kotlinx/dataframe/columns/ColumnPath;
      16: aload_1
      17: aload_0
      18: getfield      #14                 // Field $this_namedValues:Lorg/jetbrains/kotlinx/dataframe/DataRow;
      21: invokestatic  #52                 // Method org/jetbrains/kotlinx/dataframe/DataRowKt.getIndex:(Lorg/jetbrains/kotlinx/dataframe/DataRow;)I
      24: invokeinterface #58,  2           // InterfaceMethod org/jetbrains/kotlinx/dataframe/DataColumn.get:(I)Ljava/lang/Object;
      29: aload_1
      30: invokeinterface #62,  1           // InterfaceMethod org/jetbrains/kotlinx/dataframe/DataColumn.type:()Lkotlin/reflect/KType;
      35: aload_1
      36: invokeinterface #66,  1           // InterfaceMethod org/jetbrains/kotlinx/dataframe/DataColumn.defaultValue:()Ljava/lang/Object;
      41: iconst_0
      42: invokevirtual #72                 // Method org/jetbrains/kotlinx/dataframe/aggregation/NamedValue$Companion.create$dataframe:(Lorg/jetbrains/kotlinx/dataframe/columns/ColumnPath;Ljava/lang/Object;Lkotlin/reflect/KType;Ljava/lang/Object;Z)Lorg/jetbrains/kotlinx/dataframe/aggregation/NamedValue;
      45: areturn

  public java.lang.Object invoke(java.lang.Object);
    Code:
       0: aload_0
       1: aload_1
       2: checkcast     #54                 // class org/jetbrains/kotlinx/dataframe/DataColumn
       5: invokevirtual #76                 // Method invoke:(Lorg/jetbrains/kotlinx/dataframe/DataColumn;)Lorg/jetbrains/kotlinx/dataframe/aggregation/NamedValue;
       8: areturn
}
