Compiled from "DescribeBNodeClosure.java"
public class org.apache.jena.sparql.core.describe.DescribeBNodeClosure implements org.apache.jena.sparql.core.describe.DescribeHandler {
  org.apache.jena.rdf.model.Model acc;

  org.apache.jena.query.Dataset dataset;

  private static org.apache.jena.query.Query query;

  public org.apache.jena.sparql.core.describe.DescribeBNodeClosure();
    Code:
       0: aload_0
       1: invokespecial #1                  // Method java/lang/Object."<init>":()V
       4: return

  public void start(org.apache.jena.rdf.model.Model, org.apache.jena.sparql.util.Context);
    Code:
       0: aload_0
       1: aload_1
       2: putfield      #2                  // Field acc:Lorg/apache/jena/rdf/model/Model;
       5: aload_0
       6: aload_2
       7: getstatic     #3                  // Field org/apache/jena/sparql/ARQConstants.sysCurrentDataset:Lorg/apache/jena/sparql/util/Symbol;
      10: invokevirtual #4                  // Method org/apache/jena/sparql/util/Context.get:(Lorg/apache/jena/sparql/util/Symbol;)Ljava/lang/Object;
      13: checkcast     #5                  // class org/apache/jena/query/Dataset
      16: putfield      #6                  // Field dataset:Lorg/apache/jena/query/Dataset;
      19: return

  public void describe(org.apache.jena.rdf.model.Resource);
    Code:
       0: aload_1
       1: aload_0
       2: getfield      #6                  // Field dataset:Lorg/apache/jena/query/Dataset;
       5: invokeinterface #7,  1            // InterfaceMethod org/apache/jena/query/Dataset.getDefaultModel:()Lorg/apache/jena/rdf/model/Model;
      10: invokestatic  #8                  // Method otherModel:(Lorg/apache/jena/rdf/model/Resource;Lorg/apache/jena/rdf/model/Model;)Lorg/apache/jena/rdf/model/Resource;
      13: iconst_0
      14: aload_0
      15: getfield      #2                  // Field acc:Lorg/apache/jena/rdf/model/Model;
      18: invokestatic  #9                  // Method org/apache/jena/sparql/util/Closure.closure:(Lorg/apache/jena/rdf/model/Resource;ZLorg/apache/jena/rdf/model/Model;)Lorg/apache/jena/rdf/model/Model;
      21: pop
      22: new           #10                 // class org/apache/jena/query/QuerySolutionMap
      25: dup
      26: invokespecial #11                 // Method org/apache/jena/query/QuerySolutionMap."<init>":()V
      29: astore_2
      30: aload_2
      31: ldc           #12                 // String s
      33: aload_1
      34: invokevirtual #13                 // Method org/apache/jena/query/QuerySolutionMap.add:(Ljava/lang/String;Lorg/apache/jena/rdf/model/RDFNode;)V
      37: getstatic     #14                 // Field query:Lorg/apache/jena/query/Query;
      40: aload_0
      41: getfield      #6                  // Field dataset:Lorg/apache/jena/query/Dataset;
      44: aload_2
      45: invokestatic  #15                 // Method org/apache/jena/query/QueryExecutionFactory.create:(Lorg/apache/jena/query/Query;Lorg/apache/jena/query/Dataset;Lorg/apache/jena/query/QuerySolution;)Lorg/apache/jena/query/QueryExecution;
      48: astore_3
      49: aload_3
      50: invokeinterface #16,  1           // InterfaceMethod org/apache/jena/query/QueryExecution.execSelect:()Lorg/apache/jena/query/ResultSet;
      55: astore        4
      57: aload         4
      59: invokeinterface #17,  1           // InterfaceMethod org/apache/jena/query/ResultSet.hasNext:()Z
      64: ifeq          127
      67: aload         4
      69: invokeinterface #18,  1           // InterfaceMethod org/apache/jena/query/ResultSet.next:()Lorg/apache/jena/query/QuerySolution;
      74: astore        5
      76: aload         5
      78: ldc           #19                 // String g
      80: invokeinterface #20,  2           // InterfaceMethod org/apache/jena/query/QuerySolution.getResource:(Ljava/lang/String;)Lorg/apache/jena/rdf/model/Resource;
      85: invokeinterface #21,  1           // InterfaceMethod org/apache/jena/rdf/model/Resource.getURI:()Ljava/lang/String;
      90: astore        6
      92: aload_0
      93: getfield      #6                  // Field dataset:Lorg/apache/jena/query/Dataset;
      96: aload         6
      98: invokeinterface #22,  2           // InterfaceMethod org/apache/jena/query/Dataset.getNamedModel:(Ljava/lang/String;)Lorg/apache/jena/rdf/model/Model;
     103: astore        7
     105: aload_1
     106: aload         7
     108: invokestatic  #8                  // Method otherModel:(Lorg/apache/jena/rdf/model/Resource;Lorg/apache/jena/rdf/model/Model;)Lorg/apache/jena/rdf/model/Resource;
     111: astore        8
     113: aload         8
     115: iconst_0
     116: aload_0
     117: getfield      #2                  // Field acc:Lorg/apache/jena/rdf/model/Model;
     120: invokestatic  #9                  // Method org/apache/jena/sparql/util/Closure.closure:(Lorg/apache/jena/rdf/model/Resource;ZLorg/apache/jena/rdf/model/Model;)Lorg/apache/jena/rdf/model/Model;
     123: pop
     124: goto          57
     127: aload_1
     128: iconst_0
     129: aload_0
     130: getfield      #2                  // Field acc:Lorg/apache/jena/rdf/model/Model;
     133: invokestatic  #9                  // Method org/apache/jena/sparql/util/Closure.closure:(Lorg/apache/jena/rdf/model/Resource;ZLorg/apache/jena/rdf/model/Model;)Lorg/apache/jena/rdf/model/Model;
     136: pop
     137: return

  private static org.apache.jena.rdf.model.Resource otherModel(org.apache.jena.rdf.model.Resource, org.apache.jena.rdf.model.Model);
    Code:
       0: aload_0
       1: invokeinterface #23,  1           // InterfaceMethod org/apache/jena/rdf/model/Resource.isURIResource:()Z
       6: ifeq          22
       9: aload_1
      10: aload_0
      11: invokeinterface #21,  1           // InterfaceMethod org/apache/jena/rdf/model/Resource.getURI:()Ljava/lang/String;
      16: invokeinterface #24,  2           // InterfaceMethod org/apache/jena/rdf/model/Model.createResource:(Ljava/lang/String;)Lorg/apache/jena/rdf/model/Resource;
      21: areturn
      22: aload_0
      23: invokeinterface #25,  1           // InterfaceMethod org/apache/jena/rdf/model/Resource.isAnon:()Z
      28: ifeq          44
      31: aload_1
      32: aload_0
      33: invokeinterface #26,  1           // InterfaceMethod org/apache/jena/rdf/model/Resource.getId:()Lorg/apache/jena/rdf/model/AnonId;
      38: invokeinterface #27,  2           // InterfaceMethod org/apache/jena/rdf/model/Model.createResource:(Lorg/apache/jena/rdf/model/AnonId;)Lorg/apache/jena/rdf/model/Resource;
      43: areturn
      44: aload_0
      45: areturn

  public void finish();
    Code:
       0: return

  static {};
    Code:
       0: ldc           #28                 // String SELECT DISTINCT ?g { GRAPH ?g { ?s ?p ?o } }
       2: invokestatic  #29                 // Method org/apache/jena/query/QueryFactory.create:(Ljava/lang/String;)Lorg/apache/jena/query/Query;
       5: putstatic     #14                 // Field query:Lorg/apache/jena/query/Query;
       8: return
}
