Compiled from "NameResolverProviderFactory.java"
public class org.apache.bookkeeper.common.resolver.NameResolverProviderFactory extends io.grpc.NameResolver$Factory {
  private final java.util.List<io.grpc.NameResolverProvider> providers;

  public org.apache.bookkeeper.common.resolver.NameResolverProviderFactory(java.util.List<io.grpc.NameResolverProvider>);
    Code:
       0: aload_0
       1: invokespecial #1                  // Method io/grpc/NameResolver$Factory."<init>":()V
       4: aload_0
       5: aload_1
       6: putfield      #2                  // Field providers:Ljava/util/List;
       9: return

  public io.grpc.NameResolver newNameResolver(java.net.URI, io.grpc.NameResolver$Args);
    Code:
       0: aload_0
       1: invokespecial #3                  // Method checkForProviders:()V
       4: aload_0
       5: getfield      #2                  // Field providers:Ljava/util/List;
       8: invokeinterface #4,  1            // InterfaceMethod java/util/List.iterator:()Ljava/util/Iterator;
      13: astore_3
      14: aload_3
      15: invokeinterface #5,  1            // InterfaceMethod java/util/Iterator.hasNext:()Z
      20: ifeq          54
      23: aload_3
      24: invokeinterface #6,  1            // InterfaceMethod java/util/Iterator.next:()Ljava/lang/Object;
      29: checkcast     #7                  // class io/grpc/NameResolverProvider
      32: astore        4
      34: aload         4
      36: aload_1
      37: aload_2
      38: invokevirtual #8                  // Method io/grpc/NameResolverProvider.newNameResolver:(Ljava/net/URI;Lio/grpc/NameResolver$Args;)Lio/grpc/NameResolver;
      41: astore        5
      43: aload         5
      45: ifnull        51
      48: aload         5
      50: areturn
      51: goto          14
      54: aconst_null
      55: areturn

  public java.lang.String getDefaultScheme();
    Code:
       0: aload_0
       1: invokespecial #3                  // Method checkForProviders:()V
       4: aload_0
       5: getfield      #2                  // Field providers:Ljava/util/List;
       8: iconst_0
       9: invokeinterface #9,  2            // InterfaceMethod java/util/List.get:(I)Ljava/lang/Object;
      14: checkcast     #7                  // class io/grpc/NameResolverProvider
      17: invokevirtual #10                 // Method io/grpc/NameResolverProvider.getDefaultScheme:()Ljava/lang/String;
      20: areturn

  private void checkForProviders();
    Code:
       0: aload_0
       1: getfield      #2                  // Field providers:Ljava/util/List;
       4: invokeinterface #11,  1           // InterfaceMethod java/util/List.isEmpty:()Z
       9: ifne          16
      12: iconst_1
      13: goto          17
      16: iconst_0
      17: ldc           #12                 // String No NameResolverProviders found. Please check your configuration
      19: invokestatic  #13                 // Method com/google/common/base/Preconditions.checkState:(ZLjava/lang/Object;)V
      22: return
}
