Compiled from "CcrStatsResponse.java"
public final class org.elasticsearch.client.ccr.CcrStatsResponse {
  static final org.elasticsearch.common.ParseField AUTO_FOLLOW_STATS_FIELD;

  static final org.elasticsearch.common.ParseField FOLLOW_STATS_FIELD;

  private static final org.elasticsearch.common.xcontent.ConstructingObjectParser<org.elasticsearch.client.ccr.CcrStatsResponse, java.lang.Void> PARSER;

  private final org.elasticsearch.client.ccr.AutoFollowStats autoFollowStats;

  private final org.elasticsearch.client.ccr.IndicesFollowStats indicesFollowStats;

  public static org.elasticsearch.client.ccr.CcrStatsResponse fromXContent(org.elasticsearch.common.xcontent.XContentParser);
    Code:
       0: getstatic     #1                  // Field PARSER:Lorg/elasticsearch/common/xcontent/ConstructingObjectParser;
       3: aload_0
       4: aconst_null
       5: invokevirtual #2                  // Method org/elasticsearch/common/xcontent/ConstructingObjectParser.apply:(Lorg/elasticsearch/common/xcontent/XContentParser;Ljava/lang/Object;)Ljava/lang/Object;
       8: checkcast     #3                  // class org/elasticsearch/client/ccr/CcrStatsResponse
      11: areturn

  public org.elasticsearch.client.ccr.CcrStatsResponse(org.elasticsearch.client.ccr.AutoFollowStats, org.elasticsearch.client.ccr.IndicesFollowStats);
    Code:
       0: aload_0
       1: invokespecial #4                  // Method java/lang/Object."<init>":()V
       4: aload_0
       5: aload_1
       6: putfield      #5                  // Field autoFollowStats:Lorg/elasticsearch/client/ccr/AutoFollowStats;
       9: aload_0
      10: aload_2
      11: putfield      #6                  // Field indicesFollowStats:Lorg/elasticsearch/client/ccr/IndicesFollowStats;
      14: return

  public org.elasticsearch.client.ccr.AutoFollowStats getAutoFollowStats();
    Code:
       0: aload_0
       1: getfield      #5                  // Field autoFollowStats:Lorg/elasticsearch/client/ccr/AutoFollowStats;
       4: areturn

  public org.elasticsearch.client.ccr.IndicesFollowStats getIndicesFollowStats();
    Code:
       0: aload_0
       1: getfield      #6                  // Field indicesFollowStats:Lorg/elasticsearch/client/ccr/IndicesFollowStats;
       4: areturn

  private static org.elasticsearch.client.ccr.CcrStatsResponse lambda$static$0(java.lang.Object[]);
    Code:
       0: aload_0
       1: iconst_0
       2: aaload
       3: checkcast     #7                  // class org/elasticsearch/client/ccr/AutoFollowStats
       6: astore_1
       7: aload_0
       8: iconst_1
       9: aaload
      10: checkcast     #8                  // class org/elasticsearch/client/ccr/IndicesFollowStats
      13: astore_2
      14: new           #3                  // class org/elasticsearch/client/ccr/CcrStatsResponse
      17: dup
      18: aload_1
      19: aload_2
      20: invokespecial #9                  // Method "<init>":(Lorg/elasticsearch/client/ccr/AutoFollowStats;Lorg/elasticsearch/client/ccr/IndicesFollowStats;)V
      23: areturn

  static {};
    Code:
       0: new           #10                 // class org/elasticsearch/common/ParseField
       3: dup
       4: ldc           #11                 // String auto_follow_stats
       6: iconst_0
       7: anewarray     #12                 // class java/lang/String
      10: invokespecial #13                 // Method org/elasticsearch/common/ParseField."<init>":(Ljava/lang/String;[Ljava/lang/String;)V
      13: putstatic     #14                 // Field AUTO_FOLLOW_STATS_FIELD:Lorg/elasticsearch/common/ParseField;
      16: new           #10                 // class org/elasticsearch/common/ParseField
      19: dup
      20: ldc           #15                 // String follow_stats
      22: iconst_0
      23: anewarray     #12                 // class java/lang/String
      26: invokespecial #13                 // Method org/elasticsearch/common/ParseField."<init>":(Ljava/lang/String;[Ljava/lang/String;)V
      29: putstatic     #16                 // Field FOLLOW_STATS_FIELD:Lorg/elasticsearch/common/ParseField;
      32: new           #17                 // class org/elasticsearch/common/xcontent/ConstructingObjectParser
      35: dup
      36: ldc           #18                 // String indices
      38: iconst_1
      39: invokedynamic #19,  0             // InvokeDynamic #0:apply:()Ljava/util/function/Function;
      44: invokespecial #20                 // Method org/elasticsearch/common/xcontent/ConstructingObjectParser."<init>":(Ljava/lang/String;ZLjava/util/function/Function;)V
      47: putstatic     #1                  // Field PARSER:Lorg/elasticsearch/common/xcontent/ConstructingObjectParser;
      50: getstatic     #1                  // Field PARSER:Lorg/elasticsearch/common/xcontent/ConstructingObjectParser;
      53: invokestatic  #21                 // Method org/elasticsearch/common/xcontent/ConstructingObjectParser.constructorArg:()Ljava/util/function/BiConsumer;
      56: getstatic     #22                 // Field org/elasticsearch/client/ccr/AutoFollowStats.STATS_PARSER:Lorg/elasticsearch/common/xcontent/ConstructingObjectParser;
      59: getstatic     #14                 // Field AUTO_FOLLOW_STATS_FIELD:Lorg/elasticsearch/common/ParseField;
      62: invokevirtual #23                 // Method org/elasticsearch/common/xcontent/ConstructingObjectParser.declareObject:(Ljava/util/function/BiConsumer;Lorg/elasticsearch/common/xcontent/ContextParser;Lorg/elasticsearch/common/ParseField;)V
      65: getstatic     #1                  // Field PARSER:Lorg/elasticsearch/common/xcontent/ConstructingObjectParser;
      68: invokestatic  #21                 // Method org/elasticsearch/common/xcontent/ConstructingObjectParser.constructorArg:()Ljava/util/function/BiConsumer;
      71: getstatic     #24                 // Field org/elasticsearch/client/ccr/IndicesFollowStats.PARSER:Lorg/elasticsearch/common/xcontent/ConstructingObjectParser;
      74: getstatic     #16                 // Field FOLLOW_STATS_FIELD:Lorg/elasticsearch/common/ParseField;
      77: invokevirtual #23                 // Method org/elasticsearch/common/xcontent/ConstructingObjectParser.declareObject:(Ljava/util/function/BiConsumer;Lorg/elasticsearch/common/xcontent/ContextParser;Lorg/elasticsearch/common/ParseField;)V
      80: return
}
