Compiled from "ActionStatus.java"
interface org.elasticsearch.client.watcher.ActionStatus$Field {
  public static final org.elasticsearch.common.ParseField ACK_STATUS;

  public static final org.elasticsearch.common.ParseField ACK_STATUS_STATE;

  public static final org.elasticsearch.common.ParseField LAST_EXECUTION;

  public static final org.elasticsearch.common.ParseField LAST_SUCCESSFUL_EXECUTION;

  public static final org.elasticsearch.common.ParseField EXECUTION_SUCCESSFUL;

  public static final org.elasticsearch.common.ParseField LAST_THROTTLE;

  public static final org.elasticsearch.common.ParseField TIMESTAMP;

  public static final org.elasticsearch.common.ParseField REASON;

  static {};
    Code:
       0: new           #1                  // class org/elasticsearch/common/ParseField
       3: dup
       4: ldc           #2                  // String ack
       6: iconst_0
       7: anewarray     #3                  // class java/lang/String
      10: invokespecial #4                  // Method org/elasticsearch/common/ParseField."<init>":(Ljava/lang/String;[Ljava/lang/String;)V
      13: putstatic     #5                  // Field ACK_STATUS:Lorg/elasticsearch/common/ParseField;
      16: new           #1                  // class org/elasticsearch/common/ParseField
      19: dup
      20: ldc           #6                  // String state
      22: iconst_0
      23: anewarray     #3                  // class java/lang/String
      26: invokespecial #4                  // Method org/elasticsearch/common/ParseField."<init>":(Ljava/lang/String;[Ljava/lang/String;)V
      29: putstatic     #7                  // Field ACK_STATUS_STATE:Lorg/elasticsearch/common/ParseField;
      32: new           #1                  // class org/elasticsearch/common/ParseField
      35: dup
      36: ldc           #8                  // String last_execution
      38: iconst_0
      39: anewarray     #3                  // class java/lang/String
      42: invokespecial #4                  // Method org/elasticsearch/common/ParseField."<init>":(Ljava/lang/String;[Ljava/lang/String;)V
      45: putstatic     #9                  // Field LAST_EXECUTION:Lorg/elasticsearch/common/ParseField;
      48: new           #1                  // class org/elasticsearch/common/ParseField
      51: dup
      52: ldc           #10                 // String last_successful_execution
      54: iconst_0
      55: anewarray     #3                  // class java/lang/String
      58: invokespecial #4                  // Method org/elasticsearch/common/ParseField."<init>":(Ljava/lang/String;[Ljava/lang/String;)V
      61: putstatic     #11                 // Field LAST_SUCCESSFUL_EXECUTION:Lorg/elasticsearch/common/ParseField;
      64: new           #1                  // class org/elasticsearch/common/ParseField
      67: dup
      68: ldc           #12                 // String successful
      70: iconst_0
      71: anewarray     #3                  // class java/lang/String
      74: invokespecial #4                  // Method org/elasticsearch/common/ParseField."<init>":(Ljava/lang/String;[Ljava/lang/String;)V
      77: putstatic     #13                 // Field EXECUTION_SUCCESSFUL:Lorg/elasticsearch/common/ParseField;
      80: new           #1                  // class org/elasticsearch/common/ParseField
      83: dup
      84: ldc           #14                 // String last_throttle
      86: iconst_0
      87: anewarray     #3                  // class java/lang/String
      90: invokespecial #4                  // Method org/elasticsearch/common/ParseField."<init>":(Ljava/lang/String;[Ljava/lang/String;)V
      93: putstatic     #15                 // Field LAST_THROTTLE:Lorg/elasticsearch/common/ParseField;
      96: new           #1                  // class org/elasticsearch/common/ParseField
      99: dup
     100: ldc           #16                 // String timestamp
     102: iconst_0
     103: anewarray     #3                  // class java/lang/String
     106: invokespecial #4                  // Method org/elasticsearch/common/ParseField."<init>":(Ljava/lang/String;[Ljava/lang/String;)V
     109: putstatic     #17                 // Field TIMESTAMP:Lorg/elasticsearch/common/ParseField;
     112: new           #1                  // class org/elasticsearch/common/ParseField
     115: dup
     116: ldc           #18                 // String reason
     118: iconst_0
     119: anewarray     #3                  // class java/lang/String
     122: invokespecial #4                  // Method org/elasticsearch/common/ParseField."<init>":(Ljava/lang/String;[Ljava/lang/String;)V
     125: putstatic     #19                 // Field REASON:Lorg/elasticsearch/common/ParseField;
     128: return
}
