Compiled from "WatchStatus.java"
public class org.elasticsearch.client.watcher.WatchStatus$State {
  private final boolean active;

  private final org.joda.time.DateTime timestamp;

  public org.elasticsearch.client.watcher.WatchStatus$State(boolean, org.joda.time.DateTime);
    Code:
       0: aload_0
       1: invokespecial #1                  // Method java/lang/Object."<init>":()V
       4: aload_0
       5: iload_1
       6: putfield      #2                  // Field active:Z
       9: aload_0
      10: aload_2
      11: putfield      #3                  // Field timestamp:Lorg/joda/time/DateTime;
      14: return

  public boolean isActive();
    Code:
       0: aload_0
       1: getfield      #2                  // Field active:Z
       4: ireturn

  public org.joda.time.DateTime getTimestamp();
    Code:
       0: aload_0
       1: getfield      #3                  // Field timestamp:Lorg/joda/time/DateTime;
       4: areturn

  public static org.elasticsearch.client.watcher.WatchStatus$State parse(org.elasticsearch.common.xcontent.XContentParser) throws java.io.IOException;
    Code:
       0: aload_0
       1: invokeinterface #4,  1            // InterfaceMethod org/elasticsearch/common/xcontent/XContentParser.currentToken:()Lorg/elasticsearch/common/xcontent/XContentParser$Token;
       6: getstatic     #5                  // Field org/elasticsearch/common/xcontent/XContentParser$Token.START_OBJECT:Lorg/elasticsearch/common/xcontent/XContentParser$Token;
       9: if_acmpeq     35
      12: new           #6                  // class org/elasticsearch/ElasticsearchParseException
      15: dup
      16: ldc           #7                  // String expected an object but found [{}] instead
      18: iconst_1
      19: anewarray     #8                  // class java/lang/Object
      22: dup
      23: iconst_0
      24: aload_0
      25: invokeinterface #4,  1            // InterfaceMethod org/elasticsearch/common/xcontent/XContentParser.currentToken:()Lorg/elasticsearch/common/xcontent/XContentParser$Token;
      30: aastore
      31: invokespecial #9                  // Method org/elasticsearch/ElasticsearchParseException."<init>":(Ljava/lang/String;[Ljava/lang/Object;)V
      34: athrow
      35: iconst_1
      36: istore_1
      37: getstatic     #10                 // Field org/joda/time/DateTimeZone.UTC:Lorg/joda/time/DateTimeZone;
      40: invokestatic  #11                 // Method org/joda/time/DateTime.now:(Lorg/joda/time/DateTimeZone;)Lorg/joda/time/DateTime;
      43: astore_2
      44: aconst_null
      45: astore_3
      46: aload_0
      47: invokeinterface #12,  1           // InterfaceMethod org/elasticsearch/common/xcontent/XContentParser.nextToken:()Lorg/elasticsearch/common/xcontent/XContentParser$Token;
      52: dup
      53: astore        4
      55: getstatic     #13                 // Field org/elasticsearch/common/xcontent/XContentParser$Token.END_OBJECT:Lorg/elasticsearch/common/xcontent/XContentParser$Token;
      58: if_acmpeq     139
      61: aload         4
      63: getstatic     #14                 // Field org/elasticsearch/common/xcontent/XContentParser$Token.FIELD_NAME:Lorg/elasticsearch/common/xcontent/XContentParser$Token;
      66: if_acmpne     79
      69: aload_0
      70: invokeinterface #15,  1           // InterfaceMethod org/elasticsearch/common/xcontent/XContentParser.currentName:()Ljava/lang/String;
      75: astore_3
      76: goto          46
      79: getstatic     #16                 // Field org/elasticsearch/client/watcher/WatchStatus$Field.ACTIVE:Lorg/elasticsearch/common/ParseField;
      82: aload_3
      83: aload_0
      84: invokeinterface #17,  1           // InterfaceMethod org/elasticsearch/common/xcontent/XContentParser.getDeprecationHandler:()Lorg/elasticsearch/common/xcontent/DeprecationHandler;
      89: invokevirtual #18                 // Method org/elasticsearch/common/ParseField.match:(Ljava/lang/String;Lorg/elasticsearch/common/xcontent/DeprecationHandler;)Z
      92: ifeq          105
      95: aload_0
      96: invokeinterface #19,  1           // InterfaceMethod org/elasticsearch/common/xcontent/XContentParser.booleanValue:()Z
     101: istore_1
     102: goto          46
     105: getstatic     #20                 // Field org/elasticsearch/client/watcher/WatchStatus$Field.TIMESTAMP:Lorg/elasticsearch/common/ParseField;
     108: aload_3
     109: aload_0
     110: invokeinterface #17,  1           // InterfaceMethod org/elasticsearch/common/xcontent/XContentParser.getDeprecationHandler:()Lorg/elasticsearch/common/xcontent/DeprecationHandler;
     115: invokevirtual #18                 // Method org/elasticsearch/common/ParseField.match:(Ljava/lang/String;Lorg/elasticsearch/common/xcontent/DeprecationHandler;)Z
     118: ifeq          130
     121: aload_3
     122: aload_0
     123: invokestatic  #21                 // Method org/elasticsearch/client/watcher/WatchStatusDateParser.parseDate:(Ljava/lang/String;Lorg/elasticsearch/common/xcontent/XContentParser;)Lorg/joda/time/DateTime;
     126: astore_2
     127: goto          46
     130: aload_0
     131: invokeinterface #22,  1           // InterfaceMethod org/elasticsearch/common/xcontent/XContentParser.skipChildren:()V
     136: goto          46
     139: new           #23                 // class org/elasticsearch/client/watcher/WatchStatus$State
     142: dup
     143: iload_1
     144: aload_2
     145: invokespecial #24                 // Method "<init>":(ZLorg/joda/time/DateTime;)V
     148: areturn
}
