Compiled from "X509SerialNumber.java"
public interface org.opensaml.xmlsec.signature.X509SerialNumber extends org.opensaml.core.xml.XMLObject {
  public static final java.lang.String DEFAULT_ELEMENT_LOCAL_NAME;

  public static final javax.xml.namespace.QName DEFAULT_ELEMENT_NAME;

  public static final java.lang.String TYPE_LOCAL_NAME;

  public static final javax.xml.namespace.QName TYPE_NAME;

  public abstract java.math.BigInteger getValue();

  public abstract void setValue(java.math.BigInteger);

  static {};
    Code:
       0: new           #1                  // class javax/xml/namespace/QName
       3: dup
       4: ldc           #2                  // String http://www.w3.org/2000/09/xmldsig#
       6: ldc           #3                  // String X509SerialNumber
       8: ldc           #4                  // String ds
      10: invokespecial #5                  // Method javax/xml/namespace/QName."<init>":(Ljava/lang/String;Ljava/lang/String;Ljava/lang/String;)V
      13: putstatic     #6                  // Field DEFAULT_ELEMENT_NAME:Ljavax/xml/namespace/QName;
      16: new           #1                  // class javax/xml/namespace/QName
      19: dup
      20: ldc           #7                  // String http://www.w3.org/2001/XMLSchema
      22: ldc           #8                  // String integer
      24: ldc           #9                  // String xsd
      26: invokespecial #5                  // Method javax/xml/namespace/QName."<init>":(Ljava/lang/String;Ljava/lang/String;Ljava/lang/String;)V
      29: putstatic     #10                 // Field TYPE_NAME:Ljavax/xml/namespace/QName;
      32: return
}
