Compiled from "FieldAccessor.java"
public class org.assertj.core.internal.bytebuddy.implementation.FieldAccessor$ForImplicitProperty$Appender implements org.assertj.core.internal.bytebuddy.implementation.bytecode.ByteCodeAppender {
  private final org.assertj.core.internal.bytebuddy.implementation.FieldAccessor$FieldLocation$Prepared fieldLocation;

  final org.assertj.core.internal.bytebuddy.implementation.FieldAccessor$ForImplicitProperty this$0;

  protected org.assertj.core.internal.bytebuddy.implementation.FieldAccessor$ForImplicitProperty$Appender(org.assertj.core.internal.bytebuddy.implementation.FieldAccessor$ForImplicitProperty, org.assertj.core.internal.bytebuddy.implementation.FieldAccessor$FieldLocation$Prepared);
    Code:
       0: aload_0
       1: aload_1
       2: putfield      #47                 // Field this$0:Lorg/assertj/core/internal/bytebuddy/implementation/FieldAccessor$ForImplicitProperty;
       5: aload_0
       6: invokespecial #50                 // Method java/lang/Object."<init>":()V
       9: aload_0
      10: aload_2
      11: putfield      #52                 // Field fieldLocation:Lorg/assertj/core/internal/bytebuddy/implementation/FieldAccessor$FieldLocation$Prepared;
      14: return

  public org.assertj.core.internal.bytebuddy.implementation.bytecode.ByteCodeAppender$Size apply(org.assertj.core.internal.bytebuddy.jar.asm.MethodVisitor, org.assertj.core.internal.bytebuddy.implementation.Implementation$Context, org.assertj.core.internal.bytebuddy.description.method.MethodDescription);
    Code:
       0: aload_3
       1: invokeinterface #62,  1           // InterfaceMethod org/assertj/core/internal/bytebuddy/description/method/MethodDescription.isMethod:()Z
       6: ifne          36
       9: new           #64                 // class java/lang/IllegalArgumentException
      12: dup
      13: new           #66                 // class java/lang/StringBuilder
      16: dup
      17: invokespecial #67                 // Method java/lang/StringBuilder."<init>":()V
      20: aload_3
      21: invokevirtual #71                 // Method java/lang/StringBuilder.append:(Ljava/lang/Object;)Ljava/lang/StringBuilder;
      24: ldc           #73                 // String  does not describe a field getter or setter
      26: invokevirtual #76                 // Method java/lang/StringBuilder.append:(Ljava/lang/String;)Ljava/lang/StringBuilder;
      29: invokevirtual #80                 // Method java/lang/StringBuilder.toString:()Ljava/lang/String;
      32: invokespecial #83                 // Method java/lang/IllegalArgumentException."<init>":(Ljava/lang/String;)V
      35: athrow
      36: aload_0
      37: getfield      #52                 // Field fieldLocation:Lorg/assertj/core/internal/bytebuddy/implementation/FieldAccessor$FieldLocation$Prepared;
      40: aload_3
      41: invokeinterface #87,  2           // InterfaceMethod org/assertj/core/internal/bytebuddy/implementation/FieldAccessor$FieldLocation$Prepared.resolve:(Lorg/assertj/core/internal/bytebuddy/description/method/MethodDescription;)Lorg/assertj/core/internal/bytebuddy/description/field/FieldDescription;
      46: astore        4
      48: aload_3
      49: invokeinterface #91,  1           // InterfaceMethod org/assertj/core/internal/bytebuddy/description/method/MethodDescription.getReturnType:()Lorg/assertj/core/internal/bytebuddy/description/type/TypeDescription$Generic;
      54: getstatic     #97                 // Field java/lang/Void.TYPE:Ljava/lang/Class;
      57: invokeinterface #101,  2          // InterfaceMethod org/assertj/core/internal/bytebuddy/description/type/TypeDescription$Generic.represents:(Ljava/lang/reflect/Type;)Z
      62: ifne          106
      65: new           #29                 // class org/assertj/core/internal/bytebuddy/implementation/bytecode/StackManipulation$Compound
      68: dup
      69: iconst_2
      70: anewarray     #31                 // class org/assertj/core/internal/bytebuddy/implementation/bytecode/StackManipulation
      73: dup
      74: iconst_0
      75: aload_0
      76: getfield      #47                 // Field this$0:Lorg/assertj/core/internal/bytebuddy/implementation/FieldAccessor$ForImplicitProperty;
      79: aload         4
      81: aload_3
      82: invokevirtual #105                // Method org/assertj/core/internal/bytebuddy/implementation/FieldAccessor$ForImplicitProperty.getter:(Lorg/assertj/core/internal/bytebuddy/description/field/FieldDescription;Lorg/assertj/core/internal/bytebuddy/description/method/MethodDescription;)Lorg/assertj/core/internal/bytebuddy/implementation/bytecode/StackManipulation;
      85: aastore
      86: dup
      87: iconst_1
      88: aload_3
      89: invokeinterface #91,  1           // InterfaceMethod org/assertj/core/internal/bytebuddy/description/method/MethodDescription.getReturnType:()Lorg/assertj/core/internal/bytebuddy/description/type/TypeDescription$Generic;
      94: invokestatic  #111                // Method org/assertj/core/internal/bytebuddy/implementation/bytecode/member/MethodReturn.of:(Lorg/assertj/core/internal/bytebuddy/description/type/TypeDefinition;)Lorg/assertj/core/internal/bytebuddy/implementation/bytecode/StackManipulation;
      97: aastore
      98: invokespecial #114                // Method org/assertj/core/internal/bytebuddy/implementation/bytecode/StackManipulation$Compound."<init>":([Lorg/assertj/core/internal/bytebuddy/implementation/bytecode/StackManipulation;)V
     101: astore        5
     103: goto          219
     106: aload_3
     107: invokeinterface #91,  1           // InterfaceMethod org/assertj/core/internal/bytebuddy/description/method/MethodDescription.getReturnType:()Lorg/assertj/core/internal/bytebuddy/description/type/TypeDescription$Generic;
     112: getstatic     #97                 // Field java/lang/Void.TYPE:Ljava/lang/Class;
     115: invokeinterface #101,  2          // InterfaceMethod org/assertj/core/internal/bytebuddy/description/type/TypeDescription$Generic.represents:(Ljava/lang/reflect/Type;)Z
     120: ifeq          187
     123: aload_3
     124: invokeinterface #120,  1          // InterfaceMethod org/assertj/core/internal/bytebuddy/description/method/MethodDescription.getParameters:()Lorg/assertj/core/internal/bytebuddy/description/method/ParameterList;
     129: invokeinterface #126,  1          // InterfaceMethod org/assertj/core/internal/bytebuddy/description/method/ParameterList.size:()I
     134: iconst_1
     135: if_icmpne     187
     138: new           #29                 // class org/assertj/core/internal/bytebuddy/implementation/bytecode/StackManipulation$Compound
     141: dup
     142: iconst_2
     143: anewarray     #31                 // class org/assertj/core/internal/bytebuddy/implementation/bytecode/StackManipulation
     146: dup
     147: iconst_0
     148: aload_0
     149: getfield      #47                 // Field this$0:Lorg/assertj/core/internal/bytebuddy/implementation/FieldAccessor$ForImplicitProperty;
     152: aload         4
     154: aload_3
     155: invokeinterface #120,  1          // InterfaceMethod org/assertj/core/internal/bytebuddy/description/method/MethodDescription.getParameters:()Lorg/assertj/core/internal/bytebuddy/description/method/ParameterList;
     160: iconst_0
     161: invokeinterface #130,  2          // InterfaceMethod org/assertj/core/internal/bytebuddy/description/method/ParameterList.get:(I)Ljava/lang/Object;
     166: checkcast     #132                // class org/assertj/core/internal/bytebuddy/description/method/ParameterDescription
     169: invokevirtual #136                // Method org/assertj/core/internal/bytebuddy/implementation/FieldAccessor$ForImplicitProperty.setter:(Lorg/assertj/core/internal/bytebuddy/description/field/FieldDescription;Lorg/assertj/core/internal/bytebuddy/description/method/ParameterDescription;)Lorg/assertj/core/internal/bytebuddy/implementation/bytecode/StackManipulation;
     172: aastore
     173: dup
     174: iconst_1
     175: getstatic     #140                // Field org/assertj/core/internal/bytebuddy/implementation/bytecode/member/MethodReturn.VOID:Lorg/assertj/core/internal/bytebuddy/implementation/bytecode/member/MethodReturn;
     178: aastore
     179: invokespecial #114                // Method org/assertj/core/internal/bytebuddy/implementation/bytecode/StackManipulation$Compound."<init>":([Lorg/assertj/core/internal/bytebuddy/implementation/bytecode/StackManipulation;)V
     182: astore        5
     184: goto          219
     187: new           #64                 // class java/lang/IllegalArgumentException
     190: dup
     191: new           #66                 // class java/lang/StringBuilder
     194: dup
     195: invokespecial #67                 // Method java/lang/StringBuilder."<init>":()V
     198: ldc           #142                // String Method
     200: invokevirtual #76                 // Method java/lang/StringBuilder.append:(Ljava/lang/String;)Ljava/lang/StringBuilder;
     203: aload_2
     204: invokevirtual #71                 // Method java/lang/StringBuilder.append:(Ljava/lang/Object;)Ljava/lang/StringBuilder;
     207: ldc           #144                // String  is no bean property
     209: invokevirtual #76                 // Method java/lang/StringBuilder.append:(Ljava/lang/String;)Ljava/lang/StringBuilder;
     212: invokevirtual #80                 // Method java/lang/StringBuilder.toString:()Ljava/lang/String;
     215: invokespecial #83                 // Method java/lang/IllegalArgumentException."<init>":(Ljava/lang/String;)V
     218: athrow
     219: new           #26                 // class org/assertj/core/internal/bytebuddy/implementation/bytecode/ByteCodeAppender$Size
     222: dup
     223: aload         5
     225: aload_1
     226: aload_2
     227: invokeinterface #147,  3          // InterfaceMethod org/assertj/core/internal/bytebuddy/implementation/bytecode/StackManipulation.apply:(Lorg/assertj/core/internal/bytebuddy/jar/asm/MethodVisitor;Lorg/assertj/core/internal/bytebuddy/implementation/Implementation$Context;)Lorg/assertj/core/internal/bytebuddy/implementation/bytecode/StackManipulation$Size;
     232: invokevirtual #150                // Method org/assertj/core/internal/bytebuddy/implementation/bytecode/StackManipulation$Size.getMaximalSize:()I
     235: aload_3
     236: invokeinterface #153,  1          // InterfaceMethod org/assertj/core/internal/bytebuddy/description/method/MethodDescription.getStackSize:()I
     241: invokespecial #156                // Method org/assertj/core/internal/bytebuddy/implementation/bytecode/ByteCodeAppender$Size."<init>":(II)V
     244: areturn

  private org.assertj.core.internal.bytebuddy.implementation.FieldAccessor$ForImplicitProperty getOuter();
    Code:
       0: aload_0
       1: getfield      #47                 // Field this$0:Lorg/assertj/core/internal/bytebuddy/implementation/FieldAccessor$ForImplicitProperty;
       4: areturn

  public boolean equals(java.lang.Object);
    Code:
       0: aload_0
       1: aload_1
       2: if_acmpne     7
       5: iconst_1
       6: ireturn
       7: aload_1
       8: ifnull        22
      11: aload_0
      12: invokevirtual #174                // Method java/lang/Object.getClass:()Ljava/lang/Class;
      15: aload_1
      16: invokevirtual #174                // Method java/lang/Object.getClass:()Ljava/lang/Class;
      19: if_acmpeq     24
      22: iconst_0
      23: ireturn
      24: aload_1
      25: checkcast     #2                  // class org/assertj/core/internal/bytebuddy/implementation/FieldAccessor$ForImplicitProperty$Appender
      28: astore_2
      29: aload_0
      30: getfield      #52                 // Field fieldLocation:Lorg/assertj/core/internal/bytebuddy/implementation/FieldAccessor$FieldLocation$Prepared;
      33: aload_2
      34: getfield      #52                 // Field fieldLocation:Lorg/assertj/core/internal/bytebuddy/implementation/FieldAccessor$FieldLocation$Prepared;
      37: invokevirtual #176                // Method java/lang/Object.equals:(Ljava/lang/Object;)Z
      40: ifeq          61
      43: aload_0
      44: getfield      #47                 // Field this$0:Lorg/assertj/core/internal/bytebuddy/implementation/FieldAccessor$ForImplicitProperty;
      47: aload_2
      48: invokespecial #178                // Method getOuter:()Lorg/assertj/core/internal/bytebuddy/implementation/FieldAccessor$ForImplicitProperty;
      51: invokevirtual #179                // Method org/assertj/core/internal/bytebuddy/implementation/FieldAccessor$ForImplicitProperty.equals:(Ljava/lang/Object;)Z
      54: ifeq          61
      57: iconst_1
      58: goto          62
      61: iconst_0
      62: ireturn

  public int hashCode();
    Code:
       0: aload_0
       1: getfield      #52                 // Field fieldLocation:Lorg/assertj/core/internal/bytebuddy/implementation/FieldAccessor$FieldLocation$Prepared;
       4: invokevirtual #185                // Method java/lang/Object.hashCode:()I
       7: bipush        31
       9: aload_0
      10: getfield      #47                 // Field this$0:Lorg/assertj/core/internal/bytebuddy/implementation/FieldAccessor$ForImplicitProperty;
      13: invokevirtual #186                // Method org/assertj/core/internal/bytebuddy/implementation/FieldAccessor$ForImplicitProperty.hashCode:()I
      16: imul
      17: iadd
      18: ireturn
}
