Compiled from "InvokeDynamic.java"
public abstract class org.assertj.core.internal.bytebuddy.implementation.InvokeDynamic$InvocationProvider$ArgumentProvider$ConstantPoolWrapper extends java.lang.Enum<org.assertj.core.internal.bytebuddy.implementation.InvokeDynamic$InvocationProvider$ArgumentProvider$ConstantPoolWrapper> {
  public static final org.assertj.core.internal.bytebuddy.implementation.InvokeDynamic$InvocationProvider$ArgumentProvider$ConstantPoolWrapper BOOLEAN;

  public static final org.assertj.core.internal.bytebuddy.implementation.InvokeDynamic$InvocationProvider$ArgumentProvider$ConstantPoolWrapper BYTE;

  public static final org.assertj.core.internal.bytebuddy.implementation.InvokeDynamic$InvocationProvider$ArgumentProvider$ConstantPoolWrapper SHORT;

  public static final org.assertj.core.internal.bytebuddy.implementation.InvokeDynamic$InvocationProvider$ArgumentProvider$ConstantPoolWrapper CHARACTER;

  public static final org.assertj.core.internal.bytebuddy.implementation.InvokeDynamic$InvocationProvider$ArgumentProvider$ConstantPoolWrapper INTEGER;

  public static final org.assertj.core.internal.bytebuddy.implementation.InvokeDynamic$InvocationProvider$ArgumentProvider$ConstantPoolWrapper LONG;

  public static final org.assertj.core.internal.bytebuddy.implementation.InvokeDynamic$InvocationProvider$ArgumentProvider$ConstantPoolWrapper FLOAT;

  public static final org.assertj.core.internal.bytebuddy.implementation.InvokeDynamic$InvocationProvider$ArgumentProvider$ConstantPoolWrapper DOUBLE;

  private final org.assertj.core.internal.bytebuddy.description.type.TypeDescription primitiveType;

  private final org.assertj.core.internal.bytebuddy.description.type.TypeDescription wrapperType;

  private static final org.assertj.core.internal.bytebuddy.implementation.InvokeDynamic$InvocationProvider$ArgumentProvider$ConstantPoolWrapper[] $VALUES;

  public static org.assertj.core.internal.bytebuddy.implementation.InvokeDynamic$InvocationProvider$ArgumentProvider$ConstantPoolWrapper[] values();
    Code:
       0: getstatic     #87                 // Field $VALUES:[Lorg/assertj/core/internal/bytebuddy/implementation/InvokeDynamic$InvocationProvider$ArgumentProvider$ConstantPoolWrapper;
       3: invokevirtual #92                 // Method "[Lorg/assertj/core/internal/bytebuddy/implementation/InvokeDynamic$InvocationProvider$ArgumentProvider$ConstantPoolWrapper;".clone:()Ljava/lang/Object;
       6: checkcast     #88                 // class "[Lorg/assertj/core/internal/bytebuddy/implementation/InvokeDynamic$InvocationProvider$ArgumentProvider$ConstantPoolWrapper;"
       9: areturn

  public static org.assertj.core.internal.bytebuddy.implementation.InvokeDynamic$InvocationProvider$ArgumentProvider$ConstantPoolWrapper valueOf(java.lang.String);
    Code:
       0: ldc           #2                  // class org/assertj/core/internal/bytebuddy/implementation/InvokeDynamic$InvocationProvider$ArgumentProvider$ConstantPoolWrapper
       2: aload_0
       3: invokestatic  #97                 // Method java/lang/Enum.valueOf:(Ljava/lang/Class;Ljava/lang/String;)Ljava/lang/Enum;
       6: checkcast     #2                  // class org/assertj/core/internal/bytebuddy/implementation/InvokeDynamic$InvocationProvider$ArgumentProvider$ConstantPoolWrapper
       9: areturn

  private org.assertj.core.internal.bytebuddy.implementation.InvokeDynamic$InvocationProvider$ArgumentProvider$ConstantPoolWrapper(java.lang.Class<?>, java.lang.Class<?>);
    Code:
       0: aload_0
       1: aload_1
       2: iload_2
       3: invokespecial #104                // Method java/lang/Enum."<init>":(Ljava/lang/String;I)V
       6: aload_0
       7: new           #38                 // class org/assertj/core/internal/bytebuddy/description/type/TypeDescription$ForLoadedType
      10: dup
      11: aload_3
      12: invokespecial #107                // Method org/assertj/core/internal/bytebuddy/description/type/TypeDescription$ForLoadedType."<init>":(Ljava/lang/Class;)V
      15: putfield      #109                // Field primitiveType:Lorg/assertj/core/internal/bytebuddy/description/type/TypeDescription;
      18: aload_0
      19: new           #38                 // class org/assertj/core/internal/bytebuddy/description/type/TypeDescription$ForLoadedType
      22: dup
      23: aload         4
      25: invokespecial #107                // Method org/assertj/core/internal/bytebuddy/description/type/TypeDescription$ForLoadedType."<init>":(Ljava/lang/Class;)V
      28: putfield      #111                // Field wrapperType:Lorg/assertj/core/internal/bytebuddy/description/type/TypeDescription;
      31: return

  public static org.assertj.core.internal.bytebuddy.implementation.InvokeDynamic$InvocationProvider$ArgumentProvider of(java.lang.Object);
    Code:
       0: aload_0
       1: instanceof    #118                // class java/lang/Boolean
       4: ifeq          15
       7: getstatic     #120                // Field BOOLEAN:Lorg/assertj/core/internal/bytebuddy/implementation/InvokeDynamic$InvocationProvider$ArgumentProvider$ConstantPoolWrapper;
      10: aload_0
      11: invokevirtual #123                // Method make:(Ljava/lang/Object;)Lorg/assertj/core/internal/bytebuddy/implementation/InvokeDynamic$InvocationProvider$ArgumentProvider;
      14: areturn
      15: aload_0
      16: instanceof    #125                // class java/lang/Byte
      19: ifeq          30
      22: getstatic     #127                // Field BYTE:Lorg/assertj/core/internal/bytebuddy/implementation/InvokeDynamic$InvocationProvider$ArgumentProvider$ConstantPoolWrapper;
      25: aload_0
      26: invokevirtual #123                // Method make:(Ljava/lang/Object;)Lorg/assertj/core/internal/bytebuddy/implementation/InvokeDynamic$InvocationProvider$ArgumentProvider;
      29: areturn
      30: aload_0
      31: instanceof    #129                // class java/lang/Short
      34: ifeq          45
      37: getstatic     #131                // Field SHORT:Lorg/assertj/core/internal/bytebuddy/implementation/InvokeDynamic$InvocationProvider$ArgumentProvider$ConstantPoolWrapper;
      40: aload_0
      41: invokevirtual #123                // Method make:(Ljava/lang/Object;)Lorg/assertj/core/internal/bytebuddy/implementation/InvokeDynamic$InvocationProvider$ArgumentProvider;
      44: areturn
      45: aload_0
      46: instanceof    #133                // class java/lang/Character
      49: ifeq          60
      52: getstatic     #135                // Field CHARACTER:Lorg/assertj/core/internal/bytebuddy/implementation/InvokeDynamic$InvocationProvider$ArgumentProvider$ConstantPoolWrapper;
      55: aload_0
      56: invokevirtual #123                // Method make:(Ljava/lang/Object;)Lorg/assertj/core/internal/bytebuddy/implementation/InvokeDynamic$InvocationProvider$ArgumentProvider;
      59: areturn
      60: aload_0
      61: instanceof    #137                // class java/lang/Integer
      64: ifeq          75
      67: getstatic     #139                // Field INTEGER:Lorg/assertj/core/internal/bytebuddy/implementation/InvokeDynamic$InvocationProvider$ArgumentProvider$ConstantPoolWrapper;
      70: aload_0
      71: invokevirtual #123                // Method make:(Ljava/lang/Object;)Lorg/assertj/core/internal/bytebuddy/implementation/InvokeDynamic$InvocationProvider$ArgumentProvider;
      74: areturn
      75: aload_0
      76: instanceof    #141                // class java/lang/Long
      79: ifeq          90
      82: getstatic     #143                // Field LONG:Lorg/assertj/core/internal/bytebuddy/implementation/InvokeDynamic$InvocationProvider$ArgumentProvider$ConstantPoolWrapper;
      85: aload_0
      86: invokevirtual #123                // Method make:(Ljava/lang/Object;)Lorg/assertj/core/internal/bytebuddy/implementation/InvokeDynamic$InvocationProvider$ArgumentProvider;
      89: areturn
      90: aload_0
      91: instanceof    #145                // class java/lang/Float
      94: ifeq          105
      97: getstatic     #147                // Field FLOAT:Lorg/assertj/core/internal/bytebuddy/implementation/InvokeDynamic$InvocationProvider$ArgumentProvider$ConstantPoolWrapper;
     100: aload_0
     101: invokevirtual #123                // Method make:(Ljava/lang/Object;)Lorg/assertj/core/internal/bytebuddy/implementation/InvokeDynamic$InvocationProvider$ArgumentProvider;
     104: areturn
     105: aload_0
     106: instanceof    #149                // class java/lang/Double
     109: ifeq          120
     112: getstatic     #151                // Field DOUBLE:Lorg/assertj/core/internal/bytebuddy/implementation/InvokeDynamic$InvocationProvider$ArgumentProvider$ConstantPoolWrapper;
     115: aload_0
     116: invokevirtual #123                // Method make:(Ljava/lang/Object;)Lorg/assertj/core/internal/bytebuddy/implementation/InvokeDynamic$InvocationProvider$ArgumentProvider;
     119: areturn
     120: aload_0
     121: instanceof    #153                // class java/lang/String
     124: ifeq          139
     127: new           #43                 // class org/assertj/core/internal/bytebuddy/implementation/InvokeDynamic$InvocationProvider$ArgumentProvider$ForStringConstant
     130: dup
     131: aload_0
     132: checkcast     #153                // class java/lang/String
     135: invokespecial #156                // Method org/assertj/core/internal/bytebuddy/implementation/InvokeDynamic$InvocationProvider$ArgumentProvider$ForStringConstant."<init>":(Ljava/lang/String;)V
     138: areturn
     139: aload_0
     140: instanceof    #158                // class java/lang/Class
     143: ifeq          165
     146: new           #46                 // class org/assertj/core/internal/bytebuddy/implementation/InvokeDynamic$InvocationProvider$ArgumentProvider$ForClassConstant
     149: dup
     150: new           #38                 // class org/assertj/core/internal/bytebuddy/description/type/TypeDescription$ForLoadedType
     153: dup
     154: aload_0
     155: checkcast     #158                // class java/lang/Class
     158: invokespecial #107                // Method org/assertj/core/internal/bytebuddy/description/type/TypeDescription$ForLoadedType."<init>":(Ljava/lang/Class;)V
     161: invokespecial #161                // Method org/assertj/core/internal/bytebuddy/implementation/InvokeDynamic$InvocationProvider$ArgumentProvider$ForClassConstant."<init>":(Lorg/assertj/core/internal/bytebuddy/description/type/TypeDescription;)V
     164: areturn
     165: aload_0
     166: instanceof    #5                  // class java/lang/Enum
     169: ifeq          191
     172: new           #49                 // class org/assertj/core/internal/bytebuddy/implementation/InvokeDynamic$InvocationProvider$ArgumentProvider$ForEnumerationValue
     175: dup
     176: new           #52                 // class org/assertj/core/internal/bytebuddy/description/enumeration/EnumerationDescription$ForLoadedEnumeration
     179: dup
     180: aload_0
     181: checkcast     #5                  // class java/lang/Enum
     184: invokespecial #164                // Method org/assertj/core/internal/bytebuddy/description/enumeration/EnumerationDescription$ForLoadedEnumeration."<init>":(Ljava/lang/Enum;)V
     187: invokespecial #167                // Method org/assertj/core/internal/bytebuddy/implementation/InvokeDynamic$InvocationProvider$ArgumentProvider$ForEnumerationValue."<init>":(Lorg/assertj/core/internal/bytebuddy/description/enumeration/EnumerationDescription;)V
     190: areturn
     191: getstatic     #173                // Field org/assertj/core/internal/bytebuddy/utility/JavaType.METHOD_HANDLE:Lorg/assertj/core/internal/bytebuddy/utility/JavaType;
     194: invokevirtual #177                // Method org/assertj/core/internal/bytebuddy/utility/JavaType.getTypeStub:()Lorg/assertj/core/internal/bytebuddy/description/type/TypeDescription;
     197: aload_0
     198: invokeinterface #181,  2          // InterfaceMethod org/assertj/core/internal/bytebuddy/description/type/TypeDescription.isInstance:(Ljava/lang/Object;)Z
     203: ifeq          218
     206: new           #57                 // class org/assertj/core/internal/bytebuddy/implementation/InvokeDynamic$InvocationProvider$ArgumentProvider$ForJavaConstant
     209: dup
     210: aload_0
     211: invokestatic  #185                // Method org/assertj/core/internal/bytebuddy/utility/JavaConstant$MethodHandle.ofLoaded:(Ljava/lang/Object;)Lorg/assertj/core/internal/bytebuddy/utility/JavaConstant$MethodHandle;
     214: invokespecial #188                // Method org/assertj/core/internal/bytebuddy/implementation/InvokeDynamic$InvocationProvider$ArgumentProvider$ForJavaConstant."<init>":(Lorg/assertj/core/internal/bytebuddy/utility/JavaConstant;)V
     217: areturn
     218: getstatic     #191                // Field org/assertj/core/internal/bytebuddy/utility/JavaType.METHOD_TYPE:Lorg/assertj/core/internal/bytebuddy/utility/JavaType;
     221: invokevirtual #177                // Method org/assertj/core/internal/bytebuddy/utility/JavaType.getTypeStub:()Lorg/assertj/core/internal/bytebuddy/description/type/TypeDescription;
     224: aload_0
     225: invokeinterface #181,  2          // InterfaceMethod org/assertj/core/internal/bytebuddy/description/type/TypeDescription.isInstance:(Ljava/lang/Object;)Z
     230: ifeq          245
     233: new           #57                 // class org/assertj/core/internal/bytebuddy/implementation/InvokeDynamic$InvocationProvider$ArgumentProvider$ForJavaConstant
     236: dup
     237: aload_0
     238: invokestatic  #194                // Method org/assertj/core/internal/bytebuddy/utility/JavaConstant$MethodType.ofLoaded:(Ljava/lang/Object;)Lorg/assertj/core/internal/bytebuddy/utility/JavaConstant$MethodType;
     241: invokespecial #188                // Method org/assertj/core/internal/bytebuddy/implementation/InvokeDynamic$InvocationProvider$ArgumentProvider$ForJavaConstant."<init>":(Lorg/assertj/core/internal/bytebuddy/utility/JavaConstant;)V
     244: areturn
     245: aload_0
     246: invokestatic  #196                // Method org/assertj/core/internal/bytebuddy/implementation/InvokeDynamic$InvocationProvider$ArgumentProvider$ForInstance.of:(Ljava/lang/Object;)Lorg/assertj/core/internal/bytebuddy/implementation/InvokeDynamic$InvocationProvider$ArgumentProvider;
     249: areturn

  protected abstract org.assertj.core.internal.bytebuddy.implementation.InvokeDynamic$InvocationProvider$ArgumentProvider make(java.lang.Object);

  org.assertj.core.internal.bytebuddy.implementation.InvokeDynamic$InvocationProvider$ArgumentProvider$ConstantPoolWrapper(java.lang.String, int, java.lang.Class, java.lang.Class, org.assertj.core.internal.bytebuddy.implementation.InvokeDynamic$1);
    Code:
       0: aload_0
       1: aload_1
       2: iload_2
       3: aload_3
       4: aload         4
       6: invokespecial #201                // Method "<init>":(Ljava/lang/String;ILjava/lang/Class;Ljava/lang/Class;)V
       9: return

  static org.assertj.core.internal.bytebuddy.description.type.TypeDescription access$100(org.assertj.core.internal.bytebuddy.implementation.InvokeDynamic$InvocationProvider$ArgumentProvider$ConstantPoolWrapper);
    Code:
       0: aload_0
       1: getfield      #109                // Field primitiveType:Lorg/assertj/core/internal/bytebuddy/description/type/TypeDescription;
       4: areturn

  static org.assertj.core.internal.bytebuddy.description.type.TypeDescription access$200(org.assertj.core.internal.bytebuddy.implementation.InvokeDynamic$InvocationProvider$ArgumentProvider$ConstantPoolWrapper);
    Code:
       0: aload_0
       1: getfield      #111                // Field wrapperType:Lorg/assertj/core/internal/bytebuddy/description/type/TypeDescription;
       4: areturn

  static {};
    Code:
       0: new           #34                 // class org/assertj/core/internal/bytebuddy/implementation/InvokeDynamic$InvocationProvider$ArgumentProvider$ConstantPoolWrapper$1
       3: dup
       4: ldc           #214                // String BOOLEAN
       6: iconst_0
       7: getstatic     #217                // Field java/lang/Boolean.TYPE:Ljava/lang/Class;
      10: ldc           #118                // class java/lang/Boolean
      12: invokespecial #218                // Method org/assertj/core/internal/bytebuddy/implementation/InvokeDynamic$InvocationProvider$ArgumentProvider$ConstantPoolWrapper$1."<init>":(Ljava/lang/String;ILjava/lang/Class;Ljava/lang/Class;)V
      15: putstatic     #120                // Field BOOLEAN:Lorg/assertj/core/internal/bytebuddy/implementation/InvokeDynamic$InvocationProvider$ArgumentProvider$ConstantPoolWrapper;
      18: new           #32                 // class org/assertj/core/internal/bytebuddy/implementation/InvokeDynamic$InvocationProvider$ArgumentProvider$ConstantPoolWrapper$2
      21: dup
      22: ldc           #219                // String BYTE
      24: iconst_1
      25: getstatic     #220                // Field java/lang/Byte.TYPE:Ljava/lang/Class;
      28: ldc           #125                // class java/lang/Byte
      30: invokespecial #221                // Method org/assertj/core/internal/bytebuddy/implementation/InvokeDynamic$InvocationProvider$ArgumentProvider$ConstantPoolWrapper$2."<init>":(Ljava/lang/String;ILjava/lang/Class;Ljava/lang/Class;)V
      33: putstatic     #127                // Field BYTE:Lorg/assertj/core/internal/bytebuddy/implementation/InvokeDynamic$InvocationProvider$ArgumentProvider$ConstantPoolWrapper;
      36: new           #30                 // class org/assertj/core/internal/bytebuddy/implementation/InvokeDynamic$InvocationProvider$ArgumentProvider$ConstantPoolWrapper$3
      39: dup
      40: ldc           #222                // String SHORT
      42: iconst_2
      43: getstatic     #223                // Field java/lang/Short.TYPE:Ljava/lang/Class;
      46: ldc           #129                // class java/lang/Short
      48: invokespecial #224                // Method org/assertj/core/internal/bytebuddy/implementation/InvokeDynamic$InvocationProvider$ArgumentProvider$ConstantPoolWrapper$3."<init>":(Ljava/lang/String;ILjava/lang/Class;Ljava/lang/Class;)V
      51: putstatic     #131                // Field SHORT:Lorg/assertj/core/internal/bytebuddy/implementation/InvokeDynamic$InvocationProvider$ArgumentProvider$ConstantPoolWrapper;
      54: new           #28                 // class org/assertj/core/internal/bytebuddy/implementation/InvokeDynamic$InvocationProvider$ArgumentProvider$ConstantPoolWrapper$4
      57: dup
      58: ldc           #225                // String CHARACTER
      60: iconst_3
      61: getstatic     #226                // Field java/lang/Character.TYPE:Ljava/lang/Class;
      64: ldc           #133                // class java/lang/Character
      66: invokespecial #227                // Method org/assertj/core/internal/bytebuddy/implementation/InvokeDynamic$InvocationProvider$ArgumentProvider$ConstantPoolWrapper$4."<init>":(Ljava/lang/String;ILjava/lang/Class;Ljava/lang/Class;)V
      69: putstatic     #135                // Field CHARACTER:Lorg/assertj/core/internal/bytebuddy/implementation/InvokeDynamic$InvocationProvider$ArgumentProvider$ConstantPoolWrapper;
      72: new           #26                 // class org/assertj/core/internal/bytebuddy/implementation/InvokeDynamic$InvocationProvider$ArgumentProvider$ConstantPoolWrapper$5
      75: dup
      76: ldc           #228                // String INTEGER
      78: iconst_4
      79: getstatic     #229                // Field java/lang/Integer.TYPE:Ljava/lang/Class;
      82: ldc           #137                // class java/lang/Integer
      84: invokespecial #230                // Method org/assertj/core/internal/bytebuddy/implementation/InvokeDynamic$InvocationProvider$ArgumentProvider$ConstantPoolWrapper$5."<init>":(Ljava/lang/String;ILjava/lang/Class;Ljava/lang/Class;)V
      87: putstatic     #139                // Field INTEGER:Lorg/assertj/core/internal/bytebuddy/implementation/InvokeDynamic$InvocationProvider$ArgumentProvider$ConstantPoolWrapper;
      90: new           #24                 // class org/assertj/core/internal/bytebuddy/implementation/InvokeDynamic$InvocationProvider$ArgumentProvider$ConstantPoolWrapper$6
      93: dup
      94: ldc           #231                // String LONG
      96: iconst_5
      97: getstatic     #232                // Field java/lang/Long.TYPE:Ljava/lang/Class;
     100: ldc           #141                // class java/lang/Long
     102: invokespecial #233                // Method org/assertj/core/internal/bytebuddy/implementation/InvokeDynamic$InvocationProvider$ArgumentProvider$ConstantPoolWrapper$6."<init>":(Ljava/lang/String;ILjava/lang/Class;Ljava/lang/Class;)V
     105: putstatic     #143                // Field LONG:Lorg/assertj/core/internal/bytebuddy/implementation/InvokeDynamic$InvocationProvider$ArgumentProvider$ConstantPoolWrapper;
     108: new           #22                 // class org/assertj/core/internal/bytebuddy/implementation/InvokeDynamic$InvocationProvider$ArgumentProvider$ConstantPoolWrapper$7
     111: dup
     112: ldc           #234                // String FLOAT
     114: bipush        6
     116: getstatic     #235                // Field java/lang/Float.TYPE:Ljava/lang/Class;
     119: ldc           #145                // class java/lang/Float
     121: invokespecial #236                // Method org/assertj/core/internal/bytebuddy/implementation/InvokeDynamic$InvocationProvider$ArgumentProvider$ConstantPoolWrapper$7."<init>":(Ljava/lang/String;ILjava/lang/Class;Ljava/lang/Class;)V
     124: putstatic     #147                // Field FLOAT:Lorg/assertj/core/internal/bytebuddy/implementation/InvokeDynamic$InvocationProvider$ArgumentProvider$ConstantPoolWrapper;
     127: new           #20                 // class org/assertj/core/internal/bytebuddy/implementation/InvokeDynamic$InvocationProvider$ArgumentProvider$ConstantPoolWrapper$8
     130: dup
     131: ldc           #237                // String DOUBLE
     133: bipush        7
     135: getstatic     #238                // Field java/lang/Double.TYPE:Ljava/lang/Class;
     138: ldc           #149                // class java/lang/Double
     140: invokespecial #239                // Method org/assertj/core/internal/bytebuddy/implementation/InvokeDynamic$InvocationProvider$ArgumentProvider$ConstantPoolWrapper$8."<init>":(Ljava/lang/String;ILjava/lang/Class;Ljava/lang/Class;)V
     143: putstatic     #151                // Field DOUBLE:Lorg/assertj/core/internal/bytebuddy/implementation/InvokeDynamic$InvocationProvider$ArgumentProvider$ConstantPoolWrapper;
     146: bipush        8
     148: anewarray     #2                  // class org/assertj/core/internal/bytebuddy/implementation/InvokeDynamic$InvocationProvider$ArgumentProvider$ConstantPoolWrapper
     151: dup
     152: iconst_0
     153: getstatic     #120                // Field BOOLEAN:Lorg/assertj/core/internal/bytebuddy/implementation/InvokeDynamic$InvocationProvider$ArgumentProvider$ConstantPoolWrapper;
     156: aastore
     157: dup
     158: iconst_1
     159: getstatic     #127                // Field BYTE:Lorg/assertj/core/internal/bytebuddy/implementation/InvokeDynamic$InvocationProvider$ArgumentProvider$ConstantPoolWrapper;
     162: aastore
     163: dup
     164: iconst_2
     165: getstatic     #131                // Field SHORT:Lorg/assertj/core/internal/bytebuddy/implementation/InvokeDynamic$InvocationProvider$ArgumentProvider$ConstantPoolWrapper;
     168: aastore
     169: dup
     170: iconst_3
     171: getstatic     #135                // Field CHARACTER:Lorg/assertj/core/internal/bytebuddy/implementation/InvokeDynamic$InvocationProvider$ArgumentProvider$ConstantPoolWrapper;
     174: aastore
     175: dup
     176: iconst_4
     177: getstatic     #139                // Field INTEGER:Lorg/assertj/core/internal/bytebuddy/implementation/InvokeDynamic$InvocationProvider$ArgumentProvider$ConstantPoolWrapper;
     180: aastore
     181: dup
     182: iconst_5
     183: getstatic     #143                // Field LONG:Lorg/assertj/core/internal/bytebuddy/implementation/InvokeDynamic$InvocationProvider$ArgumentProvider$ConstantPoolWrapper;
     186: aastore
     187: dup
     188: bipush        6
     190: getstatic     #147                // Field FLOAT:Lorg/assertj/core/internal/bytebuddy/implementation/InvokeDynamic$InvocationProvider$ArgumentProvider$ConstantPoolWrapper;
     193: aastore
     194: dup
     195: bipush        7
     197: getstatic     #151                // Field DOUBLE:Lorg/assertj/core/internal/bytebuddy/implementation/InvokeDynamic$InvocationProvider$ArgumentProvider$ConstantPoolWrapper;
     200: aastore
     201: putstatic     #87                 // Field $VALUES:[Lorg/assertj/core/internal/bytebuddy/implementation/InvokeDynamic$InvocationProvider$ArgumentProvider$ConstantPoolWrapper;
     204: return
}
