Compiled from "MethodCall.java"
public class org.assertj.core.internal.bytebuddy.implementation.MethodCall implements org.assertj.core.internal.bytebuddy.implementation.Implementation$Composable {
  protected final org.assertj.core.internal.bytebuddy.implementation.MethodCall$MethodLocator methodLocator;

  protected final org.assertj.core.internal.bytebuddy.implementation.MethodCall$TargetHandler targetHandler;

  protected final java.util.List<org.assertj.core.internal.bytebuddy.implementation.MethodCall$ArgumentLoader$Factory> argumentLoaders;

  protected final org.assertj.core.internal.bytebuddy.implementation.MethodCall$MethodInvoker methodInvoker;

  protected final org.assertj.core.internal.bytebuddy.implementation.MethodCall$TerminationHandler terminationHandler;

  protected final org.assertj.core.internal.bytebuddy.implementation.bytecode.assign.Assigner assigner;

  protected final org.assertj.core.internal.bytebuddy.implementation.bytecode.assign.Assigner$Typing typing;

  protected org.assertj.core.internal.bytebuddy.implementation.MethodCall(org.assertj.core.internal.bytebuddy.implementation.MethodCall$MethodLocator, org.assertj.core.internal.bytebuddy.implementation.MethodCall$TargetHandler, java.util.List<org.assertj.core.internal.bytebuddy.implementation.MethodCall$ArgumentLoader$Factory>, org.assertj.core.internal.bytebuddy.implementation.MethodCall$MethodInvoker, org.assertj.core.internal.bytebuddy.implementation.MethodCall$TerminationHandler, org.assertj.core.internal.bytebuddy.implementation.bytecode.assign.Assigner, org.assertj.core.internal.bytebuddy.implementation.bytecode.assign.Assigner$Typing);
    Code:
       0: aload_0
       1: invokespecial #162                // Method java/lang/Object."<init>":()V
       4: aload_0
       5: aload_1
       6: putfield      #164                // Field methodLocator:Lorg/assertj/core/internal/bytebuddy/implementation/MethodCall$MethodLocator;
       9: aload_0
      10: aload_2
      11: putfield      #166                // Field targetHandler:Lorg/assertj/core/internal/bytebuddy/implementation/MethodCall$TargetHandler;
      14: aload_0
      15: aload_3
      16: putfield      #168                // Field argumentLoaders:Ljava/util/List;
      19: aload_0
      20: aload         4
      22: putfield      #170                // Field methodInvoker:Lorg/assertj/core/internal/bytebuddy/implementation/MethodCall$MethodInvoker;
      25: aload_0
      26: aload         5
      28: putfield      #172                // Field terminationHandler:Lorg/assertj/core/internal/bytebuddy/implementation/MethodCall$TerminationHandler;
      31: aload_0
      32: aload         6
      34: putfield      #174                // Field assigner:Lorg/assertj/core/internal/bytebuddy/implementation/bytecode/assign/Assigner;
      37: aload_0
      38: aload         7
      40: putfield      #176                // Field typing:Lorg/assertj/core/internal/bytebuddy/implementation/bytecode/assign/Assigner$Typing;
      43: return

  public static org.assertj.core.internal.bytebuddy.implementation.MethodCall$WithoutSpecifiedTarget invoke(java.lang.reflect.Method);
    Code:
       0: new           #55                 // class org/assertj/core/internal/bytebuddy/description/method/MethodDescription$ForLoadedMethod
       3: dup
       4: aload_0
       5: invokespecial #183                // Method org/assertj/core/internal/bytebuddy/description/method/MethodDescription$ForLoadedMethod."<init>":(Ljava/lang/reflect/Method;)V
       8: invokestatic  #186                // Method invoke:(Lorg/assertj/core/internal/bytebuddy/description/method/MethodDescription;)Lorg/assertj/core/internal/bytebuddy/implementation/MethodCall$WithoutSpecifiedTarget;
      11: areturn

  public static org.assertj.core.internal.bytebuddy.implementation.MethodCall$WithoutSpecifiedTarget invoke(java.lang.reflect.Constructor<?>);
    Code:
       0: new           #60                 // class org/assertj/core/internal/bytebuddy/description/method/MethodDescription$ForLoadedConstructor
       3: dup
       4: aload_0
       5: invokespecial #192                // Method org/assertj/core/internal/bytebuddy/description/method/MethodDescription$ForLoadedConstructor."<init>":(Ljava/lang/reflect/Constructor;)V
       8: invokestatic  #186                // Method invoke:(Lorg/assertj/core/internal/bytebuddy/description/method/MethodDescription;)Lorg/assertj/core/internal/bytebuddy/implementation/MethodCall$WithoutSpecifiedTarget;
      11: areturn

  public static org.assertj.core.internal.bytebuddy.implementation.MethodCall$WithoutSpecifiedTarget invoke(org.assertj.core.internal.bytebuddy.description.method.MethodDescription);
    Code:
       0: new           #63                 // class org/assertj/core/internal/bytebuddy/implementation/MethodCall$MethodLocator$ForExplicitMethod
       3: dup
       4: aload_0
       5: invokespecial #198                // Method org/assertj/core/internal/bytebuddy/implementation/MethodCall$MethodLocator$ForExplicitMethod."<init>":(Lorg/assertj/core/internal/bytebuddy/description/method/MethodDescription;)V
       8: invokestatic  #201                // Method invoke:(Lorg/assertj/core/internal/bytebuddy/implementation/MethodCall$MethodLocator;)Lorg/assertj/core/internal/bytebuddy/implementation/MethodCall$WithoutSpecifiedTarget;
      11: areturn

  public static org.assertj.core.internal.bytebuddy.implementation.MethodCall$WithoutSpecifiedTarget invoke(org.assertj.core.internal.bytebuddy.matcher.ElementMatcher<? super org.assertj.core.internal.bytebuddy.description.method.MethodDescription>);
    Code:
       0: aload_0
       1: getstatic     #208                // Field org/assertj/core/internal/bytebuddy/dynamic/scaffold/MethodGraph$Compiler.DEFAULT:Lorg/assertj/core/internal/bytebuddy/dynamic/scaffold/MethodGraph$Compiler;
       4: invokestatic  #211                // Method invoke:(Lorg/assertj/core/internal/bytebuddy/matcher/ElementMatcher;Lorg/assertj/core/internal/bytebuddy/dynamic/scaffold/MethodGraph$Compiler;)Lorg/assertj/core/internal/bytebuddy/implementation/MethodCall$WithoutSpecifiedTarget;
       7: areturn

  public static org.assertj.core.internal.bytebuddy.implementation.MethodCall$WithoutSpecifiedTarget invoke(org.assertj.core.internal.bytebuddy.matcher.ElementMatcher<? super org.assertj.core.internal.bytebuddy.description.method.MethodDescription>, org.assertj.core.internal.bytebuddy.dynamic.scaffold.MethodGraph$Compiler);
    Code:
       0: new           #66                 // class org/assertj/core/internal/bytebuddy/implementation/MethodCall$MethodLocator$ForElementMatcher
       3: dup
       4: aload_0
       5: aload_1
       6: invokespecial #217                // Method org/assertj/core/internal/bytebuddy/implementation/MethodCall$MethodLocator$ForElementMatcher."<init>":(Lorg/assertj/core/internal/bytebuddy/matcher/ElementMatcher;Lorg/assertj/core/internal/bytebuddy/dynamic/scaffold/MethodGraph$Compiler;)V
       9: invokestatic  #201                // Method invoke:(Lorg/assertj/core/internal/bytebuddy/implementation/MethodCall$MethodLocator;)Lorg/assertj/core/internal/bytebuddy/implementation/MethodCall$WithoutSpecifiedTarget;
      12: areturn

  public static org.assertj.core.internal.bytebuddy.implementation.MethodCall$WithoutSpecifiedTarget invoke(org.assertj.core.internal.bytebuddy.implementation.MethodCall$MethodLocator);
    Code:
       0: new           #14                 // class org/assertj/core/internal/bytebuddy/implementation/MethodCall$WithoutSpecifiedTarget
       3: dup
       4: aload_0
       5: invokespecial #221                // Method org/assertj/core/internal/bytebuddy/implementation/MethodCall$WithoutSpecifiedTarget."<init>":(Lorg/assertj/core/internal/bytebuddy/implementation/MethodCall$MethodLocator;)V
       8: areturn

  public static org.assertj.core.internal.bytebuddy.implementation.MethodCall$WithoutSpecifiedTarget invokeSelf();
    Code:
       0: new           #14                 // class org/assertj/core/internal/bytebuddy/implementation/MethodCall$WithoutSpecifiedTarget
       3: dup
       4: getstatic     #227                // Field org/assertj/core/internal/bytebuddy/implementation/MethodCall$MethodLocator$ForInstrumentedMethod.INSTANCE:Lorg/assertj/core/internal/bytebuddy/implementation/MethodCall$MethodLocator$ForInstrumentedMethod;
       7: invokespecial #221                // Method org/assertj/core/internal/bytebuddy/implementation/MethodCall$WithoutSpecifiedTarget."<init>":(Lorg/assertj/core/internal/bytebuddy/implementation/MethodCall$MethodLocator;)V
      10: areturn

  public static org.assertj.core.internal.bytebuddy.implementation.MethodCall invokeSuper();
    Code:
       0: invokestatic  #231                // Method invokeSelf:()Lorg/assertj/core/internal/bytebuddy/implementation/MethodCall$WithoutSpecifiedTarget;
       3: invokevirtual #234                // Method org/assertj/core/internal/bytebuddy/implementation/MethodCall$WithoutSpecifiedTarget.onSuper:()Lorg/assertj/core/internal/bytebuddy/implementation/MethodCall;
       6: areturn

  public static org.assertj.core.internal.bytebuddy.implementation.Implementation$Composable call(java.util.concurrent.Callable<?>);
    Code:
       0: ldc           #240                // class java/util/concurrent/Callable
       2: ldc           #241                // String call
       4: iconst_0
       5: anewarray     #243                // class java/lang/Class
       8: invokevirtual #247                // Method java/lang/Class.getMethod:(Ljava/lang/String;[Ljava/lang/Class;)Ljava/lang/reflect/Method;
      11: invokestatic  #249                // Method invoke:(Ljava/lang/reflect/Method;)Lorg/assertj/core/internal/bytebuddy/implementation/MethodCall$WithoutSpecifiedTarget;
      14: aload_0
      15: ldc           #240                // class java/util/concurrent/Callable
      17: invokevirtual #253                // Method org/assertj/core/internal/bytebuddy/implementation/MethodCall$WithoutSpecifiedTarget.on:(Ljava/lang/Object;Ljava/lang/Class;)Lorg/assertj/core/internal/bytebuddy/implementation/MethodCall;
      20: getstatic     #255                // Field org/assertj/core/internal/bytebuddy/implementation/bytecode/assign/Assigner.DEFAULT:Lorg/assertj/core/internal/bytebuddy/implementation/bytecode/assign/Assigner;
      23: getstatic     #258                // Field org/assertj/core/internal/bytebuddy/implementation/bytecode/assign/Assigner$Typing.DYNAMIC:Lorg/assertj/core/internal/bytebuddy/implementation/bytecode/assign/Assigner$Typing;
      26: invokevirtual #262                // Method withAssigner:(Lorg/assertj/core/internal/bytebuddy/implementation/bytecode/assign/Assigner;Lorg/assertj/core/internal/bytebuddy/implementation/bytecode/assign/Assigner$Typing;)Lorg/assertj/core/internal/bytebuddy/implementation/Implementation$Composable;
      29: areturn
      30: astore_1
      31: new           #264                // class java/lang/IllegalStateException
      34: dup
      35: ldc_w         #266                // String Could not locate Callable::call method
      38: aload_1
      39: invokespecial #269                // Method java/lang/IllegalStateException."<init>":(Ljava/lang/String;Ljava/lang/Throwable;)V
      42: athrow
    Exception table:
       from    to  target type
           0    29    30   Class java/lang/NoSuchMethodException

  public static org.assertj.core.internal.bytebuddy.implementation.Implementation$Composable run(java.lang.Runnable);
    Code:
       0: ldc_w         #278                // class java/lang/Runnable
       3: ldc_w         #279                // String run
       6: iconst_0
       7: anewarray     #243                // class java/lang/Class
      10: invokevirtual #247                // Method java/lang/Class.getMethod:(Ljava/lang/String;[Ljava/lang/Class;)Ljava/lang/reflect/Method;
      13: invokestatic  #249                // Method invoke:(Ljava/lang/reflect/Method;)Lorg/assertj/core/internal/bytebuddy/implementation/MethodCall$WithoutSpecifiedTarget;
      16: aload_0
      17: ldc_w         #278                // class java/lang/Runnable
      20: invokevirtual #253                // Method org/assertj/core/internal/bytebuddy/implementation/MethodCall$WithoutSpecifiedTarget.on:(Ljava/lang/Object;Ljava/lang/Class;)Lorg/assertj/core/internal/bytebuddy/implementation/MethodCall;
      23: getstatic     #255                // Field org/assertj/core/internal/bytebuddy/implementation/bytecode/assign/Assigner.DEFAULT:Lorg/assertj/core/internal/bytebuddy/implementation/bytecode/assign/Assigner;
      26: getstatic     #258                // Field org/assertj/core/internal/bytebuddy/implementation/bytecode/assign/Assigner$Typing.DYNAMIC:Lorg/assertj/core/internal/bytebuddy/implementation/bytecode/assign/Assigner$Typing;
      29: invokevirtual #262                // Method withAssigner:(Lorg/assertj/core/internal/bytebuddy/implementation/bytecode/assign/Assigner;Lorg/assertj/core/internal/bytebuddy/implementation/bytecode/assign/Assigner$Typing;)Lorg/assertj/core/internal/bytebuddy/implementation/Implementation$Composable;
      32: areturn
      33: astore_1
      34: new           #264                // class java/lang/IllegalStateException
      37: dup
      38: ldc_w         #281                // String Could not locate Runnable::run method
      41: aload_1
      42: invokespecial #269                // Method java/lang/IllegalStateException."<init>":(Ljava/lang/String;Ljava/lang/Throwable;)V
      45: athrow
    Exception table:
       from    to  target type
           0    32    33   Class java/lang/NoSuchMethodException

  public static org.assertj.core.internal.bytebuddy.implementation.MethodCall construct(java.lang.reflect.Constructor<?>);
    Code:
       0: new           #60                 // class org/assertj/core/internal/bytebuddy/description/method/MethodDescription$ForLoadedConstructor
       3: dup
       4: aload_0
       5: invokespecial #192                // Method org/assertj/core/internal/bytebuddy/description/method/MethodDescription$ForLoadedConstructor."<init>":(Ljava/lang/reflect/Constructor;)V
       8: invokestatic  #288                // Method construct:(Lorg/assertj/core/internal/bytebuddy/description/method/MethodDescription;)Lorg/assertj/core/internal/bytebuddy/implementation/MethodCall;
      11: areturn

  public static org.assertj.core.internal.bytebuddy.implementation.MethodCall construct(org.assertj.core.internal.bytebuddy.description.method.MethodDescription);
    Code:
       0: aload_0
       1: invokeinterface #292,  1          // InterfaceMethod org/assertj/core/internal/bytebuddy/description/method/MethodDescription.isConstructor:()Z
       6: ifne          37
       9: new           #294                // class java/lang/IllegalArgumentException
      12: dup
      13: new           #296                // class java/lang/StringBuilder
      16: dup
      17: invokespecial #297                // Method java/lang/StringBuilder."<init>":()V
      20: ldc_w         #299                // String Not a constructor:
      23: invokevirtual #303                // Method java/lang/StringBuilder.append:(Ljava/lang/String;)Ljava/lang/StringBuilder;
      26: aload_0
      27: invokevirtual #306                // Method java/lang/StringBuilder.append:(Ljava/lang/Object;)Ljava/lang/StringBuilder;
      30: invokevirtual #310                // Method java/lang/StringBuilder.toString:()Ljava/lang/String;
      33: invokespecial #313                // Method java/lang/IllegalArgumentException."<init>":(Ljava/lang/String;)V
      36: athrow
      37: new           #2                  // class org/assertj/core/internal/bytebuddy/implementation/MethodCall
      40: dup
      41: new           #63                 // class org/assertj/core/internal/bytebuddy/implementation/MethodCall$MethodLocator$ForExplicitMethod
      44: dup
      45: aload_0
      46: invokespecial #198                // Method org/assertj/core/internal/bytebuddy/implementation/MethodCall$MethodLocator$ForExplicitMethod."<init>":(Lorg/assertj/core/internal/bytebuddy/description/method/MethodDescription;)V
      49: getstatic     #316                // Field org/assertj/core/internal/bytebuddy/implementation/MethodCall$TargetHandler$ForConstructingInvocation.INSTANCE:Lorg/assertj/core/internal/bytebuddy/implementation/MethodCall$TargetHandler$ForConstructingInvocation;
      52: invokestatic  #322                // Method java/util/Collections.emptyList:()Ljava/util/List;
      55: getstatic     #325                // Field org/assertj/core/internal/bytebuddy/implementation/MethodCall$MethodInvoker$ForContextualInvocation.INSTANCE:Lorg/assertj/core/internal/bytebuddy/implementation/MethodCall$MethodInvoker$ForContextualInvocation;
      58: getstatic     #328                // Field org/assertj/core/internal/bytebuddy/implementation/MethodCall$TerminationHandler.RETURNING:Lorg/assertj/core/internal/bytebuddy/implementation/MethodCall$TerminationHandler;
      61: getstatic     #255                // Field org/assertj/core/internal/bytebuddy/implementation/bytecode/assign/Assigner.DEFAULT:Lorg/assertj/core/internal/bytebuddy/implementation/bytecode/assign/Assigner;
      64: getstatic     #331                // Field org/assertj/core/internal/bytebuddy/implementation/bytecode/assign/Assigner$Typing.STATIC:Lorg/assertj/core/internal/bytebuddy/implementation/bytecode/assign/Assigner$Typing;
      67: invokespecial #333                // Method "<init>":(Lorg/assertj/core/internal/bytebuddy/implementation/MethodCall$MethodLocator;Lorg/assertj/core/internal/bytebuddy/implementation/MethodCall$TargetHandler;Ljava/util/List;Lorg/assertj/core/internal/bytebuddy/implementation/MethodCall$MethodInvoker;Lorg/assertj/core/internal/bytebuddy/implementation/MethodCall$TerminationHandler;Lorg/assertj/core/internal/bytebuddy/implementation/bytecode/assign/Assigner;Lorg/assertj/core/internal/bytebuddy/implementation/bytecode/assign/Assigner$Typing;)V
      70: areturn

  public org.assertj.core.internal.bytebuddy.implementation.MethodCall with(java.lang.Object...);
    Code:
       0: new           #337                // class java/util/ArrayList
       3: dup
       4: aload_1
       5: arraylength
       6: invokespecial #340                // Method java/util/ArrayList."<init>":(I)V
       9: astore_2
      10: aload_1
      11: astore_3
      12: aload_3
      13: arraylength
      14: istore        4
      16: iconst_0
      17: istore        5
      19: iload         5
      21: iload         4
      23: if_icmpge     50
      26: aload_3
      27: iload         5
      29: aaload
      30: astore        6
      32: aload_2
      33: aload         6
      35: invokestatic  #348                // Method org/assertj/core/internal/bytebuddy/implementation/MethodCall$ArgumentLoader$ForStackManipulation.of:(Ljava/lang/Object;)Lorg/assertj/core/internal/bytebuddy/implementation/MethodCall$ArgumentLoader$Factory;
      38: invokeinterface #352,  2          // InterfaceMethod java/util/List.add:(Ljava/lang/Object;)Z
      43: pop
      44: iinc          5, 1
      47: goto          19
      50: aload_0
      51: aload_2
      52: invokevirtual #355                // Method with:(Ljava/util/List;)Lorg/assertj/core/internal/bytebuddy/implementation/MethodCall;
      55: areturn

  public org.assertj.core.internal.bytebuddy.implementation.MethodCall with(org.assertj.core.internal.bytebuddy.description.type.TypeDescription...);
    Code:
       0: new           #337                // class java/util/ArrayList
       3: dup
       4: aload_1
       5: arraylength
       6: invokespecial #340                // Method java/util/ArrayList."<init>":(I)V
       9: astore_2
      10: aload_1
      11: astore_3
      12: aload_3
      13: arraylength
      14: istore        4
      16: iconst_0
      17: istore        5
      19: iload         5
      21: iload         4
      23: if_icmpge     59
      26: aload_3
      27: iload         5
      29: aaload
      30: astore        6
      32: aload_2
      33: new           #69                 // class org/assertj/core/internal/bytebuddy/implementation/MethodCall$ArgumentLoader$ForStackManipulation
      36: dup
      37: aload         6
      39: invokestatic  #366                // Method org/assertj/core/internal/bytebuddy/implementation/bytecode/constant/ClassConstant.of:(Lorg/assertj/core/internal/bytebuddy/description/type/TypeDescription;)Lorg/assertj/core/internal/bytebuddy/implementation/bytecode/StackManipulation;
      42: ldc           #243                // class java/lang/Class
      44: invokespecial #369                // Method org/assertj/core/internal/bytebuddy/implementation/MethodCall$ArgumentLoader$ForStackManipulation."<init>":(Lorg/assertj/core/internal/bytebuddy/implementation/bytecode/StackManipulation;Ljava/lang/reflect/Type;)V
      47: invokeinterface #352,  2          // InterfaceMethod java/util/List.add:(Ljava/lang/Object;)Z
      52: pop
      53: iinc          5, 1
      56: goto          19
      59: aload_0
      60: aload_2
      61: invokevirtual #355                // Method with:(Ljava/util/List;)Lorg/assertj/core/internal/bytebuddy/implementation/MethodCall;
      64: areturn

  public org.assertj.core.internal.bytebuddy.implementation.MethodCall with(org.assertj.core.internal.bytebuddy.description.enumeration.EnumerationDescription...);
    Code:
       0: new           #337                // class java/util/ArrayList
       3: dup
       4: aload_1
       5: arraylength
       6: invokespecial #340                // Method java/util/ArrayList."<init>":(I)V
       9: astore_2
      10: aload_1
      11: astore_3
      12: aload_3
      13: arraylength
      14: istore        4
      16: iconst_0
      17: istore        5
      19: iload         5
      21: iload         4
      23: if_icmpge     64
      26: aload_3
      27: iload         5
      29: aaload
      30: astore        6
      32: aload_2
      33: new           #69                 // class org/assertj/core/internal/bytebuddy/implementation/MethodCall$ArgumentLoader$ForStackManipulation
      36: dup
      37: aload         6
      39: invokestatic  #381                // Method org/assertj/core/internal/bytebuddy/implementation/bytecode/member/FieldAccess.forEnumeration:(Lorg/assertj/core/internal/bytebuddy/description/enumeration/EnumerationDescription;)Lorg/assertj/core/internal/bytebuddy/implementation/bytecode/StackManipulation;
      42: aload         6
      44: invokeinterface #387,  1          // InterfaceMethod org/assertj/core/internal/bytebuddy/description/enumeration/EnumerationDescription.getEnumerationType:()Lorg/assertj/core/internal/bytebuddy/description/type/TypeDescription;
      49: invokespecial #390                // Method org/assertj/core/internal/bytebuddy/implementation/MethodCall$ArgumentLoader$ForStackManipulation."<init>":(Lorg/assertj/core/internal/bytebuddy/implementation/bytecode/StackManipulation;Lorg/assertj/core/internal/bytebuddy/description/type/TypeDefinition;)V
      52: invokeinterface #352,  2          // InterfaceMethod java/util/List.add:(Ljava/lang/Object;)Z
      57: pop
      58: iinc          5, 1
      61: goto          19
      64: aload_0
      65: aload_2
      66: invokevirtual #355                // Method with:(Ljava/util/List;)Lorg/assertj/core/internal/bytebuddy/implementation/MethodCall;
      69: areturn

  public org.assertj.core.internal.bytebuddy.implementation.MethodCall with(org.assertj.core.internal.bytebuddy.utility.JavaConstant...);
    Code:
       0: new           #337                // class java/util/ArrayList
       3: dup
       4: aload_1
       5: arraylength
       6: invokespecial #340                // Method java/util/ArrayList."<init>":(I)V
       9: astore_2
      10: aload_1
      11: astore_3
      12: aload_3
      13: arraylength
      14: istore        4
      16: iconst_0
      17: istore        5
      19: iload         5
      21: iload         4
      23: if_icmpge     66
      26: aload_3
      27: iload         5
      29: aaload
      30: astore        6
      32: aload_2
      33: new           #69                 // class org/assertj/core/internal/bytebuddy/implementation/MethodCall$ArgumentLoader$ForStackManipulation
      36: dup
      37: aload         6
      39: invokeinterface #402,  1          // InterfaceMethod org/assertj/core/internal/bytebuddy/utility/JavaConstant.asStackManipulation:()Lorg/assertj/core/internal/bytebuddy/implementation/bytecode/StackManipulation;
      44: aload         6
      46: invokeinterface #405,  1          // InterfaceMethod org/assertj/core/internal/bytebuddy/utility/JavaConstant.getType:()Lorg/assertj/core/internal/bytebuddy/description/type/TypeDescription;
      51: invokespecial #390                // Method org/assertj/core/internal/bytebuddy/implementation/MethodCall$ArgumentLoader$ForStackManipulation."<init>":(Lorg/assertj/core/internal/bytebuddy/implementation/bytecode/StackManipulation;Lorg/assertj/core/internal/bytebuddy/description/type/TypeDefinition;)V
      54: invokeinterface #352,  2          // InterfaceMethod java/util/List.add:(Ljava/lang/Object;)Z
      59: pop
      60: iinc          5, 1
      63: goto          19
      66: aload_0
      67: aload_2
      68: invokevirtual #355                // Method with:(Ljava/util/List;)Lorg/assertj/core/internal/bytebuddy/implementation/MethodCall;
      71: areturn

  public org.assertj.core.internal.bytebuddy.implementation.MethodCall withReference(java.lang.Object...);
    Code:
       0: new           #337                // class java/util/ArrayList
       3: dup
       4: aload_1
       5: arraylength
       6: invokespecial #340                // Method java/util/ArrayList."<init>":(I)V
       9: astore_2
      10: aload_1
      11: astore_3
      12: aload_3
      13: arraylength
      14: istore        4
      16: iconst_0
      17: istore        5
      19: iload         5
      21: iload         4
      23: if_icmpge     65
      26: aload_3
      27: iload         5
      29: aaload
      30: astore        6
      32: aload_2
      33: aload         6
      35: ifnonnull     44
      38: getstatic     #412                // Field org/assertj/core/internal/bytebuddy/implementation/MethodCall$ArgumentLoader$ForNullConstant.INSTANCE:Lorg/assertj/core/internal/bytebuddy/implementation/MethodCall$ArgumentLoader$ForNullConstant;
      41: goto          53
      44: new           #75                 // class org/assertj/core/internal/bytebuddy/implementation/MethodCall$ArgumentLoader$ForInstance$Factory
      47: dup
      48: aload         6
      50: invokespecial #415                // Method org/assertj/core/internal/bytebuddy/implementation/MethodCall$ArgumentLoader$ForInstance$Factory."<init>":(Ljava/lang/Object;)V
      53: invokeinterface #352,  2          // InterfaceMethod java/util/List.add:(Ljava/lang/Object;)Z
      58: pop
      59: iinc          5, 1
      62: goto          19
      65: aload_0
      66: aload_2
      67: invokevirtual #355                // Method with:(Ljava/util/List;)Lorg/assertj/core/internal/bytebuddy/implementation/MethodCall;
      70: areturn

  public org.assertj.core.internal.bytebuddy.implementation.MethodCall withArgument(int...);
    Code:
       0: new           #337                // class java/util/ArrayList
       3: dup
       4: aload_1
       5: arraylength
       6: invokespecial #340                // Method java/util/ArrayList."<init>":(I)V
       9: astore_2
      10: aload_1
      11: astore_3
      12: aload_3
      13: arraylength
      14: istore        4
      16: iconst_0
      17: istore        5
      19: iload         5
      21: iload         4
      23: if_icmpge     88
      26: aload_3
      27: iload         5
      29: iaload
      30: istore        6
      32: iload         6
      34: ifge          66
      37: new           #294                // class java/lang/IllegalArgumentException
      40: dup
      41: new           #296                // class java/lang/StringBuilder
      44: dup
      45: invokespecial #297                // Method java/lang/StringBuilder."<init>":()V
      48: ldc_w         #421                // String Negative index:
      51: invokevirtual #303                // Method java/lang/StringBuilder.append:(Ljava/lang/String;)Ljava/lang/StringBuilder;
      54: iload         6
      56: invokevirtual #424                // Method java/lang/StringBuilder.append:(I)Ljava/lang/StringBuilder;
      59: invokevirtual #310                // Method java/lang/StringBuilder.toString:()Ljava/lang/String;
      62: invokespecial #313                // Method java/lang/IllegalArgumentException."<init>":(Ljava/lang/String;)V
      65: athrow
      66: aload_2
      67: new           #80                 // class org/assertj/core/internal/bytebuddy/implementation/MethodCall$ArgumentLoader$ForMethodParameter$Factory
      70: dup
      71: iload         6
      73: invokespecial #425                // Method org/assertj/core/internal/bytebuddy/implementation/MethodCall$ArgumentLoader$ForMethodParameter$Factory."<init>":(I)V
      76: invokeinterface #352,  2          // InterfaceMethod java/util/List.add:(Ljava/lang/Object;)Z
      81: pop
      82: iinc          5, 1
      85: goto          19
      88: aload_0
      89: aload_2
      90: invokevirtual #355                // Method with:(Ljava/util/List;)Lorg/assertj/core/internal/bytebuddy/implementation/MethodCall;
      93: areturn

  public org.assertj.core.internal.bytebuddy.implementation.MethodCall withAllArguments();
    Code:
       0: aload_0
       1: iconst_1
       2: anewarray     #32                 // class org/assertj/core/internal/bytebuddy/implementation/MethodCall$ArgumentLoader$Factory
       5: dup
       6: iconst_0
       7: getstatic     #432                // Field org/assertj/core/internal/bytebuddy/implementation/MethodCall$ArgumentLoader$ForMethodParameter$OfInstrumentedMethod.INSTANCE:Lorg/assertj/core/internal/bytebuddy/implementation/MethodCall$ArgumentLoader$ForMethodParameter$OfInstrumentedMethod;
      10: aastore
      11: invokevirtual #435                // Method with:([Lorg/assertj/core/internal/bytebuddy/implementation/MethodCall$ArgumentLoader$Factory;)Lorg/assertj/core/internal/bytebuddy/implementation/MethodCall;
      14: areturn

  public org.assertj.core.internal.bytebuddy.implementation.MethodCall withArgumentArray();
    Code:
       0: aload_0
       1: iconst_1
       2: anewarray     #32                 // class org/assertj/core/internal/bytebuddy/implementation/MethodCall$ArgumentLoader$Factory
       5: dup
       6: iconst_0
       7: getstatic     #439                // Field org/assertj/core/internal/bytebuddy/implementation/MethodCall$ArgumentLoader$ForMethodParameterArray$ForInstrumentedMethod.INSTANCE:Lorg/assertj/core/internal/bytebuddy/implementation/MethodCall$ArgumentLoader$ForMethodParameterArray$ForInstrumentedMethod;
      10: aastore
      11: invokevirtual #435                // Method with:([Lorg/assertj/core/internal/bytebuddy/implementation/MethodCall$ArgumentLoader$Factory;)Lorg/assertj/core/internal/bytebuddy/implementation/MethodCall;
      14: areturn

  public org.assertj.core.internal.bytebuddy.implementation.MethodCall withArgumentArrayElements(int);
    Code:
       0: iload_1
       1: ifge          32
       4: new           #294                // class java/lang/IllegalArgumentException
       7: dup
       8: new           #296                // class java/lang/StringBuilder
      11: dup
      12: invokespecial #297                // Method java/lang/StringBuilder."<init>":()V
      15: ldc_w         #443                // String A parameter index cannot be negative:
      18: invokevirtual #303                // Method java/lang/StringBuilder.append:(Ljava/lang/String;)Ljava/lang/StringBuilder;
      21: iload_1
      22: invokevirtual #424                // Method java/lang/StringBuilder.append:(I)Ljava/lang/StringBuilder;
      25: invokevirtual #310                // Method java/lang/StringBuilder.toString:()Ljava/lang/String;
      28: invokespecial #313                // Method java/lang/IllegalArgumentException."<init>":(Ljava/lang/String;)V
      31: athrow
      32: aload_0
      33: iconst_1
      34: anewarray     #32                 // class org/assertj/core/internal/bytebuddy/implementation/MethodCall$ArgumentLoader$Factory
      37: dup
      38: iconst_0
      39: new           #85                 // class org/assertj/core/internal/bytebuddy/implementation/MethodCall$ArgumentLoader$ForMethodParameterArrayElement$OfInvokedMethod
      42: dup
      43: iload_1
      44: invokespecial #444                // Method org/assertj/core/internal/bytebuddy/implementation/MethodCall$ArgumentLoader$ForMethodParameterArrayElement$OfInvokedMethod."<init>":(I)V
      47: aastore
      48: invokevirtual #435                // Method with:([Lorg/assertj/core/internal/bytebuddy/implementation/MethodCall$ArgumentLoader$Factory;)Lorg/assertj/core/internal/bytebuddy/implementation/MethodCall;
      51: areturn

  public org.assertj.core.internal.bytebuddy.implementation.MethodCall withArgumentArrayElements(int, int);
    Code:
       0: aload_0
       1: iload_1
       2: iconst_0
       3: iload_2
       4: invokevirtual #448                // Method withArgumentArrayElements:(III)Lorg/assertj/core/internal/bytebuddy/implementation/MethodCall;
       7: areturn

  public org.assertj.core.internal.bytebuddy.implementation.MethodCall withArgumentArrayElements(int, int, int);
    Code:
       0: iload_1
       1: ifge          32
       4: new           #294                // class java/lang/IllegalArgumentException
       7: dup
       8: new           #296                // class java/lang/StringBuilder
      11: dup
      12: invokespecial #297                // Method java/lang/StringBuilder."<init>":()V
      15: ldc_w         #443                // String A parameter index cannot be negative:
      18: invokevirtual #303                // Method java/lang/StringBuilder.append:(Ljava/lang/String;)Ljava/lang/StringBuilder;
      21: iload_1
      22: invokevirtual #424                // Method java/lang/StringBuilder.append:(I)Ljava/lang/StringBuilder;
      25: invokevirtual #310                // Method java/lang/StringBuilder.toString:()Ljava/lang/String;
      28: invokespecial #313                // Method java/lang/IllegalArgumentException."<init>":(Ljava/lang/String;)V
      31: athrow
      32: iload_2
      33: ifge          64
      36: new           #294                // class java/lang/IllegalArgumentException
      39: dup
      40: new           #296                // class java/lang/StringBuilder
      43: dup
      44: invokespecial #297                // Method java/lang/StringBuilder."<init>":()V
      47: ldc_w         #451                // String An array index cannot be negative:
      50: invokevirtual #303                // Method java/lang/StringBuilder.append:(Ljava/lang/String;)Ljava/lang/StringBuilder;
      53: iload_2
      54: invokevirtual #424                // Method java/lang/StringBuilder.append:(I)Ljava/lang/StringBuilder;
      57: invokevirtual #310                // Method java/lang/StringBuilder.toString:()Ljava/lang/String;
      60: invokespecial #313                // Method java/lang/IllegalArgumentException."<init>":(Ljava/lang/String;)V
      63: athrow
      64: iload_3
      65: ifne          70
      68: aload_0
      69: areturn
      70: iload_3
      71: ifge          102
      74: new           #294                // class java/lang/IllegalArgumentException
      77: dup
      78: new           #296                // class java/lang/StringBuilder
      81: dup
      82: invokespecial #297                // Method java/lang/StringBuilder."<init>":()V
      85: ldc_w         #453                // String Size cannot be negative:
      88: invokevirtual #303                // Method java/lang/StringBuilder.append:(Ljava/lang/String;)Ljava/lang/StringBuilder;
      91: iload_3
      92: invokevirtual #424                // Method java/lang/StringBuilder.append:(I)Ljava/lang/StringBuilder;
      95: invokevirtual #310                // Method java/lang/StringBuilder.toString:()Ljava/lang/String;
      98: invokespecial #313                // Method java/lang/IllegalArgumentException."<init>":(Ljava/lang/String;)V
     101: athrow
     102: new           #337                // class java/util/ArrayList
     105: dup
     106: iload_3
     107: invokespecial #340                // Method java/util/ArrayList."<init>":(I)V
     110: astore        4
     112: iconst_0
     113: istore        5
     115: iload         5
     117: iload_3
     118: if_icmpge     147
     121: aload         4
     123: new           #88                 // class org/assertj/core/internal/bytebuddy/implementation/MethodCall$ArgumentLoader$ForMethodParameterArrayElement$OfParameter
     126: dup
     127: iload_1
     128: iload_2
     129: iload         5
     131: iadd
     132: invokespecial #456                // Method org/assertj/core/internal/bytebuddy/implementation/MethodCall$ArgumentLoader$ForMethodParameterArrayElement$OfParameter."<init>":(II)V
     135: invokeinterface #352,  2          // InterfaceMethod java/util/List.add:(Ljava/lang/Object;)Z
     140: pop
     141: iinc          5, 1
     144: goto          115
     147: aload_0
     148: aload         4
     150: invokevirtual #355                // Method with:(Ljava/util/List;)Lorg/assertj/core/internal/bytebuddy/implementation/MethodCall;
     153: areturn

  public org.assertj.core.internal.bytebuddy.implementation.MethodCall withThis();
    Code:
       0: aload_0
       1: iconst_1
       2: anewarray     #32                 // class org/assertj/core/internal/bytebuddy/implementation/MethodCall$ArgumentLoader$Factory
       5: dup
       6: iconst_0
       7: getstatic     #462                // Field org/assertj/core/internal/bytebuddy/implementation/MethodCall$ArgumentLoader$ForThisReference$Factory.INSTANCE:Lorg/assertj/core/internal/bytebuddy/implementation/MethodCall$ArgumentLoader$ForThisReference$Factory;
      10: aastore
      11: invokevirtual #435                // Method with:([Lorg/assertj/core/internal/bytebuddy/implementation/MethodCall$ArgumentLoader$Factory;)Lorg/assertj/core/internal/bytebuddy/implementation/MethodCall;
      14: areturn

  public org.assertj.core.internal.bytebuddy.implementation.MethodCall withOwnType();
    Code:
       0: aload_0
       1: iconst_1
       2: anewarray     #32                 // class org/assertj/core/internal/bytebuddy/implementation/MethodCall$ArgumentLoader$Factory
       5: dup
       6: iconst_0
       7: getstatic     #466                // Field org/assertj/core/internal/bytebuddy/implementation/MethodCall$ArgumentLoader$ForInstrumentedType$Factory.INSTANCE:Lorg/assertj/core/internal/bytebuddy/implementation/MethodCall$ArgumentLoader$ForInstrumentedType$Factory;
      10: aastore
      11: invokevirtual #435                // Method with:([Lorg/assertj/core/internal/bytebuddy/implementation/MethodCall$ArgumentLoader$Factory;)Lorg/assertj/core/internal/bytebuddy/implementation/MethodCall;
      14: areturn

  public org.assertj.core.internal.bytebuddy.implementation.MethodCall withField(java.lang.String...);
    Code:
       0: aload_0
       1: getstatic     #471                // Field org/assertj/core/internal/bytebuddy/dynamic/scaffold/FieldLocator$ForClassHierarchy$Factory.INSTANCE:Lorg/assertj/core/internal/bytebuddy/dynamic/scaffold/FieldLocator$ForClassHierarchy$Factory;
       4: aload_1
       5: invokevirtual #474                // Method withField:(Lorg/assertj/core/internal/bytebuddy/dynamic/scaffold/FieldLocator$Factory;[Ljava/lang/String;)Lorg/assertj/core/internal/bytebuddy/implementation/MethodCall;
       8: areturn

  public org.assertj.core.internal.bytebuddy.implementation.MethodCall withField(org.assertj.core.internal.bytebuddy.dynamic.scaffold.FieldLocator$Factory, java.lang.String...);
    Code:
       0: new           #337                // class java/util/ArrayList
       3: dup
       4: aload_2
       5: arraylength
       6: invokespecial #340                // Method java/util/ArrayList."<init>":(I)V
       9: astore_3
      10: aload_2
      11: astore        4
      13: aload         4
      15: arraylength
      16: istore        5
      18: iconst_0
      19: istore        6
      21: iload         6
      23: iload         5
      25: if_icmpge     58
      28: aload         4
      30: iload         6
      32: aaload
      33: astore        7
      35: aload_3
      36: new           #94                 // class org/assertj/core/internal/bytebuddy/implementation/MethodCall$ArgumentLoader$ForField$Factory
      39: dup
      40: aload         7
      42: aload_1
      43: invokespecial #480                // Method org/assertj/core/internal/bytebuddy/implementation/MethodCall$ArgumentLoader$ForField$Factory."<init>":(Ljava/lang/String;Lorg/assertj/core/internal/bytebuddy/dynamic/scaffold/FieldLocator$Factory;)V
      46: invokeinterface #352,  2          // InterfaceMethod java/util/List.add:(Ljava/lang/Object;)Z
      51: pop
      52: iinc          6, 1
      55: goto          21
      58: aload_0
      59: aload_3
      60: invokevirtual #355                // Method with:(Ljava/util/List;)Lorg/assertj/core/internal/bytebuddy/implementation/MethodCall;
      63: areturn

  public org.assertj.core.internal.bytebuddy.implementation.MethodCall with(org.assertj.core.internal.bytebuddy.implementation.bytecode.StackManipulation, java.lang.reflect.Type);
    Code:
       0: aload_0
       1: aload_1
       2: aload_2
       3: invokestatic  #489                // Method org/assertj/core/internal/bytebuddy/description/type/TypeDefinition$Sort.describe:(Ljava/lang/reflect/Type;)Lorg/assertj/core/internal/bytebuddy/description/type/TypeDescription$Generic;
       6: invokevirtual #492                // Method with:(Lorg/assertj/core/internal/bytebuddy/implementation/bytecode/StackManipulation;Lorg/assertj/core/internal/bytebuddy/description/type/TypeDefinition;)Lorg/assertj/core/internal/bytebuddy/implementation/MethodCall;
       9: areturn

  public org.assertj.core.internal.bytebuddy.implementation.MethodCall with(org.assertj.core.internal.bytebuddy.implementation.bytecode.StackManipulation, org.assertj.core.internal.bytebuddy.description.type.TypeDefinition);
    Code:
       0: aload_0
       1: iconst_1
       2: anewarray     #32                 // class org/assertj/core/internal/bytebuddy/implementation/MethodCall$ArgumentLoader$Factory
       5: dup
       6: iconst_0
       7: new           #69                 // class org/assertj/core/internal/bytebuddy/implementation/MethodCall$ArgumentLoader$ForStackManipulation
      10: dup
      11: aload_1
      12: aload_2
      13: invokespecial #390                // Method org/assertj/core/internal/bytebuddy/implementation/MethodCall$ArgumentLoader$ForStackManipulation."<init>":(Lorg/assertj/core/internal/bytebuddy/implementation/bytecode/StackManipulation;Lorg/assertj/core/internal/bytebuddy/description/type/TypeDefinition;)V
      16: aastore
      17: invokevirtual #435                // Method with:([Lorg/assertj/core/internal/bytebuddy/implementation/MethodCall$ArgumentLoader$Factory;)Lorg/assertj/core/internal/bytebuddy/implementation/MethodCall;
      20: areturn

  public org.assertj.core.internal.bytebuddy.implementation.MethodCall with(org.assertj.core.internal.bytebuddy.implementation.MethodCall$ArgumentLoader$Factory...);
    Code:
       0: aload_0
       1: aload_1
       2: invokestatic  #504                // Method java/util/Arrays.asList:([Ljava/lang/Object;)Ljava/util/List;
       5: invokevirtual #355                // Method with:(Ljava/util/List;)Lorg/assertj/core/internal/bytebuddy/implementation/MethodCall;
       8: areturn

  public org.assertj.core.internal.bytebuddy.implementation.MethodCall with(java.util.List<? extends org.assertj.core.internal.bytebuddy.implementation.MethodCall$ArgumentLoader$Factory>);
    Code:
       0: new           #2                  // class org/assertj/core/internal/bytebuddy/implementation/MethodCall
       3: dup
       4: aload_0
       5: getfield      #164                // Field methodLocator:Lorg/assertj/core/internal/bytebuddy/implementation/MethodCall$MethodLocator;
       8: aload_0
       9: getfield      #166                // Field targetHandler:Lorg/assertj/core/internal/bytebuddy/implementation/MethodCall$TargetHandler;
      12: aload_0
      13: getfield      #168                // Field argumentLoaders:Ljava/util/List;
      16: aload_1
      17: invokestatic  #511                // Method org/assertj/core/internal/bytebuddy/utility/CompoundList.of:(Ljava/util/List;Ljava/util/List;)Ljava/util/List;
      20: aload_0
      21: getfield      #170                // Field methodInvoker:Lorg/assertj/core/internal/bytebuddy/implementation/MethodCall$MethodInvoker;
      24: aload_0
      25: getfield      #172                // Field terminationHandler:Lorg/assertj/core/internal/bytebuddy/implementation/MethodCall$TerminationHandler;
      28: aload_0
      29: getfield      #174                // Field assigner:Lorg/assertj/core/internal/bytebuddy/implementation/bytecode/assign/Assigner;
      32: aload_0
      33: getfield      #176                // Field typing:Lorg/assertj/core/internal/bytebuddy/implementation/bytecode/assign/Assigner$Typing;
      36: invokespecial #333                // Method "<init>":(Lorg/assertj/core/internal/bytebuddy/implementation/MethodCall$MethodLocator;Lorg/assertj/core/internal/bytebuddy/implementation/MethodCall$TargetHandler;Ljava/util/List;Lorg/assertj/core/internal/bytebuddy/implementation/MethodCall$MethodInvoker;Lorg/assertj/core/internal/bytebuddy/implementation/MethodCall$TerminationHandler;Lorg/assertj/core/internal/bytebuddy/implementation/bytecode/assign/Assigner;Lorg/assertj/core/internal/bytebuddy/implementation/bytecode/assign/Assigner$Typing;)V
      39: areturn

  public org.assertj.core.internal.bytebuddy.implementation.Implementation$Composable withAssigner(org.assertj.core.internal.bytebuddy.implementation.bytecode.assign.Assigner, org.assertj.core.internal.bytebuddy.implementation.bytecode.assign.Assigner$Typing);
    Code:
       0: new           #2                  // class org/assertj/core/internal/bytebuddy/implementation/MethodCall
       3: dup
       4: aload_0
       5: getfield      #164                // Field methodLocator:Lorg/assertj/core/internal/bytebuddy/implementation/MethodCall$MethodLocator;
       8: aload_0
       9: getfield      #166                // Field targetHandler:Lorg/assertj/core/internal/bytebuddy/implementation/MethodCall$TargetHandler;
      12: aload_0
      13: getfield      #168                // Field argumentLoaders:Ljava/util/List;
      16: aload_0
      17: getfield      #170                // Field methodInvoker:Lorg/assertj/core/internal/bytebuddy/implementation/MethodCall$MethodInvoker;
      20: aload_0
      21: getfield      #172                // Field terminationHandler:Lorg/assertj/core/internal/bytebuddy/implementation/MethodCall$TerminationHandler;
      24: aload_1
      25: aload_2
      26: invokespecial #333                // Method "<init>":(Lorg/assertj/core/internal/bytebuddy/implementation/MethodCall$MethodLocator;Lorg/assertj/core/internal/bytebuddy/implementation/MethodCall$TargetHandler;Ljava/util/List;Lorg/assertj/core/internal/bytebuddy/implementation/MethodCall$MethodInvoker;Lorg/assertj/core/internal/bytebuddy/implementation/MethodCall$TerminationHandler;Lorg/assertj/core/internal/bytebuddy/implementation/bytecode/assign/Assigner;Lorg/assertj/core/internal/bytebuddy/implementation/bytecode/assign/Assigner$Typing;)V
      29: areturn

  public org.assertj.core.internal.bytebuddy.implementation.Implementation andThen(org.assertj.core.internal.bytebuddy.implementation.Implementation);
    Code:
       0: new           #96                 // class org/assertj/core/internal/bytebuddy/implementation/Implementation$Compound
       3: dup
       4: iconst_2
       5: anewarray     #45                 // class org/assertj/core/internal/bytebuddy/implementation/Implementation
       8: dup
       9: iconst_0
      10: new           #2                  // class org/assertj/core/internal/bytebuddy/implementation/MethodCall
      13: dup
      14: aload_0
      15: getfield      #164                // Field methodLocator:Lorg/assertj/core/internal/bytebuddy/implementation/MethodCall$MethodLocator;
      18: aload_0
      19: getfield      #166                // Field targetHandler:Lorg/assertj/core/internal/bytebuddy/implementation/MethodCall$TargetHandler;
      22: aload_0
      23: getfield      #168                // Field argumentLoaders:Ljava/util/List;
      26: aload_0
      27: getfield      #170                // Field methodInvoker:Lorg/assertj/core/internal/bytebuddy/implementation/MethodCall$MethodInvoker;
      30: getstatic     #517                // Field org/assertj/core/internal/bytebuddy/implementation/MethodCall$TerminationHandler.DROPPING:Lorg/assertj/core/internal/bytebuddy/implementation/MethodCall$TerminationHandler;
      33: aload_0
      34: getfield      #174                // Field assigner:Lorg/assertj/core/internal/bytebuddy/implementation/bytecode/assign/Assigner;
      37: aload_0
      38: getfield      #176                // Field typing:Lorg/assertj/core/internal/bytebuddy/implementation/bytecode/assign/Assigner$Typing;
      41: invokespecial #333                // Method "<init>":(Lorg/assertj/core/internal/bytebuddy/implementation/MethodCall$MethodLocator;Lorg/assertj/core/internal/bytebuddy/implementation/MethodCall$TargetHandler;Ljava/util/List;Lorg/assertj/core/internal/bytebuddy/implementation/MethodCall$MethodInvoker;Lorg/assertj/core/internal/bytebuddy/implementation/MethodCall$TerminationHandler;Lorg/assertj/core/internal/bytebuddy/implementation/bytecode/assign/Assigner;Lorg/assertj/core/internal/bytebuddy/implementation/bytecode/assign/Assigner$Typing;)V
      44: aastore
      45: dup
      46: iconst_1
      47: aload_1
      48: aastore
      49: invokespecial #520                // Method org/assertj/core/internal/bytebuddy/implementation/Implementation$Compound."<init>":([Lorg/assertj/core/internal/bytebuddy/implementation/Implementation;)V
      52: areturn

  public org.assertj.core.internal.bytebuddy.dynamic.scaffold.InstrumentedType prepare(org.assertj.core.internal.bytebuddy.dynamic.scaffold.InstrumentedType);
    Code:
       0: aload_0
       1: getfield      #168                // Field argumentLoaders:Ljava/util/List;
       4: invokeinterface #528,  1          // InterfaceMethod java/util/List.iterator:()Ljava/util/Iterator;
       9: astore_2
      10: aload_2
      11: invokeinterface #533,  1          // InterfaceMethod java/util/Iterator.hasNext:()Z
      16: ifeq          40
      19: aload_2
      20: invokeinterface #537,  1          // InterfaceMethod java/util/Iterator.next:()Ljava/lang/Object;
      25: checkcast     #32                 // class org/assertj/core/internal/bytebuddy/implementation/MethodCall$ArgumentLoader$Factory
      28: astore_3
      29: aload_3
      30: aload_1
      31: invokeinterface #539,  2          // InterfaceMethod org/assertj/core/internal/bytebuddy/implementation/MethodCall$ArgumentLoader$Factory.prepare:(Lorg/assertj/core/internal/bytebuddy/dynamic/scaffold/InstrumentedType;)Lorg/assertj/core/internal/bytebuddy/dynamic/scaffold/InstrumentedType;
      36: astore_1
      37: goto          10
      40: aload_0
      41: getfield      #166                // Field targetHandler:Lorg/assertj/core/internal/bytebuddy/implementation/MethodCall$TargetHandler;
      44: aload_1
      45: invokeinterface #540,  2          // InterfaceMethod org/assertj/core/internal/bytebuddy/implementation/MethodCall$TargetHandler.prepare:(Lorg/assertj/core/internal/bytebuddy/dynamic/scaffold/InstrumentedType;)Lorg/assertj/core/internal/bytebuddy/dynamic/scaffold/InstrumentedType;
      50: areturn

  public org.assertj.core.internal.bytebuddy.implementation.bytecode.ByteCodeAppender appender(org.assertj.core.internal.bytebuddy.implementation.Implementation$Target);
    Code:
       0: new           #11                 // class org/assertj/core/internal/bytebuddy/implementation/MethodCall$Appender
       3: dup
       4: aload_0
       5: aload_1
       6: invokespecial #548                // Method org/assertj/core/internal/bytebuddy/implementation/MethodCall$Appender."<init>":(Lorg/assertj/core/internal/bytebuddy/implementation/MethodCall;Lorg/assertj/core/internal/bytebuddy/implementation/Implementation$Target;)V
       9: areturn

  public boolean equals(java.lang.Object);
    Code:
       0: aload_1
       1: aload_0
       2: if_acmpne     7
       5: iconst_1
       6: ireturn
       7: aload_1
       8: instanceof    #2                  // class org/assertj/core/internal/bytebuddy/implementation/MethodCall
      11: ifne          16
      14: iconst_0
      15: ireturn
      16: aload_1
      17: checkcast     #2                  // class org/assertj/core/internal/bytebuddy/implementation/MethodCall
      20: astore_2
      21: aload_2
      22: aload_0
      23: invokevirtual #554                // Method canEqual:(Ljava/lang/Object;)Z
      26: ifne          31
      29: iconst_0
      30: ireturn
      31: aload_0
      32: getfield      #164                // Field methodLocator:Lorg/assertj/core/internal/bytebuddy/implementation/MethodCall$MethodLocator;
      35: astore_3
      36: aload_2
      37: getfield      #164                // Field methodLocator:Lorg/assertj/core/internal/bytebuddy/implementation/MethodCall$MethodLocator;
      40: astore        4
      42: aload_3
      43: ifnonnull     54
      46: aload         4
      48: ifnull        65
      51: goto          63
      54: aload_3
      55: aload         4
      57: invokevirtual #556                // Method java/lang/Object.equals:(Ljava/lang/Object;)Z
      60: ifne          65
      63: iconst_0
      64: ireturn
      65: aload_0
      66: getfield      #166                // Field targetHandler:Lorg/assertj/core/internal/bytebuddy/implementation/MethodCall$TargetHandler;
      69: astore        5
      71: aload_2
      72: getfield      #166                // Field targetHandler:Lorg/assertj/core/internal/bytebuddy/implementation/MethodCall$TargetHandler;
      75: astore        6
      77: aload         5
      79: ifnonnull     90
      82: aload         6
      84: ifnull        102
      87: goto          100
      90: aload         5
      92: aload         6
      94: invokevirtual #556                // Method java/lang/Object.equals:(Ljava/lang/Object;)Z
      97: ifne          102
     100: iconst_0
     101: ireturn
     102: aload_0
     103: getfield      #168                // Field argumentLoaders:Ljava/util/List;
     106: astore        7
     108: aload_2
     109: getfield      #168                // Field argumentLoaders:Ljava/util/List;
     112: astore        8
     114: aload         7
     116: ifnonnull     127
     119: aload         8
     121: ifnull        139
     124: goto          137
     127: aload         7
     129: aload         8
     131: invokevirtual #556                // Method java/lang/Object.equals:(Ljava/lang/Object;)Z
     134: ifne          139
     137: iconst_0
     138: ireturn
     139: aload_0
     140: getfield      #170                // Field methodInvoker:Lorg/assertj/core/internal/bytebuddy/implementation/MethodCall$MethodInvoker;
     143: astore        9
     145: aload_2
     146: getfield      #170                // Field methodInvoker:Lorg/assertj/core/internal/bytebuddy/implementation/MethodCall$MethodInvoker;
     149: astore        10
     151: aload         9
     153: ifnonnull     164
     156: aload         10
     158: ifnull        176
     161: goto          174
     164: aload         9
     166: aload         10
     168: invokevirtual #556                // Method java/lang/Object.equals:(Ljava/lang/Object;)Z
     171: ifne          176
     174: iconst_0
     175: ireturn
     176: aload_0
     177: getfield      #172                // Field terminationHandler:Lorg/assertj/core/internal/bytebuddy/implementation/MethodCall$TerminationHandler;
     180: astore        11
     182: aload_2
     183: getfield      #172                // Field terminationHandler:Lorg/assertj/core/internal/bytebuddy/implementation/MethodCall$TerminationHandler;
     186: astore        12
     188: aload         11
     190: ifnonnull     201
     193: aload         12
     195: ifnull        213
     198: goto          211
     201: aload         11
     203: aload         12
     205: invokevirtual #556                // Method java/lang/Object.equals:(Ljava/lang/Object;)Z
     208: ifne          213
     211: iconst_0
     212: ireturn
     213: aload_0
     214: getfield      #174                // Field assigner:Lorg/assertj/core/internal/bytebuddy/implementation/bytecode/assign/Assigner;
     217: astore        13
     219: aload_2
     220: getfield      #174                // Field assigner:Lorg/assertj/core/internal/bytebuddy/implementation/bytecode/assign/Assigner;
     223: astore        14
     225: aload         13
     227: ifnonnull     238
     230: aload         14
     232: ifnull        250
     235: goto          248
     238: aload         13
     240: aload         14
     242: invokevirtual #556                // Method java/lang/Object.equals:(Ljava/lang/Object;)Z
     245: ifne          250
     248: iconst_0
     249: ireturn
     250: aload_0
     251: getfield      #176                // Field typing:Lorg/assertj/core/internal/bytebuddy/implementation/bytecode/assign/Assigner$Typing;
     254: astore        15
     256: aload_2
     257: getfield      #176                // Field typing:Lorg/assertj/core/internal/bytebuddy/implementation/bytecode/assign/Assigner$Typing;
     260: astore        16
     262: aload         15
     264: ifnonnull     275
     267: aload         16
     269: ifnull        287
     272: goto          285
     275: aload         15
     277: aload         16
     279: invokevirtual #556                // Method java/lang/Object.equals:(Ljava/lang/Object;)Z
     282: ifne          287
     285: iconst_0
     286: ireturn
     287: iconst_1
     288: ireturn

  protected boolean canEqual(java.lang.Object);
    Code:
       0: aload_1
       1: instanceof    #2                  // class org/assertj/core/internal/bytebuddy/implementation/MethodCall
       4: ireturn

  public int hashCode();
    Code:
       0: bipush        59
       2: istore_1
       3: iconst_1
       4: istore_2
       5: aload_0
       6: getfield      #164                // Field methodLocator:Lorg/assertj/core/internal/bytebuddy/implementation/MethodCall$MethodLocator;
       9: astore_3
      10: iload_2
      11: bipush        59
      13: imul
      14: aload_3
      15: ifnonnull     23
      18: bipush        43
      20: goto          27
      23: aload_3
      24: invokevirtual #576                // Method java/lang/Object.hashCode:()I
      27: iadd
      28: istore_2
      29: aload_0
      30: getfield      #166                // Field targetHandler:Lorg/assertj/core/internal/bytebuddy/implementation/MethodCall$TargetHandler;
      33: astore        4
      35: iload_2
      36: bipush        59
      38: imul
      39: aload         4
      41: ifnonnull     49
      44: bipush        43
      46: goto          54
      49: aload         4
      51: invokevirtual #576                // Method java/lang/Object.hashCode:()I
      54: iadd
      55: istore_2
      56: aload_0
      57: getfield      #168                // Field argumentLoaders:Ljava/util/List;
      60: astore        5
      62: iload_2
      63: bipush        59
      65: imul
      66: aload         5
      68: ifnonnull     76
      71: bipush        43
      73: goto          81
      76: aload         5
      78: invokevirtual #576                // Method java/lang/Object.hashCode:()I
      81: iadd
      82: istore_2
      83: aload_0
      84: getfield      #170                // Field methodInvoker:Lorg/assertj/core/internal/bytebuddy/implementation/MethodCall$MethodInvoker;
      87: astore        6
      89: iload_2
      90: bipush        59
      92: imul
      93: aload         6
      95: ifnonnull     103
      98: bipush        43
     100: goto          108
     103: aload         6
     105: invokevirtual #576                // Method java/lang/Object.hashCode:()I
     108: iadd
     109: istore_2
     110: aload_0
     111: getfield      #172                // Field terminationHandler:Lorg/assertj/core/internal/bytebuddy/implementation/MethodCall$TerminationHandler;
     114: astore        7
     116: iload_2
     117: bipush        59
     119: imul
     120: aload         7
     122: ifnonnull     130
     125: bipush        43
     127: goto          135
     130: aload         7
     132: invokevirtual #576                // Method java/lang/Object.hashCode:()I
     135: iadd
     136: istore_2
     137: aload_0
     138: getfield      #174                // Field assigner:Lorg/assertj/core/internal/bytebuddy/implementation/bytecode/assign/Assigner;
     141: astore        8
     143: iload_2
     144: bipush        59
     146: imul
     147: aload         8
     149: ifnonnull     157
     152: bipush        43
     154: goto          162
     157: aload         8
     159: invokevirtual #576                // Method java/lang/Object.hashCode:()I
     162: iadd
     163: istore_2
     164: aload_0
     165: getfield      #176                // Field typing:Lorg/assertj/core/internal/bytebuddy/implementation/bytecode/assign/Assigner$Typing;
     168: astore        9
     170: iload_2
     171: bipush        59
     173: imul
     174: aload         9
     176: ifnonnull     184
     179: bipush        43
     181: goto          189
     184: aload         9
     186: invokevirtual #576                // Method java/lang/Object.hashCode:()I
     189: iadd
     190: istore_2
     191: iload_2
     192: ireturn
}
