Compiled from "ImmutableCommonConfig.java"
public class org.glassfish.jersey.model.internal.ImmutableCommonConfig extends org.glassfish.jersey.model.internal.CommonConfig {
  private final java.lang.String errorMessage;

  public org.glassfish.jersey.model.internal.ImmutableCommonConfig(org.glassfish.jersey.model.internal.CommonConfig, java.lang.String);
    Code:
       0: aload_0
       1: aload_1
       2: invokespecial #1                  // Method org/glassfish/jersey/model/internal/CommonConfig."<init>":(Lorg/glassfish/jersey/model/internal/CommonConfig;)V
       5: aload_0
       6: aload_2
       7: putfield      #2                  // Field errorMessage:Ljava/lang/String;
      10: return

  public org.glassfish.jersey.model.internal.ImmutableCommonConfig(org.glassfish.jersey.model.internal.CommonConfig);
    Code:
       0: aload_0
       1: aload_1
       2: invokestatic  #3                  // Method org/glassfish/jersey/internal/LocalizationMessages.CONFIGURATION_NOT_MODIFIABLE:()Ljava/lang/String;
       5: invokespecial #4                  // Method "<init>":(Lorg/glassfish/jersey/model/internal/CommonConfig;Ljava/lang/String;)V
       8: return

  public org.glassfish.jersey.model.internal.ImmutableCommonConfig property(java.lang.String, java.lang.Object);
    Code:
       0: new           #5                  // class java/lang/IllegalStateException
       3: dup
       4: aload_0
       5: getfield      #2                  // Field errorMessage:Ljava/lang/String;
       8: invokespecial #6                  // Method java/lang/IllegalStateException."<init>":(Ljava/lang/String;)V
      11: athrow

  public org.glassfish.jersey.model.internal.ImmutableCommonConfig setProperties(java.util.Map<java.lang.String, ?>);
    Code:
       0: new           #5                  // class java/lang/IllegalStateException
       3: dup
       4: aload_0
       5: getfield      #2                  // Field errorMessage:Ljava/lang/String;
       8: invokespecial #6                  // Method java/lang/IllegalStateException."<init>":(Ljava/lang/String;)V
      11: athrow

  public org.glassfish.jersey.model.internal.ImmutableCommonConfig register(java.lang.Class<?>);
    Code:
       0: new           #5                  // class java/lang/IllegalStateException
       3: dup
       4: aload_0
       5: getfield      #2                  // Field errorMessage:Ljava/lang/String;
       8: invokespecial #6                  // Method java/lang/IllegalStateException."<init>":(Ljava/lang/String;)V
      11: athrow

  public org.glassfish.jersey.model.internal.ImmutableCommonConfig register(java.lang.Class<?>, int);
    Code:
       0: new           #5                  // class java/lang/IllegalStateException
       3: dup
       4: aload_0
       5: getfield      #2                  // Field errorMessage:Ljava/lang/String;
       8: invokespecial #6                  // Method java/lang/IllegalStateException."<init>":(Ljava/lang/String;)V
      11: athrow

  public org.glassfish.jersey.model.internal.ImmutableCommonConfig register(java.lang.Class<?>, java.lang.Class<?>...);
    Code:
       0: new           #5                  // class java/lang/IllegalStateException
       3: dup
       4: aload_0
       5: getfield      #2                  // Field errorMessage:Ljava/lang/String;
       8: invokespecial #6                  // Method java/lang/IllegalStateException."<init>":(Ljava/lang/String;)V
      11: athrow

  public org.glassfish.jersey.model.internal.CommonConfig register(java.lang.Class<?>, java.util.Map<java.lang.Class<?>, java.lang.Integer>);
    Code:
       0: new           #5                  // class java/lang/IllegalStateException
       3: dup
       4: aload_0
       5: getfield      #2                  // Field errorMessage:Ljava/lang/String;
       8: invokespecial #6                  // Method java/lang/IllegalStateException."<init>":(Ljava/lang/String;)V
      11: athrow

  public org.glassfish.jersey.model.internal.ImmutableCommonConfig register(java.lang.Object);
    Code:
       0: new           #5                  // class java/lang/IllegalStateException
       3: dup
       4: aload_0
       5: getfield      #2                  // Field errorMessage:Ljava/lang/String;
       8: invokespecial #6                  // Method java/lang/IllegalStateException."<init>":(Ljava/lang/String;)V
      11: athrow

  public org.glassfish.jersey.model.internal.ImmutableCommonConfig register(java.lang.Object, int);
    Code:
       0: new           #5                  // class java/lang/IllegalStateException
       3: dup
       4: aload_0
       5: getfield      #2                  // Field errorMessage:Ljava/lang/String;
       8: invokespecial #6                  // Method java/lang/IllegalStateException."<init>":(Ljava/lang/String;)V
      11: athrow

  public org.glassfish.jersey.model.internal.ImmutableCommonConfig register(java.lang.Object, java.lang.Class<?>...);
    Code:
       0: new           #5                  // class java/lang/IllegalStateException
       3: dup
       4: aload_0
       5: getfield      #2                  // Field errorMessage:Ljava/lang/String;
       8: invokespecial #6                  // Method java/lang/IllegalStateException."<init>":(Ljava/lang/String;)V
      11: athrow

  public org.glassfish.jersey.model.internal.CommonConfig register(java.lang.Object, java.util.Map<java.lang.Class<?>, java.lang.Integer>);
    Code:
       0: new           #5                  // class java/lang/IllegalStateException
       3: dup
       4: aload_0
       5: getfield      #2                  // Field errorMessage:Ljava/lang/String;
       8: invokespecial #6                  // Method java/lang/IllegalStateException."<init>":(Ljava/lang/String;)V
      11: athrow

  public org.glassfish.jersey.model.internal.CommonConfig loadFrom(javax.ws.rs.core.Configuration);
    Code:
       0: new           #5                  // class java/lang/IllegalStateException
       3: dup
       4: aload_0
       5: getfield      #2                  // Field errorMessage:Ljava/lang/String;
       8: invokespecial #6                  // Method java/lang/IllegalStateException."<init>":(Ljava/lang/String;)V
      11: athrow

  public org.glassfish.jersey.model.internal.CommonConfig register(java.lang.Object, java.lang.Class[]);
    Code:
       0: aload_0
       1: aload_1
       2: aload_2
       3: invokevirtual #7                  // Method register:(Ljava/lang/Object;[Ljava/lang/Class;)Lorg/glassfish/jersey/model/internal/ImmutableCommonConfig;
       6: areturn

  public org.glassfish.jersey.model.internal.CommonConfig register(java.lang.Object, int);
    Code:
       0: aload_0
       1: aload_1
       2: iload_2
       3: invokevirtual #8                  // Method register:(Ljava/lang/Object;I)Lorg/glassfish/jersey/model/internal/ImmutableCommonConfig;
       6: areturn

  public org.glassfish.jersey.model.internal.CommonConfig register(java.lang.Object);
    Code:
       0: aload_0
       1: aload_1
       2: invokevirtual #9                  // Method register:(Ljava/lang/Object;)Lorg/glassfish/jersey/model/internal/ImmutableCommonConfig;
       5: areturn

  public org.glassfish.jersey.model.internal.CommonConfig register(java.lang.Class, java.lang.Class[]);
    Code:
       0: aload_0
       1: aload_1
       2: aload_2
       3: invokevirtual #10                 // Method register:(Ljava/lang/Class;[Ljava/lang/Class;)Lorg/glassfish/jersey/model/internal/ImmutableCommonConfig;
       6: areturn

  public org.glassfish.jersey.model.internal.CommonConfig register(java.lang.Class, int);
    Code:
       0: aload_0
       1: aload_1
       2: iload_2
       3: invokevirtual #11                 // Method register:(Ljava/lang/Class;I)Lorg/glassfish/jersey/model/internal/ImmutableCommonConfig;
       6: areturn

  public org.glassfish.jersey.model.internal.CommonConfig register(java.lang.Class);
    Code:
       0: aload_0
       1: aload_1
       2: invokevirtual #12                 // Method register:(Ljava/lang/Class;)Lorg/glassfish/jersey/model/internal/ImmutableCommonConfig;
       5: areturn

  public org.glassfish.jersey.model.internal.CommonConfig property(java.lang.String, java.lang.Object);
    Code:
       0: aload_0
       1: aload_1
       2: aload_2
       3: invokevirtual #13                 // Method property:(Ljava/lang/String;Ljava/lang/Object;)Lorg/glassfish/jersey/model/internal/ImmutableCommonConfig;
       6: areturn

  public org.glassfish.jersey.model.internal.CommonConfig setProperties(java.util.Map);
    Code:
       0: aload_0
       1: aload_1
       2: invokevirtual #14                 // Method setProperties:(Ljava/util/Map;)Lorg/glassfish/jersey/model/internal/ImmutableCommonConfig;
       5: areturn

  public javax.ws.rs.core.Configurable register(java.lang.Object, java.util.Map);
    Code:
       0: aload_0
       1: aload_1
       2: aload_2
       3: invokevirtual #15                 // Method register:(Ljava/lang/Object;Ljava/util/Map;)Lorg/glassfish/jersey/model/internal/CommonConfig;
       6: areturn

  public javax.ws.rs.core.Configurable register(java.lang.Object, java.lang.Class[]);
    Code:
       0: aload_0
       1: aload_1
       2: aload_2
       3: invokevirtual #7                  // Method register:(Ljava/lang/Object;[Ljava/lang/Class;)Lorg/glassfish/jersey/model/internal/ImmutableCommonConfig;
       6: areturn

  public javax.ws.rs.core.Configurable register(java.lang.Object, int);
    Code:
       0: aload_0
       1: aload_1
       2: iload_2
       3: invokevirtual #8                  // Method register:(Ljava/lang/Object;I)Lorg/glassfish/jersey/model/internal/ImmutableCommonConfig;
       6: areturn

  public javax.ws.rs.core.Configurable register(java.lang.Object);
    Code:
       0: aload_0
       1: aload_1
       2: invokevirtual #9                  // Method register:(Ljava/lang/Object;)Lorg/glassfish/jersey/model/internal/ImmutableCommonConfig;
       5: areturn

  public javax.ws.rs.core.Configurable register(java.lang.Class, java.util.Map);
    Code:
       0: aload_0
       1: aload_1
       2: aload_2
       3: invokevirtual #16                 // Method register:(Ljava/lang/Class;Ljava/util/Map;)Lorg/glassfish/jersey/model/internal/CommonConfig;
       6: areturn

  public javax.ws.rs.core.Configurable register(java.lang.Class, java.lang.Class[]);
    Code:
       0: aload_0
       1: aload_1
       2: aload_2
       3: invokevirtual #10                 // Method register:(Ljava/lang/Class;[Ljava/lang/Class;)Lorg/glassfish/jersey/model/internal/ImmutableCommonConfig;
       6: areturn

  public javax.ws.rs.core.Configurable register(java.lang.Class, int);
    Code:
       0: aload_0
       1: aload_1
       2: iload_2
       3: invokevirtual #11                 // Method register:(Ljava/lang/Class;I)Lorg/glassfish/jersey/model/internal/ImmutableCommonConfig;
       6: areturn

  public javax.ws.rs.core.Configurable register(java.lang.Class);
    Code:
       0: aload_0
       1: aload_1
       2: invokevirtual #12                 // Method register:(Ljava/lang/Class;)Lorg/glassfish/jersey/model/internal/ImmutableCommonConfig;
       5: areturn

  public javax.ws.rs.core.Configurable property(java.lang.String, java.lang.Object);
    Code:
       0: aload_0
       1: aload_1
       2: aload_2
       3: invokevirtual #13                 // Method property:(Ljava/lang/String;Ljava/lang/Object;)Lorg/glassfish/jersey/model/internal/ImmutableCommonConfig;
       6: areturn
}
