Compiled from "CustomLoadMetricConsumer.java"
public interface org.wildfly.swarm.config.modcluster.mod_cluster_config.dynamic_load_provider.CustomLoadMetricConsumer<T extends org.wildfly.swarm.config.modcluster.mod_cluster_config.dynamic_load_provider.CustomLoadMetric<T>> {
  public abstract void accept(T);

  public default org.wildfly.swarm.config.modcluster.mod_cluster_config.dynamic_load_provider.CustomLoadMetricConsumer<T> andThen(org.wildfly.swarm.config.modcluster.mod_cluster_config.dynamic_load_provider.CustomLoadMetricConsumer<T>);
    Code:
       0: aload_0
       1: aload_1
       2: invokedynamic #1,  0              // InvokeDynamic #0:accept:(Lorg/wildfly/swarm/config/modcluster/mod_cluster_config/dynamic_load_provider/CustomLoadMetricConsumer;Lorg/wildfly/swarm/config/modcluster/mod_cluster_config/dynamic_load_provider/CustomLoadMetricConsumer;)Lorg/wildfly/swarm/config/modcluster/mod_cluster_config/dynamic_load_provider/CustomLoadMetricConsumer;
       7: areturn

  private void lambda$andThen$41(org.wildfly.swarm.config.modcluster.mod_cluster_config.dynamic_load_provider.CustomLoadMetricConsumer, org.wildfly.swarm.config.modcluster.mod_cluster_config.dynamic_load_provider.CustomLoadMetric);
    Code:
       0: aload_0
       1: aload_2
       2: invokeinterface #2,  2            // InterfaceMethod accept:(Lorg/wildfly/swarm/config/modcluster/mod_cluster_config/dynamic_load_provider/CustomLoadMetric;)V
       7: aload_1
       8: aload_2
       9: invokeinterface #2,  2            // InterfaceMethod accept:(Lorg/wildfly/swarm/config/modcluster/mod_cluster_config/dynamic_load_provider/CustomLoadMetric;)V
      14: return
}
