Compiled from "VersionConditions.java"
public abstract class org.sonatype.nexus.client.core.condition.VersionConditions implements org.sonatype.nexus.client.core.Condition {
  private static final org.sonatype.aether.version.VersionConstraint POST_1_8_VERSIONS;

  private static final org.sonatype.aether.version.VersionConstraint POST_1_9_VERSIONS;

  private static final org.sonatype.aether.version.VersionConstraint POST_2_0_VERSIONS;

  private static final org.sonatype.aether.version.VersionConstraint POST_2_1_VERSIONS;

  private static final org.sonatype.aether.version.VersionConstraint POST_2_2_VERSIONS;

  private static final org.sonatype.aether.version.VersionConstraint POST_2_3_VERSIONS;

  public org.sonatype.nexus.client.core.condition.VersionConditions();
    Code:
       0: aload_0
       1: invokespecial #2                  // Method java/lang/Object."<init>":()V
       4: return

  public static org.sonatype.nexus.client.core.Condition anyModernVersion();
    Code:
       0: new           #3                  // class org/sonatype/nexus/client/core/condition/VersionConditions$VersionCondition
       3: dup
       4: getstatic     #4                  // Field POST_1_8_VERSIONS:Lorg/sonatype/aether/version/VersionConstraint;
       7: aconst_null
       8: invokespecial #5                  // Method org/sonatype/nexus/client/core/condition/VersionConditions$VersionCondition."<init>":(Lorg/sonatype/aether/version/VersionConstraint;Lorg/sonatype/nexus/client/core/condition/VersionConditions$1;)V
      11: areturn

  public static org.sonatype.nexus.client.core.Condition any20AndLaterVersion();
    Code:
       0: new           #3                  // class org/sonatype/nexus/client/core/condition/VersionConditions$VersionCondition
       3: dup
       4: getstatic     #6                  // Field POST_1_9_VERSIONS:Lorg/sonatype/aether/version/VersionConstraint;
       7: aconst_null
       8: invokespecial #5                  // Method org/sonatype/nexus/client/core/condition/VersionConditions$VersionCondition."<init>":(Lorg/sonatype/aether/version/VersionConstraint;Lorg/sonatype/nexus/client/core/condition/VersionConditions$1;)V
      11: areturn

  public static org.sonatype.nexus.client.core.Condition any21AndLaterVersion();
    Code:
       0: new           #3                  // class org/sonatype/nexus/client/core/condition/VersionConditions$VersionCondition
       3: dup
       4: getstatic     #7                  // Field POST_2_0_VERSIONS:Lorg/sonatype/aether/version/VersionConstraint;
       7: aconst_null
       8: invokespecial #5                  // Method org/sonatype/nexus/client/core/condition/VersionConditions$VersionCondition."<init>":(Lorg/sonatype/aether/version/VersionConstraint;Lorg/sonatype/nexus/client/core/condition/VersionConditions$1;)V
      11: areturn

  public static org.sonatype.nexus.client.core.Condition any22AndLaterVersion();
    Code:
       0: new           #3                  // class org/sonatype/nexus/client/core/condition/VersionConditions$VersionCondition
       3: dup
       4: getstatic     #8                  // Field POST_2_1_VERSIONS:Lorg/sonatype/aether/version/VersionConstraint;
       7: aconst_null
       8: invokespecial #5                  // Method org/sonatype/nexus/client/core/condition/VersionConditions$VersionCondition."<init>":(Lorg/sonatype/aether/version/VersionConstraint;Lorg/sonatype/nexus/client/core/condition/VersionConditions$1;)V
      11: areturn

  public static org.sonatype.nexus.client.core.Condition any23AndLaterVersion();
    Code:
       0: new           #3                  // class org/sonatype/nexus/client/core/condition/VersionConditions$VersionCondition
       3: dup
       4: getstatic     #9                  // Field POST_2_2_VERSIONS:Lorg/sonatype/aether/version/VersionConstraint;
       7: aconst_null
       8: invokespecial #5                  // Method org/sonatype/nexus/client/core/condition/VersionConditions$VersionCondition."<init>":(Lorg/sonatype/aether/version/VersionConstraint;Lorg/sonatype/nexus/client/core/condition/VersionConditions$1;)V
      11: areturn

  public static org.sonatype.nexus.client.core.Condition any24AndLaterVersion();
    Code:
       0: new           #3                  // class org/sonatype/nexus/client/core/condition/VersionConditions$VersionCondition
       3: dup
       4: getstatic     #10                 // Field POST_2_3_VERSIONS:Lorg/sonatype/aether/version/VersionConstraint;
       7: aconst_null
       8: invokespecial #5                  // Method org/sonatype/nexus/client/core/condition/VersionConditions$VersionCondition."<init>":(Lorg/sonatype/aether/version/VersionConstraint;Lorg/sonatype/nexus/client/core/condition/VersionConditions$1;)V
      11: areturn

  public static org.sonatype.nexus.client.core.Condition withVersion(java.lang.String);
    Code:
       0: new           #3                  // class org/sonatype/nexus/client/core/condition/VersionConditions$VersionCondition
       3: dup
       4: aload_0
       5: invokestatic  #11                 // Method parseVersionConstraint:(Ljava/lang/String;)Lorg/sonatype/aether/version/VersionConstraint;
       8: aconst_null
       9: invokespecial #5                  // Method org/sonatype/nexus/client/core/condition/VersionConditions$VersionCondition."<init>":(Lorg/sonatype/aether/version/VersionConstraint;Lorg/sonatype/nexus/client/core/condition/VersionConditions$1;)V
      12: areturn

  private static org.sonatype.aether.version.VersionConstraint parseVersionConstraint(java.lang.String);
    Code:
       0: new           #12                 // class org/sonatype/aether/util/version/GenericVersionScheme
       3: dup
       4: invokespecial #13                 // Method org/sonatype/aether/util/version/GenericVersionScheme."<init>":()V
       7: aload_0
       8: invokevirtual #14                 // Method org/sonatype/aether/util/version/GenericVersionScheme.parseVersionConstraint:(Ljava/lang/String;)Lorg/sonatype/aether/version/VersionConstraint;
      11: areturn
      12: astore_1
      13: new           #16                 // class java/lang/IllegalArgumentException
      16: dup
      17: new           #17                 // class java/lang/StringBuilder
      20: dup
      21: invokespecial #18                 // Method java/lang/StringBuilder."<init>":()V
      24: ldc           #19                 // String Unable to parse version constraint:
      26: invokevirtual #20                 // Method java/lang/StringBuilder.append:(Ljava/lang/String;)Ljava/lang/StringBuilder;
      29: aload_0
      30: invokevirtual #20                 // Method java/lang/StringBuilder.append:(Ljava/lang/String;)Ljava/lang/StringBuilder;
      33: invokevirtual #21                 // Method java/lang/StringBuilder.toString:()Ljava/lang/String;
      36: aload_1
      37: invokespecial #22                 // Method java/lang/IllegalArgumentException."<init>":(Ljava/lang/String;Ljava/lang/Throwable;)V
      40: athrow
    Exception table:
       from    to  target type
           0    11    12   Class org/sonatype/aether/version/InvalidVersionSpecificationException

  private static org.sonatype.aether.version.Version parseVersion(java.lang.String);
    Code:
       0: new           #12                 // class org/sonatype/aether/util/version/GenericVersionScheme
       3: dup
       4: invokespecial #13                 // Method org/sonatype/aether/util/version/GenericVersionScheme."<init>":()V
       7: aload_0
       8: invokevirtual #23                 // Method org/sonatype/aether/util/version/GenericVersionScheme.parseVersion:(Ljava/lang/String;)Lorg/sonatype/aether/version/Version;
      11: areturn
      12: astore_1
      13: new           #16                 // class java/lang/IllegalArgumentException
      16: dup
      17: new           #17                 // class java/lang/StringBuilder
      20: dup
      21: invokespecial #18                 // Method java/lang/StringBuilder."<init>":()V
      24: ldc           #24                 // String Unable to parse version:
      26: invokevirtual #20                 // Method java/lang/StringBuilder.append:(Ljava/lang/String;)Ljava/lang/StringBuilder;
      29: aload_0
      30: invokevirtual #20                 // Method java/lang/StringBuilder.append:(Ljava/lang/String;)Ljava/lang/StringBuilder;
      33: invokevirtual #21                 // Method java/lang/StringBuilder.toString:()Ljava/lang/String;
      36: aload_1
      37: invokespecial #22                 // Method java/lang/IllegalArgumentException."<init>":(Ljava/lang/String;Ljava/lang/Throwable;)V
      40: athrow
    Exception table:
       from    to  target type
           0    11    12   Class org/sonatype/aether/version/InvalidVersionSpecificationException

  static org.sonatype.aether.version.Version access$100(java.lang.String);
    Code:
       0: aload_0
       1: invokestatic  #1                  // Method parseVersion:(Ljava/lang/String;)Lorg/sonatype/aether/version/Version;
       4: areturn

  static {};
    Code:
       0: ldc           #25                 // String (1.8.99,)
       2: invokestatic  #11                 // Method parseVersionConstraint:(Ljava/lang/String;)Lorg/sonatype/aether/version/VersionConstraint;
       5: putstatic     #4                  // Field POST_1_8_VERSIONS:Lorg/sonatype/aether/version/VersionConstraint;
       8: ldc           #26                 // String (1.9.99,)
      10: invokestatic  #11                 // Method parseVersionConstraint:(Ljava/lang/String;)Lorg/sonatype/aether/version/VersionConstraint;
      13: putstatic     #6                  // Field POST_1_9_VERSIONS:Lorg/sonatype/aether/version/VersionConstraint;
      16: ldc           #27                 // String (2.0.99,)
      18: invokestatic  #11                 // Method parseVersionConstraint:(Ljava/lang/String;)Lorg/sonatype/aether/version/VersionConstraint;
      21: putstatic     #7                  // Field POST_2_0_VERSIONS:Lorg/sonatype/aether/version/VersionConstraint;
      24: ldc           #28                 // String (2.1.99,)
      26: invokestatic  #11                 // Method parseVersionConstraint:(Ljava/lang/String;)Lorg/sonatype/aether/version/VersionConstraint;
      29: putstatic     #8                  // Field POST_2_1_VERSIONS:Lorg/sonatype/aether/version/VersionConstraint;
      32: ldc           #29                 // String (2.2.99,)
      34: invokestatic  #11                 // Method parseVersionConstraint:(Ljava/lang/String;)Lorg/sonatype/aether/version/VersionConstraint;
      37: putstatic     #9                  // Field POST_2_2_VERSIONS:Lorg/sonatype/aether/version/VersionConstraint;
      40: ldc           #30                 // String (2.3.99,)
      42: invokestatic  #11                 // Method parseVersionConstraint:(Ljava/lang/String;)Lorg/sonatype/aether/version/VersionConstraint;
      45: putstatic     #10                 // Field POST_2_3_VERSIONS:Lorg/sonatype/aether/version/VersionConstraint;
      48: return
}
