Compiled from "TransformAccessArrayField.java"
public final class javassist.convert.TransformAccessArrayField extends javassist.convert.Transformer {
  private final java.lang.String methodClassname;

  private final javassist.CodeConverter$ArrayAccessReplacementMethodNames names;

  private javassist.bytecode.analysis.Frame[] frames;

  private int offset;

  public javassist.convert.TransformAccessArrayField(javassist.convert.Transformer, java.lang.String, javassist.CodeConverter$ArrayAccessReplacementMethodNames) throws javassist.NotFoundException;
    Code:
       0: aload_0
       1: aload_1
       2: invokespecial #1                  // Method javassist/convert/Transformer."<init>":(Ljavassist/convert/Transformer;)V
       5: aload_0
       6: aload_2
       7: putfield      #2                  // Field methodClassname:Ljava/lang/String;
      10: aload_0
      11: aload_3
      12: putfield      #3                  // Field names:Ljavassist/CodeConverter$ArrayAccessReplacementMethodNames;
      15: return

  public void initialize(javassist.bytecode.ConstPool, javassist.CtClass, javassist.bytecode.MethodInfo) throws javassist.CannotCompileException;
    Code:
       0: aload_3
       1: invokevirtual #4                  // Method javassist/bytecode/MethodInfo.getCodeAttribute:()Ljavassist/bytecode/CodeAttribute;
       4: invokevirtual #5                  // Method javassist/bytecode/CodeAttribute.iterator:()Ljavassist/bytecode/CodeIterator;
       7: astore        4
       9: aload         4
      11: invokevirtual #6                  // Method javassist/bytecode/CodeIterator.hasNext:()Z
      14: ifeq          214
      17: aload         4
      19: invokevirtual #7                  // Method javassist/bytecode/CodeIterator.next:()I
      22: istore        5
      24: aload         4
      26: iload         5
      28: invokevirtual #8                  // Method javassist/bytecode/CodeIterator.byteAt:(I)I
      31: istore        6
      33: iload         6
      35: bipush        50
      37: if_icmpne     46
      40: aload_0
      41: aload_2
      42: aload_3
      43: invokespecial #10                 // Method initFrames:(Ljavassist/CtClass;Ljavassist/bytecode/MethodInfo;)V
      46: iload         6
      48: bipush        50
      50: if_icmpeq     102
      53: iload         6
      55: bipush        51
      57: if_icmpeq     102
      60: iload         6
      62: bipush        52
      64: if_icmpeq     102
      67: iload         6
      69: bipush        49
      71: if_icmpeq     102
      74: iload         6
      76: bipush        48
      78: if_icmpeq     102
      81: iload         6
      83: bipush        46
      85: if_icmpeq     102
      88: iload         6
      90: bipush        47
      92: if_icmpeq     102
      95: iload         6
      97: bipush        53
      99: if_icmpne     124
     102: aload_0
     103: aload_1
     104: aload         4
     106: iload         5
     108: iload         6
     110: aload_0
     111: iload         6
     113: invokespecial #11                 // Method getLoadReplacementSignature:(I)Ljava/lang/String;
     116: invokespecial #12                 // Method replace:(Ljavassist/bytecode/ConstPool;Ljavassist/bytecode/CodeIterator;IILjava/lang/String;)I
     119: istore        5
     121: goto          199
     124: iload         6
     126: bipush        83
     128: if_icmpeq     180
     131: iload         6
     133: bipush        84
     135: if_icmpeq     180
     138: iload         6
     140: bipush        85
     142: if_icmpeq     180
     145: iload         6
     147: bipush        82
     149: if_icmpeq     180
     152: iload         6
     154: bipush        81
     156: if_icmpeq     180
     159: iload         6
     161: bipush        79
     163: if_icmpeq     180
     166: iload         6
     168: bipush        80
     170: if_icmpeq     180
     173: iload         6
     175: bipush        86
     177: if_icmpne     199
     180: aload_0
     181: aload_1
     182: aload         4
     184: iload         5
     186: iload         6
     188: aload_0
     189: iload         6
     191: invokespecial #13                 // Method getStoreReplacementSignature:(I)Ljava/lang/String;
     194: invokespecial #12                 // Method replace:(Ljavassist/bytecode/ConstPool;Ljavassist/bytecode/CodeIterator;IILjava/lang/String;)I
     197: istore        5
     199: goto          9
     202: astore        5
     204: new           #15                 // class javassist/CannotCompileException
     207: dup
     208: aload         5
     210: invokespecial #16                 // Method javassist/CannotCompileException."<init>":(Ljava/lang/Throwable;)V
     213: athrow
     214: return
    Exception table:
       from    to  target type
          17   199   202   Class java/lang/Exception

  public void clean();
    Code:
       0: aload_0
       1: aconst_null
       2: putfield      #17                 // Field frames:[Ljavassist/bytecode/analysis/Frame;
       5: aload_0
       6: iconst_m1
       7: putfield      #18                 // Field offset:I
      10: return

  public int transform(javassist.CtClass, int, javassist.bytecode.CodeIterator, javassist.bytecode.ConstPool) throws javassist.bytecode.BadBytecode;
    Code:
       0: iload_2
       1: ireturn

  private javassist.bytecode.analysis.Frame getFrame(int) throws javassist.bytecode.BadBytecode;
    Code:
       0: aload_0
       1: getfield      #17                 // Field frames:[Ljavassist/bytecode/analysis/Frame;
       4: iload_1
       5: aload_0
       6: getfield      #18                 // Field offset:I
       9: isub
      10: aaload
      11: areturn

  private void initFrames(javassist.CtClass, javassist.bytecode.MethodInfo) throws javassist.bytecode.BadBytecode;
    Code:
       0: aload_0
       1: getfield      #17                 // Field frames:[Ljavassist/bytecode/analysis/Frame;
       4: ifnonnull     28
       7: aload_0
       8: new           #19                 // class javassist/bytecode/analysis/Analyzer
      11: dup
      12: invokespecial #20                 // Method javassist/bytecode/analysis/Analyzer."<init>":()V
      15: aload_1
      16: aload_2
      17: invokevirtual #21                 // Method javassist/bytecode/analysis/Analyzer.analyze:(Ljavassist/CtClass;Ljavassist/bytecode/MethodInfo;)[Ljavassist/bytecode/analysis/Frame;
      20: putfield      #17                 // Field frames:[Ljavassist/bytecode/analysis/Frame;
      23: aload_0
      24: iconst_0
      25: putfield      #18                 // Field offset:I
      28: return

  private int updatePos(int, int);
    Code:
       0: aload_0
       1: getfield      #18                 // Field offset:I
       4: iconst_m1
       5: if_icmple     18
       8: aload_0
       9: dup
      10: getfield      #18                 // Field offset:I
      13: iload_2
      14: iadd
      15: putfield      #18                 // Field offset:I
      18: iload_1
      19: iload_2
      20: iadd
      21: ireturn

  private java.lang.String getTopType(int) throws javassist.bytecode.BadBytecode;
    Code:
       0: aload_0
       1: iload_1
       2: invokespecial #22                 // Method getFrame:(I)Ljavassist/bytecode/analysis/Frame;
       5: astore_2
       6: aload_2
       7: ifnonnull     12
      10: aconst_null
      11: areturn
      12: aload_2
      13: invokevirtual #23                 // Method javassist/bytecode/analysis/Frame.peek:()Ljavassist/bytecode/analysis/Type;
      16: invokevirtual #24                 // Method javassist/bytecode/analysis/Type.getCtClass:()Ljavassist/CtClass;
      19: astore_3
      20: aload_3
      21: ifnull        31
      24: aload_3
      25: invokestatic  #25                 // Method javassist/bytecode/Descriptor.toJvmName:(Ljavassist/CtClass;)Ljava/lang/String;
      28: goto          32
      31: aconst_null
      32: areturn

  private int replace(javassist.bytecode.ConstPool, javassist.bytecode.CodeIterator, int, int, java.lang.String) throws javassist.bytecode.BadBytecode;
    Code:
       0: aconst_null
       1: astore        6
       3: aload_0
       4: iload         4
       6: invokespecial #26                 // Method getMethodName:(I)Ljava/lang/String;
       9: astore        7
      11: aload         7
      13: ifnull        165
      16: iload         4
      18: bipush        50
      20: if_icmpne     53
      23: aload_0
      24: aload_2
      25: invokevirtual #27                 // Method javassist/bytecode/CodeIterator.lookAhead:()I
      28: invokespecial #28                 // Method getTopType:(I)Ljava/lang/String;
      31: astore        6
      33: aload         6
      35: ifnonnull     40
      38: iload_3
      39: ireturn
      40: ldc           #29                 // String java/lang/Object
      42: aload         6
      44: invokevirtual #30                 // Method java/lang/String.equals:(Ljava/lang/Object;)Z
      47: ifeq          53
      50: aconst_null
      51: astore        6
      53: aload_2
      54: iconst_0
      55: iload_3
      56: invokevirtual #31                 // Method javassist/bytecode/CodeIterator.writeByte:(II)V
      59: aload_2
      60: iload_3
      61: aload         6
      63: ifnull        70
      66: iconst_5
      67: goto          71
      70: iconst_2
      71: iconst_0
      72: invokevirtual #32                 // Method javassist/bytecode/CodeIterator.insertGapAt:(IIZ)Ljavassist/bytecode/CodeIterator$Gap;
      75: astore        8
      77: aload         8
      79: getfield      #33                 // Field javassist/bytecode/CodeIterator$Gap.position:I
      82: istore_3
      83: aload_1
      84: aload_0
      85: getfield      #2                  // Field methodClassname:Ljava/lang/String;
      88: invokevirtual #34                 // Method javassist/bytecode/ConstPool.addClassInfo:(Ljava/lang/String;)I
      91: istore        9
      93: aload_1
      94: iload         9
      96: aload         7
      98: aload         5
     100: invokevirtual #35                 // Method javassist/bytecode/ConstPool.addMethodrefInfo:(ILjava/lang/String;Ljava/lang/String;)I
     103: istore        10
     105: aload_2
     106: sipush        184
     109: iload_3
     110: invokevirtual #31                 // Method javassist/bytecode/CodeIterator.writeByte:(II)V
     113: aload_2
     114: iload         10
     116: iload_3
     117: iconst_1
     118: iadd
     119: invokevirtual #36                 // Method javassist/bytecode/CodeIterator.write16bit:(II)V
     122: aload         6
     124: ifnull        154
     127: aload_1
     128: aload         6
     130: invokevirtual #34                 // Method javassist/bytecode/ConstPool.addClassInfo:(Ljava/lang/String;)I
     133: istore        11
     135: aload_2
     136: sipush        192
     139: iload_3
     140: iconst_3
     141: iadd
     142: invokevirtual #31                 // Method javassist/bytecode/CodeIterator.writeByte:(II)V
     145: aload_2
     146: iload         11
     148: iload_3
     149: iconst_4
     150: iadd
     151: invokevirtual #36                 // Method javassist/bytecode/CodeIterator.write16bit:(II)V
     154: aload_0
     155: iload_3
     156: aload         8
     158: getfield      #37                 // Field javassist/bytecode/CodeIterator$Gap.length:I
     161: invokespecial #38                 // Method updatePos:(II)I
     164: istore_3
     165: iload_3
     166: ireturn

  private java.lang.String getMethodName(int);
    Code:
       0: aconst_null
       1: astore_2
       2: iload_1
       3: tableswitch   { // 46 to 86
                    46: 245
                    47: 271
                    48: 232
                    49: 219
                    50: 180
                    51: 193
                    52: 206
                    53: 258
                    54: 385
                    55: 385
                    56: 385
                    57: 385
                    58: 385
                    59: 385
                    60: 385
                    61: 385
                    62: 385
                    63: 385
                    64: 385
                    65: 385
                    66: 385
                    67: 385
                    68: 385
                    69: 385
                    70: 385
                    71: 385
                    72: 385
                    73: 385
                    74: 385
                    75: 385
                    76: 385
                    77: 385
                    78: 385
                    79: 349
                    80: 375
                    81: 336
                    82: 323
                    83: 284
                    84: 297
                    85: 310
                    86: 362
               default: 385
          }
     180: aload_0
     181: getfield      #3                  // Field names:Ljavassist/CodeConverter$ArrayAccessReplacementMethodNames;
     184: invokeinterface #39,  1           // InterfaceMethod javassist/CodeConverter$ArrayAccessReplacementMethodNames.objectRead:()Ljava/lang/String;
     189: astore_2
     190: goto          385
     193: aload_0
     194: getfield      #3                  // Field names:Ljavassist/CodeConverter$ArrayAccessReplacementMethodNames;
     197: invokeinterface #40,  1           // InterfaceMethod javassist/CodeConverter$ArrayAccessReplacementMethodNames.byteOrBooleanRead:()Ljava/lang/String;
     202: astore_2
     203: goto          385
     206: aload_0
     207: getfield      #3                  // Field names:Ljavassist/CodeConverter$ArrayAccessReplacementMethodNames;
     210: invokeinterface #41,  1           // InterfaceMethod javassist/CodeConverter$ArrayAccessReplacementMethodNames.charRead:()Ljava/lang/String;
     215: astore_2
     216: goto          385
     219: aload_0
     220: getfield      #3                  // Field names:Ljavassist/CodeConverter$ArrayAccessReplacementMethodNames;
     223: invokeinterface #42,  1           // InterfaceMethod javassist/CodeConverter$ArrayAccessReplacementMethodNames.doubleRead:()Ljava/lang/String;
     228: astore_2
     229: goto          385
     232: aload_0
     233: getfield      #3                  // Field names:Ljavassist/CodeConverter$ArrayAccessReplacementMethodNames;
     236: invokeinterface #43,  1           // InterfaceMethod javassist/CodeConverter$ArrayAccessReplacementMethodNames.floatRead:()Ljava/lang/String;
     241: astore_2
     242: goto          385
     245: aload_0
     246: getfield      #3                  // Field names:Ljavassist/CodeConverter$ArrayAccessReplacementMethodNames;
     249: invokeinterface #44,  1           // InterfaceMethod javassist/CodeConverter$ArrayAccessReplacementMethodNames.intRead:()Ljava/lang/String;
     254: astore_2
     255: goto          385
     258: aload_0
     259: getfield      #3                  // Field names:Ljavassist/CodeConverter$ArrayAccessReplacementMethodNames;
     262: invokeinterface #45,  1           // InterfaceMethod javassist/CodeConverter$ArrayAccessReplacementMethodNames.shortRead:()Ljava/lang/String;
     267: astore_2
     268: goto          385
     271: aload_0
     272: getfield      #3                  // Field names:Ljavassist/CodeConverter$ArrayAccessReplacementMethodNames;
     275: invokeinterface #46,  1           // InterfaceMethod javassist/CodeConverter$ArrayAccessReplacementMethodNames.longRead:()Ljava/lang/String;
     280: astore_2
     281: goto          385
     284: aload_0
     285: getfield      #3                  // Field names:Ljavassist/CodeConverter$ArrayAccessReplacementMethodNames;
     288: invokeinterface #47,  1           // InterfaceMethod javassist/CodeConverter$ArrayAccessReplacementMethodNames.objectWrite:()Ljava/lang/String;
     293: astore_2
     294: goto          385
     297: aload_0
     298: getfield      #3                  // Field names:Ljavassist/CodeConverter$ArrayAccessReplacementMethodNames;
     301: invokeinterface #48,  1           // InterfaceMethod javassist/CodeConverter$ArrayAccessReplacementMethodNames.byteOrBooleanWrite:()Ljava/lang/String;
     306: astore_2
     307: goto          385
     310: aload_0
     311: getfield      #3                  // Field names:Ljavassist/CodeConverter$ArrayAccessReplacementMethodNames;
     314: invokeinterface #49,  1           // InterfaceMethod javassist/CodeConverter$ArrayAccessReplacementMethodNames.charWrite:()Ljava/lang/String;
     319: astore_2
     320: goto          385
     323: aload_0
     324: getfield      #3                  // Field names:Ljavassist/CodeConverter$ArrayAccessReplacementMethodNames;
     327: invokeinterface #50,  1           // InterfaceMethod javassist/CodeConverter$ArrayAccessReplacementMethodNames.doubleWrite:()Ljava/lang/String;
     332: astore_2
     333: goto          385
     336: aload_0
     337: getfield      #3                  // Field names:Ljavassist/CodeConverter$ArrayAccessReplacementMethodNames;
     340: invokeinterface #51,  1           // InterfaceMethod javassist/CodeConverter$ArrayAccessReplacementMethodNames.floatWrite:()Ljava/lang/String;
     345: astore_2
     346: goto          385
     349: aload_0
     350: getfield      #3                  // Field names:Ljavassist/CodeConverter$ArrayAccessReplacementMethodNames;
     353: invokeinterface #52,  1           // InterfaceMethod javassist/CodeConverter$ArrayAccessReplacementMethodNames.intWrite:()Ljava/lang/String;
     358: astore_2
     359: goto          385
     362: aload_0
     363: getfield      #3                  // Field names:Ljavassist/CodeConverter$ArrayAccessReplacementMethodNames;
     366: invokeinterface #53,  1           // InterfaceMethod javassist/CodeConverter$ArrayAccessReplacementMethodNames.shortWrite:()Ljava/lang/String;
     371: astore_2
     372: goto          385
     375: aload_0
     376: getfield      #3                  // Field names:Ljavassist/CodeConverter$ArrayAccessReplacementMethodNames;
     379: invokeinterface #54,  1           // InterfaceMethod javassist/CodeConverter$ArrayAccessReplacementMethodNames.longWrite:()Ljava/lang/String;
     384: astore_2
     385: aload_2
     386: ldc           #55                 // String
     388: invokevirtual #30                 // Method java/lang/String.equals:(Ljava/lang/Object;)Z
     391: ifeq          396
     394: aconst_null
     395: astore_2
     396: aload_2
     397: areturn

  private java.lang.String getLoadReplacementSignature(int) throws javassist.bytecode.BadBytecode;
    Code:
       0: iload_1
       1: tableswitch   { // 46 to 53
                    46: 63
                    47: 69
                    48: 60
                    49: 57
                    50: 48
                    51: 51
                    52: 54
                    53: 66
               default: 72
          }
      48: ldc           #56                 // String (Ljava/lang/Object;I)Ljava/lang/Object;
      50: areturn
      51: ldc           #57                 // String (Ljava/lang/Object;I)B
      53: areturn
      54: ldc           #58                 // String (Ljava/lang/Object;I)C
      56: areturn
      57: ldc           #59                 // String (Ljava/lang/Object;I)D
      59: areturn
      60: ldc           #60                 // String (Ljava/lang/Object;I)F
      62: areturn
      63: ldc           #61                 // String (Ljava/lang/Object;I)I
      65: areturn
      66: ldc           #62                 // String (Ljava/lang/Object;I)S
      68: areturn
      69: ldc           #63                 // String (Ljava/lang/Object;I)J
      71: areturn
      72: new           #64                 // class javassist/bytecode/BadBytecode
      75: dup
      76: iload_1
      77: invokespecial #65                 // Method javassist/bytecode/BadBytecode."<init>":(I)V
      80: athrow

  private java.lang.String getStoreReplacementSignature(int) throws javassist.bytecode.BadBytecode;
    Code:
       0: iload_1
       1: tableswitch   { // 79 to 86
                    79: 63
                    80: 69
                    81: 60
                    82: 57
                    83: 48
                    84: 51
                    85: 54
                    86: 66
               default: 72
          }
      48: ldc           #66                 // String (Ljava/lang/Object;ILjava/lang/Object;)V
      50: areturn
      51: ldc           #67                 // String (Ljava/lang/Object;IB)V
      53: areturn
      54: ldc           #68                 // String (Ljava/lang/Object;IC)V
      56: areturn
      57: ldc           #69                 // String (Ljava/lang/Object;ID)V
      59: areturn
      60: ldc           #70                 // String (Ljava/lang/Object;IF)V
      62: areturn
      63: ldc           #71                 // String (Ljava/lang/Object;II)V
      65: areturn
      66: ldc           #72                 // String (Ljava/lang/Object;IS)V
      68: areturn
      69: ldc           #73                 // String (Ljava/lang/Object;IJ)V
      71: areturn
      72: new           #64                 // class javassist/bytecode/BadBytecode
      75: dup
      76: iload_1
      77: invokespecial #65                 // Method javassist/bytecode/BadBytecode."<init>":(I)V
      80: athrow
}
