Compiled from "ASN1OctetString.java"
public abstract class org.apache.commons.ssl.asn1.ASN1OctetString extends org.apache.commons.ssl.asn1.ASN1Object implements org.apache.commons.ssl.asn1.ASN1OctetStringParser {
  byte[] string;

  public static org.apache.commons.ssl.asn1.ASN1OctetString getInstance(org.apache.commons.ssl.asn1.ASN1TaggedObject, boolean);
    Code:
       0: aload_0
       1: invokevirtual #1                  // Method org/apache/commons/ssl/asn1/ASN1TaggedObject.getObject:()Lorg/apache/commons/ssl/asn1/DERObject;
       4: invokestatic  #2                  // Method getInstance:(Ljava/lang/Object;)Lorg/apache/commons/ssl/asn1/ASN1OctetString;
       7: areturn

  public static org.apache.commons.ssl.asn1.ASN1OctetString getInstance(java.lang.Object);
    Code:
       0: aload_0
       1: ifnull        11
       4: aload_0
       5: instanceof    #3                  // class org/apache/commons/ssl/asn1/ASN1OctetString
       8: ifeq          16
      11: aload_0
      12: checkcast     #3                  // class org/apache/commons/ssl/asn1/ASN1OctetString
      15: areturn
      16: aload_0
      17: instanceof    #4                  // class org/apache/commons/ssl/asn1/ASN1TaggedObject
      20: ifeq          34
      23: aload_0
      24: checkcast     #4                  // class org/apache/commons/ssl/asn1/ASN1TaggedObject
      27: invokevirtual #1                  // Method org/apache/commons/ssl/asn1/ASN1TaggedObject.getObject:()Lorg/apache/commons/ssl/asn1/DERObject;
      30: invokestatic  #2                  // Method getInstance:(Ljava/lang/Object;)Lorg/apache/commons/ssl/asn1/ASN1OctetString;
      33: areturn
      34: aload_0
      35: instanceof    #5                  // class org/apache/commons/ssl/asn1/ASN1Sequence
      38: ifeq          88
      41: new           #6                  // class java/util/Vector
      44: dup
      45: invokespecial #7                  // Method java/util/Vector."<init>":()V
      48: astore_1
      49: aload_0
      50: checkcast     #5                  // class org/apache/commons/ssl/asn1/ASN1Sequence
      53: invokevirtual #8                  // Method org/apache/commons/ssl/asn1/ASN1Sequence.getObjects:()Ljava/util/Enumeration;
      56: astore_2
      57: aload_2
      58: invokeinterface #9,  1            // InterfaceMethod java/util/Enumeration.hasMoreElements:()Z
      63: ifeq          79
      66: aload_1
      67: aload_2
      68: invokeinterface #10,  1           // InterfaceMethod java/util/Enumeration.nextElement:()Ljava/lang/Object;
      73: invokevirtual #11                 // Method java/util/Vector.addElement:(Ljava/lang/Object;)V
      76: goto          57
      79: new           #12                 // class org/apache/commons/ssl/asn1/BERConstructedOctetString
      82: dup
      83: aload_1
      84: invokespecial #13                 // Method org/apache/commons/ssl/asn1/BERConstructedOctetString."<init>":(Ljava/util/Vector;)V
      87: areturn
      88: new           #14                 // class java/lang/IllegalArgumentException
      91: dup
      92: new           #15                 // class java/lang/StringBuffer
      95: dup
      96: invokespecial #16                 // Method java/lang/StringBuffer."<init>":()V
      99: ldc           #17                 // String illegal object in getInstance:
     101: invokevirtual #18                 // Method java/lang/StringBuffer.append:(Ljava/lang/String;)Ljava/lang/StringBuffer;
     104: aload_0
     105: invokevirtual #19                 // Method java/lang/Object.getClass:()Ljava/lang/Class;
     108: invokevirtual #20                 // Method java/lang/Class.getName:()Ljava/lang/String;
     111: invokevirtual #18                 // Method java/lang/StringBuffer.append:(Ljava/lang/String;)Ljava/lang/StringBuffer;
     114: invokevirtual #21                 // Method java/lang/StringBuffer.toString:()Ljava/lang/String;
     117: invokespecial #22                 // Method java/lang/IllegalArgumentException."<init>":(Ljava/lang/String;)V
     120: athrow

  public org.apache.commons.ssl.asn1.ASN1OctetString(byte[]);
    Code:
       0: aload_0
       1: invokespecial #23                 // Method org/apache/commons/ssl/asn1/ASN1Object."<init>":()V
       4: aload_0
       5: aload_1
       6: putfield      #24                 // Field string:[B
       9: return

  public org.apache.commons.ssl.asn1.ASN1OctetString(org.apache.commons.ssl.asn1.DEREncodable);
    Code:
       0: aload_0
       1: invokespecial #23                 // Method org/apache/commons/ssl/asn1/ASN1Object."<init>":()V
       4: new           #25                 // class java/io/ByteArrayOutputStream
       7: dup
       8: invokespecial #26                 // Method java/io/ByteArrayOutputStream."<init>":()V
      11: astore_2
      12: new           #27                 // class org/apache/commons/ssl/asn1/DEROutputStream
      15: dup
      16: aload_2
      17: invokespecial #28                 // Method org/apache/commons/ssl/asn1/DEROutputStream."<init>":(Ljava/io/OutputStream;)V
      20: astore_3
      21: aload_3
      22: aload_1
      23: invokevirtual #29                 // Method org/apache/commons/ssl/asn1/DEROutputStream.writeObject:(Ljava/lang/Object;)V
      26: aload_3
      27: invokevirtual #30                 // Method java/io/FilterOutputStream.close:()V
      30: aload_0
      31: aload_2
      32: invokevirtual #31                 // Method java/io/ByteArrayOutputStream.toByteArray:()[B
      35: putfield      #24                 // Field string:[B
      38: goto          72
      41: astore_2
      42: new           #14                 // class java/lang/IllegalArgumentException
      45: dup
      46: new           #15                 // class java/lang/StringBuffer
      49: dup
      50: invokespecial #16                 // Method java/lang/StringBuffer."<init>":()V
      53: ldc           #33                 // String Error processing object :
      55: invokevirtual #18                 // Method java/lang/StringBuffer.append:(Ljava/lang/String;)Ljava/lang/StringBuffer;
      58: aload_2
      59: invokevirtual #34                 // Method java/lang/Throwable.toString:()Ljava/lang/String;
      62: invokevirtual #18                 // Method java/lang/StringBuffer.append:(Ljava/lang/String;)Ljava/lang/StringBuffer;
      65: invokevirtual #21                 // Method java/lang/StringBuffer.toString:()Ljava/lang/String;
      68: invokespecial #22                 // Method java/lang/IllegalArgumentException."<init>":(Ljava/lang/String;)V
      71: athrow
      72: return
    Exception table:
       from    to  target type
           4    38    41   Class java/io/IOException

  public java.io.InputStream getOctetStream();
    Code:
       0: new           #35                 // class java/io/ByteArrayInputStream
       3: dup
       4: aload_0
       5: getfield      #24                 // Field string:[B
       8: invokespecial #36                 // Method java/io/ByteArrayInputStream."<init>":([B)V
      11: areturn

  public org.apache.commons.ssl.asn1.ASN1OctetStringParser parser();
    Code:
       0: aload_0
       1: areturn

  public byte[] getOctets();
    Code:
       0: aload_0
       1: getfield      #24                 // Field string:[B
       4: areturn

  public int hashCode();
    Code:
       0: aload_0
       1: invokevirtual #37                 // Method getOctets:()[B
       4: astore_1
       5: iconst_0
       6: istore_2
       7: iconst_0
       8: istore_3
       9: iload_3
      10: aload_1
      11: arraylength
      12: if_icmpeq     35
      15: iload_2
      16: aload_1
      17: iload_3
      18: baload
      19: sipush        255
      22: iand
      23: iload_3
      24: iconst_4
      25: irem
      26: ishl
      27: ixor
      28: istore_2
      29: iinc          3, 1
      32: goto          9
      35: iload_2
      36: ireturn

  boolean asn1Equals(org.apache.commons.ssl.asn1.DERObject);
    Code:
       0: aload_1
       1: instanceof    #3                  // class org/apache/commons/ssl/asn1/ASN1OctetString
       4: ifne          9
       7: iconst_0
       8: ireturn
       9: aload_1
      10: checkcast     #3                  // class org/apache/commons/ssl/asn1/ASN1OctetString
      13: astore_2
      14: aload_2
      15: getfield      #24                 // Field string:[B
      18: astore_3
      19: aload_0
      20: getfield      #24                 // Field string:[B
      23: astore        4
      25: aload_3
      26: arraylength
      27: aload         4
      29: arraylength
      30: if_icmpeq     35
      33: iconst_0
      34: ireturn
      35: iconst_0
      36: istore        5
      38: iload         5
      40: aload_3
      41: arraylength
      42: if_icmpeq     65
      45: aload_3
      46: iload         5
      48: baload
      49: aload         4
      51: iload         5
      53: baload
      54: if_icmpeq     59
      57: iconst_0
      58: ireturn
      59: iinc          5, 1
      62: goto          38
      65: iconst_1
      66: ireturn

  abstract void encode(org.apache.commons.ssl.asn1.DEROutputStream) throws java.io.IOException;

  public java.lang.String toString();
    Code:
       0: new           #15                 // class java/lang/StringBuffer
       3: dup
       4: invokespecial #16                 // Method java/lang/StringBuffer."<init>":()V
       7: ldc           #38                 // String #
       9: invokevirtual #18                 // Method java/lang/StringBuffer.append:(Ljava/lang/String;)Ljava/lang/StringBuffer;
      12: aload_0
      13: getfield      #24                 // Field string:[B
      16: invokestatic  #39                 // Method org/apache/commons/ssl/util/Hex.encode:([B)Ljava/lang/String;
      19: invokevirtual #18                 // Method java/lang/StringBuffer.append:(Ljava/lang/String;)Ljava/lang/StringBuffer;
      22: invokevirtual #21                 // Method java/lang/StringBuffer.toString:()Ljava/lang/String;
      25: areturn
}
