Compiled from "BERSequenceGenerator.java"
public class org.apache.commons.ssl.asn1.BERSequenceGenerator extends org.apache.commons.ssl.asn1.BERGenerator {
  public org.apache.commons.ssl.asn1.BERSequenceGenerator(java.io.OutputStream) throws java.io.IOException;
    Code:
       0: aload_0
       1: aload_1
       2: invokespecial #1                  // Method org/apache/commons/ssl/asn1/BERGenerator."<init>":(Ljava/io/OutputStream;)V
       5: aload_0
       6: bipush        48
       8: invokevirtual #2                  // Method org/apache/commons/ssl/asn1/BERGenerator.writeBERHeader:(I)V
      11: return

  public org.apache.commons.ssl.asn1.BERSequenceGenerator(java.io.OutputStream, int, boolean) throws java.io.IOException;
    Code:
       0: aload_0
       1: aload_1
       2: iload_2
       3: iload_3
       4: invokespecial #3                  // Method org/apache/commons/ssl/asn1/BERGenerator."<init>":(Ljava/io/OutputStream;IZ)V
       7: aload_0
       8: bipush        48
      10: invokevirtual #2                  // Method org/apache/commons/ssl/asn1/BERGenerator.writeBERHeader:(I)V
      13: return

  public void addObject(org.apache.commons.ssl.asn1.DEREncodable) throws java.io.IOException;
    Code:
       0: aload_1
       1: invokeinterface #4,  1            // InterfaceMethod org/apache/commons/ssl/asn1/DEREncodable.getDERObject:()Lorg/apache/commons/ssl/asn1/DERObject;
       6: new           #5                  // class org/apache/commons/ssl/asn1/DEROutputStream
       9: dup
      10: aload_0
      11: getfield      #6                  // Field org/apache/commons/ssl/asn1/ASN1Generator._out:Ljava/io/OutputStream;
      14: invokespecial #7                  // Method org/apache/commons/ssl/asn1/DEROutputStream."<init>":(Ljava/io/OutputStream;)V
      17: invokevirtual #8                  // Method org/apache/commons/ssl/asn1/DERObject.encode:(Lorg/apache/commons/ssl/asn1/DEROutputStream;)V
      20: return

  public void close() throws java.io.IOException;
    Code:
       0: aload_0
       1: invokevirtual #9                  // Method org/apache/commons/ssl/asn1/BERGenerator.writeBEREnd:()V
       4: return
}
