Compiled from "DERBMPString.java"
public class org.apache.commons.ssl.asn1.DERBMPString extends org.apache.commons.ssl.asn1.ASN1Object implements org.apache.commons.ssl.asn1.DERString {
  java.lang.String string;

  public static org.apache.commons.ssl.asn1.DERBMPString getInstance(java.lang.Object);
    Code:
       0: aload_0
       1: ifnull        11
       4: aload_0
       5: instanceof    #1                  // class org/apache/commons/ssl/asn1/DERBMPString
       8: ifeq          16
      11: aload_0
      12: checkcast     #1                  // class org/apache/commons/ssl/asn1/DERBMPString
      15: areturn
      16: aload_0
      17: instanceof    #2                  // class org/apache/commons/ssl/asn1/ASN1OctetString
      20: ifeq          38
      23: new           #1                  // class org/apache/commons/ssl/asn1/DERBMPString
      26: dup
      27: aload_0
      28: checkcast     #2                  // class org/apache/commons/ssl/asn1/ASN1OctetString
      31: invokevirtual #3                  // Method org/apache/commons/ssl/asn1/ASN1OctetString.getOctets:()[B
      34: invokespecial #4                  // Method "<init>":([B)V
      37: areturn
      38: aload_0
      39: instanceof    #5                  // class org/apache/commons/ssl/asn1/ASN1TaggedObject
      42: ifeq          56
      45: aload_0
      46: checkcast     #5                  // class org/apache/commons/ssl/asn1/ASN1TaggedObject
      49: invokevirtual #6                  // Method org/apache/commons/ssl/asn1/ASN1TaggedObject.getObject:()Lorg/apache/commons/ssl/asn1/DERObject;
      52: invokestatic  #7                  // Method getInstance:(Ljava/lang/Object;)Lorg/apache/commons/ssl/asn1/DERBMPString;
      55: areturn
      56: new           #8                  // class java/lang/IllegalArgumentException
      59: dup
      60: new           #9                  // class java/lang/StringBuffer
      63: dup
      64: invokespecial #10                 // Method java/lang/StringBuffer."<init>":()V
      67: ldc           #11                 // String illegal object in getInstance:
      69: invokevirtual #12                 // Method java/lang/StringBuffer.append:(Ljava/lang/String;)Ljava/lang/StringBuffer;
      72: aload_0
      73: invokevirtual #13                 // Method java/lang/Object.getClass:()Ljava/lang/Class;
      76: invokevirtual #14                 // Method java/lang/Class.getName:()Ljava/lang/String;
      79: invokevirtual #12                 // Method java/lang/StringBuffer.append:(Ljava/lang/String;)Ljava/lang/StringBuffer;
      82: invokevirtual #15                 // Method java/lang/StringBuffer.toString:()Ljava/lang/String;
      85: invokespecial #16                 // Method java/lang/IllegalArgumentException."<init>":(Ljava/lang/String;)V
      88: athrow

  public static org.apache.commons.ssl.asn1.DERBMPString getInstance(org.apache.commons.ssl.asn1.ASN1TaggedObject, boolean);
    Code:
       0: aload_0
       1: invokevirtual #6                  // Method org/apache/commons/ssl/asn1/ASN1TaggedObject.getObject:()Lorg/apache/commons/ssl/asn1/DERObject;
       4: invokestatic  #7                  // Method getInstance:(Ljava/lang/Object;)Lorg/apache/commons/ssl/asn1/DERBMPString;
       7: areturn

  public org.apache.commons.ssl.asn1.DERBMPString(byte[]);
    Code:
       0: aload_0
       1: invokespecial #17                 // Method org/apache/commons/ssl/asn1/ASN1Object."<init>":()V
       4: aload_1
       5: arraylength
       6: iconst_2
       7: idiv
       8: newarray       char
      10: astore_2
      11: iconst_0
      12: istore_3
      13: iload_3
      14: aload_2
      15: arraylength
      16: if_icmpeq     49
      19: aload_2
      20: iload_3
      21: aload_1
      22: iconst_2
      23: iload_3
      24: imul
      25: baload
      26: bipush        8
      28: ishl
      29: aload_1
      30: iconst_2
      31: iload_3
      32: imul
      33: iconst_1
      34: iadd
      35: baload
      36: sipush        255
      39: iand
      40: ior
      41: i2c
      42: castore
      43: iinc          3, 1
      46: goto          13
      49: aload_0
      50: new           #18                 // class java/lang/String
      53: dup
      54: aload_2
      55: invokespecial #19                 // Method java/lang/String."<init>":([C)V
      58: putfield      #20                 // Field string:Ljava/lang/String;
      61: return

  public org.apache.commons.ssl.asn1.DERBMPString(java.lang.String);
    Code:
       0: aload_0
       1: invokespecial #17                 // Method org/apache/commons/ssl/asn1/ASN1Object."<init>":()V
       4: aload_0
       5: aload_1
       6: putfield      #20                 // Field string:Ljava/lang/String;
       9: return

  public java.lang.String getString();
    Code:
       0: aload_0
       1: getfield      #20                 // Field string:Ljava/lang/String;
       4: areturn

  public java.lang.String toString();
    Code:
       0: aload_0
       1: getfield      #20                 // Field string:Ljava/lang/String;
       4: areturn

  public int hashCode();
    Code:
       0: aload_0
       1: invokevirtual #21                 // Method getString:()Ljava/lang/String;
       4: invokevirtual #22                 // Method java/lang/String.hashCode:()I
       7: ireturn

  protected boolean asn1Equals(org.apache.commons.ssl.asn1.DERObject);
    Code:
       0: aload_1
       1: instanceof    #1                  // class org/apache/commons/ssl/asn1/DERBMPString
       4: ifne          9
       7: iconst_0
       8: ireturn
       9: aload_1
      10: checkcast     #1                  // class org/apache/commons/ssl/asn1/DERBMPString
      13: astore_2
      14: aload_0
      15: invokevirtual #21                 // Method getString:()Ljava/lang/String;
      18: aload_2
      19: invokevirtual #21                 // Method getString:()Ljava/lang/String;
      22: invokevirtual #23                 // Method java/lang/String.equals:(Ljava/lang/Object;)Z
      25: ireturn

  void encode(org.apache.commons.ssl.asn1.DEROutputStream) throws java.io.IOException;
    Code:
       0: aload_0
       1: getfield      #20                 // Field string:Ljava/lang/String;
       4: invokevirtual #24                 // Method java/lang/String.toCharArray:()[C
       7: astore_2
       8: aload_2
       9: arraylength
      10: iconst_2
      11: imul
      12: newarray       byte
      14: astore_3
      15: iconst_0
      16: istore        4
      18: iload         4
      20: aload_2
      21: arraylength
      22: if_icmpeq     58
      25: aload_3
      26: iconst_2
      27: iload         4
      29: imul
      30: aload_2
      31: iload         4
      33: caload
      34: bipush        8
      36: ishr
      37: i2b
      38: bastore
      39: aload_3
      40: iconst_2
      41: iload         4
      43: imul
      44: iconst_1
      45: iadd
      46: aload_2
      47: iload         4
      49: caload
      50: i2b
      51: bastore
      52: iinc          4, 1
      55: goto          18
      58: aload_1
      59: bipush        30
      61: aload_3
      62: invokevirtual #25                 // Method org/apache/commons/ssl/asn1/DEROutputStream.writeEncoded:(I[B)V
      65: return
}
