Compiled from "DERSet.java"
public class org.apache.commons.ssl.asn1.DERSet extends org.apache.commons.ssl.asn1.ASN1Set {
  public org.apache.commons.ssl.asn1.DERSet();
    Code:
       0: aload_0
       1: invokespecial #1                  // Method org/apache/commons/ssl/asn1/ASN1Set."<init>":()V
       4: return

  public org.apache.commons.ssl.asn1.DERSet(org.apache.commons.ssl.asn1.DEREncodable);
    Code:
       0: aload_0
       1: invokespecial #1                  // Method org/apache/commons/ssl/asn1/ASN1Set."<init>":()V
       4: aload_0
       5: aload_1
       6: invokevirtual #2                  // Method org/apache/commons/ssl/asn1/ASN1Set.addObject:(Lorg/apache/commons/ssl/asn1/DEREncodable;)V
       9: return

  public org.apache.commons.ssl.asn1.DERSet(org.apache.commons.ssl.asn1.DEREncodableVector);
    Code:
       0: aload_0
       1: aload_1
       2: iconst_1
       3: invokespecial #3                  // Method "<init>":(Lorg/apache/commons/ssl/asn1/DEREncodableVector;Z)V
       6: return

  public org.apache.commons.ssl.asn1.DERSet(org.apache.commons.ssl.asn1.ASN1Encodable[]);
    Code:
       0: aload_0
       1: invokespecial #1                  // Method org/apache/commons/ssl/asn1/ASN1Set."<init>":()V
       4: iconst_0
       5: istore_2
       6: iload_2
       7: aload_1
       8: arraylength
       9: if_icmpeq     25
      12: aload_0
      13: aload_1
      14: iload_2
      15: aaload
      16: invokevirtual #2                  // Method org/apache/commons/ssl/asn1/ASN1Set.addObject:(Lorg/apache/commons/ssl/asn1/DEREncodable;)V
      19: iinc          2, 1
      22: goto          6
      25: aload_0
      26: invokevirtual #4                  // Method org/apache/commons/ssl/asn1/ASN1Set.sort:()V
      29: return

  org.apache.commons.ssl.asn1.DERSet(org.apache.commons.ssl.asn1.DEREncodableVector, boolean);
    Code:
       0: aload_0
       1: invokespecial #1                  // Method org/apache/commons/ssl/asn1/ASN1Set."<init>":()V
       4: iconst_0
       5: istore_3
       6: iload_3
       7: aload_1
       8: invokevirtual #5                  // Method org/apache/commons/ssl/asn1/DEREncodableVector.size:()I
      11: if_icmpeq     29
      14: aload_0
      15: aload_1
      16: iload_3
      17: invokevirtual #6                  // Method org/apache/commons/ssl/asn1/DEREncodableVector.get:(I)Lorg/apache/commons/ssl/asn1/DEREncodable;
      20: invokevirtual #2                  // Method org/apache/commons/ssl/asn1/ASN1Set.addObject:(Lorg/apache/commons/ssl/asn1/DEREncodable;)V
      23: iinc          3, 1
      26: goto          6
      29: iload_2
      30: ifeq          37
      33: aload_0
      34: invokevirtual #4                  // Method org/apache/commons/ssl/asn1/ASN1Set.sort:()V
      37: return

  void encode(org.apache.commons.ssl.asn1.DEROutputStream) throws java.io.IOException;
    Code:
       0: new           #7                  // class java/io/ByteArrayOutputStream
       3: dup
       4: invokespecial #8                  // Method java/io/ByteArrayOutputStream."<init>":()V
       7: astore_2
       8: new           #9                  // class org/apache/commons/ssl/asn1/DEROutputStream
      11: dup
      12: aload_2
      13: invokespecial #10                 // Method org/apache/commons/ssl/asn1/DEROutputStream."<init>":(Ljava/io/OutputStream;)V
      16: astore_3
      17: aload_0
      18: invokevirtual #11                 // Method org/apache/commons/ssl/asn1/ASN1Set.getObjects:()Ljava/util/Enumeration;
      21: astore        4
      23: aload         4
      25: invokeinterface #12,  1           // InterfaceMethod java/util/Enumeration.hasMoreElements:()Z
      30: ifeq          51
      33: aload         4
      35: invokeinterface #13,  1           // InterfaceMethod java/util/Enumeration.nextElement:()Ljava/lang/Object;
      40: astore        5
      42: aload_3
      43: aload         5
      45: invokevirtual #14                 // Method org/apache/commons/ssl/asn1/DEROutputStream.writeObject:(Ljava/lang/Object;)V
      48: goto          23
      51: aload_3
      52: invokevirtual #15                 // Method java/io/FilterOutputStream.close:()V
      55: aload_2
      56: invokevirtual #16                 // Method java/io/ByteArrayOutputStream.toByteArray:()[B
      59: astore        5
      61: aload_1
      62: bipush        49
      64: aload         5
      66: invokevirtual #17                 // Method org/apache/commons/ssl/asn1/DEROutputStream.writeEncoded:(I[B)V
      69: return
}
