Compiled from "TransactionAutoConfiguration.java"
public class org.springframework.boot.autoconfigure.transaction.TransactionAutoConfiguration {
  public org.springframework.boot.autoconfigure.transaction.TransactionAutoConfiguration();
    Code:
       0: aload_0
       1: invokespecial #1                  // Method java/lang/Object."<init>":()V
       4: return

  public org.springframework.boot.autoconfigure.transaction.TransactionManagerCustomizers platformTransactionManagerCustomizers(org.springframework.beans.factory.ObjectProvider<java.util.List<org.springframework.boot.autoconfigure.transaction.PlatformTransactionManagerCustomizer<?>>>);
    Code:
       0: new           #2                  // class org/springframework/boot/autoconfigure/transaction/TransactionManagerCustomizers
       3: dup
       4: aload_1
       5: invokeinterface #3,  1            // InterfaceMethod org/springframework/beans/factory/ObjectProvider.getIfAvailable:()Ljava/lang/Object;
      10: checkcast     #4                  // class java/util/Collection
      13: invokespecial #5                  // Method org/springframework/boot/autoconfigure/transaction/TransactionManagerCustomizers."<init>":(Ljava/util/Collection;)V
      16: areturn
}
