Compiled from "FirstArrivedInOrderChargeStrategy.java"
public class org.sonatype.sisu.charger.internal.FirstArrivedInOrderChargeStrategy<E> extends org.sonatype.sisu.charger.internal.AbstractChargeStrategy<E> {
  public org.sonatype.sisu.charger.internal.FirstArrivedInOrderChargeStrategy();
    Code:
       0: aload_0
       1: invokespecial #1                  // Method org/sonatype/sisu/charger/internal/AbstractChargeStrategy."<init>":()V
       4: return

  public boolean isDone(org.sonatype.sisu.charger.internal.Charge<E>, org.sonatype.sisu.charger.internal.ChargeWrapper<E>);
    Code:
       0: aload_1
       1: invokevirtual #2                  // Method org/sonatype/sisu/charger/internal/Charge.getAmmoFutures:()Ljava/util/List;
       4: astore_3
       5: aload_3
       6: invokeinterface #3,  1            // InterfaceMethod java/util/List.iterator:()Ljava/util/Iterator;
      11: astore        4
      13: aload         4
      15: invokeinterface #4,  1            // InterfaceMethod java/util/Iterator.hasNext:()Z
      20: ifeq          78
      23: aload         4
      25: invokeinterface #5,  1            // InterfaceMethod java/util/Iterator.next:()Ljava/lang/Object;
      30: checkcast     #6                  // class org/sonatype/sisu/charger/internal/ChargeWrapper
      33: astore        5
      35: aload         5
      37: invokevirtual #7                  // Method org/sonatype/sisu/charger/internal/ChargeWrapper.getFuture:()Ljava/util/concurrent/Future;
      40: astore        6
      42: aload         6
      44: ifnull        75
      47: aload         6
      49: invokeinterface #8,  1            // InterfaceMethod java/util/concurrent/Future.isDone:()Z
      54: ifeq          75
      57: aload_0
      58: aload         5
      60: invokevirtual #9                  // Method getFutureResult:(Lorg/sonatype/sisu/charger/internal/ChargeWrapper;)Ljava/lang/Object;
      63: ifnull        68
      66: iconst_1
      67: ireturn
      68: goto          75
      71: astore        7
      73: iconst_1
      74: ireturn
      75: goto          13
      78: iconst_0
      79: ireturn
    Exception table:
       from    to  target type
          57    67    71   Class java/lang/Exception

  public java.util.List<E> getResult(org.sonatype.sisu.charger.internal.Charge<E>) throws java.lang.Exception;
    Code:
       0: aload_1
       1: invokevirtual #2                  // Method org/sonatype/sisu/charger/internal/Charge.getAmmoFutures:()Ljava/util/List;
       4: astore_2
       5: aload_2
       6: invokeinterface #3,  1            // InterfaceMethod java/util/List.iterator:()Ljava/util/Iterator;
      11: astore_3
      12: aload_3
      13: invokeinterface #4,  1            // InterfaceMethod java/util/Iterator.hasNext:()Z
      18: ifeq          54
      21: aload_3
      22: invokeinterface #5,  1            // InterfaceMethod java/util/Iterator.next:()Ljava/lang/Object;
      27: checkcast     #6                  // class org/sonatype/sisu/charger/internal/ChargeWrapper
      30: astore        4
      32: aload_0
      33: aload         4
      35: invokevirtual #9                  // Method getFutureResult:(Lorg/sonatype/sisu/charger/internal/ChargeWrapper;)Ljava/lang/Object;
      38: astore        5
      40: aload         5
      42: ifnull        51
      45: aload         5
      47: invokestatic  #11                 // Method java/util/Collections.singletonList:(Ljava/lang/Object;)Ljava/util/List;
      50: areturn
      51: goto          12
      54: invokestatic  #12                 // Method java/util/Collections.emptyList:()Ljava/util/List;
      57: areturn
}
