Compiled from "EJBApiAbstraction.java"
public class org.jboss.weld.ejb.EJBApiAbstraction extends org.jboss.weld.util.ApiAbstraction implements org.jboss.weld.bootstrap.api.Service {
  public final java.lang.Class<? extends java.lang.annotation.Annotation> EJB_ANNOTATION_CLASS;

  public final java.lang.Class<? extends java.lang.annotation.Annotation> RESOURCE_ANNOTATION_CLASS;

  public final java.lang.Class<? extends java.lang.annotation.Annotation> TIMEOUT_ANNOTATION_CLASS;

  public final java.lang.Class<? extends java.lang.annotation.Annotation> TRANSACTION_MANAGEMENT;

  public final java.lang.Class<?> TRANSACTION_MANAGEMENT_TYPE;

  public final java.lang.Object BEAN_MANAGED_TRANSACTION_MANAGEMENT_ENUM_VALUE;

  public final java.lang.Object CONTAINER_MANAGED_TRANSACTION_MANAGEMENT_ENUM_VALUE;

  public org.jboss.weld.ejb.EJBApiAbstraction(org.jboss.weld.resources.spi.ResourceLoader);
    Code:
       0: aload_0
       1: aload_1
       2: invokespecial #1                  // Method org/jboss/weld/util/ApiAbstraction."<init>":(Lorg/jboss/weld/resources/spi/ResourceLoader;)V
       5: aload_0
       6: aload_0
       7: ldc           #2                  // String javax.ejb.EJB
       9: invokevirtual #3                  // Method annotationTypeForName:(Ljava/lang/String;)Ljava/lang/Class;
      12: putfield      #4                  // Field EJB_ANNOTATION_CLASS:Ljava/lang/Class;
      15: aload_0
      16: aload_0
      17: ldc           #5                  // String javax.annotation.Resource
      19: invokevirtual #3                  // Method annotationTypeForName:(Ljava/lang/String;)Ljava/lang/Class;
      22: putfield      #6                  // Field RESOURCE_ANNOTATION_CLASS:Ljava/lang/Class;
      25: aload_0
      26: aload_0
      27: ldc           #7                  // String javax.ejb.Timeout
      29: invokevirtual #3                  // Method annotationTypeForName:(Ljava/lang/String;)Ljava/lang/Class;
      32: putfield      #8                  // Field TIMEOUT_ANNOTATION_CLASS:Ljava/lang/Class;
      35: aload_0
      36: aload_0
      37: ldc           #9                  // String javax.ejb.TransactionManagement
      39: invokevirtual #3                  // Method annotationTypeForName:(Ljava/lang/String;)Ljava/lang/Class;
      42: putfield      #10                 // Field TRANSACTION_MANAGEMENT:Ljava/lang/Class;
      45: aload_0
      46: aload_0
      47: ldc           #11                 // String javax.ejb.TransactionManagementType
      49: invokevirtual #12                 // Method classForName:(Ljava/lang/String;)Ljava/lang/Class;
      52: putfield      #13                 // Field TRANSACTION_MANAGEMENT_TYPE:Ljava/lang/Class;
      55: aload_0
      56: getfield      #13                 // Field TRANSACTION_MANAGEMENT_TYPE:Ljava/lang/Class;
      59: ldc           #14                 // class org/jboss/weld/util/ApiAbstraction$Dummy
      61: invokevirtual #15                 // Method java/lang/Object.equals:(Ljava/lang/Object;)Z
      64: ifeq          84
      67: aload_0
      68: getstatic     #16                 // Field org/jboss/weld/util/ApiAbstraction$DummyEnum.DUMMY_VALUE:Lorg/jboss/weld/util/ApiAbstraction$DummyEnum;
      71: putfield      #17                 // Field BEAN_MANAGED_TRANSACTION_MANAGEMENT_ENUM_VALUE:Ljava/lang/Object;
      74: aload_0
      75: getstatic     #16                 // Field org/jboss/weld/util/ApiAbstraction$DummyEnum.DUMMY_VALUE:Lorg/jboss/weld/util/ApiAbstraction$DummyEnum;
      78: putfield      #18                 // Field CONTAINER_MANAGED_TRANSACTION_MANAGEMENT_ENUM_VALUE:Ljava/lang/Object;
      81: goto          112
      84: aload_0
      85: aload_0
      86: aload_0
      87: getfield      #13                 // Field TRANSACTION_MANAGEMENT_TYPE:Ljava/lang/Class;
      90: ldc           #19                 // String BEAN
      92: invokevirtual #20                 // Method enumValue:(Ljava/lang/Class;Ljava/lang/String;)Ljava/lang/Object;
      95: putfield      #17                 // Field BEAN_MANAGED_TRANSACTION_MANAGEMENT_ENUM_VALUE:Ljava/lang/Object;
      98: aload_0
      99: aload_0
     100: aload_0
     101: getfield      #13                 // Field TRANSACTION_MANAGEMENT_TYPE:Ljava/lang/Class;
     104: ldc           #21                 // String CONTAINER
     106: invokevirtual #20                 // Method enumValue:(Ljava/lang/Class;Ljava/lang/String;)Ljava/lang/Object;
     109: putfield      #18                 // Field CONTAINER_MANAGED_TRANSACTION_MANAGEMENT_ENUM_VALUE:Ljava/lang/Object;
     112: return

  public void cleanup();
    Code:
       0: return

  public boolean isSessionBeanWithContainerManagedTransactions(javax.enterprise.inject.spi.Bean<?>);
    Code:
       0: aload_1
       1: instanceof    #22                 // class org/jboss/weld/bean/SessionBean
       4: ifeq          97
       7: aload_1
       8: checkcast     #22                 // class org/jboss/weld/bean/SessionBean
      11: astore_2
      12: aload_2
      13: invokevirtual #23                 // Method org/jboss/weld/bean/SessionBean.getAnnotated:()Lorg/jboss/weld/annotated/slim/SlimAnnotatedType;
      16: aload_0
      17: getfield      #10                 // Field TRANSACTION_MANAGEMENT:Ljava/lang/Class;
      20: invokeinterface #24,  2           // InterfaceMethod org/jboss/weld/annotated/slim/SlimAnnotatedType.getAnnotation:(Ljava/lang/Class;)Ljava/lang/annotation/Annotation;
      25: astore_3
      26: aload_3
      27: ifnull        37
      30: aload_3
      31: instanceof    #25                 // class org/jboss/weld/util/ApiAbstraction$DummyAnnotation
      34: ifeq          39
      37: iconst_1
      38: ireturn
      39: aload_3
      40: invokeinterface #26,  1           // InterfaceMethod java/lang/annotation/Annotation.annotationType:()Ljava/lang/Class;
      45: ldc           #27                 // String value
      47: iconst_0
      48: anewarray     #28                 // class java/lang/Class
      51: invokevirtual #29                 // Method java/lang/Class.getMethod:(Ljava/lang/String;[Ljava/lang/Class;)Ljava/lang/reflect/Method;
      54: astore        5
      56: aload         5
      58: aload_3
      59: iconst_0
      60: anewarray     #30                 // class java/lang/Object
      63: invokevirtual #31                 // Method java/lang/reflect/Method.invoke:(Ljava/lang/Object;[Ljava/lang/Object;)Ljava/lang/Object;
      66: astore        4
      68: goto          87
      71: astore        5
      73: iconst_1
      74: ireturn
      75: astore        5
      77: new           #34                 // class org/jboss/weld/exceptions/WeldException
      80: dup
      81: aload         5
      83: invokespecial #35                 // Method org/jboss/weld/exceptions/WeldException."<init>":(Ljava/lang/Throwable;)V
      86: athrow
      87: aload_0
      88: getfield      #18                 // Field CONTAINER_MANAGED_TRANSACTION_MANAGEMENT_ENUM_VALUE:Ljava/lang/Object;
      91: aload         4
      93: invokevirtual #15                 // Method java/lang/Object.equals:(Ljava/lang/Object;)Z
      96: ireturn
      97: iconst_0
      98: ireturn
    Exception table:
       from    to  target type
          39    68    71   Class java/lang/NoSuchMethodException
          39    68    75   Class java/lang/Exception
}
