Compiled from "LibertyManagedObject.java"
public class net.wasdev.wlp.common.arquillian.objects.LibertyManagedObject {
  private static final java.lang.String XML_START;

  private static final java.lang.String XML_END;

  private final java.lang.String wlpHome;

  private final java.lang.String serverName;

  private final int httpPort;

  private final java.util.Map<net.wasdev.wlp.common.arquillian.objects.LibertyProperty$LibertyPropertyI, java.lang.String> arquillianProperties;

  public net.wasdev.wlp.common.arquillian.objects.LibertyManagedObject(java.lang.String, java.lang.String, int, java.util.Map<net.wasdev.wlp.common.arquillian.objects.LibertyProperty$LibertyPropertyI, java.lang.String>);
    Code:
       0: aload_0
       1: invokespecial #1                  // Method java/lang/Object."<init>":()V
       4: aload_0
       5: aload_1
       6: putfield      #2                  // Field wlpHome:Ljava/lang/String;
       9: aload_0
      10: aload_2
      11: putfield      #3                  // Field serverName:Ljava/lang/String;
      14: aload_0
      15: iload_3
      16: putfield      #4                  // Field httpPort:I
      19: aload_0
      20: aload         4
      22: putfield      #5                  // Field arquillianProperties:Ljava/util/Map;
      25: return

  public java.lang.String getWlpHome();
    Code:
       0: aload_0
       1: getfield      #2                  // Field wlpHome:Ljava/lang/String;
       4: areturn

  public java.lang.String getServerName();
    Code:
       0: aload_0
       1: getfield      #3                  // Field serverName:Ljava/lang/String;
       4: areturn

  public int getHttpPort();
    Code:
       0: aload_0
       1: getfield      #4                  // Field httpPort:I
       4: ireturn

  public java.util.Map<net.wasdev.wlp.common.arquillian.objects.LibertyProperty$LibertyPropertyI, java.lang.String> getArquillianProperties();
    Code:
       0: aload_0
       1: getfield      #5                  // Field arquillianProperties:Ljava/util/Map;
       4: areturn

  public void build(java.io.File) throws java.io.IOException;
    Code:
       0: new           #6                  // class java/lang/StringBuilder
       3: dup
       4: ldc           #8                  // String <?xml version=\"1.0\" encoding=\"UTF-8\" standalone=\"yes\"?>\n<arquillian xmlns:xsi=\"http://www.w3.org/2001/XMLSchema-instance\"\n\txmlns=\"http://jboss.org/schema/arquillian\"\n\txsi:schemaLocation=\"http://jboss.org/schema/arquillian http://jboss.org/schema/arquillian/arquillian_1_0.xsd\">\n\t<container qualifier=\"liberty_managed\" default=\"true\">\n\t\t<configuration>\n
       6: invokespecial #9                  // Method java/lang/StringBuilder."<init>":(Ljava/lang/String;)V
       9: astore_2
      10: aload_2
      11: ldc           #10                 // String \t\t\t<property name=\"wlpHome\">
      13: invokevirtual #11                 // Method java/lang/StringBuilder.append:(Ljava/lang/String;)Ljava/lang/StringBuilder;
      16: aload_0
      17: invokevirtual #12                 // Method getWlpHome:()Ljava/lang/String;
      20: invokevirtual #11                 // Method java/lang/StringBuilder.append:(Ljava/lang/String;)Ljava/lang/StringBuilder;
      23: ldc           #13                 // String </property>\n
      25: invokevirtual #11                 // Method java/lang/StringBuilder.append:(Ljava/lang/String;)Ljava/lang/StringBuilder;
      28: pop
      29: aload_2
      30: ldc           #14                 // String \t\t\t<property name=\"serverName\">
      32: invokevirtual #11                 // Method java/lang/StringBuilder.append:(Ljava/lang/String;)Ljava/lang/StringBuilder;
      35: aload_0
      36: invokevirtual #15                 // Method getServerName:()Ljava/lang/String;
      39: invokevirtual #11                 // Method java/lang/StringBuilder.append:(Ljava/lang/String;)Ljava/lang/StringBuilder;
      42: ldc           #13                 // String </property>\n
      44: invokevirtual #11                 // Method java/lang/StringBuilder.append:(Ljava/lang/String;)Ljava/lang/StringBuilder;
      47: pop
      48: aload_2
      49: ldc           #16                 // String \t\t\t<property name=\"httpPort\">
      51: invokevirtual #11                 // Method java/lang/StringBuilder.append:(Ljava/lang/String;)Ljava/lang/StringBuilder;
      54: aload_0
      55: invokevirtual #17                 // Method getHttpPort:()I
      58: invokevirtual #18                 // Method java/lang/StringBuilder.append:(I)Ljava/lang/StringBuilder;
      61: ldc           #13                 // String </property>\n
      63: invokevirtual #11                 // Method java/lang/StringBuilder.append:(Ljava/lang/String;)Ljava/lang/StringBuilder;
      66: pop
      67: aload_0
      68: getfield      #5                  // Field arquillianProperties:Ljava/util/Map;
      71: invokeinterface #19,  1           // InterfaceMethod java/util/Map.entrySet:()Ljava/util/Set;
      76: invokeinterface #20,  1           // InterfaceMethod java/util/Set.iterator:()Ljava/util/Iterator;
      81: astore_3
      82: aload_3
      83: invokeinterface #21,  1           // InterfaceMethod java/util/Iterator.hasNext:()Z
      88: ifeq          159
      91: aload_3
      92: invokeinterface #22,  1           // InterfaceMethod java/util/Iterator.next:()Ljava/lang/Object;
      97: checkcast     #23                 // class java/util/Map$Entry
     100: astore        4
     102: aload         4
     104: invokeinterface #24,  1           // InterfaceMethod java/util/Map$Entry.getKey:()Ljava/lang/Object;
     109: checkcast     #25                 // class net/wasdev/wlp/common/arquillian/objects/LibertyManagedObject$LibertyManagedProperty
     112: astore        5
     114: aload         5
     116: invokevirtual #26                 // Method net/wasdev/wlp/common/arquillian/objects/LibertyManagedObject$LibertyManagedProperty.name:()Ljava/lang/String;
     119: astore        6
     121: aload_2
     122: ldc           #27                 // String \t\t\t<property name=\"
     124: invokevirtual #11                 // Method java/lang/StringBuilder.append:(Ljava/lang/String;)Ljava/lang/StringBuilder;
     127: aload         6
     129: invokevirtual #11                 // Method java/lang/StringBuilder.append:(Ljava/lang/String;)Ljava/lang/StringBuilder;
     132: ldc           #28                 // String \">
     134: invokevirtual #11                 // Method java/lang/StringBuilder.append:(Ljava/lang/String;)Ljava/lang/StringBuilder;
     137: aload         4
     139: invokeinterface #29,  1           // InterfaceMethod java/util/Map$Entry.getValue:()Ljava/lang/Object;
     144: checkcast     #30                 // class java/lang/String
     147: invokevirtual #11                 // Method java/lang/StringBuilder.append:(Ljava/lang/String;)Ljava/lang/StringBuilder;
     150: ldc           #13                 // String </property>\n
     152: invokevirtual #11                 // Method java/lang/StringBuilder.append:(Ljava/lang/String;)Ljava/lang/StringBuilder;
     155: pop
     156: goto          82
     159: aload_2
     160: ldc           #31                 // String \t\t</configuration>\n\t</container>\n</arquillian>\n
     162: invokevirtual #11                 // Method java/lang/StringBuilder.append:(Ljava/lang/String;)Ljava/lang/StringBuilder;
     165: pop
     166: aload_2
     167: ldc           #33                 // String <!-- This file was generated by the Liberty build plugin. -->
     169: invokevirtual #11                 // Method java/lang/StringBuilder.append:(Ljava/lang/String;)Ljava/lang/StringBuilder;
     172: pop
     173: aload_2
     174: aload_1
     175: invokestatic  #34                 // Method net/wasdev/wlp/common/arquillian/objects/LibertyProperty.write:(Ljava/lang/StringBuilder;Ljava/io/File;)V
     178: return
}
