Compiled from "BeanUtil.java"
final class org.apache.axis2.databinding.utils.BeanUtil$1 implements java.util.Comparator {
  org.apache.axis2.databinding.utils.BeanUtil$1();
    Code:
       0: aload_0
       1: invokespecial #1                  // Method java/lang/Object."<init>":()V
       4: return

  public int compare(java.lang.Object, java.lang.Object);
    Code:
       0: aload_1
       1: checkcast     #2                  // class java/lang/String
       4: astore_3
       5: aload_2
       6: checkcast     #2                  // class java/lang/String
       9: astore        4
      11: aload_3
      12: aload         4
      14: invokevirtual #3                  // Method java/lang/String.compareToIgnoreCase:(Ljava/lang/String;)I
      17: ireturn
}
