Compiled from "ListAccountAliasesPublisher.java"
class software.amazon.awssdk.services.iam.paginators.ListAccountAliasesPublisher$ListAccountAliasesResponseFetcher implements software.amazon.awssdk.core.pagination.async.AsyncPageFetcher<software.amazon.awssdk.services.iam.model.ListAccountAliasesResponse> {
  final software.amazon.awssdk.services.iam.paginators.ListAccountAliasesPublisher this$0;

  private software.amazon.awssdk.services.iam.paginators.ListAccountAliasesPublisher$ListAccountAliasesResponseFetcher(software.amazon.awssdk.services.iam.paginators.ListAccountAliasesPublisher);
    Code:
       0: aload_0
       1: aload_1
       2: putfield      #2                  // Field this$0:Lsoftware/amazon/awssdk/services/iam/paginators/ListAccountAliasesPublisher;
       5: aload_0
       6: invokespecial #3                  // Method java/lang/Object."<init>":()V
       9: return

  public boolean hasNextPage(software.amazon.awssdk.services.iam.model.ListAccountAliasesResponse);
    Code:
       0: aload_1
       1: invokevirtual #4                  // Method software/amazon/awssdk/services/iam/model/ListAccountAliasesResponse.isTruncated:()Ljava/lang/Boolean;
       4: invokevirtual #5                  // Method java/lang/Boolean.booleanValue:()Z
       7: ireturn

  public java.util.concurrent.CompletableFuture<software.amazon.awssdk.services.iam.model.ListAccountAliasesResponse> nextPage(software.amazon.awssdk.services.iam.model.ListAccountAliasesResponse);
    Code:
       0: aload_1
       1: ifnonnull     24
       4: aload_0
       5: getfield      #2                  // Field this$0:Lsoftware/amazon/awssdk/services/iam/paginators/ListAccountAliasesPublisher;
       8: invokestatic  #6                  // Method software/amazon/awssdk/services/iam/paginators/ListAccountAliasesPublisher.access$200:(Lsoftware/amazon/awssdk/services/iam/paginators/ListAccountAliasesPublisher;)Lsoftware/amazon/awssdk/services/iam/IamAsyncClient;
      11: aload_0
      12: getfield      #2                  // Field this$0:Lsoftware/amazon/awssdk/services/iam/paginators/ListAccountAliasesPublisher;
      15: invokestatic  #7                  // Method software/amazon/awssdk/services/iam/paginators/ListAccountAliasesPublisher.access$100:(Lsoftware/amazon/awssdk/services/iam/paginators/ListAccountAliasesPublisher;)Lsoftware/amazon/awssdk/services/iam/model/ListAccountAliasesRequest;
      18: invokeinterface #8,  2            // InterfaceMethod software/amazon/awssdk/services/iam/IamAsyncClient.listAccountAliases:(Lsoftware/amazon/awssdk/services/iam/model/ListAccountAliasesRequest;)Ljava/util/concurrent/CompletableFuture;
      23: areturn
      24: aload_0
      25: getfield      #2                  // Field this$0:Lsoftware/amazon/awssdk/services/iam/paginators/ListAccountAliasesPublisher;
      28: invokestatic  #6                  // Method software/amazon/awssdk/services/iam/paginators/ListAccountAliasesPublisher.access$200:(Lsoftware/amazon/awssdk/services/iam/paginators/ListAccountAliasesPublisher;)Lsoftware/amazon/awssdk/services/iam/IamAsyncClient;
      31: aload_0
      32: getfield      #2                  // Field this$0:Lsoftware/amazon/awssdk/services/iam/paginators/ListAccountAliasesPublisher;
      35: invokestatic  #7                  // Method software/amazon/awssdk/services/iam/paginators/ListAccountAliasesPublisher.access$100:(Lsoftware/amazon/awssdk/services/iam/paginators/ListAccountAliasesPublisher;)Lsoftware/amazon/awssdk/services/iam/model/ListAccountAliasesRequest;
      38: invokevirtual #9                  // Method software/amazon/awssdk/services/iam/model/ListAccountAliasesRequest.toBuilder:()Lsoftware/amazon/awssdk/services/iam/model/ListAccountAliasesRequest$Builder;
      41: aload_1
      42: invokevirtual #10                 // Method software/amazon/awssdk/services/iam/model/ListAccountAliasesResponse.marker:()Ljava/lang/String;
      45: invokeinterface #11,  2           // InterfaceMethod software/amazon/awssdk/services/iam/model/ListAccountAliasesRequest$Builder.marker:(Ljava/lang/String;)Lsoftware/amazon/awssdk/services/iam/model/ListAccountAliasesRequest$Builder;
      50: invokeinterface #12,  1           // InterfaceMethod software/amazon/awssdk/services/iam/model/ListAccountAliasesRequest$Builder.build:()Ljava/lang/Object;
      55: checkcast     #13                 // class software/amazon/awssdk/services/iam/model/ListAccountAliasesRequest
      58: invokeinterface #8,  2            // InterfaceMethod software/amazon/awssdk/services/iam/IamAsyncClient.listAccountAliases:(Lsoftware/amazon/awssdk/services/iam/model/ListAccountAliasesRequest;)Ljava/util/concurrent/CompletableFuture;
      63: areturn

  public java.util.concurrent.CompletableFuture nextPage(java.lang.Object);
    Code:
       0: aload_0
       1: aload_1
       2: checkcast     #14                 // class software/amazon/awssdk/services/iam/model/ListAccountAliasesResponse
       5: invokevirtual #15                 // Method nextPage:(Lsoftware/amazon/awssdk/services/iam/model/ListAccountAliasesResponse;)Ljava/util/concurrent/CompletableFuture;
       8: areturn

  public boolean hasNextPage(java.lang.Object);
    Code:
       0: aload_0
       1: aload_1
       2: checkcast     #14                 // class software/amazon/awssdk/services/iam/model/ListAccountAliasesResponse
       5: invokevirtual #16                 // Method hasNextPage:(Lsoftware/amazon/awssdk/services/iam/model/ListAccountAliasesResponse;)Z
       8: ireturn

  software.amazon.awssdk.services.iam.paginators.ListAccountAliasesPublisher$ListAccountAliasesResponseFetcher(software.amazon.awssdk.services.iam.paginators.ListAccountAliasesPublisher, software.amazon.awssdk.services.iam.paginators.ListAccountAliasesPublisher$1);
    Code:
       0: aload_0
       1: aload_1
       2: invokespecial #1                  // Method "<init>":(Lsoftware/amazon/awssdk/services/iam/paginators/ListAccountAliasesPublisher;)V
       5: return
}
