Compiled from "OsgiFactoryFinder.java"
public class org.apache.camel.core.osgi.OsgiFactoryFinder extends org.apache.camel.impl.DefaultFactoryFinder {
  private org.osgi.framework.BundleContext bundleContext;

  public org.apache.camel.core.osgi.OsgiFactoryFinder(org.osgi.framework.BundleContext, org.apache.camel.spi.ClassResolver, java.lang.String);
    Code:
       0: aload_0
       1: aload_2
       2: aload_3
       3: invokespecial #1                  // Method org/apache/camel/impl/DefaultFactoryFinder."<init>":(Lorg/apache/camel/spi/ClassResolver;Ljava/lang/String;)V
       6: aload_0
       7: aload_1
       8: putfield      #2                  // Field bundleContext:Lorg/osgi/framework/BundleContext;
      11: return

  public java.lang.Class<?> findClass(java.lang.String, java.lang.String, java.lang.Class<?>) throws java.lang.ClassNotFoundException, java.io.IOException;
    Code:
       0: aload_2
       1: ifnonnull     7
       4: ldc           #3                  // String
       6: astore_2
       7: aload_0
       8: getfield      #4                  // Field classMap:Ljava/util/concurrent/ConcurrentMap;
      11: new           #5                  // class java/lang/StringBuilder
      14: dup
      15: invokespecial #6                  // Method java/lang/StringBuilder."<init>":()V
      18: aload_2
      19: invokevirtual #7                  // Method java/lang/StringBuilder.append:(Ljava/lang/String;)Ljava/lang/StringBuilder;
      22: aload_1
      23: invokevirtual #7                  // Method java/lang/StringBuilder.append:(Ljava/lang/String;)Ljava/lang/StringBuilder;
      26: invokevirtual #8                  // Method java/lang/StringBuilder.toString:()Ljava/lang/String;
      29: invokeinterface #9,  2            // InterfaceMethod java/util/concurrent/ConcurrentMap.get:(Ljava/lang/Object;)Ljava/lang/Object;
      34: checkcast     #10                 // class java/lang/Class
      37: astore        4
      39: aload         4
      41: ifnonnull     269
      44: aload_0
      45: aload_1
      46: aload_3
      47: invokevirtual #11                 // Method getResource:(Ljava/lang/String;Ljava/lang/Class;)Lorg/apache/camel/core/osgi/OsgiFactoryFinder$BundleEntry;
      50: astore        5
      52: aload         5
      54: ifnull        243
      57: aload         5
      59: getfield      #12                 // Field org/apache/camel/core/osgi/OsgiFactoryFinder$BundleEntry.url:Ljava/net/URL;
      62: astore        6
      64: aload         6
      66: invokevirtual #13                 // Method java/net/URL.openStream:()Ljava/io/InputStream;
      69: astore        7
      71: aconst_null
      72: astore        8
      74: aload         7
      76: invokestatic  #14                 // Method org/apache/camel/util/IOHelper.buffered:(Ljava/io/InputStream;)Ljava/io/BufferedInputStream;
      79: astore        8
      81: new           #15                 // class java/util/Properties
      84: dup
      85: invokespecial #16                 // Method java/util/Properties."<init>":()V
      88: astore        9
      90: aload         9
      92: aload         8
      94: invokevirtual #17                 // Method java/util/Properties.load:(Ljava/io/InputStream;)V
      97: aload         9
      99: new           #5                  // class java/lang/StringBuilder
     102: dup
     103: invokespecial #6                  // Method java/lang/StringBuilder."<init>":()V
     106: aload_2
     107: invokevirtual #7                  // Method java/lang/StringBuilder.append:(Ljava/lang/String;)Ljava/lang/StringBuilder;
     110: ldc           #18                 // String class
     112: invokevirtual #7                  // Method java/lang/StringBuilder.append:(Ljava/lang/String;)Ljava/lang/StringBuilder;
     115: invokevirtual #8                  // Method java/lang/StringBuilder.toString:()Ljava/lang/String;
     118: invokevirtual #19                 // Method java/util/Properties.getProperty:(Ljava/lang/String;)Ljava/lang/String;
     121: astore        10
     123: aload         10
     125: ifnonnull     160
     128: new           #20                 // class java/io/IOException
     131: dup
     132: new           #5                  // class java/lang/StringBuilder
     135: dup
     136: invokespecial #6                  // Method java/lang/StringBuilder."<init>":()V
     139: ldc           #21                 // String Expected property is missing:
     141: invokevirtual #7                  // Method java/lang/StringBuilder.append:(Ljava/lang/String;)Ljava/lang/StringBuilder;
     144: aload_2
     145: invokevirtual #7                  // Method java/lang/StringBuilder.append:(Ljava/lang/String;)Ljava/lang/StringBuilder;
     148: ldc           #18                 // String class
     150: invokevirtual #7                  // Method java/lang/StringBuilder.append:(Ljava/lang/String;)Ljava/lang/StringBuilder;
     153: invokevirtual #8                  // Method java/lang/StringBuilder.toString:()Ljava/lang/String;
     156: invokespecial #22                 // Method java/io/IOException."<init>":(Ljava/lang/String;)V
     159: athrow
     160: aload         5
     162: getfield      #23                 // Field org/apache/camel/core/osgi/OsgiFactoryFinder$BundleEntry.bundle:Lorg/osgi/framework/Bundle;
     165: aload         10
     167: invokeinterface #24,  2           // InterfaceMethod org/osgi/framework/Bundle.loadClass:(Ljava/lang/String;)Ljava/lang/Class;
     172: astore        4
     174: aload_0
     175: getfield      #4                  // Field classMap:Ljava/util/concurrent/ConcurrentMap;
     178: new           #5                  // class java/lang/StringBuilder
     181: dup
     182: invokespecial #6                  // Method java/lang/StringBuilder."<init>":()V
     185: aload_2
     186: invokevirtual #7                  // Method java/lang/StringBuilder.append:(Ljava/lang/String;)Ljava/lang/StringBuilder;
     189: aload_1
     190: invokevirtual #7                  // Method java/lang/StringBuilder.append:(Ljava/lang/String;)Ljava/lang/StringBuilder;
     193: invokevirtual #8                  // Method java/lang/StringBuilder.toString:()Ljava/lang/String;
     196: aload         4
     198: invokeinterface #25,  3           // InterfaceMethod java/util/concurrent/ConcurrentMap.put:(Ljava/lang/Object;Ljava/lang/Object;)Ljava/lang/Object;
     203: pop
     204: aload         8
     206: aload_1
     207: aconst_null
     208: invokestatic  #26                 // Method org/apache/camel/util/IOHelper.close:(Ljava/io/Closeable;Ljava/lang/String;Lorg/slf4j/Logger;)V
     211: aload         7
     213: aload_1
     214: aconst_null
     215: invokestatic  #26                 // Method org/apache/camel/util/IOHelper.close:(Ljava/io/Closeable;Ljava/lang/String;Lorg/slf4j/Logger;)V
     218: goto          240
     221: astore        11
     223: aload         8
     225: aload_1
     226: aconst_null
     227: invokestatic  #26                 // Method org/apache/camel/util/IOHelper.close:(Ljava/io/Closeable;Ljava/lang/String;Lorg/slf4j/Logger;)V
     230: aload         7
     232: aload_1
     233: aconst_null
     234: invokestatic  #26                 // Method org/apache/camel/util/IOHelper.close:(Ljava/io/Closeable;Ljava/lang/String;Lorg/slf4j/Logger;)V
     237: aload         11
     239: athrow
     240: goto          269
     243: new           #27                 // class org/apache/camel/NoFactoryAvailableException
     246: dup
     247: new           #5                  // class java/lang/StringBuilder
     250: dup
     251: invokespecial #6                  // Method java/lang/StringBuilder."<init>":()V
     254: aload_2
     255: invokevirtual #7                  // Method java/lang/StringBuilder.append:(Ljava/lang/String;)Ljava/lang/StringBuilder;
     258: aload_1
     259: invokevirtual #7                  // Method java/lang/StringBuilder.append:(Ljava/lang/String;)Ljava/lang/StringBuilder;
     262: invokevirtual #8                  // Method java/lang/StringBuilder.toString:()Ljava/lang/String;
     265: invokespecial #28                 // Method org/apache/camel/NoFactoryAvailableException."<init>":(Ljava/lang/String;)V
     268: athrow
     269: aload         4
     271: areturn
    Exception table:
       from    to  target type
          74   204   221   any
         221   223   221   any

  public java.lang.Class<?> findClass(java.lang.String, java.lang.String) throws java.lang.ClassNotFoundException, java.io.IOException;
    Code:
       0: aload_0
       1: aload_1
       2: aload_2
       3: aconst_null
       4: invokevirtual #29                 // Method findClass:(Ljava/lang/String;Ljava/lang/String;Ljava/lang/Class;)Ljava/lang/Class;
       7: areturn

  public org.apache.camel.core.osgi.OsgiFactoryFinder$BundleEntry getResource(java.lang.String);
    Code:
       0: aload_0
       1: aload_1
       2: aconst_null
       3: invokevirtual #11                 // Method getResource:(Ljava/lang/String;Ljava/lang/Class;)Lorg/apache/camel/core/osgi/OsgiFactoryFinder$BundleEntry;
       6: areturn

  public org.apache.camel.core.osgi.OsgiFactoryFinder$BundleEntry getResource(java.lang.String, java.lang.Class<?>);
    Code:
       0: aconst_null
       1: astore_3
       2: aconst_null
       3: astore        4
       5: aload_0
       6: getfield      #2                  // Field bundleContext:Lorg/osgi/framework/BundleContext;
       9: invokeinterface #30,  1           // InterfaceMethod org/osgi/framework/BundleContext.getBundles:()[Lorg/osgi/framework/Bundle;
      14: astore        4
      16: aload         4
      18: astore        6
      20: aload         6
      22: arraylength
      23: istore        7
      25: iconst_0
      26: istore        8
      28: iload         8
      30: iload         7
      32: if_icmpge     117
      35: aload         6
      37: iload         8
      39: aaload
      40: astore        9
      42: aload         9
      44: new           #5                  // class java/lang/StringBuilder
      47: dup
      48: invokespecial #6                  // Method java/lang/StringBuilder."<init>":()V
      51: aload_0
      52: invokevirtual #31                 // Method getResourcePath:()Ljava/lang/String;
      55: invokevirtual #7                  // Method java/lang/StringBuilder.append:(Ljava/lang/String;)Ljava/lang/StringBuilder;
      58: aload_1
      59: invokevirtual #7                  // Method java/lang/StringBuilder.append:(Ljava/lang/String;)Ljava/lang/StringBuilder;
      62: invokevirtual #8                  // Method java/lang/StringBuilder.toString:()Ljava/lang/String;
      65: invokeinterface #32,  2           // InterfaceMethod org/osgi/framework/Bundle.getEntry:(Ljava/lang/String;)Ljava/net/URL;
      70: astore        5
      72: aload         5
      74: ifnull        111
      77: aload_0
      78: aload         9
      80: aload_2
      81: invokespecial #33                 // Method checkCompat:(Lorg/osgi/framework/Bundle;Ljava/lang/Class;)Z
      84: ifeq          111
      87: new           #34                 // class org/apache/camel/core/osgi/OsgiFactoryFinder$BundleEntry
      90: dup
      91: aconst_null
      92: invokespecial #35                 // Method org/apache/camel/core/osgi/OsgiFactoryFinder$BundleEntry."<init>":(Lorg/apache/camel/core/osgi/OsgiFactoryFinder$1;)V
      95: astore_3
      96: aload_3
      97: aload         5
      99: putfield      #12                 // Field org/apache/camel/core/osgi/OsgiFactoryFinder$BundleEntry.url:Ljava/net/URL;
     102: aload_3
     103: aload         9
     105: putfield      #23                 // Field org/apache/camel/core/osgi/OsgiFactoryFinder$BundleEntry.bundle:Lorg/osgi/framework/Bundle;
     108: goto          117
     111: iinc          8, 1
     114: goto          28
     117: aload_3
     118: areturn

  private boolean checkCompat(org.osgi.framework.Bundle, java.lang.Class<?>);
    Code:
       0: aload_2
       1: ifnonnull     6
       4: iconst_1
       5: ireturn
       6: aload_1
       7: aload_2
       8: invokevirtual #36                 // Method java/lang/Class.getName:()Ljava/lang/String;
      11: invokeinterface #24,  2           // InterfaceMethod org/osgi/framework/Bundle.loadClass:(Ljava/lang/String;)Ljava/lang/Class;
      16: aload_2
      17: if_acmpeq     22
      20: iconst_0
      21: ireturn
      22: goto          28
      25: astore_3
      26: iconst_0
      27: ireturn
      28: iconst_1
      29: ireturn
    Exception table:
       from    to  target type
           6    21    25   Class java/lang/Throwable
}
