Compiled from "FieldReader.java"
public class org.mockito.internal.util.reflection.FieldReader {
  final java.lang.Object target;

  final java.lang.reflect.Field field;

  final org.mockito.internal.util.reflection.AccessibilityChanger changer;

  public org.mockito.internal.util.reflection.FieldReader(java.lang.Object, java.lang.reflect.Field);
    Code:
       0: aload_0
       1: invokespecial #1                  // Method java/lang/Object."<init>":()V
       4: aload_0
       5: new           #2                  // class org/mockito/internal/util/reflection/AccessibilityChanger
       8: dup
       9: invokespecial #3                  // Method org/mockito/internal/util/reflection/AccessibilityChanger."<init>":()V
      12: putfield      #4                  // Field changer:Lorg/mockito/internal/util/reflection/AccessibilityChanger;
      15: aload_0
      16: aload_1
      17: putfield      #5                  // Field target:Ljava/lang/Object;
      20: aload_0
      21: aload_2
      22: putfield      #6                  // Field field:Ljava/lang/reflect/Field;
      25: aload_0
      26: getfield      #4                  // Field changer:Lorg/mockito/internal/util/reflection/AccessibilityChanger;
      29: aload_2
      30: invokevirtual #7                  // Method org/mockito/internal/util/reflection/AccessibilityChanger.enableAccess:(Ljava/lang/reflect/AccessibleObject;)V
      33: return

  public boolean isNull();
    Code:
       0: aload_0
       1: invokevirtual #8                  // Method read:()Ljava/lang/Object;
       4: ifnonnull     11
       7: iconst_1
       8: goto          12
      11: iconst_0
      12: ireturn

  public java.lang.Object read();
    Code:
       0: aload_0
       1: getfield      #6                  // Field field:Ljava/lang/reflect/Field;
       4: aload_0
       5: getfield      #5                  // Field target:Ljava/lang/Object;
       8: invokevirtual #9                  // Method java/lang/reflect/Field.get:(Ljava/lang/Object;)Ljava/lang/Object;
      11: areturn
      12: astore_1
      13: new           #11                 // class org/mockito/exceptions/base/MockitoException
      16: dup
      17: new           #12                 // class java/lang/StringBuilder
      20: dup
      21: invokespecial #13                 // Method java/lang/StringBuilder."<init>":()V
      24: ldc           #14                 // String Cannot read state from field:
      26: invokevirtual #15                 // Method java/lang/StringBuilder.append:(Ljava/lang/String;)Ljava/lang/StringBuilder;
      29: aload_0
      30: getfield      #6                  // Field field:Ljava/lang/reflect/Field;
      33: invokevirtual #16                 // Method java/lang/StringBuilder.append:(Ljava/lang/Object;)Ljava/lang/StringBuilder;
      36: ldc           #17                 // String , on instance:
      38: invokevirtual #15                 // Method java/lang/StringBuilder.append:(Ljava/lang/String;)Ljava/lang/StringBuilder;
      41: aload_0
      42: getfield      #5                  // Field target:Ljava/lang/Object;
      45: invokevirtual #16                 // Method java/lang/StringBuilder.append:(Ljava/lang/Object;)Ljava/lang/StringBuilder;
      48: invokevirtual #18                 // Method java/lang/StringBuilder.toString:()Ljava/lang/String;
      51: invokespecial #19                 // Method org/mockito/exceptions/base/MockitoException."<init>":(Ljava/lang/String;)V
      54: athrow
    Exception table:
       from    to  target type
           0    11    12   Class java/lang/Exception
}
