Compiled from "FieldSetter.java"
public class org.mockito.internal.util.reflection.FieldSetter {
  private final java.lang.Object target;

  private final java.lang.reflect.Field field;

  public org.mockito.internal.util.reflection.FieldSetter(java.lang.Object, java.lang.reflect.Field);
    Code:
       0: aload_0
       1: invokespecial #1                  // Method java/lang/Object."<init>":()V
       4: aload_0
       5: aload_1
       6: putfield      #2                  // Field target:Ljava/lang/Object;
       9: aload_0
      10: aload_2
      11: putfield      #3                  // Field field:Ljava/lang/reflect/Field;
      14: return

  public void set(java.lang.Object);
    Code:
       0: new           #4                  // class org/mockito/internal/util/reflection/AccessibilityChanger
       3: dup
       4: invokespecial #5                  // Method org/mockito/internal/util/reflection/AccessibilityChanger."<init>":()V
       7: astore_2
       8: aload_2
       9: aload_0
      10: getfield      #3                  // Field field:Ljava/lang/reflect/Field;
      13: invokevirtual #6                  // Method org/mockito/internal/util/reflection/AccessibilityChanger.enableAccess:(Ljava/lang/reflect/AccessibleObject;)V
      16: aload_0
      17: getfield      #3                  // Field field:Ljava/lang/reflect/Field;
      20: aload_0
      21: getfield      #2                  // Field target:Ljava/lang/Object;
      24: aload_1
      25: invokevirtual #7                  // Method java/lang/reflect/Field.set:(Ljava/lang/Object;Ljava/lang/Object;)V
      28: goto          159
      31: astore_3
      32: new           #9                  // class java/lang/RuntimeException
      35: dup
      36: new           #10                 // class java/lang/StringBuilder
      39: dup
      40: invokespecial #11                 // Method java/lang/StringBuilder."<init>":()V
      43: ldc           #12                 // String Access not authorized on field \'
      45: invokevirtual #13                 // Method java/lang/StringBuilder.append:(Ljava/lang/String;)Ljava/lang/StringBuilder;
      48: aload_0
      49: getfield      #3                  // Field field:Ljava/lang/reflect/Field;
      52: invokevirtual #14                 // Method java/lang/StringBuilder.append:(Ljava/lang/Object;)Ljava/lang/StringBuilder;
      55: ldc           #15                 // String \' of object \'
      57: invokevirtual #13                 // Method java/lang/StringBuilder.append:(Ljava/lang/String;)Ljava/lang/StringBuilder;
      60: aload_0
      61: getfield      #2                  // Field target:Ljava/lang/Object;
      64: invokevirtual #14                 // Method java/lang/StringBuilder.append:(Ljava/lang/Object;)Ljava/lang/StringBuilder;
      67: ldc           #16                 // String \' with value: \'
      69: invokevirtual #13                 // Method java/lang/StringBuilder.append:(Ljava/lang/String;)Ljava/lang/StringBuilder;
      72: aload_1
      73: invokevirtual #14                 // Method java/lang/StringBuilder.append:(Ljava/lang/Object;)Ljava/lang/StringBuilder;
      76: ldc           #17                 // String \'
      78: invokevirtual #13                 // Method java/lang/StringBuilder.append:(Ljava/lang/String;)Ljava/lang/StringBuilder;
      81: invokevirtual #18                 // Method java/lang/StringBuilder.toString:()Ljava/lang/String;
      84: aload_3
      85: invokespecial #19                 // Method java/lang/RuntimeException."<init>":(Ljava/lang/String;Ljava/lang/Throwable;)V
      88: athrow
      89: astore_3
      90: new           #9                  // class java/lang/RuntimeException
      93: dup
      94: new           #10                 // class java/lang/StringBuilder
      97: dup
      98: invokespecial #11                 // Method java/lang/StringBuilder."<init>":()V
     101: ldc           #21                 // String Wrong argument on field \'
     103: invokevirtual #13                 // Method java/lang/StringBuilder.append:(Ljava/lang/String;)Ljava/lang/StringBuilder;
     106: aload_0
     107: getfield      #3                  // Field field:Ljava/lang/reflect/Field;
     110: invokevirtual #14                 // Method java/lang/StringBuilder.append:(Ljava/lang/Object;)Ljava/lang/StringBuilder;
     113: ldc           #15                 // String \' of object \'
     115: invokevirtual #13                 // Method java/lang/StringBuilder.append:(Ljava/lang/String;)Ljava/lang/StringBuilder;
     118: aload_0
     119: getfield      #2                  // Field target:Ljava/lang/Object;
     122: invokevirtual #14                 // Method java/lang/StringBuilder.append:(Ljava/lang/Object;)Ljava/lang/StringBuilder;
     125: ldc           #16                 // String \' with value: \'
     127: invokevirtual #13                 // Method java/lang/StringBuilder.append:(Ljava/lang/String;)Ljava/lang/StringBuilder;
     130: aload_1
     131: invokevirtual #14                 // Method java/lang/StringBuilder.append:(Ljava/lang/Object;)Ljava/lang/StringBuilder;
     134: ldc           #22                 // String \', \n
     136: invokevirtual #13                 // Method java/lang/StringBuilder.append:(Ljava/lang/String;)Ljava/lang/StringBuilder;
     139: ldc           #23                 // String reason :
     141: invokevirtual #13                 // Method java/lang/StringBuilder.append:(Ljava/lang/String;)Ljava/lang/StringBuilder;
     144: aload_3
     145: invokevirtual #24                 // Method java/lang/IllegalArgumentException.getMessage:()Ljava/lang/String;
     148: invokevirtual #13                 // Method java/lang/StringBuilder.append:(Ljava/lang/String;)Ljava/lang/StringBuilder;
     151: invokevirtual #18                 // Method java/lang/StringBuilder.toString:()Ljava/lang/String;
     154: aload_3
     155: invokespecial #19                 // Method java/lang/RuntimeException."<init>":(Ljava/lang/String;Ljava/lang/Throwable;)V
     158: athrow
     159: aload_2
     160: aload_0
     161: getfield      #3                  // Field field:Ljava/lang/reflect/Field;
     164: invokevirtual #25                 // Method org/mockito/internal/util/reflection/AccessibilityChanger.safelyDisableAccess:(Ljava/lang/reflect/AccessibleObject;)V
     167: return
    Exception table:
       from    to  target type
          16    28    31   Class java/lang/IllegalAccessException
          16    28    89   Class java/lang/IllegalArgumentException
}
