Compiled from "ResolveResponse.java"
public class org.sonatype.nexus.client.core.subsystem.artifact.ResolveResponse {
  private final boolean presentLocally;

  private final java.lang.String groupId;

  private final java.lang.String artifactId;

  private final java.lang.String version;

  private final java.lang.String baseVersion;

  private final java.lang.String classifier;

  private final java.lang.String extension;

  private final boolean snapshot;

  private final long snapshotBuildNumber;

  private final long snapshotTimeStamp;

  private final java.lang.String fileName;

  private final java.lang.String sha1;

  private final java.lang.String repositoryPath;

  public org.sonatype.nexus.client.core.subsystem.artifact.ResolveResponse(boolean, java.lang.String, java.lang.String, java.lang.String, java.lang.String, java.lang.String, java.lang.String, boolean, long, long, java.lang.String, java.lang.String, java.lang.String);
    Code:
       0: aload_0
       1: invokespecial #1                  // Method java/lang/Object."<init>":()V
       4: aload_0
       5: iload_1
       6: putfield      #2                  // Field presentLocally:Z
       9: aload_0
      10: aload_2
      11: putfield      #3                  // Field groupId:Ljava/lang/String;
      14: aload_0
      15: aload_3
      16: putfield      #4                  // Field artifactId:Ljava/lang/String;
      19: aload_0
      20: aload         4
      22: putfield      #5                  // Field version:Ljava/lang/String;
      25: aload_0
      26: aload         5
      28: putfield      #6                  // Field baseVersion:Ljava/lang/String;
      31: aload_0
      32: aload         6
      34: putfield      #7                  // Field classifier:Ljava/lang/String;
      37: aload_0
      38: aload         7
      40: putfield      #8                  // Field extension:Ljava/lang/String;
      43: aload_0
      44: iload         8
      46: putfield      #9                  // Field snapshot:Z
      49: aload_0
      50: lload         9
      52: putfield      #10                 // Field snapshotBuildNumber:J
      55: aload_0
      56: lload         11
      58: putfield      #11                 // Field snapshotTimeStamp:J
      61: aload_0
      62: aload         13
      64: putfield      #12                 // Field fileName:Ljava/lang/String;
      67: aload_0
      68: aload         14
      70: putfield      #13                 // Field sha1:Ljava/lang/String;
      73: aload_0
      74: aload         15
      76: putfield      #14                 // Field repositoryPath:Ljava/lang/String;
      79: return

  public boolean isPresentLocally();
    Code:
       0: aload_0
       1: getfield      #2                  // Field presentLocally:Z
       4: ireturn

  public java.lang.String getGroupId();
    Code:
       0: aload_0
       1: getfield      #3                  // Field groupId:Ljava/lang/String;
       4: areturn

  public java.lang.String getArtifactId();
    Code:
       0: aload_0
       1: getfield      #4                  // Field artifactId:Ljava/lang/String;
       4: areturn

  public java.lang.String getVersion();
    Code:
       0: aload_0
       1: getfield      #5                  // Field version:Ljava/lang/String;
       4: areturn

  public java.lang.String getBaseVersion();
    Code:
       0: aload_0
       1: getfield      #6                  // Field baseVersion:Ljava/lang/String;
       4: areturn

  public java.lang.String getClassifier();
    Code:
       0: aload_0
       1: getfield      #7                  // Field classifier:Ljava/lang/String;
       4: areturn

  public java.lang.String getExtension();
    Code:
       0: aload_0
       1: getfield      #8                  // Field extension:Ljava/lang/String;
       4: areturn

  public boolean isSnapshot();
    Code:
       0: aload_0
       1: getfield      #9                  // Field snapshot:Z
       4: ireturn

  public long getSnapshotBuildNumber();
    Code:
       0: aload_0
       1: getfield      #10                 // Field snapshotBuildNumber:J
       4: lreturn

  public long getSnapshotTimeStamp();
    Code:
       0: aload_0
       1: getfield      #11                 // Field snapshotTimeStamp:J
       4: lreturn

  public java.lang.String getFileName();
    Code:
       0: aload_0
       1: getfield      #12                 // Field fileName:Ljava/lang/String;
       4: areturn

  public java.lang.String getSha1();
    Code:
       0: aload_0
       1: getfield      #13                 // Field sha1:Ljava/lang/String;
       4: areturn

  public java.lang.String getRepositoryPath();
    Code:
       0: aload_0
       1: getfield      #14                 // Field repositoryPath:Ljava/lang/String;
       4: areturn
}
