Compiled from "ReadKotlinClassHeaderAnnotationVisitor.java"
class kotlin.reflect.jvm.internal.impl.load.kotlin.header.ReadKotlinClassHeaderAnnotationVisitor$KotlinSerializedIrArgumentVisitor implements kotlin.reflect.jvm.internal.impl.load.kotlin.KotlinJvmBinaryClass$AnnotationArgumentVisitor {
  final kotlin.reflect.jvm.internal.impl.load.kotlin.header.ReadKotlinClassHeaderAnnotationVisitor this$0;

  private kotlin.reflect.jvm.internal.impl.load.kotlin.header.ReadKotlinClassHeaderAnnotationVisitor$KotlinSerializedIrArgumentVisitor(kotlin.reflect.jvm.internal.impl.load.kotlin.header.ReadKotlinClassHeaderAnnotationVisitor);
    Code:
       0: aload_0
       1: aload_1
       2: putfield      #25                 // Field this$0:Lkotlin/reflect/jvm/internal/impl/load/kotlin/header/ReadKotlinClassHeaderAnnotationVisitor;
       5: aload_0
       6: invokespecial #27                 // Method java/lang/Object."<init>":()V
       9: return

  public void visit(kotlin.reflect.jvm.internal.impl.name.Name, java.lang.Object);
    Code:
       0: return

  public void visitClassLiteral(kotlin.reflect.jvm.internal.impl.name.Name, kotlin.reflect.jvm.internal.impl.resolve.constants.ClassLiteralValue);
    Code:
       0: aload_2
       1: ifnonnull     8
       4: iconst_0
       5: invokestatic  #30                 // Method $$$reportNull$$$0:(I)V
       8: return

  public kotlin.reflect.jvm.internal.impl.load.kotlin.KotlinJvmBinaryClass$AnnotationArrayArgumentVisitor visitArray(kotlin.reflect.jvm.internal.impl.name.Name);
    Code:
       0: aload_1
       1: ifnull        11
       4: aload_1
       5: invokevirtual #34                 // Method kotlin/reflect/jvm/internal/impl/name/Name.asString:()Ljava/lang/String;
       8: goto          12
      11: aconst_null
      12: astore_2
      13: ldc           #2                  // String b
      15: aload_2
      16: invokevirtual #28                 // Method java/lang/String.equals:(Ljava/lang/Object;)Z
      19: ifeq          27
      22: aload_0
      23: invokespecial #32                 // Method serializedIrArrayVisitor:()Lkotlin/reflect/jvm/internal/impl/load/kotlin/KotlinJvmBinaryClass$AnnotationArrayArgumentVisitor;
      26: areturn
      27: aconst_null
      28: areturn

  private kotlin.reflect.jvm.internal.impl.load.kotlin.KotlinJvmBinaryClass$AnnotationArrayArgumentVisitor serializedIrArrayVisitor();
    Code:
       0: new           #21                 // class kotlin/reflect/jvm/internal/impl/load/kotlin/header/ReadKotlinClassHeaderAnnotationVisitor$KotlinSerializedIrArgumentVisitor$1
       3: dup
       4: aload_0
       5: invokespecial #33                 // Method kotlin/reflect/jvm/internal/impl/load/kotlin/header/ReadKotlinClassHeaderAnnotationVisitor$KotlinSerializedIrArgumentVisitor$1."<init>":(Lkotlin/reflect/jvm/internal/impl/load/kotlin/header/ReadKotlinClassHeaderAnnotationVisitor$KotlinSerializedIrArgumentVisitor;)V
       8: areturn

  public void visitEnum(kotlin.reflect.jvm.internal.impl.name.Name, kotlin.reflect.jvm.internal.impl.name.ClassId, kotlin.reflect.jvm.internal.impl.name.Name);
    Code:
       0: aload_2
       1: ifnonnull     8
       4: iconst_1
       5: invokestatic  #30                 // Method $$$reportNull$$$0:(I)V
       8: aload_3
       9: ifnonnull     16
      12: iconst_2
      13: invokestatic  #30                 // Method $$$reportNull$$$0:(I)V
      16: return

  public kotlin.reflect.jvm.internal.impl.load.kotlin.KotlinJvmBinaryClass$AnnotationArgumentVisitor visitAnnotation(kotlin.reflect.jvm.internal.impl.name.Name, kotlin.reflect.jvm.internal.impl.name.ClassId);
    Code:
       0: aload_2
       1: ifnonnull     8
       4: iconst_3
       5: invokestatic  #30                 // Method $$$reportNull$$$0:(I)V
       8: aconst_null
       9: areturn

  public void visitEnd();
    Code:
       0: return

  kotlin.reflect.jvm.internal.impl.load.kotlin.header.ReadKotlinClassHeaderAnnotationVisitor$KotlinSerializedIrArgumentVisitor(kotlin.reflect.jvm.internal.impl.load.kotlin.header.ReadKotlinClassHeaderAnnotationVisitor, kotlin.reflect.jvm.internal.impl.load.kotlin.header.ReadKotlinClassHeaderAnnotationVisitor$1);
    Code:
       0: aload_0
       1: aload_1
       2: invokespecial #31                 // Method "<init>":(Lkotlin/reflect/jvm/internal/impl/load/kotlin/header/ReadKotlinClassHeaderAnnotationVisitor;)V
       5: return

  private static void $$$reportNull$$$0(int);
    Code:
       0: ldc           #1                  // String Argument for @NotNull parameter \'%s\' of %s.%s must not be null
       2: iconst_3
       3: anewarray     #13                 // class java/lang/Object
       6: iload_0
       7: tableswitch   { // 0 to 3
                     0: 36
                     1: 44
                     2: 52
                     3: 60
               default: 36
          }
      36: dup
      37: iconst_0
      38: ldc           #4                  // String classLiteralValue
      40: aastore
      41: goto          68
      44: dup
      45: iconst_0
      46: ldc           #5                  // String enumClassId
      48: aastore
      49: goto          68
      52: dup
      53: iconst_0
      54: ldc           #6                  // String enumEntryName
      56: aastore
      57: goto          68
      60: dup
      61: iconst_0
      62: ldc           #3                  // String classId
      64: aastore
      65: goto          68
      68: dup
      69: iconst_1
      70: ldc           #7                  // String kotlin/reflect/jvm/internal/impl/load/kotlin/header/ReadKotlinClassHeaderAnnotationVisitor$KotlinSerializedIrArgumentVisitor
      72: aastore
      73: iload_0
      74: tableswitch   { // 0 to 3
                     0: 104
                     1: 112
                     2: 112
                     3: 120
               default: 104
          }
     104: dup
     105: iconst_2
     106: ldc           #9                  // String visitClassLiteral
     108: aastore
     109: goto          128
     112: dup
     113: iconst_2
     114: ldc           #10                 // String visitEnum
     116: aastore
     117: goto          128
     120: dup
     121: iconst_2
     122: ldc           #8                  // String visitAnnotation
     124: aastore
     125: goto          128
     128: invokestatic  #29                 // Method java/lang/String.format:(Ljava/lang/String;[Ljava/lang/Object;)Ljava/lang/String;
     131: new           #12                 // class java/lang/IllegalArgumentException
     134: dup_x1
     135: swap
     136: invokespecial #26                 // Method java/lang/IllegalArgumentException."<init>":(Ljava/lang/String;)V
     139: athrow
}
