public class org.bouncycastle.jcajce.provider.asymmetric.util.PKCS12BagAttributeCarrierImpl implements org.bouncycastle.jce.interfaces.PKCS12BagAttributeCarrier {
  private java.util.Hashtable pkcs12Attributes;

  private java.util.Vector pkcs12Ordering;

  org.bouncycastle.jcajce.provider.asymmetric.util.PKCS12BagAttributeCarrierImpl(java.util.Hashtable, java.util.Vector);
    Code:
       0: aload_0
       1: invokespecial #108                // Method java/lang/Object."<init>":()V
       4: aload_0
       5: aload_1
       6: putfield      #102                // Field pkcs12Attributes:Ljava/util/Hashtable;
       9: aload_0
      10: aload_2
      11: putfield      #103                // Field pkcs12Ordering:Ljava/util/Vector;
      14: return

  public org.bouncycastle.jcajce.provider.asymmetric.util.PKCS12BagAttributeCarrierImpl();
    Code:
       0: aload_0
       1: new           #51                 // class java/util/Hashtable
       4: dup
       5: invokespecial #109                // Method java/util/Hashtable."<init>":()V
       8: new           #52                 // class java/util/Vector
      11: dup
      12: invokespecial #114                // Method java/util/Vector."<init>":()V
      15: invokespecial #124                // Method "<init>":(Ljava/util/Hashtable;Ljava/util/Vector;)V
      18: return

  public void setBagAttribute(org.bouncycastle.asn1.ASN1ObjectIdentifier, org.bouncycastle.asn1.ASN1Encodable);
    Code:
       0: aload_0
       1: getfield      #102                // Field pkcs12Attributes:Ljava/util/Hashtable;
       4: aload_1
       5: invokevirtual #110                // Method java/util/Hashtable.containsKey:(Ljava/lang/Object;)Z
       8: ifeq          24
      11: aload_0
      12: getfield      #102                // Field pkcs12Attributes:Ljava/util/Hashtable;
      15: aload_1
      16: aload_2
      17: invokevirtual #112                // Method java/util/Hashtable.put:(Ljava/lang/Object;Ljava/lang/Object;)Ljava/lang/Object;
      20: pop
      21: goto          42
      24: aload_0
      25: getfield      #102                // Field pkcs12Attributes:Ljava/util/Hashtable;
      28: aload_1
      29: aload_2
      30: invokevirtual #112                // Method java/util/Hashtable.put:(Ljava/lang/Object;Ljava/lang/Object;)Ljava/lang/Object;
      33: pop
      34: aload_0
      35: getfield      #103                // Field pkcs12Ordering:Ljava/util/Vector;
      38: aload_1
      39: invokevirtual #115                // Method java/util/Vector.addElement:(Ljava/lang/Object;)V
      42: return

  public org.bouncycastle.asn1.ASN1Encodable getBagAttribute(org.bouncycastle.asn1.ASN1ObjectIdentifier);
    Code:
       0: aload_0
       1: getfield      #102                // Field pkcs12Attributes:Ljava/util/Hashtable;
       4: aload_1
       5: invokevirtual #111                // Method java/util/Hashtable.get:(Ljava/lang/Object;)Ljava/lang/Object;
       8: checkcast     #53                 // class org/bouncycastle/asn1/ASN1Encodable
      11: areturn

  public java.util.Enumeration getBagAttributeKeys();
    Code:
       0: aload_0
       1: getfield      #103                // Field pkcs12Ordering:Ljava/util/Vector;
       4: invokevirtual #116                // Method java/util/Vector.elements:()Ljava/util/Enumeration;
       7: areturn

  int size();
    Code:
       0: aload_0
       1: getfield      #103                // Field pkcs12Ordering:Ljava/util/Vector;
       4: invokevirtual #113                // Method java/util/Vector.size:()I
       7: ireturn

  java.util.Hashtable getAttributes();
    Code:
       0: aload_0
       1: getfield      #102                // Field pkcs12Attributes:Ljava/util/Hashtable;
       4: areturn

  java.util.Vector getOrdering();
    Code:
       0: aload_0
       1: getfield      #103                // Field pkcs12Ordering:Ljava/util/Vector;
       4: areturn

  public void writeObject(java.io.ObjectOutputStream) throws java.io.IOException;
    Code:
       0: aload_0
       1: getfield      #103                // Field pkcs12Ordering:Ljava/util/Vector;
       4: invokevirtual #113                // Method java/util/Vector.size:()I
       7: ifne          35
      10: aload_1
      11: new           #51                 // class java/util/Hashtable
      14: dup
      15: invokespecial #109                // Method java/util/Hashtable."<init>":()V
      18: invokevirtual #107                // Method java/io/ObjectOutputStream.writeObject:(Ljava/lang/Object;)V
      21: aload_1
      22: new           #52                 // class java/util/Vector
      25: dup
      26: invokespecial #114                // Method java/util/Vector."<init>":()V
      29: invokevirtual #107                // Method java/io/ObjectOutputStream.writeObject:(Ljava/lang/Object;)V
      32: goto          109
      35: new           #44                 // class java/io/ByteArrayOutputStream
      38: dup
      39: invokespecial #104                // Method java/io/ByteArrayOutputStream."<init>":()V
      42: astore_2
      43: aload_2
      44: invokestatic  #122                // Method org/bouncycastle/asn1/ASN1OutputStream.create:(Ljava/io/OutputStream;)Lorg/bouncycastle/asn1/ASN1OutputStream;
      47: astore_3
      48: aload_0
      49: invokevirtual #123                // Method getBagAttributeKeys:()Ljava/util/Enumeration;
      52: astore        4
      54: aload         4
      56: invokeinterface #126,  1          // InterfaceMethod java/util/Enumeration.hasMoreElements:()Z
      61: ifeq          101
      64: aload         4
      66: invokeinterface #127,  1          // InterfaceMethod java/util/Enumeration.nextElement:()Ljava/lang/Object;
      71: invokestatic  #119                // Method org/bouncycastle/asn1/ASN1ObjectIdentifier.getInstance:(Ljava/lang/Object;)Lorg/bouncycastle/asn1/ASN1ObjectIdentifier;
      74: astore        5
      76: aload_3
      77: aload         5
      79: invokevirtual #121                // Method org/bouncycastle/asn1/ASN1OutputStream.writeObject:(Lorg/bouncycastle/asn1/ASN1Primitive;)V
      82: aload_3
      83: aload_0
      84: getfield      #102                // Field pkcs12Attributes:Ljava/util/Hashtable;
      87: aload         5
      89: invokevirtual #111                // Method java/util/Hashtable.get:(Ljava/lang/Object;)Ljava/lang/Object;
      92: checkcast     #53                 // class org/bouncycastle/asn1/ASN1Encodable
      95: invokevirtual #120                // Method org/bouncycastle/asn1/ASN1OutputStream.writeObject:(Lorg/bouncycastle/asn1/ASN1Encodable;)V
      98: goto          54
     101: aload_1
     102: aload_2
     103: invokevirtual #105                // Method java/io/ByteArrayOutputStream.toByteArray:()[B
     106: invokevirtual #107                // Method java/io/ObjectOutputStream.writeObject:(Ljava/lang/Object;)V
     109: return

  public void readObject(java.io.ObjectInputStream) throws java.io.IOException, java.lang.ClassNotFoundException;
    Code:
       0: aload_1
       1: invokevirtual #106                // Method java/io/ObjectInputStream.readObject:()Ljava/lang/Object;
       4: astore_2
       5: aload_2
       6: instanceof    #51                 // class java/util/Hashtable
       9: ifeq          34
      12: aload_0
      13: aload_2
      14: checkcast     #51                 // class java/util/Hashtable
      17: putfield      #102                // Field pkcs12Attributes:Ljava/util/Hashtable;
      20: aload_0
      21: aload_1
      22: invokevirtual #106                // Method java/io/ObjectInputStream.readObject:()Ljava/lang/Object;
      25: checkcast     #52                 // class java/util/Vector
      28: putfield      #103                // Field pkcs12Ordering:Ljava/util/Vector;
      31: goto          75
      34: new           #54                 // class org/bouncycastle/asn1/ASN1InputStream
      37: dup
      38: aload_2
      39: checkcast     #43                 // class "[B"
      42: checkcast     #43                 // class "[B"
      45: invokespecial #117                // Method org/bouncycastle/asn1/ASN1InputStream."<init>":([B)V
      48: astore_3
      49: aload_3
      50: invokevirtual #118                // Method org/bouncycastle/asn1/ASN1InputStream.readObject:()Lorg/bouncycastle/asn1/ASN1Primitive;
      53: checkcast     #55                 // class org/bouncycastle/asn1/ASN1ObjectIdentifier
      56: dup
      57: astore        4
      59: ifnull        75
      62: aload_0
      63: aload         4
      65: aload_3
      66: invokevirtual #118                // Method org/bouncycastle/asn1/ASN1InputStream.readObject:()Lorg/bouncycastle/asn1/ASN1Primitive;
      69: invokevirtual #125                // Method setBagAttribute:(Lorg/bouncycastle/asn1/ASN1ObjectIdentifier;Lorg/bouncycastle/asn1/ASN1Encodable;)V
      72: goto          49
      75: return
}
