Compiled from "JmsPoolConnectionFactoryFactory.java"
public class org.springframework.boot.autoconfigure.jms.JmsPoolConnectionFactoryFactory {
  private final org.springframework.boot.autoconfigure.jms.JmsPoolConnectionFactoryProperties properties;

  public org.springframework.boot.autoconfigure.jms.JmsPoolConnectionFactoryFactory(org.springframework.boot.autoconfigure.jms.JmsPoolConnectionFactoryProperties);
    Code:
       0: aload_0
       1: invokespecial #1                  // Method java/lang/Object."<init>":()V
       4: aload_0
       5: aload_1
       6: putfield      #2                  // Field properties:Lorg/springframework/boot/autoconfigure/jms/JmsPoolConnectionFactoryProperties;
       9: return

  public org.messaginghub.pooled.jms.JmsPoolConnectionFactory createPooledConnectionFactory(javax.jms.ConnectionFactory);
    Code:
       0: new           #3                  // class org/messaginghub/pooled/jms/JmsPoolConnectionFactory
       3: dup
       4: invokespecial #4                  // Method org/messaginghub/pooled/jms/JmsPoolConnectionFactory."<init>":()V
       7: astore_2
       8: aload_2
       9: aload_1
      10: invokevirtual #5                  // Method org/messaginghub/pooled/jms/JmsPoolConnectionFactory.setConnectionFactory:(Ljava/lang/Object;)V
      13: aload_2
      14: aload_0
      15: getfield      #2                  // Field properties:Lorg/springframework/boot/autoconfigure/jms/JmsPoolConnectionFactoryProperties;
      18: invokevirtual #6                  // Method org/springframework/boot/autoconfigure/jms/JmsPoolConnectionFactoryProperties.isBlockIfFull:()Z
      21: invokevirtual #7                  // Method org/messaginghub/pooled/jms/JmsPoolConnectionFactory.setBlockIfSessionPoolIsFull:(Z)V
      24: aload_0
      25: getfield      #2                  // Field properties:Lorg/springframework/boot/autoconfigure/jms/JmsPoolConnectionFactoryProperties;
      28: invokevirtual #8                  // Method org/springframework/boot/autoconfigure/jms/JmsPoolConnectionFactoryProperties.getBlockIfFullTimeout:()Ljava/time/Duration;
      31: ifnull        48
      34: aload_2
      35: aload_0
      36: getfield      #2                  // Field properties:Lorg/springframework/boot/autoconfigure/jms/JmsPoolConnectionFactoryProperties;
      39: invokevirtual #8                  // Method org/springframework/boot/autoconfigure/jms/JmsPoolConnectionFactoryProperties.getBlockIfFullTimeout:()Ljava/time/Duration;
      42: invokevirtual #9                  // Method java/time/Duration.toMillis:()J
      45: invokevirtual #10                 // Method org/messaginghub/pooled/jms/JmsPoolConnectionFactory.setBlockIfSessionPoolIsFullTimeout:(J)V
      48: aload_0
      49: getfield      #2                  // Field properties:Lorg/springframework/boot/autoconfigure/jms/JmsPoolConnectionFactoryProperties;
      52: invokevirtual #11                 // Method org/springframework/boot/autoconfigure/jms/JmsPoolConnectionFactoryProperties.getIdleTimeout:()Ljava/time/Duration;
      55: ifnull        73
      58: aload_2
      59: aload_0
      60: getfield      #2                  // Field properties:Lorg/springframework/boot/autoconfigure/jms/JmsPoolConnectionFactoryProperties;
      63: invokevirtual #11                 // Method org/springframework/boot/autoconfigure/jms/JmsPoolConnectionFactoryProperties.getIdleTimeout:()Ljava/time/Duration;
      66: invokevirtual #9                  // Method java/time/Duration.toMillis:()J
      69: l2i
      70: invokevirtual #12                 // Method org/messaginghub/pooled/jms/JmsPoolConnectionFactory.setConnectionIdleTimeout:(I)V
      73: aload_2
      74: aload_0
      75: getfield      #2                  // Field properties:Lorg/springframework/boot/autoconfigure/jms/JmsPoolConnectionFactoryProperties;
      78: invokevirtual #13                 // Method org/springframework/boot/autoconfigure/jms/JmsPoolConnectionFactoryProperties.getMaxConnections:()I
      81: invokevirtual #14                 // Method org/messaginghub/pooled/jms/JmsPoolConnectionFactory.setMaxConnections:(I)V
      84: aload_2
      85: aload_0
      86: getfield      #2                  // Field properties:Lorg/springframework/boot/autoconfigure/jms/JmsPoolConnectionFactoryProperties;
      89: invokevirtual #15                 // Method org/springframework/boot/autoconfigure/jms/JmsPoolConnectionFactoryProperties.getMaxSessionsPerConnection:()I
      92: invokevirtual #16                 // Method org/messaginghub/pooled/jms/JmsPoolConnectionFactory.setMaxSessionsPerConnection:(I)V
      95: aload_0
      96: getfield      #2                  // Field properties:Lorg/springframework/boot/autoconfigure/jms/JmsPoolConnectionFactoryProperties;
      99: invokevirtual #17                 // Method org/springframework/boot/autoconfigure/jms/JmsPoolConnectionFactoryProperties.getTimeBetweenExpirationCheck:()Ljava/time/Duration;
     102: ifnull        119
     105: aload_2
     106: aload_0
     107: getfield      #2                  // Field properties:Lorg/springframework/boot/autoconfigure/jms/JmsPoolConnectionFactoryProperties;
     110: invokevirtual #17                 // Method org/springframework/boot/autoconfigure/jms/JmsPoolConnectionFactoryProperties.getTimeBetweenExpirationCheck:()Ljava/time/Duration;
     113: invokevirtual #9                  // Method java/time/Duration.toMillis:()J
     116: invokevirtual #18                 // Method org/messaginghub/pooled/jms/JmsPoolConnectionFactory.setConnectionCheckInterval:(J)V
     119: aload_2
     120: aload_0
     121: getfield      #2                  // Field properties:Lorg/springframework/boot/autoconfigure/jms/JmsPoolConnectionFactoryProperties;
     124: invokevirtual #19                 // Method org/springframework/boot/autoconfigure/jms/JmsPoolConnectionFactoryProperties.isUseAnonymousProducers:()Z
     127: invokevirtual #20                 // Method org/messaginghub/pooled/jms/JmsPoolConnectionFactory.setUseAnonymousProducers:(Z)V
     130: aload_2
     131: areturn
}
