Compiled from "TextParser.java"
final class org.thymeleaf.templateparser.text.TextParser {
  private final org.thymeleaf.templateparser.text.TextParser$BufferPool pool;

  private final boolean processCommentsAndLiterals;

  private final boolean standardDialectPresent;

  org.thymeleaf.templateparser.text.TextParser(int, int, boolean, boolean);
    Code:
       0: aload_0
       1: invokespecial #1                  // Method java/lang/Object."<init>":()V
       4: aload_0
       5: new           #2                  // class org/thymeleaf/templateparser/text/TextParser$BufferPool
       8: dup
       9: iload_1
      10: iload_2
      11: aconst_null
      12: invokespecial #3                  // Method org/thymeleaf/templateparser/text/TextParser$BufferPool."<init>":(IILorg/thymeleaf/templateparser/text/TextParser$1;)V
      15: putfield      #4                  // Field pool:Lorg/thymeleaf/templateparser/text/TextParser$BufferPool;
      18: aload_0
      19: iload_3
      20: putfield      #5                  // Field processCommentsAndLiterals:Z
      23: aload_0
      24: iload         4
      26: putfield      #6                  // Field standardDialectPresent:Z
      29: return

  public void parse(java.lang.String, org.thymeleaf.templateparser.text.ITextHandler) throws org.thymeleaf.templateparser.text.TextParseException;
    Code:
       0: aload_1
       1: ifnonnull     14
       4: new           #7                  // class java/lang/IllegalArgumentException
       7: dup
       8: ldc           #8                  // String Document cannot be null
      10: invokespecial #9                  // Method java/lang/IllegalArgumentException."<init>":(Ljava/lang/String;)V
      13: athrow
      14: aload_0
      15: new           #10                 // class java/io/StringReader
      18: dup
      19: aload_1
      20: invokespecial #11                 // Method java/io/StringReader."<init>":(Ljava/lang/String;)V
      23: aload_2
      24: invokevirtual #12                 // Method parse:(Ljava/io/Reader;Lorg/thymeleaf/templateparser/text/ITextHandler;)V
      27: return

  public void parse(java.io.Reader, org.thymeleaf.templateparser.text.ITextHandler) throws org.thymeleaf.templateparser.text.TextParseException;
    Code:
       0: aload_1
       1: ifnonnull     14
       4: new           #7                  // class java/lang/IllegalArgumentException
       7: dup
       8: ldc           #13                 // String Reader cannot be null
      10: invokespecial #9                  // Method java/lang/IllegalArgumentException."<init>":(Ljava/lang/String;)V
      13: athrow
      14: aload_2
      15: ifnonnull     28
      18: new           #7                  // class java/lang/IllegalArgumentException
      21: dup
      22: ldc           #14                 // String Handler cannot be null
      24: invokespecial #9                  // Method java/lang/IllegalArgumentException."<init>":(Ljava/lang/String;)V
      27: athrow
      28: aload_2
      29: astore_3
      30: new           #15                 // class org/thymeleaf/templateparser/text/EventProcessorTextHandler
      33: dup
      34: aload_3
      35: invokespecial #16                 // Method org/thymeleaf/templateparser/text/EventProcessorTextHandler."<init>":(Lorg/thymeleaf/templateparser/text/ITextHandler;)V
      38: astore_3
      39: aload_0
      40: getfield      #5                  // Field processCommentsAndLiterals:Z
      43: ifeq          59
      46: new           #17                 // class org/thymeleaf/templateparser/text/CommentProcessorTextHandler
      49: dup
      50: aload_0
      51: getfield      #6                  // Field standardDialectPresent:Z
      54: aload_3
      55: invokespecial #18                 // Method org/thymeleaf/templateparser/text/CommentProcessorTextHandler."<init>":(ZLorg/thymeleaf/templateparser/text/ITextHandler;)V
      58: astore_3
      59: aload_0
      60: aload_1
      61: aload_0
      62: getfield      #4                  // Field pool:Lorg/thymeleaf/templateparser/text/TextParser$BufferPool;
      65: invokestatic  #19                 // Method org/thymeleaf/templateparser/text/TextParser$BufferPool.access$100:(Lorg/thymeleaf/templateparser/text/TextParser$BufferPool;)I
      68: aload_3
      69: invokevirtual #20                 // Method parseDocument:(Ljava/io/Reader;ILorg/thymeleaf/templateparser/text/ITextHandler;)V
      72: return

  void parseDocument(java.io.Reader, int, org.thymeleaf.templateparser.text.ITextHandler) throws org.thymeleaf.templateparser.text.TextParseException;
    Code:
       0: invokestatic  #21                 // Method java/lang/System.nanoTime:()J
       3: lstore        4
       5: aconst_null
       6: astore        6
       8: new           #22                 // class org/thymeleaf/templateparser/text/TextParseStatus
      11: dup
      12: invokespecial #23                 // Method org/thymeleaf/templateparser/text/TextParseStatus."<init>":()V
      15: astore        7
      17: aload_3
      18: lload         4
      20: iconst_1
      21: iconst_1
      22: invokeinterface #24,  5           // InterfaceMethod org/thymeleaf/templateparser/text/ITextHandler.handleDocumentStart:(JII)V
      27: iload_2
      28: istore        8
      30: aload_0
      31: getfield      #4                  // Field pool:Lorg/thymeleaf/templateparser/text/TextParser$BufferPool;
      34: iload         8
      36: invokestatic  #25                 // Method org/thymeleaf/templateparser/text/TextParser$BufferPool.access$200:(Lorg/thymeleaf/templateparser/text/TextParser$BufferPool;I)[C
      39: astore        6
      41: aload_1
      42: aload         6
      44: invokevirtual #26                 // Method java/io/Reader.read:([C)I
      47: istore        9
      49: iload         9
      51: iconst_m1
      52: if_icmpeq     59
      55: iconst_1
      56: goto          60
      59: iconst_0
      60: istore        10
      62: aload         7
      64: iconst_m1
      65: putfield      #27                 // Field org/thymeleaf/templateparser/text/TextParseStatus.offset:I
      68: aload         7
      70: iconst_1
      71: putfield      #28                 // Field org/thymeleaf/templateparser/text/TextParseStatus.line:I
      74: aload         7
      76: iconst_1
      77: putfield      #29                 // Field org/thymeleaf/templateparser/text/TextParseStatus.col:I
      80: aload         7
      82: iconst_0
      83: putfield      #30                 // Field org/thymeleaf/templateparser/text/TextParseStatus.inStructure:Z
      86: aload         7
      88: iconst_0
      89: putfield      #31                 // Field org/thymeleaf/templateparser/text/TextParseStatus.inCommentLine:Z
      92: aload         7
      94: iconst_0
      95: putfield      #32                 // Field org/thymeleaf/templateparser/text/TextParseStatus.literalMarker:C
      98: iload         10
     100: ifeq          301
     103: aload_0
     104: aload         6
     106: iconst_0
     107: iload         9
     109: aload_3
     110: aload         7
     112: invokespecial #33                 // Method parseBuffer:([CIILorg/thymeleaf/templateparser/text/ITextHandler;Lorg/thymeleaf/templateparser/text/TextParseStatus;)V
     115: iconst_0
     116: istore        11
     118: iload         8
     120: istore        12
     122: aload         7
     124: getfield      #27                 // Field org/thymeleaf/templateparser/text/TextParseStatus.offset:I
     127: ifne          209
     130: iload         9
     132: iload         8
     134: if_icmpne     195
     137: aconst_null
     138: astore        13
     140: iload         8
     142: iconst_2
     143: imul
     144: istore        8
     146: aload_0
     147: getfield      #4                  // Field pool:Lorg/thymeleaf/templateparser/text/TextParser$BufferPool;
     150: iload         8
     152: invokestatic  #25                 // Method org/thymeleaf/templateparser/text/TextParser$BufferPool.access$200:(Lorg/thymeleaf/templateparser/text/TextParser$BufferPool;I)[C
     155: astore        13
     157: aload         6
     159: iconst_0
     160: aload         13
     162: iconst_0
     163: iload         9
     165: invokestatic  #34                 // Method java/lang/System.arraycopy:(Ljava/lang/Object;ILjava/lang/Object;II)V
     168: aload_0
     169: getfield      #4                  // Field pool:Lorg/thymeleaf/templateparser/text/TextParser$BufferPool;
     172: aload         6
     174: invokestatic  #35                 // Method org/thymeleaf/templateparser/text/TextParser$BufferPool.access$300:(Lorg/thymeleaf/templateparser/text/TextParser$BufferPool;[C)V
     177: aload         13
     179: astore        6
     181: goto          195
     184: astore        14
     186: aload_0
     187: getfield      #4                  // Field pool:Lorg/thymeleaf/templateparser/text/TextParser$BufferPool;
     190: aload         13
     192: invokestatic  #35                 // Method org/thymeleaf/templateparser/text/TextParser$BufferPool.access$300:(Lorg/thymeleaf/templateparser/text/TextParser$BufferPool;[C)V
     195: iload         9
     197: istore        11
     199: iload         8
     201: iload         11
     203: isub
     204: istore        12
     206: goto          267
     209: aload         7
     211: getfield      #27                 // Field org/thymeleaf/templateparser/text/TextParseStatus.offset:I
     214: iload         9
     216: if_icmpge     267
     219: aload         6
     221: aload         7
     223: getfield      #27                 // Field org/thymeleaf/templateparser/text/TextParseStatus.offset:I
     226: aload         6
     228: iconst_0
     229: iload         9
     231: aload         7
     233: getfield      #27                 // Field org/thymeleaf/templateparser/text/TextParseStatus.offset:I
     236: isub
     237: invokestatic  #34                 // Method java/lang/System.arraycopy:(Ljava/lang/Object;ILjava/lang/Object;II)V
     240: iload         9
     242: aload         7
     244: getfield      #27                 // Field org/thymeleaf/templateparser/text/TextParseStatus.offset:I
     247: isub
     248: istore        11
     250: iload         8
     252: iload         11
     254: isub
     255: istore        12
     257: aload         7
     259: iconst_0
     260: putfield      #27                 // Field org/thymeleaf/templateparser/text/TextParseStatus.offset:I
     263: iload         11
     265: istore        9
     267: aload_1
     268: aload         6
     270: iload         11
     272: iload         12
     274: invokevirtual #37                 // Method java/io/Reader.read:([CII)I
     277: istore        13
     279: iload         13
     281: iconst_m1
     282: if_icmpeq     295
     285: iload         11
     287: iload         13
     289: iadd
     290: istore        9
     292: goto          298
     295: iconst_0
     296: istore        10
     298: goto          98
     301: aload         7
     303: getfield      #28                 // Field org/thymeleaf/templateparser/text/TextParseStatus.line:I
     306: istore        11
     308: aload         7
     310: getfield      #29                 // Field org/thymeleaf/templateparser/text/TextParseStatus.col:I
     313: istore        12
     315: aload         7
     317: getfield      #27                 // Field org/thymeleaf/templateparser/text/TextParseStatus.offset:I
     320: istore        13
     322: iload         9
     324: iload         13
     326: isub
     327: istore        14
     329: iload         14
     331: ifle          472
     334: aload         7
     336: getfield      #30                 // Field org/thymeleaf/templateparser/text/TextParseStatus.inStructure:Z
     339: ifeq          404
     342: aload         7
     344: getfield      #31                 // Field org/thymeleaf/templateparser/text/TextParseStatus.inCommentLine:Z
     347: ifne          404
     350: new           #38                 // class org/thymeleaf/templateparser/text/TextParseException
     353: dup
     354: new           #39                 // class java/lang/StringBuilder
     357: dup
     358: invokespecial #40                 // Method java/lang/StringBuilder."<init>":()V
     361: ldc           #41                 // String Incomplete structure: \"
     363: invokevirtual #42                 // Method java/lang/StringBuilder.append:(Ljava/lang/String;)Ljava/lang/StringBuilder;
     366: new           #43                 // class java/lang/String
     369: dup
     370: aload         6
     372: iload         13
     374: iload         14
     376: invokespecial #44                 // Method java/lang/String."<init>":([CII)V
     379: invokevirtual #42                 // Method java/lang/StringBuilder.append:(Ljava/lang/String;)Ljava/lang/StringBuilder;
     382: ldc           #45                 // String \"
     384: invokevirtual #42                 // Method java/lang/StringBuilder.append:(Ljava/lang/String;)Ljava/lang/StringBuilder;
     387: invokevirtual #46                 // Method java/lang/StringBuilder.toString:()Ljava/lang/String;
     390: aload         7
     392: getfield      #28                 // Field org/thymeleaf/templateparser/text/TextParseStatus.line:I
     395: aload         7
     397: getfield      #29                 // Field org/thymeleaf/templateparser/text/TextParseStatus.col:I
     400: invokespecial #47                 // Method org/thymeleaf/templateparser/text/TextParseException."<init>":(Ljava/lang/String;II)V
     403: athrow
     404: aload_3
     405: aload         6
     407: iload         13
     409: iload         14
     411: aload         7
     413: getfield      #28                 // Field org/thymeleaf/templateparser/text/TextParseStatus.line:I
     416: aload         7
     418: getfield      #29                 // Field org/thymeleaf/templateparser/text/TextParseStatus.col:I
     421: invokeinterface #48,  6           // InterfaceMethod org/thymeleaf/templateparser/text/ITextHandler.handleText:([CIIII)V
     426: iload         13
     428: istore        15
     430: iload         15
     432: iload         13
     434: iload         14
     436: iadd
     437: if_icmpge     472
     440: aload         6
     442: iload         15
     444: caload
     445: istore        16
     447: iload         16
     449: bipush        10
     451: if_icmpne     463
     454: iinc          11, 1
     457: iconst_1
     458: istore        12
     460: goto          466
     463: iinc          12, 1
     466: iinc          15, 1
     469: goto          430
     472: invokestatic  #21                 // Method java/lang/System.nanoTime:()J
     475: lstore        15
     477: aload_3
     478: lload         15
     480: lload         15
     482: lload         4
     484: lsub
     485: iload         11
     487: iload         12
     489: invokeinterface #49,  7           // InterfaceMethod org/thymeleaf/templateparser/text/ITextHandler.handleDocumentEnd:(JJII)V
     494: aload_0
     495: getfield      #4                  // Field pool:Lorg/thymeleaf/templateparser/text/TextParser$BufferPool;
     498: aload         6
     500: invokestatic  #35                 // Method org/thymeleaf/templateparser/text/TextParser$BufferPool.access$300:(Lorg/thymeleaf/templateparser/text/TextParser$BufferPool;[C)V
     503: aload_1
     504: invokevirtual #50                 // Method java/io/Reader.close:()V
     507: goto          555
     510: astore        7
     512: goto          555
     515: astore        7
     517: aload         7
     519: athrow
     520: astore        7
     522: new           #38                 // class org/thymeleaf/templateparser/text/TextParseException
     525: dup
     526: aload         7
     528: invokespecial #52                 // Method org/thymeleaf/templateparser/text/TextParseException."<init>":(Ljava/lang/Throwable;)V
     531: athrow
     532: astore        17
     534: aload_0
     535: getfield      #4                  // Field pool:Lorg/thymeleaf/templateparser/text/TextParser$BufferPool;
     538: aload         6
     540: invokestatic  #35                 // Method org/thymeleaf/templateparser/text/TextParser$BufferPool.access$300:(Lorg/thymeleaf/templateparser/text/TextParser$BufferPool;[C)V
     543: aload_1
     544: invokevirtual #50                 // Method java/io/Reader.close:()V
     547: goto          552
     550: astore        18
     552: aload         17
     554: athrow
     555: return
    Exception table:
       from    to  target type
         140   181   184   Class java/lang/Exception
         503   507   510   Class java/lang/Throwable
           8   494   515   Class org/thymeleaf/templateparser/text/TextParseException
           8   494   520   Class java/lang/Exception
           8   494   532   any
         543   547   550   Class java/lang/Throwable
         515   534   532   any

  private void parseBuffer(char[], int, int, org.thymeleaf.templateparser.text.ITextHandler, org.thymeleaf.templateparser.text.TextParseStatus) throws org.thymeleaf.templateparser.text.TextParseException;
    Code:
       0: iconst_2
       1: newarray       int
       3: dup
       4: iconst_0
       5: aload         5
       7: getfield      #28                 // Field org/thymeleaf/templateparser/text/TextParseStatus.line:I
      10: iastore
      11: dup
      12: iconst_1
      13: aload         5
      15: getfield      #29                 // Field org/thymeleaf/templateparser/text/TextParseStatus.col:I
      18: iastore
      19: astore        6
      21: aload         6
      23: iconst_0
      24: iaload
      25: istore        7
      27: aload         6
      29: iconst_1
      30: iaload
      31: istore        8
      33: iload_2
      34: iload_3
      35: iadd
      36: istore        9
      38: iload_2
      39: istore        10
      41: iload         10
      43: istore        11
      45: iconst_0
      46: istore        14
      48: iconst_0
      49: istore        15
      51: iconst_0
      52: istore        16
      54: iconst_0
      55: istore        17
      57: iconst_0
      58: istore        18
      60: iload         10
      62: istore        19
      64: iload         10
      66: istore        20
      68: iload         10
      70: istore        21
      72: iload         10
      74: iload         9
      76: if_icmpge     1019
      79: iload         14
      81: ifne          104
      84: iload         15
      86: ifne          104
      89: iload         16
      91: ifne          104
      94: iload         17
      96: ifne          104
      99: iload         18
     101: ifeq          108
     104: iconst_1
     105: goto          109
     108: iconst_0
     109: istore        13
     111: iload         13
     113: ifne          661
     116: aload_1
     117: iload         10
     119: iload         9
     121: aload         6
     123: aload_0
     124: getfield      #5                  // Field processCommentsAndLiterals:Z
     127: invokestatic  #53                 // Method org/thymeleaf/templateparser/text/TextParsingUtil.findNextStructureStartOrLiteralMarker:([CII[IZ)I
     130: istore        19
     132: iload         19
     134: iconst_m1
     135: if_icmpne     178
     138: aload         5
     140: iload         11
     142: putfield      #27                 // Field org/thymeleaf/templateparser/text/TextParseStatus.offset:I
     145: aload         5
     147: iload         7
     149: putfield      #28                 // Field org/thymeleaf/templateparser/text/TextParseStatus.line:I
     152: aload         5
     154: iload         8
     156: putfield      #29                 // Field org/thymeleaf/templateparser/text/TextParseStatus.col:I
     159: aload         5
     161: iconst_0
     162: putfield      #30                 // Field org/thymeleaf/templateparser/text/TextParseStatus.inStructure:Z
     165: aload         5
     167: iconst_0
     168: putfield      #31                 // Field org/thymeleaf/templateparser/text/TextParseStatus.inCommentLine:Z
     171: aload         5
     173: iconst_0
     174: putfield      #32                 // Field org/thymeleaf/templateparser/text/TextParseStatus.literalMarker:C
     177: return
     178: aload_1
     179: iload         19
     181: caload
     182: istore        12
     184: aload_1
     185: iload         19
     187: iload         9
     189: invokestatic  #54                 // Method org/thymeleaf/templateparser/text/TextParsingElementUtil.isOpenElementStart:([CII)Z
     192: istore        14
     194: iload         14
     196: ifne          306
     199: aload_1
     200: iload         19
     202: iload         9
     204: invokestatic  #55                 // Method org/thymeleaf/templateparser/text/TextParsingElementUtil.isCloseElementStart:([CII)Z
     207: istore        15
     209: iload         15
     211: ifne          306
     214: aload_0
     215: getfield      #5                  // Field processCommentsAndLiterals:Z
     218: ifeq          306
     221: aload_1
     222: iload         19
     224: iload         9
     226: invokestatic  #56                 // Method org/thymeleaf/templateparser/text/TextParsingCommentUtil.isCommentBlockStart:([CII)Z
     229: istore        16
     231: iload         16
     233: ifne          306
     236: aload_1
     237: iload         19
     239: iload         9
     241: invokestatic  #57                 // Method org/thymeleaf/templateparser/text/TextParsingCommentUtil.isCommentLineStart:([CII)Z
     244: istore        17
     246: iload         17
     248: ifne          306
     251: iload         12
     253: bipush        39
     255: if_icmpeq     283
     258: iload         12
     260: bipush        34
     262: if_icmpeq     283
     265: iload         12
     267: bipush        96
     269: if_icmpeq     283
     272: aload_1
     273: iload         19
     275: iload         9
     277: invokestatic  #58                 // Method org/thymeleaf/templateparser/text/TextParsingLiteralUtil.isRegexLiteralStart:([CII)Z
     280: ifeq          287
     283: iconst_1
     284: goto          288
     287: iconst_0
     288: istore        18
     290: aload         5
     292: iload         18
     294: ifeq          302
     297: iload         12
     299: goto          303
     302: iconst_0
     303: putfield      #32                 // Field org/thymeleaf/templateparser/text/TextParseStatus.literalMarker:C
     306: iload         14
     308: ifne          331
     311: iload         15
     313: ifne          331
     316: iload         16
     318: ifne          331
     321: iload         17
     323: ifne          331
     326: iload         18
     328: ifeq          335
     331: iconst_1
     332: goto          336
     335: iconst_0
     336: istore        13
     338: iload         13
     340: ifeq          352
     343: iload         18
     345: ifne          352
     348: iload         19
     350: istore        20
     352: iload         13
     354: ifne          605
     357: aload         6
     359: iload         12
     361: invokestatic  #59                 // Method org/thymeleaf/templateparser/text/ParsingLocatorUtil.countChar:([IC)V
     364: aload_1
     365: iload         19
     367: iconst_1
     368: iadd
     369: iload         9
     371: aload         6
     373: aload_0
     374: getfield      #5                  // Field processCommentsAndLiterals:Z
     377: invokestatic  #53                 // Method org/thymeleaf/templateparser/text/TextParsingUtil.findNextStructureStartOrLiteralMarker:([CII[IZ)I
     380: istore        19
     382: iload         19
     384: iconst_m1
     385: if_icmpne     428
     388: aload         5
     390: iload         11
     392: putfield      #27                 // Field org/thymeleaf/templateparser/text/TextParseStatus.offset:I
     395: aload         5
     397: iload         7
     399: putfield      #28                 // Field org/thymeleaf/templateparser/text/TextParseStatus.line:I
     402: aload         5
     404: iload         8
     406: putfield      #29                 // Field org/thymeleaf/templateparser/text/TextParseStatus.col:I
     409: aload         5
     411: iconst_0
     412: putfield      #30                 // Field org/thymeleaf/templateparser/text/TextParseStatus.inStructure:Z
     415: aload         5
     417: iconst_0
     418: putfield      #31                 // Field org/thymeleaf/templateparser/text/TextParseStatus.inCommentLine:Z
     421: aload         5
     423: iconst_0
     424: putfield      #32                 // Field org/thymeleaf/templateparser/text/TextParseStatus.literalMarker:C
     427: return
     428: aload_1
     429: iload         19
     431: caload
     432: istore        12
     434: aload_1
     435: iload         19
     437: iload         9
     439: invokestatic  #54                 // Method org/thymeleaf/templateparser/text/TextParsingElementUtil.isOpenElementStart:([CII)Z
     442: istore        14
     444: iload         14
     446: ifne          556
     449: aload_1
     450: iload         19
     452: iload         9
     454: invokestatic  #55                 // Method org/thymeleaf/templateparser/text/TextParsingElementUtil.isCloseElementStart:([CII)Z
     457: istore        15
     459: iload         15
     461: ifne          556
     464: aload_0
     465: getfield      #5                  // Field processCommentsAndLiterals:Z
     468: ifeq          556
     471: aload_1
     472: iload         19
     474: iload         9
     476: invokestatic  #56                 // Method org/thymeleaf/templateparser/text/TextParsingCommentUtil.isCommentBlockStart:([CII)Z
     479: istore        16
     481: iload         16
     483: ifne          556
     486: aload_1
     487: iload         19
     489: iload         9
     491: invokestatic  #57                 // Method org/thymeleaf/templateparser/text/TextParsingCommentUtil.isCommentLineStart:([CII)Z
     494: istore        17
     496: iload         17
     498: ifne          556
     501: iload         12
     503: bipush        39
     505: if_icmpeq     533
     508: iload         12
     510: bipush        34
     512: if_icmpeq     533
     515: iload         12
     517: bipush        96
     519: if_icmpeq     533
     522: aload_1
     523: iload         19
     525: iload         9
     527: invokestatic  #58                 // Method org/thymeleaf/templateparser/text/TextParsingLiteralUtil.isRegexLiteralStart:([CII)Z
     530: ifeq          537
     533: iconst_1
     534: goto          538
     537: iconst_0
     538: istore        18
     540: aload         5
     542: iload         18
     544: ifeq          552
     547: iload         12
     549: goto          553
     552: iconst_0
     553: putfield      #32                 // Field org/thymeleaf/templateparser/text/TextParseStatus.literalMarker:C
     556: iload         14
     558: ifne          581
     561: iload         15
     563: ifne          581
     566: iload         16
     568: ifne          581
     571: iload         17
     573: ifne          581
     576: iload         18
     578: ifeq          585
     581: iconst_1
     582: goto          586
     585: iconst_0
     586: istore        13
     588: iload         13
     590: ifeq          352
     593: iload         18
     595: ifne          352
     598: iload         19
     600: istore        20
     602: goto          352
     605: iload         20
     607: iload         11
     609: if_icmple     631
     612: aload         4
     614: aload_1
     615: iload         11
     617: iload         20
     619: iload         11
     621: isub
     622: iload         7
     624: iload         8
     626: invokeinterface #48,  6           // InterfaceMethod org/thymeleaf/templateparser/text/ITextHandler.handleText:([CIIII)V
     631: iload         20
     633: iload         19
     635: if_icmpne     654
     638: iload         20
     640: istore        11
     642: aload         6
     644: iconst_0
     645: iaload
     646: istore        7
     648: aload         6
     650: iconst_1
     651: iaload
     652: istore        8
     654: iload         19
     656: istore        10
     658: goto          72
     661: iload         18
     663: ifeq          684
     666: aload_1
     667: iload         10
     669: iload         9
     671: aload         6
     673: aload         5
     675: getfield      #32                 // Field org/thymeleaf/templateparser/text/TextParseStatus.literalMarker:C
     678: invokestatic  #60                 // Method org/thymeleaf/templateparser/text/TextParsingUtil.findNextLiteralEnd:([CII[IC)I
     681: goto          730
     684: iload         16
     686: ifeq          702
     689: aload_1
     690: iload         10
     692: iload         9
     694: aload         6
     696: invokestatic  #61                 // Method org/thymeleaf/templateparser/text/TextParsingUtil.findNextCommentBlockEnd:([CII[I)I
     699: goto          730
     702: iload         17
     704: ifeq          720
     707: aload_1
     708: iload         10
     710: iload         9
     712: aload         6
     714: invokestatic  #62                 // Method org/thymeleaf/templateparser/text/TextParsingUtil.findNextCommentLineEnd:([CII[I)I
     717: goto          730
     720: aload_1
     721: iload         10
     723: iload         9
     725: aload         6
     727: invokestatic  #63                 // Method org/thymeleaf/templateparser/text/TextParsingUtil.findNextStructureEndAvoidQuotes:([CII[I)I
     730: istore        19
     732: iload         19
     734: ifge          778
     737: aload         5
     739: iload         11
     741: putfield      #27                 // Field org/thymeleaf/templateparser/text/TextParseStatus.offset:I
     744: aload         5
     746: iload         7
     748: putfield      #28                 // Field org/thymeleaf/templateparser/text/TextParseStatus.line:I
     751: aload         5
     753: iload         8
     755: putfield      #29                 // Field org/thymeleaf/templateparser/text/TextParseStatus.col:I
     758: aload         5
     760: iconst_1
     761: putfield      #30                 // Field org/thymeleaf/templateparser/text/TextParseStatus.inStructure:Z
     764: aload         5
     766: iload         17
     768: putfield      #31                 // Field org/thymeleaf/templateparser/text/TextParseStatus.inCommentLine:Z
     771: aload         5
     773: iconst_0
     774: putfield      #32                 // Field org/thymeleaf/templateparser/text/TextParseStatus.literalMarker:C
     777: return
     778: iload         14
     780: ifeq          845
     783: iload         19
     785: istore        21
     787: aload_1
     788: iload         21
     790: iconst_1
     791: isub
     792: caload
     793: bipush        47
     795: if_icmpne     820
     798: aload_1
     799: iload         11
     801: iload         21
     803: iload         11
     805: isub
     806: iconst_1
     807: iadd
     808: iload         7
     810: iload         8
     812: aload         4
     814: invokestatic  #64                 // Method org/thymeleaf/templateparser/text/TextParsingElementUtil.parseStandaloneElement:([CIIIILorg/thymeleaf/templateparser/text/ITextHandler;)V
     817: goto          839
     820: aload_1
     821: iload         11
     823: iload         21
     825: iload         11
     827: isub
     828: iconst_1
     829: iadd
     830: iload         7
     832: iload         8
     834: aload         4
     836: invokestatic  #65                 // Method org/thymeleaf/templateparser/text/TextParsingElementUtil.parseOpenElement:([CIIIILorg/thymeleaf/templateparser/text/ITextHandler;)V
     839: iconst_0
     840: istore        14
     842: goto          976
     845: iload         15
     847: ifeq          879
     850: iload         19
     852: istore        21
     854: aload_1
     855: iload         11
     857: iload         21
     859: iload         11
     861: isub
     862: iconst_1
     863: iadd
     864: iload         7
     866: iload         8
     868: aload         4
     870: invokestatic  #66                 // Method org/thymeleaf/templateparser/text/TextParsingElementUtil.parseCloseElement:([CIIIILorg/thymeleaf/templateparser/text/ITextHandler;)V
     873: iconst_0
     874: istore        15
     876: goto          976
     879: iload         16
     881: ifeq          913
     884: iload         19
     886: istore        21
     888: aload_1
     889: iload         11
     891: iload         21
     893: iload         11
     895: isub
     896: iconst_1
     897: iadd
     898: iload         7
     900: iload         8
     902: aload         4
     904: invokestatic  #67                 // Method org/thymeleaf/templateparser/text/TextParsingCommentUtil.parseComment:([CIIIILorg/thymeleaf/templateparser/text/ITextHandler;)V
     907: iconst_0
     908: istore        16
     910: goto          976
     913: iload         17
     915: ifeq          949
     918: iload         19
     920: istore        21
     922: aload         4
     924: aload_1
     925: iload         11
     927: iload         21
     929: iload         11
     931: isub
     932: iconst_1
     933: iadd
     934: iload         7
     936: iload         8
     938: invokeinterface #48,  6           // InterfaceMethod org/thymeleaf/templateparser/text/ITextHandler.handleText:([CIIII)V
     943: iconst_0
     944: istore        17
     946: goto          976
     949: iload         18
     951: ifeq          966
     954: iconst_0
     955: istore        18
     957: aload         5
     959: iconst_0
     960: putfield      #32                 // Field org/thymeleaf/templateparser/text/TextParseStatus.literalMarker:C
     963: goto          976
     966: new           #68                 // class java/lang/IllegalStateException
     969: dup
     970: ldc           #69                 // String Illegal parsing state: structure is not of a recognized type
     972: invokespecial #70                 // Method java/lang/IllegalStateException."<init>":(Ljava/lang/String;)V
     975: athrow
     976: aload         6
     978: aload_1
     979: iload         19
     981: caload
     982: invokestatic  #59                 // Method org/thymeleaf/templateparser/text/ParsingLocatorUtil.countChar:([IC)V
     985: iload         21
     987: iload         19
     989: if_icmpne     1010
     992: iload         21
     994: iconst_1
     995: iadd
     996: istore        11
     998: aload         6
    1000: iconst_0
    1001: iaload
    1002: istore        7
    1004: aload         6
    1006: iconst_1
    1007: iaload
    1008: istore        8
    1010: iload         19
    1012: iconst_1
    1013: iadd
    1014: istore        10
    1016: goto          72
    1019: aload         5
    1021: iload         11
    1023: putfield      #27                 // Field org/thymeleaf/templateparser/text/TextParseStatus.offset:I
    1026: aload         5
    1028: iload         7
    1030: putfield      #28                 // Field org/thymeleaf/templateparser/text/TextParseStatus.line:I
    1033: aload         5
    1035: iload         8
    1037: putfield      #29                 // Field org/thymeleaf/templateparser/text/TextParseStatus.col:I
    1040: aload         5
    1042: iconst_0
    1043: putfield      #30                 // Field org/thymeleaf/templateparser/text/TextParseStatus.inStructure:Z
    1046: aload         5
    1048: iconst_0
    1049: putfield      #31                 // Field org/thymeleaf/templateparser/text/TextParseStatus.inCommentLine:Z
    1052: aload         5
    1054: iconst_0
    1055: putfield      #32                 // Field org/thymeleaf/templateparser/text/TextParseStatus.literalMarker:C
    1058: return
}
