Compiled from "PredicatedHandlersParser.java"
class io.undertow.server.handlers.builder.PredicatedHandlersParser$OperatorNode implements io.undertow.server.handlers.builder.PredicatedHandlersParser$Node {
  private final io.undertow.server.handlers.builder.PredicatedHandlersParser$Token token;

  private io.undertow.server.handlers.builder.PredicatedHandlersParser$OperatorNode(io.undertow.server.handlers.builder.PredicatedHandlersParser$Token);
    Code:
       0: aload_0
       1: invokespecial #3                  // Method java/lang/Object."<init>":()V
       4: aload_0
       5: aload_1
       6: putfield      #1                  // Field token:Lio/undertow/server/handlers/builder/PredicatedHandlersParser$Token;
       9: return

  public io.undertow.server.handlers.builder.PredicatedHandlersParser$Token getToken();
    Code:
       0: aload_0
       1: getfield      #1                  // Field token:Lio/undertow/server/handlers/builder/PredicatedHandlersParser$Token;
       4: areturn

  io.undertow.server.handlers.builder.PredicatedHandlersParser$OperatorNode(io.undertow.server.handlers.builder.PredicatedHandlersParser$Token, io.undertow.server.handlers.builder.PredicatedHandlersParser$1);
    Code:
       0: aload_0
       1: aload_1
       2: invokespecial #2                  // Method "<init>":(Lio/undertow/server/handlers/builder/PredicatedHandlersParser$Token;)V
       5: return

  static io.undertow.server.handlers.builder.PredicatedHandlersParser$Token access$100(io.undertow.server.handlers.builder.PredicatedHandlersParser$OperatorNode);
    Code:
       0: aload_0
       1: getfield      #1                  // Field token:Lio/undertow/server/handlers/builder/PredicatedHandlersParser$Token;
       4: areturn
}
