Compiled from "AccessLogSettingConsumer.java"
public interface org.wildfly.swarm.config.undertow.server.host.AccessLogSettingConsumer<T extends org.wildfly.swarm.config.undertow.server.host.AccessLogSetting<T>> {
  public abstract void accept(T);

  public default org.wildfly.swarm.config.undertow.server.host.AccessLogSettingConsumer<T> andThen(org.wildfly.swarm.config.undertow.server.host.AccessLogSettingConsumer<T>);
    Code:
       0: aload_0
       1: aload_1
       2: invokedynamic #1,  0              // InvokeDynamic #0:accept:(Lorg/wildfly/swarm/config/undertow/server/host/AccessLogSettingConsumer;Lorg/wildfly/swarm/config/undertow/server/host/AccessLogSettingConsumer;)Lorg/wildfly/swarm/config/undertow/server/host/AccessLogSettingConsumer;
       7: areturn

  private void lambda$andThen$339(org.wildfly.swarm.config.undertow.server.host.AccessLogSettingConsumer, org.wildfly.swarm.config.undertow.server.host.AccessLogSetting);
    Code:
       0: aload_0
       1: aload_2
       2: invokeinterface #2,  2            // InterfaceMethod accept:(Lorg/wildfly/swarm/config/undertow/server/host/AccessLogSetting;)V
       7: aload_1
       8: aload_2
       9: invokeinterface #2,  2            // InterfaceMethod accept:(Lorg/wildfly/swarm/config/undertow/server/host/AccessLogSetting;)V
      14: return
}
