Compiled from "DefaultPanoramaAsyncClientBuilder.java"
final class software.amazon.awssdk.services.panorama.DefaultPanoramaAsyncClientBuilder extends software.amazon.awssdk.services.panorama.DefaultPanoramaBaseClientBuilder<software.amazon.awssdk.services.panorama.PanoramaAsyncClientBuilder, software.amazon.awssdk.services.panorama.PanoramaAsyncClient> implements software.amazon.awssdk.services.panorama.PanoramaAsyncClientBuilder {
  software.amazon.awssdk.services.panorama.DefaultPanoramaAsyncClientBuilder();
    Code:
       0: aload_0
       1: invokespecial #1                  // Method software/amazon/awssdk/services/panorama/DefaultPanoramaBaseClientBuilder."<init>":()V
       4: return

  public software.amazon.awssdk.services.panorama.DefaultPanoramaAsyncClientBuilder endpointProvider(software.amazon.awssdk.services.panorama.endpoints.PanoramaEndpointProvider);
    Code:
       0: aload_0
       1: getfield      #2                  // Field clientConfiguration:Lsoftware/amazon/awssdk/core/client/config/SdkClientConfiguration$Builder;
       4: getstatic     #3                  // Field software/amazon/awssdk/core/client/config/SdkClientOption.ENDPOINT_PROVIDER:Lsoftware/amazon/awssdk/core/client/config/SdkClientOption;
       7: aload_1
       8: invokevirtual #4                  // Method software/amazon/awssdk/core/client/config/SdkClientConfiguration$Builder.option:(Lsoftware/amazon/awssdk/core/client/config/ClientOption;Ljava/lang/Object;)Lsoftware/amazon/awssdk/core/client/config/SdkClientConfiguration$Builder;
      11: pop
      12: aload_0
      13: areturn

  protected final software.amazon.awssdk.services.panorama.PanoramaAsyncClient buildClient();
    Code:
       0: aload_0
       1: invokespecial #5                  // Method software/amazon/awssdk/services/panorama/DefaultPanoramaBaseClientBuilder.asyncClientConfiguration:()Lsoftware/amazon/awssdk/core/client/config/SdkClientConfiguration;
       4: astore_1
       5: aload_0
       6: pop
       7: aload_1
       8: invokestatic  #6                  // Method validateClientOptions:(Lsoftware/amazon/awssdk/core/client/config/SdkClientConfiguration;)V
      11: new           #7                  // class software/amazon/awssdk/services/panorama/DefaultPanoramaAsyncClient
      14: dup
      15: aload_1
      16: invokespecial #8                  // Method software/amazon/awssdk/services/panorama/DefaultPanoramaAsyncClient."<init>":(Lsoftware/amazon/awssdk/core/client/config/SdkClientConfiguration;)V
      19: areturn

  protected java.lang.Object buildClient();
    Code:
       0: aload_0
       1: invokevirtual #9                  // Method buildClient:()Lsoftware/amazon/awssdk/services/panorama/PanoramaAsyncClient;
       4: areturn

  public software.amazon.awssdk.core.client.builder.SdkAsyncClientBuilder httpClientBuilder(software.amazon.awssdk.http.async.SdkAsyncHttpClient$Builder);
    Code:
       0: aload_0
       1: aload_1
       2: invokespecial #10                 // Method software/amazon/awssdk/services/panorama/DefaultPanoramaBaseClientBuilder.httpClientBuilder:(Lsoftware/amazon/awssdk/http/async/SdkAsyncHttpClient$Builder;)Lsoftware/amazon/awssdk/core/client/builder/SdkClientBuilder;
       5: checkcast     #11                 // class software/amazon/awssdk/core/client/builder/SdkAsyncClientBuilder
       8: areturn

  public software.amazon.awssdk.core.client.builder.SdkAsyncClientBuilder httpClient(software.amazon.awssdk.http.async.SdkAsyncHttpClient);
    Code:
       0: aload_0
       1: aload_1
       2: invokespecial #12                 // Method software/amazon/awssdk/services/panorama/DefaultPanoramaBaseClientBuilder.httpClient:(Lsoftware/amazon/awssdk/http/async/SdkAsyncHttpClient;)Lsoftware/amazon/awssdk/core/client/builder/SdkClientBuilder;
       5: checkcast     #11                 // class software/amazon/awssdk/core/client/builder/SdkAsyncClientBuilder
       8: areturn

  public software.amazon.awssdk.core.client.builder.SdkAsyncClientBuilder asyncConfiguration(software.amazon.awssdk.core.client.config.ClientAsyncConfiguration);
    Code:
       0: aload_0
       1: aload_1
       2: invokespecial #13                 // Method software/amazon/awssdk/services/panorama/DefaultPanoramaBaseClientBuilder.asyncConfiguration:(Lsoftware/amazon/awssdk/core/client/config/ClientAsyncConfiguration;)Lsoftware/amazon/awssdk/core/client/builder/SdkClientBuilder;
       5: checkcast     #11                 // class software/amazon/awssdk/core/client/builder/SdkAsyncClientBuilder
       8: areturn

  public software.amazon.awssdk.services.panorama.PanoramaBaseClientBuilder endpointProvider(software.amazon.awssdk.services.panorama.endpoints.PanoramaEndpointProvider);
    Code:
       0: aload_0
       1: aload_1
       2: invokevirtual #14                 // Method endpointProvider:(Lsoftware/amazon/awssdk/services/panorama/endpoints/PanoramaEndpointProvider;)Lsoftware/amazon/awssdk/services/panorama/DefaultPanoramaAsyncClientBuilder;
       5: areturn
}
