Compiled from "CodahaleHealthChecker.java"
public final class com.zaxxer.hikari.metrics.dropwizard.CodahaleHealthChecker {
  public static void registerHealthChecks(com.zaxxer.hikari.pool.HikariPool, com.zaxxer.hikari.HikariConfig, com.codahale.metrics.health.HealthCheckRegistry);
    Code:
       0: aload_1
       1: invokevirtual #1                  // Method com/zaxxer/hikari/HikariConfig.getHealthCheckProperties:()Ljava/util/Properties;
       4: astore_3
       5: aload_1
       6: invokevirtual #2                  // Method com/zaxxer/hikari/HikariConfig.getMetricRegistry:()Ljava/lang/Object;
       9: checkcast     #3                  // class com/codahale/metrics/MetricRegistry
      12: astore        4
      14: aload_3
      15: ldc           #4                  // String connectivityCheckTimeoutMs
      17: aload_1
      18: invokevirtual #5                  // Method com/zaxxer/hikari/HikariConfig.getConnectionTimeout:()J
      21: invokestatic  #6                  // Method java/lang/String.valueOf:(J)Ljava/lang/String;
      24: invokevirtual #7                  // Method java/util/Properties.getProperty:(Ljava/lang/String;Ljava/lang/String;)Ljava/lang/String;
      27: invokestatic  #8                  // Method java/lang/Long.parseLong:(Ljava/lang/String;)J
      30: lstore        5
      32: aload_2
      33: aload_1
      34: invokevirtual #9                  // Method com/zaxxer/hikari/HikariConfig.getPoolName:()Ljava/lang/String;
      37: iconst_2
      38: anewarray     #10                 // class java/lang/String
      41: dup
      42: iconst_0
      43: ldc           #11                 // String pool
      45: aastore
      46: dup
      47: iconst_1
      48: ldc           #12                 // String ConnectivityCheck
      50: aastore
      51: invokestatic  #13                 // Method com/codahale/metrics/MetricRegistry.name:(Ljava/lang/String;[Ljava/lang/String;)Ljava/lang/String;
      54: new           #14                 // class com/zaxxer/hikari/metrics/dropwizard/CodahaleHealthChecker$ConnectivityHealthCheck
      57: dup
      58: aload_0
      59: lload         5
      61: invokespecial #15                 // Method com/zaxxer/hikari/metrics/dropwizard/CodahaleHealthChecker$ConnectivityHealthCheck."<init>":(Lcom/zaxxer/hikari/pool/HikariPool;J)V
      64: invokevirtual #16                 // Method com/codahale/metrics/health/HealthCheckRegistry.register:(Ljava/lang/String;Lcom/codahale/metrics/health/HealthCheck;)V
      67: aload_3
      68: ldc           #17                 // String expected99thPercentileMs
      70: ldc           #18                 // String 0
      72: invokevirtual #7                  // Method java/util/Properties.getProperty:(Ljava/lang/String;Ljava/lang/String;)Ljava/lang/String;
      75: invokestatic  #8                  // Method java/lang/Long.parseLong:(Ljava/lang/String;)J
      78: lstore        7
      80: aload         4
      82: ifnull        183
      85: lload         7
      87: lconst_0
      88: lcmp
      89: ifle          183
      92: aload         4
      94: new           #19                 // class com/zaxxer/hikari/metrics/dropwizard/CodahaleHealthChecker$1
      97: dup
      98: aload_1
      99: invokespecial #20                 // Method com/zaxxer/hikari/metrics/dropwizard/CodahaleHealthChecker$1."<init>":(Lcom/zaxxer/hikari/HikariConfig;)V
     102: invokevirtual #21                 // Method com/codahale/metrics/MetricRegistry.getTimers:(Lcom/codahale/metrics/MetricFilter;)Ljava/util/SortedMap;
     105: astore        9
     107: aload         9
     109: invokeinterface #22,  1           // InterfaceMethod java/util/SortedMap.isEmpty:()Z
     114: ifne          183
     117: aload         9
     119: invokeinterface #23,  1           // InterfaceMethod java/util/SortedMap.entrySet:()Ljava/util/Set;
     124: invokeinterface #24,  1           // InterfaceMethod java/util/Set.iterator:()Ljava/util/Iterator;
     129: invokeinterface #25,  1           // InterfaceMethod java/util/Iterator.next:()Ljava/lang/Object;
     134: checkcast     #26                 // class java/util/Map$Entry
     137: invokeinterface #27,  1           // InterfaceMethod java/util/Map$Entry.getValue:()Ljava/lang/Object;
     142: checkcast     #28                 // class com/codahale/metrics/Timer
     145: astore        10
     147: aload_2
     148: aload_1
     149: invokevirtual #9                  // Method com/zaxxer/hikari/HikariConfig.getPoolName:()Ljava/lang/String;
     152: iconst_2
     153: anewarray     #10                 // class java/lang/String
     156: dup
     157: iconst_0
     158: ldc           #11                 // String pool
     160: aastore
     161: dup
     162: iconst_1
     163: ldc           #29                 // String Connection99Percent
     165: aastore
     166: invokestatic  #13                 // Method com/codahale/metrics/MetricRegistry.name:(Ljava/lang/String;[Ljava/lang/String;)Ljava/lang/String;
     169: new           #30                 // class com/zaxxer/hikari/metrics/dropwizard/CodahaleHealthChecker$Connection99Percent
     172: dup
     173: aload         10
     175: lload         7
     177: invokespecial #31                 // Method com/zaxxer/hikari/metrics/dropwizard/CodahaleHealthChecker$Connection99Percent."<init>":(Lcom/codahale/metrics/Timer;J)V
     180: invokevirtual #16                 // Method com/codahale/metrics/health/HealthCheckRegistry.register:(Ljava/lang/String;Lcom/codahale/metrics/health/HealthCheck;)V
     183: return

  private com.zaxxer.hikari.metrics.dropwizard.CodahaleHealthChecker();
    Code:
       0: aload_0
       1: invokespecial #32                 // Method java/lang/Object."<init>":()V
       4: return
}
