Compiled from "ExtensionValidator.java"
public final class org.apache.catalina.util.ExtensionValidator {
  private static final org.apache.juli.logging.Log log;

  private static final org.apache.tomcat.util.res.StringManager sm;

  private static volatile java.util.List<org.apache.catalina.util.Extension> containerAvailableExtensions;

  private static final java.util.List<org.apache.catalina.util.ManifestResource> containerManifestResources;

  public org.apache.catalina.util.ExtensionValidator();
    Code:
       0: aload_0
       1: invokespecial #1                  // Method java/lang/Object."<init>":()V
       4: return

  public static synchronized boolean validateApplication(org.apache.catalina.WebResourceRoot, org.apache.catalina.Context) throws java.io.IOException;
    Code:
       0: aload_1
       1: invokeinterface #2,  1            // InterfaceMethod org/apache/catalina/Context.getName:()Ljava/lang/String;
       6: astore_2
       7: new           #3                  // class java/util/ArrayList
      10: dup
      11: invokespecial #4                  // Method java/util/ArrayList."<init>":()V
      14: astore_3
      15: aload_0
      16: ldc           #5                  // String /META-INF/MANIFEST.MF
      18: invokeinterface #6,  2            // InterfaceMethod org/apache/catalina/WebResourceRoot.getResource:(Ljava/lang/String;)Lorg/apache/catalina/WebResource;
      23: astore        4
      25: aload         4
      27: invokeinterface #7,  1            // InterfaceMethod org/apache/catalina/WebResource.isFile:()Z
      32: ifeq          174
      35: aload         4
      37: invokeinterface #8,  1            // InterfaceMethod org/apache/catalina/WebResource.getInputStream:()Ljava/io/InputStream;
      42: astore        5
      44: aconst_null
      45: astore        6
      47: new           #9                  // class java/util/jar/Manifest
      50: dup
      51: aload         5
      53: invokespecial #10                 // Method java/util/jar/Manifest."<init>":(Ljava/io/InputStream;)V
      56: astore        7
      58: new           #11                 // class org/apache/catalina/util/ManifestResource
      61: dup
      62: getstatic     #12                 // Field sm:Lorg/apache/tomcat/util/res/StringManager;
      65: ldc           #13                 // String extensionValidator.web-application-manifest
      67: invokevirtual #14                 // Method org/apache/tomcat/util/res/StringManager.getString:(Ljava/lang/String;)Ljava/lang/String;
      70: aload         7
      72: iconst_2
      73: invokespecial #15                 // Method org/apache/catalina/util/ManifestResource."<init>":(Ljava/lang/String;Ljava/util/jar/Manifest;I)V
      76: astore        8
      78: aload_3
      79: aload         8
      81: invokeinterface #16,  2           // InterfaceMethod java/util/List.add:(Ljava/lang/Object;)Z
      86: pop
      87: aload         5
      89: ifnull        174
      92: aload         6
      94: ifnull        117
      97: aload         5
      99: invokevirtual #17                 // Method java/io/InputStream.close:()V
     102: goto          174
     105: astore        7
     107: aload         6
     109: aload         7
     111: invokevirtual #19                 // Method java/lang/Throwable.addSuppressed:(Ljava/lang/Throwable;)V
     114: goto          174
     117: aload         5
     119: invokevirtual #17                 // Method java/io/InputStream.close:()V
     122: goto          174
     125: astore        7
     127: aload         7
     129: astore        6
     131: aload         7
     133: athrow
     134: astore        9
     136: aload         5
     138: ifnull        171
     141: aload         6
     143: ifnull        166
     146: aload         5
     148: invokevirtual #17                 // Method java/io/InputStream.close:()V
     151: goto          171
     154: astore        10
     156: aload         6
     158: aload         10
     160: invokevirtual #19                 // Method java/lang/Throwable.addSuppressed:(Ljava/lang/Throwable;)V
     163: goto          171
     166: aload         5
     168: invokevirtual #17                 // Method java/io/InputStream.close:()V
     171: aload         9
     173: athrow
     174: aload_0
     175: ldc           #5                  // String /META-INF/MANIFEST.MF
     177: invokeinterface #20,  2           // InterfaceMethod org/apache/catalina/WebResourceRoot.getClassLoaderResources:(Ljava/lang/String;)[Lorg/apache/catalina/WebResource;
     182: astore        5
     184: aload         5
     186: astore        6
     188: aload         6
     190: arraylength
     191: istore        7
     193: iconst_0
     194: istore        8
     196: iload         8
     198: iload         7
     200: if_icmpge     275
     203: aload         6
     205: iload         8
     207: aaload
     208: astore        9
     210: aload         9
     212: invokeinterface #7,  1            // InterfaceMethod org/apache/catalina/WebResource.isFile:()Z
     217: ifeq          269
     220: aload         9
     222: invokeinterface #21,  1           // InterfaceMethod org/apache/catalina/WebResource.getURL:()Ljava/net/URL;
     227: invokevirtual #22                 // Method java/net/URL.toExternalForm:()Ljava/lang/String;
     230: astore        10
     232: aload         9
     234: invokeinterface #23,  1           // InterfaceMethod org/apache/catalina/WebResource.getManifest:()Ljava/util/jar/Manifest;
     239: astore        11
     241: aload         11
     243: ifnull        269
     246: new           #11                 // class org/apache/catalina/util/ManifestResource
     249: dup
     250: aload         10
     252: aload         11
     254: iconst_3
     255: invokespecial #15                 // Method org/apache/catalina/util/ManifestResource."<init>":(Ljava/lang/String;Ljava/util/jar/Manifest;I)V
     258: astore        12
     260: aload_3
     261: aload         12
     263: invokeinterface #16,  2           // InterfaceMethod java/util/List.add:(Ljava/lang/Object;)Z
     268: pop
     269: iinc          8, 1
     272: goto          196
     275: aload_2
     276: aload_3
     277: invokestatic  #24                 // Method validateManifestResources:(Ljava/lang/String;Ljava/util/List;)Z
     280: ireturn
    Exception table:
       from    to  target type
          97   102   105   Class java/lang/Throwable
          47    87   125   Class java/lang/Throwable
          47    87   134   any
         146   151   154   Class java/lang/Throwable
         125   136   134   any

  public static void addSystemResource(java.io.File) throws java.io.IOException;
    Code:
       0: new           #25                 // class java/io/FileInputStream
       3: dup
       4: aload_0
       5: invokespecial #26                 // Method java/io/FileInputStream."<init>":(Ljava/io/File;)V
       8: astore_1
       9: aconst_null
      10: astore_2
      11: aload_1
      12: invokestatic  #27                 // Method getManifest:(Ljava/io/InputStream;)Ljava/util/jar/Manifest;
      15: astore_3
      16: aload_3
      17: ifnull        46
      20: new           #11                 // class org/apache/catalina/util/ManifestResource
      23: dup
      24: aload_0
      25: invokevirtual #28                 // Method java/io/File.getAbsolutePath:()Ljava/lang/String;
      28: aload_3
      29: iconst_1
      30: invokespecial #15                 // Method org/apache/catalina/util/ManifestResource."<init>":(Ljava/lang/String;Ljava/util/jar/Manifest;I)V
      33: astore        4
      35: getstatic     #29                 // Field containerManifestResources:Ljava/util/List;
      38: aload         4
      40: invokeinterface #16,  2           // InterfaceMethod java/util/List.add:(Ljava/lang/Object;)Z
      45: pop
      46: aload_1
      47: ifnull        117
      50: aload_2
      51: ifnull        70
      54: aload_1
      55: invokevirtual #17                 // Method java/io/InputStream.close:()V
      58: goto          117
      61: astore_3
      62: aload_2
      63: aload_3
      64: invokevirtual #19                 // Method java/lang/Throwable.addSuppressed:(Ljava/lang/Throwable;)V
      67: goto          117
      70: aload_1
      71: invokevirtual #17                 // Method java/io/InputStream.close:()V
      74: goto          117
      77: astore_3
      78: aload_3
      79: astore_2
      80: aload_3
      81: athrow
      82: astore        5
      84: aload_1
      85: ifnull        114
      88: aload_2
      89: ifnull        110
      92: aload_1
      93: invokevirtual #17                 // Method java/io/InputStream.close:()V
      96: goto          114
      99: astore        6
     101: aload_2
     102: aload         6
     104: invokevirtual #19                 // Method java/lang/Throwable.addSuppressed:(Ljava/lang/Throwable;)V
     107: goto          114
     110: aload_1
     111: invokevirtual #17                 // Method java/io/InputStream.close:()V
     114: aload         5
     116: athrow
     117: return
    Exception table:
       from    to  target type
          54    58    61   Class java/lang/Throwable
          11    46    77   Class java/lang/Throwable
          11    46    82   any
          92    96    99   Class java/lang/Throwable
          77    84    82   any

  private static boolean validateManifestResources(java.lang.String, java.util.List<org.apache.catalina.util.ManifestResource>);
    Code:
       0: iconst_1
       1: istore_2
       2: iconst_0
       3: istore_3
       4: aconst_null
       5: astore        4
       7: aload_1
       8: invokeinterface #30,  1           // InterfaceMethod java/util/List.iterator:()Ljava/util/Iterator;
      13: astore        5
      15: aload         5
      17: invokeinterface #31,  1           // InterfaceMethod java/util/Iterator.hasNext:()Z
      22: ifeq          295
      25: aload         5
      27: invokeinterface #32,  1           // InterfaceMethod java/util/Iterator.next:()Ljava/lang/Object;
      32: checkcast     #11                 // class org/apache/catalina/util/ManifestResource
      35: astore        6
      37: aload         6
      39: invokevirtual #33                 // Method org/apache/catalina/util/ManifestResource.getRequiredExtensions:()Ljava/util/ArrayList;
      42: astore        7
      44: aload         7
      46: ifnonnull     52
      49: goto          15
      52: aload         4
      54: ifnonnull     63
      57: aload_1
      58: invokestatic  #34                 // Method buildAvailableExtensionsList:(Ljava/util/List;)Ljava/util/List;
      61: astore        4
      63: getstatic     #35                 // Field containerAvailableExtensions:Ljava/util/List;
      66: ifnonnull     78
      69: getstatic     #29                 // Field containerManifestResources:Ljava/util/List;
      72: invokestatic  #34                 // Method buildAvailableExtensionsList:(Ljava/util/List;)Ljava/util/List;
      75: putstatic     #35                 // Field containerAvailableExtensions:Ljava/util/List;
      78: aload         7
      80: invokevirtual #36                 // Method java/util/ArrayList.iterator:()Ljava/util/Iterator;
      83: astore        8
      85: aload         8
      87: invokeinterface #31,  1           // InterfaceMethod java/util/Iterator.hasNext:()Z
      92: ifeq          292
      95: aload         8
      97: invokeinterface #32,  1           // InterfaceMethod java/util/Iterator.next:()Ljava/lang/Object;
     102: checkcast     #37                 // class org/apache/catalina/util/Extension
     105: astore        9
     107: iconst_0
     108: istore        10
     110: aload         4
     112: ifnull        171
     115: aload         4
     117: invokeinterface #30,  1           // InterfaceMethod java/util/List.iterator:()Ljava/util/Iterator;
     122: astore        11
     124: aload         11
     126: invokeinterface #31,  1           // InterfaceMethod java/util/Iterator.hasNext:()Z
     131: ifeq          171
     134: aload         11
     136: invokeinterface #32,  1           // InterfaceMethod java/util/Iterator.next:()Ljava/lang/Object;
     141: checkcast     #37                 // class org/apache/catalina/util/Extension
     144: astore        12
     146: aload         12
     148: aload         9
     150: invokevirtual #38                 // Method org/apache/catalina/util/Extension.isCompatibleWith:(Lorg/apache/catalina/util/Extension;)Z
     153: ifeq          168
     156: aload         9
     158: iconst_1
     159: invokevirtual #39                 // Method org/apache/catalina/util/Extension.setFulfilled:(Z)V
     162: iconst_1
     163: istore        10
     165: goto          171
     168: goto          124
     171: iload         10
     173: ifne          239
     176: getstatic     #35                 // Field containerAvailableExtensions:Ljava/util/List;
     179: ifnull        239
     182: getstatic     #35                 // Field containerAvailableExtensions:Ljava/util/List;
     185: invokeinterface #30,  1           // InterfaceMethod java/util/List.iterator:()Ljava/util/Iterator;
     190: astore        11
     192: aload         11
     194: invokeinterface #31,  1           // InterfaceMethod java/util/Iterator.hasNext:()Z
     199: ifeq          239
     202: aload         11
     204: invokeinterface #32,  1           // InterfaceMethod java/util/Iterator.next:()Ljava/lang/Object;
     209: checkcast     #37                 // class org/apache/catalina/util/Extension
     212: astore        12
     214: aload         12
     216: aload         9
     218: invokevirtual #38                 // Method org/apache/catalina/util/Extension.isCompatibleWith:(Lorg/apache/catalina/util/Extension;)Z
     221: ifeq          236
     224: aload         9
     226: iconst_1
     227: invokevirtual #39                 // Method org/apache/catalina/util/Extension.setFulfilled:(Z)V
     230: iconst_1
     231: istore        10
     233: goto          239
     236: goto          192
     239: iload         10
     241: ifne          289
     244: getstatic     #40                 // Field log:Lorg/apache/juli/logging/Log;
     247: getstatic     #12                 // Field sm:Lorg/apache/tomcat/util/res/StringManager;
     250: ldc           #41                 // String extensionValidator.extension-not-found-error
     252: iconst_3
     253: anewarray     #42                 // class java/lang/Object
     256: dup
     257: iconst_0
     258: aload_0
     259: aastore
     260: dup
     261: iconst_1
     262: aload         6
     264: invokevirtual #43                 // Method org/apache/catalina/util/ManifestResource.getResourceName:()Ljava/lang/String;
     267: aastore
     268: dup
     269: iconst_2
     270: aload         9
     272: invokevirtual #44                 // Method org/apache/catalina/util/Extension.getExtensionName:()Ljava/lang/String;
     275: aastore
     276: invokevirtual #45                 // Method org/apache/tomcat/util/res/StringManager.getString:(Ljava/lang/String;[Ljava/lang/Object;)Ljava/lang/String;
     279: invokeinterface #46,  2           // InterfaceMethod org/apache/juli/logging/Log.info:(Ljava/lang/Object;)V
     284: iconst_0
     285: istore_2
     286: iinc          3, 1
     289: goto          85
     292: goto          15
     295: iload_2
     296: ifne          345
     299: getstatic     #40                 // Field log:Lorg/apache/juli/logging/Log;
     302: getstatic     #12                 // Field sm:Lorg/apache/tomcat/util/res/StringManager;
     305: ldc           #47                 // String extensionValidator.extension-validation-error
     307: iconst_2
     308: anewarray     #42                 // class java/lang/Object
     311: dup
     312: iconst_0
     313: aload_0
     314: aastore
     315: dup
     316: iconst_1
     317: new           #48                 // class java/lang/StringBuilder
     320: dup
     321: invokespecial #49                 // Method java/lang/StringBuilder."<init>":()V
     324: iload_3
     325: invokevirtual #50                 // Method java/lang/StringBuilder.append:(I)Ljava/lang/StringBuilder;
     328: ldc           #51                 // String
     330: invokevirtual #52                 // Method java/lang/StringBuilder.append:(Ljava/lang/String;)Ljava/lang/StringBuilder;
     333: invokevirtual #53                 // Method java/lang/StringBuilder.toString:()Ljava/lang/String;
     336: aastore
     337: invokevirtual #45                 // Method org/apache/tomcat/util/res/StringManager.getString:(Ljava/lang/String;[Ljava/lang/Object;)Ljava/lang/String;
     340: invokeinterface #46,  2           // InterfaceMethod org/apache/juli/logging/Log.info:(Ljava/lang/Object;)V
     345: iload_2
     346: ireturn

  private static java.util.List<org.apache.catalina.util.Extension> buildAvailableExtensionsList(java.util.List<org.apache.catalina.util.ManifestResource>);
    Code:
       0: aconst_null
       1: astore_1
       2: aload_0
       3: invokeinterface #30,  1           // InterfaceMethod java/util/List.iterator:()Ljava/util/Iterator;
       8: astore_2
       9: aload_2
      10: invokeinterface #31,  1           // InterfaceMethod java/util/Iterator.hasNext:()Z
      15: ifeq          107
      18: aload_2
      19: invokeinterface #32,  1           // InterfaceMethod java/util/Iterator.next:()Ljava/lang/Object;
      24: checkcast     #11                 // class org/apache/catalina/util/ManifestResource
      27: astore_3
      28: aload_3
      29: invokevirtual #54                 // Method org/apache/catalina/util/ManifestResource.getAvailableExtensions:()Ljava/util/ArrayList;
      32: astore        4
      34: aload         4
      36: ifnull        104
      39: aload         4
      41: invokevirtual #36                 // Method java/util/ArrayList.iterator:()Ljava/util/Iterator;
      44: astore        5
      46: aload         5
      48: invokeinterface #31,  1           // InterfaceMethod java/util/Iterator.hasNext:()Z
      53: ifeq          104
      56: aload         5
      58: invokeinterface #32,  1           // InterfaceMethod java/util/Iterator.next:()Ljava/lang/Object;
      63: checkcast     #37                 // class org/apache/catalina/util/Extension
      66: astore        6
      68: aload_1
      69: ifnonnull     92
      72: new           #3                  // class java/util/ArrayList
      75: dup
      76: invokespecial #4                  // Method java/util/ArrayList."<init>":()V
      79: astore_1
      80: aload_1
      81: aload         6
      83: invokeinterface #16,  2           // InterfaceMethod java/util/List.add:(Ljava/lang/Object;)Z
      88: pop
      89: goto          101
      92: aload_1
      93: aload         6
      95: invokeinterface #16,  2           // InterfaceMethod java/util/List.add:(Ljava/lang/Object;)Z
     100: pop
     101: goto          46
     104: goto          9
     107: aload_1
     108: areturn

  private static java.util.jar.Manifest getManifest(java.io.InputStream) throws java.io.IOException;
    Code:
       0: aconst_null
       1: astore_1
       2: new           #55                 // class java/util/jar/JarInputStream
       5: dup
       6: aload_0
       7: invokespecial #56                 // Method java/util/jar/JarInputStream."<init>":(Ljava/io/InputStream;)V
      10: astore_2
      11: aconst_null
      12: astore_3
      13: aload_2
      14: invokevirtual #57                 // Method java/util/jar/JarInputStream.getManifest:()Ljava/util/jar/Manifest;
      17: astore_1
      18: aload_2
      19: ifnull        94
      22: aload_3
      23: ifnull        44
      26: aload_2
      27: invokevirtual #58                 // Method java/util/jar/JarInputStream.close:()V
      30: goto          94
      33: astore        4
      35: aload_3
      36: aload         4
      38: invokevirtual #19                 // Method java/lang/Throwable.addSuppressed:(Ljava/lang/Throwable;)V
      41: goto          94
      44: aload_2
      45: invokevirtual #58                 // Method java/util/jar/JarInputStream.close:()V
      48: goto          94
      51: astore        4
      53: aload         4
      55: astore_3
      56: aload         4
      58: athrow
      59: astore        5
      61: aload_2
      62: ifnull        91
      65: aload_3
      66: ifnull        87
      69: aload_2
      70: invokevirtual #58                 // Method java/util/jar/JarInputStream.close:()V
      73: goto          91
      76: astore        6
      78: aload_3
      79: aload         6
      81: invokevirtual #19                 // Method java/lang/Throwable.addSuppressed:(Ljava/lang/Throwable;)V
      84: goto          91
      87: aload_2
      88: invokevirtual #58                 // Method java/util/jar/JarInputStream.close:()V
      91: aload         5
      93: athrow
      94: aload_1
      95: areturn
    Exception table:
       from    to  target type
          26    30    33   Class java/lang/Throwable
          13    18    51   Class java/lang/Throwable
          13    18    59   any
          69    73    76   Class java/lang/Throwable
          51    61    59   any

  private static void addFolderList(java.lang.String);
    Code:
       0: aload_0
       1: invokestatic  #59                 // Method java/lang/System.getProperty:(Ljava/lang/String;)Ljava/lang/String;
       4: astore_1
       5: aload_1
       6: ifnull        160
       9: new           #60                 // class java/util/StringTokenizer
      12: dup
      13: aload_1
      14: getstatic     #61                 // Field java/io/File.pathSeparator:Ljava/lang/String;
      17: invokespecial #62                 // Method java/util/StringTokenizer."<init>":(Ljava/lang/String;Ljava/lang/String;)V
      20: astore_2
      21: aload_2
      22: invokevirtual #63                 // Method java/util/StringTokenizer.hasMoreTokens:()Z
      25: ifeq          160
      28: new           #64                 // class java/io/File
      31: dup
      32: aload_2
      33: invokevirtual #65                 // Method java/util/StringTokenizer.nextToken:()Ljava/lang/String;
      36: invokespecial #66                 // Method java/io/File."<init>":(Ljava/lang/String;)V
      39: astore_3
      40: aload_3
      41: invokevirtual #67                 // Method java/io/File.isDirectory:()Z
      44: ifne          50
      47: goto          21
      50: aload_3
      51: invokevirtual #68                 // Method java/io/File.listFiles:()[Ljava/io/File;
      54: astore        4
      56: aload         4
      58: ifnonnull     64
      61: goto          21
      64: iconst_0
      65: istore        5
      67: iload         5
      69: aload         4
      71: arraylength
      72: if_icmpge     157
      75: aload         4
      77: iload         5
      79: aaload
      80: invokevirtual #69                 // Method java/io/File.getName:()Ljava/lang/String;
      83: getstatic     #70                 // Field java/util/Locale.ENGLISH:Ljava/util/Locale;
      86: invokevirtual #71                 // Method java/lang/String.toLowerCase:(Ljava/util/Locale;)Ljava/lang/String;
      89: ldc           #72                 // String .jar
      91: invokevirtual #73                 // Method java/lang/String.endsWith:(Ljava/lang/String;)Z
      94: ifeq          151
      97: aload         4
      99: iload         5
     101: aaload
     102: invokevirtual #74                 // Method java/io/File.isFile:()Z
     105: ifeq          151
     108: aload         4
     110: iload         5
     112: aaload
     113: invokestatic  #75                 // Method addSystemResource:(Ljava/io/File;)V
     116: goto          151
     119: astore        6
     121: getstatic     #40                 // Field log:Lorg/apache/juli/logging/Log;
     124: getstatic     #12                 // Field sm:Lorg/apache/tomcat/util/res/StringManager;
     127: ldc           #77                 // String extensionValidator.failload
     129: iconst_1
     130: anewarray     #42                 // class java/lang/Object
     133: dup
     134: iconst_0
     135: aload         4
     137: iload         5
     139: aaload
     140: aastore
     141: invokevirtual #45                 // Method org/apache/tomcat/util/res/StringManager.getString:(Ljava/lang/String;[Ljava/lang/Object;)Ljava/lang/String;
     144: aload         6
     146: invokeinterface #78,  3           // InterfaceMethod org/apache/juli/logging/Log.error:(Ljava/lang/Object;Ljava/lang/Throwable;)V
     151: iinc          5, 1
     154: goto          67
     157: goto          21
     160: return
    Exception table:
       from    to  target type
         108   116   119   Class java/io/IOException

  static {};
    Code:
       0: ldc           #79                 // class org/apache/catalina/util/ExtensionValidator
       2: invokestatic  #80                 // Method org/apache/juli/logging/LogFactory.getLog:(Ljava/lang/Class;)Lorg/apache/juli/logging/Log;
       5: putstatic     #40                 // Field log:Lorg/apache/juli/logging/Log;
       8: ldc           #81                 // String org.apache.catalina.util
      10: invokestatic  #82                 // Method org/apache/tomcat/util/res/StringManager.getManager:(Ljava/lang/String;)Lorg/apache/tomcat/util/res/StringManager;
      13: putstatic     #12                 // Field sm:Lorg/apache/tomcat/util/res/StringManager;
      16: aconst_null
      17: putstatic     #35                 // Field containerAvailableExtensions:Ljava/util/List;
      20: new           #3                  // class java/util/ArrayList
      23: dup
      24: invokespecial #4                  // Method java/util/ArrayList."<init>":()V
      27: putstatic     #29                 // Field containerManifestResources:Ljava/util/List;
      30: ldc           #83                 // String java.class.path
      32: invokestatic  #59                 // Method java/lang/System.getProperty:(Ljava/lang/String;)Ljava/lang/String;
      35: astore_0
      36: new           #60                 // class java/util/StringTokenizer
      39: dup
      40: aload_0
      41: getstatic     #61                 // Field java/io/File.pathSeparator:Ljava/lang/String;
      44: invokespecial #62                 // Method java/util/StringTokenizer."<init>":(Ljava/lang/String;Ljava/lang/String;)V
      47: astore_1
      48: aload_1
      49: invokevirtual #63                 // Method java/util/StringTokenizer.hasMoreTokens:()Z
      52: ifeq          129
      55: aload_1
      56: invokevirtual #65                 // Method java/util/StringTokenizer.nextToken:()Ljava/lang/String;
      59: astore_2
      60: aload_2
      61: getstatic     #70                 // Field java/util/Locale.ENGLISH:Ljava/util/Locale;
      64: invokevirtual #71                 // Method java/lang/String.toLowerCase:(Ljava/util/Locale;)Ljava/lang/String;
      67: ldc           #72                 // String .jar
      69: invokevirtual #73                 // Method java/lang/String.endsWith:(Ljava/lang/String;)Z
      72: ifeq          126
      75: new           #64                 // class java/io/File
      78: dup
      79: aload_2
      80: invokespecial #66                 // Method java/io/File."<init>":(Ljava/lang/String;)V
      83: astore_3
      84: aload_3
      85: invokevirtual #74                 // Method java/io/File.isFile:()Z
      88: ifeq          126
      91: aload_3
      92: invokestatic  #75                 // Method addSystemResource:(Ljava/io/File;)V
      95: goto          126
      98: astore        4
     100: getstatic     #40                 // Field log:Lorg/apache/juli/logging/Log;
     103: getstatic     #12                 // Field sm:Lorg/apache/tomcat/util/res/StringManager;
     106: ldc           #77                 // String extensionValidator.failload
     108: iconst_1
     109: anewarray     #42                 // class java/lang/Object
     112: dup
     113: iconst_0
     114: aload_3
     115: aastore
     116: invokevirtual #45                 // Method org/apache/tomcat/util/res/StringManager.getString:(Ljava/lang/String;[Ljava/lang/Object;)Ljava/lang/String;
     119: aload         4
     121: invokeinterface #78,  3           // InterfaceMethod org/apache/juli/logging/Log.error:(Ljava/lang/Object;Ljava/lang/Throwable;)V
     126: goto          48
     129: ldc           #84                 // String java.ext.dirs
     131: invokestatic  #85                 // Method addFolderList:(Ljava/lang/String;)V
     134: return
    Exception table:
       from    to  target type
          91    95    98   Class java/io/IOException
}
