Compiled from "Snappy.java"
final class io.netty.handler.codec.compression.Snappy$State extends java.lang.Enum<io.netty.handler.codec.compression.Snappy$State> {
  public static final io.netty.handler.codec.compression.Snappy$State READING_PREAMBLE;

  public static final io.netty.handler.codec.compression.Snappy$State READING_TAG;

  public static final io.netty.handler.codec.compression.Snappy$State READING_LITERAL;

  public static final io.netty.handler.codec.compression.Snappy$State READING_COPY;

  private static final io.netty.handler.codec.compression.Snappy$State[] $VALUES;

  public static io.netty.handler.codec.compression.Snappy$State[] values();
    Code:
       0: getstatic     #1                  // Field $VALUES:[Lio/netty/handler/codec/compression/Snappy$State;
       3: invokevirtual #2                  // Method "[Lio/netty/handler/codec/compression/Snappy$State;".clone:()Ljava/lang/Object;
       6: checkcast     #3                  // class "[Lio/netty/handler/codec/compression/Snappy$State;"
       9: areturn

  public static io.netty.handler.codec.compression.Snappy$State valueOf(java.lang.String);
    Code:
       0: ldc           #4                  // class io/netty/handler/codec/compression/Snappy$State
       2: aload_0
       3: invokestatic  #5                  // Method java/lang/Enum.valueOf:(Ljava/lang/Class;Ljava/lang/String;)Ljava/lang/Enum;
       6: checkcast     #4                  // class io/netty/handler/codec/compression/Snappy$State
       9: areturn

  private io.netty.handler.codec.compression.Snappy$State();
    Code:
       0: aload_0
       1: aload_1
       2: iload_2
       3: invokespecial #6                  // Method java/lang/Enum."<init>":(Ljava/lang/String;I)V
       6: return

  static {};
    Code:
       0: new           #4                  // class io/netty/handler/codec/compression/Snappy$State
       3: dup
       4: ldc           #7                  // String READING_PREAMBLE
       6: iconst_0
       7: invokespecial #8                  // Method "<init>":(Ljava/lang/String;I)V
      10: putstatic     #9                  // Field READING_PREAMBLE:Lio/netty/handler/codec/compression/Snappy$State;
      13: new           #4                  // class io/netty/handler/codec/compression/Snappy$State
      16: dup
      17: ldc           #10                 // String READING_TAG
      19: iconst_1
      20: invokespecial #8                  // Method "<init>":(Ljava/lang/String;I)V
      23: putstatic     #11                 // Field READING_TAG:Lio/netty/handler/codec/compression/Snappy$State;
      26: new           #4                  // class io/netty/handler/codec/compression/Snappy$State
      29: dup
      30: ldc           #12                 // String READING_LITERAL
      32: iconst_2
      33: invokespecial #8                  // Method "<init>":(Ljava/lang/String;I)V
      36: putstatic     #13                 // Field READING_LITERAL:Lio/netty/handler/codec/compression/Snappy$State;
      39: new           #4                  // class io/netty/handler/codec/compression/Snappy$State
      42: dup
      43: ldc           #14                 // String READING_COPY
      45: iconst_3
      46: invokespecial #8                  // Method "<init>":(Ljava/lang/String;I)V
      49: putstatic     #15                 // Field READING_COPY:Lio/netty/handler/codec/compression/Snappy$State;
      52: iconst_4
      53: anewarray     #4                  // class io/netty/handler/codec/compression/Snappy$State
      56: dup
      57: iconst_0
      58: getstatic     #9                  // Field READING_PREAMBLE:Lio/netty/handler/codec/compression/Snappy$State;
      61: aastore
      62: dup
      63: iconst_1
      64: getstatic     #11                 // Field READING_TAG:Lio/netty/handler/codec/compression/Snappy$State;
      67: aastore
      68: dup
      69: iconst_2
      70: getstatic     #13                 // Field READING_LITERAL:Lio/netty/handler/codec/compression/Snappy$State;
      73: aastore
      74: dup
      75: iconst_3
      76: getstatic     #15                 // Field READING_COPY:Lio/netty/handler/codec/compression/Snappy$State;
      79: aastore
      80: putstatic     #1                  // Field $VALUES:[Lio/netty/handler/codec/compression/Snappy$State;
      83: return
}
