Compiled from "TokenBuffer.java"
class com.fasterxml.jackson.databind.util.TokenBuffer$1 {
  static final int[] $SwitchMap$com$fasterxml$jackson$core$JsonToken;

  static final int[] $SwitchMap$com$fasterxml$jackson$core$JsonParser$NumberType;

  static {};
    Code:
       0: invokestatic  #1                  // Method com/fasterxml/jackson/core/JsonParser$NumberType.values:()[Lcom/fasterxml/jackson/core/JsonParser$NumberType;
       3: arraylength
       4: newarray       int
       6: putstatic     #2                  // Field $SwitchMap$com$fasterxml$jackson$core$JsonParser$NumberType:[I
       9: getstatic     #2                  // Field $SwitchMap$com$fasterxml$jackson$core$JsonParser$NumberType:[I
      12: getstatic     #3                  // Field com/fasterxml/jackson/core/JsonParser$NumberType.INT:Lcom/fasterxml/jackson/core/JsonParser$NumberType;
      15: invokevirtual #4                  // Method com/fasterxml/jackson/core/JsonParser$NumberType.ordinal:()I
      18: iconst_1
      19: iastore
      20: goto          24
      23: astore_0
      24: getstatic     #2                  // Field $SwitchMap$com$fasterxml$jackson$core$JsonParser$NumberType:[I
      27: getstatic     #6                  // Field com/fasterxml/jackson/core/JsonParser$NumberType.BIG_INTEGER:Lcom/fasterxml/jackson/core/JsonParser$NumberType;
      30: invokevirtual #4                  // Method com/fasterxml/jackson/core/JsonParser$NumberType.ordinal:()I
      33: iconst_2
      34: iastore
      35: goto          39
      38: astore_0
      39: getstatic     #2                  // Field $SwitchMap$com$fasterxml$jackson$core$JsonParser$NumberType:[I
      42: getstatic     #7                  // Field com/fasterxml/jackson/core/JsonParser$NumberType.BIG_DECIMAL:Lcom/fasterxml/jackson/core/JsonParser$NumberType;
      45: invokevirtual #4                  // Method com/fasterxml/jackson/core/JsonParser$NumberType.ordinal:()I
      48: iconst_3
      49: iastore
      50: goto          54
      53: astore_0
      54: getstatic     #2                  // Field $SwitchMap$com$fasterxml$jackson$core$JsonParser$NumberType:[I
      57: getstatic     #8                  // Field com/fasterxml/jackson/core/JsonParser$NumberType.FLOAT:Lcom/fasterxml/jackson/core/JsonParser$NumberType;
      60: invokevirtual #4                  // Method com/fasterxml/jackson/core/JsonParser$NumberType.ordinal:()I
      63: iconst_4
      64: iastore
      65: goto          69
      68: astore_0
      69: getstatic     #2                  // Field $SwitchMap$com$fasterxml$jackson$core$JsonParser$NumberType:[I
      72: getstatic     #9                  // Field com/fasterxml/jackson/core/JsonParser$NumberType.LONG:Lcom/fasterxml/jackson/core/JsonParser$NumberType;
      75: invokevirtual #4                  // Method com/fasterxml/jackson/core/JsonParser$NumberType.ordinal:()I
      78: iconst_5
      79: iastore
      80: goto          84
      83: astore_0
      84: invokestatic  #10                 // Method com/fasterxml/jackson/core/JsonToken.values:()[Lcom/fasterxml/jackson/core/JsonToken;
      87: arraylength
      88: newarray       int
      90: putstatic     #11                 // Field $SwitchMap$com$fasterxml$jackson$core$JsonToken:[I
      93: getstatic     #11                 // Field $SwitchMap$com$fasterxml$jackson$core$JsonToken:[I
      96: getstatic     #12                 // Field com/fasterxml/jackson/core/JsonToken.START_OBJECT:Lcom/fasterxml/jackson/core/JsonToken;
      99: invokevirtual #13                 // Method com/fasterxml/jackson/core/JsonToken.ordinal:()I
     102: iconst_1
     103: iastore
     104: goto          108
     107: astore_0
     108: getstatic     #11                 // Field $SwitchMap$com$fasterxml$jackson$core$JsonToken:[I
     111: getstatic     #14                 // Field com/fasterxml/jackson/core/JsonToken.END_OBJECT:Lcom/fasterxml/jackson/core/JsonToken;
     114: invokevirtual #13                 // Method com/fasterxml/jackson/core/JsonToken.ordinal:()I
     117: iconst_2
     118: iastore
     119: goto          123
     122: astore_0
     123: getstatic     #11                 // Field $SwitchMap$com$fasterxml$jackson$core$JsonToken:[I
     126: getstatic     #15                 // Field com/fasterxml/jackson/core/JsonToken.START_ARRAY:Lcom/fasterxml/jackson/core/JsonToken;
     129: invokevirtual #13                 // Method com/fasterxml/jackson/core/JsonToken.ordinal:()I
     132: iconst_3
     133: iastore
     134: goto          138
     137: astore_0
     138: getstatic     #11                 // Field $SwitchMap$com$fasterxml$jackson$core$JsonToken:[I
     141: getstatic     #16                 // Field com/fasterxml/jackson/core/JsonToken.END_ARRAY:Lcom/fasterxml/jackson/core/JsonToken;
     144: invokevirtual #13                 // Method com/fasterxml/jackson/core/JsonToken.ordinal:()I
     147: iconst_4
     148: iastore
     149: goto          153
     152: astore_0
     153: getstatic     #11                 // Field $SwitchMap$com$fasterxml$jackson$core$JsonToken:[I
     156: getstatic     #17                 // Field com/fasterxml/jackson/core/JsonToken.FIELD_NAME:Lcom/fasterxml/jackson/core/JsonToken;
     159: invokevirtual #13                 // Method com/fasterxml/jackson/core/JsonToken.ordinal:()I
     162: iconst_5
     163: iastore
     164: goto          168
     167: astore_0
     168: getstatic     #11                 // Field $SwitchMap$com$fasterxml$jackson$core$JsonToken:[I
     171: getstatic     #18                 // Field com/fasterxml/jackson/core/JsonToken.VALUE_STRING:Lcom/fasterxml/jackson/core/JsonToken;
     174: invokevirtual #13                 // Method com/fasterxml/jackson/core/JsonToken.ordinal:()I
     177: bipush        6
     179: iastore
     180: goto          184
     183: astore_0
     184: getstatic     #11                 // Field $SwitchMap$com$fasterxml$jackson$core$JsonToken:[I
     187: getstatic     #19                 // Field com/fasterxml/jackson/core/JsonToken.VALUE_NUMBER_INT:Lcom/fasterxml/jackson/core/JsonToken;
     190: invokevirtual #13                 // Method com/fasterxml/jackson/core/JsonToken.ordinal:()I
     193: bipush        7
     195: iastore
     196: goto          200
     199: astore_0
     200: getstatic     #11                 // Field $SwitchMap$com$fasterxml$jackson$core$JsonToken:[I
     203: getstatic     #20                 // Field com/fasterxml/jackson/core/JsonToken.VALUE_NUMBER_FLOAT:Lcom/fasterxml/jackson/core/JsonToken;
     206: invokevirtual #13                 // Method com/fasterxml/jackson/core/JsonToken.ordinal:()I
     209: bipush        8
     211: iastore
     212: goto          216
     215: astore_0
     216: getstatic     #11                 // Field $SwitchMap$com$fasterxml$jackson$core$JsonToken:[I
     219: getstatic     #21                 // Field com/fasterxml/jackson/core/JsonToken.VALUE_TRUE:Lcom/fasterxml/jackson/core/JsonToken;
     222: invokevirtual #13                 // Method com/fasterxml/jackson/core/JsonToken.ordinal:()I
     225: bipush        9
     227: iastore
     228: goto          232
     231: astore_0
     232: getstatic     #11                 // Field $SwitchMap$com$fasterxml$jackson$core$JsonToken:[I
     235: getstatic     #22                 // Field com/fasterxml/jackson/core/JsonToken.VALUE_FALSE:Lcom/fasterxml/jackson/core/JsonToken;
     238: invokevirtual #13                 // Method com/fasterxml/jackson/core/JsonToken.ordinal:()I
     241: bipush        10
     243: iastore
     244: goto          248
     247: astore_0
     248: getstatic     #11                 // Field $SwitchMap$com$fasterxml$jackson$core$JsonToken:[I
     251: getstatic     #23                 // Field com/fasterxml/jackson/core/JsonToken.VALUE_NULL:Lcom/fasterxml/jackson/core/JsonToken;
     254: invokevirtual #13                 // Method com/fasterxml/jackson/core/JsonToken.ordinal:()I
     257: bipush        11
     259: iastore
     260: goto          264
     263: astore_0
     264: getstatic     #11                 // Field $SwitchMap$com$fasterxml$jackson$core$JsonToken:[I
     267: getstatic     #24                 // Field com/fasterxml/jackson/core/JsonToken.VALUE_EMBEDDED_OBJECT:Lcom/fasterxml/jackson/core/JsonToken;
     270: invokevirtual #13                 // Method com/fasterxml/jackson/core/JsonToken.ordinal:()I
     273: bipush        12
     275: iastore
     276: goto          280
     279: astore_0
     280: return
    Exception table:
       from    to  target type
           9    20    23   Class java/lang/NoSuchFieldError
          24    35    38   Class java/lang/NoSuchFieldError
          39    50    53   Class java/lang/NoSuchFieldError
          54    65    68   Class java/lang/NoSuchFieldError
          69    80    83   Class java/lang/NoSuchFieldError
          93   104   107   Class java/lang/NoSuchFieldError
         108   119   122   Class java/lang/NoSuchFieldError
         123   134   137   Class java/lang/NoSuchFieldError
         138   149   152   Class java/lang/NoSuchFieldError
         153   164   167   Class java/lang/NoSuchFieldError
         168   180   183   Class java/lang/NoSuchFieldError
         184   196   199   Class java/lang/NoSuchFieldError
         200   212   215   Class java/lang/NoSuchFieldError
         216   228   231   Class java/lang/NoSuchFieldError
         232   244   247   Class java/lang/NoSuchFieldError
         248   260   263   Class java/lang/NoSuchFieldError
         264   276   279   Class java/lang/NoSuchFieldError
}
