Compiled from "BindingGroupAddHandler.java"
class org.jboss.as.server.services.net.BindingGroupAddHandler$1 implements org.jboss.as.controller.OperationStepHandler {
  final org.jboss.as.controller.PathAddress val$mine;

  final org.jboss.dmr.ModelNode val$model;

  final org.jboss.as.server.services.net.BindingGroupAddHandler this$0;

  org.jboss.as.server.services.net.BindingGroupAddHandler$1(org.jboss.as.server.services.net.BindingGroupAddHandler, org.jboss.as.controller.PathAddress, org.jboss.dmr.ModelNode);
    Code:
       0: aload_0
       1: aload_1
       2: putfield      #2                  // Field this$0:Lorg/jboss/as/server/services/net/BindingGroupAddHandler;
       5: aload_0
       6: aload_2
       7: putfield      #3                  // Field val$mine:Lorg/jboss/as/controller/PathAddress;
      10: aload_0
      11: aload_3
      12: putfield      #4                  // Field val$model:Lorg/jboss/dmr/ModelNode;
      15: aload_0
      16: invokespecial #5                  // Method java/lang/Object."<init>":()V
      19: return

  public void execute(org.jboss.as.controller.OperationContext, org.jboss.dmr.ModelNode) throws org.jboss.as.controller.OperationFailedException;
    Code:
       0: aload_1
       1: aload_1
       2: invokeinterface #6,  1            // InterfaceMethod org/jboss/as/controller/OperationContext.getCurrentAddress:()Lorg/jboss/as/controller/PathAddress;
       7: invokevirtual #7                  // Method org/jboss/as/controller/PathAddress.getParent:()Lorg/jboss/as/controller/PathAddress;
      10: iconst_0
      11: invokeinterface #8,  3            // InterfaceMethod org/jboss/as/controller/OperationContext.readResourceFromRoot:(Lorg/jboss/as/controller/PathAddress;Z)Lorg/jboss/as/controller/registry/Resource;
      16: astore_3
      17: aload_3
      18: ldc           #9                  // String socket-binding-group
      20: invokeinterface #10,  2           // InterfaceMethod org/jboss/as/controller/registry/Resource.getChildren:(Ljava/lang/String;)Ljava/util/Set;
      25: astore        4
      27: aload         4
      29: invokeinterface #11,  1           // InterfaceMethod java/util/Set.size:()I
      34: iconst_1
      35: if_icmple     130
      38: aload         4
      40: invokeinterface #12,  1           // InterfaceMethod java/util/Set.iterator:()Ljava/util/Iterator;
      45: astore        5
      47: aload         5
      49: invokeinterface #13,  1           // InterfaceMethod java/util/Iterator.hasNext:()Z
      54: ifeq          130
      57: aload         5
      59: invokeinterface #14,  1           // InterfaceMethod java/util/Iterator.next:()Ljava/lang/Object;
      64: checkcast     #15                 // class org/jboss/as/controller/registry/Resource$ResourceEntry
      67: astore        6
      69: aload         6
      71: invokeinterface #16,  1           // InterfaceMethod org/jboss/as/controller/registry/Resource$ResourceEntry.getName:()Ljava/lang/String;
      76: aload_0
      77: getfield      #3                  // Field val$mine:Lorg/jboss/as/controller/PathAddress;
      80: invokevirtual #17                 // Method org/jboss/as/controller/PathAddress.getLastElement:()Lorg/jboss/as/controller/PathElement;
      83: invokevirtual #18                 // Method org/jboss/as/controller/PathElement.getValue:()Ljava/lang/String;
      86: invokevirtual #19                 // Method java/lang/String.equals:(Ljava/lang/Object;)Z
      89: ifne          127
      92: getstatic     #20                 // Field org/jboss/as/server/logging/ServerLogger.ROOT_LOGGER:Lorg/jboss/as/server/logging/ServerLogger;
      95: aload_0
      96: getfield      #3                  // Field val$mine:Lorg/jboss/as/controller/PathAddress;
      99: iconst_1
     100: anewarray     #21                 // class org/jboss/as/controller/PathElement
     103: dup
     104: iconst_0
     105: ldc           #9                  // String socket-binding-group
     107: aload         6
     109: invokeinterface #16,  1           // InterfaceMethod org/jboss/as/controller/registry/Resource$ResourceEntry.getName:()Ljava/lang/String;
     114: invokestatic  #22                 // Method org/jboss/as/controller/PathElement.pathElement:(Ljava/lang/String;Ljava/lang/String;)Lorg/jboss/as/controller/PathElement;
     117: aastore
     118: invokestatic  #23                 // Method org/jboss/as/controller/PathAddress.pathAddress:([Lorg/jboss/as/controller/PathElement;)Lorg/jboss/as/controller/PathAddress;
     121: invokeinterface #24,  3           // InterfaceMethod org/jboss/as/server/logging/ServerLogger.cannotAddMoreThanOneSocketBindingGroupForServerOrHost:(Lorg/jboss/as/controller/PathAddress;Lorg/jboss/as/controller/PathAddress;)Lorg/jboss/as/controller/OperationFailedException;
     126: athrow
     127: goto          47
     130: aload_1
     131: aload_0
     132: getfield      #4                  // Field val$model:Lorg/jboss/dmr/ModelNode;
     135: invokestatic  #25                 // Method org/jboss/as/controller/resource/AbstractSocketBindingGroupResourceDefinition.validateDefaultInterfaceReference:(Lorg/jboss/as/controller/OperationContext;Lorg/jboss/dmr/ModelNode;)V
     138: return
}
