Compiled from "InterfaceRemoveHandler.java"
public class org.jboss.as.server.services.net.InterfaceRemoveHandler extends org.jboss.as.controller.operations.common.InterfaceRemoveHandler {
  public static final org.jboss.as.server.services.net.InterfaceRemoveHandler INSTANCE;

  protected org.jboss.as.server.services.net.InterfaceRemoveHandler();
    Code:
       0: aload_0
       1: invokespecial #1                  // Method org/jboss/as/controller/operations/common/InterfaceRemoveHandler."<init>":()V
       4: return

  protected void recordCapabilitiesAndRequirements(org.jboss.as.controller.OperationContext, org.jboss.dmr.ModelNode, org.jboss.as.controller.registry.Resource) throws org.jboss.as.controller.OperationFailedException;
    Code:
       0: aload_0
       1: aload_1
       2: aload_2
       3: aload_3
       4: invokespecial #2                  // Method org/jboss/as/controller/operations/common/InterfaceRemoveHandler.recordCapabilitiesAndRequirements:(Lorg/jboss/as/controller/OperationContext;Lorg/jboss/dmr/ModelNode;Lorg/jboss/as/controller/registry/Resource;)V
       7: aload_1
       8: getstatic     #3                  // Field org/jboss/as/server/services/net/InterfaceResourceDefinition.INTERFACE_CAPABILITY:Lorg/jboss/as/controller/capability/RuntimeCapability;
      11: aload_1
      12: invokeinterface #4,  1            // InterfaceMethod org/jboss/as/controller/OperationContext.getCurrentAddressValue:()Ljava/lang/String;
      17: invokevirtual #5                  // Method org/jboss/as/controller/capability/RuntimeCapability.getDynamicName:(Ljava/lang/String;)Ljava/lang/String;
      20: invokeinterface #6,  2            // InterfaceMethod org/jboss/as/controller/OperationContext.deregisterCapability:(Ljava/lang/String;)V
      25: return

  static {};
    Code:
       0: new           #7                  // class org/jboss/as/server/services/net/InterfaceRemoveHandler
       3: dup
       4: invokespecial #8                  // Method "<init>":()V
       7: putstatic     #9                  // Field INSTANCE:Lorg/jboss/as/server/services/net/InterfaceRemoveHandler;
      10: return
}
