Compiled from "LocalDestinationOutboundSocketBindingAddHandler.java"
public class org.jboss.as.server.services.net.LocalDestinationOutboundSocketBindingAddHandler extends org.jboss.as.controller.AbstractAddStepHandler {
  static final org.jboss.as.server.services.net.LocalDestinationOutboundSocketBindingAddHandler INSTANCE;

  private org.jboss.as.server.services.net.LocalDestinationOutboundSocketBindingAddHandler();
    Code:
       0: aload_0
       1: getstatic     #3                  // Field org/jboss/as/server/services/net/LocalDestinationOutboundSocketBindingResourceDefinition.OUTBOUND_SOCKET_BINDING_CAPABILITY:Lorg/jboss/as/controller/capability/RuntimeCapability;
       4: getstatic     #4                  // Field org/jboss/as/server/services/net/LocalDestinationOutboundSocketBindingResourceDefinition.ATTRIBUTES:[Lorg/jboss/as/controller/SimpleAttributeDefinition;
       7: invokespecial #5                  // Method org/jboss/as/controller/AbstractAddStepHandler."<init>":(Lorg/jboss/as/controller/capability/RuntimeCapability;[Lorg/jboss/as/controller/AttributeDefinition;)V
      10: return

  protected void performRuntime(org.jboss.as.controller.OperationContext, org.jboss.dmr.ModelNode, org.jboss.dmr.ModelNode) throws org.jboss.as.controller.OperationFailedException;
    Code:
       0: aload_2
       1: ldc           #6                  // String address
       3: invokevirtual #7                  // Method org/jboss/dmr/ModelNode.get:(Ljava/lang/String;)Lorg/jboss/dmr/ModelNode;
       6: invokestatic  #8                  // Method org/jboss/as/controller/PathAddress.pathAddress:(Lorg/jboss/dmr/ModelNode;)Lorg/jboss/as/controller/PathAddress;
       9: astore        4
      11: aload         4
      13: invokevirtual #9                  // Method org/jboss/as/controller/PathAddress.getLastElement:()Lorg/jboss/as/controller/PathElement;
      16: invokevirtual #10                 // Method org/jboss/as/controller/PathElement.getValue:()Ljava/lang/String;
      19: astore        5
      21: aload_1
      22: aload_3
      23: aload         5
      25: invokestatic  #11                 // Method installOutboundSocketBindingService:(Lorg/jboss/as/controller/OperationContext;Lorg/jboss/dmr/ModelNode;Ljava/lang/String;)V
      28: goto          46
      31: astore        6
      33: new           #13                 // class org/jboss/as/controller/OperationFailedException
      36: dup
      37: aload         6
      39: invokevirtual #14                 // Method java/net/UnknownHostException.toString:()Ljava/lang/String;
      42: invokespecial #15                 // Method org/jboss/as/controller/OperationFailedException."<init>":(Ljava/lang/String;)V
      45: athrow
      46: return
    Exception table:
       from    to  target type
          21    28    31   Class java/net/UnknownHostException

  public static void installOutboundSocketBindingService(org.jboss.as.controller.OperationContext, org.jboss.dmr.ModelNode, java.lang.String) throws org.jboss.as.controller.OperationFailedException, java.net.UnknownHostException;
    Code:
       0: aload_0
       1: invokeinterface #16,  1           // InterfaceMethod org/jboss/as/controller/OperationContext.getServiceTarget:()Lorg/jboss/msc/service/ServiceTarget;
       6: astore_3
       7: getstatic     #17                 // Field org/jboss/as/server/services/net/LocalDestinationOutboundSocketBindingResourceDefinition.SOCKET_BINDING_REF:Lorg/jboss/as/controller/SimpleAttributeDefinition;
      10: aload_0
      11: aload_1
      12: invokevirtual #18                 // Method org/jboss/as/controller/SimpleAttributeDefinition.resolveModelAttribute:(Lorg/jboss/as/controller/OperationContext;Lorg/jboss/dmr/ModelNode;)Lorg/jboss/dmr/ModelNode;
      15: invokevirtual #19                 // Method org/jboss/dmr/ModelNode.asString:()Ljava/lang/String;
      18: astore        4
      20: getstatic     #20                 // Field org/jboss/as/server/services/net/OutboundSocketBindingResourceDefinition.SOURCE_INTERFACE:Lorg/jboss/as/controller/SimpleAttributeDefinition;
      23: aload_0
      24: aload_1
      25: invokevirtual #18                 // Method org/jboss/as/controller/SimpleAttributeDefinition.resolveModelAttribute:(Lorg/jboss/as/controller/OperationContext;Lorg/jboss/dmr/ModelNode;)Lorg/jboss/dmr/ModelNode;
      28: astore        5
      30: aload         5
      32: invokevirtual #21                 // Method org/jboss/dmr/ModelNode.isDefined:()Z
      35: ifeq          46
      38: aload         5
      40: invokevirtual #19                 // Method org/jboss/dmr/ModelNode.asString:()Ljava/lang/String;
      43: goto          47
      46: aconst_null
      47: astore        6
      49: getstatic     #22                 // Field org/jboss/as/server/services/net/OutboundSocketBindingResourceDefinition.SOURCE_PORT:Lorg/jboss/as/controller/SimpleAttributeDefinition;
      52: aload_0
      53: aload_1
      54: invokevirtual #18                 // Method org/jboss/as/controller/SimpleAttributeDefinition.resolveModelAttribute:(Lorg/jboss/as/controller/OperationContext;Lorg/jboss/dmr/ModelNode;)Lorg/jboss/dmr/ModelNode;
      57: astore        7
      59: aload         7
      61: invokevirtual #21                 // Method org/jboss/dmr/ModelNode.isDefined:()Z
      64: ifeq          78
      67: aload         7
      69: invokevirtual #23                 // Method org/jboss/dmr/ModelNode.asInt:()I
      72: invokestatic  #24                 // Method java/lang/Integer.valueOf:(I)Ljava/lang/Integer;
      75: goto          79
      78: aconst_null
      79: astore        8
      81: getstatic     #25                 // Field org/jboss/as/server/services/net/OutboundSocketBindingResourceDefinition.FIXED_SOURCE_PORT:Lorg/jboss/as/controller/SimpleAttributeDefinition;
      84: aload_0
      85: aload_1
      86: invokevirtual #18                 // Method org/jboss/as/controller/SimpleAttributeDefinition.resolveModelAttribute:(Lorg/jboss/as/controller/OperationContext;Lorg/jboss/dmr/ModelNode;)Lorg/jboss/dmr/ModelNode;
      89: invokevirtual #26                 // Method org/jboss/dmr/ModelNode.asBoolean:()Z
      92: istore        9
      94: new           #27                 // class org/jboss/as/server/services/net/LocalDestinationOutboundSocketBindingService
      97: dup
      98: aload_2
      99: aload         8
     101: iload         9
     103: invokespecial #28                 // Method org/jboss/as/server/services/net/LocalDestinationOutboundSocketBindingService."<init>":(Ljava/lang/String;Ljava/lang/Integer;Z)V
     106: astore        10
     108: getstatic     #29                 // Field org/jboss/as/server/services/net/OutboundSocketBindingResourceDefinition.OUTBOUND_SOCKET_BINDING_CAPABILITY:Lorg/jboss/as/controller/capability/RuntimeCapability;
     111: aload_2
     112: ldc           #30                 // class org/jboss/as/network/OutboundSocketBinding
     114: invokevirtual #31                 // Method org/jboss/as/controller/capability/RuntimeCapability.getCapabilityServiceName:(Ljava/lang/String;Ljava/lang/Class;)Lorg/jboss/msc/service/ServiceName;
     117: astore        11
     119: aload_3
     120: aload         11
     122: aload         10
     124: invokeinterface #32,  3           // InterfaceMethod org/jboss/msc/service/ServiceTarget.addService:(Lorg/jboss/msc/service/ServiceName;Lorg/jboss/msc/service/Service;)Lorg/jboss/msc/service/ServiceBuilder;
     129: astore        12
     131: aload         6
     133: ifnull        166
     136: aload         12
     138: getstatic     #33                 // Field org/jboss/as/server/services/net/NetworkInterfaceService.JBOSS_NETWORK_INTERFACE:Lorg/jboss/msc/service/ServiceName;
     141: iconst_1
     142: anewarray     #34                 // class java/lang/String
     145: dup
     146: iconst_0
     147: aload         6
     149: aastore
     150: invokevirtual #35                 // Method org/jboss/msc/service/ServiceName.append:([Ljava/lang/String;)Lorg/jboss/msc/service/ServiceName;
     153: ldc           #36                 // class org/jboss/as/network/NetworkInterfaceBinding
     155: aload         10
     157: invokevirtual #37                 // Method org/jboss/as/server/services/net/LocalDestinationOutboundSocketBindingService.getSourceNetworkInterfaceBindingInjector:()Lorg/jboss/msc/inject/Injector;
     160: invokeinterface #38,  4           // InterfaceMethod org/jboss/msc/service/ServiceBuilder.addDependency:(Lorg/jboss/msc/service/ServiceName;Ljava/lang/Class;Lorg/jboss/msc/inject/Injector;)Lorg/jboss/msc/service/ServiceBuilder;
     165: pop
     166: aload         12
     168: aload_0
     169: ldc           #39                 // String org.wildfly.network.socket-binding
     171: aload         4
     173: ldc           #40                 // class org/jboss/as/network/SocketBinding
     175: invokeinterface #41,  4           // InterfaceMethod org/jboss/as/controller/OperationContext.getCapabilityServiceName:(Ljava/lang/String;Ljava/lang/String;Ljava/lang/Class;)Lorg/jboss/msc/service/ServiceName;
     180: ldc           #40                 // class org/jboss/as/network/SocketBinding
     182: aload         10
     184: invokevirtual #42                 // Method org/jboss/as/server/services/net/LocalDestinationOutboundSocketBindingService.getLocalDestinationSocketBindingInjector:()Lorg/jboss/msc/inject/Injector;
     187: invokeinterface #38,  4           // InterfaceMethod org/jboss/msc/service/ServiceBuilder.addDependency:(Lorg/jboss/msc/service/ServiceName;Ljava/lang/Class;Lorg/jboss/msc/inject/Injector;)Lorg/jboss/msc/service/ServiceBuilder;
     192: getstatic     #43                 // Field org/jboss/as/network/SocketBindingManager.SOCKET_BINDING_MANAGER:Lorg/jboss/msc/service/ServiceName;
     195: ldc           #44                 // class org/jboss/as/network/SocketBindingManager
     197: aload         10
     199: invokevirtual #45                 // Method org/jboss/as/server/services/net/LocalDestinationOutboundSocketBindingService.getSocketBindingManagerInjector:()Lorg/jboss/msc/inject/Injector;
     202: invokeinterface #38,  4           // InterfaceMethod org/jboss/msc/service/ServiceBuilder.addDependency:(Lorg/jboss/msc/service/ServiceName;Ljava/lang/Class;Lorg/jboss/msc/inject/Injector;)Lorg/jboss/msc/service/ServiceBuilder;
     207: getstatic     #46                 // Field org/jboss/msc/service/ServiceController$Mode.ON_DEMAND:Lorg/jboss/msc/service/ServiceController$Mode;
     210: invokeinterface #47,  2           // InterfaceMethod org/jboss/msc/service/ServiceBuilder.setInitialMode:(Lorg/jboss/msc/service/ServiceController$Mode;)Lorg/jboss/msc/service/ServiceBuilder;
     215: iconst_1
     216: anewarray     #48                 // class org/jboss/msc/service/ServiceName
     219: dup
     220: iconst_0
     221: getstatic     #49                 // Field org/jboss/as/network/OutboundSocketBinding.OUTBOUND_SOCKET_BINDING_BASE_SERVICE_NAME:Lorg/jboss/msc/service/ServiceName;
     224: iconst_1
     225: anewarray     #34                 // class java/lang/String
     228: dup
     229: iconst_0
     230: aload_2
     231: aastore
     232: invokevirtual #35                 // Method org/jboss/msc/service/ServiceName.append:([Ljava/lang/String;)Lorg/jboss/msc/service/ServiceName;
     235: aastore
     236: invokeinterface #50,  2           // InterfaceMethod org/jboss/msc/service/ServiceBuilder.addAliases:([Lorg/jboss/msc/service/ServiceName;)Lorg/jboss/msc/service/ServiceBuilder;
     241: invokeinterface #51,  1           // InterfaceMethod org/jboss/msc/service/ServiceBuilder.install:()Lorg/jboss/msc/service/ServiceController;
     246: pop
     247: return

  static {};
    Code:
       0: new           #52                 // class org/jboss/as/server/services/net/LocalDestinationOutboundSocketBindingAddHandler
       3: dup
       4: invokespecial #53                 // Method "<init>":()V
       7: putstatic     #54                 // Field INSTANCE:Lorg/jboss/as/server/services/net/LocalDestinationOutboundSocketBindingAddHandler;
      10: return
}
