Compiled from "LocalDestinationOutboundSocketBindingService.java"
public class org.jboss.as.server.services.net.LocalDestinationOutboundSocketBindingService extends org.jboss.as.server.services.net.OutboundSocketBindingService {
  private final org.jboss.msc.value.InjectedValue<org.jboss.as.network.SocketBinding> localDestinationSocketBindingInjectedValue;

  public org.jboss.as.server.services.net.LocalDestinationOutboundSocketBindingService(java.lang.String, java.lang.Integer, boolean);
    Code:
       0: aload_0
       1: aload_1
       2: aload_2
       3: iload_3
       4: invokespecial #1                  // Method org/jboss/as/server/services/net/OutboundSocketBindingService."<init>":(Ljava/lang/String;Ljava/lang/Integer;Z)V
       7: aload_0
       8: new           #2                  // class org/jboss/msc/value/InjectedValue
      11: dup
      12: invokespecial #3                  // Method org/jboss/msc/value/InjectedValue."<init>":()V
      15: putfield      #4                  // Field localDestinationSocketBindingInjectedValue:Lorg/jboss/msc/value/InjectedValue;
      18: return

  synchronized org.jboss.msc.inject.Injector<org.jboss.as.network.SocketBinding> getLocalDestinationSocketBindingInjector();
    Code:
       0: aload_0
       1: getfield      #4                  // Field localDestinationSocketBindingInjectedValue:Lorg/jboss/msc/value/InjectedValue;
       4: areturn

  protected org.jboss.as.network.OutboundSocketBinding createOutboundSocketBinding();
    Code:
       0: aload_0
       1: invokespecial #5                  // Method getDestinationAddress:()Ljava/net/InetAddress;
       4: astore_1
       5: aload_0
       6: invokespecial #6                  // Method getDestinationPort:()I
       9: istore_2
      10: new           #7                  // class org/jboss/as/network/OutboundSocketBinding
      13: dup
      14: aload_0
      15: getfield      #8                  // Field outboundSocketName:Ljava/lang/String;
      18: aload_0
      19: getfield      #9                  // Field socketBindingManagerInjectedValue:Lorg/jboss/msc/value/InjectedValue;
      22: invokevirtual #10                 // Method org/jboss/msc/value/InjectedValue.getValue:()Ljava/lang/Object;
      25: checkcast     #11                 // class org/jboss/as/network/SocketBindingManager
      28: aload_1
      29: iload_2
      30: aload_0
      31: getfield      #12                 // Field sourceInterfaceInjectedValue:Lorg/jboss/msc/value/InjectedValue;
      34: invokevirtual #13                 // Method org/jboss/msc/value/InjectedValue.getOptionalValue:()Ljava/lang/Object;
      37: checkcast     #14                 // class org/jboss/as/network/NetworkInterfaceBinding
      40: aload_0
      41: getfield      #15                 // Field sourcePort:Ljava/lang/Integer;
      44: aload_0
      45: getfield      #16                 // Field fixedSourcePort:Z
      48: invokespecial #17                 // Method org/jboss/as/network/OutboundSocketBinding."<init>":(Ljava/lang/String;Lorg/jboss/as/network/SocketBindingManager;Ljava/net/InetAddress;ILorg/jboss/as/network/NetworkInterfaceBinding;Ljava/lang/Integer;Z)V
      51: areturn

  private java.net.InetAddress getDestinationAddress();
    Code:
       0: aload_0
       1: getfield      #4                  // Field localDestinationSocketBindingInjectedValue:Lorg/jboss/msc/value/InjectedValue;
       4: invokevirtual #10                 // Method org/jboss/msc/value/InjectedValue.getValue:()Ljava/lang/Object;
       7: checkcast     #18                 // class org/jboss/as/network/SocketBinding
      10: astore_1
      11: aload_1
      12: invokevirtual #19                 // Method org/jboss/as/network/SocketBinding.getSocketAddress:()Ljava/net/InetSocketAddress;
      15: invokevirtual #20                 // Method java/net/InetSocketAddress.getAddress:()Ljava/net/InetAddress;
      18: areturn

  private int getDestinationPort();
    Code:
       0: aload_0
       1: getfield      #4                  // Field localDestinationSocketBindingInjectedValue:Lorg/jboss/msc/value/InjectedValue;
       4: invokevirtual #10                 // Method org/jboss/msc/value/InjectedValue.getValue:()Ljava/lang/Object;
       7: checkcast     #18                 // class org/jboss/as/network/SocketBinding
      10: astore_1
      11: aload_1
      12: invokevirtual #19                 // Method org/jboss/as/network/SocketBinding.getSocketAddress:()Ljava/net/InetSocketAddress;
      15: astore_2
      16: aload_2
      17: invokevirtual #21                 // Method java/net/InetSocketAddress.getPort:()I
      20: ireturn
}
