Compiled from "ExecutorStream.java"
public class org.apache.solr.client.solrj.io.stream.ExecutorStream$StreamTask implements java.lang.Runnable {
  private java.util.concurrent.ArrayBlockingQueue<org.apache.solr.client.solrj.io.Tuple> queue;

  private org.apache.solr.client.solrj.io.stream.expr.StreamFactory streamFactory;

  private org.apache.solr.client.solrj.io.stream.StreamContext streamContext;

  public org.apache.solr.client.solrj.io.stream.ExecutorStream$StreamTask(java.util.concurrent.ArrayBlockingQueue, org.apache.solr.client.solrj.io.stream.expr.StreamFactory, org.apache.solr.client.solrj.io.stream.StreamContext);
    Code:
       0: aload_0
       1: invokespecial #1                  // Method java/lang/Object."<init>":()V
       4: aload_0
       5: aload_1
       6: putfield      #2                  // Field queue:Ljava/util/concurrent/ArrayBlockingQueue;
       9: aload_0
      10: aload_2
      11: putfield      #3                  // Field streamFactory:Lorg/apache/solr/client/solrj/io/stream/expr/StreamFactory;
      14: aload_0
      15: new           #4                  // class org/apache/solr/client/solrj/io/stream/StreamContext
      18: dup
      19: invokespecial #5                  // Method org/apache/solr/client/solrj/io/stream/StreamContext."<init>":()V
      22: putfield      #6                  // Field streamContext:Lorg/apache/solr/client/solrj/io/stream/StreamContext;
      25: aload_0
      26: getfield      #6                  // Field streamContext:Lorg/apache/solr/client/solrj/io/stream/StreamContext;
      29: aload_3
      30: invokevirtual #7                  // Method org/apache/solr/client/solrj/io/stream/StreamContext.getSolrClientCache:()Lorg/apache/solr/client/solrj/io/SolrClientCache;
      33: invokevirtual #8                  // Method org/apache/solr/client/solrj/io/stream/StreamContext.setSolrClientCache:(Lorg/apache/solr/client/solrj/io/SolrClientCache;)V
      36: aload_0
      37: getfield      #6                  // Field streamContext:Lorg/apache/solr/client/solrj/io/stream/StreamContext;
      40: aload_3
      41: invokevirtual #9                  // Method org/apache/solr/client/solrj/io/stream/StreamContext.getModelCache:()Lorg/apache/solr/client/solrj/io/ModelCache;
      44: invokevirtual #10                 // Method org/apache/solr/client/solrj/io/stream/StreamContext.setModelCache:(Lorg/apache/solr/client/solrj/io/ModelCache;)V
      47: return

  public void run();
    Code:
       0: aconst_null
       1: astore_1
       2: aload_0
       3: getfield      #2                  // Field queue:Ljava/util/concurrent/ArrayBlockingQueue;
       6: invokevirtual #11                 // Method java/util/concurrent/ArrayBlockingQueue.take:()Ljava/lang/Object;
       9: checkcast     #12                 // class org/apache/solr/client/solrj/io/Tuple
      12: astore_1
      13: goto          26
      16: astore_2
      17: new           #14                 // class java/lang/RuntimeException
      20: dup
      21: aload_2
      22: invokespecial #15                 // Method java/lang/RuntimeException."<init>":(Ljava/lang/Throwable;)V
      25: athrow
      26: aload_1
      27: ldc           #16                 // String expr_s
      29: invokevirtual #17                 // Method org/apache/solr/client/solrj/io/Tuple.getString:(Ljava/lang/Object;)Ljava/lang/String;
      32: astore_2
      33: aload_1
      34: ldc           #18                 // String id
      36: invokevirtual #19                 // Method org/apache/solr/client/solrj/io/Tuple.get:(Ljava/lang/Object;)Ljava/lang/Object;
      39: astore_3
      40: aconst_null
      41: astore        4
      43: aload_0
      44: getfield      #3                  // Field streamFactory:Lorg/apache/solr/client/solrj/io/stream/expr/StreamFactory;
      47: aload_2
      48: invokevirtual #20                 // Method org/apache/solr/client/solrj/io/stream/expr/StreamFactory.constructStream:(Ljava/lang/String;)Lorg/apache/solr/client/solrj/io/stream/TupleStream;
      51: astore        4
      53: aload         4
      55: aload_0
      56: getfield      #6                  // Field streamContext:Lorg/apache/solr/client/solrj/io/stream/StreamContext;
      59: invokevirtual #21                 // Method org/apache/solr/client/solrj/io/stream/TupleStream.setStreamContext:(Lorg/apache/solr/client/solrj/io/stream/StreamContext;)V
      62: aload         4
      64: invokevirtual #22                 // Method org/apache/solr/client/solrj/io/stream/TupleStream.open:()V
      67: aload         4
      69: invokevirtual #23                 // Method org/apache/solr/client/solrj/io/stream/TupleStream.read:()Lorg/apache/solr/client/solrj/io/Tuple;
      72: astore        5
      74: aload         5
      76: getfield      #24                 // Field org/apache/solr/client/solrj/io/Tuple.EOF:Z
      79: ifeq          85
      82: goto          88
      85: goto          67
      88: aload         4
      90: invokevirtual #25                 // Method org/apache/solr/client/solrj/io/stream/TupleStream.close:()V
      93: goto          205
      96: astore        5
      98: invokestatic  #26                 // Method org/apache/solr/client/solrj/io/stream/ExecutorStream.access$000:()Lorg/slf4j/Logger;
     101: ldc           #27                 // String Executor Error
     103: aload         5
     105: invokeinterface #28,  3           // InterfaceMethod org/slf4j/Logger.error:(Ljava/lang/String;Ljava/lang/Throwable;)V
     110: goto          205
     113: astore        5
     115: invokestatic  #26                 // Method org/apache/solr/client/solrj/io/stream/ExecutorStream.access$000:()Lorg/slf4j/Logger;
     118: new           #29                 // class java/lang/StringBuilder
     121: dup
     122: invokespecial #30                 // Method java/lang/StringBuilder."<init>":()V
     125: ldc           #31                 // String Executor Error: id=
     127: invokevirtual #32                 // Method java/lang/StringBuilder.append:(Ljava/lang/String;)Ljava/lang/StringBuilder;
     130: aload_3
     131: invokevirtual #33                 // Method java/lang/StringBuilder.append:(Ljava/lang/Object;)Ljava/lang/StringBuilder;
     134: ldc           #34                 // String  expr_s=
     136: invokevirtual #32                 // Method java/lang/StringBuilder.append:(Ljava/lang/String;)Ljava/lang/StringBuilder;
     139: aload_2
     140: invokevirtual #32                 // Method java/lang/StringBuilder.append:(Ljava/lang/String;)Ljava/lang/StringBuilder;
     143: invokevirtual #35                 // Method java/lang/StringBuilder.toString:()Ljava/lang/String;
     146: aload         5
     148: invokeinterface #28,  3           // InterfaceMethod org/slf4j/Logger.error:(Ljava/lang/String;Ljava/lang/Throwable;)V
     153: aload         4
     155: invokevirtual #25                 // Method org/apache/solr/client/solrj/io/stream/TupleStream.close:()V
     158: goto          205
     161: astore        5
     163: invokestatic  #26                 // Method org/apache/solr/client/solrj/io/stream/ExecutorStream.access$000:()Lorg/slf4j/Logger;
     166: ldc           #27                 // String Executor Error
     168: aload         5
     170: invokeinterface #28,  3           // InterfaceMethod org/slf4j/Logger.error:(Ljava/lang/String;Ljava/lang/Throwable;)V
     175: goto          205
     178: astore        6
     180: aload         4
     182: invokevirtual #25                 // Method org/apache/solr/client/solrj/io/stream/TupleStream.close:()V
     185: goto          202
     188: astore        7
     190: invokestatic  #26                 // Method org/apache/solr/client/solrj/io/stream/ExecutorStream.access$000:()Lorg/slf4j/Logger;
     193: ldc           #27                 // String Executor Error
     195: aload         7
     197: invokeinterface #28,  3           // InterfaceMethod org/slf4j/Logger.error:(Ljava/lang/String;Ljava/lang/Throwable;)V
     202: aload         6
     204: athrow
     205: return
    Exception table:
       from    to  target type
           2    13    16   Class java/lang/Exception
          88    93    96   Class java/lang/Exception
          43    88   113   Class java/lang/Exception
         153   158   161   Class java/lang/Exception
          43    88   178   any
         113   153   178   any
         180   185   188   Class java/lang/Exception
         178   180   178   any
}
