Compiled from "SelectStream.java"
public class org.apache.solr.client.solrj.io.stream.SelectStream extends org.apache.solr.client.solrj.io.stream.TupleStream implements org.apache.solr.client.solrj.io.stream.expr.Expressible {
  private static final long serialVersionUID;

  private org.apache.solr.client.solrj.io.stream.TupleStream stream;

  private java.util.Map<java.lang.String, java.lang.String> selectedFields;

  private java.util.Map<org.apache.solr.client.solrj.io.eval.StreamEvaluator, java.lang.String> selectedEvaluators;

  private java.util.List<org.apache.solr.client.solrj.io.ops.StreamOperation> operations;

  public org.apache.solr.client.solrj.io.stream.SelectStream(org.apache.solr.client.solrj.io.stream.TupleStream, java.util.List<java.lang.String>) throws java.io.IOException;
    Code:
       0: aload_0
       1: invokespecial #1                  // Method org/apache/solr/client/solrj/io/stream/TupleStream."<init>":()V
       4: aload_0
       5: aload_1
       6: putfield      #2                  // Field stream:Lorg/apache/solr/client/solrj/io/stream/TupleStream;
       9: aload_0
      10: new           #3                  // class java/util/HashMap
      13: dup
      14: invokespecial #4                  // Method java/util/HashMap."<init>":()V
      17: putfield      #5                  // Field selectedFields:Ljava/util/Map;
      20: aload_2
      21: invokeinterface #6,  1            // InterfaceMethod java/util/List.iterator:()Ljava/util/Iterator;
      26: astore_3
      27: aload_3
      28: invokeinterface #7,  1            // InterfaceMethod java/util/Iterator.hasNext:()Z
      33: ifeq          64
      36: aload_3
      37: invokeinterface #8,  1            // InterfaceMethod java/util/Iterator.next:()Ljava/lang/Object;
      42: checkcast     #9                  // class java/lang/String
      45: astore        4
      47: aload_0
      48: getfield      #5                  // Field selectedFields:Ljava/util/Map;
      51: aload         4
      53: aload         4
      55: invokeinterface #10,  3           // InterfaceMethod java/util/Map.put:(Ljava/lang/Object;Ljava/lang/Object;)Ljava/lang/Object;
      60: pop
      61: goto          27
      64: aload_0
      65: new           #11                 // class java/util/ArrayList
      68: dup
      69: invokespecial #12                 // Method java/util/ArrayList."<init>":()V
      72: putfield      #13                 // Field operations:Ljava/util/List;
      75: aload_0
      76: new           #3                  // class java/util/HashMap
      79: dup
      80: invokespecial #4                  // Method java/util/HashMap."<init>":()V
      83: putfield      #14                 // Field selectedEvaluators:Ljava/util/Map;
      86: return

  public org.apache.solr.client.solrj.io.stream.SelectStream(org.apache.solr.client.solrj.io.stream.TupleStream, java.util.Map<java.lang.String, java.lang.String>) throws java.io.IOException;
    Code:
       0: aload_0
       1: invokespecial #1                  // Method org/apache/solr/client/solrj/io/stream/TupleStream."<init>":()V
       4: aload_0
       5: aload_1
       6: putfield      #2                  // Field stream:Lorg/apache/solr/client/solrj/io/stream/TupleStream;
       9: aload_0
      10: aload_2
      11: putfield      #5                  // Field selectedFields:Ljava/util/Map;
      14: aload_0
      15: new           #11                 // class java/util/ArrayList
      18: dup
      19: invokespecial #12                 // Method java/util/ArrayList."<init>":()V
      22: putfield      #13                 // Field operations:Ljava/util/List;
      25: aload_0
      26: new           #3                  // class java/util/HashMap
      29: dup
      30: invokespecial #4                  // Method java/util/HashMap."<init>":()V
      33: putfield      #14                 // Field selectedEvaluators:Ljava/util/Map;
      36: return

  public org.apache.solr.client.solrj.io.stream.SelectStream(org.apache.solr.client.solrj.io.stream.expr.StreamExpression, org.apache.solr.client.solrj.io.stream.expr.StreamFactory) throws java.io.IOException;
    Code:
       0: aload_0
       1: invokespecial #1                  // Method org/apache/solr/client/solrj/io/stream/TupleStream."<init>":()V
       4: aload_2
       5: aload_1
       6: iconst_2
       7: anewarray     #15                 // class java/lang/Class
      10: dup
      11: iconst_0
      12: ldc           #16                 // class org/apache/solr/client/solrj/io/stream/expr/Expressible
      14: aastore
      15: dup
      16: iconst_1
      17: ldc           #17                 // class org/apache/solr/client/solrj/io/stream/TupleStream
      19: aastore
      20: invokevirtual #18                 // Method org/apache/solr/client/solrj/io/stream/expr/StreamFactory.getExpressionOperandsRepresentingTypes:(Lorg/apache/solr/client/solrj/io/stream/expr/StreamExpression;[Ljava/lang/Class;)Ljava/util/List;
      23: astore_3
      24: aload_2
      25: aload_1
      26: iconst_1
      27: anewarray     #15                 // class java/lang/Class
      30: dup
      31: iconst_0
      32: ldc           #19                 // class org/apache/solr/client/solrj/io/stream/expr/StreamExpressionValue
      34: aastore
      35: invokevirtual #20                 // Method org/apache/solr/client/solrj/io/stream/expr/StreamFactory.getOperandsOfType:(Lorg/apache/solr/client/solrj/io/stream/expr/StreamExpression;[Ljava/lang/Class;)Ljava/util/List;
      38: astore        4
      40: aload_2
      41: aload_1
      42: iconst_1
      43: anewarray     #15                 // class java/lang/Class
      46: dup
      47: iconst_0
      48: ldc           #21                 // class org/apache/solr/client/solrj/io/ops/StreamOperation
      50: aastore
      51: invokevirtual #18                 // Method org/apache/solr/client/solrj/io/stream/expr/StreamFactory.getExpressionOperandsRepresentingTypes:(Lorg/apache/solr/client/solrj/io/stream/expr/StreamExpression;[Ljava/lang/Class;)Ljava/util/List;
      54: astore        5
      56: aload_2
      57: aload_1
      58: iconst_1
      59: anewarray     #15                 // class java/lang/Class
      62: dup
      63: iconst_0
      64: ldc           #22                 // class org/apache/solr/client/solrj/io/eval/StreamEvaluator
      66: aastore
      67: invokevirtual #18                 // Method org/apache/solr/client/solrj/io/stream/expr/StreamFactory.getExpressionOperandsRepresentingTypes:(Lorg/apache/solr/client/solrj/io/stream/expr/StreamExpression;[Ljava/lang/Class;)Ljava/util/List;
      70: astore        6
      72: aload_1
      73: invokevirtual #23                 // Method org/apache/solr/client/solrj/io/stream/expr/StreamExpression.getParameters:()Ljava/util/List;
      76: invokeinterface #24,  1           // InterfaceMethod java/util/List.size:()I
      81: aload_3
      82: invokeinterface #24,  1           // InterfaceMethod java/util/List.size:()I
      87: aload         4
      89: invokeinterface #24,  1           // InterfaceMethod java/util/List.size:()I
      94: iadd
      95: aload         5
      97: invokeinterface #24,  1           // InterfaceMethod java/util/List.size:()I
     102: iadd
     103: if_icmpeq     130
     106: new           #25                 // class java/io/IOException
     109: dup
     110: getstatic     #26                 // Field java/util/Locale.ROOT:Ljava/util/Locale;
     113: ldc           #27                 // String Invalid expression %s - unknown operands found
     115: iconst_1
     116: anewarray     #28                 // class java/lang/Object
     119: dup
     120: iconst_0
     121: aload_1
     122: aastore
     123: invokestatic  #29                 // Method java/lang/String.format:(Ljava/util/Locale;Ljava/lang/String;[Ljava/lang/Object;)Ljava/lang/String;
     126: invokespecial #30                 // Method java/io/IOException."<init>":(Ljava/lang/String;)V
     129: athrow
     130: iconst_1
     131: aload_3
     132: invokeinterface #24,  1           // InterfaceMethod java/util/List.size:()I
     137: if_icmpeq     176
     140: new           #25                 // class java/io/IOException
     143: dup
     144: getstatic     #26                 // Field java/util/Locale.ROOT:Ljava/util/Locale;
     147: ldc           #31                 // String Invalid expression %s - expecting single stream but found %d (must be TupleStream types)
     149: iconst_2
     150: anewarray     #28                 // class java/lang/Object
     153: dup
     154: iconst_0
     155: aload_1
     156: aastore
     157: dup
     158: iconst_1
     159: aload_3
     160: invokeinterface #24,  1           // InterfaceMethod java/util/List.size:()I
     165: invokestatic  #32                 // Method java/lang/Integer.valueOf:(I)Ljava/lang/Integer;
     168: aastore
     169: invokestatic  #29                 // Method java/lang/String.format:(Ljava/util/Locale;Ljava/lang/String;[Ljava/lang/Object;)Ljava/lang/String;
     172: invokespecial #30                 // Method java/io/IOException."<init>":(Ljava/lang/String;)V
     175: athrow
     176: iconst_0
     177: aload         4
     179: invokeinterface #24,  1           // InterfaceMethod java/util/List.size:()I
     184: if_icmpne     223
     187: new           #25                 // class java/io/IOException
     190: dup
     191: getstatic     #26                 // Field java/util/Locale.ROOT:Ljava/util/Locale;
     194: ldc           #33                 // String Invalid expression %s - expecting at least one select field but found %d
     196: iconst_2
     197: anewarray     #28                 // class java/lang/Object
     200: dup
     201: iconst_0
     202: aload_1
     203: aastore
     204: dup
     205: iconst_1
     206: aload_3
     207: invokeinterface #24,  1           // InterfaceMethod java/util/List.size:()I
     212: invokestatic  #32                 // Method java/lang/Integer.valueOf:(I)Ljava/lang/Integer;
     215: aastore
     216: invokestatic  #29                 // Method java/lang/String.format:(Ljava/util/Locale;Ljava/lang/String;[Ljava/lang/Object;)Ljava/lang/String;
     219: invokespecial #30                 // Method java/io/IOException."<init>":(Ljava/lang/String;)V
     222: athrow
     223: iconst_0
     224: aload         6
     226: invokeinterface #24,  1           // InterfaceMethod java/util/List.size:()I
     231: if_icmpeq     271
     234: new           #25                 // class java/io/IOException
     237: dup
     238: getstatic     #26                 // Field java/util/Locale.ROOT:Ljava/util/Locale;
     241: ldc           #34                 // String Invalid expression %s - evaluators must be given a name, like \'add(...) as result\' but found %d evaluators without names
     243: iconst_2
     244: anewarray     #28                 // class java/lang/Object
     247: dup
     248: iconst_0
     249: aload_1
     250: aastore
     251: dup
     252: iconst_1
     253: aload         6
     255: invokeinterface #24,  1           // InterfaceMethod java/util/List.size:()I
     260: invokestatic  #32                 // Method java/lang/Integer.valueOf:(I)Ljava/lang/Integer;
     263: aastore
     264: invokestatic  #29                 // Method java/lang/String.format:(Ljava/util/Locale;Ljava/lang/String;[Ljava/lang/Object;)Ljava/lang/String;
     267: invokespecial #30                 // Method java/io/IOException."<init>":(Ljava/lang/String;)V
     270: athrow
     271: aload_0
     272: aload_2
     273: aload_3
     274: iconst_0
     275: invokeinterface #35,  2           // InterfaceMethod java/util/List.get:(I)Ljava/lang/Object;
     280: checkcast     #36                 // class org/apache/solr/client/solrj/io/stream/expr/StreamExpression
     283: invokevirtual #37                 // Method org/apache/solr/client/solrj/io/stream/expr/StreamFactory.constructStream:(Lorg/apache/solr/client/solrj/io/stream/expr/StreamExpression;)Lorg/apache/solr/client/solrj/io/stream/TupleStream;
     286: putfield      #2                  // Field stream:Lorg/apache/solr/client/solrj/io/stream/TupleStream;
     289: aload_0
     290: new           #3                  // class java/util/HashMap
     293: dup
     294: invokespecial #4                  // Method java/util/HashMap."<init>":()V
     297: putfield      #5                  // Field selectedFields:Ljava/util/Map;
     300: aload_0
     301: new           #3                  // class java/util/HashMap
     304: dup
     305: invokespecial #4                  // Method java/util/HashMap."<init>":()V
     308: putfield      #14                 // Field selectedEvaluators:Ljava/util/Map;
     311: aload         4
     313: invokeinterface #6,  1            // InterfaceMethod java/util/List.iterator:()Ljava/util/Iterator;
     318: astore        7
     320: aload         7
     322: invokeinterface #7,  1            // InterfaceMethod java/util/Iterator.hasNext:()Z
     327: ifeq          585
     330: aload         7
     332: invokeinterface #8,  1            // InterfaceMethod java/util/Iterator.next:()Ljava/lang/Object;
     337: checkcast     #38                 // class org/apache/solr/client/solrj/io/stream/expr/StreamExpressionParameter
     340: astore        8
     342: aload         8
     344: checkcast     #19                 // class org/apache/solr/client/solrj/io/stream/expr/StreamExpressionValue
     347: astore        9
     349: aload         9
     351: invokevirtual #39                 // Method org/apache/solr/client/solrj/io/stream/expr/StreamExpressionValue.getValue:()Ljava/lang/String;
     354: invokevirtual #40                 // Method java/lang/String.trim:()Ljava/lang/String;
     357: astore        10
     359: aload         10
     361: invokevirtual #41                 // Method java/lang/String.length:()I
     364: iconst_2
     365: if_icmple     403
     368: aload         10
     370: ldc           #42                 // String \"
     372: invokevirtual #43                 // Method java/lang/String.startsWith:(Ljava/lang/String;)Z
     375: ifeq          403
     378: aload         10
     380: ldc           #42                 // String \"
     382: invokevirtual #44                 // Method java/lang/String.endsWith:(Ljava/lang/String;)Z
     385: ifeq          403
     388: aload         10
     390: iconst_1
     391: aload         10
     393: invokevirtual #41                 // Method java/lang/String.length:()I
     396: iconst_1
     397: isub
     398: invokevirtual #45                 // Method java/lang/String.substring:(II)Ljava/lang/String;
     401: astore        10
     403: aload         10
     405: getstatic     #26                 // Field java/util/Locale.ROOT:Ljava/util/Locale;
     408: invokevirtual #46                 // Method java/lang/String.toLowerCase:(Ljava/util/Locale;)Ljava/lang/String;
     411: ldc           #47                 // String  as
     413: invokevirtual #48                 // Method java/lang/String.contains:(Ljava/lang/CharSequence;)Z
     416: ifeq          568
     419: aload         10
     421: ldc           #49                 // String (?i) as
     423: invokevirtual #50                 // Method java/lang/String.split:(Ljava/lang/String;)[Ljava/lang/String;
     426: astore        11
     428: iconst_2
     429: aload         11
     431: arraylength
     432: if_icmpeq     464
     435: new           #25                 // class java/io/IOException
     438: dup
     439: getstatic     #26                 // Field java/util/Locale.ROOT:Ljava/util/Locale;
     442: ldc           #51                 // String Invalid expression %s - expecting select field of form \'fieldA\' or \'fieldA as alias\' but found %s
     444: iconst_2
     445: anewarray     #28                 // class java/lang/Object
     448: dup
     449: iconst_0
     450: aload_1
     451: aastore
     452: dup
     453: iconst_1
     454: aload         10
     456: aastore
     457: invokestatic  #29                 // Method java/lang/String.format:(Ljava/util/Locale;Ljava/lang/String;[Ljava/lang/Object;)Ljava/lang/String;
     460: invokespecial #30                 // Method java/io/IOException."<init>":(Ljava/lang/String;)V
     463: athrow
     464: aload         11
     466: iconst_0
     467: aaload
     468: invokevirtual #40                 // Method java/lang/String.trim:()Ljava/lang/String;
     471: astore        12
     473: aload         11
     475: iconst_1
     476: aaload
     477: invokevirtual #40                 // Method java/lang/String.trim:()Ljava/lang/String;
     480: astore        13
     482: iconst_0
     483: istore        14
     485: aload         12
     487: ldc           #52                 // String (
     489: invokevirtual #48                 // Method java/lang/String.contains:(Ljava/lang/CharSequence;)Z
     492: ifeq          546
     495: aload         12
     497: invokestatic  #53                 // Method org/apache/solr/client/solrj/io/stream/expr/StreamExpressionParser.parse:(Ljava/lang/String;)Lorg/apache/solr/client/solrj/io/stream/expr/StreamExpression;
     500: astore        15
     502: aload_2
     503: aload         15
     505: iconst_1
     506: anewarray     #15                 // class java/lang/Class
     509: dup
     510: iconst_0
     511: ldc           #22                 // class org/apache/solr/client/solrj/io/eval/StreamEvaluator
     513: aastore
     514: invokevirtual #54                 // Method org/apache/solr/client/solrj/io/stream/expr/StreamFactory.doesRepresentTypes:(Lorg/apache/solr/client/solrj/io/stream/expr/StreamExpression;[Ljava/lang/Class;)Z
     517: ifeq          541
     520: aload_0
     521: getfield      #14                 // Field selectedEvaluators:Ljava/util/Map;
     524: aload_2
     525: aload         15
     527: invokevirtual #55                 // Method org/apache/solr/client/solrj/io/stream/expr/StreamFactory.constructEvaluator:(Lorg/apache/solr/client/solrj/io/stream/expr/StreamExpression;)Lorg/apache/solr/client/solrj/io/eval/StreamEvaluator;
     530: aload         13
     532: invokeinterface #10,  3           // InterfaceMethod java/util/Map.put:(Ljava/lang/Object;Ljava/lang/Object;)Ljava/lang/Object;
     537: pop
     538: iconst_1
     539: istore        14
     541: goto          546
     544: astore        15
     546: iload         14
     548: ifne          565
     551: aload_0
     552: getfield      #5                  // Field selectedFields:Ljava/util/Map;
     555: aload         12
     557: aload         13
     559: invokeinterface #10,  3           // InterfaceMethod java/util/Map.put:(Ljava/lang/Object;Ljava/lang/Object;)Ljava/lang/Object;
     564: pop
     565: goto          582
     568: aload_0
     569: getfield      #5                  // Field selectedFields:Ljava/util/Map;
     572: aload         10
     574: aload         10
     576: invokeinterface #10,  3           // InterfaceMethod java/util/Map.put:(Ljava/lang/Object;Ljava/lang/Object;)Ljava/lang/Object;
     581: pop
     582: goto          320
     585: aload_0
     586: new           #11                 // class java/util/ArrayList
     589: dup
     590: invokespecial #12                 // Method java/util/ArrayList."<init>":()V
     593: putfield      #13                 // Field operations:Ljava/util/List;
     596: aload         5
     598: invokeinterface #6,  1            // InterfaceMethod java/util/List.iterator:()Ljava/util/Iterator;
     603: astore        7
     605: aload         7
     607: invokeinterface #7,  1            // InterfaceMethod java/util/Iterator.hasNext:()Z
     612: ifeq          646
     615: aload         7
     617: invokeinterface #8,  1            // InterfaceMethod java/util/Iterator.next:()Ljava/lang/Object;
     622: checkcast     #36                 // class org/apache/solr/client/solrj/io/stream/expr/StreamExpression
     625: astore        8
     627: aload_0
     628: getfield      #13                 // Field operations:Ljava/util/List;
     631: aload_2
     632: aload         8
     634: invokevirtual #57                 // Method org/apache/solr/client/solrj/io/stream/expr/StreamFactory.constructOperation:(Lorg/apache/solr/client/solrj/io/stream/expr/StreamExpression;)Lorg/apache/solr/client/solrj/io/ops/StreamOperation;
     637: invokeinterface #58,  2           // InterfaceMethod java/util/List.add:(Ljava/lang/Object;)Z
     642: pop
     643: goto          605
     646: return
    Exception table:
       from    to  target type
         495   541   544   Class java/lang/Throwable

  public org.apache.solr.client.solrj.io.stream.expr.StreamExpression toExpression(org.apache.solr.client.solrj.io.stream.expr.StreamFactory) throws java.io.IOException;
    Code:
       0: aload_0
       1: aload_1
       2: iconst_1
       3: invokespecial #59                 // Method toExpression:(Lorg/apache/solr/client/solrj/io/stream/expr/StreamFactory;Z)Lorg/apache/solr/client/solrj/io/stream/expr/StreamExpression;
       6: areturn

  private org.apache.solr.client.solrj.io.stream.expr.StreamExpression toExpression(org.apache.solr.client.solrj.io.stream.expr.StreamFactory, boolean) throws java.io.IOException;
    Code:
       0: new           #36                 // class org/apache/solr/client/solrj/io/stream/expr/StreamExpression
       3: dup
       4: aload_1
       5: aload_0
       6: invokevirtual #60                 // Method java/lang/Object.getClass:()Ljava/lang/Class;
       9: invokevirtual #61                 // Method org/apache/solr/client/solrj/io/stream/expr/StreamFactory.getFunctionName:(Ljava/lang/Class;)Ljava/lang/String;
      12: invokespecial #62                 // Method org/apache/solr/client/solrj/io/stream/expr/StreamExpression."<init>":(Ljava/lang/String;)V
      15: astore_3
      16: iload_2
      17: ifeq          60
      20: aload_0
      21: getfield      #2                  // Field stream:Lorg/apache/solr/client/solrj/io/stream/TupleStream;
      24: instanceof    #16                 // class org/apache/solr/client/solrj/io/stream/expr/Expressible
      27: ifeq          50
      30: aload_3
      31: aload_0
      32: getfield      #2                  // Field stream:Lorg/apache/solr/client/solrj/io/stream/TupleStream;
      35: checkcast     #16                 // class org/apache/solr/client/solrj/io/stream/expr/Expressible
      38: aload_1
      39: invokeinterface #63,  2           // InterfaceMethod org/apache/solr/client/solrj/io/stream/expr/Expressible.toExpression:(Lorg/apache/solr/client/solrj/io/stream/expr/StreamFactory;)Lorg/apache/solr/client/solrj/io/stream/expr/StreamExpressionParameter;
      44: invokevirtual #64                 // Method org/apache/solr/client/solrj/io/stream/expr/StreamExpression.addParameter:(Lorg/apache/solr/client/solrj/io/stream/expr/StreamExpressionParameter;)V
      47: goto          66
      50: new           #25                 // class java/io/IOException
      53: dup
      54: ldc           #65                 // String This SelectStream contains a non-expressible TupleStream - it cannot be converted to an expression
      56: invokespecial #30                 // Method java/io/IOException."<init>":(Ljava/lang/String;)V
      59: athrow
      60: aload_3
      61: ldc           #66                 // String <stream>
      63: invokevirtual #67                 // Method org/apache/solr/client/solrj/io/stream/expr/StreamExpression.addParameter:(Ljava/lang/String;)V
      66: aload_0
      67: getfield      #5                  // Field selectedFields:Ljava/util/Map;
      70: invokeinterface #68,  1           // InterfaceMethod java/util/Map.entrySet:()Ljava/util/Set;
      75: invokeinterface #69,  1           // InterfaceMethod java/util/Set.iterator:()Ljava/util/Iterator;
      80: astore        4
      82: aload         4
      84: invokeinterface #7,  1            // InterfaceMethod java/util/Iterator.hasNext:()Z
      89: ifeq          183
      92: aload         4
      94: invokeinterface #8,  1            // InterfaceMethod java/util/Iterator.next:()Ljava/lang/Object;
      99: checkcast     #70                 // class java/util/Map$Entry
     102: astore        5
     104: aload         5
     106: invokeinterface #71,  1           // InterfaceMethod java/util/Map$Entry.getKey:()Ljava/lang/Object;
     111: checkcast     #9                  // class java/lang/String
     114: aload         5
     116: invokeinterface #72,  1           // InterfaceMethod java/util/Map$Entry.getValue:()Ljava/lang/Object;
     121: invokevirtual #73                 // Method java/lang/String.equals:(Ljava/lang/Object;)Z
     124: ifeq          144
     127: aload_3
     128: aload         5
     130: invokeinterface #71,  1           // InterfaceMethod java/util/Map$Entry.getKey:()Ljava/lang/Object;
     135: checkcast     #9                  // class java/lang/String
     138: invokevirtual #67                 // Method org/apache/solr/client/solrj/io/stream/expr/StreamExpression.addParameter:(Ljava/lang/String;)V
     141: goto          180
     144: aload_3
     145: getstatic     #26                 // Field java/util/Locale.ROOT:Ljava/util/Locale;
     148: ldc           #74                 // String %s as %s
     150: iconst_2
     151: anewarray     #28                 // class java/lang/Object
     154: dup
     155: iconst_0
     156: aload         5
     158: invokeinterface #71,  1           // InterfaceMethod java/util/Map$Entry.getKey:()Ljava/lang/Object;
     163: aastore
     164: dup
     165: iconst_1
     166: aload         5
     168: invokeinterface #72,  1           // InterfaceMethod java/util/Map$Entry.getValue:()Ljava/lang/Object;
     173: aastore
     174: invokestatic  #29                 // Method java/lang/String.format:(Ljava/util/Locale;Ljava/lang/String;[Ljava/lang/Object;)Ljava/lang/String;
     177: invokevirtual #67                 // Method org/apache/solr/client/solrj/io/stream/expr/StreamExpression.addParameter:(Ljava/lang/String;)V
     180: goto          82
     183: aload_0
     184: getfield      #14                 // Field selectedEvaluators:Ljava/util/Map;
     187: invokeinterface #68,  1           // InterfaceMethod java/util/Map.entrySet:()Ljava/util/Set;
     192: invokeinterface #69,  1           // InterfaceMethod java/util/Set.iterator:()Ljava/util/Iterator;
     197: astore        4
     199: aload         4
     201: invokeinterface #7,  1            // InterfaceMethod java/util/Iterator.hasNext:()Z
     206: ifeq          269
     209: aload         4
     211: invokeinterface #8,  1            // InterfaceMethod java/util/Iterator.next:()Ljava/lang/Object;
     216: checkcast     #70                 // class java/util/Map$Entry
     219: astore        5
     221: aload_3
     222: getstatic     #26                 // Field java/util/Locale.ROOT:Ljava/util/Locale;
     225: ldc           #74                 // String %s as %s
     227: iconst_2
     228: anewarray     #28                 // class java/lang/Object
     231: dup
     232: iconst_0
     233: aload         5
     235: invokeinterface #71,  1           // InterfaceMethod java/util/Map$Entry.getKey:()Ljava/lang/Object;
     240: checkcast     #22                 // class org/apache/solr/client/solrj/io/eval/StreamEvaluator
     243: aload_1
     244: invokeinterface #75,  2           // InterfaceMethod org/apache/solr/client/solrj/io/eval/StreamEvaluator.toExpression:(Lorg/apache/solr/client/solrj/io/stream/expr/StreamFactory;)Lorg/apache/solr/client/solrj/io/stream/expr/StreamExpressionParameter;
     249: aastore
     250: dup
     251: iconst_1
     252: aload         5
     254: invokeinterface #72,  1           // InterfaceMethod java/util/Map$Entry.getValue:()Ljava/lang/Object;
     259: aastore
     260: invokestatic  #29                 // Method java/lang/String.format:(Ljava/util/Locale;Ljava/lang/String;[Ljava/lang/Object;)Ljava/lang/String;
     263: invokevirtual #67                 // Method org/apache/solr/client/solrj/io/stream/expr/StreamExpression.addParameter:(Ljava/lang/String;)V
     266: goto          199
     269: aload_0
     270: getfield      #13                 // Field operations:Ljava/util/List;
     273: invokeinterface #6,  1            // InterfaceMethod java/util/List.iterator:()Ljava/util/Iterator;
     278: astore        4
     280: aload         4
     282: invokeinterface #7,  1            // InterfaceMethod java/util/Iterator.hasNext:()Z
     287: ifeq          317
     290: aload         4
     292: invokeinterface #8,  1            // InterfaceMethod java/util/Iterator.next:()Ljava/lang/Object;
     297: checkcast     #21                 // class org/apache/solr/client/solrj/io/ops/StreamOperation
     300: astore        5
     302: aload_3
     303: aload         5
     305: aload_1
     306: invokeinterface #76,  2           // InterfaceMethod org/apache/solr/client/solrj/io/ops/StreamOperation.toExpression:(Lorg/apache/solr/client/solrj/io/stream/expr/StreamFactory;)Lorg/apache/solr/client/solrj/io/stream/expr/StreamExpressionParameter;
     311: invokevirtual #64                 // Method org/apache/solr/client/solrj/io/stream/expr/StreamExpression.addParameter:(Lorg/apache/solr/client/solrj/io/stream/expr/StreamExpressionParameter;)V
     314: goto          280
     317: aload_3
     318: areturn

  public org.apache.solr.client.solrj.io.stream.expr.Explanation toExplanation(org.apache.solr.client.solrj.io.stream.expr.StreamFactory) throws java.io.IOException;
    Code:
       0: new           #77                 // class org/apache/solr/client/solrj/io/stream/expr/StreamExplanation
       3: dup
       4: aload_0
       5: invokevirtual #78                 // Method getStreamNodeId:()Ljava/util/UUID;
       8: invokevirtual #79                 // Method java/util/UUID.toString:()Ljava/lang/String;
      11: invokespecial #80                 // Method org/apache/solr/client/solrj/io/stream/expr/StreamExplanation."<init>":(Ljava/lang/String;)V
      14: iconst_1
      15: anewarray     #81                 // class org/apache/solr/client/solrj/io/stream/expr/Explanation
      18: dup
      19: iconst_0
      20: aload_0
      21: getfield      #2                  // Field stream:Lorg/apache/solr/client/solrj/io/stream/TupleStream;
      24: aload_1
      25: invokevirtual #82                 // Method org/apache/solr/client/solrj/io/stream/TupleStream.toExplanation:(Lorg/apache/solr/client/solrj/io/stream/expr/StreamFactory;)Lorg/apache/solr/client/solrj/io/stream/expr/Explanation;
      28: aastore
      29: invokevirtual #83                 // Method org/apache/solr/client/solrj/io/stream/expr/StreamExplanation.withChildren:([Lorg/apache/solr/client/solrj/io/stream/expr/Explanation;)Lorg/apache/solr/client/solrj/io/stream/expr/StreamExplanation;
      32: aload_1
      33: aload_0
      34: invokevirtual #60                 // Method java/lang/Object.getClass:()Ljava/lang/Class;
      37: invokevirtual #61                 // Method org/apache/solr/client/solrj/io/stream/expr/StreamFactory.getFunctionName:(Ljava/lang/Class;)Ljava/lang/String;
      40: invokevirtual #84                 // Method org/apache/solr/client/solrj/io/stream/expr/StreamExplanation.withFunctionName:(Ljava/lang/String;)Lorg/apache/solr/client/solrj/io/stream/expr/Explanation;
      43: aload_0
      44: invokevirtual #60                 // Method java/lang/Object.getClass:()Ljava/lang/Class;
      47: invokevirtual #85                 // Method java/lang/Class.getName:()Ljava/lang/String;
      50: invokevirtual #86                 // Method org/apache/solr/client/solrj/io/stream/expr/Explanation.withImplementingClass:(Ljava/lang/String;)Lorg/apache/solr/client/solrj/io/stream/expr/Explanation;
      53: ldc           #88                 // String stream-decorator
      55: invokevirtual #89                 // Method org/apache/solr/client/solrj/io/stream/expr/Explanation.withExpressionType:(Ljava/lang/String;)Lorg/apache/solr/client/solrj/io/stream/expr/Explanation;
      58: aload_0
      59: aload_1
      60: iconst_0
      61: invokespecial #59                 // Method toExpression:(Lorg/apache/solr/client/solrj/io/stream/expr/StreamFactory;Z)Lorg/apache/solr/client/solrj/io/stream/expr/StreamExpression;
      64: invokevirtual #90                 // Method org/apache/solr/client/solrj/io/stream/expr/StreamExpression.toString:()Ljava/lang/String;
      67: invokevirtual #91                 // Method org/apache/solr/client/solrj/io/stream/expr/Explanation.withExpression:(Ljava/lang/String;)Lorg/apache/solr/client/solrj/io/stream/expr/Explanation;
      70: astore_2
      71: aload_0
      72: getfield      #14                 // Field selectedEvaluators:Ljava/util/Map;
      75: invokeinterface #92,  1           // InterfaceMethod java/util/Map.keySet:()Ljava/util/Set;
      80: invokeinterface #69,  1           // InterfaceMethod java/util/Set.iterator:()Ljava/util/Iterator;
      85: astore_3
      86: aload_3
      87: invokeinterface #7,  1            // InterfaceMethod java/util/Iterator.hasNext:()Z
      92: ifeq          121
      95: aload_3
      96: invokeinterface #8,  1            // InterfaceMethod java/util/Iterator.next:()Ljava/lang/Object;
     101: checkcast     #22                 // class org/apache/solr/client/solrj/io/eval/StreamEvaluator
     104: astore        4
     106: aload_2
     107: aload         4
     109: aload_1
     110: invokeinterface #93,  2           // InterfaceMethod org/apache/solr/client/solrj/io/eval/StreamEvaluator.toExplanation:(Lorg/apache/solr/client/solrj/io/stream/expr/StreamFactory;)Lorg/apache/solr/client/solrj/io/stream/expr/Explanation;
     115: invokevirtual #94                 // Method org/apache/solr/client/solrj/io/stream/expr/Explanation.addHelper:(Lorg/apache/solr/client/solrj/io/stream/expr/Explanation;)V
     118: goto          86
     121: aload_0
     122: getfield      #13                 // Field operations:Ljava/util/List;
     125: invokeinterface #6,  1            // InterfaceMethod java/util/List.iterator:()Ljava/util/Iterator;
     130: astore_3
     131: aload_3
     132: invokeinterface #7,  1            // InterfaceMethod java/util/Iterator.hasNext:()Z
     137: ifeq          166
     140: aload_3
     141: invokeinterface #8,  1            // InterfaceMethod java/util/Iterator.next:()Ljava/lang/Object;
     146: checkcast     #21                 // class org/apache/solr/client/solrj/io/ops/StreamOperation
     149: astore        4
     151: aload_2
     152: aload         4
     154: aload_1
     155: invokeinterface #95,  2           // InterfaceMethod org/apache/solr/client/solrj/io/ops/StreamOperation.toExplanation:(Lorg/apache/solr/client/solrj/io/stream/expr/StreamFactory;)Lorg/apache/solr/client/solrj/io/stream/expr/Explanation;
     160: invokevirtual #94                 // Method org/apache/solr/client/solrj/io/stream/expr/Explanation.addHelper:(Lorg/apache/solr/client/solrj/io/stream/expr/Explanation;)V
     163: goto          131
     166: aload_2
     167: areturn

  public void setStreamContext(org.apache.solr.client.solrj.io.stream.StreamContext);
    Code:
       0: aload_0
       1: getfield      #2                  // Field stream:Lorg/apache/solr/client/solrj/io/stream/TupleStream;
       4: aload_1
       5: invokevirtual #96                 // Method org/apache/solr/client/solrj/io/stream/TupleStream.setStreamContext:(Lorg/apache/solr/client/solrj/io/stream/StreamContext;)V
       8: return

  public java.util.List<org.apache.solr.client.solrj.io.stream.TupleStream> children();
    Code:
       0: new           #11                 // class java/util/ArrayList
       3: dup
       4: invokespecial #12                 // Method java/util/ArrayList."<init>":()V
       7: astore_1
       8: aload_1
       9: aload_0
      10: getfield      #2                  // Field stream:Lorg/apache/solr/client/solrj/io/stream/TupleStream;
      13: invokeinterface #58,  2           // InterfaceMethod java/util/List.add:(Ljava/lang/Object;)Z
      18: pop
      19: aload_1
      20: areturn

  public void open() throws java.io.IOException;
    Code:
       0: aload_0
       1: getfield      #2                  // Field stream:Lorg/apache/solr/client/solrj/io/stream/TupleStream;
       4: invokevirtual #97                 // Method org/apache/solr/client/solrj/io/stream/TupleStream.open:()V
       7: return

  public void close() throws java.io.IOException;
    Code:
       0: aload_0
       1: getfield      #2                  // Field stream:Lorg/apache/solr/client/solrj/io/stream/TupleStream;
       4: invokevirtual #98                 // Method org/apache/solr/client/solrj/io/stream/TupleStream.close:()V
       7: return

  public org.apache.solr.client.solrj.io.Tuple read() throws java.io.IOException;
    Code:
       0: aload_0
       1: getfield      #2                  // Field stream:Lorg/apache/solr/client/solrj/io/stream/TupleStream;
       4: invokevirtual #99                 // Method org/apache/solr/client/solrj/io/stream/TupleStream.read:()Lorg/apache/solr/client/solrj/io/Tuple;
       7: astore_1
       8: aload_1
       9: getfield      #100                // Field org/apache/solr/client/solrj/io/Tuple.EOF:Z
      12: ifeq          17
      15: aload_1
      16: areturn
      17: new           #101                // class org/apache/solr/client/solrj/io/Tuple
      20: dup
      21: new           #3                  // class java/util/HashMap
      24: dup
      25: invokespecial #4                  // Method java/util/HashMap."<init>":()V
      28: invokespecial #102                // Method org/apache/solr/client/solrj/io/Tuple."<init>":(Ljava/util/Map;)V
      31: astore_2
      32: new           #101                // class org/apache/solr/client/solrj/io/Tuple
      35: dup
      36: new           #3                  // class java/util/HashMap
      39: dup
      40: invokespecial #4                  // Method java/util/HashMap."<init>":()V
      43: invokespecial #102                // Method org/apache/solr/client/solrj/io/Tuple."<init>":(Ljava/util/Map;)V
      46: astore_3
      47: aload_1
      48: getfield      #103                // Field org/apache/solr/client/solrj/io/Tuple.fields:Ljava/util/Map;
      51: invokeinterface #92,  1           // InterfaceMethod java/util/Map.keySet:()Ljava/util/Set;
      56: invokeinterface #69,  1           // InterfaceMethod java/util/Set.iterator:()Ljava/util/Iterator;
      61: astore        4
      63: aload         4
      65: invokeinterface #7,  1            // InterfaceMethod java/util/Iterator.hasNext:()Z
      70: ifeq          132
      73: aload         4
      75: invokeinterface #8,  1            // InterfaceMethod java/util/Iterator.next:()Ljava/lang/Object;
      80: astore        5
      82: aload_3
      83: aload         5
      85: aload_1
      86: aload         5
      88: invokevirtual #104                // Method org/apache/solr/client/solrj/io/Tuple.get:(Ljava/lang/Object;)Ljava/lang/Object;
      91: invokevirtual #105                // Method org/apache/solr/client/solrj/io/Tuple.put:(Ljava/lang/Object;Ljava/lang/Object;)V
      94: aload_0
      95: getfield      #5                  // Field selectedFields:Ljava/util/Map;
      98: aload         5
     100: invokeinterface #106,  2          // InterfaceMethod java/util/Map.containsKey:(Ljava/lang/Object;)Z
     105: ifeq          129
     108: aload_2
     109: aload_0
     110: getfield      #5                  // Field selectedFields:Ljava/util/Map;
     113: aload         5
     115: invokeinterface #107,  2          // InterfaceMethod java/util/Map.get:(Ljava/lang/Object;)Ljava/lang/Object;
     120: aload_1
     121: aload         5
     123: invokevirtual #104                // Method org/apache/solr/client/solrj/io/Tuple.get:(Ljava/lang/Object;)Ljava/lang/Object;
     126: invokevirtual #105                // Method org/apache/solr/client/solrj/io/Tuple.put:(Ljava/lang/Object;Ljava/lang/Object;)V
     129: goto          63
     132: aload_0
     133: getfield      #13                 // Field operations:Ljava/util/List;
     136: invokeinterface #6,  1            // InterfaceMethod java/util/List.iterator:()Ljava/util/Iterator;
     141: astore        4
     143: aload         4
     145: invokeinterface #7,  1            // InterfaceMethod java/util/Iterator.hasNext:()Z
     150: ifeq          184
     153: aload         4
     155: invokeinterface #8,  1            // InterfaceMethod java/util/Iterator.next:()Ljava/lang/Object;
     160: checkcast     #21                 // class org/apache/solr/client/solrj/io/ops/StreamOperation
     163: astore        5
     165: aload         5
     167: aload_2
     168: invokeinterface #108,  2          // InterfaceMethod org/apache/solr/client/solrj/io/ops/StreamOperation.operate:(Lorg/apache/solr/client/solrj/io/Tuple;)V
     173: aload         5
     175: aload_3
     176: invokeinterface #108,  2          // InterfaceMethod org/apache/solr/client/solrj/io/ops/StreamOperation.operate:(Lorg/apache/solr/client/solrj/io/Tuple;)V
     181: goto          143
     184: aload_0
     185: getfield      #14                 // Field selectedEvaluators:Ljava/util/Map;
     188: invokeinterface #68,  1           // InterfaceMethod java/util/Map.entrySet:()Ljava/util/Set;
     193: invokeinterface #69,  1           // InterfaceMethod java/util/Set.iterator:()Ljava/util/Iterator;
     198: astore        4
     200: aload         4
     202: invokeinterface #7,  1            // InterfaceMethod java/util/Iterator.hasNext:()Z
     207: ifeq          252
     210: aload         4
     212: invokeinterface #8,  1            // InterfaceMethod java/util/Iterator.next:()Ljava/lang/Object;
     217: checkcast     #70                 // class java/util/Map$Entry
     220: astore        5
     222: aload_2
     223: aload         5
     225: invokeinterface #72,  1           // InterfaceMethod java/util/Map$Entry.getValue:()Ljava/lang/Object;
     230: aload         5
     232: invokeinterface #71,  1           // InterfaceMethod java/util/Map$Entry.getKey:()Ljava/lang/Object;
     237: checkcast     #22                 // class org/apache/solr/client/solrj/io/eval/StreamEvaluator
     240: aload_3
     241: invokeinterface #109,  2          // InterfaceMethod org/apache/solr/client/solrj/io/eval/StreamEvaluator.evaluate:(Lorg/apache/solr/client/solrj/io/Tuple;)Ljava/lang/Object;
     246: invokevirtual #105                // Method org/apache/solr/client/solrj/io/Tuple.put:(Ljava/lang/Object;Ljava/lang/Object;)V
     249: goto          200
     252: aload_2
     253: areturn

  public org.apache.solr.client.solrj.io.comp.StreamComparator getStreamSort();
    Code:
       0: aload_0
       1: getfield      #2                  // Field stream:Lorg/apache/solr/client/solrj/io/stream/TupleStream;
       4: invokevirtual #110                // Method org/apache/solr/client/solrj/io/stream/TupleStream.getStreamSort:()Lorg/apache/solr/client/solrj/io/comp/StreamComparator;
       7: aload_0
       8: getfield      #5                  // Field selectedFields:Ljava/util/Map;
      11: invokeinterface #111,  2          // InterfaceMethod org/apache/solr/client/solrj/io/comp/StreamComparator.copyAliased:(Ljava/util/Map;)Lorg/apache/solr/client/solrj/io/comp/StreamComparator;
      16: areturn

  public int getCost();
    Code:
       0: iconst_0
       1: ireturn

  public org.apache.solr.client.solrj.io.stream.expr.StreamExpressionParameter toExpression(org.apache.solr.client.solrj.io.stream.expr.StreamFactory) throws java.io.IOException;
    Code:
       0: aload_0
       1: aload_1
       2: invokevirtual #112                // Method toExpression:(Lorg/apache/solr/client/solrj/io/stream/expr/StreamFactory;)Lorg/apache/solr/client/solrj/io/stream/expr/StreamExpression;
       5: areturn
}
