Compiled from "SignificantTermsStream.java"
public class org.apache.solr.client.solrj.io.stream.SignificantTermsStream extends org.apache.solr.client.solrj.io.stream.TupleStream implements org.apache.solr.client.solrj.io.stream.expr.Expressible {
  private static final long serialVersionUID;

  protected java.lang.String zkHost;

  protected java.lang.String collection;

  protected java.util.Map<java.lang.String, java.lang.String> params;

  protected java.util.Iterator<org.apache.solr.client.solrj.io.Tuple> tupleIterator;

  protected java.lang.String field;

  protected int numTerms;

  protected float minDocFreq;

  protected float maxDocFreq;

  protected int minTermLength;

  protected transient org.apache.solr.client.solrj.io.SolrClientCache cache;

  protected transient boolean isCloseCache;

  protected transient org.apache.solr.client.solrj.io.stream.StreamContext streamContext;

  protected java.util.concurrent.ExecutorService executorService;

  public org.apache.solr.client.solrj.io.stream.SignificantTermsStream(java.lang.String, java.lang.String, java.util.Map, java.lang.String, float, float, int, int) throws java.io.IOException;
    Code:
       0: aload_0
       1: invokespecial #1                  // Method org/apache/solr/client/solrj/io/stream/TupleStream."<init>":()V
       4: aload_0
       5: aload_2
       6: aload_1
       7: aload_3
       8: aload         4
      10: fload         5
      12: fload         6
      14: iload         7
      16: iload         8
      18: invokespecial #2                  // Method init:(Ljava/lang/String;Ljava/lang/String;Ljava/util/Map;Ljava/lang/String;FFII)V
      21: return

  public org.apache.solr.client.solrj.io.stream.SignificantTermsStream(org.apache.solr.client.solrj.io.stream.expr.StreamExpression, org.apache.solr.client.solrj.io.stream.expr.StreamFactory) throws java.io.IOException;
    Code:
       0: aload_0
       1: invokespecial #1                  // Method org/apache/solr/client/solrj/io/stream/TupleStream."<init>":()V
       4: aload_2
       5: aload_1
       6: iconst_0
       7: invokevirtual #3                  // Method org/apache/solr/client/solrj/io/stream/expr/StreamFactory.getValueOperand:(Lorg/apache/solr/client/solrj/io/stream/expr/StreamExpression;I)Ljava/lang/String;
      10: astore_3
      11: aload_2
      12: aload_1
      13: invokevirtual #4                  // Method org/apache/solr/client/solrj/io/stream/expr/StreamFactory.getNamedOperands:(Lorg/apache/solr/client/solrj/io/stream/expr/StreamExpression;)Ljava/util/List;
      16: astore        4
      18: aload_2
      19: aload_1
      20: ldc           #5                  // String zkHost
      22: invokevirtual #6                  // Method org/apache/solr/client/solrj/io/stream/expr/StreamFactory.getNamedOperand:(Lorg/apache/solr/client/solrj/io/stream/expr/StreamExpression;Ljava/lang/String;)Lorg/apache/solr/client/solrj/io/stream/expr/StreamExpressionNamedParameter;
      25: astore        5
      27: aload_1
      28: invokevirtual #7                  // Method org/apache/solr/client/solrj/io/stream/expr/StreamExpression.getParameters:()Ljava/util/List;
      31: invokeinterface #8,  1            // InterfaceMethod java/util/List.size:()I
      36: iconst_1
      37: aload         4
      39: invokeinterface #8,  1            // InterfaceMethod java/util/List.size:()I
      44: iadd
      45: if_icmpeq     72
      48: new           #9                  // class java/io/IOException
      51: dup
      52: getstatic     #10                 // Field java/util/Locale.ROOT:Ljava/util/Locale;
      55: ldc           #11                 // String invalid expression %s - unknown operands found
      57: iconst_1
      58: anewarray     #12                 // class java/lang/Object
      61: dup
      62: iconst_0
      63: aload_1
      64: aastore
      65: invokestatic  #13                 // Method java/lang/String.format:(Ljava/util/Locale;Ljava/lang/String;[Ljava/lang/Object;)Ljava/lang/String;
      68: invokespecial #14                 // Method java/io/IOException."<init>":(Ljava/lang/String;)V
      71: athrow
      72: aconst_null
      73: aload_3
      74: if_acmpne     101
      77: new           #9                  // class java/io/IOException
      80: dup
      81: getstatic     #10                 // Field java/util/Locale.ROOT:Ljava/util/Locale;
      84: ldc           #15                 // String invalid expression %s - collectionName expected as first operand
      86: iconst_1
      87: anewarray     #12                 // class java/lang/Object
      90: dup
      91: iconst_0
      92: aload_1
      93: aastore
      94: invokestatic  #13                 // Method java/lang/String.format:(Ljava/util/Locale;Ljava/lang/String;[Ljava/lang/Object;)Ljava/lang/String;
      97: invokespecial #14                 // Method java/io/IOException."<init>":(Ljava/lang/String;)V
     100: athrow
     101: iconst_0
     102: aload         4
     104: invokeinterface #8,  1            // InterfaceMethod java/util/List.size:()I
     109: if_icmpne     136
     112: new           #9                  // class java/io/IOException
     115: dup
     116: getstatic     #10                 // Field java/util/Locale.ROOT:Ljava/util/Locale;
     119: ldc           #16                 // String invalid expression %s - at least one named parameter expected. eg. \'q=*:*\'
     121: iconst_1
     122: anewarray     #12                 // class java/lang/Object
     125: dup
     126: iconst_0
     127: aload_1
     128: aastore
     129: invokestatic  #13                 // Method java/lang/String.format:(Ljava/util/Locale;Ljava/lang/String;[Ljava/lang/Object;)Ljava/lang/String;
     132: invokespecial #14                 // Method java/io/IOException."<init>":(Ljava/lang/String;)V
     135: athrow
     136: new           #17                 // class java/util/HashMap
     139: dup
     140: invokespecial #18                 // Method java/util/HashMap."<init>":()V
     143: astore        6
     145: aload         4
     147: invokeinterface #19,  1           // InterfaceMethod java/util/List.iterator:()Ljava/util/Iterator;
     152: astore        7
     154: aload         7
     156: invokeinterface #20,  1           // InterfaceMethod java/util/Iterator.hasNext:()Z
     161: ifeq          216
     164: aload         7
     166: invokeinterface #21,  1           // InterfaceMethod java/util/Iterator.next:()Ljava/lang/Object;
     171: checkcast     #22                 // class org/apache/solr/client/solrj/io/stream/expr/StreamExpressionNamedParameter
     174: astore        8
     176: aload         8
     178: invokevirtual #23                 // Method org/apache/solr/client/solrj/io/stream/expr/StreamExpressionNamedParameter.getName:()Ljava/lang/String;
     181: ldc           #5                  // String zkHost
     183: invokevirtual #24                 // Method java/lang/String.equals:(Ljava/lang/Object;)Z
     186: ifne          213
     189: aload         6
     191: aload         8
     193: invokevirtual #23                 // Method org/apache/solr/client/solrj/io/stream/expr/StreamExpressionNamedParameter.getName:()Ljava/lang/String;
     196: aload         8
     198: invokevirtual #25                 // Method org/apache/solr/client/solrj/io/stream/expr/StreamExpressionNamedParameter.getParameter:()Lorg/apache/solr/client/solrj/io/stream/expr/StreamExpressionParameter;
     201: invokevirtual #26                 // Method java/lang/Object.toString:()Ljava/lang/String;
     204: invokevirtual #27                 // Method java/lang/String.trim:()Ljava/lang/String;
     207: invokeinterface #28,  3           // InterfaceMethod java/util/Map.put:(Ljava/lang/Object;Ljava/lang/Object;)Ljava/lang/Object;
     212: pop
     213: goto          154
     216: aload         6
     218: ldc           #29                 // String field
     220: invokeinterface #30,  2           // InterfaceMethod java/util/Map.get:(Ljava/lang/Object;)Ljava/lang/Object;
     225: checkcast     #31                 // class java/lang/String
     228: astore        7
     230: aload         7
     232: ifnull        248
     235: aload         6
     237: ldc           #29                 // String field
     239: invokeinterface #32,  2           // InterfaceMethod java/util/Map.remove:(Ljava/lang/Object;)Ljava/lang/Object;
     244: pop
     245: goto          258
     248: new           #9                  // class java/io/IOException
     251: dup
     252: ldc           #33                 // String field param cannot be null for SignificantTermsStream
     254: invokespecial #14                 // Method java/io/IOException."<init>":(Ljava/lang/String;)V
     257: athrow
     258: aload         6
     260: ldc           #34                 // String limit
     262: invokeinterface #30,  2           // InterfaceMethod java/util/Map.get:(Ljava/lang/Object;)Ljava/lang/Object;
     267: checkcast     #31                 // class java/lang/String
     270: astore        8
     272: bipush        20
     274: istore        9
     276: aload         8
     278: ifnull        298
     281: aload         8
     283: invokestatic  #35                 // Method java/lang/Integer.parseInt:(Ljava/lang/String;)I
     286: istore        9
     288: aload         6
     290: ldc           #34                 // String limit
     292: invokeinterface #32,  2           // InterfaceMethod java/util/Map.remove:(Ljava/lang/Object;)Ljava/lang/Object;
     297: pop
     298: aload         6
     300: ldc           #36                 // String minTermLength
     302: invokeinterface #30,  2           // InterfaceMethod java/util/Map.get:(Ljava/lang/Object;)Ljava/lang/Object;
     307: checkcast     #31                 // class java/lang/String
     310: astore        10
     312: iconst_4
     313: istore        11
     315: aload         10
     317: ifnull        337
     320: aload         10
     322: invokestatic  #35                 // Method java/lang/Integer.parseInt:(Ljava/lang/String;)I
     325: istore        11
     327: aload         6
     329: ldc           #36                 // String minTermLength
     331: invokeinterface #32,  2           // InterfaceMethod java/util/Map.remove:(Ljava/lang/Object;)Ljava/lang/Object;
     336: pop
     337: aload         6
     339: ldc           #37                 // String minDocFreq
     341: invokeinterface #30,  2           // InterfaceMethod java/util/Map.get:(Ljava/lang/Object;)Ljava/lang/Object;
     346: checkcast     #31                 // class java/lang/String
     349: astore        12
     351: ldc           #38                 // float 5.0f
     353: fstore        13
     355: aload         12
     357: ifnull        377
     360: aload         12
     362: invokestatic  #39                 // Method java/lang/Float.parseFloat:(Ljava/lang/String;)F
     365: fstore        13
     367: aload         6
     369: ldc           #37                 // String minDocFreq
     371: invokeinterface #32,  2           // InterfaceMethod java/util/Map.remove:(Ljava/lang/Object;)Ljava/lang/Object;
     376: pop
     377: aload         6
     379: ldc           #40                 // String maxDocFreq
     381: invokeinterface #30,  2           // InterfaceMethod java/util/Map.get:(Ljava/lang/Object;)Ljava/lang/Object;
     386: checkcast     #31                 // class java/lang/String
     389: astore        14
     391: ldc           #41                 // float 0.3f
     393: fstore        15
     395: aload         14
     397: ifnull        417
     400: aload         14
     402: invokestatic  #39                 // Method java/lang/Float.parseFloat:(Ljava/lang/String;)F
     405: fstore        15
     407: aload         6
     409: ldc           #40                 // String maxDocFreq
     411: invokeinterface #32,  2           // InterfaceMethod java/util/Map.remove:(Ljava/lang/Object;)Ljava/lang/Object;
     416: pop
     417: aconst_null
     418: astore        16
     420: aconst_null
     421: aload         5
     423: if_acmpne     436
     426: aload_2
     427: aload_3
     428: invokevirtual #42                 // Method org/apache/solr/client/solrj/io/stream/expr/StreamFactory.getCollectionZkHost:(Ljava/lang/String;)Ljava/lang/String;
     431: astore        16
     433: goto          460
     436: aload         5
     438: invokevirtual #25                 // Method org/apache/solr/client/solrj/io/stream/expr/StreamExpressionNamedParameter.getParameter:()Lorg/apache/solr/client/solrj/io/stream/expr/StreamExpressionParameter;
     441: instanceof    #43                 // class org/apache/solr/client/solrj/io/stream/expr/StreamExpressionValue
     444: ifeq          460
     447: aload         5
     449: invokevirtual #25                 // Method org/apache/solr/client/solrj/io/stream/expr/StreamExpressionNamedParameter.getParameter:()Lorg/apache/solr/client/solrj/io/stream/expr/StreamExpressionParameter;
     452: checkcast     #43                 // class org/apache/solr/client/solrj/io/stream/expr/StreamExpressionValue
     455: invokevirtual #44                 // Method org/apache/solr/client/solrj/io/stream/expr/StreamExpressionValue.getValue:()Ljava/lang/String;
     458: astore        16
     460: aload         16
     462: ifnonnull     471
     465: aload_2
     466: invokevirtual #45                 // Method org/apache/solr/client/solrj/io/stream/expr/StreamFactory.getDefaultZkHost:()Ljava/lang/String;
     469: astore        16
     471: aload_0
     472: aload_3
     473: aload         16
     475: aload         6
     477: aload         7
     479: fload         13
     481: fload         15
     483: iload         11
     485: iload         9
     487: invokespecial #2                  // Method init:(Ljava/lang/String;Ljava/lang/String;Ljava/util/Map;Ljava/lang/String;FFII)V
     490: return

  public org.apache.solr.client.solrj.io.stream.expr.StreamExpressionParameter toExpression(org.apache.solr.client.solrj.io.stream.expr.StreamFactory) throws java.io.IOException;
    Code:
       0: new           #46                 // class org/apache/solr/client/solrj/io/stream/expr/StreamExpression
       3: dup
       4: aload_1
       5: aload_0
       6: invokevirtual #47                 // Method java/lang/Object.getClass:()Ljava/lang/Class;
       9: invokevirtual #48                 // Method org/apache/solr/client/solrj/io/stream/expr/StreamFactory.getFunctionName:(Ljava/lang/Class;)Ljava/lang/String;
      12: invokespecial #49                 // Method org/apache/solr/client/solrj/io/stream/expr/StreamExpression."<init>":(Ljava/lang/String;)V
      15: astore_2
      16: aload_2
      17: aload_0
      18: getfield      #50                 // Field collection:Ljava/lang/String;
      21: invokevirtual #51                 // Method org/apache/solr/client/solrj/io/stream/expr/StreamExpression.addParameter:(Ljava/lang/String;)V
      24: aload_0
      25: getfield      #52                 // Field params:Ljava/util/Map;
      28: invokeinterface #53,  1           // InterfaceMethod java/util/Map.entrySet:()Ljava/util/Set;
      33: invokeinterface #54,  1           // InterfaceMethod java/util/Set.iterator:()Ljava/util/Iterator;
      38: astore_3
      39: aload_3
      40: invokeinterface #20,  1           // InterfaceMethod java/util/Iterator.hasNext:()Z
      45: ifeq          93
      48: aload_3
      49: invokeinterface #21,  1           // InterfaceMethod java/util/Iterator.next:()Ljava/lang/Object;
      54: checkcast     #55                 // class java/util/Map$Entry
      57: astore        4
      59: aload_2
      60: new           #22                 // class org/apache/solr/client/solrj/io/stream/expr/StreamExpressionNamedParameter
      63: dup
      64: aload         4
      66: invokeinterface #56,  1           // InterfaceMethod java/util/Map$Entry.getKey:()Ljava/lang/Object;
      71: checkcast     #31                 // class java/lang/String
      74: aload         4
      76: invokeinterface #57,  1           // InterfaceMethod java/util/Map$Entry.getValue:()Ljava/lang/Object;
      81: checkcast     #31                 // class java/lang/String
      84: invokespecial #58                 // Method org/apache/solr/client/solrj/io/stream/expr/StreamExpressionNamedParameter."<init>":(Ljava/lang/String;Ljava/lang/String;)V
      87: invokevirtual #59                 // Method org/apache/solr/client/solrj/io/stream/expr/StreamExpression.addParameter:(Lorg/apache/solr/client/solrj/io/stream/expr/StreamExpressionParameter;)V
      90: goto          39
      93: aload_2
      94: new           #22                 // class org/apache/solr/client/solrj/io/stream/expr/StreamExpressionNamedParameter
      97: dup
      98: ldc           #29                 // String field
     100: aload_0
     101: getfield      #60                 // Field field:Ljava/lang/String;
     104: invokespecial #58                 // Method org/apache/solr/client/solrj/io/stream/expr/StreamExpressionNamedParameter."<init>":(Ljava/lang/String;Ljava/lang/String;)V
     107: invokevirtual #59                 // Method org/apache/solr/client/solrj/io/stream/expr/StreamExpression.addParameter:(Lorg/apache/solr/client/solrj/io/stream/expr/StreamExpressionParameter;)V
     110: aload_2
     111: new           #22                 // class org/apache/solr/client/solrj/io/stream/expr/StreamExpressionNamedParameter
     114: dup
     115: ldc           #37                 // String minDocFreq
     117: aload_0
     118: getfield      #61                 // Field minDocFreq:F
     121: invokestatic  #62                 // Method java/lang/Float.toString:(F)Ljava/lang/String;
     124: invokespecial #58                 // Method org/apache/solr/client/solrj/io/stream/expr/StreamExpressionNamedParameter."<init>":(Ljava/lang/String;Ljava/lang/String;)V
     127: invokevirtual #59                 // Method org/apache/solr/client/solrj/io/stream/expr/StreamExpression.addParameter:(Lorg/apache/solr/client/solrj/io/stream/expr/StreamExpressionParameter;)V
     130: aload_2
     131: new           #22                 // class org/apache/solr/client/solrj/io/stream/expr/StreamExpressionNamedParameter
     134: dup
     135: ldc           #40                 // String maxDocFreq
     137: aload_0
     138: getfield      #63                 // Field maxDocFreq:F
     141: invokestatic  #62                 // Method java/lang/Float.toString:(F)Ljava/lang/String;
     144: invokespecial #58                 // Method org/apache/solr/client/solrj/io/stream/expr/StreamExpressionNamedParameter."<init>":(Ljava/lang/String;Ljava/lang/String;)V
     147: invokevirtual #59                 // Method org/apache/solr/client/solrj/io/stream/expr/StreamExpression.addParameter:(Lorg/apache/solr/client/solrj/io/stream/expr/StreamExpressionParameter;)V
     150: aload_2
     151: new           #22                 // class org/apache/solr/client/solrj/io/stream/expr/StreamExpressionNamedParameter
     154: dup
     155: ldc           #64                 // String numTerms
     157: aload_0
     158: getfield      #65                 // Field numTerms:I
     161: invokestatic  #66                 // Method java/lang/String.valueOf:(I)Ljava/lang/String;
     164: invokespecial #58                 // Method org/apache/solr/client/solrj/io/stream/expr/StreamExpressionNamedParameter."<init>":(Ljava/lang/String;Ljava/lang/String;)V
     167: invokevirtual #59                 // Method org/apache/solr/client/solrj/io/stream/expr/StreamExpression.addParameter:(Lorg/apache/solr/client/solrj/io/stream/expr/StreamExpressionParameter;)V
     170: aload_2
     171: new           #22                 // class org/apache/solr/client/solrj/io/stream/expr/StreamExpressionNamedParameter
     174: dup
     175: ldc           #36                 // String minTermLength
     177: aload_0
     178: getfield      #67                 // Field minTermLength:I
     181: invokestatic  #66                 // Method java/lang/String.valueOf:(I)Ljava/lang/String;
     184: invokespecial #58                 // Method org/apache/solr/client/solrj/io/stream/expr/StreamExpressionNamedParameter."<init>":(Ljava/lang/String;Ljava/lang/String;)V
     187: invokevirtual #59                 // Method org/apache/solr/client/solrj/io/stream/expr/StreamExpression.addParameter:(Lorg/apache/solr/client/solrj/io/stream/expr/StreamExpressionParameter;)V
     190: aload_2
     191: new           #22                 // class org/apache/solr/client/solrj/io/stream/expr/StreamExpressionNamedParameter
     194: dup
     195: ldc           #5                  // String zkHost
     197: aload_0
     198: getfield      #68                 // Field zkHost:Ljava/lang/String;
     201: invokespecial #58                 // Method org/apache/solr/client/solrj/io/stream/expr/StreamExpressionNamedParameter."<init>":(Ljava/lang/String;Ljava/lang/String;)V
     204: invokevirtual #59                 // Method org/apache/solr/client/solrj/io/stream/expr/StreamExpression.addParameter:(Lorg/apache/solr/client/solrj/io/stream/expr/StreamExpressionParameter;)V
     207: aload_2
     208: areturn

  private void init(java.lang.String, java.lang.String, java.util.Map, java.lang.String, float, float, int, int) throws java.io.IOException;
    Code:
       0: aload_0
       1: aload_2
       2: putfield      #68                 // Field zkHost:Ljava/lang/String;
       5: aload_0
       6: aload_1
       7: putfield      #50                 // Field collection:Ljava/lang/String;
      10: aload_0
      11: aload_3
      12: putfield      #52                 // Field params:Ljava/util/Map;
      15: aload_0
      16: aload         4
      18: putfield      #60                 // Field field:Ljava/lang/String;
      21: aload_0
      22: fload         5
      24: putfield      #61                 // Field minDocFreq:F
      27: aload_0
      28: fload         6
      30: putfield      #63                 // Field maxDocFreq:F
      33: aload_0
      34: iload         8
      36: putfield      #65                 // Field numTerms:I
      39: aload_0
      40: iload         7
      42: putfield      #67                 // Field minTermLength:I
      45: return

  public void setStreamContext(org.apache.solr.client.solrj.io.stream.StreamContext);
    Code:
       0: aload_0
       1: aload_1
       2: invokevirtual #69                 // Method org/apache/solr/client/solrj/io/stream/StreamContext.getSolrClientCache:()Lorg/apache/solr/client/solrj/io/SolrClientCache;
       5: putfield      #70                 // Field cache:Lorg/apache/solr/client/solrj/io/SolrClientCache;
       8: aload_0
       9: aload_1
      10: putfield      #71                 // Field streamContext:Lorg/apache/solr/client/solrj/io/stream/StreamContext;
      13: return

  public void open() throws java.io.IOException;
    Code:
       0: aload_0
       1: getfield      #70                 // Field cache:Lorg/apache/solr/client/solrj/io/SolrClientCache;
       4: ifnonnull     26
       7: aload_0
       8: iconst_1
       9: putfield      #72                 // Field isCloseCache:Z
      12: aload_0
      13: new           #73                 // class org/apache/solr/client/solrj/io/SolrClientCache
      16: dup
      17: invokespecial #74                 // Method org/apache/solr/client/solrj/io/SolrClientCache."<init>":()V
      20: putfield      #70                 // Field cache:Lorg/apache/solr/client/solrj/io/SolrClientCache;
      23: goto          31
      26: aload_0
      27: iconst_0
      28: putfield      #72                 // Field isCloseCache:Z
      31: aload_0
      32: new           #75                 // class org/apache/solr/common/util/SolrjNamedThreadFactory
      35: dup
      36: ldc           #76                 // String SignificantTermsStream
      38: invokespecial #77                 // Method org/apache/solr/common/util/SolrjNamedThreadFactory."<init>":(Ljava/lang/String;)V
      41: invokestatic  #78                 // Method org/apache/solr/common/util/ExecutorUtil.newMDCAwareCachedThreadPool:(Ljava/util/concurrent/ThreadFactory;)Ljava/util/concurrent/ExecutorService;
      44: putfield      #79                 // Field executorService:Ljava/util/concurrent/ExecutorService;
      47: return

  public java.util.List<org.apache.solr.client.solrj.io.stream.TupleStream> children();
    Code:
       0: aconst_null
       1: areturn

  private java.util.List<java.util.concurrent.Future<org.apache.solr.common.util.NamedList>> callShards(java.util.List<java.lang.String>) throws java.io.IOException;
    Code:
       0: new           #80                 // class java/util/ArrayList
       3: dup
       4: invokespecial #81                 // Method java/util/ArrayList."<init>":()V
       7: astore_2
       8: aload_1
       9: invokeinterface #19,  1           // InterfaceMethod java/util/List.iterator:()Ljava/util/Iterator;
      14: astore_3
      15: aload_3
      16: invokeinterface #20,  1           // InterfaceMethod java/util/Iterator.hasNext:()Z
      21: ifeq          96
      24: aload_3
      25: invokeinterface #21,  1           // InterfaceMethod java/util/Iterator.next:()Ljava/lang/Object;
      30: checkcast     #31                 // class java/lang/String
      33: astore        4
      35: new           #82                 // class org/apache/solr/client/solrj/io/stream/SignificantTermsStream$SignificantTermsCall
      38: dup
      39: aload_0
      40: aload         4
      42: aload_0
      43: getfield      #52                 // Field params:Ljava/util/Map;
      46: aload_0
      47: getfield      #60                 // Field field:Ljava/lang/String;
      50: aload_0
      51: getfield      #61                 // Field minDocFreq:F
      54: aload_0
      55: getfield      #63                 // Field maxDocFreq:F
      58: aload_0
      59: getfield      #67                 // Field minTermLength:I
      62: aload_0
      63: getfield      #65                 // Field numTerms:I
      66: invokespecial #83                 // Method org/apache/solr/client/solrj/io/stream/SignificantTermsStream$SignificantTermsCall."<init>":(Lorg/apache/solr/client/solrj/io/stream/SignificantTermsStream;Ljava/lang/String;Ljava/util/Map;Ljava/lang/String;FFII)V
      69: astore        5
      71: aload_0
      72: getfield      #79                 // Field executorService:Ljava/util/concurrent/ExecutorService;
      75: aload         5
      77: invokeinterface #84,  2           // InterfaceMethod java/util/concurrent/ExecutorService.submit:(Ljava/util/concurrent/Callable;)Ljava/util/concurrent/Future;
      82: astore        6
      84: aload_2
      85: aload         6
      87: invokeinterface #85,  2           // InterfaceMethod java/util/List.add:(Ljava/lang/Object;)Z
      92: pop
      93: goto          15
      96: aload_2
      97: areturn

  public void close() throws java.io.IOException;
    Code:
       0: aload_0
       1: getfield      #72                 // Field isCloseCache:Z
       4: ifeq          14
       7: aload_0
       8: getfield      #70                 // Field cache:Lorg/apache/solr/client/solrj/io/SolrClientCache;
      11: invokevirtual #86                 // Method org/apache/solr/client/solrj/io/SolrClientCache.close:()V
      14: aload_0
      15: getfield      #79                 // Field executorService:Ljava/util/concurrent/ExecutorService;
      18: invokeinterface #87,  1           // InterfaceMethod java/util/concurrent/ExecutorService.shutdown:()V
      23: return

  public org.apache.solr.client.solrj.io.comp.StreamComparator getStreamSort();
    Code:
       0: aconst_null
       1: areturn

  public org.apache.solr.client.solrj.io.stream.expr.Explanation toExplanation(org.apache.solr.client.solrj.io.stream.expr.StreamFactory) throws java.io.IOException;
    Code:
       0: new           #88                 // class org/apache/solr/client/solrj/io/stream/expr/StreamExplanation
       3: dup
       4: aload_0
       5: invokevirtual #89                 // Method getStreamNodeId:()Ljava/util/UUID;
       8: invokevirtual #90                 // Method java/util/UUID.toString:()Ljava/lang/String;
      11: invokespecial #91                 // Method org/apache/solr/client/solrj/io/stream/expr/StreamExplanation."<init>":(Ljava/lang/String;)V
      14: aload_1
      15: aload_0
      16: invokevirtual #47                 // Method java/lang/Object.getClass:()Ljava/lang/Class;
      19: invokevirtual #48                 // Method org/apache/solr/client/solrj/io/stream/expr/StreamFactory.getFunctionName:(Ljava/lang/Class;)Ljava/lang/String;
      22: invokevirtual #92                 // Method org/apache/solr/client/solrj/io/stream/expr/StreamExplanation.withFunctionName:(Ljava/lang/String;)Lorg/apache/solr/client/solrj/io/stream/expr/Explanation;
      25: aload_0
      26: invokevirtual #47                 // Method java/lang/Object.getClass:()Ljava/lang/Class;
      29: invokevirtual #93                 // Method java/lang/Class.getName:()Ljava/lang/String;
      32: invokevirtual #94                 // Method org/apache/solr/client/solrj/io/stream/expr/Explanation.withImplementingClass:(Ljava/lang/String;)Lorg/apache/solr/client/solrj/io/stream/expr/Explanation;
      35: ldc           #96                 // String stream-decorator
      37: invokevirtual #97                 // Method org/apache/solr/client/solrj/io/stream/expr/Explanation.withExpressionType:(Ljava/lang/String;)Lorg/apache/solr/client/solrj/io/stream/expr/Explanation;
      40: aload_0
      41: aload_1
      42: invokevirtual #98                 // Method toExpression:(Lorg/apache/solr/client/solrj/io/stream/expr/StreamFactory;)Lorg/apache/solr/client/solrj/io/stream/expr/StreamExpressionParameter;
      45: invokevirtual #26                 // Method java/lang/Object.toString:()Ljava/lang/String;
      48: invokevirtual #99                 // Method org/apache/solr/client/solrj/io/stream/expr/Explanation.withExpression:(Ljava/lang/String;)Lorg/apache/solr/client/solrj/io/stream/expr/Explanation;
      51: areturn

  public org.apache.solr.client.solrj.io.Tuple read() throws java.io.IOException;
    Code:
       0: aload_0
       1: getfield      #100                // Field tupleIterator:Ljava/util/Iterator;
       4: ifnonnull     593
       7: new           #17                 // class java/util/HashMap
      10: dup
      11: invokespecial #18                 // Method java/util/HashMap."<init>":()V
      14: astore_1
      15: lconst_0
      16: lstore_2
      17: lconst_0
      18: lstore        4
      20: aload_0
      21: aload_0
      22: getfield      #68                 // Field zkHost:Ljava/lang/String;
      25: aload_0
      26: getfield      #50                 // Field collection:Ljava/lang/String;
      29: aload_0
      30: getfield      #71                 // Field streamContext:Lorg/apache/solr/client/solrj/io/stream/StreamContext;
      33: invokestatic  #101                // Method getShards:(Ljava/lang/String;Ljava/lang/String;Lorg/apache/solr/client/solrj/io/stream/StreamContext;)Ljava/util/List;
      36: invokespecial #102                // Method callShards:(Ljava/util/List;)Ljava/util/List;
      39: invokeinterface #19,  1           // InterfaceMethod java/util/List.iterator:()Ljava/util/Iterator;
      44: astore        6
      46: aload         6
      48: invokeinterface #20,  1           // InterfaceMethod java/util/Iterator.hasNext:()Z
      53: ifeq          278
      56: aload         6
      58: invokeinterface #21,  1           // InterfaceMethod java/util/Iterator.next:()Ljava/lang/Object;
      63: checkcast     #103                // class java/util/concurrent/Future
      66: astore        7
      68: aload         7
      70: invokeinterface #104,  1          // InterfaceMethod java/util/concurrent/Future.get:()Ljava/lang/Object;
      75: checkcast     #105                // class org/apache/solr/common/util/NamedList
      78: astore        8
      80: aload         8
      82: ldc           #106                // String sterms
      84: invokevirtual #107                // Method org/apache/solr/common/util/NamedList.get:(Ljava/lang/String;)Ljava/lang/Object;
      87: checkcast     #108                // class java/util/List
      90: astore        9
      92: aload         8
      94: ldc           #109                // String docFreq
      96: invokevirtual #107                // Method org/apache/solr/common/util/NamedList.get:(Ljava/lang/String;)Ljava/lang/Object;
      99: checkcast     #108                // class java/util/List
     102: astore        10
     104: aload         8
     106: ldc           #110                // String queryDocFreq
     108: invokevirtual #107                // Method org/apache/solr/common/util/NamedList.get:(Ljava/lang/String;)Ljava/lang/Object;
     111: checkcast     #108                // class java/util/List
     114: astore        11
     116: lload_2
     117: aload         8
     119: ldc           #111                // String numDocs
     121: invokevirtual #107                // Method org/apache/solr/common/util/NamedList.get:(Ljava/lang/String;)Ljava/lang/Object;
     124: checkcast     #112                // class java/lang/Integer
     127: invokevirtual #113                // Method java/lang/Integer.intValue:()I
     130: i2l
     131: ladd
     132: lstore_2
     133: lload         4
     135: aload         8
     137: ldc           #114                // String resultCount
     139: invokevirtual #107                // Method org/apache/solr/common/util/NamedList.get:(Ljava/lang/String;)Ljava/lang/Object;
     142: checkcast     #112                // class java/lang/Integer
     145: invokevirtual #113                // Method java/lang/Integer.intValue:()I
     148: i2l
     149: ladd
     150: lstore        4
     152: iconst_0
     153: istore        12
     155: iload         12
     157: aload         9
     159: invokeinterface #8,  1            // InterfaceMethod java/util/List.size:()I
     164: if_icmpge     275
     167: aload         9
     169: iload         12
     171: invokeinterface #115,  2          // InterfaceMethod java/util/List.get:(I)Ljava/lang/Object;
     176: checkcast     #31                 // class java/lang/String
     179: astore        13
     181: aload         10
     183: iload         12
     185: invokeinterface #115,  2          // InterfaceMethod java/util/List.get:(I)Ljava/lang/Object;
     190: checkcast     #112                // class java/lang/Integer
     193: invokevirtual #113                // Method java/lang/Integer.intValue:()I
     196: istore        14
     198: aload         11
     200: iload         12
     202: invokeinterface #115,  2          // InterfaceMethod java/util/List.get:(I)Ljava/lang/Object;
     207: checkcast     #112                // class java/lang/Integer
     210: invokevirtual #113                // Method java/lang/Integer.intValue:()I
     213: istore        15
     215: aload_1
     216: aload         13
     218: invokeinterface #116,  2          // InterfaceMethod java/util/Map.containsKey:(Ljava/lang/Object;)Z
     223: ifne          238
     226: aload_1
     227: aload         13
     229: iconst_2
     230: newarray       int
     232: invokeinterface #28,  3           // InterfaceMethod java/util/Map.put:(Ljava/lang/Object;Ljava/lang/Object;)Ljava/lang/Object;
     237: pop
     238: aload_1
     239: aload         13
     241: invokeinterface #30,  2           // InterfaceMethod java/util/Map.get:(Ljava/lang/Object;)Ljava/lang/Object;
     246: checkcast     #117                // class "[I"
     249: astore        16
     251: aload         16
     253: iconst_0
     254: dup2
     255: iaload
     256: iload         14
     258: iadd
     259: iastore
     260: aload         16
     262: iconst_1
     263: dup2
     264: iaload
     265: iload         15
     267: iadd
     268: iastore
     269: iinc          12, 1
     272: goto          155
     275: goto          46
     278: new           #80                 // class java/util/ArrayList
     281: dup
     282: invokespecial #81                 // Method java/util/ArrayList."<init>":()V
     285: astore        6
     287: aload_1
     288: invokeinterface #118,  1          // InterfaceMethod java/util/Map.keySet:()Ljava/util/Set;
     293: invokeinterface #54,  1           // InterfaceMethod java/util/Set.iterator:()Ljava/util/Iterator;
     298: astore        7
     300: aload         7
     302: invokeinterface #20,  1           // InterfaceMethod java/util/Iterator.hasNext:()Z
     307: ifeq          451
     310: aload         7
     312: invokeinterface #21,  1           // InterfaceMethod java/util/Iterator.next:()Ljava/lang/Object;
     317: checkcast     #31                 // class java/lang/String
     320: astore        8
     322: aload_1
     323: aload         8
     325: invokeinterface #30,  2           // InterfaceMethod java/util/Map.get:(Ljava/lang/Object;)Ljava/lang/Object;
     330: checkcast     #117                // class "[I"
     333: astore        9
     335: new           #17                 // class java/util/HashMap
     338: dup
     339: invokespecial #18                 // Method java/util/HashMap."<init>":()V
     342: astore        10
     344: aload         10
     346: ldc           #119                // String term
     348: aload         8
     350: invokeinterface #28,  3           // InterfaceMethod java/util/Map.put:(Ljava/lang/Object;Ljava/lang/Object;)Ljava/lang/Object;
     355: pop
     356: aload         10
     358: ldc           #120                // String background
     360: aload         9
     362: iconst_0
     363: iaload
     364: invokestatic  #121                // Method java/lang/Integer.valueOf:(I)Ljava/lang/Integer;
     367: invokeinterface #28,  3           // InterfaceMethod java/util/Map.put:(Ljava/lang/Object;Ljava/lang/Object;)Ljava/lang/Object;
     372: pop
     373: aload         10
     375: ldc           #122                // String foreground
     377: aload         9
     379: iconst_1
     380: iaload
     381: invokestatic  #121                // Method java/lang/Integer.valueOf:(I)Ljava/lang/Integer;
     384: invokeinterface #28,  3           // InterfaceMethod java/util/Map.put:(Ljava/lang/Object;Ljava/lang/Object;)Ljava/lang/Object;
     389: pop
     390: aload         9
     392: iconst_1
     393: iaload
     394: i2d
     395: invokestatic  #123                // Method java/lang/Math.log:(D)D
     398: dconst_1
     399: dadd
     400: d2f
     401: lload_2
     402: lconst_1
     403: ladd
     404: l2f
     405: aload         9
     407: iconst_0
     408: iaload
     409: iconst_1
     410: iadd
     411: i2f
     412: fdiv
     413: f2d
     414: invokestatic  #123                // Method java/lang/Math.log:(D)D
     417: dconst_1
     418: dadd
     419: d2f
     420: fmul
     421: fstore        11
     423: aload         10
     425: ldc           #124                // String score
     427: fload         11
     429: invokestatic  #125                // Method java/lang/Float.valueOf:(F)Ljava/lang/Float;
     432: invokeinterface #28,  3           // InterfaceMethod java/util/Map.put:(Ljava/lang/Object;Ljava/lang/Object;)Ljava/lang/Object;
     437: pop
     438: aload         6
     440: aload         10
     442: invokeinterface #85,  2           // InterfaceMethod java/util/List.add:(Ljava/lang/Object;)Z
     447: pop
     448: goto          300
     451: aload         6
     453: new           #126                // class org/apache/solr/client/solrj/io/stream/SignificantTermsStream$ScoreComp
     456: dup
     457: aload_0
     458: aconst_null
     459: invokespecial #127                // Method org/apache/solr/client/solrj/io/stream/SignificantTermsStream$ScoreComp."<init>":(Lorg/apache/solr/client/solrj/io/stream/SignificantTermsStream;Lorg/apache/solr/client/solrj/io/stream/SignificantTermsStream$1;)V
     462: invokestatic  #128                // Method java/util/Collections.sort:(Ljava/util/List;Ljava/util/Comparator;)V
     465: new           #80                 // class java/util/ArrayList
     468: dup
     469: invokespecial #81                 // Method java/util/ArrayList."<init>":()V
     472: astore        7
     474: aload         6
     476: invokeinterface #19,  1           // InterfaceMethod java/util/List.iterator:()Ljava/util/Iterator;
     481: astore        8
     483: aload         8
     485: invokeinterface #20,  1           // InterfaceMethod java/util/Iterator.hasNext:()Z
     490: ifeq          542
     493: aload         8
     495: invokeinterface #21,  1           // InterfaceMethod java/util/Iterator.next:()Ljava/lang/Object;
     500: checkcast     #129                // class java/util/Map
     503: astore        9
     505: aload         7
     507: invokeinterface #8,  1            // InterfaceMethod java/util/List.size:()I
     512: aload_0
     513: getfield      #65                 // Field numTerms:I
     516: if_icmpne     522
     519: goto          542
     522: aload         7
     524: new           #130                // class org/apache/solr/client/solrj/io/Tuple
     527: dup
     528: aload         9
     530: invokespecial #131                // Method org/apache/solr/client/solrj/io/Tuple."<init>":(Ljava/util/Map;)V
     533: invokeinterface #85,  2           // InterfaceMethod java/util/List.add:(Ljava/lang/Object;)Z
     538: pop
     539: goto          483
     542: new           #17                 // class java/util/HashMap
     545: dup
     546: invokespecial #18                 // Method java/util/HashMap."<init>":()V
     549: astore        8
     551: aload         8
     553: ldc           #132                // String EOF
     555: iconst_1
     556: invokestatic  #133                // Method java/lang/Boolean.valueOf:(Z)Ljava/lang/Boolean;
     559: invokeinterface #28,  3           // InterfaceMethod java/util/Map.put:(Ljava/lang/Object;Ljava/lang/Object;)Ljava/lang/Object;
     564: pop
     565: aload         7
     567: new           #130                // class org/apache/solr/client/solrj/io/Tuple
     570: dup
     571: aload         8
     573: invokespecial #131                // Method org/apache/solr/client/solrj/io/Tuple."<init>":(Ljava/util/Map;)V
     576: invokeinterface #85,  2           // InterfaceMethod java/util/List.add:(Ljava/lang/Object;)Z
     581: pop
     582: aload_0
     583: aload         7
     585: invokeinterface #19,  1           // InterfaceMethod java/util/List.iterator:()Ljava/util/Iterator;
     590: putfield      #100                // Field tupleIterator:Ljava/util/Iterator;
     593: aload_0
     594: getfield      #100                // Field tupleIterator:Ljava/util/Iterator;
     597: invokeinterface #21,  1           // InterfaceMethod java/util/Iterator.next:()Ljava/lang/Object;
     602: checkcast     #130                // class org/apache/solr/client/solrj/io/Tuple
     605: areturn
     606: astore_1
     607: new           #9                  // class java/io/IOException
     610: dup
     611: aload_1
     612: invokespecial #135                // Method java/io/IOException."<init>":(Ljava/lang/Throwable;)V
     615: athrow
    Exception table:
       from    to  target type
           0   605   606   Class java/lang/Exception
}
