Compiled from "ByteBufBsonDocument.java"
class com.mongodb.connection.ByteBufBsonDocument extends com.mongodb.connection.AbstractByteBufBsonDocument {
  private static final long serialVersionUID;

  private final transient org.bson.ByteBuf byteBuf;

  static java.util.List<com.mongodb.connection.ByteBufBsonDocument> createList(com.mongodb.connection.ResponseBuffers);
    Code:
       0: aload_0
       1: invokevirtual #1                  // Method com/mongodb/connection/ResponseBuffers.getReplyHeader:()Lcom/mongodb/connection/ReplyHeader;
       4: invokevirtual #2                  // Method com/mongodb/connection/ReplyHeader.getNumberReturned:()I
       7: istore_1
       8: aload_0
       9: invokevirtual #3                  // Method com/mongodb/connection/ResponseBuffers.getBodyByteBuffer:()Lorg/bson/ByteBuf;
      12: astore_2
      13: aload_2
      14: getstatic     #4                  // Field java/nio/ByteOrder.LITTLE_ENDIAN:Ljava/nio/ByteOrder;
      17: invokeinterface #5,  2            // InterfaceMethod org/bson/ByteBuf.order:(Ljava/nio/ByteOrder;)Lorg/bson/ByteBuf;
      22: pop
      23: new           #6                  // class java/util/ArrayList
      26: dup
      27: iload_1
      28: invokespecial #7                  // Method java/util/ArrayList."<init>":(I)V
      31: astore_3
      32: aload_3
      33: invokeinterface #8,  1            // InterfaceMethod java/util/List.size:()I
      38: iload_1
      39: if_icmpge     126
      42: aload_2
      43: invokeinterface #9,  1            // InterfaceMethod org/bson/ByteBuf.getInt:()I
      48: istore        4
      50: aload_2
      51: aload_2
      52: invokeinterface #10,  1           // InterfaceMethod org/bson/ByteBuf.position:()I
      57: iconst_4
      58: isub
      59: invokeinterface #11,  2           // InterfaceMethod org/bson/ByteBuf.position:(I)Lorg/bson/ByteBuf;
      64: pop
      65: aload_2
      66: invokeinterface #12,  1           // InterfaceMethod org/bson/ByteBuf.duplicate:()Lorg/bson/ByteBuf;
      71: astore        5
      73: aload         5
      75: aload         5
      77: invokeinterface #10,  1           // InterfaceMethod org/bson/ByteBuf.position:()I
      82: iload         4
      84: iadd
      85: invokeinterface #13,  2           // InterfaceMethod org/bson/ByteBuf.limit:(I)Lorg/bson/ByteBuf;
      90: pop
      91: aload_3
      92: new           #14                 // class com/mongodb/connection/ByteBufBsonDocument
      95: dup
      96: aload         5
      98: invokespecial #15                 // Method "<init>":(Lorg/bson/ByteBuf;)V
     101: invokeinterface #16,  2           // InterfaceMethod java/util/List.add:(Ljava/lang/Object;)Z
     106: pop
     107: aload_2
     108: aload_2
     109: invokeinterface #10,  1           // InterfaceMethod org/bson/ByteBuf.position:()I
     114: iload         4
     116: iadd
     117: invokeinterface #11,  2           // InterfaceMethod org/bson/ByteBuf.position:(I)Lorg/bson/ByteBuf;
     122: pop
     123: goto          32
     126: aload_3
     127: areturn

  static java.util.List<com.mongodb.connection.ByteBufBsonDocument> createList(com.mongodb.connection.ByteBufferBsonOutput, int);
    Code:
       0: aload_0
       1: invokevirtual #17                 // Method com/mongodb/connection/ByteBufferBsonOutput.getByteBuffers:()Ljava/util/List;
       4: astore_2
       5: new           #18                 // class com/mongodb/connection/CompositeByteBuf
       8: dup
       9: aload_2
      10: invokespecial #19                 // Method com/mongodb/connection/CompositeByteBuf."<init>":(Ljava/util/List;)V
      13: astore_3
      14: aload_3
      15: iload_1
      16: invokevirtual #20                 // Method com/mongodb/connection/CompositeByteBuf.position:(I)Lorg/bson/ByteBuf;
      19: pop
      20: new           #6                  // class java/util/ArrayList
      23: dup
      24: invokespecial #21                 // Method java/util/ArrayList."<init>":()V
      27: astore        4
      29: iload_1
      30: istore        5
      32: aload_3
      33: invokevirtual #22                 // Method com/mongodb/connection/CompositeByteBuf.hasRemaining:()Z
      36: ifeq          115
      39: aload_3
      40: invokevirtual #23                 // Method com/mongodb/connection/CompositeByteBuf.getInt:()I
      43: istore        6
      45: aload_3
      46: invokevirtual #24                 // Method com/mongodb/connection/CompositeByteBuf.duplicate:()Lorg/bson/ByteBuf;
      49: astore        7
      51: aload         7
      53: iload         5
      55: invokeinterface #11,  2           // InterfaceMethod org/bson/ByteBuf.position:(I)Lorg/bson/ByteBuf;
      60: pop
      61: aload         7
      63: iload         5
      65: iload         6
      67: iadd
      68: invokeinterface #13,  2           // InterfaceMethod org/bson/ByteBuf.limit:(I)Lorg/bson/ByteBuf;
      73: pop
      74: aload         4
      76: new           #14                 // class com/mongodb/connection/ByteBufBsonDocument
      79: dup
      80: aload         7
      82: invokespecial #15                 // Method "<init>":(Lorg/bson/ByteBuf;)V
      85: invokeinterface #16,  2           // InterfaceMethod java/util/List.add:(Ljava/lang/Object;)Z
      90: pop
      91: iload         5
      93: iload         6
      95: iadd
      96: istore        5
      98: aload_3
      99: aload_3
     100: invokevirtual #25                 // Method com/mongodb/connection/CompositeByteBuf.position:()I
     103: iload         6
     105: iadd
     106: iconst_4
     107: isub
     108: invokevirtual #20                 // Method com/mongodb/connection/CompositeByteBuf.position:(I)Lorg/bson/ByteBuf;
     111: pop
     112: goto          32
     115: aload_2
     116: invokeinterface #26,  1           // InterfaceMethod java/util/List.iterator:()Ljava/util/Iterator;
     121: astore        6
     123: aload         6
     125: invokeinterface #27,  1           // InterfaceMethod java/util/Iterator.hasNext:()Z
     130: ifeq          155
     133: aload         6
     135: invokeinterface #28,  1           // InterfaceMethod java/util/Iterator.next:()Ljava/lang/Object;
     140: checkcast     #29                 // class org/bson/ByteBuf
     143: astore        7
     145: aload         7
     147: invokeinterface #30,  1           // InterfaceMethod org/bson/ByteBuf.release:()V
     152: goto          123
     155: aload         4
     157: areturn

  static com.mongodb.connection.ByteBufBsonDocument createOne(com.mongodb.connection.ByteBufferBsonOutput, int);
    Code:
       0: aload_0
       1: invokevirtual #17                 // Method com/mongodb/connection/ByteBufferBsonOutput.getByteBuffers:()Ljava/util/List;
       4: astore_2
       5: new           #18                 // class com/mongodb/connection/CompositeByteBuf
       8: dup
       9: aload_2
      10: invokespecial #19                 // Method com/mongodb/connection/CompositeByteBuf."<init>":(Ljava/util/List;)V
      13: astore_3
      14: aload_3
      15: iload_1
      16: invokevirtual #20                 // Method com/mongodb/connection/CompositeByteBuf.position:(I)Lorg/bson/ByteBuf;
      19: pop
      20: aload_3
      21: invokevirtual #23                 // Method com/mongodb/connection/CompositeByteBuf.getInt:()I
      24: istore        4
      26: aload_3
      27: invokevirtual #24                 // Method com/mongodb/connection/CompositeByteBuf.duplicate:()Lorg/bson/ByteBuf;
      30: astore        5
      32: aload         5
      34: iload_1
      35: invokeinterface #11,  2           // InterfaceMethod org/bson/ByteBuf.position:(I)Lorg/bson/ByteBuf;
      40: pop
      41: aload         5
      43: iload_1
      44: iload         4
      46: iadd
      47: invokeinterface #13,  2           // InterfaceMethod org/bson/ByteBuf.limit:(I)Lorg/bson/ByteBuf;
      52: pop
      53: aload_2
      54: invokeinterface #26,  1           // InterfaceMethod java/util/List.iterator:()Ljava/util/Iterator;
      59: astore        6
      61: aload         6
      63: invokeinterface #27,  1           // InterfaceMethod java/util/Iterator.hasNext:()Z
      68: ifeq          93
      71: aload         6
      73: invokeinterface #28,  1           // InterfaceMethod java/util/Iterator.next:()Ljava/lang/Object;
      78: checkcast     #29                 // class org/bson/ByteBuf
      81: astore        7
      83: aload         7
      85: invokeinterface #30,  1           // InterfaceMethod org/bson/ByteBuf.release:()V
      90: goto          61
      93: new           #14                 // class com/mongodb/connection/ByteBufBsonDocument
      96: dup
      97: aload         5
      99: invokespecial #15                 // Method "<init>":(Lorg/bson/ByteBuf;)V
     102: areturn

  public java.lang.String toJson();
    Code:
       0: aload_0
       1: new           #31                 // class org/bson/json/JsonWriterSettings
       4: dup
       5: invokespecial #32                 // Method org/bson/json/JsonWriterSettings."<init>":()V
       8: invokevirtual #33                 // Method toJson:(Lorg/bson/json/JsonWriterSettings;)Ljava/lang/String;
      11: areturn

  public java.lang.String toJson(org.bson.json.JsonWriterSettings);
    Code:
       0: new           #34                 // class java/io/StringWriter
       3: dup
       4: invokespecial #35                 // Method java/io/StringWriter."<init>":()V
       7: astore_2
       8: new           #36                 // class org/bson/json/JsonWriter
      11: dup
      12: aload_2
      13: aload_1
      14: invokespecial #37                 // Method org/bson/json/JsonWriter."<init>":(Ljava/io/Writer;Lorg/bson/json/JsonWriterSettings;)V
      17: astore_3
      18: aload_0
      19: getfield      #38                 // Field byteBuf:Lorg/bson/ByteBuf;
      22: invokeinterface #12,  1           // InterfaceMethod org/bson/ByteBuf.duplicate:()Lorg/bson/ByteBuf;
      27: astore        4
      29: new           #39                 // class org/bson/BsonBinaryReader
      32: dup
      33: new           #40                 // class org/bson/io/ByteBufferBsonInput
      36: dup
      37: aload         4
      39: invokespecial #41                 // Method org/bson/io/ByteBufferBsonInput."<init>":(Lorg/bson/ByteBuf;)V
      42: invokespecial #42                 // Method org/bson/BsonBinaryReader."<init>":(Lorg/bson/io/BsonInput;)V
      45: astore        5
      47: aload_3
      48: aload         5
      50: invokevirtual #43                 // Method org/bson/json/JsonWriter.pipe:(Lorg/bson/BsonReader;)V
      53: aload_2
      54: invokevirtual #44                 // Method java/io/StringWriter.toString:()Ljava/lang/String;
      57: astore        6
      59: aload         4
      61: invokeinterface #30,  1           // InterfaceMethod org/bson/ByteBuf.release:()V
      66: aload         5
      68: invokevirtual #45                 // Method org/bson/BsonBinaryReader.close:()V
      71: aload         6
      73: areturn
      74: astore        7
      76: aload         4
      78: invokeinterface #30,  1           // InterfaceMethod org/bson/ByteBuf.release:()V
      83: aload         5
      85: invokevirtual #45                 // Method org/bson/BsonBinaryReader.close:()V
      88: aload         7
      90: athrow
    Exception table:
       from    to  target type
          47    59    74   any
          74    76    74   any

  <T> T findInDocument(com.mongodb.connection.AbstractByteBufBsonDocument$Finder<T>);
    Code:
       0: aload_0
       1: getfield      #38                 // Field byteBuf:Lorg/bson/ByteBuf;
       4: invokeinterface #12,  1           // InterfaceMethod org/bson/ByteBuf.duplicate:()Lorg/bson/ByteBuf;
       9: astore_2
      10: new           #39                 // class org/bson/BsonBinaryReader
      13: dup
      14: new           #40                 // class org/bson/io/ByteBufferBsonInput
      17: dup
      18: aload_0
      19: getfield      #38                 // Field byteBuf:Lorg/bson/ByteBuf;
      22: invokeinterface #12,  1           // InterfaceMethod org/bson/ByteBuf.duplicate:()Lorg/bson/ByteBuf;
      27: invokespecial #41                 // Method org/bson/io/ByteBufferBsonInput."<init>":(Lorg/bson/ByteBuf;)V
      30: invokespecial #42                 // Method org/bson/BsonBinaryReader."<init>":(Lorg/bson/io/BsonInput;)V
      33: astore_3
      34: aload_3
      35: invokevirtual #46                 // Method org/bson/BsonBinaryReader.readStartDocument:()V
      38: aload_3
      39: invokevirtual #47                 // Method org/bson/BsonBinaryReader.readBsonType:()Lorg/bson/BsonType;
      42: getstatic     #48                 // Field org/bson/BsonType.END_OF_DOCUMENT:Lorg/bson/BsonType;
      45: if_acmpeq     82
      48: aload_1
      49: aload_3
      50: invokeinterface #49,  2           // InterfaceMethod com/mongodb/connection/AbstractByteBufBsonDocument$Finder.find:(Lorg/bson/BsonReader;)Ljava/lang/Object;
      55: astore        4
      57: aload         4
      59: ifnull        79
      62: aload         4
      64: astore        5
      66: aload_2
      67: invokeinterface #30,  1           // InterfaceMethod org/bson/ByteBuf.release:()V
      72: aload_3
      73: invokevirtual #45                 // Method org/bson/BsonBinaryReader.close:()V
      76: aload         5
      78: areturn
      79: goto          38
      82: aload_3
      83: invokevirtual #50                 // Method org/bson/BsonBinaryReader.readEndDocument:()V
      86: aload_2
      87: invokeinterface #30,  1           // InterfaceMethod org/bson/ByteBuf.release:()V
      92: aload_3
      93: invokevirtual #45                 // Method org/bson/BsonBinaryReader.close:()V
      96: goto          114
      99: astore        6
     101: aload_2
     102: invokeinterface #30,  1           // InterfaceMethod org/bson/ByteBuf.release:()V
     107: aload_3
     108: invokevirtual #45                 // Method org/bson/BsonBinaryReader.close:()V
     111: aload         6
     113: athrow
     114: aload_1
     115: invokeinterface #51,  1           // InterfaceMethod com/mongodb/connection/AbstractByteBufBsonDocument$Finder.notFound:()Ljava/lang/Object;
     120: areturn
    Exception table:
       from    to  target type
          34    66    99   any
          79    86    99   any
          99   101    99   any

  public org.bson.BsonDocument clone();
    Code:
       0: aload_0
       1: getfield      #38                 // Field byteBuf:Lorg/bson/ByteBuf;
       4: invokeinterface #52,  1           // InterfaceMethod org/bson/ByteBuf.remaining:()I
       9: newarray       byte
      11: astore_1
      12: aload_0
      13: getfield      #38                 // Field byteBuf:Lorg/bson/ByteBuf;
      16: aload_0
      17: getfield      #38                 // Field byteBuf:Lorg/bson/ByteBuf;
      20: invokeinterface #10,  1           // InterfaceMethod org/bson/ByteBuf.position:()I
      25: aload_1
      26: invokeinterface #53,  3           // InterfaceMethod org/bson/ByteBuf.get:(I[B)Lorg/bson/ByteBuf;
      31: pop
      32: new           #54                 // class org/bson/RawBsonDocument
      35: dup
      36: aload_1
      37: invokespecial #55                 // Method org/bson/RawBsonDocument."<init>":([B)V
      40: areturn

  int getSizeInBytes();
    Code:
       0: aload_0
       1: getfield      #38                 // Field byteBuf:Lorg/bson/ByteBuf;
       4: aload_0
       5: getfield      #38                 // Field byteBuf:Lorg/bson/ByteBuf;
       8: invokeinterface #10,  1           // InterfaceMethod org/bson/ByteBuf.position:()I
      13: invokeinterface #56,  2           // InterfaceMethod org/bson/ByteBuf.getInt:(I)I
      18: ireturn

  org.bson.BsonDocument toBsonDocument();
    Code:
       0: aload_0
       1: getfield      #38                 // Field byteBuf:Lorg/bson/ByteBuf;
       4: invokeinterface #12,  1           // InterfaceMethod org/bson/ByteBuf.duplicate:()Lorg/bson/ByteBuf;
       9: astore_1
      10: new           #39                 // class org/bson/BsonBinaryReader
      13: dup
      14: new           #40                 // class org/bson/io/ByteBufferBsonInput
      17: dup
      18: aload_1
      19: invokespecial #41                 // Method org/bson/io/ByteBufferBsonInput."<init>":(Lorg/bson/ByteBuf;)V
      22: invokespecial #42                 // Method org/bson/BsonBinaryReader."<init>":(Lorg/bson/io/BsonInput;)V
      25: astore_2
      26: new           #57                 // class org/bson/codecs/BsonDocumentCodec
      29: dup
      30: invokespecial #58                 // Method org/bson/codecs/BsonDocumentCodec."<init>":()V
      33: aload_2
      34: invokestatic  #59                 // Method org/bson/codecs/DecoderContext.builder:()Lorg/bson/codecs/DecoderContext$Builder;
      37: invokevirtual #60                 // Method org/bson/codecs/DecoderContext$Builder.build:()Lorg/bson/codecs/DecoderContext;
      40: invokevirtual #61                 // Method org/bson/codecs/BsonDocumentCodec.decode:(Lorg/bson/BsonReader;Lorg/bson/codecs/DecoderContext;)Lorg/bson/BsonDocument;
      43: astore_3
      44: aload_1
      45: invokeinterface #30,  1           // InterfaceMethod org/bson/ByteBuf.release:()V
      50: aload_2
      51: invokevirtual #45                 // Method org/bson/BsonBinaryReader.close:()V
      54: aload_3
      55: areturn
      56: astore        4
      58: aload_1
      59: invokeinterface #30,  1           // InterfaceMethod org/bson/ByteBuf.release:()V
      64: aload_2
      65: invokevirtual #45                 // Method org/bson/BsonBinaryReader.close:()V
      68: aload         4
      70: athrow
    Exception table:
       from    to  target type
          26    44    56   any
          56    58    56   any

  com.mongodb.connection.ByteBufBsonDocument(org.bson.ByteBuf);
    Code:
       0: aload_0
       1: invokespecial #62                 // Method com/mongodb/connection/AbstractByteBufBsonDocument."<init>":()V
       4: aload_0
       5: aload_1
       6: putfield      #38                 // Field byteBuf:Lorg/bson/ByteBuf;
       9: return

  private void readObject(java.io.ObjectInputStream) throws java.io.InvalidObjectException;
    Code:
       0: new           #63                 // class java/io/InvalidObjectException
       3: dup
       4: ldc           #64                 // String Proxy required
       6: invokespecial #65                 // Method java/io/InvalidObjectException."<init>":(Ljava/lang/String;)V
       9: athrow

  public java.lang.Object clone() throws java.lang.CloneNotSupportedException;
    Code:
       0: aload_0
       1: invokevirtual #66                 // Method clone:()Lorg/bson/BsonDocument;
       4: areturn
}
