Compiled from "ClusterClock.java"
class com.mongodb.connection.ClusterClock {
  private static final java.lang.String CLUSTER_TIME_KEY;

  private org.bson.BsonDocument clusterTime;

  com.mongodb.connection.ClusterClock();
    Code:
       0: aload_0
       1: invokespecial #1                  // Method java/lang/Object."<init>":()V
       4: return

  public synchronized org.bson.BsonDocument getCurrent();
    Code:
       0: aload_0
       1: getfield      #2                  // Field clusterTime:Lorg/bson/BsonDocument;
       4: areturn

  public synchronized void advance(org.bson.BsonDocument);
    Code:
       0: aload_0
       1: aload_0
       2: aload_1
       3: invokevirtual #3                  // Method greaterOf:(Lorg/bson/BsonDocument;)Lorg/bson/BsonDocument;
       6: putfield      #2                  // Field clusterTime:Lorg/bson/BsonDocument;
       9: return

  public synchronized org.bson.BsonDocument greaterOf(org.bson.BsonDocument);
    Code:
       0: aload_1
       1: ifnonnull     9
       4: aload_0
       5: getfield      #2                  // Field clusterTime:Lorg/bson/BsonDocument;
       8: areturn
       9: aload_0
      10: getfield      #2                  // Field clusterTime:Lorg/bson/BsonDocument;
      13: ifnonnull     18
      16: aload_1
      17: areturn
      18: aload_1
      19: ldc           #5                  // String clusterTime
      21: invokevirtual #6                  // Method org/bson/BsonDocument.getTimestamp:(Ljava/lang/Object;)Lorg/bson/BsonTimestamp;
      24: aload_0
      25: getfield      #2                  // Field clusterTime:Lorg/bson/BsonDocument;
      28: ldc           #5                  // String clusterTime
      30: invokevirtual #6                  // Method org/bson/BsonDocument.getTimestamp:(Ljava/lang/Object;)Lorg/bson/BsonTimestamp;
      33: invokevirtual #7                  // Method org/bson/BsonTimestamp.compareTo:(Lorg/bson/BsonTimestamp;)I
      36: ifle          43
      39: aload_1
      40: goto          47
      43: aload_0
      44: getfield      #2                  // Field clusterTime:Lorg/bson/BsonDocument;
      47: areturn
}
