Compiled from "CommandResultBaseCallback.java"
abstract class com.mongodb.connection.CommandResultBaseCallback<T> extends com.mongodb.connection.ResponseCallback {
  public static final com.mongodb.diagnostics.logging.Logger LOGGER;

  private final org.bson.codecs.Decoder<T> decoder;

  com.mongodb.connection.CommandResultBaseCallback(org.bson.codecs.Decoder<T>, long, com.mongodb.ServerAddress);
    Code:
       0: aload_0
       1: lload_2
       2: aload         4
       4: invokespecial #1                  // Method com/mongodb/connection/ResponseCallback."<init>":(JLcom/mongodb/ServerAddress;)V
       7: aload_0
       8: aload_1
       9: putfield      #2                  // Field decoder:Lorg/bson/codecs/Decoder;
      12: return

  protected void callCallback(com.mongodb.connection.ResponseBuffers, java.lang.Throwable);
    Code:
       0: aload_2
       1: ifnonnull     8
       4: aload_1
       5: ifnonnull     17
       8: aload_0
       9: aconst_null
      10: aload_2
      11: invokevirtual #3                  // Method callCallback:(Ljava/lang/Object;Ljava/lang/Throwable;)V
      14: goto          49
      17: new           #4                  // class com/mongodb/connection/ReplyMessage
      20: dup
      21: aload_1
      22: aload_0
      23: getfield      #2                  // Field decoder:Lorg/bson/codecs/Decoder;
      26: aload_0
      27: invokevirtual #5                  // Method getRequestId:()J
      30: invokespecial #6                  // Method com/mongodb/connection/ReplyMessage."<init>":(Lcom/mongodb/connection/ResponseBuffers;Lorg/bson/codecs/Decoder;J)V
      33: astore_3
      34: aload_0
      35: aload_3
      36: invokevirtual #7                  // Method com/mongodb/connection/ReplyMessage.getDocuments:()Ljava/util/List;
      39: iconst_0
      40: invokeinterface #8,  2            // InterfaceMethod java/util/List.get:(I)Ljava/lang/Object;
      45: aconst_null
      46: invokevirtual #3                  // Method callCallback:(Ljava/lang/Object;Ljava/lang/Throwable;)V
      49: aload_1
      50: ifnull        57
      53: aload_1
      54: invokevirtual #9                  // Method com/mongodb/connection/ResponseBuffers.close:()V
      57: goto          105
      60: astore_3
      61: getstatic     #11                 // Field LOGGER:Lcom/mongodb/diagnostics/logging/Logger;
      64: ldc           #12                 // String GetMore ResponseBuffer close exception
      66: aload_3
      67: invokeinterface #13,  3           // InterfaceMethod com/mongodb/diagnostics/logging/Logger.debug:(Ljava/lang/String;Ljava/lang/Throwable;)V
      72: goto          105
      75: astore        4
      77: aload_1
      78: ifnull        85
      81: aload_1
      82: invokevirtual #9                  // Method com/mongodb/connection/ResponseBuffers.close:()V
      85: goto          102
      88: astore        5
      90: getstatic     #11                 // Field LOGGER:Lcom/mongodb/diagnostics/logging/Logger;
      93: ldc           #12                 // String GetMore ResponseBuffer close exception
      95: aload         5
      97: invokeinterface #13,  3           // InterfaceMethod com/mongodb/diagnostics/logging/Logger.debug:(Ljava/lang/String;Ljava/lang/Throwable;)V
     102: aload         4
     104: athrow
     105: return
    Exception table:
       from    to  target type
          49    57    60   Class java/lang/Throwable
           0    49    75   any
          77    85    88   Class java/lang/Throwable
          75    77    75   any

  protected abstract void callCallback(T, java.lang.Throwable);

  static {};
    Code:
       0: ldc           #14                 // String protocol.command
       2: invokestatic  #15                 // Method com/mongodb/diagnostics/logging/Loggers.getLogger:(Ljava/lang/String;)Lcom/mongodb/diagnostics/logging/Logger;
       5: putstatic     #11                 // Field LOGGER:Lcom/mongodb/diagnostics/logging/Logger;
       8: return
}
