Compiled from "KillCursorProtocol.java"
class com.mongodb.connection.KillCursorProtocol$1 implements com.mongodb.async.SingleResultCallback<java.lang.Void> {
  final com.mongodb.connection.KillCursorsMessage val$message;

  final com.mongodb.connection.InternalConnection val$connection;

  final long val$startTimeNanos;

  final com.mongodb.connection.ByteBufferBsonOutput val$bsonOutput;

  final com.mongodb.async.SingleResultCallback val$callback;

  final com.mongodb.connection.KillCursorProtocol this$0;

  com.mongodb.connection.KillCursorProtocol$1(com.mongodb.connection.KillCursorProtocol, com.mongodb.connection.KillCursorsMessage, com.mongodb.connection.InternalConnection, long, com.mongodb.connection.ByteBufferBsonOutput, com.mongodb.async.SingleResultCallback);
    Code:
       0: aload_0
       1: aload_1
       2: putfield      #2                  // Field this$0:Lcom/mongodb/connection/KillCursorProtocol;
       5: aload_0
       6: aload_2
       7: putfield      #3                  // Field val$message:Lcom/mongodb/connection/KillCursorsMessage;
      10: aload_0
      11: aload_3
      12: putfield      #4                  // Field val$connection:Lcom/mongodb/connection/InternalConnection;
      15: aload_0
      16: lload         4
      18: putfield      #5                  // Field val$startTimeNanos:J
      21: aload_0
      22: aload         6
      24: putfield      #6                  // Field val$bsonOutput:Lcom/mongodb/connection/ByteBufferBsonOutput;
      27: aload_0
      28: aload         7
      30: putfield      #7                  // Field val$callback:Lcom/mongodb/async/SingleResultCallback;
      33: aload_0
      34: invokespecial #8                  // Method java/lang/Object."<init>":()V
      37: return

  public void onResult(java.lang.Void, java.lang.Throwable);
    Code:
       0: aload_0
       1: getfield      #2                  // Field this$0:Lcom/mongodb/connection/KillCursorProtocol;
       4: invokestatic  #9                  // Method com/mongodb/connection/KillCursorProtocol.access$000:(Lcom/mongodb/connection/KillCursorProtocol;)Lcom/mongodb/event/CommandListener;
       7: ifnull        93
      10: aload_0
      11: getfield      #2                  // Field this$0:Lcom/mongodb/connection/KillCursorProtocol;
      14: invokestatic  #10                 // Method com/mongodb/connection/KillCursorProtocol.access$100:(Lcom/mongodb/connection/KillCursorProtocol;)Lcom/mongodb/MongoNamespace;
      17: ifnull        93
      20: aload_2
      21: ifnull        57
      24: aload_0
      25: getfield      #3                  // Field val$message:Lcom/mongodb/connection/KillCursorsMessage;
      28: ldc           #11                 // String killCursors
      30: aload_0
      31: getfield      #4                  // Field val$connection:Lcom/mongodb/connection/InternalConnection;
      34: invokeinterface #12,  1           // InterfaceMethod com/mongodb/connection/InternalConnection.getDescription:()Lcom/mongodb/connection/ConnectionDescription;
      39: aload_0
      40: getfield      #5                  // Field val$startTimeNanos:J
      43: aload_2
      44: aload_0
      45: getfield      #2                  // Field this$0:Lcom/mongodb/connection/KillCursorProtocol;
      48: invokestatic  #9                  // Method com/mongodb/connection/KillCursorProtocol.access$000:(Lcom/mongodb/connection/KillCursorProtocol;)Lcom/mongodb/event/CommandListener;
      51: invokestatic  #13                 // Method com/mongodb/connection/ProtocolHelper.sendCommandFailedEvent:(Lcom/mongodb/connection/RequestMessage;Ljava/lang/String;Lcom/mongodb/connection/ConnectionDescription;JLjava/lang/Throwable;Lcom/mongodb/event/CommandListener;)V
      54: goto          93
      57: aload_0
      58: getfield      #3                  // Field val$message:Lcom/mongodb/connection/KillCursorsMessage;
      61: ldc           #11                 // String killCursors
      63: aload_0
      64: getfield      #2                  // Field this$0:Lcom/mongodb/connection/KillCursorProtocol;
      67: invokestatic  #14                 // Method com/mongodb/connection/KillCursorProtocol.access$200:(Lcom/mongodb/connection/KillCursorProtocol;)Lorg/bson/BsonDocument;
      70: aload_0
      71: getfield      #4                  // Field val$connection:Lcom/mongodb/connection/InternalConnection;
      74: invokeinterface #12,  1           // InterfaceMethod com/mongodb/connection/InternalConnection.getDescription:()Lcom/mongodb/connection/ConnectionDescription;
      79: aload_0
      80: getfield      #5                  // Field val$startTimeNanos:J
      83: aload_0
      84: getfield      #2                  // Field this$0:Lcom/mongodb/connection/KillCursorProtocol;
      87: invokestatic  #9                  // Method com/mongodb/connection/KillCursorProtocol.access$000:(Lcom/mongodb/connection/KillCursorProtocol;)Lcom/mongodb/event/CommandListener;
      90: invokestatic  #15                 // Method com/mongodb/connection/ProtocolHelper.sendCommandSucceededEvent:(Lcom/mongodb/connection/RequestMessage;Ljava/lang/String;Lorg/bson/BsonDocument;Lcom/mongodb/connection/ConnectionDescription;JLcom/mongodb/event/CommandListener;)V
      93: aload_0
      94: getfield      #6                  // Field val$bsonOutput:Lcom/mongodb/connection/ByteBufferBsonOutput;
      97: invokevirtual #16                 // Method com/mongodb/connection/ByteBufferBsonOutput.close:()V
     100: aload_0
     101: getfield      #7                  // Field val$callback:Lcom/mongodb/async/SingleResultCallback;
     104: aload_1
     105: aload_2
     106: invokeinterface #17,  3           // InterfaceMethod com/mongodb/async/SingleResultCallback.onResult:(Ljava/lang/Object;Ljava/lang/Throwable;)V
     111: return

  public void onResult(java.lang.Object, java.lang.Throwable);
    Code:
       0: aload_0
       1: aload_1
       2: checkcast     #18                 // class java/lang/Void
       5: aload_2
       6: invokevirtual #19                 // Method onResult:(Ljava/lang/Void;Ljava/lang/Throwable;)V
       9: return
}
