Compiled from "QueryMessage.java"
class com.mongodb.connection.QueryMessage extends com.mongodb.connection.BaseQueryMessage {
  private final org.bson.BsonDocument queryDocument;

  private final org.bson.BsonDocument fields;

  com.mongodb.connection.QueryMessage(java.lang.String, int, int, org.bson.BsonDocument, org.bson.BsonDocument, com.mongodb.connection.MessageSettings);
    Code:
       0: aload_0
       1: aload_1
       2: iload_2
       3: iload_3
       4: aload         6
       6: invokespecial #1                  // Method com/mongodb/connection/BaseQueryMessage."<init>":(Ljava/lang/String;IILcom/mongodb/connection/MessageSettings;)V
       9: aload_0
      10: aload         4
      12: putfield      #2                  // Field queryDocument:Lorg/bson/BsonDocument;
      15: aload_0
      16: aload         5
      18: putfield      #3                  // Field fields:Lorg/bson/BsonDocument;
      21: return

  protected com.mongodb.connection.RequestMessage$EncodingMetadata encodeMessageBodyWithMetadata(org.bson.io.BsonOutput);
    Code:
       0: aload_0
       1: aload_1
       2: invokevirtual #4                  // Method writeQueryPrologue:(Lorg/bson/io/BsonOutput;)V
       5: aload_1
       6: invokeinterface #5,  1            // InterfaceMethod org/bson/io/BsonOutput.getPosition:()I
      11: istore_2
      12: aload_0
      13: aload_0
      14: getfield      #2                  // Field queryDocument:Lorg/bson/BsonDocument;
      17: aload_1
      18: new           #6                  // class com/mongodb/internal/validator/NoOpFieldNameValidator
      21: dup
      22: invokespecial #7                  // Method com/mongodb/internal/validator/NoOpFieldNameValidator."<init>":()V
      25: invokevirtual #8                  // Method addDocument:(Lorg/bson/BsonDocument;Lorg/bson/io/BsonOutput;Lorg/bson/FieldNameValidator;)V
      28: aload_0
      29: getfield      #3                  // Field fields:Lorg/bson/BsonDocument;
      32: ifnull        51
      35: aload_0
      36: aload_0
      37: getfield      #3                  // Field fields:Lorg/bson/BsonDocument;
      40: aload_1
      41: new           #6                  // class com/mongodb/internal/validator/NoOpFieldNameValidator
      44: dup
      45: invokespecial #7                  // Method com/mongodb/internal/validator/NoOpFieldNameValidator."<init>":()V
      48: invokevirtual #8                  // Method addDocument:(Lorg/bson/BsonDocument;Lorg/bson/io/BsonOutput;Lorg/bson/FieldNameValidator;)V
      51: new           #9                  // class com/mongodb/connection/RequestMessage$EncodingMetadata
      54: dup
      55: iload_2
      56: invokespecial #10                 // Method com/mongodb/connection/RequestMessage$EncodingMetadata."<init>":(I)V
      59: areturn
}
