Compiled from "ReplyMessage.java"
class com.mongodb.connection.ReplyMessage<T> {
  private final com.mongodb.connection.ReplyHeader replyHeader;

  private final java.util.List<T> documents;

  com.mongodb.connection.ReplyMessage(com.mongodb.connection.ResponseBuffers, org.bson.codecs.Decoder<T>, long);
    Code:
       0: aload_0
       1: aload_1
       2: invokevirtual #1                  // Method com/mongodb/connection/ResponseBuffers.getReplyHeader:()Lcom/mongodb/connection/ReplyHeader;
       5: lload_3
       6: invokespecial #2                  // Method "<init>":(Lcom/mongodb/connection/ReplyHeader;J)V
       9: aload_0
      10: getfield      #3                  // Field replyHeader:Lcom/mongodb/connection/ReplyHeader;
      13: invokevirtual #4                  // Method com/mongodb/connection/ReplyHeader.getNumberReturned:()I
      16: ifle          123
      19: new           #5                  // class org/bson/io/ByteBufferBsonInput
      22: dup
      23: aload_1
      24: invokevirtual #6                  // Method com/mongodb/connection/ResponseBuffers.getBodyByteBuffer:()Lorg/bson/ByteBuf;
      27: invokespecial #7                  // Method org/bson/io/ByteBufferBsonInput."<init>":(Lorg/bson/ByteBuf;)V
      30: astore        5
      32: aload_0
      33: getfield      #8                  // Field documents:Ljava/util/List;
      36: invokeinterface #9,  1            // InterfaceMethod java/util/List.size:()I
      41: aload_0
      42: getfield      #3                  // Field replyHeader:Lcom/mongodb/connection/ReplyHeader;
      45: invokevirtual #4                  // Method com/mongodb/connection/ReplyHeader.getNumberReturned:()I
      48: if_icmpge     107
      51: new           #10                 // class org/bson/BsonBinaryReader
      54: dup
      55: aload         5
      57: invokespecial #11                 // Method org/bson/BsonBinaryReader."<init>":(Lorg/bson/io/BsonInput;)V
      60: astore        6
      62: aload_0
      63: getfield      #8                  // Field documents:Ljava/util/List;
      66: aload_2
      67: aload         6
      69: invokestatic  #12                 // Method org/bson/codecs/DecoderContext.builder:()Lorg/bson/codecs/DecoderContext$Builder;
      72: invokevirtual #13                 // Method org/bson/codecs/DecoderContext$Builder.build:()Lorg/bson/codecs/DecoderContext;
      75: invokeinterface #14,  3           // InterfaceMethod org/bson/codecs/Decoder.decode:(Lorg/bson/BsonReader;Lorg/bson/codecs/DecoderContext;)Ljava/lang/Object;
      80: invokeinterface #15,  2           // InterfaceMethod java/util/List.add:(Ljava/lang/Object;)Z
      85: pop
      86: aload         6
      88: invokevirtual #16                 // Method org/bson/BsonBinaryReader.close:()V
      91: goto          104
      94: astore        7
      96: aload         6
      98: invokevirtual #16                 // Method org/bson/BsonBinaryReader.close:()V
     101: aload         7
     103: athrow
     104: goto          32
     107: aload_1
     108: invokevirtual #17                 // Method com/mongodb/connection/ResponseBuffers.reset:()V
     111: goto          123
     114: astore        8
     116: aload_1
     117: invokevirtual #17                 // Method com/mongodb/connection/ResponseBuffers.reset:()V
     120: aload         8
     122: athrow
     123: return
    Exception table:
       from    to  target type
          62    86    94   any
          94    96    94   any
          19   107   114   any
         114   116   114   any

  com.mongodb.connection.ReplyMessage(com.mongodb.connection.ReplyHeader, long);
    Code:
       0: aload_0
       1: invokespecial #18                 // Method java/lang/Object."<init>":()V
       4: lload_2
       5: aload_1
       6: invokevirtual #19                 // Method com/mongodb/connection/ReplyHeader.getResponseTo:()I
       9: i2l
      10: lcmp
      11: ifeq          48
      14: new           #20                 // class com/mongodb/MongoInternalException
      17: dup
      18: ldc           #21                 // String The responseTo (%d) in the response does not match the requestId (%d) in the request
      20: iconst_2
      21: anewarray     #22                 // class java/lang/Object
      24: dup
      25: iconst_0
      26: aload_1
      27: invokevirtual #19                 // Method com/mongodb/connection/ReplyHeader.getResponseTo:()I
      30: invokestatic  #23                 // Method java/lang/Integer.valueOf:(I)Ljava/lang/Integer;
      33: aastore
      34: dup
      35: iconst_1
      36: lload_2
      37: invokestatic  #24                 // Method java/lang/Long.valueOf:(J)Ljava/lang/Long;
      40: aastore
      41: invokestatic  #25                 // Method java/lang/String.format:(Ljava/lang/String;[Ljava/lang/Object;)Ljava/lang/String;
      44: invokespecial #26                 // Method com/mongodb/MongoInternalException."<init>":(Ljava/lang/String;)V
      47: athrow
      48: aload_0
      49: aload_1
      50: putfield      #3                  // Field replyHeader:Lcom/mongodb/connection/ReplyHeader;
      53: aload_0
      54: new           #27                 // class java/util/ArrayList
      57: dup
      58: aload_1
      59: invokevirtual #4                  // Method com/mongodb/connection/ReplyHeader.getNumberReturned:()I
      62: invokespecial #28                 // Method java/util/ArrayList."<init>":(I)V
      65: putfield      #8                  // Field documents:Ljava/util/List;
      68: return

  public com.mongodb.connection.ReplyHeader getReplyHeader();
    Code:
       0: aload_0
       1: getfield      #3                  // Field replyHeader:Lcom/mongodb/connection/ReplyHeader;
       4: areturn

  public java.util.List<T> getDocuments();
    Code:
       0: aload_0
       1: getfield      #8                  // Field documents:Ljava/util/List;
       4: areturn
}
