Compiled from "ScramSha1Authenticator.java"
class com.mongodb.connection.ScramSha1Authenticator extends com.mongodb.connection.SaslAuthenticator {
  private final com.mongodb.connection.ScramSha1Authenticator$RandomStringGenerator randomStringGenerator;

  com.mongodb.connection.ScramSha1Authenticator(com.mongodb.MongoCredential);
    Code:
       0: aload_0
       1: aload_1
       2: new           #1                  // class com/mongodb/connection/ScramSha1Authenticator$DefaultRandomStringGenerator
       5: dup
       6: invokespecial #2                  // Method com/mongodb/connection/ScramSha1Authenticator$DefaultRandomStringGenerator."<init>":()V
       9: invokespecial #3                  // Method "<init>":(Lcom/mongodb/MongoCredential;Lcom/mongodb/connection/ScramSha1Authenticator$RandomStringGenerator;)V
      12: return

  com.mongodb.connection.ScramSha1Authenticator(com.mongodb.MongoCredential, com.mongodb.connection.ScramSha1Authenticator$RandomStringGenerator);
    Code:
       0: aload_0
       1: aload_1
       2: invokespecial #4                  // Method com/mongodb/connection/SaslAuthenticator."<init>":(Lcom/mongodb/MongoCredential;)V
       5: aload_0
       6: aload_2
       7: putfield      #5                  // Field randomStringGenerator:Lcom/mongodb/connection/ScramSha1Authenticator$RandomStringGenerator;
      10: return

  public java.lang.String getMechanismName();
    Code:
       0: getstatic     #6                  // Field com/mongodb/AuthenticationMechanism.SCRAM_SHA_1:Lcom/mongodb/AuthenticationMechanism;
       3: invokevirtual #7                  // Method com/mongodb/AuthenticationMechanism.getMechanismName:()Ljava/lang/String;
       6: areturn

  protected javax.security.sasl.SaslClient createSaslClient(com.mongodb.ServerAddress);
    Code:
       0: new           #8                  // class com/mongodb/connection/ScramSha1Authenticator$ScramSha1SaslClient
       3: dup
       4: aload_0
       5: invokevirtual #9                  // Method getCredential:()Lcom/mongodb/MongoCredential;
       8: aload_0
       9: getfield      #5                  // Field randomStringGenerator:Lcom/mongodb/connection/ScramSha1Authenticator$RandomStringGenerator;
      12: invokespecial #10                 // Method com/mongodb/connection/ScramSha1Authenticator$ScramSha1SaslClient."<init>":(Lcom/mongodb/MongoCredential;Lcom/mongodb/connection/ScramSha1Authenticator$RandomStringGenerator;)V
      15: areturn
}
