Compiled from "SnappyCompressor.java"
class com.mongodb.connection.SnappyCompressor extends com.mongodb.connection.Compressor {
  com.mongodb.connection.SnappyCompressor();
    Code:
       0: aload_0
       1: invokespecial #1                  // Method com/mongodb/connection/Compressor."<init>":()V
       4: return

  public java.lang.String getName();
    Code:
       0: ldc           #2                  // String snappy
       2: areturn

  public byte getId();
    Code:
       0: iconst_1
       1: ireturn

  public void compress(java.util.List<org.bson.ByteBuf>, org.bson.io.BsonOutput);
    Code:
       0: aload_0
       1: aload_1
       2: invokespecial #3                  // Method getUncompressedSize:(Ljava/util/List;)I
       5: istore_3
       6: iload_3
       7: newarray       byte
       9: astore        4
      11: aload_0
      12: aload_1
      13: aload         4
      15: invokespecial #4                  // Method copy:(Ljava/util/List;[B)V
      18: iload_3
      19: invokestatic  #5                  // Method org/xerial/snappy/Snappy.maxCompressedLength:(I)I
      22: newarray       byte
      24: astore        5
      26: aload         4
      28: iconst_0
      29: aload         4
      31: arraylength
      32: aload         5
      34: iconst_0
      35: invokestatic  #6                  // Method org/xerial/snappy/Snappy.compress:([BII[BI)I
      38: istore        6
      40: aload_2
      41: aload         5
      43: iconst_0
      44: iload         6
      46: invokeinterface #7,  4            // InterfaceMethod org/bson/io/BsonOutput.writeBytes:([BII)V
      51: goto          68
      54: astore        5
      56: new           #9                  // class com/mongodb/MongoInternalException
      59: dup
      60: ldc           #10                 // String Unexpected IOException
      62: aload         5
      64: invokespecial #11                 // Method com/mongodb/MongoInternalException."<init>":(Ljava/lang/String;Ljava/lang/Throwable;)V
      67: athrow
      68: return
    Exception table:
       from    to  target type
          18    51    54   Class java/io/IOException

  private int getUncompressedSize(java.util.List<org.bson.ByteBuf>);
    Code:
       0: iconst_0
       1: istore_2
       2: aload_1
       3: invokeinterface #12,  1           // InterfaceMethod java/util/List.iterator:()Ljava/util/Iterator;
       8: astore_3
       9: aload_3
      10: invokeinterface #13,  1           // InterfaceMethod java/util/Iterator.hasNext:()Z
      15: ifeq          42
      18: aload_3
      19: invokeinterface #14,  1           // InterfaceMethod java/util/Iterator.next:()Ljava/lang/Object;
      24: checkcast     #15                 // class org/bson/ByteBuf
      27: astore        4
      29: iload_2
      30: aload         4
      32: invokeinterface #16,  1           // InterfaceMethod org/bson/ByteBuf.remaining:()I
      37: iadd
      38: istore_2
      39: goto          9
      42: iload_2
      43: ireturn

  private void copy(java.util.List<org.bson.ByteBuf>, byte[]);
    Code:
       0: iconst_0
       1: istore_3
       2: aload_1
       3: invokeinterface #12,  1           // InterfaceMethod java/util/List.iterator:()Ljava/util/Iterator;
       8: astore        4
      10: aload         4
      12: invokeinterface #13,  1           // InterfaceMethod java/util/Iterator.hasNext:()Z
      17: ifeq          61
      20: aload         4
      22: invokeinterface #14,  1           // InterfaceMethod java/util/Iterator.next:()Ljava/lang/Object;
      27: checkcast     #15                 // class org/bson/ByteBuf
      30: astore        5
      32: aload         5
      34: invokeinterface #16,  1           // InterfaceMethod org/bson/ByteBuf.remaining:()I
      39: istore        6
      41: aload         5
      43: aload_2
      44: iload_3
      45: iload         6
      47: invokeinterface #17,  4           // InterfaceMethod org/bson/ByteBuf.get:([BII)Lorg/bson/ByteBuf;
      52: pop
      53: iload_3
      54: iload         6
      56: iadd
      57: istore_3
      58: goto          10
      61: return

  java.io.InputStream getInputStream(java.io.InputStream) throws java.io.IOException;
    Code:
       0: new           #18                 // class org/xerial/snappy/SnappyInputStream
       3: dup
       4: aload_1
       5: invokespecial #19                 // Method org/xerial/snappy/SnappyInputStream."<init>":(Ljava/io/InputStream;)V
       8: areturn
}
