Compiled from "SslSettings.java"
public class com.mongodb.connection.SslSettings {
  private final boolean enabled;

  private final boolean invalidHostNameAllowed;

  private final javax.net.ssl.SSLContext context;

  public static com.mongodb.connection.SslSettings$Builder builder();
    Code:
       0: new           #1                  // class com/mongodb/connection/SslSettings$Builder
       3: dup
       4: invokespecial #2                  // Method com/mongodb/connection/SslSettings$Builder."<init>":()V
       7: areturn

  public boolean isEnabled();
    Code:
       0: aload_0
       1: getfield      #3                  // Field enabled:Z
       4: ireturn

  public boolean isInvalidHostNameAllowed();
    Code:
       0: aload_0
       1: getfield      #4                  // Field invalidHostNameAllowed:Z
       4: ireturn

  public javax.net.ssl.SSLContext getContext();
    Code:
       0: aload_0
       1: getfield      #5                  // Field context:Ljavax/net/ssl/SSLContext;
       4: areturn

  com.mongodb.connection.SslSettings(com.mongodb.connection.SslSettings$Builder);
    Code:
       0: aload_0
       1: invokespecial #6                  // Method java/lang/Object."<init>":()V
       4: aload_0
       5: aload_1
       6: invokestatic  #7                  // Method com/mongodb/connection/SslSettings$Builder.access$000:(Lcom/mongodb/connection/SslSettings$Builder;)Z
       9: putfield      #3                  // Field enabled:Z
      12: aload_0
      13: aload_1
      14: invokestatic  #8                  // Method com/mongodb/connection/SslSettings$Builder.access$100:(Lcom/mongodb/connection/SslSettings$Builder;)Z
      17: putfield      #4                  // Field invalidHostNameAllowed:Z
      20: aload_0
      21: getfield      #3                  // Field enabled:Z
      24: ifeq          57
      27: aload_0
      28: getfield      #4                  // Field invalidHostNameAllowed:Z
      31: ifne          57
      34: ldc           #9                  // String java.version
      36: invokestatic  #10                 // Method java/lang/System.getProperty:(Ljava/lang/String;)Ljava/lang/String;
      39: ldc           #11                 // String 1.6.
      41: invokevirtual #12                 // Method java/lang/String.startsWith:(Ljava/lang/String;)Z
      44: ifeq          57
      47: new           #13                 // class com/mongodb/MongoInternalException
      50: dup
      51: ldc           #14                 // String By default, SSL connections are only supported on Java 7 or later.  If the application must run on Java 6, you must set the SslSettings.invalidHostNameAllowed property to true
      53: invokespecial #15                 // Method com/mongodb/MongoInternalException."<init>":(Ljava/lang/String;)V
      56: athrow
      57: aload_0
      58: aload_1
      59: invokestatic  #16                 // Method com/mongodb/connection/SslSettings$Builder.access$200:(Lcom/mongodb/connection/SslSettings$Builder;)Ljavax/net/ssl/SSLContext;
      62: putfield      #5                  // Field context:Ljavax/net/ssl/SSLContext;
      65: return

  public boolean equals(java.lang.Object);
    Code:
       0: aload_0
       1: aload_1
       2: if_acmpne     7
       5: iconst_1
       6: ireturn
       7: aload_1
       8: ifnull        22
      11: aload_0
      12: invokevirtual #17                 // Method java/lang/Object.getClass:()Ljava/lang/Class;
      15: aload_1
      16: invokevirtual #17                 // Method java/lang/Object.getClass:()Ljava/lang/Class;
      19: if_acmpeq     24
      22: iconst_0
      23: ireturn
      24: aload_1
      25: checkcast     #18                 // class com/mongodb/connection/SslSettings
      28: astore_2
      29: aload_0
      30: getfield      #3                  // Field enabled:Z
      33: aload_2
      34: getfield      #3                  // Field enabled:Z
      37: if_icmpeq     42
      40: iconst_0
      41: ireturn
      42: aload_0
      43: getfield      #4                  // Field invalidHostNameAllowed:Z
      46: aload_2
      47: getfield      #4                  // Field invalidHostNameAllowed:Z
      50: if_icmpeq     55
      53: iconst_0
      54: ireturn
      55: aload_0
      56: getfield      #5                  // Field context:Ljavax/net/ssl/SSLContext;
      59: ifnull        76
      62: aload_0
      63: getfield      #5                  // Field context:Ljavax/net/ssl/SSLContext;
      66: aload_2
      67: getfield      #5                  // Field context:Ljavax/net/ssl/SSLContext;
      70: invokevirtual #19                 // Method java/lang/Object.equals:(Ljava/lang/Object;)Z
      73: goto          88
      76: aload_2
      77: getfield      #5                  // Field context:Ljavax/net/ssl/SSLContext;
      80: ifnonnull     87
      83: iconst_1
      84: goto          88
      87: iconst_0
      88: ireturn

  public int hashCode();
    Code:
       0: aload_0
       1: getfield      #3                  // Field enabled:Z
       4: ifeq          11
       7: iconst_1
       8: goto          12
      11: iconst_0
      12: istore_1
      13: bipush        31
      15: iload_1
      16: imul
      17: aload_0
      18: getfield      #4                  // Field invalidHostNameAllowed:Z
      21: ifeq          28
      24: iconst_1
      25: goto          29
      28: iconst_0
      29: iadd
      30: istore_1
      31: bipush        31
      33: iload_1
      34: imul
      35: aload_0
      36: getfield      #5                  // Field context:Ljavax/net/ssl/SSLContext;
      39: ifnull        52
      42: aload_0
      43: getfield      #5                  // Field context:Ljavax/net/ssl/SSLContext;
      46: invokevirtual #20                 // Method java/lang/Object.hashCode:()I
      49: goto          53
      52: iconst_0
      53: iadd
      54: istore_1
      55: iload_1
      56: ireturn

  public java.lang.String toString();
    Code:
       0: new           #21                 // class java/lang/StringBuilder
       3: dup
       4: invokespecial #22                 // Method java/lang/StringBuilder."<init>":()V
       7: ldc           #23                 // String SslSettings{enabled=
       9: invokevirtual #24                 // Method java/lang/StringBuilder.append:(Ljava/lang/String;)Ljava/lang/StringBuilder;
      12: aload_0
      13: getfield      #3                  // Field enabled:Z
      16: invokevirtual #25                 // Method java/lang/StringBuilder.append:(Z)Ljava/lang/StringBuilder;
      19: ldc           #26                 // String , invalidHostNameAllowed=
      21: invokevirtual #24                 // Method java/lang/StringBuilder.append:(Ljava/lang/String;)Ljava/lang/StringBuilder;
      24: aload_0
      25: getfield      #4                  // Field invalidHostNameAllowed:Z
      28: invokevirtual #25                 // Method java/lang/StringBuilder.append:(Z)Ljava/lang/StringBuilder;
      31: ldc           #27                 // String , context=
      33: invokevirtual #24                 // Method java/lang/StringBuilder.append:(Ljava/lang/String;)Ljava/lang/StringBuilder;
      36: aload_0
      37: getfield      #5                  // Field context:Ljavax/net/ssl/SSLContext;
      40: invokevirtual #28                 // Method java/lang/StringBuilder.append:(Ljava/lang/Object;)Ljava/lang/StringBuilder;
      43: bipush        125
      45: invokevirtual #29                 // Method java/lang/StringBuilder.append:(C)Ljava/lang/StringBuilder;
      48: invokevirtual #30                 // Method java/lang/StringBuilder.toString:()Ljava/lang/String;
      51: areturn
}
