Compiled from "ImagePullPolicy.java"
public final class io.dekorate.kubernetes.annotation.ImagePullPolicy extends java.lang.Enum<io.dekorate.kubernetes.annotation.ImagePullPolicy> {
  public static final io.dekorate.kubernetes.annotation.ImagePullPolicy Always;

  public static final io.dekorate.kubernetes.annotation.ImagePullPolicy IfNotPresent;

  public static final io.dekorate.kubernetes.annotation.ImagePullPolicy Never;

  private static final io.dekorate.kubernetes.annotation.ImagePullPolicy[] $VALUES;

  public static io.dekorate.kubernetes.annotation.ImagePullPolicy[] values();
    Code:
       0: getstatic     #1                  // Field $VALUES:[Lio/dekorate/kubernetes/annotation/ImagePullPolicy;
       3: invokevirtual #2                  // Method "[Lio/dekorate/kubernetes/annotation/ImagePullPolicy;".clone:()Ljava/lang/Object;
       6: checkcast     #3                  // class "[Lio/dekorate/kubernetes/annotation/ImagePullPolicy;"
       9: areturn

  public static io.dekorate.kubernetes.annotation.ImagePullPolicy valueOf(java.lang.String);
    Code:
       0: ldc           #4                  // class io/dekorate/kubernetes/annotation/ImagePullPolicy
       2: aload_0
       3: invokestatic  #5                  // Method java/lang/Enum.valueOf:(Ljava/lang/Class;Ljava/lang/String;)Ljava/lang/Enum;
       6: checkcast     #4                  // class io/dekorate/kubernetes/annotation/ImagePullPolicy
       9: areturn

  private io.dekorate.kubernetes.annotation.ImagePullPolicy();
    Code:
       0: aload_0
       1: aload_1
       2: iload_2
       3: invokespecial #6                  // Method java/lang/Enum."<init>":(Ljava/lang/String;I)V
       6: return

  static {};
    Code:
       0: new           #4                  // class io/dekorate/kubernetes/annotation/ImagePullPolicy
       3: dup
       4: ldc           #7                  // String Always
       6: iconst_0
       7: invokespecial #8                  // Method "<init>":(Ljava/lang/String;I)V
      10: putstatic     #9                  // Field Always:Lio/dekorate/kubernetes/annotation/ImagePullPolicy;
      13: new           #4                  // class io/dekorate/kubernetes/annotation/ImagePullPolicy
      16: dup
      17: ldc           #10                 // String IfNotPresent
      19: iconst_1
      20: invokespecial #8                  // Method "<init>":(Ljava/lang/String;I)V
      23: putstatic     #11                 // Field IfNotPresent:Lio/dekorate/kubernetes/annotation/ImagePullPolicy;
      26: new           #4                  // class io/dekorate/kubernetes/annotation/ImagePullPolicy
      29: dup
      30: ldc           #12                 // String Never
      32: iconst_2
      33: invokespecial #8                  // Method "<init>":(Ljava/lang/String;I)V
      36: putstatic     #13                 // Field Never:Lio/dekorate/kubernetes/annotation/ImagePullPolicy;
      39: iconst_3
      40: anewarray     #4                  // class io/dekorate/kubernetes/annotation/ImagePullPolicy
      43: dup
      44: iconst_0
      45: getstatic     #9                  // Field Always:Lio/dekorate/kubernetes/annotation/ImagePullPolicy;
      48: aastore
      49: dup
      50: iconst_1
      51: getstatic     #11                 // Field IfNotPresent:Lio/dekorate/kubernetes/annotation/ImagePullPolicy;
      54: aastore
      55: dup
      56: iconst_2
      57: getstatic     #13                 // Field Never:Lio/dekorate/kubernetes/annotation/ImagePullPolicy;
      60: aastore
      61: putstatic     #1                  // Field $VALUES:[Lio/dekorate/kubernetes/annotation/ImagePullPolicy;
      64: return
}
