Compiled from "NullAppender.java"
public class org.apache.log4j.varia.NullAppender extends org.apache.log4j.AppenderSkeleton {
  private static org.apache.log4j.varia.NullAppender instance;

  static {};
    Code:
       0: new           #2                  // class org/apache/log4j/varia/NullAppender
       3: dup
       4: invokespecial #4                  // Method "<init>":()V
       7: putstatic     #5                  // Field instance:Lorg/apache/log4j/varia/NullAppender;
      10: return

  public org.apache.log4j.varia.NullAppender();
    Code:
       0: aload_0
       1: invokespecial #3                  // Method org/apache/log4j/AppenderSkeleton."<init>":()V
       4: return

  public void activateOptions();
    Code:
       0: return

  protected void append(org.apache.log4j.spi.LoggingEvent);
    Code:
       0: return

  public void close();
    Code:
       0: return

  public void doAppend(org.apache.log4j.spi.LoggingEvent);
    Code:
       0: return

  public org.apache.log4j.varia.NullAppender getInstance();
    Code:
       0: getstatic     #5                  // Field instance:Lorg/apache/log4j/varia/NullAppender;
       3: areturn

  public boolean requiresLayout();
    Code:
       0: iconst_0
       1: ireturn
}
