Compiled from "HTTPSchemeServerAuthModule.java"
public class org.wildfly.extension.undertow.security.jaspi.modules.HTTPSchemeServerAuthModule implements javax.security.auth.message.module.ServerAuthModule {
  private final java.lang.String securityDomain;

  private io.undertow.security.api.AuthenticationMechanism authenticationMechanism;

  public org.wildfly.extension.undertow.security.jaspi.modules.HTTPSchemeServerAuthModule(java.lang.String);
    Code:
       0: aload_0
       1: invokespecial #1                  // Method java/lang/Object."<init>":()V
       4: aload_0
       5: aload_1
       6: putfield      #2                  // Field securityDomain:Ljava/lang/String;
       9: return

  public void initialize(javax.security.auth.message.MessagePolicy, javax.security.auth.message.MessagePolicy, javax.security.auth.callback.CallbackHandler, java.util.Map) throws javax.security.auth.message.AuthException;
    Code:
       0: return

  public javax.security.auth.message.AuthStatus secureResponse(javax.security.auth.message.MessageInfo, javax.security.auth.Subject) throws javax.security.auth.message.AuthException;
    Code:
       0: getstatic     #3                  // Field javax/security/auth/message/AuthStatus.SUCCESS:Ljavax/security/auth/message/AuthStatus;
       3: areturn

  public javax.security.auth.message.AuthStatus validateRequest(javax.security.auth.message.MessageInfo, javax.security.auth.Subject, javax.security.auth.Subject) throws javax.security.auth.message.AuthException;
    Code:
       0: aload_1
       1: invokeinterface #4,  1            // InterfaceMethod javax/security/auth/message/MessageInfo.getMap:()Ljava/util/Map;
       6: getstatic     #5                  // Field org/wildfly/extension/undertow/security/jaspi/JASPICAuthenticationMechanism.HTTP_SERVER_EXCHANGE_ATTACHMENT_KEY:Lio/undertow/util/AttachmentKey;
       9: invokeinterface #6,  2            // InterfaceMethod java/util/Map.get:(Ljava/lang/Object;)Ljava/lang/Object;
      14: checkcast     #7                  // class io/undertow/server/HttpServerExchange
      17: astore        4
      19: aload_1
      20: invokeinterface #4,  1            // InterfaceMethod javax/security/auth/message/MessageInfo.getMap:()Ljava/util/Map;
      25: getstatic     #8                  // Field org/wildfly/extension/undertow/security/jaspi/JASPICAuthenticationMechanism.SECURITY_CONTEXT_ATTACHMENT_KEY:Lio/undertow/util/AttachmentKey;
      28: invokeinterface #6,  2            // InterfaceMethod java/util/Map.get:(Ljava/lang/Object;)Ljava/lang/Object;
      33: checkcast     #9                  // class io/undertow/security/api/SecurityContext
      36: astore        5
      38: aload         4
      40: getstatic     #10                 // Field io/undertow/servlet/handlers/ServletRequestContext.ATTACHMENT_KEY:Lio/undertow/util/AttachmentKey;
      43: invokevirtual #11                 // Method io/undertow/server/HttpServerExchange.getAttachment:(Lio/undertow/util/AttachmentKey;)Ljava/lang/Object;
      46: checkcast     #12                 // class io/undertow/servlet/handlers/ServletRequestContext
      49: astore        6
      51: aload         6
      53: invokevirtual #13                 // Method io/undertow/servlet/handlers/ServletRequestContext.getDeployment:()Lio/undertow/servlet/api/Deployment;
      56: invokeinterface #14,  1           // InterfaceMethod io/undertow/servlet/api/Deployment.getAuthenticationMechanisms:()Ljava/util/List;
      61: astore        7
      63: iconst_0
      64: istore        8
      66: aload         7
      68: invokeinterface #15,  1           // InterfaceMethod java/util/List.iterator:()Ljava/util/Iterator;
      73: astore        9
      75: aload         9
      77: invokeinterface #16,  1           // InterfaceMethod java/util/Iterator.hasNext:()Z
      82: ifeq          138
      85: aload         9
      87: invokeinterface #17,  1           // InterfaceMethod java/util/Iterator.next:()Ljava/lang/Object;
      92: checkcast     #18                 // class io/undertow/security/api/AuthenticationMechanism
      95: astore        10
      97: aload         10
      99: aload         4
     101: aload         5
     103: invokeinterface #19,  3           // InterfaceMethod io/undertow/security/api/AuthenticationMechanism.authenticate:(Lio/undertow/server/HttpServerExchange;Lio/undertow/security/api/SecurityContext;)Lio/undertow/security/api/AuthenticationMechanism$AuthenticationMechanismOutcome;
     108: astore        11
     110: aload         11
     112: getstatic     #20                 // Field io/undertow/security/api/AuthenticationMechanism$AuthenticationMechanismOutcome.AUTHENTICATED:Lio/undertow/security/api/AuthenticationMechanism$AuthenticationMechanismOutcome;
     115: if_acmpne     124
     118: iconst_1
     119: istore        8
     121: goto          138
     124: aload         11
     126: getstatic     #21                 // Field io/undertow/security/api/AuthenticationMechanism$AuthenticationMechanismOutcome.NOT_AUTHENTICATED:Lio/undertow/security/api/AuthenticationMechanism$AuthenticationMechanismOutcome;
     129: if_acmpne     135
     132: goto          138
     135: goto          75
     138: iload         8
     140: ifne          267
     143: aload_1
     144: invokeinterface #4,  1            // InterfaceMethod javax/security/auth/message/MessageInfo.getMap:()Ljava/util/Map;
     149: ldc           #22                 // String javax.security.auth.message.MessagePolicy.isMandatory
     151: invokeinterface #6,  2            // InterfaceMethod java/util/Map.get:(Ljava/lang/Object;)Ljava/lang/Object;
     156: checkcast     #23                 // class java/lang/String
     159: astore        9
     161: aload         9
     163: ifnull        183
     166: aload         9
     168: invokevirtual #24                 // Method java/lang/String.toLowerCase:()Ljava/lang/String;
     171: ldc           #25                 // String false
     173: invokevirtual #26                 // Method java/lang/String.equals:(Ljava/lang/Object;)Z
     176: ifeq          183
     179: getstatic     #3                  // Field javax/security/auth/message/AuthStatus.SUCCESS:Ljavax/security/auth/message/AuthStatus;
     182: areturn
     183: aload         7
     185: invokeinterface #15,  1           // InterfaceMethod java/util/List.iterator:()Ljava/util/Iterator;
     190: astore        10
     192: aload         10
     194: invokeinterface #16,  1           // InterfaceMethod java/util/Iterator.hasNext:()Z
     199: ifeq          263
     202: aload         10
     204: invokeinterface #17,  1           // InterfaceMethod java/util/Iterator.next:()Ljava/lang/Object;
     209: checkcast     #18                 // class io/undertow/security/api/AuthenticationMechanism
     212: astore        11
     214: aload         11
     216: aload         4
     218: aload         5
     220: invokeinterface #27,  3           // InterfaceMethod io/undertow/security/api/AuthenticationMechanism.sendChallenge:(Lio/undertow/server/HttpServerExchange;Lio/undertow/security/api/SecurityContext;)Lio/undertow/security/api/AuthenticationMechanism$ChallengeResult;
     225: astore        12
     227: aload         12
     229: invokevirtual #28                 // Method io/undertow/security/api/AuthenticationMechanism$ChallengeResult.getDesiredResponseCode:()Ljava/lang/Integer;
     232: ifnull        249
     235: aload         4
     237: aload         12
     239: invokevirtual #28                 // Method io/undertow/security/api/AuthenticationMechanism$ChallengeResult.getDesiredResponseCode:()Ljava/lang/Integer;
     242: invokevirtual #29                 // Method java/lang/Integer.intValue:()I
     245: invokevirtual #30                 // Method io/undertow/server/HttpServerExchange.setResponseCode:(I)Lio/undertow/server/HttpServerExchange;
     248: pop
     249: aload         4
     251: invokevirtual #31                 // Method io/undertow/server/HttpServerExchange.isResponseComplete:()Z
     254: ifeq          260
     257: goto          263
     260: goto          192
     263: getstatic     #32                 // Field javax/security/auth/message/AuthStatus.SEND_CONTINUE:Ljavax/security/auth/message/AuthStatus;
     266: areturn
     267: goto          315
     270: astore        8
     272: getstatic     #34                 // Field org/wildfly/extension/undertow/logging/UndertowLogger.ROOT_LOGGER:Lorg/wildfly/extension/undertow/logging/UndertowLogger;
     275: aload         8
     277: invokeinterface #35,  2           // InterfaceMethod org/wildfly/extension/undertow/logging/UndertowLogger.debug:(Ljava/lang/Object;)V
     282: new           #36                 // class javax/security/auth/message/AuthException
     285: dup
     286: new           #37                 // class java/lang/StringBuilder
     289: dup
     290: invokespecial #38                 // Method java/lang/StringBuilder."<init>":()V
     293: ldc           #39                 // String Could not validateRequest using mechanisms [
     295: invokevirtual #40                 // Method java/lang/StringBuilder.append:(Ljava/lang/String;)Ljava/lang/StringBuilder;
     298: aload         7
     300: invokevirtual #41                 // Method java/lang/StringBuilder.append:(Ljava/lang/Object;)Ljava/lang/StringBuilder;
     303: ldc           #42                 // String .
     305: invokevirtual #40                 // Method java/lang/StringBuilder.append:(Ljava/lang/String;)Ljava/lang/StringBuilder;
     308: invokevirtual #43                 // Method java/lang/StringBuilder.toString:()Ljava/lang/String;
     311: invokespecial #44                 // Method javax/security/auth/message/AuthException."<init>":(Ljava/lang/String;)V
     314: athrow
     315: getstatic     #3                  // Field javax/security/auth/message/AuthStatus.SUCCESS:Ljavax/security/auth/message/AuthStatus;
     318: areturn
    Exception table:
       from    to  target type
          63   182   270   Class java/lang/Exception
         183   266   270   Class java/lang/Exception

  public java.lang.Class[] getSupportedMessageTypes();
    Code:
       0: iconst_4
       1: anewarray     #45                 // class java/lang/Class
       4: dup
       5: iconst_0
       6: ldc           #46                 // class javax/servlet/ServletRequest
       8: aastore
       9: dup
      10: iconst_1
      11: ldc           #47                 // class javax/servlet/ServletResponse
      13: aastore
      14: dup
      15: iconst_2
      16: ldc           #48                 // class javax/servlet/http/HttpServletRequest
      18: aastore
      19: dup
      20: iconst_3
      21: ldc           #49                 // class javax/servlet/http/HttpServletResponse
      23: aastore
      24: areturn

  public void cleanSubject(javax.security.auth.message.MessageInfo, javax.security.auth.Subject) throws javax.security.auth.message.AuthException;
    Code:
       0: return
}
