Compiled from "StoreRemoveCommand.java"
public class net.sf.ehcache.transaction.xa.commands.StoreRemoveCommand extends net.sf.ehcache.transaction.xa.commands.AbstractStoreCommand {
  private java.lang.Object key;

  public net.sf.ehcache.transaction.xa.commands.StoreRemoveCommand(java.lang.Object, net.sf.ehcache.Element);
    Code:
       0: aload_0
       1: aload_2
       2: aconst_null
       3: invokespecial #1                  // Method net/sf/ehcache/transaction/xa/commands/AbstractStoreCommand."<init>":(Lnet/sf/ehcache/Element;Lnet/sf/ehcache/Element;)V
       6: aload_0
       7: aload_1
       8: putfield      #2                  // Field key:Ljava/lang/Object;
      11: return

  public boolean isPut(java.lang.Object);
    Code:
       0: iconst_0
       1: ireturn

  public boolean isRemove(java.lang.Object);
    Code:
       0: aload_0
       1: invokevirtual #3                  // Method getObjectKey:()Ljava/lang/Object;
       4: aload_1
       5: invokevirtual #4                  // Method java/lang/Object.equals:(Ljava/lang/Object;)Z
       8: ireturn

  public java.lang.Object getObjectKey();
    Code:
       0: aload_0
       1: getfield      #2                  // Field key:Ljava/lang/Object;
       4: areturn

  public net.sf.ehcache.CacheEntry getEntry();
    Code:
       0: new           #5                  // class net/sf/ehcache/CacheEntry
       3: dup
       4: aload_0
       5: getfield      #2                  // Field key:Ljava/lang/Object;
       8: aload_0
       9: invokevirtual #6                  // Method getOldElement:()Lnet/sf/ehcache/Element;
      12: invokespecial #7                  // Method net/sf/ehcache/CacheEntry."<init>":(Ljava/lang/Object;Lnet/sf/ehcache/Element;)V
      15: areturn
}
