Compiled from "HostTable.java"
public class io.undertow.server.handlers.proxy.HostTable<H> {
  private final java.util.Map<H, java.util.Set<io.undertow.server.handlers.proxy.HostTable$Target>> hosts;

  private final java.util.Map<java.lang.String, io.undertow.util.PathMatcher<java.util.Set<H>>> targets;

  public io.undertow.server.handlers.proxy.HostTable();
    Code:
       0: aload_0
       1: invokespecial #1                  // Method java/lang/Object."<init>":()V
       4: aload_0
       5: new           #2                  // class io/undertow/util/CopyOnWriteMap
       8: dup
       9: invokespecial #3                  // Method io/undertow/util/CopyOnWriteMap."<init>":()V
      12: putfield      #4                  // Field hosts:Ljava/util/Map;
      15: aload_0
      16: new           #2                  // class io/undertow/util/CopyOnWriteMap
      19: dup
      20: invokespecial #3                  // Method io/undertow/util/CopyOnWriteMap."<init>":()V
      23: putfield      #5                  // Field targets:Ljava/util/Map;
      26: return

  public synchronized io.undertow.server.handlers.proxy.HostTable addHost(H);
    Code:
       0: aload_0
       1: getfield      #4                  // Field hosts:Ljava/util/Map;
       4: aload_1
       5: invokeinterface #6,  2            // InterfaceMethod java/util/Map.containsKey:(Ljava/lang/Object;)Z
      10: ifeq          23
      13: getstatic     #7                  // Field io/undertow/UndertowMessages.MESSAGES:Lio/undertow/UndertowMessages;
      16: aload_1
      17: invokeinterface #8,  2            // InterfaceMethod io/undertow/UndertowMessages.hostAlreadyRegistered:(Ljava/lang/Object;)Ljava/lang/RuntimeException;
      22: athrow
      23: aload_0
      24: getfield      #4                  // Field hosts:Ljava/util/Map;
      27: aload_1
      28: new           #9                  // class java/util/concurrent/CopyOnWriteArraySet
      31: dup
      32: invokespecial #10                 // Method java/util/concurrent/CopyOnWriteArraySet."<init>":()V
      35: invokeinterface #11,  3           // InterfaceMethod java/util/Map.put:(Ljava/lang/Object;Ljava/lang/Object;)Ljava/lang/Object;
      40: pop
      41: aload_0
      42: areturn

  public synchronized io.undertow.server.handlers.proxy.HostTable removeHost(H);
    Code:
       0: aload_0
       1: getfield      #4                  // Field hosts:Ljava/util/Map;
       4: aload_1
       5: invokeinterface #12,  2           // InterfaceMethod java/util/Map.remove:(Ljava/lang/Object;)Ljava/lang/Object;
      10: checkcast     #13                 // class java/util/Set
      13: astore_2
      14: aload_2
      15: invokeinterface #14,  1           // InterfaceMethod java/util/Set.iterator:()Ljava/util/Iterator;
      20: astore_3
      21: aload_3
      22: invokeinterface #15,  1           // InterfaceMethod java/util/Iterator.hasNext:()Z
      27: ifeq          60
      30: aload_3
      31: invokeinterface #16,  1           // InterfaceMethod java/util/Iterator.next:()Ljava/lang/Object;
      36: checkcast     #17                 // class io/undertow/server/handlers/proxy/HostTable$Target
      39: astore        4
      41: aload_0
      42: aload_1
      43: aload         4
      45: getfield      #18                 // Field io/undertow/server/handlers/proxy/HostTable$Target.virtualHost:Ljava/lang/String;
      48: aload         4
      50: getfield      #19                 // Field io/undertow/server/handlers/proxy/HostTable$Target.contextPath:Ljava/lang/String;
      53: invokevirtual #20                 // Method removeRoute:(Ljava/lang/Object;Ljava/lang/String;Ljava/lang/String;)Lio/undertow/server/handlers/proxy/HostTable;
      56: pop
      57: goto          21
      60: aload_0
      61: areturn

  public synchronized io.undertow.server.handlers.proxy.HostTable addRoute(H, java.lang.String, java.lang.String);
    Code:
       0: aload_0
       1: getfield      #4                  // Field hosts:Ljava/util/Map;
       4: aload_1
       5: invokeinterface #21,  2           // InterfaceMethod java/util/Map.get:(Ljava/lang/Object;)Ljava/lang/Object;
      10: checkcast     #13                 // class java/util/Set
      13: astore        4
      15: aload         4
      17: ifnonnull     30
      20: getstatic     #7                  // Field io/undertow/UndertowMessages.MESSAGES:Lio/undertow/UndertowMessages;
      23: aload_1
      24: invokeinterface #22,  2           // InterfaceMethod io/undertow/UndertowMessages.hostHasNotBeenRegistered:(Ljava/lang/Object;)Ljava/lang/RuntimeException;
      29: athrow
      30: aload         4
      32: new           #17                 // class io/undertow/server/handlers/proxy/HostTable$Target
      35: dup
      36: aload_2
      37: aload_3
      38: aconst_null
      39: invokespecial #23                 // Method io/undertow/server/handlers/proxy/HostTable$Target."<init>":(Ljava/lang/String;Ljava/lang/String;Lio/undertow/server/handlers/proxy/HostTable$1;)V
      42: invokeinterface #24,  2           // InterfaceMethod java/util/Set.add:(Ljava/lang/Object;)Z
      47: pop
      48: aload_0
      49: getfield      #5                  // Field targets:Ljava/util/Map;
      52: aload_2
      53: invokeinterface #21,  2           // InterfaceMethod java/util/Map.get:(Ljava/lang/Object;)Ljava/lang/Object;
      58: checkcast     #25                 // class io/undertow/util/PathMatcher
      61: astore        5
      63: aload         5
      65: ifnonnull     90
      68: new           #25                 // class io/undertow/util/PathMatcher
      71: dup
      72: invokespecial #26                 // Method io/undertow/util/PathMatcher."<init>":()V
      75: astore        5
      77: aload_0
      78: getfield      #5                  // Field targets:Ljava/util/Map;
      81: aload_2
      82: aload         5
      84: invokeinterface #11,  3           // InterfaceMethod java/util/Map.put:(Ljava/lang/Object;Ljava/lang/Object;)Ljava/lang/Object;
      89: pop
      90: aload         5
      92: aload_3
      93: invokevirtual #27                 // Method io/undertow/util/PathMatcher.getPrefixPath:(Ljava/lang/String;)Ljava/lang/Object;
      96: checkcast     #13                 // class java/util/Set
      99: astore        6
     101: aload         6
     103: ifnonnull     124
     106: new           #9                  // class java/util/concurrent/CopyOnWriteArraySet
     109: dup
     110: invokespecial #10                 // Method java/util/concurrent/CopyOnWriteArraySet."<init>":()V
     113: astore        6
     115: aload         5
     117: aload_3
     118: aload         6
     120: invokevirtual #28                 // Method io/undertow/util/PathMatcher.addPrefixPath:(Ljava/lang/String;Ljava/lang/Object;)Lio/undertow/util/PathMatcher;
     123: pop
     124: aload         6
     126: aload_1
     127: invokeinterface #24,  2           // InterfaceMethod java/util/Set.add:(Ljava/lang/Object;)Z
     132: pop
     133: aload_0
     134: areturn

  public synchronized io.undertow.server.handlers.proxy.HostTable removeRoute(H, java.lang.String, java.lang.String);
    Code:
       0: aload_0
       1: getfield      #4                  // Field hosts:Ljava/util/Map;
       4: aload_1
       5: invokeinterface #21,  2           // InterfaceMethod java/util/Map.get:(Ljava/lang/Object;)Ljava/lang/Object;
      10: checkcast     #13                 // class java/util/Set
      13: astore        4
      15: aload         4
      17: ifnull        38
      20: aload         4
      22: new           #17                 // class io/undertow/server/handlers/proxy/HostTable$Target
      25: dup
      26: aload_2
      27: aload_3
      28: aconst_null
      29: invokespecial #23                 // Method io/undertow/server/handlers/proxy/HostTable$Target."<init>":(Ljava/lang/String;Ljava/lang/String;Lio/undertow/server/handlers/proxy/HostTable$1;)V
      32: invokeinterface #29,  2           // InterfaceMethod java/util/Set.remove:(Ljava/lang/Object;)Z
      37: pop
      38: aload_0
      39: getfield      #5                  // Field targets:Ljava/util/Map;
      42: aload_2
      43: invokeinterface #21,  2           // InterfaceMethod java/util/Map.get:(Ljava/lang/Object;)Ljava/lang/Object;
      48: checkcast     #25                 // class io/undertow/util/PathMatcher
      51: astore        5
      53: aload         5
      55: ifnonnull     60
      58: aload_0
      59: areturn
      60: aload         5
      62: aload_3
      63: invokevirtual #27                 // Method io/undertow/util/PathMatcher.getPrefixPath:(Ljava/lang/String;)Ljava/lang/Object;
      66: checkcast     #13                 // class java/util/Set
      69: astore        6
      71: aload         6
      73: ifnonnull     78
      76: aload_0
      77: areturn
      78: aload         6
      80: aload_1
      81: invokeinterface #29,  2           // InterfaceMethod java/util/Set.remove:(Ljava/lang/Object;)Z
      86: pop
      87: aload         6
      89: invokeinterface #30,  1           // InterfaceMethod java/util/Set.isEmpty:()Z
      94: ifeq          104
      97: aload         5
      99: aload_3
     100: invokevirtual #31                 // Method io/undertow/util/PathMatcher.removePrefixPath:(Ljava/lang/String;)Lio/undertow/util/PathMatcher;
     103: pop
     104: aload_0
     105: areturn

  public java.util.Set<H> getHostsForTarget(java.lang.String, java.lang.String);
    Code:
       0: aload_0
       1: getfield      #5                  // Field targets:Ljava/util/Map;
       4: aload_1
       5: invokeinterface #21,  2           // InterfaceMethod java/util/Map.get:(Ljava/lang/Object;)Ljava/lang/Object;
      10: checkcast     #25                 // class io/undertow/util/PathMatcher
      13: astore_3
      14: aload_3
      15: ifnonnull     20
      18: aconst_null
      19: areturn
      20: aload_3
      21: aload_2
      22: invokevirtual #32                 // Method io/undertow/util/PathMatcher.match:(Ljava/lang/String;)Lio/undertow/util/PathMatcher$PathMatch;
      25: invokevirtual #33                 // Method io/undertow/util/PathMatcher$PathMatch.getValue:()Ljava/lang/Object;
      28: checkcast     #13                 // class java/util/Set
      31: areturn
}
