Compiled from "ProxyHandler.java"
final class io.undertow.server.handlers.proxy.ProxyHandler$IoExceptionHandler implements org.xnio.ChannelExceptionHandler<java.nio.channels.Channel> {
  private final io.undertow.server.HttpServerExchange exchange;

  private final io.undertow.client.ClientConnection clientConnection;

  private io.undertow.server.handlers.proxy.ProxyHandler$IoExceptionHandler(io.undertow.server.HttpServerExchange, io.undertow.client.ClientConnection);
    Code:
       0: aload_0
       1: invokespecial #2                  // Method java/lang/Object."<init>":()V
       4: aload_0
       5: aload_1
       6: putfield      #3                  // Field exchange:Lio/undertow/server/HttpServerExchange;
       9: aload_0
      10: aload_2
      11: putfield      #4                  // Field clientConnection:Lio/undertow/client/ClientConnection;
      14: return

  public void handleException(java.nio.channels.Channel, java.io.IOException);
    Code:
       0: aload_1
       1: invokestatic  #5                  // Method org/xnio/IoUtils.safeClose:(Ljava/io/Closeable;)V
       4: aload_0
       5: getfield      #4                  // Field clientConnection:Lio/undertow/client/ClientConnection;
       8: invokestatic  #5                  // Method org/xnio/IoUtils.safeClose:(Ljava/io/Closeable;)V
      11: aload_0
      12: getfield      #3                  // Field exchange:Lio/undertow/server/HttpServerExchange;
      15: invokevirtual #6                  // Method io/undertow/server/HttpServerExchange.isResponseStarted:()Z
      18: ifeq          77
      21: getstatic     #7                  // Field io/undertow/UndertowLogger.REQUEST_IO_LOGGER:Lio/undertow/UndertowLogger;
      24: ldc           #8                  // String Exception reading from target server
      26: aload_2
      27: invokeinterface #9,  3            // InterfaceMethod io/undertow/UndertowLogger.debug:(Ljava/lang/Object;Ljava/lang/Throwable;)V
      32: aload_0
      33: getfield      #3                  // Field exchange:Lio/undertow/server/HttpServerExchange;
      36: invokevirtual #6                  // Method io/undertow/server/HttpServerExchange.isResponseStarted:()Z
      39: ifne          64
      42: aload_0
      43: getfield      #3                  // Field exchange:Lio/undertow/server/HttpServerExchange;
      46: sipush        500
      49: invokevirtual #11                 // Method io/undertow/server/HttpServerExchange.setStatusCode:(I)Lio/undertow/server/HttpServerExchange;
      52: pop
      53: aload_0
      54: getfield      #3                  // Field exchange:Lio/undertow/server/HttpServerExchange;
      57: invokevirtual #12                 // Method io/undertow/server/HttpServerExchange.endExchange:()Lio/undertow/server/HttpServerExchange;
      60: pop
      61: goto          105
      64: aload_0
      65: getfield      #3                  // Field exchange:Lio/undertow/server/HttpServerExchange;
      68: invokevirtual #13                 // Method io/undertow/server/HttpServerExchange.getConnection:()Lio/undertow/server/ServerConnection;
      71: invokestatic  #5                  // Method org/xnio/IoUtils.safeClose:(Ljava/io/Closeable;)V
      74: goto          105
      77: getstatic     #7                  // Field io/undertow/UndertowLogger.REQUEST_IO_LOGGER:Lio/undertow/UndertowLogger;
      80: aload_2
      81: invokeinterface #14,  2           // InterfaceMethod io/undertow/UndertowLogger.ioException:(Ljava/io/IOException;)V
      86: aload_0
      87: getfield      #3                  // Field exchange:Lio/undertow/server/HttpServerExchange;
      90: sipush        500
      93: invokevirtual #11                 // Method io/undertow/server/HttpServerExchange.setStatusCode:(I)Lio/undertow/server/HttpServerExchange;
      96: pop
      97: aload_0
      98: getfield      #3                  // Field exchange:Lio/undertow/server/HttpServerExchange;
     101: invokevirtual #12                 // Method io/undertow/server/HttpServerExchange.endExchange:()Lio/undertow/server/HttpServerExchange;
     104: pop
     105: return

  io.undertow.server.handlers.proxy.ProxyHandler$IoExceptionHandler(io.undertow.server.HttpServerExchange, io.undertow.client.ClientConnection, io.undertow.server.handlers.proxy.ProxyHandler$1);
    Code:
       0: aload_0
       1: aload_1
       2: aload_2
       3: invokespecial #1                  // Method "<init>":(Lio/undertow/server/HttpServerExchange;Lio/undertow/client/ClientConnection;)V
       6: return
}
