Compiled from "SpringPersistenceUnitInfo.java"
class org.springframework.orm.jpa.persistenceunit.SpringPersistenceUnitInfo extends org.springframework.orm.jpa.persistenceunit.MutablePersistenceUnitInfo {
  private org.springframework.instrument.classloading.LoadTimeWeaver loadTimeWeaver;

  private java.lang.ClassLoader classLoader;

  org.springframework.orm.jpa.persistenceunit.SpringPersistenceUnitInfo();
    Code:
       0: aload_0
       1: invokespecial #1                  // Method org/springframework/orm/jpa/persistenceunit/MutablePersistenceUnitInfo."<init>":()V
       4: return

  public void init(org.springframework.instrument.classloading.LoadTimeWeaver);
    Code:
       0: aload_1
       1: ldc           #2                  // String LoadTimeWeaver must not be null
       3: invokestatic  #3                  // Method org/springframework/util/Assert.notNull:(Ljava/lang/Object;Ljava/lang/String;)V
       6: aload_0
       7: aload_1
       8: putfield      #4                  // Field loadTimeWeaver:Lorg/springframework/instrument/classloading/LoadTimeWeaver;
      11: aload_0
      12: aload_1
      13: invokeinterface #5,  1            // InterfaceMethod org/springframework/instrument/classloading/LoadTimeWeaver.getInstrumentableClassLoader:()Ljava/lang/ClassLoader;
      18: putfield      #6                  // Field classLoader:Ljava/lang/ClassLoader;
      21: return

  public void init(java.lang.ClassLoader);
    Code:
       0: aload_1
       1: ldc           #7                  // String ClassLoader must not be null
       3: invokestatic  #3                  // Method org/springframework/util/Assert.notNull:(Ljava/lang/Object;Ljava/lang/String;)V
       6: aload_0
       7: aload_1
       8: putfield      #6                  // Field classLoader:Ljava/lang/ClassLoader;
      11: return

  public java.lang.ClassLoader getClassLoader();
    Code:
       0: aload_0
       1: getfield      #6                  // Field classLoader:Ljava/lang/ClassLoader;
       4: areturn

  public void addTransformer(javax.persistence.spi.ClassTransformer);
    Code:
       0: aload_0
       1: getfield      #4                  // Field loadTimeWeaver:Lorg/springframework/instrument/classloading/LoadTimeWeaver;
       4: ifnonnull     17
       7: new           #8                  // class java/lang/IllegalStateException
      10: dup
      11: ldc           #9                  // String Cannot apply class transformer without LoadTimeWeaver specified
      13: invokespecial #10                 // Method java/lang/IllegalStateException."<init>":(Ljava/lang/String;)V
      16: athrow
      17: aload_0
      18: getfield      #4                  // Field loadTimeWeaver:Lorg/springframework/instrument/classloading/LoadTimeWeaver;
      21: new           #11                 // class org/springframework/orm/jpa/persistenceunit/ClassFileTransformerAdapter
      24: dup
      25: aload_1
      26: invokespecial #12                 // Method org/springframework/orm/jpa/persistenceunit/ClassFileTransformerAdapter."<init>":(Ljavax/persistence/spi/ClassTransformer;)V
      29: invokeinterface #13,  2           // InterfaceMethod org/springframework/instrument/classloading/LoadTimeWeaver.addTransformer:(Ljava/lang/instrument/ClassFileTransformer;)V
      34: return

  public java.lang.ClassLoader getNewTempClassLoader();
    Code:
       0: aload_0
       1: getfield      #4                  // Field loadTimeWeaver:Lorg/springframework/instrument/classloading/LoadTimeWeaver;
       4: ifnull        19
       7: aload_0
       8: getfield      #4                  // Field loadTimeWeaver:Lorg/springframework/instrument/classloading/LoadTimeWeaver;
      11: invokeinterface #14,  1           // InterfaceMethod org/springframework/instrument/classloading/LoadTimeWeaver.getThrowawayClassLoader:()Ljava/lang/ClassLoader;
      16: goto          30
      19: new           #15                 // class org/springframework/instrument/classloading/SimpleThrowawayClassLoader
      22: dup
      23: aload_0
      24: getfield      #6                  // Field classLoader:Ljava/lang/ClassLoader;
      27: invokespecial #16                 // Method org/springframework/instrument/classloading/SimpleThrowawayClassLoader."<init>":(Ljava/lang/ClassLoader;)V
      30: astore_1
      31: aload_0
      32: invokevirtual #17                 // Method getPersistenceProviderPackageName:()Ljava/lang/String;
      35: astore_2
      36: aload_2
      37: ifnull        55
      40: aload_1
      41: instanceof    #18                 // class org/springframework/core/DecoratingClassLoader
      44: ifeq          55
      47: aload_1
      48: checkcast     #18                 // class org/springframework/core/DecoratingClassLoader
      51: aload_2
      52: invokevirtual #19                 // Method org/springframework/core/DecoratingClassLoader.excludePackage:(Ljava/lang/String;)V
      55: aload_1
      56: areturn
}
