Compiled from "AsyncSQLStorage.scala"
public final class net.fwbrasil.activate.storage.relational.async.AsyncSQLStorage$$anonfun$8$$anonfun$apply$17$$anonfun$apply$18$$anonfun$apply$19 extends scala.runtime.AbstractFunction1<scala.runtime.BoxedUnit, scala.concurrent.Future<scala.runtime.BoxedUnit>> implements scala.Serializable {
  public static final long serialVersionUID;

  private final net.fwbrasil.activate.storage.relational.async.AsyncSQLStorage$$anonfun$8$$anonfun$apply$17$$anonfun$apply$18 $outer;

  private final net.fwbrasil.activate.storage.relational.NormalQlStatement statement$2;

  public final scala.concurrent.Future<scala.runtime.BoxedUnit> apply(scala.runtime.BoxedUnit);
    Code:
       0: aload_0
       1: getfield      #24                 // Field $outer:Lnet/fwbrasil/activate/storage/relational/async/AsyncSQLStorage$$anonfun$8$$anonfun$apply$17$$anonfun$apply$18;
       4: invokevirtual #28                 // Method net/fwbrasil/activate/storage/relational/async/AsyncSQLStorage$$anonfun$8$$anonfun$apply$17$$anonfun$apply$18.net$fwbrasil$activate$storage$relational$async$AsyncSQLStorage$$anonfun$$anonfun$$anonfun$$$outer:()Lnet/fwbrasil/activate/storage/relational/async/AsyncSQLStorage$$anonfun$8$$anonfun$apply$17;
       7: invokevirtual #34                 // Method net/fwbrasil/activate/storage/relational/async/AsyncSQLStorage$$anonfun$8$$anonfun$apply$17.net$fwbrasil$activate$storage$relational$async$AsyncSQLStorage$$anonfun$$anonfun$$$outer:()Lnet/fwbrasil/activate/storage/relational/async/AsyncSQLStorage$$anonfun$8;
      10: invokevirtual #40                 // Method net/fwbrasil/activate/storage/relational/async/AsyncSQLStorage$$anonfun$8.net$fwbrasil$activate$storage$relational$async$AsyncSQLStorage$$anonfun$$$outer:()Lnet/fwbrasil/activate/storage/relational/async/AsyncSQLStorage;
      13: aload_0
      14: getfield      #42                 // Field statement$2:Lnet/fwbrasil/activate/storage/relational/NormalQlStatement;
      17: aload_0
      18: getfield      #24                 // Field $outer:Lnet/fwbrasil/activate/storage/relational/async/AsyncSQLStorage$$anonfun$8$$anonfun$apply$17$$anonfun$apply$18;
      21: invokevirtual #28                 // Method net/fwbrasil/activate/storage/relational/async/AsyncSQLStorage$$anonfun$8$$anonfun$apply$17$$anonfun$apply$18.net$fwbrasil$activate$storage$relational$async$AsyncSQLStorage$$anonfun$$anonfun$$anonfun$$$outer:()Lnet/fwbrasil/activate/storage/relational/async/AsyncSQLStorage$$anonfun$8$$anonfun$apply$17;
      24: getfield      #46                 // Field net/fwbrasil/activate/storage/relational/async/AsyncSQLStorage$$anonfun$8$$anonfun$apply$17.connection$3:Lcom/github/mauricio/async/db/Connection;
      27: aload_0
      28: getfield      #24                 // Field $outer:Lnet/fwbrasil/activate/storage/relational/async/AsyncSQLStorage$$anonfun$8$$anonfun$apply$17$$anonfun$apply$18;
      31: invokevirtual #28                 // Method net/fwbrasil/activate/storage/relational/async/AsyncSQLStorage$$anonfun$8$$anonfun$apply$17$$anonfun$apply$18.net$fwbrasil$activate$storage$relational$async$AsyncSQLStorage$$anonfun$$anonfun$$anonfun$$$outer:()Lnet/fwbrasil/activate/storage/relational/async/AsyncSQLStorage$$anonfun$8$$anonfun$apply$17;
      34: invokevirtual #34                 // Method net/fwbrasil/activate/storage/relational/async/AsyncSQLStorage$$anonfun$8$$anonfun$apply$17.net$fwbrasil$activate$storage$relational$async$AsyncSQLStorage$$anonfun$$anonfun$$$outer:()Lnet/fwbrasil/activate/storage/relational/async/AsyncSQLStorage$$anonfun$8;
      37: getfield      #50                 // Field net/fwbrasil/activate/storage/relational/async/AsyncSQLStorage$$anonfun$8.isDdl$2:Z
      40: invokeinterface #56,  4           // InterfaceMethod net/fwbrasil/activate/storage/relational/async/AsyncSQLStorage.execute:(Lnet/fwbrasil/activate/storage/relational/QlStatement;Lcom/github/mauricio/async/db/Connection;Z)Lscala/concurrent/Future;
      45: areturn

  public final java.lang.Object apply(java.lang.Object);
    Code:
       0: aload_0
       1: aload_1
       2: checkcast     #63                 // class scala/runtime/BoxedUnit
       5: invokevirtual #65                 // Method apply:(Lscala/runtime/BoxedUnit;)Lscala/concurrent/Future;
       8: areturn

  public net.fwbrasil.activate.storage.relational.async.AsyncSQLStorage$$anonfun$8$$anonfun$apply$17$$anonfun$apply$18$$anonfun$apply$19(net.fwbrasil.activate.storage.relational.async.AsyncSQLStorage<C>.$anonfun$8$$anonfun$apply$17$$anonfun$apply$18);
    Code:
       0: aload_1
       1: ifnonnull     12
       4: new           #71                 // class java/lang/NullPointerException
       7: dup
       8: invokespecial #74                 // Method java/lang/NullPointerException."<init>":()V
      11: athrow
      12: aload_0
      13: aload_1
      14: putfield      #24                 // Field $outer:Lnet/fwbrasil/activate/storage/relational/async/AsyncSQLStorage$$anonfun$8$$anonfun$apply$17$$anonfun$apply$18;
      17: aload_0
      18: aload_2
      19: putfield      #42                 // Field statement$2:Lnet/fwbrasil/activate/storage/relational/NormalQlStatement;
      22: aload_0
      23: invokespecial #75                 // Method scala/runtime/AbstractFunction1."<init>":()V
      26: return
}
