Compiled from "BufferPoolResourceDefinition.java"
class org.wildfly.extension.io.BufferPoolResourceDefinition extends org.jboss.as.controller.PersistentResourceDefinition {
  static final org.jboss.as.controller.capability.RuntimeCapability<java.lang.Void> IO_POOL_RUNTIME_CAPABILITY;

  private static final int defaultBufferSize;

  private static final int defaultBuffersPerRegion;

  private static final boolean defaultDirectBuffers;

  static final org.jboss.as.controller.SimpleAttributeDefinition BUFFER_SIZE;

  static final org.jboss.as.controller.SimpleAttributeDefinition BUFFER_PER_SLICE;

  static final org.jboss.as.controller.SimpleAttributeDefinition DIRECT_BUFFERS;

  static java.util.List<org.jboss.as.controller.SimpleAttributeDefinition> ATTRIBUTES;

  public static final org.wildfly.extension.io.BufferPoolResourceDefinition INSTANCE;

  private org.wildfly.extension.io.BufferPoolResourceDefinition();
    Code:
       0: aload_0
       1: getstatic     #4                  // Field org/wildfly/extension/io/IOExtension.BUFFER_POOL_PATH:Lorg/jboss/as/controller/PathElement;
       4: iconst_1
       5: anewarray     #5                  // class java/lang/String
       8: dup
       9: iconst_0
      10: ldc           #7                  // String buffer-pool
      12: aastore
      13: invokestatic  #8                  // Method org/wildfly/extension/io/IOExtension.getResolver:([Ljava/lang/String;)Lorg/jboss/as/controller/descriptions/StandardResourceDescriptionResolver;
      16: new           #9                  // class org/wildfly/extension/io/BufferPoolResourceDefinition$BufferPoolAdd
      19: dup
      20: aconst_null
      21: invokespecial #10                 // Method org/wildfly/extension/io/BufferPoolResourceDefinition$BufferPoolAdd."<init>":(Lorg/wildfly/extension/io/BufferPoolResourceDefinition$1;)V
      24: new           #11                 // class org/jboss/as/controller/ReloadRequiredRemoveStepHandler
      27: dup
      28: invokespecial #12                 // Method org/jboss/as/controller/ReloadRequiredRemoveStepHandler."<init>":()V
      31: invokespecial #13                 // Method org/jboss/as/controller/PersistentResourceDefinition."<init>":(Lorg/jboss/as/controller/PathElement;Lorg/jboss/as/controller/descriptions/ResourceDescriptionResolver;Lorg/jboss/as/controller/OperationStepHandler;Lorg/jboss/as/controller/OperationStepHandler;)V
      34: return

  public java.util.Collection<org.jboss.as.controller.AttributeDefinition> getAttributes();
    Code:
       0: getstatic     #14                 // Field ATTRIBUTES:Ljava/util/List;
       3: areturn

  public void registerCapabilities(org.jboss.as.controller.registry.ManagementResourceRegistration);
    Code:
       0: aload_1
       1: getstatic     #15                 // Field IO_POOL_RUNTIME_CAPABILITY:Lorg/jboss/as/controller/capability/RuntimeCapability;
       4: invokeinterface #16,  2           // InterfaceMethod org/jboss/as/controller/registry/ManagementResourceRegistration.registerCapability:(Lorg/jboss/as/controller/capability/RuntimeCapability;)V
       9: return

  static int access$100();
    Code:
       0: getstatic     #3                  // Field defaultBufferSize:I
       3: ireturn

  static int access$200();
    Code:
       0: getstatic     #2                  // Field defaultBuffersPerRegion:I
       3: ireturn

  static boolean access$300();
    Code:
       0: getstatic     #1                  // Field defaultDirectBuffers:Z
       3: ireturn

  static {};
    Code:
       0: ldc           #17                 // String org.wildfly.io.buffer-pool
       2: iconst_1
       3: ldc           #18                 // class org/xnio/Pool
       5: invokestatic  #19                 // Method org/jboss/as/controller/capability/RuntimeCapability$Builder.of:(Ljava/lang/String;ZLjava/lang/Class;)Lorg/jboss/as/controller/capability/RuntimeCapability$Builder;
       8: invokevirtual #20                 // Method org/jboss/as/controller/capability/RuntimeCapability$Builder.build:()Lorg/jboss/as/controller/capability/RuntimeCapability;
      11: putstatic     #15                 // Field IO_POOL_RUNTIME_CAPABILITY:Lorg/jboss/as/controller/capability/RuntimeCapability;
      14: invokestatic  #21                 // Method java/lang/Runtime.getRuntime:()Ljava/lang/Runtime;
      17: invokevirtual #22                 // Method java/lang/Runtime.maxMemory:()J
      20: lstore_0
      21: lload_0
      22: ldc2_w        #23                 // long 67108864l
      25: lcmp
      26: ifge          47
      29: iconst_0
      30: putstatic     #1                  // Field defaultDirectBuffers:Z
      33: sipush        512
      36: putstatic     #3                  // Field defaultBufferSize:I
      39: bipush        10
      41: putstatic     #2                  // Field defaultBuffersPerRegion:I
      44: goto          88
      47: lload_0
      48: ldc2_w        #25                 // long 134217728l
      51: lcmp
      52: ifge          73
      55: iconst_1
      56: putstatic     #1                  // Field defaultDirectBuffers:Z
      59: sipush        1024
      62: putstatic     #3                  // Field defaultBufferSize:I
      65: bipush        10
      67: putstatic     #2                  // Field defaultBuffersPerRegion:I
      70: goto          88
      73: iconst_1
      74: putstatic     #1                  // Field defaultDirectBuffers:Z
      77: sipush        16384
      80: putstatic     #3                  // Field defaultBufferSize:I
      83: bipush        20
      85: putstatic     #2                  // Field defaultBuffersPerRegion:I
      88: new           #27                 // class org/jboss/as/controller/SimpleAttributeDefinitionBuilder
      91: dup
      92: ldc           #28                 // String buffer-size
      94: getstatic     #29                 // Field org/jboss/dmr/ModelType.INT:Lorg/jboss/dmr/ModelType;
      97: iconst_1
      98: invokespecial #30                 // Method org/jboss/as/controller/SimpleAttributeDefinitionBuilder."<init>":(Ljava/lang/String;Lorg/jboss/dmr/ModelType;Z)V
     101: iconst_1
     102: invokevirtual #31                 // Method org/jboss/as/controller/SimpleAttributeDefinitionBuilder.setAllowExpression:(Z)Lorg/jboss/as/controller/AbstractAttributeDefinitionBuilder;
     105: checkcast     #27                 // class org/jboss/as/controller/SimpleAttributeDefinitionBuilder
     108: invokevirtual #32                 // Method org/jboss/as/controller/SimpleAttributeDefinitionBuilder.build:()Lorg/jboss/as/controller/SimpleAttributeDefinition;
     111: putstatic     #33                 // Field BUFFER_SIZE:Lorg/jboss/as/controller/SimpleAttributeDefinition;
     114: new           #27                 // class org/jboss/as/controller/SimpleAttributeDefinitionBuilder
     117: dup
     118: ldc           #34                 // String buffers-per-slice
     120: getstatic     #29                 // Field org/jboss/dmr/ModelType.INT:Lorg/jboss/dmr/ModelType;
     123: iconst_1
     124: invokespecial #30                 // Method org/jboss/as/controller/SimpleAttributeDefinitionBuilder."<init>":(Ljava/lang/String;Lorg/jboss/dmr/ModelType;Z)V
     127: iconst_1
     128: invokevirtual #31                 // Method org/jboss/as/controller/SimpleAttributeDefinitionBuilder.setAllowExpression:(Z)Lorg/jboss/as/controller/AbstractAttributeDefinitionBuilder;
     131: checkcast     #27                 // class org/jboss/as/controller/SimpleAttributeDefinitionBuilder
     134: invokevirtual #32                 // Method org/jboss/as/controller/SimpleAttributeDefinitionBuilder.build:()Lorg/jboss/as/controller/SimpleAttributeDefinition;
     137: putstatic     #35                 // Field BUFFER_PER_SLICE:Lorg/jboss/as/controller/SimpleAttributeDefinition;
     140: new           #27                 // class org/jboss/as/controller/SimpleAttributeDefinitionBuilder
     143: dup
     144: ldc           #36                 // String direct-buffers
     146: getstatic     #37                 // Field org/jboss/dmr/ModelType.BOOLEAN:Lorg/jboss/dmr/ModelType;
     149: iconst_1
     150: invokespecial #30                 // Method org/jboss/as/controller/SimpleAttributeDefinitionBuilder."<init>":(Ljava/lang/String;Lorg/jboss/dmr/ModelType;Z)V
     153: iconst_1
     154: invokevirtual #31                 // Method org/jboss/as/controller/SimpleAttributeDefinitionBuilder.setAllowExpression:(Z)Lorg/jboss/as/controller/AbstractAttributeDefinitionBuilder;
     157: checkcast     #27                 // class org/jboss/as/controller/SimpleAttributeDefinitionBuilder
     160: invokevirtual #32                 // Method org/jboss/as/controller/SimpleAttributeDefinitionBuilder.build:()Lorg/jboss/as/controller/SimpleAttributeDefinition;
     163: putstatic     #38                 // Field DIRECT_BUFFERS:Lorg/jboss/as/controller/SimpleAttributeDefinition;
     166: iconst_3
     167: anewarray     #39                 // class org/jboss/as/controller/SimpleAttributeDefinition
     170: dup
     171: iconst_0
     172: getstatic     #33                 // Field BUFFER_SIZE:Lorg/jboss/as/controller/SimpleAttributeDefinition;
     175: aastore
     176: dup
     177: iconst_1
     178: getstatic     #35                 // Field BUFFER_PER_SLICE:Lorg/jboss/as/controller/SimpleAttributeDefinition;
     181: aastore
     182: dup
     183: iconst_2
     184: getstatic     #38                 // Field DIRECT_BUFFERS:Lorg/jboss/as/controller/SimpleAttributeDefinition;
     187: aastore
     188: invokestatic  #40                 // Method java/util/Arrays.asList:([Ljava/lang/Object;)Ljava/util/List;
     191: putstatic     #14                 // Field ATTRIBUTES:Ljava/util/List;
     194: new           #41                 // class org/wildfly/extension/io/BufferPoolResourceDefinition
     197: dup
     198: invokespecial #42                 // Method "<init>":()V
     201: putstatic     #43                 // Field INSTANCE:Lorg/wildfly/extension/io/BufferPoolResourceDefinition;
     204: return
}
