Compiled from "OptionsResourceDefinition.java"
public class org.wildfly.extension.io.OptionsResourceDefinition$Builder {
  private final org.jboss.as.controller.PathElement pathElement;

  private final org.jboss.as.controller.descriptions.ResourceDescriptionResolver resolver;

  private java.util.List<org.wildfly.extension.io.OptionAttributeDefinition> attributes;

  private org.wildfly.extension.io.OptionsResourceDefinition$Builder(org.jboss.as.controller.PathElement, org.jboss.as.controller.descriptions.ResourceDescriptionResolver);
    Code:
       0: aload_0
       1: invokespecial #2                  // Method java/lang/Object."<init>":()V
       4: aload_0
       5: new           #3                  // class java/util/LinkedList
       8: dup
       9: invokespecial #4                  // Method java/util/LinkedList."<init>":()V
      12: putfield      #5                  // Field attributes:Ljava/util/List;
      15: aload_0
      16: aload_1
      17: putfield      #6                  // Field pathElement:Lorg/jboss/as/controller/PathElement;
      20: aload_0
      21: aload_2
      22: putfield      #7                  // Field resolver:Lorg/jboss/as/controller/descriptions/ResourceDescriptionResolver;
      25: return

  public org.wildfly.extension.io.OptionsResourceDefinition$Builder addOption(org.xnio.Option<?>, java.lang.String);
    Code:
       0: aload_0
       1: getfield      #5                  // Field attributes:Ljava/util/List;
       4: aload_2
       5: aload_1
       6: invokestatic  #8                  // Method org/wildfly/extension/io/OptionAttributeDefinition.builder:(Ljava/lang/String;Lorg/xnio/Option;)Lorg/wildfly/extension/io/OptionAttributeDefinition$Builder;
       9: invokevirtual #9                  // Method org/wildfly/extension/io/OptionAttributeDefinition$Builder.build:()Lorg/wildfly/extension/io/OptionAttributeDefinition;
      12: invokeinterface #10,  2           // InterfaceMethod java/util/List.add:(Ljava/lang/Object;)Z
      17: pop
      18: aload_0
      19: areturn

  public org.wildfly.extension.io.OptionsResourceDefinition$Builder addOption(org.xnio.Option<?>, java.lang.String, org.jboss.dmr.ModelNode);
    Code:
       0: aload_0
       1: getfield      #5                  // Field attributes:Ljava/util/List;
       4: aload_2
       5: aload_1
       6: invokestatic  #8                  // Method org/wildfly/extension/io/OptionAttributeDefinition.builder:(Ljava/lang/String;Lorg/xnio/Option;)Lorg/wildfly/extension/io/OptionAttributeDefinition$Builder;
       9: aload_3
      10: invokevirtual #11                 // Method org/wildfly/extension/io/OptionAttributeDefinition$Builder.setDefaultValue:(Lorg/jboss/dmr/ModelNode;)Lorg/jboss/as/controller/AbstractAttributeDefinitionBuilder;
      13: checkcast     #12                 // class org/wildfly/extension/io/OptionAttributeDefinition$Builder
      16: invokevirtual #9                  // Method org/wildfly/extension/io/OptionAttributeDefinition$Builder.build:()Lorg/wildfly/extension/io/OptionAttributeDefinition;
      19: invokeinterface #10,  2           // InterfaceMethod java/util/List.add:(Ljava/lang/Object;)Z
      24: pop
      25: aload_0
      26: areturn

  public org.wildfly.extension.io.OptionsResourceDefinition build();
    Code:
       0: new           #13                 // class org/wildfly/extension/io/OptionsResourceDefinition
       3: dup
       4: aload_0
       5: getfield      #6                  // Field pathElement:Lorg/jboss/as/controller/PathElement;
       8: aload_0
       9: getfield      #7                  // Field resolver:Lorg/jboss/as/controller/descriptions/ResourceDescriptionResolver;
      12: aload_0
      13: getfield      #5                  // Field attributes:Ljava/util/List;
      16: aconst_null
      17: invokespecial #14                 // Method org/wildfly/extension/io/OptionsResourceDefinition."<init>":(Lorg/jboss/as/controller/PathElement;Lorg/jboss/as/controller/descriptions/ResourceDescriptionResolver;Ljava/util/List;Lorg/wildfly/extension/io/OptionsResourceDefinition$1;)V
      20: areturn

  org.wildfly.extension.io.OptionsResourceDefinition$Builder(org.jboss.as.controller.PathElement, org.jboss.as.controller.descriptions.ResourceDescriptionResolver, org.wildfly.extension.io.OptionsResourceDefinition$1);
    Code:
       0: aload_0
       1: aload_1
       2: aload_2
       3: invokespecial #1                  // Method "<init>":(Lorg/jboss/as/controller/PathElement;Lorg/jboss/as/controller/descriptions/ResourceDescriptionResolver;)V
       6: return
}
