Compiled from "CodeWithConverter.kt"
public final class org.jetbrains.kotlinx.dataframe.codeGen.CodeWithConverter {
  private final java.lang.String declarations;

  private final kotlin.jvm.functions.Function1<java.lang.String, java.lang.String> converter;

  public org.jetbrains.kotlinx.dataframe.codeGen.CodeWithConverter(java.lang.String, kotlin.jvm.functions.Function1<? super java.lang.String, java.lang.String>);
    Code:
       0: aload_1
       1: ldc           #10                 // String declarations
       3: invokestatic  #16                 // Method kotlin/jvm/internal/Intrinsics.checkNotNullParameter:(Ljava/lang/Object;Ljava/lang/String;)V
       6: aload_2
       7: ldc           #18                 // String converter
       9: invokestatic  #16                 // Method kotlin/jvm/internal/Intrinsics.checkNotNullParameter:(Ljava/lang/Object;Ljava/lang/String;)V
      12: aload_0
      13: invokespecial #21                 // Method java/lang/Object."<init>":()V
      16: aload_0
      17: aload_1
      18: putfield      #24                 // Field declarations:Ljava/lang/String;
      21: aload_0
      22: aload_2
      23: putfield      #27                 // Field converter:Lkotlin/jvm/functions/Function1;
      26: return

  public final java.lang.String getDeclarations();
    Code:
       0: aload_0
       1: getfield      #24                 // Field declarations:Ljava/lang/String;
       4: areturn

  public final kotlin.jvm.functions.Function1<java.lang.String, java.lang.String> getConverter();
    Code:
       0: aload_0
       1: getfield      #27                 // Field converter:Lkotlin/jvm/functions/Function1;
       4: areturn

  public final boolean getHasDeclarations();
    Code:
       0: aload_0
       1: getfield      #24                 // Field declarations:Ljava/lang/String;
       4: checkcast     #38                 // class java/lang/CharSequence
       7: invokestatic  #44                 // Method kotlin/text/StringsKt.isBlank:(Ljava/lang/CharSequence;)Z
      10: ifne          17
      13: iconst_1
      14: goto          18
      17: iconst_0
      18: ireturn

  public final boolean getHasConverter();
    Code:
       0: aload_0
       1: getfield      #27                 // Field converter:Lkotlin/jvm/functions/Function1;
       4: ldc           #47                 // String it
       6: invokeinterface #53,  2           // InterfaceMethod kotlin/jvm/functions/Function1.invoke:(Ljava/lang/Object;)Ljava/lang/Object;
      11: checkcast     #55                 // class java/lang/String
      14: checkcast     #38                 // class java/lang/CharSequence
      17: invokestatic  #59                 // Method kotlin/text/StringsKt.trim:(Ljava/lang/CharSequence;)Ljava/lang/CharSequence;
      20: invokevirtual #62                 // Method java/lang/Object.toString:()Ljava/lang/String;
      23: ldc           #47                 // String it
      25: invokestatic  #66                 // Method kotlin/jvm/internal/Intrinsics.areEqual:(Ljava/lang/Object;Ljava/lang/Object;)Z
      28: ifne          35
      31: iconst_1
      32: goto          36
      35: iconst_0
      36: ireturn

  public final java.lang.String with(java.lang.String);
    Code:
       0: aload_1
       1: ldc           #70                 // String name
       3: invokestatic  #16                 // Method kotlin/jvm/internal/Intrinsics.checkNotNullParameter:(Ljava/lang/Object;Ljava/lang/String;)V
       6: aload_0
       7: invokevirtual #72                 // Method getHasConverter:()Z
      10: ifne          18
      13: aload_0
      14: getfield      #24                 // Field declarations:Ljava/lang/String;
      17: areturn
      18: aload_0
      19: invokevirtual #74                 // Method getHasDeclarations:()Z
      22: ifne          39
      25: aload_0
      26: getfield      #27                 // Field converter:Lkotlin/jvm/functions/Function1;
      29: aload_1
      30: invokeinterface #53,  2           // InterfaceMethod kotlin/jvm/functions/Function1.invoke:(Ljava/lang/Object;)Ljava/lang/Object;
      35: checkcast     #55                 // class java/lang/String
      38: areturn
      39: new           #76                 // class java/lang/StringBuilder
      42: dup
      43: invokespecial #77                 // Method java/lang/StringBuilder."<init>":()V
      46: aload_0
      47: getfield      #24                 // Field declarations:Ljava/lang/String;
      50: invokevirtual #81                 // Method java/lang/StringBuilder.append:(Ljava/lang/String;)Ljava/lang/StringBuilder;
      53: bipush        10
      55: invokevirtual #84                 // Method java/lang/StringBuilder.append:(C)Ljava/lang/StringBuilder;
      58: aload_0
      59: getfield      #27                 // Field converter:Lkotlin/jvm/functions/Function1;
      62: aload_1
      63: invokeinterface #53,  2           // InterfaceMethod kotlin/jvm/functions/Function1.invoke:(Ljava/lang/Object;)Ljava/lang/Object;
      68: checkcast     #55                 // class java/lang/String
      71: invokevirtual #81                 // Method java/lang/StringBuilder.append:(Ljava/lang/String;)Ljava/lang/StringBuilder;
      74: invokevirtual #85                 // Method java/lang/StringBuilder.toString:()Ljava/lang/String;
      77: areturn

  public final java.lang.String component1();
    Code:
       0: aload_0
       1: getfield      #24                 // Field declarations:Ljava/lang/String;
       4: areturn

  public final kotlin.jvm.functions.Function1<java.lang.String, java.lang.String> component2();
    Code:
       0: aload_0
       1: getfield      #27                 // Field converter:Lkotlin/jvm/functions/Function1;
       4: areturn

  public final org.jetbrains.kotlinx.dataframe.codeGen.CodeWithConverter copy(java.lang.String, kotlin.jvm.functions.Function1<? super java.lang.String, java.lang.String>);
    Code:
       0: aload_1
       1: ldc           #10                 // String declarations
       3: invokestatic  #16                 // Method kotlin/jvm/internal/Intrinsics.checkNotNullParameter:(Ljava/lang/Object;Ljava/lang/String;)V
       6: aload_2
       7: ldc           #18                 // String converter
       9: invokestatic  #16                 // Method kotlin/jvm/internal/Intrinsics.checkNotNullParameter:(Ljava/lang/Object;Ljava/lang/String;)V
      12: new           #2                  // class org/jetbrains/kotlinx/dataframe/codeGen/CodeWithConverter
      15: dup
      16: aload_1
      17: aload_2
      18: invokespecial #92                 // Method "<init>":(Ljava/lang/String;Lkotlin/jvm/functions/Function1;)V
      21: areturn

  public static org.jetbrains.kotlinx.dataframe.codeGen.CodeWithConverter copy$default(org.jetbrains.kotlinx.dataframe.codeGen.CodeWithConverter, java.lang.String, kotlin.jvm.functions.Function1, int, java.lang.Object);
    Code:
       0: iload_3
       1: iconst_1
       2: iand
       3: ifeq          11
       6: aload_0
       7: getfield      #24                 // Field declarations:Ljava/lang/String;
      10: astore_1
      11: iload_3
      12: iconst_2
      13: iand
      14: ifeq          22
      17: aload_0
      18: getfield      #27                 // Field converter:Lkotlin/jvm/functions/Function1;
      21: astore_2
      22: aload_0
      23: aload_1
      24: aload_2
      25: invokevirtual #96                 // Method copy:(Ljava/lang/String;Lkotlin/jvm/functions/Function1;)Lorg/jetbrains/kotlinx/dataframe/codeGen/CodeWithConverter;
      28: areturn

  public java.lang.String toString();
    Code:
       0: new           #76                 // class java/lang/StringBuilder
       3: dup
       4: invokespecial #77                 // Method java/lang/StringBuilder."<init>":()V
       7: ldc           #98                 // String CodeWithConverter(declarations=
       9: invokevirtual #81                 // Method java/lang/StringBuilder.append:(Ljava/lang/String;)Ljava/lang/StringBuilder;
      12: aload_0
      13: getfield      #24                 // Field declarations:Ljava/lang/String;
      16: invokevirtual #81                 // Method java/lang/StringBuilder.append:(Ljava/lang/String;)Ljava/lang/StringBuilder;
      19: ldc           #100                // String , converter=
      21: invokevirtual #81                 // Method java/lang/StringBuilder.append:(Ljava/lang/String;)Ljava/lang/StringBuilder;
      24: aload_0
      25: getfield      #27                 // Field converter:Lkotlin/jvm/functions/Function1;
      28: invokevirtual #103                // Method java/lang/StringBuilder.append:(Ljava/lang/Object;)Ljava/lang/StringBuilder;
      31: bipush        41
      33: invokevirtual #84                 // Method java/lang/StringBuilder.append:(C)Ljava/lang/StringBuilder;
      36: invokevirtual #85                 // Method java/lang/StringBuilder.toString:()Ljava/lang/String;
      39: areturn

  public int hashCode();
    Code:
       0: aload_0
       1: getfield      #24                 // Field declarations:Ljava/lang/String;
       4: invokevirtual #107                // Method java/lang/String.hashCode:()I
       7: istore_1
       8: iload_1
       9: bipush        31
      11: imul
      12: aload_0
      13: getfield      #27                 // Field converter:Lkotlin/jvm/functions/Function1;
      16: invokevirtual #108                // Method java/lang/Object.hashCode:()I
      19: iadd
      20: istore_1
      21: iload_1
      22: ireturn

  public boolean equals(java.lang.Object);
    Code:
       0: aload_0
       1: aload_1
       2: if_acmpne     7
       5: iconst_1
       6: ireturn
       7: aload_1
       8: instanceof    #2                  // class org/jetbrains/kotlinx/dataframe/codeGen/CodeWithConverter
      11: ifne          16
      14: iconst_0
      15: ireturn
      16: aload_1
      17: checkcast     #2                  // class org/jetbrains/kotlinx/dataframe/codeGen/CodeWithConverter
      20: astore_2
      21: aload_0
      22: getfield      #24                 // Field declarations:Ljava/lang/String;
      25: aload_2
      26: getfield      #24                 // Field declarations:Ljava/lang/String;
      29: invokestatic  #66                 // Method kotlin/jvm/internal/Intrinsics.areEqual:(Ljava/lang/Object;Ljava/lang/Object;)Z
      32: ifne          37
      35: iconst_0
      36: ireturn
      37: aload_0
      38: getfield      #27                 // Field converter:Lkotlin/jvm/functions/Function1;
      41: aload_2
      42: getfield      #27                 // Field converter:Lkotlin/jvm/functions/Function1;
      45: invokestatic  #66                 // Method kotlin/jvm/internal/Intrinsics.areEqual:(Ljava/lang/Object;Ljava/lang/Object;)Z
      48: ifne          53
      51: iconst_0
      52: ireturn
      53: iconst_1
      54: ireturn
}
