Compiled from "MarkersExtractor.kt"
public final class org.jetbrains.kotlinx.dataframe.codeGen.MarkersExtractor {
  public static final org.jetbrains.kotlinx.dataframe.codeGen.MarkersExtractor INSTANCE;

  private static final java.util.Map<kotlin.reflect.KClass<?>, org.jetbrains.kotlinx.dataframe.codeGen.Marker> cache;

  private org.jetbrains.kotlinx.dataframe.codeGen.MarkersExtractor();
    Code:
       0: aload_0
       1: invokespecial #8                  // Method java/lang/Object."<init>":()V
       4: return

  public final <T> org.jetbrains.kotlinx.dataframe.codeGen.Marker get();
    Code:
       0: iconst_0
       1: istore_1
       2: aload_0
       3: iconst_4
       4: ldc           #15                 // String T
       6: invokestatic  #21                 // Method kotlin/jvm/internal/Intrinsics.reifiedOperationMarker:(ILjava/lang/String;)V
       9: ldc           #4                  // class java/lang/Object
      11: invokestatic  #27                 // Method kotlin/jvm/internal/Reflection.getOrCreateKotlinClass:(Ljava/lang/Class;)Lkotlin/reflect/KClass;
      14: invokevirtual #30                 // Method get:(Lkotlin/reflect/KClass;)Lorg/jetbrains/kotlinx/dataframe/codeGen/Marker;
      17: areturn

  public final org.jetbrains.kotlinx.dataframe.codeGen.Marker get(kotlin.reflect.KClass<?>);
    Code:
       0: aload_1
       1: ldc           #36                 // String markerClass
       3: invokestatic  #40                 // Method kotlin/jvm/internal/Intrinsics.checkNotNullParameter:(Ljava/lang/Object;Ljava/lang/String;)V
       6: getstatic     #44                 // Field cache:Ljava/util/Map;
       9: astore_2
      10: iconst_0
      11: istore_3
      12: aload_2
      13: aload_1
      14: invokeinterface #49,  2           // InterfaceMethod java/util/Map.get:(Ljava/lang/Object;)Ljava/lang/Object;
      19: astore        4
      21: aload         4
      23: ifnonnull     412
      26: iconst_0
      27: istore        5
      29: getstatic     #52                 // Field INSTANCE:Lorg/jetbrains/kotlinx/dataframe/codeGen/MarkersExtractor;
      32: aload_1
      33: invokespecial #56                 // Method getFields:(Lkotlin/reflect/KClass;)Ljava/util/List;
      36: astore        6
      38: aload_1
      39: checkcast     #58                 // class kotlin/reflect/KAnnotatedElement
      42: astore        7
      44: iconst_0
      45: istore        8
      47: aload         7
      49: invokeinterface #62,  1           // InterfaceMethod kotlin/reflect/KAnnotatedElement.getAnnotations:()Ljava/util/List;
      54: checkcast     #64                 // class java/lang/Iterable
      57: astore        9
      59: iconst_0
      60: istore        10
      62: aload         9
      64: invokeinterface #68,  1           // InterfaceMethod java/lang/Iterable.iterator:()Ljava/util/Iterator;
      69: astore        11
      71: aload         11
      73: invokeinterface #74,  1           // InterfaceMethod java/util/Iterator.hasNext:()Z
      78: ifeq          113
      81: aload         11
      83: invokeinterface #78,  1           // InterfaceMethod java/util/Iterator.next:()Ljava/lang/Object;
      88: astore        12
      90: aload         12
      92: checkcast     #80                 // class java/lang/annotation/Annotation
      95: astore        13
      97: iconst_0
      98: istore        14
     100: aload         13
     102: instanceof    #82                 // class org/jetbrains/kotlinx/dataframe/annotations/DataSchema
     105: ifeq          71
     108: aload         12
     110: goto          114
     113: aconst_null
     114: checkcast     #82                 // class org/jetbrains/kotlinx/dataframe/annotations/DataSchema
     117: checkcast     #80                 // class java/lang/annotation/Annotation
     120: nop
     121: checkcast     #82                 // class org/jetbrains/kotlinx/dataframe/annotations/DataSchema
     124: dup
     125: ifnonnull     133
     128: pop
     129: iconst_0
     130: goto          142
     133: invokeinterface #85,  1           // InterfaceMethod org/jetbrains/kotlinx/dataframe/annotations/DataSchema.isOpen:()Z
     138: istore        7
     140: iload         7
     142: istore        16
     144: aload_1
     145: invokestatic  #90                 // Method kotlin/reflect/full/KClasses.getSuperclasses:(Lkotlin/reflect/KClass;)Ljava/util/List;
     148: checkcast     #64                 // class java/lang/Iterable
     151: astore        7
     153: iconst_0
     154: istore        8
     156: aload         7
     158: astore        9
     160: new           #92                 // class java/util/ArrayList
     163: dup
     164: invokespecial #93                 // Method java/util/ArrayList."<init>":()V
     167: checkcast     #95                 // class java/util/Collection
     170: astore        10
     172: iconst_0
     173: istore        11
     175: aload         9
     177: invokeinterface #68,  1           // InterfaceMethod java/lang/Iterable.iterator:()Ljava/util/Iterator;
     182: astore        12
     184: aload         12
     186: invokeinterface #74,  1           // InterfaceMethod java/util/Iterator.hasNext:()Z
     191: ifeq          247
     194: aload         12
     196: invokeinterface #78,  1           // InterfaceMethod java/util/Iterator.next:()Ljava/lang/Object;
     201: astore        13
     203: aload         13
     205: checkcast     #97                 // class kotlin/reflect/KClass
     208: astore        14
     210: iconst_0
     211: istore        17
     213: aload         14
     215: ldc           #4                  // class java/lang/Object
     217: invokestatic  #27                 // Method kotlin/jvm/internal/Reflection.getOrCreateKotlinClass:(Ljava/lang/Class;)Lkotlin/reflect/KClass;
     220: invokestatic  #101                // Method kotlin/jvm/internal/Intrinsics.areEqual:(Ljava/lang/Object;Ljava/lang/Object;)Z
     223: ifne          230
     226: iconst_1
     227: goto          231
     230: iconst_0
     231: ifeq          184
     234: aload         10
     236: aload         13
     238: invokeinterface #105,  2          // InterfaceMethod java/util/Collection.add:(Ljava/lang/Object;)Z
     243: pop
     244: goto          184
     247: aload         10
     249: checkcast     #107                // class java/util/List
     252: nop
     253: checkcast     #64                 // class java/lang/Iterable
     256: astore        7
     258: nop
     259: iconst_0
     260: istore        8
     262: aload         7
     264: astore        9
     266: new           #92                 // class java/util/ArrayList
     269: dup
     270: aload         7
     272: bipush        10
     274: invokestatic  #113                // Method kotlin/collections/CollectionsKt.collectionSizeOrDefault:(Ljava/lang/Iterable;I)I
     277: invokespecial #116                // Method java/util/ArrayList."<init>":(I)V
     280: checkcast     #95                 // class java/util/Collection
     283: astore        10
     285: iconst_0
     286: istore        11
     288: aload         9
     290: invokeinterface #68,  1           // InterfaceMethod java/lang/Iterable.iterator:()Ljava/util/Iterator;
     295: astore        12
     297: aload         12
     299: invokeinterface #74,  1           // InterfaceMethod java/util/Iterator.hasNext:()Z
     304: ifeq          350
     307: aload         12
     309: invokeinterface #78,  1           // InterfaceMethod java/util/Iterator.next:()Ljava/lang/Object;
     314: astore        13
     316: aload         10
     318: aload         13
     320: checkcast     #97                 // class kotlin/reflect/KClass
     323: astore        14
     325: astore        18
     327: iconst_0
     328: istore        17
     330: getstatic     #52                 // Field INSTANCE:Lorg/jetbrains/kotlinx/dataframe/codeGen/MarkersExtractor;
     333: aload         14
     335: invokevirtual #30                 // Method get:(Lkotlin/reflect/KClass;)Lorg/jetbrains/kotlinx/dataframe/codeGen/Marker;
     338: aload         18
     340: swap
     341: invokeinterface #105,  2          // InterfaceMethod java/util/Collection.add:(Ljava/lang/Object;)Z
     346: pop
     347: goto          297
     350: aload         10
     352: checkcast     #107                // class java/util/List
     355: nop
     356: astore        15
     358: new           #118                // class org/jetbrains/kotlinx/dataframe/codeGen/Marker
     361: dup
     362: aload_1
     363: invokeinterface #122,  1          // InterfaceMethod kotlin/reflect/KClass.getQualifiedName:()Ljava/lang/String;
     368: dup
     369: ifnonnull     383
     372: pop
     373: aload_1
     374: invokeinterface #125,  1          // InterfaceMethod kotlin/reflect/KClass.getSimpleName:()Ljava/lang/String;
     379: dup
     380: invokestatic  #129                // Method kotlin/jvm/internal/Intrinsics.checkNotNull:(Ljava/lang/Object;)V
     383: iload         16
     385: aload         6
     387: aload         15
     389: getstatic     #135                // Field org/jetbrains/kotlinx/dataframe/codeGen/MarkerVisibility.IMPLICIT_PUBLIC:Lorg/jetbrains/kotlinx/dataframe/codeGen/MarkerVisibility;
     392: invokespecial #138                // Method org/jetbrains/kotlinx/dataframe/codeGen/Marker."<init>":(Ljava/lang/String;ZLjava/util/List;Ljava/util/List;Lorg/jetbrains/kotlinx/dataframe/codeGen/MarkerVisibility;)V
     395: astore        5
     397: aload_2
     398: aload_1
     399: aload         5
     401: invokeinterface #142,  3          // InterfaceMethod java/util/Map.put:(Ljava/lang/Object;Ljava/lang/Object;)Ljava/lang/Object;
     406: pop
     407: aload         5
     409: goto          414
     412: aload         4
     414: nop
     415: checkcast     #118                // class org/jetbrains/kotlinx/dataframe/codeGen/Marker
     418: areturn

  private final java.util.List<org.jetbrains.kotlinx.dataframe.codeGen.GeneratedField> getFields(kotlin.reflect.KClass<?>);
    Code:
       0: aload_1
       1: invokestatic  #184                // Method kotlin/reflect/full/KClasses.getDeclaredMemberProperties:(Lkotlin/reflect/KClass;)Ljava/util/Collection;
       4: checkcast     #64                 // class java/lang/Iterable
       7: astore_2
       8: iconst_0
       9: istore_3
      10: aload_2
      11: astore        4
      13: new           #92                 // class java/util/ArrayList
      16: dup
      17: aload_2
      18: bipush        10
      20: invokestatic  #113                // Method kotlin/collections/CollectionsKt.collectionSizeOrDefault:(Ljava/lang/Iterable;I)I
      23: invokespecial #116                // Method java/util/ArrayList."<init>":(I)V
      26: checkcast     #95                 // class java/util/Collection
      29: astore        5
      31: iconst_0
      32: istore        6
      34: iconst_0
      35: istore        7
      37: aload         4
      39: invokeinterface #68,  1           // InterfaceMethod java/lang/Iterable.iterator:()Ljava/util/Iterator;
      44: astore        8
      46: aload         8
      48: invokeinterface #74,  1           // InterfaceMethod java/util/Iterator.hasNext:()Z
      53: ifeq          736
      56: aload         8
      58: invokeinterface #78,  1           // InterfaceMethod java/util/Iterator.next:()Ljava/lang/Object;
      63: astore        9
      65: aload         5
      67: iload         7
      69: istore        10
      71: iload         10
      73: iconst_1
      74: iadd
      75: istore        7
      77: iload         10
      79: istore        10
      81: iload         10
      83: ifge          89
      86: invokestatic  #187                // Method kotlin/collections/CollectionsKt.throwIndexOverflow:()V
      89: iload         10
      91: aload         9
      93: checkcast     #189                // class kotlin/reflect/KProperty1
      96: astore        11
      98: istore        12
     100: astore        32
     102: iconst_0
     103: istore        13
     105: getstatic     #195                // Field org/jetbrains/kotlinx/dataframe/codeGen/ValidFieldName.Companion:Lorg/jetbrains/kotlinx/dataframe/codeGen/ValidFieldName$Companion;
     108: aload         11
     110: invokeinterface #198,  1          // InterfaceMethod kotlin/reflect/KProperty1.getName:()Ljava/lang/String;
     115: invokevirtual #204                // Method org/jetbrains/kotlinx/dataframe/codeGen/ValidFieldName$Companion.of:(Ljava/lang/String;)Lorg/jetbrains/kotlinx/dataframe/codeGen/ValidFieldName;
     118: astore        14
     120: aload         11
     122: checkcast     #58                 // class kotlin/reflect/KAnnotatedElement
     125: astore        15
     127: iconst_0
     128: istore        16
     130: aload         15
     132: invokeinterface #62,  1           // InterfaceMethod kotlin/reflect/KAnnotatedElement.getAnnotations:()Ljava/util/List;
     137: checkcast     #64                 // class java/lang/Iterable
     140: astore        17
     142: iconst_0
     143: istore        18
     145: aload         17
     147: invokeinterface #68,  1           // InterfaceMethod java/lang/Iterable.iterator:()Ljava/util/Iterator;
     152: astore        19
     154: aload         19
     156: invokeinterface #74,  1           // InterfaceMethod java/util/Iterator.hasNext:()Z
     161: ifeq          196
     164: aload         19
     166: invokeinterface #78,  1           // InterfaceMethod java/util/Iterator.next:()Ljava/lang/Object;
     171: astore        20
     173: aload         20
     175: checkcast     #80                 // class java/lang/annotation/Annotation
     178: astore        21
     180: iconst_0
     181: istore        22
     183: aload         21
     185: instanceof    #206                // class org/jetbrains/kotlinx/dataframe/annotations/ColumnName
     188: ifeq          154
     191: aload         20
     193: goto          197
     196: aconst_null
     197: checkcast     #206                // class org/jetbrains/kotlinx/dataframe/annotations/ColumnName
     200: checkcast     #80                 // class java/lang/annotation/Annotation
     203: nop
     204: checkcast     #206                // class org/jetbrains/kotlinx/dataframe/annotations/ColumnName
     207: dup
     208: ifnonnull     216
     211: pop
     212: aconst_null
     213: goto          221
     216: invokeinterface #209,  1          // InterfaceMethod org/jetbrains/kotlinx/dataframe/annotations/ColumnName.name:()Ljava/lang/String;
     221: dup
     222: ifnonnull     231
     225: pop
     226: aload         14
     228: invokevirtual #212                // Method org/jetbrains/kotlinx/dataframe/codeGen/ValidFieldName.getUnquoted:()Ljava/lang/String;
     231: astore        25
     233: aload         11
     235: invokeinterface #216,  1          // InterfaceMethod kotlin/reflect/KProperty1.getReturnType:()Lkotlin/reflect/KType;
     240: astore        24
     242: aconst_null
     243: astore        23
     245: aload         24
     247: invokestatic  #222                // Method kotlin/reflect/jvm/KTypesJvm.getJvmErasure:(Lkotlin/reflect/KType;)Lkotlin/reflect/KClass;
     250: astore        15
     252: nop
     253: aload         15
     255: ldc           #224                // class org/jetbrains/kotlinx/dataframe/DataRow
     257: invokestatic  #27                 // Method kotlin/jvm/internal/Reflection.getOrCreateKotlinClass:(Ljava/lang/Class;)Lkotlin/reflect/KClass;
     260: invokestatic  #101                // Method kotlin/jvm/internal/Intrinsics.areEqual:(Ljava/lang/Object;Ljava/lang/Object;)Z
     263: ifne          369
     266: aload         15
     268: checkcast     #58                 // class kotlin/reflect/KAnnotatedElement
     271: astore        17
     273: iconst_0
     274: istore        18
     276: aload         17
     278: astore        19
     280: iconst_0
     281: istore        20
     283: aload         19
     285: invokeinterface #62,  1           // InterfaceMethod kotlin/reflect/KAnnotatedElement.getAnnotations:()Ljava/util/List;
     290: checkcast     #64                 // class java/lang/Iterable
     293: astore        21
     295: iconst_0
     296: istore        22
     298: aload         21
     300: invokeinterface #68,  1           // InterfaceMethod java/lang/Iterable.iterator:()Ljava/util/Iterator;
     305: astore        26
     307: aload         26
     309: invokeinterface #74,  1           // InterfaceMethod java/util/Iterator.hasNext:()Z
     314: ifeq          349
     317: aload         26
     319: invokeinterface #78,  1           // InterfaceMethod java/util/Iterator.next:()Ljava/lang/Object;
     324: astore        27
     326: aload         27
     328: checkcast     #80                 // class java/lang/annotation/Annotation
     331: astore        28
     333: iconst_0
     334: istore        29
     336: aload         28
     338: instanceof    #82                 // class org/jetbrains/kotlinx/dataframe/annotations/DataSchema
     341: ifeq          307
     344: aload         27
     346: goto          350
     349: aconst_null
     350: checkcast     #82                 // class org/jetbrains/kotlinx/dataframe/annotations/DataSchema
     353: checkcast     #80                 // class java/lang/annotation/Annotation
     356: nop
     357: ifnull        364
     360: iconst_1
     361: goto          365
     364: iconst_0
     365: nop
     366: ifeq          443
     369: aload         15
     371: ldc           #224                // class org/jetbrains/kotlinx/dataframe/DataRow
     373: invokestatic  #27                 // Method kotlin/jvm/internal/Reflection.getOrCreateKotlinClass:(Ljava/lang/Class;)Lkotlin/reflect/KClass;
     376: invokestatic  #101                // Method kotlin/jvm/internal/Intrinsics.areEqual:(Ljava/lang/Object;Ljava/lang/Object;)Z
     379: ifeq          408
     382: aload         24
     384: invokeinterface #229,  1          // InterfaceMethod kotlin/reflect/KType.getArguments:()Ljava/util/List;
     389: iconst_0
     390: invokeinterface #232,  2          // InterfaceMethod java/util/List.get:(I)Ljava/lang/Object;
     395: checkcast     #234                // class kotlin/reflect/KTypeProjection
     398: invokevirtual #237                // Method kotlin/reflect/KTypeProjection.getType:()Lkotlin/reflect/KType;
     401: dup
     402: invokestatic  #129                // Method kotlin/jvm/internal/Intrinsics.checkNotNull:(Ljava/lang/Object;)V
     405: goto          410
     408: aload         24
     410: astore        17
     412: getstatic     #52                 // Field INSTANCE:Lorg/jetbrains/kotlinx/dataframe/codeGen/MarkersExtractor;
     415: aload         17
     417: invokestatic  #222                // Method kotlin/reflect/jvm/KTypesJvm.getJvmErasure:(Lkotlin/reflect/KType;)Lkotlin/reflect/KClass;
     420: invokevirtual #30                 // Method get:(Lkotlin/reflect/KClass;)Lorg/jetbrains/kotlinx/dataframe/codeGen/Marker;
     423: astore        23
     425: new           #239                // class org/jetbrains/kotlinx/dataframe/schema/ColumnSchema$Group
     428: dup
     429: aload         23
     431: invokevirtual #243                // Method org/jetbrains/kotlinx/dataframe/codeGen/Marker.getSchema:()Lorg/jetbrains/kotlinx/dataframe/schema/DataFrameSchema;
     434: invokespecial #246                // Method org/jetbrains/kotlinx/dataframe/schema/ColumnSchema$Group."<init>":(Lorg/jetbrains/kotlinx/dataframe/schema/DataFrameSchema;)V
     437: checkcast     #248                // class org/jetbrains/kotlinx/dataframe/schema/ColumnSchema
     440: goto          694
     443: aload         15
     445: ldc           #250                // class org/jetbrains/kotlinx/dataframe/DataFrame
     447: invokestatic  #27                 // Method kotlin/jvm/internal/Reflection.getOrCreateKotlinClass:(Ljava/lang/Class;)Lkotlin/reflect/KClass;
     450: invokestatic  #101                // Method kotlin/jvm/internal/Intrinsics.areEqual:(Ljava/lang/Object;Ljava/lang/Object;)Z
     453: ifne          619
     456: aload         15
     458: ldc           #107                // class java/util/List
     460: invokestatic  #27                 // Method kotlin/jvm/internal/Reflection.getOrCreateKotlinClass:(Ljava/lang/Class;)Lkotlin/reflect/KClass;
     463: invokestatic  #101                // Method kotlin/jvm/internal/Intrinsics.areEqual:(Ljava/lang/Object;Ljava/lang/Object;)Z
     466: ifeq          682
     469: aload         24
     471: invokeinterface #229,  1          // InterfaceMethod kotlin/reflect/KType.getArguments:()Ljava/util/List;
     476: iconst_0
     477: invokeinterface #232,  2          // InterfaceMethod java/util/List.get:(I)Ljava/lang/Object;
     482: checkcast     #234                // class kotlin/reflect/KTypeProjection
     485: invokevirtual #237                // Method kotlin/reflect/KTypeProjection.getType:()Lkotlin/reflect/KType;
     488: dup
     489: ifnonnull     497
     492: pop
     493: iconst_0
     494: goto          616
     497: invokestatic  #222                // Method kotlin/reflect/jvm/KTypesJvm.getJvmErasure:(Lkotlin/reflect/KType;)Lkotlin/reflect/KClass;
     500: dup
     501: ifnonnull     509
     504: pop
     505: iconst_0
     506: goto          616
     509: checkcast     #58                 // class kotlin/reflect/KAnnotatedElement
     512: astore        19
     514: iconst_0
     515: istore        20
     517: aload         19
     519: astore        21
     521: iconst_0
     522: istore        22
     524: aload         21
     526: invokeinterface #62,  1           // InterfaceMethod kotlin/reflect/KAnnotatedElement.getAnnotations:()Ljava/util/List;
     531: checkcast     #64                 // class java/lang/Iterable
     534: astore        26
     536: iconst_0
     537: istore        27
     539: aload         26
     541: invokeinterface #68,  1           // InterfaceMethod java/lang/Iterable.iterator:()Ljava/util/Iterator;
     546: astore        28
     548: aload         28
     550: invokeinterface #74,  1           // InterfaceMethod java/util/Iterator.hasNext:()Z
     555: ifeq          590
     558: aload         28
     560: invokeinterface #78,  1           // InterfaceMethod java/util/Iterator.next:()Ljava/lang/Object;
     565: astore        29
     567: aload         29
     569: checkcast     #80                 // class java/lang/annotation/Annotation
     572: astore        30
     574: iconst_0
     575: istore        31
     577: aload         30
     579: instanceof    #82                 // class org/jetbrains/kotlinx/dataframe/annotations/DataSchema
     582: ifeq          548
     585: aload         29
     587: goto          591
     590: aconst_null
     591: checkcast     #82                 // class org/jetbrains/kotlinx/dataframe/annotations/DataSchema
     594: checkcast     #80                 // class java/lang/annotation/Annotation
     597: nop
     598: ifnull        605
     601: iconst_1
     602: goto          606
     605: iconst_0
     606: nop
     607: iconst_1
     608: if_icmpne     615
     611: iconst_1
     612: goto          616
     615: iconst_0
     616: ifeq          682
     619: aload         24
     621: invokeinterface #229,  1          // InterfaceMethod kotlin/reflect/KType.getArguments:()Ljava/util/List;
     626: iconst_0
     627: invokeinterface #232,  2          // InterfaceMethod java/util/List.get:(I)Ljava/lang/Object;
     632: checkcast     #234                // class kotlin/reflect/KTypeProjection
     635: invokevirtual #237                // Method kotlin/reflect/KTypeProjection.getType:()Lkotlin/reflect/KType;
     638: dup
     639: invokestatic  #129                // Method kotlin/jvm/internal/Intrinsics.checkNotNull:(Ljava/lang/Object;)V
     642: astore        17
     644: getstatic     #52                 // Field INSTANCE:Lorg/jetbrains/kotlinx/dataframe/codeGen/MarkersExtractor;
     647: aload         17
     649: invokestatic  #222                // Method kotlin/reflect/jvm/KTypesJvm.getJvmErasure:(Lkotlin/reflect/KType;)Lkotlin/reflect/KClass;
     652: invokevirtual #30                 // Method get:(Lkotlin/reflect/KClass;)Lorg/jetbrains/kotlinx/dataframe/codeGen/Marker;
     655: astore        23
     657: new           #252                // class org/jetbrains/kotlinx/dataframe/schema/ColumnSchema$Frame
     660: dup
     661: aload         23
     663: invokevirtual #243                // Method org/jetbrains/kotlinx/dataframe/codeGen/Marker.getSchema:()Lorg/jetbrains/kotlinx/dataframe/schema/DataFrameSchema;
     666: aload         24
     668: invokeinterface #255,  1          // InterfaceMethod kotlin/reflect/KType.isMarkedNullable:()Z
     673: invokespecial #258                // Method org/jetbrains/kotlinx/dataframe/schema/ColumnSchema$Frame."<init>":(Lorg/jetbrains/kotlinx/dataframe/schema/DataFrameSchema;Z)V
     676: checkcast     #248                // class org/jetbrains/kotlinx/dataframe/schema/ColumnSchema
     679: goto          694
     682: new           #260                // class org/jetbrains/kotlinx/dataframe/schema/ColumnSchema$Value
     685: dup
     686: aload         24
     688: invokespecial #263                // Method org/jetbrains/kotlinx/dataframe/schema/ColumnSchema$Value."<init>":(Lkotlin/reflect/KType;)V
     691: checkcast     #248                // class org/jetbrains/kotlinx/dataframe/schema/ColumnSchema
     694: astore        16
     696: new           #265                // class org/jetbrains/kotlinx/dataframe/codeGen/GeneratedField
     699: dup
     700: aload         14
     702: aload         25
     704: iconst_0
     705: aload         16
     707: aload         23
     709: dup
     710: ifnonnull     718
     713: pop
     714: aconst_null
     715: goto          721
     718: invokevirtual #266                // Method org/jetbrains/kotlinx/dataframe/codeGen/Marker.getName:()Ljava/lang/String;
     721: invokespecial #269                // Method org/jetbrains/kotlinx/dataframe/codeGen/GeneratedField."<init>":(Lorg/jetbrains/kotlinx/dataframe/codeGen/ValidFieldName;Ljava/lang/String;ZLorg/jetbrains/kotlinx/dataframe/schema/ColumnSchema;Ljava/lang/String;)V
     724: aload         32
     726: swap
     727: invokeinterface #105,  2          // InterfaceMethod java/util/Collection.add:(Ljava/lang/Object;)Z
     732: pop
     733: goto          46
     736: aload         5
     738: checkcast     #107                // class java/util/List
     741: nop
     742: areturn

  static {};
    Code:
       0: new           #2                  // class org/jetbrains/kotlinx/dataframe/codeGen/MarkersExtractor
       3: dup
       4: invokespecial #299                // Method "<init>":()V
       7: putstatic     #52                 // Field INSTANCE:Lorg/jetbrains/kotlinx/dataframe/codeGen/MarkersExtractor;
      10: new           #301                // class java/util/LinkedHashMap
      13: dup
      14: invokespecial #302                // Method java/util/LinkedHashMap."<init>":()V
      17: checkcast     #46                 // class java/util/Map
      20: putstatic     #44                 // Field cache:Ljava/util/Map;
      23: return
}
