Compiled from "TraceAdminPB.java"
final class org.apache.hadoop.tracing.TraceAdminPB$TraceAdminService$1 extends org.apache.hadoop.tracing.TraceAdminPB$TraceAdminService {
  final org.apache.hadoop.tracing.TraceAdminPB$TraceAdminService$Interface val$impl;

  org.apache.hadoop.tracing.TraceAdminPB$TraceAdminService$1(org.apache.hadoop.tracing.TraceAdminPB$TraceAdminService$Interface);
    Code:
       0: aload_0
       1: aload_1
       2: putfield      #1                  // Field val$impl:Lorg/apache/hadoop/tracing/TraceAdminPB$TraceAdminService$Interface;
       5: aload_0
       6: invokespecial #2                  // Method org/apache/hadoop/tracing/TraceAdminPB$TraceAdminService."<init>":()V
       9: return

  public void listSpanReceivers(com.google.protobuf.RpcController, org.apache.hadoop.tracing.TraceAdminPB$ListSpanReceiversRequestProto, com.google.protobuf.RpcCallback<org.apache.hadoop.tracing.TraceAdminPB$ListSpanReceiversResponseProto>);
    Code:
       0: aload_0
       1: getfield      #1                  // Field val$impl:Lorg/apache/hadoop/tracing/TraceAdminPB$TraceAdminService$Interface;
       4: aload_1
       5: aload_2
       6: aload_3
       7: invokeinterface #3,  4            // InterfaceMethod org/apache/hadoop/tracing/TraceAdminPB$TraceAdminService$Interface.listSpanReceivers:(Lcom/google/protobuf/RpcController;Lorg/apache/hadoop/tracing/TraceAdminPB$ListSpanReceiversRequestProto;Lcom/google/protobuf/RpcCallback;)V
      12: return

  public void addSpanReceiver(com.google.protobuf.RpcController, org.apache.hadoop.tracing.TraceAdminPB$AddSpanReceiverRequestProto, com.google.protobuf.RpcCallback<org.apache.hadoop.tracing.TraceAdminPB$AddSpanReceiverResponseProto>);
    Code:
       0: aload_0
       1: getfield      #1                  // Field val$impl:Lorg/apache/hadoop/tracing/TraceAdminPB$TraceAdminService$Interface;
       4: aload_1
       5: aload_2
       6: aload_3
       7: invokeinterface #4,  4            // InterfaceMethod org/apache/hadoop/tracing/TraceAdminPB$TraceAdminService$Interface.addSpanReceiver:(Lcom/google/protobuf/RpcController;Lorg/apache/hadoop/tracing/TraceAdminPB$AddSpanReceiverRequestProto;Lcom/google/protobuf/RpcCallback;)V
      12: return

  public void removeSpanReceiver(com.google.protobuf.RpcController, org.apache.hadoop.tracing.TraceAdminPB$RemoveSpanReceiverRequestProto, com.google.protobuf.RpcCallback<org.apache.hadoop.tracing.TraceAdminPB$RemoveSpanReceiverResponseProto>);
    Code:
       0: aload_0
       1: getfield      #1                  // Field val$impl:Lorg/apache/hadoop/tracing/TraceAdminPB$TraceAdminService$Interface;
       4: aload_1
       5: aload_2
       6: aload_3
       7: invokeinterface #5,  4            // InterfaceMethod org/apache/hadoop/tracing/TraceAdminPB$TraceAdminService$Interface.removeSpanReceiver:(Lcom/google/protobuf/RpcController;Lorg/apache/hadoop/tracing/TraceAdminPB$RemoveSpanReceiverRequestProto;Lcom/google/protobuf/RpcCallback;)V
      12: return
}
