Compiled from "X962NamedCurves.java"
class org.bouncycastle.asn1.x9.X962NamedCurves$20 extends org.bouncycastle.asn1.x9.X9ECParametersHolder {
  org.bouncycastle.asn1.x9.X962NamedCurves$20();
    Code:
       0: aload_0
       1: invokespecial #1                  // Method org/bouncycastle/asn1/x9/X9ECParametersHolder."<init>":()V
       4: return

  protected org.bouncycastle.asn1.x9.X9ECParameters createParameters();
    Code:
       0: ldc           #2                  // String 0101D556572AABAC800101D556572AABAC8001022D5C91DD173F8FB561DA6899164443051D
       2: invokestatic  #3                  // Method org/bouncycastle/asn1/x9/X962NamedCurves.access$000:(Ljava/lang/String;)Ljava/math/BigInteger;
       5: astore_1
       6: ldc2_w        #4                  // long 65070l
       9: invokestatic  #6                  // Method java/math/BigInteger.valueOf:(J)Ljava/math/BigInteger;
      12: astore_2
      13: new           #7                  // class org/bouncycastle/math/ec/ECCurve$F2m
      16: dup
      17: sipush        304
      20: iconst_1
      21: iconst_2
      22: bipush        11
      24: ldc           #8                  // String FD0D693149A118F651E6DCE6802085377E5F882D1B510B44160074C1288078365A0396C8E681
      26: invokestatic  #3                  // Method org/bouncycastle/asn1/x9/X962NamedCurves.access$000:(Ljava/lang/String;)Ljava/math/BigInteger;
      29: ldc           #9                  // String BDDB97E555A50A908E43B01C798EA5DAA6788F1EA2794EFCF57166B8C14039601E55827340BE
      31: invokestatic  #3                  // Method org/bouncycastle/asn1/x9/X962NamedCurves.access$000:(Ljava/lang/String;)Ljava/math/BigInteger;
      34: aload_1
      35: aload_2
      36: invokespecial #10                 // Method org/bouncycastle/math/ec/ECCurve$F2m."<init>":(IIIILjava/math/BigInteger;Ljava/math/BigInteger;Ljava/math/BigInteger;Ljava/math/BigInteger;)V
      39: invokestatic  #11                 // Method org/bouncycastle/asn1/x9/X962NamedCurves.access$100:(Lorg/bouncycastle/math/ec/ECCurve;)Lorg/bouncycastle/math/ec/ECCurve;
      42: astore_3
      43: aload_3
      44: ldc           #12                 // String 02197B07845E9BE2D96ADB0F5F3C7F2CFFBD7A3EB8B6FEC35C7FD67F26DDF6285A644F740A2614
      46: invokestatic  #13                 // Method org/bouncycastle/asn1/x9/X962NamedCurves.access$200:(Lorg/bouncycastle/math/ec/ECCurve;Ljava/lang/String;)Lorg/bouncycastle/asn1/x9/X9ECPoint;
      49: astore        4
      51: new           #14                 // class org/bouncycastle/asn1/x9/X9ECParameters
      54: dup
      55: aload_3
      56: aload         4
      58: aload_1
      59: aload_2
      60: invokespecial #15                 // Method org/bouncycastle/asn1/x9/X9ECParameters."<init>":(Lorg/bouncycastle/math/ec/ECCurve;Lorg/bouncycastle/asn1/x9/X9ECPoint;Ljava/math/BigInteger;Ljava/math/BigInteger;)V
      63: areturn
}
