Compiled from "IdentifierSourceAggregatedCompositeImpl.java"
class org.hibernate.boot.model.source.internal.hbm.IdentifierSourceAggregatedCompositeImpl$SingularAttributeSourceAggregatedCompositeIdentifierImpl extends org.hibernate.boot.model.source.internal.hbm.AbstractSingularAttributeSourceEmbeddedImpl {
  private final org.hibernate.boot.model.source.internal.hbm.IdentifierSourceAggregatedCompositeImpl$EmbeddedAttributeMappingAdapterAggregatedCompositeId compositeIdAdapter;

  protected org.hibernate.boot.model.source.internal.hbm.IdentifierSourceAggregatedCompositeImpl$SingularAttributeSourceAggregatedCompositeIdentifierImpl(org.hibernate.boot.model.source.internal.hbm.MappingDocument, org.hibernate.boot.model.source.internal.hbm.IdentifierSourceAggregatedCompositeImpl$EmbeddedAttributeMappingAdapterAggregatedCompositeId);
    Code:
       0: aload_0
       1: aload_1
       2: aload_2
       3: new           #1                  // class org/hibernate/boot/model/source/internal/hbm/EmbeddableSourceImpl
       6: dup
       7: aload_1
       8: aload_2
       9: aload_2
      10: aload_2
      11: invokevirtual #2                  // Method org/hibernate/boot/model/source/internal/hbm/IdentifierSourceAggregatedCompositeImpl$EmbeddedAttributeMappingAdapterAggregatedCompositeId.getAttributes:()Ljava/util/List;
      14: iconst_0
      15: iconst_0
      16: aconst_null
      17: getstatic     #3                  // Field org/hibernate/boot/model/source/spi/NaturalIdMutability.NOT_NATURAL_ID:Lorg/hibernate/boot/model/source/spi/NaturalIdMutability;
      20: invokespecial #4                  // Method org/hibernate/boot/model/source/internal/hbm/EmbeddableSourceImpl."<init>":(Lorg/hibernate/boot/model/source/internal/hbm/MappingDocument;Lorg/hibernate/boot/model/source/internal/hbm/EmbeddableSourceContainer;Lorg/hibernate/boot/model/source/spi/EmbeddableMapping;Ljava/util/List;ZZLjava/lang/String;Lorg/hibernate/boot/model/source/spi/NaturalIdMutability;)V
      23: getstatic     #3                  // Field org/hibernate/boot/model/source/spi/NaturalIdMutability.NOT_NATURAL_ID:Lorg/hibernate/boot/model/source/spi/NaturalIdMutability;
      26: invokespecial #5                  // Method org/hibernate/boot/model/source/internal/hbm/AbstractSingularAttributeSourceEmbeddedImpl."<init>":(Lorg/hibernate/boot/model/source/internal/hbm/MappingDocument;Lorg/hibernate/boot/model/source/spi/EmbeddedAttributeMapping;Lorg/hibernate/boot/model/source/spi/EmbeddableSource;Lorg/hibernate/boot/model/source/spi/NaturalIdMutability;)V
      29: aload_0
      30: aload_2
      31: putfield      #6                  // Field compositeIdAdapter:Lorg/hibernate/boot/model/source/internal/hbm/IdentifierSourceAggregatedCompositeImpl$EmbeddedAttributeMappingAdapterAggregatedCompositeId;
      34: return

  public java.lang.Boolean isInsertable();
    Code:
       0: iconst_1
       1: invokestatic  #7                  // Method java/lang/Boolean.valueOf:(Z)Ljava/lang/Boolean;
       4: areturn

  public java.lang.Boolean isUpdatable();
    Code:
       0: iconst_0
       1: invokestatic  #7                  // Method java/lang/Boolean.valueOf:(Z)Ljava/lang/Boolean;
       4: areturn

  public boolean isBytecodeLazy();
    Code:
       0: iconst_0
       1: ireturn

  public org.hibernate.boot.model.source.internal.hbm.XmlElementMetadata getSourceType();
    Code:
       0: getstatic     #8                  // Field org/hibernate/boot/model/source/internal/hbm/XmlElementMetadata.COMPOSITE_ID:Lorg/hibernate/boot/model/source/internal/hbm/XmlElementMetadata;
       3: areturn

  public java.lang.String getXmlNodeName();
    Code:
       0: aload_0
       1: getfield      #6                  // Field compositeIdAdapter:Lorg/hibernate/boot/model/source/internal/hbm/IdentifierSourceAggregatedCompositeImpl$EmbeddedAttributeMappingAdapterAggregatedCompositeId;
       4: invokevirtual #9                  // Method org/hibernate/boot/model/source/internal/hbm/IdentifierSourceAggregatedCompositeImpl$EmbeddedAttributeMappingAdapterAggregatedCompositeId.getXmlNodeName:()Ljava/lang/String;
       7: areturn

  public org.hibernate.boot.model.source.spi.AttributePath getAttributePath();
    Code:
       0: aload_0
       1: invokevirtual #10                 // Method getEmbeddableSource:()Lorg/hibernate/boot/model/source/spi/EmbeddableSource;
       4: invokeinterface #11,  1           // InterfaceMethod org/hibernate/boot/model/source/spi/EmbeddableSource.getAttributePathBase:()Lorg/hibernate/boot/model/source/spi/AttributePath;
       9: areturn

  public org.hibernate.boot.model.source.spi.AttributeRole getAttributeRole();
    Code:
       0: aload_0
       1: invokevirtual #10                 // Method getEmbeddableSource:()Lorg/hibernate/boot/model/source/spi/EmbeddableSource;
       4: invokeinterface #12,  1           // InterfaceMethod org/hibernate/boot/model/source/spi/EmbeddableSource.getAttributeRoleBase:()Lorg/hibernate/boot/model/source/spi/AttributeRole;
       9: areturn

  public boolean isIncludedInOptimisticLocking();
    Code:
       0: iconst_0
       1: ireturn

  public org.hibernate.boot.model.source.spi.ToolingHintContext getToolingHintContext();
    Code:
       0: aload_0
       1: getfield      #6                  // Field compositeIdAdapter:Lorg/hibernate/boot/model/source/internal/hbm/IdentifierSourceAggregatedCompositeImpl$EmbeddedAttributeMappingAdapterAggregatedCompositeId;
       4: invokestatic  #13                 // Method org/hibernate/boot/model/source/internal/hbm/IdentifierSourceAggregatedCompositeImpl$EmbeddedAttributeMappingAdapterAggregatedCompositeId.access$100:(Lorg/hibernate/boot/model/source/internal/hbm/IdentifierSourceAggregatedCompositeImpl$EmbeddedAttributeMappingAdapterAggregatedCompositeId;)Lorg/hibernate/boot/model/source/spi/ToolingHintContext;
       7: areturn
}
