Compiled from "ModelBinder.java"
class org.hibernate.boot.model.source.internal.hbm.ModelBinder$ManyToOneColumnBinder$2$1 implements org.hibernate.boot.model.naming.ImplicitBasicColumnNameSource {
  final org.hibernate.boot.model.source.spi.LocalMetadataBuildingContext val$context;

  final org.hibernate.boot.model.source.internal.hbm.ModelBinder$ManyToOneColumnBinder$2 this$2;

  org.hibernate.boot.model.source.internal.hbm.ModelBinder$ManyToOneColumnBinder$2$1(org.hibernate.boot.model.source.internal.hbm.ModelBinder$ManyToOneColumnBinder$2, org.hibernate.boot.model.source.spi.LocalMetadataBuildingContext);
    Code:
       0: aload_0
       1: aload_1
       2: putfield      #1                  // Field this$2:Lorg/hibernate/boot/model/source/internal/hbm/ModelBinder$ManyToOneColumnBinder$2;
       5: aload_0
       6: aload_2
       7: putfield      #2                  // Field val$context:Lorg/hibernate/boot/model/source/spi/LocalMetadataBuildingContext;
      10: aload_0
      11: invokespecial #3                  // Method java/lang/Object."<init>":()V
      14: return

  public org.hibernate.boot.model.source.spi.AttributePath getAttributePath();
    Code:
       0: aload_0
       1: getfield      #1                  // Field this$2:Lorg/hibernate/boot/model/source/internal/hbm/ModelBinder$ManyToOneColumnBinder$2;
       4: getfield      #4                  // Field org/hibernate/boot/model/source/internal/hbm/ModelBinder$ManyToOneColumnBinder$2.this$1:Lorg/hibernate/boot/model/source/internal/hbm/ModelBinder$ManyToOneColumnBinder;
       7: invokestatic  #5                  // Method org/hibernate/boot/model/source/internal/hbm/ModelBinder$ManyToOneColumnBinder.access$1900:(Lorg/hibernate/boot/model/source/internal/hbm/ModelBinder$ManyToOneColumnBinder;)Lorg/hibernate/boot/model/source/spi/SingularAttributeSourceManyToOne;
      10: invokeinterface #6,  1            // InterfaceMethod org/hibernate/boot/model/source/spi/SingularAttributeSourceManyToOne.getAttributePath:()Lorg/hibernate/boot/model/source/spi/AttributePath;
      15: areturn

  public boolean isCollectionElement();
    Code:
       0: iconst_0
       1: ireturn

  public org.hibernate.boot.spi.MetadataBuildingContext getBuildingContext();
    Code:
       0: aload_0
       1: getfield      #2                  // Field val$context:Lorg/hibernate/boot/model/source/spi/LocalMetadataBuildingContext;
       4: areturn
}
