Compiled from "PluralAttributeMapKeySourceEmbeddedImpl.java"
public class org.hibernate.boot.model.source.internal.hbm.PluralAttributeMapKeySourceEmbeddedImpl extends org.hibernate.boot.model.source.internal.hbm.AbstractHbmSourceNode implements org.hibernate.boot.model.source.spi.PluralAttributeMapKeySourceEmbedded {
  private final org.hibernate.boot.model.source.internal.hbm.EmbeddableSourceImpl embeddableSource;

  public org.hibernate.boot.model.source.internal.hbm.PluralAttributeMapKeySourceEmbeddedImpl(org.hibernate.boot.model.source.internal.hbm.MappingDocument, org.hibernate.boot.model.source.internal.hbm.AbstractPluralAttributeSourceImpl, org.hibernate.boot.jaxb.hbm.spi.JaxbHbmCompositeIndexType);
    Code:
       0: aload_0
       1: aload_1
       2: aload_2
       3: new           #1                  // class org/hibernate/boot/model/source/internal/hbm/PluralAttributeMapKeySourceEmbeddedImpl$1
       6: dup
       7: aload_3
       8: invokespecial #2                  // Method org/hibernate/boot/model/source/internal/hbm/PluralAttributeMapKeySourceEmbeddedImpl$1."<init>":(Lorg/hibernate/boot/jaxb/hbm/spi/JaxbHbmCompositeIndexType;)V
      11: aload_3
      12: invokevirtual #3                  // Method org/hibernate/boot/jaxb/hbm/spi/JaxbHbmCompositeIndexType.getAttributes:()Ljava/util/List;
      15: invokespecial #4                  // Method "<init>":(Lorg/hibernate/boot/model/source/internal/hbm/MappingDocument;Lorg/hibernate/boot/model/source/internal/hbm/AbstractPluralAttributeSourceImpl;Lorg/hibernate/boot/model/source/spi/EmbeddableMapping;Ljava/util/List;)V
      18: return

  public org.hibernate.boot.model.source.internal.hbm.PluralAttributeMapKeySourceEmbeddedImpl(org.hibernate.boot.model.source.internal.hbm.MappingDocument, org.hibernate.boot.model.source.internal.hbm.AbstractPluralAttributeSourceImpl, org.hibernate.boot.jaxb.hbm.spi.JaxbHbmMapKeyCompositeType);
    Code:
       0: aload_0
       1: aload_1
       2: aload_2
       3: new           #5                  // class org/hibernate/boot/model/source/internal/hbm/PluralAttributeMapKeySourceEmbeddedImpl$2
       6: dup
       7: aload_3
       8: invokespecial #6                  // Method org/hibernate/boot/model/source/internal/hbm/PluralAttributeMapKeySourceEmbeddedImpl$2."<init>":(Lorg/hibernate/boot/jaxb/hbm/spi/JaxbHbmMapKeyCompositeType;)V
      11: aload_3
      12: invokevirtual #7                  // Method org/hibernate/boot/jaxb/hbm/spi/JaxbHbmMapKeyCompositeType.getAttributes:()Ljava/util/List;
      15: invokespecial #4                  // Method "<init>":(Lorg/hibernate/boot/model/source/internal/hbm/MappingDocument;Lorg/hibernate/boot/model/source/internal/hbm/AbstractPluralAttributeSourceImpl;Lorg/hibernate/boot/model/source/spi/EmbeddableMapping;Ljava/util/List;)V
      18: return

  private org.hibernate.boot.model.source.internal.hbm.PluralAttributeMapKeySourceEmbeddedImpl(org.hibernate.boot.model.source.internal.hbm.MappingDocument, org.hibernate.boot.model.source.internal.hbm.AbstractPluralAttributeSourceImpl, org.hibernate.boot.model.source.spi.EmbeddableMapping, java.util.List);
    Code:
       0: aload_0
       1: aload_1
       2: invokespecial #8                  // Method org/hibernate/boot/model/source/internal/hbm/AbstractHbmSourceNode."<init>":(Lorg/hibernate/boot/model/source/internal/hbm/MappingDocument;)V
       5: aload_0
       6: new           #9                  // class org/hibernate/boot/model/source/internal/hbm/EmbeddableSourceImpl
       9: dup
      10: aload_1
      11: new           #10                 // class org/hibernate/boot/model/source/internal/hbm/PluralAttributeMapKeySourceEmbeddedImpl$3
      14: dup
      15: aload_0
      16: aload_2
      17: invokespecial #11                 // Method org/hibernate/boot/model/source/internal/hbm/PluralAttributeMapKeySourceEmbeddedImpl$3."<init>":(Lorg/hibernate/boot/model/source/internal/hbm/PluralAttributeMapKeySourceEmbeddedImpl;Lorg/hibernate/boot/model/source/internal/hbm/AbstractPluralAttributeSourceImpl;)V
      20: aload_3
      21: aload         4
      23: iconst_0
      24: iconst_0
      25: aconst_null
      26: getstatic     #12                 // Field org/hibernate/boot/model/source/spi/NaturalIdMutability.NOT_NATURAL_ID:Lorg/hibernate/boot/model/source/spi/NaturalIdMutability;
      29: invokespecial #13                 // Method org/hibernate/boot/model/source/internal/hbm/EmbeddableSourceImpl."<init>":(Lorg/hibernate/boot/model/source/internal/hbm/MappingDocument;Lorg/hibernate/boot/model/source/internal/hbm/EmbeddableSourceContainer;Lorg/hibernate/boot/model/source/spi/EmbeddableMapping;Ljava/util/List;ZZLjava/lang/String;Lorg/hibernate/boot/model/source/spi/NaturalIdMutability;)V
      32: putfield      #14                 // Field embeddableSource:Lorg/hibernate/boot/model/source/internal/hbm/EmbeddableSourceImpl;
      35: return

  public org.hibernate.boot.model.source.spi.PluralAttributeIndexNature getNature();
    Code:
       0: getstatic     #15                 // Field org/hibernate/boot/model/source/spi/PluralAttributeIndexNature.AGGREGATE:Lorg/hibernate/boot/model/source/spi/PluralAttributeIndexNature;
       3: areturn

  public org.hibernate.boot.model.source.spi.EmbeddableSource getEmbeddableSource();
    Code:
       0: aload_0
       1: getfield      #14                 // Field embeddableSource:Lorg/hibernate/boot/model/source/internal/hbm/EmbeddableSourceImpl;
       4: areturn

  public org.hibernate.boot.model.source.spi.HibernateTypeSource getTypeInformation();
    Code:
       0: aconst_null
       1: areturn

  public java.lang.String getXmlNodeName();
    Code:
       0: aconst_null
       1: areturn
}
