Compiled from "SingularAttributeSourceManyToOneImpl.java"
class org.hibernate.boot.model.source.internal.hbm.SingularAttributeSourceManyToOneImpl extends org.hibernate.boot.model.source.internal.hbm.AbstractToOneAttributeSourceImpl implements org.hibernate.boot.model.source.spi.SingularAttributeSourceManyToOne,org.hibernate.boot.model.source.spi.RelationalValueSourceContainer {
  private final org.hibernate.boot.jaxb.hbm.spi.JaxbHbmManyToOneType manyToOneElement;

  private final org.hibernate.boot.model.source.internal.hbm.HibernateTypeSourceImpl typeSource;

  private final java.lang.String referencedTypeName;

  private final java.util.List<org.hibernate.boot.model.source.spi.RelationalValueSource> relationalValueSources;

  private final org.hibernate.boot.model.source.spi.AttributeRole attributeRole;

  private final org.hibernate.boot.model.source.spi.AttributePath attributePath;

  private final org.hibernate.boot.model.source.spi.ToolingHintContext toolingHintContext;

  private final org.hibernate.boot.model.source.internal.hbm.FetchCharacteristicsSingularAssociationImpl fetchCharacteristics;

  org.hibernate.boot.model.source.internal.hbm.SingularAttributeSourceManyToOneImpl(org.hibernate.boot.model.source.internal.hbm.MappingDocument, org.hibernate.boot.model.source.spi.AttributeSourceContainer, org.hibernate.boot.jaxb.hbm.spi.JaxbHbmManyToOneType, java.lang.String, org.hibernate.boot.model.source.spi.NaturalIdMutability);
    Code:
       0: aload_0
       1: aload_1
       2: aload         5
       4: invokespecial #2                  // Method org/hibernate/boot/model/source/internal/hbm/AbstractToOneAttributeSourceImpl."<init>":(Lorg/hibernate/boot/model/source/internal/hbm/MappingDocument;Lorg/hibernate/boot/model/source/spi/NaturalIdMutability;)V
       7: aload_0
       8: aload_3
       9: putfield      #3                  // Field manyToOneElement:Lorg/hibernate/boot/jaxb/hbm/spi/JaxbHbmManyToOneType;
      12: aload_0
      13: aload_3
      14: invokevirtual #4                  // Method org/hibernate/boot/jaxb/hbm/spi/JaxbHbmManyToOneType.getClazz:()Ljava/lang/String;
      17: ifnull        31
      20: aload_1
      21: aload_3
      22: invokevirtual #4                  // Method org/hibernate/boot/jaxb/hbm/spi/JaxbHbmManyToOneType.getClazz:()Ljava/lang/String;
      25: invokevirtual #5                  // Method org/hibernate/boot/model/source/internal/hbm/MappingDocument.qualifyClassName:(Ljava/lang/String;)Ljava/lang/String;
      28: goto          35
      31: aload_3
      32: invokevirtual #6                  // Method org/hibernate/boot/jaxb/hbm/spi/JaxbHbmManyToOneType.getEntityName:()Ljava/lang/String;
      35: putfield      #1                  // Field referencedTypeName:Ljava/lang/String;
      38: new           #7                  // class org/hibernate/boot/model/source/internal/hbm/SingularAttributeSourceManyToOneImpl$1
      41: dup
      42: aload_0
      43: invokespecial #8                  // Method org/hibernate/boot/model/source/internal/hbm/SingularAttributeSourceManyToOneImpl$1."<init>":(Lorg/hibernate/boot/model/source/internal/hbm/SingularAttributeSourceManyToOneImpl;)V
      46: astore        6
      48: aload_0
      49: new           #9                  // class org/hibernate/boot/model/source/internal/hbm/HibernateTypeSourceImpl
      52: dup
      53: aload         6
      55: invokespecial #10                 // Method org/hibernate/boot/model/source/internal/hbm/HibernateTypeSourceImpl."<init>":(Lorg/hibernate/boot/model/JavaTypeDescriptor;)V
      58: putfield      #11                 // Field typeSource:Lorg/hibernate/boot/model/source/internal/hbm/HibernateTypeSourceImpl;
      61: aload_0
      62: aload_1
      63: aload         4
      65: new           #12                 // class org/hibernate/boot/model/source/internal/hbm/ManyToOneAttributeColumnsAndFormulasSource
      68: dup
      69: aload_3
      70: invokespecial #13                 // Method org/hibernate/boot/model/source/internal/hbm/ManyToOneAttributeColumnsAndFormulasSource."<init>":(Lorg/hibernate/boot/jaxb/hbm/spi/JaxbHbmManyToOneType;)V
      73: invokestatic  #14                 // Method org/hibernate/boot/model/source/internal/hbm/RelationalValueSourceHelper.buildValueSources:(Lorg/hibernate/boot/model/source/internal/hbm/MappingDocument;Ljava/lang/String;Lorg/hibernate/boot/model/source/internal/hbm/RelationalValueSourceHelper$ColumnsAndFormulasSource;)Ljava/util/List;
      76: putfield      #15                 // Field relationalValueSources:Ljava/util/List;
      79: aload_0
      80: aload_2
      81: invokeinterface #16,  1           // InterfaceMethod org/hibernate/boot/model/source/spi/AttributeSourceContainer.getAttributeRoleBase:()Lorg/hibernate/boot/model/source/spi/AttributeRole;
      86: aload_3
      87: invokevirtual #17                 // Method org/hibernate/boot/jaxb/hbm/spi/JaxbHbmManyToOneType.getName:()Ljava/lang/String;
      90: invokevirtual #18                 // Method org/hibernate/boot/model/source/spi/AttributeRole.append:(Ljava/lang/String;)Lorg/hibernate/boot/model/source/spi/AttributeRole;
      93: putfield      #19                 // Field attributeRole:Lorg/hibernate/boot/model/source/spi/AttributeRole;
      96: aload_0
      97: aload_2
      98: invokeinterface #20,  1           // InterfaceMethod org/hibernate/boot/model/source/spi/AttributeSourceContainer.getAttributePathBase:()Lorg/hibernate/boot/model/source/spi/AttributePath;
     103: aload_3
     104: invokevirtual #17                 // Method org/hibernate/boot/jaxb/hbm/spi/JaxbHbmManyToOneType.getName:()Ljava/lang/String;
     107: invokevirtual #21                 // Method org/hibernate/boot/model/source/spi/AttributePath.append:(Ljava/lang/String;)Lorg/hibernate/boot/model/source/spi/AttributePath;
     110: putfield      #22                 // Field attributePath:Lorg/hibernate/boot/model/source/spi/AttributePath;
     113: aload_0
     114: aload_1
     115: invokevirtual #23                 // Method org/hibernate/boot/model/source/internal/hbm/MappingDocument.getMappingDefaults:()Lorg/hibernate/boot/spi/MappingDefaults;
     118: aload_3
     119: invokevirtual #24                 // Method org/hibernate/boot/jaxb/hbm/spi/JaxbHbmManyToOneType.getFetch:()Lorg/hibernate/boot/jaxb/hbm/spi/JaxbHbmFetchStyleEnum;
     122: aload_3
     123: invokevirtual #25                 // Method org/hibernate/boot/jaxb/hbm/spi/JaxbHbmManyToOneType.getOuterJoin:()Lorg/hibernate/boot/jaxb/hbm/spi/JaxbHbmOuterJoinEnum;
     126: aload_3
     127: invokevirtual #26                 // Method org/hibernate/boot/jaxb/hbm/spi/JaxbHbmManyToOneType.getLazy:()Lorg/hibernate/boot/jaxb/hbm/spi/JaxbHbmLazyWithNoProxyEnum;
     130: invokestatic  #27                 // Method org/hibernate/boot/model/source/internal/hbm/FetchCharacteristicsSingularAssociationImpl.interpretManyToOne:(Lorg/hibernate/boot/spi/MappingDefaults;Lorg/hibernate/boot/jaxb/hbm/spi/JaxbHbmFetchStyleEnum;Lorg/hibernate/boot/jaxb/hbm/spi/JaxbHbmOuterJoinEnum;Lorg/hibernate/boot/jaxb/hbm/spi/JaxbHbmLazyWithNoProxyEnum;)Lorg/hibernate/boot/model/source/internal/hbm/FetchCharacteristicsSingularAssociationImpl;
     133: putfield      #28                 // Field fetchCharacteristics:Lorg/hibernate/boot/model/source/internal/hbm/FetchCharacteristicsSingularAssociationImpl;
     136: aload_0
     137: aload_2
     138: invokeinterface #29,  1           // InterfaceMethod org/hibernate/boot/model/source/spi/AttributeSourceContainer.getToolingHintContext:()Lorg/hibernate/boot/model/source/spi/ToolingHintContext;
     143: aload_3
     144: invokestatic  #30                 // Method org/hibernate/boot/model/source/internal/hbm/Helper.collectToolingHints:(Lorg/hibernate/boot/model/source/spi/ToolingHintContext;Lorg/hibernate/boot/jaxb/hbm/spi/ToolingHintContainer;)Lorg/hibernate/boot/model/source/spi/ToolingHintContext;
     147: putfield      #31                 // Field toolingHintContext:Lorg/hibernate/boot/model/source/spi/ToolingHintContext;
     150: return

  public org.hibernate.boot.model.source.internal.hbm.XmlElementMetadata getSourceType();
    Code:
       0: getstatic     #32                 // Field org/hibernate/boot/model/source/internal/hbm/XmlElementMetadata.MANY_TO_ONE:Lorg/hibernate/boot/model/source/internal/hbm/XmlElementMetadata;
       3: areturn

  public java.lang.String getName();
    Code:
       0: aload_0
       1: getfield      #3                  // Field manyToOneElement:Lorg/hibernate/boot/jaxb/hbm/spi/JaxbHbmManyToOneType;
       4: invokevirtual #17                 // Method org/hibernate/boot/jaxb/hbm/spi/JaxbHbmManyToOneType.getName:()Ljava/lang/String;
       7: areturn

  public java.lang.String getXmlNodeName();
    Code:
       0: aload_0
       1: getfield      #3                  // Field manyToOneElement:Lorg/hibernate/boot/jaxb/hbm/spi/JaxbHbmManyToOneType;
       4: invokevirtual #33                 // Method org/hibernate/boot/jaxb/hbm/spi/JaxbHbmManyToOneType.getNode:()Ljava/lang/String;
       7: areturn

  public org.hibernate.boot.model.source.spi.AttributePath getAttributePath();
    Code:
       0: aload_0
       1: getfield      #22                 // Field attributePath:Lorg/hibernate/boot/model/source/spi/AttributePath;
       4: areturn

  public org.hibernate.boot.model.source.spi.AttributeRole getAttributeRole();
    Code:
       0: aload_0
       1: getfield      #19                 // Field attributeRole:Lorg/hibernate/boot/model/source/spi/AttributeRole;
       4: areturn

  public org.hibernate.boot.model.source.internal.hbm.HibernateTypeSourceImpl getTypeInformation();
    Code:
       0: aload_0
       1: getfield      #11                 // Field typeSource:Lorg/hibernate/boot/model/source/internal/hbm/HibernateTypeSourceImpl;
       4: areturn

  public java.lang.String getPropertyAccessorName();
    Code:
       0: aload_0
       1: getfield      #3                  // Field manyToOneElement:Lorg/hibernate/boot/jaxb/hbm/spi/JaxbHbmManyToOneType;
       4: invokevirtual #34                 // Method org/hibernate/boot/jaxb/hbm/spi/JaxbHbmManyToOneType.getAccess:()Ljava/lang/String;
       7: areturn

  public org.hibernate.boot.model.source.internal.hbm.FetchCharacteristicsSingularAssociationImpl getFetchCharacteristics();
    Code:
       0: aload_0
       1: getfield      #28                 // Field fetchCharacteristics:Lorg/hibernate/boot/model/source/internal/hbm/FetchCharacteristicsSingularAssociationImpl;
       4: areturn

  public boolean isIgnoreNotFound();
    Code:
       0: aload_0
       1: getfield      #3                  // Field manyToOneElement:Lorg/hibernate/boot/jaxb/hbm/spi/JaxbHbmManyToOneType;
       4: invokevirtual #35                 // Method org/hibernate/boot/jaxb/hbm/spi/JaxbHbmManyToOneType.getNotFound:()Lorg/hibernate/boot/jaxb/hbm/spi/JaxbHbmNotFoundEnum;
       7: ifnull        32
      10: ldc           #36                 // String ignore
      12: aload_0
      13: getfield      #3                  // Field manyToOneElement:Lorg/hibernate/boot/jaxb/hbm/spi/JaxbHbmManyToOneType;
      16: invokevirtual #35                 // Method org/hibernate/boot/jaxb/hbm/spi/JaxbHbmManyToOneType.getNotFound:()Lorg/hibernate/boot/jaxb/hbm/spi/JaxbHbmNotFoundEnum;
      19: invokevirtual #37                 // Method org/hibernate/boot/jaxb/hbm/spi/JaxbHbmNotFoundEnum.value:()Ljava/lang/String;
      22: invokevirtual #38                 // Method java/lang/String.equalsIgnoreCase:(Ljava/lang/String;)Z
      25: ifeq          32
      28: iconst_1
      29: goto          33
      32: iconst_0
      33: ireturn

  public boolean isIncludedInOptimisticLocking();
    Code:
       0: aload_0
       1: getfield      #3                  // Field manyToOneElement:Lorg/hibernate/boot/jaxb/hbm/spi/JaxbHbmManyToOneType;
       4: invokevirtual #39                 // Method org/hibernate/boot/jaxb/hbm/spi/JaxbHbmManyToOneType.isOptimisticLock:()Z
       7: ireturn

  public java.lang.String getCascadeStyleName();
    Code:
       0: aload_0
       1: getfield      #3                  // Field manyToOneElement:Lorg/hibernate/boot/jaxb/hbm/spi/JaxbHbmManyToOneType;
       4: invokevirtual #40                 // Method org/hibernate/boot/jaxb/hbm/spi/JaxbHbmManyToOneType.getCascade:()Ljava/lang/String;
       7: ifnonnull     15
      10: ldc           #41                 // String
      12: goto          22
      15: aload_0
      16: getfield      #3                  // Field manyToOneElement:Lorg/hibernate/boot/jaxb/hbm/spi/JaxbHbmManyToOneType;
      19: invokevirtual #40                 // Method org/hibernate/boot/jaxb/hbm/spi/JaxbHbmManyToOneType.getCascade:()Ljava/lang/String;
      22: areturn

  public org.hibernate.boot.model.source.spi.SingularAttributeNature getSingularAttributeNature();
    Code:
       0: getstatic     #42                 // Field org/hibernate/boot/model/source/spi/SingularAttributeNature.MANY_TO_ONE:Lorg/hibernate/boot/model/source/spi/SingularAttributeNature;
       3: areturn

  public java.lang.Boolean isInsertable();
    Code:
       0: aload_0
       1: getfield      #3                  // Field manyToOneElement:Lorg/hibernate/boot/jaxb/hbm/spi/JaxbHbmManyToOneType;
       4: invokevirtual #43                 // Method org/hibernate/boot/jaxb/hbm/spi/JaxbHbmManyToOneType.isInsert:()Z
       7: invokestatic  #44                 // Method java/lang/Boolean.valueOf:(Z)Ljava/lang/Boolean;
      10: areturn

  public java.lang.Boolean isUpdatable();
    Code:
       0: aload_0
       1: getfield      #3                  // Field manyToOneElement:Lorg/hibernate/boot/jaxb/hbm/spi/JaxbHbmManyToOneType;
       4: invokevirtual #45                 // Method org/hibernate/boot/jaxb/hbm/spi/JaxbHbmManyToOneType.isUpdate:()Z
       7: invokestatic  #44                 // Method java/lang/Boolean.valueOf:(Z)Ljava/lang/Boolean;
      10: areturn

  public boolean isBytecodeLazy();
    Code:
       0: iconst_0
       1: ireturn

  public java.lang.String getReferencedEntityAttributeName();
    Code:
       0: aload_0
       1: getfield      #3                  // Field manyToOneElement:Lorg/hibernate/boot/jaxb/hbm/spi/JaxbHbmManyToOneType;
       4: invokevirtual #46                 // Method org/hibernate/boot/jaxb/hbm/spi/JaxbHbmManyToOneType.getPropertyRef:()Ljava/lang/String;
       7: areturn

  public java.lang.String getReferencedEntityName();
    Code:
       0: aload_0
       1: getfield      #1                  // Field referencedTypeName:Ljava/lang/String;
       4: areturn

  public java.lang.Boolean isEmbedXml();
    Code:
       0: aload_0
       1: getfield      #3                  // Field manyToOneElement:Lorg/hibernate/boot/jaxb/hbm/spi/JaxbHbmManyToOneType;
       4: invokevirtual #47                 // Method org/hibernate/boot/jaxb/hbm/spi/JaxbHbmManyToOneType.isEmbedXml:()Ljava/lang/Boolean;
       7: areturn

  public boolean isUnique();
    Code:
       0: aload_0
       1: getfield      #3                  // Field manyToOneElement:Lorg/hibernate/boot/jaxb/hbm/spi/JaxbHbmManyToOneType;
       4: invokevirtual #48                 // Method org/hibernate/boot/jaxb/hbm/spi/JaxbHbmManyToOneType.isUnique:()Z
       7: ireturn

  public java.lang.String getExplicitForeignKeyName();
    Code:
       0: aload_0
       1: getfield      #3                  // Field manyToOneElement:Lorg/hibernate/boot/jaxb/hbm/spi/JaxbHbmManyToOneType;
       4: invokevirtual #49                 // Method org/hibernate/boot/jaxb/hbm/spi/JaxbHbmManyToOneType.getForeignKey:()Ljava/lang/String;
       7: areturn

  public boolean isCascadeDeleteEnabled();
    Code:
       0: iconst_0
       1: ireturn

  public org.hibernate.type.ForeignKeyDirection getForeignKeyDirection();
    Code:
       0: getstatic     #50                 // Field org/hibernate/type/ForeignKeyDirection.TO_PARENT:Lorg/hibernate/type/ForeignKeyDirection;
       3: areturn

  public java.util.List<org.hibernate.boot.model.source.spi.RelationalValueSource> getRelationalValueSources();
    Code:
       0: aload_0
       1: getfield      #15                 // Field relationalValueSources:Ljava/util/List;
       4: areturn

  public boolean areValuesIncludedInInsertByDefault();
    Code:
       0: iconst_1
       1: ireturn

  public boolean areValuesIncludedInUpdateByDefault();
    Code:
       0: iconst_1
       1: ireturn

  public boolean areValuesNullableByDefault();
    Code:
       0: iconst_1
       1: ireturn

  public org.hibernate.boot.model.source.spi.ToolingHintContext getToolingHintContext();
    Code:
       0: aload_0
       1: getfield      #31                 // Field toolingHintContext:Lorg/hibernate/boot/model/source/spi/ToolingHintContext;
       4: areturn

  public org.hibernate.boot.model.source.spi.FetchCharacteristicsSingularAssociation getFetchCharacteristics();
    Code:
       0: aload_0
       1: invokevirtual #51                 // Method getFetchCharacteristics:()Lorg/hibernate/boot/model/source/internal/hbm/FetchCharacteristicsSingularAssociationImpl;
       4: areturn

  public org.hibernate.boot.model.source.spi.HibernateTypeSource getTypeInformation();
    Code:
       0: aload_0
       1: invokevirtual #52                 // Method getTypeInformation:()Lorg/hibernate/boot/model/source/internal/hbm/HibernateTypeSourceImpl;
       4: areturn

  public org.hibernate.boot.model.source.spi.FetchCharacteristics getFetchCharacteristics();
    Code:
       0: aload_0
       1: invokevirtual #51                 // Method getFetchCharacteristics:()Lorg/hibernate/boot/model/source/internal/hbm/FetchCharacteristicsSingularAssociationImpl;
       4: areturn

  static java.lang.String access$000(org.hibernate.boot.model.source.internal.hbm.SingularAttributeSourceManyToOneImpl);
    Code:
       0: aload_0
       1: getfield      #1                  // Field referencedTypeName:Ljava/lang/String;
       4: areturn
}
