Compiled from "ObjectInputStreamWithCL.java"
class org.apache.axis2.context.externalize.ObjectInputStreamWithCL$2 implements java.security.PrivilegedExceptionAction {
  final org.apache.axis2.context.externalize.ObjectInputStreamWithCL this$0;

  org.apache.axis2.context.externalize.ObjectInputStreamWithCL$2(org.apache.axis2.context.externalize.ObjectInputStreamWithCL);
    Code:
       0: aload_0
       1: aload_1
       2: putfield      #1                  // Field this$0:Lorg/apache/axis2/context/externalize/ObjectInputStreamWithCL;
       5: aload_0
       6: invokespecial #2                  // Method java/lang/Object."<init>":()V
       9: return

  public java.lang.Object run() throws java.lang.Exception;
    Code:
       0: aconst_null
       1: astore_1
       2: aload_0
       3: getfield      #1                  // Field this$0:Lorg/apache/axis2/context/externalize/ObjectInputStreamWithCL;
       6: getfield      #3                  // Field org/apache/axis2/context/externalize/ObjectInputStreamWithCL.resolver:Lorg/apache/axis2/context/externalize/ObjectInputStreamWithCL$ClassResolver;
       9: ifnull        32
      12: aload_0
      13: getfield      #1                  // Field this$0:Lorg/apache/axis2/context/externalize/ObjectInputStreamWithCL;
      16: getfield      #3                  // Field org/apache/axis2/context/externalize/ObjectInputStreamWithCL.resolver:Lorg/apache/axis2/context/externalize/ObjectInputStreamWithCL$ClassResolver;
      19: aload_0
      20: getfield      #1                  // Field this$0:Lorg/apache/axis2/context/externalize/ObjectInputStreamWithCL;
      23: getfield      #4                  // Field org/apache/axis2/context/externalize/ObjectInputStreamWithCL.name:Ljava/lang/String;
      26: invokeinterface #5,  2            // InterfaceMethod org/apache/axis2/context/externalize/ObjectInputStreamWithCL$ClassResolver.resolveClass:(Ljava/lang/String;)Ljava/lang/Class;
      31: astore_1
      32: aload_1
      33: ifnonnull     58
      36: aload_0
      37: getfield      #1                  // Field this$0:Lorg/apache/axis2/context/externalize/ObjectInputStreamWithCL;
      40: aload_0
      41: getfield      #1                  // Field this$0:Lorg/apache/axis2/context/externalize/ObjectInputStreamWithCL;
      44: getfield      #4                  // Field org/apache/axis2/context/externalize/ObjectInputStreamWithCL.name:Ljava/lang/String;
      47: aload_0
      48: getfield      #1                  // Field this$0:Lorg/apache/axis2/context/externalize/ObjectInputStreamWithCL;
      51: getfield      #6                  // Field org/apache/axis2/context/externalize/ObjectInputStreamWithCL.classloader:Ljava/lang/ClassLoader;
      54: invokestatic  #7                  // Method org/apache/axis2/context/externalize/ObjectInputStreamWithCL.access$000:(Lorg/apache/axis2/context/externalize/ObjectInputStreamWithCL;Ljava/lang/String;Ljava/lang/ClassLoader;)Ljava/lang/Class;
      57: astore_1
      58: aload_1
      59: areturn
      60: astore_1
      61: invokestatic  #9                  // Method org/apache/axis2/context/externalize/ObjectInputStreamWithCL.access$100:()Ljava/util/HashMap;
      64: aload_0
      65: getfield      #1                  // Field this$0:Lorg/apache/axis2/context/externalize/ObjectInputStreamWithCL;
      68: getfield      #4                  // Field org/apache/axis2/context/externalize/ObjectInputStreamWithCL.name:Ljava/lang/String;
      71: invokevirtual #10                 // Method java/util/HashMap.get:(Ljava/lang/Object;)Ljava/lang/Object;
      74: checkcast     #11                 // class java/lang/Class
      77: astore_2
      78: aload_2
      79: ifnull        84
      82: aload_2
      83: areturn
      84: aload_1
      85: athrow
    Exception table:
       from    to  target type
           0    59    60   Class java/lang/ClassNotFoundException
}
