Compiled from "SafeObjectOutputStream.java"
class org.apache.axis2.context.externalize.SafeObjectOutputStream$MyOOS extends java.io.ObjectOutputStream {
  org.apache.axis2.context.externalize.SafeObjectOutputStream$MyBAOS baos;

  int dataOffset;

  org.apache.axis2.context.externalize.SafeObjectOutputStream$MyOOS(org.apache.axis2.context.externalize.SafeObjectOutputStream$MyBAOS) throws java.io.IOException;
    Code:
       0: aload_0
       1: aload_1
       2: invokespecial #1                  // Method java/io/ObjectOutputStream."<init>":(Ljava/io/OutputStream;)V
       5: aload_0
       6: invokespecial #2                  // Method java/io/ObjectOutputStream.flush:()V
       9: aload_0
      10: aload_1
      11: putfield      #3                  // Field baos:Lorg/apache/axis2/context/externalize/SafeObjectOutputStream$MyBAOS;
      14: aload_0
      15: aload_1
      16: invokevirtual #4                  // Method org/apache/axis2/context/externalize/SafeObjectOutputStream$MyBAOS.size:()I
      19: putfield      #5                  // Field dataOffset:I
      22: return

  public void reset() throws java.io.IOException;
    Code:
       0: aload_0
       1: invokespecial #6                  // Method java/io/ObjectOutputStream.reset:()V
       4: aload_0
       5: getfield      #3                  // Field baos:Lorg/apache/axis2/context/externalize/SafeObjectOutputStream$MyBAOS;
       8: aload_0
       9: getfield      #5                  // Field dataOffset:I
      12: invokevirtual #7                  // Method org/apache/axis2/context/externalize/SafeObjectOutputStream$MyBAOS.reset:(I)V
      15: return

  public void write(java.io.ObjectOutput) throws java.io.IOException;
    Code:
       0: aload_1
       1: invokeinterface #8,  1            // InterfaceMethod java/io/ObjectOutput.flush:()V
       6: aload_1
       7: aload_0
       8: getfield      #3                  // Field baos:Lorg/apache/axis2/context/externalize/SafeObjectOutputStream$MyBAOS;
      11: invokevirtual #4                  // Method org/apache/axis2/context/externalize/SafeObjectOutputStream$MyBAOS.size:()I
      14: invokeinterface #9,  2            // InterfaceMethod java/io/ObjectOutput.writeInt:(I)V
      19: aload_1
      20: aload_0
      21: getfield      #3                  // Field baos:Lorg/apache/axis2/context/externalize/SafeObjectOutputStream$MyBAOS;
      24: invokevirtual #10                 // Method org/apache/axis2/context/externalize/SafeObjectOutputStream$MyBAOS.getBytes:()[B
      27: iconst_0
      28: aload_0
      29: getfield      #3                  // Field baos:Lorg/apache/axis2/context/externalize/SafeObjectOutputStream$MyBAOS;
      32: invokevirtual #4                  // Method org/apache/axis2/context/externalize/SafeObjectOutputStream$MyBAOS.size:()I
      35: invokeinterface #11,  4           // InterfaceMethod java/io/ObjectOutput.write:([BII)V
      40: return
}
