Compiled from "BackupFailureException.java"
public class org.infinispan.xsite.BackupFailureException extends org.infinispan.remoting.RpcException {
  private java.util.Map<java.lang.String, java.lang.Throwable> failures;

  private java.lang.String localCacheName;

  public org.infinispan.xsite.BackupFailureException(java.lang.String);
    Code:
       0: aload_0
       1: invokespecial #1                  // Method org/infinispan/remoting/RpcException."<init>":()V
       4: aload_0
       5: aload_1
       6: putfield      #2                  // Field localCacheName:Ljava/lang/String;
       9: return

  public org.infinispan.xsite.BackupFailureException();
    Code:
       0: aload_0
       1: invokespecial #1                  // Method org/infinispan/remoting/RpcException."<init>":()V
       4: return

  public void addFailure(java.lang.String, java.lang.Throwable);
    Code:
       0: aload_1
       1: ifnull        39
       4: aload_2
       5: ifnull        39
       8: aload_0
       9: getfield      #3                  // Field failures:Ljava/util/Map;
      12: ifnonnull     27
      15: aload_0
      16: new           #4                  // class java/util/HashMap
      19: dup
      20: iconst_3
      21: invokespecial #5                  // Method java/util/HashMap."<init>":(I)V
      24: putfield      #3                  // Field failures:Ljava/util/Map;
      27: aload_0
      28: getfield      #3                  // Field failures:Ljava/util/Map;
      31: aload_1
      32: aload_2
      33: invokeinterface #6,  3            // InterfaceMethod java/util/Map.put:(Ljava/lang/Object;Ljava/lang/Object;)Ljava/lang/Object;
      38: pop
      39: return

  public java.lang.String getRemoteSiteNames();
    Code:
       0: aload_0
       1: getfield      #3                  // Field failures:Ljava/util/Map;
       4: ifnull        22
       7: aload_0
       8: getfield      #3                  // Field failures:Ljava/util/Map;
      11: invokeinterface #7,  1            // InterfaceMethod java/util/Map.keySet:()Ljava/util/Set;
      16: invokevirtual #8                  // Method java/lang/Object.toString:()Ljava/lang/String;
      19: goto          23
      22: aconst_null
      23: areturn

  public java.lang.String getLocalCacheName();
    Code:
       0: aload_0
       1: getfield      #2                  // Field localCacheName:Ljava/lang/String;
       4: areturn

  public java.lang.String toString();
    Code:
       0: aload_0
       1: getfield      #3                  // Field failures:Ljava/util/Map;
       4: ifnull        19
       7: aload_0
       8: getfield      #3                  // Field failures:Ljava/util/Map;
      11: invokeinterface #9,  1            // InterfaceMethod java/util/Map.isEmpty:()Z
      16: ifeq          24
      19: aload_0
      20: invokespecial #10                 // Method org/infinispan/remoting/RpcException.toString:()Ljava/lang/String;
      23: areturn
      24: new           #11                 // class java/lang/StringBuilder
      27: dup
      28: new           #11                 // class java/lang/StringBuilder
      31: dup
      32: invokespecial #12                 // Method java/lang/StringBuilder."<init>":()V
      35: ldc           #13                 // String The local cache
      37: invokevirtual #14                 // Method java/lang/StringBuilder.append:(Ljava/lang/String;)Ljava/lang/StringBuilder;
      40: aload_0
      41: getfield      #2                  // Field localCacheName:Ljava/lang/String;
      44: invokevirtual #14                 // Method java/lang/StringBuilder.append:(Ljava/lang/String;)Ljava/lang/StringBuilder;
      47: ldc           #15                 // String  failed to backup data to the remote sites:\n
      49: invokevirtual #14                 // Method java/lang/StringBuilder.append:(Ljava/lang/String;)Ljava/lang/StringBuilder;
      52: invokevirtual #16                 // Method java/lang/StringBuilder.toString:()Ljava/lang/String;
      55: invokespecial #17                 // Method java/lang/StringBuilder."<init>":(Ljava/lang/String;)V
      58: astore_1
      59: aload_0
      60: getfield      #3                  // Field failures:Ljava/util/Map;
      63: invokeinterface #18,  1           // InterfaceMethod java/util/Map.entrySet:()Ljava/util/Set;
      68: invokeinterface #19,  1           // InterfaceMethod java/util/Set.iterator:()Ljava/util/Iterator;
      73: astore_2
      74: aload_2
      75: invokeinterface #20,  1           // InterfaceMethod java/util/Iterator.hasNext:()Z
      80: ifeq          129
      83: aload_2
      84: invokeinterface #21,  1           // InterfaceMethod java/util/Iterator.next:()Ljava/lang/Object;
      89: checkcast     #22                 // class java/util/Map$Entry
      92: astore_3
      93: aload_1
      94: aload_3
      95: invokeinterface #23,  1           // InterfaceMethod java/util/Map$Entry.getKey:()Ljava/lang/Object;
     100: checkcast     #24                 // class java/lang/String
     103: invokevirtual #14                 // Method java/lang/StringBuilder.append:(Ljava/lang/String;)Ljava/lang/StringBuilder;
     106: ldc           #25                 // String :
     108: invokevirtual #14                 // Method java/lang/StringBuilder.append:(Ljava/lang/String;)Ljava/lang/StringBuilder;
     111: aload_3
     112: invokeinterface #26,  1           // InterfaceMethod java/util/Map$Entry.getValue:()Ljava/lang/Object;
     117: invokevirtual #27                 // Method java/lang/StringBuilder.append:(Ljava/lang/Object;)Ljava/lang/StringBuilder;
     120: ldc           #28                 // String \n
     122: invokevirtual #14                 // Method java/lang/StringBuilder.append:(Ljava/lang/String;)Ljava/lang/StringBuilder;
     125: pop
     126: goto          74
     129: aload_1
     130: invokevirtual #16                 // Method java/lang/StringBuilder.toString:()Ljava/lang/String;
     133: areturn
}
