Compiled from "QueryType.java"
public final class io.manbang.ebatis.core.annotation.QueryType extends java.lang.Enum<io.manbang.ebatis.core.annotation.QueryType> {
  public static final io.manbang.ebatis.core.annotation.QueryType AUTO;

  public static final io.manbang.ebatis.core.annotation.QueryType BOOL;

  public static final io.manbang.ebatis.core.annotation.QueryType FUNCTION_SCORE;

  public static final io.manbang.ebatis.core.annotation.QueryType CONSTANT_SCORE;

  public static final io.manbang.ebatis.core.annotation.QueryType BOOSTING;

  public static final io.manbang.ebatis.core.annotation.QueryType DIS_MAX;

  public static final io.manbang.ebatis.core.annotation.QueryType FIELD;

  public static final io.manbang.ebatis.core.annotation.QueryType FUZZY;

  public static final io.manbang.ebatis.core.annotation.QueryType GEO_SHAPE;

  public static final io.manbang.ebatis.core.annotation.QueryType GEO_DISTANCE;

  public static final io.manbang.ebatis.core.annotation.QueryType GEO_POLYGON;

  public static final io.manbang.ebatis.core.annotation.QueryType GEO_BOUNDING_BOX;

  public static final io.manbang.ebatis.core.annotation.QueryType HAS_CHILD;

  public static final io.manbang.ebatis.core.annotation.QueryType HAS_PARENT;

  public static final io.manbang.ebatis.core.annotation.QueryType INDICES;

  public static final io.manbang.ebatis.core.annotation.QueryType MLT;

  public static final io.manbang.ebatis.core.annotation.QueryType MULTI_MATCH;

  public static final io.manbang.ebatis.core.annotation.QueryType NESTED;

  public static final io.manbang.ebatis.core.annotation.QueryType PREFIX;

  public static final io.manbang.ebatis.core.annotation.QueryType QUERY_STRING;

  public static final io.manbang.ebatis.core.annotation.QueryType RANGE;

  public static final io.manbang.ebatis.core.annotation.QueryType SCRIPT;

  public static final io.manbang.ebatis.core.annotation.QueryType IDS;

  public static final io.manbang.ebatis.core.annotation.QueryType TERM;

  public static final io.manbang.ebatis.core.annotation.QueryType TERMS;

  public static final io.manbang.ebatis.core.annotation.QueryType EXISTS;

  public static final io.manbang.ebatis.core.annotation.QueryType MATCH_ALL;

  public static final io.manbang.ebatis.core.annotation.QueryType MATCH;

  public static final io.manbang.ebatis.core.annotation.QueryType MATCH_PHRASE;

  public static final io.manbang.ebatis.core.annotation.QueryType MATCH_PHRASE_PREFIX;

  public static final io.manbang.ebatis.core.annotation.QueryType SPAN_CONTAINING;

  public static final io.manbang.ebatis.core.annotation.QueryType SPAN_FIRST;

  public static final io.manbang.ebatis.core.annotation.QueryType SPAN_NEAR;

  public static final io.manbang.ebatis.core.annotation.QueryType SPAN_NOT;

  public static final io.manbang.ebatis.core.annotation.QueryType SPAN_OR;

  public static final io.manbang.ebatis.core.annotation.QueryType SPAN_TERM;

  public static final io.manbang.ebatis.core.annotation.QueryType SPAN_WITHIN;

  public static final io.manbang.ebatis.core.annotation.QueryType WILDCARD;

  private final io.manbang.ebatis.core.builder.QueryBuilderFactory queryBuilderFactory;

  private static final io.manbang.ebatis.core.annotation.QueryType[] $VALUES;

  public static io.manbang.ebatis.core.annotation.QueryType[] values();
    Code:
       0: getstatic     #1                  // Field $VALUES:[Lio/manbang/ebatis/core/annotation/QueryType;
       3: invokevirtual #2                  // Method "[Lio/manbang/ebatis/core/annotation/QueryType;".clone:()Ljava/lang/Object;
       6: checkcast     #3                  // class "[Lio/manbang/ebatis/core/annotation/QueryType;"
       9: areturn

  public static io.manbang.ebatis.core.annotation.QueryType valueOf(java.lang.String);
    Code:
       0: ldc           #4                  // class io/manbang/ebatis/core/annotation/QueryType
       2: aload_0
       3: invokestatic  #5                  // Method java/lang/Enum.valueOf:(Ljava/lang/Class;Ljava/lang/String;)Ljava/lang/Enum;
       6: checkcast     #4                  // class io/manbang/ebatis/core/annotation/QueryType
       9: areturn

  private io.manbang.ebatis.core.annotation.QueryType(io.manbang.ebatis.core.builder.QueryBuilderFactory);
    Code:
       0: aload_0
       1: aload_1
       2: iload_2
       3: invokespecial #6                  // Method java/lang/Enum."<init>":(Ljava/lang/String;I)V
       6: aload_0
       7: aload_3
       8: putfield      #7                  // Field queryBuilderFactory:Lio/manbang/ebatis/core/builder/QueryBuilderFactory;
      11: return

  public io.manbang.ebatis.core.builder.QueryBuilderFactory getQueryBuilderFactory();
    Code:
       0: aload_0
       1: getfield      #7                  // Field queryBuilderFactory:Lio/manbang/ebatis/core/builder/QueryBuilderFactory;
       4: areturn

  public org.elasticsearch.index.query.QueryBuilder createBuilder(io.manbang.ebatis.core.meta.FieldMeta, java.lang.Object);
    Code:
       0: aload_0
       1: getfield      #7                  // Field queryBuilderFactory:Lio/manbang/ebatis/core/builder/QueryBuilderFactory;
       4: aload_1
       5: aload_2
       6: invokeinterface #8,  3            // InterfaceMethod io/manbang/ebatis/core/builder/QueryBuilderFactory.create:(Lio/manbang/ebatis/core/meta/ConditionMeta;Ljava/lang/Object;)Lorg/elasticsearch/index/query/QueryBuilder;
      11: areturn

  static {};
    Code:
       0: new           #4                  // class io/manbang/ebatis/core/annotation/QueryType
       3: dup
       4: ldc           #9                  // String AUTO
       6: iconst_0
       7: invokestatic  #10                 // InterfaceMethod io/manbang/ebatis/core/builder/QueryBuilderFactory.auto:()Lio/manbang/ebatis/core/builder/QueryBuilderFactory;
      10: invokespecial #11                 // Method "<init>":(Ljava/lang/String;ILio/manbang/ebatis/core/builder/QueryBuilderFactory;)V
      13: putstatic     #12                 // Field AUTO:Lio/manbang/ebatis/core/annotation/QueryType;
      16: new           #4                  // class io/manbang/ebatis/core/annotation/QueryType
      19: dup
      20: ldc           #13                 // String BOOL
      22: iconst_1
      23: invokestatic  #14                 // InterfaceMethod io/manbang/ebatis/core/builder/QueryBuilderFactory.bool:()Lio/manbang/ebatis/core/builder/QueryBuilderFactory;
      26: invokespecial #11                 // Method "<init>":(Ljava/lang/String;ILio/manbang/ebatis/core/builder/QueryBuilderFactory;)V
      29: putstatic     #15                 // Field BOOL:Lio/manbang/ebatis/core/annotation/QueryType;
      32: new           #4                  // class io/manbang/ebatis/core/annotation/QueryType
      35: dup
      36: ldc           #16                 // String FUNCTION_SCORE
      38: iconst_2
      39: invokestatic  #17                 // InterfaceMethod io/manbang/ebatis/core/builder/QueryBuilderFactory.functionScore:()Lio/manbang/ebatis/core/builder/QueryBuilderFactory;
      42: invokespecial #11                 // Method "<init>":(Ljava/lang/String;ILio/manbang/ebatis/core/builder/QueryBuilderFactory;)V
      45: putstatic     #18                 // Field FUNCTION_SCORE:Lio/manbang/ebatis/core/annotation/QueryType;
      48: new           #4                  // class io/manbang/ebatis/core/annotation/QueryType
      51: dup
      52: ldc           #19                 // String CONSTANT_SCORE
      54: iconst_3
      55: invokestatic  #17                 // InterfaceMethod io/manbang/ebatis/core/builder/QueryBuilderFactory.functionScore:()Lio/manbang/ebatis/core/builder/QueryBuilderFactory;
      58: invokespecial #11                 // Method "<init>":(Ljava/lang/String;ILio/manbang/ebatis/core/builder/QueryBuilderFactory;)V
      61: putstatic     #20                 // Field CONSTANT_SCORE:Lio/manbang/ebatis/core/annotation/QueryType;
      64: new           #4                  // class io/manbang/ebatis/core/annotation/QueryType
      67: dup
      68: ldc           #21                 // String BOOSTING
      70: iconst_4
      71: invokestatic  #22                 // InterfaceMethod io/manbang/ebatis/core/builder/QueryBuilderFactory.boosting:()Lio/manbang/ebatis/core/builder/QueryBuilderFactory;
      74: invokespecial #11                 // Method "<init>":(Ljava/lang/String;ILio/manbang/ebatis/core/builder/QueryBuilderFactory;)V
      77: putstatic     #23                 // Field BOOSTING:Lio/manbang/ebatis/core/annotation/QueryType;
      80: new           #4                  // class io/manbang/ebatis/core/annotation/QueryType
      83: dup
      84: ldc           #24                 // String DIS_MAX
      86: iconst_5
      87: aconst_null
      88: invokespecial #11                 // Method "<init>":(Ljava/lang/String;ILio/manbang/ebatis/core/builder/QueryBuilderFactory;)V
      91: putstatic     #25                 // Field DIS_MAX:Lio/manbang/ebatis/core/annotation/QueryType;
      94: new           #4                  // class io/manbang/ebatis/core/annotation/QueryType
      97: dup
      98: ldc           #26                 // String FIELD
     100: bipush        6
     102: aconst_null
     103: invokespecial #11                 // Method "<init>":(Ljava/lang/String;ILio/manbang/ebatis/core/builder/QueryBuilderFactory;)V
     106: putstatic     #27                 // Field FIELD:Lio/manbang/ebatis/core/annotation/QueryType;
     109: new           #4                  // class io/manbang/ebatis/core/annotation/QueryType
     112: dup
     113: ldc           #28                 // String FUZZY
     115: bipush        7
     117: invokestatic  #29                 // InterfaceMethod io/manbang/ebatis/core/builder/QueryBuilderFactory.fuzzy:()Lio/manbang/ebatis/core/builder/QueryBuilderFactory;
     120: invokespecial #11                 // Method "<init>":(Ljava/lang/String;ILio/manbang/ebatis/core/builder/QueryBuilderFactory;)V
     123: putstatic     #30                 // Field FUZZY:Lio/manbang/ebatis/core/annotation/QueryType;
     126: new           #4                  // class io/manbang/ebatis/core/annotation/QueryType
     129: dup
     130: ldc           #31                 // String GEO_SHAPE
     132: bipush        8
     134: invokestatic  #32                 // InterfaceMethod io/manbang/ebatis/core/builder/QueryBuilderFactory.geoShape:()Lio/manbang/ebatis/core/builder/QueryBuilderFactory;
     137: invokespecial #11                 // Method "<init>":(Ljava/lang/String;ILio/manbang/ebatis/core/builder/QueryBuilderFactory;)V
     140: putstatic     #33                 // Field GEO_SHAPE:Lio/manbang/ebatis/core/annotation/QueryType;
     143: new           #4                  // class io/manbang/ebatis/core/annotation/QueryType
     146: dup
     147: ldc           #34                 // String GEO_DISTANCE
     149: bipush        9
     151: invokestatic  #35                 // InterfaceMethod io/manbang/ebatis/core/builder/QueryBuilderFactory.geoDistance:()Lio/manbang/ebatis/core/builder/QueryBuilderFactory;
     154: invokespecial #11                 // Method "<init>":(Ljava/lang/String;ILio/manbang/ebatis/core/builder/QueryBuilderFactory;)V
     157: putstatic     #36                 // Field GEO_DISTANCE:Lio/manbang/ebatis/core/annotation/QueryType;
     160: new           #4                  // class io/manbang/ebatis/core/annotation/QueryType
     163: dup
     164: ldc           #37                 // String GEO_POLYGON
     166: bipush        10
     168: aconst_null
     169: invokespecial #11                 // Method "<init>":(Ljava/lang/String;ILio/manbang/ebatis/core/builder/QueryBuilderFactory;)V
     172: putstatic     #38                 // Field GEO_POLYGON:Lio/manbang/ebatis/core/annotation/QueryType;
     175: new           #4                  // class io/manbang/ebatis/core/annotation/QueryType
     178: dup
     179: ldc           #39                 // String GEO_BOUNDING_BOX
     181: bipush        11
     183: aconst_null
     184: invokespecial #11                 // Method "<init>":(Ljava/lang/String;ILio/manbang/ebatis/core/builder/QueryBuilderFactory;)V
     187: putstatic     #40                 // Field GEO_BOUNDING_BOX:Lio/manbang/ebatis/core/annotation/QueryType;
     190: new           #4                  // class io/manbang/ebatis/core/annotation/QueryType
     193: dup
     194: ldc           #41                 // String HAS_CHILD
     196: bipush        12
     198: aconst_null
     199: invokespecial #11                 // Method "<init>":(Ljava/lang/String;ILio/manbang/ebatis/core/builder/QueryBuilderFactory;)V
     202: putstatic     #42                 // Field HAS_CHILD:Lio/manbang/ebatis/core/annotation/QueryType;
     205: new           #4                  // class io/manbang/ebatis/core/annotation/QueryType
     208: dup
     209: ldc           #43                 // String HAS_PARENT
     211: bipush        13
     213: aconst_null
     214: invokespecial #11                 // Method "<init>":(Ljava/lang/String;ILio/manbang/ebatis/core/builder/QueryBuilderFactory;)V
     217: putstatic     #44                 // Field HAS_PARENT:Lio/manbang/ebatis/core/annotation/QueryType;
     220: new           #4                  // class io/manbang/ebatis/core/annotation/QueryType
     223: dup
     224: ldc           #45                 // String INDICES
     226: bipush        14
     228: aconst_null
     229: invokespecial #11                 // Method "<init>":(Ljava/lang/String;ILio/manbang/ebatis/core/builder/QueryBuilderFactory;)V
     232: putstatic     #46                 // Field INDICES:Lio/manbang/ebatis/core/annotation/QueryType;
     235: new           #4                  // class io/manbang/ebatis/core/annotation/QueryType
     238: dup
     239: ldc           #47                 // String MLT
     241: bipush        15
     243: aconst_null
     244: invokespecial #11                 // Method "<init>":(Ljava/lang/String;ILio/manbang/ebatis/core/builder/QueryBuilderFactory;)V
     247: putstatic     #48                 // Field MLT:Lio/manbang/ebatis/core/annotation/QueryType;
     250: new           #4                  // class io/manbang/ebatis/core/annotation/QueryType
     253: dup
     254: ldc           #49                 // String MULTI_MATCH
     256: bipush        16
     258: aconst_null
     259: invokespecial #11                 // Method "<init>":(Ljava/lang/String;ILio/manbang/ebatis/core/builder/QueryBuilderFactory;)V
     262: putstatic     #50                 // Field MULTI_MATCH:Lio/manbang/ebatis/core/annotation/QueryType;
     265: new           #4                  // class io/manbang/ebatis/core/annotation/QueryType
     268: dup
     269: ldc           #51                 // String NESTED
     271: bipush        17
     273: invokestatic  #52                 // InterfaceMethod io/manbang/ebatis/core/builder/QueryBuilderFactory.nested:()Lio/manbang/ebatis/core/builder/QueryBuilderFactory;
     276: invokespecial #11                 // Method "<init>":(Ljava/lang/String;ILio/manbang/ebatis/core/builder/QueryBuilderFactory;)V
     279: putstatic     #53                 // Field NESTED:Lio/manbang/ebatis/core/annotation/QueryType;
     282: new           #4                  // class io/manbang/ebatis/core/annotation/QueryType
     285: dup
     286: ldc           #54                 // String PREFIX
     288: bipush        18
     290: aconst_null
     291: invokespecial #11                 // Method "<init>":(Ljava/lang/String;ILio/manbang/ebatis/core/builder/QueryBuilderFactory;)V
     294: putstatic     #55                 // Field PREFIX:Lio/manbang/ebatis/core/annotation/QueryType;
     297: new           #4                  // class io/manbang/ebatis/core/annotation/QueryType
     300: dup
     301: ldc           #56                 // String QUERY_STRING
     303: bipush        19
     305: aconst_null
     306: invokespecial #11                 // Method "<init>":(Ljava/lang/String;ILio/manbang/ebatis/core/builder/QueryBuilderFactory;)V
     309: putstatic     #57                 // Field QUERY_STRING:Lio/manbang/ebatis/core/annotation/QueryType;
     312: new           #4                  // class io/manbang/ebatis/core/annotation/QueryType
     315: dup
     316: ldc           #58                 // String RANGE
     318: bipush        20
     320: aconst_null
     321: invokespecial #11                 // Method "<init>":(Ljava/lang/String;ILio/manbang/ebatis/core/builder/QueryBuilderFactory;)V
     324: putstatic     #59                 // Field RANGE:Lio/manbang/ebatis/core/annotation/QueryType;
     327: new           #4                  // class io/manbang/ebatis/core/annotation/QueryType
     330: dup
     331: ldc           #60                 // String SCRIPT
     333: bipush        21
     335: aconst_null
     336: invokespecial #11                 // Method "<init>":(Ljava/lang/String;ILio/manbang/ebatis/core/builder/QueryBuilderFactory;)V
     339: putstatic     #61                 // Field SCRIPT:Lio/manbang/ebatis/core/annotation/QueryType;
     342: new           #4                  // class io/manbang/ebatis/core/annotation/QueryType
     345: dup
     346: ldc           #62                 // String IDS
     348: bipush        22
     350: aconst_null
     351: invokespecial #11                 // Method "<init>":(Ljava/lang/String;ILio/manbang/ebatis/core/builder/QueryBuilderFactory;)V
     354: putstatic     #63                 // Field IDS:Lio/manbang/ebatis/core/annotation/QueryType;
     357: new           #4                  // class io/manbang/ebatis/core/annotation/QueryType
     360: dup
     361: ldc           #64                 // String TERM
     363: bipush        23
     365: invokestatic  #65                 // InterfaceMethod io/manbang/ebatis/core/builder/QueryBuilderFactory.term:()Lio/manbang/ebatis/core/builder/QueryBuilderFactory;
     368: invokespecial #11                 // Method "<init>":(Ljava/lang/String;ILio/manbang/ebatis/core/builder/QueryBuilderFactory;)V
     371: putstatic     #66                 // Field TERM:Lio/manbang/ebatis/core/annotation/QueryType;
     374: new           #4                  // class io/manbang/ebatis/core/annotation/QueryType
     377: dup
     378: ldc           #67                 // String TERMS
     380: bipush        24
     382: invokestatic  #68                 // InterfaceMethod io/manbang/ebatis/core/builder/QueryBuilderFactory.terms:()Lio/manbang/ebatis/core/builder/QueryBuilderFactory;
     385: invokespecial #11                 // Method "<init>":(Ljava/lang/String;ILio/manbang/ebatis/core/builder/QueryBuilderFactory;)V
     388: putstatic     #69                 // Field TERMS:Lio/manbang/ebatis/core/annotation/QueryType;
     391: new           #4                  // class io/manbang/ebatis/core/annotation/QueryType
     394: dup
     395: ldc           #70                 // String EXISTS
     397: bipush        25
     399: invokestatic  #71                 // InterfaceMethod io/manbang/ebatis/core/builder/QueryBuilderFactory.exists:()Lio/manbang/ebatis/core/builder/QueryBuilderFactory;
     402: invokespecial #11                 // Method "<init>":(Ljava/lang/String;ILio/manbang/ebatis/core/builder/QueryBuilderFactory;)V
     405: putstatic     #72                 // Field EXISTS:Lio/manbang/ebatis/core/annotation/QueryType;
     408: new           #4                  // class io/manbang/ebatis/core/annotation/QueryType
     411: dup
     412: ldc           #73                 // String MATCH_ALL
     414: bipush        26
     416: invokestatic  #74                 // InterfaceMethod io/manbang/ebatis/core/builder/QueryBuilderFactory.matchAll:()Lio/manbang/ebatis/core/builder/QueryBuilderFactory;
     419: invokespecial #11                 // Method "<init>":(Ljava/lang/String;ILio/manbang/ebatis/core/builder/QueryBuilderFactory;)V
     422: putstatic     #75                 // Field MATCH_ALL:Lio/manbang/ebatis/core/annotation/QueryType;
     425: new           #4                  // class io/manbang/ebatis/core/annotation/QueryType
     428: dup
     429: ldc           #76                 // String MATCH
     431: bipush        27
     433: invokestatic  #77                 // InterfaceMethod io/manbang/ebatis/core/builder/QueryBuilderFactory.match:()Lio/manbang/ebatis/core/builder/QueryBuilderFactory;
     436: invokespecial #11                 // Method "<init>":(Ljava/lang/String;ILio/manbang/ebatis/core/builder/QueryBuilderFactory;)V
     439: putstatic     #78                 // Field MATCH:Lio/manbang/ebatis/core/annotation/QueryType;
     442: new           #4                  // class io/manbang/ebatis/core/annotation/QueryType
     445: dup
     446: ldc           #79                 // String MATCH_PHRASE
     448: bipush        28
     450: invokestatic  #80                 // InterfaceMethod io/manbang/ebatis/core/builder/QueryBuilderFactory.matchPhrase:()Lio/manbang/ebatis/core/builder/QueryBuilderFactory;
     453: invokespecial #11                 // Method "<init>":(Ljava/lang/String;ILio/manbang/ebatis/core/builder/QueryBuilderFactory;)V
     456: putstatic     #81                 // Field MATCH_PHRASE:Lio/manbang/ebatis/core/annotation/QueryType;
     459: new           #4                  // class io/manbang/ebatis/core/annotation/QueryType
     462: dup
     463: ldc           #82                 // String MATCH_PHRASE_PREFIX
     465: bipush        29
     467: invokestatic  #83                 // InterfaceMethod io/manbang/ebatis/core/builder/QueryBuilderFactory.matchPhrasePrefix:()Lio/manbang/ebatis/core/builder/QueryBuilderFactory;
     470: invokespecial #11                 // Method "<init>":(Ljava/lang/String;ILio/manbang/ebatis/core/builder/QueryBuilderFactory;)V
     473: putstatic     #84                 // Field MATCH_PHRASE_PREFIX:Lio/manbang/ebatis/core/annotation/QueryType;
     476: new           #4                  // class io/manbang/ebatis/core/annotation/QueryType
     479: dup
     480: ldc           #85                 // String SPAN_CONTAINING
     482: bipush        30
     484: aconst_null
     485: invokespecial #11                 // Method "<init>":(Ljava/lang/String;ILio/manbang/ebatis/core/builder/QueryBuilderFactory;)V
     488: putstatic     #86                 // Field SPAN_CONTAINING:Lio/manbang/ebatis/core/annotation/QueryType;
     491: new           #4                  // class io/manbang/ebatis/core/annotation/QueryType
     494: dup
     495: ldc           #87                 // String SPAN_FIRST
     497: bipush        31
     499: aconst_null
     500: invokespecial #11                 // Method "<init>":(Ljava/lang/String;ILio/manbang/ebatis/core/builder/QueryBuilderFactory;)V
     503: putstatic     #88                 // Field SPAN_FIRST:Lio/manbang/ebatis/core/annotation/QueryType;
     506: new           #4                  // class io/manbang/ebatis/core/annotation/QueryType
     509: dup
     510: ldc           #89                 // String SPAN_NEAR
     512: bipush        32
     514: aconst_null
     515: invokespecial #11                 // Method "<init>":(Ljava/lang/String;ILio/manbang/ebatis/core/builder/QueryBuilderFactory;)V
     518: putstatic     #90                 // Field SPAN_NEAR:Lio/manbang/ebatis/core/annotation/QueryType;
     521: new           #4                  // class io/manbang/ebatis/core/annotation/QueryType
     524: dup
     525: ldc           #91                 // String SPAN_NOT
     527: bipush        33
     529: aconst_null
     530: invokespecial #11                 // Method "<init>":(Ljava/lang/String;ILio/manbang/ebatis/core/builder/QueryBuilderFactory;)V
     533: putstatic     #92                 // Field SPAN_NOT:Lio/manbang/ebatis/core/annotation/QueryType;
     536: new           #4                  // class io/manbang/ebatis/core/annotation/QueryType
     539: dup
     540: ldc           #93                 // String SPAN_OR
     542: bipush        34
     544: aconst_null
     545: invokespecial #11                 // Method "<init>":(Ljava/lang/String;ILio/manbang/ebatis/core/builder/QueryBuilderFactory;)V
     548: putstatic     #94                 // Field SPAN_OR:Lio/manbang/ebatis/core/annotation/QueryType;
     551: new           #4                  // class io/manbang/ebatis/core/annotation/QueryType
     554: dup
     555: ldc           #95                 // String SPAN_TERM
     557: bipush        35
     559: aconst_null
     560: invokespecial #11                 // Method "<init>":(Ljava/lang/String;ILio/manbang/ebatis/core/builder/QueryBuilderFactory;)V
     563: putstatic     #96                 // Field SPAN_TERM:Lio/manbang/ebatis/core/annotation/QueryType;
     566: new           #4                  // class io/manbang/ebatis/core/annotation/QueryType
     569: dup
     570: ldc           #97                 // String SPAN_WITHIN
     572: bipush        36
     574: aconst_null
     575: invokespecial #11                 // Method "<init>":(Ljava/lang/String;ILio/manbang/ebatis/core/builder/QueryBuilderFactory;)V
     578: putstatic     #98                 // Field SPAN_WITHIN:Lio/manbang/ebatis/core/annotation/QueryType;
     581: new           #4                  // class io/manbang/ebatis/core/annotation/QueryType
     584: dup
     585: ldc           #99                 // String WILDCARD
     587: bipush        37
     589: invokestatic  #100                // InterfaceMethod io/manbang/ebatis/core/builder/QueryBuilderFactory.wildCard:()Lio/manbang/ebatis/core/builder/QueryBuilderFactory;
     592: invokespecial #11                 // Method "<init>":(Ljava/lang/String;ILio/manbang/ebatis/core/builder/QueryBuilderFactory;)V
     595: putstatic     #101                // Field WILDCARD:Lio/manbang/ebatis/core/annotation/QueryType;
     598: bipush        38
     600: anewarray     #4                  // class io/manbang/ebatis/core/annotation/QueryType
     603: dup
     604: iconst_0
     605: getstatic     #12                 // Field AUTO:Lio/manbang/ebatis/core/annotation/QueryType;
     608: aastore
     609: dup
     610: iconst_1
     611: getstatic     #15                 // Field BOOL:Lio/manbang/ebatis/core/annotation/QueryType;
     614: aastore
     615: dup
     616: iconst_2
     617: getstatic     #18                 // Field FUNCTION_SCORE:Lio/manbang/ebatis/core/annotation/QueryType;
     620: aastore
     621: dup
     622: iconst_3
     623: getstatic     #20                 // Field CONSTANT_SCORE:Lio/manbang/ebatis/core/annotation/QueryType;
     626: aastore
     627: dup
     628: iconst_4
     629: getstatic     #23                 // Field BOOSTING:Lio/manbang/ebatis/core/annotation/QueryType;
     632: aastore
     633: dup
     634: iconst_5
     635: getstatic     #25                 // Field DIS_MAX:Lio/manbang/ebatis/core/annotation/QueryType;
     638: aastore
     639: dup
     640: bipush        6
     642: getstatic     #27                 // Field FIELD:Lio/manbang/ebatis/core/annotation/QueryType;
     645: aastore
     646: dup
     647: bipush        7
     649: getstatic     #30                 // Field FUZZY:Lio/manbang/ebatis/core/annotation/QueryType;
     652: aastore
     653: dup
     654: bipush        8
     656: getstatic     #33                 // Field GEO_SHAPE:Lio/manbang/ebatis/core/annotation/QueryType;
     659: aastore
     660: dup
     661: bipush        9
     663: getstatic     #36                 // Field GEO_DISTANCE:Lio/manbang/ebatis/core/annotation/QueryType;
     666: aastore
     667: dup
     668: bipush        10
     670: getstatic     #38                 // Field GEO_POLYGON:Lio/manbang/ebatis/core/annotation/QueryType;
     673: aastore
     674: dup
     675: bipush        11
     677: getstatic     #40                 // Field GEO_BOUNDING_BOX:Lio/manbang/ebatis/core/annotation/QueryType;
     680: aastore
     681: dup
     682: bipush        12
     684: getstatic     #42                 // Field HAS_CHILD:Lio/manbang/ebatis/core/annotation/QueryType;
     687: aastore
     688: dup
     689: bipush        13
     691: getstatic     #44                 // Field HAS_PARENT:Lio/manbang/ebatis/core/annotation/QueryType;
     694: aastore
     695: dup
     696: bipush        14
     698: getstatic     #46                 // Field INDICES:Lio/manbang/ebatis/core/annotation/QueryType;
     701: aastore
     702: dup
     703: bipush        15
     705: getstatic     #48                 // Field MLT:Lio/manbang/ebatis/core/annotation/QueryType;
     708: aastore
     709: dup
     710: bipush        16
     712: getstatic     #50                 // Field MULTI_MATCH:Lio/manbang/ebatis/core/annotation/QueryType;
     715: aastore
     716: dup
     717: bipush        17
     719: getstatic     #53                 // Field NESTED:Lio/manbang/ebatis/core/annotation/QueryType;
     722: aastore
     723: dup
     724: bipush        18
     726: getstatic     #55                 // Field PREFIX:Lio/manbang/ebatis/core/annotation/QueryType;
     729: aastore
     730: dup
     731: bipush        19
     733: getstatic     #57                 // Field QUERY_STRING:Lio/manbang/ebatis/core/annotation/QueryType;
     736: aastore
     737: dup
     738: bipush        20
     740: getstatic     #59                 // Field RANGE:Lio/manbang/ebatis/core/annotation/QueryType;
     743: aastore
     744: dup
     745: bipush        21
     747: getstatic     #61                 // Field SCRIPT:Lio/manbang/ebatis/core/annotation/QueryType;
     750: aastore
     751: dup
     752: bipush        22
     754: getstatic     #63                 // Field IDS:Lio/manbang/ebatis/core/annotation/QueryType;
     757: aastore
     758: dup
     759: bipush        23
     761: getstatic     #66                 // Field TERM:Lio/manbang/ebatis/core/annotation/QueryType;
     764: aastore
     765: dup
     766: bipush        24
     768: getstatic     #69                 // Field TERMS:Lio/manbang/ebatis/core/annotation/QueryType;
     771: aastore
     772: dup
     773: bipush        25
     775: getstatic     #72                 // Field EXISTS:Lio/manbang/ebatis/core/annotation/QueryType;
     778: aastore
     779: dup
     780: bipush        26
     782: getstatic     #75                 // Field MATCH_ALL:Lio/manbang/ebatis/core/annotation/QueryType;
     785: aastore
     786: dup
     787: bipush        27
     789: getstatic     #78                 // Field MATCH:Lio/manbang/ebatis/core/annotation/QueryType;
     792: aastore
     793: dup
     794: bipush        28
     796: getstatic     #81                 // Field MATCH_PHRASE:Lio/manbang/ebatis/core/annotation/QueryType;
     799: aastore
     800: dup
     801: bipush        29
     803: getstatic     #84                 // Field MATCH_PHRASE_PREFIX:Lio/manbang/ebatis/core/annotation/QueryType;
     806: aastore
     807: dup
     808: bipush        30
     810: getstatic     #86                 // Field SPAN_CONTAINING:Lio/manbang/ebatis/core/annotation/QueryType;
     813: aastore
     814: dup
     815: bipush        31
     817: getstatic     #88                 // Field SPAN_FIRST:Lio/manbang/ebatis/core/annotation/QueryType;
     820: aastore
     821: dup
     822: bipush        32
     824: getstatic     #90                 // Field SPAN_NEAR:Lio/manbang/ebatis/core/annotation/QueryType;
     827: aastore
     828: dup
     829: bipush        33
     831: getstatic     #92                 // Field SPAN_NOT:Lio/manbang/ebatis/core/annotation/QueryType;
     834: aastore
     835: dup
     836: bipush        34
     838: getstatic     #94                 // Field SPAN_OR:Lio/manbang/ebatis/core/annotation/QueryType;
     841: aastore
     842: dup
     843: bipush        35
     845: getstatic     #96                 // Field SPAN_TERM:Lio/manbang/ebatis/core/annotation/QueryType;
     848: aastore
     849: dup
     850: bipush        36
     852: getstatic     #98                 // Field SPAN_WITHIN:Lio/manbang/ebatis/core/annotation/QueryType;
     855: aastore
     856: dup
     857: bipush        37
     859: getstatic     #101                // Field WILDCARD:Lio/manbang/ebatis/core/annotation/QueryType;
     862: aastore
     863: putstatic     #1                  // Field $VALUES:[Lio/manbang/ebatis/core/annotation/QueryType;
     866: return
}
