Compiled from "CBSNationalLanguage.java"
public final class org.mobicents.protocols.ss7.map.api.datacoding.CBSNationalLanguage extends java.lang.Enum<org.mobicents.protocols.ss7.map.api.datacoding.CBSNationalLanguage> {
  public static final org.mobicents.protocols.ss7.map.api.datacoding.CBSNationalLanguage German;

  public static final org.mobicents.protocols.ss7.map.api.datacoding.CBSNationalLanguage English;

  public static final org.mobicents.protocols.ss7.map.api.datacoding.CBSNationalLanguage Italian;

  public static final org.mobicents.protocols.ss7.map.api.datacoding.CBSNationalLanguage French;

  public static final org.mobicents.protocols.ss7.map.api.datacoding.CBSNationalLanguage Spanish;

  public static final org.mobicents.protocols.ss7.map.api.datacoding.CBSNationalLanguage Dutch;

  public static final org.mobicents.protocols.ss7.map.api.datacoding.CBSNationalLanguage Swedish;

  public static final org.mobicents.protocols.ss7.map.api.datacoding.CBSNationalLanguage Danish;

  public static final org.mobicents.protocols.ss7.map.api.datacoding.CBSNationalLanguage Portuguese;

  public static final org.mobicents.protocols.ss7.map.api.datacoding.CBSNationalLanguage Finnish;

  public static final org.mobicents.protocols.ss7.map.api.datacoding.CBSNationalLanguage Norwegian;

  public static final org.mobicents.protocols.ss7.map.api.datacoding.CBSNationalLanguage Greek;

  public static final org.mobicents.protocols.ss7.map.api.datacoding.CBSNationalLanguage Turkish;

  public static final org.mobicents.protocols.ss7.map.api.datacoding.CBSNationalLanguage Hungarian;

  public static final org.mobicents.protocols.ss7.map.api.datacoding.CBSNationalLanguage Polish;

  public static final org.mobicents.protocols.ss7.map.api.datacoding.CBSNationalLanguage LanguageUnspecified;

  public static final org.mobicents.protocols.ss7.map.api.datacoding.CBSNationalLanguage Czech;

  public static final org.mobicents.protocols.ss7.map.api.datacoding.CBSNationalLanguage Hebrew;

  public static final org.mobicents.protocols.ss7.map.api.datacoding.CBSNationalLanguage Arabic;

  public static final org.mobicents.protocols.ss7.map.api.datacoding.CBSNationalLanguage Russian;

  public static final org.mobicents.protocols.ss7.map.api.datacoding.CBSNationalLanguage Icelandic;

  private int code;

  private static final org.mobicents.protocols.ss7.map.api.datacoding.CBSNationalLanguage[] $VALUES;

  public static org.mobicents.protocols.ss7.map.api.datacoding.CBSNationalLanguage[] values();
    Code:
       0: getstatic     #1                  // Field $VALUES:[Lorg/mobicents/protocols/ss7/map/api/datacoding/CBSNationalLanguage;
       3: invokevirtual #2                  // Method "[Lorg/mobicents/protocols/ss7/map/api/datacoding/CBSNationalLanguage;".clone:()Ljava/lang/Object;
       6: checkcast     #3                  // class "[Lorg/mobicents/protocols/ss7/map/api/datacoding/CBSNationalLanguage;"
       9: areturn

  public static org.mobicents.protocols.ss7.map.api.datacoding.CBSNationalLanguage valueOf(java.lang.String);
    Code:
       0: ldc_w         #4                  // class org/mobicents/protocols/ss7/map/api/datacoding/CBSNationalLanguage
       3: aload_0
       4: invokestatic  #5                  // Method java/lang/Enum.valueOf:(Ljava/lang/Class;Ljava/lang/String;)Ljava/lang/Enum;
       7: checkcast     #4                  // class org/mobicents/protocols/ss7/map/api/datacoding/CBSNationalLanguage
      10: areturn

  private org.mobicents.protocols.ss7.map.api.datacoding.CBSNationalLanguage(int);
    Code:
       0: aload_0
       1: aload_1
       2: iload_2
       3: invokespecial #6                  // Method java/lang/Enum."<init>":(Ljava/lang/String;I)V
       6: aload_0
       7: iload_3
       8: putfield      #7                  // Field code:I
      11: return

  public int getCode();
    Code:
       0: aload_0
       1: getfield      #7                  // Field code:I
       4: ireturn

  public int getCBSCodingGroupBits();
    Code:
       0: aload_0
       1: getfield      #7                  // Field code:I
       4: sipush        240
       7: iand
       8: iconst_4
       9: ishr
      10: ireturn

  public int getCBSLowBits();
    Code:
       0: aload_0
       1: getfield      #7                  // Field code:I
       4: bipush        15
       6: iand
       7: ireturn

  public static org.mobicents.protocols.ss7.map.api.datacoding.CBSNationalLanguage getInstance(int, int);
    Code:
       0: iload_0
       1: ifne          144
       4: iload_1
       5: tableswitch   { // 0 to 14
                     0: 80
                     1: 84
                     2: 88
                     3: 92
                     4: 96
                     5: 100
                     6: 104
                     7: 108
                     8: 112
                     9: 116
                    10: 120
                    11: 124
                    12: 128
                    13: 132
                    14: 136
               default: 140
          }
      80: getstatic     #8                  // Field German:Lorg/mobicents/protocols/ss7/map/api/datacoding/CBSNationalLanguage;
      83: areturn
      84: getstatic     #9                  // Field English:Lorg/mobicents/protocols/ss7/map/api/datacoding/CBSNationalLanguage;
      87: areturn
      88: getstatic     #10                 // Field Italian:Lorg/mobicents/protocols/ss7/map/api/datacoding/CBSNationalLanguage;
      91: areturn
      92: getstatic     #11                 // Field French:Lorg/mobicents/protocols/ss7/map/api/datacoding/CBSNationalLanguage;
      95: areturn
      96: getstatic     #12                 // Field Spanish:Lorg/mobicents/protocols/ss7/map/api/datacoding/CBSNationalLanguage;
      99: areturn
     100: getstatic     #13                 // Field Dutch:Lorg/mobicents/protocols/ss7/map/api/datacoding/CBSNationalLanguage;
     103: areturn
     104: getstatic     #14                 // Field Swedish:Lorg/mobicents/protocols/ss7/map/api/datacoding/CBSNationalLanguage;
     107: areturn
     108: getstatic     #15                 // Field Danish:Lorg/mobicents/protocols/ss7/map/api/datacoding/CBSNationalLanguage;
     111: areturn
     112: getstatic     #16                 // Field Portuguese:Lorg/mobicents/protocols/ss7/map/api/datacoding/CBSNationalLanguage;
     115: areturn
     116: getstatic     #17                 // Field Finnish:Lorg/mobicents/protocols/ss7/map/api/datacoding/CBSNationalLanguage;
     119: areturn
     120: getstatic     #18                 // Field Norwegian:Lorg/mobicents/protocols/ss7/map/api/datacoding/CBSNationalLanguage;
     123: areturn
     124: getstatic     #19                 // Field Greek:Lorg/mobicents/protocols/ss7/map/api/datacoding/CBSNationalLanguage;
     127: areturn
     128: getstatic     #20                 // Field Turkish:Lorg/mobicents/protocols/ss7/map/api/datacoding/CBSNationalLanguage;
     131: areturn
     132: getstatic     #21                 // Field Hungarian:Lorg/mobicents/protocols/ss7/map/api/datacoding/CBSNationalLanguage;
     135: areturn
     136: getstatic     #22                 // Field Polish:Lorg/mobicents/protocols/ss7/map/api/datacoding/CBSNationalLanguage;
     139: areturn
     140: getstatic     #23                 // Field LanguageUnspecified:Lorg/mobicents/protocols/ss7/map/api/datacoding/CBSNationalLanguage;
     143: areturn
     144: iload_0
     145: iconst_2
     146: if_icmpne     208
     149: iload_1
     150: tableswitch   { // 0 to 4
                     0: 184
                     1: 188
                     2: 192
                     3: 196
                     4: 200
               default: 204
          }
     184: getstatic     #24                 // Field Czech:Lorg/mobicents/protocols/ss7/map/api/datacoding/CBSNationalLanguage;
     187: areturn
     188: getstatic     #25                 // Field Hebrew:Lorg/mobicents/protocols/ss7/map/api/datacoding/CBSNationalLanguage;
     191: areturn
     192: getstatic     #26                 // Field Arabic:Lorg/mobicents/protocols/ss7/map/api/datacoding/CBSNationalLanguage;
     195: areturn
     196: getstatic     #27                 // Field Russian:Lorg/mobicents/protocols/ss7/map/api/datacoding/CBSNationalLanguage;
     199: areturn
     200: getstatic     #28                 // Field Icelandic:Lorg/mobicents/protocols/ss7/map/api/datacoding/CBSNationalLanguage;
     203: areturn
     204: getstatic     #23                 // Field LanguageUnspecified:Lorg/mobicents/protocols/ss7/map/api/datacoding/CBSNationalLanguage;
     207: areturn
     208: getstatic     #23                 // Field LanguageUnspecified:Lorg/mobicents/protocols/ss7/map/api/datacoding/CBSNationalLanguage;
     211: areturn

  static {};
    Code:
       0: new           #4                  // class org/mobicents/protocols/ss7/map/api/datacoding/CBSNationalLanguage
       3: dup
       4: ldc           #29                 // String German
       6: iconst_0
       7: iconst_0
       8: invokespecial #30                 // Method "<init>":(Ljava/lang/String;II)V
      11: putstatic     #8                  // Field German:Lorg/mobicents/protocols/ss7/map/api/datacoding/CBSNationalLanguage;
      14: new           #4                  // class org/mobicents/protocols/ss7/map/api/datacoding/CBSNationalLanguage
      17: dup
      18: ldc           #31                 // String English
      20: iconst_1
      21: iconst_1
      22: invokespecial #30                 // Method "<init>":(Ljava/lang/String;II)V
      25: putstatic     #9                  // Field English:Lorg/mobicents/protocols/ss7/map/api/datacoding/CBSNationalLanguage;
      28: new           #4                  // class org/mobicents/protocols/ss7/map/api/datacoding/CBSNationalLanguage
      31: dup
      32: ldc           #32                 // String Italian
      34: iconst_2
      35: iconst_2
      36: invokespecial #30                 // Method "<init>":(Ljava/lang/String;II)V
      39: putstatic     #10                 // Field Italian:Lorg/mobicents/protocols/ss7/map/api/datacoding/CBSNationalLanguage;
      42: new           #4                  // class org/mobicents/protocols/ss7/map/api/datacoding/CBSNationalLanguage
      45: dup
      46: ldc           #33                 // String French
      48: iconst_3
      49: iconst_3
      50: invokespecial #30                 // Method "<init>":(Ljava/lang/String;II)V
      53: putstatic     #11                 // Field French:Lorg/mobicents/protocols/ss7/map/api/datacoding/CBSNationalLanguage;
      56: new           #4                  // class org/mobicents/protocols/ss7/map/api/datacoding/CBSNationalLanguage
      59: dup
      60: ldc           #34                 // String Spanish
      62: iconst_4
      63: iconst_4
      64: invokespecial #30                 // Method "<init>":(Ljava/lang/String;II)V
      67: putstatic     #12                 // Field Spanish:Lorg/mobicents/protocols/ss7/map/api/datacoding/CBSNationalLanguage;
      70: new           #4                  // class org/mobicents/protocols/ss7/map/api/datacoding/CBSNationalLanguage
      73: dup
      74: ldc           #35                 // String Dutch
      76: iconst_5
      77: iconst_5
      78: invokespecial #30                 // Method "<init>":(Ljava/lang/String;II)V
      81: putstatic     #13                 // Field Dutch:Lorg/mobicents/protocols/ss7/map/api/datacoding/CBSNationalLanguage;
      84: new           #4                  // class org/mobicents/protocols/ss7/map/api/datacoding/CBSNationalLanguage
      87: dup
      88: ldc           #36                 // String Swedish
      90: bipush        6
      92: bipush        6
      94: invokespecial #30                 // Method "<init>":(Ljava/lang/String;II)V
      97: putstatic     #14                 // Field Swedish:Lorg/mobicents/protocols/ss7/map/api/datacoding/CBSNationalLanguage;
     100: new           #4                  // class org/mobicents/protocols/ss7/map/api/datacoding/CBSNationalLanguage
     103: dup
     104: ldc           #37                 // String Danish
     106: bipush        7
     108: bipush        7
     110: invokespecial #30                 // Method "<init>":(Ljava/lang/String;II)V
     113: putstatic     #15                 // Field Danish:Lorg/mobicents/protocols/ss7/map/api/datacoding/CBSNationalLanguage;
     116: new           #4                  // class org/mobicents/protocols/ss7/map/api/datacoding/CBSNationalLanguage
     119: dup
     120: ldc           #38                 // String Portuguese
     122: bipush        8
     124: bipush        8
     126: invokespecial #30                 // Method "<init>":(Ljava/lang/String;II)V
     129: putstatic     #16                 // Field Portuguese:Lorg/mobicents/protocols/ss7/map/api/datacoding/CBSNationalLanguage;
     132: new           #4                  // class org/mobicents/protocols/ss7/map/api/datacoding/CBSNationalLanguage
     135: dup
     136: ldc           #39                 // String Finnish
     138: bipush        9
     140: bipush        9
     142: invokespecial #30                 // Method "<init>":(Ljava/lang/String;II)V
     145: putstatic     #17                 // Field Finnish:Lorg/mobicents/protocols/ss7/map/api/datacoding/CBSNationalLanguage;
     148: new           #4                  // class org/mobicents/protocols/ss7/map/api/datacoding/CBSNationalLanguage
     151: dup
     152: ldc           #40                 // String Norwegian
     154: bipush        10
     156: bipush        10
     158: invokespecial #30                 // Method "<init>":(Ljava/lang/String;II)V
     161: putstatic     #18                 // Field Norwegian:Lorg/mobicents/protocols/ss7/map/api/datacoding/CBSNationalLanguage;
     164: new           #4                  // class org/mobicents/protocols/ss7/map/api/datacoding/CBSNationalLanguage
     167: dup
     168: ldc           #41                 // String Greek
     170: bipush        11
     172: bipush        11
     174: invokespecial #30                 // Method "<init>":(Ljava/lang/String;II)V
     177: putstatic     #19                 // Field Greek:Lorg/mobicents/protocols/ss7/map/api/datacoding/CBSNationalLanguage;
     180: new           #4                  // class org/mobicents/protocols/ss7/map/api/datacoding/CBSNationalLanguage
     183: dup
     184: ldc           #42                 // String Turkish
     186: bipush        12
     188: bipush        12
     190: invokespecial #30                 // Method "<init>":(Ljava/lang/String;II)V
     193: putstatic     #20                 // Field Turkish:Lorg/mobicents/protocols/ss7/map/api/datacoding/CBSNationalLanguage;
     196: new           #4                  // class org/mobicents/protocols/ss7/map/api/datacoding/CBSNationalLanguage
     199: dup
     200: ldc           #43                 // String Hungarian
     202: bipush        13
     204: bipush        13
     206: invokespecial #30                 // Method "<init>":(Ljava/lang/String;II)V
     209: putstatic     #21                 // Field Hungarian:Lorg/mobicents/protocols/ss7/map/api/datacoding/CBSNationalLanguage;
     212: new           #4                  // class org/mobicents/protocols/ss7/map/api/datacoding/CBSNationalLanguage
     215: dup
     216: ldc           #44                 // String Polish
     218: bipush        14
     220: bipush        14
     222: invokespecial #30                 // Method "<init>":(Ljava/lang/String;II)V
     225: putstatic     #22                 // Field Polish:Lorg/mobicents/protocols/ss7/map/api/datacoding/CBSNationalLanguage;
     228: new           #4                  // class org/mobicents/protocols/ss7/map/api/datacoding/CBSNationalLanguage
     231: dup
     232: ldc           #45                 // String LanguageUnspecified
     234: bipush        15
     236: bipush        15
     238: invokespecial #30                 // Method "<init>":(Ljava/lang/String;II)V
     241: putstatic     #23                 // Field LanguageUnspecified:Lorg/mobicents/protocols/ss7/map/api/datacoding/CBSNationalLanguage;
     244: new           #4                  // class org/mobicents/protocols/ss7/map/api/datacoding/CBSNationalLanguage
     247: dup
     248: ldc           #46                 // String Czech
     250: bipush        16
     252: bipush        32
     254: invokespecial #30                 // Method "<init>":(Ljava/lang/String;II)V
     257: putstatic     #24                 // Field Czech:Lorg/mobicents/protocols/ss7/map/api/datacoding/CBSNationalLanguage;
     260: new           #4                  // class org/mobicents/protocols/ss7/map/api/datacoding/CBSNationalLanguage
     263: dup
     264: ldc           #47                 // String Hebrew
     266: bipush        17
     268: bipush        33
     270: invokespecial #30                 // Method "<init>":(Ljava/lang/String;II)V
     273: putstatic     #25                 // Field Hebrew:Lorg/mobicents/protocols/ss7/map/api/datacoding/CBSNationalLanguage;
     276: new           #4                  // class org/mobicents/protocols/ss7/map/api/datacoding/CBSNationalLanguage
     279: dup
     280: ldc           #48                 // String Arabic
     282: bipush        18
     284: bipush        34
     286: invokespecial #30                 // Method "<init>":(Ljava/lang/String;II)V
     289: putstatic     #26                 // Field Arabic:Lorg/mobicents/protocols/ss7/map/api/datacoding/CBSNationalLanguage;
     292: new           #4                  // class org/mobicents/protocols/ss7/map/api/datacoding/CBSNationalLanguage
     295: dup
     296: ldc           #49                 // String Russian
     298: bipush        19
     300: bipush        35
     302: invokespecial #30                 // Method "<init>":(Ljava/lang/String;II)V
     305: putstatic     #27                 // Field Russian:Lorg/mobicents/protocols/ss7/map/api/datacoding/CBSNationalLanguage;
     308: new           #4                  // class org/mobicents/protocols/ss7/map/api/datacoding/CBSNationalLanguage
     311: dup
     312: ldc           #50                 // String Icelandic
     314: bipush        20
     316: bipush        36
     318: invokespecial #30                 // Method "<init>":(Ljava/lang/String;II)V
     321: putstatic     #28                 // Field Icelandic:Lorg/mobicents/protocols/ss7/map/api/datacoding/CBSNationalLanguage;
     324: bipush        21
     326: anewarray     #4                  // class org/mobicents/protocols/ss7/map/api/datacoding/CBSNationalLanguage
     329: dup
     330: iconst_0
     331: getstatic     #8                  // Field German:Lorg/mobicents/protocols/ss7/map/api/datacoding/CBSNationalLanguage;
     334: aastore
     335: dup
     336: iconst_1
     337: getstatic     #9                  // Field English:Lorg/mobicents/protocols/ss7/map/api/datacoding/CBSNationalLanguage;
     340: aastore
     341: dup
     342: iconst_2
     343: getstatic     #10                 // Field Italian:Lorg/mobicents/protocols/ss7/map/api/datacoding/CBSNationalLanguage;
     346: aastore
     347: dup
     348: iconst_3
     349: getstatic     #11                 // Field French:Lorg/mobicents/protocols/ss7/map/api/datacoding/CBSNationalLanguage;
     352: aastore
     353: dup
     354: iconst_4
     355: getstatic     #12                 // Field Spanish:Lorg/mobicents/protocols/ss7/map/api/datacoding/CBSNationalLanguage;
     358: aastore
     359: dup
     360: iconst_5
     361: getstatic     #13                 // Field Dutch:Lorg/mobicents/protocols/ss7/map/api/datacoding/CBSNationalLanguage;
     364: aastore
     365: dup
     366: bipush        6
     368: getstatic     #14                 // Field Swedish:Lorg/mobicents/protocols/ss7/map/api/datacoding/CBSNationalLanguage;
     371: aastore
     372: dup
     373: bipush        7
     375: getstatic     #15                 // Field Danish:Lorg/mobicents/protocols/ss7/map/api/datacoding/CBSNationalLanguage;
     378: aastore
     379: dup
     380: bipush        8
     382: getstatic     #16                 // Field Portuguese:Lorg/mobicents/protocols/ss7/map/api/datacoding/CBSNationalLanguage;
     385: aastore
     386: dup
     387: bipush        9
     389: getstatic     #17                 // Field Finnish:Lorg/mobicents/protocols/ss7/map/api/datacoding/CBSNationalLanguage;
     392: aastore
     393: dup
     394: bipush        10
     396: getstatic     #18                 // Field Norwegian:Lorg/mobicents/protocols/ss7/map/api/datacoding/CBSNationalLanguage;
     399: aastore
     400: dup
     401: bipush        11
     403: getstatic     #19                 // Field Greek:Lorg/mobicents/protocols/ss7/map/api/datacoding/CBSNationalLanguage;
     406: aastore
     407: dup
     408: bipush        12
     410: getstatic     #20                 // Field Turkish:Lorg/mobicents/protocols/ss7/map/api/datacoding/CBSNationalLanguage;
     413: aastore
     414: dup
     415: bipush        13
     417: getstatic     #21                 // Field Hungarian:Lorg/mobicents/protocols/ss7/map/api/datacoding/CBSNationalLanguage;
     420: aastore
     421: dup
     422: bipush        14
     424: getstatic     #22                 // Field Polish:Lorg/mobicents/protocols/ss7/map/api/datacoding/CBSNationalLanguage;
     427: aastore
     428: dup
     429: bipush        15
     431: getstatic     #23                 // Field LanguageUnspecified:Lorg/mobicents/protocols/ss7/map/api/datacoding/CBSNationalLanguage;
     434: aastore
     435: dup
     436: bipush        16
     438: getstatic     #24                 // Field Czech:Lorg/mobicents/protocols/ss7/map/api/datacoding/CBSNationalLanguage;
     441: aastore
     442: dup
     443: bipush        17
     445: getstatic     #25                 // Field Hebrew:Lorg/mobicents/protocols/ss7/map/api/datacoding/CBSNationalLanguage;
     448: aastore
     449: dup
     450: bipush        18
     452: getstatic     #26                 // Field Arabic:Lorg/mobicents/protocols/ss7/map/api/datacoding/CBSNationalLanguage;
     455: aastore
     456: dup
     457: bipush        19
     459: getstatic     #27                 // Field Russian:Lorg/mobicents/protocols/ss7/map/api/datacoding/CBSNationalLanguage;
     462: aastore
     463: dup
     464: bipush        20
     466: getstatic     #28                 // Field Icelandic:Lorg/mobicents/protocols/ss7/map/api/datacoding/CBSNationalLanguage;
     469: aastore
     470: putstatic     #1                  // Field $VALUES:[Lorg/mobicents/protocols/ss7/map/api/datacoding/CBSNationalLanguage;
     473: return
}
