Compiled from "SimpleHashParameters.java"
public class com.scurrilous.circe.params.SimpleHashParameters implements com.scurrilous.circe.HashParameters {
  private final java.lang.String algorithm;

  public static final com.scurrilous.circe.params.SimpleHashParameters MD5;

  public static final com.scurrilous.circe.params.SimpleHashParameters SHA1;

  public static final com.scurrilous.circe.params.SimpleHashParameters SHA256;

  public static final com.scurrilous.circe.params.SimpleHashParameters SHA384;

  public static final com.scurrilous.circe.params.SimpleHashParameters SHA512;

  public com.scurrilous.circe.params.SimpleHashParameters(java.lang.String);
    Code:
       0: aload_0
       1: invokespecial #1                  // Method java/lang/Object."<init>":()V
       4: aload_0
       5: aload_1
       6: putfield      #2                  // Field algorithm:Ljava/lang/String;
       9: return

  public java.lang.String algorithm();
    Code:
       0: aload_0
       1: getfield      #2                  // Field algorithm:Ljava/lang/String;
       4: areturn

  public int hashCode();
    Code:
       0: aload_0
       1: getfield      #2                  // Field algorithm:Ljava/lang/String;
       4: invokevirtual #3                  // Method java/lang/String.hashCode:()I
       7: ireturn

  public boolean equals(java.lang.Object);
    Code:
       0: aload_1
       1: aload_0
       2: if_acmpne     7
       5: iconst_1
       6: ireturn
       7: aload_1
       8: ifnull        20
      11: aload_1
      12: invokevirtual #4                  // Method java/lang/Object.getClass:()Ljava/lang/Class;
      15: ldc           #5                  // class com/scurrilous/circe/params/SimpleHashParameters
      17: if_acmpeq     22
      20: iconst_0
      21: ireturn
      22: aload_0
      23: getfield      #2                  // Field algorithm:Ljava/lang/String;
      26: aload_1
      27: checkcast     #5                  // class com/scurrilous/circe/params/SimpleHashParameters
      30: getfield      #2                  // Field algorithm:Ljava/lang/String;
      33: invokevirtual #6                  // Method java/lang/String.equals:(Ljava/lang/Object;)Z
      36: ireturn

  public java.lang.String toString();
    Code:
       0: aload_0
       1: getfield      #2                  // Field algorithm:Ljava/lang/String;
       4: areturn

  static {};
    Code:
       0: new           #5                  // class com/scurrilous/circe/params/SimpleHashParameters
       3: dup
       4: ldc           #7                  // String MD5
       6: invokespecial #8                  // Method "<init>":(Ljava/lang/String;)V
       9: putstatic     #9                  // Field MD5:Lcom/scurrilous/circe/params/SimpleHashParameters;
      12: new           #5                  // class com/scurrilous/circe/params/SimpleHashParameters
      15: dup
      16: ldc           #10                 // String SHA-1
      18: invokespecial #8                  // Method "<init>":(Ljava/lang/String;)V
      21: putstatic     #11                 // Field SHA1:Lcom/scurrilous/circe/params/SimpleHashParameters;
      24: new           #5                  // class com/scurrilous/circe/params/SimpleHashParameters
      27: dup
      28: ldc           #12                 // String SHA-256
      30: invokespecial #8                  // Method "<init>":(Ljava/lang/String;)V
      33: putstatic     #13                 // Field SHA256:Lcom/scurrilous/circe/params/SimpleHashParameters;
      36: new           #5                  // class com/scurrilous/circe/params/SimpleHashParameters
      39: dup
      40: ldc           #14                 // String SHA-384
      42: invokespecial #8                  // Method "<init>":(Ljava/lang/String;)V
      45: putstatic     #15                 // Field SHA384:Lcom/scurrilous/circe/params/SimpleHashParameters;
      48: new           #5                  // class com/scurrilous/circe/params/SimpleHashParameters
      51: dup
      52: ldc           #16                 // String SHA-512
      54: invokespecial #8                  // Method "<init>":(Ljava/lang/String;)V
      57: putstatic     #17                 // Field SHA512:Lcom/scurrilous/circe/params/SimpleHashParameters;
      60: return
}
