Compiled from "PluginLoader.java"
public final class org.apache.cxf.tools.wsdlto.core.PluginLoader {
  public static final java.util.logging.Logger LOG;

  public static final java.lang.String DEFAULT_PROVIDER_NAME;

  private static org.apache.cxf.tools.wsdlto.core.PluginLoader pluginLoader;

  private static final java.lang.String PLUGIN_FILE_NAME;

  private java.util.Map<java.lang.String, org.apache.cxf.tools.plugin.Plugin> plugins;

  private java.util.Map<java.lang.String, org.apache.cxf.tools.plugin.FrontEnd> frontends;

  private java.util.Map<java.lang.String, org.apache.cxf.tools.plugin.DataBinding> databindings;

  private javax.xml.bind.JAXBContext jaxbContext;

  private org.apache.cxf.tools.wsdlto.core.PluginLoader();
    Code:
       0: aload_0
       1: invokespecial #1                  // Method java/lang/Object."<init>":()V
       4: aload_0
       5: new           #2                  // class java/util/LinkedHashMap
       8: dup
       9: invokespecial #3                  // Method java/util/LinkedHashMap."<init>":()V
      12: putfield      #4                  // Field plugins:Ljava/util/Map;
      15: aload_0
      16: new           #2                  // class java/util/LinkedHashMap
      19: dup
      20: invokespecial #3                  // Method java/util/LinkedHashMap."<init>":()V
      23: putfield      #5                  // Field frontends:Ljava/util/Map;
      26: aload_0
      27: new           #6                  // class java/util/TreeMap
      30: dup
      31: invokespecial #7                  // Method java/util/TreeMap."<init>":()V
      34: putfield      #8                  // Field databindings:Ljava/util/Map;
      37: aload_0
      38: invokespecial #9                  // Method init:()V
      41: return

  private void init();
    Code:
       0: aload_0
       1: ldc           #10                 // String org.apache.cxf.tools.plugin
       3: invokestatic  #11                 // Method javax/xml/bind/JAXBContext.newInstance:(Ljava/lang/String;)Ljavax/xml/bind/JAXBContext;
       6: putfield      #12                 // Field jaxbContext:Ljavax/xml/bind/JAXBContext;
       9: aload_0
      10: ldc           #13                 // String META-INF/tools-plugin.xml
      12: aload_0
      13: invokevirtual #14                 // Method java/lang/Object.getClass:()Ljava/lang/Class;
      16: invokestatic  #15                 // Method org/apache/cxf/common/classloader/ClassLoaderUtils.getResources:(Ljava/lang/String;Ljava/lang/Class;)Ljava/util/List;
      19: invokespecial #16                 // Method loadPlugins:(Ljava/util/List;)V
      22: goto          105
      25: astore_1
      26: new           #18                 // class org/apache/cxf/common/i18n/Message
      29: dup
      30: ldc           #19                 // String JAXB_CONTEXT_INIT_FAIL
      32: getstatic     #20                 // Field LOG:Ljava/util/logging/Logger;
      35: iconst_0
      36: anewarray     #21                 // class java/lang/Object
      39: invokespecial #22                 // Method org/apache/cxf/common/i18n/Message."<init>":(Ljava/lang/String;Ljava/util/logging/Logger;[Ljava/lang/Object;)V
      42: astore_2
      43: getstatic     #20                 // Field LOG:Ljava/util/logging/Logger;
      46: getstatic     #23                 // Field java/util/logging/Level.SEVERE:Ljava/util/logging/Level;
      49: aload_2
      50: invokevirtual #24                 // Method org/apache/cxf/common/i18n/Message.toString:()Ljava/lang/String;
      53: invokevirtual #25                 // Method java/util/logging/Logger.log:(Ljava/util/logging/Level;Ljava/lang/String;)V
      56: new           #26                 // class org/apache/cxf/tools/common/ToolException
      59: dup
      60: aload_2
      61: invokespecial #27                 // Method org/apache/cxf/tools/common/ToolException."<init>":(Lorg/apache/cxf/common/i18n/Message;)V
      64: athrow
      65: astore_1
      66: new           #18                 // class org/apache/cxf/common/i18n/Message
      69: dup
      70: ldc           #29                 // String LOAD_PLUGIN_EXCEPTION
      72: getstatic     #20                 // Field LOG:Ljava/util/logging/Logger;
      75: iconst_0
      76: anewarray     #21                 // class java/lang/Object
      79: invokespecial #22                 // Method org/apache/cxf/common/i18n/Message."<init>":(Ljava/lang/String;Ljava/util/logging/Logger;[Ljava/lang/Object;)V
      82: astore_2
      83: getstatic     #20                 // Field LOG:Ljava/util/logging/Logger;
      86: getstatic     #23                 // Field java/util/logging/Level.SEVERE:Ljava/util/logging/Level;
      89: aload_2
      90: invokevirtual #24                 // Method org/apache/cxf/common/i18n/Message.toString:()Ljava/lang/String;
      93: invokevirtual #25                 // Method java/util/logging/Logger.log:(Ljava/util/logging/Level;Ljava/lang/String;)V
      96: new           #26                 // class org/apache/cxf/tools/common/ToolException
      99: dup
     100: aload_2
     101: invokespecial #27                 // Method org/apache/cxf/tools/common/ToolException."<init>":(Lorg/apache/cxf/common/i18n/Message;)V
     104: athrow
     105: return
    Exception table:
       from    to  target type
           0    22    25   Class javax/xml/bind/JAXBException
           0    22    65   Class java/io/IOException

  public void refresh();
    Code:
       0: aload_0
       1: invokespecial #9                  // Method init:()V
       4: return

  private void loadPlugins(java.util.List<java.net.URL>) throws java.io.IOException;
    Code:
       0: aload_1
       1: ifnonnull     16
       4: getstatic     #20                 // Field LOG:Ljava/util/logging/Logger;
       7: getstatic     #30                 // Field java/util/logging/Level.WARNING:Ljava/util/logging/Level;
      10: ldc           #31                 // String FOUND_NO_PLUGINS
      12: invokevirtual #25                 // Method java/util/logging/Logger.log:(Ljava/util/logging/Level;Ljava/lang/String;)V
      15: return
      16: aload_1
      17: invokeinterface #32,  1           // InterfaceMethod java/util/List.iterator:()Ljava/util/Iterator;
      22: astore_2
      23: aload_2
      24: invokeinterface #33,  1           // InterfaceMethod java/util/Iterator.hasNext:()Z
      29: ifeq          50
      32: aload_2
      33: invokeinterface #34,  1           // InterfaceMethod java/util/Iterator.next:()Ljava/lang/Object;
      38: checkcast     #35                 // class java/net/URL
      41: astore_3
      42: aload_0
      43: aload_3
      44: invokevirtual #36                 // Method loadPlugin:(Ljava/net/URL;)V
      47: goto          23
      50: return

  public static org.apache.cxf.tools.wsdlto.core.PluginLoader newInstance();
    Code:
       0: new           #37                 // class org/apache/cxf/tools/wsdlto/core/PluginLoader
       3: dup
       4: invokespecial #38                 // Method "<init>":()V
       7: areturn

  public static org.apache.cxf.tools.wsdlto.core.PluginLoader getInstance();
    Code:
       0: getstatic     #39                 // Field pluginLoader:Lorg/apache/cxf/tools/wsdlto/core/PluginLoader;
       3: ifnonnull     16
       6: new           #37                 // class org/apache/cxf/tools/wsdlto/core/PluginLoader
       9: dup
      10: invokespecial #38                 // Method "<init>":()V
      13: putstatic     #39                 // Field pluginLoader:Lorg/apache/cxf/tools/wsdlto/core/PluginLoader;
      16: getstatic     #39                 // Field pluginLoader:Lorg/apache/cxf/tools/wsdlto/core/PluginLoader;
      19: areturn

  public static void unload();
    Code:
       0: aconst_null
       1: putstatic     #39                 // Field pluginLoader:Lorg/apache/cxf/tools/wsdlto/core/PluginLoader;
       4: return

  public void loadPlugin(java.net.URL) throws java.io.IOException;
    Code:
       0: getstatic     #20                 // Field LOG:Ljava/util/logging/Logger;
       3: getstatic     #40                 // Field java/util/logging/Level.FINE:Ljava/util/logging/Level;
       6: ldc           #41                 // String PLUGIN_LOADING
       8: aload_1
       9: invokevirtual #42                 // Method java/util/logging/Logger.log:(Ljava/util/logging/Level;Ljava/lang/String;Ljava/lang/Object;)V
      12: aload_0
      13: aload_0
      14: aload_1
      15: invokevirtual #43                 // Method getPlugin:(Ljava/net/URL;)Lorg/apache/cxf/tools/plugin/Plugin;
      18: invokevirtual #44                 // Method loadPlugin:(Lorg/apache/cxf/tools/plugin/Plugin;)V
      21: goto          69
      24: astore_2
      25: new           #18                 // class org/apache/cxf/common/i18n/Message
      28: dup
      29: ldc           #45                 // String PLUGIN_LOAD_FAIL
      31: getstatic     #20                 // Field LOG:Ljava/util/logging/Logger;
      34: iconst_1
      35: anewarray     #21                 // class java/lang/Object
      38: dup
      39: iconst_0
      40: aload_1
      41: aastore
      42: invokespecial #22                 // Method org/apache/cxf/common/i18n/Message."<init>":(Ljava/lang/String;Ljava/util/logging/Logger;[Ljava/lang/Object;)V
      45: astore_3
      46: getstatic     #20                 // Field LOG:Ljava/util/logging/Logger;
      49: getstatic     #23                 // Field java/util/logging/Level.SEVERE:Ljava/util/logging/Level;
      52: aload_3
      53: invokevirtual #24                 // Method org/apache/cxf/common/i18n/Message.toString:()Ljava/lang/String;
      56: invokevirtual #25                 // Method java/util/logging/Logger.log:(Ljava/util/logging/Level;Ljava/lang/String;)V
      59: new           #26                 // class org/apache/cxf/tools/common/ToolException
      62: dup
      63: aload_3
      64: aload_2
      65: invokespecial #46                 // Method org/apache/cxf/tools/common/ToolException."<init>":(Lorg/apache/cxf/common/i18n/Message;Ljava/lang/Throwable;)V
      68: athrow
      69: return
    Exception table:
       from    to  target type
           0    21    24   Class javax/xml/bind/JAXBException

  public void loadPlugin(java.lang.String);
    Code:
       0: getstatic     #20                 // Field LOG:Ljava/util/logging/Logger;
       3: getstatic     #40                 // Field java/util/logging/Level.FINE:Ljava/util/logging/Level;
       6: ldc           #41                 // String PLUGIN_LOADING
       8: aload_1
       9: invokevirtual #42                 // Method java/util/logging/Logger.log:(Ljava/util/logging/Level;Ljava/lang/String;Ljava/lang/Object;)V
      12: aload_0
      13: aload_0
      14: aload_1
      15: invokevirtual #47                 // Method getPlugin:(Ljava/lang/String;)Lorg/apache/cxf/tools/plugin/Plugin;
      18: invokevirtual #44                 // Method loadPlugin:(Lorg/apache/cxf/tools/plugin/Plugin;)V
      21: goto          114
      24: astore_2
      25: new           #18                 // class org/apache/cxf/common/i18n/Message
      28: dup
      29: ldc           #45                 // String PLUGIN_LOAD_FAIL
      31: getstatic     #20                 // Field LOG:Ljava/util/logging/Logger;
      34: iconst_1
      35: anewarray     #21                 // class java/lang/Object
      38: dup
      39: iconst_0
      40: aload_1
      41: aastore
      42: invokespecial #22                 // Method org/apache/cxf/common/i18n/Message."<init>":(Ljava/lang/String;Ljava/util/logging/Logger;[Ljava/lang/Object;)V
      45: astore_3
      46: getstatic     #20                 // Field LOG:Ljava/util/logging/Logger;
      49: getstatic     #23                 // Field java/util/logging/Level.SEVERE:Ljava/util/logging/Level;
      52: aload_3
      53: invokevirtual #24                 // Method org/apache/cxf/common/i18n/Message.toString:()Ljava/lang/String;
      56: invokevirtual #25                 // Method java/util/logging/Logger.log:(Ljava/util/logging/Level;Ljava/lang/String;)V
      59: new           #26                 // class org/apache/cxf/tools/common/ToolException
      62: dup
      63: aload_3
      64: aload_2
      65: invokespecial #46                 // Method org/apache/cxf/tools/common/ToolException."<init>":(Lorg/apache/cxf/common/i18n/Message;Ljava/lang/Throwable;)V
      68: athrow
      69: astore_2
      70: new           #18                 // class org/apache/cxf/common/i18n/Message
      73: dup
      74: ldc           #49                 // String PLUGIN_FILE_NOT_FOUND
      76: getstatic     #20                 // Field LOG:Ljava/util/logging/Logger;
      79: iconst_1
      80: anewarray     #21                 // class java/lang/Object
      83: dup
      84: iconst_0
      85: aload_1
      86: aastore
      87: invokespecial #22                 // Method org/apache/cxf/common/i18n/Message."<init>":(Ljava/lang/String;Ljava/util/logging/Logger;[Ljava/lang/Object;)V
      90: astore_3
      91: getstatic     #20                 // Field LOG:Ljava/util/logging/Logger;
      94: getstatic     #23                 // Field java/util/logging/Level.SEVERE:Ljava/util/logging/Level;
      97: aload_3
      98: invokevirtual #24                 // Method org/apache/cxf/common/i18n/Message.toString:()Ljava/lang/String;
     101: invokevirtual #25                 // Method java/util/logging/Logger.log:(Ljava/util/logging/Level;Ljava/lang/String;)V
     104: new           #26                 // class org/apache/cxf/tools/common/ToolException
     107: dup
     108: aload_3
     109: aload_2
     110: invokespecial #46                 // Method org/apache/cxf/tools/common/ToolException."<init>":(Lorg/apache/cxf/common/i18n/Message;Ljava/lang/Throwable;)V
     113: athrow
     114: return
    Exception table:
       from    to  target type
           0    21    24   Class javax/xml/bind/JAXBException
           0    21    69   Class java/io/FileNotFoundException

  protected void loadPlugin(org.apache.cxf.tools.plugin.Plugin);
    Code:
       0: aload_1
       1: invokevirtual #50                 // Method org/apache/cxf/tools/plugin/Plugin.getFrontend:()Ljava/util/List;
       4: invokeinterface #51,  1           // InterfaceMethod java/util/List.size:()I
       9: ifle          49
      12: getstatic     #20                 // Field LOG:Ljava/util/logging/Logger;
      15: getstatic     #40                 // Field java/util/logging/Level.FINE:Ljava/util/logging/Level;
      18: ldc           #52                 // String FOUND_FRONTENDS
      20: iconst_2
      21: anewarray     #21                 // class java/lang/Object
      24: dup
      25: iconst_0
      26: aload_1
      27: invokevirtual #53                 // Method org/apache/cxf/tools/plugin/Plugin.getName:()Ljava/lang/String;
      30: aastore
      31: dup
      32: iconst_1
      33: aload_1
      34: invokevirtual #50                 // Method org/apache/cxf/tools/plugin/Plugin.getFrontend:()Ljava/util/List;
      37: invokeinterface #51,  1           // InterfaceMethod java/util/List.size:()I
      42: invokestatic  #54                 // Method java/lang/Integer.valueOf:(I)Ljava/lang/Integer;
      45: aastore
      46: invokevirtual #55                 // Method java/util/logging/Logger.log:(Ljava/util/logging/Level;Ljava/lang/String;[Ljava/lang/Object;)V
      49: aload_1
      50: invokevirtual #50                 // Method org/apache/cxf/tools/plugin/Plugin.getFrontend:()Ljava/util/List;
      53: invokeinterface #32,  1           // InterfaceMethod java/util/List.iterator:()Ljava/util/Iterator;
      58: astore_2
      59: aload_2
      60: invokeinterface #33,  1           // InterfaceMethod java/util/Iterator.hasNext:()Z
      65: ifeq          223
      68: aload_2
      69: invokeinterface #34,  1           // InterfaceMethod java/util/Iterator.next:()Ljava/lang/Object;
      74: checkcast     #56                 // class org/apache/cxf/tools/plugin/FrontEnd
      77: astore_3
      78: getstatic     #20                 // Field LOG:Ljava/util/logging/Logger;
      81: getstatic     #40                 // Field java/util/logging/Level.FINE:Ljava/util/logging/Level;
      84: ldc           #57                 // String LOADING_FRONTEND
      86: iconst_2
      87: anewarray     #21                 // class java/lang/Object
      90: dup
      91: iconst_0
      92: aload_3
      93: invokevirtual #58                 // Method org/apache/cxf/tools/plugin/FrontEnd.getName:()Ljava/lang/String;
      96: aastore
      97: dup
      98: iconst_1
      99: aload_1
     100: invokevirtual #53                 // Method org/apache/cxf/tools/plugin/Plugin.getName:()Ljava/lang/String;
     103: aastore
     104: invokevirtual #55                 // Method java/util/logging/Logger.log:(Ljava/util/logging/Level;Ljava/lang/String;[Ljava/lang/Object;)V
     107: aload_3
     108: invokevirtual #58                 // Method org/apache/cxf/tools/plugin/FrontEnd.getName:()Ljava/lang/String;
     111: invokestatic  #59                 // Method org/apache/cxf/common/util/StringUtils.isEmpty:(Ljava/lang/String;)Z
     114: ifeq          135
     117: getstatic     #20                 // Field LOG:Ljava/util/logging/Logger;
     120: getstatic     #30                 // Field java/util/logging/Level.WARNING:Ljava/util/logging/Level;
     123: ldc           #60                 // String FRONTEND_MISSING_NAME
     125: aload_1
     126: invokevirtual #53                 // Method org/apache/cxf/tools/plugin/Plugin.getName:()Ljava/lang/String;
     129: invokevirtual #42                 // Method java/util/logging/Logger.log:(Ljava/util/logging/Level;Ljava/lang/String;Ljava/lang/Object;)V
     132: goto          59
     135: aload_0
     136: getfield      #5                  // Field frontends:Ljava/util/Map;
     139: aload_3
     140: invokevirtual #58                 // Method org/apache/cxf/tools/plugin/FrontEnd.getName:()Ljava/lang/String;
     143: invokeinterface #61,  2           // InterfaceMethod java/util/Map.containsKey:(Ljava/lang/Object;)Z
     148: ifeq          205
     151: ldc           #62                 // String cxf.apache.org
     153: aload_1
     154: invokevirtual #63                 // Method org/apache/cxf/tools/plugin/Plugin.getProvider:()Ljava/lang/String;
     157: invokevirtual #64                 // Method java/lang/String.equals:(Ljava/lang/Object;)Z
     160: ifeq          205
     163: new           #18                 // class org/apache/cxf/common/i18n/Message
     166: dup
     167: ldc           #65                 // String REPLACED_DEFAULT_FRONTEND
     169: getstatic     #20                 // Field LOG:Ljava/util/logging/Logger;
     172: iconst_1
     173: anewarray     #21                 // class java/lang/Object
     176: dup
     177: iconst_0
     178: aload_3
     179: invokevirtual #58                 // Method org/apache/cxf/tools/plugin/FrontEnd.getName:()Ljava/lang/String;
     182: aastore
     183: invokespecial #22                 // Method org/apache/cxf/common/i18n/Message."<init>":(Ljava/lang/String;Ljava/util/logging/Logger;[Ljava/lang/Object;)V
     186: astore        4
     188: getstatic     #20                 // Field LOG:Ljava/util/logging/Logger;
     191: getstatic     #66                 // Field java/util/logging/Level.INFO:Ljava/util/logging/Level;
     194: aload         4
     196: invokevirtual #24                 // Method org/apache/cxf/common/i18n/Message.toString:()Ljava/lang/String;
     199: invokevirtual #25                 // Method java/util/logging/Logger.log:(Ljava/util/logging/Level;Ljava/lang/String;)V
     202: goto          59
     205: aload_0
     206: getfield      #5                  // Field frontends:Ljava/util/Map;
     209: aload_3
     210: invokevirtual #58                 // Method org/apache/cxf/tools/plugin/FrontEnd.getName:()Ljava/lang/String;
     213: aload_3
     214: invokeinterface #67,  3           // InterfaceMethod java/util/Map.put:(Ljava/lang/Object;Ljava/lang/Object;)Ljava/lang/Object;
     219: pop
     220: goto          59
     223: aload_1
     224: invokevirtual #68                 // Method org/apache/cxf/tools/plugin/Plugin.getDatabinding:()Ljava/util/List;
     227: invokeinterface #51,  1           // InterfaceMethod java/util/List.size:()I
     232: ifle          272
     235: getstatic     #20                 // Field LOG:Ljava/util/logging/Logger;
     238: getstatic     #40                 // Field java/util/logging/Level.FINE:Ljava/util/logging/Level;
     241: ldc           #69                 // String FOUND_DATABINDINGS
     243: iconst_2
     244: anewarray     #21                 // class java/lang/Object
     247: dup
     248: iconst_0
     249: aload_1
     250: invokevirtual #53                 // Method org/apache/cxf/tools/plugin/Plugin.getName:()Ljava/lang/String;
     253: aastore
     254: dup
     255: iconst_1
     256: aload_1
     257: invokevirtual #68                 // Method org/apache/cxf/tools/plugin/Plugin.getDatabinding:()Ljava/util/List;
     260: invokeinterface #51,  1           // InterfaceMethod java/util/List.size:()I
     265: invokestatic  #54                 // Method java/lang/Integer.valueOf:(I)Ljava/lang/Integer;
     268: aastore
     269: invokevirtual #55                 // Method java/util/logging/Logger.log:(Ljava/util/logging/Level;Ljava/lang/String;[Ljava/lang/Object;)V
     272: aload_1
     273: invokevirtual #68                 // Method org/apache/cxf/tools/plugin/Plugin.getDatabinding:()Ljava/util/List;
     276: invokeinterface #32,  1           // InterfaceMethod java/util/List.iterator:()Ljava/util/Iterator;
     281: astore_2
     282: aload_2
     283: invokeinterface #33,  1           // InterfaceMethod java/util/Iterator.hasNext:()Z
     288: ifeq          446
     291: aload_2
     292: invokeinterface #34,  1           // InterfaceMethod java/util/Iterator.next:()Ljava/lang/Object;
     297: checkcast     #70                 // class org/apache/cxf/tools/plugin/DataBinding
     300: astore_3
     301: getstatic     #20                 // Field LOG:Ljava/util/logging/Logger;
     304: getstatic     #40                 // Field java/util/logging/Level.FINE:Ljava/util/logging/Level;
     307: ldc           #71                 // String LOADING_DATABINDING
     309: iconst_2
     310: anewarray     #21                 // class java/lang/Object
     313: dup
     314: iconst_0
     315: aload_3
     316: invokevirtual #72                 // Method org/apache/cxf/tools/plugin/DataBinding.getName:()Ljava/lang/String;
     319: aastore
     320: dup
     321: iconst_1
     322: aload_1
     323: invokevirtual #53                 // Method org/apache/cxf/tools/plugin/Plugin.getName:()Ljava/lang/String;
     326: aastore
     327: invokevirtual #55                 // Method java/util/logging/Logger.log:(Ljava/util/logging/Level;Ljava/lang/String;[Ljava/lang/Object;)V
     330: aload_3
     331: invokevirtual #72                 // Method org/apache/cxf/tools/plugin/DataBinding.getName:()Ljava/lang/String;
     334: invokestatic  #59                 // Method org/apache/cxf/common/util/StringUtils.isEmpty:(Ljava/lang/String;)Z
     337: ifeq          358
     340: getstatic     #20                 // Field LOG:Ljava/util/logging/Logger;
     343: getstatic     #30                 // Field java/util/logging/Level.WARNING:Ljava/util/logging/Level;
     346: ldc           #73                 // String DATABINDING_MISSING_NAME
     348: aload_1
     349: invokevirtual #53                 // Method org/apache/cxf/tools/plugin/Plugin.getName:()Ljava/lang/String;
     352: invokevirtual #42                 // Method java/util/logging/Logger.log:(Ljava/util/logging/Level;Ljava/lang/String;Ljava/lang/Object;)V
     355: goto          282
     358: aload_0
     359: getfield      #8                  // Field databindings:Ljava/util/Map;
     362: aload_3
     363: invokevirtual #72                 // Method org/apache/cxf/tools/plugin/DataBinding.getName:()Ljava/lang/String;
     366: invokeinterface #61,  2           // InterfaceMethod java/util/Map.containsKey:(Ljava/lang/Object;)Z
     371: ifeq          428
     374: ldc           #62                 // String cxf.apache.org
     376: aload_1
     377: invokevirtual #63                 // Method org/apache/cxf/tools/plugin/Plugin.getProvider:()Ljava/lang/String;
     380: invokevirtual #64                 // Method java/lang/String.equals:(Ljava/lang/Object;)Z
     383: ifeq          428
     386: new           #18                 // class org/apache/cxf/common/i18n/Message
     389: dup
     390: ldc           #74                 // String REPLACED_DEFAULT_DATABINDING
     392: getstatic     #20                 // Field LOG:Ljava/util/logging/Logger;
     395: iconst_1
     396: anewarray     #21                 // class java/lang/Object
     399: dup
     400: iconst_0
     401: aload_3
     402: invokevirtual #72                 // Method org/apache/cxf/tools/plugin/DataBinding.getName:()Ljava/lang/String;
     405: aastore
     406: invokespecial #22                 // Method org/apache/cxf/common/i18n/Message."<init>":(Ljava/lang/String;Ljava/util/logging/Logger;[Ljava/lang/Object;)V
     409: astore        4
     411: getstatic     #20                 // Field LOG:Ljava/util/logging/Logger;
     414: getstatic     #66                 // Field java/util/logging/Level.INFO:Ljava/util/logging/Level;
     417: aload         4
     419: invokevirtual #24                 // Method org/apache/cxf/common/i18n/Message.toString:()Ljava/lang/String;
     422: invokevirtual #25                 // Method java/util/logging/Logger.log:(Ljava/util/logging/Level;Ljava/lang/String;)V
     425: goto          282
     428: aload_0
     429: getfield      #8                  // Field databindings:Ljava/util/Map;
     432: aload_3
     433: invokevirtual #72                 // Method org/apache/cxf/tools/plugin/DataBinding.getName:()Ljava/lang/String;
     436: aload_3
     437: invokeinterface #67,  3           // InterfaceMethod java/util/Map.put:(Ljava/lang/Object;Ljava/lang/Object;)Ljava/lang/Object;
     442: pop
     443: goto          282
     446: return

  protected org.apache.cxf.tools.plugin.Plugin getPlugin(java.net.URL) throws java.io.IOException, javax.xml.bind.JAXBException, java.io.FileNotFoundException;
    Code:
       0: aload_0
       1: getfield      #4                  // Field plugins:Ljava/util/Map;
       4: aload_1
       5: invokevirtual #75                 // Method java/net/URL.toString:()Ljava/lang/String;
       8: invokeinterface #76,  2           // InterfaceMethod java/util/Map.get:(Ljava/lang/Object;)Ljava/lang/Object;
      13: checkcast     #77                 // class org/apache/cxf/tools/plugin/Plugin
      16: astore_2
      17: aconst_null
      18: astore_3
      19: aload_2
      20: ifnonnull     109
      23: aload_1
      24: invokevirtual #78                 // Method java/net/URL.openStream:()Ljava/io/InputStream;
      27: astore_3
      28: aload_0
      29: aload_3
      30: invokespecial #79                 // Method getPlugin:(Ljava/io/InputStream;)Lorg/apache/cxf/tools/plugin/Plugin;
      33: astore_2
      34: aload_2
      35: ifnull        48
      38: aload_2
      39: invokevirtual #53                 // Method org/apache/cxf/tools/plugin/Plugin.getName:()Ljava/lang/String;
      42: invokestatic  #59                 // Method org/apache/cxf/common/util/StringUtils.isEmpty:(Ljava/lang/String;)Z
      45: ifeq          94
      48: new           #18                 // class org/apache/cxf/common/i18n/Message
      51: dup
      52: ldc           #45                 // String PLUGIN_LOAD_FAIL
      54: getstatic     #20                 // Field LOG:Ljava/util/logging/Logger;
      57: iconst_1
      58: anewarray     #21                 // class java/lang/Object
      61: dup
      62: iconst_0
      63: aload_1
      64: aastore
      65: invokespecial #22                 // Method org/apache/cxf/common/i18n/Message."<init>":(Ljava/lang/String;Ljava/util/logging/Logger;[Ljava/lang/Object;)V
      68: astore        4
      70: getstatic     #20                 // Field LOG:Ljava/util/logging/Logger;
      73: getstatic     #23                 // Field java/util/logging/Level.SEVERE:Ljava/util/logging/Level;
      76: aload         4
      78: invokevirtual #24                 // Method org/apache/cxf/common/i18n/Message.toString:()Ljava/lang/String;
      81: invokevirtual #25                 // Method java/util/logging/Logger.log:(Ljava/util/logging/Level;Ljava/lang/String;)V
      84: new           #26                 // class org/apache/cxf/tools/common/ToolException
      87: dup
      88: aload         4
      90: invokespecial #27                 // Method org/apache/cxf/tools/common/ToolException."<init>":(Lorg/apache/cxf/common/i18n/Message;)V
      93: athrow
      94: aload_0
      95: getfield      #4                  // Field plugins:Ljava/util/Map;
      98: aload_1
      99: invokevirtual #75                 // Method java/net/URL.toString:()Ljava/lang/String;
     102: aload_2
     103: invokeinterface #67,  3           // InterfaceMethod java/util/Map.put:(Ljava/lang/Object;Ljava/lang/Object;)Ljava/lang/Object;
     108: pop
     109: aload_3
     110: ifnonnull     122
     113: aload_0
     114: aload_1
     115: invokevirtual #75                 // Method java/net/URL.toString:()Ljava/lang/String;
     118: invokevirtual #47                 // Method getPlugin:(Ljava/lang/String;)Lorg/apache/cxf/tools/plugin/Plugin;
     121: areturn
     122: aload_2
     123: areturn

  protected org.apache.cxf.tools.plugin.Plugin getPlugin(java.lang.String) throws javax.xml.bind.JAXBException, java.io.FileNotFoundException;
    Code:
       0: aload_0
       1: getfield      #4                  // Field plugins:Ljava/util/Map;
       4: aload_1
       5: invokeinterface #76,  2           // InterfaceMethod java/util/Map.get:(Ljava/lang/Object;)Ljava/lang/Object;
      10: checkcast     #77                 // class org/apache/cxf/tools/plugin/Plugin
      13: astore_2
      14: aload_2
      15: ifnonnull     197
      18: aconst_null
      19: astore_3
      20: new           #80                 // class java/io/File
      23: dup
      24: aload_1
      25: invokespecial #81                 // Method java/io/File."<init>":(Ljava/lang/String;)V
      28: invokevirtual #82                 // Method java/io/File.exists:()Z
      31: ifeq          60
      34: new           #83                 // class java/io/BufferedInputStream
      37: dup
      38: new           #84                 // class java/io/FileInputStream
      41: dup
      42: new           #80                 // class java/io/File
      45: dup
      46: aload_1
      47: invokespecial #81                 // Method java/io/File."<init>":(Ljava/lang/String;)V
      50: invokespecial #85                 // Method java/io/FileInputStream."<init>":(Ljava/io/File;)V
      53: invokespecial #86                 // Method java/io/BufferedInputStream."<init>":(Ljava/io/InputStream;)V
      56: astore_3
      57: goto          69
      60: aload_0
      61: invokevirtual #14                 // Method java/lang/Object.getClass:()Ljava/lang/Class;
      64: aload_1
      65: invokevirtual #87                 // Method java/lang/Class.getResourceAsStream:(Ljava/lang/String;)Ljava/io/InputStream;
      68: astore_3
      69: aload_3
      70: ifnonnull     119
      73: new           #18                 // class org/apache/cxf/common/i18n/Message
      76: dup
      77: ldc           #88                 // String PLUGIN_MISSING
      79: getstatic     #20                 // Field LOG:Ljava/util/logging/Logger;
      82: iconst_1
      83: anewarray     #21                 // class java/lang/Object
      86: dup
      87: iconst_0
      88: aload_1
      89: aastore
      90: invokespecial #22                 // Method org/apache/cxf/common/i18n/Message."<init>":(Ljava/lang/String;Ljava/util/logging/Logger;[Ljava/lang/Object;)V
      93: astore        4
      95: getstatic     #20                 // Field LOG:Ljava/util/logging/Logger;
      98: getstatic     #23                 // Field java/util/logging/Level.SEVERE:Ljava/util/logging/Level;
     101: aload         4
     103: invokevirtual #24                 // Method org/apache/cxf/common/i18n/Message.toString:()Ljava/lang/String;
     106: invokevirtual #25                 // Method java/util/logging/Logger.log:(Ljava/util/logging/Level;Ljava/lang/String;)V
     109: new           #26                 // class org/apache/cxf/tools/common/ToolException
     112: dup
     113: aload         4
     115: invokespecial #27                 // Method org/apache/cxf/tools/common/ToolException."<init>":(Lorg/apache/cxf/common/i18n/Message;)V
     118: athrow
     119: aload_0
     120: aload_3
     121: invokespecial #79                 // Method getPlugin:(Ljava/io/InputStream;)Lorg/apache/cxf/tools/plugin/Plugin;
     124: astore_2
     125: aload_2
     126: ifnull        139
     129: aload_2
     130: invokevirtual #53                 // Method org/apache/cxf/tools/plugin/Plugin.getName:()Ljava/lang/String;
     133: invokestatic  #59                 // Method org/apache/cxf/common/util/StringUtils.isEmpty:(Ljava/lang/String;)Z
     136: ifeq          185
     139: new           #18                 // class org/apache/cxf/common/i18n/Message
     142: dup
     143: ldc           #45                 // String PLUGIN_LOAD_FAIL
     145: getstatic     #20                 // Field LOG:Ljava/util/logging/Logger;
     148: iconst_1
     149: anewarray     #21                 // class java/lang/Object
     152: dup
     153: iconst_0
     154: aload_1
     155: aastore
     156: invokespecial #22                 // Method org/apache/cxf/common/i18n/Message."<init>":(Ljava/lang/String;Ljava/util/logging/Logger;[Ljava/lang/Object;)V
     159: astore        4
     161: getstatic     #20                 // Field LOG:Ljava/util/logging/Logger;
     164: getstatic     #23                 // Field java/util/logging/Level.SEVERE:Ljava/util/logging/Level;
     167: aload         4
     169: invokevirtual #24                 // Method org/apache/cxf/common/i18n/Message.toString:()Ljava/lang/String;
     172: invokevirtual #25                 // Method java/util/logging/Logger.log:(Ljava/util/logging/Level;Ljava/lang/String;)V
     175: new           #26                 // class org/apache/cxf/tools/common/ToolException
     178: dup
     179: aload         4
     181: invokespecial #27                 // Method org/apache/cxf/tools/common/ToolException."<init>":(Lorg/apache/cxf/common/i18n/Message;)V
     184: athrow
     185: aload_0
     186: getfield      #4                  // Field plugins:Ljava/util/Map;
     189: aload_1
     190: aload_2
     191: invokeinterface #67,  3           // InterfaceMethod java/util/Map.put:(Ljava/lang/Object;Ljava/lang/Object;)Ljava/lang/Object;
     196: pop
     197: aload_2
     198: areturn

  private org.apache.cxf.tools.plugin.Plugin getPlugin(java.io.InputStream) throws javax.xml.bind.JAXBException;
    Code:
       0: aload_1
       1: invokestatic  #89                 // Method org/apache/cxf/staxutils/StaxUtils.read:(Ljava/io/InputStream;)Lorg/w3c/dom/Document;
       4: astore_2
       5: aload_0
       6: getfield      #12                 // Field jaxbContext:Ljavax/xml/bind/JAXBContext;
       9: aload_2
      10: invokeinterface #90,  1           // InterfaceMethod org/w3c/dom/Document.getDocumentElement:()Lorg/w3c/dom/Element;
      15: ldc_w         #77                 // class org/apache/cxf/tools/plugin/Plugin
      18: invokestatic  #91                 // Method org/apache/cxf/common/jaxb/JAXBUtils.unmarshall:(Ljavax/xml/bind/JAXBContext;Lorg/w3c/dom/Element;Ljava/lang/Class;)Ljavax/xml/bind/JAXBElement;
      21: invokevirtual #92                 // Method javax/xml/bind/JAXBElement.getValue:()Ljava/lang/Object;
      24: checkcast     #77                 // class org/apache/cxf/tools/plugin/Plugin
      27: astore_3
      28: aload_1
      29: invokevirtual #93                 // Method java/io/InputStream.close:()V
      32: goto          37
      35: astore        4
      37: aload_3
      38: areturn
      39: astore_2
      40: new           #17                 // class javax/xml/bind/JAXBException
      43: dup
      44: aload_2
      45: invokespecial #95                 // Method javax/xml/bind/JAXBException."<init>":(Ljava/lang/Throwable;)V
      48: athrow
      49: astore        5
      51: aload_1
      52: invokevirtual #93                 // Method java/io/InputStream.close:()V
      55: goto          60
      58: astore        6
      60: aload         5
      62: athrow
    Exception table:
       from    to  target type
          28    32    35   Class java/io/IOException
           0    28    39   Class javax/xml/stream/XMLStreamException
           0    28    49   any
          51    55    58   Class java/io/IOException
          39    51    49   any

  public org.apache.cxf.tools.plugin.FrontEnd getFrontEnd(java.lang.String);
    Code:
       0: aload_0
       1: getfield      #5                  // Field frontends:Ljava/util/Map;
       4: aload_1
       5: invokeinterface #76,  2           // InterfaceMethod java/util/Map.get:(Ljava/lang/Object;)Ljava/lang/Object;
      10: checkcast     #56                 // class org/apache/cxf/tools/plugin/FrontEnd
      13: astore_2
      14: aload_2
      15: ifnonnull     48
      18: new           #18                 // class org/apache/cxf/common/i18n/Message
      21: dup
      22: ldc           #96                 // String FRONTEND_MISSING
      24: getstatic     #20                 // Field LOG:Ljava/util/logging/Logger;
      27: iconst_1
      28: anewarray     #21                 // class java/lang/Object
      31: dup
      32: iconst_0
      33: aload_1
      34: aastore
      35: invokespecial #22                 // Method org/apache/cxf/common/i18n/Message."<init>":(Ljava/lang/String;Ljava/util/logging/Logger;[Ljava/lang/Object;)V
      38: astore_3
      39: new           #26                 // class org/apache/cxf/tools/common/ToolException
      42: dup
      43: aload_3
      44: invokespecial #27                 // Method org/apache/cxf/tools/common/ToolException."<init>":(Lorg/apache/cxf/common/i18n/Message;)V
      47: athrow
      48: aload_2
      49: areturn

  private java.lang.String getGeneratorClass(org.apache.cxf.tools.plugin.FrontEnd, org.apache.cxf.tools.plugin.Generator);
    Code:
       0: aload_2
       1: invokevirtual #97                 // Method org/apache/cxf/tools/plugin/Generator.getPackage:()Ljava/lang/String;
       4: astore_3
       5: aload_3
       6: invokestatic  #59                 // Method org/apache/cxf/common/util/StringUtils.isEmpty:(Ljava/lang/String;)Z
       9: ifeq          20
      12: aload_1
      13: invokevirtual #98                 // Method org/apache/cxf/tools/plugin/FrontEnd.getGenerators:()Lorg/apache/cxf/tools/plugin/Generators;
      16: invokevirtual #99                 // Method org/apache/cxf/tools/plugin/Generators.getPackage:()Ljava/lang/String;
      19: astore_3
      20: aload_3
      21: invokestatic  #59                 // Method org/apache/cxf/common/util/StringUtils.isEmpty:(Ljava/lang/String;)Z
      24: ifeq          32
      27: aload_1
      28: invokevirtual #100                // Method org/apache/cxf/tools/plugin/FrontEnd.getPackage:()Ljava/lang/String;
      31: astore_3
      32: new           #101                // class java/lang/StringBuilder
      35: dup
      36: invokespecial #102                // Method java/lang/StringBuilder."<init>":()V
      39: aload_3
      40: invokevirtual #103                // Method java/lang/StringBuilder.append:(Ljava/lang/String;)Ljava/lang/StringBuilder;
      43: ldc           #104                // String .
      45: invokevirtual #103                // Method java/lang/StringBuilder.append:(Ljava/lang/String;)Ljava/lang/StringBuilder;
      48: aload_2
      49: invokevirtual #105                // Method org/apache/cxf/tools/plugin/Generator.getName:()Ljava/lang/String;
      52: invokevirtual #103                // Method java/lang/StringBuilder.append:(Ljava/lang/String;)Ljava/lang/StringBuilder;
      55: invokevirtual #106                // Method java/lang/StringBuilder.toString:()Ljava/lang/String;
      58: areturn

  private java.util.List<org.apache.cxf.tools.common.FrontEndGenerator> getFrontEndGenerators(org.apache.cxf.tools.plugin.FrontEnd);
    Code:
       0: new           #107                // class java/util/ArrayList
       3: dup
       4: invokespecial #108                // Method java/util/ArrayList."<init>":()V
       7: astore_2
       8: aconst_null
       9: astore_3
      10: aload_1
      11: invokevirtual #98                 // Method org/apache/cxf/tools/plugin/FrontEnd.getGenerators:()Lorg/apache/cxf/tools/plugin/Generators;
      14: invokevirtual #109                // Method org/apache/cxf/tools/plugin/Generators.getGenerator:()Ljava/util/List;
      17: invokeinterface #32,  1           // InterfaceMethod java/util/List.iterator:()Ljava/util/Iterator;
      22: astore        4
      24: aload         4
      26: invokeinterface #33,  1           // InterfaceMethod java/util/Iterator.hasNext:()Z
      31: ifeq          82
      34: aload         4
      36: invokeinterface #34,  1           // InterfaceMethod java/util/Iterator.next:()Ljava/lang/Object;
      41: checkcast     #110                // class org/apache/cxf/tools/plugin/Generator
      44: astore        5
      46: aload_0
      47: aload_1
      48: aload         5
      50: invokespecial #111                // Method getGeneratorClass:(Lorg/apache/cxf/tools/plugin/FrontEnd;Lorg/apache/cxf/tools/plugin/Generator;)Ljava/lang/String;
      53: astore_3
      54: aload_3
      55: aload_0
      56: invokevirtual #14                 // Method java/lang/Object.getClass:()Ljava/lang/Class;
      59: invokestatic  #112                // Method org/apache/cxf/common/classloader/ClassLoaderUtils.loadClass:(Ljava/lang/String;Ljava/lang/Class;)Ljava/lang/Class;
      62: astore        6
      64: aload_2
      65: aload         6
      67: invokevirtual #113                // Method java/lang/Class.newInstance:()Ljava/lang/Object;
      70: checkcast     #114                // class org/apache/cxf/tools/common/FrontEndGenerator
      73: invokeinterface #115,  2          // InterfaceMethod java/util/List.add:(Ljava/lang/Object;)Z
      78: pop
      79: goto          24
      82: goto          135
      85: astore        4
      87: new           #18                 // class org/apache/cxf/common/i18n/Message
      90: dup
      91: ldc           #117                // String FRONTEND_PROFILE_LOAD_FAIL
      93: getstatic     #20                 // Field LOG:Ljava/util/logging/Logger;
      96: iconst_1
      97: anewarray     #21                 // class java/lang/Object
     100: dup
     101: iconst_0
     102: aload_3
     103: aastore
     104: invokespecial #22                 // Method org/apache/cxf/common/i18n/Message."<init>":(Ljava/lang/String;Ljava/util/logging/Logger;[Ljava/lang/Object;)V
     107: astore        5
     109: getstatic     #20                 // Field LOG:Ljava/util/logging/Logger;
     112: getstatic     #23                 // Field java/util/logging/Level.SEVERE:Ljava/util/logging/Level;
     115: aload         5
     117: invokevirtual #24                 // Method org/apache/cxf/common/i18n/Message.toString:()Ljava/lang/String;
     120: invokevirtual #25                 // Method java/util/logging/Logger.log:(Ljava/util/logging/Level;Ljava/lang/String;)V
     123: new           #26                 // class org/apache/cxf/tools/common/ToolException
     126: dup
     127: aload         5
     129: aload         4
     131: invokespecial #46                 // Method org/apache/cxf/tools/common/ToolException."<init>":(Lorg/apache/cxf/common/i18n/Message;Ljava/lang/Throwable;)V
     134: athrow
     135: aload_2
     136: areturn
    Exception table:
       from    to  target type
          10    82    85   Class java/lang/Exception

  private org.apache.cxf.tools.wsdlto.core.FrontEndProfile loadFrontEndProfile(java.lang.String);
    Code:
       0: aconst_null
       1: astore_2
       2: aload_1
       3: aload_0
       4: invokevirtual #14                 // Method java/lang/Object.getClass:()Ljava/lang/Class;
       7: invokestatic  #112                // Method org/apache/cxf/common/classloader/ClassLoaderUtils.loadClass:(Ljava/lang/String;Ljava/lang/Class;)Ljava/lang/Class;
      10: astore_3
      11: aload_3
      12: invokevirtual #113                // Method java/lang/Class.newInstance:()Ljava/lang/Object;
      15: checkcast     #118                // class org/apache/cxf/tools/wsdlto/core/FrontEndProfile
      18: astore_2
      19: goto          70
      22: astore_3
      23: new           #18                 // class org/apache/cxf/common/i18n/Message
      26: dup
      27: ldc           #117                // String FRONTEND_PROFILE_LOAD_FAIL
      29: getstatic     #20                 // Field LOG:Ljava/util/logging/Logger;
      32: iconst_1
      33: anewarray     #21                 // class java/lang/Object
      36: dup
      37: iconst_0
      38: aload_1
      39: aastore
      40: invokespecial #22                 // Method org/apache/cxf/common/i18n/Message."<init>":(Ljava/lang/String;Ljava/util/logging/Logger;[Ljava/lang/Object;)V
      43: astore        4
      45: getstatic     #20                 // Field LOG:Ljava/util/logging/Logger;
      48: getstatic     #23                 // Field java/util/logging/Level.SEVERE:Ljava/util/logging/Level;
      51: aload         4
      53: invokevirtual #24                 // Method org/apache/cxf/common/i18n/Message.toString:()Ljava/lang/String;
      56: invokevirtual #25                 // Method java/util/logging/Logger.log:(Ljava/util/logging/Level;Ljava/lang/String;)V
      59: new           #26                 // class org/apache/cxf/tools/common/ToolException
      62: dup
      63: aload         4
      65: aload_3
      66: invokespecial #46                 // Method org/apache/cxf/tools/common/ToolException."<init>":(Lorg/apache/cxf/common/i18n/Message;Ljava/lang/Throwable;)V
      69: athrow
      70: aload_2
      71: areturn
    Exception table:
       from    to  target type
           2    19    22   Class java/lang/Exception

  private org.apache.cxf.tools.common.Processor loadProcessor(java.lang.String);
    Code:
       0: aconst_null
       1: astore_2
       2: aload_1
       3: aload_0
       4: invokevirtual #14                 // Method java/lang/Object.getClass:()Ljava/lang/Class;
       7: invokestatic  #112                // Method org/apache/cxf/common/classloader/ClassLoaderUtils.loadClass:(Ljava/lang/String;Ljava/lang/Class;)Ljava/lang/Class;
      10: invokevirtual #113                // Method java/lang/Class.newInstance:()Ljava/lang/Object;
      13: checkcast     #119                // class org/apache/cxf/tools/common/Processor
      16: astore_2
      17: goto          68
      20: astore_3
      21: new           #18                 // class org/apache/cxf/common/i18n/Message
      24: dup
      25: ldc           #120                // String LOAD_PROCESSOR_FAILED
      27: getstatic     #20                 // Field LOG:Ljava/util/logging/Logger;
      30: iconst_1
      31: anewarray     #21                 // class java/lang/Object
      34: dup
      35: iconst_0
      36: aload_1
      37: aastore
      38: invokespecial #22                 // Method org/apache/cxf/common/i18n/Message."<init>":(Ljava/lang/String;Ljava/util/logging/Logger;[Ljava/lang/Object;)V
      41: astore        4
      43: getstatic     #20                 // Field LOG:Ljava/util/logging/Logger;
      46: getstatic     #23                 // Field java/util/logging/Level.SEVERE:Ljava/util/logging/Level;
      49: aload         4
      51: invokevirtual #24                 // Method org/apache/cxf/common/i18n/Message.toString:()Ljava/lang/String;
      54: invokevirtual #25                 // Method java/util/logging/Logger.log:(Ljava/util/logging/Level;Ljava/lang/String;)V
      57: new           #26                 // class org/apache/cxf/tools/common/ToolException
      60: dup
      61: aload         4
      63: aload_3
      64: invokespecial #46                 // Method org/apache/cxf/tools/common/ToolException."<init>":(Lorg/apache/cxf/common/i18n/Message;Ljava/lang/Throwable;)V
      67: athrow
      68: aload_2
      69: areturn
    Exception table:
       from    to  target type
           2    17    20   Class java/lang/Exception

  private java.lang.Class<? extends org.apache.cxf.tools.common.toolspec.ToolContainer> loadContainerClass(java.lang.String);
    Code:
       0: aconst_null
       1: astore_2
       2: aload_1
       3: aload_0
       4: invokevirtual #14                 // Method java/lang/Object.getClass:()Ljava/lang/Class;
       7: invokestatic  #112                // Method org/apache/cxf/common/classloader/ClassLoaderUtils.loadClass:(Ljava/lang/String;Ljava/lang/Class;)Ljava/lang/Class;
      10: astore_2
      11: goto          62
      14: astore_3
      15: new           #18                 // class org/apache/cxf/common/i18n/Message
      18: dup
      19: ldc           #121                // String LOAD_CONTAINER_CLASS_FAILED
      21: getstatic     #20                 // Field LOG:Ljava/util/logging/Logger;
      24: iconst_1
      25: anewarray     #21                 // class java/lang/Object
      28: dup
      29: iconst_0
      30: aload_1
      31: aastore
      32: invokespecial #22                 // Method org/apache/cxf/common/i18n/Message."<init>":(Ljava/lang/String;Ljava/util/logging/Logger;[Ljava/lang/Object;)V
      35: astore        4
      37: getstatic     #20                 // Field LOG:Ljava/util/logging/Logger;
      40: getstatic     #23                 // Field java/util/logging/Level.SEVERE:Ljava/util/logging/Level;
      43: aload         4
      45: invokevirtual #24                 // Method org/apache/cxf/common/i18n/Message.toString:()Ljava/lang/String;
      48: invokevirtual #25                 // Method java/util/logging/Logger.log:(Ljava/util/logging/Level;Ljava/lang/String;)V
      51: new           #26                 // class org/apache/cxf/tools/common/ToolException
      54: dup
      55: aload         4
      57: aload_3
      58: invokespecial #46                 // Method org/apache/cxf/tools/common/ToolException."<init>":(Lorg/apache/cxf/common/i18n/Message;Ljava/lang/Throwable;)V
      61: athrow
      62: ldc_w         #122                // class org/apache/cxf/tools/common/toolspec/ToolContainer
      65: aload_2
      66: invokevirtual #123                // Method java/lang/Class.isAssignableFrom:(Ljava/lang/Class;)Z
      69: ifne          118
      72: new           #18                 // class org/apache/cxf/common/i18n/Message
      75: dup
      76: ldc           #124                // String CLZ_SHOULD_IMPLEMENT_INTERFACE
      78: getstatic     #20                 // Field LOG:Ljava/util/logging/Logger;
      81: iconst_1
      82: anewarray     #21                 // class java/lang/Object
      85: dup
      86: iconst_0
      87: aload_2
      88: invokevirtual #125                // Method java/lang/Class.getName:()Ljava/lang/String;
      91: aastore
      92: invokespecial #22                 // Method org/apache/cxf/common/i18n/Message."<init>":(Ljava/lang/String;Ljava/util/logging/Logger;[Ljava/lang/Object;)V
      95: astore_3
      96: getstatic     #20                 // Field LOG:Ljava/util/logging/Logger;
      99: getstatic     #23                 // Field java/util/logging/Level.SEVERE:Ljava/util/logging/Level;
     102: aload_3
     103: invokevirtual #24                 // Method org/apache/cxf/common/i18n/Message.toString:()Ljava/lang/String;
     106: invokevirtual #25                 // Method java/util/logging/Logger.log:(Ljava/util/logging/Level;Ljava/lang/String;)V
     109: new           #26                 // class org/apache/cxf/tools/common/ToolException
     112: dup
     113: aload_3
     114: invokespecial #27                 // Method org/apache/cxf/tools/common/ToolException."<init>":(Lorg/apache/cxf/common/i18n/Message;)V
     117: athrow
     118: aload_2
     119: ldc_w         #122                // class org/apache/cxf/tools/common/toolspec/ToolContainer
     122: invokevirtual #126                // Method java/lang/Class.asSubclass:(Ljava/lang/Class;)Ljava/lang/Class;
     125: areturn
    Exception table:
       from    to  target type
           2    11    14   Class java/lang/Exception

  private java.lang.String getFrontEndProfileClass(org.apache.cxf.tools.plugin.FrontEnd);
    Code:
       0: aload_1
       1: invokevirtual #127                // Method org/apache/cxf/tools/plugin/FrontEnd.getProfile:()Ljava/lang/String;
       4: invokestatic  #59                 // Method org/apache/cxf/common/util/StringUtils.isEmpty:(Ljava/lang/String;)Z
       7: ifeq          13
      10: ldc           #128                // String org.apache.cxf.tools.wsdlto.core.FrontEndProfile
      12: areturn
      13: new           #101                // class java/lang/StringBuilder
      16: dup
      17: invokespecial #102                // Method java/lang/StringBuilder."<init>":()V
      20: aload_1
      21: invokevirtual #100                // Method org/apache/cxf/tools/plugin/FrontEnd.getPackage:()Ljava/lang/String;
      24: invokevirtual #103                // Method java/lang/StringBuilder.append:(Ljava/lang/String;)Ljava/lang/StringBuilder;
      27: ldc           #104                // String .
      29: invokevirtual #103                // Method java/lang/StringBuilder.append:(Ljava/lang/String;)Ljava/lang/StringBuilder;
      32: aload_1
      33: invokevirtual #127                // Method org/apache/cxf/tools/plugin/FrontEnd.getProfile:()Ljava/lang/String;
      36: invokevirtual #103                // Method java/lang/StringBuilder.append:(Ljava/lang/String;)Ljava/lang/StringBuilder;
      39: invokevirtual #106                // Method java/lang/StringBuilder.toString:()Ljava/lang/String;
      42: areturn

  private java.lang.String getProcessorClass(org.apache.cxf.tools.plugin.FrontEnd);
    Code:
       0: aload_1
       1: invokevirtual #129                // Method org/apache/cxf/tools/plugin/FrontEnd.getProcessor:()Lorg/apache/cxf/tools/plugin/Processor;
       4: invokevirtual #130                // Method org/apache/cxf/tools/plugin/Processor.getPackage:()Ljava/lang/String;
       7: astore_2
       8: aload_2
       9: invokestatic  #59                 // Method org/apache/cxf/common/util/StringUtils.isEmpty:(Ljava/lang/String;)Z
      12: ifeq          20
      15: aload_1
      16: invokevirtual #100                // Method org/apache/cxf/tools/plugin/FrontEnd.getPackage:()Ljava/lang/String;
      19: astore_2
      20: new           #101                // class java/lang/StringBuilder
      23: dup
      24: invokespecial #102                // Method java/lang/StringBuilder."<init>":()V
      27: aload_2
      28: invokevirtual #103                // Method java/lang/StringBuilder.append:(Ljava/lang/String;)Ljava/lang/StringBuilder;
      31: ldc           #104                // String .
      33: invokevirtual #103                // Method java/lang/StringBuilder.append:(Ljava/lang/String;)Ljava/lang/StringBuilder;
      36: aload_1
      37: invokevirtual #129                // Method org/apache/cxf/tools/plugin/FrontEnd.getProcessor:()Lorg/apache/cxf/tools/plugin/Processor;
      40: invokevirtual #131                // Method org/apache/cxf/tools/plugin/Processor.getName:()Ljava/lang/String;
      43: invokevirtual #103                // Method java/lang/StringBuilder.append:(Ljava/lang/String;)Ljava/lang/StringBuilder;
      46: invokevirtual #106                // Method java/lang/StringBuilder.toString:()Ljava/lang/String;
      49: areturn

  private java.lang.String getContainerClass(org.apache.cxf.tools.plugin.FrontEnd);
    Code:
       0: new           #101                // class java/lang/StringBuilder
       3: dup
       4: invokespecial #102                // Method java/lang/StringBuilder."<init>":()V
       7: aload_0
       8: aload_1
       9: invokespecial #132                // Method getContainerPackage:(Lorg/apache/cxf/tools/plugin/FrontEnd;)Ljava/lang/String;
      12: invokevirtual #103                // Method java/lang/StringBuilder.append:(Ljava/lang/String;)Ljava/lang/StringBuilder;
      15: ldc           #104                // String .
      17: invokevirtual #103                // Method java/lang/StringBuilder.append:(Ljava/lang/String;)Ljava/lang/StringBuilder;
      20: aload_1
      21: invokevirtual #133                // Method org/apache/cxf/tools/plugin/FrontEnd.getContainer:()Lorg/apache/cxf/tools/plugin/Container;
      24: invokevirtual #134                // Method org/apache/cxf/tools/plugin/Container.getName:()Ljava/lang/String;
      27: invokevirtual #103                // Method java/lang/StringBuilder.append:(Ljava/lang/String;)Ljava/lang/StringBuilder;
      30: invokevirtual #106                // Method java/lang/StringBuilder.toString:()Ljava/lang/String;
      33: areturn

  private java.lang.String getContainerPackage(org.apache.cxf.tools.plugin.FrontEnd);
    Code:
       0: aload_1
       1: invokevirtual #133                // Method org/apache/cxf/tools/plugin/FrontEnd.getContainer:()Lorg/apache/cxf/tools/plugin/Container;
       4: invokevirtual #135                // Method org/apache/cxf/tools/plugin/Container.getPackage:()Ljava/lang/String;
       7: astore_2
       8: aload_2
       9: invokestatic  #59                 // Method org/apache/cxf/common/util/StringUtils.isEmpty:(Ljava/lang/String;)Z
      12: ifeq          20
      15: aload_1
      16: invokevirtual #100                // Method org/apache/cxf/tools/plugin/FrontEnd.getPackage:()Ljava/lang/String;
      19: astore_2
      20: aload_2
      21: areturn

  private java.lang.String getToolspec(org.apache.cxf.tools.plugin.FrontEnd);
    Code:
       0: aload_1
       1: invokevirtual #133                // Method org/apache/cxf/tools/plugin/FrontEnd.getContainer:()Lorg/apache/cxf/tools/plugin/Container;
       4: invokevirtual #136                // Method org/apache/cxf/tools/plugin/Container.getToolspec:()Ljava/lang/String;
       7: astore_2
       8: new           #101                // class java/lang/StringBuilder
      11: dup
      12: invokespecial #102                // Method java/lang/StringBuilder."<init>":()V
      15: ldc           #137                // String /
      17: invokevirtual #103                // Method java/lang/StringBuilder.append:(Ljava/lang/String;)Ljava/lang/StringBuilder;
      20: aload_0
      21: aload_1
      22: invokespecial #132                // Method getContainerPackage:(Lorg/apache/cxf/tools/plugin/FrontEnd;)Ljava/lang/String;
      25: ldc           #104                // String .
      27: ldc           #137                // String /
      29: invokevirtual #138                // Method java/lang/String.replace:(Ljava/lang/CharSequence;Ljava/lang/CharSequence;)Ljava/lang/String;
      32: invokevirtual #103                // Method java/lang/StringBuilder.append:(Ljava/lang/String;)Ljava/lang/StringBuilder;
      35: ldc           #137                // String /
      37: invokevirtual #103                // Method java/lang/StringBuilder.append:(Ljava/lang/String;)Ljava/lang/StringBuilder;
      40: aload_2
      41: invokevirtual #103                // Method java/lang/StringBuilder.append:(Ljava/lang/String;)Ljava/lang/StringBuilder;
      44: invokevirtual #106                // Method java/lang/StringBuilder.toString:()Ljava/lang/String;
      47: areturn

  private org.apache.cxf.tools.wsdlto.core.AbstractWSDLBuilder loadBuilder(java.lang.String);
    Code:
       0: aconst_null
       1: astore_2
       2: aload_1
       3: aload_0
       4: invokevirtual #14                 // Method java/lang/Object.getClass:()Ljava/lang/Class;
       7: invokestatic  #112                // Method org/apache/cxf/common/classloader/ClassLoaderUtils.loadClass:(Ljava/lang/String;Ljava/lang/Class;)Ljava/lang/Class;
      10: invokevirtual #113                // Method java/lang/Class.newInstance:()Ljava/lang/Object;
      13: checkcast     #139                // class org/apache/cxf/tools/wsdlto/core/AbstractWSDLBuilder
      16: astore_2
      17: goto          68
      20: astore_3
      21: new           #18                 // class org/apache/cxf/common/i18n/Message
      24: dup
      25: ldc           #120                // String LOAD_PROCESSOR_FAILED
      27: getstatic     #20                 // Field LOG:Ljava/util/logging/Logger;
      30: iconst_1
      31: anewarray     #21                 // class java/lang/Object
      34: dup
      35: iconst_0
      36: aload_1
      37: aastore
      38: invokespecial #22                 // Method org/apache/cxf/common/i18n/Message."<init>":(Ljava/lang/String;Ljava/util/logging/Logger;[Ljava/lang/Object;)V
      41: astore        4
      43: getstatic     #20                 // Field LOG:Ljava/util/logging/Logger;
      46: getstatic     #23                 // Field java/util/logging/Level.SEVERE:Ljava/util/logging/Level;
      49: aload         4
      51: invokevirtual #24                 // Method org/apache/cxf/common/i18n/Message.toString:()Ljava/lang/String;
      54: invokevirtual #25                 // Method java/util/logging/Logger.log:(Ljava/util/logging/Level;Ljava/lang/String;)V
      57: new           #26                 // class org/apache/cxf/tools/common/ToolException
      60: dup
      61: aload         4
      63: aload_3
      64: invokespecial #46                 // Method org/apache/cxf/tools/common/ToolException."<init>":(Lorg/apache/cxf/common/i18n/Message;Ljava/lang/Throwable;)V
      67: athrow
      68: aload_2
      69: areturn
    Exception table:
       from    to  target type
           2    17    20   Class java/lang/Exception

  private java.lang.String getBuilderClass(org.apache.cxf.tools.plugin.FrontEnd);
    Code:
       0: aload_1
       1: invokevirtual #140                // Method org/apache/cxf/tools/plugin/FrontEnd.getBuilder:()Lorg/apache/cxf/tools/plugin/Builder;
       4: invokevirtual #141                // Method org/apache/cxf/tools/plugin/Builder.getPackage:()Ljava/lang/String;
       7: astore_2
       8: aload_2
       9: invokestatic  #59                 // Method org/apache/cxf/common/util/StringUtils.isEmpty:(Ljava/lang/String;)Z
      12: ifeq          20
      15: aload_1
      16: invokevirtual #100                // Method org/apache/cxf/tools/plugin/FrontEnd.getPackage:()Ljava/lang/String;
      19: astore_2
      20: new           #101                // class java/lang/StringBuilder
      23: dup
      24: invokespecial #102                // Method java/lang/StringBuilder."<init>":()V
      27: aload_2
      28: invokevirtual #103                // Method java/lang/StringBuilder.append:(Ljava/lang/String;)Ljava/lang/StringBuilder;
      31: ldc           #104                // String .
      33: invokevirtual #103                // Method java/lang/StringBuilder.append:(Ljava/lang/String;)Ljava/lang/StringBuilder;
      36: aload_1
      37: invokevirtual #140                // Method org/apache/cxf/tools/plugin/FrontEnd.getBuilder:()Lorg/apache/cxf/tools/plugin/Builder;
      40: invokevirtual #142                // Method org/apache/cxf/tools/plugin/Builder.getName:()Ljava/lang/String;
      43: invokevirtual #103                // Method java/lang/StringBuilder.append:(Ljava/lang/String;)Ljava/lang/StringBuilder;
      46: invokevirtual #106                // Method java/lang/StringBuilder.toString:()Ljava/lang/String;
      49: areturn

  public org.apache.cxf.tools.wsdlto.core.FrontEndProfile getFrontEndProfile(java.lang.String);
    Code:
       0: aconst_null
       1: astore_2
       2: aload_0
       3: aload_1
       4: invokevirtual #143                // Method getFrontEnd:(Ljava/lang/String;)Lorg/apache/cxf/tools/plugin/FrontEnd;
       7: astore_3
       8: aload_0
       9: aload_0
      10: aload_3
      11: invokespecial #144                // Method getFrontEndProfileClass:(Lorg/apache/cxf/tools/plugin/FrontEnd;)Ljava/lang/String;
      14: invokespecial #145                // Method loadFrontEndProfile:(Ljava/lang/String;)Lorg/apache/cxf/tools/wsdlto/core/FrontEndProfile;
      17: astore_2
      18: aload_0
      19: aload_3
      20: invokespecial #146                // Method getFrontEndGenerators:(Lorg/apache/cxf/tools/plugin/FrontEnd;)Ljava/util/List;
      23: invokeinterface #32,  1           // InterfaceMethod java/util/List.iterator:()Ljava/util/Iterator;
      28: astore        4
      30: aload         4
      32: invokeinterface #33,  1           // InterfaceMethod java/util/Iterator.hasNext:()Z
      37: ifeq          61
      40: aload         4
      42: invokeinterface #34,  1           // InterfaceMethod java/util/Iterator.next:()Ljava/lang/Object;
      47: checkcast     #114                // class org/apache/cxf/tools/common/FrontEndGenerator
      50: astore        5
      52: aload_2
      53: aload         5
      55: invokevirtual #147                // Method org/apache/cxf/tools/wsdlto/core/FrontEndProfile.registerGenerator:(Lorg/apache/cxf/tools/common/FrontEndGenerator;)V
      58: goto          30
      61: aload_3
      62: invokevirtual #129                // Method org/apache/cxf/tools/plugin/FrontEnd.getProcessor:()Lorg/apache/cxf/tools/plugin/Processor;
      65: ifnull        81
      68: aload_2
      69: aload_0
      70: aload_0
      71: aload_3
      72: invokespecial #148                // Method getProcessorClass:(Lorg/apache/cxf/tools/plugin/FrontEnd;)Ljava/lang/String;
      75: invokespecial #149                // Method loadProcessor:(Ljava/lang/String;)Lorg/apache/cxf/tools/common/Processor;
      78: invokevirtual #150                // Method org/apache/cxf/tools/wsdlto/core/FrontEndProfile.setProcessor:(Lorg/apache/cxf/tools/common/Processor;)V
      81: aload_3
      82: invokevirtual #133                // Method org/apache/cxf/tools/plugin/FrontEnd.getContainer:()Lorg/apache/cxf/tools/plugin/Container;
      85: ifnull        110
      88: aload_2
      89: aload_0
      90: aload_0
      91: aload_3
      92: invokespecial #151                // Method getContainerClass:(Lorg/apache/cxf/tools/plugin/FrontEnd;)Ljava/lang/String;
      95: invokespecial #152                // Method loadContainerClass:(Ljava/lang/String;)Ljava/lang/Class;
      98: invokevirtual #153                // Method org/apache/cxf/tools/wsdlto/core/FrontEndProfile.setContainerClass:(Ljava/lang/Class;)V
     101: aload_2
     102: aload_0
     103: aload_3
     104: invokespecial #154                // Method getToolspec:(Lorg/apache/cxf/tools/plugin/FrontEnd;)Ljava/lang/String;
     107: invokevirtual #155                // Method org/apache/cxf/tools/wsdlto/core/FrontEndProfile.setToolspec:(Ljava/lang/String;)V
     110: aload_3
     111: invokevirtual #140                // Method org/apache/cxf/tools/plugin/FrontEnd.getBuilder:()Lorg/apache/cxf/tools/plugin/Builder;
     114: ifnull        130
     117: aload_2
     118: aload_0
     119: aload_0
     120: aload_3
     121: invokespecial #156                // Method getBuilderClass:(Lorg/apache/cxf/tools/plugin/FrontEnd;)Ljava/lang/String;
     124: invokespecial #157                // Method loadBuilder:(Ljava/lang/String;)Lorg/apache/cxf/tools/wsdlto/core/AbstractWSDLBuilder;
     127: invokevirtual #158                // Method org/apache/cxf/tools/wsdlto/core/FrontEndProfile.setWSDLBuilder:(Lorg/apache/cxf/tools/wsdlto/core/AbstractWSDLBuilder;)V
     130: aload_2
     131: areturn

  public org.apache.cxf.tools.plugin.DataBinding getDataBinding(java.lang.String);
    Code:
       0: aload_0
       1: getfield      #8                  // Field databindings:Ljava/util/Map;
       4: aload_1
       5: invokeinterface #76,  2           // InterfaceMethod java/util/Map.get:(Ljava/lang/Object;)Ljava/lang/Object;
      10: checkcast     #70                 // class org/apache/cxf/tools/plugin/DataBinding
      13: astore_2
      14: aload_2
      15: ifnonnull     48
      18: new           #18                 // class org/apache/cxf/common/i18n/Message
      21: dup
      22: ldc           #159                // String DATABINDING_MISSING
      24: getstatic     #20                 // Field LOG:Ljava/util/logging/Logger;
      27: iconst_1
      28: anewarray     #21                 // class java/lang/Object
      31: dup
      32: iconst_0
      33: aload_1
      34: aastore
      35: invokespecial #22                 // Method org/apache/cxf/common/i18n/Message."<init>":(Ljava/lang/String;Ljava/util/logging/Logger;[Ljava/lang/Object;)V
      38: astore_3
      39: new           #26                 // class org/apache/cxf/tools/common/ToolException
      42: dup
      43: aload_3
      44: invokespecial #27                 // Method org/apache/cxf/tools/common/ToolException."<init>":(Lorg/apache/cxf/common/i18n/Message;)V
      47: athrow
      48: aload_2
      49: areturn

  private org.apache.cxf.tools.wsdlto.core.DataBindingProfile loadDataBindingProfile(java.lang.String);
    Code:
       0: aconst_null
       1: astore_2
       2: aload_1
       3: aload_0
       4: invokevirtual #14                 // Method java/lang/Object.getClass:()Ljava/lang/Class;
       7: invokestatic  #112                // Method org/apache/cxf/common/classloader/ClassLoaderUtils.loadClass:(Ljava/lang/String;Ljava/lang/Class;)Ljava/lang/Class;
      10: invokevirtual #113                // Method java/lang/Class.newInstance:()Ljava/lang/Object;
      13: checkcast     #160                // class org/apache/cxf/tools/wsdlto/core/DataBindingProfile
      16: astore_2
      17: goto          67
      20: astore_3
      21: new           #18                 // class org/apache/cxf/common/i18n/Message
      24: dup
      25: ldc           #161                // String DATABINDING_PROFILE_LOAD_FAIL
      27: getstatic     #20                 // Field LOG:Ljava/util/logging/Logger;
      30: iconst_1
      31: anewarray     #21                 // class java/lang/Object
      34: dup
      35: iconst_0
      36: aload_1
      37: aastore
      38: invokespecial #22                 // Method org/apache/cxf/common/i18n/Message."<init>":(Ljava/lang/String;Ljava/util/logging/Logger;[Ljava/lang/Object;)V
      41: astore        4
      43: getstatic     #20                 // Field LOG:Ljava/util/logging/Logger;
      46: getstatic     #23                 // Field java/util/logging/Level.SEVERE:Ljava/util/logging/Level;
      49: aload         4
      51: invokevirtual #24                 // Method org/apache/cxf/common/i18n/Message.toString:()Ljava/lang/String;
      54: invokevirtual #25                 // Method java/util/logging/Logger.log:(Ljava/util/logging/Level;Ljava/lang/String;)V
      57: new           #26                 // class org/apache/cxf/tools/common/ToolException
      60: dup
      61: aload         4
      63: invokespecial #27                 // Method org/apache/cxf/tools/common/ToolException."<init>":(Lorg/apache/cxf/common/i18n/Message;)V
      66: athrow
      67: aload_2
      68: areturn
    Exception table:
       from    to  target type
           2    17    20   Class java/lang/Exception

  public org.apache.cxf.tools.wsdlto.core.DataBindingProfile getDataBindingProfile(java.lang.String);
    Code:
       0: aconst_null
       1: astore_2
       2: aload_0
       3: aload_1
       4: invokevirtual #162                // Method getDataBinding:(Ljava/lang/String;)Lorg/apache/cxf/tools/plugin/DataBinding;
       7: astore_3
       8: aload_0
       9: new           #101                // class java/lang/StringBuilder
      12: dup
      13: invokespecial #102                // Method java/lang/StringBuilder."<init>":()V
      16: aload_3
      17: invokevirtual #163                // Method org/apache/cxf/tools/plugin/DataBinding.getPackage:()Ljava/lang/String;
      20: invokevirtual #103                // Method java/lang/StringBuilder.append:(Ljava/lang/String;)Ljava/lang/StringBuilder;
      23: ldc           #104                // String .
      25: invokevirtual #103                // Method java/lang/StringBuilder.append:(Ljava/lang/String;)Ljava/lang/StringBuilder;
      28: aload_3
      29: invokevirtual #164                // Method org/apache/cxf/tools/plugin/DataBinding.getProfile:()Ljava/lang/String;
      32: invokevirtual #103                // Method java/lang/StringBuilder.append:(Ljava/lang/String;)Ljava/lang/StringBuilder;
      35: invokevirtual #106                // Method java/lang/StringBuilder.toString:()Ljava/lang/String;
      38: invokespecial #165                // Method loadDataBindingProfile:(Ljava/lang/String;)Lorg/apache/cxf/tools/wsdlto/core/DataBindingProfile;
      41: astore_2
      42: aload_2
      43: areturn

  public java.util.Map<java.lang.String, org.apache.cxf.tools.plugin.FrontEnd> getFrontEnds();
    Code:
       0: aload_0
       1: getfield      #5                  // Field frontends:Ljava/util/Map;
       4: areturn

  public java.util.Map<java.lang.String, org.apache.cxf.tools.plugin.DataBinding> getDataBindings();
    Code:
       0: aload_0
       1: getfield      #8                  // Field databindings:Ljava/util/Map;
       4: areturn

  public java.util.Map<java.lang.String, org.apache.cxf.tools.plugin.Plugin> getPlugins();
    Code:
       0: aload_0
       1: getfield      #4                  // Field plugins:Ljava/util/Map;
       4: areturn

  static {};
    Code:
       0: ldc_w         #37                 // class org/apache/cxf/tools/wsdlto/core/PluginLoader
       3: invokestatic  #166                // Method org/apache/cxf/common/logging/LogUtils.getL7dLogger:(Ljava/lang/Class;)Ljava/util/logging/Logger;
       6: putstatic     #20                 // Field LOG:Ljava/util/logging/Logger;
       9: return
}
