Compiled from "ImplicitGrantConfigurer.java"
public final class org.springframework.security.config.annotation.web.configurers.oauth2.client.ImplicitGrantConfigurer<B extends org.springframework.security.config.annotation.web.HttpSecurityBuilder<B>> extends org.springframework.security.config.annotation.web.configurers.AbstractHttpConfigurer<org.springframework.security.config.annotation.web.configurers.oauth2.client.ImplicitGrantConfigurer<B>, B> {
  private java.lang.String authorizationRequestBaseUri;

  public org.springframework.security.config.annotation.web.configurers.oauth2.client.ImplicitGrantConfigurer();
    Code:
       0: aload_0
       1: invokespecial #1                  // Method org/springframework/security/config/annotation/web/configurers/AbstractHttpConfigurer."<init>":()V
       4: return

  public org.springframework.security.config.annotation.web.configurers.oauth2.client.ImplicitGrantConfigurer<B> authorizationRequestBaseUri(java.lang.String);
    Code:
       0: aload_1
       1: ldc           #2                  // String authorizationRequestBaseUri cannot be empty
       3: invokestatic  #3                  // Method org/springframework/util/Assert.hasText:(Ljava/lang/String;Ljava/lang/String;)V
       6: aload_0
       7: aload_1
       8: putfield      #4                  // Field authorizationRequestBaseUri:Ljava/lang/String;
      11: aload_0
      12: areturn

  public org.springframework.security.config.annotation.web.configurers.oauth2.client.ImplicitGrantConfigurer<B> clientRegistrationRepository(org.springframework.security.oauth2.client.registration.ClientRegistrationRepository);
    Code:
       0: aload_1
       1: ldc           #5                  // String clientRegistrationRepository cannot be null
       3: invokestatic  #6                  // Method org/springframework/util/Assert.notNull:(Ljava/lang/Object;Ljava/lang/String;)V
       6: aload_0
       7: invokevirtual #7                  // Method getBuilder:()Lorg/springframework/security/config/annotation/SecurityBuilder;
      10: checkcast     #8                  // class org/springframework/security/config/annotation/web/HttpSecurityBuilder
      13: ldc           #9                  // class org/springframework/security/oauth2/client/registration/ClientRegistrationRepository
      15: aload_1
      16: invokeinterface #10,  3           // InterfaceMethod org/springframework/security/config/annotation/web/HttpSecurityBuilder.setSharedObject:(Ljava/lang/Class;Ljava/lang/Object;)V
      21: aload_0
      22: areturn

  public void configure(B) throws java.lang.Exception;
    Code:
       0: new           #11                 // class org/springframework/security/oauth2/client/web/OAuth2AuthorizationRequestRedirectFilter
       3: dup
       4: aload_0
       5: invokespecial #12                 // Method getClientRegistrationRepository:()Lorg/springframework/security/oauth2/client/registration/ClientRegistrationRepository;
       8: aload_0
       9: invokespecial #13                 // Method getAuthorizationRequestBaseUri:()Ljava/lang/String;
      12: invokespecial #14                 // Method org/springframework/security/oauth2/client/web/OAuth2AuthorizationRequestRedirectFilter."<init>":(Lorg/springframework/security/oauth2/client/registration/ClientRegistrationRepository;Ljava/lang/String;)V
      15: astore_2
      16: aload_1
      17: aload_0
      18: aload_2
      19: invokevirtual #15                 // Method postProcess:(Ljava/lang/Object;)Ljava/lang/Object;
      22: checkcast     #16                 // class javax/servlet/Filter
      25: invokeinterface #17,  2           // InterfaceMethod org/springframework/security/config/annotation/web/HttpSecurityBuilder.addFilter:(Ljavax/servlet/Filter;)Lorg/springframework/security/config/annotation/web/HttpSecurityBuilder;
      30: pop
      31: return

  private java.lang.String getAuthorizationRequestBaseUri();
    Code:
       0: aload_0
       1: getfield      #4                  // Field authorizationRequestBaseUri:Ljava/lang/String;
       4: ifnull        14
       7: aload_0
       8: getfield      #4                  // Field authorizationRequestBaseUri:Ljava/lang/String;
      11: goto          16
      14: ldc           #18                 // String /oauth2/authorization
      16: areturn

  private org.springframework.security.oauth2.client.registration.ClientRegistrationRepository getClientRegistrationRepository();
    Code:
       0: aload_0
       1: invokevirtual #7                  // Method getBuilder:()Lorg/springframework/security/config/annotation/SecurityBuilder;
       4: checkcast     #8                  // class org/springframework/security/config/annotation/web/HttpSecurityBuilder
       7: ldc           #9                  // class org/springframework/security/oauth2/client/registration/ClientRegistrationRepository
       9: invokeinterface #19,  2           // InterfaceMethod org/springframework/security/config/annotation/web/HttpSecurityBuilder.getSharedObject:(Ljava/lang/Class;)Ljava/lang/Object;
      14: checkcast     #9                  // class org/springframework/security/oauth2/client/registration/ClientRegistrationRepository
      17: astore_1
      18: aload_1
      19: ifnonnull     42
      22: aload_0
      23: invokespecial #20                 // Method getClientRegistrationRepositoryBean:()Lorg/springframework/security/oauth2/client/registration/ClientRegistrationRepository;
      26: astore_1
      27: aload_0
      28: invokevirtual #7                  // Method getBuilder:()Lorg/springframework/security/config/annotation/SecurityBuilder;
      31: checkcast     #8                  // class org/springframework/security/config/annotation/web/HttpSecurityBuilder
      34: ldc           #9                  // class org/springframework/security/oauth2/client/registration/ClientRegistrationRepository
      36: aload_1
      37: invokeinterface #10,  3           // InterfaceMethod org/springframework/security/config/annotation/web/HttpSecurityBuilder.setSharedObject:(Ljava/lang/Class;Ljava/lang/Object;)V
      42: aload_1
      43: areturn

  private org.springframework.security.oauth2.client.registration.ClientRegistrationRepository getClientRegistrationRepositoryBean();
    Code:
       0: aload_0
       1: invokevirtual #7                  // Method getBuilder:()Lorg/springframework/security/config/annotation/SecurityBuilder;
       4: checkcast     #8                  // class org/springframework/security/config/annotation/web/HttpSecurityBuilder
       7: ldc           #21                 // class org/springframework/context/ApplicationContext
       9: invokeinterface #19,  2           // InterfaceMethod org/springframework/security/config/annotation/web/HttpSecurityBuilder.getSharedObject:(Ljava/lang/Class;)Ljava/lang/Object;
      14: checkcast     #21                 // class org/springframework/context/ApplicationContext
      17: ldc           #9                  // class org/springframework/security/oauth2/client/registration/ClientRegistrationRepository
      19: invokeinterface #22,  2           // InterfaceMethod org/springframework/context/ApplicationContext.getBean:(Ljava/lang/Class;)Ljava/lang/Object;
      24: checkcast     #9                  // class org/springframework/security/oauth2/client/registration/ClientRegistrationRepository
      27: areturn

  public void configure(org.springframework.security.config.annotation.SecurityBuilder) throws java.lang.Exception;
    Code:
       0: aload_0
       1: aload_1
       2: checkcast     #8                  // class org/springframework/security/config/annotation/web/HttpSecurityBuilder
       5: invokevirtual #23                 // Method configure:(Lorg/springframework/security/config/annotation/web/HttpSecurityBuilder;)V
       8: return
}
