Compiled from "Kweb.kt"
final class kweb.Kweb$listenForWebsocketConnection$3 extends kotlin.jvm.internal.Lambda implements kotlin.jvm.functions.Function0<java.lang.Object> {
  final kweb.client.RemoteClientState $remoteClientState;

  final kweb.client.ClientConnection$Caching $cachedConnection;

  kweb.Kweb$listenForWebsocketConnection$3(kweb.client.RemoteClientState, kweb.client.ClientConnection$Caching);
    Code:
       0: aload_0
       1: aload_1
       2: putfield      #13                 // Field $remoteClientState:Lkweb/client/RemoteClientState;
       5: aload_0
       6: aload_2
       7: putfield      #17                 // Field $cachedConnection:Lkweb/client/ClientConnection$Caching;
      10: aload_0
      11: iconst_0
      12: invokespecial #20                 // Method kotlin/jvm/internal/Lambda."<init>":(I)V
      15: return

  public final java.lang.Object invoke();
    Code:
       0: aload_0
       1: getfield      #13                 // Field $remoteClientState:Lkweb/client/RemoteClientState;
       4: invokevirtual #31                 // Method kweb/client/RemoteClientState.getId:()Ljava/lang/String;
       7: aload_0
       8: getfield      #17                 // Field $cachedConnection:Lkweb/client/ClientConnection$Caching;
      11: invokevirtual #37                 // Method kweb/client/ClientConnection$Caching.getSize:()I
      14: invokedynamic #49,  0             // InvokeDynamic #0:makeConcatWithConstants:(Ljava/lang/String;I)Ljava/lang/String;
      19: areturn
}
