Compiled from "Kweb.kt"
final class kweb.Kweb$createServer$1 extends kotlin.jvm.internal.Lambda implements kotlin.jvm.functions.Function1<io.ktor.server.engine.ApplicationEngineEnvironmentBuilder, kotlin.Unit> {
  final io.ktor.server.engine.EngineSSLConnectorConfig $httpsConfig;

  final kweb.Kweb this$0;

  final kotlin.jvm.functions.Function1<kweb.WebBrowser, kotlin.Unit> $buildPage;

  final int $port;

  kweb.Kweb$createServer$1(io.ktor.server.engine.EngineSSLConnectorConfig, kweb.Kweb, kotlin.jvm.functions.Function1<? super kweb.WebBrowser, kotlin.Unit>, int);
    Code:
       0: aload_0
       1: aload_1
       2: putfield      #14                 // Field $httpsConfig:Lio/ktor/server/engine/EngineSSLConnectorConfig;
       5: aload_0
       6: aload_2
       7: putfield      #18                 // Field this$0:Lkweb/Kweb;
      10: aload_0
      11: aload_3
      12: putfield      #22                 // Field $buildPage:Lkotlin/jvm/functions/Function1;
      15: aload_0
      16: iload         4
      18: putfield      #26                 // Field $port:I
      21: aload_0
      22: iconst_1
      23: invokespecial #29                 // Method kotlin/jvm/internal/Lambda."<init>":(I)V
      26: return

  public final void invoke(io.ktor.server.engine.ApplicationEngineEnvironmentBuilder);
    Code:
       0: aload_1
       1: ldc           #37                 // String $this$applicationEngineEnvironment
       3: invokestatic  #43                 // Method kotlin/jvm/internal/Intrinsics.checkNotNullParameter:(Ljava/lang/Object;Ljava/lang/String;)V
       6: aload_1
       7: new           #45                 // class kweb/Kweb$createServer$1$1
      10: dup
      11: aload_0
      12: getfield      #18                 // Field this$0:Lkweb/Kweb;
      15: aload_0
      16: getfield      #22                 // Field $buildPage:Lkotlin/jvm/functions/Function1;
      19: invokespecial #48                 // Method kweb/Kweb$createServer$1$1."<init>":(Lkweb/Kweb;Lkotlin/jvm/functions/Function1;)V
      22: checkcast     #7                  // class kotlin/jvm/functions/Function1
      25: invokevirtual #54                 // Method io/ktor/server/engine/ApplicationEngineEnvironmentBuilder.module:(Lkotlin/jvm/functions/Function1;)V
      28: aload_1
      29: astore_2
      30: aload_0
      31: getfield      #26                 // Field $port:I
      34: istore_3
      35: iconst_0
      36: istore        4
      38: aload_2
      39: invokevirtual #58                 // Method io/ktor/server/engine/ApplicationEngineEnvironmentBuilder.getConnectors:()Ljava/util/List;
      42: new           #60                 // class io/ktor/server/engine/EngineConnectorBuilder
      45: dup
      46: aconst_null
      47: iconst_1
      48: aconst_null
      49: invokespecial #63                 // Method io/ktor/server/engine/EngineConnectorBuilder."<init>":(Lio/ktor/server/engine/ConnectorType;ILkotlin/jvm/internal/DefaultConstructorMarker;)V
      52: astore        5
      54: aload         5
      56: astore        6
      58: astore        8
      60: iconst_0
      61: istore        7
      63: aload         6
      65: iload_3
      66: invokevirtual #66                 // Method io/ktor/server/engine/EngineConnectorBuilder.setPort:(I)V
      69: aload         6
      71: ldc           #68                 // String 0.0.0.0
      73: invokevirtual #72                 // Method io/ktor/server/engine/EngineConnectorBuilder.setHost:(Ljava/lang/String;)V
      76: nop
      77: aload         8
      79: aload         5
      81: invokeinterface #78,  2           // InterfaceMethod java/util/List.add:(Ljava/lang/Object;)Z
      86: pop
      87: nop
      88: aload_0
      89: getfield      #14                 // Field $httpsConfig:Lio/ktor/server/engine/EngineSSLConnectorConfig;
      92: ifnull        109
      95: aload_1
      96: invokevirtual #58                 // Method io/ktor/server/engine/ApplicationEngineEnvironmentBuilder.getConnectors:()Ljava/util/List;
      99: aload_0
     100: getfield      #14                 // Field $httpsConfig:Lio/ktor/server/engine/EngineSSLConnectorConfig;
     103: invokeinterface #78,  2           // InterfaceMethod java/util/List.add:(Ljava/lang/Object;)Z
     108: pop
     109: return

  public java.lang.Object invoke(java.lang.Object);
    Code:
       0: aload_0
       1: aload_1
       2: checkcast     #50                 // class io/ktor/server/engine/ApplicationEngineEnvironmentBuilder
       5: invokevirtual #87                 // Method invoke:(Lio/ktor/server/engine/ApplicationEngineEnvironmentBuilder;)V
       8: getstatic     #93                 // Field kotlin/Unit.INSTANCE:Lkotlin/Unit;
      11: areturn
}
