Compiled from "WebBrowser.kt"
final class kweb.WebBrowser$callJsFunctionWithResult$3 extends kotlin.jvm.internal.Lambda implements kotlin.jvm.functions.Function1<kotlinx.serialization.json.JsonElement, kotlin.Unit> {
  final kotlinx.coroutines.CompletableDeferred<kotlinx.serialization.json.JsonElement> $cd;

  kweb.WebBrowser$callJsFunctionWithResult$3(kotlinx.coroutines.CompletableDeferred<kotlinx.serialization.json.JsonElement>);
    Code:
       0: aload_0
       1: aload_1
       2: putfield      #14                 // Field $cd:Lkotlinx/coroutines/CompletableDeferred;
       5: aload_0
       6: iconst_1
       7: invokespecial #17                 // Method kotlin/jvm/internal/Lambda."<init>":(I)V
      10: return

  public final void invoke(kotlinx.serialization.json.JsonElement);
    Code:
       0: aload_1
       1: ldc           #24                 // String response
       3: invokestatic  #30                 // Method kotlin/jvm/internal/Intrinsics.checkNotNullParameter:(Ljava/lang/Object;Ljava/lang/String;)V
       6: aload_0
       7: getfield      #14                 // Field $cd:Lkotlinx/coroutines/CompletableDeferred;
      10: aload_1
      11: invokeinterface #36,  2           // InterfaceMethod kotlinx/coroutines/CompletableDeferred.complete:(Ljava/lang/Object;)Z
      16: pop
      17: return

  public java.lang.Object invoke(java.lang.Object);
    Code:
       0: aload_0
       1: aload_1
       2: checkcast     #40                 // class kotlinx/serialization/json/JsonElement
       5: invokevirtual #42                 // Method invoke:(Lkotlinx/serialization/json/JsonElement;)V
       8: getstatic     #48                 // Field kotlin/Unit.INSTANCE:Lkotlin/Unit;
      11: areturn
}
