Compiled from "X509TrustManagerWrapper.java"
final class io.netty.handler.ssl.util.X509TrustManagerWrapper extends javax.net.ssl.X509ExtendedTrustManager {
  private final javax.net.ssl.X509TrustManager delegate;

  io.netty.handler.ssl.util.X509TrustManagerWrapper(javax.net.ssl.X509TrustManager);
    Code:
       0: aload_0
       1: invokespecial #1                  // Method javax/net/ssl/X509ExtendedTrustManager."<init>":()V
       4: aload_0
       5: aload_1
       6: ldc           #2                  // String delegate
       8: invokestatic  #3                  // Method io/netty/util/internal/ObjectUtil.checkNotNull:(Ljava/lang/Object;Ljava/lang/String;)Ljava/lang/Object;
      11: checkcast     #4                  // class javax/net/ssl/X509TrustManager
      14: putfield      #5                  // Field delegate:Ljavax/net/ssl/X509TrustManager;
      17: return

  public void checkClientTrusted(java.security.cert.X509Certificate[], java.lang.String) throws java.security.cert.CertificateException;
    Code:
       0: aload_0
       1: getfield      #5                  // Field delegate:Ljavax/net/ssl/X509TrustManager;
       4: aload_1
       5: aload_2
       6: invokeinterface #6,  3            // InterfaceMethod javax/net/ssl/X509TrustManager.checkClientTrusted:([Ljava/security/cert/X509Certificate;Ljava/lang/String;)V
      11: return

  public void checkClientTrusted(java.security.cert.X509Certificate[], java.lang.String, java.net.Socket) throws java.security.cert.CertificateException;
    Code:
       0: aload_0
       1: getfield      #5                  // Field delegate:Ljavax/net/ssl/X509TrustManager;
       4: aload_1
       5: aload_2
       6: invokeinterface #6,  3            // InterfaceMethod javax/net/ssl/X509TrustManager.checkClientTrusted:([Ljava/security/cert/X509Certificate;Ljava/lang/String;)V
      11: return

  public void checkClientTrusted(java.security.cert.X509Certificate[], java.lang.String, javax.net.ssl.SSLEngine) throws java.security.cert.CertificateException;
    Code:
       0: aload_0
       1: getfield      #5                  // Field delegate:Ljavax/net/ssl/X509TrustManager;
       4: aload_1
       5: aload_2
       6: invokeinterface #6,  3            // InterfaceMethod javax/net/ssl/X509TrustManager.checkClientTrusted:([Ljava/security/cert/X509Certificate;Ljava/lang/String;)V
      11: return

  public void checkServerTrusted(java.security.cert.X509Certificate[], java.lang.String) throws java.security.cert.CertificateException;
    Code:
       0: aload_0
       1: getfield      #5                  // Field delegate:Ljavax/net/ssl/X509TrustManager;
       4: aload_1
       5: aload_2
       6: invokeinterface #7,  3            // InterfaceMethod javax/net/ssl/X509TrustManager.checkServerTrusted:([Ljava/security/cert/X509Certificate;Ljava/lang/String;)V
      11: return

  public void checkServerTrusted(java.security.cert.X509Certificate[], java.lang.String, java.net.Socket) throws java.security.cert.CertificateException;
    Code:
       0: aload_0
       1: getfield      #5                  // Field delegate:Ljavax/net/ssl/X509TrustManager;
       4: aload_1
       5: aload_2
       6: invokeinterface #7,  3            // InterfaceMethod javax/net/ssl/X509TrustManager.checkServerTrusted:([Ljava/security/cert/X509Certificate;Ljava/lang/String;)V
      11: return

  public void checkServerTrusted(java.security.cert.X509Certificate[], java.lang.String, javax.net.ssl.SSLEngine) throws java.security.cert.CertificateException;
    Code:
       0: aload_0
       1: getfield      #5                  // Field delegate:Ljavax/net/ssl/X509TrustManager;
       4: aload_1
       5: aload_2
       6: invokeinterface #7,  3            // InterfaceMethod javax/net/ssl/X509TrustManager.checkServerTrusted:([Ljava/security/cert/X509Certificate;Ljava/lang/String;)V
      11: return

  public java.security.cert.X509Certificate[] getAcceptedIssuers();
    Code:
       0: aload_0
       1: getfield      #5                  // Field delegate:Ljavax/net/ssl/X509TrustManager;
       4: invokeinterface #8,  1            // InterfaceMethod javax/net/ssl/X509TrustManager.getAcceptedIssuers:()[Ljava/security/cert/X509Certificate;
       9: areturn
}
