Compiled from "DnsClient.java"
public class org.graylog2.lookup.adapters.dnslookup.DnsClient {
  private static final org.slf4j.Logger LOG;

  private static final int DEFAULT_DNS_PORT;

  private static final java.util.regex.Pattern VALID_HOSTNAME_PATTERN;

  private static final java.lang.String IP_4_REVERSE_SUFFIX;

  private static final java.lang.String IP_6_REVERSE_SUFFIX;

  private static final java.lang.String IP_4_VERSION;

  private static final java.lang.String IP_6_VERSION;

  private static final char[] HEX_CHARS_ARRAY;

  private io.netty.channel.nio.NioEventLoopGroup nettyEventLoop;

  private io.netty.resolver.dns.DnsNameResolver resolver;

  public org.graylog2.lookup.adapters.dnslookup.DnsClient();
    Code:
       0: aload_0
       1: invokespecial #1                  // Method java/lang/Object."<init>":()V
       4: return

  public void start(java.lang.String, long);
    Code:
       0: getstatic     #2                  // Field LOG:Lorg/slf4j/Logger;
       3: ldc           #3                  // String Attempting to start DNS client
       5: invokeinterface #4,  2            // InterfaceMethod org/slf4j/Logger.debug:(Ljava/lang/String;)V
      10: aload_0
      11: aload_1
      12: invokespecial #5                  // Method parseServerIpAddresses:(Ljava/lang/String;)Ljava/util/List;
      15: astore        4
      17: aload_0
      18: new           #6                  // class io/netty/channel/nio/NioEventLoopGroup
      21: dup
      22: invokespecial #7                  // Method io/netty/channel/nio/NioEventLoopGroup."<init>":()V
      25: putfield      #8                  // Field nettyEventLoop:Lio/netty/channel/nio/NioEventLoopGroup;
      28: new           #9                  // class io/netty/resolver/dns/DnsNameResolverBuilder
      31: dup
      32: aload_0
      33: getfield      #8                  // Field nettyEventLoop:Lio/netty/channel/nio/NioEventLoopGroup;
      36: invokevirtual #10                 // Method io/netty/channel/nio/NioEventLoopGroup.next:()Lio/netty/channel/EventLoop;
      39: invokespecial #11                 // Method io/netty/resolver/dns/DnsNameResolverBuilder."<init>":(Lio/netty/channel/EventLoop;)V
      42: astore        5
      44: aload         5
      46: ldc           #12                 // class io/netty/channel/socket/nio/NioDatagramChannel
      48: invokevirtual #13                 // Method io/netty/resolver/dns/DnsNameResolverBuilder.channelType:(Ljava/lang/Class;)Lio/netty/resolver/dns/DnsNameResolverBuilder;
      51: lload_2
      52: invokevirtual #14                 // Method io/netty/resolver/dns/DnsNameResolverBuilder.queryTimeoutMillis:(J)Lio/netty/resolver/dns/DnsNameResolverBuilder;
      55: pop
      56: aload         4
      58: invokestatic  #15                 // Method org/apache/commons/collections4/CollectionUtils.isNotEmpty:(Ljava/util/Collection;)Z
      61: ifeq          119
      64: getstatic     #2                  // Field LOG:Lorg/slf4j/Logger;
      67: ldc           #16                 // String Attempting to start DNS client with server IPs [{}] on port [{}] with timeout [{}]
      69: iconst_3
      70: anewarray     #17                 // class java/lang/Object
      73: dup
      74: iconst_0
      75: aload_1
      76: aastore
      77: dup
      78: iconst_1
      79: bipush        53
      81: invokestatic  #19                 // Method java/lang/Integer.valueOf:(I)Ljava/lang/Integer;
      84: aastore
      85: dup
      86: iconst_2
      87: lload_2
      88: invokestatic  #20                 // Method java/lang/Long.valueOf:(J)Ljava/lang/Long;
      91: aastore
      92: invokeinterface #21,  3           // InterfaceMethod org/slf4j/Logger.debug:(Ljava/lang/String;[Ljava/lang/Object;)V
      97: new           #22                 // class io/netty/resolver/dns/SequentialDnsServerAddressStreamProvider
     100: dup
     101: aload         4
     103: invokespecial #23                 // Method io/netty/resolver/dns/SequentialDnsServerAddressStreamProvider."<init>":(Ljava/lang/Iterable;)V
     106: astore        6
     108: aload         5
     110: aload         6
     112: invokevirtual #24                 // Method io/netty/resolver/dns/DnsNameResolverBuilder.nameServerProvider:(Lio/netty/resolver/dns/DnsServerAddressStreamProvider;)Lio/netty/resolver/dns/DnsNameResolverBuilder;
     115: pop
     116: goto          138
     119: getstatic     #2                  // Field LOG:Lorg/slf4j/Logger;
     122: ldc           #25                 // String Attempting to start DNS client with the local network adapter DNS server address on port [{}] with timeout [{}]
     124: bipush        53
     126: invokestatic  #19                 // Method java/lang/Integer.valueOf:(I)Ljava/lang/Integer;
     129: lload_2
     130: invokestatic  #20                 // Method java/lang/Long.valueOf:(J)Ljava/lang/Long;
     133: invokeinterface #26,  4           // InterfaceMethod org/slf4j/Logger.debug:(Ljava/lang/String;Ljava/lang/Object;Ljava/lang/Object;)V
     138: aload_0
     139: aload         5
     141: invokevirtual #27                 // Method io/netty/resolver/dns/DnsNameResolverBuilder.build:()Lio/netty/resolver/dns/DnsNameResolver;
     144: putfield      #28                 // Field resolver:Lio/netty/resolver/dns/DnsNameResolver;
     147: getstatic     #2                  // Field LOG:Lorg/slf4j/Logger;
     150: ldc           #29                 // String DNS client startup successful
     152: invokeinterface #4,  2            // InterfaceMethod org/slf4j/Logger.debug:(Ljava/lang/String;)V
     157: return

  private java.util.List<java.net.InetSocketAddress> parseServerIpAddresses(java.lang.String);
    Code:
       0: ldc           #30                 // String ,
       2: invokestatic  #31                 // Method com/google/common/base/Splitter.on:(Ljava/lang/String;)Lcom/google/common/base/Splitter;
       5: invokevirtual #32                 // Method com/google/common/base/Splitter.trimResults:()Lcom/google/common/base/Splitter;
       8: invokevirtual #33                 // Method com/google/common/base/Splitter.omitEmptyStrings:()Lcom/google/common/base/Splitter;
      11: aload_1
      12: invokevirtual #34                 // Method com/google/common/base/Splitter.split:(Ljava/lang/CharSequence;)Ljava/lang/Iterable;
      15: invokeinterface #35,  1           // InterfaceMethod java/lang/Iterable.spliterator:()Ljava/util/Spliterator;
      20: iconst_0
      21: invokestatic  #36                 // Method java/util/stream/StreamSupport.stream:(Ljava/util/Spliterator;Z)Ljava/util/stream/Stream;
      24: invokedynamic #37,  0             // InvokeDynamic #0:apply:()Ljava/util/function/Function;
      29: invokeinterface #38,  2           // InterfaceMethod java/util/stream/Stream.map:(Ljava/util/function/Function;)Ljava/util/stream/Stream;
      34: invokedynamic #39,  0             // InvokeDynamic #1:apply:()Ljava/util/function/Function;
      39: invokeinterface #38,  2           // InterfaceMethod java/util/stream/Stream.map:(Ljava/util/function/Function;)Ljava/util/stream/Stream;
      44: invokestatic  #40                 // Method java/util/stream/Collectors.toList:()Ljava/util/stream/Collector;
      47: invokeinterface #41,  2           // InterfaceMethod java/util/stream/Stream.collect:(Ljava/util/stream/Collector;)Ljava/lang/Object;
      52: checkcast     #42                 // class java/util/List
      55: areturn

  public void stop();
    Code:
       0: getstatic     #2                  // Field LOG:Lorg/slf4j/Logger;
       3: ldc           #43                 // String Attempting to stop DNS client
       5: invokeinterface #4,  2            // InterfaceMethod org/slf4j/Logger.debug:(Ljava/lang/String;)V
      10: aload_0
      11: getfield      #8                  // Field nettyEventLoop:Lio/netty/channel/nio/NioEventLoopGroup;
      14: ifnonnull     28
      17: getstatic     #2                  // Field LOG:Lorg/slf4j/Logger;
      20: ldc           #44                 // String DNS resolution event loop not initialized
      22: invokeinterface #45,  2           // InterfaceMethod org/slf4j/Logger.error:(Ljava/lang/String;)V
      27: return
      28: aload_0
      29: getfield      #8                  // Field nettyEventLoop:Lio/netty/channel/nio/NioEventLoopGroup;
      32: invokevirtual #46                 // Method io/netty/channel/nio/NioEventLoopGroup.shutdownGracefully:()Lio/netty/util/concurrent/Future;
      35: astore_1
      36: aload_1
      37: invokedynamic #47,  0             // InvokeDynamic #2:operationComplete:()Lio/netty/util/concurrent/GenericFutureListener;
      42: invokeinterface #48,  2           // InterfaceMethod io/netty/util/concurrent/Future.addListener:(Lio/netty/util/concurrent/GenericFutureListener;)Lio/netty/util/concurrent/Future;
      47: pop
      48: return

  public java.util.List<org.graylog2.lookup.adapters.dnslookup.ADnsAnswer> resolveIPv4AddressForHostname(java.lang.String, boolean) throws java.lang.InterruptedException, java.util.concurrent.ExecutionException, java.net.UnknownHostException;
    Code:
       0: aload_0
       1: aload_1
       2: getstatic     #49                 // Field io/netty/handler/codec/dns/DnsRecordType.A:Lio/netty/handler/codec/dns/DnsRecordType;
       5: iload_2
       6: invokespecial #50                 // Method resolveIpAddresses:(Ljava/lang/String;Lio/netty/handler/codec/dns/DnsRecordType;Z)Ljava/util/List;
       9: areturn

  public java.util.List<org.graylog2.lookup.adapters.dnslookup.ADnsAnswer> resolveIPv6AddressForHostname(java.lang.String, boolean) throws java.lang.InterruptedException, java.util.concurrent.ExecutionException, java.net.UnknownHostException;
    Code:
       0: aload_0
       1: aload_1
       2: getstatic     #51                 // Field io/netty/handler/codec/dns/DnsRecordType.AAAA:Lio/netty/handler/codec/dns/DnsRecordType;
       5: iload_2
       6: invokespecial #50                 // Method resolveIpAddresses:(Ljava/lang/String;Lio/netty/handler/codec/dns/DnsRecordType;Z)Ljava/util/List;
       9: areturn

  private java.util.List<org.graylog2.lookup.adapters.dnslookup.ADnsAnswer> resolveIpAddresses(java.lang.String, io.netty.handler.codec.dns.DnsRecordType, boolean) throws java.lang.InterruptedException, java.util.concurrent.ExecutionException;
    Code:
       0: getstatic     #2                  // Field LOG:Lorg/slf4j/Logger;
       3: ldc           #52                 // String Attempting to resolve [{}] records for [{}]
       5: aload_2
       6: aload_1
       7: invokeinterface #26,  4           // InterfaceMethod org/slf4j/Logger.debug:(Ljava/lang/String;Ljava/lang/Object;Ljava/lang/Object;)V
      12: aload_0
      13: invokespecial #53                 // Method isShutdown:()Z
      16: ifeq          27
      19: new           #54                 // class org/graylog2/lookup/adapters/dnslookup/DnsClientNotRunningException
      22: dup
      23: invokespecial #55                 // Method org/graylog2/lookup/adapters/dnslookup/DnsClientNotRunningException."<init>":()V
      26: athrow
      27: aload_0
      28: aload_1
      29: invokespecial #56                 // Method validateHostName:(Ljava/lang/String;)V
      32: new           #57                 // class io/netty/handler/codec/dns/DefaultDnsQuestion
      35: dup
      36: aload_1
      37: aload_2
      38: invokespecial #58                 // Method io/netty/handler/codec/dns/DefaultDnsQuestion."<init>":(Ljava/lang/String;Lio/netty/handler/codec/dns/DnsRecordType;)V
      41: astore        4
      43: aload_0
      44: getfield      #28                 // Field resolver:Lio/netty/resolver/dns/DnsNameResolver;
      47: aload         4
      49: invokevirtual #59                 // Method io/netty/resolver/dns/DnsNameResolver.resolveAll:(Lio/netty/handler/codec/dns/DnsQuestion;)Lio/netty/util/concurrent/Future;
      52: invokeinterface #60,  1           // InterfaceMethod io/netty/util/concurrent/Future.sync:()Lio/netty/util/concurrent/Future;
      57: invokeinterface #61,  1           // InterfaceMethod io/netty/util/concurrent/Future.get:()Ljava/lang/Object;
      62: checkcast     #42                 // class java/util/List
      65: invokeinterface #62,  1           // InterfaceMethod java/util/List.stream:()Ljava/util/stream/Stream;
      70: iload_3
      71: invokedynamic #63,  0             // InvokeDynamic #3:apply:(Z)Ljava/util/function/Function;
      76: invokeinterface #38,  2           // InterfaceMethod java/util/stream/Stream.map:(Ljava/util/function/Function;)Ljava/util/stream/Stream;
      81: invokedynamic #64,  0             // InvokeDynamic #4:test:()Ljava/util/function/Predicate;
      86: invokeinterface #65,  2           // InterfaceMethod java/util/stream/Stream.filter:(Ljava/util/function/Predicate;)Ljava/util/stream/Stream;
      91: invokestatic  #40                 // Method java/util/stream/Collectors.toList:()Ljava/util/stream/Collector;
      94: invokeinterface #41,  2           // InterfaceMethod java/util/stream/Stream.collect:(Ljava/util/stream/Collector;)Ljava/lang/Object;
      99: checkcast     #42                 // class java/util/List
     102: areturn

  private static org.graylog2.lookup.adapters.dnslookup.ADnsAnswer decodeDnsRecord(io.netty.handler.codec.dns.DnsRecord, boolean);
    Code:
       0: aload_0
       1: ifnonnull     6
       4: aconst_null
       5: areturn
       6: getstatic     #2                  // Field LOG:Lorg/slf4j/Logger;
       9: ldc           #66                 // String Attempting to decode DNS record [{}]
      11: aload_0
      12: invokeinterface #67,  3           // InterfaceMethod org/slf4j/Logger.trace:(Ljava/lang/String;Ljava/lang/Object;)V
      17: aload_0
      18: checkcast     #68                 // class io/netty/handler/codec/dns/DefaultDnsRawRecord
      21: astore_3
      22: aload_3
      23: invokevirtual #69                 // Method io/netty/handler/codec/dns/DefaultDnsRawRecord.content:()Lio/netty/buffer/ByteBuf;
      26: astore        4
      28: aload         4
      30: invokevirtual #70                 // Method io/netty/buffer/ByteBuf.readableBytes:()I
      33: newarray       byte
      35: astore_2
      36: aload         4
      38: invokevirtual #71                 // Method io/netty/buffer/ByteBuf.readerIndex:()I
      41: istore        5
      43: aload         4
      45: iload         5
      47: aload_2
      48: invokevirtual #72                 // Method io/netty/buffer/ByteBuf.getBytes:(I[B)Lio/netty/buffer/ByteBuf;
      51: pop
      52: aload_3
      53: invokevirtual #73                 // Method io/netty/handler/codec/dns/DefaultDnsRawRecord.release:()Z
      56: pop
      57: goto          70
      60: astore        6
      62: aload_3
      63: invokevirtual #73                 // Method io/netty/handler/codec/dns/DefaultDnsRawRecord.release:()Z
      66: pop
      67: aload         6
      69: athrow
      70: getstatic     #2                  // Field LOG:Lorg/slf4j/Logger;
      73: ldc           #74                 // String The IP address has [{}] bytes
      75: aload_2
      76: arraylength
      77: invokestatic  #19                 // Method java/lang/Integer.valueOf:(I)Ljava/lang/Integer;
      80: invokeinterface #67,  3           // InterfaceMethod org/slf4j/Logger.trace:(Ljava/lang/String;Ljava/lang/Object;)V
      85: aload_2
      86: invokestatic  #75                 // Method java/net/InetAddress.getByAddress:([B)Ljava/net/InetAddress;
      89: astore        4
      91: goto          117
      94: astore        5
      96: getstatic     #2                  // Field LOG:Lorg/slf4j/Logger;
      99: ldc           #77                 // String Could not extract IP address from DNS entry [{}]. Cause [{}]
     101: aload_0
     102: invokevirtual #78                 // Method java/lang/Object.toString:()Ljava/lang/String;
     105: aload         5
     107: invokestatic  #79                 // Method org/graylog2/shared/utilities/ExceptionUtils.getRootCauseMessage:(Ljava/lang/Throwable;)Ljava/lang/String;
     110: invokeinterface #80,  4           // InterfaceMethod org/slf4j/Logger.error:(Ljava/lang/String;Ljava/lang/Object;Ljava/lang/Object;)V
     115: aconst_null
     116: areturn
     117: getstatic     #2                  // Field LOG:Lorg/slf4j/Logger;
     120: ldc           #81                 // String The resulting IP address is [{}]
     122: aload         4
     124: invokevirtual #82                 // Method java/net/InetAddress.getHostAddress:()Ljava/lang/String;
     127: invokeinterface #67,  3           // InterfaceMethod org/slf4j/Logger.trace:(Ljava/lang/String;Ljava/lang/Object;)V
     132: invokestatic  #83                 // Method org/graylog2/lookup/adapters/dnslookup/ADnsAnswer.builder:()Lorg/graylog2/lookup/adapters/dnslookup/ADnsAnswer$Builder;
     135: aload         4
     137: invokevirtual #82                 // Method java/net/InetAddress.getHostAddress:()Ljava/lang/String;
     140: invokevirtual #84                 // Method org/graylog2/lookup/adapters/dnslookup/ADnsAnswer$Builder.ipAddress:(Ljava/lang/String;)Lorg/graylog2/lookup/adapters/dnslookup/ADnsAnswer$Builder;
     143: aload_0
     144: invokeinterface #85,  1           // InterfaceMethod io/netty/handler/codec/dns/DnsRecord.timeToLive:()J
     149: invokevirtual #86                 // Method org/graylog2/lookup/adapters/dnslookup/ADnsAnswer$Builder.dnsTTL:(J)Lorg/graylog2/lookup/adapters/dnslookup/ADnsAnswer$Builder;
     152: astore        5
     154: iload_1
     155: ifeq          179
     158: aload         5
     160: aload         4
     162: instanceof    #87                 // class java/net/Inet4Address
     165: ifeq          173
     168: ldc           #88                 // String IPv4
     170: goto          175
     173: ldc           #89                 // String IPv6
     175: invokevirtual #90                 // Method org/graylog2/lookup/adapters/dnslookup/ADnsAnswer$Builder.ipVersion:(Ljava/lang/String;)Lorg/graylog2/lookup/adapters/dnslookup/ADnsAnswer$Builder;
     178: pop
     179: aload         5
     181: invokevirtual #91                 // Method org/graylog2/lookup/adapters/dnslookup/ADnsAnswer$Builder.build:()Lorg/graylog2/lookup/adapters/dnslookup/ADnsAnswer;
     184: areturn
    Exception table:
       from    to  target type
          22    52    60   any
          60    62    60   any
          85    91    94   Class java/net/UnknownHostException

  public org.graylog2.lookup.adapters.dnslookup.PtrDnsAnswer reverseLookup(java.lang.String) throws java.lang.InterruptedException, java.util.concurrent.ExecutionException;
    Code:
       0: getstatic     #2                  // Field LOG:Lorg/slf4j/Logger;
       3: ldc           #92                 // String Attempting to perform reverse lookup for IP address [{}]
       5: aload_1
       6: invokeinterface #93,  3           // InterfaceMethod org/slf4j/Logger.debug:(Ljava/lang/String;Ljava/lang/Object;)V
      11: aload_0
      12: invokespecial #53                 // Method isShutdown:()Z
      15: ifeq          26
      18: new           #54                 // class org/graylog2/lookup/adapters/dnslookup/DnsClientNotRunningException
      21: dup
      22: invokespecial #55                 // Method org/graylog2/lookup/adapters/dnslookup/DnsClientNotRunningException."<init>":()V
      25: athrow
      26: aload_1
      27: invokestatic  #94                 // Method validateIpAddress:(Ljava/lang/String;)V
      30: aload_0
      31: aload_1
      32: invokevirtual #95                 // Method getInverseAddressFormat:(Ljava/lang/String;)Ljava/lang/String;
      35: astore_2
      36: aconst_null
      37: astore_3
      38: aload_0
      39: getfield      #28                 // Field resolver:Lio/netty/resolver/dns/DnsNameResolver;
      42: new           #57                 // class io/netty/handler/codec/dns/DefaultDnsQuestion
      45: dup
      46: aload_2
      47: getstatic     #96                 // Field io/netty/handler/codec/dns/DnsRecordType.PTR:Lio/netty/handler/codec/dns/DnsRecordType;
      50: invokespecial #58                 // Method io/netty/handler/codec/dns/DefaultDnsQuestion."<init>":(Ljava/lang/String;Lio/netty/handler/codec/dns/DnsRecordType;)V
      53: invokevirtual #97                 // Method io/netty/resolver/dns/DnsNameResolver.query:(Lio/netty/handler/codec/dns/DnsQuestion;)Lio/netty/util/concurrent/Future;
      56: invokeinterface #60,  1           // InterfaceMethod io/netty/util/concurrent/Future.sync:()Lio/netty/util/concurrent/Future;
      61: invokeinterface #61,  1           // InterfaceMethod io/netty/util/concurrent/Future.get:()Ljava/lang/Object;
      66: checkcast     #98                 // class io/netty/channel/AddressedEnvelope
      69: invokeinterface #99,  1           // InterfaceMethod io/netty/channel/AddressedEnvelope.content:()Ljava/lang/Object;
      74: checkcast     #100                // class io/netty/handler/codec/dns/DnsResponse
      77: astore_3
      78: iconst_0
      79: istore        4
      81: iload         4
      83: aload_3
      84: getstatic     #101                // Field io/netty/handler/codec/dns/DnsSection.ANSWER:Lio/netty/handler/codec/dns/DnsSection;
      87: invokeinterface #102,  2          // InterfaceMethod io/netty/handler/codec/dns/DnsResponse.count:(Lio/netty/handler/codec/dns/DnsSection;)I
      92: if_icmpge     215
      95: aload_3
      96: getstatic     #101                // Field io/netty/handler/codec/dns/DnsSection.ANSWER:Lio/netty/handler/codec/dns/DnsSection;
      99: iload         4
     101: invokeinterface #103,  3          // InterfaceMethod io/netty/handler/codec/dns/DnsResponse.recordAt:(Lio/netty/handler/codec/dns/DnsSection;I)Lio/netty/handler/codec/dns/DnsRecord;
     106: astore        5
     108: aload         5
     110: instanceof    #104                // class io/netty/handler/codec/dns/DefaultDnsPtrRecord
     113: ifeq          209
     116: aload         5
     118: checkcast     #104                // class io/netty/handler/codec/dns/DefaultDnsPtrRecord
     121: astore        6
     123: invokestatic  #105                // Method org/graylog2/lookup/adapters/dnslookup/PtrDnsAnswer.builder:()Lorg/graylog2/lookup/adapters/dnslookup/PtrDnsAnswer$Builder;
     126: astore        7
     128: aload         6
     130: invokevirtual #106                // Method io/netty/handler/codec/dns/DefaultDnsPtrRecord.hostname:()Ljava/lang/String;
     133: astore        8
     135: getstatic     #2                  // Field LOG:Lorg/slf4j/Logger;
     138: ldc           #107                // String PTR record retrieved with hostname [{}]
     140: aload         8
     142: invokeinterface #67,  3           // InterfaceMethod org/slf4j/Logger.trace:(Ljava/lang/String;Ljava/lang/Object;)V
     147: aload         7
     149: aload         8
     151: invokestatic  #108                // Method parseReverseLookupDomain:(Lorg/graylog2/lookup/adapters/dnslookup/PtrDnsAnswer$Builder;Ljava/lang/String;)V
     154: goto          180
     157: astore        9
     159: getstatic     #2                  // Field LOG:Lorg/slf4j/Logger;
     162: ldc           #110                // String Reverse lookup of [{}] was partially successful. The DNS server returned [{}], which is an invalid host name. The \"domain\" field will be left blank.
     164: aload_1
     165: aload         8
     167: invokeinterface #26,  4           // InterfaceMethod org/slf4j/Logger.debug:(Ljava/lang/String;Ljava/lang/Object;Ljava/lang/Object;)V
     172: aload         7
     174: ldc           #111                // String
     176: invokevirtual #112                // Method org/graylog2/lookup/adapters/dnslookup/PtrDnsAnswer$Builder.domain:(Ljava/lang/String;)Lorg/graylog2/lookup/adapters/dnslookup/PtrDnsAnswer$Builder;
     179: pop
     180: aload         7
     182: aload         6
     184: invokevirtual #113                // Method io/netty/handler/codec/dns/DefaultDnsPtrRecord.timeToLive:()J
     187: invokevirtual #114                // Method org/graylog2/lookup/adapters/dnslookup/PtrDnsAnswer$Builder.dnsTTL:(J)Lorg/graylog2/lookup/adapters/dnslookup/PtrDnsAnswer$Builder;
     190: invokevirtual #115                // Method org/graylog2/lookup/adapters/dnslookup/PtrDnsAnswer$Builder.build:()Lorg/graylog2/lookup/adapters/dnslookup/PtrDnsAnswer;
     193: astore        9
     195: aload_3
     196: ifnull        206
     199: aload_3
     200: invokeinterface #116,  1          // InterfaceMethod io/netty/handler/codec/dns/DnsResponse.release:()Z
     205: pop
     206: aload         9
     208: areturn
     209: iinc          4, 1
     212: goto          81
     215: aload_3
     216: ifnull        245
     219: aload_3
     220: invokeinterface #116,  1          // InterfaceMethod io/netty/handler/codec/dns/DnsResponse.release:()Z
     225: pop
     226: goto          245
     229: astore        10
     231: aload_3
     232: ifnull        242
     235: aload_3
     236: invokeinterface #116,  1          // InterfaceMethod io/netty/handler/codec/dns/DnsResponse.release:()Z
     241: pop
     242: aload         10
     244: athrow
     245: aconst_null
     246: areturn
    Exception table:
       from    to  target type
         147   154   157   Class java/lang/IllegalArgumentException
          38   195   229   any
         209   215   229   any
         229   231   229   any

  public static void parseReverseLookupDomain(org.graylog2.lookup.adapters.dnslookup.PtrDnsAnswer$Builder, java.lang.String);
    Code:
       0: aload_0
       1: aload_1
       2: invokevirtual #117                // Method org/graylog2/lookup/adapters/dnslookup/PtrDnsAnswer$Builder.fullDomain:(Ljava/lang/String;)Lorg/graylog2/lookup/adapters/dnslookup/PtrDnsAnswer$Builder;
       5: pop
       6: aload_1
       7: invokestatic  #118                // Method com/google/common/net/InternetDomainName.from:(Ljava/lang/String;)Lcom/google/common/net/InternetDomainName;
      10: astore_2
      11: aload_2
      12: invokevirtual #119                // Method com/google/common/net/InternetDomainName.hasPublicSuffix:()Z
      15: ifeq          35
      18: aload_2
      19: invokevirtual #120                // Method com/google/common/net/InternetDomainName.topDomainUnderRegistrySuffix:()Lcom/google/common/net/InternetDomainName;
      22: astore_3
      23: aload_0
      24: aload_3
      25: invokevirtual #121                // Method com/google/common/net/InternetDomainName.toString:()Ljava/lang/String;
      28: invokevirtual #112                // Method org/graylog2/lookup/adapters/dnslookup/PtrDnsAnswer$Builder.domain:(Ljava/lang/String;)Lorg/graylog2/lookup/adapters/dnslookup/PtrDnsAnswer$Builder;
      31: pop
      32: goto          111
      35: aload_1
      36: ldc           #122                // String \\.
      38: invokevirtual #123                // Method java/lang/String.split:(Ljava/lang/String;)[Ljava/lang/String;
      41: astore_3
      42: aload_3
      43: arraylength
      44: iconst_1
      45: if_icmple     89
      48: aload_0
      49: new           #124                // class java/lang/StringBuilder
      52: dup
      53: invokespecial #125                // Method java/lang/StringBuilder."<init>":()V
      56: aload_3
      57: aload_3
      58: arraylength
      59: iconst_2
      60: isub
      61: aaload
      62: invokevirtual #126                // Method java/lang/StringBuilder.append:(Ljava/lang/String;)Ljava/lang/StringBuilder;
      65: ldc           #127                // String .
      67: invokevirtual #126                // Method java/lang/StringBuilder.append:(Ljava/lang/String;)Ljava/lang/StringBuilder;
      70: aload_3
      71: aload_3
      72: arraylength
      73: iconst_1
      74: isub
      75: aaload
      76: invokevirtual #126                // Method java/lang/StringBuilder.append:(Ljava/lang/String;)Ljava/lang/StringBuilder;
      79: invokevirtual #128                // Method java/lang/StringBuilder.toString:()Ljava/lang/String;
      82: invokevirtual #112                // Method org/graylog2/lookup/adapters/dnslookup/PtrDnsAnswer$Builder.domain:(Ljava/lang/String;)Lorg/graylog2/lookup/adapters/dnslookup/PtrDnsAnswer$Builder;
      85: pop
      86: goto          111
      89: aload_3
      90: arraylength
      91: iconst_1
      92: if_icmpne     104
      95: aload_0
      96: aload_1
      97: invokevirtual #112                // Method org/graylog2/lookup/adapters/dnslookup/PtrDnsAnswer$Builder.domain:(Ljava/lang/String;)Lorg/graylog2/lookup/adapters/dnslookup/PtrDnsAnswer$Builder;
     100: pop
     101: goto          111
     104: aload_0
     105: ldc           #111                // String
     107: invokevirtual #112                // Method org/graylog2/lookup/adapters/dnslookup/PtrDnsAnswer$Builder.domain:(Ljava/lang/String;)Lorg/graylog2/lookup/adapters/dnslookup/PtrDnsAnswer$Builder;
     110: pop
     111: return

  public java.util.List<org.graylog2.lookup.adapters.dnslookup.TxtDnsAnswer> txtLookup(java.lang.String) throws java.lang.InterruptedException, java.util.concurrent.ExecutionException;
    Code:
       0: aload_0
       1: invokespecial #53                 // Method isShutdown:()Z
       4: ifeq          15
       7: new           #54                 // class org/graylog2/lookup/adapters/dnslookup/DnsClientNotRunningException
      10: dup
      11: invokespecial #55                 // Method org/graylog2/lookup/adapters/dnslookup/DnsClientNotRunningException."<init>":()V
      14: athrow
      15: getstatic     #2                  // Field LOG:Lorg/slf4j/Logger;
      18: ldc           #129                // String Attempting to perform TXT lookup for hostname [{}]
      20: aload_1
      21: invokeinterface #93,  3           // InterfaceMethod org/slf4j/Logger.debug:(Ljava/lang/String;Ljava/lang/Object;)V
      26: aload_0
      27: aload_1
      28: invokespecial #56                 // Method validateHostName:(Ljava/lang/String;)V
      31: aconst_null
      32: astore_2
      33: aload_0
      34: getfield      #28                 // Field resolver:Lio/netty/resolver/dns/DnsNameResolver;
      37: new           #57                 // class io/netty/handler/codec/dns/DefaultDnsQuestion
      40: dup
      41: aload_1
      42: getstatic     #130                // Field io/netty/handler/codec/dns/DnsRecordType.TXT:Lio/netty/handler/codec/dns/DnsRecordType;
      45: invokespecial #58                 // Method io/netty/handler/codec/dns/DefaultDnsQuestion."<init>":(Ljava/lang/String;Lio/netty/handler/codec/dns/DnsRecordType;)V
      48: invokevirtual #97                 // Method io/netty/resolver/dns/DnsNameResolver.query:(Lio/netty/handler/codec/dns/DnsQuestion;)Lio/netty/util/concurrent/Future;
      51: invokeinterface #60,  1           // InterfaceMethod io/netty/util/concurrent/Future.sync:()Lio/netty/util/concurrent/Future;
      56: invokeinterface #61,  1           // InterfaceMethod io/netty/util/concurrent/Future.get:()Ljava/lang/Object;
      61: checkcast     #98                 // class io/netty/channel/AddressedEnvelope
      64: invokeinterface #99,  1           // InterfaceMethod io/netty/channel/AddressedEnvelope.content:()Ljava/lang/Object;
      69: checkcast     #100                // class io/netty/handler/codec/dns/DnsResponse
      72: astore_2
      73: aload_2
      74: getstatic     #101                // Field io/netty/handler/codec/dns/DnsSection.ANSWER:Lio/netty/handler/codec/dns/DnsSection;
      77: invokeinterface #102,  2          // InterfaceMethod io/netty/handler/codec/dns/DnsResponse.count:(Lio/netty/handler/codec/dns/DnsSection;)I
      82: istore_3
      83: new           #131                // class java/util/ArrayList
      86: dup
      87: iload_3
      88: invokespecial #132                // Method java/util/ArrayList."<init>":(I)V
      91: astore        4
      93: iconst_0
      94: istore        5
      96: iload         5
      98: iload_3
      99: if_icmpge     207
     102: aload_2
     103: getstatic     #101                // Field io/netty/handler/codec/dns/DnsSection.ANSWER:Lio/netty/handler/codec/dns/DnsSection;
     106: iload         5
     108: invokeinterface #103,  3          // InterfaceMethod io/netty/handler/codec/dns/DnsResponse.recordAt:(Lio/netty/handler/codec/dns/DnsSection;I)Lio/netty/handler/codec/dns/DnsRecord;
     113: astore        6
     115: getstatic     #2                  // Field LOG:Lorg/slf4j/Logger;
     118: ldc           #133                // String TXT record [{}] retrieved with content [{}].
     120: iload         5
     122: invokestatic  #19                 // Method java/lang/Integer.valueOf:(I)Ljava/lang/Integer;
     125: aload         6
     127: invokeinterface #134,  4          // InterfaceMethod org/slf4j/Logger.trace:(Ljava/lang/String;Ljava/lang/Object;Ljava/lang/Object;)V
     132: aload         6
     134: instanceof    #68                 // class io/netty/handler/codec/dns/DefaultDnsRawRecord
     137: ifeq          201
     140: aload         6
     142: checkcast     #68                 // class io/netty/handler/codec/dns/DefaultDnsRawRecord
     145: astore        7
     147: invokestatic  #135                // Method org/graylog2/lookup/adapters/dnslookup/TxtDnsAnswer.builder:()Lorg/graylog2/lookup/adapters/dnslookup/TxtDnsAnswer$Builder;
     150: astore        8
     152: aload         7
     154: invokestatic  #136                // Method decodeTxtRecord:(Lio/netty/handler/codec/dns/DefaultDnsRawRecord;)Ljava/lang/String;
     157: astore        9
     159: getstatic     #2                  // Field LOG:Lorg/slf4j/Logger;
     162: ldc           #137                // String The decoded TXT record is [{}]
     164: aload         9
     166: invokeinterface #67,  3           // InterfaceMethod org/slf4j/Logger.trace:(Ljava/lang/String;Ljava/lang/Object;)V
     171: aload         8
     173: aload         9
     175: invokevirtual #138                // Method org/graylog2/lookup/adapters/dnslookup/TxtDnsAnswer$Builder.value:(Ljava/lang/String;)Lorg/graylog2/lookup/adapters/dnslookup/TxtDnsAnswer$Builder;
     178: aload         7
     180: invokevirtual #139                // Method io/netty/handler/codec/dns/DefaultDnsRawRecord.timeToLive:()J
     183: invokevirtual #140                // Method org/graylog2/lookup/adapters/dnslookup/TxtDnsAnswer$Builder.dnsTTL:(J)Lorg/graylog2/lookup/adapters/dnslookup/TxtDnsAnswer$Builder;
     186: invokevirtual #141                // Method org/graylog2/lookup/adapters/dnslookup/TxtDnsAnswer$Builder.build:()Lorg/graylog2/lookup/adapters/dnslookup/TxtDnsAnswer;
     189: pop
     190: aload         4
     192: aload         8
     194: invokevirtual #141                // Method org/graylog2/lookup/adapters/dnslookup/TxtDnsAnswer$Builder.build:()Lorg/graylog2/lookup/adapters/dnslookup/TxtDnsAnswer;
     197: invokevirtual #142                // Method java/util/ArrayList.add:(Ljava/lang/Object;)Z
     200: pop
     201: iinc          5, 1
     204: goto          96
     207: aload         4
     209: astore        5
     211: aload_2
     212: ifnull        222
     215: aload_2
     216: invokeinterface #116,  1          // InterfaceMethod io/netty/handler/codec/dns/DnsResponse.release:()Z
     221: pop
     222: aload         5
     224: areturn
     225: astore        10
     227: aload_2
     228: ifnull        238
     231: aload_2
     232: invokeinterface #116,  1          // InterfaceMethod io/netty/handler/codec/dns/DnsResponse.release:()Z
     237: pop
     238: aload         10
     240: athrow
    Exception table:
       from    to  target type
          33   211   225   any
         225   227   225   any

  private boolean isShutdown();
    Code:
       0: aload_0
       1: getfield      #8                  // Field nettyEventLoop:Lio/netty/channel/nio/NioEventLoopGroup;
       4: ifnull        17
       7: aload_0
       8: getfield      #8                  // Field nettyEventLoop:Lio/netty/channel/nio/NioEventLoopGroup;
      11: invokevirtual #143                // Method io/netty/channel/nio/NioEventLoopGroup.isShutdown:()Z
      14: ifeq          21
      17: iconst_1
      18: goto          22
      21: iconst_0
      22: ireturn

  private static java.lang.String decodeTxtRecord(io.netty.handler.codec.dns.DefaultDnsRawRecord);
    Code:
       0: getstatic     #2                  // Field LOG:Lorg/slf4j/Logger;
       3: ldc           #144                // String Attempting to read TXT value from DNS record [{}]
       5: aload_0
       6: invokeinterface #93,  3           // InterfaceMethod org/slf4j/Logger.debug:(Ljava/lang/String;Ljava/lang/Object;)V
      11: aload_0
      12: invokevirtual #69                 // Method io/netty/handler/codec/dns/DefaultDnsRawRecord.content:()Lio/netty/buffer/ByteBuf;
      15: invokestatic  #145                // Method io/netty/handler/codec/dns/DefaultDnsRecordDecoder.decodeName:(Lio/netty/buffer/ByteBuf;)Ljava/lang/String;
      18: areturn

  public java.lang.String getInverseAddressFormat(java.lang.String);
    Code:
       0: aload_1
       1: invokestatic  #146                // Method org/apache/commons/lang3/StringUtils.trim:(Ljava/lang/String;)Ljava/lang/String;
       4: astore_1
       5: aload_1
       6: invokestatic  #94                 // Method validateIpAddress:(Ljava/lang/String;)V
       9: getstatic     #2                  // Field LOG:Lorg/slf4j/Logger;
      12: ldc           #147                // String Preparing inverse format for IP address [{}]
      14: aload_1
      15: invokeinterface #93,  3           // InterfaceMethod org/slf4j/Logger.debug:(Ljava/lang/String;Ljava/lang/Object;)V
      20: aload_1
      21: invokestatic  #148                // Method isIp6Address:(Ljava/lang/String;)Z
      24: ifeq          225
      27: getstatic     #2                  // Field LOG:Lorg/slf4j/Logger;
      30: ldc           #149                // String [{}] is an IPv6 address
      32: aload_1
      33: invokeinterface #93,  3           // InterfaceMethod org/slf4j/Logger.debug:(Ljava/lang/String;Ljava/lang/Object;)V
      38: aload_1
      39: invokestatic  #150                // Method com/google/common/net/InetAddresses.forString:(Ljava/lang/String;)Ljava/net/InetAddress;
      42: invokevirtual #151                // Method java/net/InetAddress.getAddress:()[B
      45: astore_2
      46: aload_2
      47: arraylength
      48: bipush        16
      50: if_icmple     77
      53: new           #109                // class java/lang/IllegalArgumentException
      56: dup
      57: getstatic     #152                // Field java/util/Locale.ENGLISH:Ljava/util/Locale;
      60: ldc           #153                // String [%s] is an invalid IPv6 address
      62: iconst_1
      63: anewarray     #17                 // class java/lang/Object
      66: dup
      67: iconst_0
      68: aload_1
      69: aastore
      70: invokestatic  #154                // Method java/lang/String.format:(Ljava/util/Locale;Ljava/lang/String;[Ljava/lang/Object;)Ljava/lang/String;
      73: invokespecial #155                // Method java/lang/IllegalArgumentException."<init>":(Ljava/lang/String;)V
      76: athrow
      77: aload_2
      78: arraylength
      79: iconst_2
      80: imul
      81: newarray       char
      83: astore_3
      84: iconst_0
      85: istore        4
      87: iload         4
      89: aload_2
      90: arraylength
      91: if_icmpge     141
      94: aload_2
      95: iload         4
      97: baload
      98: sipush        255
     101: iand
     102: istore        5
     104: aload_3
     105: iload         4
     107: iconst_2
     108: imul
     109: getstatic     #156                // Field HEX_CHARS_ARRAY:[C
     112: iload         5
     114: iconst_4
     115: iushr
     116: caload
     117: castore
     118: aload_3
     119: iload         4
     121: iconst_2
     122: imul
     123: iconst_1
     124: iadd
     125: getstatic     #156                // Field HEX_CHARS_ARRAY:[C
     128: iload         5
     130: bipush        15
     132: iand
     133: caload
     134: castore
     135: iinc          4, 1
     138: goto          87
     141: new           #157                // class java/lang/String
     144: dup
     145: aload_3
     146: invokespecial #158                // Method java/lang/String."<init>":([C)V
     149: getstatic     #152                // Field java/util/Locale.ENGLISH:Ljava/util/Locale;
     152: invokevirtual #159                // Method java/lang/String.toLowerCase:(Ljava/util/Locale;)Ljava/lang/String;
     155: astore        4
     157: new           #124                // class java/lang/StringBuilder
     160: dup
     161: aload         4
     163: invokespecial #160                // Method java/lang/StringBuilder."<init>":(Ljava/lang/String;)V
     166: invokevirtual #161                // Method java/lang/StringBuilder.reverse:()Ljava/lang/StringBuilder;
     169: invokevirtual #128                // Method java/lang/StringBuilder.toString:()Ljava/lang/String;
     172: ldc           #111                // String
     174: invokevirtual #123                // Method java/lang/String.split:(Ljava/lang/String;)[Ljava/lang/String;
     177: astore        5
     179: ldc           #127                // String .
     181: invokestatic  #162                // Method com/google/common/base/Joiner.on:(Ljava/lang/String;)Lcom/google/common/base/Joiner;
     184: aload         5
     186: invokevirtual #163                // Method com/google/common/base/Joiner.join:([Ljava/lang/Object;)Ljava/lang/String;
     189: astore        6
     191: getstatic     #2                  // Field LOG:Lorg/slf4j/Logger;
     194: ldc           #164                // String Inverted address [{}] built for [{}]
     196: aload         6
     198: aload_1
     199: invokeinterface #26,  4           // InterfaceMethod org/slf4j/Logger.debug:(Ljava/lang/String;Ljava/lang/Object;Ljava/lang/Object;)V
     204: new           #124                // class java/lang/StringBuilder
     207: dup
     208: invokespecial #125                // Method java/lang/StringBuilder."<init>":()V
     211: aload         6
     213: invokevirtual #126                // Method java/lang/StringBuilder.append:(Ljava/lang/String;)Ljava/lang/StringBuilder;
     216: ldc           #165                // String .ip6.arpa.
     218: invokevirtual #126                // Method java/lang/StringBuilder.append:(Ljava/lang/String;)Ljava/lang/StringBuilder;
     221: invokevirtual #128                // Method java/lang/StringBuilder.toString:()Ljava/lang/String;
     224: areturn
     225: getstatic     #2                  // Field LOG:Lorg/slf4j/Logger;
     228: ldc           #166                // String [{}] is an IPv4 address
     230: aload_1
     231: invokeinterface #93,  3           // InterfaceMethod org/slf4j/Logger.debug:(Ljava/lang/String;Ljava/lang/Object;)V
     236: aload_1
     237: ldc           #122                // String \\.
     239: invokevirtual #123                // Method java/lang/String.split:(Ljava/lang/String;)[Ljava/lang/String;
     242: astore_2
     243: new           #124                // class java/lang/StringBuilder
     246: dup
     247: invokespecial #125                // Method java/lang/StringBuilder."<init>":()V
     250: aload_2
     251: iconst_3
     252: aaload
     253: invokevirtual #126                // Method java/lang/StringBuilder.append:(Ljava/lang/String;)Ljava/lang/StringBuilder;
     256: ldc           #127                // String .
     258: invokevirtual #126                // Method java/lang/StringBuilder.append:(Ljava/lang/String;)Ljava/lang/StringBuilder;
     261: aload_2
     262: iconst_2
     263: aaload
     264: invokevirtual #126                // Method java/lang/StringBuilder.append:(Ljava/lang/String;)Ljava/lang/StringBuilder;
     267: ldc           #127                // String .
     269: invokevirtual #126                // Method java/lang/StringBuilder.append:(Ljava/lang/String;)Ljava/lang/StringBuilder;
     272: aload_2
     273: iconst_1
     274: aaload
     275: invokevirtual #126                // Method java/lang/StringBuilder.append:(Ljava/lang/String;)Ljava/lang/StringBuilder;
     278: ldc           #127                // String .
     280: invokevirtual #126                // Method java/lang/StringBuilder.append:(Ljava/lang/String;)Ljava/lang/StringBuilder;
     283: aload_2
     284: iconst_0
     285: aaload
     286: invokevirtual #126                // Method java/lang/StringBuilder.append:(Ljava/lang/String;)Ljava/lang/StringBuilder;
     289: ldc           #167                // String .in-addr.arpa.
     291: invokevirtual #126                // Method java/lang/StringBuilder.append:(Ljava/lang/String;)Ljava/lang/StringBuilder;
     294: invokevirtual #128                // Method java/lang/StringBuilder.toString:()Ljava/lang/String;
     297: astore_3
     298: getstatic     #2                  // Field LOG:Lorg/slf4j/Logger;
     301: ldc           #164                // String Inverted address [{}] built for [{}]
     303: aload_3
     304: aload_1
     305: invokeinterface #26,  4           // InterfaceMethod org/slf4j/Logger.debug:(Ljava/lang/String;Ljava/lang/Object;Ljava/lang/Object;)V
     310: aload_3
     311: areturn

  private void validateHostName(java.lang.String);
    Code:
       0: aload_1
       1: invokestatic  #168                // Method isHostName:(Ljava/lang/String;)Z
       4: ifne          31
       7: new           #109                // class java/lang/IllegalArgumentException
      10: dup
      11: getstatic     #152                // Field java/util/Locale.ENGLISH:Ljava/util/Locale;
      14: ldc           #169                // String [%s] is an invalid hostname. Please supply a pure hostname (eg. api.graylog.com)
      16: iconst_1
      17: anewarray     #17                 // class java/lang/Object
      20: dup
      21: iconst_0
      22: aload_1
      23: aastore
      24: invokestatic  #154                // Method java/lang/String.format:(Ljava/util/Locale;Ljava/lang/String;[Ljava/lang/Object;)Ljava/lang/String;
      27: invokespecial #155                // Method java/lang/IllegalArgumentException."<init>":(Ljava/lang/String;)V
      30: athrow
      31: return

  public static boolean isHostName(java.lang.String);
    Code:
       0: getstatic     #170                // Field VALID_HOSTNAME_PATTERN:Ljava/util/regex/Pattern;
       3: aload_0
       4: invokevirtual #171                // Method java/util/regex/Pattern.matcher:(Ljava/lang/CharSequence;)Ljava/util/regex/Matcher;
       7: invokevirtual #172                // Method java/util/regex/Matcher.matches:()Z
      10: ireturn

  private static void validateIpAddress(java.lang.String);
    Code:
       0: aload_0
       1: invokestatic  #173                // Method isValidIpAddress:(Ljava/lang/String;)Z
       4: ifne          31
       7: new           #109                // class java/lang/IllegalArgumentException
      10: dup
      11: getstatic     #152                // Field java/util/Locale.ENGLISH:Ljava/util/Locale;
      14: ldc           #174                // String [%s] is an invalid IP address.
      16: iconst_1
      17: anewarray     #17                 // class java/lang/Object
      20: dup
      21: iconst_0
      22: aload_0
      23: aastore
      24: invokestatic  #154                // Method java/lang/String.format:(Ljava/util/Locale;Ljava/lang/String;[Ljava/lang/Object;)Ljava/lang/String;
      27: invokespecial #155                // Method java/lang/IllegalArgumentException."<init>":(Ljava/lang/String;)V
      30: athrow
      31: return

  private static boolean isValidIpAddress(java.lang.String);
    Code:
       0: aload_0
       1: invokestatic  #175                // Method isIp4Address:(Ljava/lang/String;)Z
       4: ifne          14
       7: aload_0
       8: invokestatic  #148                // Method isIp6Address:(Ljava/lang/String;)Z
      11: ifeq          18
      14: iconst_1
      15: goto          19
      18: iconst_0
      19: ireturn

  public static boolean isIp4Address(java.lang.String);
    Code:
       0: aload_0
       1: invokestatic  #150                // Method com/google/common/net/InetAddresses.forString:(Ljava/lang/String;)Ljava/net/InetAddress;
       4: astore_1
       5: aload_1
       6: instanceof    #87                 // class java/net/Inet4Address
       9: ifeq          14
      12: iconst_1
      13: ireturn
      14: goto          18
      17: astore_1
      18: iconst_0
      19: ireturn
    Exception table:
       from    to  target type
           0    13    17   Class java/lang/IllegalArgumentException

  public static boolean isIp6Address(java.lang.String);
    Code:
       0: aload_0
       1: invokestatic  #150                // Method com/google/common/net/InetAddresses.forString:(Ljava/lang/String;)Ljava/net/InetAddress;
       4: astore_1
       5: aload_1
       6: instanceof    #176                // class java/net/Inet6Address
       9: ifeq          14
      12: iconst_1
      13: ireturn
      14: goto          18
      17: astore_1
      18: iconst_0
      19: ireturn
    Exception table:
       from    to  target type
           0    13    17   Class java/lang/IllegalArgumentException

  public static boolean allIpAddressesValid(java.lang.String);
    Code:
       0: aload_0
       1: invokestatic  #177                // Method com/google/common/base/Strings.isNullOrEmpty:(Ljava/lang/String;)Z
       4: ifne          49
       7: ldc           #30                 // String ,
       9: invokestatic  #31                 // Method com/google/common/base/Splitter.on:(Ljava/lang/String;)Lcom/google/common/base/Splitter;
      12: invokevirtual #32                 // Method com/google/common/base/Splitter.trimResults:()Lcom/google/common/base/Splitter;
      15: invokevirtual #33                 // Method com/google/common/base/Splitter.omitEmptyStrings:()Lcom/google/common/base/Splitter;
      18: aload_0
      19: invokevirtual #34                 // Method com/google/common/base/Splitter.split:(Ljava/lang/CharSequence;)Ljava/lang/Iterable;
      22: invokestatic  #178                // Method com/google/common/collect/Lists.newArrayList:(Ljava/lang/Iterable;)Ljava/util/ArrayList;
      25: invokevirtual #179                // Method java/util/ArrayList.stream:()Ljava/util/stream/Stream;
      28: invokedynamic #180,  0            // InvokeDynamic #5:apply:()Ljava/util/function/Function;
      33: invokeinterface #38,  2           // InterfaceMethod java/util/stream/Stream.map:(Ljava/util/function/Function;)Ljava/util/stream/Stream;
      38: invokedynamic #181,  0            // InvokeDynamic #6:test:()Ljava/util/function/Predicate;
      43: invokeinterface #182,  2          // InterfaceMethod java/util/stream/Stream.allMatch:(Ljava/util/function/Predicate;)Z
      48: ireturn
      49: iconst_0
      50: ireturn

  private static boolean lambda$allIpAddressesValid$5(com.google.common.net.HostAndPort);
    Code:
       0: aload_0
       1: invokevirtual #183                // Method com/google/common/net/HostAndPort.getHost:()Ljava/lang/String;
       4: invokestatic  #173                // Method isValidIpAddress:(Ljava/lang/String;)Z
       7: ireturn

  private static com.google.common.net.HostAndPort lambda$allIpAddressesValid$4(java.lang.String);
    Code:
       0: aload_0
       1: invokestatic  #184                // Method com/google/common/net/HostAndPort.fromString:(Ljava/lang/String;)Lcom/google/common/net/HostAndPort;
       4: bipush        53
       6: invokevirtual #185                // Method com/google/common/net/HostAndPort.withDefaultPort:(I)Lcom/google/common/net/HostAndPort;
       9: areturn

  private static org.graylog2.lookup.adapters.dnslookup.ADnsAnswer lambda$resolveIpAddresses$3(boolean, io.netty.handler.codec.dns.DnsRecord);
    Code:
       0: aload_1
       1: iload_0
       2: invokestatic  #186                // Method decodeDnsRecord:(Lio/netty/handler/codec/dns/DnsRecord;Z)Lorg/graylog2/lookup/adapters/dnslookup/ADnsAnswer;
       5: areturn

  private static void lambda$stop$2(io.netty.util.concurrent.Future) throws java.lang.Exception;
    Code:
       0: getstatic     #2                  // Field LOG:Lorg/slf4j/Logger;
       3: ldc           #187                // String DNS client shutdown successful
       5: invokeinterface #4,  2            // InterfaceMethod org/slf4j/Logger.debug:(Ljava/lang/String;)V
      10: return

  private static java.net.InetSocketAddress lambda$parseServerIpAddresses$1(com.google.common.net.HostAndPort);
    Code:
       0: new           #188                // class java/net/InetSocketAddress
       3: dup
       4: aload_0
       5: invokevirtual #183                // Method com/google/common/net/HostAndPort.getHost:()Ljava/lang/String;
       8: aload_0
       9: invokevirtual #189                // Method com/google/common/net/HostAndPort.getPort:()I
      12: invokespecial #190                // Method java/net/InetSocketAddress."<init>":(Ljava/lang/String;I)V
      15: areturn

  private static com.google.common.net.HostAndPort lambda$parseServerIpAddresses$0(java.lang.String);
    Code:
       0: aload_0
       1: invokestatic  #184                // Method com/google/common/net/HostAndPort.fromString:(Ljava/lang/String;)Lcom/google/common/net/HostAndPort;
       4: bipush        53
       6: invokevirtual #185                // Method com/google/common/net/HostAndPort.withDefaultPort:(I)Lcom/google/common/net/HostAndPort;
       9: areturn

  static {};
    Code:
       0: ldc           #18                 // class org/graylog2/lookup/adapters/dnslookup/DnsClient
       2: invokestatic  #191                // Method org/slf4j/LoggerFactory.getLogger:(Ljava/lang/Class;)Lorg/slf4j/Logger;
       5: putstatic     #2                  // Field LOG:Lorg/slf4j/Logger;
       8: ldc           #192                // String ^(([a-zA-Z0-9]|[a-zA-Z0-9][a-zA-Z0-9\\-]*[a-zA-Z0-9])\\.)*([A-Za-z0-9]|[A-Za-z0-9][A-Za-z0-9\\-]*[A-Za-z0-9])$
      10: invokestatic  #193                // Method java/util/regex/Pattern.compile:(Ljava/lang/String;)Ljava/util/regex/Pattern;
      13: putstatic     #170                // Field VALID_HOSTNAME_PATTERN:Ljava/util/regex/Pattern;
      16: ldc           #194                // String 0123456789ABCDEF
      18: invokevirtual #195                // Method java/lang/String.toCharArray:()[C
      21: putstatic     #156                // Field HEX_CHARS_ARRAY:[C
      24: return
}
