Compiled from "PtrDnsAnswer.java"
public abstract class org.graylog2.lookup.adapters.dnslookup.PtrDnsAnswer$Builder {
  public org.graylog2.lookup.adapters.dnslookup.PtrDnsAnswer$Builder();
    Code:
       0: aload_0
       1: invokespecial #1                  // Method java/lang/Object."<init>":()V
       4: return

  public static org.graylog2.lookup.adapters.dnslookup.PtrDnsAnswer$Builder createDefault();
    Code:
       0: invokestatic  #2                  // Method org/graylog2/lookup/adapters/dnslookup/PtrDnsAnswer.builder:()Lorg/graylog2/lookup/adapters/dnslookup/PtrDnsAnswer$Builder;
       3: areturn

  public abstract org.graylog2.lookup.adapters.dnslookup.PtrDnsAnswer$Builder domain(java.lang.String);

  public abstract org.graylog2.lookup.adapters.dnslookup.PtrDnsAnswer$Builder fullDomain(java.lang.String);

  public abstract org.graylog2.lookup.adapters.dnslookup.PtrDnsAnswer$Builder dnsTTL(long);

  abstract org.graylog2.lookup.adapters.dnslookup.PtrDnsAnswer autoBuild();

  public org.graylog2.lookup.adapters.dnslookup.PtrDnsAnswer build();
    Code:
       0: aload_0
       1: invokevirtual #3                  // Method autoBuild:()Lorg/graylog2/lookup/adapters/dnslookup/PtrDnsAnswer;
       4: areturn
}
