Compiled from "SockJSImpl.java"
public class io.vertx.ext.web.handler.sockjs.impl.SockJSImpl implements io.vertx.ext.web.handler.sockjs.SockJSHandler {
  private static final io.vertx.core.impl.logging.Logger LOG;

  private final io.vertx.core.Vertx vertx;

  private final io.vertx.core.shareddata.LocalMap<java.lang.String, io.vertx.ext.web.handler.sockjs.impl.SockJSSession> sessions;

  private final io.vertx.ext.web.handler.sockjs.SockJSHandlerOptions options;

  private static final java.lang.String IFRAME_TEMPLATE;

  public io.vertx.ext.web.handler.sockjs.impl.SockJSImpl(io.vertx.core.Vertx, io.vertx.ext.web.handler.sockjs.SockJSHandlerOptions);
    Code:
       0: aload_0
       1: invokespecial #2                  // Method java/lang/Object."<init>":()V
       4: aload_0
       5: aload_1
       6: putfield      #1                  // Field vertx:Lio/vertx/core/Vertx;
       9: aload_0
      10: aload_1
      11: invokeinterface #3,  1            // InterfaceMethod io/vertx/core/Vertx.sharedData:()Lio/vertx/core/shareddata/SharedData;
      16: ldc           #4                  // String _vertx.sockjssessions
      18: invokeinterface #5,  2            // InterfaceMethod io/vertx/core/shareddata/SharedData.getLocalMap:(Ljava/lang/String;)Lio/vertx/core/shareddata/LocalMap;
      23: putfield      #6                  // Field sessions:Lio/vertx/core/shareddata/LocalMap;
      26: aload_0
      27: aload_2
      28: putfield      #7                  // Field options:Lio/vertx/ext/web/handler/sockjs/SockJSHandlerOptions;
      31: return

  public io.vertx.ext.web.Router bridge(io.vertx.ext.auth.authorization.AuthorizationProvider, io.vertx.ext.web.handler.sockjs.SockJSBridgeOptions, io.vertx.core.Handler<io.vertx.ext.web.handler.sockjs.BridgeEvent>);
    Code:
       0: aload_0
       1: new           #8                  // class io/vertx/ext/web/handler/sockjs/impl/EventBusBridgeImpl
       4: dup
       5: aload_0
       6: getfield      #1                  // Field vertx:Lio/vertx/core/Vertx;
       9: aload_1
      10: aload_2
      11: aload_3
      12: invokespecial #9                  // Method io/vertx/ext/web/handler/sockjs/impl/EventBusBridgeImpl."<init>":(Lio/vertx/core/Vertx;Lio/vertx/ext/auth/authorization/AuthorizationProvider;Lio/vertx/ext/web/handler/sockjs/SockJSBridgeOptions;Lio/vertx/core/Handler;)V
      15: invokevirtual #10                 // Method socketHandler:(Lio/vertx/core/Handler;)Lio/vertx/ext/web/Router;
      18: areturn

  public void handle(io.vertx.ext.web.RoutingContext);
    Code:
       0: new           #11                 // class java/lang/UnsupportedOperationException
       3: dup
       4: ldc           #12                 // String Mount the router as a sub-router instead. This method will not properly handle errors.
       6: invokespecial #13                 // Method java/lang/UnsupportedOperationException."<init>":(Ljava/lang/String;)V
       9: athrow

  public io.vertx.ext.web.Router socketHandler(io.vertx.core.Handler<io.vertx.ext.web.handler.sockjs.SockJSSocket>);
    Code:
       0: aload_0
       1: getfield      #1                  // Field vertx:Lio/vertx/core/Vertx;
       4: invokestatic  #14                 // InterfaceMethod io/vertx/ext/web/Router.router:(Lio/vertx/core/Vertx;)Lio/vertx/ext/web/Router;
       7: astore_2
       8: aload_2
       9: ldc           #15                 // String /
      11: invokeinterface #16,  2           // InterfaceMethod io/vertx/ext/web/Router.route:(Ljava/lang/String;)Lio/vertx/ext/web/Route;
      16: iconst_0
      17: invokeinterface #17,  2           // InterfaceMethod io/vertx/ext/web/Route.useNormalizedPath:(Z)Lio/vertx/ext/web/Route;
      22: invokedynamic #18,  0             // InvokeDynamic #0:handle:()Lio/vertx/ext/web/handler/PlatformHandler;
      27: invokeinterface #19,  2           // InterfaceMethod io/vertx/ext/web/Route.handler:(Lio/vertx/core/Handler;)Lio/vertx/ext/web/Route;
      32: pop
      33: ldc           #21                 // String <!DOCTYPE html>\n<html>\n<head>\n  <meta http-equiv=\"X-UA-Compatible\" content=\"IE=edge\" />\n  <meta http-equiv=\"Content-Type\" content=\"text/html; charset=UTF-8\" />\n  <script src=\"{{ sockjs_url }}\"></script>\n  <script>\n    document.domain = document.domain;\n    SockJS.bootstrap_iframe();\n  </script>\n</head>\n<body>\n  <h2>Don\'t panic!</h2>\n  <p>This is a SockJS hidden iframe. It\'s used for cross domain magic.</p>\n</body>\n</html>
      35: ldc           #22                 // String {{ sockjs_url }}
      37: aload_0
      38: getfield      #7                  // Field options:Lio/vertx/ext/web/handler/sockjs/SockJSHandlerOptions;
      41: invokevirtual #23                 // Method io/vertx/ext/web/handler/sockjs/SockJSHandlerOptions.getLibraryURL:()Ljava/lang/String;
      44: invokevirtual #24                 // Method java/lang/String.replace:(Ljava/lang/CharSequence;Ljava/lang/CharSequence;)Ljava/lang/String;
      47: astore_3
      48: aload_0
      49: aload_3
      50: invokespecial #25                 // Method createIFrameHandler:(Ljava/lang/String;)Lio/vertx/ext/web/handler/PlatformHandler;
      53: astore        4
      55: aload_2
      56: ldc           #26                 // String /iframe.html
      58: invokeinterface #27,  2           // InterfaceMethod io/vertx/ext/web/Router.get:(Ljava/lang/String;)Lio/vertx/ext/web/Route;
      63: aload         4
      65: invokeinterface #19,  2           // InterfaceMethod io/vertx/ext/web/Route.handler:(Lio/vertx/core/Handler;)Lio/vertx/ext/web/Route;
      70: pop
      71: aload_2
      72: ldc           #28                 // String \\/iframe-[^\\/]*\\.html
      74: invokeinterface #29,  2           // InterfaceMethod io/vertx/ext/web/Router.getWithRegex:(Ljava/lang/String;)Lio/vertx/ext/web/Route;
      79: aload         4
      81: invokeinterface #19,  2           // InterfaceMethod io/vertx/ext/web/Route.handler:(Lio/vertx/core/Handler;)Lio/vertx/ext/web/Route;
      86: pop
      87: aload_2
      88: ldc           #30                 // String /chunking_test
      90: invokeinterface #31,  2           // InterfaceMethod io/vertx/ext/web/Router.post:(Ljava/lang/String;)Lio/vertx/ext/web/Route;
      95: aload_0
      96: invokespecial #32                 // Method createChunkingTestHandler:()Lio/vertx/ext/web/handler/PlatformHandler;
      99: invokeinterface #19,  2           // InterfaceMethod io/vertx/ext/web/Route.handler:(Lio/vertx/core/Handler;)Lio/vertx/ext/web/Route;
     104: pop
     105: aload_2
     106: ldc           #30                 // String /chunking_test
     108: invokeinterface #33,  2           // InterfaceMethod io/vertx/ext/web/Router.options:(Ljava/lang/String;)Lio/vertx/ext/web/Route;
     113: aload_0
     114: getfield      #7                  // Field options:Lio/vertx/ext/web/handler/sockjs/SockJSHandlerOptions;
     117: ldc           #34                 // String OPTIONS, POST
     119: invokestatic  #35                 // Method io/vertx/ext/web/handler/sockjs/impl/BaseTransport.createCORSOptionsHandler:(Lio/vertx/ext/web/handler/sockjs/SockJSHandlerOptions;Ljava/lang/String;)Lio/vertx/ext/web/handler/SecurityPolicyHandler;
     122: invokeinterface #19,  2           // InterfaceMethod io/vertx/ext/web/Route.handler:(Lio/vertx/core/Handler;)Lio/vertx/ext/web/Route;
     127: pop
     128: aload_2
     129: ldc           #36                 // String /info
     131: invokeinterface #27,  2           // InterfaceMethod io/vertx/ext/web/Router.get:(Ljava/lang/String;)Lio/vertx/ext/web/Route;
     136: aload_0
     137: getfield      #7                  // Field options:Lio/vertx/ext/web/handler/sockjs/SockJSHandlerOptions;
     140: aload_0
     141: getfield      #1                  // Field vertx:Lio/vertx/core/Vertx;
     144: invokestatic  #37                 // InterfaceMethod io/vertx/ext/auth/VertxContextPRNG.current:(Lio/vertx/core/Vertx;)Lio/vertx/ext/auth/VertxContextPRNG;
     147: invokestatic  #38                 // Method io/vertx/ext/web/handler/sockjs/impl/BaseTransport.createInfoHandler:(Lio/vertx/ext/web/handler/sockjs/SockJSHandlerOptions;Lio/vertx/ext/auth/VertxContextPRNG;)Lio/vertx/ext/web/handler/PlatformHandler;
     150: invokeinterface #19,  2           // InterfaceMethod io/vertx/ext/web/Route.handler:(Lio/vertx/core/Handler;)Lio/vertx/ext/web/Route;
     155: pop
     156: aload_2
     157: ldc           #36                 // String /info
     159: invokeinterface #33,  2           // InterfaceMethod io/vertx/ext/web/Router.options:(Ljava/lang/String;)Lio/vertx/ext/web/Route;
     164: aload_0
     165: getfield      #7                  // Field options:Lio/vertx/ext/web/handler/sockjs/SockJSHandlerOptions;
     168: ldc           #39                 // String OPTIONS, GET
     170: invokestatic  #35                 // Method io/vertx/ext/web/handler/sockjs/impl/BaseTransport.createCORSOptionsHandler:(Lio/vertx/ext/web/handler/sockjs/SockJSHandlerOptions;Ljava/lang/String;)Lio/vertx/ext/web/handler/SecurityPolicyHandler;
     173: invokeinterface #19,  2           // InterfaceMethod io/vertx/ext/web/Route.handler:(Lio/vertx/core/Handler;)Lio/vertx/ext/web/Route;
     178: pop
     179: new           #40                 // class java/util/HashSet
     182: dup
     183: invokespecial #41                 // Method java/util/HashSet."<init>":()V
     186: astore        5
     188: aload         5
     190: getstatic     #42                 // Field io/vertx/ext/web/handler/sockjs/Transport.EVENT_SOURCE:Lio/vertx/ext/web/handler/sockjs/Transport;
     193: invokevirtual #43                 // Method io/vertx/ext/web/handler/sockjs/Transport.toString:()Ljava/lang/String;
     196: invokeinterface #44,  2           // InterfaceMethod java/util/Set.add:(Ljava/lang/Object;)Z
     201: pop
     202: aload         5
     204: getstatic     #45                 // Field io/vertx/ext/web/handler/sockjs/Transport.HTML_FILE:Lio/vertx/ext/web/handler/sockjs/Transport;
     207: invokevirtual #43                 // Method io/vertx/ext/web/handler/sockjs/Transport.toString:()Ljava/lang/String;
     210: invokeinterface #44,  2           // InterfaceMethod java/util/Set.add:(Ljava/lang/Object;)Z
     215: pop
     216: aload         5
     218: getstatic     #46                 // Field io/vertx/ext/web/handler/sockjs/Transport.JSON_P:Lio/vertx/ext/web/handler/sockjs/Transport;
     221: invokevirtual #43                 // Method io/vertx/ext/web/handler/sockjs/Transport.toString:()Ljava/lang/String;
     224: invokeinterface #44,  2           // InterfaceMethod java/util/Set.add:(Ljava/lang/Object;)Z
     229: pop
     230: aload         5
     232: getstatic     #47                 // Field io/vertx/ext/web/handler/sockjs/Transport.WEBSOCKET:Lio/vertx/ext/web/handler/sockjs/Transport;
     235: invokevirtual #43                 // Method io/vertx/ext/web/handler/sockjs/Transport.toString:()Ljava/lang/String;
     238: invokeinterface #44,  2           // InterfaceMethod java/util/Set.add:(Ljava/lang/Object;)Z
     243: pop
     244: aload         5
     246: getstatic     #48                 // Field io/vertx/ext/web/handler/sockjs/Transport.XHR:Lio/vertx/ext/web/handler/sockjs/Transport;
     249: invokevirtual #43                 // Method io/vertx/ext/web/handler/sockjs/Transport.toString:()Ljava/lang/String;
     252: invokeinterface #44,  2           // InterfaceMethod java/util/Set.add:(Ljava/lang/Object;)Z
     257: pop
     258: aload_0
     259: getfield      #7                  // Field options:Lio/vertx/ext/web/handler/sockjs/SockJSHandlerOptions;
     262: invokevirtual #49                 // Method io/vertx/ext/web/handler/sockjs/SockJSHandlerOptions.getDisabledTransports:()Ljava/util/Set;
     265: astore        6
     267: aload         6
     269: ifnonnull     281
     272: new           #40                 // class java/util/HashSet
     275: dup
     276: invokespecial #41                 // Method java/util/HashSet."<init>":()V
     279: astore        6
     281: aload         5
     283: aload         6
     285: invokeinterface #50,  2           // InterfaceMethod java/util/Set.removeAll:(Ljava/util/Collection;)Z
     290: pop
     291: aload         5
     293: getstatic     #48                 // Field io/vertx/ext/web/handler/sockjs/Transport.XHR:Lio/vertx/ext/web/handler/sockjs/Transport;
     296: invokevirtual #43                 // Method io/vertx/ext/web/handler/sockjs/Transport.toString:()Ljava/lang/String;
     299: invokeinterface #51,  2           // InterfaceMethod java/util/Set.contains:(Ljava/lang/Object;)Z
     304: ifeq          329
     307: new           #52                 // class io/vertx/ext/web/handler/sockjs/impl/XhrTransport
     310: dup
     311: aload_0
     312: getfield      #1                  // Field vertx:Lio/vertx/core/Vertx;
     315: aload_2
     316: aload_0
     317: getfield      #6                  // Field sessions:Lio/vertx/core/shareddata/LocalMap;
     320: aload_0
     321: getfield      #7                  // Field options:Lio/vertx/ext/web/handler/sockjs/SockJSHandlerOptions;
     324: aload_1
     325: invokespecial #53                 // Method io/vertx/ext/web/handler/sockjs/impl/XhrTransport."<init>":(Lio/vertx/core/Vertx;Lio/vertx/ext/web/Router;Lio/vertx/core/shareddata/LocalMap;Lio/vertx/ext/web/handler/sockjs/SockJSHandlerOptions;Lio/vertx/core/Handler;)V
     328: pop
     329: aload         5
     331: getstatic     #42                 // Field io/vertx/ext/web/handler/sockjs/Transport.EVENT_SOURCE:Lio/vertx/ext/web/handler/sockjs/Transport;
     334: invokevirtual #43                 // Method io/vertx/ext/web/handler/sockjs/Transport.toString:()Ljava/lang/String;
     337: invokeinterface #51,  2           // InterfaceMethod java/util/Set.contains:(Ljava/lang/Object;)Z
     342: ifeq          367
     345: new           #54                 // class io/vertx/ext/web/handler/sockjs/impl/EventSourceTransport
     348: dup
     349: aload_0
     350: getfield      #1                  // Field vertx:Lio/vertx/core/Vertx;
     353: aload_2
     354: aload_0
     355: getfield      #6                  // Field sessions:Lio/vertx/core/shareddata/LocalMap;
     358: aload_0
     359: getfield      #7                  // Field options:Lio/vertx/ext/web/handler/sockjs/SockJSHandlerOptions;
     362: aload_1
     363: invokespecial #55                 // Method io/vertx/ext/web/handler/sockjs/impl/EventSourceTransport."<init>":(Lio/vertx/core/Vertx;Lio/vertx/ext/web/Router;Lio/vertx/core/shareddata/LocalMap;Lio/vertx/ext/web/handler/sockjs/SockJSHandlerOptions;Lio/vertx/core/Handler;)V
     366: pop
     367: aload         5
     369: getstatic     #45                 // Field io/vertx/ext/web/handler/sockjs/Transport.HTML_FILE:Lio/vertx/ext/web/handler/sockjs/Transport;
     372: invokevirtual #43                 // Method io/vertx/ext/web/handler/sockjs/Transport.toString:()Ljava/lang/String;
     375: invokeinterface #51,  2           // InterfaceMethod java/util/Set.contains:(Ljava/lang/Object;)Z
     380: ifeq          405
     383: new           #56                 // class io/vertx/ext/web/handler/sockjs/impl/HtmlFileTransport
     386: dup
     387: aload_0
     388: getfield      #1                  // Field vertx:Lio/vertx/core/Vertx;
     391: aload_2
     392: aload_0
     393: getfield      #6                  // Field sessions:Lio/vertx/core/shareddata/LocalMap;
     396: aload_0
     397: getfield      #7                  // Field options:Lio/vertx/ext/web/handler/sockjs/SockJSHandlerOptions;
     400: aload_1
     401: invokespecial #57                 // Method io/vertx/ext/web/handler/sockjs/impl/HtmlFileTransport."<init>":(Lio/vertx/core/Vertx;Lio/vertx/ext/web/Router;Lio/vertx/core/shareddata/LocalMap;Lio/vertx/ext/web/handler/sockjs/SockJSHandlerOptions;Lio/vertx/core/Handler;)V
     404: pop
     405: aload         5
     407: getstatic     #46                 // Field io/vertx/ext/web/handler/sockjs/Transport.JSON_P:Lio/vertx/ext/web/handler/sockjs/Transport;
     410: invokevirtual #43                 // Method io/vertx/ext/web/handler/sockjs/Transport.toString:()Ljava/lang/String;
     413: invokeinterface #51,  2           // InterfaceMethod java/util/Set.contains:(Ljava/lang/Object;)Z
     418: ifeq          443
     421: new           #58                 // class io/vertx/ext/web/handler/sockjs/impl/JsonPTransport
     424: dup
     425: aload_0
     426: getfield      #1                  // Field vertx:Lio/vertx/core/Vertx;
     429: aload_2
     430: aload_0
     431: getfield      #6                  // Field sessions:Lio/vertx/core/shareddata/LocalMap;
     434: aload_0
     435: getfield      #7                  // Field options:Lio/vertx/ext/web/handler/sockjs/SockJSHandlerOptions;
     438: aload_1
     439: invokespecial #59                 // Method io/vertx/ext/web/handler/sockjs/impl/JsonPTransport."<init>":(Lio/vertx/core/Vertx;Lio/vertx/ext/web/Router;Lio/vertx/core/shareddata/LocalMap;Lio/vertx/ext/web/handler/sockjs/SockJSHandlerOptions;Lio/vertx/core/Handler;)V
     442: pop
     443: aload         5
     445: getstatic     #47                 // Field io/vertx/ext/web/handler/sockjs/Transport.WEBSOCKET:Lio/vertx/ext/web/handler/sockjs/Transport;
     448: invokevirtual #43                 // Method io/vertx/ext/web/handler/sockjs/Transport.toString:()Ljava/lang/String;
     451: invokeinterface #51,  2           // InterfaceMethod java/util/Set.contains:(Ljava/lang/Object;)Z
     456: ifeq          499
     459: new           #60                 // class io/vertx/ext/web/handler/sockjs/impl/WebSocketTransport
     462: dup
     463: aload_0
     464: getfield      #1                  // Field vertx:Lio/vertx/core/Vertx;
     467: aload_2
     468: aload_0
     469: getfield      #6                  // Field sessions:Lio/vertx/core/shareddata/LocalMap;
     472: aload_0
     473: getfield      #7                  // Field options:Lio/vertx/ext/web/handler/sockjs/SockJSHandlerOptions;
     476: aload_1
     477: invokespecial #61                 // Method io/vertx/ext/web/handler/sockjs/impl/WebSocketTransport."<init>":(Lio/vertx/core/Vertx;Lio/vertx/ext/web/Router;Lio/vertx/core/shareddata/LocalMap;Lio/vertx/ext/web/handler/sockjs/SockJSHandlerOptions;Lio/vertx/core/Handler;)V
     480: pop
     481: new           #62                 // class io/vertx/ext/web/handler/sockjs/impl/RawWebSocketTransport
     484: dup
     485: aload_0
     486: getfield      #1                  // Field vertx:Lio/vertx/core/Vertx;
     489: aload_2
     490: aload_0
     491: getfield      #7                  // Field options:Lio/vertx/ext/web/handler/sockjs/SockJSHandlerOptions;
     494: aload_1
     495: invokespecial #63                 // Method io/vertx/ext/web/handler/sockjs/impl/RawWebSocketTransport."<init>":(Lio/vertx/core/Vertx;Lio/vertx/ext/web/Router;Lio/vertx/ext/web/handler/sockjs/SockJSHandlerOptions;Lio/vertx/core/Handler;)V
     498: pop
     499: aload_2
     500: areturn

  private io.vertx.ext.web.handler.PlatformHandler createChunkingTestHandler();
    Code:
       0: new           #64                 // class io/vertx/ext/web/handler/sockjs/impl/SockJSImpl$1
       3: dup
       4: aload_0
       5: invokespecial #65                 // Method io/vertx/ext/web/handler/sockjs/impl/SockJSImpl$1."<init>":(Lio/vertx/ext/web/handler/sockjs/impl/SockJSImpl;)V
       8: areturn

  private io.vertx.ext.web.handler.PlatformHandler createIFrameHandler(java.lang.String);
    Code:
       0: aload_1
       1: invokestatic  #66                 // Method getMD5String:(Ljava/lang/String;)Ljava/lang/String;
       4: astore_2
       5: aload_2
       6: aload_1
       7: invokedynamic #67,  0             // InvokeDynamic #1:handle:(Ljava/lang/String;Ljava/lang/String;)Lio/vertx/ext/web/handler/PlatformHandler;
      12: areturn

  private static java.lang.String getMD5String(java.lang.String);
    Code:
       0: ldc           #68                 // String MD5
       2: invokestatic  #69                 // Method java/security/MessageDigest.getInstance:(Ljava/lang/String;)Ljava/security/MessageDigest;
       5: astore_1
       6: aload_1
       7: aload_0
       8: getstatic     #70                 // Field java/nio/charset/StandardCharsets.UTF_8:Ljava/nio/charset/Charset;
      11: invokevirtual #71                 // Method java/lang/String.getBytes:(Ljava/nio/charset/Charset;)[B
      14: invokevirtual #72                 // Method java/security/MessageDigest.digest:([B)[B
      17: astore_2
      18: aload_2
      19: invokestatic  #73                 // Method io/vertx/ext/auth/impl/Codec.base16Encode:([B)Ljava/lang/String;
      22: areturn
      23: astore_1
      24: getstatic     #75                 // Field LOG:Lio/vertx/core/impl/logging/Logger;
      27: ldc           #76                 // String Failed to generate MD5 for iframe, If-None-Match headers will be ignored
      29: invokeinterface #77,  2           // InterfaceMethod io/vertx/core/impl/logging/Logger.error:(Ljava/lang/Object;)V
      34: aconst_null
      35: areturn
    Exception table:
       from    to  target type
           0    22    23   Class java/lang/Exception

  public void handle(java.lang.Object);
    Code:
       0: aload_0
       1: aload_1
       2: checkcast     #78                 // class io/vertx/ext/web/RoutingContext
       5: invokevirtual #79                 // Method handle:(Lio/vertx/ext/web/RoutingContext;)V
       8: return

  private static void lambda$createIFrameHandler$1(java.lang.String, java.lang.String, io.vertx.ext.web.RoutingContext);
    Code:
       0: getstatic     #75                 // Field LOG:Lio/vertx/core/impl/logging/Logger;
       3: invokeinterface #80,  1           // InterfaceMethod io/vertx/core/impl/logging/Logger.isTraceEnabled:()Z
       8: ifeq          21
      11: getstatic     #75                 // Field LOG:Lio/vertx/core/impl/logging/Logger;
      14: ldc           #81                 // String In Iframe handler
      16: invokeinterface #82,  2           // InterfaceMethod io/vertx/core/impl/logging/Logger.trace:(Ljava/lang/Object;)V
      21: aload_0
      22: ifnull        76
      25: aload_0
      26: aload_2
      27: invokeinterface #83,  1           // InterfaceMethod io/vertx/ext/web/RoutingContext.request:()Lio/vertx/core/http/HttpServerRequest;
      32: getstatic     #84                 // Field io/vertx/core/http/HttpHeaders.IF_NONE_MATCH:Ljava/lang/CharSequence;
      35: invokeinterface #85,  2           // InterfaceMethod io/vertx/core/http/HttpServerRequest.getHeader:(Ljava/lang/CharSequence;)Ljava/lang/String;
      40: invokevirtual #86                 // Method java/lang/String.equals:(Ljava/lang/Object;)Z
      43: ifeq          76
      46: aload_2
      47: invokeinterface #87,  1           // InterfaceMethod io/vertx/ext/web/RoutingContext.response:()Lio/vertx/core/http/HttpServerResponse;
      52: sipush        304
      55: invokeinterface #88,  2           // InterfaceMethod io/vertx/core/http/HttpServerResponse.setStatusCode:(I)Lio/vertx/core/http/HttpServerResponse;
      60: pop
      61: aload_2
      62: invokeinterface #87,  1           // InterfaceMethod io/vertx/ext/web/RoutingContext.response:()Lio/vertx/core/http/HttpServerResponse;
      67: invokeinterface #89,  1           // InterfaceMethod io/vertx/core/http/HttpServerResponse.end:()Lio/vertx/core/Future;
      72: pop
      73: goto          158
      76: ldc2_w        #90                 // long 31536000000l
      79: lstore_3
      80: new           #92                 // class java/text/SimpleDateFormat
      83: dup
      84: ldc           #93                 // String EEE, dd MMM yyyy HH:mm:ss zzz
      86: invokespecial #94                 // Method java/text/SimpleDateFormat."<init>":(Ljava/lang/String;)V
      89: new           #95                 // class java/util/Date
      92: dup
      93: invokestatic  #96                 // Method java/lang/System.currentTimeMillis:()J
      96: lload_3
      97: ladd
      98: invokespecial #97                 // Method java/util/Date."<init>":(J)V
     101: invokevirtual #98                 // Method java/text/SimpleDateFormat.format:(Ljava/util/Date;)Ljava/lang/String;
     104: astore        5
     106: aload_2
     107: invokeinterface #87,  1           // InterfaceMethod io/vertx/ext/web/RoutingContext.response:()Lio/vertx/core/http/HttpServerResponse;
     112: getstatic     #99                 // Field io/vertx/core/http/HttpHeaders.CONTENT_TYPE:Ljava/lang/CharSequence;
     115: ldc           #100                // String text/html; charset=UTF-8
     117: invokeinterface #101,  3          // InterfaceMethod io/vertx/core/http/HttpServerResponse.putHeader:(Ljava/lang/CharSequence;Ljava/lang/CharSequence;)Lio/vertx/core/http/HttpServerResponse;
     122: getstatic     #102                // Field io/vertx/core/http/HttpHeaders.CACHE_CONTROL:Ljava/lang/CharSequence;
     125: ldc           #103                // String public,max-age=31536000
     127: invokeinterface #101,  3          // InterfaceMethod io/vertx/core/http/HttpServerResponse.putHeader:(Ljava/lang/CharSequence;Ljava/lang/CharSequence;)Lio/vertx/core/http/HttpServerResponse;
     132: getstatic     #104                // Field io/vertx/core/http/HttpHeaders.EXPIRES:Ljava/lang/CharSequence;
     135: aload         5
     137: invokeinterface #101,  3          // InterfaceMethod io/vertx/core/http/HttpServerResponse.putHeader:(Ljava/lang/CharSequence;Ljava/lang/CharSequence;)Lio/vertx/core/http/HttpServerResponse;
     142: getstatic     #105                // Field io/vertx/core/http/HttpHeaders.ETAG:Ljava/lang/CharSequence;
     145: aload_0
     146: invokeinterface #101,  3          // InterfaceMethod io/vertx/core/http/HttpServerResponse.putHeader:(Ljava/lang/CharSequence;Ljava/lang/CharSequence;)Lio/vertx/core/http/HttpServerResponse;
     151: aload_1
     152: invokeinterface #106,  2          // InterfaceMethod io/vertx/core/http/HttpServerResponse.end:(Ljava/lang/String;)Lio/vertx/core/Future;
     157: pop
     158: goto          173
     161: astore_3
     162: getstatic     #75                 // Field LOG:Lio/vertx/core/impl/logging/Logger;
     165: ldc           #107                // String Failed to server iframe
     167: aload_3
     168: invokeinterface #108,  3          // InterfaceMethod io/vertx/core/impl/logging/Logger.error:(Ljava/lang/Object;Ljava/lang/Throwable;)V
     173: return
    Exception table:
       from    to  target type
           0   158   161   Class java/lang/Exception

  private static void lambda$socketHandler$0(io.vertx.ext.web.RoutingContext);
    Code:
       0: getstatic     #75                 // Field LOG:Lio/vertx/core/impl/logging/Logger;
       3: invokeinterface #80,  1           // InterfaceMethod io/vertx/core/impl/logging/Logger.isTraceEnabled:()Z
       8: ifeq          21
      11: getstatic     #75                 // Field LOG:Lio/vertx/core/impl/logging/Logger;
      14: ldc           #109                // String Returning welcome response
      16: invokeinterface #82,  2           // InterfaceMethod io/vertx/core/impl/logging/Logger.trace:(Ljava/lang/Object;)V
      21: aload_0
      22: invokeinterface #87,  1           // InterfaceMethod io/vertx/ext/web/RoutingContext.response:()Lio/vertx/core/http/HttpServerResponse;
      27: getstatic     #99                 // Field io/vertx/core/http/HttpHeaders.CONTENT_TYPE:Ljava/lang/CharSequence;
      30: ldc           #110                // String text/plain; charset=UTF-8
      32: invokeinterface #101,  3          // InterfaceMethod io/vertx/core/http/HttpServerResponse.putHeader:(Ljava/lang/CharSequence;Ljava/lang/CharSequence;)Lio/vertx/core/http/HttpServerResponse;
      37: ldc           #111                // String Welcome to SockJS!\n
      39: invokeinterface #106,  2          // InterfaceMethod io/vertx/core/http/HttpServerResponse.end:(Ljava/lang/String;)Lio/vertx/core/Future;
      44: pop
      45: return

  static io.vertx.core.Vertx access$000(io.vertx.ext.web.handler.sockjs.impl.SockJSImpl);
    Code:
       0: aload_0
       1: getfield      #1                  // Field vertx:Lio/vertx/core/Vertx;
       4: areturn

  static {};
    Code:
       0: ldc           #20                 // class io/vertx/ext/web/handler/sockjs/impl/SockJSImpl
       2: invokestatic  #112                // Method io/vertx/core/impl/logging/LoggerFactory.getLogger:(Ljava/lang/Class;)Lio/vertx/core/impl/logging/Logger;
       5: putstatic     #75                 // Field LOG:Lio/vertx/core/impl/logging/Logger;
       8: return
}
