Compiled from "Turtle.java"
public final class org.hl7.fhir.utilities.turtle.Turtle$LexerTokenType extends java.lang.Enum<org.hl7.fhir.utilities.turtle.Turtle$LexerTokenType> {
  public static final org.hl7.fhir.utilities.turtle.Turtle$LexerTokenType TOKEN;

  public static final org.hl7.fhir.utilities.turtle.Turtle$LexerTokenType WORD;

  public static final org.hl7.fhir.utilities.turtle.Turtle$LexerTokenType URI;

  public static final org.hl7.fhir.utilities.turtle.Turtle$LexerTokenType LITERAL;

  private static final org.hl7.fhir.utilities.turtle.Turtle$LexerTokenType[] $VALUES;

  public static org.hl7.fhir.utilities.turtle.Turtle$LexerTokenType[] values();
    Code:
       0: getstatic     #1                  // Field $VALUES:[Lorg/hl7/fhir/utilities/turtle/Turtle$LexerTokenType;
       3: invokevirtual #2                  // Method "[Lorg/hl7/fhir/utilities/turtle/Turtle$LexerTokenType;".clone:()Ljava/lang/Object;
       6: checkcast     #3                  // class "[Lorg/hl7/fhir/utilities/turtle/Turtle$LexerTokenType;"
       9: areturn

  public static org.hl7.fhir.utilities.turtle.Turtle$LexerTokenType valueOf(java.lang.String);
    Code:
       0: ldc           #4                  // class org/hl7/fhir/utilities/turtle/Turtle$LexerTokenType
       2: aload_0
       3: invokestatic  #5                  // Method java/lang/Enum.valueOf:(Ljava/lang/Class;Ljava/lang/String;)Ljava/lang/Enum;
       6: checkcast     #4                  // class org/hl7/fhir/utilities/turtle/Turtle$LexerTokenType
       9: areturn

  private org.hl7.fhir.utilities.turtle.Turtle$LexerTokenType();
    Code:
       0: aload_0
       1: aload_1
       2: iload_2
       3: invokespecial #6                  // Method java/lang/Enum."<init>":(Ljava/lang/String;I)V
       6: return

  static {};
    Code:
       0: new           #4                  // class org/hl7/fhir/utilities/turtle/Turtle$LexerTokenType
       3: dup
       4: ldc           #7                  // String TOKEN
       6: iconst_0
       7: invokespecial #8                  // Method "<init>":(Ljava/lang/String;I)V
      10: putstatic     #9                  // Field TOKEN:Lorg/hl7/fhir/utilities/turtle/Turtle$LexerTokenType;
      13: new           #4                  // class org/hl7/fhir/utilities/turtle/Turtle$LexerTokenType
      16: dup
      17: ldc           #10                 // String WORD
      19: iconst_1
      20: invokespecial #8                  // Method "<init>":(Ljava/lang/String;I)V
      23: putstatic     #11                 // Field WORD:Lorg/hl7/fhir/utilities/turtle/Turtle$LexerTokenType;
      26: new           #4                  // class org/hl7/fhir/utilities/turtle/Turtle$LexerTokenType
      29: dup
      30: ldc           #12                 // String URI
      32: iconst_2
      33: invokespecial #8                  // Method "<init>":(Ljava/lang/String;I)V
      36: putstatic     #13                 // Field URI:Lorg/hl7/fhir/utilities/turtle/Turtle$LexerTokenType;
      39: new           #4                  // class org/hl7/fhir/utilities/turtle/Turtle$LexerTokenType
      42: dup
      43: ldc           #14                 // String LITERAL
      45: iconst_3
      46: invokespecial #8                  // Method "<init>":(Ljava/lang/String;I)V
      49: putstatic     #15                 // Field LITERAL:Lorg/hl7/fhir/utilities/turtle/Turtle$LexerTokenType;
      52: iconst_4
      53: anewarray     #4                  // class org/hl7/fhir/utilities/turtle/Turtle$LexerTokenType
      56: dup
      57: iconst_0
      58: getstatic     #9                  // Field TOKEN:Lorg/hl7/fhir/utilities/turtle/Turtle$LexerTokenType;
      61: aastore
      62: dup
      63: iconst_1
      64: getstatic     #11                 // Field WORD:Lorg/hl7/fhir/utilities/turtle/Turtle$LexerTokenType;
      67: aastore
      68: dup
      69: iconst_2
      70: getstatic     #13                 // Field URI:Lorg/hl7/fhir/utilities/turtle/Turtle$LexerTokenType;
      73: aastore
      74: dup
      75: iconst_3
      76: getstatic     #15                 // Field LITERAL:Lorg/hl7/fhir/utilities/turtle/Turtle$LexerTokenType;
      79: aastore
      80: putstatic     #1                  // Field $VALUES:[Lorg/hl7/fhir/utilities/turtle/Turtle$LexerTokenType;
      83: return
}
