Compiled from "Turtle.java"
public abstract class org.hl7.fhir.utilities.turtle.Turtle$TTLObject {
  protected int line;

  protected int col;

  final org.hl7.fhir.utilities.turtle.Turtle this$0;

  public org.hl7.fhir.utilities.turtle.Turtle$TTLObject(org.hl7.fhir.utilities.turtle.Turtle);
    Code:
       0: aload_0
       1: aload_1
       2: putfield      #1                  // Field this$0:Lorg/hl7/fhir/utilities/turtle/Turtle;
       5: aload_0
       6: invokespecial #2                  // Method java/lang/Object."<init>":()V
       9: return

  public abstract boolean hasValue(java.lang.String);

  public int getLine();
    Code:
       0: aload_0
       1: getfield      #3                  // Field line:I
       4: ireturn

  public int getCol();
    Code:
       0: aload_0
       1: getfield      #4                  // Field col:I
       4: ireturn
}
