Compiled from "AbstractPredicateLikeAssert.java"
abstract class org.assertj.core.api.AbstractPredicateLikeAssert<SELF extends org.assertj.core.api.AbstractPredicateLikeAssert<SELF, PRIMITIVE_PREDICATE, PRIMITIVE>, PRIMITIVE_PREDICATE, PRIMITIVE> extends org.assertj.core.api.AbstractAssert<SELF, PRIMITIVE_PREDICATE> {
  org.assertj.core.internal.Iterables iterables;

  java.util.function.Predicate<PRIMITIVE> primitivePredicate;

  protected org.assertj.core.api.AbstractPredicateLikeAssert(PRIMITIVE_PREDICATE, java.util.function.Predicate<PRIMITIVE>, java.lang.Class<?>);
    Code:
       0: aload_0
       1: aload_1
       2: aload_3
       3: invokespecial #17                 // Method org/assertj/core/api/AbstractAssert."<init>":(Ljava/lang/Object;Ljava/lang/Class;)V
       6: aload_0
       7: invokestatic  #23                 // Method org/assertj/core/internal/Iterables.instance:()Lorg/assertj/core/internal/Iterables;
      10: putfield      #25                 // Field iterables:Lorg/assertj/core/internal/Iterables;
      13: aload_0
      14: aload_2
      15: putfield      #27                 // Field primitivePredicate:Ljava/util/function/Predicate;
      18: return

  protected SELF acceptsInternal(PRIMITIVE);
    Code:
       0: aload_0
       1: invokevirtual #43                 // Method isNotNull:()Lorg/assertj/core/api/AbstractAssert;
       4: pop
       5: aload_0
       6: getfield      #27                 // Field primitivePredicate:Ljava/util/function/Predicate;
       9: aload_1
      10: invokeinterface #49,  2           // InterfaceMethod java/util/function/Predicate.test:(Ljava/lang/Object;)Z
      15: ifne          33
      18: aload_0
      19: aload_0
      20: getfield      #27                 // Field primitivePredicate:Ljava/util/function/Predicate;
      23: aload_1
      24: getstatic     #55                 // Field org/assertj/core/presentation/PredicateDescription.GIVEN:Lorg/assertj/core/presentation/PredicateDescription;
      27: invokestatic  #61                 // Method org/assertj/core/error/ShouldAccept.shouldAccept:(Ljava/util/function/Predicate;Ljava/lang/Object;Lorg/assertj/core/presentation/PredicateDescription;)Lorg/assertj/core/error/ErrorMessageFactory;
      30: invokevirtual #65                 // Method throwAssertionError:(Lorg/assertj/core/error/ErrorMessageFactory;)V
      33: aload_0
      34: getfield      #69                 // Field myself:Lorg/assertj/core/api/AbstractAssert;
      37: checkcast     #2                  // class org/assertj/core/api/AbstractPredicateLikeAssert
      40: areturn

  protected SELF rejectsInternal(PRIMITIVE);
    Code:
       0: aload_0
       1: invokevirtual #43                 // Method isNotNull:()Lorg/assertj/core/api/AbstractAssert;
       4: pop
       5: aload_0
       6: getfield      #27                 // Field primitivePredicate:Ljava/util/function/Predicate;
       9: aload_1
      10: invokeinterface #49,  2           // InterfaceMethod java/util/function/Predicate.test:(Ljava/lang/Object;)Z
      15: ifeq          33
      18: aload_0
      19: aload_0
      20: getfield      #27                 // Field primitivePredicate:Ljava/util/function/Predicate;
      23: aload_1
      24: getstatic     #55                 // Field org/assertj/core/presentation/PredicateDescription.GIVEN:Lorg/assertj/core/presentation/PredicateDescription;
      27: invokestatic  #77                 // Method org/assertj/core/error/ShouldNotAccept.shouldNotAccept:(Ljava/util/function/Predicate;Ljava/lang/Object;Lorg/assertj/core/presentation/PredicateDescription;)Lorg/assertj/core/error/ErrorMessageFactory;
      30: invokevirtual #65                 // Method throwAssertionError:(Lorg/assertj/core/error/ErrorMessageFactory;)V
      33: aload_0
      34: getfield      #69                 // Field myself:Lorg/assertj/core/api/AbstractAssert;
      37: checkcast     #2                  // class org/assertj/core/api/AbstractPredicateLikeAssert
      40: areturn

  protected SELF acceptsAllInternal(java.lang.Iterable<? extends PRIMITIVE>);
    Code:
       0: aload_0
       1: invokevirtual #43                 // Method isNotNull:()Lorg/assertj/core/api/AbstractAssert;
       4: pop
       5: aload_0
       6: getfield      #25                 // Field iterables:Lorg/assertj/core/internal/Iterables;
       9: aload_0
      10: getfield      #83                 // Field info:Lorg/assertj/core/api/WritableAssertionInfo;
      13: aload_1
      14: aload_0
      15: getfield      #27                 // Field primitivePredicate:Ljava/util/function/Predicate;
      18: getstatic     #55                 // Field org/assertj/core/presentation/PredicateDescription.GIVEN:Lorg/assertj/core/presentation/PredicateDescription;
      21: invokevirtual #87                 // Method org/assertj/core/internal/Iterables.assertAllMatch:(Lorg/assertj/core/api/AssertionInfo;Ljava/lang/Iterable;Ljava/util/function/Predicate;Lorg/assertj/core/presentation/PredicateDescription;)V
      24: aload_0
      25: getfield      #69                 // Field myself:Lorg/assertj/core/api/AbstractAssert;
      28: checkcast     #2                  // class org/assertj/core/api/AbstractPredicateLikeAssert
      31: areturn

  protected SELF rejectsAllInternal(java.lang.Iterable<? extends PRIMITIVE>);
    Code:
       0: aload_0
       1: invokevirtual #43                 // Method isNotNull:()Lorg/assertj/core/api/AbstractAssert;
       4: pop
       5: aload_0
       6: getfield      #25                 // Field iterables:Lorg/assertj/core/internal/Iterables;
       9: aload_0
      10: getfield      #83                 // Field info:Lorg/assertj/core/api/WritableAssertionInfo;
      13: aload_1
      14: aload_0
      15: getfield      #27                 // Field primitivePredicate:Ljava/util/function/Predicate;
      18: getstatic     #55                 // Field org/assertj/core/presentation/PredicateDescription.GIVEN:Lorg/assertj/core/presentation/PredicateDescription;
      21: invokevirtual #94                 // Method org/assertj/core/internal/Iterables.assertNoneMatch:(Lorg/assertj/core/api/AssertionInfo;Ljava/lang/Iterable;Ljava/util/function/Predicate;Lorg/assertj/core/presentation/PredicateDescription;)V
      24: aload_0
      25: getfield      #69                 // Field myself:Lorg/assertj/core/api/AbstractAssert;
      28: checkcast     #2                  // class org/assertj/core/api/AbstractPredicateLikeAssert
      31: areturn
}
