Compiled from "AbstractOffsetDateTimeAssert.java"
public abstract class org.assertj.core.api.AbstractOffsetDateTimeAssert<SELF extends org.assertj.core.api.AbstractOffsetDateTimeAssert<SELF>> extends org.assertj.core.api.AbstractTemporalAssert<SELF, java.time.OffsetDateTime> {
  public static final java.lang.String NULL_OFFSET_DATE_TIME_PARAMETER_MESSAGE;

  protected org.assertj.core.api.AbstractOffsetDateTimeAssert(java.time.OffsetDateTime, java.lang.Class<?>);
    Code:
       0: aload_0
       1: aload_1
       2: aload_2
       3: invokespecial #15                 // Method org/assertj/core/api/AbstractTemporalAssert."<init>":(Ljava/time/temporal/Temporal;Ljava/lang/Class;)V
       6: return

  public SELF isBefore(java.time.OffsetDateTime);
    Code:
       0: invokestatic  #31                 // Method org/assertj/core/internal/Objects.instance:()Lorg/assertj/core/internal/Objects;
       3: aload_0
       4: getfield      #35                 // Field info:Lorg/assertj/core/api/WritableAssertionInfo;
       7: aload_0
       8: getfield      #38                 // Field actual:Ljava/lang/Object;
      11: invokevirtual #42                 // Method org/assertj/core/internal/Objects.assertNotNull:(Lorg/assertj/core/api/AssertionInfo;Ljava/lang/Object;)V
      14: aload_1
      15: invokestatic  #46                 // Method assertOffsetDateTimeParameterIsNotNull:(Ljava/time/OffsetDateTime;)V
      18: aload_0
      19: getfield      #38                 // Field actual:Ljava/lang/Object;
      22: checkcast     #48                 // class java/time/OffsetDateTime
      25: aload_1
      26: invokevirtual #51                 // Method java/time/OffsetDateTime.isBefore:(Ljava/time/OffsetDateTime;)Z
      29: ifne          51
      32: invokestatic  #56                 // Method org/assertj/core/internal/Failures.instance:()Lorg/assertj/core/internal/Failures;
      35: aload_0
      36: getfield      #35                 // Field info:Lorg/assertj/core/api/WritableAssertionInfo;
      39: aload_0
      40: getfield      #38                 // Field actual:Ljava/lang/Object;
      43: aload_1
      44: invokestatic  #62                 // Method org/assertj/core/error/ShouldBeBefore.shouldBeBefore:(Ljava/lang/Object;Ljava/lang/Object;)Lorg/assertj/core/error/ErrorMessageFactory;
      47: invokevirtual #66                 // Method org/assertj/core/internal/Failures.failure:(Lorg/assertj/core/api/AssertionInfo;Lorg/assertj/core/error/ErrorMessageFactory;)Ljava/lang/AssertionError;
      50: athrow
      51: aload_0
      52: getfield      #70                 // Field myself:Lorg/assertj/core/api/AbstractAssert;
      55: checkcast     #2                  // class org/assertj/core/api/AbstractOffsetDateTimeAssert
      58: areturn

  public SELF isBefore(java.lang.String);
    Code:
       0: aload_1
       1: invokestatic  #76                 // Method assertOffsetDateTimeAsStringParameterIsNotNull:(Ljava/lang/String;)V
       4: aload_0
       5: aload_0
       6: aload_1
       7: invokevirtual #80                 // Method parse:(Ljava/lang/String;)Ljava/time/OffsetDateTime;
      10: invokevirtual #82                 // Method isBefore:(Ljava/time/OffsetDateTime;)Lorg/assertj/core/api/AbstractOffsetDateTimeAssert;
      13: areturn

  public SELF isBeforeOrEqualTo(java.time.OffsetDateTime);
    Code:
       0: invokestatic  #31                 // Method org/assertj/core/internal/Objects.instance:()Lorg/assertj/core/internal/Objects;
       3: aload_0
       4: getfield      #35                 // Field info:Lorg/assertj/core/api/WritableAssertionInfo;
       7: aload_0
       8: getfield      #38                 // Field actual:Ljava/lang/Object;
      11: invokevirtual #42                 // Method org/assertj/core/internal/Objects.assertNotNull:(Lorg/assertj/core/api/AssertionInfo;Ljava/lang/Object;)V
      14: aload_1
      15: invokestatic  #46                 // Method assertOffsetDateTimeParameterIsNotNull:(Ljava/time/OffsetDateTime;)V
      18: aload_0
      19: getfield      #38                 // Field actual:Ljava/lang/Object;
      22: checkcast     #48                 // class java/time/OffsetDateTime
      25: aload_1
      26: invokevirtual #87                 // Method java/time/OffsetDateTime.isAfter:(Ljava/time/OffsetDateTime;)Z
      29: ifeq          51
      32: invokestatic  #56                 // Method org/assertj/core/internal/Failures.instance:()Lorg/assertj/core/internal/Failures;
      35: aload_0
      36: getfield      #35                 // Field info:Lorg/assertj/core/api/WritableAssertionInfo;
      39: aload_0
      40: getfield      #38                 // Field actual:Ljava/lang/Object;
      43: aload_1
      44: invokestatic  #92                 // Method org/assertj/core/error/ShouldBeBeforeOrEqualsTo.shouldBeBeforeOrEqualsTo:(Ljava/lang/Object;Ljava/lang/Object;)Lorg/assertj/core/error/ErrorMessageFactory;
      47: invokevirtual #66                 // Method org/assertj/core/internal/Failures.failure:(Lorg/assertj/core/api/AssertionInfo;Lorg/assertj/core/error/ErrorMessageFactory;)Ljava/lang/AssertionError;
      50: athrow
      51: aload_0
      52: getfield      #70                 // Field myself:Lorg/assertj/core/api/AbstractAssert;
      55: checkcast     #2                  // class org/assertj/core/api/AbstractOffsetDateTimeAssert
      58: areturn

  public SELF isBeforeOrEqualTo(java.lang.String);
    Code:
       0: aload_1
       1: invokestatic  #76                 // Method assertOffsetDateTimeAsStringParameterIsNotNull:(Ljava/lang/String;)V
       4: aload_0
       5: aload_0
       6: aload_1
       7: invokevirtual #80                 // Method parse:(Ljava/lang/String;)Ljava/time/OffsetDateTime;
      10: invokevirtual #94                 // Method isBeforeOrEqualTo:(Ljava/time/OffsetDateTime;)Lorg/assertj/core/api/AbstractOffsetDateTimeAssert;
      13: areturn

  public SELF isAfterOrEqualTo(java.time.OffsetDateTime);
    Code:
       0: invokestatic  #31                 // Method org/assertj/core/internal/Objects.instance:()Lorg/assertj/core/internal/Objects;
       3: aload_0
       4: getfield      #35                 // Field info:Lorg/assertj/core/api/WritableAssertionInfo;
       7: aload_0
       8: getfield      #38                 // Field actual:Ljava/lang/Object;
      11: invokevirtual #42                 // Method org/assertj/core/internal/Objects.assertNotNull:(Lorg/assertj/core/api/AssertionInfo;Ljava/lang/Object;)V
      14: aload_1
      15: invokestatic  #46                 // Method assertOffsetDateTimeParameterIsNotNull:(Ljava/time/OffsetDateTime;)V
      18: aload_0
      19: getfield      #38                 // Field actual:Ljava/lang/Object;
      22: checkcast     #48                 // class java/time/OffsetDateTime
      25: aload_1
      26: invokevirtual #51                 // Method java/time/OffsetDateTime.isBefore:(Ljava/time/OffsetDateTime;)Z
      29: ifeq          51
      32: invokestatic  #56                 // Method org/assertj/core/internal/Failures.instance:()Lorg/assertj/core/internal/Failures;
      35: aload_0
      36: getfield      #35                 // Field info:Lorg/assertj/core/api/WritableAssertionInfo;
      39: aload_0
      40: getfield      #38                 // Field actual:Ljava/lang/Object;
      43: aload_1
      44: invokestatic  #100                // Method org/assertj/core/error/ShouldBeAfterOrEqualsTo.shouldBeAfterOrEqualsTo:(Ljava/lang/Object;Ljava/lang/Object;)Lorg/assertj/core/error/ErrorMessageFactory;
      47: invokevirtual #66                 // Method org/assertj/core/internal/Failures.failure:(Lorg/assertj/core/api/AssertionInfo;Lorg/assertj/core/error/ErrorMessageFactory;)Ljava/lang/AssertionError;
      50: athrow
      51: aload_0
      52: getfield      #70                 // Field myself:Lorg/assertj/core/api/AbstractAssert;
      55: checkcast     #2                  // class org/assertj/core/api/AbstractOffsetDateTimeAssert
      58: areturn

  public SELF isAfterOrEqualTo(java.lang.String);
    Code:
       0: aload_1
       1: invokestatic  #76                 // Method assertOffsetDateTimeAsStringParameterIsNotNull:(Ljava/lang/String;)V
       4: aload_0
       5: aload_0
       6: aload_1
       7: invokevirtual #80                 // Method parse:(Ljava/lang/String;)Ljava/time/OffsetDateTime;
      10: invokevirtual #102                // Method isAfterOrEqualTo:(Ljava/time/OffsetDateTime;)Lorg/assertj/core/api/AbstractOffsetDateTimeAssert;
      13: areturn

  public SELF isAfter(java.time.OffsetDateTime);
    Code:
       0: invokestatic  #31                 // Method org/assertj/core/internal/Objects.instance:()Lorg/assertj/core/internal/Objects;
       3: aload_0
       4: getfield      #35                 // Field info:Lorg/assertj/core/api/WritableAssertionInfo;
       7: aload_0
       8: getfield      #38                 // Field actual:Ljava/lang/Object;
      11: invokevirtual #42                 // Method org/assertj/core/internal/Objects.assertNotNull:(Lorg/assertj/core/api/AssertionInfo;Ljava/lang/Object;)V
      14: aload_1
      15: invokestatic  #46                 // Method assertOffsetDateTimeParameterIsNotNull:(Ljava/time/OffsetDateTime;)V
      18: aload_0
      19: getfield      #38                 // Field actual:Ljava/lang/Object;
      22: checkcast     #48                 // class java/time/OffsetDateTime
      25: aload_1
      26: invokevirtual #87                 // Method java/time/OffsetDateTime.isAfter:(Ljava/time/OffsetDateTime;)Z
      29: ifne          51
      32: invokestatic  #56                 // Method org/assertj/core/internal/Failures.instance:()Lorg/assertj/core/internal/Failures;
      35: aload_0
      36: getfield      #35                 // Field info:Lorg/assertj/core/api/WritableAssertionInfo;
      39: aload_0
      40: getfield      #38                 // Field actual:Ljava/lang/Object;
      43: aload_1
      44: invokestatic  #107                // Method org/assertj/core/error/ShouldBeAfter.shouldBeAfter:(Ljava/lang/Object;Ljava/lang/Object;)Lorg/assertj/core/error/ErrorMessageFactory;
      47: invokevirtual #66                 // Method org/assertj/core/internal/Failures.failure:(Lorg/assertj/core/api/AssertionInfo;Lorg/assertj/core/error/ErrorMessageFactory;)Ljava/lang/AssertionError;
      50: athrow
      51: aload_0
      52: getfield      #70                 // Field myself:Lorg/assertj/core/api/AbstractAssert;
      55: checkcast     #2                  // class org/assertj/core/api/AbstractOffsetDateTimeAssert
      58: areturn

  public SELF isAfter(java.lang.String);
    Code:
       0: aload_1
       1: invokestatic  #76                 // Method assertOffsetDateTimeAsStringParameterIsNotNull:(Ljava/lang/String;)V
       4: aload_0
       5: aload_0
       6: aload_1
       7: invokevirtual #80                 // Method parse:(Ljava/lang/String;)Ljava/time/OffsetDateTime;
      10: invokevirtual #109                // Method isAfter:(Ljava/time/OffsetDateTime;)Lorg/assertj/core/api/AbstractOffsetDateTimeAssert;
      13: areturn

  public SELF isEqualTo(java.lang.String);
    Code:
       0: aload_1
       1: invokestatic  #76                 // Method assertOffsetDateTimeAsStringParameterIsNotNull:(Ljava/lang/String;)V
       4: aload_0
       5: aload_0
       6: aload_1
       7: invokevirtual #80                 // Method parse:(Ljava/lang/String;)Ljava/time/OffsetDateTime;
      10: invokevirtual #113                // Method isEqualTo:(Ljava/lang/Object;)Lorg/assertj/core/api/AbstractAssert;
      13: checkcast     #2                  // class org/assertj/core/api/AbstractOffsetDateTimeAssert
      16: areturn

  public SELF isNotEqualTo(java.lang.String);
    Code:
       0: aload_1
       1: invokestatic  #76                 // Method assertOffsetDateTimeAsStringParameterIsNotNull:(Ljava/lang/String;)V
       4: aload_0
       5: aload_0
       6: aload_1
       7: invokevirtual #80                 // Method parse:(Ljava/lang/String;)Ljava/time/OffsetDateTime;
      10: invokevirtual #117                // Method isNotEqualTo:(Ljava/lang/Object;)Lorg/assertj/core/api/AbstractAssert;
      13: checkcast     #2                  // class org/assertj/core/api/AbstractOffsetDateTimeAssert
      16: areturn

  public SELF isIn(java.lang.String...);
    Code:
       0: aload_0
       1: aload_1
       2: invokespecial #123                // Method checkIsNotNullAndNotEmpty:([Ljava/lang/Object;)V
       5: aload_0
       6: aload_1
       7: invokestatic  #127                // Method convertToOffsetDateTimeArray:([Ljava/lang/String;)[Ljava/lang/Object;
      10: invokevirtual #130                // Method isIn:([Ljava/lang/Object;)Lorg/assertj/core/api/AbstractAssert;
      13: checkcast     #2                  // class org/assertj/core/api/AbstractOffsetDateTimeAssert
      16: areturn

  public SELF isNotIn(java.lang.String...);
    Code:
       0: aload_0
       1: aload_1
       2: invokespecial #123                // Method checkIsNotNullAndNotEmpty:([Ljava/lang/Object;)V
       5: aload_0
       6: aload_1
       7: invokestatic  #127                // Method convertToOffsetDateTimeArray:([Ljava/lang/String;)[Ljava/lang/Object;
      10: invokevirtual #135                // Method isNotIn:([Ljava/lang/Object;)Lorg/assertj/core/api/AbstractAssert;
      13: checkcast     #2                  // class org/assertj/core/api/AbstractOffsetDateTimeAssert
      16: areturn

  public SELF isEqualToIgnoringNanos(java.time.OffsetDateTime);
    Code:
       0: invokestatic  #31                 // Method org/assertj/core/internal/Objects.instance:()Lorg/assertj/core/internal/Objects;
       3: aload_0
       4: getfield      #35                 // Field info:Lorg/assertj/core/api/WritableAssertionInfo;
       7: aload_0
       8: getfield      #38                 // Field actual:Ljava/lang/Object;
      11: invokevirtual #42                 // Method org/assertj/core/internal/Objects.assertNotNull:(Lorg/assertj/core/api/AssertionInfo;Ljava/lang/Object;)V
      14: aload_1
      15: invokestatic  #46                 // Method assertOffsetDateTimeParameterIsNotNull:(Ljava/time/OffsetDateTime;)V
      18: aload_0
      19: getfield      #38                 // Field actual:Ljava/lang/Object;
      22: checkcast     #48                 // class java/time/OffsetDateTime
      25: aload_1
      26: invokestatic  #140                // Method areEqualIgnoringNanos:(Ljava/time/OffsetDateTime;Ljava/time/OffsetDateTime;)Z
      29: ifne          51
      32: invokestatic  #56                 // Method org/assertj/core/internal/Failures.instance:()Lorg/assertj/core/internal/Failures;
      35: aload_0
      36: getfield      #35                 // Field info:Lorg/assertj/core/api/WritableAssertionInfo;
      39: aload_0
      40: getfield      #38                 // Field actual:Ljava/lang/Object;
      43: aload_1
      44: invokestatic  #145                // Method org/assertj/core/error/ShouldBeEqualIgnoringNanos.shouldBeEqualIgnoringNanos:(Ljava/lang/Object;Ljava/lang/Object;)Lorg/assertj/core/error/ErrorMessageFactory;
      47: invokevirtual #66                 // Method org/assertj/core/internal/Failures.failure:(Lorg/assertj/core/api/AssertionInfo;Lorg/assertj/core/error/ErrorMessageFactory;)Ljava/lang/AssertionError;
      50: athrow
      51: aload_0
      52: getfield      #70                 // Field myself:Lorg/assertj/core/api/AbstractAssert;
      55: checkcast     #2                  // class org/assertj/core/api/AbstractOffsetDateTimeAssert
      58: areturn

  public SELF isEqualToIgnoringTimezone(java.time.OffsetDateTime);
    Code:
       0: invokestatic  #31                 // Method org/assertj/core/internal/Objects.instance:()Lorg/assertj/core/internal/Objects;
       3: aload_0
       4: getfield      #35                 // Field info:Lorg/assertj/core/api/WritableAssertionInfo;
       7: aload_0
       8: getfield      #38                 // Field actual:Ljava/lang/Object;
      11: invokevirtual #42                 // Method org/assertj/core/internal/Objects.assertNotNull:(Lorg/assertj/core/api/AssertionInfo;Ljava/lang/Object;)V
      14: aload_1
      15: invokestatic  #46                 // Method assertOffsetDateTimeParameterIsNotNull:(Ljava/time/OffsetDateTime;)V
      18: aload_0
      19: getfield      #38                 // Field actual:Ljava/lang/Object;
      22: checkcast     #48                 // class java/time/OffsetDateTime
      25: aload_1
      26: invokestatic  #149                // Method areEqualIgnoringTimezone:(Ljava/time/OffsetDateTime;Ljava/time/OffsetDateTime;)Z
      29: ifne          54
      32: invokestatic  #56                 // Method org/assertj/core/internal/Failures.instance:()Lorg/assertj/core/internal/Failures;
      35: aload_0
      36: getfield      #35                 // Field info:Lorg/assertj/core/api/WritableAssertionInfo;
      39: aload_0
      40: getfield      #38                 // Field actual:Ljava/lang/Object;
      43: checkcast     #48                 // class java/time/OffsetDateTime
      46: aload_1
      47: invokestatic  #155                // Method org/assertj/core/error/ShouldBeEqualIgnoringTimezone.shouldBeEqualIgnoringTimezone:(Ljava/time/OffsetDateTime;Ljava/time/OffsetDateTime;)Lorg/assertj/core/error/ErrorMessageFactory;
      50: invokevirtual #66                 // Method org/assertj/core/internal/Failures.failure:(Lorg/assertj/core/api/AssertionInfo;Lorg/assertj/core/error/ErrorMessageFactory;)Ljava/lang/AssertionError;
      53: athrow
      54: aload_0
      55: getfield      #70                 // Field myself:Lorg/assertj/core/api/AbstractAssert;
      58: checkcast     #2                  // class org/assertj/core/api/AbstractOffsetDateTimeAssert
      61: areturn

  public SELF isEqualToIgnoringSeconds(java.time.OffsetDateTime);
    Code:
       0: invokestatic  #31                 // Method org/assertj/core/internal/Objects.instance:()Lorg/assertj/core/internal/Objects;
       3: aload_0
       4: getfield      #35                 // Field info:Lorg/assertj/core/api/WritableAssertionInfo;
       7: aload_0
       8: getfield      #38                 // Field actual:Ljava/lang/Object;
      11: invokevirtual #42                 // Method org/assertj/core/internal/Objects.assertNotNull:(Lorg/assertj/core/api/AssertionInfo;Ljava/lang/Object;)V
      14: aload_1
      15: invokestatic  #46                 // Method assertOffsetDateTimeParameterIsNotNull:(Ljava/time/OffsetDateTime;)V
      18: aload_0
      19: getfield      #38                 // Field actual:Ljava/lang/Object;
      22: checkcast     #48                 // class java/time/OffsetDateTime
      25: aload_1
      26: invokestatic  #159                // Method areEqualIgnoringSeconds:(Ljava/time/OffsetDateTime;Ljava/time/OffsetDateTime;)Z
      29: ifne          51
      32: invokestatic  #56                 // Method org/assertj/core/internal/Failures.instance:()Lorg/assertj/core/internal/Failures;
      35: aload_0
      36: getfield      #35                 // Field info:Lorg/assertj/core/api/WritableAssertionInfo;
      39: aload_0
      40: getfield      #38                 // Field actual:Ljava/lang/Object;
      43: aload_1
      44: invokestatic  #164                // Method org/assertj/core/error/ShouldBeEqualIgnoringSeconds.shouldBeEqualIgnoringSeconds:(Ljava/lang/Object;Ljava/lang/Object;)Lorg/assertj/core/error/ErrorMessageFactory;
      47: invokevirtual #66                 // Method org/assertj/core/internal/Failures.failure:(Lorg/assertj/core/api/AssertionInfo;Lorg/assertj/core/error/ErrorMessageFactory;)Ljava/lang/AssertionError;
      50: athrow
      51: aload_0
      52: getfield      #70                 // Field myself:Lorg/assertj/core/api/AbstractAssert;
      55: checkcast     #2                  // class org/assertj/core/api/AbstractOffsetDateTimeAssert
      58: areturn

  public SELF isEqualToIgnoringMinutes(java.time.OffsetDateTime);
    Code:
       0: invokestatic  #31                 // Method org/assertj/core/internal/Objects.instance:()Lorg/assertj/core/internal/Objects;
       3: aload_0
       4: getfield      #35                 // Field info:Lorg/assertj/core/api/WritableAssertionInfo;
       7: aload_0
       8: getfield      #38                 // Field actual:Ljava/lang/Object;
      11: invokevirtual #42                 // Method org/assertj/core/internal/Objects.assertNotNull:(Lorg/assertj/core/api/AssertionInfo;Ljava/lang/Object;)V
      14: aload_1
      15: invokestatic  #46                 // Method assertOffsetDateTimeParameterIsNotNull:(Ljava/time/OffsetDateTime;)V
      18: aload_0
      19: getfield      #38                 // Field actual:Ljava/lang/Object;
      22: checkcast     #48                 // class java/time/OffsetDateTime
      25: aload_1
      26: invokestatic  #168                // Method areEqualIgnoringMinutes:(Ljava/time/OffsetDateTime;Ljava/time/OffsetDateTime;)Z
      29: ifne          51
      32: invokestatic  #56                 // Method org/assertj/core/internal/Failures.instance:()Lorg/assertj/core/internal/Failures;
      35: aload_0
      36: getfield      #35                 // Field info:Lorg/assertj/core/api/WritableAssertionInfo;
      39: aload_0
      40: getfield      #38                 // Field actual:Ljava/lang/Object;
      43: aload_1
      44: invokestatic  #173                // Method org/assertj/core/error/ShouldBeEqualIgnoringMinutes.shouldBeEqualIgnoringMinutes:(Ljava/lang/Object;Ljava/lang/Object;)Lorg/assertj/core/error/ErrorMessageFactory;
      47: invokevirtual #66                 // Method org/assertj/core/internal/Failures.failure:(Lorg/assertj/core/api/AssertionInfo;Lorg/assertj/core/error/ErrorMessageFactory;)Ljava/lang/AssertionError;
      50: athrow
      51: aload_0
      52: getfield      #70                 // Field myself:Lorg/assertj/core/api/AbstractAssert;
      55: checkcast     #2                  // class org/assertj/core/api/AbstractOffsetDateTimeAssert
      58: areturn

  public SELF isEqualToIgnoringHours(java.time.OffsetDateTime);
    Code:
       0: invokestatic  #31                 // Method org/assertj/core/internal/Objects.instance:()Lorg/assertj/core/internal/Objects;
       3: aload_0
       4: getfield      #35                 // Field info:Lorg/assertj/core/api/WritableAssertionInfo;
       7: aload_0
       8: getfield      #38                 // Field actual:Ljava/lang/Object;
      11: invokevirtual #42                 // Method org/assertj/core/internal/Objects.assertNotNull:(Lorg/assertj/core/api/AssertionInfo;Ljava/lang/Object;)V
      14: aload_1
      15: invokestatic  #46                 // Method assertOffsetDateTimeParameterIsNotNull:(Ljava/time/OffsetDateTime;)V
      18: aload_0
      19: getfield      #38                 // Field actual:Ljava/lang/Object;
      22: checkcast     #48                 // class java/time/OffsetDateTime
      25: aload_1
      26: invokestatic  #177                // Method haveSameYearMonthAndDayOfMonth:(Ljava/time/OffsetDateTime;Ljava/time/OffsetDateTime;)Z
      29: ifne          51
      32: invokestatic  #56                 // Method org/assertj/core/internal/Failures.instance:()Lorg/assertj/core/internal/Failures;
      35: aload_0
      36: getfield      #35                 // Field info:Lorg/assertj/core/api/WritableAssertionInfo;
      39: aload_0
      40: getfield      #38                 // Field actual:Ljava/lang/Object;
      43: aload_1
      44: invokestatic  #182                // Method org/assertj/core/error/ShouldBeEqualIgnoringHours.shouldBeEqualIgnoringHours:(Ljava/lang/Object;Ljava/lang/Object;)Lorg/assertj/core/error/ErrorMessageFactory;
      47: invokevirtual #66                 // Method org/assertj/core/internal/Failures.failure:(Lorg/assertj/core/api/AssertionInfo;Lorg/assertj/core/error/ErrorMessageFactory;)Ljava/lang/AssertionError;
      50: athrow
      51: aload_0
      52: getfield      #70                 // Field myself:Lorg/assertj/core/api/AbstractAssert;
      55: checkcast     #2                  // class org/assertj/core/api/AbstractOffsetDateTimeAssert
      58: areturn

  public SELF isBetween(java.time.OffsetDateTime, java.time.OffsetDateTime);
    Code:
       0: aload_0
       1: getfield      #188                // Field comparables:Lorg/assertj/core/internal/Comparables;
       4: aload_0
       5: getfield      #35                 // Field info:Lorg/assertj/core/api/WritableAssertionInfo;
       8: aload_0
       9: getfield      #38                 // Field actual:Ljava/lang/Object;
      12: checkcast     #190                // class java/lang/Comparable
      15: aload_1
      16: aload_2
      17: iconst_1
      18: iconst_1
      19: invokevirtual #196                // Method org/assertj/core/internal/Comparables.assertIsBetween:(Lorg/assertj/core/api/AssertionInfo;Ljava/lang/Comparable;Ljava/lang/Comparable;Ljava/lang/Comparable;ZZ)V
      22: aload_0
      23: getfield      #70                 // Field myself:Lorg/assertj/core/api/AbstractAssert;
      26: checkcast     #2                  // class org/assertj/core/api/AbstractOffsetDateTimeAssert
      29: areturn

  public SELF isBetween(java.lang.String, java.lang.String);
    Code:
       0: aload_0
       1: aload_0
       2: aload_1
       3: invokevirtual #80                 // Method parse:(Ljava/lang/String;)Ljava/time/OffsetDateTime;
       6: aload_0
       7: aload_2
       8: invokevirtual #80                 // Method parse:(Ljava/lang/String;)Ljava/time/OffsetDateTime;
      11: invokevirtual #201                // Method isBetween:(Ljava/time/OffsetDateTime;Ljava/time/OffsetDateTime;)Lorg/assertj/core/api/AbstractOffsetDateTimeAssert;
      14: areturn

  public SELF isStrictlyBetween(java.time.OffsetDateTime, java.time.OffsetDateTime);
    Code:
       0: aload_0
       1: getfield      #188                // Field comparables:Lorg/assertj/core/internal/Comparables;
       4: aload_0
       5: getfield      #35                 // Field info:Lorg/assertj/core/api/WritableAssertionInfo;
       8: aload_0
       9: getfield      #38                 // Field actual:Ljava/lang/Object;
      12: checkcast     #190                // class java/lang/Comparable
      15: aload_1
      16: aload_2
      17: iconst_0
      18: iconst_0
      19: invokevirtual #196                // Method org/assertj/core/internal/Comparables.assertIsBetween:(Lorg/assertj/core/api/AssertionInfo;Ljava/lang/Comparable;Ljava/lang/Comparable;Ljava/lang/Comparable;ZZ)V
      22: aload_0
      23: getfield      #70                 // Field myself:Lorg/assertj/core/api/AbstractAssert;
      26: checkcast     #2                  // class org/assertj/core/api/AbstractOffsetDateTimeAssert
      29: areturn

  public SELF isStrictlyBetween(java.lang.String, java.lang.String);
    Code:
       0: aload_0
       1: aload_0
       2: aload_1
       3: invokevirtual #80                 // Method parse:(Ljava/lang/String;)Ljava/time/OffsetDateTime;
       6: aload_0
       7: aload_2
       8: invokevirtual #80                 // Method parse:(Ljava/lang/String;)Ljava/time/OffsetDateTime;
      11: invokevirtual #204                // Method isStrictlyBetween:(Ljava/time/OffsetDateTime;Ljava/time/OffsetDateTime;)Lorg/assertj/core/api/AbstractOffsetDateTimeAssert;
      14: areturn

  protected java.time.OffsetDateTime parse(java.lang.String);
    Code:
       0: aload_1
       1: invokestatic  #207                // Method java/time/OffsetDateTime.parse:(Ljava/lang/CharSequence;)Ljava/time/OffsetDateTime;
       4: areturn

  private static boolean areEqualIgnoringNanos(java.time.OffsetDateTime, java.time.OffsetDateTime);
    Code:
       0: aload_0
       1: aload_1
       2: invokestatic  #159                // Method areEqualIgnoringSeconds:(Ljava/time/OffsetDateTime;Ljava/time/OffsetDateTime;)Z
       5: ifeq          23
       8: aload_0
       9: invokevirtual #211                // Method java/time/OffsetDateTime.getSecond:()I
      12: aload_1
      13: invokevirtual #211                // Method java/time/OffsetDateTime.getSecond:()I
      16: if_icmpne     23
      19: iconst_1
      20: goto          24
      23: iconst_0
      24: ireturn

  private static boolean areEqualIgnoringSeconds(java.time.OffsetDateTime, java.time.OffsetDateTime);
    Code:
       0: aload_0
       1: aload_1
       2: invokestatic  #168                // Method areEqualIgnoringMinutes:(Ljava/time/OffsetDateTime;Ljava/time/OffsetDateTime;)Z
       5: ifeq          23
       8: aload_0
       9: invokevirtual #214                // Method java/time/OffsetDateTime.getMinute:()I
      12: aload_1
      13: invokevirtual #214                // Method java/time/OffsetDateTime.getMinute:()I
      16: if_icmpne     23
      19: iconst_1
      20: goto          24
      23: iconst_0
      24: ireturn

  private static boolean areEqualIgnoringMinutes(java.time.OffsetDateTime, java.time.OffsetDateTime);
    Code:
       0: aload_0
       1: aload_1
       2: invokestatic  #177                // Method haveSameYearMonthAndDayOfMonth:(Ljava/time/OffsetDateTime;Ljava/time/OffsetDateTime;)Z
       5: ifeq          23
       8: aload_0
       9: invokevirtual #217                // Method java/time/OffsetDateTime.getHour:()I
      12: aload_1
      13: invokevirtual #217                // Method java/time/OffsetDateTime.getHour:()I
      16: if_icmpne     23
      19: iconst_1
      20: goto          24
      23: iconst_0
      24: ireturn

  private static boolean haveSameYearMonthAndDayOfMonth(java.time.OffsetDateTime, java.time.OffsetDateTime);
    Code:
       0: aload_0
       1: aload_1
       2: invokestatic  #220                // Method haveSameYearAndMonth:(Ljava/time/OffsetDateTime;Ljava/time/OffsetDateTime;)Z
       5: ifeq          23
       8: aload_0
       9: invokevirtual #223                // Method java/time/OffsetDateTime.getDayOfMonth:()I
      12: aload_1
      13: invokevirtual #223                // Method java/time/OffsetDateTime.getDayOfMonth:()I
      16: if_icmpne     23
      19: iconst_1
      20: goto          24
      23: iconst_0
      24: ireturn

  private static boolean haveSameYearAndMonth(java.time.OffsetDateTime, java.time.OffsetDateTime);
    Code:
       0: aload_0
       1: aload_1
       2: invokestatic  #226                // Method haveSameYear:(Ljava/time/OffsetDateTime;Ljava/time/OffsetDateTime;)Z
       5: ifeq          23
       8: aload_0
       9: invokevirtual #230                // Method java/time/OffsetDateTime.getMonth:()Ljava/time/Month;
      12: aload_1
      13: invokevirtual #230                // Method java/time/OffsetDateTime.getMonth:()Ljava/time/Month;
      16: if_acmpne     23
      19: iconst_1
      20: goto          24
      23: iconst_0
      24: ireturn

  private static boolean haveSameYear(java.time.OffsetDateTime, java.time.OffsetDateTime);
    Code:
       0: aload_0
       1: invokevirtual #233                // Method java/time/OffsetDateTime.getYear:()I
       4: aload_1
       5: invokevirtual #233                // Method java/time/OffsetDateTime.getYear:()I
       8: if_icmpne     15
      11: iconst_1
      12: goto          16
      15: iconst_0
      16: ireturn

  private static boolean areEqualIgnoringTimezone(java.time.OffsetDateTime, java.time.OffsetDateTime);
    Code:
       0: aload_0
       1: aload_1
       2: invokestatic  #140                // Method areEqualIgnoringNanos:(Ljava/time/OffsetDateTime;Ljava/time/OffsetDateTime;)Z
       5: ifeq          20
       8: aload_0
       9: aload_1
      10: invokestatic  #236                // Method haveSameNano:(Ljava/time/OffsetDateTime;Ljava/time/OffsetDateTime;)Z
      13: ifeq          20
      16: iconst_1
      17: goto          21
      20: iconst_0
      21: ireturn

  private static boolean haveSameNano(java.time.OffsetDateTime, java.time.OffsetDateTime);
    Code:
       0: aload_0
       1: invokevirtual #239                // Method java/time/OffsetDateTime.getNano:()I
       4: aload_1
       5: invokevirtual #239                // Method java/time/OffsetDateTime.getNano:()I
       8: if_icmpne     15
      11: iconst_1
      12: goto          16
      15: iconst_0
      16: ireturn

  private static java.lang.Object[] convertToOffsetDateTimeArray(java.lang.String...);
    Code:
       0: aload_0
       1: arraylength
       2: anewarray     #48                 // class java/time/OffsetDateTime
       5: astore_1
       6: iconst_0
       7: istore_2
       8: iload_2
       9: aload_0
      10: arraylength
      11: if_icmpge     29
      14: aload_1
      15: iload_2
      16: aload_0
      17: iload_2
      18: aaload
      19: invokestatic  #207                // Method java/time/OffsetDateTime.parse:(Ljava/lang/CharSequence;)Ljava/time/OffsetDateTime;
      22: aastore
      23: iinc          2, 1
      26: goto          8
      29: aload_1
      30: areturn

  private void checkIsNotNullAndNotEmpty(java.lang.Object[]);
    Code:
       0: aload_1
       1: ifnull        8
       4: iconst_1
       5: goto          9
       8: iconst_0
       9: ldc           #246                // String The given OffsetDateTime array should not be null
      11: iconst_0
      12: anewarray     #248                // class java/lang/Object
      15: invokestatic  #254                // Method org/assertj/core/util/Preconditions.checkArgument:(ZLjava/lang/String;[Ljava/lang/Object;)V
      18: aload_1
      19: arraylength
      20: ifle          27
      23: iconst_1
      24: goto          28
      27: iconst_0
      28: ldc_w         #256                // String The given OffsetDateTime array should not be empty
      31: iconst_0
      32: anewarray     #248                // class java/lang/Object
      35: invokestatic  #254                // Method org/assertj/core/util/Preconditions.checkArgument:(ZLjava/lang/String;[Ljava/lang/Object;)V
      38: return

  private static void assertOffsetDateTimeAsStringParameterIsNotNull(java.lang.String);
    Code:
       0: aload_0
       1: ifnull        8
       4: iconst_1
       5: goto          9
       8: iconst_0
       9: ldc_w         #260                // String The String representing the OffsetDateTime to compare actual with should not be null
      12: iconst_0
      13: anewarray     #248                // class java/lang/Object
      16: invokestatic  #254                // Method org/assertj/core/util/Preconditions.checkArgument:(ZLjava/lang/String;[Ljava/lang/Object;)V
      19: return

  private static void assertOffsetDateTimeParameterIsNotNull(java.time.OffsetDateTime);
    Code:
       0: aload_0
       1: ifnull        8
       4: iconst_1
       5: goto          9
       8: iconst_0
       9: ldc           #10                 // String The OffsetDateTime to compare actual with should not be null
      11: iconst_0
      12: anewarray     #248                // class java/lang/Object
      15: invokestatic  #254                // Method org/assertj/core/util/Preconditions.checkArgument:(ZLjava/lang/String;[Ljava/lang/Object;)V
      18: return

  protected java.time.temporal.Temporal parse(java.lang.String);
    Code:
       0: aload_0
       1: aload_1
       2: invokevirtual #80                 // Method parse:(Ljava/lang/String;)Ljava/time/OffsetDateTime;
       5: areturn
}
