Compiled from "ErrorCollector.java"
public class org.assertj.core.api.ErrorCollector {
  private static final java.lang.String INTERCEPT_METHOD_NAME;

  private static final java.lang.String CLASS_NAME;

  private final java.util.List<java.lang.Throwable> errors;

  private final org.assertj.core.api.ErrorCollector$LastResult lastResult;

  public org.assertj.core.api.ErrorCollector();
    Code:
       0: aload_0
       1: invokespecial #24                 // Method java/lang/Object."<init>":()V
       4: aload_0
       5: new           #26                 // class java/util/ArrayList
       8: dup
       9: invokespecial #27                 // Method java/util/ArrayList."<init>":()V
      12: putfield      #29                 // Field errors:Ljava/util/List;
      15: aload_0
      16: new           #9                  // class org/assertj/core/api/ErrorCollector$LastResult
      19: dup
      20: aconst_null
      21: invokespecial #32                 // Method org/assertj/core/api/ErrorCollector$LastResult."<init>":(Lorg/assertj/core/api/ErrorCollector$1;)V
      24: putfield      #34                 // Field lastResult:Lorg/assertj/core/api/ErrorCollector$LastResult;
      27: return

  public java.lang.Object intercept(java.lang.Object, java.util.concurrent.Callable<java.lang.Object>, java.lang.reflect.Method) throws java.lang.Exception;
    Code:
       0: aload_2
       1: invokeinterface #53,  1           // InterfaceMethod java/util/concurrent/Callable.call:()Ljava/lang/Object;
       6: astore        4
       8: aload_0
       9: getfield      #34                 // Field lastResult:Lorg/assertj/core/api/ErrorCollector$LastResult;
      12: iconst_1
      13: invokestatic  #57                 // Method org/assertj/core/api/ErrorCollector$LastResult.access$100:(Lorg/assertj/core/api/ErrorCollector$LastResult;Z)V
      16: aload         4
      18: areturn
      19: astore        4
      21: aload_0
      22: invokespecial #61                 // Method isNestedErrorCollectorProxyCall:()Z
      25: ifeq          31
      28: aload         4
      30: athrow
      31: aload_0
      32: getfield      #34                 // Field lastResult:Lorg/assertj/core/api/ErrorCollector$LastResult;
      35: iconst_0
      36: invokestatic  #57                 // Method org/assertj/core/api/ErrorCollector$LastResult.access$100:(Lorg/assertj/core/api/ErrorCollector$LastResult;Z)V
      39: aload_0
      40: getfield      #29                 // Field errors:Ljava/util/List;
      43: aload         4
      45: invokeinterface #67,  2           // InterfaceMethod java/util/List.add:(Ljava/lang/Object;)Z
      50: pop
      51: aload_3
      52: ifnull        68
      55: aload_3
      56: invokevirtual #73                 // Method java/lang/reflect/Method.getReturnType:()Ljava/lang/Class;
      59: aload_1
      60: invokevirtual #78                 // Method java/lang/Class.isInstance:(Ljava/lang/Object;)Z
      63: ifne          68
      66: aconst_null
      67: areturn
      68: aload_1
      69: areturn
    Exception table:
       from    to  target type
           0    18    19   Class java/lang/AssertionError

  public void addError(java.lang.Throwable);
    Code:
       0: aload_0
       1: getfield      #29                 // Field errors:Ljava/util/List;
       4: aload_1
       5: invokeinterface #67,  2           // InterfaceMethod java/util/List.add:(Ljava/lang/Object;)Z
      10: pop
      11: aload_0
      12: getfield      #34                 // Field lastResult:Lorg/assertj/core/api/ErrorCollector$LastResult;
      15: invokestatic  #94                 // Method org/assertj/core/api/ErrorCollector$LastResult.access$200:(Lorg/assertj/core/api/ErrorCollector$LastResult;)V
      18: return

  public java.util.List<java.lang.Throwable> errors();
    Code:
       0: aload_0
       1: getfield      #29                 // Field errors:Ljava/util/List;
       4: invokestatic  #103                // Method java/util/Collections.unmodifiableList:(Ljava/util/List;)Ljava/util/List;
       7: areturn

  public boolean wasSuccess();
    Code:
       0: aload_0
       1: getfield      #34                 // Field lastResult:Lorg/assertj/core/api/ErrorCollector$LastResult;
       4: invokestatic  #108                // Method org/assertj/core/api/ErrorCollector$LastResult.access$300:(Lorg/assertj/core/api/ErrorCollector$LastResult;)Z
       7: ireturn

  private boolean isNestedErrorCollectorProxyCall();
    Code:
       0: invokestatic  #112                // Method countErrorCollectorProxyCalls:()I
       3: iconst_1
       4: if_icmple     11
       7: iconst_1
       8: goto          12
      11: iconst_0
      12: ireturn

  private static int countErrorCollectorProxyCalls();
    Code:
       0: iconst_0
       1: istore_0
       2: invokestatic  #118                // Method java/lang/Thread.currentThread:()Ljava/lang/Thread;
       5: invokevirtual #122                // Method java/lang/Thread.getStackTrace:()[Ljava/lang/StackTraceElement;
       8: astore_1
       9: aload_1
      10: arraylength
      11: istore_2
      12: iconst_0
      13: istore_3
      14: iload_3
      15: iload_2
      16: if_icmpge     60
      19: aload_1
      20: iload_3
      21: aaload
      22: astore        4
      24: getstatic     #126                // Field CLASS_NAME:Ljava/lang/String;
      27: aload         4
      29: invokevirtual #132                // Method java/lang/StackTraceElement.getClassName:()Ljava/lang/String;
      32: invokevirtual #137                // Method java/lang/String.equals:(Ljava/lang/Object;)Z
      35: ifeq          54
      38: aload         4
      40: invokevirtual #140                // Method java/lang/StackTraceElement.getMethodName:()Ljava/lang/String;
      43: ldc           #14                 // String intercept
      45: invokevirtual #144                // Method java/lang/String.startsWith:(Ljava/lang/String;)Z
      48: ifeq          54
      51: iinc          0, 1
      54: iinc          3, 1
      57: goto          14
      60: iload_0
      61: ireturn

  static int access$400();
    Code:
       0: invokestatic  #112                // Method countErrorCollectorProxyCalls:()I
       3: ireturn

  static {};
    Code:
       0: ldc           #2                  // class org/assertj/core/api/ErrorCollector
       2: invokevirtual #153                // Method java/lang/Class.getName:()Ljava/lang/String;
       5: putstatic     #126                // Field CLASS_NAME:Ljava/lang/String;
       8: return
}
