Compiled from "FloatingPointNumberAssert.java"
public interface org.assertj.core.api.FloatingPointNumberAssert<SELF extends org.assertj.core.api.FloatingPointNumberAssert<SELF, ACTUAL>, ACTUAL extends java.lang.Number> extends org.assertj.core.api.NumberAssert<SELF, ACTUAL> {
  public abstract SELF isEqualTo(ACTUAL, org.assertj.core.data.Offset<ACTUAL>);

  public abstract SELF isCloseTo(ACTUAL, org.assertj.core.data.Offset<ACTUAL>);

  public abstract SELF isNotCloseTo(ACTUAL, org.assertj.core.data.Offset<ACTUAL>);

  public abstract SELF isNaN();

  public abstract SELF isNotNaN();

  public default org.assertj.core.api.NumberAssert isNotCloseTo(java.lang.Number, org.assertj.core.data.Offset);
    Code:
       0: aload_0
       1: aload_1
       2: aload_2
       3: invokeinterface #18,  3           // InterfaceMethod isNotCloseTo:(Ljava/lang/Number;Lorg/assertj/core/data/Offset;)Lorg/assertj/core/api/FloatingPointNumberAssert;
       8: areturn

  public default org.assertj.core.api.NumberAssert isCloseTo(java.lang.Number, org.assertj.core.data.Offset);
    Code:
       0: aload_0
       1: aload_1
       2: aload_2
       3: invokeinterface #23,  3           // InterfaceMethod isCloseTo:(Ljava/lang/Number;Lorg/assertj/core/data/Offset;)Lorg/assertj/core/api/FloatingPointNumberAssert;
       8: areturn
}
