Compiled from "ThrowableTypeAssert.java"
public class org.assertj.core.api.ThrowableTypeAssert<T extends java.lang.Throwable> implements org.assertj.core.api.Descriptable<org.assertj.core.api.ThrowableTypeAssert<T>> {
  final java.lang.Class<? extends T> expectedThrowableType;

  private org.assertj.core.description.Description description;

  org.assertj.core.api.ThrowableTypeAssert(java.lang.Class<? extends T>);
    Code:
       0: aload_0
       1: invokespecial #24                 // Method java/lang/Object."<init>":()V
       4: aload_0
       5: aload_1
       6: ldc           #26                 // String exceptionType
       8: invokestatic  #32                 // Method java/util/Objects.requireNonNull:(Ljava/lang/Object;Ljava/lang/String;)Ljava/lang/Object;
      11: checkcast     #34                 // class java/lang/Class
      14: putfield      #36                 // Field expectedThrowableType:Ljava/lang/Class;
      17: return

  public org.assertj.core.api.ThrowableAssertAlternative<T> isThrownBy(org.assertj.core.api.ThrowableAssert$ThrowingCallable);
    Code:
       0: aload_1
       1: invokestatic  #46                 // Method org/assertj/core/api/ThrowableAssert.catchThrowable:(Lorg/assertj/core/api/ThrowableAssert$ThrowingCallable;)Ljava/lang/Throwable;
       4: astore_2
       5: aload_2
       6: invokestatic  #52                 // Method org/assertj/core/api/Assertions.assertThat:(Ljava/lang/Throwable;)Lorg/assertj/core/api/AbstractThrowableAssert;
       9: aload_0
      10: getfield      #54                 // Field description:Lorg/assertj/core/description/Description;
      13: invokevirtual #60                 // Method org/assertj/core/api/AbstractThrowableAssert.as:(Lorg/assertj/core/description/Description;)Lorg/assertj/core/api/AbstractObjectAssert;
      16: checkcast     #56                 // class org/assertj/core/api/AbstractThrowableAssert
      19: invokevirtual #64                 // Method org/assertj/core/api/AbstractThrowableAssert.hasBeenThrown:()Lorg/assertj/core/api/AbstractThrowableAssert;
      22: aload_0
      23: getfield      #36                 // Field expectedThrowableType:Ljava/lang/Class;
      26: invokevirtual #68                 // Method org/assertj/core/api/AbstractThrowableAssert.isInstanceOf:(Ljava/lang/Class;)Lorg/assertj/core/api/AbstractAssert;
      29: pop
      30: aload_2
      31: astore_3
      32: new           #70                 // class org/assertj/core/api/ThrowableAssertAlternative
      35: dup
      36: aload_3
      37: invokespecial #73                 // Method org/assertj/core/api/ThrowableAssertAlternative."<init>":(Ljava/lang/Throwable;)V
      40: aload_0
      41: getfield      #54                 // Field description:Lorg/assertj/core/description/Description;
      44: invokevirtual #76                 // Method org/assertj/core/api/ThrowableAssertAlternative.as:(Lorg/assertj/core/description/Description;)Lorg/assertj/core/api/AbstractAssert;
      47: checkcast     #70                 // class org/assertj/core/api/ThrowableAssertAlternative
      50: areturn

  public org.assertj.core.api.ThrowableTypeAssert<T> as(java.lang.String, java.lang.Object...);
    Code:
       0: aload_0
       1: aload_1
       2: aload_2
       3: invokevirtual #87                 // Method describedAs:(Ljava/lang/String;[Ljava/lang/Object;)Lorg/assertj/core/api/ThrowableTypeAssert;
       6: areturn

  public org.assertj.core.api.ThrowableTypeAssert<T> as(org.assertj.core.description.Description);
    Code:
       0: aload_0
       1: aload_1
       2: invokevirtual #93                 // Method describedAs:(Lorg/assertj/core/description/Description;)Lorg/assertj/core/api/ThrowableTypeAssert;
       5: areturn

  public org.assertj.core.api.ThrowableTypeAssert<T> describedAs(java.lang.String, java.lang.Object...);
    Code:
       0: aload_0
       1: new           #95                 // class org/assertj/core/description/TextDescription
       4: dup
       5: aload_1
       6: aload_2
       7: invokespecial #98                 // Method org/assertj/core/description/TextDescription."<init>":(Ljava/lang/String;[Ljava/lang/Object;)V
      10: putfield      #54                 // Field description:Lorg/assertj/core/description/Description;
      13: aload_0
      14: areturn

  public org.assertj.core.api.ThrowableTypeAssert<T> describedAs(org.assertj.core.description.Description);
    Code:
       0: aload_0
       1: aload_1
       2: putfield      #54                 // Field description:Lorg/assertj/core/description/Description;
       5: aload_0
       6: areturn

  public java.lang.Object describedAs(org.assertj.core.description.Description);
    Code:
       0: aload_0
       1: aload_1
       2: invokevirtual #93                 // Method describedAs:(Lorg/assertj/core/description/Description;)Lorg/assertj/core/api/ThrowableTypeAssert;
       5: areturn

  public java.lang.Object describedAs(java.lang.String, java.lang.Object[]);
    Code:
       0: aload_0
       1: aload_1
       2: aload_2
       3: invokevirtual #87                 // Method describedAs:(Ljava/lang/String;[Ljava/lang/Object;)Lorg/assertj/core/api/ThrowableTypeAssert;
       6: areturn

  public java.lang.Object as(org.assertj.core.description.Description);
    Code:
       0: aload_0
       1: aload_1
       2: invokevirtual #102                // Method as:(Lorg/assertj/core/description/Description;)Lorg/assertj/core/api/ThrowableTypeAssert;
       5: areturn

  public java.lang.Object as(java.lang.String, java.lang.Object[]);
    Code:
       0: aload_0
       1: aload_1
       2: aload_2
       3: invokevirtual #104                // Method as:(Ljava/lang/String;[Ljava/lang/Object;)Lorg/assertj/core/api/ThrowableTypeAssert;
       6: areturn
}
