Compiled from "UndertowMessages_$bundle.java"
public class io.undertow.UndertowMessages_$bundle implements io.undertow.UndertowMessages,java.io.Serializable {
  private static final long serialVersionUID;

  public static final io.undertow.UndertowMessages_$bundle INSTANCE;

  private static final java.lang.String maximumConcurrentRequestsMustBeLargerThanZero;

  private static final java.lang.String responseAlreadyStarted;

  private static final java.lang.String responseChannelAlreadyProvided;

  private static final java.lang.String requestChannelAlreadyProvided;

  private static final java.lang.String handlerCannotBeNull;

  private static final java.lang.String pathMustBeSpecified;

  private static final java.lang.String sessionNotFound;

  private static final java.lang.String sessionManagerMustNotBeNull;

  private static final java.lang.String sessionManagerNotFound;

  private static final java.lang.String argumentCannotBeNull;

  private static final java.lang.String closeCalledWithDataStillToBeFlushed;

  private static final java.lang.String cookieHandlerNotPresent;

  private static final java.lang.String formValueIsAFile;

  private static final java.lang.String formValueIsAString;

  private static final java.lang.String requestEntityWasTooLarge2;

  private static final java.lang.String requestEntityWasTooLarge1;

  private static final java.lang.String sessionAlreadyInvalidated;

  private static final java.lang.String hashAlgorithmNotFound;

  private static final java.lang.String invalidBase64Token;

  private static final java.lang.String invalidNonceReceived;

  private static final java.lang.String unexpectedTokenInHeader;

  private static final java.lang.String invalidHeader;

  private static final java.lang.String couldNotFindSessionCookieConfig;

  private static final java.lang.String sessionAlreadyExists;

  private static final java.lang.String chunkedChannelClosedMidChunk;

  private static final java.lang.String userAuthenticated;

  private static final java.lang.String userLoggedOut;

  private static final java.lang.String authTypeCannotBeCombined;

  private static final java.lang.String streamIsClosed;

  private static final java.lang.String startBlockingHasNotBeenCalled;

  private static final java.lang.String connectionTerminatedReadingMultiPartData;

  private static final java.lang.String failedToParsePath;

  private static final java.lang.String authenticationFailed;

  private static final java.lang.String tooManyQueryParameters;

  private static final java.lang.String tooManyHeaders;

  private static final java.lang.String channelIsClosed;

  private static final java.lang.String couldNotDecodeTrailers;

  private static final java.lang.String dataAlreadyQueued;

  private static final java.lang.String moreThanOnePredicateWithName;

  private static final java.lang.String errorParsingPredicateString;

  private static final java.lang.String tooManyCookies;

  private static final java.lang.String tooManyParameters;

  private static final java.lang.String noRequestActive;

  private static final java.lang.String authMechanismOutcomeNull;

  private static final java.lang.String notAValidIpPattern;

  private static final java.lang.String noSessionData;

  private static final java.lang.String listenerAlreadyRegistered;

  private static final java.lang.String maxFileSizeExceeded;

  private static final java.lang.String couldNotSetAttribute;

  private static final java.lang.String couldNotParseUriTemplate;

  private static final java.lang.String mismatchedBraces;

  private static final java.lang.String moreThanOneHandlerWithName;

  private static final java.lang.String invalidSyntax;

  private static final java.lang.String errorParsingHandlerString;

  private static final java.lang.String outOfBandResponseOnlyAllowedFor100Continue;

  private static final java.lang.String ajpDoesNotSupportHTTPUpgrade;

  private static final java.lang.String fileSystemWatcherAlreadyStarted;

  private static final java.lang.String fileSystemWatcherNotStarted;

  private static final java.lang.String sslWasNull;

  private static final java.lang.String wrongMagicNumber;

  private static final java.lang.String peerUnverified;

  private static final java.lang.String servletPathMatchFailed;

  private static final java.lang.String couldNotParseCookie;

  private static final java.lang.String canOnlyBeCalledByIoThread;

  private static final java.lang.String matcherAlreadyContainsTemplate;

  private static final java.lang.String failedToDecodeURL;

  private static final java.lang.String resourceChangeListenerNotSupported;

  private static final java.lang.String couldNotRenegotiate;

  private static final java.lang.String objectWasFreed;

  private static final java.lang.String handlerNotShutdown;

  private static final java.lang.String upgradeNotSupported;

  private static final java.lang.String renegotiationNotSupported;

  private static final java.lang.String notAValidUserAgentPattern;

  private static final java.lang.String notAValidRegularExpressionPattern;

  private static final java.lang.String badRequest;

  private static final java.lang.String hostAlreadyRegistered;

  private static final java.lang.String hostHasNotBeenRegistered;

  private static final java.lang.String extraDataWrittenAfterChunkEnd;

  private static final java.lang.String couldNotGenerateUniqueSessionId;

  private static final java.lang.String mustProvideHeapBuffer;

  private static final java.lang.String unexpectedFrameType;

  private static final java.lang.String controlFrameCannotHaveBodyContent;

  private static final java.lang.String spdyNotSupported;

  private static final java.lang.String alpnNotAvailable;

  private static final java.lang.String bufferAlreadyFreed;

  private static final java.lang.String headersTooLargeToFitInHeapBuffer;

  private static final java.lang.String spdyStreamWasReset;

  private static final java.lang.String awaitCalledFromIoThread;

  private static final java.lang.String recursiveCallToFlushingSenders;

  private static final java.lang.String fixedLengthOverflow;

  private static final java.lang.String ajpRequestAlreadyInProgress;

  private static final java.lang.String httpPingDataMustBeLength8;

  private static final java.lang.String invalidPingSize;

  private static final java.lang.String streamIdMustBeZeroForFrameType;

  private static final java.lang.String streamIdMustNotBeZeroForFrameType;

  private static final java.lang.String rstStreamReceivedForIdleStream;

  private static final java.lang.String http2StreamWasReset;

  private static final java.lang.String incorrectHttp2Preface;

  private static final java.lang.String http2FrameTooLarge;

  private static final java.lang.String http2ContinuationFrameNotExpected;

  private static final java.lang.String huffmanEncodedHpackValueDidNotEndWithEOS;

  private static final java.lang.String integerEncodedOverTooManyOctets;

  private static final java.lang.String zeroNotValidHeaderTableIndex;

  private static final java.lang.String cannotSendContinueResponse;

  private static final java.lang.String parserDidNotMakeProgress;

  private static final java.lang.String headersStreamCanOnlyBeCreatedByClient;

  private static final java.lang.String pushPromiseCanOnlyBeCreatedByServer;

  private static final java.lang.String invalidAclRule;

  private static final java.lang.String serverReceivedPushPromise;

  private static final java.lang.String connectNotSupported;

  private static final java.lang.String notAConnectRequest;

  private static final java.lang.String cannotResetBuffer;

  private static final java.lang.String http2PriRequestFailed;

  private static final java.lang.String outOfBandResponseNotSupported;

  private static final java.lang.String tooManySessions;

  private static final java.lang.String proxyConnectionFailed;

  private static final java.lang.String mcmpMessageRejectedDueToSuspiciousCharacters;

  private static final java.lang.String rengotiationTimedOut;

  private static final java.lang.String requestBodyAlreadyRead;

  private static final java.lang.String blockingIoFromIOThread;

  private static final java.lang.String responseComplete;

  private static final java.lang.String couldNotReadContentLengthData;

  private static final java.lang.String failedToSendAfterBeingSafe;

  private static final java.lang.String reasonPhraseToLargeForBuffer;

  private static final java.lang.String poolIsClosed;

  private static final java.lang.String hpackFailed;

  private static final java.lang.String notAnUpgradeRequest;

  private static final java.lang.String authenticationPropertyNotSet;

  private static final java.lang.String rengotiationFailed;

  private static final java.lang.String userAgentCharsetMustHaveEvenNumberOfItems;

  private static final java.lang.String datasourceNotFound;

  private static final java.lang.String exchangeAlreadyComplete;

  private static final java.lang.String newlineNotSupportedInHttpString;

  protected io.undertow.UndertowMessages_$bundle();
    Code:
       0: aload_0
       1: invokespecial #1                  // Method java/lang/Object."<init>":()V
       4: return

  protected java.lang.Object readResolve();
    Code:
       0: getstatic     #2                  // Field INSTANCE:Lio/undertow/UndertowMessages_$bundle;
       3: areturn

  protected java.lang.String maximumConcurrentRequestsMustBeLargerThanZero$str();
    Code:
       0: ldc           #4                  // String UT000001: Maximum concurrent requests must be larger than zero.
       2: areturn

  public final java.lang.IllegalArgumentException maximumConcurrentRequestsMustBeLargerThanZero();
    Code:
       0: new           #5                  // class java/lang/IllegalArgumentException
       3: dup
       4: aload_0
       5: invokevirtual #6                  // Method maximumConcurrentRequestsMustBeLargerThanZero$str:()Ljava/lang/String;
       8: iconst_0
       9: anewarray     #7                  // class java/lang/Object
      12: invokestatic  #8                  // Method java/lang/String.format:(Ljava/lang/String;[Ljava/lang/Object;)Ljava/lang/String;
      15: invokespecial #9                  // Method java/lang/IllegalArgumentException."<init>":(Ljava/lang/String;)V
      18: astore_1
      19: aload_1
      20: invokevirtual #10                 // Method java/lang/IllegalArgumentException.getStackTrace:()[Ljava/lang/StackTraceElement;
      23: astore_2
      24: aload_1
      25: aload_2
      26: iconst_1
      27: aload_2
      28: arraylength
      29: invokestatic  #11                 // Method java/util/Arrays.copyOfRange:([Ljava/lang/Object;II)[Ljava/lang/Object;
      32: checkcast     #12                 // class "[Ljava/lang/StackTraceElement;"
      35: invokevirtual #13                 // Method java/lang/IllegalArgumentException.setStackTrace:([Ljava/lang/StackTraceElement;)V
      38: aload_1
      39: areturn

  protected java.lang.String responseAlreadyStarted$str();
    Code:
       0: ldc           #14                 // String UT000002: The response has already been started
       2: areturn

  public final java.lang.IllegalStateException responseAlreadyStarted();
    Code:
       0: new           #15                 // class java/lang/IllegalStateException
       3: dup
       4: aload_0
       5: invokevirtual #16                 // Method responseAlreadyStarted$str:()Ljava/lang/String;
       8: iconst_0
       9: anewarray     #7                  // class java/lang/Object
      12: invokestatic  #8                  // Method java/lang/String.format:(Ljava/lang/String;[Ljava/lang/Object;)Ljava/lang/String;
      15: invokespecial #17                 // Method java/lang/IllegalStateException."<init>":(Ljava/lang/String;)V
      18: astore_1
      19: aload_1
      20: invokevirtual #18                 // Method java/lang/IllegalStateException.getStackTrace:()[Ljava/lang/StackTraceElement;
      23: astore_2
      24: aload_1
      25: aload_2
      26: iconst_1
      27: aload_2
      28: arraylength
      29: invokestatic  #11                 // Method java/util/Arrays.copyOfRange:([Ljava/lang/Object;II)[Ljava/lang/Object;
      32: checkcast     #12                 // class "[Ljava/lang/StackTraceElement;"
      35: invokevirtual #19                 // Method java/lang/IllegalStateException.setStackTrace:([Ljava/lang/StackTraceElement;)V
      38: aload_1
      39: areturn

  protected java.lang.String responseChannelAlreadyProvided$str();
    Code:
       0: ldc           #20                 // String UT000004: getResponseChannel() has already been called
       2: areturn

  public final java.lang.IllegalStateException responseChannelAlreadyProvided();
    Code:
       0: new           #15                 // class java/lang/IllegalStateException
       3: dup
       4: aload_0
       5: invokevirtual #21                 // Method responseChannelAlreadyProvided$str:()Ljava/lang/String;
       8: iconst_0
       9: anewarray     #7                  // class java/lang/Object
      12: invokestatic  #8                  // Method java/lang/String.format:(Ljava/lang/String;[Ljava/lang/Object;)Ljava/lang/String;
      15: invokespecial #17                 // Method java/lang/IllegalStateException."<init>":(Ljava/lang/String;)V
      18: astore_1
      19: aload_1
      20: invokevirtual #18                 // Method java/lang/IllegalStateException.getStackTrace:()[Ljava/lang/StackTraceElement;
      23: astore_2
      24: aload_1
      25: aload_2
      26: iconst_1
      27: aload_2
      28: arraylength
      29: invokestatic  #11                 // Method java/util/Arrays.copyOfRange:([Ljava/lang/Object;II)[Ljava/lang/Object;
      32: checkcast     #12                 // class "[Ljava/lang/StackTraceElement;"
      35: invokevirtual #19                 // Method java/lang/IllegalStateException.setStackTrace:([Ljava/lang/StackTraceElement;)V
      38: aload_1
      39: areturn

  protected java.lang.String requestChannelAlreadyProvided$str();
    Code:
       0: ldc           #22                 // String UT000005: getRequestChannel() has already been called
       2: areturn

  public final java.lang.IllegalStateException requestChannelAlreadyProvided();
    Code:
       0: new           #15                 // class java/lang/IllegalStateException
       3: dup
       4: aload_0
       5: invokevirtual #23                 // Method requestChannelAlreadyProvided$str:()Ljava/lang/String;
       8: iconst_0
       9: anewarray     #7                  // class java/lang/Object
      12: invokestatic  #8                  // Method java/lang/String.format:(Ljava/lang/String;[Ljava/lang/Object;)Ljava/lang/String;
      15: invokespecial #17                 // Method java/lang/IllegalStateException."<init>":(Ljava/lang/String;)V
      18: astore_1
      19: aload_1
      20: invokevirtual #18                 // Method java/lang/IllegalStateException.getStackTrace:()[Ljava/lang/StackTraceElement;
      23: astore_2
      24: aload_1
      25: aload_2
      26: iconst_1
      27: aload_2
      28: arraylength
      29: invokestatic  #11                 // Method java/util/Arrays.copyOfRange:([Ljava/lang/Object;II)[Ljava/lang/Object;
      32: checkcast     #12                 // class "[Ljava/lang/StackTraceElement;"
      35: invokevirtual #19                 // Method java/lang/IllegalStateException.setStackTrace:([Ljava/lang/StackTraceElement;)V
      38: aload_1
      39: areturn

  protected java.lang.String handlerCannotBeNull$str();
    Code:
       0: ldc           #24                 // String UT000008: Handler cannot be null
       2: areturn

  public final java.lang.IllegalArgumentException handlerCannotBeNull();
    Code:
       0: new           #5                  // class java/lang/IllegalArgumentException
       3: dup
       4: aload_0
       5: invokevirtual #25                 // Method handlerCannotBeNull$str:()Ljava/lang/String;
       8: iconst_0
       9: anewarray     #7                  // class java/lang/Object
      12: invokestatic  #8                  // Method java/lang/String.format:(Ljava/lang/String;[Ljava/lang/Object;)Ljava/lang/String;
      15: invokespecial #9                  // Method java/lang/IllegalArgumentException."<init>":(Ljava/lang/String;)V
      18: astore_1
      19: aload_1
      20: invokevirtual #10                 // Method java/lang/IllegalArgumentException.getStackTrace:()[Ljava/lang/StackTraceElement;
      23: astore_2
      24: aload_1
      25: aload_2
      26: iconst_1
      27: aload_2
      28: arraylength
      29: invokestatic  #11                 // Method java/util/Arrays.copyOfRange:([Ljava/lang/Object;II)[Ljava/lang/Object;
      32: checkcast     #12                 // class "[Ljava/lang/StackTraceElement;"
      35: invokevirtual #13                 // Method java/lang/IllegalArgumentException.setStackTrace:([Ljava/lang/StackTraceElement;)V
      38: aload_1
      39: areturn

  protected java.lang.String pathMustBeSpecified$str();
    Code:
       0: ldc           #26                 // String UT000009: Path must be specified
       2: areturn

  public final java.lang.IllegalArgumentException pathMustBeSpecified();
    Code:
       0: new           #5                  // class java/lang/IllegalArgumentException
       3: dup
       4: aload_0
       5: invokevirtual #27                 // Method pathMustBeSpecified$str:()Ljava/lang/String;
       8: iconst_0
       9: anewarray     #7                  // class java/lang/Object
      12: invokestatic  #8                  // Method java/lang/String.format:(Ljava/lang/String;[Ljava/lang/Object;)Ljava/lang/String;
      15: invokespecial #9                  // Method java/lang/IllegalArgumentException."<init>":(Ljava/lang/String;)V
      18: astore_1
      19: aload_1
      20: invokevirtual #10                 // Method java/lang/IllegalArgumentException.getStackTrace:()[Ljava/lang/StackTraceElement;
      23: astore_2
      24: aload_1
      25: aload_2
      26: iconst_1
      27: aload_2
      28: arraylength
      29: invokestatic  #11                 // Method java/util/Arrays.copyOfRange:([Ljava/lang/Object;II)[Ljava/lang/Object;
      32: checkcast     #12                 // class "[Ljava/lang/StackTraceElement;"
      35: invokevirtual #13                 // Method java/lang/IllegalArgumentException.setStackTrace:([Ljava/lang/StackTraceElement;)V
      38: aload_1
      39: areturn

  protected java.lang.String sessionNotFound$str();
    Code:
       0: ldc           #28                 // String UT000010: Session not found %s
       2: areturn

  public final java.lang.IllegalStateException sessionNotFound(java.lang.String);
    Code:
       0: new           #15                 // class java/lang/IllegalStateException
       3: dup
       4: aload_0
       5: invokevirtual #29                 // Method sessionNotFound$str:()Ljava/lang/String;
       8: iconst_1
       9: anewarray     #7                  // class java/lang/Object
      12: dup
      13: iconst_0
      14: aload_1
      15: aastore
      16: invokestatic  #8                  // Method java/lang/String.format:(Ljava/lang/String;[Ljava/lang/Object;)Ljava/lang/String;
      19: invokespecial #17                 // Method java/lang/IllegalStateException."<init>":(Ljava/lang/String;)V
      22: astore_2
      23: aload_2
      24: invokevirtual #18                 // Method java/lang/IllegalStateException.getStackTrace:()[Ljava/lang/StackTraceElement;
      27: astore_3
      28: aload_2
      29: aload_3
      30: iconst_1
      31: aload_3
      32: arraylength
      33: invokestatic  #11                 // Method java/util/Arrays.copyOfRange:([Ljava/lang/Object;II)[Ljava/lang/Object;
      36: checkcast     #12                 // class "[Ljava/lang/StackTraceElement;"
      39: invokevirtual #19                 // Method java/lang/IllegalStateException.setStackTrace:([Ljava/lang/StackTraceElement;)V
      42: aload_2
      43: areturn

  protected java.lang.String sessionManagerMustNotBeNull$str();
    Code:
       0: ldc           #30                 // String UT000011: Session manager must not be null
       2: areturn

  public final java.lang.IllegalStateException sessionManagerMustNotBeNull();
    Code:
       0: new           #15                 // class java/lang/IllegalStateException
       3: dup
       4: aload_0
       5: invokevirtual #31                 // Method sessionManagerMustNotBeNull$str:()Ljava/lang/String;
       8: iconst_0
       9: anewarray     #7                  // class java/lang/Object
      12: invokestatic  #8                  // Method java/lang/String.format:(Ljava/lang/String;[Ljava/lang/Object;)Ljava/lang/String;
      15: invokespecial #17                 // Method java/lang/IllegalStateException."<init>":(Ljava/lang/String;)V
      18: astore_1
      19: aload_1
      20: invokevirtual #18                 // Method java/lang/IllegalStateException.getStackTrace:()[Ljava/lang/StackTraceElement;
      23: astore_2
      24: aload_1
      25: aload_2
      26: iconst_1
      27: aload_2
      28: arraylength
      29: invokestatic  #11                 // Method java/util/Arrays.copyOfRange:([Ljava/lang/Object;II)[Ljava/lang/Object;
      32: checkcast     #12                 // class "[Ljava/lang/StackTraceElement;"
      35: invokevirtual #19                 // Method java/lang/IllegalStateException.setStackTrace:([Ljava/lang/StackTraceElement;)V
      38: aload_1
      39: areturn

  protected java.lang.String sessionManagerNotFound$str();
    Code:
       0: ldc           #32                 // String UT000012: Session manager was not attached to the request. Make sure that the SessionAttachmentHandler is installed in the handler chain
       2: areturn

  public final java.lang.IllegalStateException sessionManagerNotFound();
    Code:
       0: new           #15                 // class java/lang/IllegalStateException
       3: dup
       4: aload_0
       5: invokevirtual #33                 // Method sessionManagerNotFound$str:()Ljava/lang/String;
       8: iconst_0
       9: anewarray     #7                  // class java/lang/Object
      12: invokestatic  #8                  // Method java/lang/String.format:(Ljava/lang/String;[Ljava/lang/Object;)Ljava/lang/String;
      15: invokespecial #17                 // Method java/lang/IllegalStateException."<init>":(Ljava/lang/String;)V
      18: astore_1
      19: aload_1
      20: invokevirtual #18                 // Method java/lang/IllegalStateException.getStackTrace:()[Ljava/lang/StackTraceElement;
      23: astore_2
      24: aload_1
      25: aload_2
      26: iconst_1
      27: aload_2
      28: arraylength
      29: invokestatic  #11                 // Method java/util/Arrays.copyOfRange:([Ljava/lang/Object;II)[Ljava/lang/Object;
      32: checkcast     #12                 // class "[Ljava/lang/StackTraceElement;"
      35: invokevirtual #19                 // Method java/lang/IllegalStateException.setStackTrace:([Ljava/lang/StackTraceElement;)V
      38: aload_1
      39: areturn

  protected java.lang.String argumentCannotBeNull$str();
    Code:
       0: ldc           #34                 // String UT000013: Argument %s cannot be null
       2: areturn

  public final java.lang.IllegalArgumentException argumentCannotBeNull(java.lang.String);
    Code:
       0: new           #5                  // class java/lang/IllegalArgumentException
       3: dup
       4: aload_0
       5: invokevirtual #35                 // Method argumentCannotBeNull$str:()Ljava/lang/String;
       8: iconst_1
       9: anewarray     #7                  // class java/lang/Object
      12: dup
      13: iconst_0
      14: aload_1
      15: aastore
      16: invokestatic  #8                  // Method java/lang/String.format:(Ljava/lang/String;[Ljava/lang/Object;)Ljava/lang/String;
      19: invokespecial #9                  // Method java/lang/IllegalArgumentException."<init>":(Ljava/lang/String;)V
      22: astore_2
      23: aload_2
      24: invokevirtual #10                 // Method java/lang/IllegalArgumentException.getStackTrace:()[Ljava/lang/StackTraceElement;
      27: astore_3
      28: aload_2
      29: aload_3
      30: iconst_1
      31: aload_3
      32: arraylength
      33: invokestatic  #11                 // Method java/util/Arrays.copyOfRange:([Ljava/lang/Object;II)[Ljava/lang/Object;
      36: checkcast     #12                 // class "[Ljava/lang/StackTraceElement;"
      39: invokevirtual #13                 // Method java/lang/IllegalArgumentException.setStackTrace:([Ljava/lang/StackTraceElement;)V
      42: aload_2
      43: areturn

  protected java.lang.String closeCalledWithDataStillToBeFlushed$str();
    Code:
       0: ldc           #36                 // String UT000014: close() called with data still to be flushed. Please call shutdownWrites() and then call flush() until it returns true before calling close()
       2: areturn

  public final java.io.IOException closeCalledWithDataStillToBeFlushed();
    Code:
       0: new           #37                 // class java/io/IOException
       3: dup
       4: aload_0
       5: invokevirtual #38                 // Method closeCalledWithDataStillToBeFlushed$str:()Ljava/lang/String;
       8: iconst_0
       9: anewarray     #7                  // class java/lang/Object
      12: invokestatic  #8                  // Method java/lang/String.format:(Ljava/lang/String;[Ljava/lang/Object;)Ljava/lang/String;
      15: invokespecial #39                 // Method java/io/IOException."<init>":(Ljava/lang/String;)V
      18: astore_1
      19: aload_1
      20: invokevirtual #40                 // Method java/io/IOException.getStackTrace:()[Ljava/lang/StackTraceElement;
      23: astore_2
      24: aload_1
      25: aload_2
      26: iconst_1
      27: aload_2
      28: arraylength
      29: invokestatic  #11                 // Method java/util/Arrays.copyOfRange:([Ljava/lang/Object;II)[Ljava/lang/Object;
      32: checkcast     #12                 // class "[Ljava/lang/StackTraceElement;"
      35: invokevirtual #41                 // Method java/io/IOException.setStackTrace:([Ljava/lang/StackTraceElement;)V
      38: aload_1
      39: areturn

  protected java.lang.String cookieHandlerNotPresent$str();
    Code:
       0: ldc           #42                 // String UT000016: Could not add cookie as cookie handler was not present in the handler chain
       2: areturn

  public final java.lang.IllegalStateException cookieHandlerNotPresent();
    Code:
       0: new           #15                 // class java/lang/IllegalStateException
       3: dup
       4: aload_0
       5: invokevirtual #43                 // Method cookieHandlerNotPresent$str:()Ljava/lang/String;
       8: iconst_0
       9: anewarray     #7                  // class java/lang/Object
      12: invokestatic  #8                  // Method java/lang/String.format:(Ljava/lang/String;[Ljava/lang/Object;)Ljava/lang/String;
      15: invokespecial #17                 // Method java/lang/IllegalStateException."<init>":(Ljava/lang/String;)V
      18: astore_1
      19: aload_1
      20: invokevirtual #18                 // Method java/lang/IllegalStateException.getStackTrace:()[Ljava/lang/StackTraceElement;
      23: astore_2
      24: aload_1
      25: aload_2
      26: iconst_1
      27: aload_2
      28: arraylength
      29: invokestatic  #11                 // Method java/util/Arrays.copyOfRange:([Ljava/lang/Object;II)[Ljava/lang/Object;
      32: checkcast     #12                 // class "[Ljava/lang/StackTraceElement;"
      35: invokevirtual #19                 // Method java/lang/IllegalStateException.setStackTrace:([Ljava/lang/StackTraceElement;)V
      38: aload_1
      39: areturn

  protected java.lang.String formValueIsAFile$str();
    Code:
       0: ldc           #44                 // String UT000017: Form value is a file, use getFile() instead
       2: areturn

  public final java.lang.IllegalStateException formValueIsAFile();
    Code:
       0: new           #15                 // class java/lang/IllegalStateException
       3: dup
       4: aload_0
       5: invokevirtual #45                 // Method formValueIsAFile$str:()Ljava/lang/String;
       8: iconst_0
       9: anewarray     #7                  // class java/lang/Object
      12: invokestatic  #8                  // Method java/lang/String.format:(Ljava/lang/String;[Ljava/lang/Object;)Ljava/lang/String;
      15: invokespecial #17                 // Method java/lang/IllegalStateException."<init>":(Ljava/lang/String;)V
      18: astore_1
      19: aload_1
      20: invokevirtual #18                 // Method java/lang/IllegalStateException.getStackTrace:()[Ljava/lang/StackTraceElement;
      23: astore_2
      24: aload_1
      25: aload_2
      26: iconst_1
      27: aload_2
      28: arraylength
      29: invokestatic  #11                 // Method java/util/Arrays.copyOfRange:([Ljava/lang/Object;II)[Ljava/lang/Object;
      32: checkcast     #12                 // class "[Ljava/lang/StackTraceElement;"
      35: invokevirtual #19                 // Method java/lang/IllegalStateException.setStackTrace:([Ljava/lang/StackTraceElement;)V
      38: aload_1
      39: areturn

  protected java.lang.String formValueIsAString$str();
    Code:
       0: ldc           #46                 // String UT000018: Form value is a String, use getValue() instead
       2: areturn

  public final java.lang.IllegalStateException formValueIsAString();
    Code:
       0: new           #15                 // class java/lang/IllegalStateException
       3: dup
       4: aload_0
       5: invokevirtual #47                 // Method formValueIsAString$str:()Ljava/lang/String;
       8: iconst_0
       9: anewarray     #7                  // class java/lang/Object
      12: invokestatic  #8                  // Method java/lang/String.format:(Ljava/lang/String;[Ljava/lang/Object;)Ljava/lang/String;
      15: invokespecial #17                 // Method java/lang/IllegalStateException."<init>":(Ljava/lang/String;)V
      18: astore_1
      19: aload_1
      20: invokevirtual #18                 // Method java/lang/IllegalStateException.getStackTrace:()[Ljava/lang/StackTraceElement;
      23: astore_2
      24: aload_1
      25: aload_2
      26: iconst_1
      27: aload_2
      28: arraylength
      29: invokestatic  #11                 // Method java/util/Arrays.copyOfRange:([Ljava/lang/Object;II)[Ljava/lang/Object;
      32: checkcast     #12                 // class "[Ljava/lang/StackTraceElement;"
      35: invokevirtual #19                 // Method java/lang/IllegalStateException.setStackTrace:([Ljava/lang/StackTraceElement;)V
      38: aload_1
      39: areturn

  protected java.lang.String requestEntityWasTooLarge2$str();
    Code:
       0: ldc           #48                 // String UT000019: Connection from %s terminated as request entity was larger than %s
       2: areturn

  public final java.io.IOException requestEntityWasTooLarge(java.net.SocketAddress, long);
    Code:
       0: new           #37                 // class java/io/IOException
       3: dup
       4: aload_0
       5: invokevirtual #49                 // Method requestEntityWasTooLarge2$str:()Ljava/lang/String;
       8: iconst_2
       9: anewarray     #7                  // class java/lang/Object
      12: dup
      13: iconst_0
      14: aload_1
      15: aastore
      16: dup
      17: iconst_1
      18: lload_2
      19: invokestatic  #50                 // Method java/lang/Long.valueOf:(J)Ljava/lang/Long;
      22: aastore
      23: invokestatic  #8                  // Method java/lang/String.format:(Ljava/lang/String;[Ljava/lang/Object;)Ljava/lang/String;
      26: invokespecial #39                 // Method java/io/IOException."<init>":(Ljava/lang/String;)V
      29: astore        4
      31: aload         4
      33: invokevirtual #40                 // Method java/io/IOException.getStackTrace:()[Ljava/lang/StackTraceElement;
      36: astore        5
      38: aload         4
      40: aload         5
      42: iconst_1
      43: aload         5
      45: arraylength
      46: invokestatic  #11                 // Method java/util/Arrays.copyOfRange:([Ljava/lang/Object;II)[Ljava/lang/Object;
      49: checkcast     #12                 // class "[Ljava/lang/StackTraceElement;"
      52: invokevirtual #41                 // Method java/io/IOException.setStackTrace:([Ljava/lang/StackTraceElement;)V
      55: aload         4
      57: areturn

  protected java.lang.String requestEntityWasTooLarge1$str();
    Code:
       0: ldc           #51                 // String UT000020: Connection terminated as request was larger than %s
       2: areturn

  public final java.io.IOException requestEntityWasTooLarge(long);
    Code:
       0: new           #37                 // class java/io/IOException
       3: dup
       4: aload_0
       5: invokevirtual #52                 // Method requestEntityWasTooLarge1$str:()Ljava/lang/String;
       8: iconst_1
       9: anewarray     #7                  // class java/lang/Object
      12: dup
      13: iconst_0
      14: lload_1
      15: invokestatic  #50                 // Method java/lang/Long.valueOf:(J)Ljava/lang/Long;
      18: aastore
      19: invokestatic  #8                  // Method java/lang/String.format:(Ljava/lang/String;[Ljava/lang/Object;)Ljava/lang/String;
      22: invokespecial #39                 // Method java/io/IOException."<init>":(Ljava/lang/String;)V
      25: astore_3
      26: aload_3
      27: invokevirtual #40                 // Method java/io/IOException.getStackTrace:()[Ljava/lang/StackTraceElement;
      30: astore        4
      32: aload_3
      33: aload         4
      35: iconst_1
      36: aload         4
      38: arraylength
      39: invokestatic  #11                 // Method java/util/Arrays.copyOfRange:([Ljava/lang/Object;II)[Ljava/lang/Object;
      42: checkcast     #12                 // class "[Ljava/lang/StackTraceElement;"
      45: invokevirtual #41                 // Method java/io/IOException.setStackTrace:([Ljava/lang/StackTraceElement;)V
      48: aload_3
      49: areturn

  protected java.lang.String sessionAlreadyInvalidated$str();
    Code:
       0: ldc           #53                 // String UT000021: Session already invalidated
       2: areturn

  public final java.lang.IllegalStateException sessionAlreadyInvalidated();
    Code:
       0: new           #15                 // class java/lang/IllegalStateException
       3: dup
       4: aload_0
       5: invokevirtual #54                 // Method sessionAlreadyInvalidated$str:()Ljava/lang/String;
       8: iconst_0
       9: anewarray     #7                  // class java/lang/Object
      12: invokestatic  #8                  // Method java/lang/String.format:(Ljava/lang/String;[Ljava/lang/Object;)Ljava/lang/String;
      15: invokespecial #17                 // Method java/lang/IllegalStateException."<init>":(Ljava/lang/String;)V
      18: astore_1
      19: aload_1
      20: invokevirtual #18                 // Method java/lang/IllegalStateException.getStackTrace:()[Ljava/lang/StackTraceElement;
      23: astore_2
      24: aload_1
      25: aload_2
      26: iconst_1
      27: aload_2
      28: arraylength
      29: invokestatic  #11                 // Method java/util/Arrays.copyOfRange:([Ljava/lang/Object;II)[Ljava/lang/Object;
      32: checkcast     #12                 // class "[Ljava/lang/StackTraceElement;"
      35: invokevirtual #19                 // Method java/lang/IllegalStateException.setStackTrace:([Ljava/lang/StackTraceElement;)V
      38: aload_1
      39: areturn

  protected java.lang.String hashAlgorithmNotFound$str();
    Code:
       0: ldc           #55                 // String UT000022: The specified hash algorithm \'%s\' can not be found.
       2: areturn

  public final java.lang.IllegalArgumentException hashAlgorithmNotFound(java.lang.String);
    Code:
       0: new           #5                  // class java/lang/IllegalArgumentException
       3: dup
       4: aload_0
       5: invokevirtual #56                 // Method hashAlgorithmNotFound$str:()Ljava/lang/String;
       8: iconst_1
       9: anewarray     #7                  // class java/lang/Object
      12: dup
      13: iconst_0
      14: aload_1
      15: aastore
      16: invokestatic  #8                  // Method java/lang/String.format:(Ljava/lang/String;[Ljava/lang/Object;)Ljava/lang/String;
      19: invokespecial #9                  // Method java/lang/IllegalArgumentException."<init>":(Ljava/lang/String;)V
      22: astore_2
      23: aload_2
      24: invokevirtual #10                 // Method java/lang/IllegalArgumentException.getStackTrace:()[Ljava/lang/StackTraceElement;
      27: astore_3
      28: aload_2
      29: aload_3
      30: iconst_1
      31: aload_3
      32: arraylength
      33: invokestatic  #11                 // Method java/util/Arrays.copyOfRange:([Ljava/lang/Object;II)[Ljava/lang/Object;
      36: checkcast     #12                 // class "[Ljava/lang/StackTraceElement;"
      39: invokevirtual #13                 // Method java/lang/IllegalArgumentException.setStackTrace:([Ljava/lang/StackTraceElement;)V
      42: aload_2
      43: areturn

  protected java.lang.String invalidBase64Token$str();
    Code:
       0: ldc           #57                 // String UT000023: An invalid Base64 token has been received.
       2: areturn

  public final java.lang.IllegalArgumentException invalidBase64Token(java.io.IOException);
    Code:
       0: new           #5                  // class java/lang/IllegalArgumentException
       3: dup
       4: aload_0
       5: invokevirtual #58                 // Method invalidBase64Token$str:()Ljava/lang/String;
       8: iconst_0
       9: anewarray     #7                  // class java/lang/Object
      12: invokestatic  #8                  // Method java/lang/String.format:(Ljava/lang/String;[Ljava/lang/Object;)Ljava/lang/String;
      15: aload_1
      16: invokespecial #59                 // Method java/lang/IllegalArgumentException."<init>":(Ljava/lang/String;Ljava/lang/Throwable;)V
      19: astore_2
      20: aload_2
      21: invokevirtual #10                 // Method java/lang/IllegalArgumentException.getStackTrace:()[Ljava/lang/StackTraceElement;
      24: astore_3
      25: aload_2
      26: aload_3
      27: iconst_1
      28: aload_3
      29: arraylength
      30: invokestatic  #11                 // Method java/util/Arrays.copyOfRange:([Ljava/lang/Object;II)[Ljava/lang/Object;
      33: checkcast     #12                 // class "[Ljava/lang/StackTraceElement;"
      36: invokevirtual #13                 // Method java/lang/IllegalArgumentException.setStackTrace:([Ljava/lang/StackTraceElement;)V
      39: aload_2
      40: areturn

  protected java.lang.String invalidNonceReceived$str();
    Code:
       0: ldc           #60                 // String UT000024: An invalidly formatted nonce has been received.
       2: areturn

  public final java.lang.IllegalArgumentException invalidNonceReceived();
    Code:
       0: new           #5                  // class java/lang/IllegalArgumentException
       3: dup
       4: aload_0
       5: invokevirtual #61                 // Method invalidNonceReceived$str:()Ljava/lang/String;
       8: iconst_0
       9: anewarray     #7                  // class java/lang/Object
      12: invokestatic  #8                  // Method java/lang/String.format:(Ljava/lang/String;[Ljava/lang/Object;)Ljava/lang/String;
      15: invokespecial #9                  // Method java/lang/IllegalArgumentException."<init>":(Ljava/lang/String;)V
      18: astore_1
      19: aload_1
      20: invokevirtual #10                 // Method java/lang/IllegalArgumentException.getStackTrace:()[Ljava/lang/StackTraceElement;
      23: astore_2
      24: aload_1
      25: aload_2
      26: iconst_1
      27: aload_2
      28: arraylength
      29: invokestatic  #11                 // Method java/util/Arrays.copyOfRange:([Ljava/lang/Object;II)[Ljava/lang/Object;
      32: checkcast     #12                 // class "[Ljava/lang/StackTraceElement;"
      35: invokevirtual #13                 // Method java/lang/IllegalArgumentException.setStackTrace:([Ljava/lang/StackTraceElement;)V
      38: aload_1
      39: areturn

  protected java.lang.String unexpectedTokenInHeader$str();
    Code:
       0: ldc           #62                 // String UT000025: Unexpected token \'%s\' within header.
       2: areturn

  public final java.lang.IllegalArgumentException unexpectedTokenInHeader(java.lang.String);
    Code:
       0: new           #5                  // class java/lang/IllegalArgumentException
       3: dup
       4: aload_0
       5: invokevirtual #63                 // Method unexpectedTokenInHeader$str:()Ljava/lang/String;
       8: iconst_1
       9: anewarray     #7                  // class java/lang/Object
      12: dup
      13: iconst_0
      14: aload_1
      15: aastore
      16: invokestatic  #8                  // Method java/lang/String.format:(Ljava/lang/String;[Ljava/lang/Object;)Ljava/lang/String;
      19: invokespecial #9                  // Method java/lang/IllegalArgumentException."<init>":(Ljava/lang/String;)V
      22: astore_2
      23: aload_2
      24: invokevirtual #10                 // Method java/lang/IllegalArgumentException.getStackTrace:()[Ljava/lang/StackTraceElement;
      27: astore_3
      28: aload_2
      29: aload_3
      30: iconst_1
      31: aload_3
      32: arraylength
      33: invokestatic  #11                 // Method java/util/Arrays.copyOfRange:([Ljava/lang/Object;II)[Ljava/lang/Object;
      36: checkcast     #12                 // class "[Ljava/lang/StackTraceElement;"
      39: invokevirtual #13                 // Method java/lang/IllegalArgumentException.setStackTrace:([Ljava/lang/StackTraceElement;)V
      42: aload_2
      43: areturn

  protected java.lang.String invalidHeader$str();
    Code:
       0: ldc           #64                 // String UT000026: Invalid header received.
       2: areturn

  public final java.lang.IllegalArgumentException invalidHeader();
    Code:
       0: new           #5                  // class java/lang/IllegalArgumentException
       3: dup
       4: aload_0
       5: invokevirtual #65                 // Method invalidHeader$str:()Ljava/lang/String;
       8: iconst_0
       9: anewarray     #7                  // class java/lang/Object
      12: invokestatic  #8                  // Method java/lang/String.format:(Ljava/lang/String;[Ljava/lang/Object;)Ljava/lang/String;
      15: invokespecial #9                  // Method java/lang/IllegalArgumentException."<init>":(Ljava/lang/String;)V
      18: astore_1
      19: aload_1
      20: invokevirtual #10                 // Method java/lang/IllegalArgumentException.getStackTrace:()[Ljava/lang/StackTraceElement;
      23: astore_2
      24: aload_1
      25: aload_2
      26: iconst_1
      27: aload_2
      28: arraylength
      29: invokestatic  #11                 // Method java/util/Arrays.copyOfRange:([Ljava/lang/Object;II)[Ljava/lang/Object;
      32: checkcast     #12                 // class "[Ljava/lang/StackTraceElement;"
      35: invokevirtual #13                 // Method java/lang/IllegalArgumentException.setStackTrace:([Ljava/lang/StackTraceElement;)V
      38: aload_1
      39: areturn

  protected java.lang.String couldNotFindSessionCookieConfig$str();
    Code:
       0: ldc           #66                 // String UT000027: Could not find session cookie config in the request
       2: areturn

  public final java.lang.IllegalStateException couldNotFindSessionCookieConfig();
    Code:
       0: new           #15                 // class java/lang/IllegalStateException
       3: dup
       4: aload_0
       5: invokevirtual #67                 // Method couldNotFindSessionCookieConfig$str:()Ljava/lang/String;
       8: iconst_0
       9: anewarray     #7                  // class java/lang/Object
      12: invokestatic  #8                  // Method java/lang/String.format:(Ljava/lang/String;[Ljava/lang/Object;)Ljava/lang/String;
      15: invokespecial #17                 // Method java/lang/IllegalStateException."<init>":(Ljava/lang/String;)V
      18: astore_1
      19: aload_1
      20: invokevirtual #18                 // Method java/lang/IllegalStateException.getStackTrace:()[Ljava/lang/StackTraceElement;
      23: astore_2
      24: aload_1
      25: aload_2
      26: iconst_1
      27: aload_2
      28: arraylength
      29: invokestatic  #11                 // Method java/util/Arrays.copyOfRange:([Ljava/lang/Object;II)[Ljava/lang/Object;
      32: checkcast     #12                 // class "[Ljava/lang/StackTraceElement;"
      35: invokevirtual #19                 // Method java/lang/IllegalStateException.setStackTrace:([Ljava/lang/StackTraceElement;)V
      38: aload_1
      39: areturn

  protected java.lang.String sessionAlreadyExists$str();
    Code:
       0: ldc           #68                 // String UT000028: Session %s already exists
       2: areturn

  public final java.lang.IllegalStateException sessionAlreadyExists(java.lang.String);
    Code:
       0: new           #15                 // class java/lang/IllegalStateException
       3: dup
       4: aload_0
       5: invokevirtual #69                 // Method sessionAlreadyExists$str:()Ljava/lang/String;
       8: iconst_1
       9: anewarray     #7                  // class java/lang/Object
      12: dup
      13: iconst_0
      14: aload_1
      15: aastore
      16: invokestatic  #8                  // Method java/lang/String.format:(Ljava/lang/String;[Ljava/lang/Object;)Ljava/lang/String;
      19: invokespecial #17                 // Method java/lang/IllegalStateException."<init>":(Ljava/lang/String;)V
      22: astore_2
      23: aload_2
      24: invokevirtual #18                 // Method java/lang/IllegalStateException.getStackTrace:()[Ljava/lang/StackTraceElement;
      27: astore_3
      28: aload_2
      29: aload_3
      30: iconst_1
      31: aload_3
      32: arraylength
      33: invokestatic  #11                 // Method java/util/Arrays.copyOfRange:([Ljava/lang/Object;II)[Ljava/lang/Object;
      36: checkcast     #12                 // class "[Ljava/lang/StackTraceElement;"
      39: invokevirtual #19                 // Method java/lang/IllegalStateException.setStackTrace:([Ljava/lang/StackTraceElement;)V
      42: aload_2
      43: areturn

  protected java.lang.String chunkedChannelClosedMidChunk$str();
    Code:
       0: ldc           #70                 // String UT000029: Channel was closed mid chunk, if you have attempted to write chunked data you cannot shutdown the channel until after it has all been written.
       2: areturn

  public final java.io.IOException chunkedChannelClosedMidChunk();
    Code:
       0: new           #37                 // class java/io/IOException
       3: dup
       4: aload_0
       5: invokevirtual #71                 // Method chunkedChannelClosedMidChunk$str:()Ljava/lang/String;
       8: iconst_0
       9: anewarray     #7                  // class java/lang/Object
      12: invokestatic  #8                  // Method java/lang/String.format:(Ljava/lang/String;[Ljava/lang/Object;)Ljava/lang/String;
      15: invokespecial #39                 // Method java/io/IOException."<init>":(Ljava/lang/String;)V
      18: astore_1
      19: aload_1
      20: invokevirtual #40                 // Method java/io/IOException.getStackTrace:()[Ljava/lang/StackTraceElement;
      23: astore_2
      24: aload_1
      25: aload_2
      26: iconst_1
      27: aload_2
      28: arraylength
      29: invokestatic  #11                 // Method java/util/Arrays.copyOfRange:([Ljava/lang/Object;II)[Ljava/lang/Object;
      32: checkcast     #12                 // class "[Ljava/lang/StackTraceElement;"
      35: invokevirtual #41                 // Method java/io/IOException.setStackTrace:([Ljava/lang/StackTraceElement;)V
      38: aload_1
      39: areturn

  protected java.lang.String userAuthenticated$str();
    Code:
       0: ldc           #72                 // String UT000030: User %s successfully authenticated.
       2: areturn

  public final java.lang.String userAuthenticated(java.lang.String);
    Code:
       0: aload_0
       1: invokevirtual #73                 // Method userAuthenticated$str:()Ljava/lang/String;
       4: iconst_1
       5: anewarray     #7                  // class java/lang/Object
       8: dup
       9: iconst_0
      10: aload_1
      11: aastore
      12: invokestatic  #8                  // Method java/lang/String.format:(Ljava/lang/String;[Ljava/lang/Object;)Ljava/lang/String;
      15: areturn

  protected java.lang.String userLoggedOut$str();
    Code:
       0: ldc           #74                 // String UT000031: User %s has logged out.
       2: areturn

  public final java.lang.String userLoggedOut(java.lang.String);
    Code:
       0: aload_0
       1: invokevirtual #75                 // Method userLoggedOut$str:()Ljava/lang/String;
       4: iconst_1
       5: anewarray     #7                  // class java/lang/Object
       8: dup
       9: iconst_0
      10: aload_1
      11: aastore
      12: invokestatic  #8                  // Method java/lang/String.format:(Ljava/lang/String;[Ljava/lang/Object;)Ljava/lang/String;
      15: areturn

  protected java.lang.String authTypeCannotBeCombined$str();
    Code:
       0: ldc           #76                 // String UT000033: Authentication type %s cannot be combined with %s
       2: areturn

  public final java.lang.IllegalStateException authTypeCannotBeCombined(java.lang.String, java.lang.String);
    Code:
       0: new           #15                 // class java/lang/IllegalStateException
       3: dup
       4: aload_0
       5: invokevirtual #77                 // Method authTypeCannotBeCombined$str:()Ljava/lang/String;
       8: iconst_2
       9: anewarray     #7                  // class java/lang/Object
      12: dup
      13: iconst_0
      14: aload_1
      15: aastore
      16: dup
      17: iconst_1
      18: aload_2
      19: aastore
      20: invokestatic  #8                  // Method java/lang/String.format:(Ljava/lang/String;[Ljava/lang/Object;)Ljava/lang/String;
      23: invokespecial #17                 // Method java/lang/IllegalStateException."<init>":(Ljava/lang/String;)V
      26: astore_3
      27: aload_3
      28: invokevirtual #18                 // Method java/lang/IllegalStateException.getStackTrace:()[Ljava/lang/StackTraceElement;
      31: astore        4
      33: aload_3
      34: aload         4
      36: iconst_1
      37: aload         4
      39: arraylength
      40: invokestatic  #11                 // Method java/util/Arrays.copyOfRange:([Ljava/lang/Object;II)[Ljava/lang/Object;
      43: checkcast     #12                 // class "[Ljava/lang/StackTraceElement;"
      46: invokevirtual #19                 // Method java/lang/IllegalStateException.setStackTrace:([Ljava/lang/StackTraceElement;)V
      49: aload_3
      50: areturn

  protected java.lang.String streamIsClosed$str();
    Code:
       0: ldc           #78                 // String UT000034: Stream is closed
       2: areturn

  public final java.io.IOException streamIsClosed();
    Code:
       0: new           #37                 // class java/io/IOException
       3: dup
       4: aload_0
       5: invokevirtual #79                 // Method streamIsClosed$str:()Ljava/lang/String;
       8: iconst_0
       9: anewarray     #7                  // class java/lang/Object
      12: invokestatic  #8                  // Method java/lang/String.format:(Ljava/lang/String;[Ljava/lang/Object;)Ljava/lang/String;
      15: invokespecial #39                 // Method java/io/IOException."<init>":(Ljava/lang/String;)V
      18: astore_1
      19: aload_1
      20: invokevirtual #40                 // Method java/io/IOException.getStackTrace:()[Ljava/lang/StackTraceElement;
      23: astore_2
      24: aload_1
      25: aload_2
      26: iconst_1
      27: aload_2
      28: arraylength
      29: invokestatic  #11                 // Method java/util/Arrays.copyOfRange:([Ljava/lang/Object;II)[Ljava/lang/Object;
      32: checkcast     #12                 // class "[Ljava/lang/StackTraceElement;"
      35: invokevirtual #41                 // Method java/io/IOException.setStackTrace:([Ljava/lang/StackTraceElement;)V
      38: aload_1
      39: areturn

  protected java.lang.String startBlockingHasNotBeenCalled$str();
    Code:
       0: ldc           #80                 // String UT000035: Cannot get stream as startBlocking has not been invoked
       2: areturn

  public final java.lang.IllegalStateException startBlockingHasNotBeenCalled();
    Code:
       0: new           #15                 // class java/lang/IllegalStateException
       3: dup
       4: aload_0
       5: invokevirtual #81                 // Method startBlockingHasNotBeenCalled$str:()Ljava/lang/String;
       8: iconst_0
       9: anewarray     #7                  // class java/lang/Object
      12: invokestatic  #8                  // Method java/lang/String.format:(Ljava/lang/String;[Ljava/lang/Object;)Ljava/lang/String;
      15: invokespecial #17                 // Method java/lang/IllegalStateException."<init>":(Ljava/lang/String;)V
      18: astore_1
      19: aload_1
      20: invokevirtual #18                 // Method java/lang/IllegalStateException.getStackTrace:()[Ljava/lang/StackTraceElement;
      23: astore_2
      24: aload_1
      25: aload_2
      26: iconst_1
      27: aload_2
      28: arraylength
      29: invokestatic  #11                 // Method java/util/Arrays.copyOfRange:([Ljava/lang/Object;II)[Ljava/lang/Object;
      32: checkcast     #12                 // class "[Ljava/lang/StackTraceElement;"
      35: invokevirtual #19                 // Method java/lang/IllegalStateException.setStackTrace:([Ljava/lang/StackTraceElement;)V
      38: aload_1
      39: areturn

  protected java.lang.String connectionTerminatedReadingMultiPartData$str();
    Code:
       0: ldc           #82                 // String UT000036: Connection terminated parsing multipart data
       2: areturn

  public final java.io.IOException connectionTerminatedReadingMultiPartData();
    Code:
       0: new           #37                 // class java/io/IOException
       3: dup
       4: aload_0
       5: invokevirtual #83                 // Method connectionTerminatedReadingMultiPartData$str:()Ljava/lang/String;
       8: iconst_0
       9: anewarray     #7                  // class java/lang/Object
      12: invokestatic  #8                  // Method java/lang/String.format:(Ljava/lang/String;[Ljava/lang/Object;)Ljava/lang/String;
      15: invokespecial #39                 // Method java/io/IOException."<init>":(Ljava/lang/String;)V
      18: astore_1
      19: aload_1
      20: invokevirtual #40                 // Method java/io/IOException.getStackTrace:()[Ljava/lang/StackTraceElement;
      23: astore_2
      24: aload_1
      25: aload_2
      26: iconst_1
      27: aload_2
      28: arraylength
      29: invokestatic  #11                 // Method java/util/Arrays.copyOfRange:([Ljava/lang/Object;II)[Ljava/lang/Object;
      32: checkcast     #12                 // class "[Ljava/lang/StackTraceElement;"
      35: invokevirtual #41                 // Method java/io/IOException.setStackTrace:([Ljava/lang/StackTraceElement;)V
      38: aload_1
      39: areturn

  protected java.lang.String failedToParsePath$str();
    Code:
       0: ldc           #84                 // String UT000037: Failed to parse path in HTTP request
       2: areturn

  public final java.lang.RuntimeException failedToParsePath();
    Code:
       0: new           #85                 // class java/lang/RuntimeException
       3: dup
       4: aload_0
       5: invokevirtual #86                 // Method failedToParsePath$str:()Ljava/lang/String;
       8: iconst_0
       9: anewarray     #7                  // class java/lang/Object
      12: invokestatic  #8                  // Method java/lang/String.format:(Ljava/lang/String;[Ljava/lang/Object;)Ljava/lang/String;
      15: invokespecial #87                 // Method java/lang/RuntimeException."<init>":(Ljava/lang/String;)V
      18: astore_1
      19: aload_1
      20: invokevirtual #88                 // Method java/lang/RuntimeException.getStackTrace:()[Ljava/lang/StackTraceElement;
      23: astore_2
      24: aload_1
      25: aload_2
      26: iconst_1
      27: aload_2
      28: arraylength
      29: invokestatic  #11                 // Method java/util/Arrays.copyOfRange:([Ljava/lang/Object;II)[Ljava/lang/Object;
      32: checkcast     #12                 // class "[Ljava/lang/StackTraceElement;"
      35: invokevirtual #89                 // Method java/lang/RuntimeException.setStackTrace:([Ljava/lang/StackTraceElement;)V
      38: aload_1
      39: areturn

  protected java.lang.String authenticationFailed$str();
    Code:
       0: ldc           #90                 // String UT000038: Authentication failed, requested user name \'%s\'
       2: areturn

  public final java.lang.String authenticationFailed(java.lang.String);
    Code:
       0: aload_0
       1: invokevirtual #91                 // Method authenticationFailed$str:()Ljava/lang/String;
       4: iconst_1
       5: anewarray     #7                  // class java/lang/Object
       8: dup
       9: iconst_0
      10: aload_1
      11: aastore
      12: invokestatic  #8                  // Method java/lang/String.format:(Ljava/lang/String;[Ljava/lang/Object;)Ljava/lang/String;
      15: areturn

  protected java.lang.String tooManyQueryParameters$str();
    Code:
       0: ldc           #92                 // String UT000039: To many query parameters, cannot have more than %s query parameters
       2: areturn

  public final java.lang.RuntimeException tooManyQueryParameters(int);
    Code:
       0: new           #85                 // class java/lang/RuntimeException
       3: dup
       4: aload_0
       5: invokevirtual #93                 // Method tooManyQueryParameters$str:()Ljava/lang/String;
       8: iconst_1
       9: anewarray     #7                  // class java/lang/Object
      12: dup
      13: iconst_0
      14: iload_1
      15: invokestatic  #94                 // Method java/lang/Integer.valueOf:(I)Ljava/lang/Integer;
      18: aastore
      19: invokestatic  #8                  // Method java/lang/String.format:(Ljava/lang/String;[Ljava/lang/Object;)Ljava/lang/String;
      22: invokespecial #87                 // Method java/lang/RuntimeException."<init>":(Ljava/lang/String;)V
      25: astore_2
      26: aload_2
      27: invokevirtual #88                 // Method java/lang/RuntimeException.getStackTrace:()[Ljava/lang/StackTraceElement;
      30: astore_3
      31: aload_2
      32: aload_3
      33: iconst_1
      34: aload_3
      35: arraylength
      36: invokestatic  #11                 // Method java/util/Arrays.copyOfRange:([Ljava/lang/Object;II)[Ljava/lang/Object;
      39: checkcast     #12                 // class "[Ljava/lang/StackTraceElement;"
      42: invokevirtual #89                 // Method java/lang/RuntimeException.setStackTrace:([Ljava/lang/StackTraceElement;)V
      45: aload_2
      46: areturn

  protected java.lang.String tooManyHeaders$str();
    Code:
       0: ldc           #95                 // String UT000040: To many headers, cannot have more than %s header
       2: areturn

  public final java.lang.RuntimeException tooManyHeaders(int);
    Code:
       0: new           #85                 // class java/lang/RuntimeException
       3: dup
       4: aload_0
       5: invokevirtual #96                 // Method tooManyHeaders$str:()Ljava/lang/String;
       8: iconst_1
       9: anewarray     #7                  // class java/lang/Object
      12: dup
      13: iconst_0
      14: iload_1
      15: invokestatic  #94                 // Method java/lang/Integer.valueOf:(I)Ljava/lang/Integer;
      18: aastore
      19: invokestatic  #8                  // Method java/lang/String.format:(Ljava/lang/String;[Ljava/lang/Object;)Ljava/lang/String;
      22: invokespecial #87                 // Method java/lang/RuntimeException."<init>":(Ljava/lang/String;)V
      25: astore_2
      26: aload_2
      27: invokevirtual #88                 // Method java/lang/RuntimeException.getStackTrace:()[Ljava/lang/StackTraceElement;
      30: astore_3
      31: aload_2
      32: aload_3
      33: iconst_1
      34: aload_3
      35: arraylength
      36: invokestatic  #11                 // Method java/util/Arrays.copyOfRange:([Ljava/lang/Object;II)[Ljava/lang/Object;
      39: checkcast     #12                 // class "[Ljava/lang/StackTraceElement;"
      42: invokevirtual #89                 // Method java/lang/RuntimeException.setStackTrace:([Ljava/lang/StackTraceElement;)V
      45: aload_2
      46: areturn

  protected java.lang.String channelIsClosed$str();
    Code:
       0: ldc           #97                 // String UT000041: Channel is closed
       2: areturn

  public final java.nio.channels.ClosedChannelException channelIsClosed();
    Code:
       0: new           #98                 // class java/nio/channels/ClosedChannelException
       3: dup
       4: invokespecial #99                 // Method java/nio/channels/ClosedChannelException."<init>":()V
       7: astore_1
       8: aload_1
       9: invokevirtual #100                // Method java/nio/channels/ClosedChannelException.getStackTrace:()[Ljava/lang/StackTraceElement;
      12: astore_2
      13: aload_1
      14: aload_2
      15: iconst_1
      16: aload_2
      17: arraylength
      18: invokestatic  #11                 // Method java/util/Arrays.copyOfRange:([Ljava/lang/Object;II)[Ljava/lang/Object;
      21: checkcast     #12                 // class "[Ljava/lang/StackTraceElement;"
      24: invokevirtual #101                // Method java/nio/channels/ClosedChannelException.setStackTrace:([Ljava/lang/StackTraceElement;)V
      27: aload_1
      28: areturn

  protected java.lang.String couldNotDecodeTrailers$str();
    Code:
       0: ldc           #102                // String UT000042: Could not decode trailers in HTTP request
       2: areturn

  public final java.io.IOException couldNotDecodeTrailers();
    Code:
       0: new           #37                 // class java/io/IOException
       3: dup
       4: aload_0
       5: invokevirtual #103                // Method couldNotDecodeTrailers$str:()Ljava/lang/String;
       8: iconst_0
       9: anewarray     #7                  // class java/lang/Object
      12: invokestatic  #8                  // Method java/lang/String.format:(Ljava/lang/String;[Ljava/lang/Object;)Ljava/lang/String;
      15: invokespecial #39                 // Method java/io/IOException."<init>":(Ljava/lang/String;)V
      18: astore_1
      19: aload_1
      20: invokevirtual #40                 // Method java/io/IOException.getStackTrace:()[Ljava/lang/StackTraceElement;
      23: astore_2
      24: aload_1
      25: aload_2
      26: iconst_1
      27: aload_2
      28: arraylength
      29: invokestatic  #11                 // Method java/util/Arrays.copyOfRange:([Ljava/lang/Object;II)[Ljava/lang/Object;
      32: checkcast     #12                 // class "[Ljava/lang/StackTraceElement;"
      35: invokevirtual #41                 // Method java/io/IOException.setStackTrace:([Ljava/lang/StackTraceElement;)V
      38: aload_1
      39: areturn

  protected java.lang.String dataAlreadyQueued$str();
    Code:
       0: ldc           #104                // String UT000043: Data is already being sent. You must wait for the completion callback to be be invoked before calling send() again
       2: areturn

  public final java.lang.IllegalStateException dataAlreadyQueued();
    Code:
       0: new           #15                 // class java/lang/IllegalStateException
       3: dup
       4: aload_0
       5: invokevirtual #105                // Method dataAlreadyQueued$str:()Ljava/lang/String;
       8: iconst_0
       9: anewarray     #7                  // class java/lang/Object
      12: invokestatic  #8                  // Method java/lang/String.format:(Ljava/lang/String;[Ljava/lang/Object;)Ljava/lang/String;
      15: invokespecial #17                 // Method java/lang/IllegalStateException."<init>":(Ljava/lang/String;)V
      18: astore_1
      19: aload_1
      20: invokevirtual #18                 // Method java/lang/IllegalStateException.getStackTrace:()[Ljava/lang/StackTraceElement;
      23: astore_2
      24: aload_1
      25: aload_2
      26: iconst_1
      27: aload_2
      28: arraylength
      29: invokestatic  #11                 // Method java/util/Arrays.copyOfRange:([Ljava/lang/Object;II)[Ljava/lang/Object;
      32: checkcast     #12                 // class "[Ljava/lang/StackTraceElement;"
      35: invokevirtual #19                 // Method java/lang/IllegalStateException.setStackTrace:([Ljava/lang/StackTraceElement;)V
      38: aload_1
      39: areturn

  protected java.lang.String moreThanOnePredicateWithName$str();
    Code:
       0: ldc           #106                // String UT000044: More than one predicate with name %s. Builder class %s and %s
       2: areturn

  public final java.lang.IllegalStateException moreThanOnePredicateWithName(java.lang.String, java.lang.Class<? extends io.undertow.predicate.PredicateBuilder>, java.lang.Class<? extends io.undertow.predicate.PredicateBuilder>);
    Code:
       0: new           #15                 // class java/lang/IllegalStateException
       3: dup
       4: aload_0
       5: invokevirtual #107                // Method moreThanOnePredicateWithName$str:()Ljava/lang/String;
       8: iconst_3
       9: anewarray     #7                  // class java/lang/Object
      12: dup
      13: iconst_0
      14: aload_1
      15: aastore
      16: dup
      17: iconst_1
      18: aload_2
      19: aastore
      20: dup
      21: iconst_2
      22: aload_3
      23: aastore
      24: invokestatic  #8                  // Method java/lang/String.format:(Ljava/lang/String;[Ljava/lang/Object;)Ljava/lang/String;
      27: invokespecial #17                 // Method java/lang/IllegalStateException."<init>":(Ljava/lang/String;)V
      30: astore        4
      32: aload         4
      34: invokevirtual #18                 // Method java/lang/IllegalStateException.getStackTrace:()[Ljava/lang/StackTraceElement;
      37: astore        5
      39: aload         4
      41: aload         5
      43: iconst_1
      44: aload         5
      46: arraylength
      47: invokestatic  #11                 // Method java/util/Arrays.copyOfRange:([Ljava/lang/Object;II)[Ljava/lang/Object;
      50: checkcast     #12                 // class "[Ljava/lang/StackTraceElement;"
      53: invokevirtual #19                 // Method java/lang/IllegalStateException.setStackTrace:([Ljava/lang/StackTraceElement;)V
      56: aload         4
      58: areturn

  protected java.lang.String errorParsingPredicateString$str();
    Code:
       0: ldc           #108                // String UT000045: Error parsing predicated handler string %s:%n%s
       2: areturn

  public final java.lang.IllegalArgumentException errorParsingPredicateString(java.lang.String, java.lang.String);
    Code:
       0: new           #5                  // class java/lang/IllegalArgumentException
       3: dup
       4: aload_0
       5: invokevirtual #109                // Method errorParsingPredicateString$str:()Ljava/lang/String;
       8: iconst_2
       9: anewarray     #7                  // class java/lang/Object
      12: dup
      13: iconst_0
      14: aload_1
      15: aastore
      16: dup
      17: iconst_1
      18: aload_2
      19: aastore
      20: invokestatic  #8                  // Method java/lang/String.format:(Ljava/lang/String;[Ljava/lang/Object;)Ljava/lang/String;
      23: invokespecial #9                  // Method java/lang/IllegalArgumentException."<init>":(Ljava/lang/String;)V
      26: astore_3
      27: aload_3
      28: invokevirtual #10                 // Method java/lang/IllegalArgumentException.getStackTrace:()[Ljava/lang/StackTraceElement;
      31: astore        4
      33: aload_3
      34: aload         4
      36: iconst_1
      37: aload         4
      39: arraylength
      40: invokestatic  #11                 // Method java/util/Arrays.copyOfRange:([Ljava/lang/Object;II)[Ljava/lang/Object;
      43: checkcast     #12                 // class "[Ljava/lang/StackTraceElement;"
      46: invokevirtual #13                 // Method java/lang/IllegalArgumentException.setStackTrace:([Ljava/lang/StackTraceElement;)V
      49: aload_3
      50: areturn

  protected java.lang.String tooManyCookies$str();
    Code:
       0: ldc           #110                // String UT000046: The number of cookies sent exceeded the maximum of %s
       2: areturn

  public final java.lang.IllegalStateException tooManyCookies(int);
    Code:
       0: new           #15                 // class java/lang/IllegalStateException
       3: dup
       4: aload_0
       5: invokevirtual #111                // Method tooManyCookies$str:()Ljava/lang/String;
       8: iconst_1
       9: anewarray     #7                  // class java/lang/Object
      12: dup
      13: iconst_0
      14: iload_1
      15: invokestatic  #94                 // Method java/lang/Integer.valueOf:(I)Ljava/lang/Integer;
      18: aastore
      19: invokestatic  #8                  // Method java/lang/String.format:(Ljava/lang/String;[Ljava/lang/Object;)Ljava/lang/String;
      22: invokespecial #17                 // Method java/lang/IllegalStateException."<init>":(Ljava/lang/String;)V
      25: astore_2
      26: aload_2
      27: invokevirtual #18                 // Method java/lang/IllegalStateException.getStackTrace:()[Ljava/lang/StackTraceElement;
      30: astore_3
      31: aload_2
      32: aload_3
      33: iconst_1
      34: aload_3
      35: arraylength
      36: invokestatic  #11                 // Method java/util/Arrays.copyOfRange:([Ljava/lang/Object;II)[Ljava/lang/Object;
      39: checkcast     #12                 // class "[Ljava/lang/StackTraceElement;"
      42: invokevirtual #19                 // Method java/lang/IllegalStateException.setStackTrace:([Ljava/lang/StackTraceElement;)V
      45: aload_2
      46: areturn

  protected java.lang.String tooManyParameters$str();
    Code:
       0: ldc           #112                // String UT000047: The number of parameters exceeded the maximum of %s
       2: areturn

  public final java.lang.IllegalStateException tooManyParameters(int);
    Code:
       0: new           #15                 // class java/lang/IllegalStateException
       3: dup
       4: aload_0
       5: invokevirtual #113                // Method tooManyParameters$str:()Ljava/lang/String;
       8: iconst_1
       9: anewarray     #7                  // class java/lang/Object
      12: dup
      13: iconst_0
      14: iload_1
      15: invokestatic  #94                 // Method java/lang/Integer.valueOf:(I)Ljava/lang/Integer;
      18: aastore
      19: invokestatic  #8                  // Method java/lang/String.format:(Ljava/lang/String;[Ljava/lang/Object;)Ljava/lang/String;
      22: invokespecial #17                 // Method java/lang/IllegalStateException."<init>":(Ljava/lang/String;)V
      25: astore_2
      26: aload_2
      27: invokevirtual #18                 // Method java/lang/IllegalStateException.getStackTrace:()[Ljava/lang/StackTraceElement;
      30: astore_3
      31: aload_2
      32: aload_3
      33: iconst_1
      34: aload_3
      35: arraylength
      36: invokestatic  #11                 // Method java/util/Arrays.copyOfRange:([Ljava/lang/Object;II)[Ljava/lang/Object;
      39: checkcast     #12                 // class "[Ljava/lang/StackTraceElement;"
      42: invokevirtual #19                 // Method java/lang/IllegalStateException.setStackTrace:([Ljava/lang/StackTraceElement;)V
      45: aload_2
      46: areturn

  protected java.lang.String noRequestActive$str();
    Code:
       0: ldc           #114                // String UT000048: No request is currently active
       2: areturn

  public final java.lang.IllegalStateException noRequestActive();
    Code:
       0: new           #15                 // class java/lang/IllegalStateException
       3: dup
       4: aload_0
       5: invokevirtual #115                // Method noRequestActive$str:()Ljava/lang/String;
       8: iconst_0
       9: anewarray     #7                  // class java/lang/Object
      12: invokestatic  #8                  // Method java/lang/String.format:(Ljava/lang/String;[Ljava/lang/Object;)Ljava/lang/String;
      15: invokespecial #17                 // Method java/lang/IllegalStateException."<init>":(Ljava/lang/String;)V
      18: astore_1
      19: aload_1
      20: invokevirtual #18                 // Method java/lang/IllegalStateException.getStackTrace:()[Ljava/lang/StackTraceElement;
      23: astore_2
      24: aload_1
      25: aload_2
      26: iconst_1
      27: aload_2
      28: arraylength
      29: invokestatic  #11                 // Method java/util/Arrays.copyOfRange:([Ljava/lang/Object;II)[Ljava/lang/Object;
      32: checkcast     #12                 // class "[Ljava/lang/StackTraceElement;"
      35: invokevirtual #19                 // Method java/lang/IllegalStateException.setStackTrace:([Ljava/lang/StackTraceElement;)V
      38: aload_1
      39: areturn

  protected java.lang.String authMechanismOutcomeNull$str();
    Code:
       0: ldc           #116                // String UT000050: AuthenticationMechanism Outcome is null
       2: areturn

  public final java.lang.IllegalStateException authMechanismOutcomeNull();
    Code:
       0: new           #15                 // class java/lang/IllegalStateException
       3: dup
       4: aload_0
       5: invokevirtual #117                // Method authMechanismOutcomeNull$str:()Ljava/lang/String;
       8: iconst_0
       9: anewarray     #7                  // class java/lang/Object
      12: invokestatic  #8                  // Method java/lang/String.format:(Ljava/lang/String;[Ljava/lang/Object;)Ljava/lang/String;
      15: invokespecial #17                 // Method java/lang/IllegalStateException."<init>":(Ljava/lang/String;)V
      18: astore_1
      19: aload_1
      20: invokevirtual #18                 // Method java/lang/IllegalStateException.getStackTrace:()[Ljava/lang/StackTraceElement;
      23: astore_2
      24: aload_1
      25: aload_2
      26: iconst_1
      27: aload_2
      28: arraylength
      29: invokestatic  #11                 // Method java/util/Arrays.copyOfRange:([Ljava/lang/Object;II)[Ljava/lang/Object;
      32: checkcast     #12                 // class "[Ljava/lang/StackTraceElement;"
      35: invokevirtual #19                 // Method java/lang/IllegalStateException.setStackTrace:([Ljava/lang/StackTraceElement;)V
      38: aload_1
      39: areturn

  protected java.lang.String notAValidIpPattern$str();
    Code:
       0: ldc           #118                // String UT000051: Not a valid IP pattern %s
       2: areturn

  public final java.lang.IllegalArgumentException notAValidIpPattern(java.lang.String);
    Code:
       0: new           #5                  // class java/lang/IllegalArgumentException
       3: dup
       4: aload_0
       5: invokevirtual #119                // Method notAValidIpPattern$str:()Ljava/lang/String;
       8: iconst_1
       9: anewarray     #7                  // class java/lang/Object
      12: dup
      13: iconst_0
      14: aload_1
      15: aastore
      16: invokestatic  #8                  // Method java/lang/String.format:(Ljava/lang/String;[Ljava/lang/Object;)Ljava/lang/String;
      19: invokespecial #9                  // Method java/lang/IllegalArgumentException."<init>":(Ljava/lang/String;)V
      22: astore_2
      23: aload_2
      24: invokevirtual #10                 // Method java/lang/IllegalArgumentException.getStackTrace:()[Ljava/lang/StackTraceElement;
      27: astore_3
      28: aload_2
      29: aload_3
      30: iconst_1
      31: aload_3
      32: arraylength
      33: invokestatic  #11                 // Method java/util/Arrays.copyOfRange:([Ljava/lang/Object;II)[Ljava/lang/Object;
      36: checkcast     #12                 // class "[Ljava/lang/StackTraceElement;"
      39: invokevirtual #13                 // Method java/lang/IllegalArgumentException.setStackTrace:([Ljava/lang/StackTraceElement;)V
      42: aload_2
      43: areturn

  protected java.lang.String noSessionData$str();
    Code:
       0: ldc           #120                // String UT000052: Session data requested when non session based authentication in use
       2: areturn

  public final java.lang.IllegalStateException noSessionData();
    Code:
       0: new           #15                 // class java/lang/IllegalStateException
       3: dup
       4: aload_0
       5: invokevirtual #121                // Method noSessionData$str:()Ljava/lang/String;
       8: iconst_0
       9: anewarray     #7                  // class java/lang/Object
      12: invokestatic  #8                  // Method java/lang/String.format:(Ljava/lang/String;[Ljava/lang/Object;)Ljava/lang/String;
      15: invokespecial #17                 // Method java/lang/IllegalStateException."<init>":(Ljava/lang/String;)V
      18: astore_1
      19: aload_1
      20: invokevirtual #18                 // Method java/lang/IllegalStateException.getStackTrace:()[Ljava/lang/StackTraceElement;
      23: astore_2
      24: aload_1
      25: aload_2
      26: iconst_1
      27: aload_2
      28: arraylength
      29: invokestatic  #11                 // Method java/util/Arrays.copyOfRange:([Ljava/lang/Object;II)[Ljava/lang/Object;
      32: checkcast     #12                 // class "[Ljava/lang/StackTraceElement;"
      35: invokevirtual #19                 // Method java/lang/IllegalStateException.setStackTrace:([Ljava/lang/StackTraceElement;)V
      38: aload_1
      39: areturn

  protected java.lang.String listenerAlreadyRegistered$str();
    Code:
       0: ldc           #122                // String UT000053: Listener %s already registered
       2: areturn

  public final java.lang.IllegalArgumentException listenerAlreadyRegistered(java.lang.String);
    Code:
       0: new           #5                  // class java/lang/IllegalArgumentException
       3: dup
       4: aload_0
       5: invokevirtual #123                // Method listenerAlreadyRegistered$str:()Ljava/lang/String;
       8: iconst_1
       9: anewarray     #7                  // class java/lang/Object
      12: dup
      13: iconst_0
      14: aload_1
      15: aastore
      16: invokestatic  #8                  // Method java/lang/String.format:(Ljava/lang/String;[Ljava/lang/Object;)Ljava/lang/String;
      19: invokespecial #9                  // Method java/lang/IllegalArgumentException."<init>":(Ljava/lang/String;)V
      22: astore_2
      23: aload_2
      24: invokevirtual #10                 // Method java/lang/IllegalArgumentException.getStackTrace:()[Ljava/lang/StackTraceElement;
      27: astore_3
      28: aload_2
      29: aload_3
      30: iconst_1
      31: aload_3
      32: arraylength
      33: invokestatic  #11                 // Method java/util/Arrays.copyOfRange:([Ljava/lang/Object;II)[Ljava/lang/Object;
      36: checkcast     #12                 // class "[Ljava/lang/StackTraceElement;"
      39: invokevirtual #13                 // Method java/lang/IllegalArgumentException.setStackTrace:([Ljava/lang/StackTraceElement;)V
      42: aload_2
      43: areturn

  protected java.lang.String maxFileSizeExceeded$str();
    Code:
       0: ldc           #124                // String UT000054: The maximum size %s for an individual file in a multipart request was exceeded
       2: areturn

  public final java.io.IOException maxFileSizeExceeded(long);
    Code:
       0: new           #37                 // class java/io/IOException
       3: dup
       4: aload_0
       5: invokevirtual #125                // Method maxFileSizeExceeded$str:()Ljava/lang/String;
       8: iconst_1
       9: anewarray     #7                  // class java/lang/Object
      12: dup
      13: iconst_0
      14: lload_1
      15: invokestatic  #50                 // Method java/lang/Long.valueOf:(J)Ljava/lang/Long;
      18: aastore
      19: invokestatic  #8                  // Method java/lang/String.format:(Ljava/lang/String;[Ljava/lang/Object;)Ljava/lang/String;
      22: invokespecial #39                 // Method java/io/IOException."<init>":(Ljava/lang/String;)V
      25: astore_3
      26: aload_3
      27: invokevirtual #40                 // Method java/io/IOException.getStackTrace:()[Ljava/lang/StackTraceElement;
      30: astore        4
      32: aload_3
      33: aload         4
      35: iconst_1
      36: aload         4
      38: arraylength
      39: invokestatic  #11                 // Method java/util/Arrays.copyOfRange:([Ljava/lang/Object;II)[Ljava/lang/Object;
      42: checkcast     #12                 // class "[Ljava/lang/StackTraceElement;"
      45: invokevirtual #41                 // Method java/io/IOException.setStackTrace:([Ljava/lang/StackTraceElement;)V
      48: aload_3
      49: areturn

  protected java.lang.String couldNotSetAttribute$str();
    Code:
       0: ldc           #126                // String UT000055: Could not set attribute %s to %s as it is read only
       2: areturn

  public final java.lang.String couldNotSetAttribute(java.lang.String, java.lang.String);
    Code:
       0: aload_0
       1: invokevirtual #127                // Method couldNotSetAttribute$str:()Ljava/lang/String;
       4: iconst_2
       5: anewarray     #7                  // class java/lang/Object
       8: dup
       9: iconst_0
      10: aload_1
      11: aastore
      12: dup
      13: iconst_1
      14: aload_2
      15: aastore
      16: invokestatic  #8                  // Method java/lang/String.format:(Ljava/lang/String;[Ljava/lang/Object;)Ljava/lang/String;
      19: areturn

  protected java.lang.String couldNotParseUriTemplate$str();
    Code:
       0: ldc           #128                // String UT000056: Could not parse URI template %s, exception at char %s
       2: areturn

  public final java.lang.RuntimeException couldNotParseUriTemplate(java.lang.String, int);
    Code:
       0: new           #85                 // class java/lang/RuntimeException
       3: dup
       4: aload_0
       5: invokevirtual #129                // Method couldNotParseUriTemplate$str:()Ljava/lang/String;
       8: iconst_2
       9: anewarray     #7                  // class java/lang/Object
      12: dup
      13: iconst_0
      14: aload_1
      15: aastore
      16: dup
      17: iconst_1
      18: iload_2
      19: invokestatic  #94                 // Method java/lang/Integer.valueOf:(I)Ljava/lang/Integer;
      22: aastore
      23: invokestatic  #8                  // Method java/lang/String.format:(Ljava/lang/String;[Ljava/lang/Object;)Ljava/lang/String;
      26: invokespecial #87                 // Method java/lang/RuntimeException."<init>":(Ljava/lang/String;)V
      29: astore_3
      30: aload_3
      31: invokevirtual #88                 // Method java/lang/RuntimeException.getStackTrace:()[Ljava/lang/StackTraceElement;
      34: astore        4
      36: aload_3
      37: aload         4
      39: iconst_1
      40: aload         4
      42: arraylength
      43: invokestatic  #11                 // Method java/util/Arrays.copyOfRange:([Ljava/lang/Object;II)[Ljava/lang/Object;
      46: checkcast     #12                 // class "[Ljava/lang/StackTraceElement;"
      49: invokevirtual #89                 // Method java/lang/RuntimeException.setStackTrace:([Ljava/lang/StackTraceElement;)V
      52: aload_3
      53: areturn

  protected java.lang.String mismatchedBraces$str();
    Code:
       0: ldc           #130                // String UT000057: Mismatched braces in attribute string %s
       2: areturn

  public final java.lang.RuntimeException mismatchedBraces(java.lang.String);
    Code:
       0: new           #85                 // class java/lang/RuntimeException
       3: dup
       4: aload_0
       5: invokevirtual #131                // Method mismatchedBraces$str:()Ljava/lang/String;
       8: iconst_1
       9: anewarray     #7                  // class java/lang/Object
      12: dup
      13: iconst_0
      14: aload_1
      15: aastore
      16: invokestatic  #8                  // Method java/lang/String.format:(Ljava/lang/String;[Ljava/lang/Object;)Ljava/lang/String;
      19: invokespecial #87                 // Method java/lang/RuntimeException."<init>":(Ljava/lang/String;)V
      22: astore_2
      23: aload_2
      24: invokevirtual #88                 // Method java/lang/RuntimeException.getStackTrace:()[Ljava/lang/StackTraceElement;
      27: astore_3
      28: aload_2
      29: aload_3
      30: iconst_1
      31: aload_3
      32: arraylength
      33: invokestatic  #11                 // Method java/util/Arrays.copyOfRange:([Ljava/lang/Object;II)[Ljava/lang/Object;
      36: checkcast     #12                 // class "[Ljava/lang/StackTraceElement;"
      39: invokevirtual #89                 // Method java/lang/RuntimeException.setStackTrace:([Ljava/lang/StackTraceElement;)V
      42: aload_2
      43: areturn

  protected java.lang.String moreThanOneHandlerWithName$str();
    Code:
       0: ldc           #132                // String UT000058: More than one handler with name %s. Builder class %s and %s
       2: areturn

  public final java.lang.IllegalStateException moreThanOneHandlerWithName(java.lang.String, java.lang.Class<? extends io.undertow.server.handlers.builder.HandlerBuilder>, java.lang.Class<? extends io.undertow.server.handlers.builder.HandlerBuilder>);
    Code:
       0: new           #15                 // class java/lang/IllegalStateException
       3: dup
       4: aload_0
       5: invokevirtual #133                // Method moreThanOneHandlerWithName$str:()Ljava/lang/String;
       8: iconst_3
       9: anewarray     #7                  // class java/lang/Object
      12: dup
      13: iconst_0
      14: aload_1
      15: aastore
      16: dup
      17: iconst_1
      18: aload_2
      19: aastore
      20: dup
      21: iconst_2
      22: aload_3
      23: aastore
      24: invokestatic  #8                  // Method java/lang/String.format:(Ljava/lang/String;[Ljava/lang/Object;)Ljava/lang/String;
      27: invokespecial #17                 // Method java/lang/IllegalStateException."<init>":(Ljava/lang/String;)V
      30: astore        4
      32: aload         4
      34: invokevirtual #18                 // Method java/lang/IllegalStateException.getStackTrace:()[Ljava/lang/StackTraceElement;
      37: astore        5
      39: aload         4
      41: aload         5
      43: iconst_1
      44: aload         5
      46: arraylength
      47: invokestatic  #11                 // Method java/util/Arrays.copyOfRange:([Ljava/lang/Object;II)[Ljava/lang/Object;
      50: checkcast     #12                 // class "[Ljava/lang/StackTraceElement;"
      53: invokevirtual #19                 // Method java/lang/IllegalStateException.setStackTrace:([Ljava/lang/StackTraceElement;)V
      56: aload         4
      58: areturn

  protected java.lang.String invalidSyntax$str();
    Code:
       0: ldc           #134                // String UT000059: Invalid syntax %s
       2: areturn

  public final java.lang.IllegalArgumentException invalidSyntax(java.lang.String);
    Code:
       0: new           #5                  // class java/lang/IllegalArgumentException
       3: dup
       4: aload_0
       5: invokevirtual #135                // Method invalidSyntax$str:()Ljava/lang/String;
       8: iconst_1
       9: anewarray     #7                  // class java/lang/Object
      12: dup
      13: iconst_0
      14: aload_1
      15: aastore
      16: invokestatic  #8                  // Method java/lang/String.format:(Ljava/lang/String;[Ljava/lang/Object;)Ljava/lang/String;
      19: invokespecial #9                  // Method java/lang/IllegalArgumentException."<init>":(Ljava/lang/String;)V
      22: astore_2
      23: aload_2
      24: invokevirtual #10                 // Method java/lang/IllegalArgumentException.getStackTrace:()[Ljava/lang/StackTraceElement;
      27: astore_3
      28: aload_2
      29: aload_3
      30: iconst_1
      31: aload_3
      32: arraylength
      33: invokestatic  #11                 // Method java/util/Arrays.copyOfRange:([Ljava/lang/Object;II)[Ljava/lang/Object;
      36: checkcast     #12                 // class "[Ljava/lang/StackTraceElement;"
      39: invokevirtual #13                 // Method java/lang/IllegalArgumentException.setStackTrace:([Ljava/lang/StackTraceElement;)V
      42: aload_2
      43: areturn

  protected java.lang.String errorParsingHandlerString$str();
    Code:
       0: ldc           #136                // String UT000060: Error parsing handler string %s:%n%s
       2: areturn

  public final java.lang.IllegalArgumentException errorParsingHandlerString(java.lang.String, java.lang.String);
    Code:
       0: new           #5                  // class java/lang/IllegalArgumentException
       3: dup
       4: aload_0
       5: invokevirtual #137                // Method errorParsingHandlerString$str:()Ljava/lang/String;
       8: iconst_2
       9: anewarray     #7                  // class java/lang/Object
      12: dup
      13: iconst_0
      14: aload_1
      15: aastore
      16: dup
      17: iconst_1
      18: aload_2
      19: aastore
      20: invokestatic  #8                  // Method java/lang/String.format:(Ljava/lang/String;[Ljava/lang/Object;)Ljava/lang/String;
      23: invokespecial #9                  // Method java/lang/IllegalArgumentException."<init>":(Ljava/lang/String;)V
      26: astore_3
      27: aload_3
      28: invokevirtual #10                 // Method java/lang/IllegalArgumentException.getStackTrace:()[Ljava/lang/StackTraceElement;
      31: astore        4
      33: aload_3
      34: aload         4
      36: iconst_1
      37: aload         4
      39: arraylength
      40: invokestatic  #11                 // Method java/util/Arrays.copyOfRange:([Ljava/lang/Object;II)[Ljava/lang/Object;
      43: checkcast     #12                 // class "[Ljava/lang/StackTraceElement;"
      46: invokevirtual #13                 // Method java/lang/IllegalArgumentException.setStackTrace:([Ljava/lang/StackTraceElement;)V
      49: aload_3
      50: areturn

  protected java.lang.String outOfBandResponseOnlyAllowedFor100Continue$str();
    Code:
       0: ldc           #138                // String UT000061: Out of band responses only allowed for 100-continue requests
       2: areturn

  public final java.lang.IllegalArgumentException outOfBandResponseOnlyAllowedFor100Continue();
    Code:
       0: new           #5                  // class java/lang/IllegalArgumentException
       3: dup
       4: aload_0
       5: invokevirtual #139                // Method outOfBandResponseOnlyAllowedFor100Continue$str:()Ljava/lang/String;
       8: iconst_0
       9: anewarray     #7                  // class java/lang/Object
      12: invokestatic  #8                  // Method java/lang/String.format:(Ljava/lang/String;[Ljava/lang/Object;)Ljava/lang/String;
      15: invokespecial #9                  // Method java/lang/IllegalArgumentException."<init>":(Ljava/lang/String;)V
      18: astore_1
      19: aload_1
      20: invokevirtual #10                 // Method java/lang/IllegalArgumentException.getStackTrace:()[Ljava/lang/StackTraceElement;
      23: astore_2
      24: aload_1
      25: aload_2
      26: iconst_1
      27: aload_2
      28: arraylength
      29: invokestatic  #11                 // Method java/util/Arrays.copyOfRange:([Ljava/lang/Object;II)[Ljava/lang/Object;
      32: checkcast     #12                 // class "[Ljava/lang/StackTraceElement;"
      35: invokevirtual #13                 // Method java/lang/IllegalArgumentException.setStackTrace:([Ljava/lang/StackTraceElement;)V
      38: aload_1
      39: areturn

  protected java.lang.String ajpDoesNotSupportHTTPUpgrade$str();
    Code:
       0: ldc           #140                // String UT000062: AJP does not support HTTP upgrade
       2: areturn

  public final java.lang.IllegalStateException ajpDoesNotSupportHTTPUpgrade();
    Code:
       0: new           #15                 // class java/lang/IllegalStateException
       3: dup
       4: aload_0
       5: invokevirtual #141                // Method ajpDoesNotSupportHTTPUpgrade$str:()Ljava/lang/String;
       8: iconst_0
       9: anewarray     #7                  // class java/lang/Object
      12: invokestatic  #8                  // Method java/lang/String.format:(Ljava/lang/String;[Ljava/lang/Object;)Ljava/lang/String;
      15: invokespecial #17                 // Method java/lang/IllegalStateException."<init>":(Ljava/lang/String;)V
      18: astore_1
      19: aload_1
      20: invokevirtual #18                 // Method java/lang/IllegalStateException.getStackTrace:()[Ljava/lang/StackTraceElement;
      23: astore_2
      24: aload_1
      25: aload_2
      26: iconst_1
      27: aload_2
      28: arraylength
      29: invokestatic  #11                 // Method java/util/Arrays.copyOfRange:([Ljava/lang/Object;II)[Ljava/lang/Object;
      32: checkcast     #12                 // class "[Ljava/lang/StackTraceElement;"
      35: invokevirtual #19                 // Method java/lang/IllegalStateException.setStackTrace:([Ljava/lang/StackTraceElement;)V
      38: aload_1
      39: areturn

  protected java.lang.String fileSystemWatcherAlreadyStarted$str();
    Code:
       0: ldc           #142                // String UT000063: File system watcher already started
       2: areturn

  public final java.lang.IllegalStateException fileSystemWatcherAlreadyStarted();
    Code:
       0: new           #15                 // class java/lang/IllegalStateException
       3: dup
       4: aload_0
       5: invokevirtual #143                // Method fileSystemWatcherAlreadyStarted$str:()Ljava/lang/String;
       8: iconst_0
       9: anewarray     #7                  // class java/lang/Object
      12: invokestatic  #8                  // Method java/lang/String.format:(Ljava/lang/String;[Ljava/lang/Object;)Ljava/lang/String;
      15: invokespecial #17                 // Method java/lang/IllegalStateException."<init>":(Ljava/lang/String;)V
      18: astore_1
      19: aload_1
      20: invokevirtual #18                 // Method java/lang/IllegalStateException.getStackTrace:()[Ljava/lang/StackTraceElement;
      23: astore_2
      24: aload_1
      25: aload_2
      26: iconst_1
      27: aload_2
      28: arraylength
      29: invokestatic  #11                 // Method java/util/Arrays.copyOfRange:([Ljava/lang/Object;II)[Ljava/lang/Object;
      32: checkcast     #12                 // class "[Ljava/lang/StackTraceElement;"
      35: invokevirtual #19                 // Method java/lang/IllegalStateException.setStackTrace:([Ljava/lang/StackTraceElement;)V
      38: aload_1
      39: areturn

  protected java.lang.String fileSystemWatcherNotStarted$str();
    Code:
       0: ldc           #144                // String UT000064: File system watcher not started
       2: areturn

  public final java.lang.IllegalStateException fileSystemWatcherNotStarted();
    Code:
       0: new           #15                 // class java/lang/IllegalStateException
       3: dup
       4: aload_0
       5: invokevirtual #145                // Method fileSystemWatcherNotStarted$str:()Ljava/lang/String;
       8: iconst_0
       9: anewarray     #7                  // class java/lang/Object
      12: invokestatic  #8                  // Method java/lang/String.format:(Ljava/lang/String;[Ljava/lang/Object;)Ljava/lang/String;
      15: invokespecial #17                 // Method java/lang/IllegalStateException."<init>":(Ljava/lang/String;)V
      18: astore_1
      19: aload_1
      20: invokevirtual #18                 // Method java/lang/IllegalStateException.getStackTrace:()[Ljava/lang/StackTraceElement;
      23: astore_2
      24: aload_1
      25: aload_2
      26: iconst_1
      27: aload_2
      28: arraylength
      29: invokestatic  #11                 // Method java/util/Arrays.copyOfRange:([Ljava/lang/Object;II)[Ljava/lang/Object;
      32: checkcast     #12                 // class "[Ljava/lang/StackTraceElement;"
      35: invokevirtual #19                 // Method java/lang/IllegalStateException.setStackTrace:([Ljava/lang/StackTraceElement;)V
      38: aload_1
      39: areturn

  protected java.lang.String sslWasNull$str();
    Code:
       0: ldc           #146                // String UT000065: SSL must be specified to connect to a https URL
       2: areturn

  public final java.io.IOException sslWasNull();
    Code:
       0: new           #37                 // class java/io/IOException
       3: dup
       4: aload_0
       5: invokevirtual #147                // Method sslWasNull$str:()Ljava/lang/String;
       8: iconst_0
       9: anewarray     #7                  // class java/lang/Object
      12: invokestatic  #8                  // Method java/lang/String.format:(Ljava/lang/String;[Ljava/lang/Object;)Ljava/lang/String;
      15: invokespecial #39                 // Method java/io/IOException."<init>":(Ljava/lang/String;)V
      18: astore_1
      19: aload_1
      20: invokevirtual #40                 // Method java/io/IOException.getStackTrace:()[Ljava/lang/StackTraceElement;
      23: astore_2
      24: aload_1
      25: aload_2
      26: iconst_1
      27: aload_2
      28: arraylength
      29: invokestatic  #11                 // Method java/util/Arrays.copyOfRange:([Ljava/lang/Object;II)[Ljava/lang/Object;
      32: checkcast     #12                 // class "[Ljava/lang/StackTraceElement;"
      35: invokevirtual #41                 // Method java/io/IOException.setStackTrace:([Ljava/lang/StackTraceElement;)V
      38: aload_1
      39: areturn

  protected java.lang.String wrongMagicNumber$str();
    Code:
       0: ldc           #148                // String UT000066: Incorrect magic number %s for AJP packet header
       2: areturn

  public final java.io.IOException wrongMagicNumber(int);
    Code:
       0: new           #37                 // class java/io/IOException
       3: dup
       4: aload_0
       5: invokevirtual #149                // Method wrongMagicNumber$str:()Ljava/lang/String;
       8: iconst_1
       9: anewarray     #7                  // class java/lang/Object
      12: dup
      13: iconst_0
      14: iload_1
      15: invokestatic  #94                 // Method java/lang/Integer.valueOf:(I)Ljava/lang/Integer;
      18: aastore
      19: invokestatic  #8                  // Method java/lang/String.format:(Ljava/lang/String;[Ljava/lang/Object;)Ljava/lang/String;
      22: invokespecial #39                 // Method java/io/IOException."<init>":(Ljava/lang/String;)V
      25: astore_2
      26: aload_2
      27: invokevirtual #40                 // Method java/io/IOException.getStackTrace:()[Ljava/lang/StackTraceElement;
      30: astore_3
      31: aload_2
      32: aload_3
      33: iconst_1
      34: aload_3
      35: arraylength
      36: invokestatic  #11                 // Method java/util/Arrays.copyOfRange:([Ljava/lang/Object;II)[Ljava/lang/Object;
      39: checkcast     #12                 // class "[Ljava/lang/StackTraceElement;"
      42: invokevirtual #41                 // Method java/io/IOException.setStackTrace:([Ljava/lang/StackTraceElement;)V
      45: aload_2
      46: areturn

  protected java.lang.String peerUnverified$str();
    Code:
       0: ldc           #150                // String UT000067: No client cert was provided
       2: areturn

  public final javax.net.ssl.SSLPeerUnverifiedException peerUnverified();
    Code:
       0: new           #151                // class javax/net/ssl/SSLPeerUnverifiedException
       3: dup
       4: aload_0
       5: invokevirtual #152                // Method peerUnverified$str:()Ljava/lang/String;
       8: iconst_0
       9: anewarray     #7                  // class java/lang/Object
      12: invokestatic  #8                  // Method java/lang/String.format:(Ljava/lang/String;[Ljava/lang/Object;)Ljava/lang/String;
      15: invokespecial #153                // Method javax/net/ssl/SSLPeerUnverifiedException."<init>":(Ljava/lang/String;)V
      18: astore_1
      19: aload_1
      20: invokevirtual #154                // Method javax/net/ssl/SSLPeerUnverifiedException.getStackTrace:()[Ljava/lang/StackTraceElement;
      23: astore_2
      24: aload_1
      25: aload_2
      26: iconst_1
      27: aload_2
      28: arraylength
      29: invokestatic  #11                 // Method java/util/Arrays.copyOfRange:([Ljava/lang/Object;II)[Ljava/lang/Object;
      32: checkcast     #12                 // class "[Ljava/lang/StackTraceElement;"
      35: invokevirtual #155                // Method javax/net/ssl/SSLPeerUnverifiedException.setStackTrace:([Ljava/lang/StackTraceElement;)V
      38: aload_1
      39: areturn

  protected java.lang.String servletPathMatchFailed$str();
    Code:
       0: ldc           #156                // String UT000068: Servlet path match failed
       2: areturn

  public final java.lang.IllegalArgumentException servletPathMatchFailed();
    Code:
       0: new           #5                  // class java/lang/IllegalArgumentException
       3: dup
       4: aload_0
       5: invokevirtual #157                // Method servletPathMatchFailed$str:()Ljava/lang/String;
       8: iconst_0
       9: anewarray     #7                  // class java/lang/Object
      12: invokestatic  #8                  // Method java/lang/String.format:(Ljava/lang/String;[Ljava/lang/Object;)Ljava/lang/String;
      15: invokespecial #9                  // Method java/lang/IllegalArgumentException."<init>":(Ljava/lang/String;)V
      18: astore_1
      19: aload_1
      20: invokevirtual #10                 // Method java/lang/IllegalArgumentException.getStackTrace:()[Ljava/lang/StackTraceElement;
      23: astore_2
      24: aload_1
      25: aload_2
      26: iconst_1
      27: aload_2
      28: arraylength
      29: invokestatic  #11                 // Method java/util/Arrays.copyOfRange:([Ljava/lang/Object;II)[Ljava/lang/Object;
      32: checkcast     #12                 // class "[Ljava/lang/StackTraceElement;"
      35: invokevirtual #13                 // Method java/lang/IllegalArgumentException.setStackTrace:([Ljava/lang/StackTraceElement;)V
      38: aload_1
      39: areturn

  protected java.lang.String couldNotParseCookie$str();
    Code:
       0: ldc           #158                // String UT000069: Could not parse set cookie header %s
       2: areturn

  public final java.lang.IllegalArgumentException couldNotParseCookie(java.lang.String);
    Code:
       0: new           #5                  // class java/lang/IllegalArgumentException
       3: dup
       4: aload_0
       5: invokevirtual #159                // Method couldNotParseCookie$str:()Ljava/lang/String;
       8: iconst_1
       9: anewarray     #7                  // class java/lang/Object
      12: dup
      13: iconst_0
      14: aload_1
      15: aastore
      16: invokestatic  #8                  // Method java/lang/String.format:(Ljava/lang/String;[Ljava/lang/Object;)Ljava/lang/String;
      19: invokespecial #9                  // Method java/lang/IllegalArgumentException."<init>":(Ljava/lang/String;)V
      22: astore_2
      23: aload_2
      24: invokevirtual #10                 // Method java/lang/IllegalArgumentException.getStackTrace:()[Ljava/lang/StackTraceElement;
      27: astore_3
      28: aload_2
      29: aload_3
      30: iconst_1
      31: aload_3
      32: arraylength
      33: invokestatic  #11                 // Method java/util/Arrays.copyOfRange:([Ljava/lang/Object;II)[Ljava/lang/Object;
      36: checkcast     #12                 // class "[Ljava/lang/StackTraceElement;"
      39: invokevirtual #13                 // Method java/lang/IllegalArgumentException.setStackTrace:([Ljava/lang/StackTraceElement;)V
      42: aload_2
      43: areturn

  protected java.lang.String canOnlyBeCalledByIoThread$str();
    Code:
       0: ldc           #160                // String UT000070: method can only be called by IO thread
       2: areturn

  public final java.lang.IllegalStateException canOnlyBeCalledByIoThread();
    Code:
       0: new           #15                 // class java/lang/IllegalStateException
       3: dup
       4: aload_0
       5: invokevirtual #161                // Method canOnlyBeCalledByIoThread$str:()Ljava/lang/String;
       8: iconst_0
       9: anewarray     #7                  // class java/lang/Object
      12: invokestatic  #8                  // Method java/lang/String.format:(Ljava/lang/String;[Ljava/lang/Object;)Ljava/lang/String;
      15: invokespecial #17                 // Method java/lang/IllegalStateException."<init>":(Ljava/lang/String;)V
      18: astore_1
      19: aload_1
      20: invokevirtual #18                 // Method java/lang/IllegalStateException.getStackTrace:()[Ljava/lang/StackTraceElement;
      23: astore_2
      24: aload_1
      25: aload_2
      26: iconst_1
      27: aload_2
      28: arraylength
      29: invokestatic  #11                 // Method java/util/Arrays.copyOfRange:([Ljava/lang/Object;II)[Ljava/lang/Object;
      32: checkcast     #12                 // class "[Ljava/lang/StackTraceElement;"
      35: invokevirtual #19                 // Method java/lang/IllegalStateException.setStackTrace:([Ljava/lang/StackTraceElement;)V
      38: aload_1
      39: areturn

  protected java.lang.String matcherAlreadyContainsTemplate$str();
    Code:
       0: ldc           #162                // String UT000071: Cannot add path template %s, matcher already contains an equivalent pattern %s
       2: areturn

  public final java.lang.IllegalStateException matcherAlreadyContainsTemplate(java.lang.String, java.lang.String);
    Code:
       0: new           #15                 // class java/lang/IllegalStateException
       3: dup
       4: aload_0
       5: invokevirtual #163                // Method matcherAlreadyContainsTemplate$str:()Ljava/lang/String;
       8: iconst_2
       9: anewarray     #7                  // class java/lang/Object
      12: dup
      13: iconst_0
      14: aload_1
      15: aastore
      16: dup
      17: iconst_1
      18: aload_2
      19: aastore
      20: invokestatic  #8                  // Method java/lang/String.format:(Ljava/lang/String;[Ljava/lang/Object;)Ljava/lang/String;
      23: invokespecial #17                 // Method java/lang/IllegalStateException."<init>":(Ljava/lang/String;)V
      26: astore_3
      27: aload_3
      28: invokevirtual #18                 // Method java/lang/IllegalStateException.getStackTrace:()[Ljava/lang/StackTraceElement;
      31: astore        4
      33: aload_3
      34: aload         4
      36: iconst_1
      37: aload         4
      39: arraylength
      40: invokestatic  #11                 // Method java/util/Arrays.copyOfRange:([Ljava/lang/Object;II)[Ljava/lang/Object;
      43: checkcast     #12                 // class "[Ljava/lang/StackTraceElement;"
      46: invokevirtual #19                 // Method java/lang/IllegalStateException.setStackTrace:([Ljava/lang/StackTraceElement;)V
      49: aload_3
      50: areturn

  protected java.lang.String failedToDecodeURL$str();
    Code:
       0: ldc           #164                // String UT000072: Failed to decode url %s to charset %s
       2: areturn

  public final java.lang.IllegalArgumentException failedToDecodeURL(java.lang.String, java.lang.String, java.lang.Exception);
    Code:
       0: new           #5                  // class java/lang/IllegalArgumentException
       3: dup
       4: aload_0
       5: invokevirtual #165                // Method failedToDecodeURL$str:()Ljava/lang/String;
       8: iconst_2
       9: anewarray     #7                  // class java/lang/Object
      12: dup
      13: iconst_0
      14: aload_1
      15: aastore
      16: dup
      17: iconst_1
      18: aload_2
      19: aastore
      20: invokestatic  #8                  // Method java/lang/String.format:(Ljava/lang/String;[Ljava/lang/Object;)Ljava/lang/String;
      23: aload_3
      24: invokespecial #59                 // Method java/lang/IllegalArgumentException."<init>":(Ljava/lang/String;Ljava/lang/Throwable;)V
      27: astore        4
      29: aload         4
      31: invokevirtual #10                 // Method java/lang/IllegalArgumentException.getStackTrace:()[Ljava/lang/StackTraceElement;
      34: astore        5
      36: aload         4
      38: aload         5
      40: iconst_1
      41: aload         5
      43: arraylength
      44: invokestatic  #11                 // Method java/util/Arrays.copyOfRange:([Ljava/lang/Object;II)[Ljava/lang/Object;
      47: checkcast     #12                 // class "[Ljava/lang/StackTraceElement;"
      50: invokevirtual #13                 // Method java/lang/IllegalArgumentException.setStackTrace:([Ljava/lang/StackTraceElement;)V
      53: aload         4
      55: areturn

  protected java.lang.String resourceChangeListenerNotSupported$str();
    Code:
       0: ldc           #166                // String UT000073: Resource change listeners are not supported
       2: areturn

  public final java.lang.IllegalArgumentException resourceChangeListenerNotSupported();
    Code:
       0: new           #5                  // class java/lang/IllegalArgumentException
       3: dup
       4: aload_0
       5: invokevirtual #167                // Method resourceChangeListenerNotSupported$str:()Ljava/lang/String;
       8: iconst_0
       9: anewarray     #7                  // class java/lang/Object
      12: invokestatic  #8                  // Method java/lang/String.format:(Ljava/lang/String;[Ljava/lang/Object;)Ljava/lang/String;
      15: invokespecial #9                  // Method java/lang/IllegalArgumentException."<init>":(Ljava/lang/String;)V
      18: astore_1
      19: aload_1
      20: invokevirtual #10                 // Method java/lang/IllegalArgumentException.getStackTrace:()[Ljava/lang/StackTraceElement;
      23: astore_2
      24: aload_1
      25: aload_2
      26: iconst_1
      27: aload_2
      28: arraylength
      29: invokestatic  #11                 // Method java/util/Arrays.copyOfRange:([Ljava/lang/Object;II)[Ljava/lang/Object;
      32: checkcast     #12                 // class "[Ljava/lang/StackTraceElement;"
      35: invokevirtual #13                 // Method java/lang/IllegalArgumentException.setStackTrace:([Ljava/lang/StackTraceElement;)V
      38: aload_1
      39: areturn

  protected java.lang.String couldNotRenegotiate$str();
    Code:
       0: ldc           #168                // String UT000074: Could not renegotiate SSL connection to require client certificate, as client had sent more data
       2: areturn

  public final java.lang.IllegalStateException couldNotRenegotiate();
    Code:
       0: new           #15                 // class java/lang/IllegalStateException
       3: dup
       4: aload_0
       5: invokevirtual #169                // Method couldNotRenegotiate$str:()Ljava/lang/String;
       8: iconst_0
       9: anewarray     #7                  // class java/lang/Object
      12: invokestatic  #8                  // Method java/lang/String.format:(Ljava/lang/String;[Ljava/lang/Object;)Ljava/lang/String;
      15: invokespecial #17                 // Method java/lang/IllegalStateException."<init>":(Ljava/lang/String;)V
      18: astore_1
      19: aload_1
      20: invokevirtual #18                 // Method java/lang/IllegalStateException.getStackTrace:()[Ljava/lang/StackTraceElement;
      23: astore_2
      24: aload_1
      25: aload_2
      26: iconst_1
      27: aload_2
      28: arraylength
      29: invokestatic  #11                 // Method java/util/Arrays.copyOfRange:([Ljava/lang/Object;II)[Ljava/lang/Object;
      32: checkcast     #12                 // class "[Ljava/lang/StackTraceElement;"
      35: invokevirtual #19                 // Method java/lang/IllegalStateException.setStackTrace:([Ljava/lang/StackTraceElement;)V
      38: aload_1
      39: areturn

  protected java.lang.String objectWasFreed$str();
    Code:
       0: ldc           #170                // String UT000075: Object was freed
       2: areturn

  public final java.lang.IllegalStateException objectWasFreed();
    Code:
       0: new           #15                 // class java/lang/IllegalStateException
       3: dup
       4: aload_0
       5: invokevirtual #171                // Method objectWasFreed$str:()Ljava/lang/String;
       8: iconst_0
       9: anewarray     #7                  // class java/lang/Object
      12: invokestatic  #8                  // Method java/lang/String.format:(Ljava/lang/String;[Ljava/lang/Object;)Ljava/lang/String;
      15: invokespecial #17                 // Method java/lang/IllegalStateException."<init>":(Ljava/lang/String;)V
      18: astore_1
      19: aload_1
      20: invokevirtual #18                 // Method java/lang/IllegalStateException.getStackTrace:()[Ljava/lang/StackTraceElement;
      23: astore_2
      24: aload_1
      25: aload_2
      26: iconst_1
      27: aload_2
      28: arraylength
      29: invokestatic  #11                 // Method java/util/Arrays.copyOfRange:([Ljava/lang/Object;II)[Ljava/lang/Object;
      32: checkcast     #12                 // class "[Ljava/lang/StackTraceElement;"
      35: invokevirtual #19                 // Method java/lang/IllegalStateException.setStackTrace:([Ljava/lang/StackTraceElement;)V
      38: aload_1
      39: areturn

  protected java.lang.String handlerNotShutdown$str();
    Code:
       0: ldc           #172                // String UT000076: Handler not shutdown
       2: areturn

  public final java.lang.IllegalStateException handlerNotShutdown();
    Code:
       0: new           #15                 // class java/lang/IllegalStateException
       3: dup
       4: aload_0
       5: invokevirtual #173                // Method handlerNotShutdown$str:()Ljava/lang/String;
       8: iconst_0
       9: anewarray     #7                  // class java/lang/Object
      12: invokestatic  #8                  // Method java/lang/String.format:(Ljava/lang/String;[Ljava/lang/Object;)Ljava/lang/String;
      15: invokespecial #17                 // Method java/lang/IllegalStateException."<init>":(Ljava/lang/String;)V
      18: astore_1
      19: aload_1
      20: invokevirtual #18                 // Method java/lang/IllegalStateException.getStackTrace:()[Ljava/lang/StackTraceElement;
      23: astore_2
      24: aload_1
      25: aload_2
      26: iconst_1
      27: aload_2
      28: arraylength
      29: invokestatic  #11                 // Method java/util/Arrays.copyOfRange:([Ljava/lang/Object;II)[Ljava/lang/Object;
      32: checkcast     #12                 // class "[Ljava/lang/StackTraceElement;"
      35: invokevirtual #19                 // Method java/lang/IllegalStateException.setStackTrace:([Ljava/lang/StackTraceElement;)V
      38: aload_1
      39: areturn

  protected java.lang.String upgradeNotSupported$str();
    Code:
       0: ldc           #174                // String UT000077: The underlying transport does not support HTTP upgrade
       2: areturn

  public final java.lang.IllegalStateException upgradeNotSupported();
    Code:
       0: new           #15                 // class java/lang/IllegalStateException
       3: dup
       4: aload_0
       5: invokevirtual #175                // Method upgradeNotSupported$str:()Ljava/lang/String;
       8: iconst_0
       9: anewarray     #7                  // class java/lang/Object
      12: invokestatic  #8                  // Method java/lang/String.format:(Ljava/lang/String;[Ljava/lang/Object;)Ljava/lang/String;
      15: invokespecial #17                 // Method java/lang/IllegalStateException."<init>":(Ljava/lang/String;)V
      18: astore_1
      19: aload_1
      20: invokevirtual #18                 // Method java/lang/IllegalStateException.getStackTrace:()[Ljava/lang/StackTraceElement;
      23: astore_2
      24: aload_1
      25: aload_2
      26: iconst_1
      27: aload_2
      28: arraylength
      29: invokestatic  #11                 // Method java/util/Arrays.copyOfRange:([Ljava/lang/Object;II)[Ljava/lang/Object;
      32: checkcast     #12                 // class "[Ljava/lang/StackTraceElement;"
      35: invokevirtual #19                 // Method java/lang/IllegalStateException.setStackTrace:([Ljava/lang/StackTraceElement;)V
      38: aload_1
      39: areturn

  protected java.lang.String renegotiationNotSupported$str();
    Code:
       0: ldc           #176                // String UT000078: Renegotiation not supported
       2: areturn

  public final java.io.IOException renegotiationNotSupported();
    Code:
       0: new           #37                 // class java/io/IOException
       3: dup
       4: aload_0
       5: invokevirtual #177                // Method renegotiationNotSupported$str:()Ljava/lang/String;
       8: iconst_0
       9: anewarray     #7                  // class java/lang/Object
      12: invokestatic  #8                  // Method java/lang/String.format:(Ljava/lang/String;[Ljava/lang/Object;)Ljava/lang/String;
      15: invokespecial #39                 // Method java/io/IOException."<init>":(Ljava/lang/String;)V
      18: astore_1
      19: aload_1
      20: invokevirtual #40                 // Method java/io/IOException.getStackTrace:()[Ljava/lang/StackTraceElement;
      23: astore_2
      24: aload_1
      25: aload_2
      26: iconst_1
      27: aload_2
      28: arraylength
      29: invokestatic  #11                 // Method java/util/Arrays.copyOfRange:([Ljava/lang/Object;II)[Ljava/lang/Object;
      32: checkcast     #12                 // class "[Ljava/lang/StackTraceElement;"
      35: invokevirtual #41                 // Method java/io/IOException.setStackTrace:([Ljava/lang/StackTraceElement;)V
      38: aload_1
      39: areturn

  protected java.lang.String notAValidUserAgentPattern$str();
    Code:
       0: ldc           #178                // String UT000079: Not a valid user agent pattern %s
       2: areturn

  public final java.lang.IllegalArgumentException notAValidUserAgentPattern(java.lang.String);
    Code:
       0: new           #5                  // class java/lang/IllegalArgumentException
       3: dup
       4: aload_0
       5: invokevirtual #179                // Method notAValidUserAgentPattern$str:()Ljava/lang/String;
       8: iconst_1
       9: anewarray     #7                  // class java/lang/Object
      12: dup
      13: iconst_0
      14: aload_1
      15: aastore
      16: invokestatic  #8                  // Method java/lang/String.format:(Ljava/lang/String;[Ljava/lang/Object;)Ljava/lang/String;
      19: invokespecial #9                  // Method java/lang/IllegalArgumentException."<init>":(Ljava/lang/String;)V
      22: astore_2
      23: aload_2
      24: invokevirtual #10                 // Method java/lang/IllegalArgumentException.getStackTrace:()[Ljava/lang/StackTraceElement;
      27: astore_3
      28: aload_2
      29: aload_3
      30: iconst_1
      31: aload_3
      32: arraylength
      33: invokestatic  #11                 // Method java/util/Arrays.copyOfRange:([Ljava/lang/Object;II)[Ljava/lang/Object;
      36: checkcast     #12                 // class "[Ljava/lang/StackTraceElement;"
      39: invokevirtual #13                 // Method java/lang/IllegalArgumentException.setStackTrace:([Ljava/lang/StackTraceElement;)V
      42: aload_2
      43: areturn

  protected java.lang.String notAValidRegularExpressionPattern$str();
    Code:
       0: ldc           #180                // String UT000080: Not a valid regular expression pattern %s
       2: areturn

  public final java.lang.IllegalArgumentException notAValidRegularExpressionPattern(java.lang.String);
    Code:
       0: new           #5                  // class java/lang/IllegalArgumentException
       3: dup
       4: aload_0
       5: invokevirtual #181                // Method notAValidRegularExpressionPattern$str:()Ljava/lang/String;
       8: iconst_1
       9: anewarray     #7                  // class java/lang/Object
      12: dup
      13: iconst_0
      14: aload_1
      15: aastore
      16: invokestatic  #8                  // Method java/lang/String.format:(Ljava/lang/String;[Ljava/lang/Object;)Ljava/lang/String;
      19: invokespecial #9                  // Method java/lang/IllegalArgumentException."<init>":(Ljava/lang/String;)V
      22: astore_2
      23: aload_2
      24: invokevirtual #10                 // Method java/lang/IllegalArgumentException.getStackTrace:()[Ljava/lang/StackTraceElement;
      27: astore_3
      28: aload_2
      29: aload_3
      30: iconst_1
      31: aload_3
      32: arraylength
      33: invokestatic  #11                 // Method java/util/Arrays.copyOfRange:([Ljava/lang/Object;II)[Ljava/lang/Object;
      36: checkcast     #12                 // class "[Ljava/lang/StackTraceElement;"
      39: invokevirtual #13                 // Method java/lang/IllegalArgumentException.setStackTrace:([Ljava/lang/StackTraceElement;)V
      42: aload_2
      43: areturn

  protected java.lang.String badRequest$str();
    Code:
       0: ldc           #182                // String UT000081: Bad request
       2: areturn

  public final java.lang.RuntimeException badRequest();
    Code:
       0: new           #85                 // class java/lang/RuntimeException
       3: dup
       4: aload_0
       5: invokevirtual #183                // Method badRequest$str:()Ljava/lang/String;
       8: iconst_0
       9: anewarray     #7                  // class java/lang/Object
      12: invokestatic  #8                  // Method java/lang/String.format:(Ljava/lang/String;[Ljava/lang/Object;)Ljava/lang/String;
      15: invokespecial #87                 // Method java/lang/RuntimeException."<init>":(Ljava/lang/String;)V
      18: astore_1
      19: aload_1
      20: invokevirtual #88                 // Method java/lang/RuntimeException.getStackTrace:()[Ljava/lang/StackTraceElement;
      23: astore_2
      24: aload_1
      25: aload_2
      26: iconst_1
      27: aload_2
      28: arraylength
      29: invokestatic  #11                 // Method java/util/Arrays.copyOfRange:([Ljava/lang/Object;II)[Ljava/lang/Object;
      32: checkcast     #12                 // class "[Ljava/lang/StackTraceElement;"
      35: invokevirtual #89                 // Method java/lang/RuntimeException.setStackTrace:([Ljava/lang/StackTraceElement;)V
      38: aload_1
      39: areturn

  protected java.lang.String hostAlreadyRegistered$str();
    Code:
       0: ldc           #184                // String UT000082: Host %s already registered
       2: areturn

  public final java.lang.RuntimeException hostAlreadyRegistered(java.lang.Object);
    Code:
       0: new           #85                 // class java/lang/RuntimeException
       3: dup
       4: aload_0
       5: invokevirtual #185                // Method hostAlreadyRegistered$str:()Ljava/lang/String;
       8: iconst_1
       9: anewarray     #7                  // class java/lang/Object
      12: dup
      13: iconst_0
      14: aload_1
      15: aastore
      16: invokestatic  #8                  // Method java/lang/String.format:(Ljava/lang/String;[Ljava/lang/Object;)Ljava/lang/String;
      19: invokespecial #87                 // Method java/lang/RuntimeException."<init>":(Ljava/lang/String;)V
      22: astore_2
      23: aload_2
      24: invokevirtual #88                 // Method java/lang/RuntimeException.getStackTrace:()[Ljava/lang/StackTraceElement;
      27: astore_3
      28: aload_2
      29: aload_3
      30: iconst_1
      31: aload_3
      32: arraylength
      33: invokestatic  #11                 // Method java/util/Arrays.copyOfRange:([Ljava/lang/Object;II)[Ljava/lang/Object;
      36: checkcast     #12                 // class "[Ljava/lang/StackTraceElement;"
      39: invokevirtual #89                 // Method java/lang/RuntimeException.setStackTrace:([Ljava/lang/StackTraceElement;)V
      42: aload_2
      43: areturn

  protected java.lang.String hostHasNotBeenRegistered$str();
    Code:
       0: ldc           #186                // String UT000083: Host %s has not been registered
       2: areturn

  public final java.lang.RuntimeException hostHasNotBeenRegistered(java.lang.Object);
    Code:
       0: new           #85                 // class java/lang/RuntimeException
       3: dup
       4: aload_0
       5: invokevirtual #187                // Method hostHasNotBeenRegistered$str:()Ljava/lang/String;
       8: iconst_1
       9: anewarray     #7                  // class java/lang/Object
      12: dup
      13: iconst_0
      14: aload_1
      15: aastore
      16: invokestatic  #8                  // Method java/lang/String.format:(Ljava/lang/String;[Ljava/lang/Object;)Ljava/lang/String;
      19: invokespecial #87                 // Method java/lang/RuntimeException."<init>":(Ljava/lang/String;)V
      22: astore_2
      23: aload_2
      24: invokevirtual #88                 // Method java/lang/RuntimeException.getStackTrace:()[Ljava/lang/StackTraceElement;
      27: astore_3
      28: aload_2
      29: aload_3
      30: iconst_1
      31: aload_3
      32: arraylength
      33: invokestatic  #11                 // Method java/util/Arrays.copyOfRange:([Ljava/lang/Object;II)[Ljava/lang/Object;
      36: checkcast     #12                 // class "[Ljava/lang/StackTraceElement;"
      39: invokevirtual #89                 // Method java/lang/RuntimeException.setStackTrace:([Ljava/lang/StackTraceElement;)V
      42: aload_2
      43: areturn

  protected java.lang.String extraDataWrittenAfterChunkEnd$str();
    Code:
       0: ldc           #188                // String UT000084: Attempted to write additional data after the last chunk
       2: areturn

  public final java.io.IOException extraDataWrittenAfterChunkEnd();
    Code:
       0: new           #37                 // class java/io/IOException
       3: dup
       4: aload_0
       5: invokevirtual #189                // Method extraDataWrittenAfterChunkEnd$str:()Ljava/lang/String;
       8: iconst_0
       9: anewarray     #7                  // class java/lang/Object
      12: invokestatic  #8                  // Method java/lang/String.format:(Ljava/lang/String;[Ljava/lang/Object;)Ljava/lang/String;
      15: invokespecial #39                 // Method java/io/IOException."<init>":(Ljava/lang/String;)V
      18: astore_1
      19: aload_1
      20: invokevirtual #40                 // Method java/io/IOException.getStackTrace:()[Ljava/lang/StackTraceElement;
      23: astore_2
      24: aload_1
      25: aload_2
      26: iconst_1
      27: aload_2
      28: arraylength
      29: invokestatic  #11                 // Method java/util/Arrays.copyOfRange:([Ljava/lang/Object;II)[Ljava/lang/Object;
      32: checkcast     #12                 // class "[Ljava/lang/StackTraceElement;"
      35: invokevirtual #41                 // Method java/io/IOException.setStackTrace:([Ljava/lang/StackTraceElement;)V
      38: aload_1
      39: areturn

  protected java.lang.String couldNotGenerateUniqueSessionId$str();
    Code:
       0: ldc           #190                // String UT000085: Could not generate unique session id
       2: areturn

  public final java.lang.RuntimeException couldNotGenerateUniqueSessionId();
    Code:
       0: new           #85                 // class java/lang/RuntimeException
       3: dup
       4: aload_0
       5: invokevirtual #191                // Method couldNotGenerateUniqueSessionId$str:()Ljava/lang/String;
       8: iconst_0
       9: anewarray     #7                  // class java/lang/Object
      12: invokestatic  #8                  // Method java/lang/String.format:(Ljava/lang/String;[Ljava/lang/Object;)Ljava/lang/String;
      15: invokespecial #87                 // Method java/lang/RuntimeException."<init>":(Ljava/lang/String;)V
      18: astore_1
      19: aload_1
      20: invokevirtual #88                 // Method java/lang/RuntimeException.getStackTrace:()[Ljava/lang/StackTraceElement;
      23: astore_2
      24: aload_1
      25: aload_2
      26: iconst_1
      27: aload_2
      28: arraylength
      29: invokestatic  #11                 // Method java/util/Arrays.copyOfRange:([Ljava/lang/Object;II)[Ljava/lang/Object;
      32: checkcast     #12                 // class "[Ljava/lang/StackTraceElement;"
      35: invokevirtual #89                 // Method java/lang/RuntimeException.setStackTrace:([Ljava/lang/StackTraceElement;)V
      38: aload_1
      39: areturn

  protected java.lang.String mustProvideHeapBuffer$str();
    Code:
       0: ldc           #192                // String UT000086: SPDY needs to be provided with a heap buffer pool, for use in compressing and decompressing headers.
       2: areturn

  public final java.lang.IllegalArgumentException mustProvideHeapBuffer();
    Code:
       0: new           #5                  // class java/lang/IllegalArgumentException
       3: dup
       4: aload_0
       5: invokevirtual #193                // Method mustProvideHeapBuffer$str:()Ljava/lang/String;
       8: iconst_0
       9: anewarray     #7                  // class java/lang/Object
      12: invokestatic  #8                  // Method java/lang/String.format:(Ljava/lang/String;[Ljava/lang/Object;)Ljava/lang/String;
      15: invokespecial #9                  // Method java/lang/IllegalArgumentException."<init>":(Ljava/lang/String;)V
      18: astore_1
      19: aload_1
      20: invokevirtual #10                 // Method java/lang/IllegalArgumentException.getStackTrace:()[Ljava/lang/StackTraceElement;
      23: astore_2
      24: aload_1
      25: aload_2
      26: iconst_1
      27: aload_2
      28: arraylength
      29: invokestatic  #11                 // Method java/util/Arrays.copyOfRange:([Ljava/lang/Object;II)[Ljava/lang/Object;
      32: checkcast     #12                 // class "[Ljava/lang/StackTraceElement;"
      35: invokevirtual #13                 // Method java/lang/IllegalArgumentException.setStackTrace:([Ljava/lang/StackTraceElement;)V
      38: aload_1
      39: areturn

  protected java.lang.String unexpectedFrameType$str();
    Code:
       0: ldc           #194                // String UT000087: Unexpected SPDY frame type %s
       2: areturn

  public final java.io.IOException unexpectedFrameType(int);
    Code:
       0: new           #37                 // class java/io/IOException
       3: dup
       4: aload_0
       5: invokevirtual #195                // Method unexpectedFrameType$str:()Ljava/lang/String;
       8: iconst_1
       9: anewarray     #7                  // class java/lang/Object
      12: dup
      13: iconst_0
      14: iload_1
      15: invokestatic  #94                 // Method java/lang/Integer.valueOf:(I)Ljava/lang/Integer;
      18: aastore
      19: invokestatic  #8                  // Method java/lang/String.format:(Ljava/lang/String;[Ljava/lang/Object;)Ljava/lang/String;
      22: invokespecial #39                 // Method java/io/IOException."<init>":(Ljava/lang/String;)V
      25: astore_2
      26: aload_2
      27: invokevirtual #40                 // Method java/io/IOException.getStackTrace:()[Ljava/lang/StackTraceElement;
      30: astore_3
      31: aload_2
      32: aload_3
      33: iconst_1
      34: aload_3
      35: arraylength
      36: invokestatic  #11                 // Method java/util/Arrays.copyOfRange:([Ljava/lang/Object;II)[Ljava/lang/Object;
      39: checkcast     #12                 // class "[Ljava/lang/StackTraceElement;"
      42: invokevirtual #41                 // Method java/io/IOException.setStackTrace:([Ljava/lang/StackTraceElement;)V
      45: aload_2
      46: areturn

  protected java.lang.String controlFrameCannotHaveBodyContent$str();
    Code:
       0: ldc           #196                // String UT000088: SPDY control frames cannot have body content
       2: areturn

  public final java.io.IOException controlFrameCannotHaveBodyContent();
    Code:
       0: new           #37                 // class java/io/IOException
       3: dup
       4: aload_0
       5: invokevirtual #197                // Method controlFrameCannotHaveBodyContent$str:()Ljava/lang/String;
       8: iconst_0
       9: anewarray     #7                  // class java/lang/Object
      12: invokestatic  #8                  // Method java/lang/String.format:(Ljava/lang/String;[Ljava/lang/Object;)Ljava/lang/String;
      15: invokespecial #39                 // Method java/io/IOException."<init>":(Ljava/lang/String;)V
      18: astore_1
      19: aload_1
      20: invokevirtual #40                 // Method java/io/IOException.getStackTrace:()[Ljava/lang/StackTraceElement;
      23: astore_2
      24: aload_1
      25: aload_2
      26: iconst_1
      27: aload_2
      28: arraylength
      29: invokestatic  #11                 // Method java/util/Arrays.copyOfRange:([Ljava/lang/Object;II)[Ljava/lang/Object;
      32: checkcast     #12                 // class "[Ljava/lang/StackTraceElement;"
      35: invokevirtual #41                 // Method java/io/IOException.setStackTrace:([Ljava/lang/StackTraceElement;)V
      38: aload_1
      39: areturn

  protected java.lang.String spdyNotSupported$str();
    Code:
       0: ldc           #198                // String UT000089: SPDY not supported
       2: areturn

  public final java.io.IOException spdyNotSupported();
    Code:
       0: new           #37                 // class java/io/IOException
       3: dup
       4: aload_0
       5: invokevirtual #199                // Method spdyNotSupported$str:()Ljava/lang/String;
       8: iconst_0
       9: anewarray     #7                  // class java/lang/Object
      12: invokestatic  #8                  // Method java/lang/String.format:(Ljava/lang/String;[Ljava/lang/Object;)Ljava/lang/String;
      15: invokespecial #39                 // Method java/io/IOException."<init>":(Ljava/lang/String;)V
      18: astore_1
      19: aload_1
      20: invokevirtual #40                 // Method java/io/IOException.getStackTrace:()[Ljava/lang/StackTraceElement;
      23: astore_2
      24: aload_1
      25: aload_2
      26: iconst_1
      27: aload_2
      28: arraylength
      29: invokestatic  #11                 // Method java/util/Arrays.copyOfRange:([Ljava/lang/Object;II)[Ljava/lang/Object;
      32: checkcast     #12                 // class "[Ljava/lang/StackTraceElement;"
      35: invokevirtual #41                 // Method java/io/IOException.setStackTrace:([Ljava/lang/StackTraceElement;)V
      38: aload_1
      39: areturn

  protected java.lang.String alpnNotAvailable$str();
    Code:
       0: ldc           #200                // String UT000090: No ALPN implementation available (tried Jetty ALPN and JDK9)
       2: areturn

  public final java.io.IOException alpnNotAvailable();
    Code:
       0: new           #37                 // class java/io/IOException
       3: dup
       4: aload_0
       5: invokevirtual #201                // Method alpnNotAvailable$str:()Ljava/lang/String;
       8: iconst_0
       9: anewarray     #7                  // class java/lang/Object
      12: invokestatic  #8                  // Method java/lang/String.format:(Ljava/lang/String;[Ljava/lang/Object;)Ljava/lang/String;
      15: invokespecial #39                 // Method java/io/IOException."<init>":(Ljava/lang/String;)V
      18: astore_1
      19: aload_1
      20: invokevirtual #40                 // Method java/io/IOException.getStackTrace:()[Ljava/lang/StackTraceElement;
      23: astore_2
      24: aload_1
      25: aload_2
      26: iconst_1
      27: aload_2
      28: arraylength
      29: invokestatic  #11                 // Method java/util/Arrays.copyOfRange:([Ljava/lang/Object;II)[Ljava/lang/Object;
      32: checkcast     #12                 // class "[Ljava/lang/StackTraceElement;"
      35: invokevirtual #41                 // Method java/io/IOException.setStackTrace:([Ljava/lang/StackTraceElement;)V
      38: aload_1
      39: areturn

  protected java.lang.String bufferAlreadyFreed$str();
    Code:
       0: ldc           #202                // String UT000091: Buffer has already been freed
       2: areturn

  public final java.lang.IllegalStateException bufferAlreadyFreed();
    Code:
       0: new           #15                 // class java/lang/IllegalStateException
       3: dup
       4: aload_0
       5: invokevirtual #203                // Method bufferAlreadyFreed$str:()Ljava/lang/String;
       8: iconst_0
       9: anewarray     #7                  // class java/lang/Object
      12: invokestatic  #8                  // Method java/lang/String.format:(Ljava/lang/String;[Ljava/lang/Object;)Ljava/lang/String;
      15: invokespecial #17                 // Method java/lang/IllegalStateException."<init>":(Ljava/lang/String;)V
      18: astore_1
      19: aload_1
      20: invokevirtual #18                 // Method java/lang/IllegalStateException.getStackTrace:()[Ljava/lang/StackTraceElement;
      23: astore_2
      24: aload_1
      25: aload_2
      26: iconst_1
      27: aload_2
      28: arraylength
      29: invokestatic  #11                 // Method java/util/Arrays.copyOfRange:([Ljava/lang/Object;II)[Ljava/lang/Object;
      32: checkcast     #12                 // class "[Ljava/lang/StackTraceElement;"
      35: invokevirtual #19                 // Method java/lang/IllegalStateException.setStackTrace:([Ljava/lang/StackTraceElement;)V
      38: aload_1
      39: areturn

  protected java.lang.String headersTooLargeToFitInHeapBuffer$str();
    Code:
       0: ldc           #204                // String UT000092: A SPDY header was too large to fit in a response buffer, if you want to support larger headers please increase the buffer size
       2: areturn

  public final java.lang.IllegalStateException headersTooLargeToFitInHeapBuffer();
    Code:
       0: new           #15                 // class java/lang/IllegalStateException
       3: dup
       4: aload_0
       5: invokevirtual #205                // Method headersTooLargeToFitInHeapBuffer$str:()Ljava/lang/String;
       8: iconst_0
       9: anewarray     #7                  // class java/lang/Object
      12: invokestatic  #8                  // Method java/lang/String.format:(Ljava/lang/String;[Ljava/lang/Object;)Ljava/lang/String;
      15: invokespecial #17                 // Method java/lang/IllegalStateException."<init>":(Ljava/lang/String;)V
      18: astore_1
      19: aload_1
      20: invokevirtual #18                 // Method java/lang/IllegalStateException.getStackTrace:()[Ljava/lang/StackTraceElement;
      23: astore_2
      24: aload_1
      25: aload_2
      26: iconst_1
      27: aload_2
      28: arraylength
      29: invokestatic  #11                 // Method java/util/Arrays.copyOfRange:([Ljava/lang/Object;II)[Ljava/lang/Object;
      32: checkcast     #12                 // class "[Ljava/lang/StackTraceElement;"
      35: invokevirtual #19                 // Method java/lang/IllegalStateException.setStackTrace:([Ljava/lang/StackTraceElement;)V
      38: aload_1
      39: areturn

  protected java.lang.String spdyStreamWasReset$str();
    Code:
       0: ldc           #206                // String UT000093: A SPDY stream was reset by the remote endpoint
       2: areturn

  public final java.io.IOException spdyStreamWasReset();
    Code:
       0: new           #37                 // class java/io/IOException
       3: dup
       4: aload_0
       5: invokevirtual #207                // Method spdyStreamWasReset$str:()Ljava/lang/String;
       8: iconst_0
       9: anewarray     #7                  // class java/lang/Object
      12: invokestatic  #8                  // Method java/lang/String.format:(Ljava/lang/String;[Ljava/lang/Object;)Ljava/lang/String;
      15: invokespecial #39                 // Method java/io/IOException."<init>":(Ljava/lang/String;)V
      18: astore_1
      19: aload_1
      20: invokevirtual #40                 // Method java/io/IOException.getStackTrace:()[Ljava/lang/StackTraceElement;
      23: astore_2
      24: aload_1
      25: aload_2
      26: iconst_1
      27: aload_2
      28: arraylength
      29: invokestatic  #11                 // Method java/util/Arrays.copyOfRange:([Ljava/lang/Object;II)[Ljava/lang/Object;
      32: checkcast     #12                 // class "[Ljava/lang/StackTraceElement;"
      35: invokevirtual #41                 // Method java/io/IOException.setStackTrace:([Ljava/lang/StackTraceElement;)V
      38: aload_1
      39: areturn

  protected java.lang.String awaitCalledFromIoThread$str();
    Code:
       0: ldc           #208                // String UT000094: Blocking await method called from IO thread. Blocking IO must be dispatched to a worker thread or deadlocks will result.
       2: areturn

  public final java.io.IOException awaitCalledFromIoThread();
    Code:
       0: new           #37                 // class java/io/IOException
       3: dup
       4: aload_0
       5: invokevirtual #209                // Method awaitCalledFromIoThread$str:()Ljava/lang/String;
       8: iconst_0
       9: anewarray     #7                  // class java/lang/Object
      12: invokestatic  #8                  // Method java/lang/String.format:(Ljava/lang/String;[Ljava/lang/Object;)Ljava/lang/String;
      15: invokespecial #39                 // Method java/io/IOException."<init>":(Ljava/lang/String;)V
      18: astore_1
      19: aload_1
      20: invokevirtual #40                 // Method java/io/IOException.getStackTrace:()[Ljava/lang/StackTraceElement;
      23: astore_2
      24: aload_1
      25: aload_2
      26: iconst_1
      27: aload_2
      28: arraylength
      29: invokestatic  #11                 // Method java/util/Arrays.copyOfRange:([Ljava/lang/Object;II)[Ljava/lang/Object;
      32: checkcast     #12                 // class "[Ljava/lang/StackTraceElement;"
      35: invokevirtual #41                 // Method java/io/IOException.setStackTrace:([Ljava/lang/StackTraceElement;)V
      38: aload_1
      39: areturn

  protected java.lang.String recursiveCallToFlushingSenders$str();
    Code:
       0: ldc           #210                // String UT000095: Recursive call to flushSenders()
       2: areturn

  public final java.lang.RuntimeException recursiveCallToFlushingSenders();
    Code:
       0: new           #85                 // class java/lang/RuntimeException
       3: dup
       4: aload_0
       5: invokevirtual #211                // Method recursiveCallToFlushingSenders$str:()Ljava/lang/String;
       8: iconst_0
       9: anewarray     #7                  // class java/lang/Object
      12: invokestatic  #8                  // Method java/lang/String.format:(Ljava/lang/String;[Ljava/lang/Object;)Ljava/lang/String;
      15: invokespecial #87                 // Method java/lang/RuntimeException."<init>":(Ljava/lang/String;)V
      18: astore_1
      19: aload_1
      20: invokevirtual #88                 // Method java/lang/RuntimeException.getStackTrace:()[Ljava/lang/StackTraceElement;
      23: astore_2
      24: aload_1
      25: aload_2
      26: iconst_1
      27: aload_2
      28: arraylength
      29: invokestatic  #11                 // Method java/util/Arrays.copyOfRange:([Ljava/lang/Object;II)[Ljava/lang/Object;
      32: checkcast     #12                 // class "[Ljava/lang/StackTraceElement;"
      35: invokevirtual #89                 // Method java/lang/RuntimeException.setStackTrace:([Ljava/lang/StackTraceElement;)V
      38: aload_1
      39: areturn

  protected java.lang.String fixedLengthOverflow$str();
    Code:
       0: ldc           #212                // String UT000096: More data was written to the channel than specified in the content-length
       2: areturn

  public final java.lang.IllegalStateException fixedLengthOverflow();
    Code:
       0: new           #15                 // class java/lang/IllegalStateException
       3: dup
       4: aload_0
       5: invokevirtual #213                // Method fixedLengthOverflow$str:()Ljava/lang/String;
       8: iconst_0
       9: anewarray     #7                  // class java/lang/Object
      12: invokestatic  #8                  // Method java/lang/String.format:(Ljava/lang/String;[Ljava/lang/Object;)Ljava/lang/String;
      15: invokespecial #17                 // Method java/lang/IllegalStateException."<init>":(Ljava/lang/String;)V
      18: astore_1
      19: aload_1
      20: invokevirtual #18                 // Method java/lang/IllegalStateException.getStackTrace:()[Ljava/lang/StackTraceElement;
      23: astore_2
      24: aload_1
      25: aload_2
      26: iconst_1
      27: aload_2
      28: arraylength
      29: invokestatic  #11                 // Method java/util/Arrays.copyOfRange:([Ljava/lang/Object;II)[Ljava/lang/Object;
      32: checkcast     #12                 // class "[Ljava/lang/StackTraceElement;"
      35: invokevirtual #19                 // Method java/lang/IllegalStateException.setStackTrace:([Ljava/lang/StackTraceElement;)V
      38: aload_1
      39: areturn

  protected java.lang.String ajpRequestAlreadyInProgress$str();
    Code:
       0: ldc           #214                // String UT000097: AJP request already in progress
       2: areturn

  public final java.lang.IllegalStateException ajpRequestAlreadyInProgress();
    Code:
       0: new           #15                 // class java/lang/IllegalStateException
       3: dup
       4: aload_0
       5: invokevirtual #215                // Method ajpRequestAlreadyInProgress$str:()Ljava/lang/String;
       8: iconst_0
       9: anewarray     #7                  // class java/lang/Object
      12: invokestatic  #8                  // Method java/lang/String.format:(Ljava/lang/String;[Ljava/lang/Object;)Ljava/lang/String;
      15: invokespecial #17                 // Method java/lang/IllegalStateException."<init>":(Ljava/lang/String;)V
      18: astore_1
      19: aload_1
      20: invokevirtual #18                 // Method java/lang/IllegalStateException.getStackTrace:()[Ljava/lang/StackTraceElement;
      23: astore_2
      24: aload_1
      25: aload_2
      26: iconst_1
      27: aload_2
      28: arraylength
      29: invokestatic  #11                 // Method java/util/Arrays.copyOfRange:([Ljava/lang/Object;II)[Ljava/lang/Object;
      32: checkcast     #12                 // class "[Ljava/lang/StackTraceElement;"
      35: invokevirtual #19                 // Method java/lang/IllegalStateException.setStackTrace:([Ljava/lang/StackTraceElement;)V
      38: aload_1
      39: areturn

  protected java.lang.String httpPingDataMustBeLength8$str();
    Code:
       0: ldc           #216                // String UT000098: HTTP ping data must be 8 bytes in length
       2: areturn

  public final java.lang.String httpPingDataMustBeLength8();
    Code:
       0: aload_0
       1: invokevirtual #217                // Method httpPingDataMustBeLength8$str:()Ljava/lang/String;
       4: iconst_0
       5: anewarray     #7                  // class java/lang/Object
       8: invokestatic  #8                  // Method java/lang/String.format:(Ljava/lang/String;[Ljava/lang/Object;)Ljava/lang/String;
      11: areturn

  protected java.lang.String invalidPingSize$str();
    Code:
       0: ldc           #218                // String UT000099: Received a ping of size other than 8
       2: areturn

  public final java.lang.String invalidPingSize();
    Code:
       0: aload_0
       1: invokevirtual #219                // Method invalidPingSize$str:()Ljava/lang/String;
       4: iconst_0
       5: anewarray     #7                  // class java/lang/Object
       8: invokestatic  #8                  // Method java/lang/String.format:(Ljava/lang/String;[Ljava/lang/Object;)Ljava/lang/String;
      11: areturn

  protected java.lang.String streamIdMustBeZeroForFrameType$str();
    Code:
       0: ldc           #220                // String UT000100: stream id must be zero for frame type %s
       2: areturn

  public final java.lang.String streamIdMustBeZeroForFrameType(int);
    Code:
       0: aload_0
       1: invokevirtual #221                // Method streamIdMustBeZeroForFrameType$str:()Ljava/lang/String;
       4: iconst_1
       5: anewarray     #7                  // class java/lang/Object
       8: dup
       9: iconst_0
      10: iload_1
      11: invokestatic  #94                 // Method java/lang/Integer.valueOf:(I)Ljava/lang/Integer;
      14: aastore
      15: invokestatic  #8                  // Method java/lang/String.format:(Ljava/lang/String;[Ljava/lang/Object;)Ljava/lang/String;
      18: areturn

  protected java.lang.String streamIdMustNotBeZeroForFrameType$str();
    Code:
       0: ldc           #222                // String UT000101: stream id must not be zero for frame type %s
       2: areturn

  public final java.lang.String streamIdMustNotBeZeroForFrameType(int);
    Code:
       0: aload_0
       1: invokevirtual #223                // Method streamIdMustNotBeZeroForFrameType$str:()Ljava/lang/String;
       4: iconst_1
       5: anewarray     #7                  // class java/lang/Object
       8: dup
       9: iconst_0
      10: iload_1
      11: invokestatic  #94                 // Method java/lang/Integer.valueOf:(I)Ljava/lang/Integer;
      14: aastore
      15: invokestatic  #8                  // Method java/lang/String.format:(Ljava/lang/String;[Ljava/lang/Object;)Ljava/lang/String;
      18: areturn

  protected java.lang.String rstStreamReceivedForIdleStream$str();
    Code:
       0: ldc           #224                // String UT000102: RST_STREAM received for idle stream
       2: areturn

  public final java.lang.String rstStreamReceivedForIdleStream();
    Code:
       0: aload_0
       1: invokevirtual #225                // Method rstStreamReceivedForIdleStream$str:()Ljava/lang/String;
       4: iconst_0
       5: anewarray     #7                  // class java/lang/Object
       8: invokestatic  #8                  // Method java/lang/String.format:(Ljava/lang/String;[Ljava/lang/Object;)Ljava/lang/String;
      11: areturn

  protected java.lang.String http2StreamWasReset$str();
    Code:
       0: ldc           #226                // String UT000103: Http2 stream was reset
       2: areturn

  public final java.io.IOException http2StreamWasReset();
    Code:
       0: new           #37                 // class java/io/IOException
       3: dup
       4: aload_0
       5: invokevirtual #227                // Method http2StreamWasReset$str:()Ljava/lang/String;
       8: iconst_0
       9: anewarray     #7                  // class java/lang/Object
      12: invokestatic  #8                  // Method java/lang/String.format:(Ljava/lang/String;[Ljava/lang/Object;)Ljava/lang/String;
      15: invokespecial #39                 // Method java/io/IOException."<init>":(Ljava/lang/String;)V
      18: astore_1
      19: aload_1
      20: invokevirtual #40                 // Method java/io/IOException.getStackTrace:()[Ljava/lang/StackTraceElement;
      23: astore_2
      24: aload_1
      25: aload_2
      26: iconst_1
      27: aload_2
      28: arraylength
      29: invokestatic  #11                 // Method java/util/Arrays.copyOfRange:([Ljava/lang/Object;II)[Ljava/lang/Object;
      32: checkcast     #12                 // class "[Ljava/lang/StackTraceElement;"
      35: invokevirtual #41                 // Method java/io/IOException.setStackTrace:([Ljava/lang/StackTraceElement;)V
      38: aload_1
      39: areturn

  protected java.lang.String incorrectHttp2Preface$str();
    Code:
       0: ldc           #228                // String UT000104: Incorrect HTTP2 preface
       2: areturn

  public final java.io.IOException incorrectHttp2Preface();
    Code:
       0: new           #37                 // class java/io/IOException
       3: dup
       4: aload_0
       5: invokevirtual #229                // Method incorrectHttp2Preface$str:()Ljava/lang/String;
       8: iconst_0
       9: anewarray     #7                  // class java/lang/Object
      12: invokestatic  #8                  // Method java/lang/String.format:(Ljava/lang/String;[Ljava/lang/Object;)Ljava/lang/String;
      15: invokespecial #39                 // Method java/io/IOException."<init>":(Ljava/lang/String;)V
      18: astore_1
      19: aload_1
      20: invokevirtual #40                 // Method java/io/IOException.getStackTrace:()[Ljava/lang/StackTraceElement;
      23: astore_2
      24: aload_1
      25: aload_2
      26: iconst_1
      27: aload_2
      28: arraylength
      29: invokestatic  #11                 // Method java/util/Arrays.copyOfRange:([Ljava/lang/Object;II)[Ljava/lang/Object;
      32: checkcast     #12                 // class "[Ljava/lang/StackTraceElement;"
      35: invokevirtual #41                 // Method java/io/IOException.setStackTrace:([Ljava/lang/StackTraceElement;)V
      38: aload_1
      39: areturn

  protected java.lang.String http2FrameTooLarge$str();
    Code:
       0: ldc           #230                // String UT000105: HTTP2 frame to large
       2: areturn

  public final java.io.IOException http2FrameTooLarge();
    Code:
       0: new           #37                 // class java/io/IOException
       3: dup
       4: aload_0
       5: invokevirtual #231                // Method http2FrameTooLarge$str:()Ljava/lang/String;
       8: iconst_0
       9: anewarray     #7                  // class java/lang/Object
      12: invokestatic  #8                  // Method java/lang/String.format:(Ljava/lang/String;[Ljava/lang/Object;)Ljava/lang/String;
      15: invokespecial #39                 // Method java/io/IOException."<init>":(Ljava/lang/String;)V
      18: astore_1
      19: aload_1
      20: invokevirtual #40                 // Method java/io/IOException.getStackTrace:()[Ljava/lang/StackTraceElement;
      23: astore_2
      24: aload_1
      25: aload_2
      26: iconst_1
      27: aload_2
      28: arraylength
      29: invokestatic  #11                 // Method java/util/Arrays.copyOfRange:([Ljava/lang/Object;II)[Ljava/lang/Object;
      32: checkcast     #12                 // class "[Ljava/lang/StackTraceElement;"
      35: invokevirtual #41                 // Method java/io/IOException.setStackTrace:([Ljava/lang/StackTraceElement;)V
      38: aload_1
      39: areturn

  protected java.lang.String http2ContinuationFrameNotExpected$str();
    Code:
       0: ldc           #232                // String UT000106: HTTP2 continuation frame received without a corresponding headers or push promise frame
       2: areturn

  public final java.io.IOException http2ContinuationFrameNotExpected();
    Code:
       0: new           #37                 // class java/io/IOException
       3: dup
       4: aload_0
       5: invokevirtual #233                // Method http2ContinuationFrameNotExpected$str:()Ljava/lang/String;
       8: iconst_0
       9: anewarray     #7                  // class java/lang/Object
      12: invokestatic  #8                  // Method java/lang/String.format:(Ljava/lang/String;[Ljava/lang/Object;)Ljava/lang/String;
      15: invokespecial #39                 // Method java/io/IOException."<init>":(Ljava/lang/String;)V
      18: astore_1
      19: aload_1
      20: invokevirtual #40                 // Method java/io/IOException.getStackTrace:()[Ljava/lang/StackTraceElement;
      23: astore_2
      24: aload_1
      25: aload_2
      26: iconst_1
      27: aload_2
      28: arraylength
      29: invokestatic  #11                 // Method java/util/Arrays.copyOfRange:([Ljava/lang/Object;II)[Ljava/lang/Object;
      32: checkcast     #12                 // class "[Ljava/lang/StackTraceElement;"
      35: invokevirtual #41                 // Method java/io/IOException.setStackTrace:([Ljava/lang/StackTraceElement;)V
      38: aload_1
      39: areturn

  protected java.lang.String huffmanEncodedHpackValueDidNotEndWithEOS$str();
    Code:
       0: ldc           #234                // String UT000107: Huffman encoded value in HPACK headers did not end with EOS padding
       2: areturn

  public final io.undertow.protocols.http2.HpackException huffmanEncodedHpackValueDidNotEndWithEOS();
    Code:
       0: new           #235                // class io/undertow/protocols/http2/HpackException
       3: dup
       4: invokespecial #236                // Method io/undertow/protocols/http2/HpackException."<init>":()V
       7: astore_1
       8: aload_1
       9: invokevirtual #237                // Method io/undertow/protocols/http2/HpackException.getStackTrace:()[Ljava/lang/StackTraceElement;
      12: astore_2
      13: aload_1
      14: aload_2
      15: iconst_1
      16: aload_2
      17: arraylength
      18: invokestatic  #11                 // Method java/util/Arrays.copyOfRange:([Ljava/lang/Object;II)[Ljava/lang/Object;
      21: checkcast     #12                 // class "[Ljava/lang/StackTraceElement;"
      24: invokevirtual #238                // Method io/undertow/protocols/http2/HpackException.setStackTrace:([Ljava/lang/StackTraceElement;)V
      27: aload_1
      28: areturn

  protected java.lang.String integerEncodedOverTooManyOctets$str();
    Code:
       0: ldc           #239                // String UT000108: HPACK variable length integer encoded over too many octects, max is %s
       2: areturn

  public final io.undertow.protocols.http2.HpackException integerEncodedOverTooManyOctets(int);
    Code:
       0: new           #235                // class io/undertow/protocols/http2/HpackException
       3: dup
       4: invokespecial #236                // Method io/undertow/protocols/http2/HpackException."<init>":()V
       7: astore_2
       8: aload_2
       9: invokevirtual #237                // Method io/undertow/protocols/http2/HpackException.getStackTrace:()[Ljava/lang/StackTraceElement;
      12: astore_3
      13: aload_2
      14: aload_3
      15: iconst_1
      16: aload_3
      17: arraylength
      18: invokestatic  #11                 // Method java/util/Arrays.copyOfRange:([Ljava/lang/Object;II)[Ljava/lang/Object;
      21: checkcast     #12                 // class "[Ljava/lang/StackTraceElement;"
      24: invokevirtual #238                // Method io/undertow/protocols/http2/HpackException.setStackTrace:([Ljava/lang/StackTraceElement;)V
      27: aload_2
      28: areturn

  protected java.lang.String zeroNotValidHeaderTableIndex$str();
    Code:
       0: ldc           #240                // String UT000109: Zero is not a valid header table index
       2: areturn

  public final io.undertow.protocols.http2.HpackException zeroNotValidHeaderTableIndex();
    Code:
       0: new           #235                // class io/undertow/protocols/http2/HpackException
       3: dup
       4: invokespecial #236                // Method io/undertow/protocols/http2/HpackException."<init>":()V
       7: astore_1
       8: aload_1
       9: invokevirtual #237                // Method io/undertow/protocols/http2/HpackException.getStackTrace:()[Ljava/lang/StackTraceElement;
      12: astore_2
      13: aload_1
      14: aload_2
      15: iconst_1
      16: aload_2
      17: arraylength
      18: invokestatic  #11                 // Method java/util/Arrays.copyOfRange:([Ljava/lang/Object;II)[Ljava/lang/Object;
      21: checkcast     #12                 // class "[Ljava/lang/StackTraceElement;"
      24: invokevirtual #238                // Method io/undertow/protocols/http2/HpackException.setStackTrace:([Ljava/lang/StackTraceElement;)V
      27: aload_1
      28: areturn

  protected java.lang.String cannotSendContinueResponse$str();
    Code:
       0: ldc           #241                // String UT000110: Cannot send 100-Continue, getResponseChannel() has already been called
       2: areturn

  public final java.io.IOException cannotSendContinueResponse();
    Code:
       0: new           #37                 // class java/io/IOException
       3: dup
       4: aload_0
       5: invokevirtual #242                // Method cannotSendContinueResponse$str:()Ljava/lang/String;
       8: iconst_0
       9: anewarray     #7                  // class java/lang/Object
      12: invokestatic  #8                  // Method java/lang/String.format:(Ljava/lang/String;[Ljava/lang/Object;)Ljava/lang/String;
      15: invokespecial #39                 // Method java/io/IOException."<init>":(Ljava/lang/String;)V
      18: astore_1
      19: aload_1
      20: invokevirtual #40                 // Method java/io/IOException.getStackTrace:()[Ljava/lang/StackTraceElement;
      23: astore_2
      24: aload_1
      25: aload_2
      26: iconst_1
      27: aload_2
      28: arraylength
      29: invokestatic  #11                 // Method java/util/Arrays.copyOfRange:([Ljava/lang/Object;II)[Ljava/lang/Object;
      32: checkcast     #12                 // class "[Ljava/lang/StackTraceElement;"
      35: invokevirtual #41                 // Method java/io/IOException.setStackTrace:([Ljava/lang/StackTraceElement;)V
      38: aload_1
      39: areturn

  protected java.lang.String parserDidNotMakeProgress$str();
    Code:
       0: ldc           #243                // String UT000111: Parser did not make progress
       2: areturn

  public final java.io.IOException parserDidNotMakeProgress();
    Code:
       0: new           #37                 // class java/io/IOException
       3: dup
       4: aload_0
       5: invokevirtual #244                // Method parserDidNotMakeProgress$str:()Ljava/lang/String;
       8: iconst_0
       9: anewarray     #7                  // class java/lang/Object
      12: invokestatic  #8                  // Method java/lang/String.format:(Ljava/lang/String;[Ljava/lang/Object;)Ljava/lang/String;
      15: invokespecial #39                 // Method java/io/IOException."<init>":(Ljava/lang/String;)V
      18: astore_1
      19: aload_1
      20: invokevirtual #40                 // Method java/io/IOException.getStackTrace:()[Ljava/lang/StackTraceElement;
      23: astore_2
      24: aload_1
      25: aload_2
      26: iconst_1
      27: aload_2
      28: arraylength
      29: invokestatic  #11                 // Method java/util/Arrays.copyOfRange:([Ljava/lang/Object;II)[Ljava/lang/Object;
      32: checkcast     #12                 // class "[Ljava/lang/StackTraceElement;"
      35: invokevirtual #41                 // Method java/io/IOException.setStackTrace:([Ljava/lang/StackTraceElement;)V
      38: aload_1
      39: areturn

  protected java.lang.String headersStreamCanOnlyBeCreatedByClient$str();
    Code:
       0: ldc           #245                // String UT000112: Only client side can call createStream, if you wish to send a PUSH_PROMISE frame use createPushPromiseStream instead
       2: areturn

  public final java.io.IOException headersStreamCanOnlyBeCreatedByClient();
    Code:
       0: new           #37                 // class java/io/IOException
       3: dup
       4: aload_0
       5: invokevirtual #246                // Method headersStreamCanOnlyBeCreatedByClient$str:()Ljava/lang/String;
       8: iconst_0
       9: anewarray     #7                  // class java/lang/Object
      12: invokestatic  #8                  // Method java/lang/String.format:(Ljava/lang/String;[Ljava/lang/Object;)Ljava/lang/String;
      15: invokespecial #39                 // Method java/io/IOException."<init>":(Ljava/lang/String;)V
      18: astore_1
      19: aload_1
      20: invokevirtual #40                 // Method java/io/IOException.getStackTrace:()[Ljava/lang/StackTraceElement;
      23: astore_2
      24: aload_1
      25: aload_2
      26: iconst_1
      27: aload_2
      28: arraylength
      29: invokestatic  #11                 // Method java/util/Arrays.copyOfRange:([Ljava/lang/Object;II)[Ljava/lang/Object;
      32: checkcast     #12                 // class "[Ljava/lang/StackTraceElement;"
      35: invokevirtual #41                 // Method java/io/IOException.setStackTrace:([Ljava/lang/StackTraceElement;)V
      38: aload_1
      39: areturn

  protected java.lang.String pushPromiseCanOnlyBeCreatedByServer$str();
    Code:
       0: ldc           #247                // String UT000113: Only the server side can send a push promise stream
       2: areturn

  public final java.io.IOException pushPromiseCanOnlyBeCreatedByServer();
    Code:
       0: new           #37                 // class java/io/IOException
       3: dup
       4: aload_0
       5: invokevirtual #248                // Method pushPromiseCanOnlyBeCreatedByServer$str:()Ljava/lang/String;
       8: iconst_0
       9: anewarray     #7                  // class java/lang/Object
      12: invokestatic  #8                  // Method java/lang/String.format:(Ljava/lang/String;[Ljava/lang/Object;)Ljava/lang/String;
      15: invokespecial #39                 // Method java/io/IOException."<init>":(Ljava/lang/String;)V
      18: astore_1
      19: aload_1
      20: invokevirtual #40                 // Method java/io/IOException.getStackTrace:()[Ljava/lang/StackTraceElement;
      23: astore_2
      24: aload_1
      25: aload_2
      26: iconst_1
      27: aload_2
      28: arraylength
      29: invokestatic  #11                 // Method java/util/Arrays.copyOfRange:([Ljava/lang/Object;II)[Ljava/lang/Object;
      32: checkcast     #12                 // class "[Ljava/lang/StackTraceElement;"
      35: invokevirtual #41                 // Method java/io/IOException.setStackTrace:([Ljava/lang/StackTraceElement;)V
      38: aload_1
      39: areturn

  protected java.lang.String invalidAclRule$str();
    Code:
       0: ldc           #249                // String UT000114: Invalid IP access control rule %s. Format is: [ip-match] allow|deny
       2: areturn

  public final java.lang.IllegalArgumentException invalidAclRule(java.lang.String);
    Code:
       0: new           #5                  // class java/lang/IllegalArgumentException
       3: dup
       4: aload_0
       5: invokevirtual #250                // Method invalidAclRule$str:()Ljava/lang/String;
       8: iconst_1
       9: anewarray     #7                  // class java/lang/Object
      12: dup
      13: iconst_0
      14: aload_1
      15: aastore
      16: invokestatic  #8                  // Method java/lang/String.format:(Ljava/lang/String;[Ljava/lang/Object;)Ljava/lang/String;
      19: invokespecial #9                  // Method java/lang/IllegalArgumentException."<init>":(Ljava/lang/String;)V
      22: astore_2
      23: aload_2
      24: invokevirtual #10                 // Method java/lang/IllegalArgumentException.getStackTrace:()[Ljava/lang/StackTraceElement;
      27: astore_3
      28: aload_2
      29: aload_3
      30: iconst_1
      31: aload_3
      32: arraylength
      33: invokestatic  #11                 // Method java/util/Arrays.copyOfRange:([Ljava/lang/Object;II)[Ljava/lang/Object;
      36: checkcast     #12                 // class "[Ljava/lang/StackTraceElement;"
      39: invokevirtual #13                 // Method java/lang/IllegalArgumentException.setStackTrace:([Ljava/lang/StackTraceElement;)V
      42: aload_2
      43: areturn

  protected java.lang.String serverReceivedPushPromise$str();
    Code:
       0: ldc           #251                // String UT000115: Server received PUSH_PROMISE frame from client
       2: areturn

  public final java.io.IOException serverReceivedPushPromise();
    Code:
       0: new           #37                 // class java/io/IOException
       3: dup
       4: aload_0
       5: invokevirtual #252                // Method serverReceivedPushPromise$str:()Ljava/lang/String;
       8: iconst_0
       9: anewarray     #7                  // class java/lang/Object
      12: invokestatic  #8                  // Method java/lang/String.format:(Ljava/lang/String;[Ljava/lang/Object;)Ljava/lang/String;
      15: invokespecial #39                 // Method java/io/IOException."<init>":(Ljava/lang/String;)V
      18: astore_1
      19: aload_1
      20: invokevirtual #40                 // Method java/io/IOException.getStackTrace:()[Ljava/lang/StackTraceElement;
      23: astore_2
      24: aload_1
      25: aload_2
      26: iconst_1
      27: aload_2
      28: arraylength
      29: invokestatic  #11                 // Method java/util/Arrays.copyOfRange:([Ljava/lang/Object;II)[Ljava/lang/Object;
      32: checkcast     #12                 // class "[Ljava/lang/StackTraceElement;"
      35: invokevirtual #41                 // Method java/io/IOException.setStackTrace:([Ljava/lang/StackTraceElement;)V
      38: aload_1
      39: areturn

  protected java.lang.String connectNotSupported$str();
    Code:
       0: ldc           #253                // String UT000116: CONNECT not supported by this connector
       2: areturn

  public final java.lang.IllegalStateException connectNotSupported();
    Code:
       0: new           #15                 // class java/lang/IllegalStateException
       3: dup
       4: aload_0
       5: invokevirtual #254                // Method connectNotSupported$str:()Ljava/lang/String;
       8: iconst_0
       9: anewarray     #7                  // class java/lang/Object
      12: invokestatic  #8                  // Method java/lang/String.format:(Ljava/lang/String;[Ljava/lang/Object;)Ljava/lang/String;
      15: invokespecial #17                 // Method java/lang/IllegalStateException."<init>":(Ljava/lang/String;)V
      18: astore_1
      19: aload_1
      20: invokevirtual #18                 // Method java/lang/IllegalStateException.getStackTrace:()[Ljava/lang/StackTraceElement;
      23: astore_2
      24: aload_1
      25: aload_2
      26: iconst_1
      27: aload_2
      28: arraylength
      29: invokestatic  #11                 // Method java/util/Arrays.copyOfRange:([Ljava/lang/Object;II)[Ljava/lang/Object;
      32: checkcast     #12                 // class "[Ljava/lang/StackTraceElement;"
      35: invokevirtual #19                 // Method java/lang/IllegalStateException.setStackTrace:([Ljava/lang/StackTraceElement;)V
      38: aload_1
      39: areturn

  protected java.lang.String notAConnectRequest$str();
    Code:
       0: ldc           #255                // String UT000117: Request was not a CONNECT request
       2: areturn

  public final java.lang.IllegalStateException notAConnectRequest();
    Code:
       0: new           #15                 // class java/lang/IllegalStateException
       3: dup
       4: aload_0
       5: invokevirtual #256                // Method notAConnectRequest$str:()Ljava/lang/String;
       8: iconst_0
       9: anewarray     #7                  // class java/lang/Object
      12: invokestatic  #8                  // Method java/lang/String.format:(Ljava/lang/String;[Ljava/lang/Object;)Ljava/lang/String;
      15: invokespecial #17                 // Method java/lang/IllegalStateException."<init>":(Ljava/lang/String;)V
      18: astore_1
      19: aload_1
      20: invokevirtual #18                 // Method java/lang/IllegalStateException.getStackTrace:()[Ljava/lang/StackTraceElement;
      23: astore_2
      24: aload_1
      25: aload_2
      26: iconst_1
      27: aload_2
      28: arraylength
      29: invokestatic  #11                 // Method java/util/Arrays.copyOfRange:([Ljava/lang/Object;II)[Ljava/lang/Object;
      32: checkcast     #12                 // class "[Ljava/lang/StackTraceElement;"
      35: invokevirtual #19                 // Method java/lang/IllegalStateException.setStackTrace:([Ljava/lang/StackTraceElement;)V
      38: aload_1
      39: areturn

  protected java.lang.String cannotResetBuffer$str();
    Code:
       0: ldc_w         #257                // String UT000118: Cannot reset buffer, response has already been commited
       3: areturn

  public final java.lang.IllegalStateException cannotResetBuffer();
    Code:
       0: new           #15                 // class java/lang/IllegalStateException
       3: dup
       4: aload_0
       5: invokevirtual #258                // Method cannotResetBuffer$str:()Ljava/lang/String;
       8: iconst_0
       9: anewarray     #7                  // class java/lang/Object
      12: invokestatic  #8                  // Method java/lang/String.format:(Ljava/lang/String;[Ljava/lang/Object;)Ljava/lang/String;
      15: invokespecial #17                 // Method java/lang/IllegalStateException."<init>":(Ljava/lang/String;)V
      18: astore_1
      19: aload_1
      20: invokevirtual #18                 // Method java/lang/IllegalStateException.getStackTrace:()[Ljava/lang/StackTraceElement;
      23: astore_2
      24: aload_1
      25: aload_2
      26: iconst_1
      27: aload_2
      28: arraylength
      29: invokestatic  #11                 // Method java/util/Arrays.copyOfRange:([Ljava/lang/Object;II)[Ljava/lang/Object;
      32: checkcast     #12                 // class "[Ljava/lang/StackTraceElement;"
      35: invokevirtual #19                 // Method java/lang/IllegalStateException.setStackTrace:([Ljava/lang/StackTraceElement;)V
      38: aload_1
      39: areturn

  protected java.lang.String http2PriRequestFailed$str();
    Code:
       0: ldc_w         #259                // String UT000119: HTTP2 via prior knowledge failed
       3: areturn

  public final java.io.IOException http2PriRequestFailed();
    Code:
       0: new           #37                 // class java/io/IOException
       3: dup
       4: aload_0
       5: invokevirtual #260                // Method http2PriRequestFailed$str:()Ljava/lang/String;
       8: iconst_0
       9: anewarray     #7                  // class java/lang/Object
      12: invokestatic  #8                  // Method java/lang/String.format:(Ljava/lang/String;[Ljava/lang/Object;)Ljava/lang/String;
      15: invokespecial #39                 // Method java/io/IOException."<init>":(Ljava/lang/String;)V
      18: astore_1
      19: aload_1
      20: invokevirtual #40                 // Method java/io/IOException.getStackTrace:()[Ljava/lang/StackTraceElement;
      23: astore_2
      24: aload_1
      25: aload_2
      26: iconst_1
      27: aload_2
      28: arraylength
      29: invokestatic  #11                 // Method java/util/Arrays.copyOfRange:([Ljava/lang/Object;II)[Ljava/lang/Object;
      32: checkcast     #12                 // class "[Ljava/lang/StackTraceElement;"
      35: invokevirtual #41                 // Method java/io/IOException.setStackTrace:([Ljava/lang/StackTraceElement;)V
      38: aload_1
      39: areturn

  protected java.lang.String outOfBandResponseNotSupported$str();
    Code:
       0: ldc_w         #261                // String UT000120: Out of band responses are not allowed for this connector
       3: areturn

  public final java.lang.IllegalStateException outOfBandResponseNotSupported();
    Code:
       0: new           #15                 // class java/lang/IllegalStateException
       3: dup
       4: aload_0
       5: invokevirtual #262                // Method outOfBandResponseNotSupported$str:()Ljava/lang/String;
       8: iconst_0
       9: anewarray     #7                  // class java/lang/Object
      12: invokestatic  #8                  // Method java/lang/String.format:(Ljava/lang/String;[Ljava/lang/Object;)Ljava/lang/String;
      15: invokespecial #17                 // Method java/lang/IllegalStateException."<init>":(Ljava/lang/String;)V
      18: astore_1
      19: aload_1
      20: invokevirtual #18                 // Method java/lang/IllegalStateException.getStackTrace:()[Ljava/lang/StackTraceElement;
      23: astore_2
      24: aload_1
      25: aload_2
      26: iconst_1
      27: aload_2
      28: arraylength
      29: invokestatic  #11                 // Method java/util/Arrays.copyOfRange:([Ljava/lang/Object;II)[Ljava/lang/Object;
      32: checkcast     #12                 // class "[Ljava/lang/StackTraceElement;"
      35: invokevirtual #19                 // Method java/lang/IllegalStateException.setStackTrace:([Ljava/lang/StackTraceElement;)V
      38: aload_1
      39: areturn

  protected java.lang.String tooManySessions$str();
    Code:
       0: ldc_w         #263                // String UT000121: Session was rejected as the maximum number of sessions (%s) has been hit
       3: areturn

  public final java.lang.IllegalStateException tooManySessions(int);
    Code:
       0: new           #15                 // class java/lang/IllegalStateException
       3: dup
       4: aload_0
       5: invokevirtual #264                // Method tooManySessions$str:()Ljava/lang/String;
       8: iconst_1
       9: anewarray     #7                  // class java/lang/Object
      12: dup
      13: iconst_0
      14: iload_1
      15: invokestatic  #94                 // Method java/lang/Integer.valueOf:(I)Ljava/lang/Integer;
      18: aastore
      19: invokestatic  #8                  // Method java/lang/String.format:(Ljava/lang/String;[Ljava/lang/Object;)Ljava/lang/String;
      22: invokespecial #17                 // Method java/lang/IllegalStateException."<init>":(Ljava/lang/String;)V
      25: astore_2
      26: aload_2
      27: invokevirtual #18                 // Method java/lang/IllegalStateException.getStackTrace:()[Ljava/lang/StackTraceElement;
      30: astore_3
      31: aload_2
      32: aload_3
      33: iconst_1
      34: aload_3
      35: arraylength
      36: invokestatic  #11                 // Method java/util/Arrays.copyOfRange:([Ljava/lang/Object;II)[Ljava/lang/Object;
      39: checkcast     #12                 // class "[Ljava/lang/StackTraceElement;"
      42: invokevirtual #19                 // Method java/lang/IllegalStateException.setStackTrace:([Ljava/lang/StackTraceElement;)V
      45: aload_2
      46: areturn

  protected java.lang.String proxyConnectionFailed$str();
    Code:
       0: ldc_w         #265                // String UT000122: CONNECT attempt failed as target proxy returned %s
       3: areturn

  public final java.io.IOException proxyConnectionFailed(int);
    Code:
       0: new           #37                 // class java/io/IOException
       3: dup
       4: aload_0
       5: invokevirtual #266                // Method proxyConnectionFailed$str:()Ljava/lang/String;
       8: iconst_1
       9: anewarray     #7                  // class java/lang/Object
      12: dup
      13: iconst_0
      14: iload_1
      15: invokestatic  #94                 // Method java/lang/Integer.valueOf:(I)Ljava/lang/Integer;
      18: aastore
      19: invokestatic  #8                  // Method java/lang/String.format:(Ljava/lang/String;[Ljava/lang/Object;)Ljava/lang/String;
      22: invokespecial #39                 // Method java/io/IOException."<init>":(Ljava/lang/String;)V
      25: astore_2
      26: aload_2
      27: invokevirtual #40                 // Method java/io/IOException.getStackTrace:()[Ljava/lang/StackTraceElement;
      30: astore_3
      31: aload_2
      32: aload_3
      33: iconst_1
      34: aload_3
      35: arraylength
      36: invokestatic  #11                 // Method java/util/Arrays.copyOfRange:([Ljava/lang/Object;II)[Ljava/lang/Object;
      39: checkcast     #12                 // class "[Ljava/lang/StackTraceElement;"
      42: invokevirtual #41                 // Method java/io/IOException.setStackTrace:([Ljava/lang/StackTraceElement;)V
      45: aload_2
      46: areturn

  protected java.lang.String mcmpMessageRejectedDueToSuspiciousCharacters$str();
    Code:
       0: ldc_w         #267                // String UT000123: MCMP message %s rejected due to suspicious characters
       3: areturn

  public final java.lang.RuntimeException mcmpMessageRejectedDueToSuspiciousCharacters(java.lang.String);
    Code:
       0: new           #85                 // class java/lang/RuntimeException
       3: dup
       4: aload_0
       5: invokevirtual #268                // Method mcmpMessageRejectedDueToSuspiciousCharacters$str:()Ljava/lang/String;
       8: iconst_1
       9: anewarray     #7                  // class java/lang/Object
      12: dup
      13: iconst_0
      14: aload_1
      15: aastore
      16: invokestatic  #8                  // Method java/lang/String.format:(Ljava/lang/String;[Ljava/lang/Object;)Ljava/lang/String;
      19: invokespecial #87                 // Method java/lang/RuntimeException."<init>":(Ljava/lang/String;)V
      22: astore_2
      23: aload_2
      24: invokevirtual #88                 // Method java/lang/RuntimeException.getStackTrace:()[Ljava/lang/StackTraceElement;
      27: astore_3
      28: aload_2
      29: aload_3
      30: iconst_1
      31: aload_3
      32: arraylength
      33: invokestatic  #11                 // Method java/util/Arrays.copyOfRange:([Ljava/lang/Object;II)[Ljava/lang/Object;
      36: checkcast     #12                 // class "[Ljava/lang/StackTraceElement;"
      39: invokevirtual #89                 // Method java/lang/RuntimeException.setStackTrace:([Ljava/lang/StackTraceElement;)V
      42: aload_2
      43: areturn

  protected java.lang.String rengotiationTimedOut$str();
    Code:
       0: ldc_w         #269                // String UT000124: renegotiation timed out
       3: areturn

  public final java.lang.IllegalStateException rengotiationTimedOut();
    Code:
       0: new           #15                 // class java/lang/IllegalStateException
       3: dup
       4: aload_0
       5: invokevirtual #270                // Method rengotiationTimedOut$str:()Ljava/lang/String;
       8: iconst_0
       9: anewarray     #7                  // class java/lang/Object
      12: invokestatic  #8                  // Method java/lang/String.format:(Ljava/lang/String;[Ljava/lang/Object;)Ljava/lang/String;
      15: invokespecial #17                 // Method java/lang/IllegalStateException."<init>":(Ljava/lang/String;)V
      18: astore_1
      19: aload_1
      20: invokevirtual #18                 // Method java/lang/IllegalStateException.getStackTrace:()[Ljava/lang/StackTraceElement;
      23: astore_2
      24: aload_1
      25: aload_2
      26: iconst_1
      27: aload_2
      28: arraylength
      29: invokestatic  #11                 // Method java/util/Arrays.copyOfRange:([Ljava/lang/Object;II)[Ljava/lang/Object;
      32: checkcast     #12                 // class "[Ljava/lang/StackTraceElement;"
      35: invokevirtual #19                 // Method java/lang/IllegalStateException.setStackTrace:([Ljava/lang/StackTraceElement;)V
      38: aload_1
      39: areturn

  protected java.lang.String requestBodyAlreadyRead$str();
    Code:
       0: ldc_w         #271                // String UT000125: Request body already read
       3: areturn

  public final java.lang.IllegalStateException requestBodyAlreadyRead();
    Code:
       0: new           #15                 // class java/lang/IllegalStateException
       3: dup
       4: aload_0
       5: invokevirtual #272                // Method requestBodyAlreadyRead$str:()Ljava/lang/String;
       8: iconst_0
       9: anewarray     #7                  // class java/lang/Object
      12: invokestatic  #8                  // Method java/lang/String.format:(Ljava/lang/String;[Ljava/lang/Object;)Ljava/lang/String;
      15: invokespecial #17                 // Method java/lang/IllegalStateException."<init>":(Ljava/lang/String;)V
      18: astore_1
      19: aload_1
      20: invokevirtual #18                 // Method java/lang/IllegalStateException.getStackTrace:()[Ljava/lang/StackTraceElement;
      23: astore_2
      24: aload_1
      25: aload_2
      26: iconst_1
      27: aload_2
      28: arraylength
      29: invokestatic  #11                 // Method java/util/Arrays.copyOfRange:([Ljava/lang/Object;II)[Ljava/lang/Object;
      32: checkcast     #12                 // class "[Ljava/lang/StackTraceElement;"
      35: invokevirtual #19                 // Method java/lang/IllegalStateException.setStackTrace:([Ljava/lang/StackTraceElement;)V
      38: aload_1
      39: areturn

  protected java.lang.String blockingIoFromIOThread$str();
    Code:
       0: ldc_w         #273                // String UT000126: Attempted to do blocking IO from the IO thread. This is prohibited as it may result in deadlocks
       3: areturn

  public final java.lang.IllegalStateException blockingIoFromIOThread();
    Code:
       0: new           #15                 // class java/lang/IllegalStateException
       3: dup
       4: aload_0
       5: invokevirtual #274                // Method blockingIoFromIOThread$str:()Ljava/lang/String;
       8: iconst_0
       9: anewarray     #7                  // class java/lang/Object
      12: invokestatic  #8                  // Method java/lang/String.format:(Ljava/lang/String;[Ljava/lang/Object;)Ljava/lang/String;
      15: invokespecial #17                 // Method java/lang/IllegalStateException."<init>":(Ljava/lang/String;)V
      18: astore_1
      19: aload_1
      20: invokevirtual #18                 // Method java/lang/IllegalStateException.getStackTrace:()[Ljava/lang/StackTraceElement;
      23: astore_2
      24: aload_1
      25: aload_2
      26: iconst_1
      27: aload_2
      28: arraylength
      29: invokestatic  #11                 // Method java/util/Arrays.copyOfRange:([Ljava/lang/Object;II)[Ljava/lang/Object;
      32: checkcast     #12                 // class "[Ljava/lang/StackTraceElement;"
      35: invokevirtual #19                 // Method java/lang/IllegalStateException.setStackTrace:([Ljava/lang/StackTraceElement;)V
      38: aload_1
      39: areturn

  protected java.lang.String responseComplete$str();
    Code:
       0: ldc_w         #275                // String UT000127: Response has already been sent
       3: areturn

  public final java.lang.IllegalStateException responseComplete();
    Code:
       0: new           #15                 // class java/lang/IllegalStateException
       3: dup
       4: aload_0
       5: invokevirtual #276                // Method responseComplete$str:()Ljava/lang/String;
       8: iconst_0
       9: anewarray     #7                  // class java/lang/Object
      12: invokestatic  #8                  // Method java/lang/String.format:(Ljava/lang/String;[Ljava/lang/Object;)Ljava/lang/String;
      15: invokespecial #17                 // Method java/lang/IllegalStateException."<init>":(Ljava/lang/String;)V
      18: astore_1
      19: aload_1
      20: invokevirtual #18                 // Method java/lang/IllegalStateException.getStackTrace:()[Ljava/lang/StackTraceElement;
      23: astore_2
      24: aload_1
      25: aload_2
      26: iconst_1
      27: aload_2
      28: arraylength
      29: invokestatic  #11                 // Method java/util/Arrays.copyOfRange:([Ljava/lang/Object;II)[Ljava/lang/Object;
      32: checkcast     #12                 // class "[Ljava/lang/StackTraceElement;"
      35: invokevirtual #19                 // Method java/lang/IllegalStateException.setStackTrace:([Ljava/lang/StackTraceElement;)V
      38: aload_1
      39: areturn

  protected java.lang.String couldNotReadContentLengthData$str();
    Code:
       0: ldc_w         #277                // String UT000128: Remote peer closed connection before all data could be read
       3: areturn

  public final java.io.IOException couldNotReadContentLengthData();
    Code:
       0: new           #37                 // class java/io/IOException
       3: dup
       4: aload_0
       5: invokevirtual #278                // Method couldNotReadContentLengthData$str:()Ljava/lang/String;
       8: iconst_0
       9: anewarray     #7                  // class java/lang/Object
      12: invokestatic  #8                  // Method java/lang/String.format:(Ljava/lang/String;[Ljava/lang/Object;)Ljava/lang/String;
      15: invokespecial #39                 // Method java/io/IOException."<init>":(Ljava/lang/String;)V
      18: astore_1
      19: aload_1
      20: invokevirtual #40                 // Method java/io/IOException.getStackTrace:()[Ljava/lang/StackTraceElement;
      23: astore_2
      24: aload_1
      25: aload_2
      26: iconst_1
      27: aload_2
      28: arraylength
      29: invokestatic  #11                 // Method java/util/Arrays.copyOfRange:([Ljava/lang/Object;II)[Ljava/lang/Object;
      32: checkcast     #12                 // class "[Ljava/lang/StackTraceElement;"
      35: invokevirtual #41                 // Method java/io/IOException.setStackTrace:([Ljava/lang/StackTraceElement;)V
      38: aload_1
      39: areturn

  protected java.lang.String failedToSendAfterBeingSafe$str();
    Code:
       0: ldc_w         #279                // String UT000129: Failed to send after being safe to send
       3: areturn

  public final java.lang.IllegalStateException failedToSendAfterBeingSafe();
    Code:
       0: new           #15                 // class java/lang/IllegalStateException
       3: dup
       4: aload_0
       5: invokevirtual #280                // Method failedToSendAfterBeingSafe$str:()Ljava/lang/String;
       8: iconst_0
       9: anewarray     #7                  // class java/lang/Object
      12: invokestatic  #8                  // Method java/lang/String.format:(Ljava/lang/String;[Ljava/lang/Object;)Ljava/lang/String;
      15: invokespecial #17                 // Method java/lang/IllegalStateException."<init>":(Ljava/lang/String;)V
      18: astore_1
      19: aload_1
      20: invokevirtual #18                 // Method java/lang/IllegalStateException.getStackTrace:()[Ljava/lang/StackTraceElement;
      23: astore_2
      24: aload_1
      25: aload_2
      26: iconst_1
      27: aload_2
      28: arraylength
      29: invokestatic  #11                 // Method java/util/Arrays.copyOfRange:([Ljava/lang/Object;II)[Ljava/lang/Object;
      32: checkcast     #12                 // class "[Ljava/lang/StackTraceElement;"
      35: invokevirtual #19                 // Method java/lang/IllegalStateException.setStackTrace:([Ljava/lang/StackTraceElement;)V
      38: aload_1
      39: areturn

  protected java.lang.String reasonPhraseToLargeForBuffer$str();
    Code:
       0: ldc_w         #281                // String UT000130: HTTP reason phrase was too large for the buffer. Either provide a smaller message or a bigger buffer. Phrase: %s
       3: areturn

  public final java.lang.IllegalStateException reasonPhraseToLargeForBuffer(java.lang.String);
    Code:
       0: new           #15                 // class java/lang/IllegalStateException
       3: dup
       4: aload_0
       5: invokevirtual #282                // Method reasonPhraseToLargeForBuffer$str:()Ljava/lang/String;
       8: iconst_1
       9: anewarray     #7                  // class java/lang/Object
      12: dup
      13: iconst_0
      14: aload_1
      15: aastore
      16: invokestatic  #8                  // Method java/lang/String.format:(Ljava/lang/String;[Ljava/lang/Object;)Ljava/lang/String;
      19: invokespecial #17                 // Method java/lang/IllegalStateException."<init>":(Ljava/lang/String;)V
      22: astore_2
      23: aload_2
      24: invokevirtual #18                 // Method java/lang/IllegalStateException.getStackTrace:()[Ljava/lang/StackTraceElement;
      27: astore_3
      28: aload_2
      29: aload_3
      30: iconst_1
      31: aload_3
      32: arraylength
      33: invokestatic  #11                 // Method java/util/Arrays.copyOfRange:([Ljava/lang/Object;II)[Ljava/lang/Object;
      36: checkcast     #12                 // class "[Ljava/lang/StackTraceElement;"
      39: invokevirtual #19                 // Method java/lang/IllegalStateException.setStackTrace:([Ljava/lang/StackTraceElement;)V
      42: aload_2
      43: areturn

  protected java.lang.String poolIsClosed$str();
    Code:
       0: ldc_w         #283                // String UT000131: Buffer pool is closed
       3: areturn

  public final java.lang.IllegalStateException poolIsClosed();
    Code:
       0: new           #15                 // class java/lang/IllegalStateException
       3: dup
       4: aload_0
       5: invokevirtual #284                // Method poolIsClosed$str:()Ljava/lang/String;
       8: iconst_0
       9: anewarray     #7                  // class java/lang/Object
      12: invokestatic  #8                  // Method java/lang/String.format:(Ljava/lang/String;[Ljava/lang/Object;)Ljava/lang/String;
      15: invokespecial #17                 // Method java/lang/IllegalStateException."<init>":(Ljava/lang/String;)V
      18: astore_1
      19: aload_1
      20: invokevirtual #18                 // Method java/lang/IllegalStateException.getStackTrace:()[Ljava/lang/StackTraceElement;
      23: astore_2
      24: aload_1
      25: aload_2
      26: iconst_1
      27: aload_2
      28: arraylength
      29: invokestatic  #11                 // Method java/util/Arrays.copyOfRange:([Ljava/lang/Object;II)[Ljava/lang/Object;
      32: checkcast     #12                 // class "[Ljava/lang/StackTraceElement;"
      35: invokevirtual #19                 // Method java/lang/IllegalStateException.setStackTrace:([Ljava/lang/StackTraceElement;)V
      38: aload_1
      39: areturn

  protected java.lang.String hpackFailed$str();
    Code:
       0: ldc_w         #285                // String UT000132: HPACK decode failed
       3: areturn

  public final io.undertow.protocols.http2.HpackException hpackFailed();
    Code:
       0: new           #235                // class io/undertow/protocols/http2/HpackException
       3: dup
       4: invokespecial #236                // Method io/undertow/protocols/http2/HpackException."<init>":()V
       7: astore_1
       8: aload_1
       9: invokevirtual #237                // Method io/undertow/protocols/http2/HpackException.getStackTrace:()[Ljava/lang/StackTraceElement;
      12: astore_2
      13: aload_1
      14: aload_2
      15: iconst_1
      16: aload_2
      17: arraylength
      18: invokestatic  #11                 // Method java/util/Arrays.copyOfRange:([Ljava/lang/Object;II)[Ljava/lang/Object;
      21: checkcast     #12                 // class "[Ljava/lang/StackTraceElement;"
      24: invokevirtual #238                // Method io/undertow/protocols/http2/HpackException.setStackTrace:([Ljava/lang/StackTraceElement;)V
      27: aload_1
      28: areturn

  protected java.lang.String notAnUpgradeRequest$str();
    Code:
       0: ldc_w         #286                // String UT000133: Request did not contain an Upgrade header, upgrade is not permitted
       3: areturn

  public final java.lang.IllegalStateException notAnUpgradeRequest();
    Code:
       0: new           #15                 // class java/lang/IllegalStateException
       3: dup
       4: aload_0
       5: invokevirtual #287                // Method notAnUpgradeRequest$str:()Ljava/lang/String;
       8: iconst_0
       9: anewarray     #7                  // class java/lang/Object
      12: invokestatic  #8                  // Method java/lang/String.format:(Ljava/lang/String;[Ljava/lang/Object;)Ljava/lang/String;
      15: invokespecial #17                 // Method java/lang/IllegalStateException."<init>":(Ljava/lang/String;)V
      18: astore_1
      19: aload_1
      20: invokevirtual #18                 // Method java/lang/IllegalStateException.getStackTrace:()[Ljava/lang/StackTraceElement;
      23: astore_2
      24: aload_1
      25: aload_2
      26: iconst_1
      27: aload_2
      28: arraylength
      29: invokestatic  #11                 // Method java/util/Arrays.copyOfRange:([Ljava/lang/Object;II)[Ljava/lang/Object;
      32: checkcast     #12                 // class "[Ljava/lang/StackTraceElement;"
      35: invokevirtual #19                 // Method java/lang/IllegalStateException.setStackTrace:([Ljava/lang/StackTraceElement;)V
      38: aload_1
      39: areturn

  protected java.lang.String authenticationPropertyNotSet$str();
    Code:
       0: ldc_w         #288                // String UT000134: Authentication mechanism %s requires property %s to be set
       3: areturn

  public final java.lang.IllegalStateException authenticationPropertyNotSet(java.lang.String, java.lang.String);
    Code:
       0: new           #15                 // class java/lang/IllegalStateException
       3: dup
       4: aload_0
       5: invokevirtual #289                // Method authenticationPropertyNotSet$str:()Ljava/lang/String;
       8: iconst_2
       9: anewarray     #7                  // class java/lang/Object
      12: dup
      13: iconst_0
      14: aload_1
      15: aastore
      16: dup
      17: iconst_1
      18: aload_2
      19: aastore
      20: invokestatic  #8                  // Method java/lang/String.format:(Ljava/lang/String;[Ljava/lang/Object;)Ljava/lang/String;
      23: invokespecial #17                 // Method java/lang/IllegalStateException."<init>":(Ljava/lang/String;)V
      26: astore_3
      27: aload_3
      28: invokevirtual #18                 // Method java/lang/IllegalStateException.getStackTrace:()[Ljava/lang/StackTraceElement;
      31: astore        4
      33: aload_3
      34: aload         4
      36: iconst_1
      37: aload         4
      39: arraylength
      40: invokestatic  #11                 // Method java/util/Arrays.copyOfRange:([Ljava/lang/Object;II)[Ljava/lang/Object;
      43: checkcast     #12                 // class "[Ljava/lang/StackTraceElement;"
      46: invokevirtual #19                 // Method java/lang/IllegalStateException.setStackTrace:([Ljava/lang/StackTraceElement;)V
      49: aload_3
      50: areturn

  protected java.lang.String rengotiationFailed$str();
    Code:
       0: ldc_w         #290                // String UT000135: renegotiation failed
       3: areturn

  public final java.lang.IllegalStateException rengotiationFailed();
    Code:
       0: new           #15                 // class java/lang/IllegalStateException
       3: dup
       4: aload_0
       5: invokevirtual #291                // Method rengotiationFailed$str:()Ljava/lang/String;
       8: iconst_0
       9: anewarray     #7                  // class java/lang/Object
      12: invokestatic  #8                  // Method java/lang/String.format:(Ljava/lang/String;[Ljava/lang/Object;)Ljava/lang/String;
      15: invokespecial #17                 // Method java/lang/IllegalStateException."<init>":(Ljava/lang/String;)V
      18: astore_1
      19: aload_1
      20: invokevirtual #18                 // Method java/lang/IllegalStateException.getStackTrace:()[Ljava/lang/StackTraceElement;
      23: astore_2
      24: aload_1
      25: aload_2
      26: iconst_1
      27: aload_2
      28: arraylength
      29: invokestatic  #11                 // Method java/util/Arrays.copyOfRange:([Ljava/lang/Object;II)[Ljava/lang/Object;
      32: checkcast     #12                 // class "[Ljava/lang/StackTraceElement;"
      35: invokevirtual #19                 // Method java/lang/IllegalStateException.setStackTrace:([Ljava/lang/StackTraceElement;)V
      38: aload_1
      39: areturn

  protected java.lang.String userAgentCharsetMustHaveEvenNumberOfItems$str();
    Code:
       0: ldc_w         #292                // String UT000136: User agent charset string must have an even number of items, in the form pattern,charset,pattern,charset,... Instead got: %s
       3: areturn

  public final java.lang.IllegalArgumentException userAgentCharsetMustHaveEvenNumberOfItems(java.lang.String);
    Code:
       0: new           #5                  // class java/lang/IllegalArgumentException
       3: dup
       4: aload_0
       5: invokevirtual #293                // Method userAgentCharsetMustHaveEvenNumberOfItems$str:()Ljava/lang/String;
       8: iconst_1
       9: anewarray     #7                  // class java/lang/Object
      12: dup
      13: iconst_0
      14: aload_1
      15: aastore
      16: invokestatic  #8                  // Method java/lang/String.format:(Ljava/lang/String;[Ljava/lang/Object;)Ljava/lang/String;
      19: invokespecial #9                  // Method java/lang/IllegalArgumentException."<init>":(Ljava/lang/String;)V
      22: astore_2
      23: aload_2
      24: invokevirtual #10                 // Method java/lang/IllegalArgumentException.getStackTrace:()[Ljava/lang/StackTraceElement;
      27: astore_3
      28: aload_2
      29: aload_3
      30: iconst_1
      31: aload_3
      32: arraylength
      33: invokestatic  #11                 // Method java/util/Arrays.copyOfRange:([Ljava/lang/Object;II)[Ljava/lang/Object;
      36: checkcast     #12                 // class "[Ljava/lang/StackTraceElement;"
      39: invokevirtual #13                 // Method java/lang/IllegalArgumentException.setStackTrace:([Ljava/lang/StackTraceElement;)V
      42: aload_2
      43: areturn

  protected java.lang.String datasourceNotFound$str();
    Code:
       0: ldc_w         #294                // String UT000137: Could not find the datasource called %s
       3: areturn

  public final java.lang.IllegalArgumentException datasourceNotFound(java.lang.String);
    Code:
       0: new           #5                  // class java/lang/IllegalArgumentException
       3: dup
       4: aload_0
       5: invokevirtual #295                // Method datasourceNotFound$str:()Ljava/lang/String;
       8: iconst_1
       9: anewarray     #7                  // class java/lang/Object
      12: dup
      13: iconst_0
      14: aload_1
      15: aastore
      16: invokestatic  #8                  // Method java/lang/String.format:(Ljava/lang/String;[Ljava/lang/Object;)Ljava/lang/String;
      19: invokespecial #9                  // Method java/lang/IllegalArgumentException."<init>":(Ljava/lang/String;)V
      22: astore_2
      23: aload_2
      24: invokevirtual #10                 // Method java/lang/IllegalArgumentException.getStackTrace:()[Ljava/lang/StackTraceElement;
      27: astore_3
      28: aload_2
      29: aload_3
      30: iconst_1
      31: aload_3
      32: arraylength
      33: invokestatic  #11                 // Method java/util/Arrays.copyOfRange:([Ljava/lang/Object;II)[Ljava/lang/Object;
      36: checkcast     #12                 // class "[Ljava/lang/StackTraceElement;"
      39: invokevirtual #13                 // Method java/lang/IllegalArgumentException.setStackTrace:([Ljava/lang/StackTraceElement;)V
      42: aload_2
      43: areturn

  protected java.lang.String exchangeAlreadyComplete$str();
    Code:
       0: ldc_w         #296                // String UT000139: Exchange already complete
       3: areturn

  public final java.lang.IllegalStateException exchangeAlreadyComplete();
    Code:
       0: new           #15                 // class java/lang/IllegalStateException
       3: dup
       4: aload_0
       5: invokevirtual #297                // Method exchangeAlreadyComplete$str:()Ljava/lang/String;
       8: iconst_0
       9: anewarray     #7                  // class java/lang/Object
      12: invokestatic  #8                  // Method java/lang/String.format:(Ljava/lang/String;[Ljava/lang/Object;)Ljava/lang/String;
      15: invokespecial #17                 // Method java/lang/IllegalStateException."<init>":(Ljava/lang/String;)V
      18: astore_1
      19: aload_1
      20: invokevirtual #18                 // Method java/lang/IllegalStateException.getStackTrace:()[Ljava/lang/StackTraceElement;
      23: astore_2
      24: aload_1
      25: aload_2
      26: iconst_1
      27: aload_2
      28: arraylength
      29: invokestatic  #11                 // Method java/util/Arrays.copyOfRange:([Ljava/lang/Object;II)[Ljava/lang/Object;
      32: checkcast     #12                 // class "[Ljava/lang/StackTraceElement;"
      35: invokevirtual #19                 // Method java/lang/IllegalStateException.setStackTrace:([Ljava/lang/StackTraceElement;)V
      38: aload_1
      39: areturn

  protected java.lang.String newlineNotSupportedInHttpString$str();
    Code:
       0: ldc_w         #298                // String UT000149: HttpString is not allowed to contain newlines. value: %s
       3: areturn

  public final java.lang.IllegalArgumentException newlineNotSupportedInHttpString(java.lang.String);
    Code:
       0: new           #5                  // class java/lang/IllegalArgumentException
       3: dup
       4: aload_0
       5: invokevirtual #299                // Method newlineNotSupportedInHttpString$str:()Ljava/lang/String;
       8: iconst_1
       9: anewarray     #7                  // class java/lang/Object
      12: dup
      13: iconst_0
      14: aload_1
      15: aastore
      16: invokestatic  #8                  // Method java/lang/String.format:(Ljava/lang/String;[Ljava/lang/Object;)Ljava/lang/String;
      19: invokespecial #9                  // Method java/lang/IllegalArgumentException."<init>":(Ljava/lang/String;)V
      22: astore_2
      23: aload_2
      24: invokevirtual #10                 // Method java/lang/IllegalArgumentException.getStackTrace:()[Ljava/lang/StackTraceElement;
      27: astore_3
      28: aload_2
      29: aload_3
      30: iconst_1
      31: aload_3
      32: arraylength
      33: invokestatic  #11                 // Method java/util/Arrays.copyOfRange:([Ljava/lang/Object;II)[Ljava/lang/Object;
      36: checkcast     #12                 // class "[Ljava/lang/StackTraceElement;"
      39: invokevirtual #13                 // Method java/lang/IllegalArgumentException.setStackTrace:([Ljava/lang/StackTraceElement;)V
      42: aload_2
      43: areturn

  static {};
    Code:
       0: new           #3                  // class io/undertow/UndertowMessages_$bundle
       3: dup
       4: invokespecial #300                // Method "<init>":()V
       7: putstatic     #2                  // Field INSTANCE:Lio/undertow/UndertowMessages_$bundle;
      10: return
}
