Compiled from "SerializationCopyStrategy.java"
public class net.sf.ehcache.store.compound.SerializationCopyStrategy implements net.sf.ehcache.store.compound.ReadWriteCopyStrategy<net.sf.ehcache.Element> {
  private final net.sf.ehcache.store.compound.ReadWriteSerializationCopyStrategy copyStrategy;

  public net.sf.ehcache.store.compound.SerializationCopyStrategy();
    Code:
       0: aload_0
       1: invokespecial #1                  // Method java/lang/Object."<init>":()V
       4: aload_0
       5: new           #2                  // class net/sf/ehcache/store/compound/ReadWriteSerializationCopyStrategy
       8: dup
       9: invokespecial #3                  // Method net/sf/ehcache/store/compound/ReadWriteSerializationCopyStrategy."<init>":()V
      12: putfield      #4                  // Field copyStrategy:Lnet/sf/ehcache/store/compound/ReadWriteSerializationCopyStrategy;
      15: return

  public net.sf.ehcache.Element copyForWrite(net.sf.ehcache.Element);
    Code:
       0: aload_0
       1: getfield      #4                  // Field copyStrategy:Lnet/sf/ehcache/store/compound/ReadWriteSerializationCopyStrategy;
       4: aload_0
       5: getfield      #4                  // Field copyStrategy:Lnet/sf/ehcache/store/compound/ReadWriteSerializationCopyStrategy;
       8: aload_1
       9: invokevirtual #5                  // Method net/sf/ehcache/store/compound/ReadWriteSerializationCopyStrategy.copyForWrite:(Lnet/sf/ehcache/Element;)Lnet/sf/ehcache/Element;
      12: invokevirtual #6                  // Method net/sf/ehcache/store/compound/ReadWriteSerializationCopyStrategy.copyForRead:(Lnet/sf/ehcache/Element;)Lnet/sf/ehcache/Element;
      15: areturn

  public net.sf.ehcache.Element copyForRead(net.sf.ehcache.Element);
    Code:
       0: aload_0
       1: getfield      #4                  // Field copyStrategy:Lnet/sf/ehcache/store/compound/ReadWriteSerializationCopyStrategy;
       4: aload_0
       5: getfield      #4                  // Field copyStrategy:Lnet/sf/ehcache/store/compound/ReadWriteSerializationCopyStrategy;
       8: aload_1
       9: invokevirtual #5                  // Method net/sf/ehcache/store/compound/ReadWriteSerializationCopyStrategy.copyForWrite:(Lnet/sf/ehcache/Element;)Lnet/sf/ehcache/Element;
      12: invokevirtual #6                  // Method net/sf/ehcache/store/compound/ReadWriteSerializationCopyStrategy.copyForRead:(Lnet/sf/ehcache/Element;)Lnet/sf/ehcache/Element;
      15: areturn

  public java.lang.Object copyForRead(java.lang.Object);
    Code:
       0: aload_0
       1: aload_1
       2: checkcast     #7                  // class net/sf/ehcache/Element
       5: invokevirtual #8                  // Method copyForRead:(Lnet/sf/ehcache/Element;)Lnet/sf/ehcache/Element;
       8: areturn

  public java.lang.Object copyForWrite(java.lang.Object);
    Code:
       0: aload_0
       1: aload_1
       2: checkcast     #7                  // class net/sf/ehcache/Element
       5: invokevirtual #9                  // Method copyForWrite:(Lnet/sf/ehcache/Element;)Lnet/sf/ehcache/Element;
       8: areturn
}
