Compiled from "OgmTableGenerator.java"
public class org.hibernate.ogm.id.impl.OgmTableGenerator implements org.hibernate.id.PersistentIdentifierGenerator,org.hibernate.id.Configurable {
  private static final org.hibernate.ogm.util.impl.Log log;

  public static final java.lang.String CONFIG_PREFER_SEGMENT_PER_ENTITY;

  public static final java.lang.String TABLE_PARAM;

  public static final java.lang.String DEF_TABLE;

  public static final java.lang.String VALUE_COLUMN_PARAM;

  public static final java.lang.String DEF_VALUE_COLUMN;

  public static final java.lang.String SEGMENT_COLUMN_PARAM;

  public static final java.lang.String DEF_SEGMENT_COLUMN;

  public static final java.lang.String SEGMENT_VALUE_PARAM;

  public static final java.lang.String DEF_SEGMENT_VALUE;

  public static final java.lang.String SEGMENT_LENGTH_PARAM;

  public static final int DEF_SEGMENT_LENGTH;

  public static final java.lang.String INITIAL_PARAM;

  public static final int DEFAULT_INITIAL_VALUE;

  public static final java.lang.String INCREMENT_PARAM;

  public static final int DEFAULT_INCREMENT_SIZE;

  public static final java.lang.String OPT_PARAM;

  private org.hibernate.type.Type identifierType;

  private java.lang.String tableName;

  private java.lang.String segmentColumnName;

  private java.lang.String segmentValue;

  private int segmentValueLength;

  private java.lang.String valueColumnName;

  private int initialValue;

  private int incrementSize;

  private java.lang.String selectQuery;

  private java.lang.String insertQuery;

  private java.lang.String updateQuery;

  private org.hibernate.id.enhanced.Optimizer optimizer;

  private long accessCount;

  private volatile org.hibernate.ogm.type.GridType identifierValueGridType;

  private org.hibernate.ogm.type.GridType segmentGridType;

  private volatile org.hibernate.ogm.dialect.GridDialect gridDialect;

  public org.hibernate.ogm.id.impl.OgmTableGenerator();
    Code:
       0: aload_0
       1: invokespecial #1                  // Method java/lang/Object."<init>":()V
       4: aload_0
       5: lconst_0
       6: putfield      #2                  // Field accessCount:J
       9: aload_0
      10: getstatic     #3                  // Field org/hibernate/ogm/type/StringType.INSTANCE:Lorg/hibernate/ogm/type/StringType;
      13: putfield      #4                  // Field segmentGridType:Lorg/hibernate/ogm/type/GridType;
      16: return

  public java.lang.Object generatorKey();
    Code:
       0: aload_0
       1: getfield      #5                  // Field tableName:Ljava/lang/String;
       4: areturn

  public final org.hibernate.type.Type getIdentifierType();
    Code:
       0: aload_0
       1: getfield      #6                  // Field identifierType:Lorg/hibernate/type/Type;
       4: areturn

  public final java.lang.String getTableName();
    Code:
       0: aload_0
       1: getfield      #5                  // Field tableName:Ljava/lang/String;
       4: areturn

  public final java.lang.String getSegmentColumnName();
    Code:
       0: aload_0
       1: getfield      #7                  // Field segmentColumnName:Ljava/lang/String;
       4: areturn

  public final java.lang.String getSegmentValue();
    Code:
       0: aload_0
       1: getfield      #8                  // Field segmentValue:Ljava/lang/String;
       4: areturn

  public final int getSegmentValueLength();
    Code:
       0: aload_0
       1: getfield      #9                  // Field segmentValueLength:I
       4: ireturn

  public final java.lang.String getValueColumnName();
    Code:
       0: aload_0
       1: getfield      #10                 // Field valueColumnName:Ljava/lang/String;
       4: areturn

  public final int getInitialValue();
    Code:
       0: aload_0
       1: getfield      #11                 // Field initialValue:I
       4: ireturn

  public final int getIncrementSize();
    Code:
       0: aload_0
       1: getfield      #12                 // Field incrementSize:I
       4: ireturn

  public final org.hibernate.id.enhanced.Optimizer getOptimizer();
    Code:
       0: aload_0
       1: getfield      #13                 // Field optimizer:Lorg/hibernate/id/enhanced/Optimizer;
       4: areturn

  public final long getTableAccessCount();
    Code:
       0: aload_0
       1: getfield      #2                  // Field accessCount:J
       4: lreturn

  public void configure(org.hibernate.type.Type, java.util.Properties, org.hibernate.dialect.Dialect) throws org.hibernate.MappingException;
    Code:
       0: aload_0
       1: aload_1
       2: putfield      #6                  // Field identifierType:Lorg/hibernate/type/Type;
       5: aload_0
       6: aload_0
       7: aload_2
       8: aload_3
       9: invokevirtual #14                 // Method determineGeneratorTableName:(Ljava/util/Properties;Lorg/hibernate/dialect/Dialect;)Ljava/lang/String;
      12: putfield      #5                  // Field tableName:Ljava/lang/String;
      15: aload_0
      16: aload_0
      17: aload_2
      18: aload_3
      19: invokevirtual #15                 // Method determineSegmentColumnName:(Ljava/util/Properties;Lorg/hibernate/dialect/Dialect;)Ljava/lang/String;
      22: putfield      #7                  // Field segmentColumnName:Ljava/lang/String;
      25: aload_0
      26: aload_0
      27: aload_2
      28: aload_3
      29: invokevirtual #16                 // Method determineValueColumnName:(Ljava/util/Properties;Lorg/hibernate/dialect/Dialect;)Ljava/lang/String;
      32: putfield      #10                 // Field valueColumnName:Ljava/lang/String;
      35: aload_0
      36: aload_0
      37: aload_2
      38: invokevirtual #17                 // Method determineSegmentValue:(Ljava/util/Properties;)Ljava/lang/String;
      41: putfield      #8                  // Field segmentValue:Ljava/lang/String;
      44: aload_0
      45: aload_0
      46: aload_2
      47: invokevirtual #18                 // Method determineSegmentColumnSize:(Ljava/util/Properties;)I
      50: putfield      #9                  // Field segmentValueLength:I
      53: aload_0
      54: aload_0
      55: aload_2
      56: invokevirtual #19                 // Method determineInitialValue:(Ljava/util/Properties;)I
      59: putfield      #11                 // Field initialValue:I
      62: aload_0
      63: aload_0
      64: aload_2
      65: invokevirtual #20                 // Method determineIncrementSize:(Ljava/util/Properties;)I
      68: putfield      #12                 // Field incrementSize:I
      71: ldc           #21                 // String hibernate.id.optimizer.pooled.prefer_lo
      73: aload_2
      74: iconst_0
      75: invokestatic  #22                 // Method org/hibernate/internal/util/config/ConfigurationHelper.getBoolean:(Ljava/lang/String;Ljava/util/Map;Z)Z
      78: ifeq          86
      81: ldc           #23                 // String pooled-lo
      83: goto          88
      86: ldc           #24                 // String pooled
      88: astore        4
      90: aload_0
      91: getfield      #12                 // Field incrementSize:I
      94: iconst_1
      95: if_icmpgt     104
      98: getstatic     #25                 // Field org/hibernate/id/enhanced/OptimizerFactory.NONE:Ljava/lang/String;
     101: goto          106
     104: aload         4
     106: astore        5
     108: ldc           #26                 // String optimizer
     110: aload_2
     111: aload         5
     113: invokestatic  #27                 // Method org/hibernate/internal/util/config/ConfigurationHelper.getString:(Ljava/lang/String;Ljava/util/Map;Ljava/lang/String;)Ljava/lang/String;
     116: astore        6
     118: aload_0
     119: aload         6
     121: aload_0
     122: getfield      #6                  // Field identifierType:Lorg/hibernate/type/Type;
     125: invokeinterface #28,  1           // InterfaceMethod org/hibernate/type/Type.getReturnedClass:()Ljava/lang/Class;
     130: aload_0
     131: getfield      #12                 // Field incrementSize:I
     134: ldc           #29                 // String initial_value
     136: aload_2
     137: iconst_m1
     138: invokestatic  #30                 // Method org/hibernate/internal/util/config/ConfigurationHelper.getInt:(Ljava/lang/String;Ljava/util/Map;I)I
     141: i2l
     142: invokestatic  #31                 // Method org/hibernate/id/enhanced/OptimizerFactory.buildOptimizer:(Ljava/lang/String;Ljava/lang/Class;IJ)Lorg/hibernate/id/enhanced/Optimizer;
     145: putfield      #13                 // Field optimizer:Lorg/hibernate/id/enhanced/Optimizer;
     148: return

  protected java.lang.String determineGeneratorTableName(java.util.Properties, org.hibernate.dialect.Dialect);
    Code:
       0: ldc           #32                 // String table_name
       2: aload_1
       3: ldc           #33                 // String hibernate_sequences
       5: invokestatic  #27                 // Method org/hibernate/internal/util/config/ConfigurationHelper.getString:(Ljava/lang/String;Ljava/util/Map;Ljava/lang/String;)Ljava/lang/String;
       8: astore_3
       9: aload_3
      10: bipush        46
      12: invokevirtual #34                 // Method java/lang/String.indexOf:(I)I
      15: ifge          22
      18: iconst_1
      19: goto          23
      22: iconst_0
      23: istore        4
      25: iload         4
      27: ifeq          95
      30: aload_1
      31: ldc           #35                 // String identifier_normalizer
      33: invokevirtual #36                 // Method java/util/Properties.get:(Ljava/lang/Object;)Ljava/lang/Object;
      36: checkcast     #37                 // class org/hibernate/cfg/ObjectNameNormalizer
      39: astore        5
      41: aload         5
      43: aload_3
      44: invokevirtual #38                 // Method org/hibernate/cfg/ObjectNameNormalizer.normalizeIdentifierQuoting:(Ljava/lang/String;)Ljava/lang/String;
      47: astore_3
      48: aload         5
      50: aload_1
      51: ldc           #39                 // String schema
      53: invokevirtual #40                 // Method java/util/Properties.getProperty:(Ljava/lang/String;)Ljava/lang/String;
      56: invokevirtual #38                 // Method org/hibernate/cfg/ObjectNameNormalizer.normalizeIdentifierQuoting:(Ljava/lang/String;)Ljava/lang/String;
      59: astore        6
      61: aload         5
      63: aload_1
      64: ldc           #41                 // String catalog
      66: invokevirtual #40                 // Method java/util/Properties.getProperty:(Ljava/lang/String;)Ljava/lang/String;
      69: invokevirtual #38                 // Method org/hibernate/cfg/ObjectNameNormalizer.normalizeIdentifierQuoting:(Ljava/lang/String;)Ljava/lang/String;
      72: astore        7
      74: aload_2
      75: aload         7
      77: invokevirtual #42                 // Method org/hibernate/dialect/Dialect.quote:(Ljava/lang/String;)Ljava/lang/String;
      80: aload_2
      81: aload         6
      83: invokevirtual #42                 // Method org/hibernate/dialect/Dialect.quote:(Ljava/lang/String;)Ljava/lang/String;
      86: aload_2
      87: aload_3
      88: invokevirtual #42                 // Method org/hibernate/dialect/Dialect.quote:(Ljava/lang/String;)Ljava/lang/String;
      91: invokestatic  #43                 // Method org/hibernate/mapping/Table.qualify:(Ljava/lang/String;Ljava/lang/String;Ljava/lang/String;)Ljava/lang/String;
      94: astore_3
      95: aload_3
      96: areturn

  protected java.lang.String determineSegmentColumnName(java.util.Properties, org.hibernate.dialect.Dialect);
    Code:
       0: aload_1
       1: ldc           #35                 // String identifier_normalizer
       3: invokevirtual #36                 // Method java/util/Properties.get:(Ljava/lang/Object;)Ljava/lang/Object;
       6: checkcast     #37                 // class org/hibernate/cfg/ObjectNameNormalizer
       9: astore_3
      10: ldc           #44                 // String segment_column_name
      12: aload_1
      13: ldc           #45                 // String sequence_name
      15: invokestatic  #27                 // Method org/hibernate/internal/util/config/ConfigurationHelper.getString:(Ljava/lang/String;Ljava/util/Map;Ljava/lang/String;)Ljava/lang/String;
      18: astore        4
      20: aload_2
      21: aload_3
      22: aload         4
      24: invokevirtual #38                 // Method org/hibernate/cfg/ObjectNameNormalizer.normalizeIdentifierQuoting:(Ljava/lang/String;)Ljava/lang/String;
      27: invokevirtual #42                 // Method org/hibernate/dialect/Dialect.quote:(Ljava/lang/String;)Ljava/lang/String;
      30: areturn

  protected java.lang.String determineValueColumnName(java.util.Properties, org.hibernate.dialect.Dialect);
    Code:
       0: aload_1
       1: ldc           #35                 // String identifier_normalizer
       3: invokevirtual #36                 // Method java/util/Properties.get:(Ljava/lang/Object;)Ljava/lang/Object;
       6: checkcast     #37                 // class org/hibernate/cfg/ObjectNameNormalizer
       9: astore_3
      10: ldc           #46                 // String value_column_name
      12: aload_1
      13: ldc           #47                 // String next_val
      15: invokestatic  #27                 // Method org/hibernate/internal/util/config/ConfigurationHelper.getString:(Ljava/lang/String;Ljava/util/Map;Ljava/lang/String;)Ljava/lang/String;
      18: astore        4
      20: aload_2
      21: aload_3
      22: aload         4
      24: invokevirtual #38                 // Method org/hibernate/cfg/ObjectNameNormalizer.normalizeIdentifierQuoting:(Ljava/lang/String;)Ljava/lang/String;
      27: invokevirtual #42                 // Method org/hibernate/dialect/Dialect.quote:(Ljava/lang/String;)Ljava/lang/String;
      30: areturn

  protected java.lang.String determineSegmentValue(java.util.Properties);
    Code:
       0: aload_1
       1: ldc           #48                 // String segment_value
       3: invokevirtual #40                 // Method java/util/Properties.getProperty:(Ljava/lang/String;)Ljava/lang/String;
       6: astore_2
       7: aload_2
       8: invokestatic  #49                 // Method org/hibernate/internal/util/StringHelper.isEmpty:(Ljava/lang/String;)Z
      11: ifeq          20
      14: aload_0
      15: aload_1
      16: invokevirtual #50                 // Method determineDefaultSegmentValue:(Ljava/util/Properties;)Ljava/lang/String;
      19: astore_2
      20: aload_2
      21: areturn

  protected java.lang.String determineDefaultSegmentValue(java.util.Properties);
    Code:
       0: ldc           #51                 // String prefer_entity_table_as_segment_value
       2: aload_1
       3: iconst_0
       4: invokestatic  #22                 // Method org/hibernate/internal/util/config/ConfigurationHelper.getBoolean:(Ljava/lang/String;Ljava/util/Map;Z)Z
       7: istore_2
       8: iload_2
       9: ifeq          21
      12: aload_1
      13: ldc           #52                 // String target_table
      15: invokevirtual #40                 // Method java/util/Properties.getProperty:(Ljava/lang/String;)Ljava/lang/String;
      18: goto          23
      21: ldc           #53                 // String default
      23: astore_3
      24: getstatic     #54                 // Field log:Lorg/hibernate/ogm/util/impl/Log;
      27: new           #55                 // class java/lang/StringBuilder
      30: dup
      31: invokespecial #56                 // Method java/lang/StringBuilder."<init>":()V
      34: ldc           #57                 // String explicit segment value for id generator [
      36: invokevirtual #58                 // Method java/lang/StringBuilder.append:(Ljava/lang/String;)Ljava/lang/StringBuilder;
      39: aload_0
      40: getfield      #5                  // Field tableName:Ljava/lang/String;
      43: invokevirtual #58                 // Method java/lang/StringBuilder.append:(Ljava/lang/String;)Ljava/lang/StringBuilder;
      46: bipush        46
      48: invokevirtual #59                 // Method java/lang/StringBuilder.append:(C)Ljava/lang/StringBuilder;
      51: aload_0
      52: getfield      #7                  // Field segmentColumnName:Ljava/lang/String;
      55: invokevirtual #58                 // Method java/lang/StringBuilder.append:(Ljava/lang/String;)Ljava/lang/StringBuilder;
      58: ldc           #60                 // String ] suggested; using default [
      60: invokevirtual #58                 // Method java/lang/StringBuilder.append:(Ljava/lang/String;)Ljava/lang/StringBuilder;
      63: aload_3
      64: invokevirtual #58                 // Method java/lang/StringBuilder.append:(Ljava/lang/String;)Ljava/lang/StringBuilder;
      67: ldc           #61                 // String ]
      69: invokevirtual #58                 // Method java/lang/StringBuilder.append:(Ljava/lang/String;)Ljava/lang/StringBuilder;
      72: invokevirtual #62                 // Method java/lang/StringBuilder.toString:()Ljava/lang/String;
      75: invokeinterface #63,  2           // InterfaceMethod org/hibernate/ogm/util/impl/Log.info:(Ljava/lang/Object;)V
      80: aload_3
      81: areturn

  protected int determineSegmentColumnSize(java.util.Properties);
    Code:
       0: ldc           #64                 // String segment_value_length
       2: aload_1
       3: sipush        255
       6: invokestatic  #30                 // Method org/hibernate/internal/util/config/ConfigurationHelper.getInt:(Ljava/lang/String;Ljava/util/Map;I)I
       9: ireturn

  protected int determineInitialValue(java.util.Properties);
    Code:
       0: ldc           #29                 // String initial_value
       2: aload_1
       3: iconst_1
       4: invokestatic  #30                 // Method org/hibernate/internal/util/config/ConfigurationHelper.getInt:(Ljava/lang/String;Ljava/util/Map;I)I
       7: ireturn

  protected int determineIncrementSize(java.util.Properties);
    Code:
       0: ldc           #65                 // String increment_size
       2: aload_1
       3: iconst_1
       4: invokestatic  #30                 // Method org/hibernate/internal/util/config/ConfigurationHelper.getInt:(Ljava/lang/String;Ljava/util/Map;I)I
       7: ireturn

  protected java.lang.String buildSelectQuery(org.hibernate.dialect.Dialect);
    Code:
       0: ldc           #66                 // String tbl
       2: astore_2
       3: new           #55                 // class java/lang/StringBuilder
       6: dup
       7: invokespecial #56                 // Method java/lang/StringBuilder."<init>":()V
      10: ldc           #67                 // String select
      12: invokevirtual #58                 // Method java/lang/StringBuilder.append:(Ljava/lang/String;)Ljava/lang/StringBuilder;
      15: ldc           #66                 // String tbl
      17: aload_0
      18: getfield      #10                 // Field valueColumnName:Ljava/lang/String;
      21: invokestatic  #68                 // Method org/hibernate/internal/util/StringHelper.qualify:(Ljava/lang/String;Ljava/lang/String;)Ljava/lang/String;
      24: invokevirtual #58                 // Method java/lang/StringBuilder.append:(Ljava/lang/String;)Ljava/lang/StringBuilder;
      27: ldc           #69                 // String  from
      29: invokevirtual #58                 // Method java/lang/StringBuilder.append:(Ljava/lang/String;)Ljava/lang/StringBuilder;
      32: aload_0
      33: getfield      #5                  // Field tableName:Ljava/lang/String;
      36: invokevirtual #58                 // Method java/lang/StringBuilder.append:(Ljava/lang/String;)Ljava/lang/StringBuilder;
      39: bipush        32
      41: invokevirtual #59                 // Method java/lang/StringBuilder.append:(C)Ljava/lang/StringBuilder;
      44: ldc           #66                 // String tbl
      46: invokevirtual #58                 // Method java/lang/StringBuilder.append:(Ljava/lang/String;)Ljava/lang/StringBuilder;
      49: ldc           #70                 // String  where
      51: invokevirtual #58                 // Method java/lang/StringBuilder.append:(Ljava/lang/String;)Ljava/lang/StringBuilder;
      54: ldc           #66                 // String tbl
      56: aload_0
      57: getfield      #7                  // Field segmentColumnName:Ljava/lang/String;
      60: invokestatic  #68                 // Method org/hibernate/internal/util/StringHelper.qualify:(Ljava/lang/String;Ljava/lang/String;)Ljava/lang/String;
      63: invokevirtual #58                 // Method java/lang/StringBuilder.append:(Ljava/lang/String;)Ljava/lang/StringBuilder;
      66: ldc           #71                 // String =?
      68: invokevirtual #58                 // Method java/lang/StringBuilder.append:(Ljava/lang/String;)Ljava/lang/StringBuilder;
      71: invokevirtual #62                 // Method java/lang/StringBuilder.toString:()Ljava/lang/String;
      74: astore_3
      75: new           #72                 // class org/hibernate/LockOptions
      78: dup
      79: getstatic     #73                 // Field org/hibernate/LockMode.PESSIMISTIC_WRITE:Lorg/hibernate/LockMode;
      82: invokespecial #74                 // Method org/hibernate/LockOptions."<init>":(Lorg/hibernate/LockMode;)V
      85: astore        4
      87: aload         4
      89: ldc           #66                 // String tbl
      91: getstatic     #73                 // Field org/hibernate/LockMode.PESSIMISTIC_WRITE:Lorg/hibernate/LockMode;
      94: invokevirtual #75                 // Method org/hibernate/LockOptions.setAliasSpecificLockMode:(Ljava/lang/String;Lorg/hibernate/LockMode;)Lorg/hibernate/LockOptions;
      97: pop
      98: ldc           #66                 // String tbl
     100: iconst_1
     101: anewarray     #76                 // class java/lang/String
     104: dup
     105: iconst_0
     106: aload_0
     107: getfield      #10                 // Field valueColumnName:Ljava/lang/String;
     110: aastore
     111: invokestatic  #77                 // Method java/util/Collections.singletonMap:(Ljava/lang/Object;Ljava/lang/Object;)Ljava/util/Map;
     114: astore        5
     116: aload_1
     117: aload_3
     118: aload         4
     120: aload         5
     122: invokevirtual #78                 // Method org/hibernate/dialect/Dialect.applyLocksToSql:(Ljava/lang/String;Lorg/hibernate/LockOptions;Ljava/util/Map;)Ljava/lang/String;
     125: areturn

  protected java.lang.String buildUpdateQuery();
    Code:
       0: new           #55                 // class java/lang/StringBuilder
       3: dup
       4: invokespecial #56                 // Method java/lang/StringBuilder."<init>":()V
       7: ldc           #79                 // String update
       9: invokevirtual #58                 // Method java/lang/StringBuilder.append:(Ljava/lang/String;)Ljava/lang/StringBuilder;
      12: aload_0
      13: getfield      #5                  // Field tableName:Ljava/lang/String;
      16: invokevirtual #58                 // Method java/lang/StringBuilder.append:(Ljava/lang/String;)Ljava/lang/StringBuilder;
      19: ldc           #80                 // String  set
      21: invokevirtual #58                 // Method java/lang/StringBuilder.append:(Ljava/lang/String;)Ljava/lang/StringBuilder;
      24: aload_0
      25: getfield      #10                 // Field valueColumnName:Ljava/lang/String;
      28: invokevirtual #58                 // Method java/lang/StringBuilder.append:(Ljava/lang/String;)Ljava/lang/StringBuilder;
      31: ldc           #81                 // String =?
      33: invokevirtual #58                 // Method java/lang/StringBuilder.append:(Ljava/lang/String;)Ljava/lang/StringBuilder;
      36: ldc           #70                 // String  where
      38: invokevirtual #58                 // Method java/lang/StringBuilder.append:(Ljava/lang/String;)Ljava/lang/StringBuilder;
      41: aload_0
      42: getfield      #10                 // Field valueColumnName:Ljava/lang/String;
      45: invokevirtual #58                 // Method java/lang/StringBuilder.append:(Ljava/lang/String;)Ljava/lang/StringBuilder;
      48: ldc           #82                 // String =? and
      50: invokevirtual #58                 // Method java/lang/StringBuilder.append:(Ljava/lang/String;)Ljava/lang/StringBuilder;
      53: aload_0
      54: getfield      #7                  // Field segmentColumnName:Ljava/lang/String;
      57: invokevirtual #58                 // Method java/lang/StringBuilder.append:(Ljava/lang/String;)Ljava/lang/StringBuilder;
      60: ldc           #71                 // String =?
      62: invokevirtual #58                 // Method java/lang/StringBuilder.append:(Ljava/lang/String;)Ljava/lang/StringBuilder;
      65: invokevirtual #62                 // Method java/lang/StringBuilder.toString:()Ljava/lang/String;
      68: areturn

  protected java.lang.String buildInsertQuery();
    Code:
       0: new           #55                 // class java/lang/StringBuilder
       3: dup
       4: invokespecial #56                 // Method java/lang/StringBuilder."<init>":()V
       7: ldc           #83                 // String insert into
       9: invokevirtual #58                 // Method java/lang/StringBuilder.append:(Ljava/lang/String;)Ljava/lang/StringBuilder;
      12: aload_0
      13: getfield      #5                  // Field tableName:Ljava/lang/String;
      16: invokevirtual #58                 // Method java/lang/StringBuilder.append:(Ljava/lang/String;)Ljava/lang/StringBuilder;
      19: ldc           #84                 // String  (
      21: invokevirtual #58                 // Method java/lang/StringBuilder.append:(Ljava/lang/String;)Ljava/lang/StringBuilder;
      24: aload_0
      25: getfield      #7                  // Field segmentColumnName:Ljava/lang/String;
      28: invokevirtual #58                 // Method java/lang/StringBuilder.append:(Ljava/lang/String;)Ljava/lang/StringBuilder;
      31: ldc           #85                 // String ,
      33: invokevirtual #58                 // Method java/lang/StringBuilder.append:(Ljava/lang/String;)Ljava/lang/StringBuilder;
      36: aload_0
      37: getfield      #10                 // Field valueColumnName:Ljava/lang/String;
      40: invokevirtual #58                 // Method java/lang/StringBuilder.append:(Ljava/lang/String;)Ljava/lang/StringBuilder;
      43: ldc           #86                 // String )
      45: invokevirtual #58                 // Method java/lang/StringBuilder.append:(Ljava/lang/String;)Ljava/lang/StringBuilder;
      48: ldc           #87                 // String  values (?,?)
      50: invokevirtual #58                 // Method java/lang/StringBuilder.append:(Ljava/lang/String;)Ljava/lang/StringBuilder;
      53: invokevirtual #62                 // Method java/lang/StringBuilder.toString:()Ljava/lang/String;
      56: areturn

  public synchronized java.io.Serializable generate(org.hibernate.engine.spi.SessionImplementor, java.lang.Object);
    Code:
       0: aload_0
       1: getfield      #13                 // Field optimizer:Lorg/hibernate/id/enhanced/Optimizer;
       4: new           #88                 // class org/hibernate/ogm/id/impl/OgmTableGenerator$1
       7: dup
       8: aload_0
       9: aload_1
      10: invokespecial #89                 // Method org/hibernate/ogm/id/impl/OgmTableGenerator$1."<init>":(Lorg/hibernate/ogm/id/impl/OgmTableGenerator;Lorg/hibernate/engine/spi/SessionImplementor;)V
      13: invokeinterface #90,  2           // InterfaceMethod org/hibernate/id/enhanced/Optimizer.generate:(Lorg/hibernate/id/enhanced/AccessCallback;)Ljava/io/Serializable;
      18: areturn

  public java.io.Serializable doWorkInIsolationTransaction(org.hibernate.engine.spi.SessionImplementor) throws org.hibernate.HibernateException;
    Code:
       0: iconst_0
       1: istore_2
       2: new           #91                 // class org/hibernate/ogm/id/impl/OgmTableGenerator$1Work
       5: dup
       6: aload_0
       7: aload_1
       8: invokespecial #92                 // Method org/hibernate/ogm/id/impl/OgmTableGenerator$1Work."<init>":(Lorg/hibernate/ogm/id/impl/OgmTableGenerator;Lorg/hibernate/engine/spi/SessionImplementor;)V
      11: astore_3
      12: aload_1
      13: invokeinterface #93,  1           // InterfaceMethod org/hibernate/engine/spi/SessionImplementor.getTransactionCoordinator:()Lorg/hibernate/engine/transaction/spi/TransactionCoordinator;
      18: invokeinterface #94,  1           // InterfaceMethod org/hibernate/engine/transaction/spi/TransactionCoordinator.getTransaction:()Lorg/hibernate/engine/transaction/spi/TransactionImplementor;
      23: invokeinterface #95,  1           // InterfaceMethod org/hibernate/engine/transaction/spi/TransactionImplementor.createIsolationDelegate:()Lorg/hibernate/engine/transaction/spi/IsolationDelegate;
      28: aload_3
      29: iload_2
      30: invokeinterface #96,  3           // InterfaceMethod org/hibernate/engine/transaction/spi/IsolationDelegate.delegateWork:(Lorg/hibernate/jdbc/WorkExecutorVisitable;Z)Ljava/lang/Object;
      35: checkcast     #97                 // class java/io/Serializable
      38: astore        4
      40: aload         4
      42: areturn

  public org.hibernate.id.IntegralDataTypeHolder doWorkInCurrentTransactionIfAny(org.hibernate.engine.spi.SessionImplementor);
    Code:
       0: aload_0
       1: aload_1
       2: invokespecial #98                 // Method defineGridTypes:(Lorg/hibernate/engine/spi/SessionImplementor;)V
       5: aload_0
       6: aload_0
       7: getfield      #4                  // Field segmentGridType:Lorg/hibernate/ogm/type/GridType;
      10: aload_0
      11: getfield      #8                  // Field segmentValue:Ljava/lang/String;
      14: aload_0
      15: getfield      #7                  // Field segmentColumnName:Ljava/lang/String;
      18: aload_1
      19: invokespecial #99                 // Method nullSafeSet:(Lorg/hibernate/ogm/type/GridType;Ljava/lang/Object;Ljava/lang/String;Lorg/hibernate/engine/spi/SessionImplementor;)Ljava/lang/Object;
      22: astore_2
      23: new           #100                // class org/hibernate/ogm/grid/RowKey
      26: dup
      27: aload_0
      28: getfield      #5                  // Field tableName:Ljava/lang/String;
      31: iconst_1
      32: anewarray     #76                 // class java/lang/String
      35: dup
      36: iconst_0
      37: aload_0
      38: getfield      #7                  // Field segmentColumnName:Ljava/lang/String;
      41: aastore
      42: iconst_1
      43: anewarray     #101                // class java/lang/Object
      46: dup
      47: iconst_0
      48: aload_2
      49: aastore
      50: invokespecial #102                // Method org/hibernate/ogm/grid/RowKey."<init>":(Ljava/lang/String;[Ljava/lang/String;[Ljava/lang/Object;)V
      53: astore_3
      54: aload_0
      55: aload_1
      56: invokespecial #103                // Method getDialect:(Lorg/hibernate/engine/spi/SessionImplementor;)Lorg/hibernate/ogm/dialect/GridDialect;
      59: astore        4
      61: aload_0
      62: getfield      #6                  // Field identifierType:Lorg/hibernate/type/Type;
      65: invokeinterface #28,  1           // InterfaceMethod org/hibernate/type/Type.getReturnedClass:()Ljava/lang/Class;
      70: invokestatic  #104                // Method org/hibernate/id/IdentifierGeneratorHelper.getIntegralDataTypeHolder:(Ljava/lang/Class;)Lorg/hibernate/id/IntegralDataTypeHolder;
      73: astore        5
      75: aload         4
      77: aload_3
      78: aload         5
      80: aload_0
      81: getfield      #13                 // Field optimizer:Lorg/hibernate/id/enhanced/Optimizer;
      84: invokeinterface #105,  1          // InterfaceMethod org/hibernate/id/enhanced/Optimizer.applyIncrementSizeToSourceValues:()Z
      89: ifeq          99
      92: aload_0
      93: getfield      #12                 // Field incrementSize:I
      96: goto          100
      99: iconst_1
     100: aload_0
     101: getfield      #11                 // Field initialValue:I
     104: invokeinterface #106,  5          // InterfaceMethod org/hibernate/ogm/dialect/GridDialect.nextValue:(Lorg/hibernate/ogm/grid/RowKey;Lorg/hibernate/id/IntegralDataTypeHolder;II)V
     109: aload_0
     110: dup
     111: getfield      #2                  // Field accessCount:J
     114: lconst_1
     115: ladd
     116: putfield      #2                  // Field accessCount:J
     119: aload         5
     121: areturn

  private org.hibernate.ogm.dialect.GridDialect getDialect(org.hibernate.engine.spi.SessionImplementor);
    Code:
       0: aload_0
       1: getfield      #107                // Field gridDialect:Lorg/hibernate/ogm/dialect/GridDialect;
       4: ifnonnull     38
       7: aload_0
       8: aload_1
       9: invokeinterface #108,  1          // InterfaceMethod org/hibernate/engine/spi/SessionImplementor.getFactory:()Lorg/hibernate/engine/spi/SessionFactoryImplementor;
      14: invokeinterface #109,  1          // InterfaceMethod org/hibernate/engine/spi/SessionFactoryImplementor.getServiceRegistry:()Lorg/hibernate/service/spi/ServiceRegistryImplementor;
      19: ldc_w         #110                // class org/hibernate/ogm/datastore/impl/DatastoreServices
      22: invokeinterface #111,  2          // InterfaceMethod org/hibernate/service/spi/ServiceRegistryImplementor.getService:(Ljava/lang/Class;)Lorg/hibernate/service/Service;
      27: checkcast     #110                // class org/hibernate/ogm/datastore/impl/DatastoreServices
      30: invokeinterface #112,  1          // InterfaceMethod org/hibernate/ogm/datastore/impl/DatastoreServices.getGridDialect:()Lorg/hibernate/ogm/dialect/GridDialect;
      35: putfield      #107                // Field gridDialect:Lorg/hibernate/ogm/dialect/GridDialect;
      38: aload_0
      39: getfield      #107                // Field gridDialect:Lorg/hibernate/ogm/dialect/GridDialect;
      42: areturn

  private java.lang.Object nullSafeSet(org.hibernate.ogm.type.GridType, java.lang.Object, java.lang.String, org.hibernate.engine.spi.SessionImplementor);
    Code:
       0: new           #113                // class org/hibernate/ogm/datastore/spi/Tuple
       3: dup
       4: getstatic     #114                // Field org/hibernate/ogm/datastore/impl/EmptyTupleSnapshot.SINGLETON:Lorg/hibernate/ogm/datastore/spi/TupleSnapshot;
       7: invokespecial #115                // Method org/hibernate/ogm/datastore/spi/Tuple."<init>":(Lorg/hibernate/ogm/datastore/spi/TupleSnapshot;)V
      10: astore        5
      12: aload_1
      13: aload         5
      15: aload_2
      16: iconst_1
      17: anewarray     #76                 // class java/lang/String
      20: dup
      21: iconst_0
      22: aload_3
      23: aastore
      24: aload         4
      26: invokeinterface #116,  5          // InterfaceMethod org/hibernate/ogm/type/GridType.nullSafeSet:(Lorg/hibernate/ogm/datastore/spi/Tuple;Ljava/lang/Object;[Ljava/lang/String;Lorg/hibernate/engine/spi/SessionImplementor;)V
      31: aload         5
      33: aload_3
      34: invokevirtual #117                // Method org/hibernate/ogm/datastore/spi/Tuple.get:(Ljava/lang/String;)Ljava/lang/Object;
      37: areturn

  private void defineGridTypes(org.hibernate.engine.spi.SessionImplementor);
    Code:
       0: aload_0
       1: getfield      #118                // Field identifierValueGridType:Lorg/hibernate/ogm/type/GridType;
       4: ifnonnull     47
       7: aload_1
       8: invokeinterface #108,  1          // InterfaceMethod org/hibernate/engine/spi/SessionImplementor.getFactory:()Lorg/hibernate/engine/spi/SessionFactoryImplementor;
      13: invokeinterface #109,  1          // InterfaceMethod org/hibernate/engine/spi/SessionFactoryImplementor.getServiceRegistry:()Lorg/hibernate/service/spi/ServiceRegistryImplementor;
      18: astore_2
      19: aload_0
      20: aload_2
      21: ldc_w         #119                // class org/hibernate/ogm/type/TypeTranslator
      24: invokeinterface #111,  2          // InterfaceMethod org/hibernate/service/spi/ServiceRegistryImplementor.getService:(Ljava/lang/Class;)Lorg/hibernate/service/Service;
      29: checkcast     #119                // class org/hibernate/ogm/type/TypeTranslator
      32: new           #120                // class org/hibernate/type/LongType
      35: dup
      36: invokespecial #121                // Method org/hibernate/type/LongType."<init>":()V
      39: invokeinterface #122,  2          // InterfaceMethod org/hibernate/ogm/type/TypeTranslator.getType:(Lorg/hibernate/type/Type;)Lorg/hibernate/ogm/type/GridType;
      44: putfield      #118                // Field identifierValueGridType:Lorg/hibernate/ogm/type/GridType;
      47: return

  public java.lang.String[] sqlCreateStrings(org.hibernate.dialect.Dialect) throws org.hibernate.HibernateException;
    Code:
       0: iconst_0
       1: anewarray     #76                 // class java/lang/String
       4: areturn

  public java.lang.String[] sqlDropStrings(org.hibernate.dialect.Dialect) throws org.hibernate.HibernateException;
    Code:
       0: iconst_0
       1: anewarray     #76                 // class java/lang/String
       4: areturn

  static {};
    Code:
       0: invokestatic  #123                // Method org/hibernate/ogm/util/impl/LoggerFactory.make:()Lorg/hibernate/ogm/util/impl/Log;
       3: putstatic     #54                 // Field log:Lorg/hibernate/ogm/util/impl/Log;
       6: return
}
