Compiled from "DefaultCommandLatencyCollector.java"
class io.lettuce.core.metrics.DefaultCommandLatencyCollector$Latencies {
  private final org.LatencyUtils.LatencyStats firstResponse;

  private final org.LatencyUtils.LatencyStats completion;

  io.lettuce.core.metrics.DefaultCommandLatencyCollector$Latencies(org.LatencyUtils.PauseDetector);
    Code:
       0: aload_0
       1: invokespecial #3                  // Method java/lang/Object."<init>":()V
       4: aload_0
       5: invokestatic  #4                  // Method org/LatencyUtils/LatencyStats$Builder.create:()Lorg/LatencyUtils/LatencyStats$Builder;
       8: aload_1
       9: invokevirtual #5                  // Method org/LatencyUtils/LatencyStats$Builder.pauseDetector:(Lorg/LatencyUtils/PauseDetector;)Lorg/LatencyUtils/LatencyStats$Builder;
      12: invokevirtual #6                  // Method org/LatencyUtils/LatencyStats$Builder.build:()Lorg/LatencyUtils/LatencyStats;
      15: putfield      #2                  // Field firstResponse:Lorg/LatencyUtils/LatencyStats;
      18: aload_0
      19: invokestatic  #4                  // Method org/LatencyUtils/LatencyStats$Builder.create:()Lorg/LatencyUtils/LatencyStats$Builder;
      22: aload_1
      23: invokevirtual #5                  // Method org/LatencyUtils/LatencyStats$Builder.pauseDetector:(Lorg/LatencyUtils/PauseDetector;)Lorg/LatencyUtils/LatencyStats$Builder;
      26: invokevirtual #6                  // Method org/LatencyUtils/LatencyStats$Builder.build:()Lorg/LatencyUtils/LatencyStats;
      29: putfield      #1                  // Field completion:Lorg/LatencyUtils/LatencyStats;
      32: return

  public org.HdrHistogram.Histogram getFirstResponseHistogram();
    Code:
       0: aload_0
       1: getfield      #2                  // Field firstResponse:Lorg/LatencyUtils/LatencyStats;
       4: invokevirtual #7                  // Method org/LatencyUtils/LatencyStats.getIntervalHistogram:()Lorg/HdrHistogram/Histogram;
       7: areturn

  public org.HdrHistogram.Histogram getCompletionHistogram();
    Code:
       0: aload_0
       1: getfield      #1                  // Field completion:Lorg/LatencyUtils/LatencyStats;
       4: invokevirtual #7                  // Method org/LatencyUtils/LatencyStats.getIntervalHistogram:()Lorg/HdrHistogram/Histogram;
       7: areturn

  public void stop();
    Code:
       0: aload_0
       1: getfield      #2                  // Field firstResponse:Lorg/LatencyUtils/LatencyStats;
       4: invokevirtual #8                  // Method org/LatencyUtils/LatencyStats.stop:()V
       7: aload_0
       8: getfield      #1                  // Field completion:Lorg/LatencyUtils/LatencyStats;
      11: invokevirtual #8                  // Method org/LatencyUtils/LatencyStats.stop:()V
      14: return

  static org.LatencyUtils.LatencyStats access$000(io.lettuce.core.metrics.DefaultCommandLatencyCollector$Latencies);
    Code:
       0: aload_0
       1: getfield      #2                  // Field firstResponse:Lorg/LatencyUtils/LatencyStats;
       4: areturn

  static org.LatencyUtils.LatencyStats access$100(io.lettuce.core.metrics.DefaultCommandLatencyCollector$Latencies);
    Code:
       0: aload_0
       1: getfield      #1                  // Field completion:Lorg/LatencyUtils/LatencyStats;
       4: areturn
}
