Compiled from "WebRequestDataBinder.java"
public class org.springframework.web.bind.support.WebRequestDataBinder extends org.springframework.web.bind.WebDataBinder {
  public org.springframework.web.bind.support.WebRequestDataBinder(java.lang.Object);
    Code:
       0: aload_0
       1: aload_1
       2: invokespecial #1                  // Method org/springframework/web/bind/WebDataBinder."<init>":(Ljava/lang/Object;)V
       5: return

  public org.springframework.web.bind.support.WebRequestDataBinder(java.lang.Object, java.lang.String);
    Code:
       0: aload_0
       1: aload_1
       2: aload_2
       3: invokespecial #2                  // Method org/springframework/web/bind/WebDataBinder."<init>":(Ljava/lang/Object;Ljava/lang/String;)V
       6: return

  public void bind(org.springframework.web.context.request.WebRequest);
    Code:
       0: new           #3                  // class org/springframework/beans/MutablePropertyValues
       3: dup
       4: aload_1
       5: invokeinterface #4,  1            // InterfaceMethod org/springframework/web/context/request/WebRequest.getParameterMap:()Ljava/util/Map;
      10: invokespecial #5                  // Method org/springframework/beans/MutablePropertyValues."<init>":(Ljava/util/Map;)V
      13: astore_2
      14: aload_1
      15: instanceof    #6                  // class org/springframework/web/context/request/NativeWebRequest
      18: ifeq          90
      21: aload_1
      22: checkcast     #6                  // class org/springframework/web/context/request/NativeWebRequest
      25: ldc           #7                  // class org/springframework/web/multipart/MultipartRequest
      27: invokeinterface #8,  2            // InterfaceMethod org/springframework/web/context/request/NativeWebRequest.getNativeRequest:(Ljava/lang/Class;)Ljava/lang/Object;
      32: checkcast     #7                  // class org/springframework/web/multipart/MultipartRequest
      35: astore_3
      36: aload_3
      37: ifnull        54
      40: aload_0
      41: aload_3
      42: invokeinterface #9,  1            // InterfaceMethod org/springframework/web/multipart/MultipartRequest.getMultiFileMap:()Lorg/springframework/util/MultiValueMap;
      47: aload_2
      48: invokevirtual #10                 // Method bindMultipart:(Ljava/util/Map;Lorg/springframework/beans/MutablePropertyValues;)V
      51: goto          90
      54: aload_0
      55: aload_1
      56: invokespecial #11                 // Method isMultipartRequest:(Lorg/springframework/web/context/request/WebRequest;)Z
      59: ifeq          90
      62: aload_1
      63: checkcast     #6                  // class org/springframework/web/context/request/NativeWebRequest
      66: ldc           #12                 // class javax/servlet/http/HttpServletRequest
      68: invokeinterface #8,  2            // InterfaceMethod org/springframework/web/context/request/NativeWebRequest.getNativeRequest:(Ljava/lang/Class;)Ljava/lang/Object;
      73: checkcast     #12                 // class javax/servlet/http/HttpServletRequest
      76: astore        4
      78: aload         4
      80: ifnull        90
      83: aload_0
      84: aload         4
      86: aload_2
      87: invokespecial #13                 // Method bindParts:(Ljavax/servlet/http/HttpServletRequest;Lorg/springframework/beans/MutablePropertyValues;)V
      90: aload_0
      91: aload_2
      92: invokevirtual #14                 // Method doBind:(Lorg/springframework/beans/MutablePropertyValues;)V
      95: return

  private boolean isMultipartRequest(org.springframework.web.context.request.WebRequest);
    Code:
       0: aload_1
       1: ldc           #15                 // String Content-Type
       3: invokeinterface #16,  2           // InterfaceMethod org/springframework/web/context/request/WebRequest.getHeader:(Ljava/lang/String;)Ljava/lang/String;
       8: astore_2
       9: aload_2
      10: ldc           #17                 // String multipart/
      12: invokestatic  #18                 // Method org/springframework/util/StringUtils.startsWithIgnoreCase:(Ljava/lang/String;Ljava/lang/String;)Z
      15: ireturn

  private void bindParts(javax.servlet.http.HttpServletRequest, org.springframework.beans.MutablePropertyValues);
    Code:
       0: new           #19                 // class org/springframework/util/LinkedMultiValueMap
       3: dup
       4: invokespecial #20                 // Method org/springframework/util/LinkedMultiValueMap."<init>":()V
       7: astore_3
       8: aload_1
       9: invokeinterface #21,  1           // InterfaceMethod javax/servlet/http/HttpServletRequest.getParts:()Ljava/util/Collection;
      14: invokeinterface #22,  1           // InterfaceMethod java/util/Collection.iterator:()Ljava/util/Iterator;
      19: astore        4
      21: aload         4
      23: invokeinterface #23,  1           // InterfaceMethod java/util/Iterator.hasNext:()Z
      28: ifeq          61
      31: aload         4
      33: invokeinterface #24,  1           // InterfaceMethod java/util/Iterator.next:()Ljava/lang/Object;
      38: checkcast     #25                 // class javax/servlet/http/Part
      41: astore        5
      43: aload_3
      44: aload         5
      46: invokeinterface #26,  1           // InterfaceMethod javax/servlet/http/Part.getName:()Ljava/lang/String;
      51: aload         5
      53: invokeinterface #27,  3           // InterfaceMethod org/springframework/util/MultiValueMap.add:(Ljava/lang/Object;Ljava/lang/Object;)V
      58: goto          21
      61: aload_3
      62: aload_0
      63: aload_2
      64: invokedynamic #28,  0             // InvokeDynamic #0:accept:(Lorg/springframework/web/bind/support/WebRequestDataBinder;Lorg/springframework/beans/MutablePropertyValues;)Ljava/util/function/BiConsumer;
      69: invokeinterface #29,  2           // InterfaceMethod org/springframework/util/MultiValueMap.forEach:(Ljava/util/function/BiConsumer;)V
      74: goto          89
      77: astore_3
      78: new           #31                 // class org/springframework/web/multipart/MultipartException
      81: dup
      82: ldc           #32                 // String Failed to get request parts
      84: aload_3
      85: invokespecial #33                 // Method org/springframework/web/multipart/MultipartException."<init>":(Ljava/lang/String;Ljava/lang/Throwable;)V
      88: athrow
      89: return
    Exception table:
       from    to  target type
           0    74    77   Class java/lang/Exception

  public void closeNoCatch() throws org.springframework.validation.BindException;
    Code:
       0: aload_0
       1: invokevirtual #34                 // Method getBindingResult:()Lorg/springframework/validation/BindingResult;
       4: invokeinterface #35,  1           // InterfaceMethod org/springframework/validation/BindingResult.hasErrors:()Z
       9: ifeq          24
      12: new           #36                 // class org/springframework/validation/BindException
      15: dup
      16: aload_0
      17: invokevirtual #34                 // Method getBindingResult:()Lorg/springframework/validation/BindingResult;
      20: invokespecial #37                 // Method org/springframework/validation/BindException."<init>":(Lorg/springframework/validation/BindingResult;)V
      23: athrow
      24: return

  private void lambda$bindParts$0(org.springframework.beans.MutablePropertyValues, java.lang.String, java.util.List);
    Code:
       0: aload_3
       1: invokeinterface #38,  1           // InterfaceMethod java/util/List.size:()I
       6: iconst_1
       7: if_icmpne     52
      10: aload_3
      11: iconst_0
      12: invokeinterface #39,  2           // InterfaceMethod java/util/List.get:(I)Ljava/lang/Object;
      17: checkcast     #25                 // class javax/servlet/http/Part
      20: astore        4
      22: aload_0
      23: invokevirtual #40                 // Method isBindEmptyMultipartFiles:()Z
      26: ifne          41
      29: aload         4
      31: invokeinterface #41,  1           // InterfaceMethod javax/servlet/http/Part.getSize:()J
      36: lconst_0
      37: lcmp
      38: ifle          49
      41: aload_1
      42: aload_2
      43: aload         4
      45: invokevirtual #42                 // Method org/springframework/beans/MutablePropertyValues.add:(Ljava/lang/String;Ljava/lang/Object;)Lorg/springframework/beans/MutablePropertyValues;
      48: pop
      49: goto          59
      52: aload_1
      53: aload_2
      54: aload_3
      55: invokevirtual #42                 // Method org/springframework/beans/MutablePropertyValues.add:(Ljava/lang/String;Ljava/lang/Object;)Lorg/springframework/beans/MutablePropertyValues;
      58: pop
      59: return
}
