Compiled from "ReflectionAttributeExtractor.java"
class net.sf.ehcache.search.attribute.ReflectionAttributeExtractor$MethodPart implements net.sf.ehcache.search.attribute.ReflectionAttributeExtractor$Part {
  private final java.lang.String methodName;

  private volatile transient net.sf.ehcache.search.attribute.ReflectionAttributeExtractor$MethodRef cache;

  public net.sf.ehcache.search.attribute.ReflectionAttributeExtractor$MethodPart(java.lang.String);
    Code:
       0: aload_0
       1: invokespecial #1                  // Method java/lang/Object."<init>":()V
       4: aload_0
       5: aload_1
       6: putfield      #2                  // Field methodName:Ljava/lang/String;
       9: return

  public java.lang.Object eval(java.lang.Object);
    Code:
       0: aload_1
       1: ifnonnull     39
       4: new           #3                  // class net/sf/ehcache/search/attribute/AttributeExtractorException
       7: dup
       8: new           #4                  // class java/lang/StringBuilder
      11: dup
      12: invokespecial #5                  // Method java/lang/StringBuilder."<init>":()V
      15: ldc           #6                  // String null reference encountered trying to call
      17: invokevirtual #7                  // Method java/lang/StringBuilder.append:(Ljava/lang/String;)Ljava/lang/StringBuilder;
      20: aload_0
      21: getfield      #2                  // Field methodName:Ljava/lang/String;
      24: invokevirtual #7                  // Method java/lang/StringBuilder.append:(Ljava/lang/String;)Ljava/lang/StringBuilder;
      27: ldc           #8                  // String ()
      29: invokevirtual #7                  // Method java/lang/StringBuilder.append:(Ljava/lang/String;)Ljava/lang/StringBuilder;
      32: invokevirtual #9                  // Method java/lang/StringBuilder.toString:()Ljava/lang/String;
      35: invokespecial #10                 // Method net/sf/ehcache/search/attribute/AttributeExtractorException."<init>":(Ljava/lang/String;)V
      38: athrow
      39: aload_1
      40: invokevirtual #11                 // Method java/lang/Object.getClass:()Ljava/lang/Class;
      43: astore_2
      44: aload_0
      45: getfield      #12                 // Field cache:Lnet/sf/ehcache/search/attribute/ReflectionAttributeExtractor$MethodRef;
      48: astore_3
      49: aload_3
      50: ifnull        61
      53: aload_3
      54: invokestatic  #13                 // Method net/sf/ehcache/search/attribute/ReflectionAttributeExtractor$MethodRef.access$200:(Lnet/sf/ehcache/search/attribute/ReflectionAttributeExtractor$MethodRef;)Ljava/lang/Class;
      57: aload_2
      58: if_acmpeq     171
      61: aload_2
      62: aload_0
      63: getfield      #2                  // Field methodName:Ljava/lang/String;
      66: iconst_0
      67: anewarray     #14                 // class java/lang/Class
      70: invokevirtual #15                 // Method java/lang/Class.getDeclaredMethod:(Ljava/lang/String;[Ljava/lang/Class;)Ljava/lang/reflect/Method;
      73: astore        4
      75: aload         4
      77: iconst_1
      78: invokevirtual #16                 // Method java/lang/reflect/Method.setAccessible:(Z)V
      81: new           #17                 // class net/sf/ehcache/search/attribute/ReflectionAttributeExtractor$MethodRef
      84: dup
      85: aload_1
      86: invokevirtual #11                 // Method java/lang/Object.getClass:()Ljava/lang/Class;
      89: aload         4
      91: invokespecial #18                 // Method net/sf/ehcache/search/attribute/ReflectionAttributeExtractor$MethodRef."<init>":(Ljava/lang/Class;Ljava/lang/reflect/Method;)V
      94: astore_3
      95: aload_0
      96: aload_3
      97: putfield      #12                 // Field cache:Lnet/sf/ehcache/search/attribute/ReflectionAttributeExtractor$MethodRef;
     100: goto          171
     103: astore        4
     105: aload_2
     106: invokevirtual #20                 // Method java/lang/Class.getSuperclass:()Ljava/lang/Class;
     109: astore_2
     110: aload_2
     111: ifnonnull     156
     114: new           #3                  // class net/sf/ehcache/search/attribute/AttributeExtractorException
     117: dup
     118: new           #4                  // class java/lang/StringBuilder
     121: dup
     122: invokespecial #5                  // Method java/lang/StringBuilder."<init>":()V
     125: ldc           #21                 // String No such method named \"
     127: invokevirtual #7                  // Method java/lang/StringBuilder.append:(Ljava/lang/String;)Ljava/lang/StringBuilder;
     130: aload_0
     131: getfield      #2                  // Field methodName:Ljava/lang/String;
     134: invokevirtual #7                  // Method java/lang/StringBuilder.append:(Ljava/lang/String;)Ljava/lang/StringBuilder;
     137: ldc           #22                 // String \" present on instance of
     139: invokevirtual #7                  // Method java/lang/StringBuilder.append:(Ljava/lang/String;)Ljava/lang/StringBuilder;
     142: aload_1
     143: invokevirtual #11                 // Method java/lang/Object.getClass:()Ljava/lang/Class;
     146: invokevirtual #23                 // Method java/lang/StringBuilder.append:(Ljava/lang/Object;)Ljava/lang/StringBuilder;
     149: invokevirtual #9                  // Method java/lang/StringBuilder.toString:()Ljava/lang/String;
     152: invokespecial #10                 // Method net/sf/ehcache/search/attribute/AttributeExtractorException."<init>":(Ljava/lang/String;)V
     155: athrow
     156: goto          61
     159: astore        4
     161: new           #3                  // class net/sf/ehcache/search/attribute/AttributeExtractorException
     164: dup
     165: aload         4
     167: invokespecial #25                 // Method net/sf/ehcache/search/attribute/AttributeExtractorException."<init>":(Ljava/lang/Throwable;)V
     170: athrow
     171: aload_3
     172: invokestatic  #26                 // Method net/sf/ehcache/search/attribute/ReflectionAttributeExtractor$MethodRef.access$300:(Lnet/sf/ehcache/search/attribute/ReflectionAttributeExtractor$MethodRef;)Ljava/lang/reflect/Method;
     175: aload_1
     176: iconst_0
     177: anewarray     #27                 // class java/lang/Object
     180: invokevirtual #28                 // Method java/lang/reflect/Method.invoke:(Ljava/lang/Object;[Ljava/lang/Object;)Ljava/lang/Object;
     183: areturn
     184: astore        4
     186: new           #3                  // class net/sf/ehcache/search/attribute/AttributeExtractorException
     189: dup
     190: aload         4
     192: invokevirtual #30                 // Method java/lang/reflect/InvocationTargetException.getTargetException:()Ljava/lang/Throwable;
     195: invokespecial #25                 // Method net/sf/ehcache/search/attribute/AttributeExtractorException."<init>":(Ljava/lang/Throwable;)V
     198: athrow
     199: astore        4
     201: new           #3                  // class net/sf/ehcache/search/attribute/AttributeExtractorException
     204: dup
     205: aload         4
     207: invokespecial #25                 // Method net/sf/ehcache/search/attribute/AttributeExtractorException."<init>":(Ljava/lang/Throwable;)V
     210: athrow
    Exception table:
       from    to  target type
          61   100   103   Class java/lang/NoSuchMethodException
          61   100   159   Class java/lang/Exception
         171   183   184   Class java/lang/reflect/InvocationTargetException
         171   183   199   Class java/lang/Exception
}
