Compiled from "AbstractCollectionPersister.java"
class org.hibernate.persister.collection.AbstractCollectionPersister$1$1 implements org.hibernate.persister.walking.spi.CompositeCollectionElementDefinition {
  final org.hibernate.persister.collection.AbstractCollectionPersister$1 this$1;

  org.hibernate.persister.collection.AbstractCollectionPersister$1$1(org.hibernate.persister.collection.AbstractCollectionPersister$1);
    Code:
       0: aload_0
       1: aload_1
       2: putfield      #1                  // Field this$1:Lorg/hibernate/persister/collection/AbstractCollectionPersister$1;
       5: aload_0
       6: invokespecial #2                  // Method java/lang/Object."<init>":()V
       9: return

  public java.lang.String getName();
    Code:
       0: ldc           #3                  // String index
       2: areturn

  public org.hibernate.type.CompositeType getType();
    Code:
       0: aload_0
       1: getfield      #1                  // Field this$1:Lorg/hibernate/persister/collection/AbstractCollectionPersister$1;
       4: getfield      #4                  // Field org/hibernate/persister/collection/AbstractCollectionPersister$1.this$0:Lorg/hibernate/persister/collection/AbstractCollectionPersister;
       7: invokevirtual #5                  // Method org/hibernate/persister/collection/AbstractCollectionPersister.getIndexType:()Lorg/hibernate/type/Type;
      10: checkcast     #6                  // class org/hibernate/type/CompositeType
      13: areturn

  public boolean isNullable();
    Code:
       0: iconst_0
       1: ireturn

  public org.hibernate.persister.walking.spi.AttributeSource getSource();
    Code:
       0: aload_0
       1: getfield      #1                  // Field this$1:Lorg/hibernate/persister/collection/AbstractCollectionPersister$1;
       4: getfield      #4                  // Field org/hibernate/persister/collection/AbstractCollectionPersister$1.this$0:Lorg/hibernate/persister/collection/AbstractCollectionPersister;
       7: invokevirtual #7                  // Method org/hibernate/persister/collection/AbstractCollectionPersister.getOwnerEntityPersister:()Lorg/hibernate/persister/entity/EntityPersister;
      10: areturn

  public java.lang.Iterable<org.hibernate.persister.walking.spi.AttributeDefinition> getAttributes();
    Code:
       0: aload_0
       1: invokestatic  #8                  // Method org/hibernate/persister/walking/internal/CompositionSingularSubAttributesHelper.getCompositeCollectionIndexSubAttributes:(Lorg/hibernate/persister/walking/spi/CompositeCollectionElementDefinition;)Ljava/lang/Iterable;
       4: areturn

  public org.hibernate.persister.walking.spi.CollectionDefinition getCollectionDefinition();
    Code:
       0: aload_0
       1: getfield      #1                  // Field this$1:Lorg/hibernate/persister/collection/AbstractCollectionPersister$1;
       4: getfield      #4                  // Field org/hibernate/persister/collection/AbstractCollectionPersister$1.this$0:Lorg/hibernate/persister/collection/AbstractCollectionPersister;
       7: areturn

  public org.hibernate.type.Type getType();
    Code:
       0: aload_0
       1: invokevirtual #9                  // Method getType:()Lorg/hibernate/type/CompositeType;
       4: areturn
}
