public class org.bouncycastle.asn1.eac.BidirectionalMap extends java.util.Hashtable {
  private static final long serialVersionUID;

  java.util.Hashtable reverseMap;

  public org.bouncycastle.asn1.eac.BidirectionalMap();
    Code:
       0: aload_0
       1: invokespecial #23                 // Method java/util/Hashtable."<init>":()V
       4: aload_0
       5: new           #13                 // class java/util/Hashtable
       8: dup
       9: invokespecial #23                 // Method java/util/Hashtable."<init>":()V
      12: putfield      #22                 // Field reverseMap:Ljava/util/Hashtable;
      15: return

  public java.lang.Object getReverse(java.lang.Object);
    Code:
       0: aload_0
       1: getfield      #22                 // Field reverseMap:Ljava/util/Hashtable;
       4: aload_1
       5: invokevirtual #24                 // Method java/util/Hashtable.get:(Ljava/lang/Object;)Ljava/lang/Object;
       8: areturn

  public java.lang.Object put(java.lang.Object, java.lang.Object);
    Code:
       0: aload_0
       1: getfield      #22                 // Field reverseMap:Ljava/util/Hashtable;
       4: aload_2
       5: aload_1
       6: invokevirtual #25                 // Method java/util/Hashtable.put:(Ljava/lang/Object;Ljava/lang/Object;)Ljava/lang/Object;
       9: pop
      10: aload_0
      11: aload_1
      12: aload_2
      13: invokespecial #25                 // Method java/util/Hashtable.put:(Ljava/lang/Object;Ljava/lang/Object;)Ljava/lang/Object;
      16: areturn
}
