Compiled from "JodaDeserializerBase.java"
abstract class com.fasterxml.jackson.datatype.joda.deser.JodaDeserializerBase<T> extends com.fasterxml.jackson.databind.deser.std.StdScalarDeserializer<T> {
  protected com.fasterxml.jackson.datatype.joda.deser.JodaDeserializerBase(java.lang.Class<T>);
    Code:
       0: aload_0
       1: aload_1
       2: invokespecial #1                  // Method com/fasterxml/jackson/databind/deser/std/StdScalarDeserializer."<init>":(Ljava/lang/Class;)V
       5: return

  public java.lang.Object deserializeWithType(com.fasterxml.jackson.core.JsonParser, com.fasterxml.jackson.databind.DeserializationContext, com.fasterxml.jackson.databind.jsontype.TypeDeserializer) throws java.io.IOException, com.fasterxml.jackson.core.JsonProcessingException;
    Code:
       0: aload_3
       1: aload_1
       2: aload_2
       3: invokevirtual #2                  // Method com/fasterxml/jackson/databind/jsontype/TypeDeserializer.deserializeTypedFromAny:(Lcom/fasterxml/jackson/core/JsonParser;Lcom/fasterxml/jackson/databind/DeserializationContext;)Ljava/lang/Object;
       6: areturn
}
