Compiled from "LocalTimeDeserializer.java"
public class com.fasterxml.jackson.datatype.joda.deser.LocalTimeDeserializer extends com.fasterxml.jackson.datatype.joda.deser.JodaDeserializerBase<org.joda.time.LocalTime> {
  static final org.joda.time.format.DateTimeFormatter parser;

  public com.fasterxml.jackson.datatype.joda.deser.LocalTimeDeserializer();
    Code:
       0: aload_0
       1: ldc_w         #1                  // class org/joda/time/LocalTime
       4: invokespecial #2                  // Method com/fasterxml/jackson/datatype/joda/deser/JodaDeserializerBase."<init>":(Ljava/lang/Class;)V
       7: return

  public org.joda.time.LocalTime deserialize(com.fasterxml.jackson.core.JsonParser, com.fasterxml.jackson.databind.DeserializationContext) throws java.io.IOException, com.fasterxml.jackson.core.JsonProcessingException;
    Code:
       0: getstatic     #3                  // Field com/fasterxml/jackson/datatype/joda/deser/LocalTimeDeserializer$1.$SwitchMap$com$fasterxml$jackson$core$JsonToken:[I
       3: aload_1
       4: invokevirtual #4                  // Method com/fasterxml/jackson/core/JsonParser.getCurrentToken:()Lcom/fasterxml/jackson/core/JsonToken;
       7: invokevirtual #5                  // Method com/fasterxml/jackson/core/JsonToken.ordinal:()I
      10: iaload
      11: tableswitch   { // 1 to 3
                     1: 36
                     2: 140
                     3: 152
               default: 177
          }
      36: aload_1
      37: invokevirtual #6                  // Method com/fasterxml/jackson/core/JsonParser.isExpectedStartArrayToken:()Z
      40: ifeq          177
      43: aload_1
      44: invokevirtual #7                  // Method com/fasterxml/jackson/core/JsonParser.nextToken:()Lcom/fasterxml/jackson/core/JsonToken;
      47: pop
      48: aload_1
      49: invokevirtual #8                  // Method com/fasterxml/jackson/core/JsonParser.getIntValue:()I
      52: istore_3
      53: aload_1
      54: invokevirtual #7                  // Method com/fasterxml/jackson/core/JsonParser.nextToken:()Lcom/fasterxml/jackson/core/JsonToken;
      57: pop
      58: aload_1
      59: invokevirtual #8                  // Method com/fasterxml/jackson/core/JsonParser.getIntValue:()I
      62: istore        4
      64: aload_1
      65: invokevirtual #7                  // Method com/fasterxml/jackson/core/JsonParser.nextToken:()Lcom/fasterxml/jackson/core/JsonToken;
      68: pop
      69: aload_1
      70: invokevirtual #8                  // Method com/fasterxml/jackson/core/JsonParser.getIntValue:()I
      73: istore        5
      75: aload_1
      76: invokevirtual #7                  // Method com/fasterxml/jackson/core/JsonParser.nextToken:()Lcom/fasterxml/jackson/core/JsonToken;
      79: pop
      80: iconst_0
      81: istore        6
      83: aload_1
      84: invokevirtual #4                  // Method com/fasterxml/jackson/core/JsonParser.getCurrentToken:()Lcom/fasterxml/jackson/core/JsonToken;
      87: getstatic     #9                  // Field com/fasterxml/jackson/core/JsonToken.END_ARRAY:Lcom/fasterxml/jackson/core/JsonToken;
      90: if_acmpeq     104
      93: aload_1
      94: invokevirtual #8                  // Method com/fasterxml/jackson/core/JsonParser.getIntValue:()I
      97: istore        6
      99: aload_1
     100: invokevirtual #7                  // Method com/fasterxml/jackson/core/JsonParser.nextToken:()Lcom/fasterxml/jackson/core/JsonToken;
     103: pop
     104: aload_1
     105: invokevirtual #4                  // Method com/fasterxml/jackson/core/JsonParser.getCurrentToken:()Lcom/fasterxml/jackson/core/JsonToken;
     108: getstatic     #9                  // Field com/fasterxml/jackson/core/JsonToken.END_ARRAY:Lcom/fasterxml/jackson/core/JsonToken;
     111: if_acmpeq     125
     114: aload_2
     115: aload_1
     116: getstatic     #9                  // Field com/fasterxml/jackson/core/JsonToken.END_ARRAY:Lcom/fasterxml/jackson/core/JsonToken;
     119: ldc           #10                 // String after LocalTime ints
     121: invokevirtual #11                 // Method com/fasterxml/jackson/databind/DeserializationContext.wrongTokenException:(Lcom/fasterxml/jackson/core/JsonParser;Lcom/fasterxml/jackson/core/JsonToken;Ljava/lang/String;)Lcom/fasterxml/jackson/databind/JsonMappingException;
     124: athrow
     125: new           #1                  // class org/joda/time/LocalTime
     128: dup
     129: iload_3
     130: iload         4
     132: iload         5
     134: iload         6
     136: invokespecial #12                 // Method org/joda/time/LocalTime."<init>":(IIII)V
     139: areturn
     140: new           #1                  // class org/joda/time/LocalTime
     143: dup
     144: aload_1
     145: invokevirtual #13                 // Method com/fasterxml/jackson/core/JsonParser.getLongValue:()J
     148: invokespecial #14                 // Method org/joda/time/LocalTime."<init>":(J)V
     151: areturn
     152: aload_1
     153: invokevirtual #15                 // Method com/fasterxml/jackson/core/JsonParser.getText:()Ljava/lang/String;
     156: invokevirtual #16                 // Method java/lang/String.trim:()Ljava/lang/String;
     159: astore_3
     160: aload_3
     161: invokevirtual #17                 // Method java/lang/String.length:()I
     164: ifne          169
     167: aconst_null
     168: areturn
     169: getstatic     #18                 // Field parser:Lorg/joda/time/format/DateTimeFormatter;
     172: aload_3
     173: invokevirtual #19                 // Method org/joda/time/format/DateTimeFormatter.parseLocalTime:(Ljava/lang/String;)Lorg/joda/time/LocalTime;
     176: areturn
     177: aload_2
     178: aload_1
     179: getstatic     #20                 // Field com/fasterxml/jackson/core/JsonToken.START_ARRAY:Lcom/fasterxml/jackson/core/JsonToken;
     182: ldc           #21                 // String expected JSON Array, String or Number
     184: invokevirtual #11                 // Method com/fasterxml/jackson/databind/DeserializationContext.wrongTokenException:(Lcom/fasterxml/jackson/core/JsonParser;Lcom/fasterxml/jackson/core/JsonToken;Ljava/lang/String;)Lcom/fasterxml/jackson/databind/JsonMappingException;
     187: athrow

  public java.lang.Object deserializeWithType(com.fasterxml.jackson.core.JsonParser, com.fasterxml.jackson.databind.DeserializationContext, com.fasterxml.jackson.databind.jsontype.TypeDeserializer) throws java.io.IOException, com.fasterxml.jackson.core.JsonProcessingException;
    Code:
       0: aload_0
       1: aload_1
       2: aload_2
       3: aload_3
       4: invokespecial #22                 // Method com/fasterxml/jackson/datatype/joda/deser/JodaDeserializerBase.deserializeWithType:(Lcom/fasterxml/jackson/core/JsonParser;Lcom/fasterxml/jackson/databind/DeserializationContext;Lcom/fasterxml/jackson/databind/jsontype/TypeDeserializer;)Ljava/lang/Object;
       7: areturn

  public java.lang.Object deserialize(com.fasterxml.jackson.core.JsonParser, com.fasterxml.jackson.databind.DeserializationContext) throws java.io.IOException, com.fasterxml.jackson.core.JsonProcessingException;
    Code:
       0: aload_0
       1: aload_1
       2: aload_2
       3: invokevirtual #23                 // Method deserialize:(Lcom/fasterxml/jackson/core/JsonParser;Lcom/fasterxml/jackson/databind/DeserializationContext;)Lorg/joda/time/LocalTime;
       6: areturn

  static {};
    Code:
       0: invokestatic  #24                 // Method org/joda/time/format/ISODateTimeFormat.localTimeParser:()Lorg/joda/time/format/DateTimeFormatter;
       3: putstatic     #18                 // Field parser:Lorg/joda/time/format/DateTimeFormatter;
       6: return
}
