Compiled from "RedisSessionConfiguration.java"
class org.springframework.boot.autoconfigure.session.RedisSessionConfiguration$1 {
  static final int[] $SwitchMap$org$springframework$boot$autoconfigure$session$RedisSessionProperties$ConfigureAction;

  static {};
    Code:
       0: invokestatic  #1                  // Method org/springframework/boot/autoconfigure/session/RedisSessionProperties$ConfigureAction.values:()[Lorg/springframework/boot/autoconfigure/session/RedisSessionProperties$ConfigureAction;
       3: arraylength
       4: newarray       int
       6: putstatic     #2                  // Field $SwitchMap$org$springframework$boot$autoconfigure$session$RedisSessionProperties$ConfigureAction:[I
       9: getstatic     #2                  // Field $SwitchMap$org$springframework$boot$autoconfigure$session$RedisSessionProperties$ConfigureAction:[I
      12: getstatic     #3                  // Field org/springframework/boot/autoconfigure/session/RedisSessionProperties$ConfigureAction.NOTIFY_KEYSPACE_EVENTS:Lorg/springframework/boot/autoconfigure/session/RedisSessionProperties$ConfigureAction;
      15: invokevirtual #4                  // Method org/springframework/boot/autoconfigure/session/RedisSessionProperties$ConfigureAction.ordinal:()I
      18: iconst_1
      19: iastore
      20: goto          24
      23: astore_0
      24: getstatic     #2                  // Field $SwitchMap$org$springframework$boot$autoconfigure$session$RedisSessionProperties$ConfigureAction:[I
      27: getstatic     #6                  // Field org/springframework/boot/autoconfigure/session/RedisSessionProperties$ConfigureAction.NONE:Lorg/springframework/boot/autoconfigure/session/RedisSessionProperties$ConfigureAction;
      30: invokevirtual #4                  // Method org/springframework/boot/autoconfigure/session/RedisSessionProperties$ConfigureAction.ordinal:()I
      33: iconst_2
      34: iastore
      35: goto          39
      38: astore_0
      39: return
    Exception table:
       from    to  target type
           9    20    23   Class java/lang/NoSuchFieldError
          24    35    38   Class java/lang/NoSuchFieldError
}
