Compiled from "BeanDefinitionDsl.kt"
public class org.springframework.context.support.BeanDefinitionDsl implements org.springframework.context.ApplicationContextInitializer<org.springframework.context.support.GenericApplicationContext> {
  private final java.util.ArrayList<org.springframework.context.support.BeanDefinitionDsl> children;

  public org.springframework.context.support.GenericApplicationContext context;

  private final kotlin.jvm.functions.Function1<org.springframework.context.support.BeanDefinitionDsl, kotlin.Unit> init;

  private final kotlin.jvm.functions.Function1<org.springframework.core.env.ConfigurableEnvironment, java.lang.Boolean> condition;

  public static void children$annotations();
    Code:
       0: return

  public final java.util.ArrayList<org.springframework.context.support.BeanDefinitionDsl> getChildren();
    Code:
       0: aload_0
       1: getfield      #18                 // Field children:Ljava/util/ArrayList;
       4: areturn

  public static void context$annotations();
    Code:
       0: return

  public final org.springframework.context.support.GenericApplicationContext getContext();
    Code:
       0: aload_0
       1: getfield      #27                 // Field context:Lorg/springframework/context/support/GenericApplicationContext;
       4: dup
       5: ifnonnull     13
       8: ldc           #28                 // String context
      10: invokestatic  #34                 // Method kotlin/jvm/internal/Intrinsics.throwUninitializedPropertyAccessException:(Ljava/lang/String;)V
      13: areturn

  public final void setContext(org.springframework.context.support.GenericApplicationContext);
    Code:
       0: aload_1
       1: ldc           #40                 // String <set-?>
       3: invokestatic  #44                 // Method kotlin/jvm/internal/Intrinsics.checkParameterIsNotNull:(Ljava/lang/Object;Ljava/lang/String;)V
       6: aload_0
       7: aload_1
       8: putfield      #27                 // Field context:Lorg/springframework/context/support/GenericApplicationContext;
      11: return

  public final org.springframework.core.env.ConfigurableEnvironment getEnv();
    Code:
       0: aload_0
       1: getfield      #27                 // Field context:Lorg/springframework/context/support/GenericApplicationContext;
       4: dup
       5: ifnonnull     13
       8: ldc           #28                 // String context
      10: invokestatic  #34                 // Method kotlin/jvm/internal/Intrinsics.throwUninitializedPropertyAccessException:(Ljava/lang/String;)V
      13: invokevirtual #49                 // Method org/springframework/context/support/GenericApplicationContext.getEnvironment:()Lorg/springframework/core/env/ConfigurableEnvironment;
      16: dup
      17: ldc           #51                 // String context.environment
      19: invokestatic  #54                 // Method kotlin/jvm/internal/Intrinsics.checkExpressionValueIsNotNull:(Ljava/lang/Object;Ljava/lang/String;)V
      22: areturn

  private final <T> void bean(java.lang.String, org.springframework.context.support.BeanDefinitionDsl$Scope, java.lang.Boolean, java.lang.Boolean, java.lang.Boolean, java.lang.String, java.lang.String, java.lang.String, org.springframework.context.support.BeanDefinitionDsl$Role);
    Code:
       0: new           #58                 // class org/springframework/context/support/BeanDefinitionDsl$bean$customizer$1
       3: dup
       4: aload_2
       5: aload_3
       6: aload         4
       8: aload         5
      10: aload         6
      12: aload         7
      14: aload         8
      16: aload         9
      18: invokespecial #62                 // Method org/springframework/context/support/BeanDefinitionDsl$bean$customizer$1."<init>":(Lorg/springframework/context/support/BeanDefinitionDsl$Scope;Ljava/lang/Boolean;Ljava/lang/Boolean;Ljava/lang/Boolean;Ljava/lang/String;Ljava/lang/String;Ljava/lang/String;Lorg/springframework/context/support/BeanDefinitionDsl$Role;)V
      21: checkcast     #64                 // class org/springframework/beans/factory/config/BeanDefinitionCustomizer
      24: astore        11
      26: aload_1
      27: dup
      28: ifnull        34
      31: goto          62
      34: pop
      35: iconst_4
      36: ldc           #66                 // String T
      38: invokestatic  #70                 // Method kotlin/jvm/internal/Intrinsics.reifiedOperationMarker:(ILjava/lang/String;)V
      41: ldc           #5                  // class java/lang/Object
      43: invokevirtual #76                 // Method java/lang/Class.getName:()Ljava/lang/String;
      46: aload_0
      47: invokevirtual #78                 // Method getContext:()Lorg/springframework/context/support/GenericApplicationContext;
      50: checkcast     #80                 // class org/springframework/beans/factory/support/BeanDefinitionRegistry
      53: invokestatic  #86                 // Method org/springframework/beans/factory/support/BeanDefinitionReaderUtils.uniqueBeanName:(Ljava/lang/String;Lorg/springframework/beans/factory/support/BeanDefinitionRegistry;)Ljava/lang/String;
      56: dup
      57: ldc           #88                 // String BeanDefinitionReaderUtil…class.java.name, context)
      59: invokestatic  #54                 // Method kotlin/jvm/internal/Intrinsics.checkExpressionValueIsNotNull:(Ljava/lang/Object;Ljava/lang/String;)V
      62: astore        12
      64: aload_0
      65: invokevirtual #78                 // Method getContext:()Lorg/springframework/context/support/GenericApplicationContext;
      68: aload         12
      70: iconst_4
      71: ldc           #66                 // String T
      73: invokestatic  #70                 // Method kotlin/jvm/internal/Intrinsics.reifiedOperationMarker:(ILjava/lang/String;)V
      76: ldc           #5                  // class java/lang/Object
      78: iconst_1
      79: anewarray     #64                 // class org/springframework/beans/factory/config/BeanDefinitionCustomizer
      82: dup
      83: iconst_0
      84: aload         11
      86: aastore
      87: invokevirtual #92                 // Method org/springframework/context/support/GenericApplicationContext.registerBean:(Ljava/lang/String;Ljava/lang/Class;[Lorg/springframework/beans/factory/config/BeanDefinitionCustomizer;)V
      90: return

  static void bean$default(org.springframework.context.support.BeanDefinitionDsl, java.lang.String, org.springframework.context.support.BeanDefinitionDsl$Scope, java.lang.Boolean, java.lang.Boolean, java.lang.Boolean, java.lang.String, java.lang.String, java.lang.String, org.springframework.context.support.BeanDefinitionDsl$Role, int, java.lang.Object);
    Code:
       0: aload         11
       2: ifnull        15
       5: new           #122                // class java/lang/UnsupportedOperationException
       8: dup
       9: ldc           #124                // String Super calls with default arguments not supported in this target, function: bean
      11: invokespecial #126                // Method java/lang/UnsupportedOperationException."<init>":(Ljava/lang/String;)V
      14: athrow
      15: iload         10
      17: iconst_1
      18: iand
      19: ifeq          27
      22: aconst_null
      23: checkcast     #112                // class java/lang/String
      26: astore_1
      27: iload         10
      29: iconst_2
      30: iand
      31: ifeq          39
      34: aconst_null
      35: checkcast     #114                // class org/springframework/context/support/BeanDefinitionDsl$Scope
      38: astore_2
      39: iload         10
      41: iconst_4
      42: iand
      43: ifeq          51
      46: aconst_null
      47: checkcast     #116                // class java/lang/Boolean
      50: astore_3
      51: iload         10
      53: bipush        8
      55: iand
      56: ifeq          65
      59: aconst_null
      60: checkcast     #116                // class java/lang/Boolean
      63: astore        4
      65: iload         10
      67: bipush        16
      69: iand
      70: ifeq          79
      73: aconst_null
      74: checkcast     #116                // class java/lang/Boolean
      77: astore        5
      79: iload         10
      81: bipush        32
      83: iand
      84: ifeq          93
      87: aconst_null
      88: checkcast     #112                // class java/lang/String
      91: astore        6
      93: iload         10
      95: bipush        64
      97: iand
      98: ifeq          107
     101: aconst_null
     102: checkcast     #112                // class java/lang/String
     105: astore        7
     107: iload         10
     109: sipush        128
     112: iand
     113: ifeq          122
     116: aconst_null
     117: checkcast     #112                // class java/lang/String
     120: astore        8
     122: iload         10
     124: sipush        256
     127: iand
     128: ifeq          137
     131: aconst_null
     132: checkcast     #118                // class org/springframework/context/support/BeanDefinitionDsl$Role
     135: astore        9
     137: new           #58                 // class org/springframework/context/support/BeanDefinitionDsl$bean$customizer$1
     140: dup
     141: aload_2
     142: aload_3
     143: aload         4
     145: aload         5
     147: aload         6
     149: aload         7
     151: aload         8
     153: aload         9
     155: invokespecial #62                 // Method org/springframework/context/support/BeanDefinitionDsl$bean$customizer$1."<init>":(Lorg/springframework/context/support/BeanDefinitionDsl$Scope;Ljava/lang/Boolean;Ljava/lang/Boolean;Ljava/lang/Boolean;Ljava/lang/String;Ljava/lang/String;Ljava/lang/String;Lorg/springframework/context/support/BeanDefinitionDsl$Role;)V
     158: checkcast     #64                 // class org/springframework/beans/factory/config/BeanDefinitionCustomizer
     161: astore        11
     163: aload_1
     164: dup
     165: ifnull        171
     168: goto          199
     171: pop
     172: iconst_4
     173: ldc           #66                 // String T
     175: invokestatic  #70                 // Method kotlin/jvm/internal/Intrinsics.reifiedOperationMarker:(ILjava/lang/String;)V
     178: ldc           #5                  // class java/lang/Object
     180: invokevirtual #76                 // Method java/lang/Class.getName:()Ljava/lang/String;
     183: aload_0
     184: invokevirtual #78                 // Method getContext:()Lorg/springframework/context/support/GenericApplicationContext;
     187: checkcast     #80                 // class org/springframework/beans/factory/support/BeanDefinitionRegistry
     190: invokestatic  #86                 // Method org/springframework/beans/factory/support/BeanDefinitionReaderUtils.uniqueBeanName:(Ljava/lang/String;Lorg/springframework/beans/factory/support/BeanDefinitionRegistry;)Ljava/lang/String;
     193: dup
     194: ldc           #88                 // String BeanDefinitionReaderUtil…class.java.name, context)
     196: invokestatic  #54                 // Method kotlin/jvm/internal/Intrinsics.checkExpressionValueIsNotNull:(Ljava/lang/Object;Ljava/lang/String;)V
     199: astore        12
     201: aload_0
     202: invokevirtual #78                 // Method getContext:()Lorg/springframework/context/support/GenericApplicationContext;
     205: aload         12
     207: iconst_4
     208: ldc           #66                 // String T
     210: invokestatic  #70                 // Method kotlin/jvm/internal/Intrinsics.reifiedOperationMarker:(ILjava/lang/String;)V
     213: ldc           #5                  // class java/lang/Object
     215: iconst_1
     216: anewarray     #64                 // class org/springframework/beans/factory/config/BeanDefinitionCustomizer
     219: dup
     220: iconst_0
     221: aload         11
     223: aastore
     224: invokevirtual #92                 // Method org/springframework/context/support/GenericApplicationContext.registerBean:(Ljava/lang/String;Ljava/lang/Class;[Lorg/springframework/beans/factory/config/BeanDefinitionCustomizer;)V
     227: return

  private final <T> void bean(java.lang.String, org.springframework.context.support.BeanDefinitionDsl$Scope, java.lang.Boolean, java.lang.Boolean, java.lang.Boolean, java.lang.String, java.lang.String, java.lang.String, org.springframework.context.support.BeanDefinitionDsl$Role, kotlin.jvm.functions.Function0<? extends T>);
    Code:
       0: new           #129                // class org/springframework/context/support/BeanDefinitionDsl$bean$customizer$2
       3: dup
       4: aload_2
       5: aload_3
       6: aload         4
       8: aload         5
      10: aload         6
      12: aload         7
      14: aload         8
      16: aload         9
      18: invokespecial #130                // Method org/springframework/context/support/BeanDefinitionDsl$bean$customizer$2."<init>":(Lorg/springframework/context/support/BeanDefinitionDsl$Scope;Ljava/lang/Boolean;Ljava/lang/Boolean;Ljava/lang/Boolean;Ljava/lang/String;Ljava/lang/String;Ljava/lang/String;Lorg/springframework/context/support/BeanDefinitionDsl$Role;)V
      21: checkcast     #64                 // class org/springframework/beans/factory/config/BeanDefinitionCustomizer
      24: astore        12
      26: aload_1
      27: dup
      28: ifnull        34
      31: goto          62
      34: pop
      35: iconst_4
      36: ldc           #66                 // String T
      38: invokestatic  #70                 // Method kotlin/jvm/internal/Intrinsics.reifiedOperationMarker:(ILjava/lang/String;)V
      41: ldc           #5                  // class java/lang/Object
      43: invokevirtual #76                 // Method java/lang/Class.getName:()Ljava/lang/String;
      46: aload_0
      47: invokevirtual #78                 // Method getContext:()Lorg/springframework/context/support/GenericApplicationContext;
      50: checkcast     #80                 // class org/springframework/beans/factory/support/BeanDefinitionRegistry
      53: invokestatic  #86                 // Method org/springframework/beans/factory/support/BeanDefinitionReaderUtils.uniqueBeanName:(Ljava/lang/String;Lorg/springframework/beans/factory/support/BeanDefinitionRegistry;)Ljava/lang/String;
      56: dup
      57: ldc           #88                 // String BeanDefinitionReaderUtil…class.java.name, context)
      59: invokestatic  #54                 // Method kotlin/jvm/internal/Intrinsics.checkExpressionValueIsNotNull:(Ljava/lang/Object;Ljava/lang/String;)V
      62: astore        13
      64: aload_0
      65: invokevirtual #78                 // Method getContext:()Lorg/springframework/context/support/GenericApplicationContext;
      68: aload         13
      70: iconst_4
      71: ldc           #66                 // String T
      73: invokestatic  #70                 // Method kotlin/jvm/internal/Intrinsics.reifiedOperationMarker:(ILjava/lang/String;)V
      76: ldc           #5                  // class java/lang/Object
      78: new           #132                // class org/springframework/context/support/BeanDefinitionDsl$bean$1
      81: dup
      82: aload         10
      84: invokespecial #135                // Method org/springframework/context/support/BeanDefinitionDsl$bean$1."<init>":(Lkotlin/jvm/functions/Function0;)V
      87: checkcast     #137                // class java/util/function/Supplier
      90: iconst_1
      91: anewarray     #64                 // class org/springframework/beans/factory/config/BeanDefinitionCustomizer
      94: dup
      95: iconst_0
      96: aload         12
      98: aastore
      99: invokevirtual #140                // Method org/springframework/context/support/GenericApplicationContext.registerBean:(Ljava/lang/String;Ljava/lang/Class;Ljava/util/function/Supplier;[Lorg/springframework/beans/factory/config/BeanDefinitionCustomizer;)V
     102: return

  static void bean$default(org.springframework.context.support.BeanDefinitionDsl, java.lang.String, org.springframework.context.support.BeanDefinitionDsl$Scope, java.lang.Boolean, java.lang.Boolean, java.lang.Boolean, java.lang.String, java.lang.String, java.lang.String, org.springframework.context.support.BeanDefinitionDsl$Role, kotlin.jvm.functions.Function0, int, java.lang.Object);
    Code:
       0: aload         12
       2: ifnull        15
       5: new           #122                // class java/lang/UnsupportedOperationException
       8: dup
       9: ldc           #124                // String Super calls with default arguments not supported in this target, function: bean
      11: invokespecial #126                // Method java/lang/UnsupportedOperationException."<init>":(Ljava/lang/String;)V
      14: athrow
      15: iload         11
      17: iconst_1
      18: iand
      19: ifeq          27
      22: aconst_null
      23: checkcast     #112                // class java/lang/String
      26: astore_1
      27: iload         11
      29: iconst_2
      30: iand
      31: ifeq          39
      34: aconst_null
      35: checkcast     #114                // class org/springframework/context/support/BeanDefinitionDsl$Scope
      38: astore_2
      39: iload         11
      41: iconst_4
      42: iand
      43: ifeq          51
      46: aconst_null
      47: checkcast     #116                // class java/lang/Boolean
      50: astore_3
      51: iload         11
      53: bipush        8
      55: iand
      56: ifeq          65
      59: aconst_null
      60: checkcast     #116                // class java/lang/Boolean
      63: astore        4
      65: iload         11
      67: bipush        16
      69: iand
      70: ifeq          79
      73: aconst_null
      74: checkcast     #116                // class java/lang/Boolean
      77: astore        5
      79: iload         11
      81: bipush        32
      83: iand
      84: ifeq          93
      87: aconst_null
      88: checkcast     #112                // class java/lang/String
      91: astore        6
      93: iload         11
      95: bipush        64
      97: iand
      98: ifeq          107
     101: aconst_null
     102: checkcast     #112                // class java/lang/String
     105: astore        7
     107: iload         11
     109: sipush        128
     112: iand
     113: ifeq          122
     116: aconst_null
     117: checkcast     #112                // class java/lang/String
     120: astore        8
     122: iload         11
     124: sipush        256
     127: iand
     128: ifeq          137
     131: aconst_null
     132: checkcast     #118                // class org/springframework/context/support/BeanDefinitionDsl$Role
     135: astore        9
     137: new           #129                // class org/springframework/context/support/BeanDefinitionDsl$bean$customizer$2
     140: dup
     141: aload_2
     142: aload_3
     143: aload         4
     145: aload         5
     147: aload         6
     149: aload         7
     151: aload         8
     153: aload         9
     155: invokespecial #130                // Method org/springframework/context/support/BeanDefinitionDsl$bean$customizer$2."<init>":(Lorg/springframework/context/support/BeanDefinitionDsl$Scope;Ljava/lang/Boolean;Ljava/lang/Boolean;Ljava/lang/Boolean;Ljava/lang/String;Ljava/lang/String;Ljava/lang/String;Lorg/springframework/context/support/BeanDefinitionDsl$Role;)V
     158: checkcast     #64                 // class org/springframework/beans/factory/config/BeanDefinitionCustomizer
     161: astore        12
     163: aload_1
     164: dup
     165: ifnull        171
     168: goto          199
     171: pop
     172: iconst_4
     173: ldc           #66                 // String T
     175: invokestatic  #70                 // Method kotlin/jvm/internal/Intrinsics.reifiedOperationMarker:(ILjava/lang/String;)V
     178: ldc           #5                  // class java/lang/Object
     180: invokevirtual #76                 // Method java/lang/Class.getName:()Ljava/lang/String;
     183: aload_0
     184: invokevirtual #78                 // Method getContext:()Lorg/springframework/context/support/GenericApplicationContext;
     187: checkcast     #80                 // class org/springframework/beans/factory/support/BeanDefinitionRegistry
     190: invokestatic  #86                 // Method org/springframework/beans/factory/support/BeanDefinitionReaderUtils.uniqueBeanName:(Ljava/lang/String;Lorg/springframework/beans/factory/support/BeanDefinitionRegistry;)Ljava/lang/String;
     193: dup
     194: ldc           #88                 // String BeanDefinitionReaderUtil…class.java.name, context)
     196: invokestatic  #54                 // Method kotlin/jvm/internal/Intrinsics.checkExpressionValueIsNotNull:(Ljava/lang/Object;Ljava/lang/String;)V
     199: astore        13
     201: aload_0
     202: invokevirtual #78                 // Method getContext:()Lorg/springframework/context/support/GenericApplicationContext;
     205: aload         13
     207: iconst_4
     208: ldc           #66                 // String T
     210: invokestatic  #70                 // Method kotlin/jvm/internal/Intrinsics.reifiedOperationMarker:(ILjava/lang/String;)V
     213: ldc           #5                  // class java/lang/Object
     215: new           #132                // class org/springframework/context/support/BeanDefinitionDsl$bean$1
     218: dup
     219: aload         10
     221: invokespecial #135                // Method org/springframework/context/support/BeanDefinitionDsl$bean$1."<init>":(Lkotlin/jvm/functions/Function0;)V
     224: checkcast     #137                // class java/util/function/Supplier
     227: iconst_1
     228: anewarray     #64                 // class org/springframework/beans/factory/config/BeanDefinitionCustomizer
     231: dup
     232: iconst_0
     233: aload         12
     235: aastore
     236: invokevirtual #140                // Method org/springframework/context/support/GenericApplicationContext.registerBean:(Ljava/lang/String;Ljava/lang/Class;Ljava/util/function/Supplier;[Lorg/springframework/beans/factory/config/BeanDefinitionCustomizer;)V
     239: return

  private final <T> T ref(java.lang.String);
    Code:
       0: aload_1
       1: astore_3
       2: aload_3
       3: ifnonnull     30
       6: aload_0
       7: invokevirtual #78                 // Method getContext:()Lorg/springframework/context/support/GenericApplicationContext;
      10: iconst_4
      11: ldc           #66                 // String T
      13: invokestatic  #70                 // Method kotlin/jvm/internal/Intrinsics.reifiedOperationMarker:(ILjava/lang/String;)V
      16: ldc           #5                  // class java/lang/Object
      18: invokevirtual #151                // Method org/springframework/context/support/GenericApplicationContext.getBean:(Ljava/lang/Class;)Ljava/lang/Object;
      21: dup
      22: ldc           #153                // String context.getBean(T::class.java)
      24: invokestatic  #54                 // Method kotlin/jvm/internal/Intrinsics.checkExpressionValueIsNotNull:(Ljava/lang/Object;Ljava/lang/String;)V
      27: goto          52
      30: aload_0
      31: invokevirtual #78                 // Method getContext:()Lorg/springframework/context/support/GenericApplicationContext;
      34: aload_1
      35: iconst_4
      36: ldc           #66                 // String T
      38: invokestatic  #70                 // Method kotlin/jvm/internal/Intrinsics.reifiedOperationMarker:(ILjava/lang/String;)V
      41: ldc           #5                  // class java/lang/Object
      43: invokevirtual #156                // Method org/springframework/context/support/GenericApplicationContext.getBean:(Ljava/lang/String;Ljava/lang/Class;)Ljava/lang/Object;
      46: dup
      47: ldc           #158                // String context.getBean(name, T::class.java)
      49: invokestatic  #54                 // Method kotlin/jvm/internal/Intrinsics.checkExpressionValueIsNotNull:(Ljava/lang/Object;Ljava/lang/String;)V
      52: areturn

  static java.lang.Object ref$default(org.springframework.context.support.BeanDefinitionDsl, java.lang.String, int, java.lang.Object);
    Code:
       0: aload_3
       1: ifnull        14
       4: new           #122                // class java/lang/UnsupportedOperationException
       7: dup
       8: ldc           #163                // String Super calls with default arguments not supported in this target, function: ref
      10: invokespecial #126                // Method java/lang/UnsupportedOperationException."<init>":(Ljava/lang/String;)V
      13: athrow
      14: iload_2
      15: iconst_1
      16: iand
      17: ifeq          25
      20: aconst_null
      21: checkcast     #112                // class java/lang/String
      24: astore_1
      25: aload_1
      26: astore_3
      27: aload_3
      28: ifnonnull     55
      31: aload_0
      32: invokevirtual #78                 // Method getContext:()Lorg/springframework/context/support/GenericApplicationContext;
      35: iconst_4
      36: ldc           #66                 // String T
      38: invokestatic  #70                 // Method kotlin/jvm/internal/Intrinsics.reifiedOperationMarker:(ILjava/lang/String;)V
      41: ldc           #5                  // class java/lang/Object
      43: invokevirtual #151                // Method org/springframework/context/support/GenericApplicationContext.getBean:(Ljava/lang/Class;)Ljava/lang/Object;
      46: dup
      47: ldc           #153                // String context.getBean(T::class.java)
      49: invokestatic  #54                 // Method kotlin/jvm/internal/Intrinsics.checkExpressionValueIsNotNull:(Ljava/lang/Object;Ljava/lang/String;)V
      52: goto          77
      55: aload_0
      56: invokevirtual #78                 // Method getContext:()Lorg/springframework/context/support/GenericApplicationContext;
      59: aload_1
      60: iconst_4
      61: ldc           #66                 // String T
      63: invokestatic  #70                 // Method kotlin/jvm/internal/Intrinsics.reifiedOperationMarker:(ILjava/lang/String;)V
      66: ldc           #5                  // class java/lang/Object
      68: invokevirtual #156                // Method org/springframework/context/support/GenericApplicationContext.getBean:(Ljava/lang/String;Ljava/lang/Class;)Ljava/lang/Object;
      71: dup
      72: ldc           #158                // String context.getBean(name, T::class.java)
      74: invokestatic  #54                 // Method kotlin/jvm/internal/Intrinsics.checkExpressionValueIsNotNull:(Ljava/lang/Object;Ljava/lang/String;)V
      77: areturn

  private final <T> org.springframework.beans.factory.ObjectProvider<T> provider();
    Code:
       0: aload_0
       1: invokevirtual #78                 // Method getContext:()Lorg/springframework/context/support/GenericApplicationContext;
       4: checkcast     #167                // class org/springframework/beans/factory/BeanFactory
       7: astore_2
       8: aload_2
       9: invokestatic  #170                // Method kotlin/jvm/internal/Intrinsics.needClassReification:()V
      12: new           #172                // class org/springframework/context/support/BeanDefinitionDsl$provider$$inlined$getBeanProvider$1
      15: dup
      16: invokespecial #174                // Method org/springframework/context/support/BeanDefinitionDsl$provider$$inlined$getBeanProvider$1."<init>":()V
      19: invokevirtual #178                // Method org/springframework/context/support/BeanDefinitionDsl$provider$$inlined$getBeanProvider$1.getType:()Ljava/lang/reflect/Type;
      22: invokestatic  #184                // Method org/springframework/core/ResolvableType.forType:(Ljava/lang/reflect/Type;)Lorg/springframework/core/ResolvableType;
      25: invokeinterface #188,  2          // InterfaceMethod org/springframework/beans/factory/BeanFactory.getBeanProvider:(Lorg/springframework/core/ResolvableType;)Lorg/springframework/beans/factory/ObjectProvider;
      30: dup
      31: ldc           #190                // String getBeanProvider(Resolvab…Reference<T>() {}).type))
      33: invokestatic  #54                 // Method kotlin/jvm/internal/Intrinsics.checkExpressionValueIsNotNull:(Ljava/lang/Object;Ljava/lang/String;)V
      36: areturn

  public final void profile(java.lang.String, kotlin.jvm.functions.Function1<? super org.springframework.context.support.BeanDefinitionDsl, kotlin.Unit>);
    Code:
       0: aload_1
       1: ldc           #197                // String profile
       3: invokestatic  #44                 // Method kotlin/jvm/internal/Intrinsics.checkParameterIsNotNull:(Ljava/lang/Object;Ljava/lang/String;)V
       6: aload_2
       7: ldc           #199                // String init
       9: invokestatic  #44                 // Method kotlin/jvm/internal/Intrinsics.checkParameterIsNotNull:(Ljava/lang/Object;Ljava/lang/String;)V
      12: new           #2                  // class org/springframework/context/support/BeanDefinitionDsl
      15: dup
      16: aload_2
      17: new           #201                // class org/springframework/context/support/BeanDefinitionDsl$profile$beans$1
      20: dup
      21: aload_1
      22: invokespecial #202                // Method org/springframework/context/support/BeanDefinitionDsl$profile$beans$1."<init>":(Ljava/lang/String;)V
      25: checkcast     #204                // class kotlin/jvm/functions/Function1
      28: invokespecial #207                // Method "<init>":(Lkotlin/jvm/functions/Function1;Lkotlin/jvm/functions/Function1;)V
      31: astore_3
      32: aload_0
      33: getfield      #18                 // Field children:Ljava/util/ArrayList;
      36: aload_3
      37: invokevirtual #213                // Method java/util/ArrayList.add:(Ljava/lang/Object;)Z
      40: pop
      41: return

  public final void environment(kotlin.jvm.functions.Function1<? super org.springframework.core.env.ConfigurableEnvironment, java.lang.Boolean>, kotlin.jvm.functions.Function1<? super org.springframework.context.support.BeanDefinitionDsl, kotlin.Unit>);
    Code:
       0: aload_1
       1: ldc           #218                // String condition
       3: invokestatic  #44                 // Method kotlin/jvm/internal/Intrinsics.checkParameterIsNotNull:(Ljava/lang/Object;Ljava/lang/String;)V
       6: aload_2
       7: ldc           #199                // String init
       9: invokestatic  #44                 // Method kotlin/jvm/internal/Intrinsics.checkParameterIsNotNull:(Ljava/lang/Object;Ljava/lang/String;)V
      12: new           #2                  // class org/springframework/context/support/BeanDefinitionDsl
      15: dup
      16: aload_2
      17: new           #220                // class org/springframework/context/support/BeanDefinitionDsl$environment$beans$1
      20: dup
      21: aload_1
      22: invokespecial #223                // Method org/springframework/context/support/BeanDefinitionDsl$environment$beans$1."<init>":(Lkotlin/jvm/functions/Function1;)V
      25: checkcast     #204                // class kotlin/jvm/functions/Function1
      28: invokespecial #207                // Method "<init>":(Lkotlin/jvm/functions/Function1;Lkotlin/jvm/functions/Function1;)V
      31: astore_3
      32: aload_0
      33: getfield      #18                 // Field children:Ljava/util/ArrayList;
      36: aload_3
      37: invokevirtual #213                // Method java/util/ArrayList.add:(Ljava/lang/Object;)Z
      40: pop
      41: return

  public void initialize(org.springframework.context.support.GenericApplicationContext);
    Code:
       0: aload_1
       1: ldc           #28                 // String context
       3: invokestatic  #44                 // Method kotlin/jvm/internal/Intrinsics.checkParameterIsNotNull:(Ljava/lang/Object;Ljava/lang/String;)V
       6: aload_0
       7: aload_1
       8: putfield      #27                 // Field context:Lorg/springframework/context/support/GenericApplicationContext;
      11: aload_0
      12: getfield      #229                // Field init:Lkotlin/jvm/functions/Function1;
      15: aload_0
      16: invokeinterface #233,  2          // InterfaceMethod kotlin/jvm/functions/Function1.invoke:(Ljava/lang/Object;)Ljava/lang/Object;
      21: pop
      22: aload_0
      23: getfield      #18                 // Field children:Ljava/util/ArrayList;
      26: invokevirtual #237                // Method java/util/ArrayList.iterator:()Ljava/util/Iterator;
      29: astore_3
      30: aload_3
      31: invokeinterface #243,  1          // InterfaceMethod java/util/Iterator.hasNext:()Z
      36: ifeq          85
      39: aload_3
      40: invokeinterface #247,  1          // InterfaceMethod java/util/Iterator.next:()Ljava/lang/Object;
      45: checkcast     #2                  // class org/springframework/context/support/BeanDefinitionDsl
      48: astore_2
      49: aload_2
      50: getfield      #249                // Field condition:Lkotlin/jvm/functions/Function1;
      53: aload_1
      54: invokevirtual #49                 // Method org/springframework/context/support/GenericApplicationContext.getEnvironment:()Lorg/springframework/core/env/ConfigurableEnvironment;
      57: dup
      58: ldc           #51                 // String context.environment
      60: invokestatic  #54                 // Method kotlin/jvm/internal/Intrinsics.checkExpressionValueIsNotNull:(Ljava/lang/Object;Ljava/lang/String;)V
      63: invokeinterface #233,  2          // InterfaceMethod kotlin/jvm/functions/Function1.invoke:(Ljava/lang/Object;)Ljava/lang/Object;
      68: checkcast     #116                // class java/lang/Boolean
      71: invokevirtual #252                // Method java/lang/Boolean.booleanValue:()Z
      74: ifeq          82
      77: aload_2
      78: aload_1
      79: invokevirtual #227                // Method initialize:(Lorg/springframework/context/support/GenericApplicationContext;)V
      82: goto          30
      85: return

  public void initialize(org.springframework.context.ConfigurableApplicationContext);
    Code:
       0: aload_0
       1: aload_1
       2: checkcast     #36                 // class org/springframework/context/support/GenericApplicationContext
       5: invokevirtual #227                // Method initialize:(Lorg/springframework/context/support/GenericApplicationContext;)V
       8: return

  public org.springframework.context.support.BeanDefinitionDsl(kotlin.jvm.functions.Function1<? super org.springframework.context.support.BeanDefinitionDsl, kotlin.Unit>, kotlin.jvm.functions.Function1<? super org.springframework.core.env.ConfigurableEnvironment, java.lang.Boolean>);
    Code:
       0: aload_1
       1: ldc           #199                // String init
       3: invokestatic  #44                 // Method kotlin/jvm/internal/Intrinsics.checkParameterIsNotNull:(Ljava/lang/Object;Ljava/lang/String;)V
       6: aload_2
       7: ldc           #218                // String condition
       9: invokestatic  #44                 // Method kotlin/jvm/internal/Intrinsics.checkParameterIsNotNull:(Ljava/lang/Object;Ljava/lang/String;)V
      12: aload_0
      13: invokespecial #256                // Method java/lang/Object."<init>":()V
      16: aload_0
      17: aload_1
      18: putfield      #229                // Field init:Lkotlin/jvm/functions/Function1;
      21: aload_0
      22: aload_2
      23: putfield      #249                // Field condition:Lkotlin/jvm/functions/Function1;
      26: aload_0
      27: astore_3
      28: new           #209                // class java/util/ArrayList
      31: dup
      32: invokespecial #257                // Method java/util/ArrayList."<init>":()V
      35: astore        4
      37: aload_3
      38: aload         4
      40: putfield      #18                 // Field children:Ljava/util/ArrayList;
      43: return

  public org.springframework.context.support.BeanDefinitionDsl(kotlin.jvm.functions.Function1, kotlin.jvm.functions.Function1, int, kotlin.jvm.internal.DefaultConstructorMarker);
    Code:
       0: iload_3
       1: iconst_2
       2: iand
       3: ifeq          13
       6: getstatic     #264                // Field org/springframework/context/support/BeanDefinitionDsl$1.INSTANCE:Lorg/springframework/context/support/BeanDefinitionDsl$1;
       9: checkcast     #204                // class kotlin/jvm/functions/Function1
      12: astore_2
      13: aload_0
      14: aload_1
      15: aload_2
      16: invokespecial #207                // Method "<init>":(Lkotlin/jvm/functions/Function1;Lkotlin/jvm/functions/Function1;)V
      19: return
}
