Compiled from "RealmSubjectUserInfo.java"
public class org.jboss.as.core.security.RealmSubjectUserInfo implements org.jboss.as.core.security.SubjectUserInfo {
  private final java.lang.String userName;

  private final javax.security.auth.Subject subject;

  public org.jboss.as.core.security.RealmSubjectUserInfo(javax.security.auth.Subject);
    Code:
       0: aload_0
       1: invokespecial #1                  // Method java/lang/Object."<init>":()V
       4: aload_0
       5: aload_1
       6: putfield      #2                  // Field subject:Ljavax/security/auth/Subject;
       9: aload_1
      10: ldc           #3                  // class org/jboss/as/core/security/RealmUser
      12: invokevirtual #4                  // Method javax/security/auth/Subject.getPrincipals:(Ljava/lang/Class;)Ljava/util/Set;
      15: astore_2
      16: aload_0
      17: aload_2
      18: invokeinterface #5,  1            // InterfaceMethod java/util/Set.isEmpty:()Z
      23: ifeq          30
      26: aconst_null
      27: goto          47
      30: aload_2
      31: invokeinterface #6,  1            // InterfaceMethod java/util/Set.iterator:()Ljava/util/Iterator;
      36: invokeinterface #7,  1            // InterfaceMethod java/util/Iterator.next:()Ljava/lang/Object;
      41: checkcast     #3                  // class org/jboss/as/core/security/RealmUser
      44: invokevirtual #8                  // Method org/jboss/as/core/security/RealmUser.getName:()Ljava/lang/String;
      47: putfield      #9                  // Field userName:Ljava/lang/String;
      50: return

  public java.lang.String getUserName();
    Code:
       0: aload_0
       1: getfield      #9                  // Field userName:Ljava/lang/String;
       4: areturn

  public java.util.Collection<java.security.Principal> getPrincipals();
    Code:
       0: aload_0
       1: getfield      #2                  // Field subject:Ljavax/security/auth/Subject;
       4: invokevirtual #10                 // Method javax/security/auth/Subject.getPrincipals:()Ljava/util/Set;
       7: areturn

  public javax.security.auth.Subject getSubject();
    Code:
       0: aload_0
       1: getfield      #2                  // Field subject:Ljavax/security/auth/Subject;
       4: areturn
}
