Compiled from "ConstructorInstantiator.java"
public class org.mockito.internal.creation.instance.ConstructorInstantiator implements org.mockito.internal.creation.instance.Instantiator {
  private final java.lang.Object outerClassInstance;

  public org.mockito.internal.creation.instance.ConstructorInstantiator(java.lang.Object);
    Code:
       0: aload_0
       1: invokespecial #1                  // Method java/lang/Object."<init>":()V
       4: aload_0
       5: aload_1
       6: putfield      #2                  // Field outerClassInstance:Ljava/lang/Object;
       9: return

  public <T> T newInstance(java.lang.Class<T>);
    Code:
       0: aload_0
       1: getfield      #2                  // Field outerClassInstance:Ljava/lang/Object;
       4: ifnonnull     12
       7: aload_1
       8: invokestatic  #3                  // Method noArgConstructor:(Ljava/lang/Class;)Ljava/lang/Object;
      11: areturn
      12: aload_1
      13: iconst_1
      14: anewarray     #4                  // class java/lang/Object
      17: dup
      18: iconst_0
      19: aload_0
      20: getfield      #2                  // Field outerClassInstance:Ljava/lang/Object;
      23: aastore
      24: invokestatic  #5                  // Method withParams:(Ljava/lang/Class;[Ljava/lang/Object;)Ljava/lang/Object;
      27: areturn

  private static <T> T withParams(java.lang.Class<T>, java.lang.Object...);
    Code:
       0: aload_0
       1: invokevirtual #6                  // Method java/lang/Class.getDeclaredConstructors:()[Ljava/lang/reflect/Constructor;
       4: astore_2
       5: aload_2
       6: arraylength
       7: istore_3
       8: iconst_0
       9: istore        4
      11: iload         4
      13: iload_3
      14: if_icmpge     52
      17: aload_2
      18: iload         4
      20: aaload
      21: astore        5
      23: aload         5
      25: invokevirtual #7                  // Method java/lang/reflect/Constructor.getParameterTypes:()[Ljava/lang/Class;
      28: astore        6
      30: aload         6
      32: aload_1
      33: invokestatic  #8                  // Method paramsMatch:([Ljava/lang/Class;[Ljava/lang/Object;)Z
      36: ifeq          46
      39: aload         5
      41: aload_1
      42: invokestatic  #9                  // Method invokeConstructor:(Ljava/lang/reflect/Constructor;[Ljava/lang/Object;)Ljava/lang/Object;
      45: areturn
      46: iinc          4, 1
      49: goto          11
      52: goto          62
      55: astore_2
      56: aload_0
      57: aload_2
      58: invokestatic  #11                 // Method paramsException:(Ljava/lang/Class;Ljava/lang/Exception;)Lorg/mockito/internal/creation/instance/InstantiationException;
      61: athrow
      62: aload_0
      63: aconst_null
      64: invokestatic  #11                 // Method paramsException:(Ljava/lang/Class;Ljava/lang/Exception;)Lorg/mockito/internal/creation/instance/InstantiationException;
      67: athrow
    Exception table:
       from    to  target type
           0    45    55   Class java/lang/Exception
          46    52    55   Class java/lang/Exception

  private static <T> T invokeConstructor(java.lang.reflect.Constructor<?>, java.lang.Object...) throws java.lang.InstantiationException, java.lang.IllegalAccessException, java.lang.reflect.InvocationTargetException;
    Code:
       0: new           #12                 // class org/mockito/internal/util/reflection/AccessibilityChanger
       3: dup
       4: invokespecial #13                 // Method org/mockito/internal/util/reflection/AccessibilityChanger."<init>":()V
       7: astore_2
       8: aload_2
       9: aload_0
      10: invokevirtual #14                 // Method org/mockito/internal/util/reflection/AccessibilityChanger.enableAccess:(Ljava/lang/reflect/AccessibleObject;)V
      13: aload_0
      14: aload_1
      15: invokevirtual #15                 // Method java/lang/reflect/Constructor.newInstance:([Ljava/lang/Object;)Ljava/lang/Object;
      18: areturn

  private static <T> org.mockito.internal.creation.instance.InstantiationException paramsException(java.lang.Class<T>, java.lang.Exception);
    Code:
       0: new           #16                 // class org/mockito/internal/creation/instance/InstantiationException
       3: dup
       4: iconst_2
       5: anewarray     #4                  // class java/lang/Object
       8: dup
       9: iconst_0
      10: new           #17                 // class java/lang/StringBuilder
      13: dup
      14: invokespecial #18                 // Method java/lang/StringBuilder."<init>":()V
      17: ldc           #19                 // String Unable to create instance of \'
      19: invokevirtual #20                 // Method java/lang/StringBuilder.append:(Ljava/lang/String;)Ljava/lang/StringBuilder;
      22: aload_0
      23: invokevirtual #21                 // Method java/lang/Class.getSimpleName:()Ljava/lang/String;
      26: invokevirtual #20                 // Method java/lang/StringBuilder.append:(Ljava/lang/String;)Ljava/lang/StringBuilder;
      29: ldc           #22                 // String \'.
      31: invokevirtual #20                 // Method java/lang/StringBuilder.append:(Ljava/lang/String;)Ljava/lang/StringBuilder;
      34: invokevirtual #23                 // Method java/lang/StringBuilder.toString:()Ljava/lang/String;
      37: aastore
      38: dup
      39: iconst_1
      40: ldc           #24                 // String Please ensure that the outer instance has correct type and that the target class has 0-arg constructor.
      42: aastore
      43: invokestatic  #25                 // Method org/mockito/internal/util/StringJoiner.join:([Ljava/lang/Object;)Ljava/lang/String;
      46: aload_1
      47: invokespecial #26                 // Method org/mockito/internal/creation/instance/InstantiationException."<init>":(Ljava/lang/String;Ljava/lang/Throwable;)V
      50: areturn

  private static boolean paramsMatch(java.lang.Class<?>[], java.lang.Object[]);
    Code:
       0: aload_1
       1: arraylength
       2: aload_0
       3: arraylength
       4: if_icmpeq     9
       7: iconst_0
       8: ireturn
       9: iconst_0
      10: istore_2
      11: iload_2
      12: aload_1
      13: arraylength
      14: if_icmpge     37
      17: aload_0
      18: iload_2
      19: aaload
      20: aload_1
      21: iload_2
      22: aaload
      23: invokevirtual #27                 // Method java/lang/Class.isInstance:(Ljava/lang/Object;)Z
      26: ifne          31
      29: iconst_0
      30: ireturn
      31: iinc          2, 1
      34: goto          11
      37: iconst_1
      38: ireturn

  private static <T> T noArgConstructor(java.lang.Class<T>);
    Code:
       0: aload_0
       1: iconst_0
       2: anewarray     #28                 // class java/lang/Class
       5: invokevirtual #29                 // Method java/lang/Class.getDeclaredConstructor:([Ljava/lang/Class;)Ljava/lang/reflect/Constructor;
       8: iconst_0
       9: anewarray     #4                  // class java/lang/Object
      12: invokestatic  #9                  // Method invokeConstructor:(Ljava/lang/reflect/Constructor;[Ljava/lang/Object;)Ljava/lang/Object;
      15: areturn
      16: astore_1
      17: new           #16                 // class org/mockito/internal/creation/instance/InstantiationException
      20: dup
      21: iconst_2
      22: anewarray     #4                  // class java/lang/Object
      25: dup
      26: iconst_0
      27: new           #17                 // class java/lang/StringBuilder
      30: dup
      31: invokespecial #18                 // Method java/lang/StringBuilder."<init>":()V
      34: ldc           #19                 // String Unable to create instance of \'
      36: invokevirtual #20                 // Method java/lang/StringBuilder.append:(Ljava/lang/String;)Ljava/lang/StringBuilder;
      39: aload_0
      40: invokevirtual #21                 // Method java/lang/Class.getSimpleName:()Ljava/lang/String;
      43: invokevirtual #20                 // Method java/lang/StringBuilder.append:(Ljava/lang/String;)Ljava/lang/StringBuilder;
      46: ldc           #22                 // String \'.
      48: invokevirtual #20                 // Method java/lang/StringBuilder.append:(Ljava/lang/String;)Ljava/lang/StringBuilder;
      51: invokevirtual #23                 // Method java/lang/StringBuilder.toString:()Ljava/lang/String;
      54: aastore
      55: dup
      56: iconst_1
      57: ldc           #31                 // String Please ensure it has 0-arg constructor which invokes cleanly.
      59: aastore
      60: invokestatic  #25                 // Method org/mockito/internal/util/StringJoiner.join:([Ljava/lang/Object;)Ljava/lang/String;
      63: aload_1
      64: invokespecial #26                 // Method org/mockito/internal/creation/instance/InstantiationException."<init>":(Ljava/lang/String;Ljava/lang/Throwable;)V
      67: athrow
    Exception table:
       from    to  target type
           0    15    16   Class java/lang/Throwable
}
