Compiled from "AdminObjectService.java"
final class org.jboss.as.connector.subsystems.resourceadapters.AdminObjectService implements org.jboss.msc.service.Service<org.jboss.as.connector.subsystems.resourceadapters.ModifiableAdminObject> {
  private final org.jboss.as.connector.subsystems.resourceadapters.ModifiableAdminObject value;

  private final org.jboss.msc.value.InjectedValue<org.jboss.as.connector.subsystems.resourceadapters.ModifiableResourceAdapter> ra;

  public org.jboss.as.connector.subsystems.resourceadapters.AdminObjectService(org.jboss.as.connector.subsystems.resourceadapters.ModifiableAdminObject);
    Code:
       0: aload_0
       1: invokespecial #1                  // Method java/lang/Object."<init>":()V
       4: aload_0
       5: new           #2                  // class org/jboss/msc/value/InjectedValue
       8: dup
       9: invokespecial #3                  // Method org/jboss/msc/value/InjectedValue."<init>":()V
      12: putfield      #4                  // Field ra:Lorg/jboss/msc/value/InjectedValue;
      15: aload_0
      16: aload_1
      17: putfield      #5                  // Field value:Lorg/jboss/as/connector/subsystems/resourceadapters/ModifiableAdminObject;
      20: return

  public org.jboss.as.connector.subsystems.resourceadapters.ModifiableAdminObject getValue() throws java.lang.IllegalStateException;
    Code:
       0: aload_0
       1: getfield      #5                  // Field value:Lorg/jboss/as/connector/subsystems/resourceadapters/ModifiableAdminObject;
       4: areturn

  public void start(org.jboss.msc.service.StartContext) throws org.jboss.msc.service.StartException;
    Code:
       0: aload_0
       1: getfield      #4                  // Field ra:Lorg/jboss/msc/value/InjectedValue;
       4: invokevirtual #6                  // Method org/jboss/msc/value/InjectedValue.getValue:()Ljava/lang/Object;
       7: checkcast     #7                  // class org/jboss/as/connector/subsystems/resourceadapters/ModifiableResourceAdapter
      10: aload_0
      11: getfield      #5                  // Field value:Lorg/jboss/as/connector/subsystems/resourceadapters/ModifiableAdminObject;
      14: invokevirtual #8                  // Method org/jboss/as/connector/subsystems/resourceadapters/ModifiableResourceAdapter.addAdminObject:(Lorg/jboss/jca/common/api/metadata/resourceadapter/AdminObject;)V
      17: getstatic     #9                  // Field org/jboss/as/connector/logging/ConnectorLogger.SUBSYSTEM_RA_LOGGER:Lorg/jboss/as/connector/logging/ConnectorLogger;
      20: ldc           #10                 // String Starting ResourceAdapters Service
      22: iconst_0
      23: anewarray     #11                 // class java/lang/Object
      26: invokeinterface #12,  3           // InterfaceMethod org/jboss/as/connector/logging/ConnectorLogger.debugf:(Ljava/lang/String;[Ljava/lang/Object;)V
      31: return

  public void stop(org.jboss.msc.service.StopContext);
    Code:
       0: return

  public org.jboss.msc.inject.Injector<org.jboss.as.connector.subsystems.resourceadapters.ModifiableResourceAdapter> getRaInjector();
    Code:
       0: aload_0
       1: getfield      #4                  // Field ra:Lorg/jboss/msc/value/InjectedValue;
       4: areturn

  public java.lang.Object getValue() throws java.lang.IllegalStateException, java.lang.IllegalArgumentException;
    Code:
       0: aload_0
       1: invokevirtual #13                 // Method getValue:()Lorg/jboss/as/connector/subsystems/resourceadapters/ModifiableAdminObject;
       4: areturn
}
