Compiled from "AS7ResourceAdapterTags.java"
public final class org.jboss.as.connector.subsystems.resourceadapters.AS7ResourceAdapterTags extends java.lang.Enum<org.jboss.as.connector.subsystems.resourceadapters.AS7ResourceAdapterTags> {
  public static final org.jboss.as.connector.subsystems.resourceadapters.AS7ResourceAdapterTags UNKNOWN;

  public static final org.jboss.as.connector.subsystems.resourceadapters.AS7ResourceAdapterTags ID;

  public static final org.jboss.as.connector.subsystems.resourceadapters.AS7ResourceAdapterTags CONFIG_PROPERTY;

  public static final org.jboss.as.connector.subsystems.resourceadapters.AS7ResourceAdapterTags ARCHIVE;

  public static final org.jboss.as.connector.subsystems.resourceadapters.AS7ResourceAdapterTags MODULE;

  public static final org.jboss.as.connector.subsystems.resourceadapters.AS7ResourceAdapterTags BEAN_VALIDATION_GROUPS;

  public static final org.jboss.as.connector.subsystems.resourceadapters.AS7ResourceAdapterTags BEAN_VALIDATION_GROUP;

  public static final org.jboss.as.connector.subsystems.resourceadapters.AS7ResourceAdapterTags BOOTSTRAP_CONTEXT;

  public static final org.jboss.as.connector.subsystems.resourceadapters.AS7ResourceAdapterTags TRANSACTION_SUPPORT;

  public static final org.jboss.as.connector.subsystems.resourceadapters.AS7ResourceAdapterTags CONNECTION_DEFINITIONS;

  public static final org.jboss.as.connector.subsystems.resourceadapters.AS7ResourceAdapterTags CONNECTION_DEFINITION;

  public static final org.jboss.as.connector.subsystems.resourceadapters.AS7ResourceAdapterTags ADMIN_OBJECTS;

  public static final org.jboss.as.connector.subsystems.resourceadapters.AS7ResourceAdapterTags ADMIN_OBJECT;

  public static final org.jboss.as.connector.subsystems.resourceadapters.AS7ResourceAdapterTags WORKMANAGER;

  private java.lang.String name;

  private static final java.util.Map<java.lang.String, org.jboss.as.connector.subsystems.resourceadapters.AS7ResourceAdapterTags> MAP;

  private static final org.jboss.as.connector.subsystems.resourceadapters.AS7ResourceAdapterTags[] $VALUES;

  public static org.jboss.as.connector.subsystems.resourceadapters.AS7ResourceAdapterTags[] values();
    Code:
       0: getstatic     #1                  // Field $VALUES:[Lorg/jboss/as/connector/subsystems/resourceadapters/AS7ResourceAdapterTags;
       3: invokevirtual #2                  // Method "[Lorg/jboss/as/connector/subsystems/resourceadapters/AS7ResourceAdapterTags;".clone:()Ljava/lang/Object;
       6: checkcast     #3                  // class "[Lorg/jboss/as/connector/subsystems/resourceadapters/AS7ResourceAdapterTags;"
       9: areturn

  public static org.jboss.as.connector.subsystems.resourceadapters.AS7ResourceAdapterTags valueOf(java.lang.String);
    Code:
       0: ldc           #4                  // class org/jboss/as/connector/subsystems/resourceadapters/AS7ResourceAdapterTags
       2: aload_0
       3: invokestatic  #5                  // Method java/lang/Enum.valueOf:(Ljava/lang/Class;Ljava/lang/String;)Ljava/lang/Enum;
       6: checkcast     #4                  // class org/jboss/as/connector/subsystems/resourceadapters/AS7ResourceAdapterTags
       9: areturn

  private org.jboss.as.connector.subsystems.resourceadapters.AS7ResourceAdapterTags(java.lang.String);
    Code:
       0: aload_0
       1: aload_1
       2: iload_2
       3: invokespecial #6                  // Method java/lang/Enum."<init>":(Ljava/lang/String;I)V
       6: aload_0
       7: aload_3
       8: putfield      #7                  // Field name:Ljava/lang/String;
      11: return

  public java.lang.String getLocalName();
    Code:
       0: aload_0
       1: getfield      #7                  // Field name:Ljava/lang/String;
       4: areturn

  public java.lang.String toString();
    Code:
       0: aload_0
       1: getfield      #7                  // Field name:Ljava/lang/String;
       4: areturn

  org.jboss.as.connector.subsystems.resourceadapters.AS7ResourceAdapterTags value(java.lang.String);
    Code:
       0: aload_0
       1: aload_1
       2: putfield      #7                  // Field name:Ljava/lang/String;
       5: aload_0
       6: areturn

  public static org.jboss.as.connector.subsystems.resourceadapters.AS7ResourceAdapterTags forName(java.lang.String);
    Code:
       0: getstatic     #8                  // Field MAP:Ljava/util/Map;
       3: aload_0
       4: invokeinterface #9,  2            // InterfaceMethod java/util/Map.get:(Ljava/lang/Object;)Ljava/lang/Object;
       9: checkcast     #4                  // class org/jboss/as/connector/subsystems/resourceadapters/AS7ResourceAdapterTags
      12: astore_1
      13: aload_1
      14: ifnonnull     27
      17: getstatic     #10                 // Field UNKNOWN:Lorg/jboss/as/connector/subsystems/resourceadapters/AS7ResourceAdapterTags;
      20: aload_0
      21: invokevirtual #11                 // Method value:(Ljava/lang/String;)Lorg/jboss/as/connector/subsystems/resourceadapters/AS7ResourceAdapterTags;
      24: goto          28
      27: aload_1
      28: areturn

  static {};
    Code:
       0: new           #4                  // class org/jboss/as/connector/subsystems/resourceadapters/AS7ResourceAdapterTags
       3: dup
       4: ldc           #12                 // String UNKNOWN
       6: iconst_0
       7: aconst_null
       8: invokespecial #13                 // Method "<init>":(Ljava/lang/String;ILjava/lang/String;)V
      11: putstatic     #10                 // Field UNKNOWN:Lorg/jboss/as/connector/subsystems/resourceadapters/AS7ResourceAdapterTags;
      14: new           #4                  // class org/jboss/as/connector/subsystems/resourceadapters/AS7ResourceAdapterTags
      17: dup
      18: ldc           #14                 // String ID
      20: iconst_1
      21: ldc           #15                 // String id
      23: invokespecial #13                 // Method "<init>":(Ljava/lang/String;ILjava/lang/String;)V
      26: putstatic     #16                 // Field ID:Lorg/jboss/as/connector/subsystems/resourceadapters/AS7ResourceAdapterTags;
      29: new           #4                  // class org/jboss/as/connector/subsystems/resourceadapters/AS7ResourceAdapterTags
      32: dup
      33: ldc           #17                 // String CONFIG_PROPERTY
      35: iconst_2
      36: ldc           #18                 // String config-property
      38: invokespecial #13                 // Method "<init>":(Ljava/lang/String;ILjava/lang/String;)V
      41: putstatic     #19                 // Field CONFIG_PROPERTY:Lorg/jboss/as/connector/subsystems/resourceadapters/AS7ResourceAdapterTags;
      44: new           #4                  // class org/jboss/as/connector/subsystems/resourceadapters/AS7ResourceAdapterTags
      47: dup
      48: ldc           #20                 // String ARCHIVE
      50: iconst_3
      51: ldc           #21                 // String archive
      53: invokespecial #13                 // Method "<init>":(Ljava/lang/String;ILjava/lang/String;)V
      56: putstatic     #22                 // Field ARCHIVE:Lorg/jboss/as/connector/subsystems/resourceadapters/AS7ResourceAdapterTags;
      59: new           #4                  // class org/jboss/as/connector/subsystems/resourceadapters/AS7ResourceAdapterTags
      62: dup
      63: ldc           #23                 // String MODULE
      65: iconst_4
      66: ldc           #24                 // String module
      68: invokespecial #13                 // Method "<init>":(Ljava/lang/String;ILjava/lang/String;)V
      71: putstatic     #25                 // Field MODULE:Lorg/jboss/as/connector/subsystems/resourceadapters/AS7ResourceAdapterTags;
      74: new           #4                  // class org/jboss/as/connector/subsystems/resourceadapters/AS7ResourceAdapterTags
      77: dup
      78: ldc           #26                 // String BEAN_VALIDATION_GROUPS
      80: iconst_5
      81: ldc           #27                 // String bean-validation-groups
      83: invokespecial #13                 // Method "<init>":(Ljava/lang/String;ILjava/lang/String;)V
      86: putstatic     #28                 // Field BEAN_VALIDATION_GROUPS:Lorg/jboss/as/connector/subsystems/resourceadapters/AS7ResourceAdapterTags;
      89: new           #4                  // class org/jboss/as/connector/subsystems/resourceadapters/AS7ResourceAdapterTags
      92: dup
      93: ldc           #29                 // String BEAN_VALIDATION_GROUP
      95: bipush        6
      97: ldc           #30                 // String bean-validation-group
      99: invokespecial #13                 // Method "<init>":(Ljava/lang/String;ILjava/lang/String;)V
     102: putstatic     #31                 // Field BEAN_VALIDATION_GROUP:Lorg/jboss/as/connector/subsystems/resourceadapters/AS7ResourceAdapterTags;
     105: new           #4                  // class org/jboss/as/connector/subsystems/resourceadapters/AS7ResourceAdapterTags
     108: dup
     109: ldc           #32                 // String BOOTSTRAP_CONTEXT
     111: bipush        7
     113: ldc           #33                 // String bootstrap-context
     115: invokespecial #13                 // Method "<init>":(Ljava/lang/String;ILjava/lang/String;)V
     118: putstatic     #34                 // Field BOOTSTRAP_CONTEXT:Lorg/jboss/as/connector/subsystems/resourceadapters/AS7ResourceAdapterTags;
     121: new           #4                  // class org/jboss/as/connector/subsystems/resourceadapters/AS7ResourceAdapterTags
     124: dup
     125: ldc           #35                 // String TRANSACTION_SUPPORT
     127: bipush        8
     129: ldc           #36                 // String transaction-support
     131: invokespecial #13                 // Method "<init>":(Ljava/lang/String;ILjava/lang/String;)V
     134: putstatic     #37                 // Field TRANSACTION_SUPPORT:Lorg/jboss/as/connector/subsystems/resourceadapters/AS7ResourceAdapterTags;
     137: new           #4                  // class org/jboss/as/connector/subsystems/resourceadapters/AS7ResourceAdapterTags
     140: dup
     141: ldc           #38                 // String CONNECTION_DEFINITIONS
     143: bipush        9
     145: ldc           #39                 // String connection-definitions
     147: invokespecial #13                 // Method "<init>":(Ljava/lang/String;ILjava/lang/String;)V
     150: putstatic     #40                 // Field CONNECTION_DEFINITIONS:Lorg/jboss/as/connector/subsystems/resourceadapters/AS7ResourceAdapterTags;
     153: new           #4                  // class org/jboss/as/connector/subsystems/resourceadapters/AS7ResourceAdapterTags
     156: dup
     157: ldc           #41                 // String CONNECTION_DEFINITION
     159: bipush        10
     161: ldc           #42                 // String connection-definition
     163: invokespecial #13                 // Method "<init>":(Ljava/lang/String;ILjava/lang/String;)V
     166: putstatic     #43                 // Field CONNECTION_DEFINITION:Lorg/jboss/as/connector/subsystems/resourceadapters/AS7ResourceAdapterTags;
     169: new           #4                  // class org/jboss/as/connector/subsystems/resourceadapters/AS7ResourceAdapterTags
     172: dup
     173: ldc           #44                 // String ADMIN_OBJECTS
     175: bipush        11
     177: ldc           #45                 // String admin-objects
     179: invokespecial #13                 // Method "<init>":(Ljava/lang/String;ILjava/lang/String;)V
     182: putstatic     #46                 // Field ADMIN_OBJECTS:Lorg/jboss/as/connector/subsystems/resourceadapters/AS7ResourceAdapterTags;
     185: new           #4                  // class org/jboss/as/connector/subsystems/resourceadapters/AS7ResourceAdapterTags
     188: dup
     189: ldc           #47                 // String ADMIN_OBJECT
     191: bipush        12
     193: ldc           #48                 // String admin-object
     195: invokespecial #13                 // Method "<init>":(Ljava/lang/String;ILjava/lang/String;)V
     198: putstatic     #49                 // Field ADMIN_OBJECT:Lorg/jboss/as/connector/subsystems/resourceadapters/AS7ResourceAdapterTags;
     201: new           #4                  // class org/jboss/as/connector/subsystems/resourceadapters/AS7ResourceAdapterTags
     204: dup
     205: ldc           #50                 // String WORKMANAGER
     207: bipush        13
     209: ldc           #51                 // String workmanager
     211: invokespecial #13                 // Method "<init>":(Ljava/lang/String;ILjava/lang/String;)V
     214: putstatic     #52                 // Field WORKMANAGER:Lorg/jboss/as/connector/subsystems/resourceadapters/AS7ResourceAdapterTags;
     217: bipush        14
     219: anewarray     #4                  // class org/jboss/as/connector/subsystems/resourceadapters/AS7ResourceAdapterTags
     222: dup
     223: iconst_0
     224: getstatic     #10                 // Field UNKNOWN:Lorg/jboss/as/connector/subsystems/resourceadapters/AS7ResourceAdapterTags;
     227: aastore
     228: dup
     229: iconst_1
     230: getstatic     #16                 // Field ID:Lorg/jboss/as/connector/subsystems/resourceadapters/AS7ResourceAdapterTags;
     233: aastore
     234: dup
     235: iconst_2
     236: getstatic     #19                 // Field CONFIG_PROPERTY:Lorg/jboss/as/connector/subsystems/resourceadapters/AS7ResourceAdapterTags;
     239: aastore
     240: dup
     241: iconst_3
     242: getstatic     #22                 // Field ARCHIVE:Lorg/jboss/as/connector/subsystems/resourceadapters/AS7ResourceAdapterTags;
     245: aastore
     246: dup
     247: iconst_4
     248: getstatic     #25                 // Field MODULE:Lorg/jboss/as/connector/subsystems/resourceadapters/AS7ResourceAdapterTags;
     251: aastore
     252: dup
     253: iconst_5
     254: getstatic     #28                 // Field BEAN_VALIDATION_GROUPS:Lorg/jboss/as/connector/subsystems/resourceadapters/AS7ResourceAdapterTags;
     257: aastore
     258: dup
     259: bipush        6
     261: getstatic     #31                 // Field BEAN_VALIDATION_GROUP:Lorg/jboss/as/connector/subsystems/resourceadapters/AS7ResourceAdapterTags;
     264: aastore
     265: dup
     266: bipush        7
     268: getstatic     #34                 // Field BOOTSTRAP_CONTEXT:Lorg/jboss/as/connector/subsystems/resourceadapters/AS7ResourceAdapterTags;
     271: aastore
     272: dup
     273: bipush        8
     275: getstatic     #37                 // Field TRANSACTION_SUPPORT:Lorg/jboss/as/connector/subsystems/resourceadapters/AS7ResourceAdapterTags;
     278: aastore
     279: dup
     280: bipush        9
     282: getstatic     #40                 // Field CONNECTION_DEFINITIONS:Lorg/jboss/as/connector/subsystems/resourceadapters/AS7ResourceAdapterTags;
     285: aastore
     286: dup
     287: bipush        10
     289: getstatic     #43                 // Field CONNECTION_DEFINITION:Lorg/jboss/as/connector/subsystems/resourceadapters/AS7ResourceAdapterTags;
     292: aastore
     293: dup
     294: bipush        11
     296: getstatic     #46                 // Field ADMIN_OBJECTS:Lorg/jboss/as/connector/subsystems/resourceadapters/AS7ResourceAdapterTags;
     299: aastore
     300: dup
     301: bipush        12
     303: getstatic     #49                 // Field ADMIN_OBJECT:Lorg/jboss/as/connector/subsystems/resourceadapters/AS7ResourceAdapterTags;
     306: aastore
     307: dup
     308: bipush        13
     310: getstatic     #52                 // Field WORKMANAGER:Lorg/jboss/as/connector/subsystems/resourceadapters/AS7ResourceAdapterTags;
     313: aastore
     314: putstatic     #1                  // Field $VALUES:[Lorg/jboss/as/connector/subsystems/resourceadapters/AS7ResourceAdapterTags;
     317: new           #53                 // class java/util/HashMap
     320: dup
     321: invokespecial #54                 // Method java/util/HashMap."<init>":()V
     324: astore_0
     325: invokestatic  #55                 // Method values:()[Lorg/jboss/as/connector/subsystems/resourceadapters/AS7ResourceAdapterTags;
     328: astore_1
     329: aload_1
     330: arraylength
     331: istore_2
     332: iconst_0
     333: istore_3
     334: iload_3
     335: iload_2
     336: if_icmpge     373
     339: aload_1
     340: iload_3
     341: aaload
     342: astore        4
     344: aload         4
     346: invokevirtual #56                 // Method getLocalName:()Ljava/lang/String;
     349: astore        5
     351: aload         5
     353: ifnull        367
     356: aload_0
     357: aload         5
     359: aload         4
     361: invokeinterface #57,  3           // InterfaceMethod java/util/Map.put:(Ljava/lang/Object;Ljava/lang/Object;)Ljava/lang/Object;
     366: pop
     367: iinc          3, 1
     370: goto          334
     373: aload_0
     374: putstatic     #8                  // Field MAP:Ljava/util/Map;
     377: return
}
