Compiled from "Constants.java"
public class org.jboss.as.connector.subsystems.resourceadapters.Constants {
  public static final java.lang.String RESOURCEADAPTER_NAME;

  public static final java.lang.String WORKMANAGER_NAME;

  public static final java.lang.String DISTRIBUTED_WORKMANAGER_NAME;

  static final java.lang.String RESOURCEADAPTERS_NAME;

  public static final java.lang.String IRONJACAMAR_NAME;

  public static final java.lang.String STATISTICS_NAME;

  public static final java.lang.String CONNECTIONDEFINITIONS_NAME;

  private static final java.lang.String CLASS_NAME_NAME;

  static final java.lang.String POOL_NAME_NAME;

  private static final java.lang.String USE_JAVA_CONTEXT_NAME;

  private static final java.lang.String ENABLED_NAME;

  private static final java.lang.String CONNECTABLE_NAME;

  private static final java.lang.String TRACKING_NAME;

  private static final java.lang.String JNDINAME_NAME;

  private static final java.lang.String ALLOCATION_RETRY_NAME;

  private static final java.lang.String ALLOCATION_RETRY_WAIT_MILLIS_NAME;

  private static final java.lang.String XA_RESOURCE_TIMEOUT_NAME;

  private static final java.lang.String USETRYLOCK_NAME;

  private static final java.lang.String SECURITY_DOMAIN_AND_APPLICATION_NAME;

  private static final java.lang.String SECURITY_DOMAIN_NAME;

  private static final java.lang.String APPLICATION_NAME;

  private static final java.lang.String USE_CCM_NAME;

  private static final java.lang.String SHARABLE_NAME;

  private static final java.lang.String ENLISTMENT_NAME;

  private static final java.lang.String ENLISTMENT_TRACE_NAME;

  private static final java.lang.String MCP_NAME;

  private static final java.lang.String CONFIG_PROPERTIES_NAME;

  private static final java.lang.String CONFIG_PROPERTY_VALUE_NAME;

  private static final java.lang.String ARCHIVE_NAME;

  private static final java.lang.String MODULE_NAME;

  private static final java.lang.String BOOTSTRAPCONTEXT_NAME;

  private static final java.lang.String TRANSACTIONSUPPORT_NAME;

  private static final java.lang.String WM_SECURITY_NAME;

  private static final java.lang.String WM_SECURITY_MAPPING_REQUIRED_NAME;

  private static final java.lang.String WM_SECURITY_DOMAIN_NAME;

  private static final java.lang.String WM_SECURITY_DEFAULT_PRINCIPAL_NAME;

  private static final java.lang.String WM_SECURITY_DEFAULT_GROUP_NAME;

  private static final java.lang.String WM_SECURITY_DEFAULT_GROUPS_NAME;

  private static final java.lang.String WM_SECURITY_MAPPING_FROM_NAME;

  private static final java.lang.String WM_SECURITY_MAPPING_TO_NAME;

  private static final java.lang.String WM_SECURITY_MAPPING_GROUP_NAME;

  private static final java.lang.String WM_SECURITY_MAPPING_GROUPS_NAME;

  private static final java.lang.String WM_SECURITY_MAPPING_USER_NAME;

  private static final java.lang.String WM_SECURITY_MAPPING_USERS_NAME;

  private static final java.lang.String BEANVALIDATIONGROUPS_NAME;

  public static final java.lang.String ADMIN_OBJECTS_NAME;

  private static final java.lang.String INTERLEAVING_NAME;

  private static final java.lang.String NOTXSEPARATEPOOL_NAME;

  private static final java.lang.String PAD_XID_NAME;

  private static final java.lang.String SAME_RM_OVERRIDE_NAME;

  private static final java.lang.String WRAP_XA_RESOURCE_NAME;

  private static final java.lang.String RECOVERY_USERNAME_NAME;

  private static final java.lang.String RECOVERY_PASSWORD_NAME;

  private static final java.lang.String RECOVERY_SECURITY_DOMAIN_NAME;

  private static final java.lang.String RECOVERLUGIN_CLASSNAME_NAME;

  private static final java.lang.String RECOVERLUGIN_PROPERTIES_NAME;

  private static final java.lang.String NO_RECOVERY_NAME;

  public static final java.lang.String ACTIVATE;

  public static final java.lang.String FLUSH_ALL_CONNECTION_IN_POOL;

  public static final java.lang.String FLUSH_IDLE_CONNECTION_IN_POOL;

  public static final java.lang.String FLUSH_INVALID_CONNECTION_IN_POOL;

  public static final java.lang.String FLUSH_GRACEFULLY_CONNECTION_IN_POOL;

  public static final java.lang.String TEST_CONNECTION_IN_POOL;

  public static final java.lang.String CLEAR_STATISTICS;

  static final org.jboss.as.controller.SimpleAttributeDefinition CLASS_NAME;

  static org.jboss.as.controller.SimpleAttributeDefinition JNDINAME;

  public static final org.jboss.as.controller.SimpleAttributeDefinition CONFIG_PROPERTIES;

  static final org.jboss.as.controller.SimpleAttributeDefinition CONFIG_PROPERTY_VALUE;

  static final org.jboss.as.controller.SimpleAttributeDefinition ARCHIVE;

  static final org.jboss.as.controller.SimpleAttributeDefinition MODULE;

  static final org.jboss.as.controller.SimpleAttributeDefinition BOOTSTRAP_CONTEXT;

  static final org.jboss.as.controller.SimpleAttributeDefinition TRANSACTION_SUPPORT;

  static org.jboss.as.controller.SimpleAttributeDefinition STATISTICS_ENABLED;

  static final org.jboss.as.controller.SimpleAttributeDefinition WM_SECURITY;

  static final org.jboss.as.controller.SimpleAttributeDefinition WM_SECURITY_MAPPING_REQUIRED;

  static final org.jboss.as.controller.SimpleAttributeDefinition WM_SECURITY_DOMAIN;

  static final org.jboss.as.controller.SimpleAttributeDefinition WM_SECURITY_DEFAULT_PRINCIPAL;

  static final org.jboss.as.controller.StringListAttributeDefinition WM_SECURITY_DEFAULT_GROUPS;

  static final org.jboss.as.controller.SimpleAttributeDefinition WM_SECURITY_DEFAULT_GROUP;

  static final org.jboss.as.controller.SimpleAttributeDefinition WM_SECURITY_MAPPING_FROM;

  static final org.jboss.as.controller.SimpleAttributeDefinition WM_SECURITY_MAPPING_TO;

  static final org.jboss.as.controller.ObjectTypeAttributeDefinition WM_SECURITY_MAPPING_GROUP;

  static final org.jboss.as.controller.ObjectListAttributeDefinition WM_SECURITY_MAPPING_GROUPS;

  static final org.jboss.as.controller.ObjectTypeAttributeDefinition WM_SECURITY_MAPPING_USER;

  static final org.jboss.as.controller.ObjectListAttributeDefinition WM_SECURITY_MAPPING_USERS;

  static final org.jboss.as.controller.StringListAttributeDefinition BEANVALIDATION_GROUPS;

  static final org.jboss.as.controller.SimpleAttributeDefinition BEANVALIDATIONGROUP;

  static org.jboss.as.controller.SimpleAttributeDefinition USE_JAVA_CONTEXT;

  static org.jboss.as.controller.SimpleAttributeDefinition ENABLED;

  static org.jboss.as.controller.SimpleAttributeDefinition CONNECTABLE;

  static org.jboss.as.controller.SimpleAttributeDefinition TRACKING;

  static org.jboss.as.controller.SimpleAttributeDefinition SECURITY_DOMAIN;

  static final org.jboss.as.controller.SimpleAttributeDefinition SECURITY_DOMAIN_AND_APPLICATION;

  static final org.jboss.as.controller.SimpleAttributeDefinition APPLICATION;

  static org.jboss.as.controller.SimpleAttributeDefinition ALLOCATION_RETRY;

  static org.jboss.as.controller.SimpleAttributeDefinition ALLOCATION_RETRY_WAIT_MILLIS;

  static org.jboss.as.controller.SimpleAttributeDefinition USETRYLOCK;

  static org.jboss.as.controller.SimpleAttributeDefinition USE_CCM;

  static org.jboss.as.controller.SimpleAttributeDefinition SHARABLE;

  static org.jboss.as.controller.SimpleAttributeDefinition ENLISTMENT;

  static org.jboss.as.controller.SimpleAttributeDefinition ENLISTMENT_TRACE;

  static org.jboss.as.controller.SimpleAttributeDefinition MCP;

  static org.jboss.as.controller.SimpleAttributeDefinition INTERLEAVING;

  static org.jboss.as.controller.SimpleAttributeDefinition NOTXSEPARATEPOOL;

  static org.jboss.as.controller.SimpleAttributeDefinition PAD_XID;

  static org.jboss.as.controller.SimpleAttributeDefinition SAME_RM_OVERRIDE;

  static org.jboss.as.controller.SimpleAttributeDefinition WRAP_XA_RESOURCE;

  static org.jboss.as.controller.SimpleAttributeDefinition XA_RESOURCE_TIMEOUT;

  static org.jboss.as.controller.SimpleAttributeDefinition RECOVERY_USERNAME;

  static org.jboss.as.controller.SimpleAttributeDefinition RECOVERY_PASSWORD;

  static org.jboss.as.controller.SimpleAttributeDefinition RECOVERY_SECURITY_DOMAIN;

  static org.jboss.as.controller.SimpleAttributeDefinition NO_RECOVERY;

  static org.jboss.as.controller.SimpleAttributeDefinition RECOVERLUGIN_CLASSNAME;

  static org.jboss.as.controller.PropertiesAttributeDefinition RECOVERLUGIN_PROPERTIES;

  static final java.lang.String WORK_ACTIVE_NAME;

  static final java.lang.String WORK_SUCEESSFUL_NAME;

  static final java.lang.String WORK_FAILED_NAME;

  static final java.lang.String DO_WORK_ACCEPTED_NAME;

  static final java.lang.String DO_WORK_REJECTED_NAME;

  static final java.lang.String SCHEDULED_WORK_ACCEPTED_NAME;

  static final java.lang.String SCHEDULED_WORK_REJECTED_NAME;

  static final java.lang.String START_WORK_ACCEPTED_NAME;

  static final java.lang.String START_WORK_REJECTED_NAME;

  static org.jboss.as.controller.SimpleAttributeDefinition WORK_ACTIVE;

  static org.jboss.as.controller.SimpleAttributeDefinition WORK_SUCCESSFUL;

  static org.jboss.as.controller.SimpleAttributeDefinition WORK_FAILED;

  static org.jboss.as.controller.SimpleAttributeDefinition DO_WORK_ACCEPTED;

  static org.jboss.as.controller.SimpleAttributeDefinition DO_WORK_REJECTED;

  static org.jboss.as.controller.SimpleAttributeDefinition SCHEDULED_WORK_ACCEPTED;

  static org.jboss.as.controller.SimpleAttributeDefinition SCHEDULED_WORK_REJECTED;

  static org.jboss.as.controller.SimpleAttributeDefinition START_WORK_ACCEPTED;

  static org.jboss.as.controller.SimpleAttributeDefinition START_WORK_REJECTED;

  public static org.jboss.as.controller.SimpleAttributeDefinition[] WORKMANAGER_METRICS;

  public static final java.lang.String WORKMANAGER_STATISTICS_ENABLED_NAME;

  public static org.jboss.as.controller.SimpleAttributeDefinition WORKMANAGER_STATISTICS_ENABLED;

  public static org.jboss.as.controller.SimpleAttributeDefinition WORKMANAGER_STATISTICS_ENABLED_DEPRECATED;

  public static final java.lang.String DISTRIBUTED_STATISTICS_ENABLED_NAME;

  public static org.jboss.as.controller.SimpleAttributeDefinition DISTRIBUTED_STATISTICS_ENABLED;

  public static org.jboss.as.controller.SimpleAttributeDefinition DISTRIBUTED_STATISTICS_ENABLED_DEPRECATED;

  public static final java.lang.String DOWORK_DISTRIBUTION_ENABLED_NAME;

  public static org.jboss.as.controller.SimpleAttributeDefinition DOWORK_DISTRIBUTION_ENABLED;

  public static final java.lang.String SCHEDULEWORK_DISTRIBUTION_ENABLED_NAME;

  public static org.jboss.as.controller.SimpleAttributeDefinition SCHEDULEWORK_DISTRIBUTION_ENABLED;

  public static final java.lang.String STARTWORK_DISTRIBUTION_ENABLED_NAME;

  public static org.jboss.as.controller.SimpleAttributeDefinition STARTWORK_DISTRIBUTION_ENABLED;

  public static org.jboss.as.controller.SimpleAttributeDefinition[] WORKMANAGER_RW_ATTRIBUTES;

  public static org.jboss.as.controller.SimpleAttributeDefinition[] DISTRIBUTED_WORKMANAGER_RW_ATTRIBUTES;

  public org.jboss.as.connector.subsystems.resourceadapters.Constants();
    Code:
       0: aload_0
       1: invokespecial #1                  // Method java/lang/Object."<init>":()V
       4: return

  static {};
    Code:
       0: new           #2                  // class org/jboss/as/controller/SimpleAttributeDefinitionBuilder
       3: dup
       4: ldc           #4                  // String class-name
       6: getstatic     #5                  // Field org/jboss/dmr/ModelType.STRING:Lorg/jboss/dmr/ModelType;
       9: iconst_0
      10: invokespecial #6                  // Method org/jboss/as/controller/SimpleAttributeDefinitionBuilder."<init>":(Ljava/lang/String;Lorg/jboss/dmr/ModelType;Z)V
      13: getstatic     #7                  // Field org/jboss/jca/common/api/metadata/resourceadapter/ConnectionDefinition$Attribute.CLASS_NAME:Lorg/jboss/jca/common/api/metadata/resourceadapter/ConnectionDefinition$Attribute;
      16: invokevirtual #8                  // Method org/jboss/jca/common/api/metadata/resourceadapter/ConnectionDefinition$Attribute.getLocalName:()Ljava/lang/String;
      19: invokevirtual #9                  // Method org/jboss/as/controller/SimpleAttributeDefinitionBuilder.setXmlName:(Ljava/lang/String;)Lorg/jboss/as/controller/AbstractAttributeDefinitionBuilder;
      22: checkcast     #2                  // class org/jboss/as/controller/SimpleAttributeDefinitionBuilder
      25: iconst_1
      26: invokevirtual #10                 // Method org/jboss/as/controller/SimpleAttributeDefinitionBuilder.setAllowExpression:(Z)Lorg/jboss/as/controller/AbstractAttributeDefinitionBuilder;
      29: checkcast     #2                  // class org/jboss/as/controller/SimpleAttributeDefinitionBuilder
      32: invokevirtual #11                 // Method org/jboss/as/controller/SimpleAttributeDefinitionBuilder.build:()Lorg/jboss/as/controller/SimpleAttributeDefinition;
      35: putstatic     #12                 // Field CLASS_NAME:Lorg/jboss/as/controller/SimpleAttributeDefinition;
      38: new           #2                  // class org/jboss/as/controller/SimpleAttributeDefinitionBuilder
      41: dup
      42: ldc           #13                 // String jndi-name
      44: getstatic     #5                  // Field org/jboss/dmr/ModelType.STRING:Lorg/jboss/dmr/ModelType;
      47: iconst_1
      48: invokespecial #6                  // Method org/jboss/as/controller/SimpleAttributeDefinitionBuilder."<init>":(Ljava/lang/String;Lorg/jboss/dmr/ModelType;Z)V
      51: getstatic     #14                 // Field org/jboss/jca/common/api/metadata/resourceadapter/ConnectionDefinition$Attribute.JNDI_NAME:Lorg/jboss/jca/common/api/metadata/resourceadapter/ConnectionDefinition$Attribute;
      54: invokevirtual #8                  // Method org/jboss/jca/common/api/metadata/resourceadapter/ConnectionDefinition$Attribute.getLocalName:()Ljava/lang/String;
      57: invokevirtual #9                  // Method org/jboss/as/controller/SimpleAttributeDefinitionBuilder.setXmlName:(Ljava/lang/String;)Lorg/jboss/as/controller/AbstractAttributeDefinitionBuilder;
      60: checkcast     #2                  // class org/jboss/as/controller/SimpleAttributeDefinitionBuilder
      63: iconst_1
      64: invokevirtual #10                 // Method org/jboss/as/controller/SimpleAttributeDefinitionBuilder.setAllowExpression:(Z)Lorg/jboss/as/controller/AbstractAttributeDefinitionBuilder;
      67: checkcast     #2                  // class org/jboss/as/controller/SimpleAttributeDefinitionBuilder
      70: invokevirtual #11                 // Method org/jboss/as/controller/SimpleAttributeDefinitionBuilder.build:()Lorg/jboss/as/controller/SimpleAttributeDefinition;
      73: putstatic     #15                 // Field JNDINAME:Lorg/jboss/as/controller/SimpleAttributeDefinition;
      76: new           #2                  // class org/jboss/as/controller/SimpleAttributeDefinitionBuilder
      79: dup
      80: ldc           #16                 // String config-properties
      82: getstatic     #5                  // Field org/jboss/dmr/ModelType.STRING:Lorg/jboss/dmr/ModelType;
      85: iconst_1
      86: invokespecial #6                  // Method org/jboss/as/controller/SimpleAttributeDefinitionBuilder."<init>":(Ljava/lang/String;Lorg/jboss/dmr/ModelType;Z)V
      89: getstatic     #17                 // Field org/jboss/jca/common/api/metadata/resourceadapter/ConnectionDefinition$Tag.CONFIG_PROPERTY:Lorg/jboss/jca/common/api/metadata/resourceadapter/ConnectionDefinition$Tag;
      92: invokevirtual #18                 // Method org/jboss/jca/common/api/metadata/resourceadapter/ConnectionDefinition$Tag.getLocalName:()Ljava/lang/String;
      95: invokevirtual #9                  // Method org/jboss/as/controller/SimpleAttributeDefinitionBuilder.setXmlName:(Ljava/lang/String;)Lorg/jboss/as/controller/AbstractAttributeDefinitionBuilder;
      98: checkcast     #2                  // class org/jboss/as/controller/SimpleAttributeDefinitionBuilder
     101: iconst_1
     102: invokevirtual #10                 // Method org/jboss/as/controller/SimpleAttributeDefinitionBuilder.setAllowExpression:(Z)Lorg/jboss/as/controller/AbstractAttributeDefinitionBuilder;
     105: checkcast     #2                  // class org/jboss/as/controller/SimpleAttributeDefinitionBuilder
     108: invokevirtual #11                 // Method org/jboss/as/controller/SimpleAttributeDefinitionBuilder.build:()Lorg/jboss/as/controller/SimpleAttributeDefinition;
     111: putstatic     #19                 // Field CONFIG_PROPERTIES:Lorg/jboss/as/controller/SimpleAttributeDefinition;
     114: new           #2                  // class org/jboss/as/controller/SimpleAttributeDefinitionBuilder
     117: dup
     118: ldc           #20                 // String value
     120: getstatic     #5                  // Field org/jboss/dmr/ModelType.STRING:Lorg/jboss/dmr/ModelType;
     123: iconst_1
     124: invokespecial #6                  // Method org/jboss/as/controller/SimpleAttributeDefinitionBuilder."<init>":(Ljava/lang/String;Lorg/jboss/dmr/ModelType;Z)V
     127: getstatic     #17                 // Field org/jboss/jca/common/api/metadata/resourceadapter/ConnectionDefinition$Tag.CONFIG_PROPERTY:Lorg/jboss/jca/common/api/metadata/resourceadapter/ConnectionDefinition$Tag;
     130: invokevirtual #18                 // Method org/jboss/jca/common/api/metadata/resourceadapter/ConnectionDefinition$Tag.getLocalName:()Ljava/lang/String;
     133: invokevirtual #9                  // Method org/jboss/as/controller/SimpleAttributeDefinitionBuilder.setXmlName:(Ljava/lang/String;)Lorg/jboss/as/controller/AbstractAttributeDefinitionBuilder;
     136: checkcast     #2                  // class org/jboss/as/controller/SimpleAttributeDefinitionBuilder
     139: iconst_1
     140: invokevirtual #10                 // Method org/jboss/as/controller/SimpleAttributeDefinitionBuilder.setAllowExpression:(Z)Lorg/jboss/as/controller/AbstractAttributeDefinitionBuilder;
     143: checkcast     #2                  // class org/jboss/as/controller/SimpleAttributeDefinitionBuilder
     146: invokevirtual #11                 // Method org/jboss/as/controller/SimpleAttributeDefinitionBuilder.build:()Lorg/jboss/as/controller/SimpleAttributeDefinition;
     149: putstatic     #21                 // Field CONFIG_PROPERTY_VALUE:Lorg/jboss/as/controller/SimpleAttributeDefinition;
     152: ldc           #22                 // String archive
     154: getstatic     #5                  // Field org/jboss/dmr/ModelType.STRING:Lorg/jboss/dmr/ModelType;
     157: invokestatic  #23                 // Method org/jboss/as/controller/SimpleAttributeDefinitionBuilder.create:(Ljava/lang/String;Lorg/jboss/dmr/ModelType;)Lorg/jboss/as/controller/SimpleAttributeDefinitionBuilder;
     160: getstatic     #24                 // Field org/jboss/jca/common/api/metadata/resourceadapter/Activation$Tag.ARCHIVE:Lorg/jboss/jca/common/api/metadata/resourceadapter/Activation$Tag;
     163: invokevirtual #25                 // Method org/jboss/jca/common/api/metadata/resourceadapter/Activation$Tag.getLocalName:()Ljava/lang/String;
     166: invokevirtual #9                  // Method org/jboss/as/controller/SimpleAttributeDefinitionBuilder.setXmlName:(Ljava/lang/String;)Lorg/jboss/as/controller/AbstractAttributeDefinitionBuilder;
     169: checkcast     #2                  // class org/jboss/as/controller/SimpleAttributeDefinitionBuilder
     172: iconst_1
     173: invokevirtual #26                 // Method org/jboss/as/controller/SimpleAttributeDefinitionBuilder.setAllowNull:(Z)Lorg/jboss/as/controller/AbstractAttributeDefinitionBuilder;
     176: checkcast     #2                  // class org/jboss/as/controller/SimpleAttributeDefinitionBuilder
     179: iconst_0
     180: invokevirtual #10                 // Method org/jboss/as/controller/SimpleAttributeDefinitionBuilder.setAllowExpression:(Z)Lorg/jboss/as/controller/AbstractAttributeDefinitionBuilder;
     183: checkcast     #2                  // class org/jboss/as/controller/SimpleAttributeDefinitionBuilder
     186: getstatic     #27                 // Field org/jboss/as/controller/client/helpers/MeasurementUnit.NONE:Lorg/jboss/as/controller/client/helpers/MeasurementUnit;
     189: invokevirtual #28                 // Method org/jboss/as/controller/SimpleAttributeDefinitionBuilder.setMeasurementUnit:(Lorg/jboss/as/controller/client/helpers/MeasurementUnit;)Lorg/jboss/as/controller/AbstractAttributeDefinitionBuilder;
     192: checkcast     #2                  // class org/jboss/as/controller/SimpleAttributeDefinitionBuilder
     195: new           #29                 // class org/jboss/as/connector/subsystems/resourceadapters/Constants$1
     198: dup
     199: invokespecial #30                 // Method org/jboss/as/connector/subsystems/resourceadapters/Constants$1."<init>":()V
     202: invokevirtual #31                 // Method org/jboss/as/controller/SimpleAttributeDefinitionBuilder.setAttributeMarshaller:(Lorg/jboss/as/controller/AttributeMarshaller;)Lorg/jboss/as/controller/AbstractAttributeDefinitionBuilder;
     205: checkcast     #2                  // class org/jboss/as/controller/SimpleAttributeDefinitionBuilder
     208: iconst_1
     209: anewarray     #32                 // class java/lang/String
     212: dup
     213: iconst_0
     214: ldc           #33                 // String module
     216: aastore
     217: invokevirtual #34                 // Method org/jboss/as/controller/SimpleAttributeDefinitionBuilder.setAlternatives:([Ljava/lang/String;)Lorg/jboss/as/controller/AbstractAttributeDefinitionBuilder;
     220: checkcast     #2                  // class org/jboss/as/controller/SimpleAttributeDefinitionBuilder
     223: invokevirtual #11                 // Method org/jboss/as/controller/SimpleAttributeDefinitionBuilder.build:()Lorg/jboss/as/controller/SimpleAttributeDefinition;
     226: putstatic     #35                 // Field ARCHIVE:Lorg/jboss/as/controller/SimpleAttributeDefinition;
     229: ldc           #33                 // String module
     231: getstatic     #5                  // Field org/jboss/dmr/ModelType.STRING:Lorg/jboss/dmr/ModelType;
     234: invokestatic  #23                 // Method org/jboss/as/controller/SimpleAttributeDefinitionBuilder.create:(Ljava/lang/String;Lorg/jboss/dmr/ModelType;)Lorg/jboss/as/controller/SimpleAttributeDefinitionBuilder;
     237: getstatic     #36                 // Field org/jboss/as/connector/subsystems/resourceadapters/AS7ResourceAdapterTags.MODULE:Lorg/jboss/as/connector/subsystems/resourceadapters/AS7ResourceAdapterTags;
     240: invokevirtual #37                 // Method org/jboss/as/connector/subsystems/resourceadapters/AS7ResourceAdapterTags.getLocalName:()Ljava/lang/String;
     243: invokevirtual #9                  // Method org/jboss/as/controller/SimpleAttributeDefinitionBuilder.setXmlName:(Ljava/lang/String;)Lorg/jboss/as/controller/AbstractAttributeDefinitionBuilder;
     246: checkcast     #2                  // class org/jboss/as/controller/SimpleAttributeDefinitionBuilder
     249: iconst_1
     250: invokevirtual #26                 // Method org/jboss/as/controller/SimpleAttributeDefinitionBuilder.setAllowNull:(Z)Lorg/jboss/as/controller/AbstractAttributeDefinitionBuilder;
     253: checkcast     #2                  // class org/jboss/as/controller/SimpleAttributeDefinitionBuilder
     256: iconst_0
     257: invokevirtual #10                 // Method org/jboss/as/controller/SimpleAttributeDefinitionBuilder.setAllowExpression:(Z)Lorg/jboss/as/controller/AbstractAttributeDefinitionBuilder;
     260: checkcast     #2                  // class org/jboss/as/controller/SimpleAttributeDefinitionBuilder
     263: getstatic     #27                 // Field org/jboss/as/controller/client/helpers/MeasurementUnit.NONE:Lorg/jboss/as/controller/client/helpers/MeasurementUnit;
     266: invokevirtual #28                 // Method org/jboss/as/controller/SimpleAttributeDefinitionBuilder.setMeasurementUnit:(Lorg/jboss/as/controller/client/helpers/MeasurementUnit;)Lorg/jboss/as/controller/AbstractAttributeDefinitionBuilder;
     269: checkcast     #2                  // class org/jboss/as/controller/SimpleAttributeDefinitionBuilder
     272: new           #38                 // class org/jboss/as/connector/subsystems/resourceadapters/Constants$2
     275: dup
     276: invokespecial #39                 // Method org/jboss/as/connector/subsystems/resourceadapters/Constants$2."<init>":()V
     279: invokevirtual #31                 // Method org/jboss/as/controller/SimpleAttributeDefinitionBuilder.setAttributeMarshaller:(Lorg/jboss/as/controller/AttributeMarshaller;)Lorg/jboss/as/controller/AbstractAttributeDefinitionBuilder;
     282: checkcast     #2                  // class org/jboss/as/controller/SimpleAttributeDefinitionBuilder
     285: iconst_1
     286: anewarray     #32                 // class java/lang/String
     289: dup
     290: iconst_0
     291: ldc           #22                 // String archive
     293: aastore
     294: invokevirtual #34                 // Method org/jboss/as/controller/SimpleAttributeDefinitionBuilder.setAlternatives:([Ljava/lang/String;)Lorg/jboss/as/controller/AbstractAttributeDefinitionBuilder;
     297: checkcast     #2                  // class org/jboss/as/controller/SimpleAttributeDefinitionBuilder
     300: invokevirtual #11                 // Method org/jboss/as/controller/SimpleAttributeDefinitionBuilder.build:()Lorg/jboss/as/controller/SimpleAttributeDefinition;
     303: putstatic     #40                 // Field MODULE:Lorg/jboss/as/controller/SimpleAttributeDefinition;
     306: new           #2                  // class org/jboss/as/controller/SimpleAttributeDefinitionBuilder
     309: dup
     310: ldc           #41                 // String bootstrap-context
     312: getstatic     #5                  // Field org/jboss/dmr/ModelType.STRING:Lorg/jboss/dmr/ModelType;
     315: iconst_1
     316: invokespecial #6                  // Method org/jboss/as/controller/SimpleAttributeDefinitionBuilder."<init>":(Ljava/lang/String;Lorg/jboss/dmr/ModelType;Z)V
     319: getstatic     #42                 // Field org/jboss/jca/common/api/metadata/resourceadapter/Activation$Tag.BOOTSTRAP_CONTEXT:Lorg/jboss/jca/common/api/metadata/resourceadapter/Activation$Tag;
     322: invokevirtual #25                 // Method org/jboss/jca/common/api/metadata/resourceadapter/Activation$Tag.getLocalName:()Ljava/lang/String;
     325: invokevirtual #9                  // Method org/jboss/as/controller/SimpleAttributeDefinitionBuilder.setXmlName:(Ljava/lang/String;)Lorg/jboss/as/controller/AbstractAttributeDefinitionBuilder;
     328: checkcast     #2                  // class org/jboss/as/controller/SimpleAttributeDefinitionBuilder
     331: iconst_1
     332: invokevirtual #10                 // Method org/jboss/as/controller/SimpleAttributeDefinitionBuilder.setAllowExpression:(Z)Lorg/jboss/as/controller/AbstractAttributeDefinitionBuilder;
     335: checkcast     #2                  // class org/jboss/as/controller/SimpleAttributeDefinitionBuilder
     338: invokevirtual #11                 // Method org/jboss/as/controller/SimpleAttributeDefinitionBuilder.build:()Lorg/jboss/as/controller/SimpleAttributeDefinition;
     341: putstatic     #43                 // Field BOOTSTRAP_CONTEXT:Lorg/jboss/as/controller/SimpleAttributeDefinition;
     344: new           #2                  // class org/jboss/as/controller/SimpleAttributeDefinitionBuilder
     347: dup
     348: ldc           #44                 // String transaction-support
     350: getstatic     #5                  // Field org/jboss/dmr/ModelType.STRING:Lorg/jboss/dmr/ModelType;
     353: iconst_1
     354: invokespecial #6                  // Method org/jboss/as/controller/SimpleAttributeDefinitionBuilder."<init>":(Ljava/lang/String;Lorg/jboss/dmr/ModelType;Z)V
     357: getstatic     #45                 // Field org/jboss/jca/common/api/metadata/resourceadapter/Activation$Tag.TRANSACTION_SUPPORT:Lorg/jboss/jca/common/api/metadata/resourceadapter/Activation$Tag;
     360: invokevirtual #25                 // Method org/jboss/jca/common/api/metadata/resourceadapter/Activation$Tag.getLocalName:()Ljava/lang/String;
     363: invokevirtual #9                  // Method org/jboss/as/controller/SimpleAttributeDefinitionBuilder.setXmlName:(Ljava/lang/String;)Lorg/jboss/as/controller/AbstractAttributeDefinitionBuilder;
     366: checkcast     #2                  // class org/jboss/as/controller/SimpleAttributeDefinitionBuilder
     369: iconst_1
     370: invokevirtual #10                 // Method org/jboss/as/controller/SimpleAttributeDefinitionBuilder.setAllowExpression:(Z)Lorg/jboss/as/controller/AbstractAttributeDefinitionBuilder;
     373: checkcast     #2                  // class org/jboss/as/controller/SimpleAttributeDefinitionBuilder
     376: new           #46                 // class org/jboss/as/controller/operations/validation/EnumValidator
     379: dup
     380: ldc           #47                 // class org/jboss/jca/common/api/metadata/common/TransactionSupportEnum
     382: iconst_1
     383: iconst_1
     384: invokespecial #48                 // Method org/jboss/as/controller/operations/validation/EnumValidator."<init>":(Ljava/lang/Class;ZZ)V
     387: invokevirtual #49                 // Method org/jboss/as/controller/SimpleAttributeDefinitionBuilder.setValidator:(Lorg/jboss/as/controller/operations/validation/ParameterValidator;)Lorg/jboss/as/controller/AbstractAttributeDefinitionBuilder;
     390: checkcast     #2                  // class org/jboss/as/controller/SimpleAttributeDefinitionBuilder
     393: invokevirtual #11                 // Method org/jboss/as/controller/SimpleAttributeDefinitionBuilder.build:()Lorg/jboss/as/controller/SimpleAttributeDefinition;
     396: putstatic     #50                 // Field TRANSACTION_SUPPORT:Lorg/jboss/as/controller/SimpleAttributeDefinition;
     399: new           #2                  // class org/jboss/as/controller/SimpleAttributeDefinitionBuilder
     402: dup
     403: ldc           #52                 // String statistics-enabled
     405: getstatic     #53                 // Field org/jboss/dmr/ModelType.BOOLEAN:Lorg/jboss/dmr/ModelType;
     408: invokespecial #54                 // Method org/jboss/as/controller/SimpleAttributeDefinitionBuilder."<init>":(Ljava/lang/String;Lorg/jboss/dmr/ModelType;)V
     411: new           #55                 // class org/jboss/dmr/ModelNode
     414: dup
     415: iconst_0
     416: invokespecial #56                 // Method org/jboss/dmr/ModelNode."<init>":(Z)V
     419: invokevirtual #57                 // Method org/jboss/as/controller/SimpleAttributeDefinitionBuilder.setDefaultValue:(Lorg/jboss/dmr/ModelNode;)Lorg/jboss/as/controller/AbstractAttributeDefinitionBuilder;
     422: checkcast     #2                  // class org/jboss/as/controller/SimpleAttributeDefinitionBuilder
     425: iconst_1
     426: invokevirtual #26                 // Method org/jboss/as/controller/SimpleAttributeDefinitionBuilder.setAllowNull:(Z)Lorg/jboss/as/controller/AbstractAttributeDefinitionBuilder;
     429: checkcast     #2                  // class org/jboss/as/controller/SimpleAttributeDefinitionBuilder
     432: iconst_1
     433: invokevirtual #10                 // Method org/jboss/as/controller/SimpleAttributeDefinitionBuilder.setAllowExpression:(Z)Lorg/jboss/as/controller/AbstractAttributeDefinitionBuilder;
     436: checkcast     #2                  // class org/jboss/as/controller/SimpleAttributeDefinitionBuilder
     439: invokevirtual #11                 // Method org/jboss/as/controller/SimpleAttributeDefinitionBuilder.build:()Lorg/jboss/as/controller/SimpleAttributeDefinition;
     442: putstatic     #58                 // Field STATISTICS_ENABLED:Lorg/jboss/as/controller/SimpleAttributeDefinition;
     445: new           #2                  // class org/jboss/as/controller/SimpleAttributeDefinitionBuilder
     448: dup
     449: ldc           #59                 // String wm-security
     451: getstatic     #53                 // Field org/jboss/dmr/ModelType.BOOLEAN:Lorg/jboss/dmr/ModelType;
     454: invokespecial #54                 // Method org/jboss/as/controller/SimpleAttributeDefinitionBuilder."<init>":(Ljava/lang/String;Lorg/jboss/dmr/ModelType;)V
     457: iconst_1
     458: invokevirtual #10                 // Method org/jboss/as/controller/SimpleAttributeDefinitionBuilder.setAllowExpression:(Z)Lorg/jboss/as/controller/AbstractAttributeDefinitionBuilder;
     461: checkcast     #2                  // class org/jboss/as/controller/SimpleAttributeDefinitionBuilder
     464: iconst_1
     465: invokevirtual #26                 // Method org/jboss/as/controller/SimpleAttributeDefinitionBuilder.setAllowNull:(Z)Lorg/jboss/as/controller/AbstractAttributeDefinitionBuilder;
     468: checkcast     #2                  // class org/jboss/as/controller/SimpleAttributeDefinitionBuilder
     471: new           #55                 // class org/jboss/dmr/ModelNode
     474: dup
     475: iconst_0
     476: invokespecial #56                 // Method org/jboss/dmr/ModelNode."<init>":(Z)V
     479: invokevirtual #57                 // Method org/jboss/as/controller/SimpleAttributeDefinitionBuilder.setDefaultValue:(Lorg/jboss/dmr/ModelNode;)Lorg/jboss/as/controller/AbstractAttributeDefinitionBuilder;
     482: checkcast     #2                  // class org/jboss/as/controller/SimpleAttributeDefinitionBuilder
     485: invokevirtual #11                 // Method org/jboss/as/controller/SimpleAttributeDefinitionBuilder.build:()Lorg/jboss/as/controller/SimpleAttributeDefinition;
     488: putstatic     #60                 // Field WM_SECURITY:Lorg/jboss/as/controller/SimpleAttributeDefinition;
     491: new           #2                  // class org/jboss/as/controller/SimpleAttributeDefinitionBuilder
     494: dup
     495: ldc           #61                 // String wm-security-mapping-required
     497: getstatic     #53                 // Field org/jboss/dmr/ModelType.BOOLEAN:Lorg/jboss/dmr/ModelType;
     500: invokespecial #54                 // Method org/jboss/as/controller/SimpleAttributeDefinitionBuilder."<init>":(Ljava/lang/String;Lorg/jboss/dmr/ModelType;)V
     503: iconst_1
     504: invokevirtual #10                 // Method org/jboss/as/controller/SimpleAttributeDefinitionBuilder.setAllowExpression:(Z)Lorg/jboss/as/controller/AbstractAttributeDefinitionBuilder;
     507: checkcast     #2                  // class org/jboss/as/controller/SimpleAttributeDefinitionBuilder
     510: iconst_1
     511: invokevirtual #26                 // Method org/jboss/as/controller/SimpleAttributeDefinitionBuilder.setAllowNull:(Z)Lorg/jboss/as/controller/AbstractAttributeDefinitionBuilder;
     514: checkcast     #2                  // class org/jboss/as/controller/SimpleAttributeDefinitionBuilder
     517: new           #55                 // class org/jboss/dmr/ModelNode
     520: dup
     521: iconst_0
     522: invokespecial #56                 // Method org/jboss/dmr/ModelNode."<init>":(Z)V
     525: invokevirtual #57                 // Method org/jboss/as/controller/SimpleAttributeDefinitionBuilder.setDefaultValue:(Lorg/jboss/dmr/ModelNode;)Lorg/jboss/as/controller/AbstractAttributeDefinitionBuilder;
     528: checkcast     #2                  // class org/jboss/as/controller/SimpleAttributeDefinitionBuilder
     531: getstatic     #62                 // Field org/jboss/jca/common/api/metadata/resourceadapter/WorkManagerSecurity$Tag.MAPPING_REQUIRED:Lorg/jboss/jca/common/api/metadata/resourceadapter/WorkManagerSecurity$Tag;
     534: invokevirtual #63                 // Method org/jboss/jca/common/api/metadata/resourceadapter/WorkManagerSecurity$Tag.getLocalName:()Ljava/lang/String;
     537: invokevirtual #9                  // Method org/jboss/as/controller/SimpleAttributeDefinitionBuilder.setXmlName:(Ljava/lang/String;)Lorg/jboss/as/controller/AbstractAttributeDefinitionBuilder;
     540: checkcast     #2                  // class org/jboss/as/controller/SimpleAttributeDefinitionBuilder
     543: invokevirtual #11                 // Method org/jboss/as/controller/SimpleAttributeDefinitionBuilder.build:()Lorg/jboss/as/controller/SimpleAttributeDefinition;
     546: putstatic     #64                 // Field WM_SECURITY_MAPPING_REQUIRED:Lorg/jboss/as/controller/SimpleAttributeDefinition;
     549: new           #2                  // class org/jboss/as/controller/SimpleAttributeDefinitionBuilder
     552: dup
     553: ldc           #65                 // String wm-security-domain
     555: getstatic     #5                  // Field org/jboss/dmr/ModelType.STRING:Lorg/jboss/dmr/ModelType;
     558: invokespecial #54                 // Method org/jboss/as/controller/SimpleAttributeDefinitionBuilder."<init>":(Ljava/lang/String;Lorg/jboss/dmr/ModelType;)V
     561: iconst_1
     562: invokevirtual #10                 // Method org/jboss/as/controller/SimpleAttributeDefinitionBuilder.setAllowExpression:(Z)Lorg/jboss/as/controller/AbstractAttributeDefinitionBuilder;
     565: checkcast     #2                  // class org/jboss/as/controller/SimpleAttributeDefinitionBuilder
     568: iconst_1
     569: invokevirtual #26                 // Method org/jboss/as/controller/SimpleAttributeDefinitionBuilder.setAllowNull:(Z)Lorg/jboss/as/controller/AbstractAttributeDefinitionBuilder;
     572: checkcast     #2                  // class org/jboss/as/controller/SimpleAttributeDefinitionBuilder
     575: new           #55                 // class org/jboss/dmr/ModelNode
     578: dup
     579: ldc           #66                 // String other
     581: invokespecial #67                 // Method org/jboss/dmr/ModelNode."<init>":(Ljava/lang/String;)V
     584: invokevirtual #57                 // Method org/jboss/as/controller/SimpleAttributeDefinitionBuilder.setDefaultValue:(Lorg/jboss/dmr/ModelNode;)Lorg/jboss/as/controller/AbstractAttributeDefinitionBuilder;
     587: checkcast     #2                  // class org/jboss/as/controller/SimpleAttributeDefinitionBuilder
     590: getstatic     #68                 // Field org/jboss/jca/common/api/metadata/resourceadapter/WorkManagerSecurity$Tag.DOMAIN:Lorg/jboss/jca/common/api/metadata/resourceadapter/WorkManagerSecurity$Tag;
     593: invokevirtual #63                 // Method org/jboss/jca/common/api/metadata/resourceadapter/WorkManagerSecurity$Tag.getLocalName:()Ljava/lang/String;
     596: invokevirtual #9                  // Method org/jboss/as/controller/SimpleAttributeDefinitionBuilder.setXmlName:(Ljava/lang/String;)Lorg/jboss/as/controller/AbstractAttributeDefinitionBuilder;
     599: checkcast     #2                  // class org/jboss/as/controller/SimpleAttributeDefinitionBuilder
     602: invokevirtual #11                 // Method org/jboss/as/controller/SimpleAttributeDefinitionBuilder.build:()Lorg/jboss/as/controller/SimpleAttributeDefinition;
     605: putstatic     #69                 // Field WM_SECURITY_DOMAIN:Lorg/jboss/as/controller/SimpleAttributeDefinition;
     608: new           #2                  // class org/jboss/as/controller/SimpleAttributeDefinitionBuilder
     611: dup
     612: ldc           #70                 // String wm-security-default-principal
     614: getstatic     #5                  // Field org/jboss/dmr/ModelType.STRING:Lorg/jboss/dmr/ModelType;
     617: invokespecial #54                 // Method org/jboss/as/controller/SimpleAttributeDefinitionBuilder."<init>":(Ljava/lang/String;Lorg/jboss/dmr/ModelType;)V
     620: iconst_1
     621: invokevirtual #10                 // Method org/jboss/as/controller/SimpleAttributeDefinitionBuilder.setAllowExpression:(Z)Lorg/jboss/as/controller/AbstractAttributeDefinitionBuilder;
     624: checkcast     #2                  // class org/jboss/as/controller/SimpleAttributeDefinitionBuilder
     627: iconst_1
     628: invokevirtual #26                 // Method org/jboss/as/controller/SimpleAttributeDefinitionBuilder.setAllowNull:(Z)Lorg/jboss/as/controller/AbstractAttributeDefinitionBuilder;
     631: checkcast     #2                  // class org/jboss/as/controller/SimpleAttributeDefinitionBuilder
     634: getstatic     #71                 // Field org/jboss/jca/common/api/metadata/resourceadapter/WorkManagerSecurity$Tag.DEFAULT_PRINCIPAL:Lorg/jboss/jca/common/api/metadata/resourceadapter/WorkManagerSecurity$Tag;
     637: invokevirtual #63                 // Method org/jboss/jca/common/api/metadata/resourceadapter/WorkManagerSecurity$Tag.getLocalName:()Ljava/lang/String;
     640: invokevirtual #9                  // Method org/jboss/as/controller/SimpleAttributeDefinitionBuilder.setXmlName:(Ljava/lang/String;)Lorg/jboss/as/controller/AbstractAttributeDefinitionBuilder;
     643: checkcast     #2                  // class org/jboss/as/controller/SimpleAttributeDefinitionBuilder
     646: invokevirtual #11                 // Method org/jboss/as/controller/SimpleAttributeDefinitionBuilder.build:()Lorg/jboss/as/controller/SimpleAttributeDefinition;
     649: putstatic     #72                 // Field WM_SECURITY_DEFAULT_PRINCIPAL:Lorg/jboss/as/controller/SimpleAttributeDefinition;
     652: new           #73                 // class org/jboss/as/controller/StringListAttributeDefinition$Builder
     655: dup
     656: ldc           #74                 // String wm-security-default-groups
     658: invokespecial #75                 // Method org/jboss/as/controller/StringListAttributeDefinition$Builder."<init>":(Ljava/lang/String;)V
     661: getstatic     #76                 // Field org/jboss/jca/common/api/metadata/resourceadapter/WorkManagerSecurity$Tag.DEFAULT_GROUPS:Lorg/jboss/jca/common/api/metadata/resourceadapter/WorkManagerSecurity$Tag;
     664: invokevirtual #63                 // Method org/jboss/jca/common/api/metadata/resourceadapter/WorkManagerSecurity$Tag.getLocalName:()Ljava/lang/String;
     667: invokevirtual #77                 // Method org/jboss/as/controller/StringListAttributeDefinition$Builder.setXmlName:(Ljava/lang/String;)Lorg/jboss/as/controller/AbstractAttributeDefinitionBuilder;
     670: checkcast     #73                 // class org/jboss/as/controller/StringListAttributeDefinition$Builder
     673: iconst_1
     674: invokevirtual #78                 // Method org/jboss/as/controller/StringListAttributeDefinition$Builder.setAllowNull:(Z)Lorg/jboss/as/controller/AbstractAttributeDefinitionBuilder;
     677: checkcast     #73                 // class org/jboss/as/controller/StringListAttributeDefinition$Builder
     680: iconst_1
     681: invokevirtual #79                 // Method org/jboss/as/controller/StringListAttributeDefinition$Builder.setAllowExpression:(Z)Lorg/jboss/as/controller/AbstractAttributeDefinitionBuilder;
     684: checkcast     #73                 // class org/jboss/as/controller/StringListAttributeDefinition$Builder
     687: new           #80                 // class org/jboss/as/controller/operations/validation/StringLengthValidator
     690: dup
     691: iconst_1
     692: iconst_0
     693: iconst_1
     694: invokespecial #81                 // Method org/jboss/as/controller/operations/validation/StringLengthValidator."<init>":(IZZ)V
     697: invokevirtual #82                 // Method org/jboss/as/controller/StringListAttributeDefinition$Builder.setElementValidator:(Lorg/jboss/as/controller/operations/validation/ParameterValidator;)Lorg/jboss/as/controller/ListAttributeDefinition$Builder;
     700: checkcast     #73                 // class org/jboss/as/controller/StringListAttributeDefinition$Builder
     703: invokevirtual #83                 // Method org/jboss/as/controller/StringListAttributeDefinition$Builder.build:()Lorg/jboss/as/controller/StringListAttributeDefinition;
     706: putstatic     #84                 // Field WM_SECURITY_DEFAULT_GROUPS:Lorg/jboss/as/controller/StringListAttributeDefinition;
     709: new           #2                  // class org/jboss/as/controller/SimpleAttributeDefinitionBuilder
     712: dup
     713: ldc           #85                 // String wm-security-default-group
     715: getstatic     #5                  // Field org/jboss/dmr/ModelType.STRING:Lorg/jboss/dmr/ModelType;
     718: iconst_1
     719: invokespecial #6                  // Method org/jboss/as/controller/SimpleAttributeDefinitionBuilder."<init>":(Ljava/lang/String;Lorg/jboss/dmr/ModelType;Z)V
     722: getstatic     #86                 // Field org/jboss/jca/common/api/metadata/resourceadapter/WorkManagerSecurity$Tag.GROUP:Lorg/jboss/jca/common/api/metadata/resourceadapter/WorkManagerSecurity$Tag;
     725: invokevirtual #63                 // Method org/jboss/jca/common/api/metadata/resourceadapter/WorkManagerSecurity$Tag.getLocalName:()Ljava/lang/String;
     728: invokevirtual #9                  // Method org/jboss/as/controller/SimpleAttributeDefinitionBuilder.setXmlName:(Ljava/lang/String;)Lorg/jboss/as/controller/AbstractAttributeDefinitionBuilder;
     731: checkcast     #2                  // class org/jboss/as/controller/SimpleAttributeDefinitionBuilder
     734: iconst_1
     735: invokevirtual #10                 // Method org/jboss/as/controller/SimpleAttributeDefinitionBuilder.setAllowExpression:(Z)Lorg/jboss/as/controller/AbstractAttributeDefinitionBuilder;
     738: checkcast     #2                  // class org/jboss/as/controller/SimpleAttributeDefinitionBuilder
     741: invokevirtual #11                 // Method org/jboss/as/controller/SimpleAttributeDefinitionBuilder.build:()Lorg/jboss/as/controller/SimpleAttributeDefinition;
     744: putstatic     #87                 // Field WM_SECURITY_DEFAULT_GROUP:Lorg/jboss/as/controller/SimpleAttributeDefinition;
     747: new           #2                  // class org/jboss/as/controller/SimpleAttributeDefinitionBuilder
     750: dup
     751: ldc           #88                 // String from
     753: getstatic     #5                  // Field org/jboss/dmr/ModelType.STRING:Lorg/jboss/dmr/ModelType;
     756: invokespecial #54                 // Method org/jboss/as/controller/SimpleAttributeDefinitionBuilder."<init>":(Ljava/lang/String;Lorg/jboss/dmr/ModelType;)V
     759: iconst_1
     760: invokevirtual #10                 // Method org/jboss/as/controller/SimpleAttributeDefinitionBuilder.setAllowExpression:(Z)Lorg/jboss/as/controller/AbstractAttributeDefinitionBuilder;
     763: checkcast     #2                  // class org/jboss/as/controller/SimpleAttributeDefinitionBuilder
     766: iconst_1
     767: invokevirtual #26                 // Method org/jboss/as/controller/SimpleAttributeDefinitionBuilder.setAllowNull:(Z)Lorg/jboss/as/controller/AbstractAttributeDefinitionBuilder;
     770: checkcast     #2                  // class org/jboss/as/controller/SimpleAttributeDefinitionBuilder
     773: getstatic     #89                 // Field org/jboss/jca/common/api/metadata/resourceadapter/WorkManagerSecurity$Attribute.FROM:Lorg/jboss/jca/common/api/metadata/resourceadapter/WorkManagerSecurity$Attribute;
     776: invokevirtual #90                 // Method org/jboss/jca/common/api/metadata/resourceadapter/WorkManagerSecurity$Attribute.getLocalName:()Ljava/lang/String;
     779: invokevirtual #9                  // Method org/jboss/as/controller/SimpleAttributeDefinitionBuilder.setXmlName:(Ljava/lang/String;)Lorg/jboss/as/controller/AbstractAttributeDefinitionBuilder;
     782: checkcast     #2                  // class org/jboss/as/controller/SimpleAttributeDefinitionBuilder
     785: invokevirtual #11                 // Method org/jboss/as/controller/SimpleAttributeDefinitionBuilder.build:()Lorg/jboss/as/controller/SimpleAttributeDefinition;
     788: putstatic     #91                 // Field WM_SECURITY_MAPPING_FROM:Lorg/jboss/as/controller/SimpleAttributeDefinition;
     791: new           #2                  // class org/jboss/as/controller/SimpleAttributeDefinitionBuilder
     794: dup
     795: ldc           #92                 // String to
     797: getstatic     #5                  // Field org/jboss/dmr/ModelType.STRING:Lorg/jboss/dmr/ModelType;
     800: invokespecial #54                 // Method org/jboss/as/controller/SimpleAttributeDefinitionBuilder."<init>":(Ljava/lang/String;Lorg/jboss/dmr/ModelType;)V
     803: iconst_1
     804: invokevirtual #10                 // Method org/jboss/as/controller/SimpleAttributeDefinitionBuilder.setAllowExpression:(Z)Lorg/jboss/as/controller/AbstractAttributeDefinitionBuilder;
     807: checkcast     #2                  // class org/jboss/as/controller/SimpleAttributeDefinitionBuilder
     810: iconst_1
     811: invokevirtual #26                 // Method org/jboss/as/controller/SimpleAttributeDefinitionBuilder.setAllowNull:(Z)Lorg/jboss/as/controller/AbstractAttributeDefinitionBuilder;
     814: checkcast     #2                  // class org/jboss/as/controller/SimpleAttributeDefinitionBuilder
     817: getstatic     #93                 // Field org/jboss/jca/common/api/metadata/resourceadapter/WorkManagerSecurity$Attribute.TO:Lorg/jboss/jca/common/api/metadata/resourceadapter/WorkManagerSecurity$Attribute;
     820: invokevirtual #90                 // Method org/jboss/jca/common/api/metadata/resourceadapter/WorkManagerSecurity$Attribute.getLocalName:()Ljava/lang/String;
     823: invokevirtual #9                  // Method org/jboss/as/controller/SimpleAttributeDefinitionBuilder.setXmlName:(Ljava/lang/String;)Lorg/jboss/as/controller/AbstractAttributeDefinitionBuilder;
     826: checkcast     #2                  // class org/jboss/as/controller/SimpleAttributeDefinitionBuilder
     829: invokevirtual #11                 // Method org/jboss/as/controller/SimpleAttributeDefinitionBuilder.build:()Lorg/jboss/as/controller/SimpleAttributeDefinition;
     832: putstatic     #94                 // Field WM_SECURITY_MAPPING_TO:Lorg/jboss/as/controller/SimpleAttributeDefinition;
     835: ldc           #95                 // String wm-security-mapping-group
     837: iconst_2
     838: anewarray     #96                 // class org/jboss/as/controller/AttributeDefinition
     841: dup
     842: iconst_0
     843: getstatic     #91                 // Field WM_SECURITY_MAPPING_FROM:Lorg/jboss/as/controller/SimpleAttributeDefinition;
     846: aastore
     847: dup
     848: iconst_1
     849: getstatic     #94                 // Field WM_SECURITY_MAPPING_TO:Lorg/jboss/as/controller/SimpleAttributeDefinition;
     852: aastore
     853: invokestatic  #97                 // Method org/jboss/as/controller/ObjectTypeAttributeDefinition$Builder.of:(Ljava/lang/String;[Lorg/jboss/as/controller/AttributeDefinition;)Lorg/jboss/as/controller/ObjectTypeAttributeDefinition$Builder;
     856: invokevirtual #98                 // Method org/jboss/as/controller/ObjectTypeAttributeDefinition$Builder.build:()Lorg/jboss/as/controller/ObjectTypeAttributeDefinition;
     859: putstatic     #99                 // Field WM_SECURITY_MAPPING_GROUP:Lorg/jboss/as/controller/ObjectTypeAttributeDefinition;
     862: ldc           #100                // String wm-security-mapping-groups
     864: getstatic     #99                 // Field WM_SECURITY_MAPPING_GROUP:Lorg/jboss/as/controller/ObjectTypeAttributeDefinition;
     867: invokestatic  #101                // Method org/jboss/as/controller/ObjectListAttributeDefinition$Builder.of:(Ljava/lang/String;Lorg/jboss/as/controller/ObjectTypeAttributeDefinition;)Lorg/jboss/as/controller/ObjectListAttributeDefinition$Builder;
     870: iconst_1
     871: invokevirtual #102                // Method org/jboss/as/controller/ObjectListAttributeDefinition$Builder.setAllowNull:(Z)Lorg/jboss/as/controller/ObjectListAttributeDefinition$Builder;
     874: invokevirtual #103                // Method org/jboss/as/controller/ObjectListAttributeDefinition$Builder.build:()Lorg/jboss/as/controller/ObjectListAttributeDefinition;
     877: putstatic     #104                // Field WM_SECURITY_MAPPING_GROUPS:Lorg/jboss/as/controller/ObjectListAttributeDefinition;
     880: ldc           #105                // String wm-security-mapping-user
     882: iconst_2
     883: anewarray     #96                 // class org/jboss/as/controller/AttributeDefinition
     886: dup
     887: iconst_0
     888: getstatic     #91                 // Field WM_SECURITY_MAPPING_FROM:Lorg/jboss/as/controller/SimpleAttributeDefinition;
     891: aastore
     892: dup
     893: iconst_1
     894: getstatic     #94                 // Field WM_SECURITY_MAPPING_TO:Lorg/jboss/as/controller/SimpleAttributeDefinition;
     897: aastore
     898: invokestatic  #97                 // Method org/jboss/as/controller/ObjectTypeAttributeDefinition$Builder.of:(Ljava/lang/String;[Lorg/jboss/as/controller/AttributeDefinition;)Lorg/jboss/as/controller/ObjectTypeAttributeDefinition$Builder;
     901: invokevirtual #98                 // Method org/jboss/as/controller/ObjectTypeAttributeDefinition$Builder.build:()Lorg/jboss/as/controller/ObjectTypeAttributeDefinition;
     904: putstatic     #106                // Field WM_SECURITY_MAPPING_USER:Lorg/jboss/as/controller/ObjectTypeAttributeDefinition;
     907: ldc           #107                // String wm-security-mapping-users
     909: getstatic     #106                // Field WM_SECURITY_MAPPING_USER:Lorg/jboss/as/controller/ObjectTypeAttributeDefinition;
     912: invokestatic  #101                // Method org/jboss/as/controller/ObjectListAttributeDefinition$Builder.of:(Ljava/lang/String;Lorg/jboss/as/controller/ObjectTypeAttributeDefinition;)Lorg/jboss/as/controller/ObjectListAttributeDefinition$Builder;
     915: iconst_1
     916: invokevirtual #102                // Method org/jboss/as/controller/ObjectListAttributeDefinition$Builder.setAllowNull:(Z)Lorg/jboss/as/controller/ObjectListAttributeDefinition$Builder;
     919: invokevirtual #103                // Method org/jboss/as/controller/ObjectListAttributeDefinition$Builder.build:()Lorg/jboss/as/controller/ObjectListAttributeDefinition;
     922: putstatic     #108                // Field WM_SECURITY_MAPPING_USERS:Lorg/jboss/as/controller/ObjectListAttributeDefinition;
     925: new           #73                 // class org/jboss/as/controller/StringListAttributeDefinition$Builder
     928: dup
     929: ldc           #109                // String beanvalidationgroups
     931: invokespecial #75                 // Method org/jboss/as/controller/StringListAttributeDefinition$Builder."<init>":(Ljava/lang/String;)V
     934: getstatic     #110                // Field org/jboss/jca/common/api/metadata/resourceadapter/Activation$Tag.BEAN_VALIDATION_GROUP:Lorg/jboss/jca/common/api/metadata/resourceadapter/Activation$Tag;
     937: invokevirtual #25                 // Method org/jboss/jca/common/api/metadata/resourceadapter/Activation$Tag.getLocalName:()Ljava/lang/String;
     940: invokevirtual #77                 // Method org/jboss/as/controller/StringListAttributeDefinition$Builder.setXmlName:(Ljava/lang/String;)Lorg/jboss/as/controller/AbstractAttributeDefinitionBuilder;
     943: checkcast     #73                 // class org/jboss/as/controller/StringListAttributeDefinition$Builder
     946: iconst_1
     947: invokevirtual #78                 // Method org/jboss/as/controller/StringListAttributeDefinition$Builder.setAllowNull:(Z)Lorg/jboss/as/controller/AbstractAttributeDefinitionBuilder;
     950: checkcast     #73                 // class org/jboss/as/controller/StringListAttributeDefinition$Builder
     953: iconst_1
     954: invokevirtual #79                 // Method org/jboss/as/controller/StringListAttributeDefinition$Builder.setAllowExpression:(Z)Lorg/jboss/as/controller/AbstractAttributeDefinitionBuilder;
     957: checkcast     #73                 // class org/jboss/as/controller/StringListAttributeDefinition$Builder
     960: new           #80                 // class org/jboss/as/controller/operations/validation/StringLengthValidator
     963: dup
     964: iconst_1
     965: iconst_0
     966: iconst_1
     967: invokespecial #81                 // Method org/jboss/as/controller/operations/validation/StringLengthValidator."<init>":(IZZ)V
     970: invokevirtual #82                 // Method org/jboss/as/controller/StringListAttributeDefinition$Builder.setElementValidator:(Lorg/jboss/as/controller/operations/validation/ParameterValidator;)Lorg/jboss/as/controller/ListAttributeDefinition$Builder;
     973: checkcast     #73                 // class org/jboss/as/controller/StringListAttributeDefinition$Builder
     976: invokevirtual #83                 // Method org/jboss/as/controller/StringListAttributeDefinition$Builder.build:()Lorg/jboss/as/controller/StringListAttributeDefinition;
     979: putstatic     #111                // Field BEANVALIDATION_GROUPS:Lorg/jboss/as/controller/StringListAttributeDefinition;
     982: new           #2                  // class org/jboss/as/controller/SimpleAttributeDefinitionBuilder
     985: dup
     986: ldc           #109                // String beanvalidationgroups
     988: getstatic     #5                  // Field org/jboss/dmr/ModelType.STRING:Lorg/jboss/dmr/ModelType;
     991: iconst_1
     992: invokespecial #6                  // Method org/jboss/as/controller/SimpleAttributeDefinitionBuilder."<init>":(Ljava/lang/String;Lorg/jboss/dmr/ModelType;Z)V
     995: getstatic     #110                // Field org/jboss/jca/common/api/metadata/resourceadapter/Activation$Tag.BEAN_VALIDATION_GROUP:Lorg/jboss/jca/common/api/metadata/resourceadapter/Activation$Tag;
     998: invokevirtual #25                 // Method org/jboss/jca/common/api/metadata/resourceadapter/Activation$Tag.getLocalName:()Ljava/lang/String;
    1001: invokevirtual #9                  // Method org/jboss/as/controller/SimpleAttributeDefinitionBuilder.setXmlName:(Ljava/lang/String;)Lorg/jboss/as/controller/AbstractAttributeDefinitionBuilder;
    1004: checkcast     #2                  // class org/jboss/as/controller/SimpleAttributeDefinitionBuilder
    1007: iconst_1
    1008: invokevirtual #10                 // Method org/jboss/as/controller/SimpleAttributeDefinitionBuilder.setAllowExpression:(Z)Lorg/jboss/as/controller/AbstractAttributeDefinitionBuilder;
    1011: checkcast     #2                  // class org/jboss/as/controller/SimpleAttributeDefinitionBuilder
    1014: invokevirtual #11                 // Method org/jboss/as/controller/SimpleAttributeDefinitionBuilder.build:()Lorg/jboss/as/controller/SimpleAttributeDefinition;
    1017: putstatic     #112                // Field BEANVALIDATIONGROUP:Lorg/jboss/as/controller/SimpleAttributeDefinition;
    1020: new           #2                  // class org/jboss/as/controller/SimpleAttributeDefinitionBuilder
    1023: dup
    1024: ldc           #113                // String use-java-context
    1026: getstatic     #53                 // Field org/jboss/dmr/ModelType.BOOLEAN:Lorg/jboss/dmr/ModelType;
    1029: iconst_1
    1030: invokespecial #6                  // Method org/jboss/as/controller/SimpleAttributeDefinitionBuilder."<init>":(Ljava/lang/String;Lorg/jboss/dmr/ModelType;Z)V
    1033: getstatic     #114                // Field org/jboss/jca/common/api/metadata/ds/DataSource$Attribute.USE_JAVA_CONTEXT:Lorg/jboss/jca/common/api/metadata/ds/DataSource$Attribute;
    1036: invokevirtual #115                // Method org/jboss/jca/common/api/metadata/ds/DataSource$Attribute.getLocalName:()Ljava/lang/String;
    1039: invokevirtual #9                  // Method org/jboss/as/controller/SimpleAttributeDefinitionBuilder.setXmlName:(Ljava/lang/String;)Lorg/jboss/as/controller/AbstractAttributeDefinitionBuilder;
    1042: checkcast     #2                  // class org/jboss/as/controller/SimpleAttributeDefinitionBuilder
    1045: iconst_1
    1046: invokevirtual #10                 // Method org/jboss/as/controller/SimpleAttributeDefinitionBuilder.setAllowExpression:(Z)Lorg/jboss/as/controller/AbstractAttributeDefinitionBuilder;
    1049: checkcast     #2                  // class org/jboss/as/controller/SimpleAttributeDefinitionBuilder
    1052: new           #55                 // class org/jboss/dmr/ModelNode
    1055: dup
    1056: getstatic     #116                // Field org/jboss/jca/common/api/metadata/Defaults.USE_JAVA_CONTEXT:Ljava/lang/Boolean;
    1059: invokevirtual #117                // Method java/lang/Boolean.booleanValue:()Z
    1062: invokespecial #56                 // Method org/jboss/dmr/ModelNode."<init>":(Z)V
    1065: invokevirtual #57                 // Method org/jboss/as/controller/SimpleAttributeDefinitionBuilder.setDefaultValue:(Lorg/jboss/dmr/ModelNode;)Lorg/jboss/as/controller/AbstractAttributeDefinitionBuilder;
    1068: checkcast     #2                  // class org/jboss/as/controller/SimpleAttributeDefinitionBuilder
    1071: invokevirtual #11                 // Method org/jboss/as/controller/SimpleAttributeDefinitionBuilder.build:()Lorg/jboss/as/controller/SimpleAttributeDefinition;
    1074: putstatic     #118                // Field USE_JAVA_CONTEXT:Lorg/jboss/as/controller/SimpleAttributeDefinition;
    1077: new           #2                  // class org/jboss/as/controller/SimpleAttributeDefinitionBuilder
    1080: dup
    1081: ldc           #119                // String enabled
    1083: getstatic     #53                 // Field org/jboss/dmr/ModelType.BOOLEAN:Lorg/jboss/dmr/ModelType;
    1086: iconst_1
    1087: invokespecial #6                  // Method org/jboss/as/controller/SimpleAttributeDefinitionBuilder."<init>":(Ljava/lang/String;Lorg/jboss/dmr/ModelType;Z)V
    1090: getstatic     #120                // Field org/jboss/jca/common/api/metadata/ds/DataSource$Attribute.ENABLED:Lorg/jboss/jca/common/api/metadata/ds/DataSource$Attribute;
    1093: invokevirtual #115                // Method org/jboss/jca/common/api/metadata/ds/DataSource$Attribute.getLocalName:()Ljava/lang/String;
    1096: invokevirtual #9                  // Method org/jboss/as/controller/SimpleAttributeDefinitionBuilder.setXmlName:(Ljava/lang/String;)Lorg/jboss/as/controller/AbstractAttributeDefinitionBuilder;
    1099: checkcast     #2                  // class org/jboss/as/controller/SimpleAttributeDefinitionBuilder
    1102: new           #55                 // class org/jboss/dmr/ModelNode
    1105: dup
    1106: getstatic     #121                // Field org/jboss/jca/common/api/metadata/Defaults.ENABLED:Ljava/lang/Boolean;
    1109: invokevirtual #117                // Method java/lang/Boolean.booleanValue:()Z
    1112: invokespecial #56                 // Method org/jboss/dmr/ModelNode."<init>":(Z)V
    1115: invokevirtual #57                 // Method org/jboss/as/controller/SimpleAttributeDefinitionBuilder.setDefaultValue:(Lorg/jboss/dmr/ModelNode;)Lorg/jboss/as/controller/AbstractAttributeDefinitionBuilder;
    1118: checkcast     #2                  // class org/jboss/as/controller/SimpleAttributeDefinitionBuilder
    1121: iconst_1
    1122: invokevirtual #10                 // Method org/jboss/as/controller/SimpleAttributeDefinitionBuilder.setAllowExpression:(Z)Lorg/jboss/as/controller/AbstractAttributeDefinitionBuilder;
    1125: checkcast     #2                  // class org/jboss/as/controller/SimpleAttributeDefinitionBuilder
    1128: invokevirtual #11                 // Method org/jboss/as/controller/SimpleAttributeDefinitionBuilder.build:()Lorg/jboss/as/controller/SimpleAttributeDefinition;
    1131: putstatic     #122                // Field ENABLED:Lorg/jboss/as/controller/SimpleAttributeDefinition;
    1134: new           #2                  // class org/jboss/as/controller/SimpleAttributeDefinitionBuilder
    1137: dup
    1138: ldc           #123                // String connectable
    1140: getstatic     #53                 // Field org/jboss/dmr/ModelType.BOOLEAN:Lorg/jboss/dmr/ModelType;
    1143: invokespecial #54                 // Method org/jboss/as/controller/SimpleAttributeDefinitionBuilder."<init>":(Ljava/lang/String;Lorg/jboss/dmr/ModelType;)V
    1146: getstatic     #124                // Field org/jboss/jca/common/api/metadata/ds/DataSource$Attribute.CONNECTABLE:Lorg/jboss/jca/common/api/metadata/ds/DataSource$Attribute;
    1149: invokevirtual #115                // Method org/jboss/jca/common/api/metadata/ds/DataSource$Attribute.getLocalName:()Ljava/lang/String;
    1152: invokevirtual #9                  // Method org/jboss/as/controller/SimpleAttributeDefinitionBuilder.setXmlName:(Ljava/lang/String;)Lorg/jboss/as/controller/AbstractAttributeDefinitionBuilder;
    1155: checkcast     #2                  // class org/jboss/as/controller/SimpleAttributeDefinitionBuilder
    1158: iconst_1
    1159: invokevirtual #10                 // Method org/jboss/as/controller/SimpleAttributeDefinitionBuilder.setAllowExpression:(Z)Lorg/jboss/as/controller/AbstractAttributeDefinitionBuilder;
    1162: checkcast     #2                  // class org/jboss/as/controller/SimpleAttributeDefinitionBuilder
    1165: new           #55                 // class org/jboss/dmr/ModelNode
    1168: dup
    1169: getstatic     #125                // Field org/jboss/jca/common/api/metadata/Defaults.CONNECTABLE:Ljava/lang/Boolean;
    1172: invokevirtual #117                // Method java/lang/Boolean.booleanValue:()Z
    1175: invokespecial #56                 // Method org/jboss/dmr/ModelNode."<init>":(Z)V
    1178: invokevirtual #57                 // Method org/jboss/as/controller/SimpleAttributeDefinitionBuilder.setDefaultValue:(Lorg/jboss/dmr/ModelNode;)Lorg/jboss/as/controller/AbstractAttributeDefinitionBuilder;
    1181: checkcast     #2                  // class org/jboss/as/controller/SimpleAttributeDefinitionBuilder
    1184: iconst_1
    1185: invokevirtual #26                 // Method org/jboss/as/controller/SimpleAttributeDefinitionBuilder.setAllowNull:(Z)Lorg/jboss/as/controller/AbstractAttributeDefinitionBuilder;
    1188: checkcast     #2                  // class org/jboss/as/controller/SimpleAttributeDefinitionBuilder
    1191: invokevirtual #11                 // Method org/jboss/as/controller/SimpleAttributeDefinitionBuilder.build:()Lorg/jboss/as/controller/SimpleAttributeDefinition;
    1194: putstatic     #126                // Field CONNECTABLE:Lorg/jboss/as/controller/SimpleAttributeDefinition;
    1197: new           #2                  // class org/jboss/as/controller/SimpleAttributeDefinitionBuilder
    1200: dup
    1201: ldc           #127                // String tracking
    1203: getstatic     #53                 // Field org/jboss/dmr/ModelType.BOOLEAN:Lorg/jboss/dmr/ModelType;
    1206: invokespecial #54                 // Method org/jboss/as/controller/SimpleAttributeDefinitionBuilder."<init>":(Ljava/lang/String;Lorg/jboss/dmr/ModelType;)V
    1209: getstatic     #128                // Field org/jboss/jca/common/api/metadata/ds/DataSource$Attribute.TRACKING:Lorg/jboss/jca/common/api/metadata/ds/DataSource$Attribute;
    1212: invokevirtual #115                // Method org/jboss/jca/common/api/metadata/ds/DataSource$Attribute.getLocalName:()Ljava/lang/String;
    1215: invokevirtual #9                  // Method org/jboss/as/controller/SimpleAttributeDefinitionBuilder.setXmlName:(Ljava/lang/String;)Lorg/jboss/as/controller/AbstractAttributeDefinitionBuilder;
    1218: checkcast     #2                  // class org/jboss/as/controller/SimpleAttributeDefinitionBuilder
    1221: iconst_1
    1222: invokevirtual #10                 // Method org/jboss/as/controller/SimpleAttributeDefinitionBuilder.setAllowExpression:(Z)Lorg/jboss/as/controller/AbstractAttributeDefinitionBuilder;
    1225: checkcast     #2                  // class org/jboss/as/controller/SimpleAttributeDefinitionBuilder
    1228: iconst_1
    1229: invokevirtual #26                 // Method org/jboss/as/controller/SimpleAttributeDefinitionBuilder.setAllowNull:(Z)Lorg/jboss/as/controller/AbstractAttributeDefinitionBuilder;
    1232: checkcast     #2                  // class org/jboss/as/controller/SimpleAttributeDefinitionBuilder
    1235: invokevirtual #11                 // Method org/jboss/as/controller/SimpleAttributeDefinitionBuilder.build:()Lorg/jboss/as/controller/SimpleAttributeDefinition;
    1238: putstatic     #129                // Field TRACKING:Lorg/jboss/as/controller/SimpleAttributeDefinition;
    1241: new           #2                  // class org/jboss/as/controller/SimpleAttributeDefinitionBuilder
    1244: dup
    1245: ldc           #130                // String security-domain
    1247: getstatic     #5                  // Field org/jboss/dmr/ModelType.STRING:Lorg/jboss/dmr/ModelType;
    1250: invokespecial #54                 // Method org/jboss/as/controller/SimpleAttributeDefinitionBuilder."<init>":(Ljava/lang/String;Lorg/jboss/dmr/ModelType;)V
    1253: getstatic     #131                // Field org/jboss/jca/common/api/metadata/common/Security$Tag.SECURITY_DOMAIN:Lorg/jboss/jca/common/api/metadata/common/Security$Tag;
    1256: invokevirtual #132                // Method org/jboss/jca/common/api/metadata/common/Security$Tag.getLocalName:()Ljava/lang/String;
    1259: invokevirtual #9                  // Method org/jboss/as/controller/SimpleAttributeDefinitionBuilder.setXmlName:(Ljava/lang/String;)Lorg/jboss/as/controller/AbstractAttributeDefinitionBuilder;
    1262: checkcast     #2                  // class org/jboss/as/controller/SimpleAttributeDefinitionBuilder
    1265: iconst_1
    1266: invokevirtual #10                 // Method org/jboss/as/controller/SimpleAttributeDefinitionBuilder.setAllowExpression:(Z)Lorg/jboss/as/controller/AbstractAttributeDefinitionBuilder;
    1269: checkcast     #2                  // class org/jboss/as/controller/SimpleAttributeDefinitionBuilder
    1272: iconst_1
    1273: invokevirtual #26                 // Method org/jboss/as/controller/SimpleAttributeDefinitionBuilder.setAllowNull:(Z)Lorg/jboss/as/controller/AbstractAttributeDefinitionBuilder;
    1276: checkcast     #2                  // class org/jboss/as/controller/SimpleAttributeDefinitionBuilder
    1279: iconst_2
    1280: anewarray     #32                 // class java/lang/String
    1283: dup
    1284: iconst_0
    1285: ldc           #133                // String security-domain-and-application
    1287: aastore
    1288: dup
    1289: iconst_1
    1290: ldc           #134                // String security-application
    1292: aastore
    1293: invokevirtual #34                 // Method org/jboss/as/controller/SimpleAttributeDefinitionBuilder.setAlternatives:([Ljava/lang/String;)Lorg/jboss/as/controller/AbstractAttributeDefinitionBuilder;
    1296: checkcast     #2                  // class org/jboss/as/controller/SimpleAttributeDefinitionBuilder
    1299: getstatic     #135                // Field org/jboss/as/controller/access/management/SensitiveTargetAccessConstraintDefinition.SECURITY_DOMAIN_REF:Lorg/jboss/as/controller/access/management/SensitiveTargetAccessConstraintDefinition;
    1302: invokevirtual #136                // Method org/jboss/as/controller/SimpleAttributeDefinitionBuilder.addAccessConstraint:(Lorg/jboss/as/controller/access/management/AccessConstraintDefinition;)Lorg/jboss/as/controller/AbstractAttributeDefinitionBuilder;
    1305: checkcast     #2                  // class org/jboss/as/controller/SimpleAttributeDefinitionBuilder
    1308: getstatic     #137                // Field org/jboss/as/connector/subsystems/resourceadapters/ResourceAdaptersExtension.RA_SECURITY_DEF:Lorg/jboss/as/controller/access/management/SensitiveTargetAccessConstraintDefinition;
    1311: invokevirtual #136                // Method org/jboss/as/controller/SimpleAttributeDefinitionBuilder.addAccessConstraint:(Lorg/jboss/as/controller/access/management/AccessConstraintDefinition;)Lorg/jboss/as/controller/AbstractAttributeDefinitionBuilder;
    1314: checkcast     #2                  // class org/jboss/as/controller/SimpleAttributeDefinitionBuilder
    1317: invokevirtual #11                 // Method org/jboss/as/controller/SimpleAttributeDefinitionBuilder.build:()Lorg/jboss/as/controller/SimpleAttributeDefinition;
    1320: putstatic     #138                // Field SECURITY_DOMAIN:Lorg/jboss/as/controller/SimpleAttributeDefinition;
    1323: new           #2                  // class org/jboss/as/controller/SimpleAttributeDefinitionBuilder
    1326: dup
    1327: ldc           #133                // String security-domain-and-application
    1329: getstatic     #5                  // Field org/jboss/dmr/ModelType.STRING:Lorg/jboss/dmr/ModelType;
    1332: invokespecial #54                 // Method org/jboss/as/controller/SimpleAttributeDefinitionBuilder."<init>":(Ljava/lang/String;Lorg/jboss/dmr/ModelType;)V
    1335: getstatic     #139                // Field org/jboss/jca/common/api/metadata/common/Security$Tag.SECURITY_DOMAIN_AND_APPLICATION:Lorg/jboss/jca/common/api/metadata/common/Security$Tag;
    1338: invokevirtual #132                // Method org/jboss/jca/common/api/metadata/common/Security$Tag.getLocalName:()Ljava/lang/String;
    1341: invokevirtual #9                  // Method org/jboss/as/controller/SimpleAttributeDefinitionBuilder.setXmlName:(Ljava/lang/String;)Lorg/jboss/as/controller/AbstractAttributeDefinitionBuilder;
    1344: checkcast     #2                  // class org/jboss/as/controller/SimpleAttributeDefinitionBuilder
    1347: iconst_1
    1348: invokevirtual #10                 // Method org/jboss/as/controller/SimpleAttributeDefinitionBuilder.setAllowExpression:(Z)Lorg/jboss/as/controller/AbstractAttributeDefinitionBuilder;
    1351: checkcast     #2                  // class org/jboss/as/controller/SimpleAttributeDefinitionBuilder
    1354: iconst_1
    1355: invokevirtual #26                 // Method org/jboss/as/controller/SimpleAttributeDefinitionBuilder.setAllowNull:(Z)Lorg/jboss/as/controller/AbstractAttributeDefinitionBuilder;
    1358: checkcast     #2                  // class org/jboss/as/controller/SimpleAttributeDefinitionBuilder
    1361: iconst_2
    1362: anewarray     #32                 // class java/lang/String
    1365: dup
    1366: iconst_0
    1367: ldc           #130                // String security-domain
    1369: aastore
    1370: dup
    1371: iconst_1
    1372: ldc           #134                // String security-application
    1374: aastore
    1375: invokevirtual #34                 // Method org/jboss/as/controller/SimpleAttributeDefinitionBuilder.setAlternatives:([Ljava/lang/String;)Lorg/jboss/as/controller/AbstractAttributeDefinitionBuilder;
    1378: checkcast     #2                  // class org/jboss/as/controller/SimpleAttributeDefinitionBuilder
    1381: getstatic     #135                // Field org/jboss/as/controller/access/management/SensitiveTargetAccessConstraintDefinition.SECURITY_DOMAIN_REF:Lorg/jboss/as/controller/access/management/SensitiveTargetAccessConstraintDefinition;
    1384: invokevirtual #136                // Method org/jboss/as/controller/SimpleAttributeDefinitionBuilder.addAccessConstraint:(Lorg/jboss/as/controller/access/management/AccessConstraintDefinition;)Lorg/jboss/as/controller/AbstractAttributeDefinitionBuilder;
    1387: checkcast     #2                  // class org/jboss/as/controller/SimpleAttributeDefinitionBuilder
    1390: getstatic     #137                // Field org/jboss/as/connector/subsystems/resourceadapters/ResourceAdaptersExtension.RA_SECURITY_DEF:Lorg/jboss/as/controller/access/management/SensitiveTargetAccessConstraintDefinition;
    1393: invokevirtual #136                // Method org/jboss/as/controller/SimpleAttributeDefinitionBuilder.addAccessConstraint:(Lorg/jboss/as/controller/access/management/AccessConstraintDefinition;)Lorg/jboss/as/controller/AbstractAttributeDefinitionBuilder;
    1396: checkcast     #2                  // class org/jboss/as/controller/SimpleAttributeDefinitionBuilder
    1399: invokevirtual #11                 // Method org/jboss/as/controller/SimpleAttributeDefinitionBuilder.build:()Lorg/jboss/as/controller/SimpleAttributeDefinition;
    1402: putstatic     #140                // Field SECURITY_DOMAIN_AND_APPLICATION:Lorg/jboss/as/controller/SimpleAttributeDefinition;
    1405: new           #2                  // class org/jboss/as/controller/SimpleAttributeDefinitionBuilder
    1408: dup
    1409: ldc           #134                // String security-application
    1411: getstatic     #53                 // Field org/jboss/dmr/ModelType.BOOLEAN:Lorg/jboss/dmr/ModelType;
    1414: invokespecial #54                 // Method org/jboss/as/controller/SimpleAttributeDefinitionBuilder."<init>":(Ljava/lang/String;Lorg/jboss/dmr/ModelType;)V
    1417: getstatic     #141                // Field org/jboss/jca/common/api/metadata/common/Security$Tag.APPLICATION:Lorg/jboss/jca/common/api/metadata/common/Security$Tag;
    1420: invokevirtual #132                // Method org/jboss/jca/common/api/metadata/common/Security$Tag.getLocalName:()Ljava/lang/String;
    1423: invokevirtual #9                  // Method org/jboss/as/controller/SimpleAttributeDefinitionBuilder.setXmlName:(Ljava/lang/String;)Lorg/jboss/as/controller/AbstractAttributeDefinitionBuilder;
    1426: checkcast     #2                  // class org/jboss/as/controller/SimpleAttributeDefinitionBuilder
    1429: new           #55                 // class org/jboss/dmr/ModelNode
    1432: dup
    1433: getstatic     #142                // Field org/jboss/jca/common/api/metadata/Defaults.APPLICATION_MANAGED_SECURITY:Ljava/lang/Boolean;
    1436: invokevirtual #117                // Method java/lang/Boolean.booleanValue:()Z
    1439: invokespecial #56                 // Method org/jboss/dmr/ModelNode."<init>":(Z)V
    1442: invokevirtual #57                 // Method org/jboss/as/controller/SimpleAttributeDefinitionBuilder.setDefaultValue:(Lorg/jboss/dmr/ModelNode;)Lorg/jboss/as/controller/AbstractAttributeDefinitionBuilder;
    1445: checkcast     #2                  // class org/jboss/as/controller/SimpleAttributeDefinitionBuilder
    1448: iconst_1
    1449: invokevirtual #10                 // Method org/jboss/as/controller/SimpleAttributeDefinitionBuilder.setAllowExpression:(Z)Lorg/jboss/as/controller/AbstractAttributeDefinitionBuilder;
    1452: checkcast     #2                  // class org/jboss/as/controller/SimpleAttributeDefinitionBuilder
    1455: iconst_1
    1456: invokevirtual #26                 // Method org/jboss/as/controller/SimpleAttributeDefinitionBuilder.setAllowNull:(Z)Lorg/jboss/as/controller/AbstractAttributeDefinitionBuilder;
    1459: checkcast     #2                  // class org/jboss/as/controller/SimpleAttributeDefinitionBuilder
    1462: getstatic     #27                 // Field org/jboss/as/controller/client/helpers/MeasurementUnit.NONE:Lorg/jboss/as/controller/client/helpers/MeasurementUnit;
    1465: invokevirtual #28                 // Method org/jboss/as/controller/SimpleAttributeDefinitionBuilder.setMeasurementUnit:(Lorg/jboss/as/controller/client/helpers/MeasurementUnit;)Lorg/jboss/as/controller/AbstractAttributeDefinitionBuilder;
    1468: checkcast     #2                  // class org/jboss/as/controller/SimpleAttributeDefinitionBuilder
    1471: iconst_2
    1472: anewarray     #32                 // class java/lang/String
    1475: dup
    1476: iconst_0
    1477: ldc           #130                // String security-domain
    1479: aastore
    1480: dup
    1481: iconst_1
    1482: ldc           #133                // String security-domain-and-application
    1484: aastore
    1485: invokevirtual #34                 // Method org/jboss/as/controller/SimpleAttributeDefinitionBuilder.setAlternatives:([Ljava/lang/String;)Lorg/jboss/as/controller/AbstractAttributeDefinitionBuilder;
    1488: checkcast     #2                  // class org/jboss/as/controller/SimpleAttributeDefinitionBuilder
    1491: getstatic     #135                // Field org/jboss/as/controller/access/management/SensitiveTargetAccessConstraintDefinition.SECURITY_DOMAIN_REF:Lorg/jboss/as/controller/access/management/SensitiveTargetAccessConstraintDefinition;
    1494: invokevirtual #136                // Method org/jboss/as/controller/SimpleAttributeDefinitionBuilder.addAccessConstraint:(Lorg/jboss/as/controller/access/management/AccessConstraintDefinition;)Lorg/jboss/as/controller/AbstractAttributeDefinitionBuilder;
    1497: checkcast     #2                  // class org/jboss/as/controller/SimpleAttributeDefinitionBuilder
    1500: getstatic     #137                // Field org/jboss/as/connector/subsystems/resourceadapters/ResourceAdaptersExtension.RA_SECURITY_DEF:Lorg/jboss/as/controller/access/management/SensitiveTargetAccessConstraintDefinition;
    1503: invokevirtual #136                // Method org/jboss/as/controller/SimpleAttributeDefinitionBuilder.addAccessConstraint:(Lorg/jboss/as/controller/access/management/AccessConstraintDefinition;)Lorg/jboss/as/controller/AbstractAttributeDefinitionBuilder;
    1506: checkcast     #2                  // class org/jboss/as/controller/SimpleAttributeDefinitionBuilder
    1509: invokevirtual #11                 // Method org/jboss/as/controller/SimpleAttributeDefinitionBuilder.build:()Lorg/jboss/as/controller/SimpleAttributeDefinition;
    1512: putstatic     #143                // Field APPLICATION:Lorg/jboss/as/controller/SimpleAttributeDefinition;
    1515: new           #2                  // class org/jboss/as/controller/SimpleAttributeDefinitionBuilder
    1518: dup
    1519: ldc           #144                // String allocation-retry
    1521: getstatic     #145                // Field org/jboss/dmr/ModelType.INT:Lorg/jboss/dmr/ModelType;
    1524: iconst_1
    1525: invokespecial #6                  // Method org/jboss/as/controller/SimpleAttributeDefinitionBuilder."<init>":(Ljava/lang/String;Lorg/jboss/dmr/ModelType;Z)V
    1528: getstatic     #146                // Field org/jboss/jca/common/api/metadata/ds/TimeOut$Tag.ALLOCATION_RETRY:Lorg/jboss/jca/common/api/metadata/ds/TimeOut$Tag;
    1531: invokevirtual #147                // Method org/jboss/jca/common/api/metadata/ds/TimeOut$Tag.getLocalName:()Ljava/lang/String;
    1534: invokevirtual #9                  // Method org/jboss/as/controller/SimpleAttributeDefinitionBuilder.setXmlName:(Ljava/lang/String;)Lorg/jboss/as/controller/AbstractAttributeDefinitionBuilder;
    1537: checkcast     #2                  // class org/jboss/as/controller/SimpleAttributeDefinitionBuilder
    1540: iconst_1
    1541: invokevirtual #10                 // Method org/jboss/as/controller/SimpleAttributeDefinitionBuilder.setAllowExpression:(Z)Lorg/jboss/as/controller/AbstractAttributeDefinitionBuilder;
    1544: checkcast     #2                  // class org/jboss/as/controller/SimpleAttributeDefinitionBuilder
    1547: invokevirtual #11                 // Method org/jboss/as/controller/SimpleAttributeDefinitionBuilder.build:()Lorg/jboss/as/controller/SimpleAttributeDefinition;
    1550: putstatic     #148                // Field ALLOCATION_RETRY:Lorg/jboss/as/controller/SimpleAttributeDefinition;
    1553: new           #2                  // class org/jboss/as/controller/SimpleAttributeDefinitionBuilder
    1556: dup
    1557: ldc           #149                // String allocation-retry-wait-millis
    1559: getstatic     #150                // Field org/jboss/dmr/ModelType.LONG:Lorg/jboss/dmr/ModelType;
    1562: iconst_1
    1563: invokespecial #6                  // Method org/jboss/as/controller/SimpleAttributeDefinitionBuilder."<init>":(Ljava/lang/String;Lorg/jboss/dmr/ModelType;Z)V
    1566: getstatic     #151                // Field org/jboss/jca/common/api/metadata/ds/TimeOut$Tag.ALLOCATION_RETRY_WAIT_MILLIS:Lorg/jboss/jca/common/api/metadata/ds/TimeOut$Tag;
    1569: invokevirtual #147                // Method org/jboss/jca/common/api/metadata/ds/TimeOut$Tag.getLocalName:()Ljava/lang/String;
    1572: invokevirtual #9                  // Method org/jboss/as/controller/SimpleAttributeDefinitionBuilder.setXmlName:(Ljava/lang/String;)Lorg/jboss/as/controller/AbstractAttributeDefinitionBuilder;
    1575: checkcast     #2                  // class org/jboss/as/controller/SimpleAttributeDefinitionBuilder
    1578: iconst_1
    1579: invokevirtual #10                 // Method org/jboss/as/controller/SimpleAttributeDefinitionBuilder.setAllowExpression:(Z)Lorg/jboss/as/controller/AbstractAttributeDefinitionBuilder;
    1582: checkcast     #2                  // class org/jboss/as/controller/SimpleAttributeDefinitionBuilder
    1585: invokevirtual #11                 // Method org/jboss/as/controller/SimpleAttributeDefinitionBuilder.build:()Lorg/jboss/as/controller/SimpleAttributeDefinition;
    1588: putstatic     #152                // Field ALLOCATION_RETRY_WAIT_MILLIS:Lorg/jboss/as/controller/SimpleAttributeDefinition;
    1591: new           #2                  // class org/jboss/as/controller/SimpleAttributeDefinitionBuilder
    1594: dup
    1595: ldc           #153                // String use-try-lock
    1597: getstatic     #150                // Field org/jboss/dmr/ModelType.LONG:Lorg/jboss/dmr/ModelType;
    1600: iconst_1
    1601: invokespecial #6                  // Method org/jboss/as/controller/SimpleAttributeDefinitionBuilder."<init>":(Ljava/lang/String;Lorg/jboss/dmr/ModelType;Z)V
    1604: getstatic     #154                // Field org/jboss/jca/common/api/metadata/ds/TimeOut$Tag.USE_TRY_LOCK:Lorg/jboss/jca/common/api/metadata/ds/TimeOut$Tag;
    1607: invokevirtual #147                // Method org/jboss/jca/common/api/metadata/ds/TimeOut$Tag.getLocalName:()Ljava/lang/String;
    1610: invokevirtual #9                  // Method org/jboss/as/controller/SimpleAttributeDefinitionBuilder.setXmlName:(Ljava/lang/String;)Lorg/jboss/as/controller/AbstractAttributeDefinitionBuilder;
    1613: checkcast     #2                  // class org/jboss/as/controller/SimpleAttributeDefinitionBuilder
    1616: iconst_1
    1617: invokevirtual #10                 // Method org/jboss/as/controller/SimpleAttributeDefinitionBuilder.setAllowExpression:(Z)Lorg/jboss/as/controller/AbstractAttributeDefinitionBuilder;
    1620: checkcast     #2                  // class org/jboss/as/controller/SimpleAttributeDefinitionBuilder
    1623: invokevirtual #11                 // Method org/jboss/as/controller/SimpleAttributeDefinitionBuilder.build:()Lorg/jboss/as/controller/SimpleAttributeDefinition;
    1626: putstatic     #155                // Field USETRYLOCK:Lorg/jboss/as/controller/SimpleAttributeDefinition;
    1629: new           #2                  // class org/jboss/as/controller/SimpleAttributeDefinitionBuilder
    1632: dup
    1633: ldc           #156                // String use-ccm
    1635: getstatic     #53                 // Field org/jboss/dmr/ModelType.BOOLEAN:Lorg/jboss/dmr/ModelType;
    1638: iconst_1
    1639: invokespecial #6                  // Method org/jboss/as/controller/SimpleAttributeDefinitionBuilder."<init>":(Ljava/lang/String;Lorg/jboss/dmr/ModelType;Z)V
    1642: getstatic     #157                // Field org/jboss/jca/common/api/metadata/ds/DataSource$Attribute.USE_CCM:Lorg/jboss/jca/common/api/metadata/ds/DataSource$Attribute;
    1645: invokevirtual #115                // Method org/jboss/jca/common/api/metadata/ds/DataSource$Attribute.getLocalName:()Ljava/lang/String;
    1648: invokevirtual #9                  // Method org/jboss/as/controller/SimpleAttributeDefinitionBuilder.setXmlName:(Ljava/lang/String;)Lorg/jboss/as/controller/AbstractAttributeDefinitionBuilder;
    1651: checkcast     #2                  // class org/jboss/as/controller/SimpleAttributeDefinitionBuilder
    1654: new           #55                 // class org/jboss/dmr/ModelNode
    1657: dup
    1658: getstatic     #158                // Field org/jboss/jca/common/api/metadata/Defaults.USE_CCM:Ljava/lang/Boolean;
    1661: invokevirtual #117                // Method java/lang/Boolean.booleanValue:()Z
    1664: invokespecial #56                 // Method org/jboss/dmr/ModelNode."<init>":(Z)V
    1667: invokevirtual #57                 // Method org/jboss/as/controller/SimpleAttributeDefinitionBuilder.setDefaultValue:(Lorg/jboss/dmr/ModelNode;)Lorg/jboss/as/controller/AbstractAttributeDefinitionBuilder;
    1670: checkcast     #2                  // class org/jboss/as/controller/SimpleAttributeDefinitionBuilder
    1673: iconst_1
    1674: invokevirtual #10                 // Method org/jboss/as/controller/SimpleAttributeDefinitionBuilder.setAllowExpression:(Z)Lorg/jboss/as/controller/AbstractAttributeDefinitionBuilder;
    1677: checkcast     #2                  // class org/jboss/as/controller/SimpleAttributeDefinitionBuilder
    1680: invokevirtual #11                 // Method org/jboss/as/controller/SimpleAttributeDefinitionBuilder.build:()Lorg/jboss/as/controller/SimpleAttributeDefinition;
    1683: putstatic     #159                // Field USE_CCM:Lorg/jboss/as/controller/SimpleAttributeDefinition;
    1686: new           #2                  // class org/jboss/as/controller/SimpleAttributeDefinitionBuilder
    1689: dup
    1690: ldc           #160                // String sharable
    1692: getstatic     #53                 // Field org/jboss/dmr/ModelType.BOOLEAN:Lorg/jboss/dmr/ModelType;
    1695: invokespecial #54                 // Method org/jboss/as/controller/SimpleAttributeDefinitionBuilder."<init>":(Ljava/lang/String;Lorg/jboss/dmr/ModelType;)V
    1698: iconst_1
    1699: invokevirtual #10                 // Method org/jboss/as/controller/SimpleAttributeDefinitionBuilder.setAllowExpression:(Z)Lorg/jboss/as/controller/AbstractAttributeDefinitionBuilder;
    1702: checkcast     #2                  // class org/jboss/as/controller/SimpleAttributeDefinitionBuilder
    1705: iconst_1
    1706: invokevirtual #26                 // Method org/jboss/as/controller/SimpleAttributeDefinitionBuilder.setAllowNull:(Z)Lorg/jboss/as/controller/AbstractAttributeDefinitionBuilder;
    1709: checkcast     #2                  // class org/jboss/as/controller/SimpleAttributeDefinitionBuilder
    1712: new           #55                 // class org/jboss/dmr/ModelNode
    1715: dup
    1716: getstatic     #161                // Field org/jboss/jca/common/api/metadata/Defaults.SHARABLE:Ljava/lang/Boolean;
    1719: invokevirtual #117                // Method java/lang/Boolean.booleanValue:()Z
    1722: invokespecial #56                 // Method org/jboss/dmr/ModelNode."<init>":(Z)V
    1725: invokevirtual #57                 // Method org/jboss/as/controller/SimpleAttributeDefinitionBuilder.setDefaultValue:(Lorg/jboss/dmr/ModelNode;)Lorg/jboss/as/controller/AbstractAttributeDefinitionBuilder;
    1728: checkcast     #2                  // class org/jboss/as/controller/SimpleAttributeDefinitionBuilder
    1731: getstatic     #162                // Field org/jboss/jca/common/api/metadata/resourceadapter/ConnectionDefinition$Attribute.SHARABLE:Lorg/jboss/jca/common/api/metadata/resourceadapter/ConnectionDefinition$Attribute;
    1734: invokevirtual #8                  // Method org/jboss/jca/common/api/metadata/resourceadapter/ConnectionDefinition$Attribute.getLocalName:()Ljava/lang/String;
    1737: invokevirtual #9                  // Method org/jboss/as/controller/SimpleAttributeDefinitionBuilder.setXmlName:(Ljava/lang/String;)Lorg/jboss/as/controller/AbstractAttributeDefinitionBuilder;
    1740: checkcast     #2                  // class org/jboss/as/controller/SimpleAttributeDefinitionBuilder
    1743: invokevirtual #11                 // Method org/jboss/as/controller/SimpleAttributeDefinitionBuilder.build:()Lorg/jboss/as/controller/SimpleAttributeDefinition;
    1746: putstatic     #163                // Field SHARABLE:Lorg/jboss/as/controller/SimpleAttributeDefinition;
    1749: new           #2                  // class org/jboss/as/controller/SimpleAttributeDefinitionBuilder
    1752: dup
    1753: ldc           #164                // String enlistment
    1755: getstatic     #53                 // Field org/jboss/dmr/ModelType.BOOLEAN:Lorg/jboss/dmr/ModelType;
    1758: invokespecial #54                 // Method org/jboss/as/controller/SimpleAttributeDefinitionBuilder."<init>":(Ljava/lang/String;Lorg/jboss/dmr/ModelType;)V
    1761: iconst_1
    1762: invokevirtual #10                 // Method org/jboss/as/controller/SimpleAttributeDefinitionBuilder.setAllowExpression:(Z)Lorg/jboss/as/controller/AbstractAttributeDefinitionBuilder;
    1765: checkcast     #2                  // class org/jboss/as/controller/SimpleAttributeDefinitionBuilder
    1768: iconst_1
    1769: invokevirtual #26                 // Method org/jboss/as/controller/SimpleAttributeDefinitionBuilder.setAllowNull:(Z)Lorg/jboss/as/controller/AbstractAttributeDefinitionBuilder;
    1772: checkcast     #2                  // class org/jboss/as/controller/SimpleAttributeDefinitionBuilder
    1775: new           #55                 // class org/jboss/dmr/ModelNode
    1778: dup
    1779: getstatic     #165                // Field org/jboss/jca/common/api/metadata/Defaults.ENLISTMENT:Ljava/lang/Boolean;
    1782: invokevirtual #117                // Method java/lang/Boolean.booleanValue:()Z
    1785: invokespecial #56                 // Method org/jboss/dmr/ModelNode."<init>":(Z)V
    1788: invokevirtual #57                 // Method org/jboss/as/controller/SimpleAttributeDefinitionBuilder.setDefaultValue:(Lorg/jboss/dmr/ModelNode;)Lorg/jboss/as/controller/AbstractAttributeDefinitionBuilder;
    1791: checkcast     #2                  // class org/jboss/as/controller/SimpleAttributeDefinitionBuilder
    1794: getstatic     #166                // Field org/jboss/jca/common/api/metadata/resourceadapter/ConnectionDefinition$Attribute.ENLISTMENT:Lorg/jboss/jca/common/api/metadata/resourceadapter/ConnectionDefinition$Attribute;
    1797: invokevirtual #8                  // Method org/jboss/jca/common/api/metadata/resourceadapter/ConnectionDefinition$Attribute.getLocalName:()Ljava/lang/String;
    1800: invokevirtual #9                  // Method org/jboss/as/controller/SimpleAttributeDefinitionBuilder.setXmlName:(Ljava/lang/String;)Lorg/jboss/as/controller/AbstractAttributeDefinitionBuilder;
    1803: checkcast     #2                  // class org/jboss/as/controller/SimpleAttributeDefinitionBuilder
    1806: invokevirtual #11                 // Method org/jboss/as/controller/SimpleAttributeDefinitionBuilder.build:()Lorg/jboss/as/controller/SimpleAttributeDefinition;
    1809: putstatic     #167                // Field ENLISTMENT:Lorg/jboss/as/controller/SimpleAttributeDefinition;
    1812: new           #2                  // class org/jboss/as/controller/SimpleAttributeDefinitionBuilder
    1815: dup
    1816: ldc           #168                // String enlistment-trace
    1818: getstatic     #53                 // Field org/jboss/dmr/ModelType.BOOLEAN:Lorg/jboss/dmr/ModelType;
    1821: invokespecial #54                 // Method org/jboss/as/controller/SimpleAttributeDefinitionBuilder."<init>":(Ljava/lang/String;Lorg/jboss/dmr/ModelType;)V
    1824: iconst_1
    1825: invokevirtual #10                 // Method org/jboss/as/controller/SimpleAttributeDefinitionBuilder.setAllowExpression:(Z)Lorg/jboss/as/controller/AbstractAttributeDefinitionBuilder;
    1828: checkcast     #2                  // class org/jboss/as/controller/SimpleAttributeDefinitionBuilder
    1831: iconst_1
    1832: invokevirtual #26                 // Method org/jboss/as/controller/SimpleAttributeDefinitionBuilder.setAllowNull:(Z)Lorg/jboss/as/controller/AbstractAttributeDefinitionBuilder;
    1835: checkcast     #2                  // class org/jboss/as/controller/SimpleAttributeDefinitionBuilder
    1838: getstatic     #169                // Field org/jboss/jca/common/api/metadata/resourceadapter/ConnectionDefinition$Attribute.ENLISTMENT_TRACE:Lorg/jboss/jca/common/api/metadata/resourceadapter/ConnectionDefinition$Attribute;
    1841: invokevirtual #8                  // Method org/jboss/jca/common/api/metadata/resourceadapter/ConnectionDefinition$Attribute.getLocalName:()Ljava/lang/String;
    1844: invokevirtual #9                  // Method org/jboss/as/controller/SimpleAttributeDefinitionBuilder.setXmlName:(Ljava/lang/String;)Lorg/jboss/as/controller/AbstractAttributeDefinitionBuilder;
    1847: checkcast     #2                  // class org/jboss/as/controller/SimpleAttributeDefinitionBuilder
    1850: invokevirtual #11                 // Method org/jboss/as/controller/SimpleAttributeDefinitionBuilder.build:()Lorg/jboss/as/controller/SimpleAttributeDefinition;
    1853: putstatic     #170                // Field ENLISTMENT_TRACE:Lorg/jboss/as/controller/SimpleAttributeDefinition;
    1856: new           #2                  // class org/jboss/as/controller/SimpleAttributeDefinitionBuilder
    1859: dup
    1860: ldc           #171                // String mcp
    1862: getstatic     #5                  // Field org/jboss/dmr/ModelType.STRING:Lorg/jboss/dmr/ModelType;
    1865: invokespecial #54                 // Method org/jboss/as/controller/SimpleAttributeDefinitionBuilder."<init>":(Ljava/lang/String;Lorg/jboss/dmr/ModelType;)V
    1868: iconst_1
    1869: invokevirtual #10                 // Method org/jboss/as/controller/SimpleAttributeDefinitionBuilder.setAllowExpression:(Z)Lorg/jboss/as/controller/AbstractAttributeDefinitionBuilder;
    1872: checkcast     #2                  // class org/jboss/as/controller/SimpleAttributeDefinitionBuilder
    1875: iconst_1
    1876: invokevirtual #26                 // Method org/jboss/as/controller/SimpleAttributeDefinitionBuilder.setAllowNull:(Z)Lorg/jboss/as/controller/AbstractAttributeDefinitionBuilder;
    1879: checkcast     #2                  // class org/jboss/as/controller/SimpleAttributeDefinitionBuilder
    1882: getstatic     #172                // Field org/jboss/jca/common/api/metadata/resourceadapter/ConnectionDefinition$Attribute.MCP:Lorg/jboss/jca/common/api/metadata/resourceadapter/ConnectionDefinition$Attribute;
    1885: invokevirtual #8                  // Method org/jboss/jca/common/api/metadata/resourceadapter/ConnectionDefinition$Attribute.getLocalName:()Ljava/lang/String;
    1888: invokevirtual #9                  // Method org/jboss/as/controller/SimpleAttributeDefinitionBuilder.setXmlName:(Ljava/lang/String;)Lorg/jboss/as/controller/AbstractAttributeDefinitionBuilder;
    1891: checkcast     #2                  // class org/jboss/as/controller/SimpleAttributeDefinitionBuilder
    1894: invokevirtual #11                 // Method org/jboss/as/controller/SimpleAttributeDefinitionBuilder.build:()Lorg/jboss/as/controller/SimpleAttributeDefinition;
    1897: putstatic     #173                // Field MCP:Lorg/jboss/as/controller/SimpleAttributeDefinition;
    1900: new           #2                  // class org/jboss/as/controller/SimpleAttributeDefinitionBuilder
    1903: dup
    1904: ldc           #174                // String interleaving
    1906: getstatic     #53                 // Field org/jboss/dmr/ModelType.BOOLEAN:Lorg/jboss/dmr/ModelType;
    1909: iconst_1
    1910: invokespecial #6                  // Method org/jboss/as/controller/SimpleAttributeDefinitionBuilder."<init>":(Ljava/lang/String;Lorg/jboss/dmr/ModelType;Z)V
    1913: getstatic     #175                // Field org/jboss/jca/common/api/metadata/common/XaPool$Tag.INTERLEAVING:Lorg/jboss/jca/common/api/metadata/common/XaPool$Tag;
    1916: invokevirtual #176                // Method org/jboss/jca/common/api/metadata/common/XaPool$Tag.getLocalName:()Ljava/lang/String;
    1919: invokevirtual #9                  // Method org/jboss/as/controller/SimpleAttributeDefinitionBuilder.setXmlName:(Ljava/lang/String;)Lorg/jboss/as/controller/AbstractAttributeDefinitionBuilder;
    1922: checkcast     #2                  // class org/jboss/as/controller/SimpleAttributeDefinitionBuilder
    1925: new           #55                 // class org/jboss/dmr/ModelNode
    1928: dup
    1929: getstatic     #177                // Field org/jboss/jca/common/api/metadata/Defaults.INTERLEAVING:Ljava/lang/Boolean;
    1932: invokevirtual #117                // Method java/lang/Boolean.booleanValue:()Z
    1935: invokespecial #56                 // Method org/jboss/dmr/ModelNode."<init>":(Z)V
    1938: invokevirtual #57                 // Method org/jboss/as/controller/SimpleAttributeDefinitionBuilder.setDefaultValue:(Lorg/jboss/dmr/ModelNode;)Lorg/jboss/as/controller/AbstractAttributeDefinitionBuilder;
    1941: checkcast     #2                  // class org/jboss/as/controller/SimpleAttributeDefinitionBuilder
    1944: iconst_1
    1945: invokevirtual #10                 // Method org/jboss/as/controller/SimpleAttributeDefinitionBuilder.setAllowExpression:(Z)Lorg/jboss/as/controller/AbstractAttributeDefinitionBuilder;
    1948: checkcast     #2                  // class org/jboss/as/controller/SimpleAttributeDefinitionBuilder
    1951: invokevirtual #11                 // Method org/jboss/as/controller/SimpleAttributeDefinitionBuilder.build:()Lorg/jboss/as/controller/SimpleAttributeDefinition;
    1954: putstatic     #178                // Field INTERLEAVING:Lorg/jboss/as/controller/SimpleAttributeDefinition;
    1957: new           #2                  // class org/jboss/as/controller/SimpleAttributeDefinitionBuilder
    1960: dup
    1961: ldc           #179                // String no-tx-separate-pool
    1963: getstatic     #53                 // Field org/jboss/dmr/ModelType.BOOLEAN:Lorg/jboss/dmr/ModelType;
    1966: iconst_1
    1967: invokespecial #6                  // Method org/jboss/as/controller/SimpleAttributeDefinitionBuilder."<init>":(Ljava/lang/String;Lorg/jboss/dmr/ModelType;Z)V
    1970: getstatic     #180                // Field org/jboss/jca/common/api/metadata/common/XaPool$Tag.NO_TX_SEPARATE_POOLS:Lorg/jboss/jca/common/api/metadata/common/XaPool$Tag;
    1973: invokevirtual #176                // Method org/jboss/jca/common/api/metadata/common/XaPool$Tag.getLocalName:()Ljava/lang/String;
    1976: invokevirtual #9                  // Method org/jboss/as/controller/SimpleAttributeDefinitionBuilder.setXmlName:(Ljava/lang/String;)Lorg/jboss/as/controller/AbstractAttributeDefinitionBuilder;
    1979: checkcast     #2                  // class org/jboss/as/controller/SimpleAttributeDefinitionBuilder
    1982: new           #55                 // class org/jboss/dmr/ModelNode
    1985: dup
    1986: getstatic     #181                // Field org/jboss/jca/common/api/metadata/Defaults.NO_TX_SEPARATE_POOL:Ljava/lang/Boolean;
    1989: invokevirtual #117                // Method java/lang/Boolean.booleanValue:()Z
    1992: invokespecial #56                 // Method org/jboss/dmr/ModelNode."<init>":(Z)V
    1995: invokevirtual #57                 // Method org/jboss/as/controller/SimpleAttributeDefinitionBuilder.setDefaultValue:(Lorg/jboss/dmr/ModelNode;)Lorg/jboss/as/controller/AbstractAttributeDefinitionBuilder;
    1998: checkcast     #2                  // class org/jboss/as/controller/SimpleAttributeDefinitionBuilder
    2001: iconst_1
    2002: invokevirtual #10                 // Method org/jboss/as/controller/SimpleAttributeDefinitionBuilder.setAllowExpression:(Z)Lorg/jboss/as/controller/AbstractAttributeDefinitionBuilder;
    2005: checkcast     #2                  // class org/jboss/as/controller/SimpleAttributeDefinitionBuilder
    2008: invokevirtual #11                 // Method org/jboss/as/controller/SimpleAttributeDefinitionBuilder.build:()Lorg/jboss/as/controller/SimpleAttributeDefinition;
    2011: putstatic     #182                // Field NOTXSEPARATEPOOL:Lorg/jboss/as/controller/SimpleAttributeDefinition;
    2014: new           #2                  // class org/jboss/as/controller/SimpleAttributeDefinitionBuilder
    2017: dup
    2018: ldc           #183                // String pad-xid
    2020: getstatic     #53                 // Field org/jboss/dmr/ModelType.BOOLEAN:Lorg/jboss/dmr/ModelType;
    2023: iconst_1
    2024: invokespecial #6                  // Method org/jboss/as/controller/SimpleAttributeDefinitionBuilder."<init>":(Ljava/lang/String;Lorg/jboss/dmr/ModelType;Z)V
    2027: getstatic     #184                // Field org/jboss/jca/common/api/metadata/common/XaPool$Tag.PAD_XID:Lorg/jboss/jca/common/api/metadata/common/XaPool$Tag;
    2030: invokevirtual #176                // Method org/jboss/jca/common/api/metadata/common/XaPool$Tag.getLocalName:()Ljava/lang/String;
    2033: invokevirtual #9                  // Method org/jboss/as/controller/SimpleAttributeDefinitionBuilder.setXmlName:(Ljava/lang/String;)Lorg/jboss/as/controller/AbstractAttributeDefinitionBuilder;
    2036: checkcast     #2                  // class org/jboss/as/controller/SimpleAttributeDefinitionBuilder
    2039: new           #55                 // class org/jboss/dmr/ModelNode
    2042: dup
    2043: getstatic     #185                // Field org/jboss/jca/common/api/metadata/Defaults.PAD_XID:Ljava/lang/Boolean;
    2046: invokevirtual #117                // Method java/lang/Boolean.booleanValue:()Z
    2049: invokespecial #56                 // Method org/jboss/dmr/ModelNode."<init>":(Z)V
    2052: invokevirtual #57                 // Method org/jboss/as/controller/SimpleAttributeDefinitionBuilder.setDefaultValue:(Lorg/jboss/dmr/ModelNode;)Lorg/jboss/as/controller/AbstractAttributeDefinitionBuilder;
    2055: checkcast     #2                  // class org/jboss/as/controller/SimpleAttributeDefinitionBuilder
    2058: iconst_1
    2059: invokevirtual #10                 // Method org/jboss/as/controller/SimpleAttributeDefinitionBuilder.setAllowExpression:(Z)Lorg/jboss/as/controller/AbstractAttributeDefinitionBuilder;
    2062: checkcast     #2                  // class org/jboss/as/controller/SimpleAttributeDefinitionBuilder
    2065: invokevirtual #11                 // Method org/jboss/as/controller/SimpleAttributeDefinitionBuilder.build:()Lorg/jboss/as/controller/SimpleAttributeDefinition;
    2068: putstatic     #186                // Field PAD_XID:Lorg/jboss/as/controller/SimpleAttributeDefinition;
    2071: new           #2                  // class org/jboss/as/controller/SimpleAttributeDefinitionBuilder
    2074: dup
    2075: ldc           #187                // String same-rm-override
    2077: getstatic     #53                 // Field org/jboss/dmr/ModelType.BOOLEAN:Lorg/jboss/dmr/ModelType;
    2080: invokespecial #54                 // Method org/jboss/as/controller/SimpleAttributeDefinitionBuilder."<init>":(Ljava/lang/String;Lorg/jboss/dmr/ModelType;)V
    2083: iconst_1
    2084: invokevirtual #26                 // Method org/jboss/as/controller/SimpleAttributeDefinitionBuilder.setAllowNull:(Z)Lorg/jboss/as/controller/AbstractAttributeDefinitionBuilder;
    2087: checkcast     #2                  // class org/jboss/as/controller/SimpleAttributeDefinitionBuilder
    2090: iconst_1
    2091: invokevirtual #10                 // Method org/jboss/as/controller/SimpleAttributeDefinitionBuilder.setAllowExpression:(Z)Lorg/jboss/as/controller/AbstractAttributeDefinitionBuilder;
    2094: checkcast     #2                  // class org/jboss/as/controller/SimpleAttributeDefinitionBuilder
    2097: getstatic     #188                // Field org/jboss/jca/common/api/metadata/common/XaPool$Tag.IS_SAME_RM_OVERRIDE:Lorg/jboss/jca/common/api/metadata/common/XaPool$Tag;
    2100: invokevirtual #176                // Method org/jboss/jca/common/api/metadata/common/XaPool$Tag.getLocalName:()Ljava/lang/String;
    2103: invokevirtual #9                  // Method org/jboss/as/controller/SimpleAttributeDefinitionBuilder.setXmlName:(Ljava/lang/String;)Lorg/jboss/as/controller/AbstractAttributeDefinitionBuilder;
    2106: checkcast     #2                  // class org/jboss/as/controller/SimpleAttributeDefinitionBuilder
    2109: invokevirtual #11                 // Method org/jboss/as/controller/SimpleAttributeDefinitionBuilder.build:()Lorg/jboss/as/controller/SimpleAttributeDefinition;
    2112: putstatic     #189                // Field SAME_RM_OVERRIDE:Lorg/jboss/as/controller/SimpleAttributeDefinition;
    2115: new           #2                  // class org/jboss/as/controller/SimpleAttributeDefinitionBuilder
    2118: dup
    2119: ldc           #190                // String wrap-xa-resource
    2121: getstatic     #53                 // Field org/jboss/dmr/ModelType.BOOLEAN:Lorg/jboss/dmr/ModelType;
    2124: iconst_1
    2125: invokespecial #6                  // Method org/jboss/as/controller/SimpleAttributeDefinitionBuilder."<init>":(Ljava/lang/String;Lorg/jboss/dmr/ModelType;Z)V
    2128: getstatic     #191                // Field org/jboss/jca/common/api/metadata/common/XaPool$Tag.WRAP_XA_RESOURCE:Lorg/jboss/jca/common/api/metadata/common/XaPool$Tag;
    2131: invokevirtual #176                // Method org/jboss/jca/common/api/metadata/common/XaPool$Tag.getLocalName:()Ljava/lang/String;
    2134: invokevirtual #9                  // Method org/jboss/as/controller/SimpleAttributeDefinitionBuilder.setXmlName:(Ljava/lang/String;)Lorg/jboss/as/controller/AbstractAttributeDefinitionBuilder;
    2137: checkcast     #2                  // class org/jboss/as/controller/SimpleAttributeDefinitionBuilder
    2140: new           #55                 // class org/jboss/dmr/ModelNode
    2143: dup
    2144: getstatic     #192                // Field org/jboss/jca/common/api/metadata/Defaults.WRAP_XA_RESOURCE:Ljava/lang/Boolean;
    2147: invokevirtual #117                // Method java/lang/Boolean.booleanValue:()Z
    2150: invokespecial #56                 // Method org/jboss/dmr/ModelNode."<init>":(Z)V
    2153: invokevirtual #57                 // Method org/jboss/as/controller/SimpleAttributeDefinitionBuilder.setDefaultValue:(Lorg/jboss/dmr/ModelNode;)Lorg/jboss/as/controller/AbstractAttributeDefinitionBuilder;
    2156: checkcast     #2                  // class org/jboss/as/controller/SimpleAttributeDefinitionBuilder
    2159: iconst_1
    2160: invokevirtual #10                 // Method org/jboss/as/controller/SimpleAttributeDefinitionBuilder.setAllowExpression:(Z)Lorg/jboss/as/controller/AbstractAttributeDefinitionBuilder;
    2163: checkcast     #2                  // class org/jboss/as/controller/SimpleAttributeDefinitionBuilder
    2166: invokevirtual #11                 // Method org/jboss/as/controller/SimpleAttributeDefinitionBuilder.build:()Lorg/jboss/as/controller/SimpleAttributeDefinition;
    2169: putstatic     #193                // Field WRAP_XA_RESOURCE:Lorg/jboss/as/controller/SimpleAttributeDefinition;
    2172: new           #2                  // class org/jboss/as/controller/SimpleAttributeDefinitionBuilder
    2175: dup
    2176: ldc           #194                // String xa-resource-timeout
    2178: getstatic     #145                // Field org/jboss/dmr/ModelType.INT:Lorg/jboss/dmr/ModelType;
    2181: iconst_1
    2182: invokespecial #6                  // Method org/jboss/as/controller/SimpleAttributeDefinitionBuilder."<init>":(Ljava/lang/String;Lorg/jboss/dmr/ModelType;Z)V
    2185: getstatic     #195                // Field org/jboss/jca/common/api/metadata/ds/TimeOut$Tag.XA_RESOURCE_TIMEOUT:Lorg/jboss/jca/common/api/metadata/ds/TimeOut$Tag;
    2188: invokevirtual #147                // Method org/jboss/jca/common/api/metadata/ds/TimeOut$Tag.getLocalName:()Ljava/lang/String;
    2191: invokevirtual #9                  // Method org/jboss/as/controller/SimpleAttributeDefinitionBuilder.setXmlName:(Ljava/lang/String;)Lorg/jboss/as/controller/AbstractAttributeDefinitionBuilder;
    2194: checkcast     #2                  // class org/jboss/as/controller/SimpleAttributeDefinitionBuilder
    2197: iconst_1
    2198: invokevirtual #10                 // Method org/jboss/as/controller/SimpleAttributeDefinitionBuilder.setAllowExpression:(Z)Lorg/jboss/as/controller/AbstractAttributeDefinitionBuilder;
    2201: checkcast     #2                  // class org/jboss/as/controller/SimpleAttributeDefinitionBuilder
    2204: invokevirtual #11                 // Method org/jboss/as/controller/SimpleAttributeDefinitionBuilder.build:()Lorg/jboss/as/controller/SimpleAttributeDefinition;
    2207: putstatic     #196                // Field XA_RESOURCE_TIMEOUT:Lorg/jboss/as/controller/SimpleAttributeDefinition;
    2210: new           #2                  // class org/jboss/as/controller/SimpleAttributeDefinitionBuilder
    2213: dup
    2214: ldc           #197                // String recovery-username
    2216: getstatic     #5                  // Field org/jboss/dmr/ModelType.STRING:Lorg/jboss/dmr/ModelType;
    2219: iconst_1
    2220: invokespecial #6                  // Method org/jboss/as/controller/SimpleAttributeDefinitionBuilder."<init>":(Ljava/lang/String;Lorg/jboss/dmr/ModelType;Z)V
    2223: getstatic     #198                // Field org/jboss/jca/common/api/metadata/common/Credential$Tag.USER_NAME:Lorg/jboss/jca/common/api/metadata/common/Credential$Tag;
    2226: invokevirtual #199                // Method org/jboss/jca/common/api/metadata/common/Credential$Tag.getLocalName:()Ljava/lang/String;
    2229: invokevirtual #9                  // Method org/jboss/as/controller/SimpleAttributeDefinitionBuilder.setXmlName:(Ljava/lang/String;)Lorg/jboss/as/controller/AbstractAttributeDefinitionBuilder;
    2232: checkcast     #2                  // class org/jboss/as/controller/SimpleAttributeDefinitionBuilder
    2235: new           #55                 // class org/jboss/dmr/ModelNode
    2238: dup
    2239: invokespecial #200                // Method org/jboss/dmr/ModelNode."<init>":()V
    2242: invokevirtual #57                 // Method org/jboss/as/controller/SimpleAttributeDefinitionBuilder.setDefaultValue:(Lorg/jboss/dmr/ModelNode;)Lorg/jboss/as/controller/AbstractAttributeDefinitionBuilder;
    2245: checkcast     #2                  // class org/jboss/as/controller/SimpleAttributeDefinitionBuilder
    2248: iconst_1
    2249: invokevirtual #10                 // Method org/jboss/as/controller/SimpleAttributeDefinitionBuilder.setAllowExpression:(Z)Lorg/jboss/as/controller/AbstractAttributeDefinitionBuilder;
    2252: checkcast     #2                  // class org/jboss/as/controller/SimpleAttributeDefinitionBuilder
    2255: getstatic     #27                 // Field org/jboss/as/controller/client/helpers/MeasurementUnit.NONE:Lorg/jboss/as/controller/client/helpers/MeasurementUnit;
    2258: invokevirtual #28                 // Method org/jboss/as/controller/SimpleAttributeDefinitionBuilder.setMeasurementUnit:(Lorg/jboss/as/controller/client/helpers/MeasurementUnit;)Lorg/jboss/as/controller/AbstractAttributeDefinitionBuilder;
    2261: checkcast     #2                  // class org/jboss/as/controller/SimpleAttributeDefinitionBuilder
    2264: getstatic     #201                // Field org/jboss/as/controller/access/management/SensitiveTargetAccessConstraintDefinition.CREDENTIAL:Lorg/jboss/as/controller/access/management/SensitiveTargetAccessConstraintDefinition;
    2267: invokevirtual #136                // Method org/jboss/as/controller/SimpleAttributeDefinitionBuilder.addAccessConstraint:(Lorg/jboss/as/controller/access/management/AccessConstraintDefinition;)Lorg/jboss/as/controller/AbstractAttributeDefinitionBuilder;
    2270: checkcast     #2                  // class org/jboss/as/controller/SimpleAttributeDefinitionBuilder
    2273: getstatic     #137                // Field org/jboss/as/connector/subsystems/resourceadapters/ResourceAdaptersExtension.RA_SECURITY_DEF:Lorg/jboss/as/controller/access/management/SensitiveTargetAccessConstraintDefinition;
    2276: invokevirtual #136                // Method org/jboss/as/controller/SimpleAttributeDefinitionBuilder.addAccessConstraint:(Lorg/jboss/as/controller/access/management/AccessConstraintDefinition;)Lorg/jboss/as/controller/AbstractAttributeDefinitionBuilder;
    2279: checkcast     #2                  // class org/jboss/as/controller/SimpleAttributeDefinitionBuilder
    2282: invokevirtual #11                 // Method org/jboss/as/controller/SimpleAttributeDefinitionBuilder.build:()Lorg/jboss/as/controller/SimpleAttributeDefinition;
    2285: putstatic     #202                // Field RECOVERY_USERNAME:Lorg/jboss/as/controller/SimpleAttributeDefinition;
    2288: new           #2                  // class org/jboss/as/controller/SimpleAttributeDefinitionBuilder
    2291: dup
    2292: ldc           #203                // String recovery-password
    2294: getstatic     #5                  // Field org/jboss/dmr/ModelType.STRING:Lorg/jboss/dmr/ModelType;
    2297: iconst_1
    2298: invokespecial #6                  // Method org/jboss/as/controller/SimpleAttributeDefinitionBuilder."<init>":(Ljava/lang/String;Lorg/jboss/dmr/ModelType;Z)V
    2301: getstatic     #204                // Field org/jboss/jca/common/api/metadata/common/Credential$Tag.PASSWORD:Lorg/jboss/jca/common/api/metadata/common/Credential$Tag;
    2304: invokevirtual #199                // Method org/jboss/jca/common/api/metadata/common/Credential$Tag.getLocalName:()Ljava/lang/String;
    2307: invokevirtual #9                  // Method org/jboss/as/controller/SimpleAttributeDefinitionBuilder.setXmlName:(Ljava/lang/String;)Lorg/jboss/as/controller/AbstractAttributeDefinitionBuilder;
    2310: checkcast     #2                  // class org/jboss/as/controller/SimpleAttributeDefinitionBuilder
    2313: new           #55                 // class org/jboss/dmr/ModelNode
    2316: dup
    2317: invokespecial #200                // Method org/jboss/dmr/ModelNode."<init>":()V
    2320: invokevirtual #57                 // Method org/jboss/as/controller/SimpleAttributeDefinitionBuilder.setDefaultValue:(Lorg/jboss/dmr/ModelNode;)Lorg/jboss/as/controller/AbstractAttributeDefinitionBuilder;
    2323: checkcast     #2                  // class org/jboss/as/controller/SimpleAttributeDefinitionBuilder
    2326: iconst_1
    2327: invokevirtual #10                 // Method org/jboss/as/controller/SimpleAttributeDefinitionBuilder.setAllowExpression:(Z)Lorg/jboss/as/controller/AbstractAttributeDefinitionBuilder;
    2330: checkcast     #2                  // class org/jboss/as/controller/SimpleAttributeDefinitionBuilder
    2333: getstatic     #27                 // Field org/jboss/as/controller/client/helpers/MeasurementUnit.NONE:Lorg/jboss/as/controller/client/helpers/MeasurementUnit;
    2336: invokevirtual #28                 // Method org/jboss/as/controller/SimpleAttributeDefinitionBuilder.setMeasurementUnit:(Lorg/jboss/as/controller/client/helpers/MeasurementUnit;)Lorg/jboss/as/controller/AbstractAttributeDefinitionBuilder;
    2339: checkcast     #2                  // class org/jboss/as/controller/SimpleAttributeDefinitionBuilder
    2342: getstatic     #201                // Field org/jboss/as/controller/access/management/SensitiveTargetAccessConstraintDefinition.CREDENTIAL:Lorg/jboss/as/controller/access/management/SensitiveTargetAccessConstraintDefinition;
    2345: invokevirtual #136                // Method org/jboss/as/controller/SimpleAttributeDefinitionBuilder.addAccessConstraint:(Lorg/jboss/as/controller/access/management/AccessConstraintDefinition;)Lorg/jboss/as/controller/AbstractAttributeDefinitionBuilder;
    2348: checkcast     #2                  // class org/jboss/as/controller/SimpleAttributeDefinitionBuilder
    2351: getstatic     #137                // Field org/jboss/as/connector/subsystems/resourceadapters/ResourceAdaptersExtension.RA_SECURITY_DEF:Lorg/jboss/as/controller/access/management/SensitiveTargetAccessConstraintDefinition;
    2354: invokevirtual #136                // Method org/jboss/as/controller/SimpleAttributeDefinitionBuilder.addAccessConstraint:(Lorg/jboss/as/controller/access/management/AccessConstraintDefinition;)Lorg/jboss/as/controller/AbstractAttributeDefinitionBuilder;
    2357: checkcast     #2                  // class org/jboss/as/controller/SimpleAttributeDefinitionBuilder
    2360: invokevirtual #11                 // Method org/jboss/as/controller/SimpleAttributeDefinitionBuilder.build:()Lorg/jboss/as/controller/SimpleAttributeDefinition;
    2363: putstatic     #205                // Field RECOVERY_PASSWORD:Lorg/jboss/as/controller/SimpleAttributeDefinition;
    2366: new           #2                  // class org/jboss/as/controller/SimpleAttributeDefinitionBuilder
    2369: dup
    2370: ldc           #206                // String recovery-security-domain
    2372: getstatic     #5                  // Field org/jboss/dmr/ModelType.STRING:Lorg/jboss/dmr/ModelType;
    2375: iconst_1
    2376: invokespecial #6                  // Method org/jboss/as/controller/SimpleAttributeDefinitionBuilder."<init>":(Ljava/lang/String;Lorg/jboss/dmr/ModelType;Z)V
    2379: getstatic     #207                // Field org/jboss/jca/common/api/metadata/common/Credential$Tag.SECURITY_DOMAIN:Lorg/jboss/jca/common/api/metadata/common/Credential$Tag;
    2382: invokevirtual #199                // Method org/jboss/jca/common/api/metadata/common/Credential$Tag.getLocalName:()Ljava/lang/String;
    2385: invokevirtual #9                  // Method org/jboss/as/controller/SimpleAttributeDefinitionBuilder.setXmlName:(Ljava/lang/String;)Lorg/jboss/as/controller/AbstractAttributeDefinitionBuilder;
    2388: checkcast     #2                  // class org/jboss/as/controller/SimpleAttributeDefinitionBuilder
    2391: iconst_1
    2392: invokevirtual #10                 // Method org/jboss/as/controller/SimpleAttributeDefinitionBuilder.setAllowExpression:(Z)Lorg/jboss/as/controller/AbstractAttributeDefinitionBuilder;
    2395: checkcast     #2                  // class org/jboss/as/controller/SimpleAttributeDefinitionBuilder
    2398: getstatic     #27                 // Field org/jboss/as/controller/client/helpers/MeasurementUnit.NONE:Lorg/jboss/as/controller/client/helpers/MeasurementUnit;
    2401: invokevirtual #28                 // Method org/jboss/as/controller/SimpleAttributeDefinitionBuilder.setMeasurementUnit:(Lorg/jboss/as/controller/client/helpers/MeasurementUnit;)Lorg/jboss/as/controller/AbstractAttributeDefinitionBuilder;
    2404: checkcast     #2                  // class org/jboss/as/controller/SimpleAttributeDefinitionBuilder
    2407: new           #55                 // class org/jboss/dmr/ModelNode
    2410: dup
    2411: invokespecial #200                // Method org/jboss/dmr/ModelNode."<init>":()V
    2414: invokevirtual #57                 // Method org/jboss/as/controller/SimpleAttributeDefinitionBuilder.setDefaultValue:(Lorg/jboss/dmr/ModelNode;)Lorg/jboss/as/controller/AbstractAttributeDefinitionBuilder;
    2417: checkcast     #2                  // class org/jboss/as/controller/SimpleAttributeDefinitionBuilder
    2420: getstatic     #135                // Field org/jboss/as/controller/access/management/SensitiveTargetAccessConstraintDefinition.SECURITY_DOMAIN_REF:Lorg/jboss/as/controller/access/management/SensitiveTargetAccessConstraintDefinition;
    2423: invokevirtual #136                // Method org/jboss/as/controller/SimpleAttributeDefinitionBuilder.addAccessConstraint:(Lorg/jboss/as/controller/access/management/AccessConstraintDefinition;)Lorg/jboss/as/controller/AbstractAttributeDefinitionBuilder;
    2426: checkcast     #2                  // class org/jboss/as/controller/SimpleAttributeDefinitionBuilder
    2429: getstatic     #137                // Field org/jboss/as/connector/subsystems/resourceadapters/ResourceAdaptersExtension.RA_SECURITY_DEF:Lorg/jboss/as/controller/access/management/SensitiveTargetAccessConstraintDefinition;
    2432: invokevirtual #136                // Method org/jboss/as/controller/SimpleAttributeDefinitionBuilder.addAccessConstraint:(Lorg/jboss/as/controller/access/management/AccessConstraintDefinition;)Lorg/jboss/as/controller/AbstractAttributeDefinitionBuilder;
    2435: checkcast     #2                  // class org/jboss/as/controller/SimpleAttributeDefinitionBuilder
    2438: invokevirtual #11                 // Method org/jboss/as/controller/SimpleAttributeDefinitionBuilder.build:()Lorg/jboss/as/controller/SimpleAttributeDefinition;
    2441: putstatic     #208                // Field RECOVERY_SECURITY_DOMAIN:Lorg/jboss/as/controller/SimpleAttributeDefinition;
    2444: new           #2                  // class org/jboss/as/controller/SimpleAttributeDefinitionBuilder
    2447: dup
    2448: ldc           #209                // String no-recovery
    2450: getstatic     #53                 // Field org/jboss/dmr/ModelType.BOOLEAN:Lorg/jboss/dmr/ModelType;
    2453: iconst_1
    2454: invokespecial #6                  // Method org/jboss/as/controller/SimpleAttributeDefinitionBuilder."<init>":(Ljava/lang/String;Lorg/jboss/dmr/ModelType;Z)V
    2457: getstatic     #210                // Field org/jboss/jca/common/api/metadata/common/Recovery$Attribute.NO_RECOVERY:Lorg/jboss/jca/common/api/metadata/common/Recovery$Attribute;
    2460: invokevirtual #211                // Method org/jboss/jca/common/api/metadata/common/Recovery$Attribute.getLocalName:()Ljava/lang/String;
    2463: invokevirtual #9                  // Method org/jboss/as/controller/SimpleAttributeDefinitionBuilder.setXmlName:(Ljava/lang/String;)Lorg/jboss/as/controller/AbstractAttributeDefinitionBuilder;
    2466: checkcast     #2                  // class org/jboss/as/controller/SimpleAttributeDefinitionBuilder
    2469: new           #55                 // class org/jboss/dmr/ModelNode
    2472: dup
    2473: iconst_0
    2474: invokespecial #56                 // Method org/jboss/dmr/ModelNode."<init>":(Z)V
    2477: invokevirtual #57                 // Method org/jboss/as/controller/SimpleAttributeDefinitionBuilder.setDefaultValue:(Lorg/jboss/dmr/ModelNode;)Lorg/jboss/as/controller/AbstractAttributeDefinitionBuilder;
    2480: checkcast     #2                  // class org/jboss/as/controller/SimpleAttributeDefinitionBuilder
    2483: iconst_1
    2484: invokevirtual #10                 // Method org/jboss/as/controller/SimpleAttributeDefinitionBuilder.setAllowExpression:(Z)Lorg/jboss/as/controller/AbstractAttributeDefinitionBuilder;
    2487: checkcast     #2                  // class org/jboss/as/controller/SimpleAttributeDefinitionBuilder
    2490: invokevirtual #11                 // Method org/jboss/as/controller/SimpleAttributeDefinitionBuilder.build:()Lorg/jboss/as/controller/SimpleAttributeDefinition;
    2493: putstatic     #212                // Field NO_RECOVERY:Lorg/jboss/as/controller/SimpleAttributeDefinition;
    2496: new           #2                  // class org/jboss/as/controller/SimpleAttributeDefinitionBuilder
    2499: dup
    2500: ldc           #213                // String recovery-plugin-class-name
    2502: getstatic     #5                  // Field org/jboss/dmr/ModelType.STRING:Lorg/jboss/dmr/ModelType;
    2505: iconst_1
    2506: invokespecial #6                  // Method org/jboss/as/controller/SimpleAttributeDefinitionBuilder."<init>":(Ljava/lang/String;Lorg/jboss/dmr/ModelType;Z)V
    2509: getstatic     #214                // Field org/jboss/jca/common/api/metadata/common/Extension$Attribute.CLASS_NAME:Lorg/jboss/jca/common/api/metadata/common/Extension$Attribute;
    2512: invokevirtual #215                // Method org/jboss/jca/common/api/metadata/common/Extension$Attribute.getLocalName:()Ljava/lang/String;
    2515: invokevirtual #9                  // Method org/jboss/as/controller/SimpleAttributeDefinitionBuilder.setXmlName:(Ljava/lang/String;)Lorg/jboss/as/controller/AbstractAttributeDefinitionBuilder;
    2518: checkcast     #2                  // class org/jboss/as/controller/SimpleAttributeDefinitionBuilder
    2521: iconst_1
    2522: invokevirtual #10                 // Method org/jboss/as/controller/SimpleAttributeDefinitionBuilder.setAllowExpression:(Z)Lorg/jboss/as/controller/AbstractAttributeDefinitionBuilder;
    2525: checkcast     #2                  // class org/jboss/as/controller/SimpleAttributeDefinitionBuilder
    2528: invokevirtual #11                 // Method org/jboss/as/controller/SimpleAttributeDefinitionBuilder.build:()Lorg/jboss/as/controller/SimpleAttributeDefinition;
    2531: putstatic     #216                // Field RECOVERLUGIN_CLASSNAME:Lorg/jboss/as/controller/SimpleAttributeDefinition;
    2534: new           #217                // class org/jboss/as/controller/PropertiesAttributeDefinition$Builder
    2537: dup
    2538: ldc           #218                // String recovery-plugin-properties
    2540: iconst_1
    2541: invokespecial #219                // Method org/jboss/as/controller/PropertiesAttributeDefinition$Builder."<init>":(Ljava/lang/String;Z)V
    2544: iconst_1
    2545: invokevirtual #220                // Method org/jboss/as/controller/PropertiesAttributeDefinition$Builder.setAllowExpression:(Z)Lorg/jboss/as/controller/AbstractAttributeDefinitionBuilder;
    2548: checkcast     #217                // class org/jboss/as/controller/PropertiesAttributeDefinition$Builder
    2551: getstatic     #221                // Field org/jboss/jca/common/api/metadata/common/Extension$Tag.CONFIG_PROPERTY:Lorg/jboss/jca/common/api/metadata/common/Extension$Tag;
    2554: invokevirtual #222                // Method org/jboss/jca/common/api/metadata/common/Extension$Tag.getLocalName:()Ljava/lang/String;
    2557: invokevirtual #223                // Method org/jboss/as/controller/PropertiesAttributeDefinition$Builder.setXmlName:(Ljava/lang/String;)Lorg/jboss/as/controller/PropertiesAttributeDefinition$Builder;
    2560: invokevirtual #224                // Method org/jboss/as/controller/PropertiesAttributeDefinition$Builder.build:()Lorg/jboss/as/controller/PropertiesAttributeDefinition;
    2563: putstatic     #225                // Field RECOVERLUGIN_PROPERTIES:Lorg/jboss/as/controller/PropertiesAttributeDefinition;
    2566: new           #2                  // class org/jboss/as/controller/SimpleAttributeDefinitionBuilder
    2569: dup
    2570: ldc           #226                // String work-active
    2572: getstatic     #145                // Field org/jboss/dmr/ModelType.INT:Lorg/jboss/dmr/ModelType;
    2575: invokespecial #54                 // Method org/jboss/as/controller/SimpleAttributeDefinitionBuilder."<init>":(Ljava/lang/String;Lorg/jboss/dmr/ModelType;)V
    2578: invokevirtual #227                // Method org/jboss/as/controller/SimpleAttributeDefinitionBuilder.setStorageRuntime:()Lorg/jboss/as/controller/AbstractAttributeDefinitionBuilder;
    2581: checkcast     #2                  // class org/jboss/as/controller/SimpleAttributeDefinitionBuilder
    2584: new           #55                 // class org/jboss/dmr/ModelNode
    2587: dup
    2588: iconst_0
    2589: invokespecial #228                // Method org/jboss/dmr/ModelNode."<init>":(I)V
    2592: invokevirtual #229                // Method org/jboss/as/controller/SimpleAttributeDefinitionBuilder.setUndefinedMetricValue:(Lorg/jboss/dmr/ModelNode;)Lorg/jboss/as/controller/AbstractAttributeDefinitionBuilder;
    2595: checkcast     #2                  // class org/jboss/as/controller/SimpleAttributeDefinitionBuilder
    2598: invokevirtual #11                 // Method org/jboss/as/controller/SimpleAttributeDefinitionBuilder.build:()Lorg/jboss/as/controller/SimpleAttributeDefinition;
    2601: putstatic     #230                // Field WORK_ACTIVE:Lorg/jboss/as/controller/SimpleAttributeDefinition;
    2604: new           #2                  // class org/jboss/as/controller/SimpleAttributeDefinitionBuilder
    2607: dup
    2608: ldc           #231                // String work-successful
    2610: getstatic     #145                // Field org/jboss/dmr/ModelType.INT:Lorg/jboss/dmr/ModelType;
    2613: invokespecial #54                 // Method org/jboss/as/controller/SimpleAttributeDefinitionBuilder."<init>":(Ljava/lang/String;Lorg/jboss/dmr/ModelType;)V
    2616: invokevirtual #227                // Method org/jboss/as/controller/SimpleAttributeDefinitionBuilder.setStorageRuntime:()Lorg/jboss/as/controller/AbstractAttributeDefinitionBuilder;
    2619: checkcast     #2                  // class org/jboss/as/controller/SimpleAttributeDefinitionBuilder
    2622: new           #55                 // class org/jboss/dmr/ModelNode
    2625: dup
    2626: iconst_0
    2627: invokespecial #228                // Method org/jboss/dmr/ModelNode."<init>":(I)V
    2630: invokevirtual #229                // Method org/jboss/as/controller/SimpleAttributeDefinitionBuilder.setUndefinedMetricValue:(Lorg/jboss/dmr/ModelNode;)Lorg/jboss/as/controller/AbstractAttributeDefinitionBuilder;
    2633: checkcast     #2                  // class org/jboss/as/controller/SimpleAttributeDefinitionBuilder
    2636: invokevirtual #11                 // Method org/jboss/as/controller/SimpleAttributeDefinitionBuilder.build:()Lorg/jboss/as/controller/SimpleAttributeDefinition;
    2639: putstatic     #232                // Field WORK_SUCCESSFUL:Lorg/jboss/as/controller/SimpleAttributeDefinition;
    2642: new           #2                  // class org/jboss/as/controller/SimpleAttributeDefinitionBuilder
    2645: dup
    2646: ldc           #233                // String work-failed
    2648: getstatic     #145                // Field org/jboss/dmr/ModelType.INT:Lorg/jboss/dmr/ModelType;
    2651: invokespecial #54                 // Method org/jboss/as/controller/SimpleAttributeDefinitionBuilder."<init>":(Ljava/lang/String;Lorg/jboss/dmr/ModelType;)V
    2654: invokevirtual #227                // Method org/jboss/as/controller/SimpleAttributeDefinitionBuilder.setStorageRuntime:()Lorg/jboss/as/controller/AbstractAttributeDefinitionBuilder;
    2657: checkcast     #2                  // class org/jboss/as/controller/SimpleAttributeDefinitionBuilder
    2660: new           #55                 // class org/jboss/dmr/ModelNode
    2663: dup
    2664: iconst_0
    2665: invokespecial #228                // Method org/jboss/dmr/ModelNode."<init>":(I)V
    2668: invokevirtual #229                // Method org/jboss/as/controller/SimpleAttributeDefinitionBuilder.setUndefinedMetricValue:(Lorg/jboss/dmr/ModelNode;)Lorg/jboss/as/controller/AbstractAttributeDefinitionBuilder;
    2671: checkcast     #2                  // class org/jboss/as/controller/SimpleAttributeDefinitionBuilder
    2674: invokevirtual #11                 // Method org/jboss/as/controller/SimpleAttributeDefinitionBuilder.build:()Lorg/jboss/as/controller/SimpleAttributeDefinition;
    2677: putstatic     #234                // Field WORK_FAILED:Lorg/jboss/as/controller/SimpleAttributeDefinition;
    2680: new           #2                  // class org/jboss/as/controller/SimpleAttributeDefinitionBuilder
    2683: dup
    2684: ldc           #235                // String dowork-accepted
    2686: getstatic     #145                // Field org/jboss/dmr/ModelType.INT:Lorg/jboss/dmr/ModelType;
    2689: invokespecial #54                 // Method org/jboss/as/controller/SimpleAttributeDefinitionBuilder."<init>":(Ljava/lang/String;Lorg/jboss/dmr/ModelType;)V
    2692: invokevirtual #227                // Method org/jboss/as/controller/SimpleAttributeDefinitionBuilder.setStorageRuntime:()Lorg/jboss/as/controller/AbstractAttributeDefinitionBuilder;
    2695: checkcast     #2                  // class org/jboss/as/controller/SimpleAttributeDefinitionBuilder
    2698: new           #55                 // class org/jboss/dmr/ModelNode
    2701: dup
    2702: iconst_0
    2703: invokespecial #228                // Method org/jboss/dmr/ModelNode."<init>":(I)V
    2706: invokevirtual #229                // Method org/jboss/as/controller/SimpleAttributeDefinitionBuilder.setUndefinedMetricValue:(Lorg/jboss/dmr/ModelNode;)Lorg/jboss/as/controller/AbstractAttributeDefinitionBuilder;
    2709: checkcast     #2                  // class org/jboss/as/controller/SimpleAttributeDefinitionBuilder
    2712: invokevirtual #11                 // Method org/jboss/as/controller/SimpleAttributeDefinitionBuilder.build:()Lorg/jboss/as/controller/SimpleAttributeDefinition;
    2715: putstatic     #236                // Field DO_WORK_ACCEPTED:Lorg/jboss/as/controller/SimpleAttributeDefinition;
    2718: new           #2                  // class org/jboss/as/controller/SimpleAttributeDefinitionBuilder
    2721: dup
    2722: ldc           #237                // String dowork-rejected
    2724: getstatic     #145                // Field org/jboss/dmr/ModelType.INT:Lorg/jboss/dmr/ModelType;
    2727: invokespecial #54                 // Method org/jboss/as/controller/SimpleAttributeDefinitionBuilder."<init>":(Ljava/lang/String;Lorg/jboss/dmr/ModelType;)V
    2730: invokevirtual #227                // Method org/jboss/as/controller/SimpleAttributeDefinitionBuilder.setStorageRuntime:()Lorg/jboss/as/controller/AbstractAttributeDefinitionBuilder;
    2733: checkcast     #2                  // class org/jboss/as/controller/SimpleAttributeDefinitionBuilder
    2736: new           #55                 // class org/jboss/dmr/ModelNode
    2739: dup
    2740: iconst_0
    2741: invokespecial #228                // Method org/jboss/dmr/ModelNode."<init>":(I)V
    2744: invokevirtual #229                // Method org/jboss/as/controller/SimpleAttributeDefinitionBuilder.setUndefinedMetricValue:(Lorg/jboss/dmr/ModelNode;)Lorg/jboss/as/controller/AbstractAttributeDefinitionBuilder;
    2747: checkcast     #2                  // class org/jboss/as/controller/SimpleAttributeDefinitionBuilder
    2750: invokevirtual #11                 // Method org/jboss/as/controller/SimpleAttributeDefinitionBuilder.build:()Lorg/jboss/as/controller/SimpleAttributeDefinition;
    2753: putstatic     #238                // Field DO_WORK_REJECTED:Lorg/jboss/as/controller/SimpleAttributeDefinition;
    2756: new           #2                  // class org/jboss/as/controller/SimpleAttributeDefinitionBuilder
    2759: dup
    2760: ldc           #239                // String schedulework-accepted
    2762: getstatic     #145                // Field org/jboss/dmr/ModelType.INT:Lorg/jboss/dmr/ModelType;
    2765: invokespecial #54                 // Method org/jboss/as/controller/SimpleAttributeDefinitionBuilder."<init>":(Ljava/lang/String;Lorg/jboss/dmr/ModelType;)V
    2768: invokevirtual #227                // Method org/jboss/as/controller/SimpleAttributeDefinitionBuilder.setStorageRuntime:()Lorg/jboss/as/controller/AbstractAttributeDefinitionBuilder;
    2771: checkcast     #2                  // class org/jboss/as/controller/SimpleAttributeDefinitionBuilder
    2774: new           #55                 // class org/jboss/dmr/ModelNode
    2777: dup
    2778: iconst_0
    2779: invokespecial #228                // Method org/jboss/dmr/ModelNode."<init>":(I)V
    2782: invokevirtual #229                // Method org/jboss/as/controller/SimpleAttributeDefinitionBuilder.setUndefinedMetricValue:(Lorg/jboss/dmr/ModelNode;)Lorg/jboss/as/controller/AbstractAttributeDefinitionBuilder;
    2785: checkcast     #2                  // class org/jboss/as/controller/SimpleAttributeDefinitionBuilder
    2788: invokevirtual #11                 // Method org/jboss/as/controller/SimpleAttributeDefinitionBuilder.build:()Lorg/jboss/as/controller/SimpleAttributeDefinition;
    2791: putstatic     #240                // Field SCHEDULED_WORK_ACCEPTED:Lorg/jboss/as/controller/SimpleAttributeDefinition;
    2794: new           #2                  // class org/jboss/as/controller/SimpleAttributeDefinitionBuilder
    2797: dup
    2798: ldc           #241                // String schedulework-rejected
    2800: getstatic     #145                // Field org/jboss/dmr/ModelType.INT:Lorg/jboss/dmr/ModelType;
    2803: invokespecial #54                 // Method org/jboss/as/controller/SimpleAttributeDefinitionBuilder."<init>":(Ljava/lang/String;Lorg/jboss/dmr/ModelType;)V
    2806: invokevirtual #227                // Method org/jboss/as/controller/SimpleAttributeDefinitionBuilder.setStorageRuntime:()Lorg/jboss/as/controller/AbstractAttributeDefinitionBuilder;
    2809: checkcast     #2                  // class org/jboss/as/controller/SimpleAttributeDefinitionBuilder
    2812: new           #55                 // class org/jboss/dmr/ModelNode
    2815: dup
    2816: iconst_0
    2817: invokespecial #228                // Method org/jboss/dmr/ModelNode."<init>":(I)V
    2820: invokevirtual #229                // Method org/jboss/as/controller/SimpleAttributeDefinitionBuilder.setUndefinedMetricValue:(Lorg/jboss/dmr/ModelNode;)Lorg/jboss/as/controller/AbstractAttributeDefinitionBuilder;
    2823: checkcast     #2                  // class org/jboss/as/controller/SimpleAttributeDefinitionBuilder
    2826: invokevirtual #11                 // Method org/jboss/as/controller/SimpleAttributeDefinitionBuilder.build:()Lorg/jboss/as/controller/SimpleAttributeDefinition;
    2829: putstatic     #242                // Field SCHEDULED_WORK_REJECTED:Lorg/jboss/as/controller/SimpleAttributeDefinition;
    2832: new           #2                  // class org/jboss/as/controller/SimpleAttributeDefinitionBuilder
    2835: dup
    2836: ldc           #243                // String startwork-accepted
    2838: getstatic     #145                // Field org/jboss/dmr/ModelType.INT:Lorg/jboss/dmr/ModelType;
    2841: invokespecial #54                 // Method org/jboss/as/controller/SimpleAttributeDefinitionBuilder."<init>":(Ljava/lang/String;Lorg/jboss/dmr/ModelType;)V
    2844: invokevirtual #227                // Method org/jboss/as/controller/SimpleAttributeDefinitionBuilder.setStorageRuntime:()Lorg/jboss/as/controller/AbstractAttributeDefinitionBuilder;
    2847: checkcast     #2                  // class org/jboss/as/controller/SimpleAttributeDefinitionBuilder
    2850: new           #55                 // class org/jboss/dmr/ModelNode
    2853: dup
    2854: iconst_0
    2855: invokespecial #228                // Method org/jboss/dmr/ModelNode."<init>":(I)V
    2858: invokevirtual #229                // Method org/jboss/as/controller/SimpleAttributeDefinitionBuilder.setUndefinedMetricValue:(Lorg/jboss/dmr/ModelNode;)Lorg/jboss/as/controller/AbstractAttributeDefinitionBuilder;
    2861: checkcast     #2                  // class org/jboss/as/controller/SimpleAttributeDefinitionBuilder
    2864: invokevirtual #11                 // Method org/jboss/as/controller/SimpleAttributeDefinitionBuilder.build:()Lorg/jboss/as/controller/SimpleAttributeDefinition;
    2867: putstatic     #244                // Field START_WORK_ACCEPTED:Lorg/jboss/as/controller/SimpleAttributeDefinition;
    2870: new           #2                  // class org/jboss/as/controller/SimpleAttributeDefinitionBuilder
    2873: dup
    2874: ldc           #245                // String startwork-rejected
    2876: getstatic     #145                // Field org/jboss/dmr/ModelType.INT:Lorg/jboss/dmr/ModelType;
    2879: invokespecial #54                 // Method org/jboss/as/controller/SimpleAttributeDefinitionBuilder."<init>":(Ljava/lang/String;Lorg/jboss/dmr/ModelType;)V
    2882: invokevirtual #227                // Method org/jboss/as/controller/SimpleAttributeDefinitionBuilder.setStorageRuntime:()Lorg/jboss/as/controller/AbstractAttributeDefinitionBuilder;
    2885: checkcast     #2                  // class org/jboss/as/controller/SimpleAttributeDefinitionBuilder
    2888: new           #55                 // class org/jboss/dmr/ModelNode
    2891: dup
    2892: iconst_0
    2893: invokespecial #228                // Method org/jboss/dmr/ModelNode."<init>":(I)V
    2896: invokevirtual #229                // Method org/jboss/as/controller/SimpleAttributeDefinitionBuilder.setUndefinedMetricValue:(Lorg/jboss/dmr/ModelNode;)Lorg/jboss/as/controller/AbstractAttributeDefinitionBuilder;
    2899: checkcast     #2                  // class org/jboss/as/controller/SimpleAttributeDefinitionBuilder
    2902: invokevirtual #11                 // Method org/jboss/as/controller/SimpleAttributeDefinitionBuilder.build:()Lorg/jboss/as/controller/SimpleAttributeDefinition;
    2905: putstatic     #246                // Field START_WORK_REJECTED:Lorg/jboss/as/controller/SimpleAttributeDefinition;
    2908: bipush        9
    2910: anewarray     #247                // class org/jboss/as/controller/SimpleAttributeDefinition
    2913: dup
    2914: iconst_0
    2915: getstatic     #230                // Field WORK_ACTIVE:Lorg/jboss/as/controller/SimpleAttributeDefinition;
    2918: aastore
    2919: dup
    2920: iconst_1
    2921: getstatic     #232                // Field WORK_SUCCESSFUL:Lorg/jboss/as/controller/SimpleAttributeDefinition;
    2924: aastore
    2925: dup
    2926: iconst_2
    2927: getstatic     #234                // Field WORK_FAILED:Lorg/jboss/as/controller/SimpleAttributeDefinition;
    2930: aastore
    2931: dup
    2932: iconst_3
    2933: getstatic     #236                // Field DO_WORK_ACCEPTED:Lorg/jboss/as/controller/SimpleAttributeDefinition;
    2936: aastore
    2937: dup
    2938: iconst_4
    2939: getstatic     #238                // Field DO_WORK_REJECTED:Lorg/jboss/as/controller/SimpleAttributeDefinition;
    2942: aastore
    2943: dup
    2944: iconst_5
    2945: getstatic     #240                // Field SCHEDULED_WORK_ACCEPTED:Lorg/jboss/as/controller/SimpleAttributeDefinition;
    2948: aastore
    2949: dup
    2950: bipush        6
    2952: getstatic     #242                // Field SCHEDULED_WORK_REJECTED:Lorg/jboss/as/controller/SimpleAttributeDefinition;
    2955: aastore
    2956: dup
    2957: bipush        7
    2959: getstatic     #244                // Field START_WORK_ACCEPTED:Lorg/jboss/as/controller/SimpleAttributeDefinition;
    2962: aastore
    2963: dup
    2964: bipush        8
    2966: getstatic     #246                // Field START_WORK_REJECTED:Lorg/jboss/as/controller/SimpleAttributeDefinition;
    2969: aastore
    2970: putstatic     #248                // Field WORKMANAGER_METRICS:[Lorg/jboss/as/controller/SimpleAttributeDefinition;
    2973: new           #2                  // class org/jboss/as/controller/SimpleAttributeDefinitionBuilder
    2976: dup
    2977: ldc           #52                 // String statistics-enabled
    2979: getstatic     #53                 // Field org/jboss/dmr/ModelType.BOOLEAN:Lorg/jboss/dmr/ModelType;
    2982: invokespecial #54                 // Method org/jboss/as/controller/SimpleAttributeDefinitionBuilder."<init>":(Ljava/lang/String;Lorg/jboss/dmr/ModelType;)V
    2985: invokevirtual #227                // Method org/jboss/as/controller/SimpleAttributeDefinitionBuilder.setStorageRuntime:()Lorg/jboss/as/controller/AbstractAttributeDefinitionBuilder;
    2988: checkcast     #2                  // class org/jboss/as/controller/SimpleAttributeDefinitionBuilder
    2991: invokevirtual #11                 // Method org/jboss/as/controller/SimpleAttributeDefinitionBuilder.build:()Lorg/jboss/as/controller/SimpleAttributeDefinition;
    2994: putstatic     #249                // Field WORKMANAGER_STATISTICS_ENABLED:Lorg/jboss/as/controller/SimpleAttributeDefinition;
    2997: new           #2                  // class org/jboss/as/controller/SimpleAttributeDefinitionBuilder
    3000: dup
    3001: ldc           #250                // String workmanager-statistics-enabled
    3003: getstatic     #53                 // Field org/jboss/dmr/ModelType.BOOLEAN:Lorg/jboss/dmr/ModelType;
    3006: invokespecial #54                 // Method org/jboss/as/controller/SimpleAttributeDefinitionBuilder."<init>":(Ljava/lang/String;Lorg/jboss/dmr/ModelType;)V
    3009: invokevirtual #227                // Method org/jboss/as/controller/SimpleAttributeDefinitionBuilder.setStorageRuntime:()Lorg/jboss/as/controller/AbstractAttributeDefinitionBuilder;
    3012: checkcast     #2                  // class org/jboss/as/controller/SimpleAttributeDefinitionBuilder
    3015: iconst_2
    3016: invokestatic  #251                // Method org/jboss/as/controller/ModelVersion.create:(I)Lorg/jboss/as/controller/ModelVersion;
    3019: invokevirtual #252                // Method org/jboss/as/controller/SimpleAttributeDefinitionBuilder.setDeprecated:(Lorg/jboss/as/controller/ModelVersion;)Lorg/jboss/as/controller/AbstractAttributeDefinitionBuilder;
    3022: checkcast     #2                  // class org/jboss/as/controller/SimpleAttributeDefinitionBuilder
    3025: invokevirtual #11                 // Method org/jboss/as/controller/SimpleAttributeDefinitionBuilder.build:()Lorg/jboss/as/controller/SimpleAttributeDefinition;
    3028: putstatic     #253                // Field WORKMANAGER_STATISTICS_ENABLED_DEPRECATED:Lorg/jboss/as/controller/SimpleAttributeDefinition;
    3031: new           #2                  // class org/jboss/as/controller/SimpleAttributeDefinitionBuilder
    3034: dup
    3035: ldc           #52                 // String statistics-enabled
    3037: getstatic     #53                 // Field org/jboss/dmr/ModelType.BOOLEAN:Lorg/jboss/dmr/ModelType;
    3040: invokespecial #54                 // Method org/jboss/as/controller/SimpleAttributeDefinitionBuilder."<init>":(Ljava/lang/String;Lorg/jboss/dmr/ModelType;)V
    3043: invokevirtual #227                // Method org/jboss/as/controller/SimpleAttributeDefinitionBuilder.setStorageRuntime:()Lorg/jboss/as/controller/AbstractAttributeDefinitionBuilder;
    3046: checkcast     #2                  // class org/jboss/as/controller/SimpleAttributeDefinitionBuilder
    3049: invokevirtual #11                 // Method org/jboss/as/controller/SimpleAttributeDefinitionBuilder.build:()Lorg/jboss/as/controller/SimpleAttributeDefinition;
    3052: putstatic     #254                // Field DISTRIBUTED_STATISTICS_ENABLED:Lorg/jboss/as/controller/SimpleAttributeDefinition;
    3055: new           #2                  // class org/jboss/as/controller/SimpleAttributeDefinitionBuilder
    3058: dup
    3059: ldc           #255                // String distributed-workmanager-statistics-enabled
    3061: getstatic     #53                 // Field org/jboss/dmr/ModelType.BOOLEAN:Lorg/jboss/dmr/ModelType;
    3064: invokespecial #54                 // Method org/jboss/as/controller/SimpleAttributeDefinitionBuilder."<init>":(Ljava/lang/String;Lorg/jboss/dmr/ModelType;)V
    3067: invokevirtual #227                // Method org/jboss/as/controller/SimpleAttributeDefinitionBuilder.setStorageRuntime:()Lorg/jboss/as/controller/AbstractAttributeDefinitionBuilder;
    3070: checkcast     #2                  // class org/jboss/as/controller/SimpleAttributeDefinitionBuilder
    3073: iconst_2
    3074: invokestatic  #251                // Method org/jboss/as/controller/ModelVersion.create:(I)Lorg/jboss/as/controller/ModelVersion;
    3077: invokevirtual #252                // Method org/jboss/as/controller/SimpleAttributeDefinitionBuilder.setDeprecated:(Lorg/jboss/as/controller/ModelVersion;)Lorg/jboss/as/controller/AbstractAttributeDefinitionBuilder;
    3080: checkcast     #2                  // class org/jboss/as/controller/SimpleAttributeDefinitionBuilder
    3083: invokevirtual #11                 // Method org/jboss/as/controller/SimpleAttributeDefinitionBuilder.build:()Lorg/jboss/as/controller/SimpleAttributeDefinition;
    3086: putstatic     #256                // Field DISTRIBUTED_STATISTICS_ENABLED_DEPRECATED:Lorg/jboss/as/controller/SimpleAttributeDefinition;
    3089: new           #2                  // class org/jboss/as/controller/SimpleAttributeDefinitionBuilder
    3092: dup
    3093: ldc_w         #257                // String dowork-distribution-enabled
    3096: getstatic     #53                 // Field org/jboss/dmr/ModelType.BOOLEAN:Lorg/jboss/dmr/ModelType;
    3099: invokespecial #54                 // Method org/jboss/as/controller/SimpleAttributeDefinitionBuilder."<init>":(Ljava/lang/String;Lorg/jboss/dmr/ModelType;)V
    3102: invokevirtual #227                // Method org/jboss/as/controller/SimpleAttributeDefinitionBuilder.setStorageRuntime:()Lorg/jboss/as/controller/AbstractAttributeDefinitionBuilder;
    3105: checkcast     #2                  // class org/jboss/as/controller/SimpleAttributeDefinitionBuilder
    3108: invokevirtual #11                 // Method org/jboss/as/controller/SimpleAttributeDefinitionBuilder.build:()Lorg/jboss/as/controller/SimpleAttributeDefinition;
    3111: putstatic     #258                // Field DOWORK_DISTRIBUTION_ENABLED:Lorg/jboss/as/controller/SimpleAttributeDefinition;
    3114: new           #2                  // class org/jboss/as/controller/SimpleAttributeDefinitionBuilder
    3117: dup
    3118: ldc_w         #259                // String schedulework-distribution-enabled
    3121: getstatic     #53                 // Field org/jboss/dmr/ModelType.BOOLEAN:Lorg/jboss/dmr/ModelType;
    3124: invokespecial #54                 // Method org/jboss/as/controller/SimpleAttributeDefinitionBuilder."<init>":(Ljava/lang/String;Lorg/jboss/dmr/ModelType;)V
    3127: invokevirtual #227                // Method org/jboss/as/controller/SimpleAttributeDefinitionBuilder.setStorageRuntime:()Lorg/jboss/as/controller/AbstractAttributeDefinitionBuilder;
    3130: checkcast     #2                  // class org/jboss/as/controller/SimpleAttributeDefinitionBuilder
    3133: invokevirtual #11                 // Method org/jboss/as/controller/SimpleAttributeDefinitionBuilder.build:()Lorg/jboss/as/controller/SimpleAttributeDefinition;
    3136: putstatic     #260                // Field SCHEDULEWORK_DISTRIBUTION_ENABLED:Lorg/jboss/as/controller/SimpleAttributeDefinition;
    3139: new           #2                  // class org/jboss/as/controller/SimpleAttributeDefinitionBuilder
    3142: dup
    3143: ldc_w         #261                // String startwork-distribution-enabled
    3146: getstatic     #53                 // Field org/jboss/dmr/ModelType.BOOLEAN:Lorg/jboss/dmr/ModelType;
    3149: invokespecial #54                 // Method org/jboss/as/controller/SimpleAttributeDefinitionBuilder."<init>":(Ljava/lang/String;Lorg/jboss/dmr/ModelType;)V
    3152: invokevirtual #227                // Method org/jboss/as/controller/SimpleAttributeDefinitionBuilder.setStorageRuntime:()Lorg/jboss/as/controller/AbstractAttributeDefinitionBuilder;
    3155: checkcast     #2                  // class org/jboss/as/controller/SimpleAttributeDefinitionBuilder
    3158: invokevirtual #11                 // Method org/jboss/as/controller/SimpleAttributeDefinitionBuilder.build:()Lorg/jboss/as/controller/SimpleAttributeDefinition;
    3161: putstatic     #262                // Field STARTWORK_DISTRIBUTION_ENABLED:Lorg/jboss/as/controller/SimpleAttributeDefinition;
    3164: iconst_2
    3165: anewarray     #247                // class org/jboss/as/controller/SimpleAttributeDefinition
    3168: dup
    3169: iconst_0
    3170: getstatic     #249                // Field WORKMANAGER_STATISTICS_ENABLED:Lorg/jboss/as/controller/SimpleAttributeDefinition;
    3173: aastore
    3174: dup
    3175: iconst_1
    3176: getstatic     #253                // Field WORKMANAGER_STATISTICS_ENABLED_DEPRECATED:Lorg/jboss/as/controller/SimpleAttributeDefinition;
    3179: aastore
    3180: putstatic     #263                // Field WORKMANAGER_RW_ATTRIBUTES:[Lorg/jboss/as/controller/SimpleAttributeDefinition;
    3183: iconst_5
    3184: anewarray     #247                // class org/jboss/as/controller/SimpleAttributeDefinition
    3187: dup
    3188: iconst_0
    3189: getstatic     #254                // Field DISTRIBUTED_STATISTICS_ENABLED:Lorg/jboss/as/controller/SimpleAttributeDefinition;
    3192: aastore
    3193: dup
    3194: iconst_1
    3195: getstatic     #256                // Field DISTRIBUTED_STATISTICS_ENABLED_DEPRECATED:Lorg/jboss/as/controller/SimpleAttributeDefinition;
    3198: aastore
    3199: dup
    3200: iconst_2
    3201: getstatic     #258                // Field DOWORK_DISTRIBUTION_ENABLED:Lorg/jboss/as/controller/SimpleAttributeDefinition;
    3204: aastore
    3205: dup
    3206: iconst_3
    3207: getstatic     #260                // Field SCHEDULEWORK_DISTRIBUTION_ENABLED:Lorg/jboss/as/controller/SimpleAttributeDefinition;
    3210: aastore
    3211: dup
    3212: iconst_4
    3213: getstatic     #262                // Field STARTWORK_DISTRIBUTION_ENABLED:Lorg/jboss/as/controller/SimpleAttributeDefinition;
    3216: aastore
    3217: putstatic     #264                // Field DISTRIBUTED_WORKMANAGER_RW_ATTRIBUTES:[Lorg/jboss/as/controller/SimpleAttributeDefinition;
    3220: return
}
