Compiled from "ModifiableResourceAdapter.java"
public class org.jboss.as.connector.subsystems.resourceadapters.ModifiableResourceAdapter extends org.jboss.jca.common.metadata.resourceadapter.ActivationImpl {
  private volatile org.jboss.msc.service.ServiceName raXmlDeploymentServiceName;

  public org.jboss.as.connector.subsystems.resourceadapters.ModifiableResourceAdapter(java.lang.String, java.lang.String, org.jboss.jca.common.api.metadata.common.TransactionSupportEnum, java.util.List<org.jboss.jca.common.api.metadata.resourceadapter.ConnectionDefinition>, java.util.List<org.jboss.jca.common.api.metadata.resourceadapter.AdminObject>, java.util.Map<java.lang.String, java.lang.String>, java.util.List<java.lang.String>, java.lang.String, org.jboss.jca.common.api.metadata.resourceadapter.WorkManager);
    Code:
       0: aload_0
       1: aload_1
       2: aload_2
       3: aload_3
       4: aload         4
       6: aload         5
       8: aload         6
      10: aload         7
      12: aload         8
      14: aload         9
      16: invokespecial #1                  // Method org/jboss/jca/common/metadata/resourceadapter/ActivationImpl."<init>":(Ljava/lang/String;Ljava/lang/String;Lorg/jboss/jca/common/api/metadata/common/TransactionSupportEnum;Ljava/util/List;Ljava/util/List;Ljava/util/Map;Ljava/util/List;Ljava/lang/String;Lorg/jboss/jca/common/api/metadata/resourceadapter/WorkManager;)V
      19: aload_0
      20: aconst_null
      21: putfield      #2                  // Field raXmlDeploymentServiceName:Lorg/jboss/msc/service/ServiceName;
      24: return

  public synchronized void addConfigProperty(java.lang.String, java.lang.String);
    Code:
       0: aload_0
       1: getfield      #3                  // Field configProperties:Ljava/util/Map;
       4: aload_1
       5: aload_2
       6: invokeinterface #4,  3            // InterfaceMethod java/util/Map.put:(Ljava/lang/Object;Ljava/lang/Object;)Ljava/lang/Object;
      11: pop
      12: return

  public synchronized void addConnectionDefinition(org.jboss.jca.common.api.metadata.resourceadapter.ConnectionDefinition);
    Code:
       0: aload_0
       1: getfield      #5                  // Field connectionDefinitions:Ljava/util/List;
       4: aload_1
       5: invokeinterface #6,  2            // InterfaceMethod java/util/List.add:(Ljava/lang/Object;)Z
      10: pop
      11: return

  public synchronized int connectionDefinitionSize();
    Code:
       0: aload_0
       1: getfield      #5                  // Field connectionDefinitions:Ljava/util/List;
       4: invokeinterface #7,  1            // InterfaceMethod java/util/List.size:()I
       9: ireturn

  public synchronized void addAdminObject(org.jboss.jca.common.api.metadata.resourceadapter.AdminObject);
    Code:
       0: aload_0
       1: getfield      #8                  // Field adminObjects:Ljava/util/List;
       4: aload_1
       5: invokeinterface #6,  2            // InterfaceMethod java/util/List.add:(Ljava/lang/Object;)Z
      10: pop
      11: return

  public synchronized int adminObjectSize();
    Code:
       0: aload_0
       1: getfield      #8                  // Field adminObjects:Ljava/util/List;
       4: invokeinterface #7,  1            // InterfaceMethod java/util/List.size:()I
       9: ireturn

  public org.jboss.msc.service.ServiceName getRaXmlDeploymentServiceName();
    Code:
       0: aload_0
       1: getfield      #2                  // Field raXmlDeploymentServiceName:Lorg/jboss/msc/service/ServiceName;
       4: areturn

  public void setRaXmlDeploymentServiceName(org.jboss.msc.service.ServiceName);
    Code:
       0: aload_0
       1: aload_1
       2: putfield      #2                  // Field raXmlDeploymentServiceName:Lorg/jboss/msc/service/ServiceName;
       5: return
}
