Compiled from "EagerLoadingTestCase.java"
public class org.wso2.carbon.esb.eager.loading.EagerLoadingTestCase extends org.wso2.esb.integration.common.utils.ESBIntegrationTest {
  private org.wso2.esb.integration.common.utils.common.ServerConfigurationManager serverManager;

  private org.wso2.carbon.integration.common.admin.client.LogViewerClient logViewerClient;

  public org.wso2.carbon.esb.eager.loading.EagerLoadingTestCase();
    Code:
       0: aload_0
       1: invokespecial #1                  // Method org/wso2/esb/integration/common/utils/ESBIntegrationTest."<init>":()V
       4: aload_0
       5: aconst_null
       6: putfield      #2                  // Field serverManager:Lorg/wso2/esb/integration/common/utils/common/ServerConfigurationManager;
       9: return

  protected void startServerWithEagerLoading() throws java.lang.Exception;
    Code:
       0: aload_0
       1: getstatic     #3                  // Field org/wso2/carbon/automation/engine/context/TestUserMode.SUPER_TENANT_USER:Lorg/wso2/carbon/automation/engine/context/TestUserMode;
       4: invokespecial #4                  // Method org/wso2/esb/integration/common/utils/ESBIntegrationTest.init:(Lorg/wso2/carbon/automation/engine/context/TestUserMode;)V
       7: aload_0
       8: new           #5                  // class org/wso2/esb/integration/common/utils/common/ServerConfigurationManager
      11: dup
      12: aload_0
      13: getfield      #6                  // Field context:Lorg/wso2/carbon/automation/engine/context/AutomationContext;
      16: invokespecial #7                  // Method org/wso2/esb/integration/common/utils/common/ServerConfigurationManager."<init>":(Lorg/wso2/carbon/automation/engine/context/AutomationContext;)V
      19: putfield      #2                  // Field serverManager:Lorg/wso2/esb/integration/common/utils/common/ServerConfigurationManager;
      22: new           #8                  // class org/wso2/carbon/automation/engine/context/AutomationContext
      25: dup
      26: invokespecial #9                  // Method org/wso2/carbon/automation/engine/context/AutomationContext."<init>":()V
      29: astore_1
      30: new           #10                 // class java/io/File
      33: dup
      34: new           #11                 // class java/lang/StringBuilder
      37: dup
      38: invokespecial #12                 // Method java/lang/StringBuilder."<init>":()V
      41: invokestatic  #13                 // Method org/wso2/carbon/automation/engine/frameworkutils/FrameworkPathUtil.getSystemResourceLocation:()Ljava/lang/String;
      44: invokevirtual #14                 // Method java/lang/StringBuilder.append:(Ljava/lang/String;)Ljava/lang/StringBuilder;
      47: ldc           #15                 // String /artifacts/ESB/eager/loading/ESBJAVA3602-FaultySeq.xml
      49: invokevirtual #14                 // Method java/lang/StringBuilder.append:(Ljava/lang/String;)Ljava/lang/StringBuilder;
      52: invokevirtual #16                 // Method java/lang/StringBuilder.toString:()Ljava/lang/String;
      55: invokespecial #17                 // Method java/io/File."<init>":(Ljava/lang/String;)V
      58: aload_0
      59: invokevirtual #18                 // Method getSynapseDeploymentDir:()Ljava/io/File;
      62: invokestatic  #19                 // Method org/apache/commons/io/FileUtils.copyFileToDirectory:(Ljava/io/File;Ljava/io/File;)V
      65: new           #10                 // class java/io/File
      68: dup
      69: new           #11                 // class java/lang/StringBuilder
      72: dup
      73: invokespecial #12                 // Method java/lang/StringBuilder."<init>":()V
      76: invokestatic  #13                 // Method org/wso2/carbon/automation/engine/frameworkutils/FrameworkPathUtil.getSystemResourceLocation:()Ljava/lang/String;
      79: invokevirtual #14                 // Method java/lang/StringBuilder.append:(Ljava/lang/String;)Ljava/lang/StringBuilder;
      82: ldc           #20                 // String /artifacts/ESB/eager/loading/ESBJAVA3602Carbon.xml
      84: invokevirtual #14                 // Method java/lang/StringBuilder.append:(Ljava/lang/String;)Ljava/lang/StringBuilder;
      87: invokevirtual #16                 // Method java/lang/StringBuilder.toString:()Ljava/lang/String;
      90: invokespecial #17                 // Method java/io/File."<init>":(Ljava/lang/String;)V
      93: astore_2
      94: aload_0
      95: getfield      #2                  // Field serverManager:Lorg/wso2/esb/integration/common/utils/common/ServerConfigurationManager;
      98: aload_2
      99: aload_0
     100: invokevirtual #21                 // Method getCarbonXmlFile:()Ljava/io/File;
     103: invokevirtual #22                 // Method org/wso2/esb/integration/common/utils/common/ServerConfigurationManager.applyConfiguration:(Ljava/io/File;Ljava/io/File;)V
     106: aload_0
     107: getstatic     #23                 // Field org/wso2/carbon/automation/engine/context/TestUserMode.TENANT_ADMIN:Lorg/wso2/carbon/automation/engine/context/TestUserMode;
     110: invokespecial #4                  // Method org/wso2/esb/integration/common/utils/ESBIntegrationTest.init:(Lorg/wso2/carbon/automation/engine/context/TestUserMode;)V
     113: aload_0
     114: new           #24                 // class org/wso2/carbon/integration/common/admin/client/LogViewerClient
     117: dup
     118: aload_0
     119: getfield      #25                 // Field contextUrls:Lorg/wso2/carbon/automation/engine/context/beans/ContextUrls;
     122: invokevirtual #26                 // Method org/wso2/carbon/automation/engine/context/beans/ContextUrls.getBackEndUrl:()Ljava/lang/String;
     125: aload_0
     126: invokevirtual #27                 // Method getSessionCookie:()Ljava/lang/String;
     129: invokespecial #28                 // Method org/wso2/carbon/integration/common/admin/client/LogViewerClient."<init>":(Ljava/lang/String;Ljava/lang/String;)V
     132: putfield      #29                 // Field logViewerClient:Lorg/wso2/carbon/integration/common/admin/client/LogViewerClient;
     135: return

  public void testStartupLogs() throws java.lang.Exception;
    Code:
       0: aload_0
       1: getfield      #29                 // Field logViewerClient:Lorg/wso2/carbon/integration/common/admin/client/LogViewerClient;
       4: invokevirtual #30                 // Method org/wso2/carbon/integration/common/admin/client/LogViewerClient.getAllSystemLogs:()[Lorg/wso2/carbon/logging/view/stub/types/carbon/LogEvent;
       7: astore_1
       8: aload_1
       9: ldc           #31                 // String No logs found
      11: invokestatic  #32                 // Method org/testng/Assert.assertNotNull:(Ljava/lang/Object;Ljava/lang/String;)V
      14: aload_1
      15: arraylength
      16: ifle          23
      19: iconst_1
      20: goto          24
      23: iconst_0
      24: ldc           #31                 // String No logs found
      26: invokestatic  #33                 // Method org/testng/Assert.assertTrue:(ZLjava/lang/String;)V
      29: iconst_0
      30: istore_2
      31: iconst_0
      32: istore_3
      33: aload_1
      34: arraylength
      35: ifle          103
      38: iconst_0
      39: istore        4
      41: iload         4
      43: aload_1
      44: arraylength
      45: if_icmpge     91
      48: aload_1
      49: iload         4
      51: aaload
      52: invokevirtual #34                 // Method org/wso2/carbon/logging/view/stub/types/carbon/LogEvent.getMessage:()Ljava/lang/String;
      55: ldc           #35                 // String Using tenant eager loading policy
      57: invokevirtual #36                 // Method java/lang/String.contains:(Ljava/lang/CharSequence;)Z
      60: ifeq          68
      63: iconst_1
      64: istore_3
      65: goto          85
      68: aload_1
      69: iload         4
      71: aaload
      72: invokevirtual #34                 // Method org/wso2/carbon/logging/view/stub/types/carbon/LogEvent.getMessage:()Ljava/lang/String;
      75: ldc           #37                 // String WSO2 Carbon started in
      77: invokevirtual #36                 // Method java/lang/String.contains:(Ljava/lang/CharSequence;)Z
      80: ifeq          85
      83: iconst_1
      84: istore_2
      85: iinc          4, 1
      88: goto          41
      91: iload_3
      92: ldc           #38                 // String Server was not started with Tenant Eager Loading enabled.
      94: invokestatic  #33                 // Method org/testng/Assert.assertTrue:(ZLjava/lang/String;)V
      97: iload_2
      98: ldc           #39                 // String Server start-up failed with Tenant Eager Loading enabled.
     100: invokestatic  #33                 // Method org/testng/Assert.assertTrue:(ZLjava/lang/String;)V
     103: return

  public void restoreSettings() throws java.lang.Exception;
    Code:
       0: aload_0
       1: getfield      #2                  // Field serverManager:Lorg/wso2/esb/integration/common/utils/common/ServerConfigurationManager;
       4: invokevirtual #40                 // Method org/wso2/esb/integration/common/utils/common/ServerConfigurationManager.restoreToLastConfiguration:()V
       7: return

  public java.io.File getCarbonXmlFile();
    Code:
       0: ldc           #41                 // String carbon.home
       2: invokestatic  #42                 // Method java/lang/System.getProperty:(Ljava/lang/String;)Ljava/lang/String;
       5: astore_1
       6: new           #10                 // class java/io/File
       9: dup
      10: new           #11                 // class java/lang/StringBuilder
      13: dup
      14: invokespecial #12                 // Method java/lang/StringBuilder."<init>":()V
      17: aload_1
      18: invokevirtual #14                 // Method java/lang/StringBuilder.append:(Ljava/lang/String;)Ljava/lang/StringBuilder;
      21: getstatic     #43                 // Field java/io/File.separator:Ljava/lang/String;
      24: invokevirtual #14                 // Method java/lang/StringBuilder.append:(Ljava/lang/String;)Ljava/lang/StringBuilder;
      27: ldc           #44                 // String repository
      29: invokevirtual #14                 // Method java/lang/StringBuilder.append:(Ljava/lang/String;)Ljava/lang/StringBuilder;
      32: getstatic     #43                 // Field java/io/File.separator:Ljava/lang/String;
      35: invokevirtual #14                 // Method java/lang/StringBuilder.append:(Ljava/lang/String;)Ljava/lang/StringBuilder;
      38: ldc           #45                 // String conf
      40: invokevirtual #14                 // Method java/lang/StringBuilder.append:(Ljava/lang/String;)Ljava/lang/StringBuilder;
      43: getstatic     #43                 // Field java/io/File.separator:Ljava/lang/String;
      46: invokevirtual #14                 // Method java/lang/StringBuilder.append:(Ljava/lang/String;)Ljava/lang/StringBuilder;
      49: ldc           #46                 // String carbon.xml
      51: invokevirtual #14                 // Method java/lang/StringBuilder.append:(Ljava/lang/String;)Ljava/lang/StringBuilder;
      54: invokevirtual #16                 // Method java/lang/StringBuilder.toString:()Ljava/lang/String;
      57: invokespecial #17                 // Method java/io/File."<init>":(Ljava/lang/String;)V
      60: astore_2
      61: aload_2
      62: areturn

  public java.io.File getSynapseDeploymentDir();
    Code:
       0: ldc           #41                 // String carbon.home
       2: invokestatic  #42                 // Method java/lang/System.getProperty:(Ljava/lang/String;)Ljava/lang/String;
       5: astore_1
       6: new           #10                 // class java/io/File
       9: dup
      10: new           #11                 // class java/lang/StringBuilder
      13: dup
      14: invokespecial #12                 // Method java/lang/StringBuilder."<init>":()V
      17: aload_1
      18: invokevirtual #14                 // Method java/lang/StringBuilder.append:(Ljava/lang/String;)Ljava/lang/StringBuilder;
      21: getstatic     #43                 // Field java/io/File.separator:Ljava/lang/String;
      24: invokevirtual #14                 // Method java/lang/StringBuilder.append:(Ljava/lang/String;)Ljava/lang/StringBuilder;
      27: ldc           #44                 // String repository
      29: invokevirtual #14                 // Method java/lang/StringBuilder.append:(Ljava/lang/String;)Ljava/lang/StringBuilder;
      32: getstatic     #43                 // Field java/io/File.separator:Ljava/lang/String;
      35: invokevirtual #14                 // Method java/lang/StringBuilder.append:(Ljava/lang/String;)Ljava/lang/StringBuilder;
      38: ldc           #47                 // String deployment
      40: invokevirtual #14                 // Method java/lang/StringBuilder.append:(Ljava/lang/String;)Ljava/lang/StringBuilder;
      43: getstatic     #43                 // Field java/io/File.separator:Ljava/lang/String;
      46: invokevirtual #14                 // Method java/lang/StringBuilder.append:(Ljava/lang/String;)Ljava/lang/StringBuilder;
      49: ldc           #48                 // String server/synapse-configs/default/sequences
      51: invokevirtual #14                 // Method java/lang/StringBuilder.append:(Ljava/lang/String;)Ljava/lang/StringBuilder;
      54: invokevirtual #16                 // Method java/lang/StringBuilder.toString:()Ljava/lang/String;
      57: invokespecial #17                 // Method java/io/File."<init>":(Ljava/lang/String;)V
      60: astore_2
      61: aload_2
      62: areturn
}
