Compiled from "AbstractStandardExpressionAttributeTagProcessor.java"
public abstract class org.thymeleaf.standard.processor.AbstractStandardExpressionAttributeTagProcessor extends org.thymeleaf.processor.element.AbstractAttributeTagProcessor {
  private final org.thymeleaf.standard.expression.StandardExpressionExecutionContext expressionExecutionContext;

  private final boolean removeIfNoop;

  protected org.thymeleaf.standard.processor.AbstractStandardExpressionAttributeTagProcessor(org.thymeleaf.templatemode.TemplateMode, java.lang.String, java.lang.String, int, boolean);
    Code:
       0: aload_0
       1: aload_1
       2: aload_2
       3: aload_3
       4: iload         4
       6: iload         5
       8: getstatic     #1                  // Field org/thymeleaf/standard/expression/StandardExpressionExecutionContext.NORMAL:Lorg/thymeleaf/standard/expression/StandardExpressionExecutionContext;
      11: invokespecial #2                  // Method "<init>":(Lorg/thymeleaf/templatemode/TemplateMode;Ljava/lang/String;Ljava/lang/String;IZLorg/thymeleaf/standard/expression/StandardExpressionExecutionContext;)V
      14: return

  protected org.thymeleaf.standard.processor.AbstractStandardExpressionAttributeTagProcessor(org.thymeleaf.templatemode.TemplateMode, java.lang.String, java.lang.String, int, boolean, boolean);
    Code:
       0: aload_0
       1: aload_1
       2: aload_2
       3: aload_3
       4: iload         4
       6: iload         5
       8: iload         6
      10: ifeq          19
      13: getstatic     #3                  // Field org/thymeleaf/standard/expression/StandardExpressionExecutionContext.RESTRICTED:Lorg/thymeleaf/standard/expression/StandardExpressionExecutionContext;
      16: goto          22
      19: getstatic     #1                  // Field org/thymeleaf/standard/expression/StandardExpressionExecutionContext.NORMAL:Lorg/thymeleaf/standard/expression/StandardExpressionExecutionContext;
      22: invokespecial #2                  // Method "<init>":(Lorg/thymeleaf/templatemode/TemplateMode;Ljava/lang/String;Ljava/lang/String;IZLorg/thymeleaf/standard/expression/StandardExpressionExecutionContext;)V
      25: return

  protected org.thymeleaf.standard.processor.AbstractStandardExpressionAttributeTagProcessor(org.thymeleaf.templatemode.TemplateMode, java.lang.String, java.lang.String, int, boolean, org.thymeleaf.standard.expression.StandardExpressionExecutionContext);
    Code:
       0: aload_0
       1: aload_1
       2: aload_2
       3: aconst_null
       4: iconst_0
       5: aload_3
       6: iconst_1
       7: iload         4
       9: iload         5
      11: invokespecial #4                  // Method org/thymeleaf/processor/element/AbstractAttributeTagProcessor."<init>":(Lorg/thymeleaf/templatemode/TemplateMode;Ljava/lang/String;Ljava/lang/String;ZLjava/lang/String;ZIZ)V
      14: aload_0
      15: iload         5
      17: ifne          24
      20: iconst_1
      21: goto          25
      24: iconst_0
      25: putfield      #5                  // Field removeIfNoop:Z
      28: aload_0
      29: aload         6
      31: putfield      #6                  // Field expressionExecutionContext:Lorg/thymeleaf/standard/expression/StandardExpressionExecutionContext;
      34: return

  protected final void doProcess(org.thymeleaf.context.ITemplateContext, org.thymeleaf.model.IProcessableElementTag, org.thymeleaf.engine.AttributeName, java.lang.String, org.thymeleaf.processor.element.IElementTagStructureHandler);
    Code:
       0: aload         4
       2: ifnull        68
       5: aload_1
       6: aload_2
       7: aload_3
       8: aload         4
      10: invokestatic  #7                  // Method org/thymeleaf/engine/EngineEventUtils.computeAttributeExpression:(Lorg/thymeleaf/context/ITemplateContext;Lorg/thymeleaf/model/IProcessableElementTag;Lorg/thymeleaf/engine/AttributeName;Ljava/lang/String;)Lorg/thymeleaf/standard/expression/IStandardExpression;
      13: astore        7
      15: aload         7
      17: ifnull        51
      20: aload         7
      22: instanceof    #8                  // class org/thymeleaf/standard/expression/FragmentExpression
      25: ifeq          51
      28: aload_1
      29: aload         7
      31: checkcast     #8                  // class org/thymeleaf/standard/expression/FragmentExpression
      34: invokestatic  #9                  // Method org/thymeleaf/standard/expression/FragmentExpression.createExecutedFragmentExpression:(Lorg/thymeleaf/context/IExpressionContext;Lorg/thymeleaf/standard/expression/FragmentExpression;)Lorg/thymeleaf/standard/expression/FragmentExpression$ExecutedFragmentExpression;
      37: astore        8
      39: aload_1
      40: aload         8
      42: iconst_1
      43: invokestatic  #10                 // Method org/thymeleaf/standard/expression/FragmentExpression.resolveExecutedFragmentExpression:(Lorg/thymeleaf/context/ITemplateContext;Lorg/thymeleaf/standard/expression/FragmentExpression$ExecutedFragmentExpression;Z)Lorg/thymeleaf/standard/expression/Fragment;
      46: astore        6
      48: goto          65
      51: aload         7
      53: aload_1
      54: aload_0
      55: getfield      #6                  // Field expressionExecutionContext:Lorg/thymeleaf/standard/expression/StandardExpressionExecutionContext;
      58: invokeinterface #11,  3           // InterfaceMethod org/thymeleaf/standard/expression/IStandardExpression.execute:(Lorg/thymeleaf/context/IExpressionContext;Lorg/thymeleaf/standard/expression/StandardExpressionExecutionContext;)Ljava/lang/Object;
      63: astore        6
      65: goto          71
      68: aconst_null
      69: astore        6
      71: aload         6
      73: getstatic     #12                 // Field org/thymeleaf/standard/expression/NoOpToken.VALUE:Lorg/thymeleaf/standard/expression/NoOpToken;
      76: if_acmpne     95
      79: aload_0
      80: getfield      #5                  // Field removeIfNoop:Z
      83: ifeq          94
      86: aload         5
      88: aload_3
      89: invokeinterface #13,  2           // InterfaceMethod org/thymeleaf/processor/element/IElementTagStructureHandler.removeAttribute:(Lorg/thymeleaf/engine/AttributeName;)V
      94: return
      95: aload_0
      96: aload_1
      97: aload_2
      98: aload_3
      99: aload         4
     101: aload         6
     103: aload         5
     105: invokevirtual #14                 // Method doProcess:(Lorg/thymeleaf/context/ITemplateContext;Lorg/thymeleaf/model/IProcessableElementTag;Lorg/thymeleaf/engine/AttributeName;Ljava/lang/String;Ljava/lang/Object;Lorg/thymeleaf/processor/element/IElementTagStructureHandler;)V
     108: return

  protected abstract void doProcess(org.thymeleaf.context.ITemplateContext, org.thymeleaf.model.IProcessableElementTag, org.thymeleaf.engine.AttributeName, java.lang.String, java.lang.Object, org.thymeleaf.processor.element.IElementTagStructureHandler);
}
