Compiled from "StandardIncludeTagProcessor.java"
public final class org.thymeleaf.standard.processor.StandardIncludeTagProcessor extends org.thymeleaf.standard.processor.AbstractStandardFragmentInsertionTagProcessor {
  public static final int PRECEDENCE;

  public static final java.lang.String ATTR_NAME;

  public org.thymeleaf.standard.processor.StandardIncludeTagProcessor(org.thymeleaf.templatemode.TemplateMode, java.lang.String);
    Code:
       0: aload_0
       1: aload_1
       2: aload_2
       3: ldc           #2                  // String include
       5: bipush        100
       7: iconst_0
       8: iconst_1
       9: invokespecial #3                  // Method org/thymeleaf/standard/processor/AbstractStandardFragmentInsertionTagProcessor."<init>":(Lorg/thymeleaf/templatemode/TemplateMode;Ljava/lang/String;Ljava/lang/String;IZZ)V
      12: return
}
