Compiled from "ExecutionSpecificParameters.java"
public class io.lettuce.core.dynamic.parameter.ExecutionSpecificParameters extends io.lettuce.core.dynamic.parameter.Parameters<io.lettuce.core.dynamic.parameter.ExecutionSpecificParameters$ExecutionAwareParameter> {
  private static final java.util.List<java.lang.Class<?>> TYPES;

  private final int timeoutIndex;

  private final int commandBatchingIndex;

  public io.lettuce.core.dynamic.parameter.ExecutionSpecificParameters(java.lang.reflect.Method);
    Code:
       0: aload_0
       1: aload_1
       2: invokespecial #2                  // Method io/lettuce/core/dynamic/parameter/Parameters."<init>":(Ljava/lang/reflect/Method;)V
       5: iconst_m1
       6: istore_2
       7: iconst_m1
       8: istore_3
       9: aload_0
      10: invokevirtual #3                  // Method getParameters:()Ljava/util/List;
      13: astore        4
      15: iconst_0
      16: istore        5
      18: iload         5
      20: aload_1
      21: invokevirtual #4                  // Method java/lang/reflect/Method.getParameterCount:()I
      24: if_icmpge     81
      27: aload         4
      29: iload         5
      31: invokeinterface #5,  2            // InterfaceMethod java/util/List.get:(I)Ljava/lang/Object;
      36: checkcast     #6                  // class io/lettuce/core/dynamic/parameter/Parameter
      39: astore        6
      41: aload         6
      43: invokevirtual #7                  // Method io/lettuce/core/dynamic/parameter/Parameter.isSpecialParameter:()Z
      46: ifeq          75
      49: aload         6
      51: ldc           #8                  // class io/lettuce/core/dynamic/domain/Timeout
      53: invokevirtual #9                  // Method io/lettuce/core/dynamic/parameter/Parameter.isAssignableTo:(Ljava/lang/Class;)Z
      56: ifeq          62
      59: iload         5
      61: istore_2
      62: aload         6
      64: ldc           #10                 // class io/lettuce/core/dynamic/batch/CommandBatching
      66: invokevirtual #9                  // Method io/lettuce/core/dynamic/parameter/Parameter.isAssignableTo:(Ljava/lang/Class;)Z
      69: ifeq          75
      72: iload         5
      74: istore_3
      75: iinc          5, 1
      78: goto          18
      81: aload_0
      82: iload_2
      83: putfield      #11                 // Field timeoutIndex:I
      86: aload_0
      87: iload_3
      88: putfield      #12                 // Field commandBatchingIndex:I
      91: return

  public int getTimeoutIndex();
    Code:
       0: aload_0
       1: getfield      #11                 // Field timeoutIndex:I
       4: ireturn

  public int getCommandBatchingIndex();
    Code:
       0: aload_0
       1: getfield      #12                 // Field commandBatchingIndex:I
       4: ireturn

  protected io.lettuce.core.dynamic.parameter.ExecutionSpecificParameters$ExecutionAwareParameter createParameter(java.lang.reflect.Method, int);
    Code:
       0: new           #13                 // class io/lettuce/core/dynamic/parameter/ExecutionSpecificParameters$ExecutionAwareParameter
       3: dup
       4: aload_1
       5: iload_2
       6: invokespecial #14                 // Method io/lettuce/core/dynamic/parameter/ExecutionSpecificParameters$ExecutionAwareParameter."<init>":(Ljava/lang/reflect/Method;I)V
       9: areturn

  public boolean hasCommandBatchingIndex();
    Code:
       0: aload_0
       1: getfield      #12                 // Field commandBatchingIndex:I
       4: iconst_m1
       5: if_icmpeq     12
       8: iconst_1
       9: goto          13
      12: iconst_0
      13: ireturn

  public boolean hasTimeoutIndex();
    Code:
       0: aload_0
       1: invokevirtual #15                 // Method getTimeoutIndex:()I
       4: iconst_m1
       5: if_icmpeq     12
       8: iconst_1
       9: goto          13
      12: iconst_0
      13: ireturn

  protected io.lettuce.core.dynamic.parameter.Parameter createParameter(java.lang.reflect.Method, int);
    Code:
       0: aload_0
       1: aload_1
       2: iload_2
       3: invokevirtual #16                 // Method createParameter:(Ljava/lang/reflect/Method;I)Lio/lettuce/core/dynamic/parameter/ExecutionSpecificParameters$ExecutionAwareParameter;
       6: areturn

  static java.util.List access$000();
    Code:
       0: getstatic     #1                  // Field TYPES:Ljava/util/List;
       3: areturn

  static {};
    Code:
       0: iconst_2
       1: anewarray     #17                 // class java/lang/Class
       4: dup
       5: iconst_0
       6: ldc           #8                  // class io/lettuce/core/dynamic/domain/Timeout
       8: aastore
       9: dup
      10: iconst_1
      11: ldc           #10                 // class io/lettuce/core/dynamic/batch/CommandBatching
      13: aastore
      14: invokestatic  #18                 // Method java/util/Arrays.asList:([Ljava/lang/Object;)Ljava/util/List;
      17: putstatic     #1                  // Field TYPES:Ljava/util/List;
      20: return
}
