Compiled from "JvmXml.java"
class org.jboss.as.host.controller.parsing.JvmXml$1 {
  static final int[] $SwitchMap$org$jboss$as$controller$parsing$Attribute;

  static final int[] $SwitchMap$org$jboss$as$controller$parsing$Element;

  static {};
    Code:
       0: invokestatic  #1                  // Method org/jboss/as/controller/parsing/Element.values:()[Lorg/jboss/as/controller/parsing/Element;
       3: arraylength
       4: newarray       int
       6: putstatic     #2                  // Field $SwitchMap$org$jboss$as$controller$parsing$Element:[I
       9: getstatic     #2                  // Field $SwitchMap$org$jboss$as$controller$parsing$Element:[I
      12: getstatic     #3                  // Field org/jboss/as/controller/parsing/Element.HEAP:Lorg/jboss/as/controller/parsing/Element;
      15: invokevirtual #4                  // Method org/jboss/as/controller/parsing/Element.ordinal:()I
      18: iconst_1
      19: iastore
      20: goto          24
      23: astore_0
      24: getstatic     #2                  // Field $SwitchMap$org$jboss$as$controller$parsing$Element:[I
      27: getstatic     #6                  // Field org/jboss/as/controller/parsing/Element.PERMGEN:Lorg/jboss/as/controller/parsing/Element;
      30: invokevirtual #4                  // Method org/jboss/as/controller/parsing/Element.ordinal:()I
      33: iconst_2
      34: iastore
      35: goto          39
      38: astore_0
      39: getstatic     #2                  // Field $SwitchMap$org$jboss$as$controller$parsing$Element:[I
      42: getstatic     #7                  // Field org/jboss/as/controller/parsing/Element.STACK:Lorg/jboss/as/controller/parsing/Element;
      45: invokevirtual #4                  // Method org/jboss/as/controller/parsing/Element.ordinal:()I
      48: iconst_3
      49: iastore
      50: goto          54
      53: astore_0
      54: getstatic     #2                  // Field $SwitchMap$org$jboss$as$controller$parsing$Element:[I
      57: getstatic     #8                  // Field org/jboss/as/controller/parsing/Element.AGENT_LIB:Lorg/jboss/as/controller/parsing/Element;
      60: invokevirtual #4                  // Method org/jboss/as/controller/parsing/Element.ordinal:()I
      63: iconst_4
      64: iastore
      65: goto          69
      68: astore_0
      69: getstatic     #2                  // Field $SwitchMap$org$jboss$as$controller$parsing$Element:[I
      72: getstatic     #9                  // Field org/jboss/as/controller/parsing/Element.AGENT_PATH:Lorg/jboss/as/controller/parsing/Element;
      75: invokevirtual #4                  // Method org/jboss/as/controller/parsing/Element.ordinal:()I
      78: iconst_5
      79: iastore
      80: goto          84
      83: astore_0
      84: getstatic     #2                  // Field $SwitchMap$org$jboss$as$controller$parsing$Element:[I
      87: getstatic     #10                 // Field org/jboss/as/controller/parsing/Element.JAVA_AGENT:Lorg/jboss/as/controller/parsing/Element;
      90: invokevirtual #4                  // Method org/jboss/as/controller/parsing/Element.ordinal:()I
      93: bipush        6
      95: iastore
      96: goto          100
      99: astore_0
     100: getstatic     #2                  // Field $SwitchMap$org$jboss$as$controller$parsing$Element:[I
     103: getstatic     #11                 // Field org/jboss/as/controller/parsing/Element.ENVIRONMENT_VARIABLES:Lorg/jboss/as/controller/parsing/Element;
     106: invokevirtual #4                  // Method org/jboss/as/controller/parsing/Element.ordinal:()I
     109: bipush        7
     111: iastore
     112: goto          116
     115: astore_0
     116: getstatic     #2                  // Field $SwitchMap$org$jboss$as$controller$parsing$Element:[I
     119: getstatic     #12                 // Field org/jboss/as/controller/parsing/Element.JVM_OPTIONS:Lorg/jboss/as/controller/parsing/Element;
     122: invokevirtual #4                  // Method org/jboss/as/controller/parsing/Element.ordinal:()I
     125: bipush        8
     127: iastore
     128: goto          132
     131: astore_0
     132: getstatic     #2                  // Field $SwitchMap$org$jboss$as$controller$parsing$Element:[I
     135: getstatic     #13                 // Field org/jboss/as/controller/parsing/Element.LAUNCH_COMMAND:Lorg/jboss/as/controller/parsing/Element;
     138: invokevirtual #4                  // Method org/jboss/as/controller/parsing/Element.ordinal:()I
     141: bipush        9
     143: iastore
     144: goto          148
     147: astore_0
     148: invokestatic  #14                 // Method org/jboss/as/controller/parsing/Attribute.values:()[Lorg/jboss/as/controller/parsing/Attribute;
     151: arraylength
     152: newarray       int
     154: putstatic     #15                 // Field $SwitchMap$org$jboss$as$controller$parsing$Attribute:[I
     157: getstatic     #15                 // Field $SwitchMap$org$jboss$as$controller$parsing$Attribute:[I
     160: getstatic     #16                 // Field org/jboss/as/controller/parsing/Attribute.NAME:Lorg/jboss/as/controller/parsing/Attribute;
     163: invokevirtual #17                 // Method org/jboss/as/controller/parsing/Attribute.ordinal:()I
     166: iconst_1
     167: iastore
     168: goto          172
     171: astore_0
     172: getstatic     #15                 // Field $SwitchMap$org$jboss$as$controller$parsing$Attribute:[I
     175: getstatic     #18                 // Field org/jboss/as/controller/parsing/Attribute.JAVA_HOME:Lorg/jboss/as/controller/parsing/Attribute;
     178: invokevirtual #17                 // Method org/jboss/as/controller/parsing/Attribute.ordinal:()I
     181: iconst_2
     182: iastore
     183: goto          187
     186: astore_0
     187: getstatic     #15                 // Field $SwitchMap$org$jboss$as$controller$parsing$Attribute:[I
     190: getstatic     #19                 // Field org/jboss/as/controller/parsing/Attribute.TYPE:Lorg/jboss/as/controller/parsing/Attribute;
     193: invokevirtual #17                 // Method org/jboss/as/controller/parsing/Attribute.ordinal:()I
     196: iconst_3
     197: iastore
     198: goto          202
     201: astore_0
     202: getstatic     #15                 // Field $SwitchMap$org$jboss$as$controller$parsing$Attribute:[I
     205: getstatic     #20                 // Field org/jboss/as/controller/parsing/Attribute.DEBUG_ENABLED:Lorg/jboss/as/controller/parsing/Attribute;
     208: invokevirtual #17                 // Method org/jboss/as/controller/parsing/Attribute.ordinal:()I
     211: iconst_4
     212: iastore
     213: goto          217
     216: astore_0
     217: getstatic     #15                 // Field $SwitchMap$org$jboss$as$controller$parsing$Attribute:[I
     220: getstatic     #21                 // Field org/jboss/as/controller/parsing/Attribute.DEBUG_OPTIONS:Lorg/jboss/as/controller/parsing/Attribute;
     223: invokevirtual #17                 // Method org/jboss/as/controller/parsing/Attribute.ordinal:()I
     226: iconst_5
     227: iastore
     228: goto          232
     231: astore_0
     232: getstatic     #15                 // Field $SwitchMap$org$jboss$as$controller$parsing$Attribute:[I
     235: getstatic     #22                 // Field org/jboss/as/controller/parsing/Attribute.ENV_CLASSPATH_IGNORED:Lorg/jboss/as/controller/parsing/Attribute;
     238: invokevirtual #17                 // Method org/jboss/as/controller/parsing/Attribute.ordinal:()I
     241: bipush        6
     243: iastore
     244: goto          248
     247: astore_0
     248: getstatic     #15                 // Field $SwitchMap$org$jboss$as$controller$parsing$Attribute:[I
     251: getstatic     #23                 // Field org/jboss/as/controller/parsing/Attribute.SIZE:Lorg/jboss/as/controller/parsing/Attribute;
     254: invokevirtual #17                 // Method org/jboss/as/controller/parsing/Attribute.ordinal:()I
     257: bipush        7
     259: iastore
     260: goto          264
     263: astore_0
     264: getstatic     #15                 // Field $SwitchMap$org$jboss$as$controller$parsing$Attribute:[I
     267: getstatic     #24                 // Field org/jboss/as/controller/parsing/Attribute.MAX_SIZE:Lorg/jboss/as/controller/parsing/Attribute;
     270: invokevirtual #17                 // Method org/jboss/as/controller/parsing/Attribute.ordinal:()I
     273: bipush        8
     275: iastore
     276: goto          280
     279: astore_0
     280: getstatic     #15                 // Field $SwitchMap$org$jboss$as$controller$parsing$Attribute:[I
     283: getstatic     #25                 // Field org/jboss/as/controller/parsing/Attribute.VALUE:Lorg/jboss/as/controller/parsing/Attribute;
     286: invokevirtual #17                 // Method org/jboss/as/controller/parsing/Attribute.ordinal:()I
     289: bipush        9
     291: iastore
     292: goto          296
     295: astore_0
     296: getstatic     #15                 // Field $SwitchMap$org$jboss$as$controller$parsing$Attribute:[I
     299: getstatic     #26                 // Field org/jboss/as/controller/parsing/Attribute.PREFIX:Lorg/jboss/as/controller/parsing/Attribute;
     302: invokevirtual #17                 // Method org/jboss/as/controller/parsing/Attribute.ordinal:()I
     305: bipush        10
     307: iastore
     308: goto          312
     311: astore_0
     312: return
    Exception table:
       from    to  target type
           9    20    23   Class java/lang/NoSuchFieldError
          24    35    38   Class java/lang/NoSuchFieldError
          39    50    53   Class java/lang/NoSuchFieldError
          54    65    68   Class java/lang/NoSuchFieldError
          69    80    83   Class java/lang/NoSuchFieldError
          84    96    99   Class java/lang/NoSuchFieldError
         100   112   115   Class java/lang/NoSuchFieldError
         116   128   131   Class java/lang/NoSuchFieldError
         132   144   147   Class java/lang/NoSuchFieldError
         157   168   171   Class java/lang/NoSuchFieldError
         172   183   186   Class java/lang/NoSuchFieldError
         187   198   201   Class java/lang/NoSuchFieldError
         202   213   216   Class java/lang/NoSuchFieldError
         217   228   231   Class java/lang/NoSuchFieldError
         232   244   247   Class java/lang/NoSuchFieldError
         248   260   263   Class java/lang/NoSuchFieldError
         264   276   279   Class java/lang/NoSuchFieldError
         280   292   295   Class java/lang/NoSuchFieldError
         296   308   311   Class java/lang/NoSuchFieldError
}
