Compiled from "Joiner.java"
class com.google.api.client.repackaged.com.google.common.base.Joiner$1 extends com.google.api.client.repackaged.com.google.common.base.Joiner {
  final java.lang.String val$nullText;

  final com.google.api.client.repackaged.com.google.common.base.Joiner this$0;

  com.google.api.client.repackaged.com.google.common.base.Joiner$1(com.google.api.client.repackaged.com.google.common.base.Joiner, com.google.api.client.repackaged.com.google.common.base.Joiner, java.lang.String);
    Code:
       0: aload_0
       1: aload_1
       2: putfield      #16                 // Field this$0:Lcom/google/api/client/repackaged/com/google/common/base/Joiner;
       5: aload_0
       6: aload_3
       7: putfield      #18                 // Field val$nullText:Ljava/lang/String;
      10: aload_0
      11: aload_2
      12: aconst_null
      13: invokespecial #21                 // Method com/google/api/client/repackaged/com/google/common/base/Joiner."<init>":(Lcom/google/api/client/repackaged/com/google/common/base/Joiner;Lcom/google/api/client/repackaged/com/google/common/base/Joiner$1;)V
      16: return

  java.lang.CharSequence toString(java.lang.Object);
    Code:
       0: aload_1
       1: ifnonnull     11
       4: aload_0
       5: getfield      #18                 // Field val$nullText:Ljava/lang/String;
       8: goto          19
      11: aload_0
      12: getfield      #16                 // Field this$0:Lcom/google/api/client/repackaged/com/google/common/base/Joiner;
      15: aload_1
      16: invokevirtual #29                 // Method com/google/api/client/repackaged/com/google/common/base/Joiner.toString:(Ljava/lang/Object;)Ljava/lang/CharSequence;
      19: areturn

  public com.google.api.client.repackaged.com.google.common.base.Joiner useForNull(java.lang.String);
    Code:
       0: new           #33                 // class java/lang/UnsupportedOperationException
       3: dup
       4: ldc           #35                 // String already specified useForNull
       6: invokespecial #38                 // Method java/lang/UnsupportedOperationException."<init>":(Ljava/lang/String;)V
       9: athrow

  public com.google.api.client.repackaged.com.google.common.base.Joiner skipNulls();
    Code:
       0: new           #33                 // class java/lang/UnsupportedOperationException
       3: dup
       4: ldc           #35                 // String already specified useForNull
       6: invokespecial #38                 // Method java/lang/UnsupportedOperationException."<init>":(Ljava/lang/String;)V
       9: athrow
}
