Compiled from "JdbcArray.java"
public class org.h2.jdbc.JdbcArray extends org.h2.message.TraceObject implements java.sql.Array {
  private org.h2.value.Value value;

  private final org.h2.jdbc.JdbcConnection conn;

  public org.h2.jdbc.JdbcArray(org.h2.jdbc.JdbcConnection, org.h2.value.Value, int);
    Code:
       0: aload_0
       1: invokespecial #1                  // Method org/h2/message/TraceObject."<init>":()V
       4: aload_0
       5: aload_1
       6: invokevirtual #2                  // Method org/h2/jdbc/JdbcConnection.getSession:()Lorg/h2/engine/SessionInterface;
       9: invokeinterface #3,  1            // InterfaceMethod org/h2/engine/SessionInterface.getTrace:()Lorg/h2/message/Trace;
      14: bipush        16
      16: iload_3
      17: invokevirtual #4                  // Method setTrace:(Lorg/h2/message/Trace;II)V
      20: aload_0
      21: aload_1
      22: putfield      #5                  // Field conn:Lorg/h2/jdbc/JdbcConnection;
      25: aload_0
      26: aload_2
      27: putfield      #6                  // Field value:Lorg/h2/value/Value;
      30: return

  public java.lang.Object getArray() throws java.sql.SQLException;
    Code:
       0: aload_0
       1: ldc           #7                  // String getArray
       3: invokevirtual #8                  // Method debugCodeCall:(Ljava/lang/String;)V
       6: aload_0
       7: invokespecial #9                  // Method checkClosed:()V
      10: aload_0
      11: invokespecial #10                 // Method get:()[Ljava/lang/Object;
      14: areturn
      15: astore_1
      16: aload_0
      17: aload_1
      18: invokevirtual #12                 // Method logAndConvert:(Ljava/lang/Throwable;)Ljava/sql/SQLException;
      21: athrow
    Exception table:
       from    to  target type
           0    14    15   Class java/lang/Exception

  public java.lang.Object getArray(java.util.Map<java.lang.String, java.lang.Class<?>>) throws java.sql.SQLException;
    Code:
       0: aload_0
       1: invokevirtual #13                 // Method isDebugEnabled:()Z
       4: ifeq          38
       7: aload_0
       8: new           #14                 // class java/lang/StringBuilder
      11: dup
      12: invokespecial #15                 // Method java/lang/StringBuilder."<init>":()V
      15: ldc           #16                 // String getArray(
      17: invokevirtual #17                 // Method java/lang/StringBuilder.append:(Ljava/lang/String;)Ljava/lang/StringBuilder;
      20: aload_1
      21: invokestatic  #18                 // Method quoteMap:(Ljava/util/Map;)Ljava/lang/String;
      24: invokevirtual #17                 // Method java/lang/StringBuilder.append:(Ljava/lang/String;)Ljava/lang/StringBuilder;
      27: ldc           #19                 // String );
      29: invokevirtual #17                 // Method java/lang/StringBuilder.append:(Ljava/lang/String;)Ljava/lang/StringBuilder;
      32: invokevirtual #20                 // Method java/lang/StringBuilder.toString:()Ljava/lang/String;
      35: invokevirtual #21                 // Method debugCode:(Ljava/lang/String;)V
      38: aload_1
      39: invokestatic  #22                 // Method org/h2/jdbc/JdbcConnection.checkMap:(Ljava/util/Map;)V
      42: aload_0
      43: invokespecial #9                  // Method checkClosed:()V
      46: aload_0
      47: invokespecial #10                 // Method get:()[Ljava/lang/Object;
      50: areturn
      51: astore_2
      52: aload_0
      53: aload_2
      54: invokevirtual #12                 // Method logAndConvert:(Ljava/lang/Throwable;)Ljava/sql/SQLException;
      57: athrow
    Exception table:
       from    to  target type
           0    50    51   Class java/lang/Exception

  public java.lang.Object getArray(long, int) throws java.sql.SQLException;
    Code:
       0: aload_0
       1: invokevirtual #13                 // Method isDebugEnabled:()Z
       4: ifeq          44
       7: aload_0
       8: new           #14                 // class java/lang/StringBuilder
      11: dup
      12: invokespecial #15                 // Method java/lang/StringBuilder."<init>":()V
      15: ldc           #16                 // String getArray(
      17: invokevirtual #17                 // Method java/lang/StringBuilder.append:(Ljava/lang/String;)Ljava/lang/StringBuilder;
      20: lload_1
      21: invokevirtual #23                 // Method java/lang/StringBuilder.append:(J)Ljava/lang/StringBuilder;
      24: ldc           #24                 // String ,
      26: invokevirtual #17                 // Method java/lang/StringBuilder.append:(Ljava/lang/String;)Ljava/lang/StringBuilder;
      29: iload_3
      30: invokevirtual #25                 // Method java/lang/StringBuilder.append:(I)Ljava/lang/StringBuilder;
      33: ldc           #19                 // String );
      35: invokevirtual #17                 // Method java/lang/StringBuilder.append:(Ljava/lang/String;)Ljava/lang/StringBuilder;
      38: invokevirtual #20                 // Method java/lang/StringBuilder.toString:()Ljava/lang/String;
      41: invokevirtual #21                 // Method debugCode:(Ljava/lang/String;)V
      44: aload_0
      45: invokespecial #9                  // Method checkClosed:()V
      48: aload_0
      49: lload_1
      50: iload_3
      51: invokespecial #26                 // Method get:(JI)[Ljava/lang/Object;
      54: areturn
      55: astore        4
      57: aload_0
      58: aload         4
      60: invokevirtual #12                 // Method logAndConvert:(Ljava/lang/Throwable;)Ljava/sql/SQLException;
      63: athrow
    Exception table:
       from    to  target type
           0    54    55   Class java/lang/Exception

  public java.lang.Object getArray(long, int, java.util.Map<java.lang.String, java.lang.Class<?>>) throws java.sql.SQLException;
    Code:
       0: aload_0
       1: invokevirtual #13                 // Method isDebugEnabled:()Z
       4: ifeq          57
       7: aload_0
       8: new           #14                 // class java/lang/StringBuilder
      11: dup
      12: invokespecial #15                 // Method java/lang/StringBuilder."<init>":()V
      15: ldc           #16                 // String getArray(
      17: invokevirtual #17                 // Method java/lang/StringBuilder.append:(Ljava/lang/String;)Ljava/lang/StringBuilder;
      20: lload_1
      21: invokevirtual #23                 // Method java/lang/StringBuilder.append:(J)Ljava/lang/StringBuilder;
      24: ldc           #24                 // String ,
      26: invokevirtual #17                 // Method java/lang/StringBuilder.append:(Ljava/lang/String;)Ljava/lang/StringBuilder;
      29: iload_3
      30: invokevirtual #25                 // Method java/lang/StringBuilder.append:(I)Ljava/lang/StringBuilder;
      33: ldc           #24                 // String ,
      35: invokevirtual #17                 // Method java/lang/StringBuilder.append:(Ljava/lang/String;)Ljava/lang/StringBuilder;
      38: aload         4
      40: invokestatic  #18                 // Method quoteMap:(Ljava/util/Map;)Ljava/lang/String;
      43: invokevirtual #17                 // Method java/lang/StringBuilder.append:(Ljava/lang/String;)Ljava/lang/StringBuilder;
      46: ldc           #19                 // String );
      48: invokevirtual #17                 // Method java/lang/StringBuilder.append:(Ljava/lang/String;)Ljava/lang/StringBuilder;
      51: invokevirtual #20                 // Method java/lang/StringBuilder.toString:()Ljava/lang/String;
      54: invokevirtual #21                 // Method debugCode:(Ljava/lang/String;)V
      57: aload_0
      58: invokespecial #9                  // Method checkClosed:()V
      61: aload         4
      63: invokestatic  #22                 // Method org/h2/jdbc/JdbcConnection.checkMap:(Ljava/util/Map;)V
      66: aload_0
      67: lload_1
      68: iload_3
      69: invokespecial #26                 // Method get:(JI)[Ljava/lang/Object;
      72: areturn
      73: astore        5
      75: aload_0
      76: aload         5
      78: invokevirtual #12                 // Method logAndConvert:(Ljava/lang/Throwable;)Ljava/sql/SQLException;
      81: athrow
    Exception table:
       from    to  target type
           0    72    73   Class java/lang/Exception

  public int getBaseType() throws java.sql.SQLException;
    Code:
       0: aload_0
       1: ldc           #27                 // String getBaseType
       3: invokevirtual #8                  // Method debugCodeCall:(Ljava/lang/String;)V
       6: aload_0
       7: invokespecial #9                  // Method checkClosed:()V
      10: iconst_0
      11: ireturn
      12: astore_1
      13: aload_0
      14: aload_1
      15: invokevirtual #12                 // Method logAndConvert:(Ljava/lang/Throwable;)Ljava/sql/SQLException;
      18: athrow
    Exception table:
       from    to  target type
           0    11    12   Class java/lang/Exception

  public java.lang.String getBaseTypeName() throws java.sql.SQLException;
    Code:
       0: aload_0
       1: ldc           #28                 // String getBaseTypeName
       3: invokevirtual #8                  // Method debugCodeCall:(Ljava/lang/String;)V
       6: aload_0
       7: invokespecial #9                  // Method checkClosed:()V
      10: ldc           #29                 // String NULL
      12: areturn
      13: astore_1
      14: aload_0
      15: aload_1
      16: invokevirtual #12                 // Method logAndConvert:(Ljava/lang/Throwable;)Ljava/sql/SQLException;
      19: athrow
    Exception table:
       from    to  target type
           0    12    13   Class java/lang/Exception

  public java.sql.ResultSet getResultSet() throws java.sql.SQLException;
    Code:
       0: aload_0
       1: ldc           #30                 // String getResultSet
       3: invokevirtual #8                  // Method debugCodeCall:(Ljava/lang/String;)V
       6: aload_0
       7: invokespecial #9                  // Method checkClosed:()V
      10: aload_0
      11: invokespecial #10                 // Method get:()[Ljava/lang/Object;
      14: lconst_0
      15: invokestatic  #31                 // Method getResultSet:([Ljava/lang/Object;J)Ljava/sql/ResultSet;
      18: areturn
      19: astore_1
      20: aload_0
      21: aload_1
      22: invokevirtual #12                 // Method logAndConvert:(Ljava/lang/Throwable;)Ljava/sql/SQLException;
      25: athrow
    Exception table:
       from    to  target type
           0    18    19   Class java/lang/Exception

  public java.sql.ResultSet getResultSet(java.util.Map<java.lang.String, java.lang.Class<?>>) throws java.sql.SQLException;
    Code:
       0: aload_0
       1: invokevirtual #13                 // Method isDebugEnabled:()Z
       4: ifeq          38
       7: aload_0
       8: new           #14                 // class java/lang/StringBuilder
      11: dup
      12: invokespecial #15                 // Method java/lang/StringBuilder."<init>":()V
      15: ldc           #32                 // String getResultSet(
      17: invokevirtual #17                 // Method java/lang/StringBuilder.append:(Ljava/lang/String;)Ljava/lang/StringBuilder;
      20: aload_1
      21: invokestatic  #18                 // Method quoteMap:(Ljava/util/Map;)Ljava/lang/String;
      24: invokevirtual #17                 // Method java/lang/StringBuilder.append:(Ljava/lang/String;)Ljava/lang/StringBuilder;
      27: ldc           #19                 // String );
      29: invokevirtual #17                 // Method java/lang/StringBuilder.append:(Ljava/lang/String;)Ljava/lang/StringBuilder;
      32: invokevirtual #20                 // Method java/lang/StringBuilder.toString:()Ljava/lang/String;
      35: invokevirtual #21                 // Method debugCode:(Ljava/lang/String;)V
      38: aload_0
      39: invokespecial #9                  // Method checkClosed:()V
      42: aload_1
      43: invokestatic  #22                 // Method org/h2/jdbc/JdbcConnection.checkMap:(Ljava/util/Map;)V
      46: aload_0
      47: invokespecial #10                 // Method get:()[Ljava/lang/Object;
      50: lconst_0
      51: invokestatic  #31                 // Method getResultSet:([Ljava/lang/Object;J)Ljava/sql/ResultSet;
      54: areturn
      55: astore_2
      56: aload_0
      57: aload_2
      58: invokevirtual #12                 // Method logAndConvert:(Ljava/lang/Throwable;)Ljava/sql/SQLException;
      61: athrow
    Exception table:
       from    to  target type
           0    54    55   Class java/lang/Exception

  public java.sql.ResultSet getResultSet(long, int) throws java.sql.SQLException;
    Code:
       0: aload_0
       1: invokevirtual #13                 // Method isDebugEnabled:()Z
       4: ifeq          44
       7: aload_0
       8: new           #14                 // class java/lang/StringBuilder
      11: dup
      12: invokespecial #15                 // Method java/lang/StringBuilder."<init>":()V
      15: ldc           #32                 // String getResultSet(
      17: invokevirtual #17                 // Method java/lang/StringBuilder.append:(Ljava/lang/String;)Ljava/lang/StringBuilder;
      20: lload_1
      21: invokevirtual #23                 // Method java/lang/StringBuilder.append:(J)Ljava/lang/StringBuilder;
      24: ldc           #24                 // String ,
      26: invokevirtual #17                 // Method java/lang/StringBuilder.append:(Ljava/lang/String;)Ljava/lang/StringBuilder;
      29: iload_3
      30: invokevirtual #25                 // Method java/lang/StringBuilder.append:(I)Ljava/lang/StringBuilder;
      33: ldc           #19                 // String );
      35: invokevirtual #17                 // Method java/lang/StringBuilder.append:(Ljava/lang/String;)Ljava/lang/StringBuilder;
      38: invokevirtual #20                 // Method java/lang/StringBuilder.toString:()Ljava/lang/String;
      41: invokevirtual #21                 // Method debugCode:(Ljava/lang/String;)V
      44: aload_0
      45: invokespecial #9                  // Method checkClosed:()V
      48: aload_0
      49: lload_1
      50: iload_3
      51: invokespecial #26                 // Method get:(JI)[Ljava/lang/Object;
      54: lload_1
      55: lconst_1
      56: lsub
      57: invokestatic  #31                 // Method getResultSet:([Ljava/lang/Object;J)Ljava/sql/ResultSet;
      60: areturn
      61: astore        4
      63: aload_0
      64: aload         4
      66: invokevirtual #12                 // Method logAndConvert:(Ljava/lang/Throwable;)Ljava/sql/SQLException;
      69: athrow
    Exception table:
       from    to  target type
           0    60    61   Class java/lang/Exception

  public java.sql.ResultSet getResultSet(long, int, java.util.Map<java.lang.String, java.lang.Class<?>>) throws java.sql.SQLException;
    Code:
       0: aload_0
       1: invokevirtual #13                 // Method isDebugEnabled:()Z
       4: ifeq          57
       7: aload_0
       8: new           #14                 // class java/lang/StringBuilder
      11: dup
      12: invokespecial #15                 // Method java/lang/StringBuilder."<init>":()V
      15: ldc           #32                 // String getResultSet(
      17: invokevirtual #17                 // Method java/lang/StringBuilder.append:(Ljava/lang/String;)Ljava/lang/StringBuilder;
      20: lload_1
      21: invokevirtual #23                 // Method java/lang/StringBuilder.append:(J)Ljava/lang/StringBuilder;
      24: ldc           #24                 // String ,
      26: invokevirtual #17                 // Method java/lang/StringBuilder.append:(Ljava/lang/String;)Ljava/lang/StringBuilder;
      29: iload_3
      30: invokevirtual #25                 // Method java/lang/StringBuilder.append:(I)Ljava/lang/StringBuilder;
      33: ldc           #24                 // String ,
      35: invokevirtual #17                 // Method java/lang/StringBuilder.append:(Ljava/lang/String;)Ljava/lang/StringBuilder;
      38: aload         4
      40: invokestatic  #18                 // Method quoteMap:(Ljava/util/Map;)Ljava/lang/String;
      43: invokevirtual #17                 // Method java/lang/StringBuilder.append:(Ljava/lang/String;)Ljava/lang/StringBuilder;
      46: ldc           #19                 // String );
      48: invokevirtual #17                 // Method java/lang/StringBuilder.append:(Ljava/lang/String;)Ljava/lang/StringBuilder;
      51: invokevirtual #20                 // Method java/lang/StringBuilder.toString:()Ljava/lang/String;
      54: invokevirtual #21                 // Method debugCode:(Ljava/lang/String;)V
      57: aload_0
      58: invokespecial #9                  // Method checkClosed:()V
      61: aload         4
      63: invokestatic  #22                 // Method org/h2/jdbc/JdbcConnection.checkMap:(Ljava/util/Map;)V
      66: aload_0
      67: lload_1
      68: iload_3
      69: invokespecial #26                 // Method get:(JI)[Ljava/lang/Object;
      72: lload_1
      73: lconst_1
      74: lsub
      75: invokestatic  #31                 // Method getResultSet:([Ljava/lang/Object;J)Ljava/sql/ResultSet;
      78: areturn
      79: astore        5
      81: aload_0
      82: aload         5
      84: invokevirtual #12                 // Method logAndConvert:(Ljava/lang/Throwable;)Ljava/sql/SQLException;
      87: athrow
    Exception table:
       from    to  target type
           0    78    79   Class java/lang/Exception

  public void free();
    Code:
       0: aload_0
       1: ldc           #33                 // String free
       3: invokevirtual #8                  // Method debugCodeCall:(Ljava/lang/String;)V
       6: aload_0
       7: aconst_null
       8: putfield      #6                  // Field value:Lorg/h2/value/Value;
      11: return

  private static java.sql.ResultSet getResultSet(java.lang.Object[], long);
    Code:
       0: new           #34                 // class org/h2/tools/SimpleResultSet
       3: dup
       4: invokespecial #35                 // Method org/h2/tools/SimpleResultSet."<init>":()V
       7: astore_3
       8: aload_3
       9: ldc           #36                 // String INDEX
      11: bipush        -5
      13: iconst_0
      14: iconst_0
      15: invokevirtual #37                 // Method org/h2/tools/SimpleResultSet.addColumn:(Ljava/lang/String;III)V
      18: aload_3
      19: ldc           #38                 // String VALUE
      21: iconst_0
      22: iconst_0
      23: iconst_0
      24: invokevirtual #37                 // Method org/h2/tools/SimpleResultSet.addColumn:(Ljava/lang/String;III)V
      27: iconst_0
      28: istore        4
      30: iload         4
      32: aload_0
      33: arraylength
      34: if_icmpge     71
      37: aload_3
      38: iconst_2
      39: anewarray     #39                 // class java/lang/Object
      42: dup
      43: iconst_0
      44: lload_1
      45: iload         4
      47: i2l
      48: ladd
      49: lconst_1
      50: ladd
      51: invokestatic  #40                 // Method java/lang/Long.valueOf:(J)Ljava/lang/Long;
      54: aastore
      55: dup
      56: iconst_1
      57: aload_0
      58: iload         4
      60: aaload
      61: aastore
      62: invokevirtual #41                 // Method org/h2/tools/SimpleResultSet.addRow:([Ljava/lang/Object;)V
      65: iinc          4, 1
      68: goto          30
      71: aload_3
      72: areturn

  private void checkClosed();
    Code:
       0: aload_0
       1: getfield      #5                  // Field conn:Lorg/h2/jdbc/JdbcConnection;
       4: invokevirtual #42                 // Method org/h2/jdbc/JdbcConnection.checkClosed:()V
       7: aload_0
       8: getfield      #6                  // Field value:Lorg/h2/value/Value;
      11: ifnonnull     20
      14: ldc           #43                 // int 90007
      16: invokestatic  #44                 // Method org/h2/message/DbException.get:(I)Lorg/h2/message/DbException;
      19: athrow
      20: return

  private java.lang.Object[] get();
    Code:
       0: aload_0
       1: getfield      #6                  // Field value:Lorg/h2/value/Value;
       4: bipush        17
       6: invokevirtual #45                 // Method org/h2/value/Value.convertTo:(I)Lorg/h2/value/Value;
       9: invokevirtual #46                 // Method org/h2/value/Value.getObject:()Ljava/lang/Object;
      12: checkcast     #47                 // class "[Ljava/lang/Object;"
      15: checkcast     #47                 // class "[Ljava/lang/Object;"
      18: areturn

  private java.lang.Object[] get(long, int);
    Code:
       0: aload_0
       1: invokespecial #10                 // Method get:()[Ljava/lang/Object;
       4: astore        4
       6: iload_3
       7: iflt          17
      10: iload_3
      11: aload         4
      13: arraylength
      14: if_icmple     51
      17: new           #14                 // class java/lang/StringBuilder
      20: dup
      21: invokespecial #15                 // Method java/lang/StringBuilder."<init>":()V
      24: ldc           #48                 // String count (1..
      26: invokevirtual #17                 // Method java/lang/StringBuilder.append:(Ljava/lang/String;)Ljava/lang/StringBuilder;
      29: aload         4
      31: arraylength
      32: invokevirtual #25                 // Method java/lang/StringBuilder.append:(I)Ljava/lang/StringBuilder;
      35: ldc           #49                 // String )
      37: invokevirtual #17                 // Method java/lang/StringBuilder.append:(Ljava/lang/String;)Ljava/lang/StringBuilder;
      40: invokevirtual #20                 // Method java/lang/StringBuilder.toString:()Ljava/lang/String;
      43: iload_3
      44: invokestatic  #50                 // Method java/lang/Integer.valueOf:(I)Ljava/lang/Integer;
      47: invokestatic  #51                 // Method org/h2/message/DbException.getInvalidValueException:(Ljava/lang/String;Ljava/lang/Object;)Lorg/h2/message/DbException;
      50: athrow
      51: lload_1
      52: lconst_1
      53: lcmp
      54: iflt          66
      57: lload_1
      58: aload         4
      60: arraylength
      61: i2l
      62: lcmp
      63: ifle          100
      66: new           #14                 // class java/lang/StringBuilder
      69: dup
      70: invokespecial #15                 // Method java/lang/StringBuilder."<init>":()V
      73: ldc           #52                 // String index (1..
      75: invokevirtual #17                 // Method java/lang/StringBuilder.append:(Ljava/lang/String;)Ljava/lang/StringBuilder;
      78: aload         4
      80: arraylength
      81: invokevirtual #25                 // Method java/lang/StringBuilder.append:(I)Ljava/lang/StringBuilder;
      84: ldc           #49                 // String )
      86: invokevirtual #17                 // Method java/lang/StringBuilder.append:(Ljava/lang/String;)Ljava/lang/StringBuilder;
      89: invokevirtual #20                 // Method java/lang/StringBuilder.toString:()Ljava/lang/String;
      92: lload_1
      93: invokestatic  #40                 // Method java/lang/Long.valueOf:(J)Ljava/lang/Long;
      96: invokestatic  #51                 // Method org/h2/message/DbException.getInvalidValueException:(Ljava/lang/String;Ljava/lang/Object;)Lorg/h2/message/DbException;
      99: athrow
     100: lload_1
     101: lconst_1
     102: lsub
     103: l2i
     104: istore        5
     106: aload         4
     108: iload         5
     110: iload         5
     112: iload_3
     113: iadd
     114: invokestatic  #53                 // Method java/util/Arrays.copyOfRange:([Ljava/lang/Object;II)[Ljava/lang/Object;
     117: areturn

  public java.lang.String toString();
    Code:
       0: aload_0
       1: getfield      #6                  // Field value:Lorg/h2/value/Value;
       4: ifnonnull     12
       7: ldc           #54                 // String null
       9: goto          44
      12: new           #14                 // class java/lang/StringBuilder
      15: dup
      16: invokespecial #15                 // Method java/lang/StringBuilder."<init>":()V
      19: aload_0
      20: invokevirtual #55                 // Method getTraceObjectName:()Ljava/lang/String;
      23: invokevirtual #17                 // Method java/lang/StringBuilder.append:(Ljava/lang/String;)Ljava/lang/StringBuilder;
      26: ldc           #56                 // String :
      28: invokevirtual #17                 // Method java/lang/StringBuilder.append:(Ljava/lang/String;)Ljava/lang/StringBuilder;
      31: aload_0
      32: getfield      #6                  // Field value:Lorg/h2/value/Value;
      35: invokevirtual #57                 // Method org/h2/value/Value.getTraceSQL:()Ljava/lang/String;
      38: invokevirtual #17                 // Method java/lang/StringBuilder.append:(Ljava/lang/String;)Ljava/lang/StringBuilder;
      41: invokevirtual #20                 // Method java/lang/StringBuilder.toString:()Ljava/lang/String;
      44: areturn
}
