Compiled from "NegatedServerWebExchangeMatcher.java"
public class org.springframework.security.web.server.util.matcher.NegatedServerWebExchangeMatcher implements org.springframework.security.web.server.util.matcher.ServerWebExchangeMatcher {
  private final org.springframework.security.web.server.util.matcher.ServerWebExchangeMatcher matcher;

  public org.springframework.security.web.server.util.matcher.NegatedServerWebExchangeMatcher(org.springframework.security.web.server.util.matcher.ServerWebExchangeMatcher);
    Code:
       0: aload_0
       1: invokespecial #1                  // Method java/lang/Object."<init>":()V
       4: aload_1
       5: ldc           #2                  // String matcher cannot be null
       7: invokestatic  #3                  // Method org/springframework/util/Assert.notNull:(Ljava/lang/Object;Ljava/lang/String;)V
      10: aload_0
      11: aload_1
      12: putfield      #4                  // Field matcher:Lorg/springframework/security/web/server/util/matcher/ServerWebExchangeMatcher;
      15: return

  public reactor.core.publisher.Mono<org.springframework.security.web.server.util.matcher.ServerWebExchangeMatcher$MatchResult> matches(org.springframework.web.server.ServerWebExchange);
    Code:
       0: aload_0
       1: getfield      #4                  // Field matcher:Lorg/springframework/security/web/server/util/matcher/ServerWebExchangeMatcher;
       4: aload_1
       5: invokeinterface #5,  2            // InterfaceMethod org/springframework/security/web/server/util/matcher/ServerWebExchangeMatcher.matches:(Lorg/springframework/web/server/ServerWebExchange;)Lreactor/core/publisher/Mono;
      10: invokedynamic #6,  0              // InvokeDynamic #0:apply:()Ljava/util/function/Function;
      15: invokevirtual #7                  // Method reactor/core/publisher/Mono.flatMap:(Ljava/util/function/Function;)Lreactor/core/publisher/Mono;
      18: areturn

  public java.lang.String toString();
    Code:
       0: new           #8                  // class java/lang/StringBuilder
       3: dup
       4: invokespecial #9                  // Method java/lang/StringBuilder."<init>":()V
       7: ldc           #10                 // String NegatedServerWebExchangeMatcher{matcher=
       9: invokevirtual #11                 // Method java/lang/StringBuilder.append:(Ljava/lang/String;)Ljava/lang/StringBuilder;
      12: aload_0
      13: getfield      #4                  // Field matcher:Lorg/springframework/security/web/server/util/matcher/ServerWebExchangeMatcher;
      16: invokevirtual #12                 // Method java/lang/StringBuilder.append:(Ljava/lang/Object;)Ljava/lang/StringBuilder;
      19: bipush        125
      21: invokevirtual #13                 // Method java/lang/StringBuilder.append:(C)Ljava/lang/StringBuilder;
      24: invokevirtual #14                 // Method java/lang/StringBuilder.toString:()Ljava/lang/String;
      27: areturn

  private static reactor.core.publisher.Mono lambda$matches$0(org.springframework.security.web.server.util.matcher.ServerWebExchangeMatcher$MatchResult);
    Code:
       0: aload_0
       1: invokevirtual #15                 // Method org/springframework/security/web/server/util/matcher/ServerWebExchangeMatcher$MatchResult.isMatch:()Z
       4: ifeq          13
       7: invokestatic  #16                 // Method org/springframework/security/web/server/util/matcher/ServerWebExchangeMatcher$MatchResult.notMatch:()Lreactor/core/publisher/Mono;
      10: goto          16
      13: invokestatic  #17                 // Method org/springframework/security/web/server/util/matcher/ServerWebExchangeMatcher$MatchResult.match:()Lreactor/core/publisher/Mono;
      16: areturn
}
