Compiled from "ConventionAnnotationImpl.java"
final class org.bson.codecs.pojo.ConventionAnnotationImpl implements org.bson.codecs.pojo.Convention {
  org.bson.codecs.pojo.ConventionAnnotationImpl();
    Code:
       0: aload_0
       1: invokespecial #1                  // Method java/lang/Object."<init>":()V
       4: return

  public void apply(org.bson.codecs.pojo.ClassModelBuilder<?>);
    Code:
       0: aload_1
       1: invokevirtual #2                  // Method org/bson/codecs/pojo/ClassModelBuilder.getAnnotations:()Ljava/util/List;
       4: invokeinterface #3,  1            // InterfaceMethod java/util/List.iterator:()Ljava/util/Iterator;
       9: astore_2
      10: aload_2
      11: invokeinterface #4,  1            // InterfaceMethod java/util/Iterator.hasNext:()Z
      16: ifeq          38
      19: aload_2
      20: invokeinterface #5,  1            // InterfaceMethod java/util/Iterator.next:()Ljava/lang/Object;
      25: checkcast     #6                  // class java/lang/annotation/Annotation
      28: astore_3
      29: aload_0
      30: aload_1
      31: aload_3
      32: invokespecial #7                  // Method processClassAnnotation:(Lorg/bson/codecs/pojo/ClassModelBuilder;Ljava/lang/annotation/Annotation;)V
      35: goto          10
      38: aload_1
      39: invokevirtual #8                  // Method org/bson/codecs/pojo/ClassModelBuilder.getPropertyModelBuilders:()Ljava/util/List;
      42: invokeinterface #3,  1            // InterfaceMethod java/util/List.iterator:()Ljava/util/Iterator;
      47: astore_2
      48: aload_2
      49: invokeinterface #4,  1            // InterfaceMethod java/util/Iterator.hasNext:()Z
      54: ifeq          76
      57: aload_2
      58: invokeinterface #5,  1            // InterfaceMethod java/util/Iterator.next:()Ljava/lang/Object;
      63: checkcast     #9                  // class org/bson/codecs/pojo/PropertyModelBuilder
      66: astore_3
      67: aload_0
      68: aload_1
      69: aload_3
      70: invokespecial #10                 // Method processPropertyAnnotations:(Lorg/bson/codecs/pojo/ClassModelBuilder;Lorg/bson/codecs/pojo/PropertyModelBuilder;)V
      73: goto          48
      76: aload_0
      77: aload_1
      78: invokespecial #11                 // Method processCreatorAnnotation:(Lorg/bson/codecs/pojo/ClassModelBuilder;)V
      81: aload_0
      82: aload_1
      83: invokespecial #12                 // Method cleanPropertyBuilders:(Lorg/bson/codecs/pojo/ClassModelBuilder;)V
      86: return

  private void processClassAnnotation(org.bson.codecs.pojo.ClassModelBuilder<?>, java.lang.annotation.Annotation);
    Code:
       0: aload_2
       1: instanceof    #13                 // class org/bson/codecs/pojo/annotations/BsonDiscriminator
       4: ifeq          68
       7: aload_2
       8: checkcast     #13                 // class org/bson/codecs/pojo/annotations/BsonDiscriminator
      11: astore_3
      12: aload_3
      13: invokeinterface #14,  1           // InterfaceMethod org/bson/codecs/pojo/annotations/BsonDiscriminator.key:()Ljava/lang/String;
      18: astore        4
      20: aload         4
      22: ldc           #15                 // String
      24: invokevirtual #16                 // Method java/lang/String.equals:(Ljava/lang/Object;)Z
      27: ifne          37
      30: aload_1
      31: aload         4
      33: invokevirtual #17                 // Method org/bson/codecs/pojo/ClassModelBuilder.discriminatorKey:(Ljava/lang/String;)Lorg/bson/codecs/pojo/ClassModelBuilder;
      36: pop
      37: aload_3
      38: invokeinterface #18,  1           // InterfaceMethod org/bson/codecs/pojo/annotations/BsonDiscriminator.value:()Ljava/lang/String;
      43: astore        5
      45: aload         5
      47: ldc           #15                 // String
      49: invokevirtual #16                 // Method java/lang/String.equals:(Ljava/lang/Object;)Z
      52: ifne          62
      55: aload_1
      56: aload         5
      58: invokevirtual #19                 // Method org/bson/codecs/pojo/ClassModelBuilder.discriminator:(Ljava/lang/String;)Lorg/bson/codecs/pojo/ClassModelBuilder;
      61: pop
      62: aload_1
      63: iconst_1
      64: invokevirtual #20                 // Method org/bson/codecs/pojo/ClassModelBuilder.enableDiscriminator:(Z)Lorg/bson/codecs/pojo/ClassModelBuilder;
      67: pop
      68: return

  private void processPropertyAnnotations(org.bson.codecs.pojo.ClassModelBuilder<?>, org.bson.codecs.pojo.PropertyModelBuilder<?>);
    Code:
       0: aload_2
       1: invokevirtual #21                 // Method org/bson/codecs/pojo/PropertyModelBuilder.getReadAnnotations:()Ljava/util/List;
       4: invokeinterface #3,  1            // InterfaceMethod java/util/List.iterator:()Ljava/util/Iterator;
       9: astore_3
      10: aload_3
      11: invokeinterface #4,  1            // InterfaceMethod java/util/Iterator.hasNext:()Z
      16: ifeq          124
      19: aload_3
      20: invokeinterface #5,  1            // InterfaceMethod java/util/Iterator.next:()Ljava/lang/Object;
      25: checkcast     #6                  // class java/lang/annotation/Annotation
      28: astore        4
      30: aload         4
      32: instanceof    #22                 // class org/bson/codecs/pojo/annotations/BsonProperty
      35: ifeq          87
      38: aload         4
      40: checkcast     #22                 // class org/bson/codecs/pojo/annotations/BsonProperty
      43: astore        5
      45: ldc           #15                 // String
      47: aload         5
      49: invokeinterface #23,  1           // InterfaceMethod org/bson/codecs/pojo/annotations/BsonProperty.value:()Ljava/lang/String;
      54: invokevirtual #16                 // Method java/lang/String.equals:(Ljava/lang/Object;)Z
      57: ifne          72
      60: aload_2
      61: aload         5
      63: invokeinterface #23,  1           // InterfaceMethod org/bson/codecs/pojo/annotations/BsonProperty.value:()Ljava/lang/String;
      68: invokevirtual #24                 // Method org/bson/codecs/pojo/PropertyModelBuilder.readName:(Ljava/lang/String;)Lorg/bson/codecs/pojo/PropertyModelBuilder;
      71: pop
      72: aload_2
      73: aload         5
      75: invokeinterface #25,  1           // InterfaceMethod org/bson/codecs/pojo/annotations/BsonProperty.useDiscriminator:()Z
      80: invokevirtual #26                 // Method org/bson/codecs/pojo/PropertyModelBuilder.discriminatorEnabled:(Z)Lorg/bson/codecs/pojo/PropertyModelBuilder;
      83: pop
      84: goto          121
      87: aload         4
      89: instanceof    #27                 // class org/bson/codecs/pojo/annotations/BsonId
      92: ifeq          107
      95: aload_1
      96: aload_2
      97: invokevirtual #28                 // Method org/bson/codecs/pojo/PropertyModelBuilder.getName:()Ljava/lang/String;
     100: invokevirtual #29                 // Method org/bson/codecs/pojo/ClassModelBuilder.idPropertyName:(Ljava/lang/String;)Lorg/bson/codecs/pojo/ClassModelBuilder;
     103: pop
     104: goto          121
     107: aload         4
     109: instanceof    #30                 // class org/bson/codecs/pojo/annotations/BsonIgnore
     112: ifeq          121
     115: aload_2
     116: aconst_null
     117: invokevirtual #24                 // Method org/bson/codecs/pojo/PropertyModelBuilder.readName:(Ljava/lang/String;)Lorg/bson/codecs/pojo/PropertyModelBuilder;
     120: pop
     121: goto          10
     124: aload_2
     125: invokevirtual #31                 // Method org/bson/codecs/pojo/PropertyModelBuilder.getWriteAnnotations:()Ljava/util/List;
     128: invokeinterface #3,  1            // InterfaceMethod java/util/List.iterator:()Ljava/util/Iterator;
     133: astore_3
     134: aload_3
     135: invokeinterface #4,  1            // InterfaceMethod java/util/Iterator.hasNext:()Z
     140: ifeq          216
     143: aload_3
     144: invokeinterface #5,  1            // InterfaceMethod java/util/Iterator.next:()Ljava/lang/Object;
     149: checkcast     #6                  // class java/lang/annotation/Annotation
     152: astore        4
     154: aload         4
     156: instanceof    #22                 // class org/bson/codecs/pojo/annotations/BsonProperty
     159: ifeq          199
     162: aload         4
     164: checkcast     #22                 // class org/bson/codecs/pojo/annotations/BsonProperty
     167: astore        5
     169: ldc           #15                 // String
     171: aload         5
     173: invokeinterface #23,  1           // InterfaceMethod org/bson/codecs/pojo/annotations/BsonProperty.value:()Ljava/lang/String;
     178: invokevirtual #16                 // Method java/lang/String.equals:(Ljava/lang/Object;)Z
     181: ifne          196
     184: aload_2
     185: aload         5
     187: invokeinterface #23,  1           // InterfaceMethod org/bson/codecs/pojo/annotations/BsonProperty.value:()Ljava/lang/String;
     192: invokevirtual #32                 // Method org/bson/codecs/pojo/PropertyModelBuilder.writeName:(Ljava/lang/String;)Lorg/bson/codecs/pojo/PropertyModelBuilder;
     195: pop
     196: goto          213
     199: aload         4
     201: instanceof    #30                 // class org/bson/codecs/pojo/annotations/BsonIgnore
     204: ifeq          213
     207: aload_2
     208: aconst_null
     209: invokevirtual #32                 // Method org/bson/codecs/pojo/PropertyModelBuilder.writeName:(Ljava/lang/String;)Lorg/bson/codecs/pojo/PropertyModelBuilder;
     212: pop
     213: goto          134
     216: return

  private <T> void processCreatorAnnotation(org.bson.codecs.pojo.ClassModelBuilder<T>);
    Code:
       0: aload_1
       1: invokevirtual #33                 // Method org/bson/codecs/pojo/ClassModelBuilder.getType:()Ljava/lang/Class;
       4: astore_2
       5: aconst_null
       6: astore_3
       7: aload_2
       8: invokevirtual #34                 // Method java/lang/Class.getDeclaredConstructors:()[Ljava/lang/reflect/Constructor;
      11: astore        4
      13: aload         4
      15: arraylength
      16: istore        5
      18: iconst_0
      19: istore        6
      21: iload         6
      23: iload         5
      25: if_icmpge     135
      28: aload         4
      30: iload         6
      32: aaload
      33: astore        7
      35: aload         7
      37: invokevirtual #35                 // Method java/lang/reflect/Constructor.getModifiers:()I
      40: invokestatic  #36                 // Method java/lang/reflect/Modifier.isPublic:(I)Z
      43: ifeq          129
      46: aload         7
      48: invokevirtual #37                 // Method java/lang/reflect/Constructor.isSynthetic:()Z
      51: ifne          129
      54: aload         7
      56: invokevirtual #38                 // Method java/lang/reflect/Constructor.getDeclaredAnnotations:()[Ljava/lang/annotation/Annotation;
      59: astore        8
      61: aload         8
      63: arraylength
      64: istore        9
      66: iconst_0
      67: istore        10
      69: iload         10
      71: iload         9
      73: if_icmpge     129
      76: aload         8
      78: iload         10
      80: aaload
      81: astore        11
      83: aload         11
      85: invokeinterface #39,  1           // InterfaceMethod java/lang/annotation/Annotation.annotationType:()Ljava/lang/Class;
      90: ldc           #40                 // class org/bson/codecs/pojo/annotations/BsonCreator
      92: invokevirtual #41                 // Method java/lang/Object.equals:(Ljava/lang/Object;)Z
      95: ifeq          123
      98: aload_3
      99: ifnull        112
     102: new           #42                 // class org/bson/codecs/configuration/CodecConfigurationException
     105: dup
     106: ldc           #43                 // String Found multiple constructors annotated with @BsonCreator
     108: invokespecial #44                 // Method org/bson/codecs/configuration/CodecConfigurationException."<init>":(Ljava/lang/String;)V
     111: athrow
     112: new           #45                 // class org/bson/codecs/pojo/CreatorExecutable
     115: dup
     116: aload_2
     117: aload         7
     119: invokespecial #46                 // Method org/bson/codecs/pojo/CreatorExecutable."<init>":(Ljava/lang/Class;Ljava/lang/reflect/Constructor;)V
     122: astore_3
     123: iinc          10, 1
     126: goto          69
     129: iinc          6, 1
     132: goto          21
     135: aload_2
     136: astore        4
     138: iconst_0
     139: istore        5
     141: aload         4
     143: ifnull        344
     146: iload         5
     148: ifne          344
     151: aload         4
     153: invokevirtual #47                 // Method java/lang/Class.getDeclaredMethods:()[Ljava/lang/reflect/Method;
     156: astore        6
     158: aload         6
     160: arraylength
     161: istore        7
     163: iconst_0
     164: istore        8
     166: iload         8
     168: iload         7
     170: if_icmpge     334
     173: aload         6
     175: iload         8
     177: aaload
     178: astore        9
     180: aload         9
     182: invokevirtual #48                 // Method java/lang/reflect/Method.getModifiers:()I
     185: invokestatic  #49                 // Method java/lang/reflect/Modifier.isStatic:(I)Z
     188: ifeq          328
     191: aload         9
     193: invokevirtual #50                 // Method java/lang/reflect/Method.isSynthetic:()Z
     196: ifne          328
     199: aload         9
     201: invokevirtual #51                 // Method java/lang/reflect/Method.isBridge:()Z
     204: ifne          328
     207: aload         9
     209: invokevirtual #52                 // Method java/lang/reflect/Method.getDeclaredAnnotations:()[Ljava/lang/annotation/Annotation;
     212: astore        10
     214: aload         10
     216: arraylength
     217: istore        11
     219: iconst_0
     220: istore        12
     222: iload         12
     224: iload         11
     226: if_icmpge     328
     229: aload         10
     231: iload         12
     233: aaload
     234: astore        13
     236: aload         13
     238: invokeinterface #39,  1           // InterfaceMethod java/lang/annotation/Annotation.annotationType:()Ljava/lang/Class;
     243: ldc           #40                 // class org/bson/codecs/pojo/annotations/BsonCreator
     245: invokevirtual #41                 // Method java/lang/Object.equals:(Ljava/lang/Object;)Z
     248: ifeq          322
     251: aload_3
     252: ifnull        265
     255: new           #42                 // class org/bson/codecs/configuration/CodecConfigurationException
     258: dup
     259: ldc           #53                 // String Found multiple constructors / methods annotated with @BsonCreator
     261: invokespecial #44                 // Method org/bson/codecs/configuration/CodecConfigurationException."<init>":(Ljava/lang/String;)V
     264: athrow
     265: aload         4
     267: aload         9
     269: invokevirtual #54                 // Method java/lang/reflect/Method.getReturnType:()Ljava/lang/Class;
     272: invokevirtual #55                 // Method java/lang/Class.isAssignableFrom:(Ljava/lang/Class;)Z
     275: ifne          308
     278: new           #42                 // class org/bson/codecs/configuration/CodecConfigurationException
     281: dup
     282: ldc           #56                 // String Invalid method annotated with @BsonCreator. Returns \'%s\', expected %s
     284: iconst_2
     285: anewarray     #57                 // class java/lang/Object
     288: dup
     289: iconst_0
     290: aload         9
     292: invokevirtual #54                 // Method java/lang/reflect/Method.getReturnType:()Ljava/lang/Class;
     295: aastore
     296: dup
     297: iconst_1
     298: aload         4
     300: aastore
     301: invokestatic  #58                 // Method java/lang/String.format:(Ljava/lang/String;[Ljava/lang/Object;)Ljava/lang/String;
     304: invokespecial #44                 // Method org/bson/codecs/configuration/CodecConfigurationException."<init>":(Ljava/lang/String;)V
     307: athrow
     308: new           #45                 // class org/bson/codecs/pojo/CreatorExecutable
     311: dup
     312: aload_2
     313: aload         9
     315: invokespecial #59                 // Method org/bson/codecs/pojo/CreatorExecutable."<init>":(Ljava/lang/Class;Ljava/lang/reflect/Method;)V
     318: astore_3
     319: iconst_1
     320: istore        5
     322: iinc          12, 1
     325: goto          222
     328: iinc          8, 1
     331: goto          166
     334: aload         4
     336: invokevirtual #60                 // Method java/lang/Class.getSuperclass:()Ljava/lang/Class;
     339: astore        4
     341: goto          141
     344: aload_3
     345: ifnull        734
     348: aload_3
     349: invokevirtual #61                 // Method org/bson/codecs/pojo/CreatorExecutable.getProperties:()Ljava/util/List;
     352: astore        6
     354: aload_3
     355: invokevirtual #62                 // Method org/bson/codecs/pojo/CreatorExecutable.getParameterTypes:()Ljava/util/List;
     358: astore        7
     360: aload_3
     361: invokevirtual #63                 // Method org/bson/codecs/pojo/CreatorExecutable.getParameterGenericTypes:()Ljava/util/List;
     364: astore        8
     366: aload         6
     368: invokeinterface #64,  1           // InterfaceMethod java/util/List.size:()I
     373: aload         7
     375: invokeinterface #64,  1           // InterfaceMethod java/util/List.size:()I
     380: if_icmpeq     391
     383: aload_3
     384: aload_2
     385: ldc           #65                 // String All parameters in the @BsonCreator method / constructor must be annotated with a @BsonProperty.
     387: invokevirtual #66                 // Method org/bson/codecs/pojo/CreatorExecutable.getError:(Ljava/lang/Class;Ljava/lang/String;)Lorg/bson/codecs/configuration/CodecConfigurationException;
     390: athrow
     391: iconst_0
     392: istore        9
     394: iload         9
     396: aload         6
     398: invokeinterface #64,  1           // InterfaceMethod java/util/List.size:()I
     403: if_icmpge     721
     406: aload_3
     407: invokevirtual #67                 // Method org/bson/codecs/pojo/CreatorExecutable.getIdPropertyIndex:()Ljava/lang/Integer;
     410: ifnull        432
     413: aload_3
     414: invokevirtual #67                 // Method org/bson/codecs/pojo/CreatorExecutable.getIdPropertyIndex:()Ljava/lang/Integer;
     417: iload         9
     419: invokestatic  #68                 // Method java/lang/Integer.valueOf:(I)Ljava/lang/Integer;
     422: invokevirtual #69                 // Method java/lang/Integer.equals:(Ljava/lang/Object;)Z
     425: ifeq          432
     428: iconst_1
     429: goto          433
     432: iconst_0
     433: istore        10
     435: aload         7
     437: iload         9
     439: invokeinterface #70,  2           // InterfaceMethod java/util/List.get:(I)Ljava/lang/Object;
     444: checkcast     #71                 // class java/lang/Class
     447: astore        11
     449: aload         8
     451: iload         9
     453: invokeinterface #70,  2           // InterfaceMethod java/util/List.get:(I)Ljava/lang/Object;
     458: checkcast     #72                 // class java/lang/reflect/Type
     461: astore        12
     463: aconst_null
     464: astore        13
     466: iload         10
     468: ifeq          484
     471: aload_1
     472: aload_1
     473: invokevirtual #73                 // Method org/bson/codecs/pojo/ClassModelBuilder.getIdPropertyName:()Ljava/lang/String;
     476: invokevirtual #74                 // Method org/bson/codecs/pojo/ClassModelBuilder.getProperty:(Ljava/lang/String;)Lorg/bson/codecs/pojo/PropertyModelBuilder;
     479: astore        13
     481: goto          663
     484: aload         6
     486: iload         9
     488: invokeinterface #70,  2           // InterfaceMethod java/util/List.get:(I)Ljava/lang/Object;
     493: checkcast     #22                 // class org/bson/codecs/pojo/annotations/BsonProperty
     496: astore        14
     498: aload_1
     499: invokevirtual #8                  // Method org/bson/codecs/pojo/ClassModelBuilder.getPropertyModelBuilders:()Ljava/util/List;
     502: invokeinterface #3,  1            // InterfaceMethod java/util/List.iterator:()Ljava/util/Iterator;
     507: astore        15
     509: aload         15
     511: invokeinterface #4,  1            // InterfaceMethod java/util/Iterator.hasNext:()Z
     516: ifeq          581
     519: aload         15
     521: invokeinterface #5,  1            // InterfaceMethod java/util/Iterator.next:()Ljava/lang/Object;
     526: checkcast     #9                  // class org/bson/codecs/pojo/PropertyModelBuilder
     529: astore        16
     531: aload         14
     533: invokeinterface #23,  1           // InterfaceMethod org/bson/codecs/pojo/annotations/BsonProperty.value:()Ljava/lang/String;
     538: aload         16
     540: invokevirtual #75                 // Method org/bson/codecs/pojo/PropertyModelBuilder.getWriteName:()Ljava/lang/String;
     543: invokevirtual #16                 // Method java/lang/String.equals:(Ljava/lang/Object;)Z
     546: ifeq          556
     549: aload         16
     551: astore        13
     553: goto          581
     556: aload         14
     558: invokeinterface #23,  1           // InterfaceMethod org/bson/codecs/pojo/annotations/BsonProperty.value:()Ljava/lang/String;
     563: aload         16
     565: invokevirtual #76                 // Method org/bson/codecs/pojo/PropertyModelBuilder.getReadName:()Ljava/lang/String;
     568: invokevirtual #16                 // Method java/lang/String.equals:(Ljava/lang/Object;)Z
     571: ifeq          578
     574: aload         16
     576: astore        13
     578: goto          509
     581: aload         13
     583: ifnonnull     599
     586: aload_1
     587: aload         14
     589: invokeinterface #23,  1           // InterfaceMethod org/bson/codecs/pojo/annotations/BsonProperty.value:()Ljava/lang/String;
     594: invokevirtual #74                 // Method org/bson/codecs/pojo/ClassModelBuilder.getProperty:(Ljava/lang/String;)Lorg/bson/codecs/pojo/PropertyModelBuilder;
     597: astore        13
     599: aload         13
     601: ifnonnull     623
     604: aload_0
     605: aload_1
     606: aload         14
     608: invokeinterface #23,  1           // InterfaceMethod org/bson/codecs/pojo/annotations/BsonProperty.value:()Ljava/lang/String;
     613: aload         11
     615: invokespecial #77                 // Method addCreatorPropertyToClassModelBuilder:(Lorg/bson/codecs/pojo/ClassModelBuilder;Ljava/lang/String;Ljava/lang/Class;)Lorg/bson/codecs/pojo/PropertyModelBuilder;
     618: astore        13
     620: goto          663
     623: aload         14
     625: invokeinterface #23,  1           // InterfaceMethod org/bson/codecs/pojo/annotations/BsonProperty.value:()Ljava/lang/String;
     630: aload         13
     632: invokevirtual #28                 // Method org/bson/codecs/pojo/PropertyModelBuilder.getName:()Ljava/lang/String;
     635: invokevirtual #16                 // Method java/lang/String.equals:(Ljava/lang/Object;)Z
     638: ifne          654
     641: aload         13
     643: aload         14
     645: invokeinterface #23,  1           // InterfaceMethod org/bson/codecs/pojo/annotations/BsonProperty.value:()Ljava/lang/String;
     650: invokevirtual #32                 // Method org/bson/codecs/pojo/PropertyModelBuilder.writeName:(Ljava/lang/String;)Lorg/bson/codecs/pojo/PropertyModelBuilder;
     653: pop
     654: aload         11
     656: aload         13
     658: aload         12
     660: invokestatic  #78                 // Method tryToExpandToGenericType:(Ljava/lang/Class;Lorg/bson/codecs/pojo/PropertyModelBuilder;Ljava/lang/reflect/Type;)V
     663: aload         13
     665: invokevirtual #79                 // Method org/bson/codecs/pojo/PropertyModelBuilder.getTypeData:()Lorg/bson/codecs/pojo/TypeData;
     668: aload         11
     670: invokevirtual #80                 // Method org/bson/codecs/pojo/TypeData.isAssignableFrom:(Ljava/lang/Class;)Z
     673: ifne          715
     676: aload_3
     677: aload_2
     678: ldc           #81                 // String Invalid Property type for \'%s\'. Expected %s, found %s.
     680: iconst_3
     681: anewarray     #57                 // class java/lang/Object
     684: dup
     685: iconst_0
     686: aload         13
     688: invokevirtual #75                 // Method org/bson/codecs/pojo/PropertyModelBuilder.getWriteName:()Ljava/lang/String;
     691: aastore
     692: dup
     693: iconst_1
     694: aload         13
     696: invokevirtual #79                 // Method org/bson/codecs/pojo/PropertyModelBuilder.getTypeData:()Lorg/bson/codecs/pojo/TypeData;
     699: invokevirtual #82                 // Method org/bson/codecs/pojo/TypeData.getType:()Ljava/lang/Class;
     702: aastore
     703: dup
     704: iconst_2
     705: aload         11
     707: aastore
     708: invokestatic  #58                 // Method java/lang/String.format:(Ljava/lang/String;[Ljava/lang/Object;)Ljava/lang/String;
     711: invokevirtual #66                 // Method org/bson/codecs/pojo/CreatorExecutable.getError:(Ljava/lang/Class;Ljava/lang/String;)Lorg/bson/codecs/configuration/CodecConfigurationException;
     714: athrow
     715: iinc          9, 1
     718: goto          394
     721: aload_1
     722: new           #83                 // class org/bson/codecs/pojo/InstanceCreatorFactoryImpl
     725: dup
     726: aload_3
     727: invokespecial #84                 // Method org/bson/codecs/pojo/InstanceCreatorFactoryImpl."<init>":(Lorg/bson/codecs/pojo/CreatorExecutable;)V
     730: invokevirtual #85                 // Method org/bson/codecs/pojo/ClassModelBuilder.instanceCreatorFactory:(Lorg/bson/codecs/pojo/InstanceCreatorFactory;)Lorg/bson/codecs/pojo/ClassModelBuilder;
     733: pop
     734: return

  private static <T> void tryToExpandToGenericType(java.lang.Class<?>, org.bson.codecs.pojo.PropertyModelBuilder<T>, java.lang.reflect.Type);
    Code:
       0: aload_0
       1: aload_1
       2: invokevirtual #79                 // Method org/bson/codecs/pojo/PropertyModelBuilder.getTypeData:()Lorg/bson/codecs/pojo/TypeData;
       5: invokevirtual #82                 // Method org/bson/codecs/pojo/TypeData.getType:()Ljava/lang/Class;
       8: invokevirtual #55                 // Method java/lang/Class.isAssignableFrom:(Ljava/lang/Class;)Z
      11: ifeq          24
      14: aload_1
      15: aload_2
      16: aload_0
      17: invokestatic  #86                 // Method org/bson/codecs/pojo/TypeData.newInstance:(Ljava/lang/reflect/Type;Ljava/lang/Class;)Lorg/bson/codecs/pojo/TypeData;
      20: invokevirtual #87                 // Method org/bson/codecs/pojo/PropertyModelBuilder.typeData:(Lorg/bson/codecs/pojo/TypeData;)Lorg/bson/codecs/pojo/PropertyModelBuilder;
      23: pop
      24: return

  private <T, S> org.bson.codecs.pojo.PropertyModelBuilder<S> addCreatorPropertyToClassModelBuilder(org.bson.codecs.pojo.ClassModelBuilder<T>, java.lang.String, java.lang.Class<S>);
    Code:
       0: new           #88                 // class org/bson/codecs/pojo/PropertyMetadata
       3: dup
       4: aload_2
       5: aload_1
       6: invokevirtual #33                 // Method org/bson/codecs/pojo/ClassModelBuilder.getType:()Ljava/lang/Class;
       9: invokevirtual #89                 // Method java/lang/Class.getSimpleName:()Ljava/lang/String;
      12: aload_3
      13: invokestatic  #90                 // Method org/bson/codecs/pojo/TypeData.builder:(Ljava/lang/Class;)Lorg/bson/codecs/pojo/TypeData$Builder;
      16: invokevirtual #91                 // Method org/bson/codecs/pojo/TypeData$Builder.build:()Lorg/bson/codecs/pojo/TypeData;
      19: invokespecial #92                 // Method org/bson/codecs/pojo/PropertyMetadata."<init>":(Ljava/lang/String;Ljava/lang/String;Lorg/bson/codecs/pojo/TypeData;)V
      22: invokestatic  #93                 // Method org/bson/codecs/pojo/PojoBuilderHelper.createPropertyModelBuilder:(Lorg/bson/codecs/pojo/PropertyMetadata;)Lorg/bson/codecs/pojo/PropertyModelBuilder;
      25: aconst_null
      26: invokevirtual #24                 // Method org/bson/codecs/pojo/PropertyModelBuilder.readName:(Ljava/lang/String;)Lorg/bson/codecs/pojo/PropertyModelBuilder;
      29: aload_2
      30: invokevirtual #32                 // Method org/bson/codecs/pojo/PropertyModelBuilder.writeName:(Ljava/lang/String;)Lorg/bson/codecs/pojo/PropertyModelBuilder;
      33: astore        4
      35: aload_1
      36: aload         4
      38: invokevirtual #94                 // Method org/bson/codecs/pojo/ClassModelBuilder.addProperty:(Lorg/bson/codecs/pojo/PropertyModelBuilder;)Lorg/bson/codecs/pojo/ClassModelBuilder;
      41: pop
      42: aload         4
      44: areturn

  private void cleanPropertyBuilders(org.bson.codecs.pojo.ClassModelBuilder<?>);
    Code:
       0: new           #95                 // class java/util/ArrayList
       3: dup
       4: invokespecial #96                 // Method java/util/ArrayList."<init>":()V
       7: astore_2
       8: aload_1
       9: invokevirtual #8                  // Method org/bson/codecs/pojo/ClassModelBuilder.getPropertyModelBuilders:()Ljava/util/List;
      12: invokeinterface #3,  1            // InterfaceMethod java/util/List.iterator:()Ljava/util/Iterator;
      17: astore_3
      18: aload_3
      19: invokeinterface #4,  1            // InterfaceMethod java/util/Iterator.hasNext:()Z
      24: ifeq          69
      27: aload_3
      28: invokeinterface #5,  1            // InterfaceMethod java/util/Iterator.next:()Ljava/lang/Object;
      33: checkcast     #9                  // class org/bson/codecs/pojo/PropertyModelBuilder
      36: astore        4
      38: aload         4
      40: invokevirtual #97                 // Method org/bson/codecs/pojo/PropertyModelBuilder.isReadable:()Z
      43: ifne          66
      46: aload         4
      48: invokevirtual #98                 // Method org/bson/codecs/pojo/PropertyModelBuilder.isWritable:()Z
      51: ifne          66
      54: aload_2
      55: aload         4
      57: invokevirtual #28                 // Method org/bson/codecs/pojo/PropertyModelBuilder.getName:()Ljava/lang/String;
      60: invokeinterface #99,  2           // InterfaceMethod java/util/List.add:(Ljava/lang/Object;)Z
      65: pop
      66: goto          18
      69: aload_2
      70: invokeinterface #3,  1            // InterfaceMethod java/util/List.iterator:()Ljava/util/Iterator;
      75: astore_3
      76: aload_3
      77: invokeinterface #4,  1            // InterfaceMethod java/util/Iterator.hasNext:()Z
      82: ifeq          106
      85: aload_3
      86: invokeinterface #5,  1            // InterfaceMethod java/util/Iterator.next:()Ljava/lang/Object;
      91: checkcast     #100                // class java/lang/String
      94: astore        4
      96: aload_1
      97: aload         4
      99: invokevirtual #101                // Method org/bson/codecs/pojo/ClassModelBuilder.removeProperty:(Ljava/lang/String;)Z
     102: pop
     103: goto          76
     106: return
}
