Compiled from "ImmutableEntityEntry.java"
public final class org.hibernate.engine.internal.ImmutableEntityEntry extends org.hibernate.engine.internal.AbstractEntityEntry {
  public org.hibernate.engine.internal.ImmutableEntityEntry(org.hibernate.engine.spi.Status, java.lang.Object[], java.lang.Object, java.io.Serializable, java.lang.Object, org.hibernate.LockMode, boolean, org.hibernate.persister.entity.EntityPersister, org.hibernate.EntityMode, java.lang.String, boolean, boolean, org.hibernate.engine.spi.PersistenceContext);
    Code:
       0: aload_0
       1: aload_1
       2: aload_2
       3: aload_3
       4: aload         4
       6: aload         5
       8: aload         6
      10: iload         7
      12: aload         8
      14: iload         11
      16: iload         12
      18: aconst_null
      19: invokespecial #1                  // Method "<init>":(Lorg/hibernate/engine/spi/Status;[Ljava/lang/Object;Ljava/lang/Object;Ljava/io/Serializable;Ljava/lang/Object;Lorg/hibernate/LockMode;ZLorg/hibernate/persister/entity/EntityPersister;ZZLorg/hibernate/engine/spi/PersistenceContext;)V
      22: return

  public org.hibernate.engine.internal.ImmutableEntityEntry(org.hibernate.engine.spi.Status, java.lang.Object[], java.lang.Object, java.io.Serializable, java.lang.Object, org.hibernate.LockMode, boolean, org.hibernate.persister.entity.EntityPersister, boolean, boolean, org.hibernate.engine.spi.PersistenceContext);
    Code:
       0: aload_0
       1: aload_1
       2: aload_2
       3: aload_3
       4: aload         4
       6: aload         5
       8: aload         6
      10: iload         7
      12: aload         8
      14: iload         9
      16: iload         10
      18: aconst_null
      19: invokespecial #2                  // Method org/hibernate/engine/internal/AbstractEntityEntry."<init>":(Lorg/hibernate/engine/spi/Status;[Ljava/lang/Object;Ljava/lang/Object;Ljava/io/Serializable;Ljava/lang/Object;Lorg/hibernate/LockMode;ZLorg/hibernate/persister/entity/EntityPersister;ZZLorg/hibernate/engine/spi/PersistenceContext;)V
      22: return

  private org.hibernate.engine.internal.ImmutableEntityEntry(org.hibernate.engine.spi.SessionFactoryImplementor, java.lang.String, java.io.Serializable, org.hibernate.engine.spi.Status, org.hibernate.engine.spi.Status, java.lang.Object[], java.lang.Object[], java.lang.Object, org.hibernate.LockMode, boolean, boolean, boolean, org.hibernate.engine.spi.PersistenceContext);
    Code:
       0: aload_0
       1: aload_1
       2: aload_2
       3: aload_3
       4: aload         4
       6: aload         5
       8: aload         6
      10: aload         7
      12: aload         8
      14: aload         9
      16: iload         10
      18: iload         11
      20: iload         12
      22: aload         13
      24: invokespecial #3                  // Method org/hibernate/engine/internal/AbstractEntityEntry."<init>":(Lorg/hibernate/engine/spi/SessionFactoryImplementor;Ljava/lang/String;Ljava/io/Serializable;Lorg/hibernate/engine/spi/Status;Lorg/hibernate/engine/spi/Status;[Ljava/lang/Object;[Ljava/lang/Object;Ljava/lang/Object;Lorg/hibernate/LockMode;ZZZLorg/hibernate/engine/spi/PersistenceContext;)V
      27: return

  public void setLockMode(org.hibernate.LockMode);
    Code:
       0: getstatic     #4                  // Field org/hibernate/engine/internal/ImmutableEntityEntry$1.$SwitchMap$org$hibernate$LockMode:[I
       3: aload_1
       4: invokevirtual #5                  // Method org/hibernate/LockMode.ordinal:()I
       7: iaload
       8: lookupswitch  { // 2
                     1: 36
                     2: 36
               default: 47
          }
      36: aload_0
      37: getstatic     #6                  // Field org/hibernate/engine/internal/AbstractEntityEntry$EnumState.LOCK_MODE:Lorg/hibernate/engine/internal/AbstractEntityEntry$EnumState;
      40: aload_1
      41: invokevirtual #7                  // Method setCompressedValue:(Lorg/hibernate/engine/internal/AbstractEntityEntry$EnumState;Ljava/lang/Enum;)V
      44: goto          57
      47: new           #8                  // class org/hibernate/UnsupportedLockAttemptException
      50: dup
      51: ldc           #9                  // String Lock mode not supported
      53: invokespecial #10                 // Method org/hibernate/UnsupportedLockAttemptException."<init>":(Ljava/lang/String;)V
      56: athrow
      57: return

  public static org.hibernate.engine.spi.EntityEntry deserialize(java.io.ObjectInputStream, org.hibernate.engine.spi.PersistenceContext) throws java.io.IOException, java.lang.ClassNotFoundException;
    Code:
       0: new           #11                 // class org/hibernate/engine/internal/ImmutableEntityEntry
       3: dup
       4: aload_1
       5: invokeinterface #12,  1           // InterfaceMethod org/hibernate/engine/spi/PersistenceContext.getSession:()Lorg/hibernate/engine/spi/SessionImplementor;
      10: invokeinterface #13,  1           // InterfaceMethod org/hibernate/engine/spi/SessionImplementor.getFactory:()Lorg/hibernate/engine/spi/SessionFactoryImplementor;
      15: aload_0
      16: invokevirtual #14                 // Method java/io/ObjectInputStream.readObject:()Ljava/lang/Object;
      19: checkcast     #15                 // class java/lang/String
      22: aload_0
      23: invokevirtual #14                 // Method java/io/ObjectInputStream.readObject:()Ljava/lang/Object;
      26: checkcast     #16                 // class java/io/Serializable
      29: aload_0
      30: invokevirtual #14                 // Method java/io/ObjectInputStream.readObject:()Ljava/lang/Object;
      33: checkcast     #15                 // class java/lang/String
      36: invokestatic  #17                 // Method org/hibernate/engine/spi/Status.valueOf:(Ljava/lang/String;)Lorg/hibernate/engine/spi/Status;
      39: aload_0
      40: invokevirtual #14                 // Method java/io/ObjectInputStream.readObject:()Ljava/lang/Object;
      43: checkcast     #15                 // class java/lang/String
      46: dup
      47: astore_2
      48: invokevirtual #18                 // Method java/lang/String.length:()I
      51: ifne          58
      54: aconst_null
      55: goto          62
      58: aload_2
      59: invokestatic  #17                 // Method org/hibernate/engine/spi/Status.valueOf:(Ljava/lang/String;)Lorg/hibernate/engine/spi/Status;
      62: aload_0
      63: invokevirtual #14                 // Method java/io/ObjectInputStream.readObject:()Ljava/lang/Object;
      66: checkcast     #19                 // class "[Ljava/lang/Object;"
      69: checkcast     #19                 // class "[Ljava/lang/Object;"
      72: aload_0
      73: invokevirtual #14                 // Method java/io/ObjectInputStream.readObject:()Ljava/lang/Object;
      76: checkcast     #19                 // class "[Ljava/lang/Object;"
      79: checkcast     #19                 // class "[Ljava/lang/Object;"
      82: aload_0
      83: invokevirtual #14                 // Method java/io/ObjectInputStream.readObject:()Ljava/lang/Object;
      86: aload_0
      87: invokevirtual #14                 // Method java/io/ObjectInputStream.readObject:()Ljava/lang/Object;
      90: checkcast     #15                 // class java/lang/String
      93: invokestatic  #20                 // Method org/hibernate/LockMode.valueOf:(Ljava/lang/String;)Lorg/hibernate/LockMode;
      96: aload_0
      97: invokevirtual #21                 // Method java/io/ObjectInputStream.readBoolean:()Z
     100: aload_0
     101: invokevirtual #21                 // Method java/io/ObjectInputStream.readBoolean:()Z
     104: aload_0
     105: invokevirtual #21                 // Method java/io/ObjectInputStream.readBoolean:()Z
     108: aconst_null
     109: invokespecial #22                 // Method "<init>":(Lorg/hibernate/engine/spi/SessionFactoryImplementor;Ljava/lang/String;Ljava/io/Serializable;Lorg/hibernate/engine/spi/Status;Lorg/hibernate/engine/spi/Status;[Ljava/lang/Object;[Ljava/lang/Object;Ljava/lang/Object;Lorg/hibernate/LockMode;ZZZLorg/hibernate/engine/spi/PersistenceContext;)V
     112: areturn

  public org.hibernate.engine.spi.PersistenceContext getPersistenceContext();
    Code:
       0: new           #23                 // class org/hibernate/AssertionFailure
       3: dup
       4: ldc           #24                 // String Session/PersistenceContext is not available from an ImmutableEntityEntry
       6: invokespecial #25                 // Method org/hibernate/AssertionFailure."<init>":(Ljava/lang/String;)V
       9: athrow
}
