Compiled from "JoinHelper.java"
public final class org.hibernate.engine.internal.JoinHelper {
  public static java.lang.String[] getAliasedLHSColumnNames(org.hibernate.type.AssociationType, java.lang.String, int, org.hibernate.persister.entity.OuterJoinLoadable, org.hibernate.engine.spi.Mapping);
    Code:
       0: aload_0
       1: aload_1
       2: iload_2
       3: iconst_0
       4: aload_3
       5: aload         4
       7: invokestatic  #1                  // Method getAliasedLHSColumnNames:(Lorg/hibernate/type/AssociationType;Ljava/lang/String;IILorg/hibernate/persister/entity/OuterJoinLoadable;Lorg/hibernate/engine/spi/Mapping;)[Ljava/lang/String;
      10: areturn

  public static java.lang.String[] getLHSColumnNames(org.hibernate.type.AssociationType, int, org.hibernate.persister.entity.OuterJoinLoadable, org.hibernate.engine.spi.Mapping);
    Code:
       0: aload_0
       1: iload_1
       2: iconst_0
       3: aload_2
       4: aload_3
       5: invokestatic  #2                  // Method getLHSColumnNames:(Lorg/hibernate/type/AssociationType;IILorg/hibernate/persister/entity/OuterJoinLoadable;Lorg/hibernate/engine/spi/Mapping;)[Ljava/lang/String;
       8: areturn

  public static java.lang.String[] getAliasedLHSColumnNames(org.hibernate.type.AssociationType, java.lang.String, int, int, org.hibernate.persister.entity.OuterJoinLoadable, org.hibernate.engine.spi.Mapping);
    Code:
       0: aload_0
       1: invokeinterface #3,  1            // InterfaceMethod org/hibernate/type/AssociationType.useLHSPrimaryKey:()Z
       6: ifeq          21
       9: aload_1
      10: aload         4
      12: invokeinterface #4,  1            // InterfaceMethod org/hibernate/persister/entity/OuterJoinLoadable.getIdentifierColumnNames:()[Ljava/lang/String;
      17: invokestatic  #5                  // Method org/hibernate/internal/util/StringHelper.qualify:(Ljava/lang/String;[Ljava/lang/String;)[Ljava/lang/String;
      20: areturn
      21: aload_0
      22: invokeinterface #6,  1            // InterfaceMethod org/hibernate/type/AssociationType.getLHSPropertyName:()Ljava/lang/String;
      27: astore        6
      29: aload         6
      31: ifnonnull     54
      34: aload         4
      36: aload_1
      37: iload_2
      38: invokestatic  #7                  // Method toColumns:(Lorg/hibernate/persister/entity/OuterJoinLoadable;Ljava/lang/String;I)[Ljava/lang/String;
      41: iload_3
      42: aload_0
      43: aload         5
      45: invokeinterface #8,  2            // InterfaceMethod org/hibernate/type/AssociationType.getColumnSpan:(Lorg/hibernate/engine/spi/Mapping;)I
      50: invokestatic  #9                  // Method org/hibernate/internal/util/collections/ArrayHelper.slice:([Ljava/lang/String;II)[Ljava/lang/String;
      53: areturn
      54: aload         4
      56: checkcast     #10                 // class org/hibernate/persister/entity/PropertyMapping
      59: aload_1
      60: aload         6
      62: invokeinterface #11,  3           // InterfaceMethod org/hibernate/persister/entity/PropertyMapping.toColumns:(Ljava/lang/String;Ljava/lang/String;)[Ljava/lang/String;
      67: areturn

  private static java.lang.String[] toColumns(org.hibernate.persister.entity.OuterJoinLoadable, java.lang.String, int);
    Code:
       0: iload_2
       1: iflt          13
       4: aload_0
       5: aload_1
       6: iload_2
       7: invokeinterface #12,  3           // InterfaceMethod org/hibernate/persister/entity/OuterJoinLoadable.toColumns:(Ljava/lang/String;I)[Ljava/lang/String;
      12: areturn
      13: aload_0
      14: invokeinterface #4,  1            // InterfaceMethod org/hibernate/persister/entity/OuterJoinLoadable.getIdentifierColumnNames:()[Ljava/lang/String;
      19: astore_3
      20: aload_3
      21: arraylength
      22: anewarray     #13                 // class java/lang/String
      25: astore        4
      27: iconst_0
      28: istore        5
      30: iload         5
      32: aload_3
      33: arraylength
      34: if_icmpge     56
      37: aload         4
      39: iload         5
      41: aload_1
      42: aload_3
      43: iload         5
      45: aaload
      46: invokestatic  #14                 // Method org/hibernate/internal/util/StringHelper.qualify:(Ljava/lang/String;Ljava/lang/String;)Ljava/lang/String;
      49: aastore
      50: iinc          5, 1
      53: goto          30
      56: aload         4
      58: areturn

  public static java.lang.String[] getLHSColumnNames(org.hibernate.type.AssociationType, int, int, org.hibernate.persister.entity.OuterJoinLoadable, org.hibernate.engine.spi.Mapping);
    Code:
       0: aload_0
       1: invokeinterface #3,  1            // InterfaceMethod org/hibernate/type/AssociationType.useLHSPrimaryKey:()Z
       6: ifeq          16
       9: aload_3
      10: invokeinterface #4,  1            // InterfaceMethod org/hibernate/persister/entity/OuterJoinLoadable.getIdentifierColumnNames:()[Ljava/lang/String;
      15: areturn
      16: aload_0
      17: invokeinterface #6,  1            // InterfaceMethod org/hibernate/type/AssociationType.getLHSPropertyName:()Ljava/lang/String;
      22: astore        5
      24: aload         5
      26: ifnonnull     62
      29: iload_1
      30: ifge          42
      33: aload_3
      34: invokeinterface #4,  1            // InterfaceMethod org/hibernate/persister/entity/OuterJoinLoadable.getIdentifierColumnNames:()[Ljava/lang/String;
      39: goto          49
      42: aload_3
      43: iload_1
      44: invokeinterface #15,  2           // InterfaceMethod org/hibernate/persister/entity/OuterJoinLoadable.getSubclassPropertyColumnNames:(I)[Ljava/lang/String;
      49: iload_2
      50: aload_0
      51: aload         4
      53: invokeinterface #8,  2            // InterfaceMethod org/hibernate/type/AssociationType.getColumnSpan:(Lorg/hibernate/engine/spi/Mapping;)I
      58: invokestatic  #9                  // Method org/hibernate/internal/util/collections/ArrayHelper.slice:([Ljava/lang/String;II)[Ljava/lang/String;
      61: areturn
      62: aload_3
      63: aload         5
      65: invokeinterface #16,  2           // InterfaceMethod org/hibernate/persister/entity/OuterJoinLoadable.getPropertyColumnNames:(Ljava/lang/String;)[Ljava/lang/String;
      70: areturn

  public static java.lang.String getLHSTableName(org.hibernate.type.AssociationType, int, org.hibernate.persister.entity.OuterJoinLoadable);
    Code:
       0: aload_0
       1: invokeinterface #3,  1            // InterfaceMethod org/hibernate/type/AssociationType.useLHSPrimaryKey:()Z
       6: ifne          13
       9: iload_1
      10: ifge          20
      13: aload_2
      14: invokeinterface #17,  1           // InterfaceMethod org/hibernate/persister/entity/OuterJoinLoadable.getTableName:()Ljava/lang/String;
      19: areturn
      20: aload_0
      21: invokeinterface #6,  1            // InterfaceMethod org/hibernate/type/AssociationType.getLHSPropertyName:()Ljava/lang/String;
      26: astore_3
      27: aload_3
      28: ifnonnull     39
      31: aload_2
      32: iload_1
      33: invokeinterface #18,  2           // InterfaceMethod org/hibernate/persister/entity/OuterJoinLoadable.getSubclassPropertyTableName:(I)Ljava/lang/String;
      38: areturn
      39: aload_2
      40: aload_3
      41: invokeinterface #19,  2           // InterfaceMethod org/hibernate/persister/entity/OuterJoinLoadable.getPropertyTableName:(Ljava/lang/String;)Ljava/lang/String;
      46: astore        4
      48: aload         4
      50: ifnonnull     62
      53: aload_2
      54: iload_1
      55: invokeinterface #18,  2           // InterfaceMethod org/hibernate/persister/entity/OuterJoinLoadable.getSubclassPropertyTableName:(I)Ljava/lang/String;
      60: astore        4
      62: aload         4
      64: areturn

  public static java.lang.String[] getRHSColumnNames(org.hibernate.type.AssociationType, org.hibernate.engine.spi.SessionFactoryImplementor);
    Code:
       0: aload_0
       1: invokeinterface #20,  1           // InterfaceMethod org/hibernate/type/AssociationType.getRHSUniqueKeyPropertyName:()Ljava/lang/String;
       6: astore_2
       7: aload_0
       8: aload_1
       9: invokeinterface #21,  2           // InterfaceMethod org/hibernate/type/AssociationType.getAssociatedJoinable:(Lorg/hibernate/engine/spi/SessionFactoryImplementor;)Lorg/hibernate/persister/entity/Joinable;
      14: astore_3
      15: aload_2
      16: ifnonnull     26
      19: aload_3
      20: invokeinterface #22,  1           // InterfaceMethod org/hibernate/persister/entity/Joinable.getKeyColumnNames:()[Ljava/lang/String;
      25: areturn
      26: aload_3
      27: checkcast     #23                 // class org/hibernate/persister/entity/OuterJoinLoadable
      30: aload_2
      31: invokeinterface #16,  2           // InterfaceMethod org/hibernate/persister/entity/OuterJoinLoadable.getPropertyColumnNames:(Ljava/lang/String;)[Ljava/lang/String;
      36: areturn

  private org.hibernate.engine.internal.JoinHelper();
    Code:
       0: aload_0
       1: invokespecial #24                 // Method java/lang/Object."<init>":()V
       4: return
}
