Compiled from "FastDateFormat.java"
class org.apache.commons.lang.time.FastDateFormat$UnpaddedMonthField implements org.apache.commons.lang.time.FastDateFormat$NumberRule {
  static final org.apache.commons.lang.time.FastDateFormat$UnpaddedMonthField INSTANCE;

  org.apache.commons.lang.time.FastDateFormat$UnpaddedMonthField();
    Code:
       0: aload_0
       1: invokespecial #17                 // Method java/lang/Object."<init>":()V
       4: return

  public int estimateLength();
    Code:
       0: iconst_2
       1: ireturn

  public void appendTo(java.lang.StringBuffer, java.util.Calendar);
    Code:
       0: aload_0
       1: aload_1
       2: aload_2
       3: iconst_2
       4: invokevirtual #28                 // Method java/util/Calendar.get:(I)I
       7: iconst_1
       8: iadd
       9: invokevirtual #31                 // Method appendTo:(Ljava/lang/StringBuffer;I)V
      12: return

  public final void appendTo(java.lang.StringBuffer, int);
    Code:
       0: iload_2
       1: bipush        10
       3: if_icmpge     19
       6: aload_1
       7: iload_2
       8: bipush        48
      10: iadd
      11: i2c
      12: invokevirtual #41                 // Method java/lang/StringBuffer.append:(C)Ljava/lang/StringBuffer;
      15: pop
      16: goto          45
      19: aload_1
      20: iload_2
      21: bipush        10
      23: idiv
      24: bipush        48
      26: iadd
      27: i2c
      28: invokevirtual #41                 // Method java/lang/StringBuffer.append:(C)Ljava/lang/StringBuffer;
      31: pop
      32: aload_1
      33: iload_2
      34: bipush        10
      36: irem
      37: bipush        48
      39: iadd
      40: i2c
      41: invokevirtual #41                 // Method java/lang/StringBuffer.append:(C)Ljava/lang/StringBuffer;
      44: pop
      45: return

  static {};
    Code:
       0: new           #2                  // class org/apache/commons/lang/time/FastDateFormat$UnpaddedMonthField
       3: dup
       4: invokespecial #45                 // Method "<init>":()V
       7: putstatic     #47                 // Field INSTANCE:Lorg/apache/commons/lang/time/FastDateFormat$UnpaddedMonthField;
      10: return
}
