Compiled from "Preloader.java"
public class javafx.application.Preloader$ErrorNotification implements javafx.application.Preloader$PreloaderNotification {
  private java.lang.String location;

  private java.lang.String details;

  private java.lang.Throwable cause;

  public javafx.application.Preloader$ErrorNotification(java.lang.String, java.lang.String, java.lang.Throwable);
    Code:
       0: aload_0
       1: invokespecial #1                  // Method java/lang/Object."<init>":()V
       4: aload_0
       5: ldc           #2                  // String
       7: putfield      #3                  // Field details:Ljava/lang/String;
      10: aload_2
      11: ifnonnull     22
      14: new           #4                  // class java/lang/NullPointerException
      17: dup
      18: invokespecial #5                  // Method java/lang/NullPointerException."<init>":()V
      21: athrow
      22: aload_0
      23: aload_1
      24: putfield      #6                  // Field location:Ljava/lang/String;
      27: aload_0
      28: aload_2
      29: putfield      #3                  // Field details:Ljava/lang/String;
      32: aload_0
      33: aload_3
      34: putfield      #7                  // Field cause:Ljava/lang/Throwable;
      37: return

  public java.lang.String getLocation();
    Code:
       0: aload_0
       1: getfield      #6                  // Field location:Ljava/lang/String;
       4: areturn

  public java.lang.String getDetails();
    Code:
       0: aload_0
       1: getfield      #3                  // Field details:Ljava/lang/String;
       4: areturn

  public java.lang.Throwable getCause();
    Code:
       0: aload_0
       1: getfield      #7                  // Field cause:Ljava/lang/Throwable;
       4: areturn

  public java.lang.String toString();
    Code:
       0: new           #8                  // class java/lang/StringBuilder
       3: dup
       4: ldc           #9                  // String Preloader.ErrorNotification:
       6: invokespecial #10                 // Method java/lang/StringBuilder."<init>":(Ljava/lang/String;)V
       9: astore_1
      10: aload_1
      11: aload_0
      12: getfield      #3                  // Field details:Ljava/lang/String;
      15: invokevirtual #11                 // Method java/lang/StringBuilder.append:(Ljava/lang/String;)Ljava/lang/StringBuilder;
      18: pop
      19: aload_0
      20: getfield      #7                  // Field cause:Ljava/lang/Throwable;
      23: ifnull        49
      26: aload_1
      27: invokestatic  #12                 // Method javafx/application/Preloader.access$000:()Ljava/lang/String;
      30: invokevirtual #11                 // Method java/lang/StringBuilder.append:(Ljava/lang/String;)Ljava/lang/StringBuilder;
      33: ldc           #13                 // String Caused by:
      35: invokevirtual #11                 // Method java/lang/StringBuilder.append:(Ljava/lang/String;)Ljava/lang/StringBuilder;
      38: aload_0
      39: getfield      #7                  // Field cause:Ljava/lang/Throwable;
      42: invokevirtual #14                 // Method java/lang/Throwable.toString:()Ljava/lang/String;
      45: invokevirtual #11                 // Method java/lang/StringBuilder.append:(Ljava/lang/String;)Ljava/lang/StringBuilder;
      48: pop
      49: aload_0
      50: getfield      #6                  // Field location:Ljava/lang/String;
      53: ifnull        76
      56: aload_1
      57: invokestatic  #12                 // Method javafx/application/Preloader.access$000:()Ljava/lang/String;
      60: invokevirtual #11                 // Method java/lang/StringBuilder.append:(Ljava/lang/String;)Ljava/lang/StringBuilder;
      63: ldc           #15                 // String Location:
      65: invokevirtual #11                 // Method java/lang/StringBuilder.append:(Ljava/lang/String;)Ljava/lang/StringBuilder;
      68: aload_0
      69: getfield      #6                  // Field location:Ljava/lang/String;
      72: invokevirtual #11                 // Method java/lang/StringBuilder.append:(Ljava/lang/String;)Ljava/lang/StringBuilder;
      75: pop
      76: aload_1
      77: invokevirtual #16                 // Method java/lang/StringBuilder.toString:()Ljava/lang/String;
      80: areturn
}
