Compiled from "Edge.java"
public interface software.amazon.awssdk.services.xray.model.Edge$Builder extends software.amazon.awssdk.core.SdkPojo, software.amazon.awssdk.utils.builder.CopyableBuilder<software.amazon.awssdk.services.xray.model.Edge$Builder, software.amazon.awssdk.services.xray.model.Edge> {
  public abstract software.amazon.awssdk.services.xray.model.Edge$Builder referenceId(java.lang.Integer);

  public abstract software.amazon.awssdk.services.xray.model.Edge$Builder startTime(java.time.Instant);

  public abstract software.amazon.awssdk.services.xray.model.Edge$Builder endTime(java.time.Instant);

  public abstract software.amazon.awssdk.services.xray.model.Edge$Builder summaryStatistics(software.amazon.awssdk.services.xray.model.EdgeStatistics);

  public default software.amazon.awssdk.services.xray.model.Edge$Builder summaryStatistics(java.util.function.Consumer<software.amazon.awssdk.services.xray.model.EdgeStatistics$Builder>);
    Code:
       0: aload_0
       1: invokestatic  #1                  // Method software/amazon/awssdk/services/xray/model/EdgeStatistics.builder:()Lsoftware/amazon/awssdk/services/xray/model/EdgeStatistics$Builder;
       4: aload_1
       5: invokeinterface #2,  2            // InterfaceMethod software/amazon/awssdk/services/xray/model/EdgeStatistics$Builder.applyMutation:(Ljava/util/function/Consumer;)Lsoftware/amazon/awssdk/utils/builder/SdkBuilder;
      10: checkcast     #3                  // class software/amazon/awssdk/services/xray/model/EdgeStatistics$Builder
      13: invokeinterface #4,  1            // InterfaceMethod software/amazon/awssdk/services/xray/model/EdgeStatistics$Builder.build:()Ljava/lang/Object;
      18: checkcast     #5                  // class software/amazon/awssdk/services/xray/model/EdgeStatistics
      21: invokeinterface #6,  2            // InterfaceMethod summaryStatistics:(Lsoftware/amazon/awssdk/services/xray/model/EdgeStatistics;)Lsoftware/amazon/awssdk/services/xray/model/Edge$Builder;
      26: areturn

  public abstract software.amazon.awssdk.services.xray.model.Edge$Builder responseTimeHistogram(java.util.Collection<software.amazon.awssdk.services.xray.model.HistogramEntry>);

  public abstract software.amazon.awssdk.services.xray.model.Edge$Builder responseTimeHistogram(software.amazon.awssdk.services.xray.model.HistogramEntry...);

  public abstract software.amazon.awssdk.services.xray.model.Edge$Builder responseTimeHistogram(java.util.function.Consumer<software.amazon.awssdk.services.xray.model.HistogramEntry$Builder>...);

  public abstract software.amazon.awssdk.services.xray.model.Edge$Builder aliases(java.util.Collection<software.amazon.awssdk.services.xray.model.Alias>);

  public abstract software.amazon.awssdk.services.xray.model.Edge$Builder aliases(software.amazon.awssdk.services.xray.model.Alias...);

  public abstract software.amazon.awssdk.services.xray.model.Edge$Builder aliases(java.util.function.Consumer<software.amazon.awssdk.services.xray.model.Alias$Builder>...);
}
