Compiled from "GetTraceSummariesRequest.java"
final class software.amazon.awssdk.services.xray.model.GetTraceSummariesRequest$BuilderImpl extends software.amazon.awssdk.services.xray.model.XRayRequest$BuilderImpl implements software.amazon.awssdk.services.xray.model.GetTraceSummariesRequest$Builder {
  private java.time.Instant startTime;

  private java.time.Instant endTime;

  private java.lang.String timeRangeType;

  private java.lang.Boolean sampling;

  private software.amazon.awssdk.services.xray.model.SamplingStrategy samplingStrategy;

  private java.lang.String filterExpression;

  private java.lang.String nextToken;

  private software.amazon.awssdk.services.xray.model.GetTraceSummariesRequest$BuilderImpl();
    Code:
       0: aload_0
       1: invokespecial #10                 // Method software/amazon/awssdk/services/xray/model/XRayRequest$BuilderImpl."<init>":()V
       4: return

  private software.amazon.awssdk.services.xray.model.GetTraceSummariesRequest$BuilderImpl(software.amazon.awssdk.services.xray.model.GetTraceSummariesRequest);
    Code:
       0: aload_0
       1: aload_1
       2: invokespecial #11                 // Method software/amazon/awssdk/services/xray/model/XRayRequest$BuilderImpl."<init>":(Lsoftware/amazon/awssdk/services/xray/model/XRayRequest;)V
       5: aload_0
       6: aload_1
       7: invokestatic  #12                 // Method software/amazon/awssdk/services/xray/model/GetTraceSummariesRequest.access$900:(Lsoftware/amazon/awssdk/services/xray/model/GetTraceSummariesRequest;)Ljava/time/Instant;
      10: invokevirtual #13                 // Method startTime:(Ljava/time/Instant;)Lsoftware/amazon/awssdk/services/xray/model/GetTraceSummariesRequest$Builder;
      13: pop
      14: aload_0
      15: aload_1
      16: invokestatic  #14                 // Method software/amazon/awssdk/services/xray/model/GetTraceSummariesRequest.access$1000:(Lsoftware/amazon/awssdk/services/xray/model/GetTraceSummariesRequest;)Ljava/time/Instant;
      19: invokevirtual #15                 // Method endTime:(Ljava/time/Instant;)Lsoftware/amazon/awssdk/services/xray/model/GetTraceSummariesRequest$Builder;
      22: pop
      23: aload_0
      24: aload_1
      25: invokestatic  #16                 // Method software/amazon/awssdk/services/xray/model/GetTraceSummariesRequest.access$1100:(Lsoftware/amazon/awssdk/services/xray/model/GetTraceSummariesRequest;)Ljava/lang/String;
      28: invokevirtual #17                 // Method timeRangeType:(Ljava/lang/String;)Lsoftware/amazon/awssdk/services/xray/model/GetTraceSummariesRequest$Builder;
      31: pop
      32: aload_0
      33: aload_1
      34: invokestatic  #18                 // Method software/amazon/awssdk/services/xray/model/GetTraceSummariesRequest.access$1200:(Lsoftware/amazon/awssdk/services/xray/model/GetTraceSummariesRequest;)Ljava/lang/Boolean;
      37: invokevirtual #19                 // Method sampling:(Ljava/lang/Boolean;)Lsoftware/amazon/awssdk/services/xray/model/GetTraceSummariesRequest$Builder;
      40: pop
      41: aload_0
      42: aload_1
      43: invokestatic  #20                 // Method software/amazon/awssdk/services/xray/model/GetTraceSummariesRequest.access$1300:(Lsoftware/amazon/awssdk/services/xray/model/GetTraceSummariesRequest;)Lsoftware/amazon/awssdk/services/xray/model/SamplingStrategy;
      46: invokevirtual #21                 // Method samplingStrategy:(Lsoftware/amazon/awssdk/services/xray/model/SamplingStrategy;)Lsoftware/amazon/awssdk/services/xray/model/GetTraceSummariesRequest$Builder;
      49: pop
      50: aload_0
      51: aload_1
      52: invokestatic  #22                 // Method software/amazon/awssdk/services/xray/model/GetTraceSummariesRequest.access$1400:(Lsoftware/amazon/awssdk/services/xray/model/GetTraceSummariesRequest;)Ljava/lang/String;
      55: invokevirtual #23                 // Method filterExpression:(Ljava/lang/String;)Lsoftware/amazon/awssdk/services/xray/model/GetTraceSummariesRequest$Builder;
      58: pop
      59: aload_0
      60: aload_1
      61: invokestatic  #24                 // Method software/amazon/awssdk/services/xray/model/GetTraceSummariesRequest.access$1500:(Lsoftware/amazon/awssdk/services/xray/model/GetTraceSummariesRequest;)Ljava/lang/String;
      64: invokevirtual #25                 // Method nextToken:(Ljava/lang/String;)Lsoftware/amazon/awssdk/services/xray/model/GetTraceSummariesRequest$Builder;
      67: pop
      68: return

  public final java.time.Instant getStartTime();
    Code:
       0: aload_0
       1: getfield      #9                  // Field startTime:Ljava/time/Instant;
       4: areturn

  public final void setStartTime(java.time.Instant);
    Code:
       0: aload_0
       1: aload_1
       2: putfield      #9                  // Field startTime:Ljava/time/Instant;
       5: return

  public final software.amazon.awssdk.services.xray.model.GetTraceSummariesRequest$Builder startTime(java.time.Instant);
    Code:
       0: aload_0
       1: aload_1
       2: putfield      #9                  // Field startTime:Ljava/time/Instant;
       5: aload_0
       6: areturn

  public final java.time.Instant getEndTime();
    Code:
       0: aload_0
       1: getfield      #8                  // Field endTime:Ljava/time/Instant;
       4: areturn

  public final void setEndTime(java.time.Instant);
    Code:
       0: aload_0
       1: aload_1
       2: putfield      #8                  // Field endTime:Ljava/time/Instant;
       5: return

  public final software.amazon.awssdk.services.xray.model.GetTraceSummariesRequest$Builder endTime(java.time.Instant);
    Code:
       0: aload_0
       1: aload_1
       2: putfield      #8                  // Field endTime:Ljava/time/Instant;
       5: aload_0
       6: areturn

  public final java.lang.String getTimeRangeType();
    Code:
       0: aload_0
       1: getfield      #7                  // Field timeRangeType:Ljava/lang/String;
       4: areturn

  public final void setTimeRangeType(java.lang.String);
    Code:
       0: aload_0
       1: aload_1
       2: putfield      #7                  // Field timeRangeType:Ljava/lang/String;
       5: return

  public final software.amazon.awssdk.services.xray.model.GetTraceSummariesRequest$Builder timeRangeType(java.lang.String);
    Code:
       0: aload_0
       1: aload_1
       2: putfield      #7                  // Field timeRangeType:Ljava/lang/String;
       5: aload_0
       6: areturn

  public final software.amazon.awssdk.services.xray.model.GetTraceSummariesRequest$Builder timeRangeType(software.amazon.awssdk.services.xray.model.TimeRangeType);
    Code:
       0: aload_0
       1: aload_1
       2: ifnonnull     9
       5: aconst_null
       6: goto          13
       9: aload_1
      10: invokevirtual #26                 // Method software/amazon/awssdk/services/xray/model/TimeRangeType.toString:()Ljava/lang/String;
      13: invokevirtual #17                 // Method timeRangeType:(Ljava/lang/String;)Lsoftware/amazon/awssdk/services/xray/model/GetTraceSummariesRequest$Builder;
      16: pop
      17: aload_0
      18: areturn

  public final java.lang.Boolean getSampling();
    Code:
       0: aload_0
       1: getfield      #6                  // Field sampling:Ljava/lang/Boolean;
       4: areturn

  public final void setSampling(java.lang.Boolean);
    Code:
       0: aload_0
       1: aload_1
       2: putfield      #6                  // Field sampling:Ljava/lang/Boolean;
       5: return

  public final software.amazon.awssdk.services.xray.model.GetTraceSummariesRequest$Builder sampling(java.lang.Boolean);
    Code:
       0: aload_0
       1: aload_1
       2: putfield      #6                  // Field sampling:Ljava/lang/Boolean;
       5: aload_0
       6: areturn

  public final software.amazon.awssdk.services.xray.model.SamplingStrategy$Builder getSamplingStrategy();
    Code:
       0: aload_0
       1: getfield      #5                  // Field samplingStrategy:Lsoftware/amazon/awssdk/services/xray/model/SamplingStrategy;
       4: ifnull        17
       7: aload_0
       8: getfield      #5                  // Field samplingStrategy:Lsoftware/amazon/awssdk/services/xray/model/SamplingStrategy;
      11: invokevirtual #27                 // Method software/amazon/awssdk/services/xray/model/SamplingStrategy.toBuilder:()Lsoftware/amazon/awssdk/services/xray/model/SamplingStrategy$Builder;
      14: goto          18
      17: aconst_null
      18: areturn

  public final void setSamplingStrategy(software.amazon.awssdk.services.xray.model.SamplingStrategy$BuilderImpl);
    Code:
       0: aload_0
       1: aload_1
       2: ifnull        12
       5: aload_1
       6: invokevirtual #28                 // Method software/amazon/awssdk/services/xray/model/SamplingStrategy$BuilderImpl.build:()Lsoftware/amazon/awssdk/services/xray/model/SamplingStrategy;
       9: goto          13
      12: aconst_null
      13: putfield      #5                  // Field samplingStrategy:Lsoftware/amazon/awssdk/services/xray/model/SamplingStrategy;
      16: return

  public final software.amazon.awssdk.services.xray.model.GetTraceSummariesRequest$Builder samplingStrategy(software.amazon.awssdk.services.xray.model.SamplingStrategy);
    Code:
       0: aload_0
       1: aload_1
       2: putfield      #5                  // Field samplingStrategy:Lsoftware/amazon/awssdk/services/xray/model/SamplingStrategy;
       5: aload_0
       6: areturn

  public final java.lang.String getFilterExpression();
    Code:
       0: aload_0
       1: getfield      #4                  // Field filterExpression:Ljava/lang/String;
       4: areturn

  public final void setFilterExpression(java.lang.String);
    Code:
       0: aload_0
       1: aload_1
       2: putfield      #4                  // Field filterExpression:Ljava/lang/String;
       5: return

  public final software.amazon.awssdk.services.xray.model.GetTraceSummariesRequest$Builder filterExpression(java.lang.String);
    Code:
       0: aload_0
       1: aload_1
       2: putfield      #4                  // Field filterExpression:Ljava/lang/String;
       5: aload_0
       6: areturn

  public final java.lang.String getNextToken();
    Code:
       0: aload_0
       1: getfield      #3                  // Field nextToken:Ljava/lang/String;
       4: areturn

  public final void setNextToken(java.lang.String);
    Code:
       0: aload_0
       1: aload_1
       2: putfield      #3                  // Field nextToken:Ljava/lang/String;
       5: return

  public final software.amazon.awssdk.services.xray.model.GetTraceSummariesRequest$Builder nextToken(java.lang.String);
    Code:
       0: aload_0
       1: aload_1
       2: putfield      #3                  // Field nextToken:Ljava/lang/String;
       5: aload_0
       6: areturn

  public software.amazon.awssdk.services.xray.model.GetTraceSummariesRequest$Builder overrideConfiguration(software.amazon.awssdk.awscore.AwsRequestOverrideConfiguration);
    Code:
       0: aload_0
       1: aload_1
       2: invokespecial #29                 // Method software/amazon/awssdk/services/xray/model/XRayRequest$BuilderImpl.overrideConfiguration:(Lsoftware/amazon/awssdk/awscore/AwsRequestOverrideConfiguration;)Lsoftware/amazon/awssdk/awscore/AwsRequest$Builder;
       5: pop
       6: aload_0
       7: areturn

  public software.amazon.awssdk.services.xray.model.GetTraceSummariesRequest$Builder overrideConfiguration(java.util.function.Consumer<software.amazon.awssdk.awscore.AwsRequestOverrideConfiguration$Builder>);
    Code:
       0: aload_0
       1: aload_1
       2: invokespecial #30                 // Method software/amazon/awssdk/services/xray/model/XRayRequest$BuilderImpl.overrideConfiguration:(Ljava/util/function/Consumer;)Lsoftware/amazon/awssdk/awscore/AwsRequest$Builder;
       5: pop
       6: aload_0
       7: areturn

  public software.amazon.awssdk.services.xray.model.GetTraceSummariesRequest build();
    Code:
       0: new           #31                 // class software/amazon/awssdk/services/xray/model/GetTraceSummariesRequest
       3: dup
       4: aload_0
       5: aconst_null
       6: invokespecial #32                 // Method software/amazon/awssdk/services/xray/model/GetTraceSummariesRequest."<init>":(Lsoftware/amazon/awssdk/services/xray/model/GetTraceSummariesRequest$BuilderImpl;Lsoftware/amazon/awssdk/services/xray/model/GetTraceSummariesRequest$1;)V
       9: areturn

  public java.util.List<software.amazon.awssdk.core.SdkField<?>> sdkFields();
    Code:
       0: invokestatic  #33                 // Method software/amazon/awssdk/services/xray/model/GetTraceSummariesRequest.access$1700:()Ljava/util/List;
       3: areturn

  public software.amazon.awssdk.services.xray.model.XRayRequest build();
    Code:
       0: aload_0
       1: invokevirtual #34                 // Method build:()Lsoftware/amazon/awssdk/services/xray/model/GetTraceSummariesRequest;
       4: areturn

  public software.amazon.awssdk.awscore.AwsRequest build();
    Code:
       0: aload_0
       1: invokevirtual #34                 // Method build:()Lsoftware/amazon/awssdk/services/xray/model/GetTraceSummariesRequest;
       4: areturn

  public software.amazon.awssdk.awscore.AwsRequest$Builder overrideConfiguration(java.util.function.Consumer);
    Code:
       0: aload_0
       1: aload_1
       2: invokevirtual #35                 // Method overrideConfiguration:(Ljava/util/function/Consumer;)Lsoftware/amazon/awssdk/services/xray/model/GetTraceSummariesRequest$Builder;
       5: areturn

  public software.amazon.awssdk.awscore.AwsRequest$Builder overrideConfiguration(software.amazon.awssdk.awscore.AwsRequestOverrideConfiguration);
    Code:
       0: aload_0
       1: aload_1
       2: invokevirtual #36                 // Method overrideConfiguration:(Lsoftware/amazon/awssdk/awscore/AwsRequestOverrideConfiguration;)Lsoftware/amazon/awssdk/services/xray/model/GetTraceSummariesRequest$Builder;
       5: areturn

  public software.amazon.awssdk.core.SdkRequest build();
    Code:
       0: aload_0
       1: invokevirtual #34                 // Method build:()Lsoftware/amazon/awssdk/services/xray/model/GetTraceSummariesRequest;
       4: areturn

  public java.lang.Object build();
    Code:
       0: aload_0
       1: invokevirtual #34                 // Method build:()Lsoftware/amazon/awssdk/services/xray/model/GetTraceSummariesRequest;
       4: areturn

  static java.time.Instant access$000(software.amazon.awssdk.services.xray.model.GetTraceSummariesRequest$BuilderImpl);
    Code:
       0: aload_0
       1: getfield      #9                  // Field startTime:Ljava/time/Instant;
       4: areturn

  static java.time.Instant access$100(software.amazon.awssdk.services.xray.model.GetTraceSummariesRequest$BuilderImpl);
    Code:
       0: aload_0
       1: getfield      #8                  // Field endTime:Ljava/time/Instant;
       4: areturn

  static java.lang.String access$200(software.amazon.awssdk.services.xray.model.GetTraceSummariesRequest$BuilderImpl);
    Code:
       0: aload_0
       1: getfield      #7                  // Field timeRangeType:Ljava/lang/String;
       4: areturn

  static java.lang.Boolean access$300(software.amazon.awssdk.services.xray.model.GetTraceSummariesRequest$BuilderImpl);
    Code:
       0: aload_0
       1: getfield      #6                  // Field sampling:Ljava/lang/Boolean;
       4: areturn

  static software.amazon.awssdk.services.xray.model.SamplingStrategy access$400(software.amazon.awssdk.services.xray.model.GetTraceSummariesRequest$BuilderImpl);
    Code:
       0: aload_0
       1: getfield      #5                  // Field samplingStrategy:Lsoftware/amazon/awssdk/services/xray/model/SamplingStrategy;
       4: areturn

  static java.lang.String access$500(software.amazon.awssdk.services.xray.model.GetTraceSummariesRequest$BuilderImpl);
    Code:
       0: aload_0
       1: getfield      #4                  // Field filterExpression:Ljava/lang/String;
       4: areturn

  static java.lang.String access$600(software.amazon.awssdk.services.xray.model.GetTraceSummariesRequest$BuilderImpl);
    Code:
       0: aload_0
       1: getfield      #3                  // Field nextToken:Ljava/lang/String;
       4: areturn

  software.amazon.awssdk.services.xray.model.GetTraceSummariesRequest$BuilderImpl(software.amazon.awssdk.services.xray.model.GetTraceSummariesRequest, software.amazon.awssdk.services.xray.model.GetTraceSummariesRequest$1);
    Code:
       0: aload_0
       1: aload_1
       2: invokespecial #2                  // Method "<init>":(Lsoftware/amazon/awssdk/services/xray/model/GetTraceSummariesRequest;)V
       5: return

  software.amazon.awssdk.services.xray.model.GetTraceSummariesRequest$BuilderImpl(software.amazon.awssdk.services.xray.model.GetTraceSummariesRequest$1);
    Code:
       0: aload_0
       1: invokespecial #1                  // Method "<init>":()V
       4: return
}
