Compiled from "GetTimeSeriesServiceStatisticsRequest.java"
public interface software.amazon.awssdk.services.xray.model.GetTimeSeriesServiceStatisticsRequest$Builder extends software.amazon.awssdk.services.xray.model.XRayRequest$Builder, software.amazon.awssdk.core.SdkPojo, software.amazon.awssdk.utils.builder.CopyableBuilder<software.amazon.awssdk.services.xray.model.GetTimeSeriesServiceStatisticsRequest$Builder, software.amazon.awssdk.services.xray.model.GetTimeSeriesServiceStatisticsRequest> {
  public abstract software.amazon.awssdk.services.xray.model.GetTimeSeriesServiceStatisticsRequest$Builder startTime(java.time.Instant);

  public abstract software.amazon.awssdk.services.xray.model.GetTimeSeriesServiceStatisticsRequest$Builder endTime(java.time.Instant);

  public abstract software.amazon.awssdk.services.xray.model.GetTimeSeriesServiceStatisticsRequest$Builder groupName(java.lang.String);

  public abstract software.amazon.awssdk.services.xray.model.GetTimeSeriesServiceStatisticsRequest$Builder groupARN(java.lang.String);

  public abstract software.amazon.awssdk.services.xray.model.GetTimeSeriesServiceStatisticsRequest$Builder entitySelectorExpression(java.lang.String);

  public abstract software.amazon.awssdk.services.xray.model.GetTimeSeriesServiceStatisticsRequest$Builder period(java.lang.Integer);

  public abstract software.amazon.awssdk.services.xray.model.GetTimeSeriesServiceStatisticsRequest$Builder forecastStatistics(java.lang.Boolean);

  public abstract software.amazon.awssdk.services.xray.model.GetTimeSeriesServiceStatisticsRequest$Builder nextToken(java.lang.String);

  public abstract software.amazon.awssdk.services.xray.model.GetTimeSeriesServiceStatisticsRequest$Builder overrideConfiguration(software.amazon.awssdk.awscore.AwsRequestOverrideConfiguration);

  public abstract software.amazon.awssdk.services.xray.model.GetTimeSeriesServiceStatisticsRequest$Builder overrideConfiguration(java.util.function.Consumer<software.amazon.awssdk.awscore.AwsRequestOverrideConfiguration$Builder>);

  public default software.amazon.awssdk.awscore.AwsRequest$Builder overrideConfiguration(java.util.function.Consumer);
    Code:
       0: aload_0
       1: aload_1
       2: invokeinterface #1,  2            // InterfaceMethod overrideConfiguration:(Ljava/util/function/Consumer;)Lsoftware/amazon/awssdk/services/xray/model/GetTimeSeriesServiceStatisticsRequest$Builder;
       7: areturn

  public default software.amazon.awssdk.awscore.AwsRequest$Builder overrideConfiguration(software.amazon.awssdk.awscore.AwsRequestOverrideConfiguration);
    Code:
       0: aload_0
       1: aload_1
       2: invokeinterface #2,  2            // InterfaceMethod overrideConfiguration:(Lsoftware/amazon/awssdk/awscore/AwsRequestOverrideConfiguration;)Lsoftware/amazon/awssdk/services/xray/model/GetTimeSeriesServiceStatisticsRequest$Builder;
       7: areturn
}
