Compiled from "InsightSummary.java"
final class software.amazon.awssdk.services.xray.model.InsightSummary$BuilderImpl implements software.amazon.awssdk.services.xray.model.InsightSummary$Builder {
  private java.lang.String insightId;

  private java.lang.String groupARN;

  private java.lang.String groupName;

  private software.amazon.awssdk.services.xray.model.ServiceId rootCauseServiceId;

  private java.util.List<java.lang.String> categories;

  private java.lang.String state;

  private java.time.Instant startTime;

  private java.time.Instant endTime;

  private java.lang.String summary;

  private software.amazon.awssdk.services.xray.model.RequestImpactStatistics clientRequestImpactStatistics;

  private software.amazon.awssdk.services.xray.model.RequestImpactStatistics rootCauseServiceRequestImpactStatistics;

  private java.util.List<software.amazon.awssdk.services.xray.model.AnomalousService> topAnomalousServices;

  private java.time.Instant lastUpdateTime;

  private software.amazon.awssdk.services.xray.model.InsightSummary$BuilderImpl();
    Code:
       0: aload_0
       1: invokespecial #16                 // Method java/lang/Object."<init>":()V
       4: aload_0
       5: invokestatic  #17                 // Method software/amazon/awssdk/core/util/DefaultSdkAutoConstructList.getInstance:()Lsoftware/amazon/awssdk/core/util/DefaultSdkAutoConstructList;
       8: putfield      #11                 // Field categories:Ljava/util/List;
      11: aload_0
      12: invokestatic  #17                 // Method software/amazon/awssdk/core/util/DefaultSdkAutoConstructList.getInstance:()Lsoftware/amazon/awssdk/core/util/DefaultSdkAutoConstructList;
      15: putfield      #4                  // Field topAnomalousServices:Ljava/util/List;
      18: return

  private software.amazon.awssdk.services.xray.model.InsightSummary$BuilderImpl(software.amazon.awssdk.services.xray.model.InsightSummary);
    Code:
       0: aload_0
       1: invokespecial #16                 // Method java/lang/Object."<init>":()V
       4: aload_0
       5: invokestatic  #17                 // Method software/amazon/awssdk/core/util/DefaultSdkAutoConstructList.getInstance:()Lsoftware/amazon/awssdk/core/util/DefaultSdkAutoConstructList;
       8: putfield      #11                 // Field categories:Ljava/util/List;
      11: aload_0
      12: invokestatic  #17                 // Method software/amazon/awssdk/core/util/DefaultSdkAutoConstructList.getInstance:()Lsoftware/amazon/awssdk/core/util/DefaultSdkAutoConstructList;
      15: putfield      #4                  // Field topAnomalousServices:Ljava/util/List;
      18: aload_0
      19: aload_1
      20: invokestatic  #18                 // Method software/amazon/awssdk/services/xray/model/InsightSummary.access$1500:(Lsoftware/amazon/awssdk/services/xray/model/InsightSummary;)Ljava/lang/String;
      23: invokevirtual #19                 // Method insightId:(Ljava/lang/String;)Lsoftware/amazon/awssdk/services/xray/model/InsightSummary$Builder;
      26: pop
      27: aload_0
      28: aload_1
      29: invokestatic  #20                 // Method software/amazon/awssdk/services/xray/model/InsightSummary.access$1600:(Lsoftware/amazon/awssdk/services/xray/model/InsightSummary;)Ljava/lang/String;
      32: invokevirtual #21                 // Method groupARN:(Ljava/lang/String;)Lsoftware/amazon/awssdk/services/xray/model/InsightSummary$Builder;
      35: pop
      36: aload_0
      37: aload_1
      38: invokestatic  #22                 // Method software/amazon/awssdk/services/xray/model/InsightSummary.access$1700:(Lsoftware/amazon/awssdk/services/xray/model/InsightSummary;)Ljava/lang/String;
      41: invokevirtual #23                 // Method groupName:(Ljava/lang/String;)Lsoftware/amazon/awssdk/services/xray/model/InsightSummary$Builder;
      44: pop
      45: aload_0
      46: aload_1
      47: invokestatic  #24                 // Method software/amazon/awssdk/services/xray/model/InsightSummary.access$1800:(Lsoftware/amazon/awssdk/services/xray/model/InsightSummary;)Lsoftware/amazon/awssdk/services/xray/model/ServiceId;
      50: invokevirtual #25                 // Method rootCauseServiceId:(Lsoftware/amazon/awssdk/services/xray/model/ServiceId;)Lsoftware/amazon/awssdk/services/xray/model/InsightSummary$Builder;
      53: pop
      54: aload_0
      55: aload_1
      56: invokestatic  #26                 // Method software/amazon/awssdk/services/xray/model/InsightSummary.access$1900:(Lsoftware/amazon/awssdk/services/xray/model/InsightSummary;)Ljava/util/List;
      59: invokevirtual #27                 // Method categoriesWithStrings:(Ljava/util/Collection;)Lsoftware/amazon/awssdk/services/xray/model/InsightSummary$Builder;
      62: pop
      63: aload_0
      64: aload_1
      65: invokestatic  #28                 // Method software/amazon/awssdk/services/xray/model/InsightSummary.access$2000:(Lsoftware/amazon/awssdk/services/xray/model/InsightSummary;)Ljava/lang/String;
      68: invokevirtual #29                 // Method state:(Ljava/lang/String;)Lsoftware/amazon/awssdk/services/xray/model/InsightSummary$Builder;
      71: pop
      72: aload_0
      73: aload_1
      74: invokestatic  #30                 // Method software/amazon/awssdk/services/xray/model/InsightSummary.access$2100:(Lsoftware/amazon/awssdk/services/xray/model/InsightSummary;)Ljava/time/Instant;
      77: invokevirtual #31                 // Method startTime:(Ljava/time/Instant;)Lsoftware/amazon/awssdk/services/xray/model/InsightSummary$Builder;
      80: pop
      81: aload_0
      82: aload_1
      83: invokestatic  #32                 // Method software/amazon/awssdk/services/xray/model/InsightSummary.access$2200:(Lsoftware/amazon/awssdk/services/xray/model/InsightSummary;)Ljava/time/Instant;
      86: invokevirtual #33                 // Method endTime:(Ljava/time/Instant;)Lsoftware/amazon/awssdk/services/xray/model/InsightSummary$Builder;
      89: pop
      90: aload_0
      91: aload_1
      92: invokestatic  #34                 // Method software/amazon/awssdk/services/xray/model/InsightSummary.access$2300:(Lsoftware/amazon/awssdk/services/xray/model/InsightSummary;)Ljava/lang/String;
      95: invokevirtual #35                 // Method summary:(Ljava/lang/String;)Lsoftware/amazon/awssdk/services/xray/model/InsightSummary$Builder;
      98: pop
      99: aload_0
     100: aload_1
     101: invokestatic  #36                 // Method software/amazon/awssdk/services/xray/model/InsightSummary.access$2400:(Lsoftware/amazon/awssdk/services/xray/model/InsightSummary;)Lsoftware/amazon/awssdk/services/xray/model/RequestImpactStatistics;
     104: invokevirtual #37                 // Method clientRequestImpactStatistics:(Lsoftware/amazon/awssdk/services/xray/model/RequestImpactStatistics;)Lsoftware/amazon/awssdk/services/xray/model/InsightSummary$Builder;
     107: pop
     108: aload_0
     109: aload_1
     110: invokestatic  #38                 // Method software/amazon/awssdk/services/xray/model/InsightSummary.access$2500:(Lsoftware/amazon/awssdk/services/xray/model/InsightSummary;)Lsoftware/amazon/awssdk/services/xray/model/RequestImpactStatistics;
     113: invokevirtual #39                 // Method rootCauseServiceRequestImpactStatistics:(Lsoftware/amazon/awssdk/services/xray/model/RequestImpactStatistics;)Lsoftware/amazon/awssdk/services/xray/model/InsightSummary$Builder;
     116: pop
     117: aload_0
     118: aload_1
     119: invokestatic  #40                 // Method software/amazon/awssdk/services/xray/model/InsightSummary.access$2600:(Lsoftware/amazon/awssdk/services/xray/model/InsightSummary;)Ljava/util/List;
     122: invokevirtual #41                 // Method topAnomalousServices:(Ljava/util/Collection;)Lsoftware/amazon/awssdk/services/xray/model/InsightSummary$Builder;
     125: pop
     126: aload_0
     127: aload_1
     128: invokestatic  #42                 // Method software/amazon/awssdk/services/xray/model/InsightSummary.access$2700:(Lsoftware/amazon/awssdk/services/xray/model/InsightSummary;)Ljava/time/Instant;
     131: invokevirtual #43                 // Method lastUpdateTime:(Ljava/time/Instant;)Lsoftware/amazon/awssdk/services/xray/model/InsightSummary$Builder;
     134: pop
     135: return

  public final java.lang.String getInsightId();
    Code:
       0: aload_0
       1: getfield      #15                 // Field insightId:Ljava/lang/String;
       4: areturn

  public final void setInsightId(java.lang.String);
    Code:
       0: aload_0
       1: aload_1
       2: putfield      #15                 // Field insightId:Ljava/lang/String;
       5: return

  public final software.amazon.awssdk.services.xray.model.InsightSummary$Builder insightId(java.lang.String);
    Code:
       0: aload_0
       1: aload_1
       2: putfield      #15                 // Field insightId:Ljava/lang/String;
       5: aload_0
       6: areturn

  public final java.lang.String getGroupARN();
    Code:
       0: aload_0
       1: getfield      #14                 // Field groupARN:Ljava/lang/String;
       4: areturn

  public final void setGroupARN(java.lang.String);
    Code:
       0: aload_0
       1: aload_1
       2: putfield      #14                 // Field groupARN:Ljava/lang/String;
       5: return

  public final software.amazon.awssdk.services.xray.model.InsightSummary$Builder groupARN(java.lang.String);
    Code:
       0: aload_0
       1: aload_1
       2: putfield      #14                 // Field groupARN:Ljava/lang/String;
       5: aload_0
       6: areturn

  public final java.lang.String getGroupName();
    Code:
       0: aload_0
       1: getfield      #13                 // Field groupName:Ljava/lang/String;
       4: areturn

  public final void setGroupName(java.lang.String);
    Code:
       0: aload_0
       1: aload_1
       2: putfield      #13                 // Field groupName:Ljava/lang/String;
       5: return

  public final software.amazon.awssdk.services.xray.model.InsightSummary$Builder groupName(java.lang.String);
    Code:
       0: aload_0
       1: aload_1
       2: putfield      #13                 // Field groupName:Ljava/lang/String;
       5: aload_0
       6: areturn

  public final software.amazon.awssdk.services.xray.model.ServiceId$Builder getRootCauseServiceId();
    Code:
       0: aload_0
       1: getfield      #12                 // Field rootCauseServiceId:Lsoftware/amazon/awssdk/services/xray/model/ServiceId;
       4: ifnull        17
       7: aload_0
       8: getfield      #12                 // Field rootCauseServiceId:Lsoftware/amazon/awssdk/services/xray/model/ServiceId;
      11: invokevirtual #44                 // Method software/amazon/awssdk/services/xray/model/ServiceId.toBuilder:()Lsoftware/amazon/awssdk/services/xray/model/ServiceId$Builder;
      14: goto          18
      17: aconst_null
      18: areturn

  public final void setRootCauseServiceId(software.amazon.awssdk.services.xray.model.ServiceId$BuilderImpl);
    Code:
       0: aload_0
       1: aload_1
       2: ifnull        12
       5: aload_1
       6: invokevirtual #45                 // Method software/amazon/awssdk/services/xray/model/ServiceId$BuilderImpl.build:()Lsoftware/amazon/awssdk/services/xray/model/ServiceId;
       9: goto          13
      12: aconst_null
      13: putfield      #12                 // Field rootCauseServiceId:Lsoftware/amazon/awssdk/services/xray/model/ServiceId;
      16: return

  public final software.amazon.awssdk.services.xray.model.InsightSummary$Builder rootCauseServiceId(software.amazon.awssdk.services.xray.model.ServiceId);
    Code:
       0: aload_0
       1: aload_1
       2: putfield      #12                 // Field rootCauseServiceId:Lsoftware/amazon/awssdk/services/xray/model/ServiceId;
       5: aload_0
       6: areturn

  public final java.util.Collection<java.lang.String> getCategories();
    Code:
       0: aload_0
       1: getfield      #11                 // Field categories:Ljava/util/List;
       4: instanceof    #46                 // class software/amazon/awssdk/core/util/SdkAutoConstructList
       7: ifeq          12
      10: aconst_null
      11: areturn
      12: aload_0
      13: getfield      #11                 // Field categories:Ljava/util/List;
      16: areturn

  public final void setCategories(java.util.Collection<java.lang.String>);
    Code:
       0: aload_0
       1: aload_1
       2: invokestatic  #47                 // Method software/amazon/awssdk/services/xray/model/InsightCategoryListCopier.copy:(Ljava/util/Collection;)Ljava/util/List;
       5: putfield      #11                 // Field categories:Ljava/util/List;
       8: return

  public final software.amazon.awssdk.services.xray.model.InsightSummary$Builder categoriesWithStrings(java.util.Collection<java.lang.String>);
    Code:
       0: aload_0
       1: aload_1
       2: invokestatic  #47                 // Method software/amazon/awssdk/services/xray/model/InsightCategoryListCopier.copy:(Ljava/util/Collection;)Ljava/util/List;
       5: putfield      #11                 // Field categories:Ljava/util/List;
       8: aload_0
       9: areturn

  public final software.amazon.awssdk.services.xray.model.InsightSummary$Builder categoriesWithStrings(java.lang.String...);
    Code:
       0: aload_0
       1: aload_1
       2: invokestatic  #48                 // Method java/util/Arrays.asList:([Ljava/lang/Object;)Ljava/util/List;
       5: invokevirtual #27                 // Method categoriesWithStrings:(Ljava/util/Collection;)Lsoftware/amazon/awssdk/services/xray/model/InsightSummary$Builder;
       8: pop
       9: aload_0
      10: areturn

  public final software.amazon.awssdk.services.xray.model.InsightSummary$Builder categories(java.util.Collection<software.amazon.awssdk.services.xray.model.InsightCategory>);
    Code:
       0: aload_0
       1: aload_1
       2: invokestatic  #49                 // Method software/amazon/awssdk/services/xray/model/InsightCategoryListCopier.copyEnumToString:(Ljava/util/Collection;)Ljava/util/List;
       5: putfield      #11                 // Field categories:Ljava/util/List;
       8: aload_0
       9: areturn

  public final software.amazon.awssdk.services.xray.model.InsightSummary$Builder categories(software.amazon.awssdk.services.xray.model.InsightCategory...);
    Code:
       0: aload_0
       1: aload_1
       2: invokestatic  #48                 // Method java/util/Arrays.asList:([Ljava/lang/Object;)Ljava/util/List;
       5: invokevirtual #50                 // Method categories:(Ljava/util/Collection;)Lsoftware/amazon/awssdk/services/xray/model/InsightSummary$Builder;
       8: pop
       9: aload_0
      10: areturn

  public final java.lang.String getState();
    Code:
       0: aload_0
       1: getfield      #10                 // Field state:Ljava/lang/String;
       4: areturn

  public final void setState(java.lang.String);
    Code:
       0: aload_0
       1: aload_1
       2: putfield      #10                 // Field state:Ljava/lang/String;
       5: return

  public final software.amazon.awssdk.services.xray.model.InsightSummary$Builder state(java.lang.String);
    Code:
       0: aload_0
       1: aload_1
       2: putfield      #10                 // Field state:Ljava/lang/String;
       5: aload_0
       6: areturn

  public final software.amazon.awssdk.services.xray.model.InsightSummary$Builder state(software.amazon.awssdk.services.xray.model.InsightState);
    Code:
       0: aload_0
       1: aload_1
       2: ifnonnull     9
       5: aconst_null
       6: goto          13
       9: aload_1
      10: invokevirtual #51                 // Method software/amazon/awssdk/services/xray/model/InsightState.toString:()Ljava/lang/String;
      13: invokevirtual #29                 // Method state:(Ljava/lang/String;)Lsoftware/amazon/awssdk/services/xray/model/InsightSummary$Builder;
      16: pop
      17: aload_0
      18: areturn

  public final java.time.Instant getStartTime();
    Code:
       0: aload_0
       1: getfield      #9                  // Field startTime:Ljava/time/Instant;
       4: areturn

  public final void setStartTime(java.time.Instant);
    Code:
       0: aload_0
       1: aload_1
       2: putfield      #9                  // Field startTime:Ljava/time/Instant;
       5: return

  public final software.amazon.awssdk.services.xray.model.InsightSummary$Builder startTime(java.time.Instant);
    Code:
       0: aload_0
       1: aload_1
       2: putfield      #9                  // Field startTime:Ljava/time/Instant;
       5: aload_0
       6: areturn

  public final java.time.Instant getEndTime();
    Code:
       0: aload_0
       1: getfield      #8                  // Field endTime:Ljava/time/Instant;
       4: areturn

  public final void setEndTime(java.time.Instant);
    Code:
       0: aload_0
       1: aload_1
       2: putfield      #8                  // Field endTime:Ljava/time/Instant;
       5: return

  public final software.amazon.awssdk.services.xray.model.InsightSummary$Builder endTime(java.time.Instant);
    Code:
       0: aload_0
       1: aload_1
       2: putfield      #8                  // Field endTime:Ljava/time/Instant;
       5: aload_0
       6: areturn

  public final java.lang.String getSummary();
    Code:
       0: aload_0
       1: getfield      #7                  // Field summary:Ljava/lang/String;
       4: areturn

  public final void setSummary(java.lang.String);
    Code:
       0: aload_0
       1: aload_1
       2: putfield      #7                  // Field summary:Ljava/lang/String;
       5: return

  public final software.amazon.awssdk.services.xray.model.InsightSummary$Builder summary(java.lang.String);
    Code:
       0: aload_0
       1: aload_1
       2: putfield      #7                  // Field summary:Ljava/lang/String;
       5: aload_0
       6: areturn

  public final software.amazon.awssdk.services.xray.model.RequestImpactStatistics$Builder getClientRequestImpactStatistics();
    Code:
       0: aload_0
       1: getfield      #6                  // Field clientRequestImpactStatistics:Lsoftware/amazon/awssdk/services/xray/model/RequestImpactStatistics;
       4: ifnull        17
       7: aload_0
       8: getfield      #6                  // Field clientRequestImpactStatistics:Lsoftware/amazon/awssdk/services/xray/model/RequestImpactStatistics;
      11: invokevirtual #52                 // Method software/amazon/awssdk/services/xray/model/RequestImpactStatistics.toBuilder:()Lsoftware/amazon/awssdk/services/xray/model/RequestImpactStatistics$Builder;
      14: goto          18
      17: aconst_null
      18: areturn

  public final void setClientRequestImpactStatistics(software.amazon.awssdk.services.xray.model.RequestImpactStatistics$BuilderImpl);
    Code:
       0: aload_0
       1: aload_1
       2: ifnull        12
       5: aload_1
       6: invokevirtual #53                 // Method software/amazon/awssdk/services/xray/model/RequestImpactStatistics$BuilderImpl.build:()Lsoftware/amazon/awssdk/services/xray/model/RequestImpactStatistics;
       9: goto          13
      12: aconst_null
      13: putfield      #6                  // Field clientRequestImpactStatistics:Lsoftware/amazon/awssdk/services/xray/model/RequestImpactStatistics;
      16: return

  public final software.amazon.awssdk.services.xray.model.InsightSummary$Builder clientRequestImpactStatistics(software.amazon.awssdk.services.xray.model.RequestImpactStatistics);
    Code:
       0: aload_0
       1: aload_1
       2: putfield      #6                  // Field clientRequestImpactStatistics:Lsoftware/amazon/awssdk/services/xray/model/RequestImpactStatistics;
       5: aload_0
       6: areturn

  public final software.amazon.awssdk.services.xray.model.RequestImpactStatistics$Builder getRootCauseServiceRequestImpactStatistics();
    Code:
       0: aload_0
       1: getfield      #5                  // Field rootCauseServiceRequestImpactStatistics:Lsoftware/amazon/awssdk/services/xray/model/RequestImpactStatistics;
       4: ifnull        17
       7: aload_0
       8: getfield      #5                  // Field rootCauseServiceRequestImpactStatistics:Lsoftware/amazon/awssdk/services/xray/model/RequestImpactStatistics;
      11: invokevirtual #52                 // Method software/amazon/awssdk/services/xray/model/RequestImpactStatistics.toBuilder:()Lsoftware/amazon/awssdk/services/xray/model/RequestImpactStatistics$Builder;
      14: goto          18
      17: aconst_null
      18: areturn

  public final void setRootCauseServiceRequestImpactStatistics(software.amazon.awssdk.services.xray.model.RequestImpactStatistics$BuilderImpl);
    Code:
       0: aload_0
       1: aload_1
       2: ifnull        12
       5: aload_1
       6: invokevirtual #53                 // Method software/amazon/awssdk/services/xray/model/RequestImpactStatistics$BuilderImpl.build:()Lsoftware/amazon/awssdk/services/xray/model/RequestImpactStatistics;
       9: goto          13
      12: aconst_null
      13: putfield      #5                  // Field rootCauseServiceRequestImpactStatistics:Lsoftware/amazon/awssdk/services/xray/model/RequestImpactStatistics;
      16: return

  public final software.amazon.awssdk.services.xray.model.InsightSummary$Builder rootCauseServiceRequestImpactStatistics(software.amazon.awssdk.services.xray.model.RequestImpactStatistics);
    Code:
       0: aload_0
       1: aload_1
       2: putfield      #5                  // Field rootCauseServiceRequestImpactStatistics:Lsoftware/amazon/awssdk/services/xray/model/RequestImpactStatistics;
       5: aload_0
       6: areturn

  public final java.util.List<software.amazon.awssdk.services.xray.model.AnomalousService$Builder> getTopAnomalousServices();
    Code:
       0: aload_0
       1: getfield      #4                  // Field topAnomalousServices:Ljava/util/List;
       4: invokestatic  #54                 // Method software/amazon/awssdk/services/xray/model/AnomalousServiceListCopier.copyToBuilder:(Ljava/util/Collection;)Ljava/util/List;
       7: astore_1
       8: aload_1
       9: instanceof    #46                 // class software/amazon/awssdk/core/util/SdkAutoConstructList
      12: ifeq          17
      15: aconst_null
      16: areturn
      17: aload_1
      18: areturn

  public final void setTopAnomalousServices(java.util.Collection<software.amazon.awssdk.services.xray.model.AnomalousService$BuilderImpl>);
    Code:
       0: aload_0
       1: aload_1
       2: invokestatic  #55                 // Method software/amazon/awssdk/services/xray/model/AnomalousServiceListCopier.copyFromBuilder:(Ljava/util/Collection;)Ljava/util/List;
       5: putfield      #4                  // Field topAnomalousServices:Ljava/util/List;
       8: return

  public final software.amazon.awssdk.services.xray.model.InsightSummary$Builder topAnomalousServices(java.util.Collection<software.amazon.awssdk.services.xray.model.AnomalousService>);
    Code:
       0: aload_0
       1: aload_1
       2: invokestatic  #56                 // Method software/amazon/awssdk/services/xray/model/AnomalousServiceListCopier.copy:(Ljava/util/Collection;)Ljava/util/List;
       5: putfield      #4                  // Field topAnomalousServices:Ljava/util/List;
       8: aload_0
       9: areturn

  public final software.amazon.awssdk.services.xray.model.InsightSummary$Builder topAnomalousServices(software.amazon.awssdk.services.xray.model.AnomalousService...);
    Code:
       0: aload_0
       1: aload_1
       2: invokestatic  #48                 // Method java/util/Arrays.asList:([Ljava/lang/Object;)Ljava/util/List;
       5: invokevirtual #41                 // Method topAnomalousServices:(Ljava/util/Collection;)Lsoftware/amazon/awssdk/services/xray/model/InsightSummary$Builder;
       8: pop
       9: aload_0
      10: areturn

  public final software.amazon.awssdk.services.xray.model.InsightSummary$Builder topAnomalousServices(java.util.function.Consumer<software.amazon.awssdk.services.xray.model.AnomalousService$Builder>...);
    Code:
       0: aload_0
       1: aload_1
       2: invokestatic  #57                 // InterfaceMethod java/util/stream/Stream.of:([Ljava/lang/Object;)Ljava/util/stream/Stream;
       5: invokedynamic #58,  0             // InvokeDynamic #0:apply:()Ljava/util/function/Function;
      10: invokeinterface #59,  2           // InterfaceMethod java/util/stream/Stream.map:(Ljava/util/function/Function;)Ljava/util/stream/Stream;
      15: invokestatic  #60                 // Method java/util/stream/Collectors.toList:()Ljava/util/stream/Collector;
      18: invokeinterface #61,  2           // InterfaceMethod java/util/stream/Stream.collect:(Ljava/util/stream/Collector;)Ljava/lang/Object;
      23: checkcast     #62                 // class java/util/Collection
      26: invokevirtual #41                 // Method topAnomalousServices:(Ljava/util/Collection;)Lsoftware/amazon/awssdk/services/xray/model/InsightSummary$Builder;
      29: pop
      30: aload_0
      31: areturn

  public final java.time.Instant getLastUpdateTime();
    Code:
       0: aload_0
       1: getfield      #3                  // Field lastUpdateTime:Ljava/time/Instant;
       4: areturn

  public final void setLastUpdateTime(java.time.Instant);
    Code:
       0: aload_0
       1: aload_1
       2: putfield      #3                  // Field lastUpdateTime:Ljava/time/Instant;
       5: return

  public final software.amazon.awssdk.services.xray.model.InsightSummary$Builder lastUpdateTime(java.time.Instant);
    Code:
       0: aload_0
       1: aload_1
       2: putfield      #3                  // Field lastUpdateTime:Ljava/time/Instant;
       5: aload_0
       6: areturn

  public software.amazon.awssdk.services.xray.model.InsightSummary build();
    Code:
       0: new           #63                 // class software/amazon/awssdk/services/xray/model/InsightSummary
       3: dup
       4: aload_0
       5: aconst_null
       6: invokespecial #64                 // Method software/amazon/awssdk/services/xray/model/InsightSummary."<init>":(Lsoftware/amazon/awssdk/services/xray/model/InsightSummary$BuilderImpl;Lsoftware/amazon/awssdk/services/xray/model/InsightSummary$1;)V
       9: areturn

  public java.util.List<software.amazon.awssdk.core.SdkField<?>> sdkFields();
    Code:
       0: invokestatic  #65                 // Method software/amazon/awssdk/services/xray/model/InsightSummary.access$2900:()Ljava/util/List;
       3: areturn

  public java.lang.Object build();
    Code:
       0: aload_0
       1: invokevirtual #66                 // Method build:()Lsoftware/amazon/awssdk/services/xray/model/InsightSummary;
       4: areturn

  private static software.amazon.awssdk.services.xray.model.AnomalousService lambda$topAnomalousServices$0(java.util.function.Consumer);
    Code:
       0: invokestatic  #67                 // Method software/amazon/awssdk/services/xray/model/AnomalousService.builder:()Lsoftware/amazon/awssdk/services/xray/model/AnomalousService$Builder;
       3: aload_0
       4: invokeinterface #68,  2           // InterfaceMethod software/amazon/awssdk/services/xray/model/AnomalousService$Builder.applyMutation:(Ljava/util/function/Consumer;)Lsoftware/amazon/awssdk/utils/builder/SdkBuilder;
       9: checkcast     #69                 // class software/amazon/awssdk/services/xray/model/AnomalousService$Builder
      12: invokeinterface #70,  1           // InterfaceMethod software/amazon/awssdk/services/xray/model/AnomalousService$Builder.build:()Ljava/lang/Object;
      17: checkcast     #71                 // class software/amazon/awssdk/services/xray/model/AnomalousService
      20: areturn

  static java.lang.String access$000(software.amazon.awssdk.services.xray.model.InsightSummary$BuilderImpl);
    Code:
       0: aload_0
       1: getfield      #15                 // Field insightId:Ljava/lang/String;
       4: areturn

  static java.lang.String access$100(software.amazon.awssdk.services.xray.model.InsightSummary$BuilderImpl);
    Code:
       0: aload_0
       1: getfield      #14                 // Field groupARN:Ljava/lang/String;
       4: areturn

  static java.lang.String access$200(software.amazon.awssdk.services.xray.model.InsightSummary$BuilderImpl);
    Code:
       0: aload_0
       1: getfield      #13                 // Field groupName:Ljava/lang/String;
       4: areturn

  static software.amazon.awssdk.services.xray.model.ServiceId access$300(software.amazon.awssdk.services.xray.model.InsightSummary$BuilderImpl);
    Code:
       0: aload_0
       1: getfield      #12                 // Field rootCauseServiceId:Lsoftware/amazon/awssdk/services/xray/model/ServiceId;
       4: areturn

  static java.util.List access$400(software.amazon.awssdk.services.xray.model.InsightSummary$BuilderImpl);
    Code:
       0: aload_0
       1: getfield      #11                 // Field categories:Ljava/util/List;
       4: areturn

  static java.lang.String access$500(software.amazon.awssdk.services.xray.model.InsightSummary$BuilderImpl);
    Code:
       0: aload_0
       1: getfield      #10                 // Field state:Ljava/lang/String;
       4: areturn

  static java.time.Instant access$600(software.amazon.awssdk.services.xray.model.InsightSummary$BuilderImpl);
    Code:
       0: aload_0
       1: getfield      #9                  // Field startTime:Ljava/time/Instant;
       4: areturn

  static java.time.Instant access$700(software.amazon.awssdk.services.xray.model.InsightSummary$BuilderImpl);
    Code:
       0: aload_0
       1: getfield      #8                  // Field endTime:Ljava/time/Instant;
       4: areturn

  static java.lang.String access$800(software.amazon.awssdk.services.xray.model.InsightSummary$BuilderImpl);
    Code:
       0: aload_0
       1: getfield      #7                  // Field summary:Ljava/lang/String;
       4: areturn

  static software.amazon.awssdk.services.xray.model.RequestImpactStatistics access$900(software.amazon.awssdk.services.xray.model.InsightSummary$BuilderImpl);
    Code:
       0: aload_0
       1: getfield      #6                  // Field clientRequestImpactStatistics:Lsoftware/amazon/awssdk/services/xray/model/RequestImpactStatistics;
       4: areturn

  static software.amazon.awssdk.services.xray.model.RequestImpactStatistics access$1000(software.amazon.awssdk.services.xray.model.InsightSummary$BuilderImpl);
    Code:
       0: aload_0
       1: getfield      #5                  // Field rootCauseServiceRequestImpactStatistics:Lsoftware/amazon/awssdk/services/xray/model/RequestImpactStatistics;
       4: areturn

  static java.util.List access$1100(software.amazon.awssdk.services.xray.model.InsightSummary$BuilderImpl);
    Code:
       0: aload_0
       1: getfield      #4                  // Field topAnomalousServices:Ljava/util/List;
       4: areturn

  static java.time.Instant access$1200(software.amazon.awssdk.services.xray.model.InsightSummary$BuilderImpl);
    Code:
       0: aload_0
       1: getfield      #3                  // Field lastUpdateTime:Ljava/time/Instant;
       4: areturn

  software.amazon.awssdk.services.xray.model.InsightSummary$BuilderImpl(software.amazon.awssdk.services.xray.model.InsightSummary, software.amazon.awssdk.services.xray.model.InsightSummary$1);
    Code:
       0: aload_0
       1: aload_1
       2: invokespecial #2                  // Method "<init>":(Lsoftware/amazon/awssdk/services/xray/model/InsightSummary;)V
       5: return

  software.amazon.awssdk.services.xray.model.InsightSummary$BuilderImpl(software.amazon.awssdk.services.xray.model.InsightSummary$1);
    Code:
       0: aload_0
       1: invokespecial #1                  // Method "<init>":()V
       4: return
}
