Compiled from "ValueWithServiceIds.java"
final class software.amazon.awssdk.services.xray.model.ValueWithServiceIds$BuilderImpl implements software.amazon.awssdk.services.xray.model.ValueWithServiceIds$Builder {
  private software.amazon.awssdk.services.xray.model.AnnotationValue annotationValue;

  private java.util.List<software.amazon.awssdk.services.xray.model.ServiceId> serviceIds;

  private software.amazon.awssdk.services.xray.model.ValueWithServiceIds$BuilderImpl();
    Code:
       0: aload_0
       1: invokespecial #5                  // Method java/lang/Object."<init>":()V
       4: aload_0
       5: invokestatic  #6                  // Method software/amazon/awssdk/core/util/DefaultSdkAutoConstructList.getInstance:()Lsoftware/amazon/awssdk/core/util/DefaultSdkAutoConstructList;
       8: putfield      #3                  // Field serviceIds:Ljava/util/List;
      11: return

  private software.amazon.awssdk.services.xray.model.ValueWithServiceIds$BuilderImpl(software.amazon.awssdk.services.xray.model.ValueWithServiceIds);
    Code:
       0: aload_0
       1: invokespecial #5                  // Method java/lang/Object."<init>":()V
       4: aload_0
       5: invokestatic  #6                  // Method software/amazon/awssdk/core/util/DefaultSdkAutoConstructList.getInstance:()Lsoftware/amazon/awssdk/core/util/DefaultSdkAutoConstructList;
       8: putfield      #3                  // Field serviceIds:Ljava/util/List;
      11: aload_0
      12: aload_1
      13: invokestatic  #7                  // Method software/amazon/awssdk/services/xray/model/ValueWithServiceIds.access$400:(Lsoftware/amazon/awssdk/services/xray/model/ValueWithServiceIds;)Lsoftware/amazon/awssdk/services/xray/model/AnnotationValue;
      16: invokevirtual #8                  // Method annotationValue:(Lsoftware/amazon/awssdk/services/xray/model/AnnotationValue;)Lsoftware/amazon/awssdk/services/xray/model/ValueWithServiceIds$Builder;
      19: pop
      20: aload_0
      21: aload_1
      22: invokestatic  #9                  // Method software/amazon/awssdk/services/xray/model/ValueWithServiceIds.access$500:(Lsoftware/amazon/awssdk/services/xray/model/ValueWithServiceIds;)Ljava/util/List;
      25: invokevirtual #10                 // Method serviceIds:(Ljava/util/Collection;)Lsoftware/amazon/awssdk/services/xray/model/ValueWithServiceIds$Builder;
      28: pop
      29: return

  public final software.amazon.awssdk.services.xray.model.AnnotationValue$Builder getAnnotationValue();
    Code:
       0: aload_0
       1: getfield      #4                  // Field annotationValue:Lsoftware/amazon/awssdk/services/xray/model/AnnotationValue;
       4: ifnull        17
       7: aload_0
       8: getfield      #4                  // Field annotationValue:Lsoftware/amazon/awssdk/services/xray/model/AnnotationValue;
      11: invokevirtual #11                 // Method software/amazon/awssdk/services/xray/model/AnnotationValue.toBuilder:()Lsoftware/amazon/awssdk/services/xray/model/AnnotationValue$Builder;
      14: goto          18
      17: aconst_null
      18: areturn

  public final void setAnnotationValue(software.amazon.awssdk.services.xray.model.AnnotationValue$BuilderImpl);
    Code:
       0: aload_0
       1: aload_1
       2: ifnull        12
       5: aload_1
       6: invokevirtual #12                 // Method software/amazon/awssdk/services/xray/model/AnnotationValue$BuilderImpl.build:()Lsoftware/amazon/awssdk/services/xray/model/AnnotationValue;
       9: goto          13
      12: aconst_null
      13: putfield      #4                  // Field annotationValue:Lsoftware/amazon/awssdk/services/xray/model/AnnotationValue;
      16: return

  public final software.amazon.awssdk.services.xray.model.ValueWithServiceIds$Builder annotationValue(software.amazon.awssdk.services.xray.model.AnnotationValue);
    Code:
       0: aload_0
       1: aload_1
       2: putfield      #4                  // Field annotationValue:Lsoftware/amazon/awssdk/services/xray/model/AnnotationValue;
       5: aload_0
       6: areturn

  public final java.util.List<software.amazon.awssdk.services.xray.model.ServiceId$Builder> getServiceIds();
    Code:
       0: aload_0
       1: getfield      #3                  // Field serviceIds:Ljava/util/List;
       4: invokestatic  #13                 // Method software/amazon/awssdk/services/xray/model/ServiceIdsCopier.copyToBuilder:(Ljava/util/Collection;)Ljava/util/List;
       7: astore_1
       8: aload_1
       9: instanceof    #14                 // class software/amazon/awssdk/core/util/SdkAutoConstructList
      12: ifeq          17
      15: aconst_null
      16: areturn
      17: aload_1
      18: areturn

  public final void setServiceIds(java.util.Collection<software.amazon.awssdk.services.xray.model.ServiceId$BuilderImpl>);
    Code:
       0: aload_0
       1: aload_1
       2: invokestatic  #15                 // Method software/amazon/awssdk/services/xray/model/ServiceIdsCopier.copyFromBuilder:(Ljava/util/Collection;)Ljava/util/List;
       5: putfield      #3                  // Field serviceIds:Ljava/util/List;
       8: return

  public final software.amazon.awssdk.services.xray.model.ValueWithServiceIds$Builder serviceIds(java.util.Collection<software.amazon.awssdk.services.xray.model.ServiceId>);
    Code:
       0: aload_0
       1: aload_1
       2: invokestatic  #16                 // Method software/amazon/awssdk/services/xray/model/ServiceIdsCopier.copy:(Ljava/util/Collection;)Ljava/util/List;
       5: putfield      #3                  // Field serviceIds:Ljava/util/List;
       8: aload_0
       9: areturn

  public final software.amazon.awssdk.services.xray.model.ValueWithServiceIds$Builder serviceIds(software.amazon.awssdk.services.xray.model.ServiceId...);
    Code:
       0: aload_0
       1: aload_1
       2: invokestatic  #17                 // Method java/util/Arrays.asList:([Ljava/lang/Object;)Ljava/util/List;
       5: invokevirtual #10                 // Method serviceIds:(Ljava/util/Collection;)Lsoftware/amazon/awssdk/services/xray/model/ValueWithServiceIds$Builder;
       8: pop
       9: aload_0
      10: areturn

  public final software.amazon.awssdk.services.xray.model.ValueWithServiceIds$Builder serviceIds(java.util.function.Consumer<software.amazon.awssdk.services.xray.model.ServiceId$Builder>...);
    Code:
       0: aload_0
       1: aload_1
       2: invokestatic  #18                 // InterfaceMethod java/util/stream/Stream.of:([Ljava/lang/Object;)Ljava/util/stream/Stream;
       5: invokedynamic #19,  0             // InvokeDynamic #0:apply:()Ljava/util/function/Function;
      10: invokeinterface #20,  2           // InterfaceMethod java/util/stream/Stream.map:(Ljava/util/function/Function;)Ljava/util/stream/Stream;
      15: invokestatic  #21                 // Method java/util/stream/Collectors.toList:()Ljava/util/stream/Collector;
      18: invokeinterface #22,  2           // InterfaceMethod java/util/stream/Stream.collect:(Ljava/util/stream/Collector;)Ljava/lang/Object;
      23: checkcast     #23                 // class java/util/Collection
      26: invokevirtual #10                 // Method serviceIds:(Ljava/util/Collection;)Lsoftware/amazon/awssdk/services/xray/model/ValueWithServiceIds$Builder;
      29: pop
      30: aload_0
      31: areturn

  public software.amazon.awssdk.services.xray.model.ValueWithServiceIds build();
    Code:
       0: new           #24                 // class software/amazon/awssdk/services/xray/model/ValueWithServiceIds
       3: dup
       4: aload_0
       5: aconst_null
       6: invokespecial #25                 // Method software/amazon/awssdk/services/xray/model/ValueWithServiceIds."<init>":(Lsoftware/amazon/awssdk/services/xray/model/ValueWithServiceIds$BuilderImpl;Lsoftware/amazon/awssdk/services/xray/model/ValueWithServiceIds$1;)V
       9: areturn

  public java.util.List<software.amazon.awssdk.core.SdkField<?>> sdkFields();
    Code:
       0: invokestatic  #26                 // Method software/amazon/awssdk/services/xray/model/ValueWithServiceIds.access$700:()Ljava/util/List;
       3: areturn

  public java.lang.Object build();
    Code:
       0: aload_0
       1: invokevirtual #27                 // Method build:()Lsoftware/amazon/awssdk/services/xray/model/ValueWithServiceIds;
       4: areturn

  private static software.amazon.awssdk.services.xray.model.ServiceId lambda$serviceIds$0(java.util.function.Consumer);
    Code:
       0: invokestatic  #28                 // Method software/amazon/awssdk/services/xray/model/ServiceId.builder:()Lsoftware/amazon/awssdk/services/xray/model/ServiceId$Builder;
       3: aload_0
       4: invokeinterface #29,  2           // InterfaceMethod software/amazon/awssdk/services/xray/model/ServiceId$Builder.applyMutation:(Ljava/util/function/Consumer;)Lsoftware/amazon/awssdk/utils/builder/SdkBuilder;
       9: checkcast     #30                 // class software/amazon/awssdk/services/xray/model/ServiceId$Builder
      12: invokeinterface #31,  1           // InterfaceMethod software/amazon/awssdk/services/xray/model/ServiceId$Builder.build:()Ljava/lang/Object;
      17: checkcast     #32                 // class software/amazon/awssdk/services/xray/model/ServiceId
      20: areturn

  static software.amazon.awssdk.services.xray.model.AnnotationValue access$000(software.amazon.awssdk.services.xray.model.ValueWithServiceIds$BuilderImpl);
    Code:
       0: aload_0
       1: getfield      #4                  // Field annotationValue:Lsoftware/amazon/awssdk/services/xray/model/AnnotationValue;
       4: areturn

  static java.util.List access$100(software.amazon.awssdk.services.xray.model.ValueWithServiceIds$BuilderImpl);
    Code:
       0: aload_0
       1: getfield      #3                  // Field serviceIds:Ljava/util/List;
       4: areturn

  software.amazon.awssdk.services.xray.model.ValueWithServiceIds$BuilderImpl(software.amazon.awssdk.services.xray.model.ValueWithServiceIds, software.amazon.awssdk.services.xray.model.ValueWithServiceIds$1);
    Code:
       0: aload_0
       1: aload_1
       2: invokespecial #2                  // Method "<init>":(Lsoftware/amazon/awssdk/services/xray/model/ValueWithServiceIds;)V
       5: return

  software.amazon.awssdk.services.xray.model.ValueWithServiceIds$BuilderImpl(software.amazon.awssdk.services.xray.model.ValueWithServiceIds$1);
    Code:
       0: aload_0
       1: invokespecial #1                  // Method "<init>":()V
       4: return
}
