Compiled from "ValueWithServiceIds.java"
public interface software.amazon.awssdk.services.xray.model.ValueWithServiceIds$Builder extends software.amazon.awssdk.core.SdkPojo, software.amazon.awssdk.utils.builder.CopyableBuilder<software.amazon.awssdk.services.xray.model.ValueWithServiceIds$Builder, software.amazon.awssdk.services.xray.model.ValueWithServiceIds> {
  public abstract software.amazon.awssdk.services.xray.model.ValueWithServiceIds$Builder annotationValue(software.amazon.awssdk.services.xray.model.AnnotationValue);

  public default software.amazon.awssdk.services.xray.model.ValueWithServiceIds$Builder annotationValue(java.util.function.Consumer<software.amazon.awssdk.services.xray.model.AnnotationValue$Builder>);
    Code:
       0: aload_0
       1: invokestatic  #1                  // Method software/amazon/awssdk/services/xray/model/AnnotationValue.builder:()Lsoftware/amazon/awssdk/services/xray/model/AnnotationValue$Builder;
       4: aload_1
       5: invokeinterface #2,  2            // InterfaceMethod software/amazon/awssdk/services/xray/model/AnnotationValue$Builder.applyMutation:(Ljava/util/function/Consumer;)Lsoftware/amazon/awssdk/utils/builder/SdkBuilder;
      10: checkcast     #3                  // class software/amazon/awssdk/services/xray/model/AnnotationValue$Builder
      13: invokeinterface #4,  1            // InterfaceMethod software/amazon/awssdk/services/xray/model/AnnotationValue$Builder.build:()Ljava/lang/Object;
      18: checkcast     #5                  // class software/amazon/awssdk/services/xray/model/AnnotationValue
      21: invokeinterface #6,  2            // InterfaceMethod annotationValue:(Lsoftware/amazon/awssdk/services/xray/model/AnnotationValue;)Lsoftware/amazon/awssdk/services/xray/model/ValueWithServiceIds$Builder;
      26: areturn

  public abstract software.amazon.awssdk.services.xray.model.ValueWithServiceIds$Builder serviceIds(java.util.Collection<software.amazon.awssdk.services.xray.model.ServiceId>);

  public abstract software.amazon.awssdk.services.xray.model.ValueWithServiceIds$Builder serviceIds(software.amazon.awssdk.services.xray.model.ServiceId...);

  public abstract software.amazon.awssdk.services.xray.model.ValueWithServiceIds$Builder serviceIds(java.util.function.Consumer<software.amazon.awssdk.services.xray.model.ServiceId$Builder>...);
}
