Compiled from "ChildWorkflowExecutionFailedEventAttributesJsonMarshaller.java"
public class com.amazonaws.services.simpleworkflow.model.transform.ChildWorkflowExecutionFailedEventAttributesJsonMarshaller {
  private static com.amazonaws.services.simpleworkflow.model.transform.ChildWorkflowExecutionFailedEventAttributesJsonMarshaller instance;

  public com.amazonaws.services.simpleworkflow.model.transform.ChildWorkflowExecutionFailedEventAttributesJsonMarshaller();
    Code:
       0: aload_0
       1: invokespecial #1                  // Method java/lang/Object."<init>":()V
       4: return

  public void marshall(com.amazonaws.services.simpleworkflow.model.ChildWorkflowExecutionFailedEventAttributes, com.amazonaws.protocol.json.StructuredJsonGenerator);
    Code:
       0: aload_1
       1: ifnonnull     14
       4: new           #2                  // class com/amazonaws/AmazonClientException
       7: dup
       8: ldc           #3                  // String Invalid argument passed to marshall(...)
      10: invokespecial #4                  // Method com/amazonaws/AmazonClientException."<init>":(Ljava/lang/String;)V
      13: athrow
      14: aload_2
      15: invokeinterface #5,  1            // InterfaceMethod com/amazonaws/protocol/json/StructuredJsonGenerator.writeStartObject:()Lcom/amazonaws/protocol/json/StructuredJsonGenerator;
      20: pop
      21: aload_1
      22: invokevirtual #6                  // Method com/amazonaws/services/simpleworkflow/model/ChildWorkflowExecutionFailedEventAttributes.getWorkflowExecution:()Lcom/amazonaws/services/simpleworkflow/model/WorkflowExecution;
      25: ifnull        48
      28: aload_2
      29: ldc           #7                  // String workflowExecution
      31: invokeinterface #8,  2            // InterfaceMethod com/amazonaws/protocol/json/StructuredJsonGenerator.writeFieldName:(Ljava/lang/String;)Lcom/amazonaws/protocol/json/StructuredJsonGenerator;
      36: pop
      37: invokestatic  #9                  // Method com/amazonaws/services/simpleworkflow/model/transform/WorkflowExecutionJsonMarshaller.getInstance:()Lcom/amazonaws/services/simpleworkflow/model/transform/WorkflowExecutionJsonMarshaller;
      40: aload_1
      41: invokevirtual #6                  // Method com/amazonaws/services/simpleworkflow/model/ChildWorkflowExecutionFailedEventAttributes.getWorkflowExecution:()Lcom/amazonaws/services/simpleworkflow/model/WorkflowExecution;
      44: aload_2
      45: invokevirtual #10                 // Method com/amazonaws/services/simpleworkflow/model/transform/WorkflowExecutionJsonMarshaller.marshall:(Lcom/amazonaws/services/simpleworkflow/model/WorkflowExecution;Lcom/amazonaws/protocol/json/StructuredJsonGenerator;)V
      48: aload_1
      49: invokevirtual #11                 // Method com/amazonaws/services/simpleworkflow/model/ChildWorkflowExecutionFailedEventAttributes.getWorkflowType:()Lcom/amazonaws/services/simpleworkflow/model/WorkflowType;
      52: ifnull        75
      55: aload_2
      56: ldc           #12                 // String workflowType
      58: invokeinterface #8,  2            // InterfaceMethod com/amazonaws/protocol/json/StructuredJsonGenerator.writeFieldName:(Ljava/lang/String;)Lcom/amazonaws/protocol/json/StructuredJsonGenerator;
      63: pop
      64: invokestatic  #13                 // Method com/amazonaws/services/simpleworkflow/model/transform/WorkflowTypeJsonMarshaller.getInstance:()Lcom/amazonaws/services/simpleworkflow/model/transform/WorkflowTypeJsonMarshaller;
      67: aload_1
      68: invokevirtual #11                 // Method com/amazonaws/services/simpleworkflow/model/ChildWorkflowExecutionFailedEventAttributes.getWorkflowType:()Lcom/amazonaws/services/simpleworkflow/model/WorkflowType;
      71: aload_2
      72: invokevirtual #14                 // Method com/amazonaws/services/simpleworkflow/model/transform/WorkflowTypeJsonMarshaller.marshall:(Lcom/amazonaws/services/simpleworkflow/model/WorkflowType;Lcom/amazonaws/protocol/json/StructuredJsonGenerator;)V
      75: aload_1
      76: invokevirtual #15                 // Method com/amazonaws/services/simpleworkflow/model/ChildWorkflowExecutionFailedEventAttributes.getReason:()Ljava/lang/String;
      79: ifnull        100
      82: aload_2
      83: ldc           #16                 // String reason
      85: invokeinterface #8,  2            // InterfaceMethod com/amazonaws/protocol/json/StructuredJsonGenerator.writeFieldName:(Ljava/lang/String;)Lcom/amazonaws/protocol/json/StructuredJsonGenerator;
      90: aload_1
      91: invokevirtual #15                 // Method com/amazonaws/services/simpleworkflow/model/ChildWorkflowExecutionFailedEventAttributes.getReason:()Ljava/lang/String;
      94: invokeinterface #17,  2           // InterfaceMethod com/amazonaws/protocol/json/StructuredJsonGenerator.writeValue:(Ljava/lang/String;)Lcom/amazonaws/protocol/json/StructuredJsonGenerator;
      99: pop
     100: aload_1
     101: invokevirtual #18                 // Method com/amazonaws/services/simpleworkflow/model/ChildWorkflowExecutionFailedEventAttributes.getDetails:()Ljava/lang/String;
     104: ifnull        125
     107: aload_2
     108: ldc           #19                 // String details
     110: invokeinterface #8,  2            // InterfaceMethod com/amazonaws/protocol/json/StructuredJsonGenerator.writeFieldName:(Ljava/lang/String;)Lcom/amazonaws/protocol/json/StructuredJsonGenerator;
     115: aload_1
     116: invokevirtual #18                 // Method com/amazonaws/services/simpleworkflow/model/ChildWorkflowExecutionFailedEventAttributes.getDetails:()Ljava/lang/String;
     119: invokeinterface #17,  2           // InterfaceMethod com/amazonaws/protocol/json/StructuredJsonGenerator.writeValue:(Ljava/lang/String;)Lcom/amazonaws/protocol/json/StructuredJsonGenerator;
     124: pop
     125: aload_1
     126: invokevirtual #20                 // Method com/amazonaws/services/simpleworkflow/model/ChildWorkflowExecutionFailedEventAttributes.getInitiatedEventId:()Ljava/lang/Long;
     129: ifnull        153
     132: aload_2
     133: ldc           #21                 // String initiatedEventId
     135: invokeinterface #8,  2            // InterfaceMethod com/amazonaws/protocol/json/StructuredJsonGenerator.writeFieldName:(Ljava/lang/String;)Lcom/amazonaws/protocol/json/StructuredJsonGenerator;
     140: aload_1
     141: invokevirtual #20                 // Method com/amazonaws/services/simpleworkflow/model/ChildWorkflowExecutionFailedEventAttributes.getInitiatedEventId:()Ljava/lang/Long;
     144: invokevirtual #22                 // Method java/lang/Long.longValue:()J
     147: invokeinterface #23,  3           // InterfaceMethod com/amazonaws/protocol/json/StructuredJsonGenerator.writeValue:(J)Lcom/amazonaws/protocol/json/StructuredJsonGenerator;
     152: pop
     153: aload_1
     154: invokevirtual #24                 // Method com/amazonaws/services/simpleworkflow/model/ChildWorkflowExecutionFailedEventAttributes.getStartedEventId:()Ljava/lang/Long;
     157: ifnull        181
     160: aload_2
     161: ldc           #25                 // String startedEventId
     163: invokeinterface #8,  2            // InterfaceMethod com/amazonaws/protocol/json/StructuredJsonGenerator.writeFieldName:(Ljava/lang/String;)Lcom/amazonaws/protocol/json/StructuredJsonGenerator;
     168: aload_1
     169: invokevirtual #24                 // Method com/amazonaws/services/simpleworkflow/model/ChildWorkflowExecutionFailedEventAttributes.getStartedEventId:()Ljava/lang/Long;
     172: invokevirtual #22                 // Method java/lang/Long.longValue:()J
     175: invokeinterface #23,  3           // InterfaceMethod com/amazonaws/protocol/json/StructuredJsonGenerator.writeValue:(J)Lcom/amazonaws/protocol/json/StructuredJsonGenerator;
     180: pop
     181: aload_2
     182: invokeinterface #26,  1           // InterfaceMethod com/amazonaws/protocol/json/StructuredJsonGenerator.writeEndObject:()Lcom/amazonaws/protocol/json/StructuredJsonGenerator;
     187: pop
     188: goto          223
     191: astore_3
     192: new           #2                  // class com/amazonaws/AmazonClientException
     195: dup
     196: new           #28                 // class java/lang/StringBuilder
     199: dup
     200: invokespecial #29                 // Method java/lang/StringBuilder."<init>":()V
     203: ldc           #30                 // String Unable to marshall request to JSON:
     205: invokevirtual #31                 // Method java/lang/StringBuilder.append:(Ljava/lang/String;)Ljava/lang/StringBuilder;
     208: aload_3
     209: invokevirtual #32                 // Method java/lang/Throwable.getMessage:()Ljava/lang/String;
     212: invokevirtual #31                 // Method java/lang/StringBuilder.append:(Ljava/lang/String;)Ljava/lang/StringBuilder;
     215: invokevirtual #33                 // Method java/lang/StringBuilder.toString:()Ljava/lang/String;
     218: aload_3
     219: invokespecial #34                 // Method com/amazonaws/AmazonClientException."<init>":(Ljava/lang/String;Ljava/lang/Throwable;)V
     222: athrow
     223: return
    Exception table:
       from    to  target type
          14   188   191   Class java/lang/Throwable

  public static com.amazonaws.services.simpleworkflow.model.transform.ChildWorkflowExecutionFailedEventAttributesJsonMarshaller getInstance();
    Code:
       0: getstatic     #35                 // Field instance:Lcom/amazonaws/services/simpleworkflow/model/transform/ChildWorkflowExecutionFailedEventAttributesJsonMarshaller;
       3: ifnonnull     16
       6: new           #36                 // class com/amazonaws/services/simpleworkflow/model/transform/ChildWorkflowExecutionFailedEventAttributesJsonMarshaller
       9: dup
      10: invokespecial #37                 // Method "<init>":()V
      13: putstatic     #35                 // Field instance:Lcom/amazonaws/services/simpleworkflow/model/transform/ChildWorkflowExecutionFailedEventAttributesJsonMarshaller;
      16: getstatic     #35                 // Field instance:Lcom/amazonaws/services/simpleworkflow/model/transform/ChildWorkflowExecutionFailedEventAttributesJsonMarshaller;
      19: areturn
}
