Compiled from "CRC32DigestManager.java"
final class org.apache.bookkeeper.proto.checksum.CRC32DigestManager$1 extends io.netty.util.concurrent.FastThreadLocal<org.apache.bookkeeper.proto.checksum.CRC32DigestManager$CRC32Digest> {
  org.apache.bookkeeper.proto.checksum.CRC32DigestManager$1();
    Code:
       0: aload_0
       1: invokespecial #1                  // Method io/netty/util/concurrent/FastThreadLocal."<init>":()V
       4: return

  protected org.apache.bookkeeper.proto.checksum.CRC32DigestManager$CRC32Digest initialValue();
    Code:
       0: invokestatic  #2                  // Method org/apache/bookkeeper/proto/checksum/DirectMemoryCRC32Digest.isSupported:()Z
       3: ifeq          14
       6: new           #3                  // class org/apache/bookkeeper/proto/checksum/DirectMemoryCRC32Digest
       9: dup
      10: invokespecial #4                  // Method org/apache/bookkeeper/proto/checksum/DirectMemoryCRC32Digest."<init>":()V
      13: areturn
      14: new           #5                  // class org/apache/bookkeeper/proto/checksum/StandardCRC32Digest
      17: dup
      18: invokespecial #6                  // Method org/apache/bookkeeper/proto/checksum/StandardCRC32Digest."<init>":()V
      21: areturn

  protected java.lang.Object initialValue() throws java.lang.Exception;
    Code:
       0: aload_0
       1: invokevirtual #7                  // Method initialValue:()Lorg/apache/bookkeeper/proto/checksum/CRC32DigestManager$CRC32Digest;
       4: areturn
}
