Compiled from "ResponseObjectEntityExtractorFactory.java"
class org.jboss.resteasy.client.core.extractors.ResponseObjectEntityExtractorFactory$6 implements org.jboss.resteasy.client.core.extractors.EntityExtractor {
  final java.lang.reflect.Method val$method;

  final org.jboss.resteasy.annotations.LinkHeaderParam val$link;

  final org.jboss.resteasy.client.core.extractors.ResponseObjectEntityExtractorFactory this$0;

  org.jboss.resteasy.client.core.extractors.ResponseObjectEntityExtractorFactory$6(org.jboss.resteasy.client.core.extractors.ResponseObjectEntityExtractorFactory, java.lang.reflect.Method, org.jboss.resteasy.annotations.LinkHeaderParam);
    Code:
       0: aload_0
       1: aload_1
       2: putfield      #1                  // Field this$0:Lorg/jboss/resteasy/client/core/extractors/ResponseObjectEntityExtractorFactory;
       5: aload_0
       6: aload_2
       7: putfield      #2                  // Field val$method:Ljava/lang/reflect/Method;
      10: aload_0
      11: aload_3
      12: putfield      #3                  // Field val$link:Lorg/jboss/resteasy/annotations/LinkHeaderParam;
      15: aload_0
      16: invokespecial #4                  // Method java/lang/Object."<init>":()V
      19: return

  public java.lang.Object extractEntity(org.jboss.resteasy.client.core.extractors.ClientRequestContext, java.lang.Object...);
    Code:
       0: aload_0
       1: getfield      #1                  // Field this$0:Lorg/jboss/resteasy/client/core/extractors/ResponseObjectEntityExtractorFactory;
       4: aload_0
       5: getfield      #2                  // Field val$method:Ljava/lang/reflect/Method;
       8: aload_0
       9: getfield      #3                  // Field val$link:Lorg/jboss/resteasy/annotations/LinkHeaderParam;
      12: aload_1
      13: invokestatic  #5                  // Method org/jboss/resteasy/client/core/extractors/ResponseObjectEntityExtractorFactory.access$100:(Lorg/jboss/resteasy/client/core/extractors/ResponseObjectEntityExtractorFactory;Ljava/lang/reflect/Method;Lorg/jboss/resteasy/annotations/LinkHeaderParam;Lorg/jboss/resteasy/client/core/extractors/ClientRequestContext;)Ljava/net/URI;
      16: astore_3
      17: aload_3
      18: ifnonnull     23
      21: aconst_null
      22: areturn
      23: aload_1
      24: invokevirtual #6                  // Method org/jboss/resteasy/client/core/extractors/ClientRequestContext.getRequest:()Lorg/jboss/resteasy/client/ClientRequest;
      27: astore        4
      29: aload_1
      30: invokevirtual #7                  // Method org/jboss/resteasy/client/core/extractors/ClientRequestContext.getExtractorFactory:()Lorg/jboss/resteasy/client/core/extractors/EntityExtractorFactory;
      33: astore        5
      35: aload         4
      37: invokevirtual #8                  // Method org/jboss/resteasy/client/ClientRequest.getProviderFactory:()Lorg/jboss/resteasy/spi/ResteasyProviderFactory;
      40: astore        6
      42: aload         4
      44: invokevirtual #9                  // Method org/jboss/resteasy/client/ClientRequest.getExecutor:()Lorg/jboss/resteasy/client/ClientExecutor;
      47: astore        7
      49: aload_0
      50: getfield      #2                  // Field val$method:Ljava/lang/reflect/Method;
      53: invokevirtual #10                 // Method java/lang/reflect/Method.getDeclaringClass:()Ljava/lang/Class;
      56: aload_0
      57: getfield      #2                  // Field val$method:Ljava/lang/reflect/Method;
      60: aload_3
      61: aload         7
      63: aload         6
      65: aload         5
      67: invokestatic  #11                 // Method org/jboss/resteasy/client/ProxyFactory.createClientInvoker:(Ljava/lang/Class;Ljava/lang/reflect/Method;Ljava/net/URI;Lorg/jboss/resteasy/client/ClientExecutor;Lorg/jboss/resteasy/spi/ResteasyProviderFactory;Lorg/jboss/resteasy/client/core/extractors/EntityExtractorFactory;)Lorg/jboss/resteasy/client/core/ClientInvoker;
      70: aload_2
      71: invokevirtual #12                 // Method org/jboss/resteasy/client/core/ClientInvoker.invoke:([Ljava/lang/Object;)Ljava/lang/Object;
      74: areturn
}
