Compiled from "ResponseObjectEntityExtractorFactory.java"
class org.jboss.resteasy.client.core.extractors.ResponseObjectEntityExtractorFactory$4 implements org.jboss.resteasy.client.core.extractors.EntityExtractor {
  final org.jboss.resteasy.client.core.extractors.ResponseObjectEntityExtractorFactory this$0;

  org.jboss.resteasy.client.core.extractors.ResponseObjectEntityExtractorFactory$4(org.jboss.resteasy.client.core.extractors.ResponseObjectEntityExtractorFactory);
    Code:
       0: aload_0
       1: aload_1
       2: putfield      #1                  // Field this$0:Lorg/jboss/resteasy/client/core/extractors/ResponseObjectEntityExtractorFactory;
       5: aload_0
       6: invokespecial #2                  // Method java/lang/Object."<init>":()V
       9: return

  public java.lang.Object extractEntity(org.jboss.resteasy.client.core.extractors.ClientRequestContext, java.lang.Object...);
    Code:
       0: aload_1
       1: invokevirtual #3                  // Method org/jboss/resteasy/client/core/extractors/ClientRequestContext.getClientResponse:()Lorg/jboss/resteasy/client/core/BaseClientResponse;
       4: invokevirtual #4                  // Method org/jboss/resteasy/client/core/BaseClientResponse.getLinkHeader:()Lorg/jboss/resteasy/spi/LinkHeader;
       7: areturn
}
