Compiled from "ExtensionRegistryLite.java"
public class kotlin.reflect.jvm.internal.impl.protobuf.ExtensionRegistryLite {
  private static volatile boolean eagerlyParseMessageSets;

  private final java.util.Map<kotlin.reflect.jvm.internal.impl.protobuf.ExtensionRegistryLite$ObjectIntPair, kotlin.reflect.jvm.internal.impl.protobuf.GeneratedMessageLite$GeneratedExtension<?, ?>> extensionsByNumber;

  private static final kotlin.reflect.jvm.internal.impl.protobuf.ExtensionRegistryLite EMPTY;

  public static kotlin.reflect.jvm.internal.impl.protobuf.ExtensionRegistryLite newInstance();
    Code:
       0: new           #5                  // class kotlin/reflect/jvm/internal/impl/protobuf/ExtensionRegistryLite
       3: dup
       4: invokespecial #15                 // Method "<init>":()V
       7: areturn

  public static kotlin.reflect.jvm.internal.impl.protobuf.ExtensionRegistryLite getEmptyRegistry();
    Code:
       0: getstatic     #9                  // Field EMPTY:Lkotlin/reflect/jvm/internal/impl/protobuf/ExtensionRegistryLite;
       3: areturn

  public <ContainingType extends kotlin.reflect.jvm.internal.impl.protobuf.MessageLite> kotlin.reflect.jvm.internal.impl.protobuf.GeneratedMessageLite$GeneratedExtension<ContainingType, ?> findLiteExtensionByNumber(ContainingType, int);
    Code:
       0: aload_0
       1: getfield      #11                 // Field extensionsByNumber:Ljava/util/Map;
       4: new           #6                  // class kotlin/reflect/jvm/internal/impl/protobuf/ExtensionRegistryLite$ObjectIntPair
       7: dup
       8: aload_1
       9: iload_2
      10: invokespecial #17                 // Method kotlin/reflect/jvm/internal/impl/protobuf/ExtensionRegistryLite$ObjectIntPair."<init>":(Ljava/lang/Object;I)V
      13: invokeinterface #20,  2           // InterfaceMethod java/util/Map.get:(Ljava/lang/Object;)Ljava/lang/Object;
      18: checkcast     #8                  // class kotlin/reflect/jvm/internal/impl/protobuf/GeneratedMessageLite$GeneratedExtension
      21: areturn

  public final void add(kotlin.reflect.jvm.internal.impl.protobuf.GeneratedMessageLite$GeneratedExtension<?, ?>);
    Code:
       0: aload_0
       1: getfield      #11                 // Field extensionsByNumber:Ljava/util/Map;
       4: new           #6                  // class kotlin/reflect/jvm/internal/impl/protobuf/ExtensionRegistryLite$ObjectIntPair
       7: dup
       8: aload_1
       9: invokevirtual #18                 // Method kotlin/reflect/jvm/internal/impl/protobuf/GeneratedMessageLite$GeneratedExtension.getContainingTypeDefaultInstance:()Lkotlin/reflect/jvm/internal/impl/protobuf/MessageLite;
      12: aload_1
      13: invokevirtual #19                 // Method kotlin/reflect/jvm/internal/impl/protobuf/GeneratedMessageLite$GeneratedExtension.getNumber:()I
      16: invokespecial #17                 // Method kotlin/reflect/jvm/internal/impl/protobuf/ExtensionRegistryLite$ObjectIntPair."<init>":(Ljava/lang/Object;I)V
      19: aload_1
      20: invokeinterface #21,  3           // InterfaceMethod java/util/Map.put:(Ljava/lang/Object;Ljava/lang/Object;)Ljava/lang/Object;
      25: pop
      26: return

  kotlin.reflect.jvm.internal.impl.protobuf.ExtensionRegistryLite();
    Code:
       0: aload_0
       1: invokespecial #12                 // Method java/lang/Object."<init>":()V
       4: aload_0
       5: new           #3                  // class java/util/HashMap
       8: dup
       9: invokespecial #14                 // Method java/util/HashMap."<init>":()V
      12: putfield      #11                 // Field extensionsByNumber:Ljava/util/Map;
      15: return

  private kotlin.reflect.jvm.internal.impl.protobuf.ExtensionRegistryLite(boolean);
    Code:
       0: aload_0
       1: invokespecial #12                 // Method java/lang/Object."<init>":()V
       4: aload_0
       5: invokestatic  #13                 // Method java/util/Collections.emptyMap:()Ljava/util/Map;
       8: putfield      #11                 // Field extensionsByNumber:Ljava/util/Map;
      11: return

  static {};
    Code:
       0: iconst_0
       1: putstatic     #10                 // Field eagerlyParseMessageSets:Z
       4: new           #5                  // class kotlin/reflect/jvm/internal/impl/protobuf/ExtensionRegistryLite
       7: dup
       8: iconst_1
       9: invokespecial #16                 // Method "<init>":(Z)V
      12: putstatic     #9                  // Field EMPTY:Lkotlin/reflect/jvm/internal/impl/protobuf/ExtensionRegistryLite;
      15: return
}
