Compiled from "SmallSortedMap.java"
class kotlin.reflect.jvm.internal.impl.protobuf.SmallSortedMap$EntryIterator implements java.util.Iterator<java.util.Map$Entry<K, V>> {
  private int pos;

  private boolean nextCalledBeforeRemove;

  private java.util.Iterator<java.util.Map$Entry<K, V>> lazyOverflowIterator;

  final kotlin.reflect.jvm.internal.impl.protobuf.SmallSortedMap this$0;

  private kotlin.reflect.jvm.internal.impl.protobuf.SmallSortedMap$EntryIterator(kotlin.reflect.jvm.internal.impl.protobuf.SmallSortedMap);
    Code:
       0: aload_0
       1: aload_1
       2: putfield      #15                 // Field this$0:Lkotlin/reflect/jvm/internal/impl/protobuf/SmallSortedMap;
       5: aload_0
       6: invokespecial #17                 // Method java/lang/Object."<init>":()V
       9: aload_0
      10: iconst_m1
      11: putfield      #14                 // Field pos:I
      14: return

  public boolean hasNext();
    Code:
       0: aload_0
       1: getfield      #14                 // Field pos:I
       4: iconst_1
       5: iadd
       6: aload_0
       7: getfield      #15                 // Field this$0:Lkotlin/reflect/jvm/internal/impl/protobuf/SmallSortedMap;
      10: invokestatic  #19                 // Method kotlin/reflect/jvm/internal/impl/protobuf/SmallSortedMap.access$400:(Lkotlin/reflect/jvm/internal/impl/protobuf/SmallSortedMap;)Ljava/util/List;
      13: invokeinterface #29,  1           // InterfaceMethod java/util/List.size:()I
      18: if_icmplt     33
      21: aload_0
      22: invokespecial #23                 // Method getOverflowIterator:()Ljava/util/Iterator;
      25: invokeinterface #25,  1           // InterfaceMethod java/util/Iterator.hasNext:()Z
      30: ifeq          37
      33: iconst_1
      34: goto          38
      37: iconst_0
      38: ireturn

  public java.util.Map$Entry<K, V> next();
    Code:
       0: aload_0
       1: iconst_1
       2: putfield      #13                 // Field nextCalledBeforeRemove:Z
       5: aload_0
       6: dup
       7: getfield      #14                 // Field pos:I
      10: iconst_1
      11: iadd
      12: dup_x1
      13: putfield      #14                 // Field pos:I
      16: aload_0
      17: getfield      #15                 // Field this$0:Lkotlin/reflect/jvm/internal/impl/protobuf/SmallSortedMap;
      20: invokestatic  #19                 // Method kotlin/reflect/jvm/internal/impl/protobuf/SmallSortedMap.access$400:(Lkotlin/reflect/jvm/internal/impl/protobuf/SmallSortedMap;)Ljava/util/List;
      23: invokeinterface #29,  1           // InterfaceMethod java/util/List.size:()I
      28: if_icmpge     51
      31: aload_0
      32: getfield      #15                 // Field this$0:Lkotlin/reflect/jvm/internal/impl/protobuf/SmallSortedMap;
      35: invokestatic  #19                 // Method kotlin/reflect/jvm/internal/impl/protobuf/SmallSortedMap.access$400:(Lkotlin/reflect/jvm/internal/impl/protobuf/SmallSortedMap;)Ljava/util/List;
      38: aload_0
      39: getfield      #14                 // Field pos:I
      42: invokeinterface #28,  2           // InterfaceMethod java/util/List.get:(I)Ljava/lang/Object;
      47: checkcast     #7                  // class java/util/Map$Entry
      50: areturn
      51: aload_0
      52: invokespecial #23                 // Method getOverflowIterator:()Ljava/util/Iterator;
      55: invokeinterface #26,  1           // InterfaceMethod java/util/Iterator.next:()Ljava/lang/Object;
      60: checkcast     #7                  // class java/util/Map$Entry
      63: areturn

  public void remove();
    Code:
       0: aload_0
       1: getfield      #13                 // Field nextCalledBeforeRemove:Z
       4: ifne          17
       7: new           #2                  // class java/lang/IllegalStateException
      10: dup
      11: ldc           #1                  // String remove() was called before next()
      13: invokespecial #16                 // Method java/lang/IllegalStateException."<init>":(Ljava/lang/String;)V
      16: athrow
      17: aload_0
      18: iconst_0
      19: putfield      #13                 // Field nextCalledBeforeRemove:Z
      22: aload_0
      23: getfield      #15                 // Field this$0:Lkotlin/reflect/jvm/internal/impl/protobuf/SmallSortedMap;
      26: invokestatic  #18                 // Method kotlin/reflect/jvm/internal/impl/protobuf/SmallSortedMap.access$200:(Lkotlin/reflect/jvm/internal/impl/protobuf/SmallSortedMap;)V
      29: aload_0
      30: getfield      #14                 // Field pos:I
      33: aload_0
      34: getfield      #15                 // Field this$0:Lkotlin/reflect/jvm/internal/impl/protobuf/SmallSortedMap;
      37: invokestatic  #19                 // Method kotlin/reflect/jvm/internal/impl/protobuf/SmallSortedMap.access$400:(Lkotlin/reflect/jvm/internal/impl/protobuf/SmallSortedMap;)Ljava/util/List;
      40: invokeinterface #29,  1           // InterfaceMethod java/util/List.size:()I
      45: if_icmpge     70
      48: aload_0
      49: getfield      #15                 // Field this$0:Lkotlin/reflect/jvm/internal/impl/protobuf/SmallSortedMap;
      52: aload_0
      53: dup
      54: getfield      #14                 // Field pos:I
      57: dup_x1
      58: iconst_1
      59: isub
      60: putfield      #14                 // Field pos:I
      63: invokestatic  #20                 // Method kotlin/reflect/jvm/internal/impl/protobuf/SmallSortedMap.access$500:(Lkotlin/reflect/jvm/internal/impl/protobuf/SmallSortedMap;I)Ljava/lang/Object;
      66: pop
      67: goto          79
      70: aload_0
      71: invokespecial #23                 // Method getOverflowIterator:()Ljava/util/Iterator;
      74: invokeinterface #27,  1           // InterfaceMethod java/util/Iterator.remove:()V
      79: return

  private java.util.Iterator<java.util.Map$Entry<K, V>> getOverflowIterator();
    Code:
       0: aload_0
       1: getfield      #12                 // Field lazyOverflowIterator:Ljava/util/Iterator;
       4: ifnonnull     28
       7: aload_0
       8: aload_0
       9: getfield      #15                 // Field this$0:Lkotlin/reflect/jvm/internal/impl/protobuf/SmallSortedMap;
      12: invokestatic  #21                 // Method kotlin/reflect/jvm/internal/impl/protobuf/SmallSortedMap.access$600:(Lkotlin/reflect/jvm/internal/impl/protobuf/SmallSortedMap;)Ljava/util/Map;
      15: invokeinterface #30,  1           // InterfaceMethod java/util/Map.entrySet:()Ljava/util/Set;
      20: invokeinterface #31,  1           // InterfaceMethod java/util/Set.iterator:()Ljava/util/Iterator;
      25: putfield      #12                 // Field lazyOverflowIterator:Ljava/util/Iterator;
      28: aload_0
      29: getfield      #12                 // Field lazyOverflowIterator:Ljava/util/Iterator;
      32: areturn

  public java.lang.Object next();
    Code:
       0: aload_0
       1: invokevirtual #24                 // Method next:()Ljava/util/Map$Entry;
       4: areturn

  kotlin.reflect.jvm.internal.impl.protobuf.SmallSortedMap$EntryIterator(kotlin.reflect.jvm.internal.impl.protobuf.SmallSortedMap, kotlin.reflect.jvm.internal.impl.protobuf.SmallSortedMap$1);
    Code:
       0: aload_0
       1: aload_1
       2: invokespecial #22                 // Method "<init>":(Lkotlin/reflect/jvm/internal/impl/protobuf/SmallSortedMap;)V
       5: return
}
