Compiled from "Curve.java"
public class org.signal.libsignal.protocol.ecc.Curve {
  public static final int DJB_TYPE;

  public org.signal.libsignal.protocol.ecc.Curve();
    Code:
       0: aload_0
       1: invokespecial #1                  // Method java/lang/Object."<init>":()V
       4: return

  public static org.signal.libsignal.protocol.ecc.ECKeyPair generateKeyPair();
    Code:
       0: invokestatic  #2                  // Method org/signal/libsignal/protocol/ecc/ECPrivateKey.generate:()Lorg/signal/libsignal/protocol/ecc/ECPrivateKey;
       3: astore_0
       4: aload_0
       5: invokevirtual #3                  // Method org/signal/libsignal/protocol/ecc/ECPrivateKey.publicKey:()Lorg/signal/libsignal/protocol/ecc/ECPublicKey;
       8: astore_1
       9: new           #4                  // class org/signal/libsignal/protocol/ecc/ECKeyPair
      12: dup
      13: aload_1
      14: aload_0
      15: invokespecial #5                  // Method org/signal/libsignal/protocol/ecc/ECKeyPair."<init>":(Lorg/signal/libsignal/protocol/ecc/ECPublicKey;Lorg/signal/libsignal/protocol/ecc/ECPrivateKey;)V
      18: areturn

  public static org.signal.libsignal.protocol.ecc.ECPublicKey decodePoint(byte[], int) throws org.signal.libsignal.protocol.InvalidKeyException;
    Code:
       0: aload_0
       1: ifnull        12
       4: aload_0
       5: arraylength
       6: iload_1
       7: isub
       8: iconst_1
       9: if_icmpge     22
      12: new           #6                  // class org/signal/libsignal/protocol/InvalidKeyException
      15: dup
      16: ldc           #7                  // String No key type identifier
      18: invokespecial #8                  // Method org/signal/libsignal/protocol/InvalidKeyException."<init>":(Ljava/lang/String;)V
      21: athrow
      22: new           #9                  // class org/signal/libsignal/protocol/ecc/ECPublicKey
      25: dup
      26: aload_0
      27: iload_1
      28: invokespecial #10                 // Method org/signal/libsignal/protocol/ecc/ECPublicKey."<init>":([BI)V
      31: areturn

  public static org.signal.libsignal.protocol.ecc.ECPrivateKey decodePrivatePoint(byte[]);
    Code:
       0: new           #11                 // class org/signal/libsignal/protocol/ecc/ECPrivateKey
       3: dup
       4: aload_0
       5: invokespecial #12                 // Method org/signal/libsignal/protocol/ecc/ECPrivateKey."<init>":([B)V
       8: areturn

  public static byte[] calculateAgreement(org.signal.libsignal.protocol.ecc.ECPublicKey, org.signal.libsignal.protocol.ecc.ECPrivateKey) throws org.signal.libsignal.protocol.InvalidKeyException;
    Code:
       0: aload_0
       1: ifnonnull     14
       4: new           #6                  // class org/signal/libsignal/protocol/InvalidKeyException
       7: dup
       8: ldc           #13                 // String public value is null
      10: invokespecial #8                  // Method org/signal/libsignal/protocol/InvalidKeyException."<init>":(Ljava/lang/String;)V
      13: athrow
      14: aload_1
      15: ifnonnull     28
      18: new           #6                  // class org/signal/libsignal/protocol/InvalidKeyException
      21: dup
      22: ldc           #14                 // String private value is null
      24: invokespecial #8                  // Method org/signal/libsignal/protocol/InvalidKeyException."<init>":(Ljava/lang/String;)V
      27: athrow
      28: aload_1
      29: aload_0
      30: invokevirtual #15                 // Method org/signal/libsignal/protocol/ecc/ECPrivateKey.calculateAgreement:(Lorg/signal/libsignal/protocol/ecc/ECPublicKey;)[B
      33: areturn

  public static boolean verifySignature(org.signal.libsignal.protocol.ecc.ECPublicKey, byte[], byte[]) throws org.signal.libsignal.protocol.InvalidKeyException;
    Code:
       0: aload_0
       1: ifnull        12
       4: aload_1
       5: ifnull        12
       8: aload_2
       9: ifnonnull     22
      12: new           #6                  // class org/signal/libsignal/protocol/InvalidKeyException
      15: dup
      16: ldc           #16                 // String Values must not be null
      18: invokespecial #8                  // Method org/signal/libsignal/protocol/InvalidKeyException."<init>":(Ljava/lang/String;)V
      21: athrow
      22: aload_0
      23: aload_1
      24: aload_2
      25: invokevirtual #17                 // Method org/signal/libsignal/protocol/ecc/ECPublicKey.verifySignature:([B[B)Z
      28: ireturn

  public static byte[] calculateSignature(org.signal.libsignal.protocol.ecc.ECPrivateKey, byte[]) throws org.signal.libsignal.protocol.InvalidKeyException;
    Code:
       0: aload_0
       1: ifnull        8
       4: aload_1
       5: ifnonnull     18
       8: new           #6                  // class org/signal/libsignal/protocol/InvalidKeyException
      11: dup
      12: ldc           #16                 // String Values must not be null
      14: invokespecial #8                  // Method org/signal/libsignal/protocol/InvalidKeyException."<init>":(Ljava/lang/String;)V
      17: athrow
      18: aload_0
      19: aload_1
      20: invokevirtual #18                 // Method org/signal/libsignal/protocol/ecc/ECPrivateKey.calculateSignature:([B)[B
      23: areturn
}
