Compiled from "TCAPProviderImpl.java"
public class org.mobicents.protocols.ss7.tcap.TCAPProviderImpl$PrevewDialogDataKey {
  public int dpc;

  public java.lang.String sccpDigits;

  public int ssn;

  public long origTxId;

  final org.mobicents.protocols.ss7.tcap.TCAPProviderImpl this$0;

  public org.mobicents.protocols.ss7.tcap.TCAPProviderImpl$PrevewDialogDataKey(org.mobicents.protocols.ss7.tcap.TCAPProviderImpl, int, java.lang.String, int, long);
    Code:
       0: aload_0
       1: aload_1
       2: putfield      #1                  // Field this$0:Lorg/mobicents/protocols/ss7/tcap/TCAPProviderImpl;
       5: aload_0
       6: invokespecial #2                  // Method java/lang/Object."<init>":()V
       9: aload_0
      10: iload_2
      11: putfield      #3                  // Field dpc:I
      14: aload_0
      15: aload_3
      16: putfield      #4                  // Field sccpDigits:Ljava/lang/String;
      19: aload_0
      20: iload         4
      22: putfield      #5                  // Field ssn:I
      25: aload_0
      26: lload         5
      28: putfield      #6                  // Field origTxId:J
      31: return

  public boolean equals(java.lang.Object);
    Code:
       0: aload_1
       1: ifnonnull     6
       4: iconst_0
       5: ireturn
       6: aload_1
       7: instanceof    #7                  // class org/mobicents/protocols/ss7/tcap/TCAPProviderImpl$PrevewDialogDataKey
      10: ifne          15
      13: iconst_0
      14: ireturn
      15: aload_1
      16: checkcast     #7                  // class org/mobicents/protocols/ss7/tcap/TCAPProviderImpl$PrevewDialogDataKey
      19: astore_2
      20: aload_0
      21: getfield      #4                  // Field sccpDigits:Ljava/lang/String;
      24: ifnull        43
      27: aload_0
      28: getfield      #4                  // Field sccpDigits:Ljava/lang/String;
      31: aload_2
      32: getfield      #4                  // Field sccpDigits:Ljava/lang/String;
      35: invokevirtual #8                  // Method java/lang/String.equals:(Ljava/lang/Object;)Z
      38: ifne          56
      41: iconst_0
      42: ireturn
      43: aload_0
      44: getfield      #3                  // Field dpc:I
      47: aload_2
      48: getfield      #3                  // Field dpc:I
      51: if_icmpeq     56
      54: iconst_0
      55: ireturn
      56: aload_0
      57: getfield      #5                  // Field ssn:I
      60: aload_2
      61: getfield      #5                  // Field ssn:I
      64: if_icmpeq     69
      67: iconst_0
      68: ireturn
      69: aload_0
      70: getfield      #6                  // Field origTxId:J
      73: aload_2
      74: getfield      #6                  // Field origTxId:J
      77: lcmp
      78: ifeq          83
      81: iconst_0
      82: ireturn
      83: iconst_1
      84: ireturn

  public int hashCode();
    Code:
       0: bipush        31
       2: istore_1
       3: iconst_1
       4: istore_2
       5: aload_0
       6: getfield      #4                  // Field sccpDigits:Ljava/lang/String;
       9: ifnull        39
      12: bipush        31
      14: iload_2
      15: imul
      16: aload_0
      17: getfield      #4                  // Field sccpDigits:Ljava/lang/String;
      20: ifnonnull     27
      23: iconst_0
      24: goto          34
      27: aload_0
      28: getfield      #4                  // Field sccpDigits:Ljava/lang/String;
      31: invokevirtual #9                  // Method java/lang/String.hashCode:()I
      34: iadd
      35: istore_2
      36: goto          49
      39: bipush        31
      41: iload_2
      42: imul
      43: aload_0
      44: getfield      #3                  // Field dpc:I
      47: iadd
      48: istore_2
      49: bipush        31
      51: iload_2
      52: imul
      53: aload_0
      54: getfield      #5                  // Field ssn:I
      57: iadd
      58: istore_2
      59: bipush        31
      61: iload_2
      62: imul
      63: aload_0
      64: getfield      #6                  // Field origTxId:J
      67: aload_0
      68: getfield      #6                  // Field origTxId:J
      71: bipush        32
      73: lshr
      74: ladd
      75: l2i
      76: iadd
      77: istore_2
      78: iload_2
      79: ireturn
}
