Compiled from "HttpSecurityDsl.kt"
public final class org.springframework.security.config.web.servlet.HttpSecurityDslKt {
  public static final void invoke(org.springframework.security.config.annotation.web.builders.HttpSecurity, kotlin.jvm.functions.Function1<? super org.springframework.security.config.web.servlet.HttpSecurityDsl, kotlin.Unit>);
    Code:
       0: aload_0
       1: ldc           #10                 // String $this$invoke
       3: invokestatic  #16                 // Method kotlin/jvm/internal/Intrinsics.checkParameterIsNotNull:(Ljava/lang/Object;Ljava/lang/String;)V
       6: aload_1
       7: ldc           #18                 // String httpConfiguration
       9: invokestatic  #16                 // Method kotlin/jvm/internal/Intrinsics.checkParameterIsNotNull:(Ljava/lang/Object;Ljava/lang/String;)V
      12: new           #20                 // class org/springframework/security/config/web/servlet/HttpSecurityDsl
      15: dup
      16: aload_0
      17: aload_1
      18: invokespecial #23                 // Method org/springframework/security/config/web/servlet/HttpSecurityDsl."<init>":(Lorg/springframework/security/config/annotation/web/builders/HttpSecurity;Lkotlin/jvm/functions/Function1;)V
      21: invokevirtual #27                 // Method org/springframework/security/config/web/servlet/HttpSecurityDsl.build$spring_security_config:()V
      24: return
}
