Compiled from "OAuth2ClientDsl.kt"
public final class org.springframework.security.config.web.servlet.OAuth2ClientDsl {
  private org.springframework.security.oauth2.client.registration.ClientRegistrationRepository clientRegistrationRepository;

  private org.springframework.security.oauth2.client.web.OAuth2AuthorizedClientRepository authorizedClientRepository;

  private org.springframework.security.oauth2.client.OAuth2AuthorizedClientService authorizedClientService;

  private kotlin.jvm.functions.Function1<? super org.springframework.security.config.annotation.web.configurers.oauth2.client.OAuth2ClientConfigurer<org.springframework.security.config.annotation.web.builders.HttpSecurity>.AuthorizationCodeGrantConfigurer, kotlin.Unit> authorizationCodeGrant;

  public final org.springframework.security.oauth2.client.registration.ClientRegistrationRepository getClientRegistrationRepository();
    Code:
       0: aload_0
       1: getfield      #12                 // Field clientRegistrationRepository:Lorg/springframework/security/oauth2/client/registration/ClientRegistrationRepository;
       4: areturn

  public final void setClientRegistrationRepository(org.springframework.security.oauth2.client.registration.ClientRegistrationRepository);
    Code:
       0: aload_0
       1: aload_1
       2: putfield      #12                 // Field clientRegistrationRepository:Lorg/springframework/security/oauth2/client/registration/ClientRegistrationRepository;
       5: return

  public final org.springframework.security.oauth2.client.web.OAuth2AuthorizedClientRepository getAuthorizedClientRepository();
    Code:
       0: aload_0
       1: getfield      #23                 // Field authorizedClientRepository:Lorg/springframework/security/oauth2/client/web/OAuth2AuthorizedClientRepository;
       4: areturn

  public final void setAuthorizedClientRepository(org.springframework.security.oauth2.client.web.OAuth2AuthorizedClientRepository);
    Code:
       0: aload_0
       1: aload_1
       2: putfield      #23                 // Field authorizedClientRepository:Lorg/springframework/security/oauth2/client/web/OAuth2AuthorizedClientRepository;
       5: return

  public final org.springframework.security.oauth2.client.OAuth2AuthorizedClientService getAuthorizedClientService();
    Code:
       0: aload_0
       1: getfield      #31                 // Field authorizedClientService:Lorg/springframework/security/oauth2/client/OAuth2AuthorizedClientService;
       4: areturn

  public final void setAuthorizedClientService(org.springframework.security.oauth2.client.OAuth2AuthorizedClientService);
    Code:
       0: aload_0
       1: aload_1
       2: putfield      #31                 // Field authorizedClientService:Lorg/springframework/security/oauth2/client/OAuth2AuthorizedClientService;
       5: return

  public final void authorizationCodeGrant(kotlin.jvm.functions.Function1<? super org.springframework.security.config.web.servlet.oauth2.client.AuthorizationCodeGrantDsl, kotlin.Unit>);
    Code:
       0: aload_1
       1: ldc           #41                 // String authorizationCodeGrantConfig
       3: invokestatic  #47                 // Method kotlin/jvm/internal/Intrinsics.checkParameterIsNotNull:(Ljava/lang/Object;Ljava/lang/String;)V
       6: aload_0
       7: new           #49                 // class org/springframework/security/config/web/servlet/oauth2/client/AuthorizationCodeGrantDsl
      10: dup
      11: invokespecial #53                 // Method org/springframework/security/config/web/servlet/oauth2/client/AuthorizationCodeGrantDsl."<init>":()V
      14: astore_2
      15: astore        5
      17: iconst_0
      18: istore_3
      19: iconst_0
      20: istore        4
      22: aload_1
      23: aload_2
      24: invokeinterface #59,  2           // InterfaceMethod kotlin/jvm/functions/Function1.invoke:(Ljava/lang/Object;)Ljava/lang/Object;
      29: pop
      30: aload_2
      31: astore        6
      33: aload         5
      35: aload         6
      37: invokevirtual #63                 // Method org/springframework/security/config/web/servlet/oauth2/client/AuthorizationCodeGrantDsl.get$spring_security_config:()Lkotlin/jvm/functions/Function1;
      40: putfield      #65                 // Field authorizationCodeGrant:Lkotlin/jvm/functions/Function1;
      43: return

  public final kotlin.jvm.functions.Function1<org.springframework.security.config.annotation.web.configurers.oauth2.client.OAuth2ClientConfigurer<org.springframework.security.config.annotation.web.builders.HttpSecurity>, kotlin.Unit> get$spring_security_config();
    Code:
       0: new           #68                 // class org/springframework/security/config/web/servlet/OAuth2ClientDsl$get$1
       3: dup
       4: aload_0
       5: invokespecial #71                 // Method org/springframework/security/config/web/servlet/OAuth2ClientDsl$get$1."<init>":(Lorg/springframework/security/config/web/servlet/OAuth2ClientDsl;)V
       8: checkcast     #55                 // class kotlin/jvm/functions/Function1
      11: areturn

  public org.springframework.security.config.web.servlet.OAuth2ClientDsl();
    Code:
       0: aload_0
       1: invokespecial #72                 // Method java/lang/Object."<init>":()V
       4: return

  public static final kotlin.jvm.functions.Function1 access$getAuthorizationCodeGrant$p(org.springframework.security.config.web.servlet.OAuth2ClientDsl);
    Code:
       0: aload_0
       1: getfield      #65                 // Field authorizationCodeGrant:Lkotlin/jvm/functions/Function1;
       4: areturn

  public static final void access$setAuthorizationCodeGrant$p(org.springframework.security.config.web.servlet.OAuth2ClientDsl, kotlin.jvm.functions.Function1);
    Code:
       0: aload_0
       1: aload_1
       2: putfield      #65                 // Field authorizationCodeGrant:Lkotlin/jvm/functions/Function1;
       5: return
}
