Compiled from "X509Dsl.kt"
final class org.springframework.security.config.web.servlet.X509Dsl$get$1 extends kotlin.jvm.internal.Lambda implements kotlin.jvm.functions.Function1<org.springframework.security.config.annotation.web.configurers.X509Configurer<org.springframework.security.config.annotation.web.builders.HttpSecurity>, kotlin.Unit> {
  final org.springframework.security.config.web.servlet.X509Dsl this$0;

  public java.lang.Object invoke(java.lang.Object);
    Code:
       0: aload_0
       1: aload_1
       2: checkcast     #11                 // class org/springframework/security/config/annotation/web/configurers/X509Configurer
       5: invokevirtual #14                 // Method invoke:(Lorg/springframework/security/config/annotation/web/configurers/X509Configurer;)V
       8: getstatic     #20                 // Field kotlin/Unit.INSTANCE:Lkotlin/Unit;
      11: areturn

  public final void invoke(org.springframework.security.config.annotation.web.configurers.X509Configurer<org.springframework.security.config.annotation.web.builders.HttpSecurity>);
    Code:
       0: aload_1
       1: ldc           #24                 // String x509
       3: invokestatic  #30                 // Method kotlin/jvm/internal/Intrinsics.checkParameterIsNotNull:(Ljava/lang/Object;Ljava/lang/String;)V
       6: aload_0
       7: getfield      #34                 // Field this$0:Lorg/springframework/security/config/web/servlet/X509Dsl;
      10: invokevirtual #40                 // Method org/springframework/security/config/web/servlet/X509Dsl.getX509AuthenticationFilter:()Lorg/springframework/security/web/authentication/preauth/x509/X509AuthenticationFilter;
      13: dup
      14: ifnull        44
      17: astore_2
      18: iconst_0
      19: istore_3
      20: iconst_0
      21: istore        4
      23: aload_2
      24: astore        5
      26: iconst_0
      27: istore        6
      29: aload_1
      30: aload_0
      31: getfield      #34                 // Field this$0:Lorg/springframework/security/config/web/servlet/X509Dsl;
      34: invokevirtual #40                 // Method org/springframework/security/config/web/servlet/X509Dsl.getX509AuthenticationFilter:()Lorg/springframework/security/web/authentication/preauth/x509/X509AuthenticationFilter;
      37: invokevirtual #44                 // Method org/springframework/security/config/annotation/web/configurers/X509Configurer.x509AuthenticationFilter:(Lorg/springframework/security/web/authentication/preauth/x509/X509AuthenticationFilter;)Lorg/springframework/security/config/annotation/web/configurers/X509Configurer;
      40: pop
      41: goto          45
      44: pop
      45: aload_0
      46: getfield      #34                 // Field this$0:Lorg/springframework/security/config/web/servlet/X509Dsl;
      49: invokevirtual #48                 // Method org/springframework/security/config/web/servlet/X509Dsl.getX509PrincipalExtractor:()Lorg/springframework/security/web/authentication/preauth/x509/X509PrincipalExtractor;
      52: dup
      53: ifnull        83
      56: astore_2
      57: iconst_0
      58: istore_3
      59: iconst_0
      60: istore        4
      62: aload_2
      63: astore        5
      65: iconst_0
      66: istore        6
      68: aload_1
      69: aload_0
      70: getfield      #34                 // Field this$0:Lorg/springframework/security/config/web/servlet/X509Dsl;
      73: invokevirtual #48                 // Method org/springframework/security/config/web/servlet/X509Dsl.getX509PrincipalExtractor:()Lorg/springframework/security/web/authentication/preauth/x509/X509PrincipalExtractor;
      76: invokevirtual #52                 // Method org/springframework/security/config/annotation/web/configurers/X509Configurer.x509PrincipalExtractor:(Lorg/springframework/security/web/authentication/preauth/x509/X509PrincipalExtractor;)Lorg/springframework/security/config/annotation/web/configurers/X509Configurer;
      79: pop
      80: goto          84
      83: pop
      84: aload_0
      85: getfield      #34                 // Field this$0:Lorg/springframework/security/config/web/servlet/X509Dsl;
      88: invokevirtual #56                 // Method org/springframework/security/config/web/servlet/X509Dsl.getAuthenticationDetailsSource:()Lorg/springframework/security/authentication/AuthenticationDetailsSource;
      91: dup
      92: ifnull        122
      95: astore_2
      96: iconst_0
      97: istore_3
      98: iconst_0
      99: istore        4
     101: aload_2
     102: astore        5
     104: iconst_0
     105: istore        6
     107: aload_1
     108: aload_0
     109: getfield      #34                 // Field this$0:Lorg/springframework/security/config/web/servlet/X509Dsl;
     112: invokevirtual #56                 // Method org/springframework/security/config/web/servlet/X509Dsl.getAuthenticationDetailsSource:()Lorg/springframework/security/authentication/AuthenticationDetailsSource;
     115: invokevirtual #60                 // Method org/springframework/security/config/annotation/web/configurers/X509Configurer.authenticationDetailsSource:(Lorg/springframework/security/authentication/AuthenticationDetailsSource;)Lorg/springframework/security/config/annotation/web/configurers/X509Configurer;
     118: pop
     119: goto          123
     122: pop
     123: aload_0
     124: getfield      #34                 // Field this$0:Lorg/springframework/security/config/web/servlet/X509Dsl;
     127: invokevirtual #64                 // Method org/springframework/security/config/web/servlet/X509Dsl.getUserDetailsService:()Lorg/springframework/security/core/userdetails/UserDetailsService;
     130: dup
     131: ifnull        161
     134: astore_2
     135: iconst_0
     136: istore_3
     137: iconst_0
     138: istore        4
     140: aload_2
     141: astore        5
     143: iconst_0
     144: istore        6
     146: aload_1
     147: aload_0
     148: getfield      #34                 // Field this$0:Lorg/springframework/security/config/web/servlet/X509Dsl;
     151: invokevirtual #64                 // Method org/springframework/security/config/web/servlet/X509Dsl.getUserDetailsService:()Lorg/springframework/security/core/userdetails/UserDetailsService;
     154: invokevirtual #68                 // Method org/springframework/security/config/annotation/web/configurers/X509Configurer.userDetailsService:(Lorg/springframework/security/core/userdetails/UserDetailsService;)Lorg/springframework/security/config/annotation/web/configurers/X509Configurer;
     157: pop
     158: goto          162
     161: pop
     162: aload_0
     163: getfield      #34                 // Field this$0:Lorg/springframework/security/config/web/servlet/X509Dsl;
     166: invokevirtual #72                 // Method org/springframework/security/config/web/servlet/X509Dsl.getAuthenticationUserDetailsService:()Lorg/springframework/security/core/userdetails/AuthenticationUserDetailsService;
     169: dup
     170: ifnull        200
     173: astore_2
     174: iconst_0
     175: istore_3
     176: iconst_0
     177: istore        4
     179: aload_2
     180: astore        5
     182: iconst_0
     183: istore        6
     185: aload_1
     186: aload_0
     187: getfield      #34                 // Field this$0:Lorg/springframework/security/config/web/servlet/X509Dsl;
     190: invokevirtual #72                 // Method org/springframework/security/config/web/servlet/X509Dsl.getAuthenticationUserDetailsService:()Lorg/springframework/security/core/userdetails/AuthenticationUserDetailsService;
     193: invokevirtual #76                 // Method org/springframework/security/config/annotation/web/configurers/X509Configurer.authenticationUserDetailsService:(Lorg/springframework/security/core/userdetails/AuthenticationUserDetailsService;)Lorg/springframework/security/config/annotation/web/configurers/X509Configurer;
     196: pop
     197: goto          201
     200: pop
     201: aload_0
     202: getfield      #34                 // Field this$0:Lorg/springframework/security/config/web/servlet/X509Dsl;
     205: invokevirtual #80                 // Method org/springframework/security/config/web/servlet/X509Dsl.getSubjectPrincipalRegex:()Ljava/lang/String;
     208: dup
     209: ifnull        239
     212: astore_2
     213: iconst_0
     214: istore_3
     215: iconst_0
     216: istore        4
     218: aload_2
     219: astore        5
     221: iconst_0
     222: istore        6
     224: aload_1
     225: aload_0
     226: getfield      #34                 // Field this$0:Lorg/springframework/security/config/web/servlet/X509Dsl;
     229: invokevirtual #80                 // Method org/springframework/security/config/web/servlet/X509Dsl.getSubjectPrincipalRegex:()Ljava/lang/String;
     232: invokevirtual #84                 // Method org/springframework/security/config/annotation/web/configurers/X509Configurer.subjectPrincipalRegex:(Ljava/lang/String;)Lorg/springframework/security/config/annotation/web/configurers/X509Configurer;
     235: pop
     236: goto          240
     239: pop
     240: return

  org.springframework.security.config.web.servlet.X509Dsl$get$1(org.springframework.security.config.web.servlet.X509Dsl);
    Code:
       0: aload_0
       1: aload_1
       2: putfield      #34                 // Field this$0:Lorg/springframework/security/config/web/servlet/X509Dsl;
       5: aload_0
       6: iconst_1
       7: invokespecial #118                // Method kotlin/jvm/internal/Lambda."<init>":(I)V
      10: return
}
