Compiled from "BitSet.java"
public final class org.joni.BitSet {
  static final int BITS_PER_BYTE;

  public static final int SINGLE_BYTE_SIZE;

  private static final int BITS_IN_ROOM;

  static final int BITSET_SIZE;

  static final int ROOM_SHIFT;

  final int[] bits;

  private static final int BITS_TO_STRING_WRAP;

  public org.joni.BitSet();
    Code:
       0: aload_0
       1: invokespecial #1                  // Method java/lang/Object."<init>":()V
       4: aload_0
       5: bipush        8
       7: newarray       int
       9: putfield      #2                  // Field bits:[I
      12: return

  public java.lang.String toString();
    Code:
       0: new           #3                  // class java/lang/StringBuilder
       3: dup
       4: invokespecial #4                  // Method java/lang/StringBuilder."<init>":()V
       7: astore_1
       8: aload_1
       9: ldc           #5                  // String BitSet
      11: invokevirtual #6                  // Method java/lang/StringBuilder.append:(Ljava/lang/String;)Ljava/lang/StringBuilder;
      14: pop
      15: iconst_0
      16: istore_2
      17: iload_2
      18: sipush        256
      21: if_icmpge     64
      24: iload_2
      25: bipush        64
      27: irem
      28: ifne          38
      31: aload_1
      32: ldc           #7                  // String \n
      34: invokevirtual #6                  // Method java/lang/StringBuilder.append:(Ljava/lang/String;)Ljava/lang/StringBuilder;
      37: pop
      38: aload_1
      39: aload_0
      40: iload_2
      41: invokevirtual #8                  // Method at:(I)Z
      44: ifeq          52
      47: ldc           #9                  // String 1
      49: goto          54
      52: ldc           #10                 // String 0
      54: invokevirtual #6                  // Method java/lang/StringBuilder.append:(Ljava/lang/String;)Ljava/lang/StringBuilder;
      57: pop
      58: iinc          2, 1
      61: goto          17
      64: aload_1
      65: invokevirtual #11                 // Method java/lang/StringBuilder.toString:()Ljava/lang/String;
      68: areturn

  public boolean at(int);
    Code:
       0: aload_0
       1: getfield      #2                  // Field bits:[I
       4: iload_1
       5: getstatic     #12                 // Field ROOM_SHIFT:I
       8: iushr
       9: iaload
      10: iload_1
      11: invokestatic  #13                 // Method bit:(I)I
      14: iand
      15: ifeq          22
      18: iconst_1
      19: goto          23
      22: iconst_0
      23: ireturn

  public void set(int);
    Code:
       0: aload_0
       1: getfield      #2                  // Field bits:[I
       4: iload_1
       5: getstatic     #12                 // Field ROOM_SHIFT:I
       8: iushr
       9: dup2
      10: iaload
      11: iload_1
      12: invokestatic  #13                 // Method bit:(I)I
      15: ior
      16: iastore
      17: return

  public void clear(int);
    Code:
       0: aload_0
       1: getfield      #2                  // Field bits:[I
       4: iload_1
       5: getstatic     #12                 // Field ROOM_SHIFT:I
       8: iushr
       9: dup2
      10: iaload
      11: iload_1
      12: invokestatic  #13                 // Method bit:(I)I
      15: iconst_m1
      16: ixor
      17: iand
      18: iastore
      19: return

  public void invert(int);
    Code:
       0: aload_0
       1: getfield      #2                  // Field bits:[I
       4: iload_1
       5: getstatic     #12                 // Field ROOM_SHIFT:I
       8: iushr
       9: dup2
      10: iaload
      11: iload_1
      12: invokestatic  #13                 // Method bit:(I)I
      15: ixor
      16: iastore
      17: return

  public void clear();
    Code:
       0: iconst_0
       1: istore_1
       2: iload_1
       3: bipush        8
       5: if_icmpge     21
       8: aload_0
       9: getfield      #2                  // Field bits:[I
      12: iload_1
      13: iconst_0
      14: iastore
      15: iinc          1, 1
      18: goto          2
      21: return

  public boolean isEmpty();
    Code:
       0: iconst_0
       1: istore_1
       2: iload_1
       3: bipush        8
       5: if_icmpge     25
       8: aload_0
       9: getfield      #2                  // Field bits:[I
      12: iload_1
      13: iaload
      14: ifeq          19
      17: iconst_0
      18: ireturn
      19: iinc          1, 1
      22: goto          2
      25: iconst_1
      26: ireturn

  public void setRange(int, int);
    Code:
       0: iload_1
       1: istore_3
       2: iload_3
       3: iload_2
       4: if_icmpgt     25
       7: iload_3
       8: sipush        256
      11: if_icmpge     25
      14: aload_0
      15: iload_3
      16: invokevirtual #14                 // Method set:(I)V
      19: iinc          3, 1
      22: goto          2
      25: return

  public void setAll();
    Code:
       0: iconst_0
       1: istore_1
       2: iload_1
       3: bipush        8
       5: if_icmpge     21
       8: aload_0
       9: getfield      #2                  // Field bits:[I
      12: iload_1
      13: iconst_m1
      14: iastore
      15: iinc          1, 1
      18: goto          2
      21: return

  public void invert();
    Code:
       0: iconst_0
       1: istore_1
       2: iload_1
       3: bipush        8
       5: if_icmpge     28
       8: aload_0
       9: getfield      #2                  // Field bits:[I
      12: iload_1
      13: aload_0
      14: getfield      #2                  // Field bits:[I
      17: iload_1
      18: iaload
      19: iconst_m1
      20: ixor
      21: iastore
      22: iinc          1, 1
      25: goto          2
      28: return

  public void invertTo(org.joni.BitSet);
    Code:
       0: iconst_0
       1: istore_2
       2: iload_2
       3: bipush        8
       5: if_icmpge     28
       8: aload_1
       9: getfield      #2                  // Field bits:[I
      12: iload_2
      13: aload_0
      14: getfield      #2                  // Field bits:[I
      17: iload_2
      18: iaload
      19: iconst_m1
      20: ixor
      21: iastore
      22: iinc          2, 1
      25: goto          2
      28: return

  public void and(org.joni.BitSet);
    Code:
       0: iconst_0
       1: istore_2
       2: iload_2
       3: bipush        8
       5: if_icmpge     29
       8: aload_0
       9: getfield      #2                  // Field bits:[I
      12: iload_2
      13: dup2
      14: iaload
      15: aload_1
      16: getfield      #2                  // Field bits:[I
      19: iload_2
      20: iaload
      21: iand
      22: iastore
      23: iinc          2, 1
      26: goto          2
      29: return

  public void or(org.joni.BitSet);
    Code:
       0: iconst_0
       1: istore_2
       2: iload_2
       3: bipush        8
       5: if_icmpge     29
       8: aload_0
       9: getfield      #2                  // Field bits:[I
      12: iload_2
      13: dup2
      14: iaload
      15: aload_1
      16: getfield      #2                  // Field bits:[I
      19: iload_2
      20: iaload
      21: ior
      22: iastore
      23: iinc          2, 1
      26: goto          2
      29: return

  public void copy(org.joni.BitSet);
    Code:
       0: iconst_0
       1: istore_2
       2: iload_2
       3: bipush        8
       5: if_icmpge     26
       8: aload_0
       9: getfield      #2                  // Field bits:[I
      12: iload_2
      13: aload_1
      14: getfield      #2                  // Field bits:[I
      17: iload_2
      18: iaload
      19: iastore
      20: iinc          2, 1
      23: goto          2
      26: return

  public int numOn();
    Code:
       0: iconst_0
       1: istore_1
       2: iconst_0
       3: istore_2
       4: iload_2
       5: sipush        256
       8: if_icmpge     28
      11: aload_0
      12: iload_2
      13: invokevirtual #8                  // Method at:(I)Z
      16: ifeq          22
      19: iinc          1, 1
      22: iinc          2, 1
      25: goto          4
      28: iload_1
      29: ireturn

  static int bit(int);
    Code:
       0: iconst_1
       1: iload_0
       2: sipush        256
       5: irem
       6: ishl
       7: ireturn

  private static int log2(int);
    Code:
       0: iconst_0
       1: istore_1
       2: iload_0
       3: iconst_1
       4: iushr
       5: dup
       6: istore_0
       7: ifeq          16
      10: iinc          1, 1
      13: goto          2
      16: iload_1
      17: ireturn

  static {};
    Code:
       0: bipush        32
       2: invokestatic  #15                 // Method log2:(I)I
       5: putstatic     #12                 // Field ROOM_SHIFT:I
       8: return
}
