Compiled from "Matcher.java"
public abstract class org.joni.Matcher extends org.jcodings.IntHolder {
  protected final org.joni.Regex regex;

  protected final org.jcodings.Encoding enc;

  protected final byte[] bytes;

  protected final int str;

  protected final int end;

  protected int msaStart;

  protected int msaOptions;

  protected final org.joni.Region msaRegion;

  protected int msaBestLen;

  protected int msaBestS;

  protected int msaBegin;

  protected int msaEnd;

  int low;

  int high;

  public org.joni.Matcher(org.joni.Regex, byte[]);
    Code:
       0: aload_0
       1: aload_1
       2: aload_2
       3: iconst_0
       4: aload_2
       5: arraylength
       6: invokespecial #1                  // Method "<init>":(Lorg/joni/Regex;[BII)V
       9: return

  public org.joni.Matcher(org.joni.Regex, byte[], int, int);
    Code:
       0: aload_0
       1: invokespecial #2                  // Method org/jcodings/IntHolder."<init>":()V
       4: aload_0
       5: aload_1
       6: putfield      #3                  // Field regex:Lorg/joni/Regex;
       9: aload_0
      10: aload_1
      11: getfield      #4                  // Field org/joni/Regex.enc:Lorg/jcodings/Encoding;
      14: putfield      #5                  // Field enc:Lorg/jcodings/Encoding;
      17: aload_0
      18: aload_2
      19: putfield      #6                  // Field bytes:[B
      22: aload_0
      23: iload_3
      24: putfield      #7                  // Field str:I
      27: aload_0
      28: iload         4
      30: putfield      #8                  // Field end:I
      33: aload_0
      34: aload_1
      35: getfield      #9                  // Field org/joni/Regex.numMem:I
      38: ifne          45
      41: aconst_null
      42: goto          58
      45: new           #10                 // class org/joni/Region
      48: dup
      49: aload_1
      50: getfield      #9                  // Field org/joni/Regex.numMem:I
      53: iconst_1
      54: iadd
      55: invokespecial #11                 // Method org/joni/Region."<init>":(I)V
      58: putfield      #12                 // Field msaRegion:Lorg/joni/Region;
      61: return

  protected abstract int matchAt(int, int, int);

  protected abstract void stateCheckBuffInit(int, int, int);

  protected abstract void stateCheckBuffClear();

  public final org.joni.Region getRegion();
    Code:
       0: aload_0
       1: getfield      #12                 // Field msaRegion:Lorg/joni/Region;
       4: areturn

  public final org.joni.Region getEagerRegion();
    Code:
       0: aload_0
       1: getfield      #12                 // Field msaRegion:Lorg/joni/Region;
       4: ifnull        14
       7: aload_0
       8: getfield      #12                 // Field msaRegion:Lorg/joni/Region;
      11: goto          29
      14: new           #10                 // class org/joni/Region
      17: dup
      18: aload_0
      19: getfield      #13                 // Field msaBegin:I
      22: aload_0
      23: getfield      #14                 // Field msaEnd:I
      26: invokespecial #15                 // Method org/joni/Region."<init>":(II)V
      29: areturn

  public final int getBegin();
    Code:
       0: aload_0
       1: getfield      #13                 // Field msaBegin:I
       4: ireturn

  public final int getEnd();
    Code:
       0: aload_0
       1: getfield      #14                 // Field msaEnd:I
       4: ireturn

  protected final void msaInit(int, int);
    Code:
       0: aload_0
       1: iload_1
       2: putfield      #16                 // Field msaOptions:I
       5: aload_0
       6: iload_2
       7: putfield      #17                 // Field msaStart:I
      10: aload_0
      11: iconst_m1
      12: putfield      #18                 // Field msaBestLen:I
      15: return

  public final int match(int, int, int);
    Code:
       0: aload_0
       1: iload_3
       2: iload_1
       3: invokevirtual #19                 // Method msaInit:(II)V
       6: aload_0
       7: getfield      #5                  // Field enc:Lorg/jcodings/Encoding;
      10: aload_0
      11: getfield      #6                  // Field bytes:[B
      14: aload_0
      15: getfield      #7                  // Field str:I
      18: iload_1
      19: aload_0
      20: getfield      #8                  // Field end:I
      23: invokevirtual #20                 // Method org/jcodings/Encoding.prevCharHead:([BIII)I
      26: istore        4
      28: aload_0
      29: iload_2
      30: iload_1
      31: iload         4
      33: invokevirtual #21                 // Method matchAt:(III)I
      36: ireturn

  private boolean forwardSearchRange(byte[], int, int, int, int, org.jcodings.IntHolder);
    Code:
       0: iconst_m1
       1: istore        7
       3: iload         4
       5: istore        8
       7: aload_0
       8: getfield      #3                  // Field regex:Lorg/joni/Regex;
      11: getfield      #22                 // Field org/joni/Regex.dMin:I
      14: ifle          80
      17: aload_0
      18: getfield      #5                  // Field enc:Lorg/jcodings/Encoding;
      21: invokevirtual #23                 // Method org/jcodings/Encoding.isSingleByte:()Z
      24: ifeq          42
      27: iload         8
      29: aload_0
      30: getfield      #3                  // Field regex:Lorg/joni/Regex;
      33: getfield      #22                 // Field org/joni/Regex.dMin:I
      36: iadd
      37: istore        8
      39: goto          80
      42: iload         8
      44: aload_0
      45: getfield      #3                  // Field regex:Lorg/joni/Regex;
      48: getfield      #22                 // Field org/joni/Regex.dMin:I
      51: iadd
      52: istore        9
      54: iload         8
      56: iload         9
      58: if_icmpge     80
      61: iload         8
      63: aload_0
      64: getfield      #5                  // Field enc:Lorg/jcodings/Encoding;
      67: aload_1
      68: iload         8
      70: iload_3
      71: invokevirtual #24                 // Method org/jcodings/Encoding.length:([BII)I
      74: iadd
      75: istore        8
      77: goto          54
      80: aload_0
      81: getfield      #3                  // Field regex:Lorg/joni/Regex;
      84: getfield      #25                 // Field org/joni/Regex.searchAlgorithm:Lorg/joni/SearchAlgorithm;
      87: aload_0
      88: getfield      #3                  // Field regex:Lorg/joni/Regex;
      91: aload_1
      92: iload         8
      94: iload_3
      95: iload         5
      97: invokevirtual #26                 // Method org/joni/SearchAlgorithm.search:(Lorg/joni/Regex;[BIII)I
     100: istore        8
     102: iload         8
     104: iconst_m1
     105: if_icmpeq     550
     108: iload         8
     110: iload         5
     112: if_icmpge     550
     115: iload         8
     117: aload_0
     118: getfield      #3                  // Field regex:Lorg/joni/Regex;
     121: getfield      #22                 // Field org/joni/Regex.dMin:I
     124: isub
     125: iload         4
     127: if_icmpge     153
     130: iload         8
     132: istore        7
     134: iload         8
     136: aload_0
     137: getfield      #5                  // Field enc:Lorg/jcodings/Encoding;
     140: aload_1
     141: iload         8
     143: iload_3
     144: invokevirtual #24                 // Method org/jcodings/Encoding.length:([BII)I
     147: iadd
     148: istore        8
     150: goto          80
     153: aload_0
     154: getfield      #3                  // Field regex:Lorg/joni/Regex;
     157: getfield      #27                 // Field org/joni/Regex.subAnchor:I
     160: ifeq          313
     163: aload_0
     164: getfield      #3                  // Field regex:Lorg/joni/Regex;
     167: getfield      #27                 // Field org/joni/Regex.subAnchor:I
     170: lookupswitch  { // 2
                     2: 196
                    32: 267
               default: 313
          }
     196: iload         8
     198: iload_2
     199: if_icmpeq     313
     202: aload_0
     203: getfield      #5                  // Field enc:Lorg/jcodings/Encoding;
     206: aload_1
     207: iload         7
     209: iconst_m1
     210: if_icmpeq     218
     213: iload         7
     215: goto          219
     218: iload_2
     219: iload         8
     221: iload_3
     222: invokevirtual #20                 // Method org/jcodings/Encoding.prevCharHead:([BIII)I
     225: istore        9
     227: aload_0
     228: getfield      #5                  // Field enc:Lorg/jcodings/Encoding;
     231: aload_1
     232: iload         9
     234: iload_3
     235: invokevirtual #28                 // Method org/jcodings/Encoding.isNewLine:([BII)Z
     238: ifne          264
     241: iload         8
     243: istore        7
     245: iload         8
     247: aload_0
     248: getfield      #5                  // Field enc:Lorg/jcodings/Encoding;
     251: aload_1
     252: iload         8
     254: iload_3
     255: invokevirtual #24                 // Method org/jcodings/Encoding.length:([BII)I
     258: iadd
     259: istore        8
     261: goto          80
     264: goto          313
     267: iload         8
     269: iload_3
     270: if_icmpne     276
     273: goto          313
     276: aload_0
     277: getfield      #5                  // Field enc:Lorg/jcodings/Encoding;
     280: aload_1
     281: iload         8
     283: iload_3
     284: invokevirtual #28                 // Method org/jcodings/Encoding.isNewLine:([BII)Z
     287: ifne          313
     290: iload         8
     292: istore        7
     294: iload         8
     296: aload_0
     297: getfield      #5                  // Field enc:Lorg/jcodings/Encoding;
     300: aload_1
     301: iload         8
     303: iload_3
     304: invokevirtual #24                 // Method org/jcodings/Encoding.length:([BII)I
     307: iadd
     308: istore        8
     310: goto          80
     313: aload_0
     314: getfield      #3                  // Field regex:Lorg/joni/Regex;
     317: getfield      #29                 // Field org/joni/Regex.dMax:I
     320: ifne          395
     323: aload_0
     324: iload         8
     326: putfield      #30                 // Field low:I
     329: aload         6
     331: ifnull        534
     334: aload_0
     335: getfield      #30                 // Field low:I
     338: iload         4
     340: if_icmple     364
     343: aload         6
     345: aload_0
     346: getfield      #5                  // Field enc:Lorg/jcodings/Encoding;
     349: aload_1
     350: iload         4
     352: iload         8
     354: iload_3
     355: invokevirtual #20                 // Method org/jcodings/Encoding.prevCharHead:([BIII)I
     358: putfield      #31                 // Field org/jcodings/IntHolder.value:I
     361: goto          534
     364: aload         6
     366: aload_0
     367: getfield      #5                  // Field enc:Lorg/jcodings/Encoding;
     370: aload_1
     371: iload         7
     373: iconst_m1
     374: if_icmpeq     382
     377: iload         7
     379: goto          383
     382: iload_2
     383: iload         8
     385: iload_3
     386: invokevirtual #20                 // Method org/jcodings/Encoding.prevCharHead:([BIII)I
     389: putfield      #31                 // Field org/jcodings/IntHolder.value:I
     392: goto          534
     395: aload_0
     396: getfield      #3                  // Field regex:Lorg/joni/Regex;
     399: getfield      #29                 // Field org/joni/Regex.dMax:I
     402: ldc           #32                 // int 2147483647
     404: if_icmpeq     534
     407: aload_0
     408: iload         8
     410: aload_0
     411: getfield      #3                  // Field regex:Lorg/joni/Regex;
     414: getfield      #29                 // Field org/joni/Regex.dMax:I
     417: isub
     418: putfield      #30                 // Field low:I
     421: aload_0
     422: getfield      #30                 // Field low:I
     425: iload         4
     427: if_icmple     499
     430: aload_0
     431: aload_0
     432: getfield      #5                  // Field enc:Lorg/jcodings/Encoding;
     435: aload_1
     436: iload         4
     438: aload_0
     439: getfield      #30                 // Field low:I
     442: iload_3
     443: aload         6
     445: invokevirtual #33                 // Method org/jcodings/Encoding.rightAdjustCharHeadWithPrev:([BIIILorg/jcodings/IntHolder;)I
     448: putfield      #30                 // Field low:I
     451: aload         6
     453: ifnull        534
     456: aload         6
     458: getfield      #31                 // Field org/jcodings/IntHolder.value:I
     461: iconst_m1
     462: if_icmpne     534
     465: aload         6
     467: aload_0
     468: getfield      #5                  // Field enc:Lorg/jcodings/Encoding;
     471: aload_1
     472: iload         7
     474: iconst_m1
     475: if_icmpeq     483
     478: iload         7
     480: goto          485
     483: iload         4
     485: aload_0
     486: getfield      #30                 // Field low:I
     489: iload_3
     490: invokevirtual #20                 // Method org/jcodings/Encoding.prevCharHead:([BIII)I
     493: putfield      #31                 // Field org/jcodings/IntHolder.value:I
     496: goto          534
     499: aload         6
     501: ifnull        534
     504: aload         6
     506: aload_0
     507: getfield      #5                  // Field enc:Lorg/jcodings/Encoding;
     510: aload_1
     511: iload         7
     513: iconst_m1
     514: if_icmpeq     522
     517: iload         7
     519: goto          523
     522: iload_2
     523: aload_0
     524: getfield      #30                 // Field low:I
     527: iload_3
     528: invokevirtual #20                 // Method org/jcodings/Encoding.prevCharHead:([BIII)I
     531: putfield      #31                 // Field org/jcodings/IntHolder.value:I
     534: aload_0
     535: iload         8
     537: aload_0
     538: getfield      #3                  // Field regex:Lorg/joni/Regex;
     541: getfield      #22                 // Field org/joni/Regex.dMin:I
     544: isub
     545: putfield      #34                 // Field high:I
     548: iconst_1
     549: ireturn
     550: iconst_0
     551: ireturn

  private boolean backwardSearchRange(byte[], int, int, int, int, int);
    Code:
       0: iload         5
       2: aload_0
       3: getfield      #3                  // Field regex:Lorg/joni/Regex;
       6: getfield      #22                 // Field org/joni/Regex.dMin:I
       9: iadd
      10: istore        5
      12: iload         4
      14: istore        7
      16: aload_0
      17: getfield      #3                  // Field regex:Lorg/joni/Regex;
      20: getfield      #25                 // Field org/joni/Regex.searchAlgorithm:Lorg/joni/SearchAlgorithm;
      23: aload_0
      24: getfield      #3                  // Field regex:Lorg/joni/Regex;
      27: aload_1
      28: iload         5
      30: iload         6
      32: iload_3
      33: iload         7
      35: iload         4
      37: iload         5
      39: invokevirtual #35                 // Method org/joni/SearchAlgorithm.searchBackward:(Lorg/joni/Regex;[BIIIIII)I
      42: istore        7
      44: iload         7
      46: iconst_m1
      47: if_icmpeq     243
      50: aload_0
      51: getfield      #3                  // Field regex:Lorg/joni/Regex;
      54: getfield      #27                 // Field org/joni/Regex.subAnchor:I
      57: ifeq          182
      60: aload_0
      61: getfield      #3                  // Field regex:Lorg/joni/Regex;
      64: getfield      #27                 // Field org/joni/Regex.subAnchor:I
      67: lookupswitch  { // 2
                     2: 92
                    32: 136
               default: 182
          }
      92: iload         7
      94: iload_2
      95: if_icmpeq     182
      98: aload_0
      99: getfield      #5                  // Field enc:Lorg/jcodings/Encoding;
     102: aload_1
     103: iload_2
     104: iload         7
     106: iload_3
     107: invokevirtual #20                 // Method org/jcodings/Encoding.prevCharHead:([BIII)I
     110: istore        8
     112: aload_0
     113: getfield      #5                  // Field enc:Lorg/jcodings/Encoding;
     116: aload_1
     117: iload         8
     119: iload_3
     120: invokevirtual #28                 // Method org/jcodings/Encoding.isNewLine:([BII)Z
     123: ifne          133
     126: iload         8
     128: istore        7
     130: goto          16
     133: goto          182
     136: iload         7
     138: iload_3
     139: if_icmpne     145
     142: goto          182
     145: aload_0
     146: getfield      #5                  // Field enc:Lorg/jcodings/Encoding;
     149: aload_1
     150: iload         7
     152: iload_3
     153: invokevirtual #28                 // Method org/jcodings/Encoding.isNewLine:([BII)Z
     156: ifne          182
     159: aload_0
     160: getfield      #5                  // Field enc:Lorg/jcodings/Encoding;
     163: aload_1
     164: iload         6
     166: iload         7
     168: iload_3
     169: invokevirtual #20                 // Method org/jcodings/Encoding.prevCharHead:([BIII)I
     172: istore        7
     174: iload         7
     176: iconst_m1
     177: if_icmpne     16
     180: iconst_0
     181: ireturn
     182: aload_0
     183: getfield      #3                  // Field regex:Lorg/joni/Regex;
     186: getfield      #29                 // Field org/joni/Regex.dMax:I
     189: ldc           #32                 // int 2147483647
     191: if_icmpeq     241
     194: aload_0
     195: iload         7
     197: aload_0
     198: getfield      #3                  // Field regex:Lorg/joni/Regex;
     201: getfield      #29                 // Field org/joni/Regex.dMax:I
     204: isub
     205: putfield      #30                 // Field low:I
     208: aload_0
     209: iload         7
     211: aload_0
     212: getfield      #3                  // Field regex:Lorg/joni/Regex;
     215: getfield      #22                 // Field org/joni/Regex.dMin:I
     218: isub
     219: putfield      #34                 // Field high:I
     222: aload_0
     223: aload_0
     224: getfield      #5                  // Field enc:Lorg/jcodings/Encoding;
     227: aload_1
     228: iload         6
     230: aload_0
     231: getfield      #34                 // Field high:I
     234: iload_3
     235: invokevirtual #36                 // Method org/jcodings/Encoding.rightAdjustCharHead:([BIII)I
     238: putfield      #34                 // Field high:I
     241: iconst_1
     242: ireturn
     243: iconst_0
     244: ireturn

  private boolean matchCheck(int, int, int);
    Code:
       0: aload_0
       1: aload_0
       2: getfield      #8                  // Field end:I
       5: iload_2
       6: iload_3
       7: invokevirtual #21                 // Method matchAt:(III)I
      10: iconst_m1
      11: if_icmpeq     29
      14: aload_0
      15: getfield      #3                  // Field regex:Lorg/joni/Regex;
      18: getfield      #37                 // Field org/joni/Regex.options:I
      21: invokestatic  #38                 // Method org/joni/Option.isFindLongest:(I)Z
      24: ifne          29
      27: iconst_1
      28: ireturn
      29: iconst_0
      30: ireturn

  public final int search(int, int, int);
    Code:
       0: iload_1
       1: istore        6
       3: iload_2
       4: istore        7
       6: iload_1
       7: aload_0
       8: getfield      #8                  // Field end:I
      11: if_icmpgt     22
      14: iload_1
      15: aload_0
      16: getfield      #7                  // Field str:I
      19: if_icmpge     24
      22: iconst_m1
      23: ireturn
      24: aload_0
      25: getfield      #3                  // Field regex:Lorg/joni/Regex;
      28: getfield      #39                 // Field org/joni/Regex.anchor:I
      31: ifeq          324
      34: aload_0
      35: getfield      #7                  // Field str:I
      38: aload_0
      39: getfield      #8                  // Field end:I
      42: if_icmpge     324
      45: aload_0
      46: getfield      #3                  // Field regex:Lorg/joni/Regex;
      49: getfield      #39                 // Field org/joni/Regex.anchor:I
      52: iconst_4
      53: iand
      54: ifeq          74
      57: iload_2
      58: iload_1
      59: if_icmple     69
      62: iload_1
      63: iconst_1
      64: iadd
      65: istore_2
      66: goto          391
      69: iload_1
      70: istore_2
      71: goto          391
      74: aload_0
      75: getfield      #3                  // Field regex:Lorg/joni/Regex;
      78: getfield      #39                 // Field org/joni/Regex.anchor:I
      81: iconst_1
      82: iand
      83: ifeq          134
      86: iload_2
      87: iload_1
      88: if_icmple     111
      91: iload_1
      92: aload_0
      93: getfield      #7                  // Field str:I
      96: if_icmpeq     101
      99: iconst_m1
     100: ireturn
     101: aload_0
     102: getfield      #7                  // Field str:I
     105: iconst_1
     106: iadd
     107: istore_2
     108: goto          391
     111: iload_2
     112: aload_0
     113: getfield      #7                  // Field str:I
     116: if_icmpgt     132
     119: aload_0
     120: getfield      #7                  // Field str:I
     123: istore_1
     124: aload_0
     125: getfield      #7                  // Field str:I
     128: istore_2
     129: goto          391
     132: iconst_m1
     133: ireturn
     134: aload_0
     135: getfield      #3                  // Field regex:Lorg/joni/Regex;
     138: getfield      #39                 // Field org/joni/Regex.anchor:I
     141: bipush        8
     143: iand
     144: ifeq          171
     147: aload_0
     148: getfield      #8                  // Field end:I
     151: dup
     152: istore        9
     154: istore        8
     156: aload_0
     157: iload_1
     158: iload_2
     159: iload         8
     161: iload         9
     163: invokespecial #40                 // Method endBuf:(IIII)Z
     166: ifeq          391
     169: iconst_m1
     170: ireturn
     171: aload_0
     172: getfield      #3                  // Field regex:Lorg/joni/Regex;
     175: getfield      #39                 // Field org/joni/Regex.anchor:I
     178: bipush        16
     180: iand
     181: ifeq          294
     184: aload_0
     185: getfield      #5                  // Field enc:Lorg/jcodings/Encoding;
     188: aload_0
     189: getfield      #6                  // Field bytes:[B
     192: aload_0
     193: getfield      #7                  // Field str:I
     196: aload_0
     197: getfield      #8                  // Field end:I
     200: aload_0
     201: getfield      #8                  // Field end:I
     204: iconst_1
     205: invokevirtual #41                 // Method org/jcodings/Encoding.stepBack:([BIIII)I
     208: istore        10
     210: aload_0
     211: getfield      #8                  // Field end:I
     214: istore        9
     216: aload_0
     217: getfield      #5                  // Field enc:Lorg/jcodings/Encoding;
     220: aload_0
     221: getfield      #6                  // Field bytes:[B
     224: iload         10
     226: aload_0
     227: getfield      #8                  // Field end:I
     230: invokevirtual #28                 // Method org/jcodings/Encoding.isNewLine:([BII)Z
     233: ifeq          270
     236: iload         10
     238: istore        8
     240: iload         8
     242: aload_0
     243: getfield      #7                  // Field str:I
     246: if_icmple     291
     249: iload_1
     250: iload         8
     252: if_icmpgt     291
     255: aload_0
     256: iload_1
     257: iload_2
     258: iload         8
     260: iload         9
     262: invokespecial #40                 // Method endBuf:(IIII)Z
     265: ifeq          291
     268: iconst_m1
     269: ireturn
     270: aload_0
     271: getfield      #8                  // Field end:I
     274: istore        8
     276: aload_0
     277: iload_1
     278: iload_2
     279: iload         8
     281: iload         9
     283: invokespecial #40                 // Method endBuf:(IIII)Z
     286: ifeq          291
     289: iconst_m1
     290: ireturn
     291: goto          391
     294: aload_0
     295: getfield      #3                  // Field regex:Lorg/joni/Regex;
     298: getfield      #39                 // Field org/joni/Regex.anchor:I
     301: ldc           #42                 // int 32768
     303: iand
     304: ifeq          391
     307: iload_2
     308: iload_1
     309: if_icmple     319
     312: iload_1
     313: iconst_1
     314: iadd
     315: istore_2
     316: goto          391
     319: iload_1
     320: istore_2
     321: goto          391
     324: aload_0
     325: getfield      #7                  // Field str:I
     328: aload_0
     329: getfield      #8                  // Field end:I
     332: if_icmpne     391
     335: aload_0
     336: getfield      #3                  // Field regex:Lorg/joni/Regex;
     339: getfield      #43                 // Field org/joni/Regex.thresholdLength:I
     342: ifne          389
     345: aload_0
     346: getfield      #7                  // Field str:I
     349: dup
     350: istore_1
     351: istore        4
     353: iconst_m1
     354: istore        5
     356: aload_0
     357: iload_3
     358: iload_1
     359: invokevirtual #19                 // Method msaInit:(II)V
     362: aload_0
     363: aload_0
     364: getfield      #8                  // Field end:I
     367: iload         4
     369: iload         5
     371: invokespecial #44                 // Method matchCheck:(III)Z
     374: ifeq          384
     377: aload_0
     378: iload         4
     380: invokespecial #45                 // Method match:(I)I
     383: ireturn
     384: aload_0
     385: invokespecial #46                 // Method mismatch:()I
     388: ireturn
     389: iconst_m1
     390: ireturn
     391: aload_0
     392: iload_3
     393: iload         6
     395: invokevirtual #19                 // Method msaInit:(II)V
     398: iload_1
     399: istore        4
     401: iload_2
     402: iload_1
     403: if_icmple     903
     406: iload         4
     408: aload_0
     409: getfield      #7                  // Field str:I
     412: if_icmple     441
     415: aload_0
     416: getfield      #5                  // Field enc:Lorg/jcodings/Encoding;
     419: aload_0
     420: getfield      #6                  // Field bytes:[B
     423: aload_0
     424: getfield      #7                  // Field str:I
     427: iload         4
     429: aload_0
     430: getfield      #8                  // Field end:I
     433: invokevirtual #20                 // Method org/jcodings/Encoding.prevCharHead:([BIII)I
     436: istore        5
     438: goto          444
     441: iconst_0
     442: istore        5
     444: aload_0
     445: getfield      #3                  // Field regex:Lorg/joni/Regex;
     448: getfield      #25                 // Field org/joni/Regex.searchAlgorithm:Lorg/joni/SearchAlgorithm;
     451: getstatic     #47                 // Field org/joni/SearchAlgorithm.NONE:Lorg/joni/SearchAlgorithm;
     454: if_acmpeq     825
     457: iload_2
     458: istore        8
     460: aload_0
     461: getfield      #3                  // Field regex:Lorg/joni/Regex;
     464: getfield      #29                 // Field org/joni/Regex.dMax:I
     467: ifeq          518
     470: aload_0
     471: getfield      #3                  // Field regex:Lorg/joni/Regex;
     474: getfield      #29                 // Field org/joni/Regex.dMax:I
     477: ldc           #32                 // int 2147483647
     479: if_icmpne     491
     482: aload_0
     483: getfield      #8                  // Field end:I
     486: istore        8
     488: goto          518
     491: iload         8
     493: aload_0
     494: getfield      #3                  // Field regex:Lorg/joni/Regex;
     497: getfield      #29                 // Field org/joni/Regex.dMax:I
     500: iadd
     501: istore        8
     503: iload         8
     505: aload_0
     506: getfield      #8                  // Field end:I
     509: if_icmple     518
     512: aload_0
     513: getfield      #8                  // Field end:I
     516: istore        8
     518: aload_0
     519: getfield      #8                  // Field end:I
     522: iload_1
     523: isub
     524: aload_0
     525: getfield      #3                  // Field regex:Lorg/joni/Regex;
     528: getfield      #43                 // Field org/joni/Regex.thresholdLength:I
     531: if_icmpge     539
     534: aload_0
     535: invokespecial #46                 // Method mismatch:()I
     538: ireturn
     539: aload_0
     540: getfield      #3                  // Field regex:Lorg/joni/Regex;
     543: getfield      #29                 // Field org/joni/Regex.dMax:I
     546: ldc           #32                 // int 2147483647
     548: if_icmpeq     670
     551: aload_0
     552: aload_0
     553: getfield      #6                  // Field bytes:[B
     556: aload_0
     557: getfield      #7                  // Field str:I
     560: aload_0
     561: getfield      #8                  // Field end:I
     564: iload         4
     566: iload         8
     568: aload_0
     569: invokespecial #48                 // Method forwardSearchRange:([BIIIILorg/jcodings/IntHolder;)Z
     572: ifne          580
     575: aload_0
     576: invokespecial #46                 // Method mismatch:()I
     579: ireturn
     580: iload         4
     582: aload_0
     583: getfield      #30                 // Field low:I
     586: if_icmpge     601
     589: aload_0
     590: getfield      #30                 // Field low:I
     593: istore        4
     595: aload_0
     596: getfield      #49                 // Field value:I
     599: istore        5
     601: iload         4
     603: aload_0
     604: getfield      #34                 // Field high:I
     607: if_icmpgt     659
     610: aload_0
     611: iload         7
     613: iload         4
     615: iload         5
     617: invokespecial #44                 // Method matchCheck:(III)Z
     620: ifeq          630
     623: aload_0
     624: iload         4
     626: invokespecial #45                 // Method match:(I)I
     629: ireturn
     630: iload         4
     632: istore        5
     634: iload         4
     636: aload_0
     637: getfield      #5                  // Field enc:Lorg/jcodings/Encoding;
     640: aload_0
     641: getfield      #6                  // Field bytes:[B
     644: iload         4
     646: aload_0
     647: getfield      #8                  // Field end:I
     650: invokevirtual #24                 // Method org/jcodings/Encoding.length:([BII)I
     653: iadd
     654: istore        4
     656: goto          601
     659: iload         4
     661: iload_2
     662: if_icmplt     551
     665: aload_0
     666: invokespecial #46                 // Method mismatch:()I
     669: ireturn
     670: aload_0
     671: aload_0
     672: getfield      #6                  // Field bytes:[B
     675: aload_0
     676: getfield      #7                  // Field str:I
     679: aload_0
     680: getfield      #8                  // Field end:I
     683: iload         4
     685: iload         8
     687: aconst_null
     688: invokespecial #48                 // Method forwardSearchRange:([BIIIILorg/jcodings/IntHolder;)Z
     691: ifne          699
     694: aload_0
     695: invokespecial #46                 // Method mismatch:()I
     698: ireturn
     699: aload_0
     700: getfield      #3                  // Field regex:Lorg/joni/Regex;
     703: getfield      #39                 // Field org/joni/Regex.anchor:I
     706: sipush        16384
     709: iand
     710: ifeq          825
     713: aload_0
     714: iload         7
     716: iload         4
     718: iload         5
     720: invokespecial #44                 // Method matchCheck:(III)Z
     723: ifeq          733
     726: aload_0
     727: iload         4
     729: invokespecial #45                 // Method match:(I)I
     732: ireturn
     733: iload         4
     735: istore        5
     737: iload         4
     739: aload_0
     740: getfield      #5                  // Field enc:Lorg/jcodings/Encoding;
     743: aload_0
     744: getfield      #6                  // Field bytes:[B
     747: iload         4
     749: aload_0
     750: getfield      #8                  // Field end:I
     753: invokevirtual #24                 // Method org/jcodings/Encoding.length:([BII)I
     756: iadd
     757: istore        4
     759: aload_0
     760: getfield      #5                  // Field enc:Lorg/jcodings/Encoding;
     763: aload_0
     764: getfield      #6                  // Field bytes:[B
     767: iload         5
     769: aload_0
     770: getfield      #8                  // Field end:I
     773: invokevirtual #28                 // Method org/jcodings/Encoding.isNewLine:([BII)Z
     776: ifne          814
     779: iload         4
     781: iload_2
     782: if_icmpge     814
     785: iload         4
     787: istore        5
     789: iload         4
     791: aload_0
     792: getfield      #5                  // Field enc:Lorg/jcodings/Encoding;
     795: aload_0
     796: getfield      #6                  // Field bytes:[B
     799: iload         4
     801: aload_0
     802: getfield      #8                  // Field end:I
     805: invokevirtual #24                 // Method org/jcodings/Encoding.length:([BII)I
     808: iadd
     809: istore        4
     811: goto          759
     814: iload         4
     816: iload_2
     817: if_icmplt     713
     820: aload_0
     821: invokespecial #46                 // Method mismatch:()I
     824: ireturn
     825: aload_0
     826: iload         7
     828: iload         4
     830: iload         5
     832: invokespecial #44                 // Method matchCheck:(III)Z
     835: ifeq          845
     838: aload_0
     839: iload         4
     841: invokespecial #45                 // Method match:(I)I
     844: ireturn
     845: iload         4
     847: istore        5
     849: iload         4
     851: aload_0
     852: getfield      #5                  // Field enc:Lorg/jcodings/Encoding;
     855: aload_0
     856: getfield      #6                  // Field bytes:[B
     859: iload         4
     861: aload_0
     862: getfield      #8                  // Field end:I
     865: invokevirtual #24                 // Method org/jcodings/Encoding.length:([BII)I
     868: iadd
     869: istore        4
     871: iload         4
     873: iload_2
     874: if_icmplt     825
     877: iload         4
     879: iload_2
     880: if_icmpne     1318
     883: aload_0
     884: iload         7
     886: iload         4
     888: iload         5
     890: invokespecial #44                 // Method matchCheck:(III)Z
     893: ifeq          1318
     896: aload_0
     897: iload         4
     899: invokespecial #45                 // Method match:(I)I
     902: ireturn
     903: aload_0
     904: getfield      #3                  // Field regex:Lorg/joni/Regex;
     907: getfield      #25                 // Field org/joni/Regex.searchAlgorithm:Lorg/joni/SearchAlgorithm;
     910: getstatic     #47                 // Field org/joni/SearchAlgorithm.NONE:Lorg/joni/SearchAlgorithm;
     913: if_acmpeq     1265
     916: iload_2
     917: aload_0
     918: getfield      #8                  // Field end:I
     921: if_icmpge     949
     924: aload_0
     925: getfield      #5                  // Field enc:Lorg/jcodings/Encoding;
     928: aload_0
     929: getfield      #6                  // Field bytes:[B
     932: aload_0
     933: getfield      #7                  // Field str:I
     936: iload_2
     937: aload_0
     938: getfield      #8                  // Field end:I
     941: invokevirtual #50                 // Method org/jcodings/Encoding.leftAdjustCharHead:([BIII)I
     944: istore        8
     946: goto          955
     949: aload_0
     950: getfield      #8                  // Field end:I
     953: istore        8
     955: aload_0
     956: getfield      #3                  // Field regex:Lorg/joni/Regex;
     959: getfield      #29                 // Field org/joni/Regex.dMax:I
     962: ldc           #32                 // int 2147483647
     964: if_icmpeq     1130
     967: aload_0
     968: getfield      #8                  // Field end:I
     971: iload_2
     972: isub
     973: aload_0
     974: getfield      #3                  // Field regex:Lorg/joni/Regex;
     977: getfield      #43                 // Field org/joni/Regex.thresholdLength:I
     980: if_icmplt     1130
     983: iload         4
     985: aload_0
     986: getfield      #3                  // Field regex:Lorg/joni/Regex;
     989: getfield      #29                 // Field org/joni/Regex.dMax:I
     992: iadd
     993: istore        9
     995: iload         9
     997: aload_0
     998: getfield      #8                  // Field end:I
    1001: if_icmple     1010
    1004: aload_0
    1005: getfield      #8                  // Field end:I
    1008: istore        9
    1010: aload_0
    1011: aload_0
    1012: getfield      #6                  // Field bytes:[B
    1015: aload_0
    1016: getfield      #7                  // Field str:I
    1019: aload_0
    1020: getfield      #8                  // Field end:I
    1023: iload         9
    1025: iload_2
    1026: iload         8
    1028: invokespecial #51                 // Method backwardSearchRange:([BIIIII)Z
    1031: ifne          1039
    1034: aload_0
    1035: invokespecial #46                 // Method mismatch:()I
    1038: ireturn
    1039: iload         4
    1041: aload_0
    1042: getfield      #34                 // Field high:I
    1045: if_icmple     1054
    1048: aload_0
    1049: getfield      #34                 // Field high:I
    1052: istore        4
    1054: iload         4
    1056: iconst_m1
    1057: if_icmpeq     1119
    1060: iload         4
    1062: aload_0
    1063: getfield      #30                 // Field low:I
    1066: if_icmplt     1119
    1069: aload_0
    1070: getfield      #5                  // Field enc:Lorg/jcodings/Encoding;
    1073: aload_0
    1074: getfield      #6                  // Field bytes:[B
    1077: aload_0
    1078: getfield      #7                  // Field str:I
    1081: iload         4
    1083: aload_0
    1084: getfield      #8                  // Field end:I
    1087: invokevirtual #20                 // Method org/jcodings/Encoding.prevCharHead:([BIII)I
    1090: istore        5
    1092: aload_0
    1093: iload         6
    1095: iload         4
    1097: iload         5
    1099: invokespecial #44                 // Method matchCheck:(III)Z
    1102: ifeq          1112
    1105: aload_0
    1106: iload         4
    1108: invokespecial #45                 // Method match:(I)I
    1111: ireturn
    1112: iload         5
    1114: istore        4
    1116: goto          1054
    1119: iload         4
    1121: iload_2
    1122: if_icmpge     983
    1125: aload_0
    1126: invokespecial #46                 // Method mismatch:()I
    1129: ireturn
    1130: aload_0
    1131: getfield      #8                  // Field end:I
    1134: iload_2
    1135: isub
    1136: aload_0
    1137: getfield      #3                  // Field regex:Lorg/joni/Regex;
    1140: getfield      #43                 // Field org/joni/Regex.thresholdLength:I
    1143: if_icmpge     1151
    1146: aload_0
    1147: invokespecial #46                 // Method mismatch:()I
    1150: ireturn
    1151: iload         4
    1153: istore        9
    1155: aload_0
    1156: getfield      #3                  // Field regex:Lorg/joni/Regex;
    1159: getfield      #29                 // Field org/joni/Regex.dMax:I
    1162: ifeq          1236
    1165: aload_0
    1166: getfield      #3                  // Field regex:Lorg/joni/Regex;
    1169: getfield      #29                 // Field org/joni/Regex.dMax:I
    1172: ldc           #32                 // int 2147483647
    1174: if_icmpne     1186
    1177: aload_0
    1178: getfield      #8                  // Field end:I
    1181: istore        9
    1183: goto          1236
    1186: iload         9
    1188: aload_0
    1189: getfield      #3                  // Field regex:Lorg/joni/Regex;
    1192: getfield      #29                 // Field org/joni/Regex.dMax:I
    1195: iadd
    1196: istore        9
    1198: iload         9
    1200: aload_0
    1201: getfield      #8                  // Field end:I
    1204: if_icmple     1216
    1207: aload_0
    1208: getfield      #8                  // Field end:I
    1211: istore        9
    1213: goto          1236
    1216: aload_0
    1217: getfield      #5                  // Field enc:Lorg/jcodings/Encoding;
    1220: aload_0
    1221: getfield      #6                  // Field bytes:[B
    1224: iload_1
    1225: iload         9
    1227: aload_0
    1228: getfield      #8                  // Field end:I
    1231: invokevirtual #50                 // Method org/jcodings/Encoding.leftAdjustCharHead:([BIII)I
    1234: istore        9
    1236: aload_0
    1237: aload_0
    1238: getfield      #6                  // Field bytes:[B
    1241: aload_0
    1242: getfield      #7                  // Field str:I
    1245: aload_0
    1246: getfield      #8                  // Field end:I
    1249: iload         9
    1251: iload_2
    1252: iload         8
    1254: invokespecial #51                 // Method backwardSearchRange:([BIIIII)Z
    1257: ifne          1265
    1260: aload_0
    1261: invokespecial #46                 // Method mismatch:()I
    1264: ireturn
    1265: aload_0
    1266: getfield      #5                  // Field enc:Lorg/jcodings/Encoding;
    1269: aload_0
    1270: getfield      #6                  // Field bytes:[B
    1273: aload_0
    1274: getfield      #7                  // Field str:I
    1277: iload         4
    1279: aload_0
    1280: getfield      #8                  // Field end:I
    1283: invokevirtual #20                 // Method org/jcodings/Encoding.prevCharHead:([BIII)I
    1286: istore        5
    1288: aload_0
    1289: iload         6
    1291: iload         4
    1293: iload         5
    1295: invokespecial #44                 // Method matchCheck:(III)Z
    1298: ifeq          1308
    1301: aload_0
    1302: iload         4
    1304: invokespecial #45                 // Method match:(I)I
    1307: ireturn
    1308: iload         5
    1310: istore        4
    1312: iload         4
    1314: iload_2
    1315: if_icmpge     1265
    1318: aload_0
    1319: invokespecial #46                 // Method mismatch:()I
    1322: ireturn

  private boolean endBuf(int, int, int, int);
    Code:
       0: iload         4
       2: aload_0
       3: getfield      #7                  // Field str:I
       6: isub
       7: aload_0
       8: getfield      #3                  // Field regex:Lorg/joni/Regex;
      11: getfield      #52                 // Field org/joni/Regex.anchorDmin:I
      14: if_icmpge     19
      17: iconst_1
      18: ireturn
      19: iload_2
      20: iload_1
      21: if_icmple     139
      24: iload_3
      25: iload_1
      26: isub
      27: aload_0
      28: getfield      #3                  // Field regex:Lorg/joni/Regex;
      31: getfield      #53                 // Field org/joni/Regex.anchorDmax:I
      34: if_icmple     103
      37: iload_3
      38: aload_0
      39: getfield      #3                  // Field regex:Lorg/joni/Regex;
      42: getfield      #53                 // Field org/joni/Regex.anchorDmax:I
      45: isub
      46: istore_1
      47: iload_1
      48: aload_0
      49: getfield      #8                  // Field end:I
      52: if_icmpge     79
      55: aload_0
      56: getfield      #5                  // Field enc:Lorg/jcodings/Encoding;
      59: aload_0
      60: getfield      #6                  // Field bytes:[B
      63: aload_0
      64: getfield      #7                  // Field str:I
      67: iload_1
      68: aload_0
      69: getfield      #8                  // Field end:I
      72: invokevirtual #36                 // Method org/jcodings/Encoding.rightAdjustCharHead:([BIII)I
      75: istore_1
      76: goto          103
      79: aload_0
      80: getfield      #5                  // Field enc:Lorg/jcodings/Encoding;
      83: aload_0
      84: getfield      #6                  // Field bytes:[B
      87: aload_0
      88: getfield      #7                  // Field str:I
      91: aload_0
      92: getfield      #8                  // Field end:I
      95: aload_0
      96: getfield      #8                  // Field end:I
      99: invokevirtual #20                 // Method org/jcodings/Encoding.prevCharHead:([BIII)I
     102: istore_1
     103: iload         4
     105: iload_2
     106: iconst_1
     107: isub
     108: isub
     109: aload_0
     110: getfield      #3                  // Field regex:Lorg/joni/Regex;
     113: getfield      #52                 // Field org/joni/Regex.anchorDmin:I
     116: if_icmpge     132
     119: iload         4
     121: aload_0
     122: getfield      #3                  // Field regex:Lorg/joni/Regex;
     125: getfield      #52                 // Field org/joni/Regex.anchorDmin:I
     128: isub
     129: iconst_1
     130: iadd
     131: istore_2
     132: iload_1
     133: iload_2
     134: if_icmplt     215
     137: iconst_1
     138: ireturn
     139: iload_3
     140: iload_2
     141: isub
     142: aload_0
     143: getfield      #3                  // Field regex:Lorg/joni/Regex;
     146: getfield      #53                 // Field org/joni/Regex.anchorDmax:I
     149: if_icmple     162
     152: iload_3
     153: aload_0
     154: getfield      #3                  // Field regex:Lorg/joni/Regex;
     157: getfield      #53                 // Field org/joni/Regex.anchorDmax:I
     160: isub
     161: istore_2
     162: iload         4
     164: iload_1
     165: isub
     166: aload_0
     167: getfield      #3                  // Field regex:Lorg/joni/Regex;
     170: getfield      #52                 // Field org/joni/Regex.anchorDmin:I
     173: if_icmpge     208
     176: iload         4
     178: aload_0
     179: getfield      #3                  // Field regex:Lorg/joni/Regex;
     182: getfield      #52                 // Field org/joni/Regex.anchorDmin:I
     185: isub
     186: istore_1
     187: aload_0
     188: getfield      #5                  // Field enc:Lorg/jcodings/Encoding;
     191: aload_0
     192: getfield      #6                  // Field bytes:[B
     195: aload_0
     196: getfield      #7                  // Field str:I
     199: iload_1
     200: aload_0
     201: getfield      #8                  // Field end:I
     204: invokevirtual #50                 // Method org/jcodings/Encoding.leftAdjustCharHead:([BIII)I
     207: istore_1
     208: iload_2
     209: iload_1
     210: if_icmple     215
     213: iconst_1
     214: ireturn
     215: iconst_0
     216: ireturn

  private int match(int);
    Code:
       0: iload_1
       1: aload_0
       2: getfield      #7                  // Field str:I
       5: isub
       6: ireturn

  private int mismatch();
    Code:
       0: aload_0
       1: getfield      #18                 // Field msaBestLen:I
       4: iflt          18
       7: aload_0
       8: getfield      #54                 // Field msaBestS:I
      11: istore_1
      12: aload_0
      13: iload_1
      14: invokespecial #45                 // Method match:(I)I
      17: ireturn
      18: iconst_m1
      19: ireturn
}
