Compiled from "ScannerSupport.java"
abstract class org.joni.ScannerSupport extends org.jcodings.IntHolder implements org.joni.exception.ErrorMessages {
  protected final org.jcodings.Encoding enc;

  protected final byte[] bytes;

  protected int p;

  protected int stop;

  private int lastFetched;

  protected int c;

  private final int begin;

  private final int end;

  protected int _p;

  private final int INT_SIGN_BIT;

  protected org.joni.ScannerSupport(org.jcodings.Encoding, byte[], int, int);
    Code:
       0: aload_0
       1: invokespecial #1                  // Method org/jcodings/IntHolder."<init>":()V
       4: aload_0
       5: ldc           #2                  // int -2147483648
       7: putfield      #3                  // Field INT_SIGN_BIT:I
      10: aload_0
      11: aload_1
      12: putfield      #4                  // Field enc:Lorg/jcodings/Encoding;
      15: aload_0
      16: aload_2
      17: putfield      #5                  // Field bytes:[B
      20: aload_0
      21: iload_3
      22: putfield      #6                  // Field begin:I
      25: aload_0
      26: iload         4
      28: putfield      #7                  // Field end:I
      31: aload_0
      32: invokevirtual #8                  // Method reset:()V
      35: return

  protected int getBegin();
    Code:
       0: aload_0
       1: getfield      #6                  // Field begin:I
       4: ireturn

  protected int getEnd();
    Code:
       0: aload_0
       1: getfield      #7                  // Field end:I
       4: ireturn

  protected final int scanUnsignedNumber();
    Code:
       0: iconst_0
       1: istore_1
       2: aload_0
       3: invokevirtual #9                  // Method left:()Z
       6: ifeq          63
       9: aload_0
      10: invokevirtual #10                 // Method fetch:()V
      13: aload_0
      14: getfield      #4                  // Field enc:Lorg/jcodings/Encoding;
      17: aload_0
      18: getfield      #11                 // Field c:I
      21: invokevirtual #12                 // Method org/jcodings/Encoding.isDigit:(I)Z
      24: ifeq          56
      27: iload_1
      28: istore_2
      29: iload_1
      30: bipush        10
      32: imul
      33: aload_0
      34: getfield      #11                 // Field c:I
      37: invokestatic  #13                 // Method org/jcodings/Encoding.digitVal:(I)I
      40: iadd
      41: istore_1
      42: iload_2
      43: iload_1
      44: ixor
      45: ldc           #2                  // int -2147483648
      47: iand
      48: ifeq          53
      51: iconst_m1
      52: ireturn
      53: goto          2
      56: aload_0
      57: invokevirtual #14                 // Method unfetch:()V
      60: goto          63
      63: iload_1
      64: ireturn

  protected final int scanUnsignedHexadecimalNumber(int);
    Code:
       0: iconst_0
       1: istore_2
       2: aload_0
       3: invokevirtual #9                  // Method left:()Z
       6: ifeq          78
       9: iload_1
      10: dup
      11: iconst_1
      12: isub
      13: istore_1
      14: ifeq          78
      17: aload_0
      18: invokevirtual #10                 // Method fetch:()V
      21: aload_0
      22: getfield      #4                  // Field enc:Lorg/jcodings/Encoding;
      25: aload_0
      26: getfield      #11                 // Field c:I
      29: invokevirtual #15                 // Method org/jcodings/Encoding.isXDigit:(I)Z
      32: ifeq          71
      35: iload_2
      36: istore_3
      37: aload_0
      38: getfield      #4                  // Field enc:Lorg/jcodings/Encoding;
      41: aload_0
      42: getfield      #11                 // Field c:I
      45: invokevirtual #16                 // Method org/jcodings/Encoding.xdigitVal:(I)I
      48: istore        4
      50: iload_2
      51: iconst_4
      52: ishl
      53: iload         4
      55: iadd
      56: istore_2
      57: iload_3
      58: iload_2
      59: ixor
      60: ldc           #2                  // int -2147483648
      62: iand
      63: ifeq          68
      66: iconst_m1
      67: ireturn
      68: goto          2
      71: aload_0
      72: invokevirtual #14                 // Method unfetch:()V
      75: goto          78
      78: iload_2
      79: ireturn

  protected final int scanUnsignedOctalNumber(int);
    Code:
       0: iconst_0
       1: istore_2
       2: aload_0
       3: invokevirtual #9                  // Method left:()Z
       6: ifeq          83
       9: iload_1
      10: dup
      11: iconst_1
      12: isub
      13: istore_1
      14: ifeq          83
      17: aload_0
      18: invokevirtual #10                 // Method fetch:()V
      21: aload_0
      22: getfield      #4                  // Field enc:Lorg/jcodings/Encoding;
      25: aload_0
      26: getfield      #11                 // Field c:I
      29: invokevirtual #12                 // Method org/jcodings/Encoding.isDigit:(I)Z
      32: ifeq          76
      35: aload_0
      36: getfield      #11                 // Field c:I
      39: bipush        56
      41: if_icmpge     76
      44: iload_2
      45: istore_3
      46: aload_0
      47: getfield      #11                 // Field c:I
      50: invokestatic  #17                 // Method org/jcodings/Encoding.odigitVal:(I)I
      53: istore        4
      55: iload_2
      56: iconst_3
      57: ishl
      58: iload         4
      60: iadd
      61: istore_2
      62: iload_3
      63: iload_2
      64: ixor
      65: ldc           #2                  // int -2147483648
      67: iand
      68: ifeq          73
      71: iconst_m1
      72: ireturn
      73: goto          2
      76: aload_0
      77: invokevirtual #14                 // Method unfetch:()V
      80: goto          83
      83: iload_2
      84: ireturn

  protected final void reset();
    Code:
       0: aload_0
       1: aload_0
       2: getfield      #6                  // Field begin:I
       5: putfield      #18                 // Field p:I
       8: aload_0
       9: aload_0
      10: getfield      #7                  // Field end:I
      13: putfield      #19                 // Field stop:I
      16: return

  protected final void mark();
    Code:
       0: aload_0
       1: aload_0
       2: getfield      #18                 // Field p:I
       5: putfield      #20                 // Field _p:I
       8: return

  protected final void restore();
    Code:
       0: aload_0
       1: aload_0
       2: getfield      #20                 // Field _p:I
       5: putfield      #18                 // Field p:I
       8: return

  protected final void inc();
    Code:
       0: aload_0
       1: aload_0
       2: getfield      #18                 // Field p:I
       5: putfield      #21                 // Field lastFetched:I
       8: aload_0
       9: dup
      10: getfield      #18                 // Field p:I
      13: aload_0
      14: getfield      #4                  // Field enc:Lorg/jcodings/Encoding;
      17: aload_0
      18: getfield      #5                  // Field bytes:[B
      21: aload_0
      22: getfield      #18                 // Field p:I
      25: aload_0
      26: getfield      #19                 // Field stop:I
      29: invokevirtual #22                 // Method org/jcodings/Encoding.length:([BII)I
      32: iadd
      33: putfield      #18                 // Field p:I
      36: return

  protected final void fetch();
    Code:
       0: aload_0
       1: aload_0
       2: getfield      #4                  // Field enc:Lorg/jcodings/Encoding;
       5: aload_0
       6: getfield      #5                  // Field bytes:[B
       9: aload_0
      10: getfield      #18                 // Field p:I
      13: aload_0
      14: getfield      #19                 // Field stop:I
      17: invokevirtual #23                 // Method org/jcodings/Encoding.mbcToCode:([BII)I
      20: putfield      #11                 // Field c:I
      23: aload_0
      24: aload_0
      25: getfield      #18                 // Field p:I
      28: putfield      #21                 // Field lastFetched:I
      31: aload_0
      32: dup
      33: getfield      #18                 // Field p:I
      36: aload_0
      37: getfield      #4                  // Field enc:Lorg/jcodings/Encoding;
      40: aload_0
      41: getfield      #5                  // Field bytes:[B
      44: aload_0
      45: getfield      #18                 // Field p:I
      48: aload_0
      49: getfield      #19                 // Field stop:I
      52: invokevirtual #22                 // Method org/jcodings/Encoding.length:([BII)I
      55: iadd
      56: putfield      #18                 // Field p:I
      59: return

  protected int fetchTo();
    Code:
       0: aload_0
       1: getfield      #4                  // Field enc:Lorg/jcodings/Encoding;
       4: aload_0
       5: getfield      #5                  // Field bytes:[B
       8: aload_0
       9: getfield      #18                 // Field p:I
      12: aload_0
      13: getfield      #19                 // Field stop:I
      16: invokevirtual #23                 // Method org/jcodings/Encoding.mbcToCode:([BII)I
      19: istore_1
      20: aload_0
      21: aload_0
      22: getfield      #18                 // Field p:I
      25: putfield      #21                 // Field lastFetched:I
      28: aload_0
      29: dup
      30: getfield      #18                 // Field p:I
      33: aload_0
      34: getfield      #4                  // Field enc:Lorg/jcodings/Encoding;
      37: aload_0
      38: getfield      #5                  // Field bytes:[B
      41: aload_0
      42: getfield      #18                 // Field p:I
      45: aload_0
      46: getfield      #19                 // Field stop:I
      49: invokevirtual #22                 // Method org/jcodings/Encoding.length:([BII)I
      52: iadd
      53: putfield      #18                 // Field p:I
      56: iload_1
      57: ireturn

  protected final void unfetch();
    Code:
       0: aload_0
       1: aload_0
       2: getfield      #21                 // Field lastFetched:I
       5: putfield      #18                 // Field p:I
       8: return

  protected final int peek();
    Code:
       0: aload_0
       1: getfield      #18                 // Field p:I
       4: aload_0
       5: getfield      #19                 // Field stop:I
       8: if_icmpge     33
      11: aload_0
      12: getfield      #4                  // Field enc:Lorg/jcodings/Encoding;
      15: aload_0
      16: getfield      #5                  // Field bytes:[B
      19: aload_0
      20: getfield      #18                 // Field p:I
      23: aload_0
      24: getfield      #19                 // Field stop:I
      27: invokevirtual #23                 // Method org/jcodings/Encoding.mbcToCode:([BII)I
      30: goto          34
      33: iconst_0
      34: ireturn

  protected final boolean peekIs(int);
    Code:
       0: aload_0
       1: invokevirtual #24                 // Method peek:()I
       4: iload_1
       5: if_icmpne     12
       8: iconst_1
       9: goto          13
      12: iconst_0
      13: ireturn

  protected final boolean left();
    Code:
       0: aload_0
       1: getfield      #18                 // Field p:I
       4: aload_0
       5: getfield      #19                 // Field stop:I
       8: if_icmpge     15
      11: iconst_1
      12: goto          16
      15: iconst_0
      16: ireturn

  protected void newSyntaxException(java.lang.String);
    Code:
       0: new           #25                 // class org/joni/exception/SyntaxException
       3: dup
       4: aload_1
       5: invokespecial #26                 // Method org/joni/exception/SyntaxException."<init>":(Ljava/lang/String;)V
       8: athrow

  protected void newValueException(java.lang.String);
    Code:
       0: new           #27                 // class org/joni/exception/ValueException
       3: dup
       4: aload_1
       5: invokespecial #28                 // Method org/joni/exception/ValueException."<init>":(Ljava/lang/String;)V
       8: athrow

  protected void newValueException(java.lang.String, java.lang.String);
    Code:
       0: new           #27                 // class org/joni/exception/ValueException
       3: dup
       4: aload_1
       5: aload_2
       6: invokespecial #29                 // Method org/joni/exception/ValueException."<init>":(Ljava/lang/String;Ljava/lang/String;)V
       9: athrow

  protected void newValueException(java.lang.String, int, int);
    Code:
       0: new           #27                 // class org/joni/exception/ValueException
       3: dup
       4: aload_1
       5: new           #30                 // class java/lang/String
       8: dup
       9: aload_0
      10: getfield      #5                  // Field bytes:[B
      13: iload_2
      14: iload_3
      15: iload_2
      16: isub
      17: invokespecial #31                 // Method java/lang/String."<init>":([BII)V
      20: invokespecial #29                 // Method org/joni/exception/ValueException."<init>":(Ljava/lang/String;Ljava/lang/String;)V
      23: athrow

  protected void newInternalException(java.lang.String);
    Code:
       0: new           #32                 // class org/joni/exception/InternalException
       3: dup
       4: aload_1
       5: invokespecial #33                 // Method org/joni/exception/InternalException."<init>":(Ljava/lang/String;)V
       8: athrow
}
