Compiled from "SearchAlgorithm.java"
public final class org.joni.SearchAlgorithm$SLOW_IC extends org.joni.SearchAlgorithm {
  private final byte[] buf;

  private final org.jcodings.IntHolder holder;

  private final int caseFoldFlag;

  private final org.jcodings.Encoding enc;

  public org.joni.SearchAlgorithm$SLOW_IC(org.joni.Regex);
    Code:
       0: aload_0
       1: invokespecial #1                  // Method org/joni/SearchAlgorithm."<init>":()V
       4: aload_0
       5: bipush        18
       7: newarray       byte
       9: putfield      #2                  // Field buf:[B
      12: aload_0
      13: new           #3                  // class org/jcodings/IntHolder
      16: dup
      17: invokespecial #4                  // Method org/jcodings/IntHolder."<init>":()V
      20: putfield      #5                  // Field holder:Lorg/jcodings/IntHolder;
      23: aload_0
      24: aload_1
      25: getfield      #6                  // Field org/joni/Regex.caseFoldFlag:I
      28: putfield      #7                  // Field caseFoldFlag:I
      31: aload_0
      32: aload_1
      33: getfield      #8                  // Field org/joni/Regex.enc:Lorg/jcodings/Encoding;
      36: putfield      #9                  // Field enc:Lorg/jcodings/Encoding;
      39: return

  public final java.lang.String getName();
    Code:
       0: ldc           #10                 // String EXACT_IC
       2: areturn

  public final int search(org.joni.Regex, byte[], int, int, int);
    Code:
       0: aload_1
       1: getfield      #11                 // Field org/joni/Regex.exact:[B
       4: astore        6
       6: aload_1
       7: getfield      #12                 // Field org/joni/Regex.exactP:I
      10: istore        7
      12: aload_1
      13: getfield      #13                 // Field org/joni/Regex.exactEnd:I
      16: istore        8
      18: iload         4
      20: istore        9
      22: iload         9
      24: iload         8
      26: iload         7
      28: isub
      29: iconst_1
      30: isub
      31: isub
      32: istore        9
      34: iload         9
      36: iload         5
      38: if_icmple     45
      41: iload         5
      43: istore        9
      45: iload_3
      46: istore        10
      48: iload         10
      50: iload         9
      52: if_icmpge     96
      55: aload_0
      56: aload         6
      58: iload         7
      60: iload         8
      62: aload_2
      63: iload         10
      65: iload         4
      67: invokespecial #14                 // Method lowerCaseMatch:([BII[BII)Z
      70: ifeq          76
      73: iload         10
      75: ireturn
      76: iload         10
      78: aload_0
      79: getfield      #9                  // Field enc:Lorg/jcodings/Encoding;
      82: aload_2
      83: iload         10
      85: iload         4
      87: invokevirtual #15                 // Method org/jcodings/Encoding.length:([BII)I
      90: iadd
      91: istore        10
      93: goto          48
      96: iconst_m1
      97: ireturn

  public final int searchBackward(org.joni.Regex, byte[], int, int, int, int, int, int);
    Code:
       0: aload_1
       1: getfield      #11                 // Field org/joni/Regex.exact:[B
       4: astore        9
       6: aload_1
       7: getfield      #12                 // Field org/joni/Regex.exactP:I
      10: istore        10
      12: aload_1
      13: getfield      #13                 // Field org/joni/Regex.exactEnd:I
      16: istore        11
      18: iload         5
      20: istore        12
      22: iload         12
      24: iload         11
      26: iload         10
      28: isub
      29: isub
      30: istore        12
      32: iload         12
      34: iload         6
      36: if_icmple     46
      39: iload         6
      41: istore        12
      43: goto          62
      46: aload_0
      47: getfield      #9                  // Field enc:Lorg/jcodings/Encoding;
      50: aload_2
      51: iload         4
      53: iload         12
      55: iload         5
      57: invokevirtual #16                 // Method org/jcodings/Encoding.leftAdjustCharHead:([BIII)I
      60: istore        12
      62: iload         12
      64: iload_3
      65: if_icmplt     108
      68: aload_0
      69: aload         9
      71: iload         10
      73: iload         11
      75: aload_2
      76: iload         12
      78: iload         5
      80: invokespecial #14                 // Method lowerCaseMatch:([BII[BII)Z
      83: ifeq          89
      86: iload         12
      88: ireturn
      89: aload_0
      90: getfield      #9                  // Field enc:Lorg/jcodings/Encoding;
      93: aload_2
      94: iload         4
      96: iload         12
      98: iload         5
     100: invokevirtual #17                 // Method org/jcodings/Encoding.prevCharHead:([BIII)I
     103: istore        12
     105: goto          62
     108: iconst_m1
     109: ireturn

  private boolean lowerCaseMatch(byte[], int, int, byte[], int, int);
    Code:
       0: aload_0
       1: getfield      #5                  // Field holder:Lorg/jcodings/IntHolder;
       4: iload         5
       6: putfield      #18                 // Field org/jcodings/IntHolder.value:I
       9: iload_2
      10: iload_3
      11: if_icmpge     100
      14: aload_0
      15: getfield      #9                  // Field enc:Lorg/jcodings/Encoding;
      18: aload_0
      19: getfield      #7                  // Field caseFoldFlag:I
      22: aload         4
      24: aload_0
      25: getfield      #5                  // Field holder:Lorg/jcodings/IntHolder;
      28: iload         6
      30: aload_0
      31: getfield      #2                  // Field buf:[B
      34: invokevirtual #19                 // Method org/jcodings/Encoding.mbcCaseFold:(I[BLorg/jcodings/IntHolder;I[B)I
      37: istore        7
      39: iload         7
      41: iconst_1
      42: if_icmpne     62
      45: aload_1
      46: iload_2
      47: iinc          2, 1
      50: baload
      51: aload_0
      52: getfield      #2                  // Field buf:[B
      55: iconst_0
      56: baload
      57: if_icmpeq     97
      60: iconst_0
      61: ireturn
      62: iconst_0
      63: istore        8
      65: iload         7
      67: ifle          97
      70: aload_1
      71: iload_2
      72: iinc          2, 1
      75: baload
      76: aload_0
      77: getfield      #2                  // Field buf:[B
      80: iload         8
      82: iinc          8, 1
      85: baload
      86: if_icmpeq     91
      89: iconst_0
      90: ireturn
      91: iinc          7, -1
      94: goto          65
      97: goto          9
     100: iconst_1
     101: ireturn
}
