Compiled from "ChainedPlaceholderResolver.java"
class org.jboss.as.controller.transform.description.ChainedPlaceholderResolver implements org.jboss.as.controller.registry.OperationTransformerRegistry$PlaceholderResolver {
  private final org.jboss.as.controller.transform.description.TransformationDescription description;

  private final java.util.Map<java.lang.String, org.jboss.as.controller.transform.description.ChainedPlaceholderResolver$SubRegistry> subRegistries;

  private org.jboss.as.controller.transform.description.ChainedPlaceholderResolver(org.jboss.as.controller.transform.description.TransformationDescription, java.util.Map<java.lang.String, org.jboss.as.controller.transform.description.ChainedPlaceholderResolver$SubRegistry>);
    Code:
       0: aload_0
       1: invokespecial #3                  // Method java/lang/Object."<init>":()V
       4: aload_0
       5: aload_1
       6: putfield      #2                  // Field description:Lorg/jboss/as/controller/transform/description/TransformationDescription;
       9: aload_0
      10: aload_2
      11: putfield      #4                  // Field subRegistries:Ljava/util/Map;
      14: return

  static org.jboss.as.controller.transform.description.ChainedPlaceholderResolver create(org.jboss.as.controller.transform.description.TransformationDescription);
    Code:
       0: new           #5                  // class java/util/HashMap
       3: dup
       4: invokespecial #6                  // Method java/util/HashMap."<init>":()V
       7: astore_1
       8: aload_0
       9: invokeinterface #7,  1            // InterfaceMethod org/jboss/as/controller/transform/description/TransformationDescription.getChildren:()Ljava/util/List;
      14: invokeinterface #8,  1            // InterfaceMethod java/util/List.iterator:()Ljava/util/Iterator;
      19: astore_2
      20: aload_2
      21: invokeinterface #9,  1            // InterfaceMethod java/util/Iterator.hasNext:()Z
      26: ifeq          130
      29: aload_2
      30: invokeinterface #10,  1           // InterfaceMethod java/util/Iterator.next:()Ljava/lang/Object;
      35: checkcast     #11                 // class org/jboss/as/controller/transform/description/TransformationDescription
      38: astore_3
      39: aload_3
      40: invokestatic  #12                 // Method create:(Lorg/jboss/as/controller/transform/description/TransformationDescription;)Lorg/jboss/as/controller/transform/description/ChainedPlaceholderResolver;
      43: astore        4
      45: aload_3
      46: invokeinterface #13,  1           // InterfaceMethod org/jboss/as/controller/transform/description/TransformationDescription.getPath:()Lorg/jboss/as/controller/PathElement;
      51: astore        5
      53: aload_1
      54: aload         5
      56: invokevirtual #14                 // Method org/jboss/as/controller/PathElement.getKey:()Ljava/lang/String;
      59: invokeinterface #15,  2           // InterfaceMethod java/util/Map.get:(Ljava/lang/Object;)Ljava/lang/Object;
      64: checkcast     #16                 // class java/util/Map
      67: astore        6
      69: aload         6
      71: ifnonnull     97
      74: new           #5                  // class java/util/HashMap
      77: dup
      78: invokespecial #6                  // Method java/util/HashMap."<init>":()V
      81: astore        6
      83: aload_1
      84: aload         5
      86: invokevirtual #14                 // Method org/jboss/as/controller/PathElement.getKey:()Ljava/lang/String;
      89: aload         6
      91: invokeinterface #17,  3           // InterfaceMethod java/util/Map.put:(Ljava/lang/Object;Ljava/lang/Object;)Ljava/lang/Object;
      96: pop
      97: aload         6
      99: aload         5
     101: invokevirtual #18                 // Method org/jboss/as/controller/PathElement.getValue:()Ljava/lang/String;
     104: invokeinterface #19,  2           // InterfaceMethod java/util/Map.containsKey:(Ljava/lang/Object;)Z
     109: ifne          127
     112: aload         6
     114: aload         5
     116: invokevirtual #18                 // Method org/jboss/as/controller/PathElement.getValue:()Ljava/lang/String;
     119: aload         4
     121: invokeinterface #17,  3           // InterfaceMethod java/util/Map.put:(Ljava/lang/Object;Ljava/lang/Object;)Ljava/lang/Object;
     126: pop
     127: goto          20
     130: new           #5                  // class java/util/HashMap
     133: dup
     134: invokespecial #6                  // Method java/util/HashMap."<init>":()V
     137: astore_2
     138: aload_1
     139: invokeinterface #20,  1           // InterfaceMethod java/util/Map.entrySet:()Ljava/util/Set;
     144: invokeinterface #21,  1           // InterfaceMethod java/util/Set.iterator:()Ljava/util/Iterator;
     149: astore_3
     150: aload_3
     151: invokeinterface #9,  1            // InterfaceMethod java/util/Iterator.hasNext:()Z
     156: ifeq          207
     159: aload_3
     160: invokeinterface #10,  1           // InterfaceMethod java/util/Iterator.next:()Ljava/lang/Object;
     165: checkcast     #22                 // class java/util/Map$Entry
     168: astore        4
     170: aload_2
     171: aload         4
     173: invokeinterface #23,  1           // InterfaceMethod java/util/Map$Entry.getKey:()Ljava/lang/Object;
     178: new           #24                 // class org/jboss/as/controller/transform/description/ChainedPlaceholderResolver$SubRegistry
     181: dup
     182: aload         4
     184: invokeinterface #25,  1           // InterfaceMethod java/util/Map$Entry.getValue:()Ljava/lang/Object;
     189: checkcast     #16                 // class java/util/Map
     192: invokestatic  #26                 // Method java/util/Collections.unmodifiableMap:(Ljava/util/Map;)Ljava/util/Map;
     195: invokespecial #27                 // Method org/jboss/as/controller/transform/description/ChainedPlaceholderResolver$SubRegistry."<init>":(Ljava/util/Map;)V
     198: invokeinterface #17,  3           // InterfaceMethod java/util/Map.put:(Ljava/lang/Object;Ljava/lang/Object;)Ljava/lang/Object;
     203: pop
     204: goto          150
     207: new           #28                 // class org/jboss/as/controller/transform/description/ChainedPlaceholderResolver
     210: dup
     211: aload_0
     212: aload_2
     213: invokestatic  #26                 // Method java/util/Collections.unmodifiableMap:(Ljava/util/Map;)Ljava/util/Map;
     216: invokespecial #29                 // Method "<init>":(Lorg/jboss/as/controller/transform/description/TransformationDescription;Ljava/util/Map;)V
     219: areturn

  org.jboss.as.controller.transform.description.TransformationDescription getDescription();
    Code:
       0: aload_0
       1: getfield      #2                  // Field description:Lorg/jboss/as/controller/transform/description/TransformationDescription;
       4: areturn

  public org.jboss.as.controller.registry.OperationTransformerRegistry$OperationTransformerEntry resolveOperationTransformer(java.util.Iterator<org.jboss.as.controller.PathElement>, java.lang.String);
    Code:
       0: aload_1
       1: invokeinterface #9,  1            // InterfaceMethod java/util/Iterator.hasNext:()Z
       6: ifne          114
       9: aload_0
      10: getfield      #2                  // Field description:Lorg/jboss/as/controller/transform/description/TransformationDescription;
      13: invokeinterface #30,  1           // InterfaceMethod org/jboss/as/controller/transform/description/TransformationDescription.getDiscardedOperations:()Ljava/util/Set;
      18: aload_2
      19: invokeinterface #31,  2           // InterfaceMethod java/util/Set.contains:(Ljava/lang/Object;)Z
      24: ifeq          47
      27: new           #32                 // class org/jboss/as/controller/registry/OperationTransformerRegistry$OperationTransformerEntry
      30: dup
      31: getstatic     #33                 // Field org/jboss/as/controller/transform/OperationTransformer.DISCARD:Lorg/jboss/as/controller/transform/OperationTransformer;
      34: aload_0
      35: getfield      #2                  // Field description:Lorg/jboss/as/controller/transform/description/TransformationDescription;
      38: invokeinterface #34,  1           // InterfaceMethod org/jboss/as/controller/transform/description/TransformationDescription.isInherited:()Z
      43: invokespecial #35                 // Method org/jboss/as/controller/registry/OperationTransformerRegistry$OperationTransformerEntry."<init>":(Lorg/jboss/as/controller/transform/OperationTransformer;Z)V
      46: areturn
      47: aload_0
      48: getfield      #2                  // Field description:Lorg/jboss/as/controller/transform/description/TransformationDescription;
      51: invokeinterface #36,  1           // InterfaceMethod org/jboss/as/controller/transform/description/TransformationDescription.getOperationTransformers:()Ljava/util/Map;
      56: aload_2
      57: invokeinterface #15,  2           // InterfaceMethod java/util/Map.get:(Ljava/lang/Object;)Ljava/lang/Object;
      62: checkcast     #37                 // class org/jboss/as/controller/transform/OperationTransformer
      65: astore_3
      66: aload_3
      67: ifnonnull     96
      70: new           #32                 // class org/jboss/as/controller/registry/OperationTransformerRegistry$OperationTransformerEntry
      73: dup
      74: aload_0
      75: getfield      #2                  // Field description:Lorg/jboss/as/controller/transform/description/TransformationDescription;
      78: invokeinterface #38,  1           // InterfaceMethod org/jboss/as/controller/transform/description/TransformationDescription.getOperationTransformer:()Lorg/jboss/as/controller/transform/OperationTransformer;
      83: aload_0
      84: getfield      #2                  // Field description:Lorg/jboss/as/controller/transform/description/TransformationDescription;
      87: invokeinterface #34,  1           // InterfaceMethod org/jboss/as/controller/transform/description/TransformationDescription.isInherited:()Z
      92: invokespecial #35                 // Method org/jboss/as/controller/registry/OperationTransformerRegistry$OperationTransformerEntry."<init>":(Lorg/jboss/as/controller/transform/OperationTransformer;Z)V
      95: areturn
      96: new           #32                 // class org/jboss/as/controller/registry/OperationTransformerRegistry$OperationTransformerEntry
      99: dup
     100: aload_3
     101: aload_0
     102: getfield      #2                  // Field description:Lorg/jboss/as/controller/transform/description/TransformationDescription;
     105: invokeinterface #34,  1           // InterfaceMethod org/jboss/as/controller/transform/description/TransformationDescription.isInherited:()Z
     110: invokespecial #35                 // Method org/jboss/as/controller/registry/OperationTransformerRegistry$OperationTransformerEntry."<init>":(Lorg/jboss/as/controller/transform/OperationTransformer;Z)V
     113: areturn
     114: aload_1
     115: invokeinterface #10,  1           // InterfaceMethod java/util/Iterator.next:()Ljava/lang/Object;
     120: checkcast     #39                 // class org/jboss/as/controller/PathElement
     123: astore_3
     124: aload_3
     125: invokevirtual #14                 // Method org/jboss/as/controller/PathElement.getKey:()Ljava/lang/String;
     128: astore        4
     130: aload_0
     131: getfield      #4                  // Field subRegistries:Ljava/util/Map;
     134: aload         4
     136: invokeinterface #15,  2           // InterfaceMethod java/util/Map.get:(Ljava/lang/Object;)Ljava/lang/Object;
     141: checkcast     #24                 // class org/jboss/as/controller/transform/description/ChainedPlaceholderResolver$SubRegistry
     144: astore        5
     146: aload         5
     148: ifnull        172
     151: aload         5
     153: aload_1
     154: aload_3
     155: invokevirtual #18                 // Method org/jboss/as/controller/PathElement.getValue:()Ljava/lang/String;
     158: aload_2
     159: invokevirtual #40                 // Method org/jboss/as/controller/transform/description/ChainedPlaceholderResolver$SubRegistry.resolveTransformer:(Ljava/util/Iterator;Ljava/lang/String;Ljava/lang/String;)Lorg/jboss/as/controller/registry/OperationTransformerRegistry$OperationTransformerEntry;
     162: astore        6
     164: aload         6
     166: ifnull        172
     169: aload         6
     171: areturn
     172: aload_0
     173: getfield      #2                  // Field description:Lorg/jboss/as/controller/transform/description/TransformationDescription;
     176: invokeinterface #36,  1           // InterfaceMethod org/jboss/as/controller/transform/description/TransformationDescription.getOperationTransformers:()Ljava/util/Map;
     181: aload_2
     182: invokeinterface #15,  2           // InterfaceMethod java/util/Map.get:(Ljava/lang/Object;)Ljava/lang/Object;
     187: checkcast     #37                 // class org/jboss/as/controller/transform/OperationTransformer
     190: astore        6
     192: aload         6
     194: ifnull        228
     197: aload_0
     198: getfield      #2                  // Field description:Lorg/jboss/as/controller/transform/description/TransformationDescription;
     201: invokeinterface #34,  1           // InterfaceMethod org/jboss/as/controller/transform/description/TransformationDescription.isInherited:()Z
     206: ifeq          228
     209: new           #32                 // class org/jboss/as/controller/registry/OperationTransformerRegistry$OperationTransformerEntry
     212: dup
     213: aload         6
     215: aload_0
     216: getfield      #2                  // Field description:Lorg/jboss/as/controller/transform/description/TransformationDescription;
     219: invokeinterface #34,  1           // InterfaceMethod org/jboss/as/controller/transform/description/TransformationDescription.isInherited:()Z
     224: invokespecial #35                 // Method org/jboss/as/controller/registry/OperationTransformerRegistry$OperationTransformerEntry."<init>":(Lorg/jboss/as/controller/transform/OperationTransformer;Z)V
     227: areturn
     228: aload_0
     229: getfield      #2                  // Field description:Lorg/jboss/as/controller/transform/description/TransformationDescription;
     232: invokeinterface #38,  1           // InterfaceMethod org/jboss/as/controller/transform/description/TransformationDescription.getOperationTransformer:()Lorg/jboss/as/controller/transform/OperationTransformer;
     237: astore        6
     239: aload         6
     241: ifnull        275
     244: aload_0
     245: getfield      #2                  // Field description:Lorg/jboss/as/controller/transform/description/TransformationDescription;
     248: invokeinterface #34,  1           // InterfaceMethod org/jboss/as/controller/transform/description/TransformationDescription.isInherited:()Z
     253: ifeq          275
     256: new           #32                 // class org/jboss/as/controller/registry/OperationTransformerRegistry$OperationTransformerEntry
     259: dup
     260: aload         6
     262: aload_0
     263: getfield      #2                  // Field description:Lorg/jboss/as/controller/transform/description/TransformationDescription;
     266: invokeinterface #34,  1           // InterfaceMethod org/jboss/as/controller/transform/description/TransformationDescription.isInherited:()Z
     271: invokespecial #35                 // Method org/jboss/as/controller/registry/OperationTransformerRegistry$OperationTransformerEntry."<init>":(Lorg/jboss/as/controller/transform/OperationTransformer;Z)V
     274: areturn
     275: aconst_null
     276: areturn

  public org.jboss.as.controller.transform.TransformerEntry resolveTransformerEntry(java.util.Iterator<org.jboss.as.controller.PathElement>);
    Code:
       0: aload_1
       1: invokeinterface #9,  1            // InterfaceMethod java/util/Iterator.hasNext:()Z
       6: ifne          14
       9: aload_0
      10: invokespecial #41                 // Method getTransformerEntry:()Lorg/jboss/as/controller/transform/TransformerEntry;
      13: areturn
      14: aload_1
      15: invokeinterface #10,  1           // InterfaceMethod java/util/Iterator.next:()Ljava/lang/Object;
      20: checkcast     #39                 // class org/jboss/as/controller/PathElement
      23: astore_2
      24: aload_0
      25: getfield      #4                  // Field subRegistries:Ljava/util/Map;
      28: aload_2
      29: invokevirtual #14                 // Method org/jboss/as/controller/PathElement.getKey:()Ljava/lang/String;
      32: invokeinterface #15,  2           // InterfaceMethod java/util/Map.get:(Ljava/lang/Object;)Ljava/lang/Object;
      37: checkcast     #24                 // class org/jboss/as/controller/transform/description/ChainedPlaceholderResolver$SubRegistry
      40: astore_3
      41: aload_3
      42: ifnonnull     47
      45: aconst_null
      46: areturn
      47: aload_3
      48: aload_2
      49: invokevirtual #18                 // Method org/jboss/as/controller/PathElement.getValue:()Ljava/lang/String;
      52: invokevirtual #42                 // Method org/jboss/as/controller/transform/description/ChainedPlaceholderResolver$SubRegistry.get:(Ljava/lang/String;)Lorg/jboss/as/controller/transform/description/ChainedPlaceholderResolver;
      55: astore        4
      57: aload         4
      59: ifnonnull     64
      62: aconst_null
      63: areturn
      64: aload         4
      66: aload_1
      67: invokevirtual #43                 // Method resolveTransformerEntry:(Ljava/util/Iterator;)Lorg/jboss/as/controller/transform/TransformerEntry;
      70: areturn

  public void resolvePathTransformers(java.util.Iterator<org.jboss.as.controller.PathElement>, java.util.List<org.jboss.as.controller.transform.PathAddressTransformer>);
    Code:
       0: aload_1
       1: invokeinterface #9,  1            // InterfaceMethod java/util/Iterator.hasNext:()Z
       6: ifeq          96
       9: aload_1
      10: invokeinterface #10,  1           // InterfaceMethod java/util/Iterator.next:()Ljava/lang/Object;
      15: checkcast     #39                 // class org/jboss/as/controller/PathElement
      18: astore_3
      19: aload_0
      20: getfield      #4                  // Field subRegistries:Ljava/util/Map;
      23: aload_3
      24: invokevirtual #14                 // Method org/jboss/as/controller/PathElement.getKey:()Ljava/lang/String;
      27: invokeinterface #15,  2           // InterfaceMethod java/util/Map.get:(Ljava/lang/Object;)Ljava/lang/Object;
      32: checkcast     #24                 // class org/jboss/as/controller/transform/description/ChainedPlaceholderResolver$SubRegistry
      35: astore        4
      37: aload         4
      39: ifnull        83
      42: aload         4
      44: aload_3
      45: invokevirtual #18                 // Method org/jboss/as/controller/PathElement.getValue:()Ljava/lang/String;
      48: invokevirtual #42                 // Method org/jboss/as/controller/transform/description/ChainedPlaceholderResolver$SubRegistry.get:(Ljava/lang/String;)Lorg/jboss/as/controller/transform/description/ChainedPlaceholderResolver;
      51: astore        5
      53: aload         5
      55: ifnull        83
      58: aload_2
      59: aload         5
      61: getfield      #2                  // Field description:Lorg/jboss/as/controller/transform/description/TransformationDescription;
      64: invokeinterface #44,  1           // InterfaceMethod org/jboss/as/controller/transform/description/TransformationDescription.getPathAddressTransformer:()Lorg/jboss/as/controller/transform/PathAddressTransformer;
      69: invokeinterface #45,  2           // InterfaceMethod java/util/List.add:(Ljava/lang/Object;)Z
      74: pop
      75: aload         5
      77: aload_1
      78: aload_2
      79: invokevirtual #46                 // Method resolvePathTransformers:(Ljava/util/Iterator;Ljava/util/List;)V
      82: return
      83: aload_2
      84: getstatic     #47                 // Field org/jboss/as/controller/transform/PathAddressTransformer.DEFAULT:Lorg/jboss/as/controller/transform/PathAddressTransformer;
      87: invokeinterface #45,  2           // InterfaceMethod java/util/List.add:(Ljava/lang/Object;)Z
      92: pop
      93: goto          112
      96: aload_2
      97: aload_0
      98: getfield      #2                  // Field description:Lorg/jboss/as/controller/transform/description/TransformationDescription;
     101: invokeinterface #44,  1           // InterfaceMethod org/jboss/as/controller/transform/description/TransformationDescription.getPathAddressTransformer:()Lorg/jboss/as/controller/transform/PathAddressTransformer;
     106: invokeinterface #45,  2           // InterfaceMethod java/util/List.add:(Ljava/lang/Object;)Z
     111: pop
     112: return

  private org.jboss.as.controller.transform.description.ChainedPlaceholderResolver resolveChild(java.util.Iterator<org.jboss.as.controller.PathElement>);
    Code:
       0: aload_1
       1: invokeinterface #9,  1            // InterfaceMethod java/util/Iterator.hasNext:()Z
       6: ifne          11
       9: aload_0
      10: areturn
      11: aload_1
      12: invokeinterface #10,  1           // InterfaceMethod java/util/Iterator.next:()Ljava/lang/Object;
      17: checkcast     #39                 // class org/jboss/as/controller/PathElement
      20: astore_2
      21: aload_0
      22: getfield      #4                  // Field subRegistries:Ljava/util/Map;
      25: aload_2
      26: invokevirtual #14                 // Method org/jboss/as/controller/PathElement.getKey:()Ljava/lang/String;
      29: invokeinterface #15,  2           // InterfaceMethod java/util/Map.get:(Ljava/lang/Object;)Ljava/lang/Object;
      34: checkcast     #24                 // class org/jboss/as/controller/transform/description/ChainedPlaceholderResolver$SubRegistry
      37: astore_3
      38: aload_3
      39: ifnonnull     44
      42: aconst_null
      43: areturn
      44: aload_3
      45: aload_2
      46: invokevirtual #18                 // Method org/jboss/as/controller/PathElement.getValue:()Ljava/lang/String;
      49: aload_1
      50: invokevirtual #48                 // Method org/jboss/as/controller/transform/description/ChainedPlaceholderResolver$SubRegistry.get:(Ljava/lang/String;Ljava/util/Iterator;)Lorg/jboss/as/controller/transform/description/ChainedPlaceholderResolver;
      53: areturn

  private org.jboss.as.controller.transform.TransformerEntry getTransformerEntry();
    Code:
       0: new           #49                 // class org/jboss/as/controller/transform/description/ChainedPlaceholderResolver$1
       3: dup
       4: aload_0
       5: invokespecial #50                 // Method org/jboss/as/controller/transform/description/ChainedPlaceholderResolver$1."<init>":(Lorg/jboss/as/controller/transform/description/ChainedPlaceholderResolver;)V
       8: areturn

  static org.jboss.as.controller.transform.description.TransformationDescription access$000(org.jboss.as.controller.transform.description.ChainedPlaceholderResolver);
    Code:
       0: aload_0
       1: getfield      #2                  // Field description:Lorg/jboss/as/controller/transform/description/TransformationDescription;
       4: areturn

  static org.jboss.as.controller.transform.description.ChainedPlaceholderResolver access$100(org.jboss.as.controller.transform.description.ChainedPlaceholderResolver, java.util.Iterator);
    Code:
       0: aload_0
       1: aload_1
       2: invokespecial #1                  // Method resolveChild:(Ljava/util/Iterator;)Lorg/jboss/as/controller/transform/description/ChainedPlaceholderResolver;
       5: areturn
}
