Compiled from "ConcreteAttributeTransformationDescriptionBuilder.java"
class org.jboss.as.controller.transform.description.ConcreteAttributeTransformationDescriptionBuilder extends org.jboss.as.controller.transform.description.AttributeTransformationDescriptionBuilderImpl<org.jboss.as.controller.transform.description.AttributeTransformationDescriptionBuilder> implements org.jboss.as.controller.transform.description.AttributeTransformationDescriptionBuilder {
  protected org.jboss.as.controller.transform.description.ConcreteAttributeTransformationDescriptionBuilder(org.jboss.as.controller.transform.description.ResourceTransformationDescriptionBuilder, org.jboss.as.controller.transform.description.AttributeTransformationDescriptionBuilderImpl$AttributeTransformationDescriptionBuilderRegistry);
    Code:
       0: aload_0
       1: aload_1
       2: aload_2
       3: invokespecial #1                  // Method org/jboss/as/controller/transform/description/AttributeTransformationDescriptionBuilderImpl."<init>":(Lorg/jboss/as/controller/transform/description/ResourceTransformationDescriptionBuilder;Lorg/jboss/as/controller/transform/description/AttributeTransformationDescriptionBuilderImpl$AttributeTransformationDescriptionBuilderRegistry;)V
       6: return

  protected org.jboss.as.controller.transform.description.AttributeTransformationDescriptionBuilder thisBuilder();
    Code:
       0: aload_0
       1: areturn

  protected org.jboss.as.controller.transform.description.BaseAttributeTransformationDescriptionBuilder thisBuilder();
    Code:
       0: aload_0
       1: invokevirtual #2                  // Method thisBuilder:()Lorg/jboss/as/controller/transform/description/AttributeTransformationDescriptionBuilder;
       4: areturn
}
