Compiled from "OperationTransformationRules.java"
class org.jboss.as.controller.transform.description.OperationTransformationRules {
  static final org.jboss.dmr.ModelNode UNDEFINED;

  org.jboss.as.controller.transform.description.OperationTransformationRules();
    Code:
       0: aload_0
       1: invokespecial #1                  // Method java/lang/Object."<init>":()V
       4: return

  static org.jboss.as.controller.transform.OperationTransformer createWriteOperation(java.util.Map<java.lang.String, org.jboss.as.controller.transform.description.AttributeTransformationDescription>);
    Code:
       0: new           #2                  // class org/jboss/as/controller/transform/description/OperationTransformationRules$DefaultTransformer
       3: dup
       4: new           #3                  // class org/jboss/as/controller/transform/description/OperationTransformationRules$WriteAttributeRule
       7: dup
       8: aload_0
       9: invokespecial #4                  // Method org/jboss/as/controller/transform/description/OperationTransformationRules$WriteAttributeRule."<init>":(Ljava/util/Map;)V
      12: invokespecial #5                  // Method org/jboss/as/controller/transform/description/OperationTransformationRules$DefaultTransformer."<init>":(Lorg/jboss/as/controller/transform/description/TransformationRule;)V
      15: areturn

  static org.jboss.as.controller.transform.OperationTransformer createUndefinedOperation(java.util.Map<java.lang.String, org.jboss.as.controller.transform.description.AttributeTransformationDescription>);
    Code:
       0: new           #2                  // class org/jboss/as/controller/transform/description/OperationTransformationRules$DefaultTransformer
       3: dup
       4: new           #6                  // class org/jboss/as/controller/transform/description/OperationTransformationRules$UndefineAttributeRule
       7: dup
       8: aload_0
       9: invokespecial #7                  // Method org/jboss/as/controller/transform/description/OperationTransformationRules$UndefineAttributeRule."<init>":(Ljava/util/Map;)V
      12: invokespecial #5                  // Method org/jboss/as/controller/transform/description/OperationTransformationRules$DefaultTransformer."<init>":(Lorg/jboss/as/controller/transform/description/TransformationRule;)V
      15: areturn

  static {};
    Code:
       0: new           #8                  // class org/jboss/dmr/ModelNode
       3: dup
       4: invokespecial #9                  // Method org/jboss/dmr/ModelNode."<init>":()V
       7: putstatic     #10                 // Field UNDEFINED:Lorg/jboss/dmr/ModelNode;
      10: return
}
