Compiled from "ResourceTransformationDescriptionBuilderImpl.java"
class org.jboss.as.controller.transform.description.ResourceTransformationDescriptionBuilderImpl$1 extends org.jboss.as.controller.transform.description.AbstractTransformationDescriptionBuilder$OperationTransformationEntry {
  final org.jboss.as.controller.transform.description.OperationTransformationOverrideBuilderImpl val$transformationBuilder;

  final org.jboss.as.controller.transform.description.ResourceTransformationDescriptionBuilderImpl this$0;

  org.jboss.as.controller.transform.description.ResourceTransformationDescriptionBuilderImpl$1(org.jboss.as.controller.transform.description.ResourceTransformationDescriptionBuilderImpl, org.jboss.as.controller.transform.description.OperationTransformationOverrideBuilderImpl);
    Code:
       0: aload_0
       1: aload_1
       2: putfield      #1                  // Field this$0:Lorg/jboss/as/controller/transform/description/ResourceTransformationDescriptionBuilderImpl;
       5: aload_0
       6: aload_2
       7: putfield      #2                  // Field val$transformationBuilder:Lorg/jboss/as/controller/transform/description/OperationTransformationOverrideBuilderImpl;
      10: aload_0
      11: invokespecial #3                  // Method org/jboss/as/controller/transform/description/AbstractTransformationDescriptionBuilder$OperationTransformationEntry."<init>":()V
      14: return

  org.jboss.as.controller.transform.OperationTransformer getOperationTransformer(org.jboss.as.controller.transform.description.AttributeTransformationDescriptionBuilderImpl$AttributeTransformationDescriptionBuilderRegistry);
    Code:
       0: aload_0
       1: getfield      #2                  // Field val$transformationBuilder:Lorg/jboss/as/controller/transform/description/OperationTransformationOverrideBuilderImpl;
       4: aload_1
       5: invokevirtual #4                  // Method org/jboss/as/controller/transform/description/OperationTransformationOverrideBuilderImpl.createTransformer:(Lorg/jboss/as/controller/transform/description/AttributeTransformationDescriptionBuilderImpl$AttributeTransformationDescriptionBuilderRegistry;)Lorg/jboss/as/controller/transform/OperationTransformer;
       8: areturn
}
