Compiled from "WebApplicationMessageException.java"
public class org.sonatype.sisu.siesta.common.error.WebApplicationMessageException extends javax.ws.rs.WebApplicationException {
  public org.sonatype.sisu.siesta.common.error.WebApplicationMessageException(javax.ws.rs.core.Response$Status, java.lang.String);
    Code:
       0: aload_0
       1: aload_1
       2: invokestatic  #1                  // Method com/google/common/base/Preconditions.checkNotNull:(Ljava/lang/Object;)Ljava/lang/Object;
       5: checkcast     #2                  // class javax/ws/rs/core/Response$Status
       8: invokestatic  #3                  // Method javax/ws/rs/core/Response.status:(Ljavax/ws/rs/core/Response$Status;)Ljavax/ws/rs/core/Response$ResponseBuilder;
      11: aload_2
      12: invokestatic  #1                  // Method com/google/common/base/Preconditions.checkNotNull:(Ljava/lang/Object;)Ljava/lang/Object;
      15: invokevirtual #4                  // Method javax/ws/rs/core/Response$ResponseBuilder.entity:(Ljava/lang/Object;)Ljavax/ws/rs/core/Response$ResponseBuilder;
      18: ldc           #5                  // String text/plain
      20: invokevirtual #6                  // Method javax/ws/rs/core/Response$ResponseBuilder.type:(Ljava/lang/String;)Ljavax/ws/rs/core/Response$ResponseBuilder;
      23: invokevirtual #7                  // Method javax/ws/rs/core/Response$ResponseBuilder.build:()Ljavax/ws/rs/core/Response;
      26: invokespecial #8                  // Method javax/ws/rs/WebApplicationException."<init>":(Ljavax/ws/rs/core/Response;)V
      29: return
}
