Compiled from "InputStreamSinkStage.scala"
public final class akka.stream.impl.io.InputStreamSinkStage$$anon$1$$anonfun$1 extends scala.runtime.AbstractFunction1<akka.stream.impl.io.InputStreamSinkStage$AdapterToStageMessage, scala.runtime.BoxedUnit> implements scala.Serializable {
  public static final long serialVersionUID;

  private final akka.stream.impl.io.InputStreamSinkStage$$anon$1 $outer;

  public final void apply(akka.stream.impl.io.InputStreamSinkStage$AdapterToStageMessage);
    Code:
       0: aload_1
       1: astore_2
       2: getstatic     #24                 // Field akka/stream/impl/io/InputStreamSinkStage$ReadElementAcknowledgement$.MODULE$:Lakka/stream/impl/io/InputStreamSinkStage$ReadElementAcknowledgement$;
       5: aload_2
       6: invokevirtual #30                 // Method java/lang/Object.equals:(Ljava/lang/Object;)Z
       9: ifeq          26
      12: aload_0
      13: getfield      #32                 // Field $outer:Lakka/stream/impl/io/InputStreamSinkStage$$anon$1;
      16: invokevirtual #36                 // Method akka/stream/impl/io/InputStreamSinkStage$$anon$1.akka$stream$impl$io$InputStreamSinkStage$$anon$$sendPullIfAllowed:()V
      19: getstatic     #42                 // Field scala/runtime/BoxedUnit.UNIT:Lscala/runtime/BoxedUnit;
      22: astore_3
      23: goto          47
      26: getstatic     #47                 // Field akka/stream/impl/io/InputStreamSinkStage$Close$.MODULE$:Lakka/stream/impl/io/InputStreamSinkStage$Close$;
      29: aload_2
      30: invokevirtual #30                 // Method java/lang/Object.equals:(Ljava/lang/Object;)Z
      33: ifeq          48
      36: aload_0
      37: getfield      #32                 // Field $outer:Lakka/stream/impl/io/InputStreamSinkStage$$anon$1;
      40: invokevirtual #50                 // Method akka/stream/impl/io/InputStreamSinkStage$$anon$1.completeStage:()V
      43: getstatic     #42                 // Field scala/runtime/BoxedUnit.UNIT:Lscala/runtime/BoxedUnit;
      46: astore_3
      47: return
      48: new           #52                 // class scala/MatchError
      51: dup
      52: aload_2
      53: invokespecial #56                 // Method scala/MatchError."<init>":(Ljava/lang/Object;)V
      56: athrow

  public final java.lang.Object apply(java.lang.Object);
    Code:
       0: aload_0
       1: aload_1
       2: checkcast     #62                 // class akka/stream/impl/io/InputStreamSinkStage$AdapterToStageMessage
       5: invokevirtual #65                 // Method apply:(Lakka/stream/impl/io/InputStreamSinkStage$AdapterToStageMessage;)V
       8: getstatic     #42                 // Field scala/runtime/BoxedUnit.UNIT:Lscala/runtime/BoxedUnit;
      11: areturn

  public akka.stream.impl.io.InputStreamSinkStage$$anon$1$$anonfun$1(akka.stream.impl.io.InputStreamSinkStage$$anon$1);
    Code:
       0: aload_1
       1: ifnonnull     6
       4: aconst_null
       5: athrow
       6: aload_0
       7: aload_1
       8: putfield      #32                 // Field $outer:Lakka/stream/impl/io/InputStreamSinkStage$$anon$1;
      11: aload_0
      12: invokespecial #70                 // Method scala/runtime/AbstractFunction1."<init>":()V
      15: return
}
