Compiled from "TcpStages.scala"
public class akka.stream.impl.io.TcpConnectionStage$TcpStreamLogic extends akka.stream.stage.GraphStageLogic {
  private final akka.stream.FlowShape<akka.util.ByteString, akka.util.ByteString> shape;

  private final akka.stream.impl.io.TcpConnectionStage$TcpRole role;

  private akka.actor.ActorRef akka$stream$impl$io$TcpConnectionStage$TcpStreamLogic$$connection;

  private final akka.stream.stage.OutHandler readHandler;

  public akka.stream.FlowShape<akka.util.ByteString, akka.util.ByteString> shape();
    Code:
       0: aload_0
       1: getfield      #17                 // Field shape:Lakka/stream/FlowShape;
       4: areturn

  public akka.stream.impl.io.TcpConnectionStage$TcpRole role();
    Code:
       0: aload_0
       1: getfield      #22                 // Field role:Lakka/stream/impl/io/TcpConnectionStage$TcpRole;
       4: areturn

  public akka.actor.ActorRef self();
    Code:
       0: aload_0
       1: invokevirtual #28                 // Method stageActor:()Lakka/stream/stage/GraphStageLogic$StageActor;
       4: invokevirtual #33                 // Method akka/stream/stage/GraphStageLogic$StageActor.ref:()Lakka/actor/ActorRef;
       7: areturn

  public akka.stream.Inlet<akka.util.ByteString> akka$stream$impl$io$TcpConnectionStage$TcpStreamLogic$$bytesIn();
    Code:
       0: aload_0
       1: invokevirtual #37                 // Method shape:()Lakka/stream/FlowShape;
       4: invokevirtual #42                 // Method akka/stream/FlowShape.in:()Lakka/stream/Inlet;
       7: areturn

  public akka.stream.Outlet<akka.util.ByteString> akka$stream$impl$io$TcpConnectionStage$TcpStreamLogic$$bytesOut();
    Code:
       0: aload_0
       1: invokevirtual #37                 // Method shape:()Lakka/stream/FlowShape;
       4: invokevirtual #47                 // Method akka/stream/FlowShape.out:()Lakka/stream/Outlet;
       7: areturn

  public akka.actor.ActorRef akka$stream$impl$io$TcpConnectionStage$TcpStreamLogic$$connection();
    Code:
       0: aload_0
       1: getfield      #49                 // Field akka$stream$impl$io$TcpConnectionStage$TcpStreamLogic$$connection:Lakka/actor/ActorRef;
       4: areturn

  private void akka$stream$impl$io$TcpConnectionStage$TcpStreamLogic$$connection_$eq(akka.actor.ActorRef);
    Code:
       0: aload_0
       1: aload_1
       2: putfield      #49                 // Field akka$stream$impl$io$TcpConnectionStage$TcpStreamLogic$$connection:Lakka/actor/ActorRef;
       5: return

  public void preStart();
    Code:
       0: aload_0
       1: iconst_1
       2: invokevirtual #58                 // Method setKeepGoing:(Z)V
       5: aload_0
       6: invokevirtual #60                 // Method role:()Lakka/stream/impl/io/TcpConnectionStage$TcpRole;
       9: astore_1
      10: aload_1
      11: instanceof    #62                 // class akka/stream/impl/io/TcpConnectionStage$Inbound
      14: ifeq          111
      17: aload_1
      18: checkcast     #62                 // class akka/stream/impl/io/TcpConnectionStage$Inbound
      21: astore_2
      22: aload_2
      23: invokevirtual #65                 // Method akka/stream/impl/io/TcpConnectionStage$Inbound.connection:()Lakka/actor/ActorRef;
      26: astore_3
      27: aload_0
      28: aload_0
      29: invokevirtual #67                 // Method akka$stream$impl$io$TcpConnectionStage$TcpStreamLogic$$bytesOut:()Lakka/stream/Outlet;
      32: aload_0
      33: invokevirtual #70                 // Method readHandler:()Lakka/stream/stage/OutHandler;
      36: invokevirtual #74                 // Method setHandler:(Lakka/stream/Outlet;Lakka/stream/stage/OutHandler;)V
      39: aload_0
      40: aload_3
      41: invokespecial #76                 // Method akka$stream$impl$io$TcpConnectionStage$TcpStreamLogic$$connection_$eq:(Lakka/actor/ActorRef;)V
      44: aload_0
      45: new           #78                 // class akka/stream/impl/io/TcpConnectionStage$TcpStreamLogic$$anonfun$preStart$2
      48: dup
      49: aload_0
      50: invokespecial #82                 // Method akka/stream/impl/io/TcpConnectionStage$TcpStreamLogic$$anonfun$preStart$2."<init>":(Lakka/stream/impl/io/TcpConnectionStage$TcpStreamLogic;)V
      53: invokevirtual #86                 // Method getStageActor:(Lscala/Function1;)Lakka/stream/stage/GraphStageLogic$StageActor;
      56: aload_0
      57: invokevirtual #88                 // Method akka$stream$impl$io$TcpConnectionStage$TcpStreamLogic$$connection:()Lakka/actor/ActorRef;
      60: invokevirtual #91                 // Method akka/stream/stage/GraphStageLogic$StageActor.watch:(Lakka/actor/ActorRef;)V
      63: getstatic     #97                 // Field akka/actor/package$.MODULE$:Lakka/actor/package$;
      66: aload_0
      67: invokevirtual #88                 // Method akka$stream$impl$io$TcpConnectionStage$TcpStreamLogic$$connection:()Lakka/actor/ActorRef;
      70: invokevirtual #101                // Method akka/actor/package$.actorRef2Scala:(Lakka/actor/ActorRef;)Lakka/actor/ScalaActorRef;
      73: new           #103                // class akka/io/Tcp$Register
      76: dup
      77: aload_0
      78: invokevirtual #105                // Method self:()Lakka/actor/ActorRef;
      81: iconst_1
      82: iconst_0
      83: invokespecial #108                // Method akka/io/Tcp$Register."<init>":(Lakka/actor/ActorRef;ZZ)V
      86: aload_0
      87: invokevirtual #105                // Method self:()Lakka/actor/ActorRef;
      90: invokeinterface #114,  3          // InterfaceMethod akka/actor/ScalaActorRef.$bang:(Ljava/lang/Object;Lakka/actor/ActorRef;)V
      95: aload_0
      96: aload_0
      97: invokevirtual #116                // Method akka$stream$impl$io$TcpConnectionStage$TcpStreamLogic$$bytesIn:()Lakka/stream/Inlet;
     100: invokevirtual #120                // Method pull:(Lakka/stream/Inlet;)V
     103: getstatic     #126                // Field scala/runtime/BoxedUnit.UNIT:Lscala/runtime/BoxedUnit;
     106: astore        4
     108: goto          181
     111: aload_1
     112: instanceof    #128                // class akka/stream/impl/io/TcpConnectionStage$Outbound
     115: ifeq          182
     118: aload_1
     119: checkcast     #128                // class akka/stream/impl/io/TcpConnectionStage$Outbound
     122: astore        5
     124: aload         5
     126: invokevirtual #131                // Method akka/stream/impl/io/TcpConnectionStage$Outbound.manager:()Lakka/actor/ActorRef;
     129: astore        6
     131: aload         5
     133: invokevirtual #135                // Method akka/stream/impl/io/TcpConnectionStage$Outbound.connectCmd:()Lakka/io/Tcp$Connect;
     136: astore        7
     138: aload_0
     139: new           #137                // class akka/stream/impl/io/TcpConnectionStage$TcpStreamLogic$$anonfun$preStart$3
     142: dup
     143: aload_0
     144: aload         5
     146: invokespecial #140                // Method akka/stream/impl/io/TcpConnectionStage$TcpStreamLogic$$anonfun$preStart$3."<init>":(Lakka/stream/impl/io/TcpConnectionStage$TcpStreamLogic;Lakka/stream/impl/io/TcpConnectionStage$Outbound;)V
     149: invokevirtual #86                 // Method getStageActor:(Lscala/Function1;)Lakka/stream/stage/GraphStageLogic$StageActor;
     152: aload         6
     154: invokevirtual #91                 // Method akka/stream/stage/GraphStageLogic$StageActor.watch:(Lakka/actor/ActorRef;)V
     157: getstatic     #97                 // Field akka/actor/package$.MODULE$:Lakka/actor/package$;
     160: aload         6
     162: invokevirtual #101                // Method akka/actor/package$.actorRef2Scala:(Lakka/actor/ActorRef;)Lakka/actor/ScalaActorRef;
     165: aload         7
     167: aload_0
     168: invokevirtual #105                // Method self:()Lakka/actor/ActorRef;
     171: invokeinterface #114,  3          // InterfaceMethod akka/actor/ScalaActorRef.$bang:(Ljava/lang/Object;Lakka/actor/ActorRef;)V
     176: getstatic     #126                // Field scala/runtime/BoxedUnit.UNIT:Lscala/runtime/BoxedUnit;
     179: astore        4
     181: return
     182: new           #142                // class scala/MatchError
     185: dup
     186: aload_1
     187: invokespecial #145                // Method scala/MatchError."<init>":(Ljava/lang/Object;)V
     190: athrow

  public void akka$stream$impl$io$TcpConnectionStage$TcpStreamLogic$$connecting(akka.stream.impl.io.TcpConnectionStage$Outbound, scala.Tuple2<akka.actor.ActorRef, java.lang.Object>);
    Code:
       0: aload_2
       1: invokevirtual #158                // Method scala/Tuple2._1:()Ljava/lang/Object;
       4: checkcast     #160                // class akka/actor/ActorRef
       7: astore_3
       8: aload_2
       9: invokevirtual #163                // Method scala/Tuple2._2:()Ljava/lang/Object;
      12: astore        4
      14: aload         4
      16: astore        5
      18: aload         5
      20: instanceof    #165                // class akka/actor/Terminated
      23: ifeq          47
      26: aload_0
      27: new           #167                // class akka/stream/StreamTcpException
      30: dup
      31: ldc           #169                // String The IO manager actor (TCP) has terminated. Stopping now.
      33: invokespecial #172                // Method akka/stream/StreamTcpException."<init>":(Ljava/lang/String;)V
      36: invokevirtual #176                // Method failStage:(Ljava/lang/Throwable;)V
      39: getstatic     #126                // Field scala/runtime/BoxedUnit.UNIT:Lscala/runtime/BoxedUnit;
      42: astore        6
      44: goto          304
      47: aload         5
      49: instanceof    #178                // class akka/io/Tcp$CommandFailed
      52: ifeq          136
      55: aload         5
      57: checkcast     #178                // class akka/io/Tcp$CommandFailed
      60: astore        7
      62: aload         7
      64: invokevirtual #181                // Method akka/io/Tcp$CommandFailed.cmd:()Lakka/io/Tcp$Command;
      67: astore        8
      69: aload_0
      70: new           #167                // class akka/stream/StreamTcpException
      73: dup
      74: new           #183                // class scala/StringContext
      77: dup
      78: getstatic     #188                // Field scala/Predef$.MODULE$:Lscala/Predef$;
      81: iconst_2
      82: anewarray     #190                // class java/lang/String
      85: dup
      86: iconst_0
      87: ldc           #192                // String Tcp command [
      89: aastore
      90: dup
      91: iconst_1
      92: ldc           #194                // String ] failed
      94: aastore
      95: checkcast     #196                // class "[Ljava/lang/Object;"
      98: invokevirtual #200                // Method scala/Predef$.wrapRefArray:([Ljava/lang/Object;)Lscala/collection/mutable/WrappedArray;
     101: invokespecial #203                // Method scala/StringContext."<init>":(Lscala/collection/Seq;)V
     104: getstatic     #188                // Field scala/Predef$.MODULE$:Lscala/Predef$;
     107: iconst_1
     108: anewarray     #205                // class java/lang/Object
     111: dup
     112: iconst_0
     113: aload         8
     115: aastore
     116: invokevirtual #209                // Method scala/Predef$.genericWrapArray:(Ljava/lang/Object;)Lscala/collection/mutable/WrappedArray;
     119: invokevirtual #213                // Method scala/StringContext.s:(Lscala/collection/Seq;)Ljava/lang/String;
     122: invokespecial #172                // Method akka/stream/StreamTcpException."<init>":(Ljava/lang/String;)V
     125: invokevirtual #176                // Method failStage:(Ljava/lang/Throwable;)V
     128: getstatic     #126                // Field scala/runtime/BoxedUnit.UNIT:Lscala/runtime/BoxedUnit;
     131: astore        6
     133: goto          304
     136: aload         5
     138: instanceof    #215                // class akka/io/Tcp$Connected
     141: ifeq          305
     144: aload         5
     146: checkcast     #215                // class akka/io/Tcp$Connected
     149: astore        9
     151: aload_0
     152: invokevirtual #60                 // Method role:()Lakka/stream/impl/io/TcpConnectionStage$TcpRole;
     155: checkcast     #128                // class akka/stream/impl/io/TcpConnectionStage$Outbound
     158: invokevirtual #219                // Method akka/stream/impl/io/TcpConnectionStage$Outbound.localAddressPromise:()Lscala/concurrent/Promise;
     161: aload         9
     163: invokevirtual #223                // Method akka/io/Tcp$Connected.localAddress:()Ljava/net/InetSocketAddress;
     166: invokeinterface #229,  2          // InterfaceMethod scala/concurrent/Promise.success:(Ljava/lang/Object;)Lscala/concurrent/Promise;
     171: pop
     172: aload_0
     173: aload_3
     174: invokespecial #76                 // Method akka$stream$impl$io$TcpConnectionStage$TcpStreamLogic$$connection_$eq:(Lakka/actor/ActorRef;)V
     177: aload_0
     178: aload_0
     179: invokevirtual #67                 // Method akka$stream$impl$io$TcpConnectionStage$TcpStreamLogic$$bytesOut:()Lakka/stream/Outlet;
     182: aload_0
     183: invokevirtual #70                 // Method readHandler:()Lakka/stream/stage/OutHandler;
     186: invokevirtual #74                 // Method setHandler:(Lakka/stream/Outlet;Lakka/stream/stage/OutHandler;)V
     189: aload_0
     190: invokevirtual #28                 // Method stageActor:()Lakka/stream/stage/GraphStageLogic$StageActor;
     193: aload_1
     194: invokevirtual #131                // Method akka/stream/impl/io/TcpConnectionStage$Outbound.manager:()Lakka/actor/ActorRef;
     197: invokevirtual #232                // Method akka/stream/stage/GraphStageLogic$StageActor.unwatch:(Lakka/actor/ActorRef;)V
     200: aload_0
     201: invokevirtual #28                 // Method stageActor:()Lakka/stream/stage/GraphStageLogic$StageActor;
     204: new           #234                // class akka/stream/impl/io/TcpConnectionStage$TcpStreamLogic$$anonfun$akka$stream$impl$io$TcpConnectionStage$TcpStreamLogic$$connecting$1
     207: dup
     208: aload_0
     209: invokespecial #235                // Method akka/stream/impl/io/TcpConnectionStage$TcpStreamLogic$$anonfun$akka$stream$impl$io$TcpConnectionStage$TcpStreamLogic$$connecting$1."<init>":(Lakka/stream/impl/io/TcpConnectionStage$TcpStreamLogic;)V
     212: invokevirtual #239                // Method akka/stream/stage/GraphStageLogic$StageActor.become:(Lscala/Function1;)V
     215: aload_0
     216: invokevirtual #28                 // Method stageActor:()Lakka/stream/stage/GraphStageLogic$StageActor;
     219: aload_0
     220: invokevirtual #88                 // Method akka$stream$impl$io$TcpConnectionStage$TcpStreamLogic$$connection:()Lakka/actor/ActorRef;
     223: invokevirtual #91                 // Method akka/stream/stage/GraphStageLogic$StageActor.watch:(Lakka/actor/ActorRef;)V
     226: getstatic     #97                 // Field akka/actor/package$.MODULE$:Lakka/actor/package$;
     229: aload_0
     230: invokevirtual #88                 // Method akka$stream$impl$io$TcpConnectionStage$TcpStreamLogic$$connection:()Lakka/actor/ActorRef;
     233: invokevirtual #101                // Method akka/actor/package$.actorRef2Scala:(Lakka/actor/ActorRef;)Lakka/actor/ScalaActorRef;
     236: new           #103                // class akka/io/Tcp$Register
     239: dup
     240: aload_0
     241: invokevirtual #105                // Method self:()Lakka/actor/ActorRef;
     244: iconst_1
     245: iconst_0
     246: invokespecial #108                // Method akka/io/Tcp$Register."<init>":(Lakka/actor/ActorRef;ZZ)V
     249: aload_0
     250: invokevirtual #105                // Method self:()Lakka/actor/ActorRef;
     253: invokeinterface #114,  3          // InterfaceMethod akka/actor/ScalaActorRef.$bang:(Ljava/lang/Object;Lakka/actor/ActorRef;)V
     258: aload_0
     259: aload_0
     260: invokevirtual #67                 // Method akka$stream$impl$io$TcpConnectionStage$TcpStreamLogic$$bytesOut:()Lakka/stream/Outlet;
     263: invokevirtual #243                // Method isAvailable:(Lakka/stream/Outlet;)Z
     266: ifeq          291
     269: getstatic     #97                 // Field akka/actor/package$.MODULE$:Lakka/actor/package$;
     272: aload_0
     273: invokevirtual #88                 // Method akka$stream$impl$io$TcpConnectionStage$TcpStreamLogic$$connection:()Lakka/actor/ActorRef;
     276: invokevirtual #101                // Method akka/actor/package$.actorRef2Scala:(Lakka/actor/ActorRef;)Lakka/actor/ScalaActorRef;
     279: getstatic     #248                // Field akka/io/Tcp$ResumeReading$.MODULE$:Lakka/io/Tcp$ResumeReading$;
     282: aload_0
     283: invokevirtual #105                // Method self:()Lakka/actor/ActorRef;
     286: invokeinterface #114,  3          // InterfaceMethod akka/actor/ScalaActorRef.$bang:(Ljava/lang/Object;Lakka/actor/ActorRef;)V
     291: aload_0
     292: aload_0
     293: invokevirtual #116                // Method akka$stream$impl$io$TcpConnectionStage$TcpStreamLogic$$bytesIn:()Lakka/stream/Inlet;
     296: invokevirtual #120                // Method pull:(Lakka/stream/Inlet;)V
     299: getstatic     #126                // Field scala/runtime/BoxedUnit.UNIT:Lscala/runtime/BoxedUnit;
     302: astore        6
     304: return
     305: new           #142                // class scala/MatchError
     308: dup
     309: aload         5
     311: invokespecial #145                // Method scala/MatchError."<init>":(Ljava/lang/Object;)V
     314: athrow

  public void akka$stream$impl$io$TcpConnectionStage$TcpStreamLogic$$connected(scala.Tuple2<akka.actor.ActorRef, java.lang.Object>);
    Code:
       0: aload_1
       1: invokevirtual #158                // Method scala/Tuple2._1:()Ljava/lang/Object;
       4: checkcast     #160                // class akka/actor/ActorRef
       7: astore_2
       8: aload_1
       9: invokevirtual #163                // Method scala/Tuple2._2:()Ljava/lang/Object;
      12: astore_3
      13: aload_3
      14: astore        4
      16: aload         4
      18: instanceof    #165                // class akka/actor/Terminated
      21: ifeq          46
      24: aload_0
      25: new           #167                // class akka/stream/StreamTcpException
      28: dup
      29: ldc_w         #260                // String The connection actor has terminated. Stopping now.
      32: invokespecial #172                // Method akka/stream/StreamTcpException."<init>":(Ljava/lang/String;)V
      35: invokevirtual #176                // Method failStage:(Ljava/lang/Throwable;)V
      38: getstatic     #126                // Field scala/runtime/BoxedUnit.UNIT:Lscala/runtime/BoxedUnit;
      41: astore        5
      43: goto          452
      46: aload         4
      48: instanceof    #178                // class akka/io/Tcp$CommandFailed
      51: ifeq          135
      54: aload         4
      56: checkcast     #178                // class akka/io/Tcp$CommandFailed
      59: astore        6
      61: aload         6
      63: invokevirtual #181                // Method akka/io/Tcp$CommandFailed.cmd:()Lakka/io/Tcp$Command;
      66: astore        7
      68: aload_0
      69: new           #167                // class akka/stream/StreamTcpException
      72: dup
      73: new           #183                // class scala/StringContext
      76: dup
      77: getstatic     #188                // Field scala/Predef$.MODULE$:Lscala/Predef$;
      80: iconst_2
      81: anewarray     #190                // class java/lang/String
      84: dup
      85: iconst_0
      86: ldc           #192                // String Tcp command [
      88: aastore
      89: dup
      90: iconst_1
      91: ldc           #194                // String ] failed
      93: aastore
      94: checkcast     #196                // class "[Ljava/lang/Object;"
      97: invokevirtual #200                // Method scala/Predef$.wrapRefArray:([Ljava/lang/Object;)Lscala/collection/mutable/WrappedArray;
     100: invokespecial #203                // Method scala/StringContext."<init>":(Lscala/collection/Seq;)V
     103: getstatic     #188                // Field scala/Predef$.MODULE$:Lscala/Predef$;
     106: iconst_1
     107: anewarray     #205                // class java/lang/Object
     110: dup
     111: iconst_0
     112: aload         7
     114: aastore
     115: invokevirtual #209                // Method scala/Predef$.genericWrapArray:(Ljava/lang/Object;)Lscala/collection/mutable/WrappedArray;
     118: invokevirtual #213                // Method scala/StringContext.s:(Lscala/collection/Seq;)Ljava/lang/String;
     121: invokespecial #172                // Method akka/stream/StreamTcpException."<init>":(Ljava/lang/String;)V
     124: invokevirtual #176                // Method failStage:(Ljava/lang/Throwable;)V
     127: getstatic     #126                // Field scala/runtime/BoxedUnit.UNIT:Lscala/runtime/BoxedUnit;
     130: astore        5
     132: goto          452
     135: aload         4
     137: instanceof    #262                // class akka/io/Tcp$ErrorClosed
     140: ifeq          226
     143: aload         4
     145: checkcast     #262                // class akka/io/Tcp$ErrorClosed
     148: astore        8
     150: aload         8
     152: invokevirtual #266                // Method akka/io/Tcp$ErrorClosed.cause:()Ljava/lang/String;
     155: astore        9
     157: aload_0
     158: new           #167                // class akka/stream/StreamTcpException
     161: dup
     162: new           #183                // class scala/StringContext
     165: dup
     166: getstatic     #188                // Field scala/Predef$.MODULE$:Lscala/Predef$;
     169: iconst_2
     170: anewarray     #190                // class java/lang/String
     173: dup
     174: iconst_0
     175: ldc_w         #268                // String The connection closed with error:
     178: aastore
     179: dup
     180: iconst_1
     181: ldc_w         #270                // String
     184: aastore
     185: checkcast     #196                // class "[Ljava/lang/Object;"
     188: invokevirtual #200                // Method scala/Predef$.wrapRefArray:([Ljava/lang/Object;)Lscala/collection/mutable/WrappedArray;
     191: invokespecial #203                // Method scala/StringContext."<init>":(Lscala/collection/Seq;)V
     194: getstatic     #188                // Field scala/Predef$.MODULE$:Lscala/Predef$;
     197: iconst_1
     198: anewarray     #205                // class java/lang/Object
     201: dup
     202: iconst_0
     203: aload         9
     205: aastore
     206: invokevirtual #209                // Method scala/Predef$.genericWrapArray:(Ljava/lang/Object;)Lscala/collection/mutable/WrappedArray;
     209: invokevirtual #213                // Method scala/StringContext.s:(Lscala/collection/Seq;)Ljava/lang/String;
     212: invokespecial #172                // Method akka/stream/StreamTcpException."<init>":(Ljava/lang/String;)V
     215: invokevirtual #176                // Method failStage:(Ljava/lang/Throwable;)V
     218: getstatic     #126                // Field scala/runtime/BoxedUnit.UNIT:Lscala/runtime/BoxedUnit;
     221: astore        5
     223: goto          452
     226: getstatic     #275                // Field akka/io/Tcp$Aborted$.MODULE$:Lakka/io/Tcp$Aborted$;
     229: aload         4
     231: invokevirtual #279                // Method java/lang/Object.equals:(Ljava/lang/Object;)Z
     234: ifeq          259
     237: aload_0
     238: new           #167                // class akka/stream/StreamTcpException
     241: dup
     242: ldc_w         #281                // String The connection has been aborted
     245: invokespecial #172                // Method akka/stream/StreamTcpException."<init>":(Ljava/lang/String;)V
     248: invokevirtual #176                // Method failStage:(Ljava/lang/Throwable;)V
     251: getstatic     #126                // Field scala/runtime/BoxedUnit.UNIT:Lscala/runtime/BoxedUnit;
     254: astore        5
     256: goto          452
     259: getstatic     #286                // Field akka/io/Tcp$Closed$.MODULE$:Lakka/io/Tcp$Closed$;
     262: aload         4
     264: invokevirtual #279                // Method java/lang/Object.equals:(Ljava/lang/Object;)Z
     267: ifeq          282
     270: aload_0
     271: invokevirtual #289                // Method completeStage:()V
     274: getstatic     #126                // Field scala/runtime/BoxedUnit.UNIT:Lscala/runtime/BoxedUnit;
     277: astore        5
     279: goto          452
     282: getstatic     #294                // Field akka/io/Tcp$ConfirmedClosed$.MODULE$:Lakka/io/Tcp$ConfirmedClosed$;
     285: aload         4
     287: invokevirtual #279                // Method java/lang/Object.equals:(Ljava/lang/Object;)Z
     290: ifeq          305
     293: aload_0
     294: invokevirtual #289                // Method completeStage:()V
     297: getstatic     #126                // Field scala/runtime/BoxedUnit.UNIT:Lscala/runtime/BoxedUnit;
     300: astore        5
     302: goto          452
     305: getstatic     #299                // Field akka/io/Tcp$PeerClosed$.MODULE$:Lakka/io/Tcp$PeerClosed$;
     308: aload         4
     310: invokevirtual #279                // Method java/lang/Object.equals:(Ljava/lang/Object;)Z
     313: ifeq          332
     316: aload_0
     317: aload_0
     318: invokevirtual #67                 // Method akka$stream$impl$io$TcpConnectionStage$TcpStreamLogic$$bytesOut:()Lakka/stream/Outlet;
     321: invokevirtual #303                // Method complete:(Lakka/stream/Outlet;)V
     324: getstatic     #126                // Field scala/runtime/BoxedUnit.UNIT:Lscala/runtime/BoxedUnit;
     327: astore        5
     329: goto          452
     332: aload         4
     334: instanceof    #305                // class akka/io/Tcp$Received
     337: ifeq          411
     340: aload         4
     342: checkcast     #305                // class akka/io/Tcp$Received
     345: astore        10
     347: aload         10
     349: invokevirtual #309                // Method akka/io/Tcp$Received.data:()Lakka/util/ByteString;
     352: astore        11
     354: aload_0
     355: aload_0
     356: invokevirtual #67                 // Method akka$stream$impl$io$TcpConnectionStage$TcpStreamLogic$$bytesOut:()Lakka/stream/Outlet;
     359: invokevirtual #312                // Method isClosed:(Lakka/stream/Outlet;)Z
     362: ifeq          393
     365: getstatic     #97                 // Field akka/actor/package$.MODULE$:Lakka/actor/package$;
     368: aload_0
     369: invokevirtual #88                 // Method akka$stream$impl$io$TcpConnectionStage$TcpStreamLogic$$connection:()Lakka/actor/ActorRef;
     372: invokevirtual #101                // Method akka/actor/package$.actorRef2Scala:(Lakka/actor/ActorRef;)Lakka/actor/ScalaActorRef;
     375: getstatic     #248                // Field akka/io/Tcp$ResumeReading$.MODULE$:Lakka/io/Tcp$ResumeReading$;
     378: aload_0
     379: invokevirtual #105                // Method self:()Lakka/actor/ActorRef;
     382: invokeinterface #114,  3          // InterfaceMethod akka/actor/ScalaActorRef.$bang:(Ljava/lang/Object;Lakka/actor/ActorRef;)V
     387: getstatic     #126                // Field scala/runtime/BoxedUnit.UNIT:Lscala/runtime/BoxedUnit;
     390: goto          406
     393: aload_0
     394: aload_0
     395: invokevirtual #67                 // Method akka$stream$impl$io$TcpConnectionStage$TcpStreamLogic$$bytesOut:()Lakka/stream/Outlet;
     398: aload         11
     400: invokevirtual #316                // Method push:(Lakka/stream/Outlet;Ljava/lang/Object;)V
     403: getstatic     #126                // Field scala/runtime/BoxedUnit.UNIT:Lscala/runtime/BoxedUnit;
     406: astore        5
     408: goto          452
     411: getstatic     #321                // Field akka/stream/impl/io/TcpConnectionStage$WriteAck$.MODULE$:Lakka/stream/impl/io/TcpConnectionStage$WriteAck$;
     414: aload         4
     416: invokevirtual #279                // Method java/lang/Object.equals:(Ljava/lang/Object;)Z
     419: ifeq          453
     422: aload_0
     423: aload_0
     424: invokevirtual #116                // Method akka$stream$impl$io$TcpConnectionStage$TcpStreamLogic$$bytesIn:()Lakka/stream/Inlet;
     427: invokevirtual #324                // Method isClosed:(Lakka/stream/Inlet;)Z
     430: ifeq          439
     433: getstatic     #126                // Field scala/runtime/BoxedUnit.UNIT:Lscala/runtime/BoxedUnit;
     436: goto          450
     439: aload_0
     440: aload_0
     441: invokevirtual #116                // Method akka$stream$impl$io$TcpConnectionStage$TcpStreamLogic$$bytesIn:()Lakka/stream/Inlet;
     444: invokevirtual #120                // Method pull:(Lakka/stream/Inlet;)V
     447: getstatic     #126                // Field scala/runtime/BoxedUnit.UNIT:Lscala/runtime/BoxedUnit;
     450: astore        5
     452: return
     453: new           #142                // class scala/MatchError
     456: dup
     457: aload         4
     459: invokespecial #145                // Method scala/MatchError."<init>":(Ljava/lang/Object;)V
     462: athrow

  public akka.stream.stage.OutHandler readHandler();
    Code:
       0: aload_0
       1: getfield      #330                // Field readHandler:Lakka/stream/stage/OutHandler;
       4: areturn

  public void postStop();
    Code:
       0: aload_0
       1: invokevirtual #60                 // Method role:()Lakka/stream/impl/io/TcpConnectionStage$TcpRole;
       4: astore_1
       5: aload_1
       6: instanceof    #128                // class akka/stream/impl/io/TcpConnectionStage$Outbound
       9: ifeq          47
      12: aload_1
      13: checkcast     #128                // class akka/stream/impl/io/TcpConnectionStage$Outbound
      16: astore_2
      17: aload_2
      18: invokevirtual #219                // Method akka/stream/impl/io/TcpConnectionStage$Outbound.localAddressPromise:()Lscala/concurrent/Promise;
      21: astore_3
      22: aload_3
      23: new           #167                // class akka/stream/StreamTcpException
      26: dup
      27: ldc_w         #333                // String Connection failed.
      30: invokespecial #172                // Method akka/stream/StreamTcpException."<init>":(Ljava/lang/String;)V
      33: invokeinterface #337,  2          // InterfaceMethod scala/concurrent/Promise.tryFailure:(Ljava/lang/Throwable;)Z
      38: pop
      39: getstatic     #126                // Field scala/runtime/BoxedUnit.UNIT:Lscala/runtime/BoxedUnit;
      42: astore        4
      44: goto          52
      47: getstatic     #126                // Field scala/runtime/BoxedUnit.UNIT:Lscala/runtime/BoxedUnit;
      50: astore        4
      52: return

  public akka.stream.impl.io.TcpConnectionStage$TcpStreamLogic(akka.stream.FlowShape<akka.util.ByteString, akka.util.ByteString>, akka.stream.impl.io.TcpConnectionStage$TcpRole);
    Code:
       0: aload_0
       1: aload_1
       2: putfield      #17                 // Field shape:Lakka/stream/FlowShape;
       5: aload_0
       6: aload_2
       7: putfield      #22                 // Field role:Lakka/stream/impl/io/TcpConnectionStage$TcpRole;
      10: aload_0
      11: aload_1
      12: invokespecial #342                // Method akka/stream/stage/GraphStageLogic."<init>":(Lakka/stream/Shape;)V
      15: aload_0
      16: aload_0
      17: invokevirtual #67                 // Method akka$stream$impl$io$TcpConnectionStage$TcpStreamLogic$$bytesOut:()Lakka/stream/Outlet;
      20: new           #344                // class akka/stream/impl/io/TcpConnectionStage$TcpStreamLogic$$anon$4
      23: dup
      24: aload_0
      25: invokespecial #345                // Method akka/stream/impl/io/TcpConnectionStage$TcpStreamLogic$$anon$4."<init>":(Lakka/stream/impl/io/TcpConnectionStage$TcpStreamLogic;)V
      28: invokevirtual #74                 // Method setHandler:(Lakka/stream/Outlet;Lakka/stream/stage/OutHandler;)V
      31: aload_0
      32: new           #347                // class akka/stream/impl/io/TcpConnectionStage$TcpStreamLogic$$anon$3
      35: dup
      36: aload_0
      37: invokespecial #348                // Method akka/stream/impl/io/TcpConnectionStage$TcpStreamLogic$$anon$3."<init>":(Lakka/stream/impl/io/TcpConnectionStage$TcpStreamLogic;)V
      40: putfield      #330                // Field readHandler:Lakka/stream/stage/OutHandler;
      43: aload_0
      44: aload_0
      45: invokevirtual #116                // Method akka$stream$impl$io$TcpConnectionStage$TcpStreamLogic$$bytesIn:()Lakka/stream/Inlet;
      48: new           #350                // class akka/stream/impl/io/TcpConnectionStage$TcpStreamLogic$$anon$5
      51: dup
      52: aload_0
      53: invokespecial #351                // Method akka/stream/impl/io/TcpConnectionStage$TcpStreamLogic$$anon$5."<init>":(Lakka/stream/impl/io/TcpConnectionStage$TcpStreamLogic;)V
      56: invokevirtual #354                // Method setHandler:(Lakka/stream/Inlet;Lakka/stream/stage/InHandler;)V
      59: return
}
