Compiled from "ReferenceUnmarshaller.java"
public class org.opensaml.ws.wssecurity.impl.ReferenceUnmarshaller extends org.opensaml.ws.wssecurity.impl.AbstractWSSecurityObjectUnmarshaller {
  public org.opensaml.ws.wssecurity.impl.ReferenceUnmarshaller();
    Code:
       0: aload_0
       1: invokespecial #1                  // Method org/opensaml/ws/wssecurity/impl/AbstractWSSecurityObjectUnmarshaller."<init>":()V
       4: return

  protected void processAttribute(org.opensaml.xml.XMLObject, org.w3c.dom.Attr) throws org.opensaml.xml.io.UnmarshallingException;
    Code:
       0: aload_1
       1: checkcast     #2                  // class org/opensaml/ws/wssecurity/Reference
       4: astore_3
       5: aload_2
       6: invokeinterface #3,  1            // InterfaceMethod org/w3c/dom/Attr.getLocalName:()Ljava/lang/String;
      11: astore        4
      13: ldc           #4                  // String URI
      15: aload         4
      17: invokevirtual #5                  // Method java/lang/String.equals:(Ljava/lang/Object;)Z
      20: ifeq          38
      23: aload_3
      24: aload_2
      25: invokeinterface #6,  1            // InterfaceMethod org/w3c/dom/Attr.getValue:()Ljava/lang/String;
      30: invokeinterface #7,  2            // InterfaceMethod org/opensaml/ws/wssecurity/Reference.setURI:(Ljava/lang/String;)V
      35: goto          73
      38: ldc           #8                  // String ValueType
      40: aload         4
      42: invokevirtual #5                  // Method java/lang/String.equals:(Ljava/lang/Object;)Z
      45: ifeq          63
      48: aload_3
      49: aload_2
      50: invokeinterface #6,  1            // InterfaceMethod org/w3c/dom/Attr.getValue:()Ljava/lang/String;
      55: invokeinterface #9,  2            // InterfaceMethod org/opensaml/ws/wssecurity/Reference.setValueType:(Ljava/lang/String;)V
      60: goto          73
      63: aload_3
      64: invokeinterface #10,  1           // InterfaceMethod org/opensaml/ws/wssecurity/Reference.getUnknownAttributes:()Lorg/opensaml/xml/util/AttributeMap;
      69: aload_2
      70: invokestatic  #11                 // Method org/opensaml/xml/util/XMLHelper.unmarshallToAttributeMap:(Lorg/opensaml/xml/util/AttributeMap;Lorg/w3c/dom/Attr;)V
      73: return
}
