Compiled from "UiPermissions.java"
public class edu.internet2.middleware.grouper.ui.UiPermissions$Target {
  private java.util.Map permissions;

  private java.lang.String name;

  final edu.internet2.middleware.grouper.ui.UiPermissions this$0;

  protected edu.internet2.middleware.grouper.ui.UiPermissions$Target(edu.internet2.middleware.grouper.ui.UiPermissions, java.lang.String);
    Code:
       0: aload_0
       1: aload_1
       2: putfield      #1                  // Field this$0:Ledu/internet2/middleware/grouper/ui/UiPermissions;
       5: aload_0
       6: invokespecial #2                  // Method java/lang/Object."<init>":()V
       9: aload_0
      10: new           #3                  // class java/util/HashMap
      13: dup
      14: invokespecial #4                  // Method java/util/HashMap."<init>":()V
      17: putfield      #5                  // Field permissions:Ljava/util/Map;
      20: aload_0
      21: aload_2
      22: putfield      #6                  // Field name:Ljava/lang/String;
      25: return

  protected void addPermission(edu.internet2.middleware.grouper.ui.UiPermissions$Permission);
    Code:
       0: aload_0
       1: getfield      #5                  // Field permissions:Ljava/util/Map;
       4: aload_1
       5: invokevirtual #7                  // Method edu/internet2/middleware/grouper/ui/UiPermissions$Permission.getAction:()Ljava/lang/String;
       8: aload_1
       9: invokeinterface #8,  3            // InterfaceMethod java/util/Map.put:(Ljava/lang/Object;Ljava/lang/Object;)Ljava/lang/Object;
      14: pop
      15: return

  protected boolean can(edu.internet2.middleware.subject.Subject, java.lang.String);
    Code:
       0: aload_0
       1: getfield      #5                  // Field permissions:Ljava/util/Map;
       4: aload_2
       5: invokeinterface #9,  2            // InterfaceMethod java/util/Map.get:(Ljava/lang/Object;)Ljava/lang/Object;
      10: checkcast     #10                 // class edu/internet2/middleware/grouper/ui/UiPermissions$Permission
      13: astore_3
      14: aload_3
      15: ifnonnull     20
      18: iconst_1
      19: ireturn
      20: aload_3
      21: aload_1
      22: invokevirtual #11                 // Method edu/internet2/middleware/grouper/ui/UiPermissions$Permission.can:(Ledu/internet2/middleware/subject/Subject;)Z
      25: ireturn
}
