Compiled from "AbstractContextUserTestCase.java"
public abstract class juzu.impl.bridge.context.AbstractContextUserTestCase extends juzu.test.AbstractWebTestCase {
  public static java.util.Locale locale;

  public juzu.impl.bridge.context.AbstractContextUserTestCase();
    Code:
       0: aload_0
       1: invokespecial #1                  // Method juzu/test/AbstractWebTestCase."<init>":()V
       4: return

  protected void test(java.net.URL) throws java.lang.Exception;
    Code:
       0: aconst_null
       1: putstatic     #2                  // Field locale:Ljava/util/Locale;
       4: aload_1
       5: invokevirtual #3                  // Method java/net/URL.openConnection:()Ljava/net/URLConnection;
       8: checkcast     #4                  // class java/net/HttpURLConnection
      11: astore_2
      12: aload_2
      13: ldc           #5                  // String Accept-Language
      15: ldc           #6                  // String fr-FR
      17: invokevirtual #7                  // Method java/net/HttpURLConnection.addRequestProperty:(Ljava/lang/String;Ljava/lang/String;)V
      20: sipush        200
      23: aload_2
      24: invokevirtual #8                  // Method java/net/HttpURLConnection.getResponseCode:()I
      27: invokestatic  #9                  // Method assertEquals:(II)V
      30: getstatic     #10                 // Field java/util/Locale.FRANCE:Ljava/util/Locale;
      33: getstatic     #2                  // Field locale:Ljava/util/Locale;
      36: invokestatic  #11                 // Method assertEquals:(Ljava/lang/Object;Ljava/lang/Object;)V
      39: return
}
