Compiled from "SimpleKeyboard.java"
public class org.jboss.as.domain.management.security.password.simple.SimpleKeyboard implements org.jboss.as.domain.management.security.password.Keyboard {
  protected java.util.Map<java.lang.Character, java.util.Set<java.lang.Character>> keys;

  public org.jboss.as.domain.management.security.password.simple.SimpleKeyboard();
    Code:
       0: aload_0
       1: invokespecial #1                  // Method java/lang/Object."<init>":()V
       4: aload_0
       5: new           #2                  // class java/util/TreeMap
       8: dup
       9: invokespecial #3                  // Method java/util/TreeMap."<init>":()V
      12: putfield      #4                  // Field keys:Ljava/util/Map;
      15: ldc           #5                  // class org/jboss/as/domain/management/security/password/Keyboard
      17: ldc           #6                  // String keybord.properties
      19: invokevirtual #7                  // Method java/lang/Class.getResourceAsStream:(Ljava/lang/String;)Ljava/io/InputStream;
      22: astore_1
      23: aload_1
      24: ifnull        32
      27: aload_0
      28: aload_1
      29: invokevirtual #8                  // Method init:(Ljava/io/InputStream;)V
      32: return

  public org.jboss.as.domain.management.security.password.simple.SimpleKeyboard(java.io.InputStream);
    Code:
       0: aload_0
       1: invokespecial #1                  // Method java/lang/Object."<init>":()V
       4: aload_0
       5: new           #2                  // class java/util/TreeMap
       8: dup
       9: invokespecial #3                  // Method java/util/TreeMap."<init>":()V
      12: putfield      #4                  // Field keys:Ljava/util/Map;
      15: aload_0
      16: aload_1
      17: invokevirtual #8                  // Method init:(Ljava/io/InputStream;)V
      20: return

  protected void init(java.io.InputStream);
    Code:
       0: new           #9                  // class java/util/Properties
       3: dup
       4: invokespecial #10                 // Method java/util/Properties."<init>":()V
       7: astore_2
       8: aload_2
       9: aload_1
      10: invokevirtual #11                 // Method java/util/Properties.load:(Ljava/io/InputStream;)V
      13: aload_2
      14: invokevirtual #12                 // Method java/util/Properties.keySet:()Ljava/util/Set;
      17: invokeinterface #13,  1           // InterfaceMethod java/util/Set.iterator:()Ljava/util/Iterator;
      22: astore_3
      23: aload_3
      24: invokeinterface #14,  1           // InterfaceMethod java/util/Iterator.hasNext:()Z
      29: ifeq          153
      32: aload_3
      33: invokeinterface #15,  1           // InterfaceMethod java/util/Iterator.next:()Ljava/lang/Object;
      38: checkcast     #16                 // class java/lang/String
      41: astore        4
      43: aload_2
      44: aload         4
      46: invokevirtual #17                 // Method java/util/Properties.get:(Ljava/lang/Object;)Ljava/lang/Object;
      49: checkcast     #16                 // class java/lang/String
      52: astore        5
      54: aconst_null
      55: astore        6
      57: aload         4
      59: invokevirtual #18                 // Method java/lang/String.length:()I
      62: ifle          79
      65: aload         4
      67: iconst_0
      68: invokevirtual #19                 // Method java/lang/String.charAt:(I)C
      71: invokestatic  #20                 // Method java/lang/Character.valueOf:(C)Ljava/lang/Character;
      74: astore        6
      76: goto          86
      79: bipush        32
      81: invokestatic  #20                 // Method java/lang/Character.valueOf:(C)Ljava/lang/Character;
      84: astore        6
      86: new           #21                 // class java/util/TreeSet
      89: dup
      90: invokespecial #22                 // Method java/util/TreeSet."<init>":()V
      93: astore        7
      95: iconst_0
      96: istore        8
      98: iload         8
     100: aload         5
     102: invokevirtual #18                 // Method java/lang/String.length:()I
     105: if_icmpge     136
     108: aload         5
     110: iload         8
     112: invokevirtual #19                 // Method java/lang/String.charAt:(I)C
     115: invokestatic  #20                 // Method java/lang/Character.valueOf:(C)Ljava/lang/Character;
     118: astore        9
     120: aload         7
     122: aload         9
     124: invokeinterface #23,  2           // InterfaceMethod java/util/Set.add:(Ljava/lang/Object;)Z
     129: pop
     130: iinc          8, 1
     133: goto          98
     136: aload_0
     137: getfield      #4                  // Field keys:Ljava/util/Map;
     140: aload         6
     142: aload         7
     144: invokeinterface #24,  3           // InterfaceMethod java/util/Map.put:(Ljava/lang/Object;Ljava/lang/Object;)Ljava/lang/Object;
     149: pop
     150: goto          23
     153: goto          161
     156: astore_2
     157: aload_2
     158: invokevirtual #26                 // Method java/lang/Exception.printStackTrace:()V
     161: return
    Exception table:
       from    to  target type
           0   153   156   Class java/lang/Exception

  public boolean siblings(java.lang.String, int);
    Code:
       0: aload_0
       1: aload_1
       2: iload_2
       3: iload_2
       4: iconst_1
       5: iadd
       6: invokevirtual #27                 // Method siblings:(Ljava/lang/String;II)Z
       9: ireturn

  public boolean siblings(java.lang.String, int, int);
    Code:
       0: aload_1
       1: ifnonnull     12
       4: new           #28                 // class java/lang/IllegalArgumentException
       7: dup
       8: invokespecial #29                 // Method java/lang/IllegalArgumentException."<init>":()V
      11: athrow
      12: iload_2
      13: iload_3
      14: if_icmplt     25
      17: new           #28                 // class java/lang/IllegalArgumentException
      20: dup
      21: invokespecial #29                 // Method java/lang/IllegalArgumentException."<init>":()V
      24: athrow
      25: aload_1
      26: invokevirtual #18                 // Method java/lang/String.length:()I
      29: istore        4
      31: iload_2
      32: iload         4
      34: if_icmplt     45
      37: new           #28                 // class java/lang/IllegalArgumentException
      40: dup
      41: invokespecial #29                 // Method java/lang/IllegalArgumentException."<init>":()V
      44: athrow
      45: aload_1
      46: iload_2
      47: invokevirtual #19                 // Method java/lang/String.charAt:(I)C
      50: invokestatic  #20                 // Method java/lang/Character.valueOf:(C)Ljava/lang/Character;
      53: astore        5
      55: aload_1
      56: iload_3
      57: invokevirtual #19                 // Method java/lang/String.charAt:(I)C
      60: invokestatic  #20                 // Method java/lang/Character.valueOf:(C)Ljava/lang/Character;
      63: astore        6
      65: aload_0
      66: getfield      #4                  // Field keys:Ljava/util/Map;
      69: aload         5
      71: invokeinterface #30,  2           // InterfaceMethod java/util/Map.get:(Ljava/lang/Object;)Ljava/lang/Object;
      76: checkcast     #31                 // class java/util/Set
      79: astore        7
      81: aload         7
      83: ifnull        100
      86: aload         7
      88: aload         6
      90: invokeinterface #32,  2           // InterfaceMethod java/util/Set.contains:(Ljava/lang/Object;)Z
      95: ifeq          100
      98: iconst_1
      99: ireturn
     100: iconst_0
     101: ireturn

  public int sequence(java.lang.String, int);
    Code:
       0: aload_1
       1: invokevirtual #18                 // Method java/lang/String.length:()I
       4: istore_3
       5: iload_2
       6: iload_3
       7: if_icmplt     20
      10: new           #28                 // class java/lang/IllegalArgumentException
      13: dup
      14: ldc           #33                 // String Start index greater than word length
      16: invokespecial #34                 // Method java/lang/IllegalArgumentException."<init>":(Ljava/lang/String;)V
      19: athrow
      20: iconst_0
      21: istore        4
      23: iload_2
      24: istore        5
      26: iload         5
      28: iconst_1
      29: iadd
      30: iload_3
      31: if_icmpge     59
      34: aload_0
      35: aload_1
      36: iload         5
      38: invokevirtual #35                 // Method siblings:(Ljava/lang/String;I)Z
      41: ifeq          50
      44: iinc          4, 1
      47: goto          53
      50: iload         4
      52: ireturn
      53: iinc          5, 1
      56: goto          26
      59: iload         4
      61: ireturn
}
