Compiled from "AbstractASTTransformUtil.java"
public abstract class org.codehaus.groovy.transform.AbstractASTTransformUtil implements groovyjarjarasm.asm.Opcodes {
  public org.codehaus.groovy.transform.AbstractASTTransformUtil();
    Code:
       0: aload_0
       1: invokespecial #12                 // Method java/lang/Object."<init>":()V
       4: return

  public static org.codehaus.groovy.ast.stmt.Statement assignStatement(org.codehaus.groovy.ast.expr.Expression, org.codehaus.groovy.ast.expr.Expression);
    Code:
       0: aload_0
       1: aload_1
       2: invokestatic  #21                 // Method org/codehaus/groovy/ast/tools/GeneralUtils.assignS:(Lorg/codehaus/groovy/ast/expr/Expression;Lorg/codehaus/groovy/ast/expr/Expression;)Lorg/codehaus/groovy/ast/stmt/Statement;
       5: areturn

  public static org.codehaus.groovy.ast.stmt.Statement createConstructorStatementDefault(org.codehaus.groovy.ast.FieldNode);
    Code:
       0: aload_0
       1: invokestatic  #28                 // Method org/codehaus/groovy/ast/tools/GeneralUtils.createConstructorStatementDefault:(Lorg/codehaus/groovy/ast/FieldNode;)Lorg/codehaus/groovy/ast/stmt/Statement;
       4: areturn

  public static org.codehaus.groovy.ast.stmt.ExpressionStatement declStatement(org.codehaus.groovy.ast.expr.Expression, org.codehaus.groovy.ast.expr.Expression);
    Code:
       0: aload_0
       1: aload_1
       2: invokestatic  #35                 // Method org/codehaus/groovy/ast/tools/GeneralUtils.declS:(Lorg/codehaus/groovy/ast/expr/Expression;Lorg/codehaus/groovy/ast/expr/Expression;)Lorg/codehaus/groovy/ast/stmt/Statement;
       5: checkcast     #37                 // class org/codehaus/groovy/ast/stmt/ExpressionStatement
       8: areturn

  public static org.codehaus.groovy.ast.expr.BooleanExpression differentExpr(org.codehaus.groovy.ast.expr.Expression, org.codehaus.groovy.ast.expr.Expression);
    Code:
       0: aload_0
       1: aload_1
       2: invokestatic  #44                 // Method org/codehaus/groovy/ast/tools/GeneralUtils.sameX:(Lorg/codehaus/groovy/ast/expr/Expression;Lorg/codehaus/groovy/ast/expr/Expression;)Lorg/codehaus/groovy/ast/expr/BooleanExpression;
       5: invokestatic  #48                 // Method org/codehaus/groovy/ast/tools/GeneralUtils.notX:(Lorg/codehaus/groovy/ast/expr/Expression;)Lorg/codehaus/groovy/ast/expr/NotExpression;
       8: areturn

  public static org.codehaus.groovy.ast.expr.BooleanExpression differentFieldExpr(org.codehaus.groovy.ast.FieldNode, org.codehaus.groovy.ast.expr.Expression);
    Code:
       0: aload_0
       1: aload_1
       2: invokestatic  #55                 // Method org/codehaus/groovy/ast/tools/GeneralUtils.hasSameFieldX:(Lorg/codehaus/groovy/ast/FieldNode;Lorg/codehaus/groovy/ast/expr/Expression;)Lorg/codehaus/groovy/ast/expr/BooleanExpression;
       5: invokestatic  #48                 // Method org/codehaus/groovy/ast/tools/GeneralUtils.notX:(Lorg/codehaus/groovy/ast/expr/Expression;)Lorg/codehaus/groovy/ast/expr/NotExpression;
       8: areturn

  public static org.codehaus.groovy.ast.expr.BooleanExpression differentPropertyExpr(org.codehaus.groovy.ast.PropertyNode, org.codehaus.groovy.ast.expr.Expression);
    Code:
       0: aload_0
       1: aload_1
       2: invokestatic  #60                 // Method org/codehaus/groovy/ast/tools/GeneralUtils.hasSamePropertyX:(Lorg/codehaus/groovy/ast/PropertyNode;Lorg/codehaus/groovy/ast/expr/Expression;)Lorg/codehaus/groovy/ast/expr/BooleanExpression;
       5: invokestatic  #48                 // Method org/codehaus/groovy/ast/tools/GeneralUtils.notX:(Lorg/codehaus/groovy/ast/expr/Expression;)Lorg/codehaus/groovy/ast/expr/NotExpression;
       8: areturn

  public static org.codehaus.groovy.ast.expr.BooleanExpression equalsNullExpr(org.codehaus.groovy.ast.expr.Expression);
    Code:
       0: aload_0
       1: invokestatic  #67                 // Method org/codehaus/groovy/ast/tools/GeneralUtils.equalsNullX:(Lorg/codehaus/groovy/ast/expr/Expression;)Lorg/codehaus/groovy/ast/expr/BooleanExpression;
       4: areturn

  public static org.codehaus.groovy.ast.expr.Expression findArg(java.lang.String);
    Code:
       0: aload_0
       1: invokestatic  #72                 // Method org/codehaus/groovy/ast/tools/GeneralUtils.findArg:(Ljava/lang/String;)Lorg/codehaus/groovy/ast/expr/Expression;
       4: areturn

  public static java.util.List<org.codehaus.groovy.ast.FieldNode> getInstanceNonPropertyFields(org.codehaus.groovy.ast.ClassNode);
    Code:
       0: aload_0
       1: invokestatic  #78                 // Method org/codehaus/groovy/ast/tools/GeneralUtils.getInstanceNonPropertyFields:(Lorg/codehaus/groovy/ast/ClassNode;)Ljava/util/List;
       4: areturn

  public static java.util.List<org.codehaus.groovy.ast.PropertyNode> getInstanceProperties(org.codehaus.groovy.ast.ClassNode);
    Code:
       0: aload_0
       1: invokestatic  #83                 // Method org/codehaus/groovy/ast/tools/GeneralUtils.getInstanceProperties:(Lorg/codehaus/groovy/ast/ClassNode;)Ljava/util/List;
       4: areturn

  public static java.util.List<org.codehaus.groovy.ast.FieldNode> getInstancePropertyFields(org.codehaus.groovy.ast.ClassNode);
    Code:
       0: aload_0
       1: invokestatic  #86                 // Method org/codehaus/groovy/ast/tools/GeneralUtils.getInstancePropertyFields:(Lorg/codehaus/groovy/ast/ClassNode;)Ljava/util/List;
       4: areturn

  public static java.util.List<org.codehaus.groovy.ast.FieldNode> getSuperNonPropertyFields(org.codehaus.groovy.ast.ClassNode);
    Code:
       0: aload_0
       1: invokestatic  #89                 // Method org/codehaus/groovy/ast/tools/GeneralUtils.getSuperNonPropertyFields:(Lorg/codehaus/groovy/ast/ClassNode;)Ljava/util/List;
       4: areturn

  public static java.util.List<org.codehaus.groovy.ast.FieldNode> getSuperPropertyFields(org.codehaus.groovy.ast.ClassNode);
    Code:
       0: aload_0
       1: invokestatic  #92                 // Method org/codehaus/groovy/ast/tools/GeneralUtils.getSuperPropertyFields:(Lorg/codehaus/groovy/ast/ClassNode;)Ljava/util/List;
       4: areturn

  public static boolean hasDeclaredMethod(org.codehaus.groovy.ast.ClassNode, java.lang.String, int);
    Code:
       0: aload_0
       1: aload_1
       2: iload_2
       3: invokestatic  #96                 // Method org/codehaus/groovy/ast/tools/GeneralUtils.hasDeclaredMethod:(Lorg/codehaus/groovy/ast/ClassNode;Ljava/lang/String;I)Z
       6: ireturn

  public static org.codehaus.groovy.ast.expr.BooleanExpression identicalExpr(org.codehaus.groovy.ast.expr.Expression, org.codehaus.groovy.ast.expr.Expression);
    Code:
       0: aload_0
       1: aload_1
       2: invokestatic  #44                 // Method org/codehaus/groovy/ast/tools/GeneralUtils.sameX:(Lorg/codehaus/groovy/ast/expr/Expression;Lorg/codehaus/groovy/ast/expr/Expression;)Lorg/codehaus/groovy/ast/expr/BooleanExpression;
       5: areturn

  public static org.codehaus.groovy.ast.expr.BooleanExpression isInstanceOf(org.codehaus.groovy.ast.expr.Expression, org.codehaus.groovy.ast.ClassNode);
    Code:
       0: aload_0
       1: aload_1
       2: invokestatic  #105                // Method org/codehaus/groovy/ast/tools/GeneralUtils.isInstanceOfX:(Lorg/codehaus/groovy/ast/expr/Expression;Lorg/codehaus/groovy/ast/ClassNode;)Lorg/codehaus/groovy/ast/expr/BooleanExpression;
       5: areturn

  public static org.codehaus.groovy.ast.expr.BooleanExpression isInstanceof(org.codehaus.groovy.ast.ClassNode, org.codehaus.groovy.ast.expr.Expression);
    Code:
       0: aload_1
       1: aload_0
       2: invokestatic  #105                // Method org/codehaus/groovy/ast/tools/GeneralUtils.isInstanceOfX:(Lorg/codehaus/groovy/ast/expr/Expression;Lorg/codehaus/groovy/ast/ClassNode;)Lorg/codehaus/groovy/ast/expr/BooleanExpression;
       5: areturn

  public static org.codehaus.groovy.ast.expr.BooleanExpression isOneExpr(org.codehaus.groovy.ast.expr.Expression);
    Code:
       0: aload_0
       1: invokestatic  #112                // Method org/codehaus/groovy/ast/tools/GeneralUtils.isOneX:(Lorg/codehaus/groovy/ast/expr/Expression;)Lorg/codehaus/groovy/ast/expr/BooleanExpression;
       4: areturn

  public static boolean isOrImplements(org.codehaus.groovy.ast.ClassNode, org.codehaus.groovy.ast.ClassNode);
    Code:
       0: aload_0
       1: aload_1
       2: invokestatic  #117                // Method org/codehaus/groovy/ast/tools/GeneralUtils.isOrImplements:(Lorg/codehaus/groovy/ast/ClassNode;Lorg/codehaus/groovy/ast/ClassNode;)Z
       5: ireturn

  public static org.codehaus.groovy.ast.expr.BooleanExpression isTrueExpr(org.codehaus.groovy.ast.expr.Expression);
    Code:
       0: aload_0
       1: invokestatic  #123                // Method org/codehaus/groovy/ast/tools/GeneralUtils.isTrueX:(Lorg/codehaus/groovy/ast/expr/Expression;)Lorg/codehaus/groovy/ast/expr/BooleanExpression;
       4: areturn

  public static org.codehaus.groovy.ast.expr.BooleanExpression isZeroExpr(org.codehaus.groovy.ast.expr.Expression);
    Code:
       0: aload_0
       1: invokestatic  #127                // Method org/codehaus/groovy/ast/tools/GeneralUtils.isZeroX:(Lorg/codehaus/groovy/ast/expr/Expression;)Lorg/codehaus/groovy/ast/expr/BooleanExpression;
       4: areturn

  public static org.codehaus.groovy.ast.expr.BooleanExpression notNullExpr(org.codehaus.groovy.ast.expr.Expression);
    Code:
       0: aload_0
       1: invokestatic  #131                // Method org/codehaus/groovy/ast/tools/GeneralUtils.notNullX:(Lorg/codehaus/groovy/ast/expr/Expression;)Lorg/codehaus/groovy/ast/expr/BooleanExpression;
       4: areturn

  public static org.codehaus.groovy.ast.stmt.Statement returnFalseIfFieldNotEqual(org.codehaus.groovy.ast.FieldNode, org.codehaus.groovy.ast.expr.Expression);
    Code:
       0: aload_0
       1: aload_1
       2: invokestatic  #137                // Method org/codehaus/groovy/ast/tools/GeneralUtils.hasEqualFieldX:(Lorg/codehaus/groovy/ast/FieldNode;Lorg/codehaus/groovy/ast/expr/Expression;)Lorg/codehaus/groovy/ast/expr/BinaryExpression;
       5: invokestatic  #48                 // Method org/codehaus/groovy/ast/tools/GeneralUtils.notX:(Lorg/codehaus/groovy/ast/expr/Expression;)Lorg/codehaus/groovy/ast/expr/NotExpression;
       8: getstatic     #143                // Field java/lang/Boolean.FALSE:Ljava/lang/Boolean;
      11: invokestatic  #147                // Method org/codehaus/groovy/ast/tools/GeneralUtils.constX:(Ljava/lang/Object;)Lorg/codehaus/groovy/ast/expr/ConstantExpression;
      14: invokestatic  #151                // Method org/codehaus/groovy/ast/tools/GeneralUtils.returnS:(Lorg/codehaus/groovy/ast/expr/Expression;)Lorg/codehaus/groovy/ast/stmt/Statement;
      17: invokestatic  #155                // Method org/codehaus/groovy/ast/tools/GeneralUtils.ifS:(Lorg/codehaus/groovy/ast/expr/Expression;Lorg/codehaus/groovy/ast/stmt/Statement;)Lorg/codehaus/groovy/ast/stmt/Statement;
      20: areturn

  public static org.codehaus.groovy.ast.stmt.Statement returnFalseIfNotInstanceof(org.codehaus.groovy.ast.ClassNode, org.codehaus.groovy.ast.expr.Expression);
    Code:
       0: aload_1
       1: aload_0
       2: invokestatic  #105                // Method org/codehaus/groovy/ast/tools/GeneralUtils.isInstanceOfX:(Lorg/codehaus/groovy/ast/expr/Expression;Lorg/codehaus/groovy/ast/ClassNode;)Lorg/codehaus/groovy/ast/expr/BooleanExpression;
       5: invokestatic  #48                 // Method org/codehaus/groovy/ast/tools/GeneralUtils.notX:(Lorg/codehaus/groovy/ast/expr/Expression;)Lorg/codehaus/groovy/ast/expr/NotExpression;
       8: getstatic     #143                // Field java/lang/Boolean.FALSE:Ljava/lang/Boolean;
      11: invokestatic  #147                // Method org/codehaus/groovy/ast/tools/GeneralUtils.constX:(Ljava/lang/Object;)Lorg/codehaus/groovy/ast/expr/ConstantExpression;
      14: invokestatic  #151                // Method org/codehaus/groovy/ast/tools/GeneralUtils.returnS:(Lorg/codehaus/groovy/ast/expr/Expression;)Lorg/codehaus/groovy/ast/stmt/Statement;
      17: invokestatic  #155                // Method org/codehaus/groovy/ast/tools/GeneralUtils.ifS:(Lorg/codehaus/groovy/ast/expr/Expression;Lorg/codehaus/groovy/ast/stmt/Statement;)Lorg/codehaus/groovy/ast/stmt/Statement;
      20: areturn

  public static org.codehaus.groovy.ast.stmt.IfStatement returnFalseIfNull(org.codehaus.groovy.ast.expr.Expression);
    Code:
       0: aload_0
       1: invokestatic  #67                 // Method org/codehaus/groovy/ast/tools/GeneralUtils.equalsNullX:(Lorg/codehaus/groovy/ast/expr/Expression;)Lorg/codehaus/groovy/ast/expr/BooleanExpression;
       4: getstatic     #143                // Field java/lang/Boolean.FALSE:Ljava/lang/Boolean;
       7: invokestatic  #147                // Method org/codehaus/groovy/ast/tools/GeneralUtils.constX:(Ljava/lang/Object;)Lorg/codehaus/groovy/ast/expr/ConstantExpression;
      10: invokestatic  #151                // Method org/codehaus/groovy/ast/tools/GeneralUtils.returnS:(Lorg/codehaus/groovy/ast/expr/Expression;)Lorg/codehaus/groovy/ast/stmt/Statement;
      13: invokestatic  #155                // Method org/codehaus/groovy/ast/tools/GeneralUtils.ifS:(Lorg/codehaus/groovy/ast/expr/Expression;Lorg/codehaus/groovy/ast/stmt/Statement;)Lorg/codehaus/groovy/ast/stmt/Statement;
      16: checkcast     #161                // class org/codehaus/groovy/ast/stmt/IfStatement
      19: areturn

  public static org.codehaus.groovy.ast.stmt.Statement returnFalseIfPropertyNotEqual(org.codehaus.groovy.ast.PropertyNode, org.codehaus.groovy.ast.expr.Expression);
    Code:
       0: aload_0
       1: aload_1
       2: invokestatic  #167                // Method org/codehaus/groovy/ast/tools/GeneralUtils.hasEqualPropertyX:(Lorg/codehaus/groovy/ast/PropertyNode;Lorg/codehaus/groovy/ast/expr/Expression;)Lorg/codehaus/groovy/ast/expr/BinaryExpression;
       5: invokestatic  #48                 // Method org/codehaus/groovy/ast/tools/GeneralUtils.notX:(Lorg/codehaus/groovy/ast/expr/Expression;)Lorg/codehaus/groovy/ast/expr/NotExpression;
       8: getstatic     #143                // Field java/lang/Boolean.FALSE:Ljava/lang/Boolean;
      11: invokestatic  #147                // Method org/codehaus/groovy/ast/tools/GeneralUtils.constX:(Ljava/lang/Object;)Lorg/codehaus/groovy/ast/expr/ConstantExpression;
      14: invokestatic  #151                // Method org/codehaus/groovy/ast/tools/GeneralUtils.returnS:(Lorg/codehaus/groovy/ast/expr/Expression;)Lorg/codehaus/groovy/ast/stmt/Statement;
      17: invokestatic  #155                // Method org/codehaus/groovy/ast/tools/GeneralUtils.ifS:(Lorg/codehaus/groovy/ast/expr/Expression;Lorg/codehaus/groovy/ast/stmt/Statement;)Lorg/codehaus/groovy/ast/stmt/Statement;
      20: areturn

  public static org.codehaus.groovy.ast.stmt.Statement returnFalseIfWrongType(org.codehaus.groovy.ast.ClassNode, org.codehaus.groovy.ast.expr.Expression);
    Code:
       0: aload_1
       1: aload_0
       2: invokestatic  #172                // Method org/codehaus/groovy/ast/tools/GeneralUtils.hasClassX:(Lorg/codehaus/groovy/ast/expr/Expression;Lorg/codehaus/groovy/ast/ClassNode;)Lorg/codehaus/groovy/ast/expr/BinaryExpression;
       5: invokestatic  #48                 // Method org/codehaus/groovy/ast/tools/GeneralUtils.notX:(Lorg/codehaus/groovy/ast/expr/Expression;)Lorg/codehaus/groovy/ast/expr/NotExpression;
       8: getstatic     #143                // Field java/lang/Boolean.FALSE:Ljava/lang/Boolean;
      11: invokestatic  #147                // Method org/codehaus/groovy/ast/tools/GeneralUtils.constX:(Ljava/lang/Object;)Lorg/codehaus/groovy/ast/expr/ConstantExpression;
      14: invokestatic  #151                // Method org/codehaus/groovy/ast/tools/GeneralUtils.returnS:(Lorg/codehaus/groovy/ast/expr/Expression;)Lorg/codehaus/groovy/ast/stmt/Statement;
      17: invokestatic  #155                // Method org/codehaus/groovy/ast/tools/GeneralUtils.ifS:(Lorg/codehaus/groovy/ast/expr/Expression;Lorg/codehaus/groovy/ast/stmt/Statement;)Lorg/codehaus/groovy/ast/stmt/Statement;
      20: areturn

  public static org.codehaus.groovy.ast.stmt.IfStatement returnTrueIfIdentical(org.codehaus.groovy.ast.expr.Expression, org.codehaus.groovy.ast.expr.Expression);
    Code:
       0: aload_0
       1: aload_1
       2: invokestatic  #44                 // Method org/codehaus/groovy/ast/tools/GeneralUtils.sameX:(Lorg/codehaus/groovy/ast/expr/Expression;Lorg/codehaus/groovy/ast/expr/Expression;)Lorg/codehaus/groovy/ast/expr/BooleanExpression;
       5: getstatic     #177                // Field java/lang/Boolean.TRUE:Ljava/lang/Boolean;
       8: invokestatic  #147                // Method org/codehaus/groovy/ast/tools/GeneralUtils.constX:(Ljava/lang/Object;)Lorg/codehaus/groovy/ast/expr/ConstantExpression;
      11: invokestatic  #151                // Method org/codehaus/groovy/ast/tools/GeneralUtils.returnS:(Lorg/codehaus/groovy/ast/expr/Expression;)Lorg/codehaus/groovy/ast/stmt/Statement;
      14: invokestatic  #155                // Method org/codehaus/groovy/ast/tools/GeneralUtils.ifS:(Lorg/codehaus/groovy/ast/expr/Expression;Lorg/codehaus/groovy/ast/stmt/Statement;)Lorg/codehaus/groovy/ast/stmt/Statement;
      17: checkcast     #161                // class org/codehaus/groovy/ast/stmt/IfStatement
      20: areturn

  public static org.codehaus.groovy.ast.stmt.Statement safeExpression(org.codehaus.groovy.ast.expr.Expression, org.codehaus.groovy.ast.expr.Expression);
    Code:
       0: aload_0
       1: aload_1
       2: invokestatic  #180                // Method org/codehaus/groovy/ast/tools/GeneralUtils.safeExpression:(Lorg/codehaus/groovy/ast/expr/Expression;Lorg/codehaus/groovy/ast/expr/Expression;)Lorg/codehaus/groovy/ast/stmt/Statement;
       5: areturn
}
