Compiled from "BuilderASTTransformation.java"
public class org.codehaus.groovy.transform.BuilderASTTransformation$AbstractBuilderStrategy$PropertyInfo {
  private java.lang.String name;

  private org.codehaus.groovy.ast.ClassNode type;

  public org.codehaus.groovy.transform.BuilderASTTransformation$AbstractBuilderStrategy$PropertyInfo(java.lang.String, org.codehaus.groovy.ast.ClassNode);
    Code:
       0: aload_0
       1: invokespecial #20                 // Method java/lang/Object."<init>":()V
       4: aload_0
       5: aload_1
       6: putfield      #22                 // Field name:Ljava/lang/String;
       9: aload_0
      10: aload_2
      11: putfield      #24                 // Field type:Lorg/codehaus/groovy/ast/ClassNode;
      14: return

  public java.lang.String getName();
    Code:
       0: aload_0
       1: getfield      #22                 // Field name:Ljava/lang/String;
       4: areturn

  public org.codehaus.groovy.ast.ClassNode getType();
    Code:
       0: aload_0
       1: getfield      #24                 // Field type:Lorg/codehaus/groovy/ast/ClassNode;
       4: areturn

  public void setName(java.lang.String);
    Code:
       0: aload_0
       1: aload_1
       2: putfield      #22                 // Field name:Ljava/lang/String;
       5: return

  public void setType(org.codehaus.groovy.ast.ClassNode);
    Code:
       0: aload_0
       1: aload_1
       2: putfield      #24                 // Field type:Lorg/codehaus/groovy/ast/ClassNode;
       5: return
}
