Compiled from "ReplaceContentRule.java"
public class org.owasp.esapi.waf.rules.ReplaceContentRule extends org.owasp.esapi.waf.rules.Rule {
  private java.util.regex.Pattern pattern;

  private java.lang.String replacement;

  private java.util.regex.Pattern contentType;

  private java.util.regex.Pattern path;

  public org.owasp.esapi.waf.rules.ReplaceContentRule(java.lang.String, java.util.regex.Pattern, java.lang.String, java.util.regex.Pattern, java.util.regex.Pattern);
    Code:
       0: aload_0
       1: invokespecial #1                  // Method org/owasp/esapi/waf/rules/Rule."<init>":()V
       4: aload_0
       5: aload_2
       6: putfield      #2                  // Field pattern:Ljava/util/regex/Pattern;
       9: aload_0
      10: aload_3
      11: putfield      #3                  // Field replacement:Ljava/lang/String;
      14: aload_0
      15: aload         5
      17: putfield      #4                  // Field path:Ljava/util/regex/Pattern;
      20: aload_0
      21: aload         4
      23: putfield      #5                  // Field contentType:Ljava/util/regex/Pattern;
      26: aload_0
      27: aload_1
      28: invokevirtual #6                  // Method setId:(Ljava/lang/String;)V
      31: return

  public org.owasp.esapi.waf.actions.Action check(javax.servlet.http.HttpServletRequest, org.owasp.esapi.waf.internal.InterceptingHTTPServletResponse, javax.servlet.http.HttpServletResponse);
    Code:
       0: aload_1
       1: invokeinterface #7,  1            // InterfaceMethod javax/servlet/http/HttpServletRequest.getRequestURI:()Ljava/lang/String;
       6: astore        4
       8: aload_0
       9: getfield      #4                  // Field path:Ljava/util/regex/Pattern;
      12: ifnull        38
      15: aload_0
      16: getfield      #4                  // Field path:Ljava/util/regex/Pattern;
      19: aload         4
      21: invokevirtual #8                  // Method java/util/regex/Pattern.matcher:(Ljava/lang/CharSequence;)Ljava/util/regex/Matcher;
      24: invokevirtual #9                  // Method java/util/regex/Matcher.matches:()Z
      27: ifne          38
      30: new           #10                 // class org/owasp/esapi/waf/actions/DoNothingAction
      33: dup
      34: invokespecial #11                 // Method org/owasp/esapi/waf/actions/DoNothingAction."<init>":()V
      37: areturn
      38: aload_0
      39: getfield      #5                  // Field contentType:Ljava/util/regex/Pattern;
      42: ifnull        77
      45: aload_2
      46: invokevirtual #12                 // Method org/owasp/esapi/waf/internal/InterceptingHTTPServletResponse.getContentType:()Ljava/lang/String;
      49: ifnull        77
      52: aload_0
      53: getfield      #5                  // Field contentType:Ljava/util/regex/Pattern;
      56: aload_2
      57: invokevirtual #12                 // Method org/owasp/esapi/waf/internal/InterceptingHTTPServletResponse.getContentType:()Ljava/lang/String;
      60: invokevirtual #8                  // Method java/util/regex/Pattern.matcher:(Ljava/lang/CharSequence;)Ljava/util/regex/Matcher;
      63: invokevirtual #9                  // Method java/util/regex/Matcher.matches:()Z
      66: ifne          77
      69: new           #10                 // class org/owasp/esapi/waf/actions/DoNothingAction
      72: dup
      73: invokespecial #11                 // Method org/owasp/esapi/waf/actions/DoNothingAction."<init>":()V
      76: areturn
      77: aconst_null
      78: astore        5
      80: aload_2
      81: invokevirtual #13                 // Method org/owasp/esapi/waf/internal/InterceptingHTTPServletResponse.getInterceptingServletOutputStream:()Lorg/owasp/esapi/waf/internal/InterceptingServletOutputStream;
      84: invokevirtual #14                 // Method org/owasp/esapi/waf/internal/InterceptingServletOutputStream.getResponseBytes:()[B
      87: astore        5
      89: goto          164
      92: astore        6
      94: aload_0
      95: aload_1
      96: new           #16                 // class java/lang/StringBuilder
      99: dup
     100: invokespecial #17                 // Method java/lang/StringBuilder."<init>":()V
     103: ldc           #18                 // String Error matching pattern \'
     105: invokevirtual #19                 // Method java/lang/StringBuilder.append:(Ljava/lang/String;)Ljava/lang/StringBuilder;
     108: aload_0
     109: getfield      #2                  // Field pattern:Ljava/util/regex/Pattern;
     112: invokevirtual #20                 // Method java/util/regex/Pattern.pattern:()Ljava/lang/String;
     115: invokevirtual #19                 // Method java/lang/StringBuilder.append:(Ljava/lang/String;)Ljava/lang/StringBuilder;
     118: ldc           #21                 // String \', IOException encountered (possibly too large?):
     120: invokevirtual #19                 // Method java/lang/StringBuilder.append:(Ljava/lang/String;)Ljava/lang/StringBuilder;
     123: aload         6
     125: invokevirtual #22                 // Method java/io/IOException.getMessage:()Ljava/lang/String;
     128: invokevirtual #19                 // Method java/lang/StringBuilder.append:(Ljava/lang/String;)Ljava/lang/StringBuilder;
     131: ldc           #23                 // String  (in response to URL: \'
     133: invokevirtual #19                 // Method java/lang/StringBuilder.append:(Ljava/lang/String;)Ljava/lang/StringBuilder;
     136: aload_1
     137: invokeinterface #24,  1           // InterfaceMethod javax/servlet/http/HttpServletRequest.getRequestURL:()Ljava/lang/StringBuffer;
     142: invokevirtual #25                 // Method java/lang/StringBuilder.append:(Ljava/lang/Object;)Ljava/lang/StringBuilder;
     145: ldc           #26                 // String \')
     147: invokevirtual #19                 // Method java/lang/StringBuilder.append:(Ljava/lang/String;)Ljava/lang/StringBuilder;
     150: invokevirtual #27                 // Method java/lang/StringBuilder.toString:()Ljava/lang/String;
     153: invokevirtual #28                 // Method log:(Ljavax/servlet/http/HttpServletRequest;Ljava/lang/String;)V
     156: new           #10                 // class org/owasp/esapi/waf/actions/DoNothingAction
     159: dup
     160: invokespecial #11                 // Method org/owasp/esapi/waf/actions/DoNothingAction."<init>":()V
     163: areturn
     164: new           #29                 // class java/lang/String
     167: dup
     168: aload         5
     170: aload_2
     171: invokevirtual #30                 // Method org/owasp/esapi/waf/internal/InterceptingHTTPServletResponse.getCharacterEncoding:()Ljava/lang/String;
     174: invokespecial #31                 // Method java/lang/String."<init>":([BLjava/lang/String;)V
     177: astore        6
     179: aload_0
     180: getfield      #2                  // Field pattern:Ljava/util/regex/Pattern;
     183: aload         6
     185: invokevirtual #8                  // Method java/util/regex/Pattern.matcher:(Ljava/lang/CharSequence;)Ljava/util/regex/Matcher;
     188: astore        7
     190: aload         7
     192: aload_0
     193: getfield      #3                  // Field replacement:Ljava/lang/String;
     196: invokevirtual #32                 // Method java/util/regex/Matcher.replaceAll:(Ljava/lang/String;)Ljava/lang/String;
     199: astore        8
     201: aload         6
     203: aload         8
     205: invokevirtual #33                 // Method java/lang/String.equals:(Ljava/lang/Object;)Z
     208: ifne          282
     211: aload_2
     212: invokevirtual #13                 // Method org/owasp/esapi/waf/internal/InterceptingHTTPServletResponse.getInterceptingServletOutputStream:()Lorg/owasp/esapi/waf/internal/InterceptingServletOutputStream;
     215: aload         8
     217: aload_2
     218: invokevirtual #30                 // Method org/owasp/esapi/waf/internal/InterceptingHTTPServletResponse.getCharacterEncoding:()Ljava/lang/String;
     221: invokevirtual #34                 // Method java/lang/String.getBytes:(Ljava/lang/String;)[B
     224: invokevirtual #35                 // Method org/owasp/esapi/waf/internal/InterceptingServletOutputStream.setResponseBytes:([B)V
     227: getstatic     #36                 // Field logger:Lorg/owasp/esapi/Logger;
     230: getstatic     #37                 // Field org/owasp/esapi/Logger.SECURITY_SUCCESS:Lorg/owasp/esapi/Logger$EventType;
     233: new           #16                 // class java/lang/StringBuilder
     236: dup
     237: invokespecial #17                 // Method java/lang/StringBuilder."<init>":()V
     240: ldc           #38                 // String Successfully replaced pattern \'
     242: invokevirtual #19                 // Method java/lang/StringBuilder.append:(Ljava/lang/String;)Ljava/lang/StringBuilder;
     245: aload_0
     246: getfield      #2                  // Field pattern:Ljava/util/regex/Pattern;
     249: invokevirtual #20                 // Method java/util/regex/Pattern.pattern:()Ljava/lang/String;
     252: invokevirtual #19                 // Method java/lang/StringBuilder.append:(Ljava/lang/String;)Ljava/lang/StringBuilder;
     255: ldc           #39                 // String \' on response to URL \'
     257: invokevirtual #19                 // Method java/lang/StringBuilder.append:(Ljava/lang/String;)Ljava/lang/StringBuilder;
     260: aload_1
     261: invokeinterface #24,  1           // InterfaceMethod javax/servlet/http/HttpServletRequest.getRequestURL:()Ljava/lang/StringBuffer;
     266: invokevirtual #25                 // Method java/lang/StringBuilder.append:(Ljava/lang/Object;)Ljava/lang/StringBuilder;
     269: ldc           #40                 // String \'
     271: invokevirtual #19                 // Method java/lang/StringBuilder.append:(Ljava/lang/String;)Ljava/lang/StringBuilder;
     274: invokevirtual #27                 // Method java/lang/StringBuilder.toString:()Ljava/lang/String;
     277: invokeinterface #41,  3           // InterfaceMethod org/owasp/esapi/Logger.debug:(Lorg/owasp/esapi/Logger$EventType;Ljava/lang/String;)V
     282: goto          355
     285: astore        9
     287: getstatic     #36                 // Field logger:Lorg/owasp/esapi/Logger;
     290: getstatic     #42                 // Field org/owasp/esapi/Logger.SECURITY_FAILURE:Lorg/owasp/esapi/Logger$EventType;
     293: new           #16                 // class java/lang/StringBuilder
     296: dup
     297: invokespecial #17                 // Method java/lang/StringBuilder."<init>":()V
     300: ldc           #43                 // String Failed to replace pattern \'
     302: invokevirtual #19                 // Method java/lang/StringBuilder.append:(Ljava/lang/String;)Ljava/lang/StringBuilder;
     305: aload_0
     306: getfield      #2                  // Field pattern:Ljava/util/regex/Pattern;
     309: invokevirtual #20                 // Method java/util/regex/Pattern.pattern:()Ljava/lang/String;
     312: invokevirtual #19                 // Method java/lang/StringBuilder.append:(Ljava/lang/String;)Ljava/lang/StringBuilder;
     315: ldc           #39                 // String \' on response to URL \'
     317: invokevirtual #19                 // Method java/lang/StringBuilder.append:(Ljava/lang/String;)Ljava/lang/StringBuilder;
     320: aload_1
     321: invokeinterface #24,  1           // InterfaceMethod javax/servlet/http/HttpServletRequest.getRequestURL:()Ljava/lang/StringBuffer;
     326: invokevirtual #25                 // Method java/lang/StringBuilder.append:(Ljava/lang/Object;)Ljava/lang/StringBuilder;
     329: ldc           #44                 // String \' due to [
     331: invokevirtual #19                 // Method java/lang/StringBuilder.append:(Ljava/lang/String;)Ljava/lang/StringBuilder;
     334: aload         9
     336: invokevirtual #22                 // Method java/io/IOException.getMessage:()Ljava/lang/String;
     339: invokevirtual #19                 // Method java/lang/StringBuilder.append:(Ljava/lang/String;)Ljava/lang/StringBuilder;
     342: ldc           #45                 // String ]
     344: invokevirtual #19                 // Method java/lang/StringBuilder.append:(Ljava/lang/String;)Ljava/lang/StringBuilder;
     347: invokevirtual #27                 // Method java/lang/StringBuilder.toString:()Ljava/lang/String;
     350: invokeinterface #46,  3           // InterfaceMethod org/owasp/esapi/Logger.error:(Lorg/owasp/esapi/Logger$EventType;Ljava/lang/String;)V
     355: goto          428
     358: astore        6
     360: getstatic     #36                 // Field logger:Lorg/owasp/esapi/Logger;
     363: getstatic     #42                 // Field org/owasp/esapi/Logger.SECURITY_FAILURE:Lorg/owasp/esapi/Logger$EventType;
     366: new           #16                 // class java/lang/StringBuilder
     369: dup
     370: invokespecial #17                 // Method java/lang/StringBuilder."<init>":()V
     373: ldc           #43                 // String Failed to replace pattern \'
     375: invokevirtual #19                 // Method java/lang/StringBuilder.append:(Ljava/lang/String;)Ljava/lang/StringBuilder;
     378: aload_0
     379: getfield      #2                  // Field pattern:Ljava/util/regex/Pattern;
     382: invokevirtual #20                 // Method java/util/regex/Pattern.pattern:()Ljava/lang/String;
     385: invokevirtual #19                 // Method java/lang/StringBuilder.append:(Ljava/lang/String;)Ljava/lang/StringBuilder;
     388: ldc           #39                 // String \' on response to URL \'
     390: invokevirtual #19                 // Method java/lang/StringBuilder.append:(Ljava/lang/String;)Ljava/lang/StringBuilder;
     393: aload_1
     394: invokeinterface #24,  1           // InterfaceMethod javax/servlet/http/HttpServletRequest.getRequestURL:()Ljava/lang/StringBuffer;
     399: invokevirtual #25                 // Method java/lang/StringBuilder.append:(Ljava/lang/Object;)Ljava/lang/StringBuilder;
     402: ldc           #44                 // String \' due to [
     404: invokevirtual #19                 // Method java/lang/StringBuilder.append:(Ljava/lang/String;)Ljava/lang/StringBuilder;
     407: aload         6
     409: invokevirtual #48                 // Method java/io/UnsupportedEncodingException.getMessage:()Ljava/lang/String;
     412: invokevirtual #19                 // Method java/lang/StringBuilder.append:(Ljava/lang/String;)Ljava/lang/StringBuilder;
     415: ldc           #45                 // String ]
     417: invokevirtual #19                 // Method java/lang/StringBuilder.append:(Ljava/lang/String;)Ljava/lang/StringBuilder;
     420: invokevirtual #27                 // Method java/lang/StringBuilder.toString:()Ljava/lang/String;
     423: invokeinterface #46,  3           // InterfaceMethod org/owasp/esapi/Logger.error:(Lorg/owasp/esapi/Logger$EventType;Ljava/lang/String;)V
     428: new           #10                 // class org/owasp/esapi/waf/actions/DoNothingAction
     431: dup
     432: invokespecial #11                 // Method org/owasp/esapi/waf/actions/DoNothingAction."<init>":()V
     435: areturn
    Exception table:
       from    to  target type
          80    89    92   Class java/io/IOException
         201   282   285   Class java/io/IOException
         164   355   358   Class java/io/UnsupportedEncodingException
}
