Compiled from "StackedChartWidgetStrategy.java"
class org.graylog2.dashboards.widgets.strategies.StackedChartWidgetStrategy$Series {
  final java.lang.String field;

  final java.lang.String query;

  final java.lang.String statisticalFunction;

  public static org.graylog2.dashboards.widgets.strategies.StackedChartWidgetStrategy$Series fromMap(java.util.Map<java.lang.String, java.lang.Object>);
    Code:
       0: new           #1                  // class org/graylog2/dashboards/widgets/strategies/StackedChartWidgetStrategy$Series
       3: dup
       4: aload_0
       5: ldc           #2                  // String query
       7: invokeinterface #3,  2            // InterfaceMethod java/util/Map.get:(Ljava/lang/Object;)Ljava/lang/Object;
      12: checkcast     #4                  // class java/lang/String
      15: aload_0
      16: ldc           #5                  // String field
      18: invokeinterface #3,  2            // InterfaceMethod java/util/Map.get:(Ljava/lang/Object;)Ljava/lang/Object;
      23: checkcast     #4                  // class java/lang/String
      26: aload_0
      27: ldc           #6                  // String statistical_function
      29: invokeinterface #3,  2            // InterfaceMethod java/util/Map.get:(Ljava/lang/Object;)Ljava/lang/Object;
      34: checkcast     #4                  // class java/lang/String
      37: invokespecial #7                  // Method "<init>":(Ljava/lang/String;Ljava/lang/String;Ljava/lang/String;)V
      40: areturn

  org.graylog2.dashboards.widgets.strategies.StackedChartWidgetStrategy$Series(java.lang.String, java.lang.String, java.lang.String);
    Code:
       0: aload_0
       1: invokespecial #8                  // Method java/lang/Object."<init>":()V
       4: aload_1
       5: ifnull        18
       8: aload_1
       9: invokevirtual #9                  // Method java/lang/String.trim:()Ljava/lang/String;
      12: invokevirtual #10                 // Method java/lang/String.isEmpty:()Z
      15: ifeq          27
      18: aload_0
      19: ldc           #11                 // String *
      21: putfield      #12                 // Field query:Ljava/lang/String;
      24: goto          32
      27: aload_0
      28: aload_1
      29: putfield      #12                 // Field query:Ljava/lang/String;
      32: aload_0
      33: aload_2
      34: putfield      #13                 // Field field:Ljava/lang/String;
      37: aload_0
      38: aload_3
      39: putfield      #14                 // Field statisticalFunction:Ljava/lang/String;
      42: return

  public java.util.Map<java.lang.String, java.lang.Object> toMap();
    Code:
       0: invokestatic  #15                 // Method com/google/common/collect/ImmutableMap.builder:()Lcom/google/common/collect/ImmutableMap$Builder;
       3: ldc           #2                  // String query
       5: aload_0
       6: getfield      #12                 // Field query:Ljava/lang/String;
       9: invokevirtual #16                 // Method com/google/common/collect/ImmutableMap$Builder.put:(Ljava/lang/Object;Ljava/lang/Object;)Lcom/google/common/collect/ImmutableMap$Builder;
      12: ldc           #5                  // String field
      14: aload_0
      15: getfield      #13                 // Field field:Ljava/lang/String;
      18: invokevirtual #16                 // Method com/google/common/collect/ImmutableMap$Builder.put:(Ljava/lang/Object;Ljava/lang/Object;)Lcom/google/common/collect/ImmutableMap$Builder;
      21: ldc           #6                  // String statistical_function
      23: aload_0
      24: getfield      #14                 // Field statisticalFunction:Ljava/lang/String;
      27: invokevirtual #16                 // Method com/google/common/collect/ImmutableMap$Builder.put:(Ljava/lang/Object;Ljava/lang/Object;)Lcom/google/common/collect/ImmutableMap$Builder;
      30: astore_1
      31: aload_1
      32: invokevirtual #17                 // Method com/google/common/collect/ImmutableMap$Builder.build:()Lcom/google/common/collect/ImmutableMap;
      35: areturn
}
