Compiled from "StreamSearchResultCountWidgetStrategy.java"
public class org.graylog2.dashboards.widgets.strategies.StreamSearchResultCountWidgetStrategy extends org.graylog2.dashboards.widgets.strategies.SearchResultCountWidgetStrategy {
  private final java.lang.String streamId;

  public org.graylog2.dashboards.widgets.strategies.StreamSearchResultCountWidgetStrategy(org.graylog2.indexer.searches.Searches, java.util.Map<java.lang.String, java.lang.Object>, org.graylog2.plugin.indexer.searches.timeranges.TimeRange, java.lang.String);
    Code:
       0: aload_0
       1: aload_1
       2: aload_2
       3: aload_3
       4: aload         4
       6: invokespecial #1                  // Method org/graylog2/dashboards/widgets/strategies/SearchResultCountWidgetStrategy."<init>":(Lorg/graylog2/indexer/searches/Searches;Ljava/util/Map;Lorg/graylog2/plugin/indexer/searches/timeranges/TimeRange;Ljava/lang/String;)V
       9: aload_0
      10: aload_2
      11: ldc           #2                  // String stream_id
      13: invokeinterface #3,  2            // InterfaceMethod java/util/Map.get:(Ljava/lang/Object;)Ljava/lang/Object;
      18: checkcast     #4                  // class java/lang/String
      21: putfield      #5                  // Field streamId:Ljava/lang/String;
      24: return

  public org.graylog2.plugin.dashboards.widgets.ComputationResult compute();
    Code:
       0: aconst_null
       1: astore_1
       2: aload_0
       3: getfield      #5                  // Field streamId:Ljava/lang/String;
       6: invokestatic  #6                  // Method com/google/common/base/Strings.isNullOrEmpty:(Ljava/lang/String;)Z
       9: ifne          35
      12: new           #7                  // class java/lang/StringBuilder
      15: dup
      16: invokespecial #8                  // Method java/lang/StringBuilder."<init>":()V
      19: ldc           #9                  // String streams:
      21: invokevirtual #10                 // Method java/lang/StringBuilder.append:(Ljava/lang/String;)Ljava/lang/StringBuilder;
      24: aload_0
      25: getfield      #5                  // Field streamId:Ljava/lang/String;
      28: invokevirtual #10                 // Method java/lang/StringBuilder.append:(Ljava/lang/String;)Ljava/lang/StringBuilder;
      31: invokevirtual #11                 // Method java/lang/StringBuilder.toString:()Ljava/lang/String;
      34: astore_1
      35: aload_0
      36: aload_1
      37: invokevirtual #12                 // Method computeInternal:(Ljava/lang/String;)Lorg/graylog2/plugin/dashboards/widgets/ComputationResult;
      40: areturn
}
