Compiled from "HttpResponseStatus.java"
public class org.jboss.netty.handler.codec.http.HttpResponseStatus implements java.lang.Comparable<org.jboss.netty.handler.codec.http.HttpResponseStatus> {
  public static final org.jboss.netty.handler.codec.http.HttpResponseStatus CONTINUE;

  public static final org.jboss.netty.handler.codec.http.HttpResponseStatus SWITCHING_PROTOCOLS;

  public static final org.jboss.netty.handler.codec.http.HttpResponseStatus PROCESSING;

  public static final org.jboss.netty.handler.codec.http.HttpResponseStatus OK;

  public static final org.jboss.netty.handler.codec.http.HttpResponseStatus CREATED;

  public static final org.jboss.netty.handler.codec.http.HttpResponseStatus ACCEPTED;

  public static final org.jboss.netty.handler.codec.http.HttpResponseStatus NON_AUTHORITATIVE_INFORMATION;

  public static final org.jboss.netty.handler.codec.http.HttpResponseStatus NO_CONTENT;

  public static final org.jboss.netty.handler.codec.http.HttpResponseStatus RESET_CONTENT;

  public static final org.jboss.netty.handler.codec.http.HttpResponseStatus PARTIAL_CONTENT;

  public static final org.jboss.netty.handler.codec.http.HttpResponseStatus MULTI_STATUS;

  public static final org.jboss.netty.handler.codec.http.HttpResponseStatus MULTIPLE_CHOICES;

  public static final org.jboss.netty.handler.codec.http.HttpResponseStatus MOVED_PERMANENTLY;

  public static final org.jboss.netty.handler.codec.http.HttpResponseStatus FOUND;

  public static final org.jboss.netty.handler.codec.http.HttpResponseStatus SEE_OTHER;

  public static final org.jboss.netty.handler.codec.http.HttpResponseStatus NOT_MODIFIED;

  public static final org.jboss.netty.handler.codec.http.HttpResponseStatus USE_PROXY;

  public static final org.jboss.netty.handler.codec.http.HttpResponseStatus TEMPORARY_REDIRECT;

  public static final org.jboss.netty.handler.codec.http.HttpResponseStatus BAD_REQUEST;

  public static final org.jboss.netty.handler.codec.http.HttpResponseStatus UNAUTHORIZED;

  public static final org.jboss.netty.handler.codec.http.HttpResponseStatus PAYMENT_REQUIRED;

  public static final org.jboss.netty.handler.codec.http.HttpResponseStatus FORBIDDEN;

  public static final org.jboss.netty.handler.codec.http.HttpResponseStatus NOT_FOUND;

  public static final org.jboss.netty.handler.codec.http.HttpResponseStatus METHOD_NOT_ALLOWED;

  public static final org.jboss.netty.handler.codec.http.HttpResponseStatus NOT_ACCEPTABLE;

  public static final org.jboss.netty.handler.codec.http.HttpResponseStatus PROXY_AUTHENTICATION_REQUIRED;

  public static final org.jboss.netty.handler.codec.http.HttpResponseStatus REQUEST_TIMEOUT;

  public static final org.jboss.netty.handler.codec.http.HttpResponseStatus CONFLICT;

  public static final org.jboss.netty.handler.codec.http.HttpResponseStatus GONE;

  public static final org.jboss.netty.handler.codec.http.HttpResponseStatus LENGTH_REQUIRED;

  public static final org.jboss.netty.handler.codec.http.HttpResponseStatus PRECONDITION_FAILED;

  public static final org.jboss.netty.handler.codec.http.HttpResponseStatus REQUEST_ENTITY_TOO_LARGE;

  public static final org.jboss.netty.handler.codec.http.HttpResponseStatus REQUEST_URI_TOO_LONG;

  public static final org.jboss.netty.handler.codec.http.HttpResponseStatus UNSUPPORTED_MEDIA_TYPE;

  public static final org.jboss.netty.handler.codec.http.HttpResponseStatus REQUESTED_RANGE_NOT_SATISFIABLE;

  public static final org.jboss.netty.handler.codec.http.HttpResponseStatus EXPECTATION_FAILED;

  public static final org.jboss.netty.handler.codec.http.HttpResponseStatus UNPROCESSABLE_ENTITY;

  public static final org.jboss.netty.handler.codec.http.HttpResponseStatus LOCKED;

  public static final org.jboss.netty.handler.codec.http.HttpResponseStatus FAILED_DEPENDENCY;

  public static final org.jboss.netty.handler.codec.http.HttpResponseStatus UNORDERED_COLLECTION;

  public static final org.jboss.netty.handler.codec.http.HttpResponseStatus UPGRADE_REQUIRED;

  public static final org.jboss.netty.handler.codec.http.HttpResponseStatus PRECONDITION_REQUIRED;

  public static final org.jboss.netty.handler.codec.http.HttpResponseStatus TOO_MANY_REQUESTS;

  public static final org.jboss.netty.handler.codec.http.HttpResponseStatus REQUEST_HEADER_FIELDS_TOO_LARGE;

  public static final org.jboss.netty.handler.codec.http.HttpResponseStatus INTERNAL_SERVER_ERROR;

  public static final org.jboss.netty.handler.codec.http.HttpResponseStatus NOT_IMPLEMENTED;

  public static final org.jboss.netty.handler.codec.http.HttpResponseStatus BAD_GATEWAY;

  public static final org.jboss.netty.handler.codec.http.HttpResponseStatus SERVICE_UNAVAILABLE;

  public static final org.jboss.netty.handler.codec.http.HttpResponseStatus GATEWAY_TIMEOUT;

  public static final org.jboss.netty.handler.codec.http.HttpResponseStatus HTTP_VERSION_NOT_SUPPORTED;

  public static final org.jboss.netty.handler.codec.http.HttpResponseStatus VARIANT_ALSO_NEGOTIATES;

  public static final org.jboss.netty.handler.codec.http.HttpResponseStatus INSUFFICIENT_STORAGE;

  public static final org.jboss.netty.handler.codec.http.HttpResponseStatus NOT_EXTENDED;

  public static final org.jboss.netty.handler.codec.http.HttpResponseStatus NETWORK_AUTHENTICATION_REQUIRED;

  private final int code;

  private final java.lang.String reasonPhrase;

  public static org.jboss.netty.handler.codec.http.HttpResponseStatus valueOf(int);
    Code:
       0: iload_0
       1: lookupswitch  { // 54
                   100: 444
                   101: 448
                   102: 452
                   200: 456
                   201: 460
                   202: 464
                   203: 468
                   204: 472
                   205: 476
                   206: 480
                   207: 484
                   300: 488
                   301: 492
                   302: 496
                   303: 500
                   304: 504
                   305: 508
                   307: 512
                   400: 516
                   401: 520
                   402: 524
                   403: 528
                   404: 532
                   405: 536
                   406: 540
                   407: 544
                   408: 548
                   409: 552
                   410: 556
                   411: 560
                   412: 564
                   413: 568
                   414: 572
                   415: 576
                   416: 580
                   417: 584
                   422: 588
                   423: 592
                   424: 596
                   425: 600
                   426: 604
                   428: 608
                   429: 612
                   431: 616
                   500: 620
                   501: 624
                   502: 628
                   503: 632
                   504: 636
                   505: 640
                   506: 644
                   507: 648
                   510: 652
                   511: 656
               default: 660
          }
     444: getstatic     #1                  // Field CONTINUE:Lorg/jboss/netty/handler/codec/http/HttpResponseStatus;
     447: areturn
     448: getstatic     #2                  // Field SWITCHING_PROTOCOLS:Lorg/jboss/netty/handler/codec/http/HttpResponseStatus;
     451: areturn
     452: getstatic     #3                  // Field PROCESSING:Lorg/jboss/netty/handler/codec/http/HttpResponseStatus;
     455: areturn
     456: getstatic     #4                  // Field OK:Lorg/jboss/netty/handler/codec/http/HttpResponseStatus;
     459: areturn
     460: getstatic     #5                  // Field CREATED:Lorg/jboss/netty/handler/codec/http/HttpResponseStatus;
     463: areturn
     464: getstatic     #6                  // Field ACCEPTED:Lorg/jboss/netty/handler/codec/http/HttpResponseStatus;
     467: areturn
     468: getstatic     #7                  // Field NON_AUTHORITATIVE_INFORMATION:Lorg/jboss/netty/handler/codec/http/HttpResponseStatus;
     471: areturn
     472: getstatic     #8                  // Field NO_CONTENT:Lorg/jboss/netty/handler/codec/http/HttpResponseStatus;
     475: areturn
     476: getstatic     #9                  // Field RESET_CONTENT:Lorg/jboss/netty/handler/codec/http/HttpResponseStatus;
     479: areturn
     480: getstatic     #10                 // Field PARTIAL_CONTENT:Lorg/jboss/netty/handler/codec/http/HttpResponseStatus;
     483: areturn
     484: getstatic     #11                 // Field MULTI_STATUS:Lorg/jboss/netty/handler/codec/http/HttpResponseStatus;
     487: areturn
     488: getstatic     #12                 // Field MULTIPLE_CHOICES:Lorg/jboss/netty/handler/codec/http/HttpResponseStatus;
     491: areturn
     492: getstatic     #13                 // Field MOVED_PERMANENTLY:Lorg/jboss/netty/handler/codec/http/HttpResponseStatus;
     495: areturn
     496: getstatic     #14                 // Field FOUND:Lorg/jboss/netty/handler/codec/http/HttpResponseStatus;
     499: areturn
     500: getstatic     #15                 // Field SEE_OTHER:Lorg/jboss/netty/handler/codec/http/HttpResponseStatus;
     503: areturn
     504: getstatic     #16                 // Field NOT_MODIFIED:Lorg/jboss/netty/handler/codec/http/HttpResponseStatus;
     507: areturn
     508: getstatic     #17                 // Field USE_PROXY:Lorg/jboss/netty/handler/codec/http/HttpResponseStatus;
     511: areturn
     512: getstatic     #18                 // Field TEMPORARY_REDIRECT:Lorg/jboss/netty/handler/codec/http/HttpResponseStatus;
     515: areturn
     516: getstatic     #19                 // Field BAD_REQUEST:Lorg/jboss/netty/handler/codec/http/HttpResponseStatus;
     519: areturn
     520: getstatic     #20                 // Field UNAUTHORIZED:Lorg/jboss/netty/handler/codec/http/HttpResponseStatus;
     523: areturn
     524: getstatic     #21                 // Field PAYMENT_REQUIRED:Lorg/jboss/netty/handler/codec/http/HttpResponseStatus;
     527: areturn
     528: getstatic     #22                 // Field FORBIDDEN:Lorg/jboss/netty/handler/codec/http/HttpResponseStatus;
     531: areturn
     532: getstatic     #23                 // Field NOT_FOUND:Lorg/jboss/netty/handler/codec/http/HttpResponseStatus;
     535: areturn
     536: getstatic     #24                 // Field METHOD_NOT_ALLOWED:Lorg/jboss/netty/handler/codec/http/HttpResponseStatus;
     539: areturn
     540: getstatic     #25                 // Field NOT_ACCEPTABLE:Lorg/jboss/netty/handler/codec/http/HttpResponseStatus;
     543: areturn
     544: getstatic     #26                 // Field PROXY_AUTHENTICATION_REQUIRED:Lorg/jboss/netty/handler/codec/http/HttpResponseStatus;
     547: areturn
     548: getstatic     #27                 // Field REQUEST_TIMEOUT:Lorg/jboss/netty/handler/codec/http/HttpResponseStatus;
     551: areturn
     552: getstatic     #28                 // Field CONFLICT:Lorg/jboss/netty/handler/codec/http/HttpResponseStatus;
     555: areturn
     556: getstatic     #29                 // Field GONE:Lorg/jboss/netty/handler/codec/http/HttpResponseStatus;
     559: areturn
     560: getstatic     #30                 // Field LENGTH_REQUIRED:Lorg/jboss/netty/handler/codec/http/HttpResponseStatus;
     563: areturn
     564: getstatic     #31                 // Field PRECONDITION_FAILED:Lorg/jboss/netty/handler/codec/http/HttpResponseStatus;
     567: areturn
     568: getstatic     #32                 // Field REQUEST_ENTITY_TOO_LARGE:Lorg/jboss/netty/handler/codec/http/HttpResponseStatus;
     571: areturn
     572: getstatic     #33                 // Field REQUEST_URI_TOO_LONG:Lorg/jboss/netty/handler/codec/http/HttpResponseStatus;
     575: areturn
     576: getstatic     #34                 // Field UNSUPPORTED_MEDIA_TYPE:Lorg/jboss/netty/handler/codec/http/HttpResponseStatus;
     579: areturn
     580: getstatic     #35                 // Field REQUESTED_RANGE_NOT_SATISFIABLE:Lorg/jboss/netty/handler/codec/http/HttpResponseStatus;
     583: areturn
     584: getstatic     #36                 // Field EXPECTATION_FAILED:Lorg/jboss/netty/handler/codec/http/HttpResponseStatus;
     587: areturn
     588: getstatic     #37                 // Field UNPROCESSABLE_ENTITY:Lorg/jboss/netty/handler/codec/http/HttpResponseStatus;
     591: areturn
     592: getstatic     #38                 // Field LOCKED:Lorg/jboss/netty/handler/codec/http/HttpResponseStatus;
     595: areturn
     596: getstatic     #39                 // Field FAILED_DEPENDENCY:Lorg/jboss/netty/handler/codec/http/HttpResponseStatus;
     599: areturn
     600: getstatic     #40                 // Field UNORDERED_COLLECTION:Lorg/jboss/netty/handler/codec/http/HttpResponseStatus;
     603: areturn
     604: getstatic     #41                 // Field UPGRADE_REQUIRED:Lorg/jboss/netty/handler/codec/http/HttpResponseStatus;
     607: areturn
     608: getstatic     #42                 // Field PRECONDITION_REQUIRED:Lorg/jboss/netty/handler/codec/http/HttpResponseStatus;
     611: areturn
     612: getstatic     #43                 // Field TOO_MANY_REQUESTS:Lorg/jboss/netty/handler/codec/http/HttpResponseStatus;
     615: areturn
     616: getstatic     #44                 // Field REQUEST_HEADER_FIELDS_TOO_LARGE:Lorg/jboss/netty/handler/codec/http/HttpResponseStatus;
     619: areturn
     620: getstatic     #45                 // Field INTERNAL_SERVER_ERROR:Lorg/jboss/netty/handler/codec/http/HttpResponseStatus;
     623: areturn
     624: getstatic     #46                 // Field NOT_IMPLEMENTED:Lorg/jboss/netty/handler/codec/http/HttpResponseStatus;
     627: areturn
     628: getstatic     #47                 // Field BAD_GATEWAY:Lorg/jboss/netty/handler/codec/http/HttpResponseStatus;
     631: areturn
     632: getstatic     #48                 // Field SERVICE_UNAVAILABLE:Lorg/jboss/netty/handler/codec/http/HttpResponseStatus;
     635: areturn
     636: getstatic     #49                 // Field GATEWAY_TIMEOUT:Lorg/jboss/netty/handler/codec/http/HttpResponseStatus;
     639: areturn
     640: getstatic     #50                 // Field HTTP_VERSION_NOT_SUPPORTED:Lorg/jboss/netty/handler/codec/http/HttpResponseStatus;
     643: areturn
     644: getstatic     #51                 // Field VARIANT_ALSO_NEGOTIATES:Lorg/jboss/netty/handler/codec/http/HttpResponseStatus;
     647: areturn
     648: getstatic     #52                 // Field INSUFFICIENT_STORAGE:Lorg/jboss/netty/handler/codec/http/HttpResponseStatus;
     651: areturn
     652: getstatic     #53                 // Field NOT_EXTENDED:Lorg/jboss/netty/handler/codec/http/HttpResponseStatus;
     655: areturn
     656: getstatic     #54                 // Field NETWORK_AUTHENTICATION_REQUIRED:Lorg/jboss/netty/handler/codec/http/HttpResponseStatus;
     659: areturn
     660: iload_0
     661: bipush        100
     663: if_icmpge     672
     666: ldc           #55                 // String Unknown Status
     668: astore_1
     669: goto          740
     672: iload_0
     673: sipush        200
     676: if_icmpge     685
     679: ldc           #56                 // String Informational
     681: astore_1
     682: goto          740
     685: iload_0
     686: sipush        300
     689: if_icmpge     698
     692: ldc           #57                 // String Successful
     694: astore_1
     695: goto          740
     698: iload_0
     699: sipush        400
     702: if_icmpge     711
     705: ldc           #58                 // String Redirection
     707: astore_1
     708: goto          740
     711: iload_0
     712: sipush        500
     715: if_icmpge     724
     718: ldc           #59                 // String Client Error
     720: astore_1
     721: goto          740
     724: iload_0
     725: sipush        600
     728: if_icmpge     737
     731: ldc           #60                 // String Server Error
     733: astore_1
     734: goto          740
     737: ldc           #55                 // String Unknown Status
     739: astore_1
     740: new           #61                 // class org/jboss/netty/handler/codec/http/HttpResponseStatus
     743: dup
     744: iload_0
     745: new           #62                 // class java/lang/StringBuilder
     748: dup
     749: invokespecial #63                 // Method java/lang/StringBuilder."<init>":()V
     752: aload_1
     753: invokevirtual #64                 // Method java/lang/StringBuilder.append:(Ljava/lang/String;)Ljava/lang/StringBuilder;
     756: ldc           #65                 // String  (
     758: invokevirtual #64                 // Method java/lang/StringBuilder.append:(Ljava/lang/String;)Ljava/lang/StringBuilder;
     761: iload_0
     762: invokevirtual #66                 // Method java/lang/StringBuilder.append:(I)Ljava/lang/StringBuilder;
     765: bipush        41
     767: invokevirtual #67                 // Method java/lang/StringBuilder.append:(C)Ljava/lang/StringBuilder;
     770: invokevirtual #68                 // Method java/lang/StringBuilder.toString:()Ljava/lang/String;
     773: invokespecial #69                 // Method "<init>":(ILjava/lang/String;)V
     776: areturn

  public org.jboss.netty.handler.codec.http.HttpResponseStatus(int, java.lang.String);
    Code:
       0: aload_0
       1: invokespecial #70                 // Method java/lang/Object."<init>":()V
       4: iload_1
       5: ifge          40
       8: new           #71                 // class java/lang/IllegalArgumentException
      11: dup
      12: new           #62                 // class java/lang/StringBuilder
      15: dup
      16: invokespecial #63                 // Method java/lang/StringBuilder."<init>":()V
      19: ldc           #72                 // String code:
      21: invokevirtual #64                 // Method java/lang/StringBuilder.append:(Ljava/lang/String;)Ljava/lang/StringBuilder;
      24: iload_1
      25: invokevirtual #66                 // Method java/lang/StringBuilder.append:(I)Ljava/lang/StringBuilder;
      28: ldc           #73                 // String  (expected: 0+)
      30: invokevirtual #64                 // Method java/lang/StringBuilder.append:(Ljava/lang/String;)Ljava/lang/StringBuilder;
      33: invokevirtual #68                 // Method java/lang/StringBuilder.toString:()Ljava/lang/String;
      36: invokespecial #74                 // Method java/lang/IllegalArgumentException."<init>":(Ljava/lang/String;)V
      39: athrow
      40: aload_2
      41: ifnonnull     54
      44: new           #75                 // class java/lang/NullPointerException
      47: dup
      48: ldc           #76                 // String reasonPhrase
      50: invokespecial #77                 // Method java/lang/NullPointerException."<init>":(Ljava/lang/String;)V
      53: athrow
      54: iconst_0
      55: istore_3
      56: iload_3
      57: aload_2
      58: invokevirtual #78                 // Method java/lang/String.length:()I
      61: if_icmpge     133
      64: aload_2
      65: iload_3
      66: invokevirtual #79                 // Method java/lang/String.charAt:(I)C
      69: istore        4
      71: iload         4
      73: lookupswitch  { // 2
                    10: 100
                    13: 100
               default: 127
          }
     100: new           #71                 // class java/lang/IllegalArgumentException
     103: dup
     104: new           #62                 // class java/lang/StringBuilder
     107: dup
     108: invokespecial #63                 // Method java/lang/StringBuilder."<init>":()V
     111: ldc           #80                 // String reasonPhrase contains one of the following prohibited characters: \\r\\n:
     113: invokevirtual #64                 // Method java/lang/StringBuilder.append:(Ljava/lang/String;)Ljava/lang/StringBuilder;
     116: aload_2
     117: invokevirtual #64                 // Method java/lang/StringBuilder.append:(Ljava/lang/String;)Ljava/lang/StringBuilder;
     120: invokevirtual #68                 // Method java/lang/StringBuilder.toString:()Ljava/lang/String;
     123: invokespecial #74                 // Method java/lang/IllegalArgumentException."<init>":(Ljava/lang/String;)V
     126: athrow
     127: iinc          3, 1
     130: goto          56
     133: aload_0
     134: iload_1
     135: putfield      #81                 // Field code:I
     138: aload_0
     139: aload_2
     140: putfield      #82                 // Field reasonPhrase:Ljava/lang/String;
     143: return

  public int getCode();
    Code:
       0: aload_0
       1: getfield      #81                 // Field code:I
       4: ireturn

  public java.lang.String getReasonPhrase();
    Code:
       0: aload_0
       1: getfield      #82                 // Field reasonPhrase:Ljava/lang/String;
       4: areturn

  public int hashCode();
    Code:
       0: aload_0
       1: invokevirtual #83                 // Method getCode:()I
       4: ireturn

  public boolean equals(java.lang.Object);
    Code:
       0: aload_1
       1: instanceof    #61                 // class org/jboss/netty/handler/codec/http/HttpResponseStatus
       4: ifne          9
       7: iconst_0
       8: ireturn
       9: aload_0
      10: invokevirtual #83                 // Method getCode:()I
      13: aload_1
      14: checkcast     #61                 // class org/jboss/netty/handler/codec/http/HttpResponseStatus
      17: invokevirtual #83                 // Method getCode:()I
      20: if_icmpne     27
      23: iconst_1
      24: goto          28
      27: iconst_0
      28: ireturn

  public int compareTo(org.jboss.netty.handler.codec.http.HttpResponseStatus);
    Code:
       0: aload_0
       1: invokevirtual #83                 // Method getCode:()I
       4: aload_1
       5: invokevirtual #83                 // Method getCode:()I
       8: isub
       9: ireturn

  public java.lang.String toString();
    Code:
       0: new           #62                 // class java/lang/StringBuilder
       3: dup
       4: aload_0
       5: getfield      #82                 // Field reasonPhrase:Ljava/lang/String;
       8: invokevirtual #78                 // Method java/lang/String.length:()I
      11: iconst_5
      12: iadd
      13: invokespecial #84                 // Method java/lang/StringBuilder."<init>":(I)V
      16: astore_1
      17: aload_1
      18: aload_0
      19: getfield      #81                 // Field code:I
      22: invokevirtual #66                 // Method java/lang/StringBuilder.append:(I)Ljava/lang/StringBuilder;
      25: pop
      26: aload_1
      27: bipush        32
      29: invokevirtual #67                 // Method java/lang/StringBuilder.append:(C)Ljava/lang/StringBuilder;
      32: pop
      33: aload_1
      34: aload_0
      35: getfield      #82                 // Field reasonPhrase:Ljava/lang/String;
      38: invokevirtual #64                 // Method java/lang/StringBuilder.append:(Ljava/lang/String;)Ljava/lang/StringBuilder;
      41: pop
      42: aload_1
      43: invokevirtual #68                 // Method java/lang/StringBuilder.toString:()Ljava/lang/String;
      46: areturn

  public int compareTo(java.lang.Object);
    Code:
       0: aload_0
       1: aload_1
       2: checkcast     #61                 // class org/jboss/netty/handler/codec/http/HttpResponseStatus
       5: invokevirtual #85                 // Method compareTo:(Lorg/jboss/netty/handler/codec/http/HttpResponseStatus;)I
       8: ireturn

  static {};
    Code:
       0: new           #61                 // class org/jboss/netty/handler/codec/http/HttpResponseStatus
       3: dup
       4: bipush        100
       6: ldc           #86                 // String Continue
       8: invokespecial #69                 // Method "<init>":(ILjava/lang/String;)V
      11: putstatic     #1                  // Field CONTINUE:Lorg/jboss/netty/handler/codec/http/HttpResponseStatus;
      14: new           #61                 // class org/jboss/netty/handler/codec/http/HttpResponseStatus
      17: dup
      18: bipush        101
      20: ldc           #87                 // String Switching Protocols
      22: invokespecial #69                 // Method "<init>":(ILjava/lang/String;)V
      25: putstatic     #2                  // Field SWITCHING_PROTOCOLS:Lorg/jboss/netty/handler/codec/http/HttpResponseStatus;
      28: new           #61                 // class org/jboss/netty/handler/codec/http/HttpResponseStatus
      31: dup
      32: bipush        102
      34: ldc           #88                 // String Processing
      36: invokespecial #69                 // Method "<init>":(ILjava/lang/String;)V
      39: putstatic     #3                  // Field PROCESSING:Lorg/jboss/netty/handler/codec/http/HttpResponseStatus;
      42: new           #61                 // class org/jboss/netty/handler/codec/http/HttpResponseStatus
      45: dup
      46: sipush        200
      49: ldc           #89                 // String OK
      51: invokespecial #69                 // Method "<init>":(ILjava/lang/String;)V
      54: putstatic     #4                  // Field OK:Lorg/jboss/netty/handler/codec/http/HttpResponseStatus;
      57: new           #61                 // class org/jboss/netty/handler/codec/http/HttpResponseStatus
      60: dup
      61: sipush        201
      64: ldc           #90                 // String Created
      66: invokespecial #69                 // Method "<init>":(ILjava/lang/String;)V
      69: putstatic     #5                  // Field CREATED:Lorg/jboss/netty/handler/codec/http/HttpResponseStatus;
      72: new           #61                 // class org/jboss/netty/handler/codec/http/HttpResponseStatus
      75: dup
      76: sipush        202
      79: ldc           #91                 // String Accepted
      81: invokespecial #69                 // Method "<init>":(ILjava/lang/String;)V
      84: putstatic     #6                  // Field ACCEPTED:Lorg/jboss/netty/handler/codec/http/HttpResponseStatus;
      87: new           #61                 // class org/jboss/netty/handler/codec/http/HttpResponseStatus
      90: dup
      91: sipush        203
      94: ldc           #92                 // String Non-Authoritative Information
      96: invokespecial #69                 // Method "<init>":(ILjava/lang/String;)V
      99: putstatic     #7                  // Field NON_AUTHORITATIVE_INFORMATION:Lorg/jboss/netty/handler/codec/http/HttpResponseStatus;
     102: new           #61                 // class org/jboss/netty/handler/codec/http/HttpResponseStatus
     105: dup
     106: sipush        204
     109: ldc           #93                 // String No Content
     111: invokespecial #69                 // Method "<init>":(ILjava/lang/String;)V
     114: putstatic     #8                  // Field NO_CONTENT:Lorg/jboss/netty/handler/codec/http/HttpResponseStatus;
     117: new           #61                 // class org/jboss/netty/handler/codec/http/HttpResponseStatus
     120: dup
     121: sipush        205
     124: ldc           #94                 // String Reset Content
     126: invokespecial #69                 // Method "<init>":(ILjava/lang/String;)V
     129: putstatic     #9                  // Field RESET_CONTENT:Lorg/jboss/netty/handler/codec/http/HttpResponseStatus;
     132: new           #61                 // class org/jboss/netty/handler/codec/http/HttpResponseStatus
     135: dup
     136: sipush        206
     139: ldc           #95                 // String Partial Content
     141: invokespecial #69                 // Method "<init>":(ILjava/lang/String;)V
     144: putstatic     #10                 // Field PARTIAL_CONTENT:Lorg/jboss/netty/handler/codec/http/HttpResponseStatus;
     147: new           #61                 // class org/jboss/netty/handler/codec/http/HttpResponseStatus
     150: dup
     151: sipush        207
     154: ldc           #96                 // String Multi-Status
     156: invokespecial #69                 // Method "<init>":(ILjava/lang/String;)V
     159: putstatic     #11                 // Field MULTI_STATUS:Lorg/jboss/netty/handler/codec/http/HttpResponseStatus;
     162: new           #61                 // class org/jboss/netty/handler/codec/http/HttpResponseStatus
     165: dup
     166: sipush        300
     169: ldc           #97                 // String Multiple Choices
     171: invokespecial #69                 // Method "<init>":(ILjava/lang/String;)V
     174: putstatic     #12                 // Field MULTIPLE_CHOICES:Lorg/jboss/netty/handler/codec/http/HttpResponseStatus;
     177: new           #61                 // class org/jboss/netty/handler/codec/http/HttpResponseStatus
     180: dup
     181: sipush        301
     184: ldc           #98                 // String Moved Permanently
     186: invokespecial #69                 // Method "<init>":(ILjava/lang/String;)V
     189: putstatic     #13                 // Field MOVED_PERMANENTLY:Lorg/jboss/netty/handler/codec/http/HttpResponseStatus;
     192: new           #61                 // class org/jboss/netty/handler/codec/http/HttpResponseStatus
     195: dup
     196: sipush        302
     199: ldc           #99                 // String Found
     201: invokespecial #69                 // Method "<init>":(ILjava/lang/String;)V
     204: putstatic     #14                 // Field FOUND:Lorg/jboss/netty/handler/codec/http/HttpResponseStatus;
     207: new           #61                 // class org/jboss/netty/handler/codec/http/HttpResponseStatus
     210: dup
     211: sipush        303
     214: ldc           #100                // String See Other
     216: invokespecial #69                 // Method "<init>":(ILjava/lang/String;)V
     219: putstatic     #15                 // Field SEE_OTHER:Lorg/jboss/netty/handler/codec/http/HttpResponseStatus;
     222: new           #61                 // class org/jboss/netty/handler/codec/http/HttpResponseStatus
     225: dup
     226: sipush        304
     229: ldc           #101                // String Not Modified
     231: invokespecial #69                 // Method "<init>":(ILjava/lang/String;)V
     234: putstatic     #16                 // Field NOT_MODIFIED:Lorg/jboss/netty/handler/codec/http/HttpResponseStatus;
     237: new           #61                 // class org/jboss/netty/handler/codec/http/HttpResponseStatus
     240: dup
     241: sipush        305
     244: ldc           #102                // String Use Proxy
     246: invokespecial #69                 // Method "<init>":(ILjava/lang/String;)V
     249: putstatic     #17                 // Field USE_PROXY:Lorg/jboss/netty/handler/codec/http/HttpResponseStatus;
     252: new           #61                 // class org/jboss/netty/handler/codec/http/HttpResponseStatus
     255: dup
     256: sipush        307
     259: ldc           #103                // String Temporary Redirect
     261: invokespecial #69                 // Method "<init>":(ILjava/lang/String;)V
     264: putstatic     #18                 // Field TEMPORARY_REDIRECT:Lorg/jboss/netty/handler/codec/http/HttpResponseStatus;
     267: new           #61                 // class org/jboss/netty/handler/codec/http/HttpResponseStatus
     270: dup
     271: sipush        400
     274: ldc           #104                // String Bad Request
     276: invokespecial #69                 // Method "<init>":(ILjava/lang/String;)V
     279: putstatic     #19                 // Field BAD_REQUEST:Lorg/jboss/netty/handler/codec/http/HttpResponseStatus;
     282: new           #61                 // class org/jboss/netty/handler/codec/http/HttpResponseStatus
     285: dup
     286: sipush        401
     289: ldc           #105                // String Unauthorized
     291: invokespecial #69                 // Method "<init>":(ILjava/lang/String;)V
     294: putstatic     #20                 // Field UNAUTHORIZED:Lorg/jboss/netty/handler/codec/http/HttpResponseStatus;
     297: new           #61                 // class org/jboss/netty/handler/codec/http/HttpResponseStatus
     300: dup
     301: sipush        402
     304: ldc           #106                // String Payment Required
     306: invokespecial #69                 // Method "<init>":(ILjava/lang/String;)V
     309: putstatic     #21                 // Field PAYMENT_REQUIRED:Lorg/jboss/netty/handler/codec/http/HttpResponseStatus;
     312: new           #61                 // class org/jboss/netty/handler/codec/http/HttpResponseStatus
     315: dup
     316: sipush        403
     319: ldc           #107                // String Forbidden
     321: invokespecial #69                 // Method "<init>":(ILjava/lang/String;)V
     324: putstatic     #22                 // Field FORBIDDEN:Lorg/jboss/netty/handler/codec/http/HttpResponseStatus;
     327: new           #61                 // class org/jboss/netty/handler/codec/http/HttpResponseStatus
     330: dup
     331: sipush        404
     334: ldc           #108                // String Not Found
     336: invokespecial #69                 // Method "<init>":(ILjava/lang/String;)V
     339: putstatic     #23                 // Field NOT_FOUND:Lorg/jboss/netty/handler/codec/http/HttpResponseStatus;
     342: new           #61                 // class org/jboss/netty/handler/codec/http/HttpResponseStatus
     345: dup
     346: sipush        405
     349: ldc           #109                // String Method Not Allowed
     351: invokespecial #69                 // Method "<init>":(ILjava/lang/String;)V
     354: putstatic     #24                 // Field METHOD_NOT_ALLOWED:Lorg/jboss/netty/handler/codec/http/HttpResponseStatus;
     357: new           #61                 // class org/jboss/netty/handler/codec/http/HttpResponseStatus
     360: dup
     361: sipush        406
     364: ldc           #110                // String Not Acceptable
     366: invokespecial #69                 // Method "<init>":(ILjava/lang/String;)V
     369: putstatic     #25                 // Field NOT_ACCEPTABLE:Lorg/jboss/netty/handler/codec/http/HttpResponseStatus;
     372: new           #61                 // class org/jboss/netty/handler/codec/http/HttpResponseStatus
     375: dup
     376: sipush        407
     379: ldc           #111                // String Proxy Authentication Required
     381: invokespecial #69                 // Method "<init>":(ILjava/lang/String;)V
     384: putstatic     #26                 // Field PROXY_AUTHENTICATION_REQUIRED:Lorg/jboss/netty/handler/codec/http/HttpResponseStatus;
     387: new           #61                 // class org/jboss/netty/handler/codec/http/HttpResponseStatus
     390: dup
     391: sipush        408
     394: ldc           #112                // String Request Timeout
     396: invokespecial #69                 // Method "<init>":(ILjava/lang/String;)V
     399: putstatic     #27                 // Field REQUEST_TIMEOUT:Lorg/jboss/netty/handler/codec/http/HttpResponseStatus;
     402: new           #61                 // class org/jboss/netty/handler/codec/http/HttpResponseStatus
     405: dup
     406: sipush        409
     409: ldc           #113                // String Conflict
     411: invokespecial #69                 // Method "<init>":(ILjava/lang/String;)V
     414: putstatic     #28                 // Field CONFLICT:Lorg/jboss/netty/handler/codec/http/HttpResponseStatus;
     417: new           #61                 // class org/jboss/netty/handler/codec/http/HttpResponseStatus
     420: dup
     421: sipush        410
     424: ldc           #114                // String Gone
     426: invokespecial #69                 // Method "<init>":(ILjava/lang/String;)V
     429: putstatic     #29                 // Field GONE:Lorg/jboss/netty/handler/codec/http/HttpResponseStatus;
     432: new           #61                 // class org/jboss/netty/handler/codec/http/HttpResponseStatus
     435: dup
     436: sipush        411
     439: ldc           #115                // String Length Required
     441: invokespecial #69                 // Method "<init>":(ILjava/lang/String;)V
     444: putstatic     #30                 // Field LENGTH_REQUIRED:Lorg/jboss/netty/handler/codec/http/HttpResponseStatus;
     447: new           #61                 // class org/jboss/netty/handler/codec/http/HttpResponseStatus
     450: dup
     451: sipush        412
     454: ldc           #116                // String Precondition Failed
     456: invokespecial #69                 // Method "<init>":(ILjava/lang/String;)V
     459: putstatic     #31                 // Field PRECONDITION_FAILED:Lorg/jboss/netty/handler/codec/http/HttpResponseStatus;
     462: new           #61                 // class org/jboss/netty/handler/codec/http/HttpResponseStatus
     465: dup
     466: sipush        413
     469: ldc           #117                // String Request Entity Too Large
     471: invokespecial #69                 // Method "<init>":(ILjava/lang/String;)V
     474: putstatic     #32                 // Field REQUEST_ENTITY_TOO_LARGE:Lorg/jboss/netty/handler/codec/http/HttpResponseStatus;
     477: new           #61                 // class org/jboss/netty/handler/codec/http/HttpResponseStatus
     480: dup
     481: sipush        414
     484: ldc           #118                // String Request-URI Too Long
     486: invokespecial #69                 // Method "<init>":(ILjava/lang/String;)V
     489: putstatic     #33                 // Field REQUEST_URI_TOO_LONG:Lorg/jboss/netty/handler/codec/http/HttpResponseStatus;
     492: new           #61                 // class org/jboss/netty/handler/codec/http/HttpResponseStatus
     495: dup
     496: sipush        415
     499: ldc           #119                // String Unsupported Media Type
     501: invokespecial #69                 // Method "<init>":(ILjava/lang/String;)V
     504: putstatic     #34                 // Field UNSUPPORTED_MEDIA_TYPE:Lorg/jboss/netty/handler/codec/http/HttpResponseStatus;
     507: new           #61                 // class org/jboss/netty/handler/codec/http/HttpResponseStatus
     510: dup
     511: sipush        416
     514: ldc           #120                // String Requested Range Not Satisfiable
     516: invokespecial #69                 // Method "<init>":(ILjava/lang/String;)V
     519: putstatic     #35                 // Field REQUESTED_RANGE_NOT_SATISFIABLE:Lorg/jboss/netty/handler/codec/http/HttpResponseStatus;
     522: new           #61                 // class org/jboss/netty/handler/codec/http/HttpResponseStatus
     525: dup
     526: sipush        417
     529: ldc           #121                // String Expectation Failed
     531: invokespecial #69                 // Method "<init>":(ILjava/lang/String;)V
     534: putstatic     #36                 // Field EXPECTATION_FAILED:Lorg/jboss/netty/handler/codec/http/HttpResponseStatus;
     537: new           #61                 // class org/jboss/netty/handler/codec/http/HttpResponseStatus
     540: dup
     541: sipush        422
     544: ldc           #122                // String Unprocessable Entity
     546: invokespecial #69                 // Method "<init>":(ILjava/lang/String;)V
     549: putstatic     #37                 // Field UNPROCESSABLE_ENTITY:Lorg/jboss/netty/handler/codec/http/HttpResponseStatus;
     552: new           #61                 // class org/jboss/netty/handler/codec/http/HttpResponseStatus
     555: dup
     556: sipush        423
     559: ldc           #123                // String Locked
     561: invokespecial #69                 // Method "<init>":(ILjava/lang/String;)V
     564: putstatic     #38                 // Field LOCKED:Lorg/jboss/netty/handler/codec/http/HttpResponseStatus;
     567: new           #61                 // class org/jboss/netty/handler/codec/http/HttpResponseStatus
     570: dup
     571: sipush        424
     574: ldc           #124                // String Failed Dependency
     576: invokespecial #69                 // Method "<init>":(ILjava/lang/String;)V
     579: putstatic     #39                 // Field FAILED_DEPENDENCY:Lorg/jboss/netty/handler/codec/http/HttpResponseStatus;
     582: new           #61                 // class org/jboss/netty/handler/codec/http/HttpResponseStatus
     585: dup
     586: sipush        425
     589: ldc           #125                // String Unordered Collection
     591: invokespecial #69                 // Method "<init>":(ILjava/lang/String;)V
     594: putstatic     #40                 // Field UNORDERED_COLLECTION:Lorg/jboss/netty/handler/codec/http/HttpResponseStatus;
     597: new           #61                 // class org/jboss/netty/handler/codec/http/HttpResponseStatus
     600: dup
     601: sipush        426
     604: ldc           #126                // String Upgrade Required
     606: invokespecial #69                 // Method "<init>":(ILjava/lang/String;)V
     609: putstatic     #41                 // Field UPGRADE_REQUIRED:Lorg/jboss/netty/handler/codec/http/HttpResponseStatus;
     612: new           #61                 // class org/jboss/netty/handler/codec/http/HttpResponseStatus
     615: dup
     616: sipush        428
     619: ldc           #127                // String Precondition Required
     621: invokespecial #69                 // Method "<init>":(ILjava/lang/String;)V
     624: putstatic     #42                 // Field PRECONDITION_REQUIRED:Lorg/jboss/netty/handler/codec/http/HttpResponseStatus;
     627: new           #61                 // class org/jboss/netty/handler/codec/http/HttpResponseStatus
     630: dup
     631: sipush        429
     634: ldc           #128                // String Too Many Requests
     636: invokespecial #69                 // Method "<init>":(ILjava/lang/String;)V
     639: putstatic     #43                 // Field TOO_MANY_REQUESTS:Lorg/jboss/netty/handler/codec/http/HttpResponseStatus;
     642: new           #61                 // class org/jboss/netty/handler/codec/http/HttpResponseStatus
     645: dup
     646: sipush        431
     649: ldc           #129                // String Request Header Fields Too Large
     651: invokespecial #69                 // Method "<init>":(ILjava/lang/String;)V
     654: putstatic     #44                 // Field REQUEST_HEADER_FIELDS_TOO_LARGE:Lorg/jboss/netty/handler/codec/http/HttpResponseStatus;
     657: new           #61                 // class org/jboss/netty/handler/codec/http/HttpResponseStatus
     660: dup
     661: sipush        500
     664: ldc           #130                // String Internal Server Error
     666: invokespecial #69                 // Method "<init>":(ILjava/lang/String;)V
     669: putstatic     #45                 // Field INTERNAL_SERVER_ERROR:Lorg/jboss/netty/handler/codec/http/HttpResponseStatus;
     672: new           #61                 // class org/jboss/netty/handler/codec/http/HttpResponseStatus
     675: dup
     676: sipush        501
     679: ldc           #131                // String Not Implemented
     681: invokespecial #69                 // Method "<init>":(ILjava/lang/String;)V
     684: putstatic     #46                 // Field NOT_IMPLEMENTED:Lorg/jboss/netty/handler/codec/http/HttpResponseStatus;
     687: new           #61                 // class org/jboss/netty/handler/codec/http/HttpResponseStatus
     690: dup
     691: sipush        502
     694: ldc           #132                // String Bad Gateway
     696: invokespecial #69                 // Method "<init>":(ILjava/lang/String;)V
     699: putstatic     #47                 // Field BAD_GATEWAY:Lorg/jboss/netty/handler/codec/http/HttpResponseStatus;
     702: new           #61                 // class org/jboss/netty/handler/codec/http/HttpResponseStatus
     705: dup
     706: sipush        503
     709: ldc           #133                // String Service Unavailable
     711: invokespecial #69                 // Method "<init>":(ILjava/lang/String;)V
     714: putstatic     #48                 // Field SERVICE_UNAVAILABLE:Lorg/jboss/netty/handler/codec/http/HttpResponseStatus;
     717: new           #61                 // class org/jboss/netty/handler/codec/http/HttpResponseStatus
     720: dup
     721: sipush        504
     724: ldc           #134                // String Gateway Timeout
     726: invokespecial #69                 // Method "<init>":(ILjava/lang/String;)V
     729: putstatic     #49                 // Field GATEWAY_TIMEOUT:Lorg/jboss/netty/handler/codec/http/HttpResponseStatus;
     732: new           #61                 // class org/jboss/netty/handler/codec/http/HttpResponseStatus
     735: dup
     736: sipush        505
     739: ldc           #135                // String HTTP Version Not Supported
     741: invokespecial #69                 // Method "<init>":(ILjava/lang/String;)V
     744: putstatic     #50                 // Field HTTP_VERSION_NOT_SUPPORTED:Lorg/jboss/netty/handler/codec/http/HttpResponseStatus;
     747: new           #61                 // class org/jboss/netty/handler/codec/http/HttpResponseStatus
     750: dup
     751: sipush        506
     754: ldc           #136                // String Variant Also Negotiates
     756: invokespecial #69                 // Method "<init>":(ILjava/lang/String;)V
     759: putstatic     #51                 // Field VARIANT_ALSO_NEGOTIATES:Lorg/jboss/netty/handler/codec/http/HttpResponseStatus;
     762: new           #61                 // class org/jboss/netty/handler/codec/http/HttpResponseStatus
     765: dup
     766: sipush        507
     769: ldc           #137                // String Insufficient Storage
     771: invokespecial #69                 // Method "<init>":(ILjava/lang/String;)V
     774: putstatic     #52                 // Field INSUFFICIENT_STORAGE:Lorg/jboss/netty/handler/codec/http/HttpResponseStatus;
     777: new           #61                 // class org/jboss/netty/handler/codec/http/HttpResponseStatus
     780: dup
     781: sipush        510
     784: ldc           #138                // String Not Extended
     786: invokespecial #69                 // Method "<init>":(ILjava/lang/String;)V
     789: putstatic     #53                 // Field NOT_EXTENDED:Lorg/jboss/netty/handler/codec/http/HttpResponseStatus;
     792: new           #61                 // class org/jboss/netty/handler/codec/http/HttpResponseStatus
     795: dup
     796: sipush        511
     799: ldc           #139                // String Network Authentication Required
     801: invokespecial #69                 // Method "<init>":(ILjava/lang/String;)V
     804: putstatic     #54                 // Field NETWORK_AUTHENTICATION_REQUIRED:Lorg/jboss/netty/handler/codec/http/HttpResponseStatus;
     807: return
}
