Compiled from "HttpRequestDecoder.java"
public class org.jboss.netty.handler.codec.http.HttpRequestDecoder extends org.jboss.netty.handler.codec.http.HttpMessageDecoder {
  public org.jboss.netty.handler.codec.http.HttpRequestDecoder();
    Code:
       0: aload_0
       1: invokespecial #1                  // Method org/jboss/netty/handler/codec/http/HttpMessageDecoder."<init>":()V
       4: return

  public org.jboss.netty.handler.codec.http.HttpRequestDecoder(int, int, int);
    Code:
       0: aload_0
       1: iload_1
       2: iload_2
       3: iload_3
       4: invokespecial #2                  // Method org/jboss/netty/handler/codec/http/HttpMessageDecoder."<init>":(III)V
       7: return

  protected org.jboss.netty.handler.codec.http.HttpMessage createMessage(java.lang.String[]) throws java.lang.Exception;
    Code:
       0: new           #3                  // class org/jboss/netty/handler/codec/http/DefaultHttpRequest
       3: dup
       4: aload_1
       5: iconst_2
       6: aaload
       7: invokestatic  #4                  // Method org/jboss/netty/handler/codec/http/HttpVersion.valueOf:(Ljava/lang/String;)Lorg/jboss/netty/handler/codec/http/HttpVersion;
      10: aload_1
      11: iconst_0
      12: aaload
      13: invokestatic  #5                  // Method org/jboss/netty/handler/codec/http/HttpMethod.valueOf:(Ljava/lang/String;)Lorg/jboss/netty/handler/codec/http/HttpMethod;
      16: aload_1
      17: iconst_1
      18: aaload
      19: invokespecial #6                  // Method org/jboss/netty/handler/codec/http/DefaultHttpRequest."<init>":(Lorg/jboss/netty/handler/codec/http/HttpVersion;Lorg/jboss/netty/handler/codec/http/HttpMethod;Ljava/lang/String;)V
      22: areturn

  protected boolean isDecodingRequest();
    Code:
       0: iconst_1
       1: ireturn
}
