Compiled from "NonTerminalAroundInvokeInvocationContext.java"
class org.jboss.weld.interceptor.proxy.NonTerminalAroundInvokeInvocationContext extends org.jboss.weld.interceptor.proxy.AroundInvokeInvocationContext {
  private final int position;

  private final java.util.List<org.jboss.weld.interceptor.proxy.InterceptorMethodInvocation> chain;

  public org.jboss.weld.interceptor.proxy.NonTerminalAroundInvokeInvocationContext(java.lang.Object, java.lang.reflect.Method, java.lang.reflect.Method, java.lang.Object[], java.util.List<org.jboss.weld.interceptor.proxy.InterceptorMethodInvocation>, org.jboss.weld.bean.proxy.CombinedInterceptorAndDecoratorStackMethodHandler);
    Code:
       0: aload_0
       1: aload_1
       2: aload_2
       3: aload_3
       4: aload         4
       6: new           #1                  // class java/util/HashMap
       9: dup
      10: invokespecial #2                  // Method java/util/HashMap."<init>":()V
      13: iconst_0
      14: aload         5
      16: aload         6
      18: invokespecial #3                  // Method "<init>":(Ljava/lang/Object;Ljava/lang/reflect/Method;Ljava/lang/reflect/Method;[Ljava/lang/Object;Ljava/util/Map;ILjava/util/List;Lorg/jboss/weld/bean/proxy/CombinedInterceptorAndDecoratorStackMethodHandler;)V
      21: return

  public org.jboss.weld.interceptor.proxy.NonTerminalAroundInvokeInvocationContext(org.jboss.weld.interceptor.proxy.NonTerminalAroundInvokeInvocationContext);
    Code:
       0: aload_0
       1: aload_1
       2: invokevirtual #4                  // Method getTarget:()Ljava/lang/Object;
       5: aload_1
       6: invokevirtual #5                  // Method getMethod:()Ljava/lang/reflect/Method;
       9: aload_1
      10: invokevirtual #6                  // Method getProceed:()Ljava/lang/reflect/Method;
      13: aload_1
      14: invokevirtual #7                  // Method getParameters:()[Ljava/lang/Object;
      17: aload_1
      18: getfield      #8                  // Field contextData:Ljava/util/Map;
      21: aload_1
      22: getfield      #9                  // Field position:I
      25: iconst_1
      26: iadd
      27: aload_1
      28: getfield      #10                 // Field chain:Ljava/util/List;
      31: aload_1
      32: getfield      #11                 // Field currentHandler:Lorg/jboss/weld/bean/proxy/CombinedInterceptorAndDecoratorStackMethodHandler;
      35: invokespecial #3                  // Method "<init>":(Ljava/lang/Object;Ljava/lang/reflect/Method;Ljava/lang/reflect/Method;[Ljava/lang/Object;Ljava/util/Map;ILjava/util/List;Lorg/jboss/weld/bean/proxy/CombinedInterceptorAndDecoratorStackMethodHandler;)V
      38: return

  private org.jboss.weld.interceptor.proxy.NonTerminalAroundInvokeInvocationContext(java.lang.Object, java.lang.reflect.Method, java.lang.reflect.Method, java.lang.Object[], java.util.Map<java.lang.String, java.lang.Object>, int, java.util.List<org.jboss.weld.interceptor.proxy.InterceptorMethodInvocation>, org.jboss.weld.bean.proxy.CombinedInterceptorAndDecoratorStackMethodHandler);
    Code:
       0: aload_0
       1: aload_1
       2: aload_2
       3: aload_3
       4: aload         4
       6: aload         5
       8: aload         8
      10: invokespecial #12                 // Method org/jboss/weld/interceptor/proxy/AroundInvokeInvocationContext."<init>":(Ljava/lang/Object;Ljava/lang/reflect/Method;Ljava/lang/reflect/Method;[Ljava/lang/Object;Ljava/util/Map;Lorg/jboss/weld/bean/proxy/CombinedInterceptorAndDecoratorStackMethodHandler;)V
      13: aload_0
      14: iload         6
      16: putfield      #9                  // Field position:I
      19: aload_0
      20: aload         7
      22: putfield      #10                 // Field chain:Ljava/util/List;
      25: return

  public java.lang.Object proceedInternal() throws java.lang.Exception;
    Code:
       0: aload_0
       1: invokespecial #13                 // Method createNextContext:()Ljavax/interceptor/InvocationContext;
       4: astore_1
       5: aload_0
       6: getfield      #10                 // Field chain:Ljava/util/List;
       9: aload_0
      10: getfield      #9                  // Field position:I
      13: iconst_1
      14: iadd
      15: invokeinterface #14,  2           // InterfaceMethod java/util/List.get:(I)Ljava/lang/Object;
      20: checkcast     #15                 // class org/jboss/weld/interceptor/proxy/InterceptorMethodInvocation
      23: aload_1
      24: invokeinterface #16,  2           // InterfaceMethod org/jboss/weld/interceptor/proxy/InterceptorMethodInvocation.invoke:(Ljavax/interceptor/InvocationContext;)Ljava/lang/Object;
      29: areturn

  private javax.interceptor.InvocationContext createNextContext();
    Code:
       0: aload_0
       1: getfield      #9                  // Field position:I
       4: iconst_2
       5: iadd
       6: aload_0
       7: getfield      #10                 // Field chain:Ljava/util/List;
      10: invokeinterface #17,  1           // InterfaceMethod java/util/List.size:()I
      15: if_icmpne     27
      18: new           #18                 // class org/jboss/weld/interceptor/proxy/TerminalAroundInvokeInvocationContext
      21: dup
      22: aload_0
      23: invokespecial #19                 // Method org/jboss/weld/interceptor/proxy/TerminalAroundInvokeInvocationContext."<init>":(Lorg/jboss/weld/interceptor/proxy/NonTerminalAroundInvokeInvocationContext;)V
      26: areturn
      27: new           #20                 // class org/jboss/weld/interceptor/proxy/NonTerminalAroundInvokeInvocationContext
      30: dup
      31: aload_0
      32: invokespecial #21                 // Method "<init>":(Lorg/jboss/weld/interceptor/proxy/NonTerminalAroundInvokeInvocationContext;)V
      35: areturn

  public java.lang.String toString();
    Code:
       0: new           #22                 // class java/lang/StringBuilder
       3: dup
       4: invokespecial #23                 // Method java/lang/StringBuilder."<init>":()V
       7: ldc           #24                 // String NonTerminalAroundInvokeInvocationContext [method=
       9: invokevirtual #25                 // Method java/lang/StringBuilder.append:(Ljava/lang/String;)Ljava/lang/StringBuilder;
      12: aload_0
      13: getfield      #26                 // Field method:Ljava/lang/reflect/Method;
      16: invokevirtual #27                 // Method java/lang/StringBuilder.append:(Ljava/lang/Object;)Ljava/lang/StringBuilder;
      19: ldc           #28                 // String , interceptor=
      21: invokevirtual #25                 // Method java/lang/StringBuilder.append:(Ljava/lang/String;)Ljava/lang/StringBuilder;
      24: aload_0
      25: getfield      #10                 // Field chain:Ljava/util/List;
      28: aload_0
      29: getfield      #9                  // Field position:I
      32: invokeinterface #14,  2           // InterfaceMethod java/util/List.get:(I)Ljava/lang/Object;
      37: invokevirtual #27                 // Method java/lang/StringBuilder.append:(Ljava/lang/Object;)Ljava/lang/StringBuilder;
      40: bipush        93
      42: invokevirtual #29                 // Method java/lang/StringBuilder.append:(C)Ljava/lang/StringBuilder;
      45: invokevirtual #30                 // Method java/lang/StringBuilder.toString:()Ljava/lang/String;
      48: areturn
}
