Compiled from "AbstractBsonReader.java"
public class org.bson.AbstractBsonReader$Mark implements org.bson.BsonReaderMark {
  private final org.bson.AbstractBsonReader$State state;

  private final org.bson.AbstractBsonReader$Context parentContext;

  private final org.bson.BsonContextType contextType;

  private final org.bson.BsonType currentBsonType;

  private final java.lang.String currentName;

  final org.bson.AbstractBsonReader this$0;

  protected org.bson.AbstractBsonReader$Context getParentContext();
    Code:
       0: aload_0
       1: getfield      #1                  // Field parentContext:Lorg/bson/AbstractBsonReader$Context;
       4: areturn

  protected org.bson.BsonContextType getContextType();
    Code:
       0: aload_0
       1: getfield      #2                  // Field contextType:Lorg/bson/BsonContextType;
       4: areturn

  protected org.bson.AbstractBsonReader$Mark(org.bson.AbstractBsonReader);
    Code:
       0: aload_0
       1: aload_1
       2: putfield      #3                  // Field this$0:Lorg/bson/AbstractBsonReader;
       5: aload_0
       6: invokespecial #4                  // Method java/lang/Object."<init>":()V
       9: aload_0
      10: aload_1
      11: invokestatic  #5                  // Method org/bson/AbstractBsonReader.access$000:(Lorg/bson/AbstractBsonReader;)Lorg/bson/AbstractBsonReader$State;
      14: putfield      #6                  // Field state:Lorg/bson/AbstractBsonReader$State;
      17: aload_0
      18: aload_1
      19: invokestatic  #7                  // Method org/bson/AbstractBsonReader.access$100:(Lorg/bson/AbstractBsonReader;)Lorg/bson/AbstractBsonReader$Context;
      22: invokestatic  #8                  // Method org/bson/AbstractBsonReader$Context.access$200:(Lorg/bson/AbstractBsonReader$Context;)Lorg/bson/AbstractBsonReader$Context;
      25: putfield      #1                  // Field parentContext:Lorg/bson/AbstractBsonReader$Context;
      28: aload_0
      29: aload_1
      30: invokestatic  #7                  // Method org/bson/AbstractBsonReader.access$100:(Lorg/bson/AbstractBsonReader;)Lorg/bson/AbstractBsonReader$Context;
      33: invokestatic  #9                  // Method org/bson/AbstractBsonReader$Context.access$300:(Lorg/bson/AbstractBsonReader$Context;)Lorg/bson/BsonContextType;
      36: putfield      #2                  // Field contextType:Lorg/bson/BsonContextType;
      39: aload_0
      40: aload_1
      41: invokestatic  #10                 // Method org/bson/AbstractBsonReader.access$400:(Lorg/bson/AbstractBsonReader;)Lorg/bson/BsonType;
      44: putfield      #11                 // Field currentBsonType:Lorg/bson/BsonType;
      47: aload_0
      48: aload_1
      49: invokestatic  #12                 // Method org/bson/AbstractBsonReader.access$500:(Lorg/bson/AbstractBsonReader;)Ljava/lang/String;
      52: putfield      #13                 // Field currentName:Ljava/lang/String;
      55: return

  public void reset();
    Code:
       0: aload_0
       1: getfield      #3                  // Field this$0:Lorg/bson/AbstractBsonReader;
       4: aload_0
       5: getfield      #6                  // Field state:Lorg/bson/AbstractBsonReader$State;
       8: invokestatic  #14                 // Method org/bson/AbstractBsonReader.access$002:(Lorg/bson/AbstractBsonReader;Lorg/bson/AbstractBsonReader$State;)Lorg/bson/AbstractBsonReader$State;
      11: pop
      12: aload_0
      13: getfield      #3                  // Field this$0:Lorg/bson/AbstractBsonReader;
      16: aload_0
      17: getfield      #11                 // Field currentBsonType:Lorg/bson/BsonType;
      20: invokestatic  #15                 // Method org/bson/AbstractBsonReader.access$402:(Lorg/bson/AbstractBsonReader;Lorg/bson/BsonType;)Lorg/bson/BsonType;
      23: pop
      24: aload_0
      25: getfield      #3                  // Field this$0:Lorg/bson/AbstractBsonReader;
      28: aload_0
      29: getfield      #13                 // Field currentName:Ljava/lang/String;
      32: invokestatic  #16                 // Method org/bson/AbstractBsonReader.access$502:(Lorg/bson/AbstractBsonReader;Ljava/lang/String;)Ljava/lang/String;
      35: pop
      36: return
}
