Compiled from "BsonDocument.java"
class org.bson.BsonDocument$SerializationProxy implements java.io.Serializable {
  private static final long serialVersionUID;

  private final byte[] bytes;

  org.bson.BsonDocument$SerializationProxy(org.bson.BsonDocument);
    Code:
       0: aload_0
       1: invokespecial #1                  // Method java/lang/Object."<init>":()V
       4: new           #2                  // class org/bson/io/BasicOutputBuffer
       7: dup
       8: invokespecial #3                  // Method org/bson/io/BasicOutputBuffer."<init>":()V
      11: astore_2
      12: new           #4                  // class org/bson/codecs/BsonDocumentCodec
      15: dup
      16: invokespecial #5                  // Method org/bson/codecs/BsonDocumentCodec."<init>":()V
      19: new           #6                  // class org/bson/BsonBinaryWriter
      22: dup
      23: aload_2
      24: invokespecial #7                  // Method org/bson/BsonBinaryWriter."<init>":(Lorg/bson/io/BsonOutput;)V
      27: aload_1
      28: invokestatic  #8                  // Method org/bson/codecs/EncoderContext.builder:()Lorg/bson/codecs/EncoderContext$Builder;
      31: invokevirtual #9                  // Method org/bson/codecs/EncoderContext$Builder.build:()Lorg/bson/codecs/EncoderContext;
      34: invokevirtual #10                 // Method org/bson/codecs/BsonDocumentCodec.encode:(Lorg/bson/BsonWriter;Lorg/bson/BsonDocument;Lorg/bson/codecs/EncoderContext;)V
      37: aload_0
      38: aload_2
      39: invokevirtual #11                 // Method org/bson/io/BasicOutputBuffer.size:()I
      42: newarray       byte
      44: putfield      #12                 // Field bytes:[B
      47: iconst_0
      48: istore_3
      49: aload_2
      50: invokevirtual #13                 // Method org/bson/io/BasicOutputBuffer.getByteBuffers:()Ljava/util/List;
      53: invokeinterface #14,  1           // InterfaceMethod java/util/List.iterator:()Ljava/util/Iterator;
      58: astore        4
      60: aload         4
      62: invokeinterface #15,  1           // InterfaceMethod java/util/Iterator.hasNext:()Z
      67: ifeq          124
      70: aload         4
      72: invokeinterface #16,  1           // InterfaceMethod java/util/Iterator.next:()Ljava/lang/Object;
      77: checkcast     #17                 // class org/bson/ByteBuf
      80: astore        5
      82: aload         5
      84: invokeinterface #18,  1           // InterfaceMethod org/bson/ByteBuf.array:()[B
      89: aload         5
      91: invokeinterface #19,  1           // InterfaceMethod org/bson/ByteBuf.position:()I
      96: aload_0
      97: getfield      #12                 // Field bytes:[B
     100: iload_3
     101: aload         5
     103: invokeinterface #20,  1           // InterfaceMethod org/bson/ByteBuf.limit:()I
     108: invokestatic  #21                 // Method java/lang/System.arraycopy:(Ljava/lang/Object;ILjava/lang/Object;II)V
     111: iload_3
     112: aload         5
     114: invokeinterface #19,  1           // InterfaceMethod org/bson/ByteBuf.position:()I
     119: iadd
     120: istore_3
     121: goto          60
     124: return

  private java.lang.Object readResolve();
    Code:
       0: new           #4                  // class org/bson/codecs/BsonDocumentCodec
       3: dup
       4: invokespecial #5                  // Method org/bson/codecs/BsonDocumentCodec."<init>":()V
       7: new           #22                 // class org/bson/BsonBinaryReader
      10: dup
      11: aload_0
      12: getfield      #12                 // Field bytes:[B
      15: invokestatic  #23                 // Method java/nio/ByteBuffer.wrap:([B)Ljava/nio/ByteBuffer;
      18: getstatic     #24                 // Field java/nio/ByteOrder.LITTLE_ENDIAN:Ljava/nio/ByteOrder;
      21: invokevirtual #25                 // Method java/nio/ByteBuffer.order:(Ljava/nio/ByteOrder;)Ljava/nio/ByteBuffer;
      24: invokespecial #26                 // Method org/bson/BsonBinaryReader."<init>":(Ljava/nio/ByteBuffer;)V
      27: invokestatic  #27                 // Method org/bson/codecs/DecoderContext.builder:()Lorg/bson/codecs/DecoderContext$Builder;
      30: invokevirtual #28                 // Method org/bson/codecs/DecoderContext$Builder.build:()Lorg/bson/codecs/DecoderContext;
      33: invokevirtual #29                 // Method org/bson/codecs/BsonDocumentCodec.decode:(Lorg/bson/BsonReader;Lorg/bson/codecs/DecoderContext;)Lorg/bson/BsonDocument;
      36: areturn
}
