Compiled from "Var.java"
public class org.aspectj.weaver.ast.Var extends org.aspectj.weaver.ast.Expr {
  public static final org.aspectj.weaver.ast.Var[] NONE;

  org.aspectj.weaver.ResolvedType variableType;

  public org.aspectj.weaver.ast.Var(org.aspectj.weaver.ResolvedType);
    Code:
       0: aload_0
       1: invokespecial #1                  // Method org/aspectj/weaver/ast/Expr."<init>":()V
       4: aload_0
       5: aload_1
       6: putfield      #2                  // Field variableType:Lorg/aspectj/weaver/ResolvedType;
       9: return

  public org.aspectj.weaver.ResolvedType getType();
    Code:
       0: aload_0
       1: getfield      #2                  // Field variableType:Lorg/aspectj/weaver/ResolvedType;
       4: areturn

  public java.lang.String toString();
    Code:
       0: new           #3                  // class java/lang/StringBuilder
       3: dup
       4: invokespecial #4                  // Method java/lang/StringBuilder."<init>":()V
       7: ldc           #5                  // String (Var
       9: invokevirtual #6                  // Method java/lang/StringBuilder.append:(Ljava/lang/String;)Ljava/lang/StringBuilder;
      12: aload_0
      13: getfield      #2                  // Field variableType:Lorg/aspectj/weaver/ResolvedType;
      16: invokevirtual #7                  // Method java/lang/StringBuilder.append:(Ljava/lang/Object;)Ljava/lang/StringBuilder;
      19: ldc           #8                  // String )
      21: invokevirtual #6                  // Method java/lang/StringBuilder.append:(Ljava/lang/String;)Ljava/lang/StringBuilder;
      24: invokevirtual #9                  // Method java/lang/StringBuilder.toString:()Ljava/lang/String;
      27: areturn

  public void accept(org.aspectj.weaver.ast.IExprVisitor);
    Code:
       0: aload_1
       1: aload_0
       2: invokeinterface #10,  2           // InterfaceMethod org/aspectj/weaver/ast/IExprVisitor.visit:(Lorg/aspectj/weaver/ast/Var;)V
       7: return

  public org.aspectj.weaver.ast.Var getAccessorForValue(org.aspectj.weaver.ResolvedType, java.lang.String);
    Code:
       0: new           #11                 // class java/lang/IllegalStateException
       3: dup
       4: ldc           #12                 // String Only makes sense for annotation variables
       6: invokespecial #13                 // Method java/lang/IllegalStateException."<init>":(Ljava/lang/String;)V
       9: athrow

  static {};
    Code:
       0: iconst_0
       1: anewarray     #14                 // class org/aspectj/weaver/ast/Var
       4: putstatic     #15                 // Field NONE:[Lorg/aspectj/weaver/ast/Var;
       7: return
}
