Compiled from "Billboard.java"
public abstract class be.yildiz.module.graphic.Billboard {
  private float width;

  private float height;

  private be.yildiz.common.vector.Point3D position;

  protected be.yildiz.module.graphic.Billboard();
    Code:
       0: aload_0
       1: invokespecial #1                  // Method java/lang/Object."<init>":()V
       4: aload_0
       5: getstatic     #2                  // Field be/yildiz/common/vector/Point3D.ZERO:Lbe/yildiz/common/vector/Point3D;
       8: putfield      #3                  // Field position:Lbe/yildiz/common/vector/Point3D;
      11: return

  public final void setSize(float, float);
    Code:
       0: aload_0
       1: fload_1
       2: putfield      #4                  // Field width:F
       5: aload_0
       6: fload_2
       7: putfield      #5                  // Field height:F
      10: aload_0
      11: fload_1
      12: fload_2
      13: invokevirtual #6                  // Method setSizeImpl:(FF)V
      16: return

  public final be.yildiz.common.vector.Point3D getPosition();
    Code:
       0: aload_0
       1: getfield      #3                  // Field position:Lbe/yildiz/common/vector/Point3D;
       4: areturn

  public final void setPosition(be.yildiz.common.vector.Point3D);
    Code:
       0: aload_0
       1: aload_1
       2: putfield      #3                  // Field position:Lbe/yildiz/common/vector/Point3D;
       5: aload_0
       6: aload_1
       7: invokevirtual #7                  // Method setPositionImpl:(Lbe/yildiz/common/vector/Point3D;)V
      10: return

  public final float getWidth();
    Code:
       0: aload_0
       1: getfield      #4                  // Field width:F
       4: freturn

  public final float getHeight();
    Code:
       0: aload_0
       1: getfield      #5                  // Field height:F
       4: freturn

  public abstract void setColor(be.yildiz.common.Color);

  protected abstract void setPositionImpl(be.yildiz.common.vector.Point3D);

  protected abstract void setSizeImpl(float, float);
}
