Compiled from "MaterialTechnique.java"
public abstract class be.yildiz.module.graphic.MaterialTechnique implements java.lang.Comparable<be.yildiz.module.graphic.MaterialTechnique> {
  private final java.util.List<be.yildiz.module.graphic.MaterialPass> materialPassList;

  private final int index;

  protected be.yildiz.module.graphic.MaterialTechnique(int);
    Code:
       0: aload_0
       1: invokespecial #1                  // Method java/lang/Object."<init>":()V
       4: aload_0
       5: invokestatic  #2                  // InterfaceMethod be/yildiz/common/collections/Lists.newList:()Ljava/util/List;
       8: putfield      #3                  // Field materialPassList:Ljava/util/List;
      11: aload_0
      12: iload_1
      13: putfield      #4                  // Field index:I
      16: return

  protected be.yildiz.module.graphic.MaterialTechnique(int, java.util.List<be.yildiz.module.graphic.MaterialPass>);
    Code:
       0: aload_0
       1: invokespecial #1                  // Method java/lang/Object."<init>":()V
       4: aload_0
       5: aload_2
       6: putfield      #3                  // Field materialPassList:Ljava/util/List;
       9: aload_0
      10: iload_1
      11: putfield      #4                  // Field index:I
      14: return

  public final be.yildiz.module.graphic.MaterialPass createTexturePass();
    Code:
       0: aload_0
       1: aload_0
       2: getfield      #3                  // Field materialPassList:Ljava/util/List;
       5: invokeinterface #5,  1            // InterfaceMethod java/util/List.size:()I
      10: invokevirtual #6                  // Method createPassImpl:(I)Lbe/yildiz/module/graphic/MaterialPass;
      13: astore_1
      14: aload_0
      15: getfield      #3                  // Field materialPassList:Ljava/util/List;
      18: aload_1
      19: invokeinterface #7,  2            // InterfaceMethod java/util/List.add:(Ljava/lang/Object;)Z
      24: pop
      25: aload_1
      26: areturn

  protected abstract be.yildiz.module.graphic.MaterialPass createPassImpl(int);

  public final be.yildiz.module.graphic.MaterialPass getPass(int);
    Code:
       0: aload_0
       1: getfield      #3                  // Field materialPassList:Ljava/util/List;
       4: iload_1
       5: invokeinterface #8,  2            // InterfaceMethod java/util/List.get:(I)Ljava/lang/Object;
      10: checkcast     #9                  // class be/yildiz/module/graphic/MaterialPass
      13: astore_2
      14: aload_2
      15: ifnonnull     28
      18: new           #10                 // class java/security/InvalidParameterException
      21: dup
      22: ldc           #11                 // String No technique found for this index.
      24: invokespecial #12                 // Method java/security/InvalidParameterException."<init>":(Ljava/lang/String;)V
      27: athrow
      28: aload_2
      29: areturn

  public final void setGlow();
    Code:
       0: aload_0
       1: invokevirtual #13                 // Method setGlowImpl:()V
       4: return

  final java.util.List<be.yildiz.module.graphic.MaterialPass> getPassList();
    Code:
       0: aload_0
       1: getfield      #3                  // Field materialPassList:Ljava/util/List;
       4: invokestatic  #14                 // Method java/util/Collections.unmodifiableList:(Ljava/util/List;)Ljava/util/List;
       7: areturn

  protected abstract void setGlowImpl();

  public final int compareTo(be.yildiz.module.graphic.MaterialTechnique);
    Code:
       0: aload_0
       1: getfield      #4                  // Field index:I
       4: aload_1
       5: getfield      #4                  // Field index:I
       8: if_icmpge     13
      11: iconst_m1
      12: ireturn
      13: aload_0
      14: getfield      #4                  // Field index:I
      17: aload_1
      18: getfield      #4                  // Field index:I
      21: if_icmple     26
      24: iconst_1
      25: ireturn
      26: iconst_0
      27: ireturn

  public final int hashCode();
    Code:
       0: bipush        31
       2: istore_1
       3: iconst_1
       4: istore_2
       5: bipush        31
       7: iload_2
       8: imul
       9: aload_0
      10: getfield      #4                  // Field index:I
      13: iadd
      14: istore_2
      15: bipush        31
      17: iload_2
      18: imul
      19: aload_0
      20: getfield      #3                  // Field materialPassList:Ljava/util/List;
      23: ifnonnull     30
      26: iconst_0
      27: goto          39
      30: aload_0
      31: getfield      #3                  // Field materialPassList:Ljava/util/List;
      34: invokeinterface #15,  1           // InterfaceMethod java/util/List.hashCode:()I
      39: iadd
      40: istore_2
      41: iload_2
      42: ireturn

  public final boolean equals(java.lang.Object);
    Code:
       0: aload_0
       1: aload_1
       2: if_acmpne     7
       5: iconst_1
       6: ireturn
       7: aload_1
       8: instanceof    #16                 // class be/yildiz/module/graphic/MaterialTechnique
      11: ifne          16
      14: iconst_0
      15: ireturn
      16: aload_1
      17: checkcast     #16                 // class be/yildiz/module/graphic/MaterialTechnique
      20: astore_2
      21: aload_0
      22: getfield      #4                  // Field index:I
      25: aload_2
      26: getfield      #4                  // Field index:I
      29: if_icmpeq     34
      32: iconst_0
      33: ireturn
      34: aload_0
      35: getfield      #3                  // Field materialPassList:Ljava/util/List;
      38: ifnonnull     50
      41: aload_2
      42: getfield      #3                  // Field materialPassList:Ljava/util/List;
      45: ifnull        68
      48: iconst_0
      49: ireturn
      50: aload_0
      51: getfield      #3                  // Field materialPassList:Ljava/util/List;
      54: aload_2
      55: getfield      #3                  // Field materialPassList:Ljava/util/List;
      58: invokeinterface #17,  2           // InterfaceMethod java/util/List.equals:(Ljava/lang/Object;)Z
      63: ifne          68
      66: iconst_0
      67: ireturn
      68: iconst_1
      69: ireturn

  public int compareTo(java.lang.Object);
    Code:
       0: aload_0
       1: aload_1
       2: checkcast     #16                 // class be/yildiz/module/graphic/MaterialTechnique
       5: invokevirtual #18                 // Method compareTo:(Lbe/yildiz/module/graphic/MaterialTechnique;)I
       8: ireturn
}
