Compiled from "MaterialPass.java"
public final class be.yildiz.module.graphic.MaterialPass$SceneBlend extends java.lang.Enum<be.yildiz.module.graphic.MaterialPass$SceneBlend> {
  public static final be.yildiz.module.graphic.MaterialPass$SceneBlend ZERO;

  public static final be.yildiz.module.graphic.MaterialPass$SceneBlend ONE;

  public static final be.yildiz.module.graphic.MaterialPass$SceneBlend DEST_COLOR;

  public static final be.yildiz.module.graphic.MaterialPass$SceneBlend SRC_COLOR;

  public static final be.yildiz.module.graphic.MaterialPass$SceneBlend ONE_MINUS_DEST_COLOR;

  public static final be.yildiz.module.graphic.MaterialPass$SceneBlend ONE_MINUS_SRC_COLOR;

  public static final be.yildiz.module.graphic.MaterialPass$SceneBlend DEST_ALPHA;

  public static final be.yildiz.module.graphic.MaterialPass$SceneBlend SRC_ALPHA;

  public static final be.yildiz.module.graphic.MaterialPass$SceneBlend ONE_MINUS_DEST_ALPHA;

  public static final be.yildiz.module.graphic.MaterialPass$SceneBlend ONE_MINUS_SRC_ALPHA;

  public static final be.yildiz.module.graphic.MaterialPass$SceneBlend NONE;

  private static final be.yildiz.module.graphic.MaterialPass$SceneBlend[] $VALUES;

  public static be.yildiz.module.graphic.MaterialPass$SceneBlend[] values();
    Code:
       0: getstatic     #1                  // Field $VALUES:[Lbe/yildiz/module/graphic/MaterialPass$SceneBlend;
       3: invokevirtual #2                  // Method "[Lbe/yildiz/module/graphic/MaterialPass$SceneBlend;".clone:()Ljava/lang/Object;
       6: checkcast     #3                  // class "[Lbe/yildiz/module/graphic/MaterialPass$SceneBlend;"
       9: areturn

  public static be.yildiz.module.graphic.MaterialPass$SceneBlend valueOf(java.lang.String);
    Code:
       0: ldc           #4                  // class be/yildiz/module/graphic/MaterialPass$SceneBlend
       2: aload_0
       3: invokestatic  #5                  // Method java/lang/Enum.valueOf:(Ljava/lang/Class;Ljava/lang/String;)Ljava/lang/Enum;
       6: checkcast     #4                  // class be/yildiz/module/graphic/MaterialPass$SceneBlend
       9: areturn

  private be.yildiz.module.graphic.MaterialPass$SceneBlend();
    Code:
       0: aload_0
       1: aload_1
       2: iload_2
       3: invokespecial #6                  // Method java/lang/Enum."<init>":(Ljava/lang/String;I)V
       6: return

  static {};
    Code:
       0: new           #4                  // class be/yildiz/module/graphic/MaterialPass$SceneBlend
       3: dup
       4: ldc           #7                  // String ZERO
       6: iconst_0
       7: invokespecial #8                  // Method "<init>":(Ljava/lang/String;I)V
      10: putstatic     #9                  // Field ZERO:Lbe/yildiz/module/graphic/MaterialPass$SceneBlend;
      13: new           #4                  // class be/yildiz/module/graphic/MaterialPass$SceneBlend
      16: dup
      17: ldc           #10                 // String ONE
      19: iconst_1
      20: invokespecial #8                  // Method "<init>":(Ljava/lang/String;I)V
      23: putstatic     #11                 // Field ONE:Lbe/yildiz/module/graphic/MaterialPass$SceneBlend;
      26: new           #4                  // class be/yildiz/module/graphic/MaterialPass$SceneBlend
      29: dup
      30: ldc           #12                 // String DEST_COLOR
      32: iconst_2
      33: invokespecial #8                  // Method "<init>":(Ljava/lang/String;I)V
      36: putstatic     #13                 // Field DEST_COLOR:Lbe/yildiz/module/graphic/MaterialPass$SceneBlend;
      39: new           #4                  // class be/yildiz/module/graphic/MaterialPass$SceneBlend
      42: dup
      43: ldc           #14                 // String SRC_COLOR
      45: iconst_3
      46: invokespecial #8                  // Method "<init>":(Ljava/lang/String;I)V
      49: putstatic     #15                 // Field SRC_COLOR:Lbe/yildiz/module/graphic/MaterialPass$SceneBlend;
      52: new           #4                  // class be/yildiz/module/graphic/MaterialPass$SceneBlend
      55: dup
      56: ldc           #16                 // String ONE_MINUS_DEST_COLOR
      58: iconst_4
      59: invokespecial #8                  // Method "<init>":(Ljava/lang/String;I)V
      62: putstatic     #17                 // Field ONE_MINUS_DEST_COLOR:Lbe/yildiz/module/graphic/MaterialPass$SceneBlend;
      65: new           #4                  // class be/yildiz/module/graphic/MaterialPass$SceneBlend
      68: dup
      69: ldc           #18                 // String ONE_MINUS_SRC_COLOR
      71: iconst_5
      72: invokespecial #8                  // Method "<init>":(Ljava/lang/String;I)V
      75: putstatic     #19                 // Field ONE_MINUS_SRC_COLOR:Lbe/yildiz/module/graphic/MaterialPass$SceneBlend;
      78: new           #4                  // class be/yildiz/module/graphic/MaterialPass$SceneBlend
      81: dup
      82: ldc           #20                 // String DEST_ALPHA
      84: bipush        6
      86: invokespecial #8                  // Method "<init>":(Ljava/lang/String;I)V
      89: putstatic     #21                 // Field DEST_ALPHA:Lbe/yildiz/module/graphic/MaterialPass$SceneBlend;
      92: new           #4                  // class be/yildiz/module/graphic/MaterialPass$SceneBlend
      95: dup
      96: ldc           #22                 // String SRC_ALPHA
      98: bipush        7
     100: invokespecial #8                  // Method "<init>":(Ljava/lang/String;I)V
     103: putstatic     #23                 // Field SRC_ALPHA:Lbe/yildiz/module/graphic/MaterialPass$SceneBlend;
     106: new           #4                  // class be/yildiz/module/graphic/MaterialPass$SceneBlend
     109: dup
     110: ldc           #24                 // String ONE_MINUS_DEST_ALPHA
     112: bipush        8
     114: invokespecial #8                  // Method "<init>":(Ljava/lang/String;I)V
     117: putstatic     #25                 // Field ONE_MINUS_DEST_ALPHA:Lbe/yildiz/module/graphic/MaterialPass$SceneBlend;
     120: new           #4                  // class be/yildiz/module/graphic/MaterialPass$SceneBlend
     123: dup
     124: ldc           #26                 // String ONE_MINUS_SRC_ALPHA
     126: bipush        9
     128: invokespecial #8                  // Method "<init>":(Ljava/lang/String;I)V
     131: putstatic     #27                 // Field ONE_MINUS_SRC_ALPHA:Lbe/yildiz/module/graphic/MaterialPass$SceneBlend;
     134: new           #4                  // class be/yildiz/module/graphic/MaterialPass$SceneBlend
     137: dup
     138: ldc           #28                 // String NONE
     140: bipush        10
     142: invokespecial #8                  // Method "<init>":(Ljava/lang/String;I)V
     145: putstatic     #29                 // Field NONE:Lbe/yildiz/module/graphic/MaterialPass$SceneBlend;
     148: bipush        11
     150: anewarray     #4                  // class be/yildiz/module/graphic/MaterialPass$SceneBlend
     153: dup
     154: iconst_0
     155: getstatic     #9                  // Field ZERO:Lbe/yildiz/module/graphic/MaterialPass$SceneBlend;
     158: aastore
     159: dup
     160: iconst_1
     161: getstatic     #11                 // Field ONE:Lbe/yildiz/module/graphic/MaterialPass$SceneBlend;
     164: aastore
     165: dup
     166: iconst_2
     167: getstatic     #13                 // Field DEST_COLOR:Lbe/yildiz/module/graphic/MaterialPass$SceneBlend;
     170: aastore
     171: dup
     172: iconst_3
     173: getstatic     #15                 // Field SRC_COLOR:Lbe/yildiz/module/graphic/MaterialPass$SceneBlend;
     176: aastore
     177: dup
     178: iconst_4
     179: getstatic     #17                 // Field ONE_MINUS_DEST_COLOR:Lbe/yildiz/module/graphic/MaterialPass$SceneBlend;
     182: aastore
     183: dup
     184: iconst_5
     185: getstatic     #19                 // Field ONE_MINUS_SRC_COLOR:Lbe/yildiz/module/graphic/MaterialPass$SceneBlend;
     188: aastore
     189: dup
     190: bipush        6
     192: getstatic     #21                 // Field DEST_ALPHA:Lbe/yildiz/module/graphic/MaterialPass$SceneBlend;
     195: aastore
     196: dup
     197: bipush        7
     199: getstatic     #23                 // Field SRC_ALPHA:Lbe/yildiz/module/graphic/MaterialPass$SceneBlend;
     202: aastore
     203: dup
     204: bipush        8
     206: getstatic     #25                 // Field ONE_MINUS_DEST_ALPHA:Lbe/yildiz/module/graphic/MaterialPass$SceneBlend;
     209: aastore
     210: dup
     211: bipush        9
     213: getstatic     #27                 // Field ONE_MINUS_SRC_ALPHA:Lbe/yildiz/module/graphic/MaterialPass$SceneBlend;
     216: aastore
     217: dup
     218: bipush        10
     220: getstatic     #29                 // Field NONE:Lbe/yildiz/module/graphic/MaterialPass$SceneBlend;
     223: aastore
     224: putstatic     #1                  // Field $VALUES:[Lbe/yildiz/module/graphic/MaterialPass$SceneBlend;
     227: return
}
