Compiled from "ManagedBean.java"
public class org.apache.tomcat.util.modeler.ManagedBean implements java.io.Serializable {
  private static final long serialVersionUID;

  private static final java.lang.String BASE_MBEAN;

  static final java.lang.Class<?>[] NO_ARGS_PARAM_SIG;

  private final java.util.concurrent.locks.ReadWriteLock mBeanInfoLock;

  private volatile transient javax.management.MBeanInfo info;

  private java.util.Map<java.lang.String, org.apache.tomcat.util.modeler.AttributeInfo> attributes;

  private java.util.Map<java.lang.String, org.apache.tomcat.util.modeler.OperationInfo> operations;

  protected java.lang.String className;

  protected java.lang.String description;

  protected java.lang.String domain;

  protected java.lang.String group;

  protected java.lang.String name;

  private org.apache.tomcat.util.modeler.NotificationInfo[] notifications;

  protected java.lang.String type;

  public org.apache.tomcat.util.modeler.ManagedBean();
    Code:
       0: aload_0
       1: invokespecial #1                  // Method java/lang/Object."<init>":()V
       4: aload_0
       5: new           #2                  // class java/util/concurrent/locks/ReentrantReadWriteLock
       8: dup
       9: invokespecial #3                  // Method java/util/concurrent/locks/ReentrantReadWriteLock."<init>":()V
      12: putfield      #4                  // Field mBeanInfoLock:Ljava/util/concurrent/locks/ReadWriteLock;
      15: aload_0
      16: aconst_null
      17: putfield      #5                  // Field info:Ljavax/management/MBeanInfo;
      20: aload_0
      21: new           #6                  // class java/util/HashMap
      24: dup
      25: invokespecial #7                  // Method java/util/HashMap."<init>":()V
      28: putfield      #8                  // Field attributes:Ljava/util/Map;
      31: aload_0
      32: new           #6                  // class java/util/HashMap
      35: dup
      36: invokespecial #7                  // Method java/util/HashMap."<init>":()V
      39: putfield      #9                  // Field operations:Ljava/util/Map;
      42: aload_0
      43: ldc           #10                 // String org.apache.tomcat.util.modeler.BaseModelMBean
      45: putfield      #11                 // Field className:Ljava/lang/String;
      48: aload_0
      49: aconst_null
      50: putfield      #12                 // Field description:Ljava/lang/String;
      53: aload_0
      54: aconst_null
      55: putfield      #13                 // Field domain:Ljava/lang/String;
      58: aload_0
      59: aconst_null
      60: putfield      #14                 // Field group:Ljava/lang/String;
      63: aload_0
      64: aconst_null
      65: putfield      #15                 // Field name:Ljava/lang/String;
      68: aload_0
      69: iconst_0
      70: anewarray     #16                 // class org/apache/tomcat/util/modeler/NotificationInfo
      73: putfield      #17                 // Field notifications:[Lorg/apache/tomcat/util/modeler/NotificationInfo;
      76: aload_0
      77: aconst_null
      78: putfield      #18                 // Field type:Ljava/lang/String;
      81: new           #19                 // class org/apache/tomcat/util/modeler/AttributeInfo
      84: dup
      85: invokespecial #20                 // Method org/apache/tomcat/util/modeler/AttributeInfo."<init>":()V
      88: astore_1
      89: aload_1
      90: ldc           #21                 // String modelerType
      92: invokevirtual #22                 // Method org/apache/tomcat/util/modeler/AttributeInfo.setName:(Ljava/lang/String;)V
      95: aload_1
      96: ldc           #23                 // String Type of the modeled resource. Can be set only once
      98: invokevirtual #24                 // Method org/apache/tomcat/util/modeler/AttributeInfo.setDescription:(Ljava/lang/String;)V
     101: aload_1
     102: ldc           #25                 // String java.lang.String
     104: invokevirtual #26                 // Method org/apache/tomcat/util/modeler/AttributeInfo.setType:(Ljava/lang/String;)V
     107: aload_1
     108: iconst_0
     109: invokevirtual #27                 // Method org/apache/tomcat/util/modeler/AttributeInfo.setWriteable:(Z)V
     112: aload_0
     113: aload_1
     114: invokevirtual #28                 // Method addAttribute:(Lorg/apache/tomcat/util/modeler/AttributeInfo;)V
     117: return

  public org.apache.tomcat.util.modeler.AttributeInfo[] getAttributes();
    Code:
       0: aload_0
       1: getfield      #8                  // Field attributes:Ljava/util/Map;
       4: invokeinterface #29,  1           // InterfaceMethod java/util/Map.size:()I
       9: anewarray     #19                 // class org/apache/tomcat/util/modeler/AttributeInfo
      12: astore_1
      13: aload_0
      14: getfield      #8                  // Field attributes:Ljava/util/Map;
      17: invokeinterface #30,  1           // InterfaceMethod java/util/Map.values:()Ljava/util/Collection;
      22: aload_1
      23: invokeinterface #31,  2           // InterfaceMethod java/util/Collection.toArray:([Ljava/lang/Object;)[Ljava/lang/Object;
      28: pop
      29: aload_1
      30: areturn

  public java.lang.String getClassName();
    Code:
       0: aload_0
       1: getfield      #11                 // Field className:Ljava/lang/String;
       4: areturn

  public void setClassName(java.lang.String);
    Code:
       0: aload_0
       1: getfield      #4                  // Field mBeanInfoLock:Ljava/util/concurrent/locks/ReadWriteLock;
       4: invokeinterface #32,  1           // InterfaceMethod java/util/concurrent/locks/ReadWriteLock.writeLock:()Ljava/util/concurrent/locks/Lock;
       9: invokeinterface #33,  1           // InterfaceMethod java/util/concurrent/locks/Lock.lock:()V
      14: aload_0
      15: aload_1
      16: putfield      #11                 // Field className:Ljava/lang/String;
      19: aload_0
      20: aconst_null
      21: putfield      #5                  // Field info:Ljavax/management/MBeanInfo;
      24: aload_0
      25: getfield      #4                  // Field mBeanInfoLock:Ljava/util/concurrent/locks/ReadWriteLock;
      28: invokeinterface #32,  1           // InterfaceMethod java/util/concurrent/locks/ReadWriteLock.writeLock:()Ljava/util/concurrent/locks/Lock;
      33: invokeinterface #34,  1           // InterfaceMethod java/util/concurrent/locks/Lock.unlock:()V
      38: goto          58
      41: astore_2
      42: aload_0
      43: getfield      #4                  // Field mBeanInfoLock:Ljava/util/concurrent/locks/ReadWriteLock;
      46: invokeinterface #32,  1           // InterfaceMethod java/util/concurrent/locks/ReadWriteLock.writeLock:()Ljava/util/concurrent/locks/Lock;
      51: invokeinterface #34,  1           // InterfaceMethod java/util/concurrent/locks/Lock.unlock:()V
      56: aload_2
      57: athrow
      58: return
    Exception table:
       from    to  target type
          14    24    41   any
          41    42    41   any

  public java.lang.String getDescription();
    Code:
       0: aload_0
       1: getfield      #12                 // Field description:Ljava/lang/String;
       4: areturn

  public void setDescription(java.lang.String);
    Code:
       0: aload_0
       1: getfield      #4                  // Field mBeanInfoLock:Ljava/util/concurrent/locks/ReadWriteLock;
       4: invokeinterface #32,  1           // InterfaceMethod java/util/concurrent/locks/ReadWriteLock.writeLock:()Ljava/util/concurrent/locks/Lock;
       9: invokeinterface #33,  1           // InterfaceMethod java/util/concurrent/locks/Lock.lock:()V
      14: aload_0
      15: aload_1
      16: putfield      #12                 // Field description:Ljava/lang/String;
      19: aload_0
      20: aconst_null
      21: putfield      #5                  // Field info:Ljavax/management/MBeanInfo;
      24: aload_0
      25: getfield      #4                  // Field mBeanInfoLock:Ljava/util/concurrent/locks/ReadWriteLock;
      28: invokeinterface #32,  1           // InterfaceMethod java/util/concurrent/locks/ReadWriteLock.writeLock:()Ljava/util/concurrent/locks/Lock;
      33: invokeinterface #34,  1           // InterfaceMethod java/util/concurrent/locks/Lock.unlock:()V
      38: goto          58
      41: astore_2
      42: aload_0
      43: getfield      #4                  // Field mBeanInfoLock:Ljava/util/concurrent/locks/ReadWriteLock;
      46: invokeinterface #32,  1           // InterfaceMethod java/util/concurrent/locks/ReadWriteLock.writeLock:()Ljava/util/concurrent/locks/Lock;
      51: invokeinterface #34,  1           // InterfaceMethod java/util/concurrent/locks/Lock.unlock:()V
      56: aload_2
      57: athrow
      58: return
    Exception table:
       from    to  target type
          14    24    41   any
          41    42    41   any

  public java.lang.String getDomain();
    Code:
       0: aload_0
       1: getfield      #13                 // Field domain:Ljava/lang/String;
       4: areturn

  public void setDomain(java.lang.String);
    Code:
       0: aload_0
       1: aload_1
       2: putfield      #13                 // Field domain:Ljava/lang/String;
       5: return

  public java.lang.String getGroup();
    Code:
       0: aload_0
       1: getfield      #14                 // Field group:Ljava/lang/String;
       4: areturn

  public void setGroup(java.lang.String);
    Code:
       0: aload_0
       1: aload_1
       2: putfield      #14                 // Field group:Ljava/lang/String;
       5: return

  public java.lang.String getName();
    Code:
       0: aload_0
       1: getfield      #15                 // Field name:Ljava/lang/String;
       4: areturn

  public void setName(java.lang.String);
    Code:
       0: aload_0
       1: getfield      #4                  // Field mBeanInfoLock:Ljava/util/concurrent/locks/ReadWriteLock;
       4: invokeinterface #32,  1           // InterfaceMethod java/util/concurrent/locks/ReadWriteLock.writeLock:()Ljava/util/concurrent/locks/Lock;
       9: invokeinterface #33,  1           // InterfaceMethod java/util/concurrent/locks/Lock.lock:()V
      14: aload_0
      15: aload_1
      16: putfield      #15                 // Field name:Ljava/lang/String;
      19: aload_0
      20: aconst_null
      21: putfield      #5                  // Field info:Ljavax/management/MBeanInfo;
      24: aload_0
      25: getfield      #4                  // Field mBeanInfoLock:Ljava/util/concurrent/locks/ReadWriteLock;
      28: invokeinterface #32,  1           // InterfaceMethod java/util/concurrent/locks/ReadWriteLock.writeLock:()Ljava/util/concurrent/locks/Lock;
      33: invokeinterface #34,  1           // InterfaceMethod java/util/concurrent/locks/Lock.unlock:()V
      38: goto          58
      41: astore_2
      42: aload_0
      43: getfield      #4                  // Field mBeanInfoLock:Ljava/util/concurrent/locks/ReadWriteLock;
      46: invokeinterface #32,  1           // InterfaceMethod java/util/concurrent/locks/ReadWriteLock.writeLock:()Ljava/util/concurrent/locks/Lock;
      51: invokeinterface #34,  1           // InterfaceMethod java/util/concurrent/locks/Lock.unlock:()V
      56: aload_2
      57: athrow
      58: return
    Exception table:
       from    to  target type
          14    24    41   any
          41    42    41   any

  public org.apache.tomcat.util.modeler.NotificationInfo[] getNotifications();
    Code:
       0: aload_0
       1: getfield      #17                 // Field notifications:[Lorg/apache/tomcat/util/modeler/NotificationInfo;
       4: areturn

  public org.apache.tomcat.util.modeler.OperationInfo[] getOperations();
    Code:
       0: aload_0
       1: getfield      #9                  // Field operations:Ljava/util/Map;
       4: invokeinterface #29,  1           // InterfaceMethod java/util/Map.size:()I
       9: anewarray     #35                 // class org/apache/tomcat/util/modeler/OperationInfo
      12: astore_1
      13: aload_0
      14: getfield      #9                  // Field operations:Ljava/util/Map;
      17: invokeinterface #30,  1           // InterfaceMethod java/util/Map.values:()Ljava/util/Collection;
      22: aload_1
      23: invokeinterface #31,  2           // InterfaceMethod java/util/Collection.toArray:([Ljava/lang/Object;)[Ljava/lang/Object;
      28: pop
      29: aload_1
      30: areturn

  public java.lang.String getType();
    Code:
       0: aload_0
       1: getfield      #18                 // Field type:Ljava/lang/String;
       4: areturn

  public void setType(java.lang.String);
    Code:
       0: aload_0
       1: getfield      #4                  // Field mBeanInfoLock:Ljava/util/concurrent/locks/ReadWriteLock;
       4: invokeinterface #32,  1           // InterfaceMethod java/util/concurrent/locks/ReadWriteLock.writeLock:()Ljava/util/concurrent/locks/Lock;
       9: invokeinterface #33,  1           // InterfaceMethod java/util/concurrent/locks/Lock.lock:()V
      14: aload_0
      15: aload_1
      16: putfield      #18                 // Field type:Ljava/lang/String;
      19: aload_0
      20: aconst_null
      21: putfield      #5                  // Field info:Ljavax/management/MBeanInfo;
      24: aload_0
      25: getfield      #4                  // Field mBeanInfoLock:Ljava/util/concurrent/locks/ReadWriteLock;
      28: invokeinterface #32,  1           // InterfaceMethod java/util/concurrent/locks/ReadWriteLock.writeLock:()Ljava/util/concurrent/locks/Lock;
      33: invokeinterface #34,  1           // InterfaceMethod java/util/concurrent/locks/Lock.unlock:()V
      38: goto          58
      41: astore_2
      42: aload_0
      43: getfield      #4                  // Field mBeanInfoLock:Ljava/util/concurrent/locks/ReadWriteLock;
      46: invokeinterface #32,  1           // InterfaceMethod java/util/concurrent/locks/ReadWriteLock.writeLock:()Ljava/util/concurrent/locks/Lock;
      51: invokeinterface #34,  1           // InterfaceMethod java/util/concurrent/locks/Lock.unlock:()V
      56: aload_2
      57: athrow
      58: return
    Exception table:
       from    to  target type
          14    24    41   any
          41    42    41   any

  public void addAttribute(org.apache.tomcat.util.modeler.AttributeInfo);
    Code:
       0: aload_0
       1: getfield      #8                  // Field attributes:Ljava/util/Map;
       4: aload_1
       5: invokevirtual #36                 // Method org/apache/tomcat/util/modeler/AttributeInfo.getName:()Ljava/lang/String;
       8: aload_1
       9: invokeinterface #37,  3           // InterfaceMethod java/util/Map.put:(Ljava/lang/Object;Ljava/lang/Object;)Ljava/lang/Object;
      14: pop
      15: return

  public void addNotification(org.apache.tomcat.util.modeler.NotificationInfo);
    Code:
       0: aload_0
       1: getfield      #4                  // Field mBeanInfoLock:Ljava/util/concurrent/locks/ReadWriteLock;
       4: invokeinterface #32,  1           // InterfaceMethod java/util/concurrent/locks/ReadWriteLock.writeLock:()Ljava/util/concurrent/locks/Lock;
       9: invokeinterface #33,  1           // InterfaceMethod java/util/concurrent/locks/Lock.lock:()V
      14: aload_0
      15: getfield      #17                 // Field notifications:[Lorg/apache/tomcat/util/modeler/NotificationInfo;
      18: arraylength
      19: iconst_1
      20: iadd
      21: anewarray     #16                 // class org/apache/tomcat/util/modeler/NotificationInfo
      24: astore_2
      25: aload_0
      26: getfield      #17                 // Field notifications:[Lorg/apache/tomcat/util/modeler/NotificationInfo;
      29: iconst_0
      30: aload_2
      31: iconst_0
      32: aload_0
      33: getfield      #17                 // Field notifications:[Lorg/apache/tomcat/util/modeler/NotificationInfo;
      36: arraylength
      37: invokestatic  #38                 // Method java/lang/System.arraycopy:(Ljava/lang/Object;ILjava/lang/Object;II)V
      40: aload_2
      41: aload_0
      42: getfield      #17                 // Field notifications:[Lorg/apache/tomcat/util/modeler/NotificationInfo;
      45: arraylength
      46: aload_1
      47: aastore
      48: aload_0
      49: aload_2
      50: putfield      #17                 // Field notifications:[Lorg/apache/tomcat/util/modeler/NotificationInfo;
      53: aload_0
      54: aconst_null
      55: putfield      #5                  // Field info:Ljavax/management/MBeanInfo;
      58: aload_0
      59: getfield      #4                  // Field mBeanInfoLock:Ljava/util/concurrent/locks/ReadWriteLock;
      62: invokeinterface #32,  1           // InterfaceMethod java/util/concurrent/locks/ReadWriteLock.writeLock:()Ljava/util/concurrent/locks/Lock;
      67: invokeinterface #34,  1           // InterfaceMethod java/util/concurrent/locks/Lock.unlock:()V
      72: goto          92
      75: astore_3
      76: aload_0
      77: getfield      #4                  // Field mBeanInfoLock:Ljava/util/concurrent/locks/ReadWriteLock;
      80: invokeinterface #32,  1           // InterfaceMethod java/util/concurrent/locks/ReadWriteLock.writeLock:()Ljava/util/concurrent/locks/Lock;
      85: invokeinterface #34,  1           // InterfaceMethod java/util/concurrent/locks/Lock.unlock:()V
      90: aload_3
      91: athrow
      92: return
    Exception table:
       from    to  target type
          14    58    75   any
          75    76    75   any

  public void addOperation(org.apache.tomcat.util.modeler.OperationInfo);
    Code:
       0: aload_0
       1: getfield      #9                  // Field operations:Ljava/util/Map;
       4: aload_0
       5: aload_1
       6: invokespecial #39                 // Method createOperationKey:(Lorg/apache/tomcat/util/modeler/OperationInfo;)Ljava/lang/String;
       9: aload_1
      10: invokeinterface #37,  3           // InterfaceMethod java/util/Map.put:(Ljava/lang/Object;Ljava/lang/Object;)Ljava/lang/Object;
      15: pop
      16: return

  public javax.management.DynamicMBean createMBean(java.lang.Object) throws javax.management.InstanceNotFoundException, javax.management.MBeanException, javax.management.RuntimeOperationsException;
    Code:
       0: aconst_null
       1: astore_2
       2: aload_0
       3: invokevirtual #40                 // Method getClassName:()Ljava/lang/String;
       6: ldc           #10                 // String org.apache.tomcat.util.modeler.BaseModelMBean
       8: invokevirtual #41                 // Method java/lang/String.equals:(Ljava/lang/Object;)Z
      11: ifeq          25
      14: new           #42                 // class org/apache/tomcat/util/modeler/BaseModelMBean
      17: dup
      18: invokespecial #43                 // Method org/apache/tomcat/util/modeler/BaseModelMBean."<init>":()V
      21: astore_2
      22: goto          176
      25: aconst_null
      26: astore_3
      27: aconst_null
      28: astore        4
      30: aload_0
      31: invokevirtual #40                 // Method getClassName:()Ljava/lang/String;
      34: invokestatic  #44                 // Method java/lang/Class.forName:(Ljava/lang/String;)Ljava/lang/Class;
      37: astore_3
      38: goto          43
      41: astore        5
      43: aload_3
      44: ifnonnull     79
      47: invokestatic  #46                 // Method java/lang/Thread.currentThread:()Ljava/lang/Thread;
      50: invokevirtual #47                 // Method java/lang/Thread.getContextClassLoader:()Ljava/lang/ClassLoader;
      53: astore        5
      55: aload         5
      57: ifnull        70
      60: aload         5
      62: aload_0
      63: invokevirtual #40                 // Method getClassName:()Ljava/lang/String;
      66: invokevirtual #48                 // Method java/lang/ClassLoader.loadClass:(Ljava/lang/String;)Ljava/lang/Class;
      69: astore_3
      70: goto          79
      73: astore        5
      75: aload         5
      77: astore        4
      79: aload_3
      80: ifnonnull     115
      83: new           #49                 // class javax/management/MBeanException
      86: dup
      87: aload         4
      89: new           #50                 // class java/lang/StringBuilder
      92: dup
      93: invokespecial #51                 // Method java/lang/StringBuilder."<init>":()V
      96: ldc           #52                 // String Cannot load ModelMBean class
      98: invokevirtual #53                 // Method java/lang/StringBuilder.append:(Ljava/lang/String;)Ljava/lang/StringBuilder;
     101: aload_0
     102: invokevirtual #40                 // Method getClassName:()Ljava/lang/String;
     105: invokevirtual #53                 // Method java/lang/StringBuilder.append:(Ljava/lang/String;)Ljava/lang/StringBuilder;
     108: invokevirtual #54                 // Method java/lang/StringBuilder.toString:()Ljava/lang/String;
     111: invokespecial #55                 // Method javax/management/MBeanException."<init>":(Ljava/lang/Exception;Ljava/lang/String;)V
     114: athrow
     115: aload_3
     116: iconst_0
     117: anewarray     #56                 // class java/lang/Class
     120: invokevirtual #57                 // Method java/lang/Class.getConstructor:([Ljava/lang/Class;)Ljava/lang/reflect/Constructor;
     123: iconst_0
     124: anewarray     #58                 // class java/lang/Object
     127: invokevirtual #59                 // Method java/lang/reflect/Constructor.newInstance:([Ljava/lang/Object;)Ljava/lang/Object;
     130: checkcast     #42                 // class org/apache/tomcat/util/modeler/BaseModelMBean
     133: astore_2
     134: goto          176
     137: astore        5
     139: aload         5
     141: athrow
     142: astore        5
     144: new           #49                 // class javax/management/MBeanException
     147: dup
     148: aload         5
     150: new           #50                 // class java/lang/StringBuilder
     153: dup
     154: invokespecial #51                 // Method java/lang/StringBuilder."<init>":()V
     157: ldc           #61                 // String Cannot instantiate ModelMBean of class
     159: invokevirtual #53                 // Method java/lang/StringBuilder.append:(Ljava/lang/String;)Ljava/lang/StringBuilder;
     162: aload_0
     163: invokevirtual #40                 // Method getClassName:()Ljava/lang/String;
     166: invokevirtual #53                 // Method java/lang/StringBuilder.append:(Ljava/lang/String;)Ljava/lang/StringBuilder;
     169: invokevirtual #54                 // Method java/lang/StringBuilder.toString:()Ljava/lang/String;
     172: invokespecial #55                 // Method javax/management/MBeanException."<init>":(Ljava/lang/Exception;Ljava/lang/String;)V
     175: athrow
     176: aload_2
     177: aload_0
     178: invokevirtual #62                 // Method org/apache/tomcat/util/modeler/BaseModelMBean.setManagedBean:(Lorg/apache/tomcat/util/modeler/ManagedBean;)V
     181: aload_1
     182: ifnull        192
     185: aload_2
     186: aload_1
     187: ldc           #63                 // String ObjectReference
     189: invokevirtual #64                 // Method org/apache/tomcat/util/modeler/BaseModelMBean.setManagedResource:(Ljava/lang/Object;Ljava/lang/String;)V
     192: goto          198
     195: astore_3
     196: aload_3
     197: athrow
     198: aload_2
     199: areturn
    Exception table:
       from    to  target type
          30    38    41   Class java/lang/Exception
          47    70    73   Class java/lang/Exception
         115   134   137   Class javax/management/RuntimeOperationsException
         115   134   142   Class java/lang/Exception
         181   192   195   Class javax/management/InstanceNotFoundException

  javax.management.MBeanInfo getMBeanInfo();
    Code:
       0: aload_0
       1: getfield      #4                  // Field mBeanInfoLock:Ljava/util/concurrent/locks/ReadWriteLock;
       4: invokeinterface #66,  1           // InterfaceMethod java/util/concurrent/locks/ReadWriteLock.readLock:()Ljava/util/concurrent/locks/Lock;
       9: invokeinterface #33,  1           // InterfaceMethod java/util/concurrent/locks/Lock.lock:()V
      14: aload_0
      15: getfield      #5                  // Field info:Ljavax/management/MBeanInfo;
      18: ifnull        42
      21: aload_0
      22: getfield      #5                  // Field info:Ljavax/management/MBeanInfo;
      25: astore_1
      26: aload_0
      27: getfield      #4                  // Field mBeanInfoLock:Ljava/util/concurrent/locks/ReadWriteLock;
      30: invokeinterface #66,  1           // InterfaceMethod java/util/concurrent/locks/ReadWriteLock.readLock:()Ljava/util/concurrent/locks/Lock;
      35: invokeinterface #34,  1           // InterfaceMethod java/util/concurrent/locks/Lock.unlock:()V
      40: aload_1
      41: areturn
      42: aload_0
      43: getfield      #4                  // Field mBeanInfoLock:Ljava/util/concurrent/locks/ReadWriteLock;
      46: invokeinterface #66,  1           // InterfaceMethod java/util/concurrent/locks/ReadWriteLock.readLock:()Ljava/util/concurrent/locks/Lock;
      51: invokeinterface #34,  1           // InterfaceMethod java/util/concurrent/locks/Lock.unlock:()V
      56: goto          76
      59: astore_2
      60: aload_0
      61: getfield      #4                  // Field mBeanInfoLock:Ljava/util/concurrent/locks/ReadWriteLock;
      64: invokeinterface #66,  1           // InterfaceMethod java/util/concurrent/locks/ReadWriteLock.readLock:()Ljava/util/concurrent/locks/Lock;
      69: invokeinterface #34,  1           // InterfaceMethod java/util/concurrent/locks/Lock.unlock:()V
      74: aload_2
      75: athrow
      76: aload_0
      77: getfield      #4                  // Field mBeanInfoLock:Ljava/util/concurrent/locks/ReadWriteLock;
      80: invokeinterface #32,  1           // InterfaceMethod java/util/concurrent/locks/ReadWriteLock.writeLock:()Ljava/util/concurrent/locks/Lock;
      85: invokeinterface #33,  1           // InterfaceMethod java/util/concurrent/locks/Lock.lock:()V
      90: aload_0
      91: getfield      #5                  // Field info:Ljavax/management/MBeanInfo;
      94: ifnonnull     243
      97: aload_0
      98: invokevirtual #67                 // Method getAttributes:()[Lorg/apache/tomcat/util/modeler/AttributeInfo;
     101: astore_1
     102: aload_1
     103: arraylength
     104: anewarray     #68                 // class javax/management/MBeanAttributeInfo
     107: astore_2
     108: iconst_0
     109: istore_3
     110: iload_3
     111: aload_1
     112: arraylength
     113: if_icmpge     131
     116: aload_2
     117: iload_3
     118: aload_1
     119: iload_3
     120: aaload
     121: invokevirtual #69                 // Method org/apache/tomcat/util/modeler/AttributeInfo.createAttributeInfo:()Ljavax/management/MBeanAttributeInfo;
     124: aastore
     125: iinc          3, 1
     128: goto          110
     131: aload_0
     132: invokevirtual #70                 // Method getOperations:()[Lorg/apache/tomcat/util/modeler/OperationInfo;
     135: astore_3
     136: aload_3
     137: arraylength
     138: anewarray     #71                 // class javax/management/MBeanOperationInfo
     141: astore        4
     143: iconst_0
     144: istore        5
     146: iload         5
     148: aload_3
     149: arraylength
     150: if_icmpge     171
     153: aload         4
     155: iload         5
     157: aload_3
     158: iload         5
     160: aaload
     161: invokevirtual #72                 // Method org/apache/tomcat/util/modeler/OperationInfo.createOperationInfo:()Ljavax/management/MBeanOperationInfo;
     164: aastore
     165: iinc          5, 1
     168: goto          146
     171: aload_0
     172: invokevirtual #73                 // Method getNotifications:()[Lorg/apache/tomcat/util/modeler/NotificationInfo;
     175: astore        5
     177: aload         5
     179: arraylength
     180: anewarray     #74                 // class javax/management/MBeanNotificationInfo
     183: astore        6
     185: iconst_0
     186: istore        7
     188: iload         7
     190: aload         5
     192: arraylength
     193: if_icmpge     215
     196: aload         6
     198: iload         7
     200: aload         5
     202: iload         7
     204: aaload
     205: invokevirtual #75                 // Method org/apache/tomcat/util/modeler/NotificationInfo.createNotificationInfo:()Ljavax/management/MBeanNotificationInfo;
     208: aastore
     209: iinc          7, 1
     212: goto          188
     215: aload_0
     216: new           #76                 // class javax/management/MBeanInfo
     219: dup
     220: aload_0
     221: invokevirtual #40                 // Method getClassName:()Ljava/lang/String;
     224: aload_0
     225: invokevirtual #77                 // Method getDescription:()Ljava/lang/String;
     228: aload_2
     229: iconst_0
     230: anewarray     #78                 // class javax/management/MBeanConstructorInfo
     233: aload         4
     235: aload         6
     237: invokespecial #79                 // Method javax/management/MBeanInfo."<init>":(Ljava/lang/String;Ljava/lang/String;[Ljavax/management/MBeanAttributeInfo;[Ljavax/management/MBeanConstructorInfo;[Ljavax/management/MBeanOperationInfo;[Ljavax/management/MBeanNotificationInfo;)V
     240: putfield      #5                  // Field info:Ljavax/management/MBeanInfo;
     243: aload_0
     244: getfield      #5                  // Field info:Ljavax/management/MBeanInfo;
     247: astore_1
     248: aload_0
     249: getfield      #4                  // Field mBeanInfoLock:Ljava/util/concurrent/locks/ReadWriteLock;
     252: invokeinterface #32,  1           // InterfaceMethod java/util/concurrent/locks/ReadWriteLock.writeLock:()Ljava/util/concurrent/locks/Lock;
     257: invokeinterface #34,  1           // InterfaceMethod java/util/concurrent/locks/Lock.unlock:()V
     262: aload_1
     263: areturn
     264: astore        8
     266: aload_0
     267: getfield      #4                  // Field mBeanInfoLock:Ljava/util/concurrent/locks/ReadWriteLock;
     270: invokeinterface #32,  1           // InterfaceMethod java/util/concurrent/locks/ReadWriteLock.writeLock:()Ljava/util/concurrent/locks/Lock;
     275: invokeinterface #34,  1           // InterfaceMethod java/util/concurrent/locks/Lock.unlock:()V
     280: aload         8
     282: athrow
    Exception table:
       from    to  target type
          14    26    59   any
          59    60    59   any
          90   248   264   any
         264   266   264   any

  public java.lang.String toString();
    Code:
       0: new           #50                 // class java/lang/StringBuilder
       3: dup
       4: ldc           #80                 // String ManagedBean[
       6: invokespecial #81                 // Method java/lang/StringBuilder."<init>":(Ljava/lang/String;)V
       9: astore_1
      10: aload_1
      11: ldc           #82                 // String name=
      13: invokevirtual #53                 // Method java/lang/StringBuilder.append:(Ljava/lang/String;)Ljava/lang/StringBuilder;
      16: pop
      17: aload_1
      18: aload_0
      19: getfield      #15                 // Field name:Ljava/lang/String;
      22: invokevirtual #53                 // Method java/lang/StringBuilder.append:(Ljava/lang/String;)Ljava/lang/StringBuilder;
      25: pop
      26: aload_1
      27: ldc           #83                 // String , className=
      29: invokevirtual #53                 // Method java/lang/StringBuilder.append:(Ljava/lang/String;)Ljava/lang/StringBuilder;
      32: pop
      33: aload_1
      34: aload_0
      35: getfield      #11                 // Field className:Ljava/lang/String;
      38: invokevirtual #53                 // Method java/lang/StringBuilder.append:(Ljava/lang/String;)Ljava/lang/StringBuilder;
      41: pop
      42: aload_1
      43: ldc           #84                 // String , description=
      45: invokevirtual #53                 // Method java/lang/StringBuilder.append:(Ljava/lang/String;)Ljava/lang/StringBuilder;
      48: pop
      49: aload_1
      50: aload_0
      51: getfield      #12                 // Field description:Ljava/lang/String;
      54: invokevirtual #53                 // Method java/lang/StringBuilder.append:(Ljava/lang/String;)Ljava/lang/StringBuilder;
      57: pop
      58: aload_0
      59: getfield      #14                 // Field group:Ljava/lang/String;
      62: ifnull        81
      65: aload_1
      66: ldc           #85                 // String , group=
      68: invokevirtual #53                 // Method java/lang/StringBuilder.append:(Ljava/lang/String;)Ljava/lang/StringBuilder;
      71: pop
      72: aload_1
      73: aload_0
      74: getfield      #14                 // Field group:Ljava/lang/String;
      77: invokevirtual #53                 // Method java/lang/StringBuilder.append:(Ljava/lang/String;)Ljava/lang/StringBuilder;
      80: pop
      81: aload_1
      82: ldc           #86                 // String , type=
      84: invokevirtual #53                 // Method java/lang/StringBuilder.append:(Ljava/lang/String;)Ljava/lang/StringBuilder;
      87: pop
      88: aload_1
      89: aload_0
      90: getfield      #18                 // Field type:Ljava/lang/String;
      93: invokevirtual #53                 // Method java/lang/StringBuilder.append:(Ljava/lang/String;)Ljava/lang/StringBuilder;
      96: pop
      97: aload_1
      98: ldc           #87                 // String ]
     100: invokevirtual #53                 // Method java/lang/StringBuilder.append:(Ljava/lang/String;)Ljava/lang/StringBuilder;
     103: pop
     104: aload_1
     105: invokevirtual #54                 // Method java/lang/StringBuilder.toString:()Ljava/lang/String;
     108: areturn

  java.lang.reflect.Method getGetter(java.lang.String, org.apache.tomcat.util.modeler.BaseModelMBean, java.lang.Object) throws javax.management.AttributeNotFoundException, javax.management.ReflectionException;
    Code:
       0: aconst_null
       1: astore        4
       3: aload_0
       4: getfield      #8                  // Field attributes:Ljava/util/Map;
       7: aload_1
       8: invokeinterface #88,  2           // InterfaceMethod java/util/Map.get:(Ljava/lang/Object;)Ljava/lang/Object;
      13: checkcast     #19                 // class org/apache/tomcat/util/modeler/AttributeInfo
      16: astore        5
      18: aload         5
      20: ifnonnull     59
      23: new           #89                 // class javax/management/AttributeNotFoundException
      26: dup
      27: new           #50                 // class java/lang/StringBuilder
      30: dup
      31: invokespecial #51                 // Method java/lang/StringBuilder."<init>":()V
      34: ldc           #90                 // String  Cannot find attribute
      36: invokevirtual #53                 // Method java/lang/StringBuilder.append:(Ljava/lang/String;)Ljava/lang/StringBuilder;
      39: aload_1
      40: invokevirtual #53                 // Method java/lang/StringBuilder.append:(Ljava/lang/String;)Ljava/lang/StringBuilder;
      43: ldc           #91                 // String  for
      45: invokevirtual #53                 // Method java/lang/StringBuilder.append:(Ljava/lang/String;)Ljava/lang/StringBuilder;
      48: aload_3
      49: invokevirtual #92                 // Method java/lang/StringBuilder.append:(Ljava/lang/Object;)Ljava/lang/StringBuilder;
      52: invokevirtual #54                 // Method java/lang/StringBuilder.toString:()Ljava/lang/String;
      55: invokespecial #93                 // Method javax/management/AttributeNotFoundException."<init>":(Ljava/lang/String;)V
      58: athrow
      59: aload         5
      61: invokevirtual #94                 // Method org/apache/tomcat/util/modeler/AttributeInfo.getGetMethod:()Ljava/lang/String;
      64: astore        6
      66: aload         6
      68: ifnonnull     103
      71: new           #89                 // class javax/management/AttributeNotFoundException
      74: dup
      75: new           #50                 // class java/lang/StringBuilder
      78: dup
      79: invokespecial #51                 // Method java/lang/StringBuilder."<init>":()V
      82: ldc           #95                 // String Cannot find attribute
      84: invokevirtual #53                 // Method java/lang/StringBuilder.append:(Ljava/lang/String;)Ljava/lang/StringBuilder;
      87: aload_1
      88: invokevirtual #53                 // Method java/lang/StringBuilder.append:(Ljava/lang/String;)Ljava/lang/StringBuilder;
      91: ldc           #96                 // String  get method name
      93: invokevirtual #53                 // Method java/lang/StringBuilder.append:(Ljava/lang/String;)Ljava/lang/StringBuilder;
      96: invokevirtual #54                 // Method java/lang/StringBuilder.toString:()Ljava/lang/String;
      99: invokespecial #93                 // Method javax/management/AttributeNotFoundException."<init>":(Ljava/lang/String;)V
     102: athrow
     103: aconst_null
     104: astore        7
     106: aconst_null
     107: astore        8
     109: aload_2
     110: astore        7
     112: aload         7
     114: invokevirtual #97                 // Method java/lang/Object.getClass:()Ljava/lang/Class;
     117: aload         6
     119: getstatic     #98                 // Field NO_ARGS_PARAM_SIG:[Ljava/lang/Class;
     122: invokevirtual #99                 // Method java/lang/Class.getMethod:(Ljava/lang/String;[Ljava/lang/Class;)Ljava/lang/reflect/Method;
     125: astore        4
     127: goto          136
     130: astore        9
     132: aload         9
     134: astore        8
     136: aload         4
     138: ifnonnull     175
     141: aload_3
     142: ifnull        175
     145: aload_3
     146: astore        7
     148: aload         7
     150: invokevirtual #97                 // Method java/lang/Object.getClass:()Ljava/lang/Class;
     153: aload         6
     155: getstatic     #98                 // Field NO_ARGS_PARAM_SIG:[Ljava/lang/Class;
     158: invokevirtual #99                 // Method java/lang/Class.getMethod:(Ljava/lang/String;[Ljava/lang/Class;)Ljava/lang/reflect/Method;
     161: astore        4
     163: aconst_null
     164: astore        8
     166: goto          175
     169: astore        9
     171: aload         9
     173: astore        8
     175: aload         8
     177: ifnull        210
     180: new           #101                // class javax/management/ReflectionException
     183: dup
     184: aload         8
     186: new           #50                 // class java/lang/StringBuilder
     189: dup
     190: invokespecial #51                 // Method java/lang/StringBuilder."<init>":()V
     193: ldc           #102                // String Cannot find getter method
     195: invokevirtual #53                 // Method java/lang/StringBuilder.append:(Ljava/lang/String;)Ljava/lang/StringBuilder;
     198: aload         6
     200: invokevirtual #53                 // Method java/lang/StringBuilder.append:(Ljava/lang/String;)Ljava/lang/StringBuilder;
     203: invokevirtual #54                 // Method java/lang/StringBuilder.toString:()Ljava/lang/String;
     206: invokespecial #103                // Method javax/management/ReflectionException."<init>":(Ljava/lang/Exception;Ljava/lang/String;)V
     209: athrow
     210: aload         4
     212: areturn
    Exception table:
       from    to  target type
         109   127   130   Class java/lang/NoSuchMethodException
         145   166   169   Class java/lang/NoSuchMethodException

  public java.lang.reflect.Method getSetter(java.lang.String, org.apache.tomcat.util.modeler.BaseModelMBean, java.lang.Object) throws javax.management.AttributeNotFoundException, javax.management.ReflectionException;
    Code:
       0: aconst_null
       1: astore        4
       3: aload_0
       4: getfield      #8                  // Field attributes:Ljava/util/Map;
       7: aload_1
       8: invokeinterface #88,  2           // InterfaceMethod java/util/Map.get:(Ljava/lang/Object;)Ljava/lang/Object;
      13: checkcast     #19                 // class org/apache/tomcat/util/modeler/AttributeInfo
      16: astore        5
      18: aload         5
      20: ifnonnull     50
      23: new           #89                 // class javax/management/AttributeNotFoundException
      26: dup
      27: new           #50                 // class java/lang/StringBuilder
      30: dup
      31: invokespecial #51                 // Method java/lang/StringBuilder."<init>":()V
      34: ldc           #90                 // String  Cannot find attribute
      36: invokevirtual #53                 // Method java/lang/StringBuilder.append:(Ljava/lang/String;)Ljava/lang/StringBuilder;
      39: aload_1
      40: invokevirtual #53                 // Method java/lang/StringBuilder.append:(Ljava/lang/String;)Ljava/lang/StringBuilder;
      43: invokevirtual #54                 // Method java/lang/StringBuilder.toString:()Ljava/lang/String;
      46: invokespecial #93                 // Method javax/management/AttributeNotFoundException."<init>":(Ljava/lang/String;)V
      49: athrow
      50: aload         5
      52: invokevirtual #104                // Method org/apache/tomcat/util/modeler/AttributeInfo.getSetMethod:()Ljava/lang/String;
      55: astore        6
      57: aload         6
      59: ifnonnull     94
      62: new           #89                 // class javax/management/AttributeNotFoundException
      65: dup
      66: new           #50                 // class java/lang/StringBuilder
      69: dup
      70: invokespecial #51                 // Method java/lang/StringBuilder."<init>":()V
      73: ldc           #95                 // String Cannot find attribute
      75: invokevirtual #53                 // Method java/lang/StringBuilder.append:(Ljava/lang/String;)Ljava/lang/StringBuilder;
      78: aload_1
      79: invokevirtual #53                 // Method java/lang/StringBuilder.append:(Ljava/lang/String;)Ljava/lang/StringBuilder;
      82: ldc           #105                // String  set method name
      84: invokevirtual #53                 // Method java/lang/StringBuilder.append:(Ljava/lang/String;)Ljava/lang/StringBuilder;
      87: invokevirtual #54                 // Method java/lang/StringBuilder.toString:()Ljava/lang/String;
      90: invokespecial #93                 // Method javax/management/AttributeNotFoundException."<init>":(Ljava/lang/String;)V
      93: athrow
      94: aload         5
      96: invokevirtual #106                // Method org/apache/tomcat/util/modeler/AttributeInfo.getType:()Ljava/lang/String;
      99: astore        7
     101: iconst_1
     102: anewarray     #56                 // class java/lang/Class
     105: dup
     106: iconst_0
     107: aload         7
     109: invokestatic  #107                // Method org/apache/tomcat/util/modeler/BaseModelMBean.getAttributeClass:(Ljava/lang/String;)Ljava/lang/Class;
     112: aastore
     113: astore        8
     115: aconst_null
     116: astore        9
     118: aconst_null
     119: astore        10
     121: aload_2
     122: astore        9
     124: aload         9
     126: invokevirtual #97                 // Method java/lang/Object.getClass:()Ljava/lang/Class;
     129: aload         6
     131: aload         8
     133: invokevirtual #99                 // Method java/lang/Class.getMethod:(Ljava/lang/String;[Ljava/lang/Class;)Ljava/lang/reflect/Method;
     136: astore        4
     138: goto          147
     141: astore        11
     143: aload         11
     145: astore        10
     147: aload         4
     149: ifnonnull     185
     152: aload_3
     153: ifnull        185
     156: aload_3
     157: astore        9
     159: aload         9
     161: invokevirtual #97                 // Method java/lang/Object.getClass:()Ljava/lang/Class;
     164: aload         6
     166: aload         8
     168: invokevirtual #99                 // Method java/lang/Class.getMethod:(Ljava/lang/String;[Ljava/lang/Class;)Ljava/lang/reflect/Method;
     171: astore        4
     173: aconst_null
     174: astore        10
     176: goto          185
     179: astore        11
     181: aload         11
     183: astore        10
     185: aload         10
     187: ifnull        229
     190: new           #101                // class javax/management/ReflectionException
     193: dup
     194: aload         10
     196: new           #50                 // class java/lang/StringBuilder
     199: dup
     200: invokespecial #51                 // Method java/lang/StringBuilder."<init>":()V
     203: ldc           #108                // String Cannot find setter method
     205: invokevirtual #53                 // Method java/lang/StringBuilder.append:(Ljava/lang/String;)Ljava/lang/StringBuilder;
     208: aload         6
     210: invokevirtual #53                 // Method java/lang/StringBuilder.append:(Ljava/lang/String;)Ljava/lang/StringBuilder;
     213: ldc           #109                // String
     215: invokevirtual #53                 // Method java/lang/StringBuilder.append:(Ljava/lang/String;)Ljava/lang/StringBuilder;
     218: aload_3
     219: invokevirtual #92                 // Method java/lang/StringBuilder.append:(Ljava/lang/Object;)Ljava/lang/StringBuilder;
     222: invokevirtual #54                 // Method java/lang/StringBuilder.toString:()Ljava/lang/String;
     225: invokespecial #103                // Method javax/management/ReflectionException."<init>":(Ljava/lang/Exception;Ljava/lang/String;)V
     228: athrow
     229: aload         4
     231: areturn
    Exception table:
       from    to  target type
         121   138   141   Class java/lang/NoSuchMethodException
         156   176   179   Class java/lang/NoSuchMethodException

  public java.lang.reflect.Method getInvoke(java.lang.String, java.lang.Object[], java.lang.String[], org.apache.tomcat.util.modeler.BaseModelMBean, java.lang.Object) throws javax.management.MBeanException, javax.management.ReflectionException;
    Code:
       0: aconst_null
       1: astore        6
       3: aload_2
       4: ifnonnull     12
       7: iconst_0
       8: anewarray     #58                 // class java/lang/Object
      11: astore_2
      12: aload_3
      13: ifnonnull     21
      16: iconst_0
      17: anewarray     #110                // class java/lang/String
      20: astore_3
      21: aload_2
      22: arraylength
      23: aload_3
      24: arraylength
      25: if_icmpeq     47
      28: new           #60                 // class javax/management/RuntimeOperationsException
      31: dup
      32: new           #111                // class java/lang/IllegalArgumentException
      35: dup
      36: ldc           #112                // String Inconsistent arguments and signature
      38: invokespecial #113                // Method java/lang/IllegalArgumentException."<init>":(Ljava/lang/String;)V
      41: ldc           #112                // String Inconsistent arguments and signature
      43: invokespecial #114                // Method javax/management/RuntimeOperationsException."<init>":(Ljava/lang/RuntimeException;Ljava/lang/String;)V
      46: athrow
      47: aload_0
      48: getfield      #9                  // Field operations:Ljava/util/Map;
      51: aload_0
      52: aload_1
      53: aload_3
      54: invokespecial #115                // Method createOperationKey:(Ljava/lang/String;[Ljava/lang/String;)Ljava/lang/String;
      57: invokeinterface #88,  2           // InterfaceMethod java/util/Map.get:(Ljava/lang/Object;)Ljava/lang/Object;
      62: checkcast     #35                 // class org/apache/tomcat/util/modeler/OperationInfo
      65: astore        7
      67: aload         7
      69: ifnonnull     125
      72: new           #49                 // class javax/management/MBeanException
      75: dup
      76: new           #116                // class javax/management/ServiceNotFoundException
      79: dup
      80: new           #50                 // class java/lang/StringBuilder
      83: dup
      84: invokespecial #51                 // Method java/lang/StringBuilder."<init>":()V
      87: ldc           #117                // String Cannot find operation
      89: invokevirtual #53                 // Method java/lang/StringBuilder.append:(Ljava/lang/String;)Ljava/lang/StringBuilder;
      92: aload_1
      93: invokevirtual #53                 // Method java/lang/StringBuilder.append:(Ljava/lang/String;)Ljava/lang/StringBuilder;
      96: invokevirtual #54                 // Method java/lang/StringBuilder.toString:()Ljava/lang/String;
      99: invokespecial #118                // Method javax/management/ServiceNotFoundException."<init>":(Ljava/lang/String;)V
     102: new           #50                 // class java/lang/StringBuilder
     105: dup
     106: invokespecial #51                 // Method java/lang/StringBuilder."<init>":()V
     109: ldc           #117                // String Cannot find operation
     111: invokevirtual #53                 // Method java/lang/StringBuilder.append:(Ljava/lang/String;)Ljava/lang/StringBuilder;
     114: aload_1
     115: invokevirtual #53                 // Method java/lang/StringBuilder.append:(Ljava/lang/String;)Ljava/lang/StringBuilder;
     118: invokevirtual #54                 // Method java/lang/StringBuilder.toString:()Ljava/lang/String;
     121: invokespecial #55                 // Method javax/management/MBeanException."<init>":(Ljava/lang/Exception;Ljava/lang/String;)V
     124: athrow
     125: aload_3
     126: arraylength
     127: anewarray     #56                 // class java/lang/Class
     130: astore        8
     132: iconst_0
     133: istore        9
     135: iload         9
     137: aload_3
     138: arraylength
     139: if_icmpge     160
     142: aload         8
     144: iload         9
     146: aload_3
     147: iload         9
     149: aaload
     150: invokestatic  #107                // Method org/apache/tomcat/util/modeler/BaseModelMBean.getAttributeClass:(Ljava/lang/String;)Ljava/lang/Class;
     153: aastore
     154: iinc          9, 1
     157: goto          135
     160: aconst_null
     161: astore        9
     163: aconst_null
     164: astore        10
     166: aload         4
     168: astore        9
     170: aload         9
     172: invokevirtual #97                 // Method java/lang/Object.getClass:()Ljava/lang/Class;
     175: aload_1
     176: aload         8
     178: invokevirtual #99                 // Method java/lang/Class.getMethod:(Ljava/lang/String;[Ljava/lang/Class;)Ljava/lang/reflect/Method;
     181: astore        6
     183: goto          192
     186: astore        11
     188: aload         11
     190: astore        10
     192: aload         6
     194: ifnonnull     219
     197: aload         5
     199: ifnull        219
     202: aload         5
     204: astore        9
     206: aload         9
     208: invokevirtual #97                 // Method java/lang/Object.getClass:()Ljava/lang/Class;
     211: aload_1
     212: aload         8
     214: invokevirtual #99                 // Method java/lang/Class.getMethod:(Ljava/lang/String;[Ljava/lang/Class;)Ljava/lang/reflect/Method;
     217: astore        6
     219: goto          228
     222: astore        11
     224: aload         11
     226: astore        10
     228: aload         6
     230: ifnonnull     267
     233: new           #101                // class javax/management/ReflectionException
     236: dup
     237: aload         10
     239: new           #50                 // class java/lang/StringBuilder
     242: dup
     243: invokespecial #51                 // Method java/lang/StringBuilder."<init>":()V
     246: ldc           #119                // String Cannot find method
     248: invokevirtual #53                 // Method java/lang/StringBuilder.append:(Ljava/lang/String;)Ljava/lang/StringBuilder;
     251: aload_1
     252: invokevirtual #53                 // Method java/lang/StringBuilder.append:(Ljava/lang/String;)Ljava/lang/StringBuilder;
     255: ldc           #120                // String  with this signature
     257: invokevirtual #53                 // Method java/lang/StringBuilder.append:(Ljava/lang/String;)Ljava/lang/StringBuilder;
     260: invokevirtual #54                 // Method java/lang/StringBuilder.toString:()Ljava/lang/String;
     263: invokespecial #103                // Method javax/management/ReflectionException."<init>":(Ljava/lang/Exception;Ljava/lang/String;)V
     266: athrow
     267: aload         6
     269: areturn
    Exception table:
       from    to  target type
         166   183   186   Class java/lang/NoSuchMethodException
         192   219   222   Class java/lang/NoSuchMethodException

  private java.lang.String createOperationKey(org.apache.tomcat.util.modeler.OperationInfo);
    Code:
       0: new           #50                 // class java/lang/StringBuilder
       3: dup
       4: aload_1
       5: invokevirtual #121                // Method org/apache/tomcat/util/modeler/OperationInfo.getName:()Ljava/lang/String;
       8: invokespecial #81                 // Method java/lang/StringBuilder."<init>":(Ljava/lang/String;)V
      11: astore_2
      12: aload_2
      13: bipush        40
      15: invokevirtual #122                // Method java/lang/StringBuilder.append:(C)Ljava/lang/StringBuilder;
      18: pop
      19: aload_1
      20: invokevirtual #123                // Method org/apache/tomcat/util/modeler/OperationInfo.getSignature:()[Lorg/apache/tomcat/util/modeler/ParameterInfo;
      23: bipush        44
      25: new           #124                // class org/apache/tomcat/util/modeler/ManagedBean$1
      28: dup
      29: aload_0
      30: invokespecial #125                // Method org/apache/tomcat/util/modeler/ManagedBean$1."<init>":(Lorg/apache/tomcat/util/modeler/ManagedBean;)V
      33: aload_2
      34: invokestatic  #126                // Method org/apache/tomcat/util/buf/StringUtils.join:([Ljava/lang/Object;CLorg/apache/tomcat/util/buf/StringUtils$Function;Ljava/lang/StringBuilder;)V
      37: aload_2
      38: bipush        41
      40: invokevirtual #122                // Method java/lang/StringBuilder.append:(C)Ljava/lang/StringBuilder;
      43: pop
      44: aload_2
      45: invokevirtual #54                 // Method java/lang/StringBuilder.toString:()Ljava/lang/String;
      48: invokevirtual #127                // Method java/lang/String.intern:()Ljava/lang/String;
      51: areturn

  private java.lang.String createOperationKey(java.lang.String, java.lang.String[]);
    Code:
       0: new           #50                 // class java/lang/StringBuilder
       3: dup
       4: aload_1
       5: invokespecial #81                 // Method java/lang/StringBuilder."<init>":(Ljava/lang/String;)V
       8: astore_3
       9: aload_3
      10: bipush        40
      12: invokevirtual #122                // Method java/lang/StringBuilder.append:(C)Ljava/lang/StringBuilder;
      15: pop
      16: aload_2
      17: bipush        44
      19: aload_3
      20: invokestatic  #128                // Method org/apache/tomcat/util/buf/StringUtils.join:([Ljava/lang/String;CLjava/lang/StringBuilder;)V
      23: aload_3
      24: bipush        41
      26: invokevirtual #122                // Method java/lang/StringBuilder.append:(C)Ljava/lang/StringBuilder;
      29: pop
      30: aload_3
      31: invokevirtual #54                 // Method java/lang/StringBuilder.toString:()Ljava/lang/String;
      34: invokevirtual #127                // Method java/lang/String.intern:()Ljava/lang/String;
      37: areturn

  static {};
    Code:
       0: iconst_0
       1: anewarray     #56                 // class java/lang/Class
       4: putstatic     #98                 // Field NO_ARGS_PARAM_SIG:[Ljava/lang/Class;
       7: return
}
