Compiled from "BeanValidator.java"
public abstract class info.archinnov.achilles.internals.parser.validator.BeanValidator {
  public final java.util.List<java.lang.String> RESERVED_KEYWORDS;

  public info.archinnov.achilles.internals.parser.validator.BeanValidator();
    Code:
       0: aload_0
       1: invokespecial #1                  // Method java/lang/Object."<init>":()V
       4: aload_0
       5: ldc           #2                  // String add,allow,alter,and,any,apply,asc,authorize,batch,begin,by,columnfamily,create,delete,desc,drop,each_quorum,from,grant,in,index,inet,infinity,insert,into,keyspace,keyspaces,limit,local_one,local_quorum,modify,nan,norecursive,of,on,order,primary,quorum,rename,revoke,schema,select,set,table,three,to,token,truncate,two,unlogged,update,use,using,where,with
       7: ldc           #3                  // String ,
       9: invokevirtual #4                  // Method java/lang/String.split:(Ljava/lang/String;)[Ljava/lang/String;
      12: invokestatic  #5                  // Method java/util/Arrays.asList:([Ljava/lang/Object;)Ljava/util/List;
      15: putfield      #6                  // Field RESERVED_KEYWORDS:Ljava/util/List;
      18: return

  public void validateEntityNames(info.archinnov.achilles.internals.apt.AptUtils, java.util.List<javax.lang.model.element.TypeElement>);
    Code:
       0: new           #7                  // class org/apache/commons/collections/map/HashedMap
       3: dup
       4: invokespecial #8                  // Method org/apache/commons/collections/map/HashedMap."<init>":()V
       7: astore_3
       8: aload_2
       9: invokeinterface #9,  1            // InterfaceMethod java/util/List.iterator:()Ljava/util/Iterator;
      14: astore        4
      16: aload         4
      18: invokeinterface #10,  1           // InterfaceMethod java/util/Iterator.hasNext:()Z
      23: ifeq          147
      26: aload         4
      28: invokeinterface #11,  1           // InterfaceMethod java/util/Iterator.next:()Ljava/lang/Object;
      33: checkcast     #12                 // class javax/lang/model/element/TypeElement
      36: astore        5
      38: aload         5
      40: invokeinterface #13,  1           // InterfaceMethod javax/lang/model/element/TypeElement.getSimpleName:()Ljavax/lang/model/element/Name;
      45: invokevirtual #14                 // Method java/lang/Object.toString:()Ljava/lang/String;
      48: astore        6
      50: aload         5
      52: invokeinterface #15,  1           // InterfaceMethod javax/lang/model/element/TypeElement.getQualifiedName:()Ljavax/lang/model/element/Name;
      57: invokevirtual #14                 // Method java/lang/Object.toString:()Ljava/lang/String;
      60: astore        7
      62: aload_3
      63: aload         6
      65: invokeinterface #16,  2           // InterfaceMethod java/util/Map.containsKey:(Ljava/lang/Object;)Z
      70: ifeq          133
      73: aload_3
      74: aload         6
      76: invokeinterface #17,  2           // InterfaceMethod java/util/Map.get:(Ljava/lang/Object;)Ljava/lang/Object;
      81: checkcast     #18                 // class java/lang/String
      84: astore        8
      86: aload_1
      87: ldc           #19                 // String %s and %s both share the same class name, it is forbidden by Achilles
      89: iconst_2
      90: anewarray     #20                 // class java/lang/Object
      93: dup
      94: iconst_0
      95: aload         7
      97: aastore
      98: dup
      99: iconst_1
     100: aload         8
     102: aastore
     103: invokevirtual #21                 // Method info/archinnov/achilles/internals/apt/AptUtils.printError:(Ljava/lang/String;[Ljava/lang/Object;)V
     106: new           #22                 // class java/lang/IllegalStateException
     109: dup
     110: ldc           #19                 // String %s and %s both share the same class name, it is forbidden by Achilles
     112: iconst_2
     113: anewarray     #20                 // class java/lang/Object
     116: dup
     117: iconst_0
     118: aload         7
     120: aastore
     121: dup
     122: iconst_1
     123: aload         8
     125: aastore
     126: invokestatic  #23                 // Method java/lang/String.format:(Ljava/lang/String;[Ljava/lang/Object;)Ljava/lang/String;
     129: invokespecial #24                 // Method java/lang/IllegalStateException."<init>":(Ljava/lang/String;)V
     132: athrow
     133: aload_3
     134: aload         6
     136: aload         7
     138: invokeinterface #25,  3           // InterfaceMethod java/util/Map.put:(Ljava/lang/Object;Ljava/lang/Object;)Ljava/lang/Object;
     143: pop
     144: goto          16
     147: return

  public void validateIsAConcreteNonFinalClass(info.archinnov.achilles.internals.apt.AptUtils, javax.lang.model.element.TypeElement);
    Code:
       0: aload_2
       1: invokeinterface #15,  1           // InterfaceMethod javax/lang/model/element/TypeElement.getQualifiedName:()Ljavax/lang/model/element/Name;
       6: astore_3
       7: aload_1
       8: aload_2
       9: invokeinterface #26,  1           // InterfaceMethod javax/lang/model/element/TypeElement.getKind:()Ljavax/lang/model/element/ElementKind;
      14: getstatic     #27                 // Field javax/lang/model/element/ElementKind.CLASS:Ljavax/lang/model/element/ElementKind;
      17: if_acmpne     24
      20: iconst_1
      21: goto          25
      24: iconst_0
      25: ldc           #28                 // String Bean type \'%s\' should be a class
      27: iconst_1
      28: anewarray     #20                 // class java/lang/Object
      31: dup
      32: iconst_0
      33: aload_3
      34: aastore
      35: invokevirtual #29                 // Method info/archinnov/achilles/internals/apt/AptUtils.validateTrue:(ZLjava/lang/String;[Ljava/lang/Object;)V
      38: aload_2
      39: invokeinterface #30,  1           // InterfaceMethod javax/lang/model/element/TypeElement.getModifiers:()Ljava/util/Set;
      44: astore        4
      46: aload_1
      47: aload         4
      49: getstatic     #31                 // Field javax/lang/model/element/Modifier.ABSTRACT:Ljavax/lang/model/element/Modifier;
      52: invokeinterface #32,  2           // InterfaceMethod java/util/Set.contains:(Ljava/lang/Object;)Z
      57: ldc           #33                 // String Bean type \'%s\' should not be abstract
      59: iconst_1
      60: anewarray     #20                 // class java/lang/Object
      63: dup
      64: iconst_0
      65: aload_3
      66: aastore
      67: invokevirtual #34                 // Method info/archinnov/achilles/internals/apt/AptUtils.validateFalse:(ZLjava/lang/String;[Ljava/lang/Object;)V
      70: aload_1
      71: aload         4
      73: getstatic     #35                 // Field javax/lang/model/element/Modifier.FINAL:Ljavax/lang/model/element/Modifier;
      76: invokeinterface #32,  2           // InterfaceMethod java/util/Set.contains:(Ljava/lang/Object;)Z
      81: ldc           #36                 // String Bean type \'%s\' should not be final
      83: iconst_1
      84: anewarray     #20                 // class java/lang/Object
      87: dup
      88: iconst_0
      89: aload_3
      90: aastore
      91: invokevirtual #34                 // Method info/archinnov/achilles/internals/apt/AptUtils.validateFalse:(ZLjava/lang/String;[Ljava/lang/Object;)V
      94: return

  public void validateHasPublicConstructor(info.archinnov.achilles.internals.apt.AptUtils, com.squareup.javapoet.TypeName, javax.lang.model.element.TypeElement);
    Code:
       0: aload_3
       1: invokeinterface #37,  1           // InterfaceMethod javax/lang/model/element/TypeElement.getEnclosedElements:()Ljava/util/List;
       6: invokestatic  #38                 // Method javax/lang/model/util/ElementFilter.constructorsIn:(Ljava/lang/Iterable;)Ljava/util/List;
       9: invokeinterface #39,  1           // InterfaceMethod java/util/List.stream:()Ljava/util/stream/Stream;
      14: invokedynamic #40,  0             // InvokeDynamic #0:test:()Ljava/util/function/Predicate;
      19: invokeinterface #41,  2           // InterfaceMethod java/util/stream/Stream.filter:(Ljava/util/function/Predicate;)Ljava/util/stream/Stream;
      24: invokedynamic #42,  0             // InvokeDynamic #1:test:()Ljava/util/function/Predicate;
      29: invokeinterface #41,  2           // InterfaceMethod java/util/stream/Stream.filter:(Ljava/util/function/Predicate;)Ljava/util/stream/Stream;
      34: invokeinterface #43,  1           // InterfaceMethod java/util/stream/Stream.count:()J
      39: lstore        4
      41: aload_1
      42: lload         4
      44: lconst_1
      45: lcmp
      46: ifne          53
      49: iconst_1
      50: goto          54
      53: iconst_0
      54: ldc           #44                 // String Bean type \'%s\' should have a public no-args constructor
      56: iconst_1
      57: anewarray     #20                 // class java/lang/Object
      60: dup
      61: iconst_0
      62: aload_2
      63: aastore
      64: invokevirtual #29                 // Method info/archinnov/achilles/internals/apt/AptUtils.validateTrue:(ZLjava/lang/String;[Ljava/lang/Object;)V
      67: return

  public void validateNoDuplicateNames(info.archinnov.achilles.internals.apt.AptUtils, com.squareup.javapoet.TypeName, java.util.List<info.archinnov.achilles.internals.parser.FieldParser$FieldMetaSignature>);
    Code:
       0: new           #45                 // class java/util/HashMap
       3: dup
       4: invokespecial #46                 // Method java/util/HashMap."<init>":()V
       7: astore        4
       9: aload_3
      10: invokeinterface #39,  1           // InterfaceMethod java/util/List.stream:()Ljava/util/stream/Stream;
      15: invokedynamic #47,  0             // InvokeDynamic #2:apply:()Ljava/util/function/Function;
      20: invokeinterface #48,  2           // InterfaceMethod java/util/stream/Stream.map:(Ljava/util/function/Function;)Ljava/util/stream/Stream;
      25: aload         4
      27: aload_1
      28: aload_2
      29: invokedynamic #49,  0             // InvokeDynamic #3:accept:(Ljava/util/Map;Linfo/archinnov/achilles/internals/apt/AptUtils;Lcom/squareup/javapoet/TypeName;)Ljava/util/function/Consumer;
      34: invokeinterface #50,  2           // InterfaceMethod java/util/stream/Stream.forEach:(Ljava/util/function/Consumer;)V
      39: return

  public void validateCqlColumnNotReservedWords(info.archinnov.achilles.internals.apt.AptUtils, com.squareup.javapoet.TypeName, java.util.List<info.archinnov.achilles.internals.parser.FieldParser$FieldMetaSignature>);
    Code:
       0: aload_3
       1: invokeinterface #39,  1           // InterfaceMethod java/util/List.stream:()Ljava/util/stream/Stream;
       6: invokedynamic #51,  0             // InvokeDynamic #4:apply:()Ljava/util/function/Function;
      11: invokeinterface #48,  2           // InterfaceMethod java/util/stream/Stream.map:(Ljava/util/function/Function;)Ljava/util/stream/Stream;
      16: aload_0
      17: aload_1
      18: aload_2
      19: invokedynamic #52,  0             // InvokeDynamic #5:accept:(Linfo/archinnov/achilles/internals/parser/validator/BeanValidator;Linfo/archinnov/achilles/internals/apt/AptUtils;Lcom/squareup/javapoet/TypeName;)Ljava/util/function/Consumer;
      24: invokeinterface #50,  2           // InterfaceMethod java/util/stream/Stream.forEach:(Ljava/util/function/Consumer;)V
      29: return

  public void validateStaticColumns(info.archinnov.achilles.internals.apt.AptUtils, com.squareup.javapoet.TypeName, java.util.List<info.archinnov.achilles.internals.parser.FieldParser$FieldMetaSignature>);
    Code:
       0: aload_3
       1: invokeinterface #39,  1           // InterfaceMethod java/util/List.stream:()Ljava/util/stream/Stream;
       6: invokedynamic #53,  0             // InvokeDynamic #6:test:()Ljava/util/function/Predicate;
      11: invokeinterface #41,  2           // InterfaceMethod java/util/stream/Stream.filter:(Ljava/util/function/Predicate;)Ljava/util/stream/Stream;
      16: invokeinterface #43,  1           // InterfaceMethod java/util/stream/Stream.count:()J
      21: lconst_0
      22: lcmp
      23: ifle          30
      26: iconst_1
      27: goto          31
      30: iconst_0
      31: istore        4
      33: aload_3
      34: invokeinterface #39,  1           // InterfaceMethod java/util/List.stream:()Ljava/util/stream/Stream;
      39: invokedynamic #54,  0             // InvokeDynamic #7:test:()Ljava/util/function/Predicate;
      44: invokeinterface #41,  2           // InterfaceMethod java/util/stream/Stream.filter:(Ljava/util/function/Predicate;)Ljava/util/stream/Stream;
      49: invokeinterface #43,  1           // InterfaceMethod java/util/stream/Stream.count:()J
      54: lconst_0
      55: lcmp
      56: ifle          63
      59: iconst_1
      60: goto          64
      63: iconst_0
      64: istore        5
      66: iload         4
      68: ifeq          87
      71: aload_1
      72: iload         5
      74: ldc           #55                 // String The class \'%s\' cannot have static columns without at least 1 clustering column
      76: iconst_1
      77: anewarray     #20                 // class java/lang/Object
      80: dup
      81: iconst_0
      82: aload_2
      83: aastore
      84: invokevirtual #29                 // Method info/archinnov/achilles/internals/apt/AptUtils.validateTrue:(ZLjava/lang/String;[Ljava/lang/Object;)V
      87: return

  public void validateNoStaticColumnsForView(info.archinnov.achilles.internals.apt.AptUtils, com.squareup.javapoet.TypeName, java.util.List<info.archinnov.achilles.internals.parser.FieldParser$FieldMetaSignature>);
    Code:
       0: return

  public void validateHasPartitionKey(info.archinnov.achilles.internals.apt.AptUtils, com.squareup.javapoet.TypeName, java.util.List<info.archinnov.achilles.internals.parser.FieldParser$FieldMetaSignature>);
    Code:
       0: aload_3
       1: invokeinterface #39,  1           // InterfaceMethod java/util/List.stream:()Ljava/util/stream/Stream;
       6: invokedynamic #56,  0             // InvokeDynamic #8:test:()Ljava/util/function/Predicate;
      11: invokeinterface #41,  2           // InterfaceMethod java/util/stream/Stream.filter:(Ljava/util/function/Predicate;)Ljava/util/stream/Stream;
      16: invokeinterface #43,  1           // InterfaceMethod java/util/stream/Stream.count:()J
      21: lconst_0
      22: lcmp
      23: ifle          30
      26: iconst_1
      27: goto          31
      30: iconst_0
      31: istore        4
      33: aload_1
      34: iload         4
      36: ldc           #57                 // String The class \'%s\' should have at least 1 partition key (@PartitionKey)
      38: iconst_1
      39: anewarray     #20                 // class java/lang/Object
      42: dup
      43: iconst_0
      44: aload_2
      45: aastore
      46: invokevirtual #29                 // Method info/archinnov/achilles/internals/apt/AptUtils.validateTrue:(ZLjava/lang/String;[Ljava/lang/Object;)V
      49: return

  public boolean isCounterTable(info.archinnov.achilles.internals.apt.AptUtils, com.squareup.javapoet.TypeName, java.util.List<info.archinnov.achilles.internals.parser.FieldParser$FieldMetaSignature>);
    Code:
       0: aload_3
       1: invokeinterface #39,  1           // InterfaceMethod java/util/List.stream:()Ljava/util/stream/Stream;
       6: invokedynamic #58,  0             // InvokeDynamic #9:test:()Ljava/util/function/Predicate;
      11: invokeinterface #41,  2           // InterfaceMethod java/util/stream/Stream.filter:(Ljava/util/function/Predicate;)Ljava/util/stream/Stream;
      16: invokeinterface #43,  1           // InterfaceMethod java/util/stream/Stream.count:()J
      21: lconst_0
      22: lcmp
      23: ifle          30
      26: iconst_1
      27: goto          31
      30: iconst_0
      31: istore        4
      33: aload_3
      34: invokeinterface #39,  1           // InterfaceMethod java/util/List.stream:()Ljava/util/stream/Stream;
      39: invokedynamic #59,  0             // InvokeDynamic #10:test:()Ljava/util/function/Predicate;
      44: invokeinterface #41,  2           // InterfaceMethod java/util/stream/Stream.filter:(Ljava/util/function/Predicate;)Ljava/util/stream/Stream;
      49: invokeinterface #43,  1           // InterfaceMethod java/util/stream/Stream.count:()J
      54: lconst_0
      55: lcmp
      56: ifle          63
      59: iconst_1
      60: goto          64
      63: iconst_0
      64: istore        5
      66: aload_3
      67: invokeinterface #39,  1           // InterfaceMethod java/util/List.stream:()Ljava/util/stream/Stream;
      72: invokedynamic #60,  0             // InvokeDynamic #11:test:()Ljava/util/function/Predicate;
      77: invokeinterface #41,  2           // InterfaceMethod java/util/stream/Stream.filter:(Ljava/util/function/Predicate;)Ljava/util/stream/Stream;
      82: invokeinterface #43,  1           // InterfaceMethod java/util/stream/Stream.count:()J
      87: lconst_0
      88: lcmp
      89: ifle          96
      92: iconst_1
      93: goto          97
      96: iconst_0
      97: istore        6
      99: iload         4
     101: ifne          109
     104: iload         5
     106: ifeq          125
     109: aload_1
     110: iload         6
     112: ldc           #61                 // String Class \'%s\' should not mix counter and normal columns
     114: iconst_1
     115: anewarray     #20                 // class java/lang/Object
     118: dup
     119: iconst_0
     120: aload_2
     121: aastore
     122: invokevirtual #34                 // Method info/archinnov/achilles/internals/apt/AptUtils.validateFalse:(ZLjava/lang/String;[Ljava/lang/Object;)V
     125: iload         4
     127: ifne          135
     130: iload         5
     132: ifeq          139
     135: iconst_1
     136: goto          140
     139: iconst_0
     140: ireturn

  public void validateComputed(info.archinnov.achilles.internals.apt.AptUtils, com.squareup.javapoet.TypeName, java.util.List<info.archinnov.achilles.internals.parser.FieldParser$FieldMetaSignature>);
    Code:
       0: aload_3
       1: invokeinterface #39,  1           // InterfaceMethod java/util/List.stream:()Ljava/util/stream/Stream;
       6: invokedynamic #62,  0             // InvokeDynamic #12:apply:()Ljava/util/function/Function;
      11: invokeinterface #48,  2           // InterfaceMethod java/util/stream/Stream.map:(Ljava/util/function/Function;)Ljava/util/stream/Stream;
      16: invokestatic  #63                 // Method java/util/stream/Collectors.toList:()Ljava/util/stream/Collector;
      19: invokeinterface #64,  2           // InterfaceMethod java/util/stream/Stream.collect:(Ljava/util/stream/Collector;)Ljava/lang/Object;
      24: checkcast     #65                 // class java/util/List
      27: astore        4
      29: new           #66                 // class java/util/HashSet
      32: dup
      33: invokespecial #67                 // Method java/util/HashSet."<init>":()V
      36: astore        5
      38: aload_3
      39: invokeinterface #39,  1           // InterfaceMethod java/util/List.stream:()Ljava/util/stream/Stream;
      44: invokedynamic #68,  0             // InvokeDynamic #13:test:()Ljava/util/function/Predicate;
      49: invokeinterface #41,  2           // InterfaceMethod java/util/stream/Stream.filter:(Ljava/util/function/Predicate;)Ljava/util/stream/Stream;
      54: invokedynamic #69,  0             // InvokeDynamic #14:apply:()Ljava/util/function/Function;
      59: invokeinterface #48,  2           // InterfaceMethod java/util/stream/Stream.map:(Ljava/util/function/Function;)Ljava/util/stream/Stream;
      64: aload_1
      65: aload         5
      67: invokedynamic #70,  0             // InvokeDynamic #15:accept:(Linfo/archinnov/achilles/internals/apt/AptUtils;Ljava/util/Set;)Ljava/util/function/Consumer;
      72: invokeinterface #50,  2           // InterfaceMethod java/util/stream/Stream.forEach:(Ljava/util/function/Consumer;)V
      77: aload_3
      78: invokeinterface #39,  1           // InterfaceMethod java/util/List.stream:()Ljava/util/stream/Stream;
      83: invokedynamic #71,  0             // InvokeDynamic #16:test:()Ljava/util/function/Predicate;
      88: invokeinterface #41,  2           // InterfaceMethod java/util/stream/Stream.filter:(Ljava/util/function/Predicate;)Ljava/util/stream/Stream;
      93: aload_1
      94: aload         4
      96: aload_2
      97: invokedynamic #72,  0             // InvokeDynamic #17:accept:(Linfo/archinnov/achilles/internals/apt/AptUtils;Ljava/util/List;Lcom/squareup/javapoet/TypeName;)Ljava/util/function/Consumer;
     102: invokeinterface #50,  2           // InterfaceMethod java/util/stream/Stream.forEach:(Ljava/util/function/Consumer;)V
     107: return

  public void validateViewsAgainstBaseTable(info.archinnov.achilles.internals.apt.AptUtils, java.util.List<info.archinnov.achilles.internals.codegen.meta.EntityMetaCodeGen$EntityMetaSignature>, java.util.List<info.archinnov.achilles.internals.codegen.meta.EntityMetaCodeGen$EntityMetaSignature>);
    Code:
       0: return

  private static void lambda$validateComputed$123(info.archinnov.achilles.internals.apt.AptUtils, java.util.List, com.squareup.javapoet.TypeName, info.archinnov.achilles.internals.parser.FieldParser$FieldMetaSignature);
    Code:
       0: aload_3
       1: getfield      #73                 // Field info/archinnov/achilles/internals/parser/FieldParser$FieldMetaSignature.context:Linfo/archinnov/achilles/internals/parser/context/FieldParsingContext;
       4: getfield      #74                 // Field info/archinnov/achilles/internals/parser/context/FieldParsingContext.columnInfo:Linfo/archinnov/achilles/internals/metamodel/columns/ColumnInfo;
       7: checkcast     #75                 // class info/archinnov/achilles/internals/metamodel/columns/ComputedColumnInfo
      10: astore        4
      12: aload         4
      14: getfield      #76                 // Field info/archinnov/achilles/internals/metamodel/columns/ComputedColumnInfo.functionArgs:Ljava/util/List;
      17: invokeinterface #9,  1            // InterfaceMethod java/util/List.iterator:()Ljava/util/Iterator;
      22: astore        5
      24: aload         5
      26: invokeinterface #10,  1           // InterfaceMethod java/util/Iterator.hasNext:()Z
      31: ifeq          86
      34: aload         5
      36: invokeinterface #11,  1           // InterfaceMethod java/util/Iterator.next:()Ljava/lang/Object;
      41: checkcast     #18                 // class java/lang/String
      44: astore        6
      46: aload_0
      47: aload_1
      48: aload         6
      50: invokeinterface #77,  2           // InterfaceMethod java/util/List.contains:(Ljava/lang/Object;)Z
      55: ldc           #78                 // String Target field \'%s\' in @Computed annotation of field \'%s\' of class \'%s\' does not exist
      57: iconst_3
      58: anewarray     #20                 // class java/lang/Object
      61: dup
      62: iconst_0
      63: aload         6
      65: aastore
      66: dup
      67: iconst_1
      68: aload_3
      69: getfield      #73                 // Field info/archinnov/achilles/internals/parser/FieldParser$FieldMetaSignature.context:Linfo/archinnov/achilles/internals/parser/context/FieldParsingContext;
      72: getfield      #79                 // Field info/archinnov/achilles/internals/parser/context/FieldParsingContext.fieldName:Ljava/lang/String;
      75: aastore
      76: dup
      77: iconst_2
      78: aload_2
      79: aastore
      80: invokevirtual #29                 // Method info/archinnov/achilles/internals/apt/AptUtils.validateTrue:(ZLjava/lang/String;[Ljava/lang/Object;)V
      83: goto          24
      86: return

  private static boolean lambda$validateComputed$122(info.archinnov.achilles.internals.parser.FieldParser$FieldMetaSignature);
    Code:
       0: aload_0
       1: getfield      #73                 // Field info/archinnov/achilles/internals/parser/FieldParser$FieldMetaSignature.context:Linfo/archinnov/achilles/internals/parser/context/FieldParsingContext;
       4: getfield      #80                 // Field info/archinnov/achilles/internals/parser/context/FieldParsingContext.columnType:Linfo/archinnov/achilles/internals/metamodel/columns/ColumnType;
       7: getstatic     #81                 // Field info/archinnov/achilles/internals/metamodel/columns/ColumnType.COMPUTED:Linfo/archinnov/achilles/internals/metamodel/columns/ColumnType;
      10: if_acmpne     17
      13: iconst_1
      14: goto          18
      17: iconst_0
      18: ireturn

  private static void lambda$validateComputed$121(info.archinnov.achilles.internals.apt.AptUtils, java.util.Set, info.archinnov.achilles.type.tuples.Tuple2);
    Code:
       0: aload_0
       1: aload_1
       2: aload_2
       3: invokevirtual #82                 // Method info/archinnov/achilles/type/tuples/Tuple2._2:()Ljava/lang/Object;
       6: invokeinterface #32,  2           // InterfaceMethod java/util/Set.contains:(Ljava/lang/Object;)Z
      11: ldc           #83                 // String Alias \'%s\' in @Computed annotation on field \'%s\' is already used by another @Computed field
      13: iconst_2
      14: anewarray     #20                 // class java/lang/Object
      17: dup
      18: iconst_0
      19: aload_2
      20: invokevirtual #82                 // Method info/archinnov/achilles/type/tuples/Tuple2._2:()Ljava/lang/Object;
      23: aastore
      24: dup
      25: iconst_1
      26: aload_2
      27: invokevirtual #84                 // Method info/archinnov/achilles/type/tuples/Tuple2._1:()Ljava/lang/Object;
      30: aastore
      31: invokevirtual #34                 // Method info/archinnov/achilles/internals/apt/AptUtils.validateFalse:(ZLjava/lang/String;[Ljava/lang/Object;)V
      34: aload_1
      35: aload_2
      36: invokevirtual #82                 // Method info/archinnov/achilles/type/tuples/Tuple2._2:()Ljava/lang/Object;
      39: invokeinterface #32,  2           // InterfaceMethod java/util/Set.contains:(Ljava/lang/Object;)Z
      44: ifne          58
      47: aload_1
      48: aload_2
      49: invokevirtual #82                 // Method info/archinnov/achilles/type/tuples/Tuple2._2:()Ljava/lang/Object;
      52: invokeinterface #85,  2           // InterfaceMethod java/util/Set.add:(Ljava/lang/Object;)Z
      57: pop
      58: return

  private static info.archinnov.achilles.type.tuples.Tuple2 lambda$validateComputed$120(info.archinnov.achilles.internals.parser.FieldParser$FieldMetaSignature);
    Code:
       0: aload_0
       1: getfield      #73                 // Field info/archinnov/achilles/internals/parser/FieldParser$FieldMetaSignature.context:Linfo/archinnov/achilles/internals/parser/context/FieldParsingContext;
       4: getfield      #79                 // Field info/archinnov/achilles/internals/parser/context/FieldParsingContext.fieldName:Ljava/lang/String;
       7: aload_0
       8: getfield      #73                 // Field info/archinnov/achilles/internals/parser/FieldParser$FieldMetaSignature.context:Linfo/archinnov/achilles/internals/parser/context/FieldParsingContext;
      11: getfield      #74                 // Field info/archinnov/achilles/internals/parser/context/FieldParsingContext.columnInfo:Linfo/archinnov/achilles/internals/metamodel/columns/ColumnInfo;
      14: checkcast     #75                 // class info/archinnov/achilles/internals/metamodel/columns/ComputedColumnInfo
      17: getfield      #86                 // Field info/archinnov/achilles/internals/metamodel/columns/ComputedColumnInfo.alias:Ljava/lang/String;
      20: invokestatic  #87                 // Method info/archinnov/achilles/type/tuples/Tuple2.of:(Ljava/lang/Object;Ljava/lang/Object;)Linfo/archinnov/achilles/type/tuples/Tuple2;
      23: areturn

  private static boolean lambda$validateComputed$119(info.archinnov.achilles.internals.parser.FieldParser$FieldMetaSignature);
    Code:
       0: aload_0
       1: getfield      #73                 // Field info/archinnov/achilles/internals/parser/FieldParser$FieldMetaSignature.context:Linfo/archinnov/achilles/internals/parser/context/FieldParsingContext;
       4: getfield      #80                 // Field info/archinnov/achilles/internals/parser/context/FieldParsingContext.columnType:Linfo/archinnov/achilles/internals/metamodel/columns/ColumnType;
       7: getstatic     #81                 // Field info/archinnov/achilles/internals/metamodel/columns/ColumnType.COMPUTED:Linfo/archinnov/achilles/internals/metamodel/columns/ColumnType;
      10: if_acmpne     17
      13: iconst_1
      14: goto          18
      17: iconst_0
      18: ireturn

  private static java.lang.String lambda$validateComputed$118(info.archinnov.achilles.internals.parser.FieldParser$FieldMetaSignature);
    Code:
       0: aload_0
       1: getfield      #73                 // Field info/archinnov/achilles/internals/parser/FieldParser$FieldMetaSignature.context:Linfo/archinnov/achilles/internals/parser/context/FieldParsingContext;
       4: getfield      #79                 // Field info/archinnov/achilles/internals/parser/context/FieldParsingContext.fieldName:Ljava/lang/String;
       7: areturn

  private static boolean lambda$isCounterTable$117(info.archinnov.achilles.internals.parser.FieldParser$FieldMetaSignature);
    Code:
       0: aload_0
       1: getfield      #73                 // Field info/archinnov/achilles/internals/parser/FieldParser$FieldMetaSignature.context:Linfo/archinnov/achilles/internals/parser/context/FieldParsingContext;
       4: getfield      #80                 // Field info/archinnov/achilles/internals/parser/context/FieldParsingContext.columnType:Linfo/archinnov/achilles/internals/metamodel/columns/ColumnType;
       7: getstatic     #88                 // Field info/archinnov/achilles/internals/metamodel/columns/ColumnType.NORMAL:Linfo/archinnov/achilles/internals/metamodel/columns/ColumnType;
      10: if_acmpne     17
      13: iconst_1
      14: goto          18
      17: iconst_0
      18: ireturn

  private static boolean lambda$isCounterTable$116(info.archinnov.achilles.internals.parser.FieldParser$FieldMetaSignature);
    Code:
       0: aload_0
       1: getfield      #73                 // Field info/archinnov/achilles/internals/parser/FieldParser$FieldMetaSignature.context:Linfo/archinnov/achilles/internals/parser/context/FieldParsingContext;
       4: getfield      #80                 // Field info/archinnov/achilles/internals/parser/context/FieldParsingContext.columnType:Linfo/archinnov/achilles/internals/metamodel/columns/ColumnType;
       7: getstatic     #89                 // Field info/archinnov/achilles/internals/metamodel/columns/ColumnType.STATIC_COUNTER:Linfo/archinnov/achilles/internals/metamodel/columns/ColumnType;
      10: if_acmpne     17
      13: iconst_1
      14: goto          18
      17: iconst_0
      18: ireturn

  private static boolean lambda$isCounterTable$115(info.archinnov.achilles.internals.parser.FieldParser$FieldMetaSignature);
    Code:
       0: aload_0
       1: getfield      #73                 // Field info/archinnov/achilles/internals/parser/FieldParser$FieldMetaSignature.context:Linfo/archinnov/achilles/internals/parser/context/FieldParsingContext;
       4: getfield      #80                 // Field info/archinnov/achilles/internals/parser/context/FieldParsingContext.columnType:Linfo/archinnov/achilles/internals/metamodel/columns/ColumnType;
       7: getstatic     #90                 // Field info/archinnov/achilles/internals/metamodel/columns/ColumnType.COUNTER:Linfo/archinnov/achilles/internals/metamodel/columns/ColumnType;
      10: if_acmpne     17
      13: iconst_1
      14: goto          18
      17: iconst_0
      18: ireturn

  private static boolean lambda$validateHasPartitionKey$114(info.archinnov.achilles.internals.parser.FieldParser$FieldMetaSignature);
    Code:
       0: aload_0
       1: getfield      #73                 // Field info/archinnov/achilles/internals/parser/FieldParser$FieldMetaSignature.context:Linfo/archinnov/achilles/internals/parser/context/FieldParsingContext;
       4: getfield      #80                 // Field info/archinnov/achilles/internals/parser/context/FieldParsingContext.columnType:Linfo/archinnov/achilles/internals/metamodel/columns/ColumnType;
       7: getstatic     #91                 // Field info/archinnov/achilles/internals/metamodel/columns/ColumnType.PARTITION:Linfo/archinnov/achilles/internals/metamodel/columns/ColumnType;
      10: if_acmpne     17
      13: iconst_1
      14: goto          18
      17: iconst_0
      18: ireturn

  private static boolean lambda$validateStaticColumns$113(info.archinnov.achilles.internals.parser.FieldParser$FieldMetaSignature);
    Code:
       0: aload_0
       1: getfield      #73                 // Field info/archinnov/achilles/internals/parser/FieldParser$FieldMetaSignature.context:Linfo/archinnov/achilles/internals/parser/context/FieldParsingContext;
       4: getfield      #80                 // Field info/archinnov/achilles/internals/parser/context/FieldParsingContext.columnType:Linfo/archinnov/achilles/internals/metamodel/columns/ColumnType;
       7: getstatic     #92                 // Field info/archinnov/achilles/internals/metamodel/columns/ColumnType.CLUSTERING:Linfo/archinnov/achilles/internals/metamodel/columns/ColumnType;
      10: if_acmpne     17
      13: iconst_1
      14: goto          18
      17: iconst_0
      18: ireturn

  private static boolean lambda$validateStaticColumns$112(info.archinnov.achilles.internals.parser.FieldParser$FieldMetaSignature);
    Code:
       0: aload_0
       1: getfield      #73                 // Field info/archinnov/achilles/internals/parser/FieldParser$FieldMetaSignature.context:Linfo/archinnov/achilles/internals/parser/context/FieldParsingContext;
       4: getfield      #80                 // Field info/archinnov/achilles/internals/parser/context/FieldParsingContext.columnType:Linfo/archinnov/achilles/internals/metamodel/columns/ColumnType;
       7: getstatic     #93                 // Field info/archinnov/achilles/internals/metamodel/columns/ColumnType.STATIC:Linfo/archinnov/achilles/internals/metamodel/columns/ColumnType;
      10: if_acmpeq     26
      13: aload_0
      14: getfield      #73                 // Field info/archinnov/achilles/internals/parser/FieldParser$FieldMetaSignature.context:Linfo/archinnov/achilles/internals/parser/context/FieldParsingContext;
      17: getfield      #80                 // Field info/archinnov/achilles/internals/parser/context/FieldParsingContext.columnType:Linfo/archinnov/achilles/internals/metamodel/columns/ColumnType;
      20: getstatic     #89                 // Field info/archinnov/achilles/internals/metamodel/columns/ColumnType.STATIC_COUNTER:Linfo/archinnov/achilles/internals/metamodel/columns/ColumnType;
      23: if_acmpne     30
      26: iconst_1
      27: goto          31
      30: iconst_0
      31: ireturn

  private void lambda$validateCqlColumnNotReservedWords$111(info.archinnov.achilles.internals.apt.AptUtils, com.squareup.javapoet.TypeName, info.archinnov.achilles.type.tuples.Tuple2);
    Code:
       0: aload_1
       1: aload_0
       2: getfield      #6                  // Field RESERVED_KEYWORDS:Ljava/util/List;
       5: aload_3
       6: invokevirtual #84                 // Method info/archinnov/achilles/type/tuples/Tuple2._1:()Ljava/lang/Object;
       9: checkcast     #18                 // class java/lang/String
      12: invokevirtual #94                 // Method java/lang/String.toLowerCase:()Ljava/lang/String;
      15: invokeinterface #77,  2           // InterfaceMethod java/util/List.contains:(Ljava/lang/Object;)Z
      20: ldc           #95                 // String The cql column \'%s\' on field \'%s\' of class \'%s\' is a CQL reserved word and cannot be used
      22: iconst_3
      23: anewarray     #20                 // class java/lang/Object
      26: dup
      27: iconst_0
      28: aload_3
      29: invokevirtual #84                 // Method info/archinnov/achilles/type/tuples/Tuple2._1:()Ljava/lang/Object;
      32: aastore
      33: dup
      34: iconst_1
      35: aload_3
      36: invokevirtual #82                 // Method info/archinnov/achilles/type/tuples/Tuple2._2:()Ljava/lang/Object;
      39: aastore
      40: dup
      41: iconst_2
      42: aload_2
      43: aastore
      44: invokevirtual #34                 // Method info/archinnov/achilles/internals/apt/AptUtils.validateFalse:(ZLjava/lang/String;[Ljava/lang/Object;)V
      47: return

  private static info.archinnov.achilles.type.tuples.Tuple2 lambda$validateCqlColumnNotReservedWords$110(info.archinnov.achilles.internals.parser.FieldParser$FieldMetaSignature);
    Code:
       0: aload_0
       1: getfield      #73                 // Field info/archinnov/achilles/internals/parser/FieldParser$FieldMetaSignature.context:Linfo/archinnov/achilles/internals/parser/context/FieldParsingContext;
       4: getfield      #96                 // Field info/archinnov/achilles/internals/parser/context/FieldParsingContext.cqlColumn:Ljava/lang/String;
       7: aload_0
       8: getfield      #73                 // Field info/archinnov/achilles/internals/parser/FieldParser$FieldMetaSignature.context:Linfo/archinnov/achilles/internals/parser/context/FieldParsingContext;
      11: getfield      #79                 // Field info/archinnov/achilles/internals/parser/context/FieldParsingContext.fieldName:Ljava/lang/String;
      14: invokestatic  #87                 // Method info/archinnov/achilles/type/tuples/Tuple2.of:(Ljava/lang/Object;Ljava/lang/Object;)Linfo/archinnov/achilles/type/tuples/Tuple2;
      17: areturn

  private static void lambda$validateNoDuplicateNames$109(java.util.Map, info.archinnov.achilles.internals.apt.AptUtils, com.squareup.javapoet.TypeName, info.archinnov.achilles.internals.parser.context.FieldParsingContext);
    Code:
       0: aload_3
       1: getfield      #79                 // Field info/archinnov/achilles/internals/parser/context/FieldParsingContext.fieldName:Ljava/lang/String;
       4: astore        4
       6: aload_3
       7: getfield      #96                 // Field info/archinnov/achilles/internals/parser/context/FieldParsingContext.cqlColumn:Ljava/lang/String;
      10: astore        5
      12: aload_0
      13: aload         4
      15: invokeinterface #16,  2           // InterfaceMethod java/util/Map.containsKey:(Ljava/lang/Object;)Z
      20: ifeq          45
      23: aload_1
      24: ldc           #97                 // String The class \'%s\' already contains a field with name \'%s\'
      26: iconst_2
      27: anewarray     #20                 // class java/lang/Object
      30: dup
      31: iconst_0
      32: aload_2
      33: aastore
      34: dup
      35: iconst_1
      36: aload         4
      38: aastore
      39: invokevirtual #21                 // Method info/archinnov/achilles/internals/apt/AptUtils.printError:(Ljava/lang/String;[Ljava/lang/Object;)V
      42: goto          89
      45: aload_0
      46: aload         5
      48: invokeinterface #98,  2           // InterfaceMethod java/util/Map.containsValue:(Ljava/lang/Object;)Z
      53: ifeq          78
      56: aload_1
      57: ldc           #99                 // String The class \'%s\' already contains a cql column with name \'%s\'
      59: iconst_2
      60: anewarray     #20                 // class java/lang/Object
      63: dup
      64: iconst_0
      65: aload_2
      66: aastore
      67: dup
      68: iconst_1
      69: aload         5
      71: aastore
      72: invokevirtual #21                 // Method info/archinnov/achilles/internals/apt/AptUtils.printError:(Ljava/lang/String;[Ljava/lang/Object;)V
      75: goto          89
      78: aload_0
      79: aload         4
      81: aload         5
      83: invokeinterface #25,  3           // InterfaceMethod java/util/Map.put:(Ljava/lang/Object;Ljava/lang/Object;)Ljava/lang/Object;
      88: pop
      89: return

  private static info.archinnov.achilles.internals.parser.context.FieldParsingContext lambda$validateNoDuplicateNames$108(info.archinnov.achilles.internals.parser.FieldParser$FieldMetaSignature);
    Code:
       0: aload_0
       1: getfield      #73                 // Field info/archinnov/achilles/internals/parser/FieldParser$FieldMetaSignature.context:Linfo/archinnov/achilles/internals/parser/context/FieldParsingContext;
       4: areturn

  private static boolean lambda$validateHasPublicConstructor$107(javax.lang.model.element.ExecutableElement);
    Code:
       0: aload_0
       1: invokeinterface #100,  1          // InterfaceMethod javax/lang/model/element/ExecutableElement.getParameters:()Ljava/util/List;
       6: invokeinterface #101,  1          // InterfaceMethod java/util/List.size:()I
      11: ifne          18
      14: iconst_1
      15: goto          19
      18: iconst_0
      19: ireturn

  private static boolean lambda$validateHasPublicConstructor$106(javax.lang.model.element.ExecutableElement);
    Code:
       0: aload_0
       1: invokeinterface #102,  1          // InterfaceMethod javax/lang/model/element/ExecutableElement.getModifiers:()Ljava/util/Set;
       6: getstatic     #103                // Field javax/lang/model/element/Modifier.PUBLIC:Ljavax/lang/model/element/Modifier;
       9: invokeinterface #32,  2           // InterfaceMethod java/util/Set.contains:(Ljava/lang/Object;)Z
      14: ireturn
}
