Compiled from "SubjectSourceDiagnostics.java"
final class edu.internet2.middleware.grouper.grouperUi.serviceLogic.SubjectSourceDiagnostics$1 implements edu.internet2.middleware.grouper.misc.GrouperSessionHandler {
  final java.lang.String[] val$args;

  edu.internet2.middleware.grouper.grouperUi.serviceLogic.SubjectSourceDiagnostics$1(java.lang.String[]);
    Code:
       0: aload_0
       1: aload_1
       2: putfield      #1                  // Field val$args:[Ljava/lang/String;
       5: aload_0
       6: invokespecial #2                  // Method java/lang/Object."<init>":()V
       9: return

  public java.lang.Object callback(edu.internet2.middleware.grouper.GrouperSession) throws edu.internet2.middleware.grouper.exception.GrouperSessionException;
    Code:
       0: new           #3                  // class edu/internet2/middleware/grouper/grouperUi/serviceLogic/SubjectSourceDiagnostics
       3: dup
       4: invokespecial #4                  // Method edu/internet2/middleware/grouper/grouperUi/serviceLogic/SubjectSourceDiagnostics."<init>":()V
       7: aload_0
       8: getfield      #1                  // Field val$args:[Ljava/lang/String;
      11: iconst_0
      12: aaload
      13: invokevirtual #5                  // Method edu/internet2/middleware/grouper/grouperUi/serviceLogic/SubjectSourceDiagnostics.assignSourceId:(Ljava/lang/String;)Ledu/internet2/middleware/grouper/grouperUi/serviceLogic/SubjectSourceDiagnostics;
      16: aload_0
      17: getfield      #1                  // Field val$args:[Ljava/lang/String;
      20: arraylength
      21: iconst_1
      22: if_icmple     34
      25: aload_0
      26: getfield      #1                  // Field val$args:[Ljava/lang/String;
      29: iconst_1
      30: aaload
      31: goto          35
      34: aconst_null
      35: invokevirtual #6                  // Method edu/internet2/middleware/grouper/grouperUi/serviceLogic/SubjectSourceDiagnostics.assignSubjectId:(Ljava/lang/String;)Ledu/internet2/middleware/grouper/grouperUi/serviceLogic/SubjectSourceDiagnostics;
      38: aload_0
      39: getfield      #1                  // Field val$args:[Ljava/lang/String;
      42: arraylength
      43: iconst_2
      44: if_icmple     56
      47: aload_0
      48: getfield      #1                  // Field val$args:[Ljava/lang/String;
      51: iconst_2
      52: aaload
      53: goto          57
      56: aconst_null
      57: invokevirtual #7                  // Method edu/internet2/middleware/grouper/grouperUi/serviceLogic/SubjectSourceDiagnostics.assignSubjectIdentifier:(Ljava/lang/String;)Ledu/internet2/middleware/grouper/grouperUi/serviceLogic/SubjectSourceDiagnostics;
      60: aload_0
      61: getfield      #1                  // Field val$args:[Ljava/lang/String;
      64: arraylength
      65: iconst_3
      66: if_icmple     78
      69: aload_0
      70: getfield      #1                  // Field val$args:[Ljava/lang/String;
      73: iconst_3
      74: aaload
      75: goto          79
      78: aconst_null
      79: invokevirtual #8                  // Method edu/internet2/middleware/grouper/grouperUi/serviceLogic/SubjectSourceDiagnostics.assignSearchString:(Ljava/lang/String;)Ledu/internet2/middleware/grouper/grouperUi/serviceLogic/SubjectSourceDiagnostics;
      82: invokevirtual #9                  // Method edu/internet2/middleware/grouper/grouperUi/serviceLogic/SubjectSourceDiagnostics.subjectSourceDiagnostics:()Ljava/lang/StringBuilder;
      85: pop
      86: aconst_null
      87: areturn
}
