Compiled from "UiV2Deprovisioning.java"
class edu.internet2.middleware.grouper.grouperUi.serviceLogic.UiV2Deprovisioning$14 extends edu.internet2.middleware.grouper.grouperUi.beans.dojo.DojoComboQueryLogicBase<edu.internet2.middleware.subject.Subject> {
  final edu.internet2.middleware.grouper.grouperUi.serviceLogic.UiV2Deprovisioning this$0;

  edu.internet2.middleware.grouper.grouperUi.serviceLogic.UiV2Deprovisioning$14(edu.internet2.middleware.grouper.grouperUi.serviceLogic.UiV2Deprovisioning);
    Code:
       0: aload_0
       1: aload_1
       2: putfield      #1                  // Field this$0:Ledu/internet2/middleware/grouper/grouperUi/serviceLogic/UiV2Deprovisioning;
       5: aload_0
       6: invokespecial #2                  // Method edu/internet2/middleware/grouper/grouperUi/beans/dojo/DojoComboQueryLogicBase."<init>":()V
       9: return

  public edu.internet2.middleware.subject.Subject lookup(javax.servlet.http.HttpServletRequest, edu.internet2.middleware.grouper.GrouperSession, java.lang.String);
    Code:
       0: aconst_null
       1: astore        4
       3: iconst_1
       4: invokestatic  #3                  // Method edu/internet2/middleware/grouper/GrouperSourceAdapter.searchForGroupsWithReadPrivilege:(Z)V
       7: aload_3
       8: ifnull        51
      11: aload_3
      12: ldc           #4                  // String ||
      14: invokevirtual #5                  // Method java/lang/String.contains:(Ljava/lang/CharSequence;)Z
      17: ifeq          51
      20: aload_3
      21: ldc           #4                  // String ||
      23: iconst_1
      24: invokestatic  #6                  // Method edu/internet2/middleware/grouper/util/GrouperUtil.prefixOrSuffix:(Ljava/lang/String;Ljava/lang/String;Z)Ljava/lang/String;
      27: astore        5
      29: aload_3
      30: ldc           #4                  // String ||
      32: iconst_0
      33: invokestatic  #6                  // Method edu/internet2/middleware/grouper/util/GrouperUtil.prefixOrSuffix:(Ljava/lang/String;Ljava/lang/String;Z)Ljava/lang/String;
      36: astore        6
      38: aload         6
      40: aload         5
      42: iconst_0
      43: invokestatic  #7                  // Method edu/internet2/middleware/grouper/SubjectFinder.findByIdOrIdentifierAndSource:(Ljava/lang/String;Ljava/lang/String;Z)Ledu/internet2/middleware/subject/Subject;
      46: astore        4
      48: goto          106
      51: aload_3
      52: iconst_0
      53: invokestatic  #8                  // Method edu/internet2/middleware/grouper/SubjectFinder.findByIdOrIdentifier:(Ljava/lang/String;Z)Ledu/internet2/middleware/subject/Subject;
      56: astore        4
      58: goto          106
      61: astore        5
      63: invokestatic  #10                 // Method edu/internet2/middleware/grouper/grouperUi/serviceLogic/UiV2Deprovisioning.access$000:()Lorg/apache/commons/logging/Log;
      66: invokeinterface #11,  1           // InterfaceMethod org/apache/commons/logging/Log.isDebugEnabled:()Z
      71: ifeq          106
      74: invokestatic  #10                 // Method edu/internet2/middleware/grouper/grouperUi/serviceLogic/UiV2Deprovisioning.access$000:()Lorg/apache/commons/logging/Log;
      77: new           #12                 // class java/lang/StringBuilder
      80: dup
      81: invokespecial #13                 // Method java/lang/StringBuilder."<init>":()V
      84: ldc           #14                 // String Find by id or identifier not unique: \'
      86: invokevirtual #15                 // Method java/lang/StringBuilder.append:(Ljava/lang/String;)Ljava/lang/StringBuilder;
      89: aload_3
      90: invokevirtual #15                 // Method java/lang/StringBuilder.append:(Ljava/lang/String;)Ljava/lang/StringBuilder;
      93: ldc           #16                 // String \'
      95: invokevirtual #15                 // Method java/lang/StringBuilder.append:(Ljava/lang/String;)Ljava/lang/StringBuilder;
      98: invokevirtual #17                 // Method java/lang/StringBuilder.toString:()Ljava/lang/String;
     101: invokeinterface #18,  2           // InterfaceMethod org/apache/commons/logging/Log.debug:(Ljava/lang/Object;)V
     106: invokestatic  #19                 // Method edu/internet2/middleware/grouper/GrouperSourceAdapter.clearSearchForGroupsWithReadPrivilege:()V
     109: goto          120
     112: astore        7
     114: invokestatic  #19                 // Method edu/internet2/middleware/grouper/GrouperSourceAdapter.clearSearchForGroupsWithReadPrivilege:()V
     117: aload         7
     119: athrow
     120: aload         4
     122: ifnull        144
     125: invokestatic  #20                 // Method edu/internet2/middleware/grouper/app/deprovisioning/GrouperDeprovisioningSettings.retrieveSourcesAllowedToDeprovision:()Ljava/util/Set;
     128: aload         4
     130: invokeinterface #21,  1           // InterfaceMethod edu/internet2/middleware/subject/Subject.getSource:()Ledu/internet2/middleware/subject/Source;
     135: invokestatic  #22                 // Method edu/internet2/middleware/grouper/subj/SubjectHelper.inSourceList:(Ljava/util/Collection;Ledu/internet2/middleware/subject/Source;)Z
     138: ifne          144
     141: aconst_null
     142: astore        4
     144: aload         4
     146: areturn
    Exception table:
       from    to  target type
          51    58    61   Class edu/internet2/middleware/subject/SubjectNotUniqueException
           3   106   112   any
         112   114   112   any

  public java.util.Collection<edu.internet2.middleware.subject.Subject> search(javax.servlet.http.HttpServletRequest, edu.internet2.middleware.grouper.GrouperSession, java.lang.String);
    Code:
       0: iconst_1
       1: invokestatic  #3                  // Method edu/internet2/middleware/grouper/GrouperSourceAdapter.searchForGroupsWithReadPrivilege:(Z)V
       4: aload_3
       5: invokestatic  #20                 // Method edu/internet2/middleware/grouper/app/deprovisioning/GrouperDeprovisioningSettings.retrieveSourcesAllowedToDeprovision:()Ljava/util/Set;
       8: invokestatic  #23                 // Method edu/internet2/middleware/grouper/SubjectFinder.findPage:(Ljava/lang/String;Ljava/util/Set;)Ledu/internet2/middleware/subject/SearchPageResult;
      11: invokevirtual #24                 // Method edu/internet2/middleware/subject/SearchPageResult.getResults:()Ljava/util/Set;
      14: astore        4
      16: aload         4
      18: astore        5
      20: invokestatic  #19                 // Method edu/internet2/middleware/grouper/GrouperSourceAdapter.clearSearchForGroupsWithReadPrivilege:()V
      23: aload         5
      25: areturn
      26: astore        6
      28: invokestatic  #19                 // Method edu/internet2/middleware/grouper/GrouperSourceAdapter.clearSearchForGroupsWithReadPrivilege:()V
      31: aload         6
      33: athrow
    Exception table:
       from    to  target type
           0    20    26   any
          26    28    26   any

  public java.lang.String retrieveId(edu.internet2.middleware.grouper.GrouperSession, edu.internet2.middleware.subject.Subject);
    Code:
       0: new           #12                 // class java/lang/StringBuilder
       3: dup
       4: invokespecial #13                 // Method java/lang/StringBuilder."<init>":()V
       7: aload_2
       8: invokeinterface #25,  1           // InterfaceMethod edu/internet2/middleware/subject/Subject.getSourceId:()Ljava/lang/String;
      13: invokevirtual #15                 // Method java/lang/StringBuilder.append:(Ljava/lang/String;)Ljava/lang/StringBuilder;
      16: ldc           #4                  // String ||
      18: invokevirtual #15                 // Method java/lang/StringBuilder.append:(Ljava/lang/String;)Ljava/lang/StringBuilder;
      21: aload_2
      22: invokeinterface #26,  1           // InterfaceMethod edu/internet2/middleware/subject/Subject.getId:()Ljava/lang/String;
      27: invokevirtual #15                 // Method java/lang/StringBuilder.append:(Ljava/lang/String;)Ljava/lang/StringBuilder;
      30: invokevirtual #17                 // Method java/lang/StringBuilder.toString:()Ljava/lang/String;
      33: areturn

  public java.lang.String retrieveLabel(edu.internet2.middleware.grouper.GrouperSession, edu.internet2.middleware.subject.Subject);
    Code:
       0: new           #27                 // class edu/internet2/middleware/grouper/grouperUi/beans/api/GuiSubject
       3: dup
       4: aload_2
       5: invokespecial #28                 // Method edu/internet2/middleware/grouper/grouperUi/beans/api/GuiSubject."<init>":(Ledu/internet2/middleware/subject/Subject;)V
       8: invokevirtual #29                 // Method edu/internet2/middleware/grouper/grouperUi/beans/api/GuiSubject.getScreenLabelLong:()Ljava/lang/String;
      11: areturn

  public java.lang.String retrieveHtmlLabel(edu.internet2.middleware.grouper.GrouperSession, edu.internet2.middleware.subject.Subject);
    Code:
       0: new           #27                 // class edu/internet2/middleware/grouper/grouperUi/beans/api/GuiSubject
       3: dup
       4: aload_2
       5: invokespecial #28                 // Method edu/internet2/middleware/grouper/grouperUi/beans/api/GuiSubject."<init>":(Ledu/internet2/middleware/subject/Subject;)V
       8: invokevirtual #30                 // Method edu/internet2/middleware/grouper/grouperUi/beans/api/GuiSubject.getScreenLabelLongWithIcon:()Ljava/lang/String;
      11: astore_3
      12: aload_3
      13: areturn

  public java.lang.String initialValidationError(javax.servlet.http.HttpServletRequest, edu.internet2.middleware.grouper.GrouperSession);
    Code:
       0: aconst_null
       1: areturn

  public java.lang.String retrieveHtmlLabel(edu.internet2.middleware.grouper.GrouperSession, java.lang.Object);
    Code:
       0: aload_0
       1: aload_1
       2: aload_2
       3: checkcast     #31                 // class edu/internet2/middleware/subject/Subject
       6: invokevirtual #32                 // Method retrieveHtmlLabel:(Ledu/internet2/middleware/grouper/GrouperSession;Ledu/internet2/middleware/subject/Subject;)Ljava/lang/String;
       9: areturn

  public java.lang.String retrieveLabel(edu.internet2.middleware.grouper.GrouperSession, java.lang.Object);
    Code:
       0: aload_0
       1: aload_1
       2: aload_2
       3: checkcast     #31                 // class edu/internet2/middleware/subject/Subject
       6: invokevirtual #33                 // Method retrieveLabel:(Ledu/internet2/middleware/grouper/GrouperSession;Ledu/internet2/middleware/subject/Subject;)Ljava/lang/String;
       9: areturn

  public java.lang.String retrieveId(edu.internet2.middleware.grouper.GrouperSession, java.lang.Object);
    Code:
       0: aload_0
       1: aload_1
       2: aload_2
       3: checkcast     #31                 // class edu/internet2/middleware/subject/Subject
       6: invokevirtual #34                 // Method retrieveId:(Ledu/internet2/middleware/grouper/GrouperSession;Ledu/internet2/middleware/subject/Subject;)Ljava/lang/String;
       9: areturn

  public java.lang.Object lookup(javax.servlet.http.HttpServletRequest, edu.internet2.middleware.grouper.GrouperSession, java.lang.String);
    Code:
       0: aload_0
       1: aload_1
       2: aload_2
       3: aload_3
       4: invokevirtual #35                 // Method lookup:(Ljavax/servlet/http/HttpServletRequest;Ledu/internet2/middleware/grouper/GrouperSession;Ljava/lang/String;)Ledu/internet2/middleware/subject/Subject;
       7: areturn
}
