Compiled from "UiV2Stem.java"
public class edu.internet2.middleware.grouper.grouperUi.serviceLogic.UiV2Stem$RetrieveStemHelperResult {
  private edu.internet2.middleware.grouper.Stem stem;

  private boolean addedError;

  public edu.internet2.middleware.grouper.grouperUi.serviceLogic.UiV2Stem$RetrieveStemHelperResult();
    Code:
       0: aload_0
       1: invokespecial #1                  // Method java/lang/Object."<init>":()V
       4: return

  public edu.internet2.middleware.grouper.Stem getStem();
    Code:
       0: aload_0
       1: getfield      #2                  // Field stem:Ledu/internet2/middleware/grouper/Stem;
       4: areturn

  public void setStem(edu.internet2.middleware.grouper.Stem);
    Code:
       0: aload_0
       1: aload_1
       2: putfield      #2                  // Field stem:Ledu/internet2/middleware/grouper/Stem;
       5: return

  public boolean isAddedError();
    Code:
       0: aload_0
       1: getfield      #3                  // Field addedError:Z
       4: ireturn

  public void setAddedError(boolean);
    Code:
       0: aload_0
       1: iload_1
       2: putfield      #3                  // Field addedError:Z
       5: return
}
