Compiled from "UiV2Visualization.java"
public class edu.internet2.middleware.grouper.grouperUi.serviceLogic.UiV2Visualization$TextNode extends edu.internet2.middleware.grouper.grouperUi.serviceLogic.UiV2Visualization$Node {
  private long indent;

  private java.util.List<java.lang.String> parentNodeIds;

  private java.util.List<java.lang.String> childNodeIds;

  final edu.internet2.middleware.grouper.grouperUi.serviceLogic.UiV2Visualization this$0;

  private edu.internet2.middleware.grouper.grouperUi.serviceLogic.UiV2Visualization$TextNode(java.lang.String, java.lang.String, java.lang.String, java.lang.String, java.lang.String, java.lang.String, java.lang.String, long, long, java.util.List<java.lang.String>, long);
    Code:
       0: aload_0
       1: aload_1
       2: putfield      #4                  // Field this$0:Ledu/internet2/middleware/grouper/grouperUi/serviceLogic/UiV2Visualization;
       5: aload_0
       6: aload_1
       7: aload_2
       8: aload_3
       9: aload         4
      11: aload         5
      13: aload         6
      15: aload         7
      17: aload         8
      19: lload         9
      21: lload         11
      23: aload         13
      25: aconst_null
      26: invokespecial #5                  // Method edu/internet2/middleware/grouper/grouperUi/serviceLogic/UiV2Visualization$Node."<init>":(Ledu/internet2/middleware/grouper/grouperUi/serviceLogic/UiV2Visualization;Ljava/lang/String;Ljava/lang/String;Ljava/lang/String;Ljava/lang/String;Ljava/lang/String;Ljava/lang/String;Ljava/lang/String;JJLjava/util/List;Ledu/internet2/middleware/grouper/grouperUi/serviceLogic/UiV2Visualization$1;)V
      29: aload_0
      30: lload         14
      32: putfield      #6                  // Field indent:J
      35: aload_0
      36: new           #7                  // class java/util/LinkedList
      39: dup
      40: invokespecial #8                  // Method java/util/LinkedList."<init>":()V
      43: putfield      #9                  // Field parentNodeIds:Ljava/util/List;
      46: aload_0
      47: new           #7                  // class java/util/LinkedList
      50: dup
      51: invokespecial #8                  // Method java/util/LinkedList."<init>":()V
      54: putfield      #10                 // Field childNodeIds:Ljava/util/List;
      57: return

  public long getIndent();
    Code:
       0: aload_0
       1: getfield      #6                  // Field indent:J
       4: lreturn

  public java.util.List<java.lang.String> getParentNodeIds();
    Code:
       0: aload_0
       1: getfield      #9                  // Field parentNodeIds:Ljava/util/List;
       4: areturn

  private void addParentNodeId(java.lang.String);
    Code:
       0: aload_0
       1: getfield      #9                  // Field parentNodeIds:Ljava/util/List;
       4: aload_1
       5: invokeinterface #11,  2           // InterfaceMethod java/util/List.add:(Ljava/lang/Object;)Z
      10: pop
      11: return

  public java.util.List<java.lang.String> getChildNodeIds();
    Code:
       0: aload_0
       1: getfield      #10                 // Field childNodeIds:Ljava/util/List;
       4: areturn

  private void addChildNodeId(java.lang.String);
    Code:
       0: aload_0
       1: getfield      #10                 // Field childNodeIds:Ljava/util/List;
       4: aload_1
       5: invokeinterface #11,  2           // InterfaceMethod java/util/List.add:(Ljava/lang/Object;)Z
      10: pop
      11: return

  edu.internet2.middleware.grouper.grouperUi.serviceLogic.UiV2Visualization$TextNode(edu.internet2.middleware.grouper.grouperUi.serviceLogic.UiV2Visualization, java.lang.String, java.lang.String, java.lang.String, java.lang.String, java.lang.String, java.lang.String, java.lang.String, long, long, java.util.List, long, edu.internet2.middleware.grouper.grouperUi.serviceLogic.UiV2Visualization$1);
    Code:
       0: aload_0
       1: aload_1
       2: aload_2
       3: aload_3
       4: aload         4
       6: aload         5
       8: aload         6
      10: aload         7
      12: aload         8
      14: lload         9
      16: lload         11
      18: aload         13
      20: lload         14
      22: invokespecial #3                  // Method "<init>":(Ledu/internet2/middleware/grouper/grouperUi/serviceLogic/UiV2Visualization;Ljava/lang/String;Ljava/lang/String;Ljava/lang/String;Ljava/lang/String;Ljava/lang/String;Ljava/lang/String;Ljava/lang/String;JJLjava/util/List;J)V
      25: return

  static void access$700(edu.internet2.middleware.grouper.grouperUi.serviceLogic.UiV2Visualization$TextNode, java.lang.String);
    Code:
       0: aload_0
       1: aload_1
       2: invokespecial #2                  // Method addParentNodeId:(Ljava/lang/String;)V
       5: return

  static void access$800(edu.internet2.middleware.grouper.grouperUi.serviceLogic.UiV2Visualization$TextNode, java.lang.String);
    Code:
       0: aload_0
       1: aload_1
       2: invokespecial #1                  // Method addChildNodeId:(Ljava/lang/String;)V
       5: return
}
