Compiled from "UiV2Provisioning.java"
class edu.internet2.middleware.grouper.grouperUi.serviceLogic.UiV2Provisioning$17 implements edu.internet2.middleware.grouper.misc.GrouperSessionHandler {
  final edu.internet2.middleware.grouper.grouperUi.beans.ui.ProvisioningContainer val$provisioningContainer;

  final java.lang.String val$targetName;

  final edu.internet2.middleware.grouper.Stem val$STEM;

  final edu.internet2.middleware.grouper.grouperUi.serviceLogic.UiV2Provisioning this$0;

  edu.internet2.middleware.grouper.grouperUi.serviceLogic.UiV2Provisioning$17(edu.internet2.middleware.grouper.grouperUi.serviceLogic.UiV2Provisioning, edu.internet2.middleware.grouper.grouperUi.beans.ui.ProvisioningContainer, java.lang.String, edu.internet2.middleware.grouper.Stem);
    Code:
       0: aload_0
       1: aload_1
       2: putfield      #1                  // Field this$0:Ledu/internet2/middleware/grouper/grouperUi/serviceLogic/UiV2Provisioning;
       5: aload_0
       6: aload_2
       7: putfield      #2                  // Field val$provisioningContainer:Ledu/internet2/middleware/grouper/grouperUi/beans/ui/ProvisioningContainer;
      10: aload_0
      11: aload_3
      12: putfield      #3                  // Field val$targetName:Ljava/lang/String;
      15: aload_0
      16: aload         4
      18: putfield      #4                  // Field val$STEM:Ledu/internet2/middleware/grouper/Stem;
      21: aload_0
      22: invokespecial #5                  // Method java/lang/Object."<init>":()V
      25: return

  public java.lang.Object callback(edu.internet2.middleware.grouper.GrouperSession) throws edu.internet2.middleware.grouper.exception.GrouperSessionException;
    Code:
       0: aload_0
       1: getfield      #2                  // Field val$provisioningContainer:Ledu/internet2/middleware/grouper/grouperUi/beans/ui/ProvisioningContainer;
       4: aload_0
       5: getfield      #3                  // Field val$targetName:Ljava/lang/String;
       8: invokevirtual #6                  // Method edu/internet2/middleware/grouper/grouperUi/beans/ui/ProvisioningContainer.setTargetName:(Ljava/lang/String;)V
      11: aload_0
      12: getfield      #4                  // Field val$STEM:Ledu/internet2/middleware/grouper/Stem;
      15: invokevirtual #7                  // Method edu/internet2/middleware/grouper/Stem.getId:()Ljava/lang/String;
      18: aload_0
      19: getfield      #3                  // Field val$targetName:Ljava/lang/String;
      22: invokestatic  #8                  // Method edu/internet2/middleware/grouper/app/provisioning/GrouperProvisioningService.retrieveNumberOfGroupsInTargetInStem:(Ljava/lang/String;Ljava/lang/String;)J
      25: lstore_2
      26: aload_0
      27: getfield      #4                  // Field val$STEM:Ledu/internet2/middleware/grouper/Stem;
      30: invokevirtual #7                  // Method edu/internet2/middleware/grouper/Stem.getId:()Ljava/lang/String;
      33: aload_0
      34: getfield      #3                  // Field val$targetName:Ljava/lang/String;
      37: invokestatic  #9                  // Method edu/internet2/middleware/grouper/app/provisioning/GrouperProvisioningService.retrieveNumberOfUsersInTargetInStem:(Ljava/lang/String;Ljava/lang/String;)J
      40: lstore        4
      42: aload_0
      43: getfield      #4                  // Field val$STEM:Ledu/internet2/middleware/grouper/Stem;
      46: invokevirtual #7                  // Method edu/internet2/middleware/grouper/Stem.getId:()Ljava/lang/String;
      49: aload_0
      50: getfield      #3                  // Field val$targetName:Ljava/lang/String;
      53: invokestatic  #10                 // Method edu/internet2/middleware/grouper/app/provisioning/GrouperProvisioningService.retrieveNumberOfMembershipsInTargetInStem:(Ljava/lang/String;Ljava/lang/String;)J
      56: lstore        6
      58: aload_0
      59: getfield      #2                  // Field val$provisioningContainer:Ledu/internet2/middleware/grouper/grouperUi/beans/ui/ProvisioningContainer;
      62: lload_2
      63: invokevirtual #11                 // Method edu/internet2/middleware/grouper/grouperUi/beans/ui/ProvisioningContainer.setGroupsCount:(J)V
      66: aload_0
      67: getfield      #2                  // Field val$provisioningContainer:Ledu/internet2/middleware/grouper/grouperUi/beans/ui/ProvisioningContainer;
      70: lload         4
      72: invokevirtual #12                 // Method edu/internet2/middleware/grouper/grouperUi/beans/ui/ProvisioningContainer.setUsersCount:(J)V
      75: aload_0
      76: getfield      #2                  // Field val$provisioningContainer:Ledu/internet2/middleware/grouper/grouperUi/beans/ui/ProvisioningContainer;
      79: lload         6
      81: invokevirtual #13                 // Method edu/internet2/middleware/grouper/grouperUi/beans/ui/ProvisioningContainer.setMembershipsCount:(J)V
      84: aconst_null
      85: areturn
}
