Compiled from "UiV2CustomUi.java"
class edu.internet2.middleware.grouper.grouperUi.serviceLogic.UiV2CustomUi$2 implements edu.internet2.middleware.grouper.misc.GrouperSessionHandler {
  final javax.servlet.http.HttpServletRequest val$request;

  final edu.internet2.middleware.grouper.grouperUi.beans.ui.CustomUiContainer val$customUiContainer;

  final edu.internet2.middleware.subject.Subject val$loggedInSubject;

  final edu.internet2.middleware.subject.Subject val$subject;

  final edu.internet2.middleware.grouper.grouperUi.serviceLogic.UiV2CustomUi this$0;

  edu.internet2.middleware.grouper.grouperUi.serviceLogic.UiV2CustomUi$2(edu.internet2.middleware.grouper.grouperUi.serviceLogic.UiV2CustomUi, javax.servlet.http.HttpServletRequest, edu.internet2.middleware.grouper.grouperUi.beans.ui.CustomUiContainer, edu.internet2.middleware.subject.Subject, edu.internet2.middleware.subject.Subject);
    Code:
       0: aload_0
       1: aload_1
       2: putfield      #1                  // Field this$0:Ledu/internet2/middleware/grouper/grouperUi/serviceLogic/UiV2CustomUi;
       5: aload_0
       6: aload_2
       7: putfield      #2                  // Field val$request:Ljavax/servlet/http/HttpServletRequest;
      10: aload_0
      11: aload_3
      12: putfield      #3                  // Field val$customUiContainer:Ledu/internet2/middleware/grouper/grouperUi/beans/ui/CustomUiContainer;
      15: aload_0
      16: aload         4
      18: putfield      #4                  // Field val$loggedInSubject:Ledu/internet2/middleware/subject/Subject;
      21: aload_0
      22: aload         5
      24: putfield      #5                  // Field val$subject:Ledu/internet2/middleware/subject/Subject;
      27: aload_0
      28: invokespecial #6                  // Method java/lang/Object."<init>":()V
      31: return

  public java.lang.Object callback(edu.internet2.middleware.grouper.GrouperSession) throws edu.internet2.middleware.grouper.exception.GrouperSessionException;
    Code:
       0: aload_0
       1: getfield      #1                  // Field this$0:Ledu/internet2/middleware/grouper/grouperUi/serviceLogic/UiV2CustomUi;
       4: aload_0
       5: getfield      #2                  // Field val$request:Ljavax/servlet/http/HttpServletRequest;
       8: invokestatic  #7                  // Method edu/internet2/middleware/grouper/grouperUi/serviceLogic/UiV2CustomUi.access$000:(Ledu/internet2/middleware/grouper/grouperUi/serviceLogic/UiV2CustomUi;Ljavax/servlet/http/HttpServletRequest;)Ledu/internet2/middleware/grouper/Group;
      11: astore_2
      12: new           #8                  // class edu/internet2/middleware/grouper/ui/customUi/CustomUiEngine
      15: dup
      16: invokespecial #9                  // Method edu/internet2/middleware/grouper/ui/customUi/CustomUiEngine."<init>":()V
      19: astore_3
      20: aload_0
      21: getfield      #3                  // Field val$customUiContainer:Ledu/internet2/middleware/grouper/grouperUi/beans/ui/CustomUiContainer;
      24: aload_3
      25: invokevirtual #10                 // Method edu/internet2/middleware/grouper/grouperUi/beans/ui/CustomUiContainer.setCustomUiEngine:(Ledu/internet2/middleware/grouper/ui/customUi/CustomUiEngine;)V
      28: aload_3
      29: aload_2
      30: aload_0
      31: getfield      #4                  // Field val$loggedInSubject:Ledu/internet2/middleware/subject/Subject;
      34: aload_0
      35: getfield      #5                  // Field val$subject:Ledu/internet2/middleware/subject/Subject;
      38: invokevirtual #11                 // Method edu/internet2/middleware/grouper/ui/customUi/CustomUiEngine.processGroup:(Ledu/internet2/middleware/grouper/Group;Ledu/internet2/middleware/subject/Subject;Ledu/internet2/middleware/subject/Subject;)V
      41: aload_3
      42: invokevirtual #12                 // Method edu/internet2/middleware/grouper/ui/customUi/CustomUiEngine.userQueryVariables:()Ljava/util/Map;
      45: ldc           #13                 // String cu_managerIsLoggedIn
      47: aload_0
      48: getfield      #3                  // Field val$customUiContainer:Ledu/internet2/middleware/grouper/grouperUi/beans/ui/CustomUiContainer;
      51: invokevirtual #14                 // Method edu/internet2/middleware/grouper/grouperUi/beans/ui/CustomUiContainer.isManager:()Z
      54: invokestatic  #15                 // Method java/lang/Boolean.valueOf:(Z)Ljava/lang/Boolean;
      57: invokeinterface #16,  3           // InterfaceMethod java/util/Map.put:(Ljava/lang/Object;Ljava/lang/Object;)Ljava/lang/Object;
      62: pop
      63: aload_3
      64: invokevirtual #12                 // Method edu/internet2/middleware/grouper/ui/customUi/CustomUiEngine.userQueryVariables:()Ljava/util/Map;
      67: ldc           #17                 // String cu_grouperEnroll
      69: aload_0
      70: getfield      #3                  // Field val$customUiContainer:Ledu/internet2/middleware/grouper/grouperUi/beans/ui/CustomUiContainer;
      73: invokevirtual #18                 // Method edu/internet2/middleware/grouper/grouperUi/beans/ui/CustomUiContainer.isEnroll:()Z
      76: invokestatic  #15                 // Method java/lang/Boolean.valueOf:(Z)Ljava/lang/Boolean;
      79: invokeinterface #16,  3           // InterfaceMethod java/util/Map.put:(Ljava/lang/Object;Ljava/lang/Object;)Ljava/lang/Object;
      84: pop
      85: aconst_null
      86: areturn
}
