Compiled from "UiV2GrouperLoader.java"
class edu.internet2.middleware.grouper.grouperUi.serviceLogic.UiV2GrouperLoader$4 implements edu.internet2.middleware.grouper.misc.GrouperSessionHandler {
  final edu.internet2.middleware.grouper.Group val$group;

  final edu.internet2.middleware.grouper.grouperUi.beans.ui.GrouperLoaderContainer val$grouperLoaderContainer;

  final edu.internet2.middleware.grouper.grouperUi.serviceLogic.UiV2GrouperLoader this$0;

  edu.internet2.middleware.grouper.grouperUi.serviceLogic.UiV2GrouperLoader$4(edu.internet2.middleware.grouper.grouperUi.serviceLogic.UiV2GrouperLoader, edu.internet2.middleware.grouper.Group, edu.internet2.middleware.grouper.grouperUi.beans.ui.GrouperLoaderContainer);
    Code:
       0: aload_0
       1: aload_1
       2: putfield      #1                  // Field this$0:Ledu/internet2/middleware/grouper/grouperUi/serviceLogic/UiV2GrouperLoader;
       5: aload_0
       6: aload_2
       7: putfield      #2                  // Field val$group:Ledu/internet2/middleware/grouper/Group;
      10: aload_0
      11: aload_3
      12: putfield      #3                  // Field val$grouperLoaderContainer:Ledu/internet2/middleware/grouper/grouperUi/beans/ui/GrouperLoaderContainer;
      15: aload_0
      16: invokespecial #4                  // Method java/lang/Object."<init>":()V
      19: return

  public java.lang.Object callback(edu.internet2.middleware.grouper.GrouperSession) throws edu.internet2.middleware.grouper.exception.GrouperSessionException;
    Code:
       0: invokestatic  #5                  // Method edu/internet2/middleware/grouper/misc/GrouperDAOFactory.getFactory:()Ledu/internet2/middleware/grouper/misc/GrouperDAOFactory;
       3: invokevirtual #6                  // Method edu/internet2/middleware/grouper/misc/GrouperDAOFactory.getAttributeDefName:()Ledu/internet2/middleware/grouper/internal/dao/AttributeDefNameDAO;
       6: new           #7                  // class java/lang/StringBuilder
       9: dup
      10: invokespecial #8                  // Method java/lang/StringBuilder."<init>":()V
      13: invokestatic  #9                  // Method edu/internet2/middleware/grouper/app/serviceLifecycle/GrouperRecentMemberships.recentMembershipsStemName:()Ljava/lang/String;
      16: invokevirtual #10                 // Method java/lang/StringBuilder.append:(Ljava/lang/String;)Ljava/lang/StringBuilder;
      19: ldc           #11                 // String :
      21: invokevirtual #10                 // Method java/lang/StringBuilder.append:(Ljava/lang/String;)Ljava/lang/StringBuilder;
      24: ldc           #13                 // String grouperRecentMembershipsMarker
      26: invokevirtual #10                 // Method java/lang/StringBuilder.append:(Ljava/lang/String;)Ljava/lang/StringBuilder;
      29: invokevirtual #14                 // Method java/lang/StringBuilder.toString:()Ljava/lang/String;
      32: iconst_0
      33: invokeinterface #15,  3           // InterfaceMethod edu/internet2/middleware/grouper/internal/dao/AttributeDefNameDAO.findByNameSecure:(Ljava/lang/String;Z)Ledu/internet2/middleware/grouper/attr/AttributeDefName;
      38: astore_2
      39: aload_2
      40: ifnonnull     53
      43: new           #16                 // class java/lang/RuntimeException
      46: dup
      47: ldc           #17                 // String Cant find recent memberships attribute!
      49: invokespecial #18                 // Method java/lang/RuntimeException."<init>":(Ljava/lang/String;)V
      52: athrow
      53: aload_0
      54: getfield      #2                  // Field val$group:Ledu/internet2/middleware/grouper/Group;
      57: invokevirtual #19                 // Method edu/internet2/middleware/grouper/Group.getAttributeDelegate:()Ledu/internet2/middleware/grouper/attr/assign/AttributeAssignGroupDelegate;
      60: aconst_null
      61: aload_2
      62: iconst_0
      63: iconst_0
      64: invokevirtual #20                 // Method edu/internet2/middleware/grouper/attr/assign/AttributeAssignGroupDelegate.retrieveAssignment:(Ljava/lang/String;Ledu/internet2/middleware/grouper/attr/AttributeDefName;ZZ)Ledu/internet2/middleware/grouper/attr/assign/AttributeAssign;
      67: astore_3
      68: aload_3
      69: ifnonnull     87
      72: aload_0
      73: getfield      #2                  // Field val$group:Ledu/internet2/middleware/grouper/Group;
      76: invokevirtual #19                 // Method edu/internet2/middleware/grouper/Group.getAttributeDelegate:()Ledu/internet2/middleware/grouper/attr/assign/AttributeAssignGroupDelegate;
      79: aload_2
      80: invokevirtual #21                 // Method edu/internet2/middleware/grouper/attr/assign/AttributeAssignGroupDelegate.assignAttribute:(Ledu/internet2/middleware/grouper/attr/AttributeDefName;)Ledu/internet2/middleware/grouper/attr/assign/AttributeAssignResult;
      83: invokevirtual #22                 // Method edu/internet2/middleware/grouper/attr/assign/AttributeAssignResult.getAttributeAssign:()Ledu/internet2/middleware/grouper/attr/assign/AttributeAssign;
      86: astore_3
      87: aload_3
      88: invokevirtual #23                 // Method edu/internet2/middleware/grouper/attr/assign/AttributeAssign.getAttributeValueDelegate:()Ledu/internet2/middleware/grouper/attr/value/AttributeValueDelegate;
      91: new           #7                  // class java/lang/StringBuilder
      94: dup
      95: invokespecial #8                  // Method java/lang/StringBuilder."<init>":()V
      98: invokestatic  #9                  // Method edu/internet2/middleware/grouper/app/serviceLifecycle/GrouperRecentMemberships.recentMembershipsStemName:()Ljava/lang/String;
     101: invokevirtual #10                 // Method java/lang/StringBuilder.append:(Ljava/lang/String;)Ljava/lang/StringBuilder;
     104: ldc           #11                 // String :
     106: invokevirtual #10                 // Method java/lang/StringBuilder.append:(Ljava/lang/String;)Ljava/lang/StringBuilder;
     109: ldc           #24                 // String grouperRecentMembershipsGroupUuidFrom
     111: invokevirtual #10                 // Method java/lang/StringBuilder.append:(Ljava/lang/String;)Ljava/lang/StringBuilder;
     114: invokevirtual #14                 // Method java/lang/StringBuilder.toString:()Ljava/lang/String;
     117: aload_0
     118: getfield      #3                  // Field val$grouperLoaderContainer:Ledu/internet2/middleware/grouper/grouperUi/beans/ui/GrouperLoaderContainer;
     121: invokevirtual #25                 // Method edu/internet2/middleware/grouper/grouperUi/beans/ui/GrouperLoaderContainer.getEditLoaderRecentGroupUuidFrom:()Ljava/lang/String;
     124: invokevirtual #26                 // Method edu/internet2/middleware/grouper/attr/value/AttributeValueDelegate.assignValue:(Ljava/lang/String;Ljava/lang/String;)Ledu/internet2/middleware/grouper/attr/value/AttributeValueResult;
     127: pop
     128: aload_3
     129: invokevirtual #23                 // Method edu/internet2/middleware/grouper/attr/assign/AttributeAssign.getAttributeValueDelegate:()Ledu/internet2/middleware/grouper/attr/value/AttributeValueDelegate;
     132: new           #7                  // class java/lang/StringBuilder
     135: dup
     136: invokespecial #8                  // Method java/lang/StringBuilder."<init>":()V
     139: invokestatic  #9                  // Method edu/internet2/middleware/grouper/app/serviceLifecycle/GrouperRecentMemberships.recentMembershipsStemName:()Ljava/lang/String;
     142: invokevirtual #10                 // Method java/lang/StringBuilder.append:(Ljava/lang/String;)Ljava/lang/StringBuilder;
     145: ldc           #11                 // String :
     147: invokevirtual #10                 // Method java/lang/StringBuilder.append:(Ljava/lang/String;)Ljava/lang/StringBuilder;
     150: ldc           #27                 // String grouperRecentMembershipsIncludeCurrent
     152: invokevirtual #10                 // Method java/lang/StringBuilder.append:(Ljava/lang/String;)Ljava/lang/StringBuilder;
     155: invokevirtual #14                 // Method java/lang/StringBuilder.toString:()Ljava/lang/String;
     158: aload_0
     159: getfield      #3                  // Field val$grouperLoaderContainer:Ledu/internet2/middleware/grouper/grouperUi/beans/ui/GrouperLoaderContainer;
     162: invokevirtual #28                 // Method edu/internet2/middleware/grouper/grouperUi/beans/ui/GrouperLoaderContainer.getEditLoaderRecentIncludeCurrent:()Ljava/lang/String;
     165: invokestatic  #29                 // Method edu/internet2/middleware/grouper/util/GrouperUtil.booleanValue:(Ljava/lang/Object;)Z
     168: ifeq          176
     171: ldc           #30                 // String T
     173: goto          178
     176: ldc           #31                 // String F
     178: invokevirtual #26                 // Method edu/internet2/middleware/grouper/attr/value/AttributeValueDelegate.assignValue:(Ljava/lang/String;Ljava/lang/String;)Ledu/internet2/middleware/grouper/attr/value/AttributeValueResult;
     181: pop
     182: aload_0
     183: getfield      #3                  // Field val$grouperLoaderContainer:Ledu/internet2/middleware/grouper/grouperUi/beans/ui/GrouperLoaderContainer;
     186: invokevirtual #32                 // Method edu/internet2/middleware/grouper/grouperUi/beans/ui/GrouperLoaderContainer.getEditLoaderRecentDays:()Ljava/lang/String;
     189: astore        4
     191: aload         4
     193: invokestatic  #33                 // Method edu/internet2/middleware/grouper/util/GrouperUtil.doubleValue:(Ljava/lang/Object;)D
     196: dstore        5
     198: dload         5
     200: ldc2_w        #34                 // double 24.0d
     203: dmul
     204: ldc2_w        #36                 // double 60.0d
     207: dmul
     208: ldc2_w        #36                 // double 60.0d
     211: dmul
     212: ldc2_w        #38                 // double 1000.0d
     215: dmul
     216: ldc2_w        #38                 // double 1000.0d
     219: dmul
     220: invokestatic  #40                 // Method java/lang/Math.round:(D)J
     223: lstore        7
     225: aload_3
     226: invokevirtual #23                 // Method edu/internet2/middleware/grouper/attr/assign/AttributeAssign.getAttributeValueDelegate:()Ledu/internet2/middleware/grouper/attr/value/AttributeValueDelegate;
     229: new           #7                  // class java/lang/StringBuilder
     232: dup
     233: invokespecial #8                  // Method java/lang/StringBuilder."<init>":()V
     236: invokestatic  #9                  // Method edu/internet2/middleware/grouper/app/serviceLifecycle/GrouperRecentMemberships.recentMembershipsStemName:()Ljava/lang/String;
     239: invokevirtual #10                 // Method java/lang/StringBuilder.append:(Ljava/lang/String;)Ljava/lang/StringBuilder;
     242: ldc           #11                 // String :
     244: invokevirtual #10                 // Method java/lang/StringBuilder.append:(Ljava/lang/String;)Ljava/lang/StringBuilder;
     247: ldc           #41                 // String grouperRecentMembershipsMicros
     249: invokevirtual #10                 // Method java/lang/StringBuilder.append:(Ljava/lang/String;)Ljava/lang/StringBuilder;
     252: invokevirtual #14                 // Method java/lang/StringBuilder.toString:()Ljava/lang/String;
     255: lload         7
     257: invokestatic  #42                 // Method java/lang/Long.toString:(J)Ljava/lang/String;
     260: invokevirtual #26                 // Method edu/internet2/middleware/grouper/attr/value/AttributeValueDelegate.assignValue:(Ljava/lang/String;Ljava/lang/String;)Ledu/internet2/middleware/grouper/attr/value/AttributeValueResult;
     263: pop
     264: aconst_null
     265: areturn
}
