Compiled from "AnnotatedConstructor.java"
public final class org.codehaus.jackson.map.introspect.AnnotatedConstructor extends org.codehaus.jackson.map.introspect.AnnotatedWithParams {
  protected final java.lang.reflect.Constructor<?> _constructor;

  public org.codehaus.jackson.map.introspect.AnnotatedConstructor(java.lang.reflect.Constructor<?>, org.codehaus.jackson.map.introspect.AnnotationMap, org.codehaus.jackson.map.introspect.AnnotationMap[]);
    Code:
       0: aload_0
       1: aload_2
       2: aload_3
       3: invokespecial #1                  // Method org/codehaus/jackson/map/introspect/AnnotatedWithParams."<init>":(Lorg/codehaus/jackson/map/introspect/AnnotationMap;[Lorg/codehaus/jackson/map/introspect/AnnotationMap;)V
       6: aload_1
       7: ifnonnull     20
      10: new           #2                  // class java/lang/IllegalArgumentException
      13: dup
      14: ldc           #3                  // String Null constructor not allowed
      16: invokespecial #4                  // Method java/lang/IllegalArgumentException."<init>":(Ljava/lang/String;)V
      19: athrow
      20: aload_0
      21: aload_1
      22: putfield      #5                  // Field _constructor:Ljava/lang/reflect/Constructor;
      25: return

  public org.codehaus.jackson.map.introspect.AnnotatedConstructor withAnnotations(org.codehaus.jackson.map.introspect.AnnotationMap);
    Code:
       0: new           #6                  // class org/codehaus/jackson/map/introspect/AnnotatedConstructor
       3: dup
       4: aload_0
       5: getfield      #5                  // Field _constructor:Ljava/lang/reflect/Constructor;
       8: aload_1
       9: aload_0
      10: getfield      #7                  // Field _paramAnnotations:[Lorg/codehaus/jackson/map/introspect/AnnotationMap;
      13: invokespecial #8                  // Method "<init>":(Ljava/lang/reflect/Constructor;Lorg/codehaus/jackson/map/introspect/AnnotationMap;[Lorg/codehaus/jackson/map/introspect/AnnotationMap;)V
      16: areturn

  public java.lang.reflect.Constructor<?> getAnnotated();
    Code:
       0: aload_0
       1: getfield      #5                  // Field _constructor:Ljava/lang/reflect/Constructor;
       4: areturn

  public int getModifiers();
    Code:
       0: aload_0
       1: getfield      #5                  // Field _constructor:Ljava/lang/reflect/Constructor;
       4: invokevirtual #9                  // Method java/lang/reflect/Constructor.getModifiers:()I
       7: ireturn

  public java.lang.String getName();
    Code:
       0: aload_0
       1: getfield      #5                  // Field _constructor:Ljava/lang/reflect/Constructor;
       4: invokevirtual #10                 // Method java/lang/reflect/Constructor.getName:()Ljava/lang/String;
       7: areturn

  public java.lang.reflect.Type getGenericType();
    Code:
       0: aload_0
       1: invokevirtual #11                 // Method getRawType:()Ljava/lang/Class;
       4: areturn

  public java.lang.Class<?> getRawType();
    Code:
       0: aload_0
       1: getfield      #5                  // Field _constructor:Ljava/lang/reflect/Constructor;
       4: invokevirtual #12                 // Method java/lang/reflect/Constructor.getDeclaringClass:()Ljava/lang/Class;
       7: areturn

  public org.codehaus.jackson.type.JavaType getType(org.codehaus.jackson.map.type.TypeBindings);
    Code:
       0: aload_0
       1: aload_1
       2: aload_0
       3: getfield      #5                  // Field _constructor:Ljava/lang/reflect/Constructor;
       6: invokevirtual #13                 // Method java/lang/reflect/Constructor.getTypeParameters:()[Ljava/lang/reflect/TypeVariable;
       9: invokevirtual #14                 // Method getType:(Lorg/codehaus/jackson/map/type/TypeBindings;[Ljava/lang/reflect/TypeVariable;)Lorg/codehaus/jackson/type/JavaType;
      12: areturn

  public int getParameterCount();
    Code:
       0: aload_0
       1: getfield      #5                  // Field _constructor:Ljava/lang/reflect/Constructor;
       4: invokevirtual #15                 // Method java/lang/reflect/Constructor.getParameterTypes:()[Ljava/lang/Class;
       7: arraylength
       8: ireturn

  public java.lang.Class<?> getParameterClass(int);
    Code:
       0: aload_0
       1: getfield      #5                  // Field _constructor:Ljava/lang/reflect/Constructor;
       4: invokevirtual #15                 // Method java/lang/reflect/Constructor.getParameterTypes:()[Ljava/lang/Class;
       7: astore_2
       8: iload_1
       9: aload_2
      10: arraylength
      11: if_icmplt     18
      14: aconst_null
      15: goto          21
      18: aload_2
      19: iload_1
      20: aaload
      21: areturn

  public java.lang.reflect.Type getParameterType(int);
    Code:
       0: aload_0
       1: getfield      #5                  // Field _constructor:Ljava/lang/reflect/Constructor;
       4: invokevirtual #16                 // Method java/lang/reflect/Constructor.getGenericParameterTypes:()[Ljava/lang/reflect/Type;
       7: astore_2
       8: iload_1
       9: aload_2
      10: arraylength
      11: if_icmplt     18
      14: aconst_null
      15: goto          21
      18: aload_2
      19: iload_1
      20: aaload
      21: areturn

  public final java.lang.Object call() throws java.lang.Exception;
    Code:
       0: aload_0
       1: getfield      #5                  // Field _constructor:Ljava/lang/reflect/Constructor;
       4: iconst_0
       5: anewarray     #17                 // class java/lang/Object
       8: invokevirtual #18                 // Method java/lang/reflect/Constructor.newInstance:([Ljava/lang/Object;)Ljava/lang/Object;
      11: areturn

  public final java.lang.Object call(java.lang.Object[]) throws java.lang.Exception;
    Code:
       0: aload_0
       1: getfield      #5                  // Field _constructor:Ljava/lang/reflect/Constructor;
       4: aload_1
       5: invokevirtual #18                 // Method java/lang/reflect/Constructor.newInstance:([Ljava/lang/Object;)Ljava/lang/Object;
       8: areturn

  public final java.lang.Object call1(java.lang.Object) throws java.lang.Exception;
    Code:
       0: aload_0
       1: getfield      #5                  // Field _constructor:Ljava/lang/reflect/Constructor;
       4: iconst_1
       5: anewarray     #17                 // class java/lang/Object
       8: dup
       9: iconst_0
      10: aload_1
      11: aastore
      12: invokevirtual #18                 // Method java/lang/reflect/Constructor.newInstance:([Ljava/lang/Object;)Ljava/lang/Object;
      15: areturn

  public java.lang.Class<?> getDeclaringClass();
    Code:
       0: aload_0
       1: getfield      #5                  // Field _constructor:Ljava/lang/reflect/Constructor;
       4: invokevirtual #12                 // Method java/lang/reflect/Constructor.getDeclaringClass:()Ljava/lang/Class;
       7: areturn

  public java.lang.reflect.Member getMember();
    Code:
       0: aload_0
       1: getfield      #5                  // Field _constructor:Ljava/lang/reflect/Constructor;
       4: areturn

  public void setValue(java.lang.Object, java.lang.Object) throws java.lang.UnsupportedOperationException;
    Code:
       0: new           #19                 // class java/lang/UnsupportedOperationException
       3: dup
       4: new           #20                 // class java/lang/StringBuilder
       7: dup
       8: invokespecial #21                 // Method java/lang/StringBuilder."<init>":()V
      11: ldc           #22                 // String Cannot call setValue() on constructor of
      13: invokevirtual #23                 // Method java/lang/StringBuilder.append:(Ljava/lang/String;)Ljava/lang/StringBuilder;
      16: aload_0
      17: invokevirtual #24                 // Method getDeclaringClass:()Ljava/lang/Class;
      20: invokevirtual #25                 // Method java/lang/Class.getName:()Ljava/lang/String;
      23: invokevirtual #23                 // Method java/lang/StringBuilder.append:(Ljava/lang/String;)Ljava/lang/StringBuilder;
      26: invokevirtual #26                 // Method java/lang/StringBuilder.toString:()Ljava/lang/String;
      29: invokespecial #27                 // Method java/lang/UnsupportedOperationException."<init>":(Ljava/lang/String;)V
      32: athrow

  public java.lang.String toString();
    Code:
       0: new           #20                 // class java/lang/StringBuilder
       3: dup
       4: invokespecial #21                 // Method java/lang/StringBuilder."<init>":()V
       7: ldc           #28                 // String [constructor for
       9: invokevirtual #23                 // Method java/lang/StringBuilder.append:(Ljava/lang/String;)Ljava/lang/StringBuilder;
      12: aload_0
      13: invokevirtual #29                 // Method getName:()Ljava/lang/String;
      16: invokevirtual #23                 // Method java/lang/StringBuilder.append:(Ljava/lang/String;)Ljava/lang/StringBuilder;
      19: ldc           #30                 // String , annotations:
      21: invokevirtual #23                 // Method java/lang/StringBuilder.append:(Ljava/lang/String;)Ljava/lang/StringBuilder;
      24: aload_0
      25: getfield      #31                 // Field _annotations:Lorg/codehaus/jackson/map/introspect/AnnotationMap;
      28: invokevirtual #32                 // Method java/lang/StringBuilder.append:(Ljava/lang/Object;)Ljava/lang/StringBuilder;
      31: ldc           #33                 // String ]
      33: invokevirtual #23                 // Method java/lang/StringBuilder.append:(Ljava/lang/String;)Ljava/lang/StringBuilder;
      36: invokevirtual #26                 // Method java/lang/StringBuilder.toString:()Ljava/lang/String;
      39: areturn

  public java.lang.reflect.AnnotatedElement getAnnotated();
    Code:
       0: aload_0
       1: invokevirtual #34                 // Method getAnnotated:()Ljava/lang/reflect/Constructor;
       4: areturn

  public org.codehaus.jackson.map.introspect.Annotated withAnnotations(org.codehaus.jackson.map.introspect.AnnotationMap);
    Code:
       0: aload_0
       1: aload_1
       2: invokevirtual #35                 // Method withAnnotations:(Lorg/codehaus/jackson/map/introspect/AnnotationMap;)Lorg/codehaus/jackson/map/introspect/AnnotatedConstructor;
       5: areturn
}
