Compiled from "RedirectServerAvpImpl.java"
public class org.mobicents.slee.resource.diameter.cca.events.avp.RedirectServerAvpImpl extends org.mobicents.slee.resource.diameter.base.events.avp.GroupedAvpImpl implements net.java.slee.resource.diameter.cca.events.avp.RedirectServerAvp {
  public org.mobicents.slee.resource.diameter.cca.events.avp.RedirectServerAvpImpl();
    Code:
       0: aload_0
       1: invokespecial #1                  // Method org/mobicents/slee/resource/diameter/base/events/avp/GroupedAvpImpl."<init>":()V
       4: return

  public org.mobicents.slee.resource.diameter.cca.events.avp.RedirectServerAvpImpl(int, long, int, int, byte[]);
    Code:
       0: aload_0
       1: iload_1
       2: lload_2
       3: iload         4
       5: iload         5
       7: aload         6
       9: invokespecial #2                  // Method org/mobicents/slee/resource/diameter/base/events/avp/GroupedAvpImpl."<init>":(IJII[B)V
      12: return

  public net.java.slee.resource.diameter.cca.events.avp.RedirectAddressType getRedirectAddressType();
    Code:
       0: aload_0
       1: sipush        433
       4: ldc_w         #3                  // class net/java/slee/resource/diameter/cca/events/avp/RedirectAddressType
       7: invokevirtual #4                  // Method getAvpAsEnumerated:(ILjava/lang/Class;)Ljava/lang/Object;
      10: checkcast     #3                  // class net/java/slee/resource/diameter/cca/events/avp/RedirectAddressType
      13: areturn

  public java.lang.String getRedirectServerAddress();
    Code:
       0: aload_0
       1: sipush        435
       4: invokevirtual #5                  // Method getAvpAsUTF8String:(I)Ljava/lang/String;
       7: areturn

  public boolean hasRedirectAddressType();
    Code:
       0: aload_0
       1: sipush        433
       4: invokevirtual #6                  // Method hasAvp:(I)Z
       7: ireturn

  public boolean hasRedirectServerAddress();
    Code:
       0: aload_0
       1: sipush        435
       4: invokevirtual #6                  // Method hasAvp:(I)Z
       7: ireturn

  public void setRedirectAddressType(net.java.slee.resource.diameter.cca.events.avp.RedirectAddressType);
    Code:
       0: aload_0
       1: sipush        433
       4: aload_1
       5: invokevirtual #7                  // Method net/java/slee/resource/diameter/cca/events/avp/RedirectAddressType.getValue:()I
       8: invokestatic  #8                  // Method java/lang/Integer.valueOf:(I)Ljava/lang/Integer;
      11: invokevirtual #9                  // Method addAvp:(ILjava/lang/Object;)V
      14: return

  public void setRedirectServerAddress(java.lang.String);
    Code:
       0: aload_0
       1: sipush        435
       4: aload_1
       5: invokevirtual #9                  // Method addAvp:(ILjava/lang/Object;)V
       8: return
}
