Compiled from "PersistedServiceImpl.java"
public class org.graylog2.database.PersistedServiceImpl implements org.graylog2.plugin.database.PersistedService {
  private static final org.slf4j.Logger LOG;

  public final org.graylog2.database.MongoConnection mongoConnection;

  protected org.graylog2.database.PersistedServiceImpl(org.graylog2.database.MongoConnection);
    Code:
       0: aload_0
       1: invokespecial #1                  // Method java/lang/Object."<init>":()V
       4: aload_0
       5: aload_1
       6: putfield      #2                  // Field mongoConnection:Lorg/graylog2/database/MongoConnection;
       9: return

  protected com.mongodb.DBObject get(org.bson.types.ObjectId, java.lang.String);
    Code:
       0: aload_0
       1: aload_2
       2: invokespecial #3                  // Method collection:(Ljava/lang/String;)Lcom/mongodb/DBCollection;
       5: new           #4                  // class com/mongodb/BasicDBObject
       8: dup
       9: ldc           #5                  // String _id
      11: aload_1
      12: invokespecial #6                  // Method com/mongodb/BasicDBObject."<init>":(Ljava/lang/String;Ljava/lang/Object;)V
      15: invokevirtual #7                  // Method com/mongodb/DBCollection.findOne:(Lcom/mongodb/DBObject;)Lcom/mongodb/DBObject;
      18: areturn

  protected <T extends org.graylog2.plugin.database.Persisted> com.mongodb.DBObject get(java.lang.Class<T>, org.bson.types.ObjectId);
    Code:
       0: aload_0
       1: aload_1
       2: invokevirtual #8                  // Method collection:(Ljava/lang/Class;)Lcom/mongodb/DBCollection;
       5: new           #4                  // class com/mongodb/BasicDBObject
       8: dup
       9: ldc           #5                  // String _id
      11: aload_2
      12: invokespecial #6                  // Method com/mongodb/BasicDBObject."<init>":(Ljava/lang/String;Ljava/lang/Object;)V
      15: invokevirtual #7                  // Method com/mongodb/DBCollection.findOne:(Lcom/mongodb/DBObject;)Lcom/mongodb/DBObject;
      18: areturn

  protected <T extends org.graylog2.plugin.database.Persisted> com.mongodb.DBObject get(java.lang.Class<T>, java.lang.String);
    Code:
       0: aload_0
       1: aload_1
       2: new           #9                  // class org/bson/types/ObjectId
       5: dup
       6: aload_2
       7: invokespecial #10                 // Method org/bson/types/ObjectId."<init>":(Ljava/lang/String;)V
      10: invokevirtual #11                 // Method get:(Ljava/lang/Class;Lorg/bson/types/ObjectId;)Lcom/mongodb/DBObject;
      13: areturn

  protected java.util.List<com.mongodb.DBObject> query(com.mongodb.DBObject, java.lang.String);
    Code:
       0: aload_0
       1: aload_1
       2: aload_0
       3: aload_2
       4: invokespecial #3                  // Method collection:(Ljava/lang/String;)Lcom/mongodb/DBCollection;
       7: invokevirtual #12                 // Method query:(Lcom/mongodb/DBObject;Lcom/mongodb/DBCollection;)Ljava/util/List;
      10: areturn

  protected java.util.List<com.mongodb.DBObject> query(com.mongodb.DBObject, com.mongodb.DBCollection);
    Code:
       0: aload_0
       1: aload_2
       2: aload_1
       3: invokevirtual #13                 // Method com/mongodb/DBCollection.find:(Lcom/mongodb/DBObject;)Lcom/mongodb/DBCursor;
       6: invokevirtual #14                 // Method cursorToList:(Lcom/mongodb/DBCursor;)Ljava/util/List;
       9: areturn

  protected <T extends org.graylog2.plugin.database.Persisted> java.util.List<com.mongodb.DBObject> query(java.lang.Class<T>, com.mongodb.DBObject);
    Code:
       0: aload_0
       1: aload_2
       2: aload_0
       3: aload_1
       4: invokevirtual #8                  // Method collection:(Ljava/lang/Class;)Lcom/mongodb/DBCollection;
       7: invokevirtual #12                 // Method query:(Lcom/mongodb/DBObject;Lcom/mongodb/DBCollection;)Ljava/util/List;
      10: areturn

  protected <T extends org.graylog2.plugin.database.Persisted> java.util.List<com.mongodb.DBObject> query(java.lang.Class<T>, com.mongodb.DBObject, com.mongodb.DBObject);
    Code:
       0: aload_0
       1: aload_0
       2: aload_1
       3: invokevirtual #8                  // Method collection:(Ljava/lang/Class;)Lcom/mongodb/DBCollection;
       6: aload_2
       7: invokevirtual #13                 // Method com/mongodb/DBCollection.find:(Lcom/mongodb/DBObject;)Lcom/mongodb/DBCursor;
      10: aload_3
      11: invokevirtual #15                 // Method com/mongodb/DBCursor.sort:(Lcom/mongodb/DBObject;)Lcom/mongodb/DBCursor;
      14: invokevirtual #14                 // Method cursorToList:(Lcom/mongodb/DBCursor;)Ljava/util/List;
      17: areturn

  protected <T extends org.graylog2.plugin.database.Persisted> java.util.List<com.mongodb.DBObject> query(java.lang.Class<T>, com.mongodb.DBObject, com.mongodb.DBObject, int, int);
    Code:
       0: aload_0
       1: aload_0
       2: aload_1
       3: invokevirtual #8                  // Method collection:(Ljava/lang/Class;)Lcom/mongodb/DBCollection;
       6: aload_2
       7: invokevirtual #13                 // Method com/mongodb/DBCollection.find:(Lcom/mongodb/DBObject;)Lcom/mongodb/DBCursor;
      10: aload_3
      11: invokevirtual #15                 // Method com/mongodb/DBCursor.sort:(Lcom/mongodb/DBObject;)Lcom/mongodb/DBCursor;
      14: iload         4
      16: invokevirtual #16                 // Method com/mongodb/DBCursor.limit:(I)Lcom/mongodb/DBCursor;
      19: iload         5
      21: invokevirtual #17                 // Method com/mongodb/DBCursor.skip:(I)Lcom/mongodb/DBCursor;
      24: invokevirtual #14                 // Method cursorToList:(Lcom/mongodb/DBCursor;)Ljava/util/List;
      27: areturn

  protected long count(com.mongodb.DBObject, java.lang.String);
    Code:
       0: aload_0
       1: aload_2
       2: invokespecial #3                  // Method collection:(Ljava/lang/String;)Lcom/mongodb/DBCollection;
       5: aload_1
       6: invokevirtual #18                 // Method com/mongodb/DBCollection.count:(Lcom/mongodb/DBObject;)J
       9: lreturn

  protected <T extends org.graylog2.plugin.database.Persisted> long count(java.lang.Class<T>, com.mongodb.DBObject);
    Code:
       0: aload_0
       1: aload_1
       2: invokevirtual #8                  // Method collection:(Ljava/lang/Class;)Lcom/mongodb/DBCollection;
       5: aload_2
       6: invokevirtual #18                 // Method com/mongodb/DBCollection.count:(Lcom/mongodb/DBObject;)J
       9: lreturn

  private com.mongodb.DBCollection collection(java.lang.String);
    Code:
       0: aload_0
       1: getfield      #2                  // Field mongoConnection:Lorg/graylog2/database/MongoConnection;
       4: invokeinterface #19,  1           // InterfaceMethod org/graylog2/database/MongoConnection.getDatabase:()Lcom/mongodb/DB;
       9: aload_1
      10: invokevirtual #20                 // Method com/mongodb/DB.getCollection:(Ljava/lang/String;)Lcom/mongodb/DBCollection;
      13: areturn

  protected <T extends org.graylog2.plugin.database.Persisted> com.mongodb.DBCollection collection(java.lang.Class<T>);
    Code:
       0: aload_1
       1: ldc           #21                 // class org/graylog2/database/CollectionName
       3: invokevirtual #22                 // Method java/lang/Class.getAnnotation:(Ljava/lang/Class;)Ljava/lang/annotation/Annotation;
       6: checkcast     #21                 // class org/graylog2/database/CollectionName
       9: astore_2
      10: aload_2
      11: ifnonnull     44
      14: new           #23                 // class java/lang/RuntimeException
      17: dup
      18: new           #24                 // class java/lang/StringBuilder
      21: dup
      22: invokespecial #25                 // Method java/lang/StringBuilder."<init>":()V
      25: ldc           #26                 // String Unable to determine collection for class
      27: invokevirtual #27                 // Method java/lang/StringBuilder.append:(Ljava/lang/String;)Ljava/lang/StringBuilder;
      30: aload_1
      31: invokevirtual #28                 // Method java/lang/Class.getCanonicalName:()Ljava/lang/String;
      34: invokevirtual #27                 // Method java/lang/StringBuilder.append:(Ljava/lang/String;)Ljava/lang/StringBuilder;
      37: invokevirtual #29                 // Method java/lang/StringBuilder.toString:()Ljava/lang/String;
      40: invokespecial #30                 // Method java/lang/RuntimeException."<init>":(Ljava/lang/String;)V
      43: athrow
      44: aload_2
      45: invokeinterface #31,  1           // InterfaceMethod org/graylog2/database/CollectionName.value:()Ljava/lang/String;
      50: astore_3
      51: aload_0
      52: aload_3
      53: invokespecial #3                  // Method collection:(Ljava/lang/String;)Lcom/mongodb/DBCollection;
      56: areturn

  protected <T extends org.graylog2.plugin.database.Persisted> com.mongodb.DBCollection collection(T);
    Code:
       0: aload_0
       1: aload_1
       2: invokevirtual #32                 // Method java/lang/Object.getClass:()Ljava/lang/Class;
       5: invokevirtual #8                  // Method collection:(Ljava/lang/Class;)Lcom/mongodb/DBCollection;
       8: areturn

  protected java.util.List<com.mongodb.DBObject> cursorToList(com.mongodb.DBCursor);
    Code:
       0: aload_1
       1: ifnonnull     8
       4: invokestatic  #33                 // Method java/util/Collections.emptyList:()Ljava/util/List;
       7: areturn
       8: aload_1
       9: invokestatic  #34                 // Method com/google/common/collect/Lists.newArrayList:(Ljava/lang/Iterable;)Ljava/util/ArrayList;
      12: astore_2
      13: aload_1
      14: invokevirtual #35                 // Method com/mongodb/DBCursor.close:()V
      17: aload_2
      18: areturn
      19: astore_3
      20: aload_1
      21: invokevirtual #35                 // Method com/mongodb/DBCursor.close:()V
      24: aload_3
      25: athrow
    Exception table:
       from    to  target type
           8    13    19   any

  protected <T extends org.graylog2.plugin.database.Persisted> com.mongodb.DBObject findOne(java.lang.Class<T>, com.mongodb.DBObject);
    Code:
       0: aload_0
       1: aload_1
       2: invokevirtual #8                  // Method collection:(Ljava/lang/Class;)Lcom/mongodb/DBCollection;
       5: aload_2
       6: invokevirtual #7                  // Method com/mongodb/DBCollection.findOne:(Lcom/mongodb/DBObject;)Lcom/mongodb/DBObject;
       9: areturn

  protected <T extends org.graylog2.plugin.database.Persisted> com.mongodb.DBObject findOne(java.lang.Class<T>, com.mongodb.DBObject, com.mongodb.DBObject);
    Code:
       0: aload_0
       1: aload_1
       2: invokevirtual #8                  // Method collection:(Ljava/lang/Class;)Lcom/mongodb/DBCollection;
       5: aload_2
       6: new           #4                  // class com/mongodb/BasicDBObject
       9: dup
      10: invokespecial #36                 // Method com/mongodb/BasicDBObject."<init>":()V
      13: aload_3
      14: invokevirtual #37                 // Method com/mongodb/DBCollection.findOne:(Lcom/mongodb/DBObject;Lcom/mongodb/DBObject;Lcom/mongodb/DBObject;)Lcom/mongodb/DBObject;
      17: areturn

  protected com.mongodb.DBObject findOne(com.mongodb.DBObject, java.lang.String);
    Code:
       0: aload_0
       1: aload_2
       2: invokespecial #3                  // Method collection:(Ljava/lang/String;)Lcom/mongodb/DBCollection;
       5: aload_1
       6: invokevirtual #7                  // Method com/mongodb/DBCollection.findOne:(Lcom/mongodb/DBObject;)Lcom/mongodb/DBObject;
       9: areturn

  protected com.mongodb.DBObject findOne(com.mongodb.DBObject, com.mongodb.DBObject, java.lang.String);
    Code:
       0: aload_0
       1: aload_3
       2: invokespecial #3                  // Method collection:(Ljava/lang/String;)Lcom/mongodb/DBCollection;
       5: aload_1
       6: new           #4                  // class com/mongodb/BasicDBObject
       9: dup
      10: invokespecial #36                 // Method com/mongodb/BasicDBObject."<init>":()V
      13: aload_2
      14: invokevirtual #37                 // Method com/mongodb/DBCollection.findOne:(Lcom/mongodb/DBObject;Lcom/mongodb/DBObject;Lcom/mongodb/DBObject;)Lcom/mongodb/DBObject;
      17: areturn

  protected long totalCount(java.lang.String);
    Code:
       0: aload_0
       1: aload_1
       2: invokespecial #3                  // Method collection:(Ljava/lang/String;)Lcom/mongodb/DBCollection;
       5: invokevirtual #38                 // Method com/mongodb/DBCollection.count:()J
       8: lreturn

  protected <T extends org.graylog2.plugin.database.Persisted> long totalCount(java.lang.Class<T>);
    Code:
       0: aload_0
       1: aload_1
       2: invokevirtual #8                  // Method collection:(Ljava/lang/Class;)Lcom/mongodb/DBCollection;
       5: invokevirtual #38                 // Method com/mongodb/DBCollection.count:()J
       8: lreturn

  public <T extends org.graylog2.plugin.database.Persisted> int destroy(T);
    Code:
       0: aload_0
       1: aload_1
       2: invokevirtual #39                 // Method collection:(Lorg/graylog2/plugin/database/Persisted;)Lcom/mongodb/DBCollection;
       5: new           #4                  // class com/mongodb/BasicDBObject
       8: dup
       9: ldc           #5                  // String _id
      11: new           #9                  // class org/bson/types/ObjectId
      14: dup
      15: aload_1
      16: invokeinterface #40,  1           // InterfaceMethod org/graylog2/plugin/database/Persisted.getId:()Ljava/lang/String;
      21: invokespecial #10                 // Method org/bson/types/ObjectId."<init>":(Ljava/lang/String;)V
      24: invokespecial #6                  // Method com/mongodb/BasicDBObject."<init>":(Ljava/lang/String;Ljava/lang/Object;)V
      27: invokevirtual #41                 // Method com/mongodb/DBCollection.remove:(Lcom/mongodb/DBObject;)Lcom/mongodb/WriteResult;
      30: invokevirtual #42                 // Method com/mongodb/WriteResult.getN:()I
      33: ireturn

  public <T extends org.graylog2.plugin.database.Persisted> int destroyAll(java.lang.Class<T>);
    Code:
       0: aload_0
       1: aload_1
       2: invokevirtual #8                  // Method collection:(Ljava/lang/Class;)Lcom/mongodb/DBCollection;
       5: new           #4                  // class com/mongodb/BasicDBObject
       8: dup
       9: invokespecial #36                 // Method com/mongodb/BasicDBObject."<init>":()V
      12: invokevirtual #41                 // Method com/mongodb/DBCollection.remove:(Lcom/mongodb/DBObject;)Lcom/mongodb/WriteResult;
      15: invokevirtual #42                 // Method com/mongodb/WriteResult.getN:()I
      18: ireturn

  protected int destroyAll(java.lang.String);
    Code:
       0: aload_0
       1: aload_1
       2: invokespecial #3                  // Method collection:(Ljava/lang/String;)Lcom/mongodb/DBCollection;
       5: new           #4                  // class com/mongodb/BasicDBObject
       8: dup
       9: invokespecial #36                 // Method com/mongodb/BasicDBObject."<init>":()V
      12: invokevirtual #41                 // Method com/mongodb/DBCollection.remove:(Lcom/mongodb/DBObject;)Lcom/mongodb/WriteResult;
      15: invokevirtual #42                 // Method com/mongodb/WriteResult.getN:()I
      18: ireturn

  protected int destroy(com.mongodb.DBObject, java.lang.String);
    Code:
       0: aload_0
       1: aload_2
       2: invokespecial #3                  // Method collection:(Ljava/lang/String;)Lcom/mongodb/DBCollection;
       5: aload_1
       6: invokevirtual #41                 // Method com/mongodb/DBCollection.remove:(Lcom/mongodb/DBObject;)Lcom/mongodb/WriteResult;
       9: invokevirtual #42                 // Method com/mongodb/WriteResult.getN:()I
      12: ireturn

  protected <T extends org.graylog2.plugin.database.Persisted> int destroyAll(java.lang.Class<T>, com.mongodb.DBObject);
    Code:
       0: aload_0
       1: aload_1
       2: invokevirtual #8                  // Method collection:(Ljava/lang/Class;)Lcom/mongodb/DBCollection;
       5: aload_2
       6: invokevirtual #41                 // Method com/mongodb/DBCollection.remove:(Lcom/mongodb/DBObject;)Lcom/mongodb/WriteResult;
       9: invokevirtual #42                 // Method com/mongodb/WriteResult.getN:()I
      12: ireturn

  public <T extends org.graylog2.plugin.database.Persisted> java.lang.String save(T) throws org.graylog2.plugin.database.ValidationException;
    Code:
       0: aload_0
       1: aload_1
       2: aload_1
       3: invokeinterface #43,  1           // InterfaceMethod org/graylog2/plugin/database/Persisted.getFields:()Ljava/util/Map;
       8: invokevirtual #44                 // Method validate:(Lorg/graylog2/plugin/database/Persisted;Ljava/util/Map;)Ljava/util/Map;
      11: astore_2
      12: aload_2
      13: invokeinterface #45,  1           // InterfaceMethod java/util/Map.isEmpty:()Z
      18: ifne          30
      21: new           #46                 // class org/graylog2/plugin/database/ValidationException
      24: dup
      25: aload_2
      26: invokespecial #47                 // Method org/graylog2/plugin/database/ValidationException."<init>":(Ljava/util/Map;)V
      29: athrow
      30: new           #4                  // class com/mongodb/BasicDBObject
      33: dup
      34: aload_1
      35: invokeinterface #43,  1           // InterfaceMethod org/graylog2/plugin/database/Persisted.getFields:()Ljava/util/Map;
      40: invokespecial #48                 // Method com/mongodb/BasicDBObject."<init>":(Ljava/util/Map;)V
      43: astore_3
      44: aload_3
      45: ldc           #5                  // String _id
      47: new           #9                  // class org/bson/types/ObjectId
      50: dup
      51: aload_1
      52: invokeinterface #40,  1           // InterfaceMethod org/graylog2/plugin/database/Persisted.getId:()Ljava/lang/String;
      57: invokespecial #10                 // Method org/bson/types/ObjectId."<init>":(Ljava/lang/String;)V
      60: invokevirtual #49                 // Method com/mongodb/BasicDBObject.put:(Ljava/lang/Object;Ljava/lang/Object;)Ljava/lang/Object;
      63: pop
      64: aload_0
      65: aload_3
      66: invokespecial #50                 // Method fieldTransformations:(Ljava/util/Map;)V
      69: new           #4                  // class com/mongodb/BasicDBObject
      72: dup
      73: ldc           #5                  // String _id
      75: new           #9                  // class org/bson/types/ObjectId
      78: dup
      79: aload_1
      80: invokeinterface #40,  1           // InterfaceMethod org/graylog2/plugin/database/Persisted.getId:()Ljava/lang/String;
      85: invokespecial #10                 // Method org/bson/types/ObjectId."<init>":(Ljava/lang/String;)V
      88: invokespecial #6                  // Method com/mongodb/BasicDBObject."<init>":(Ljava/lang/String;Ljava/lang/Object;)V
      91: astore        4
      93: aload_0
      94: aload_1
      95: invokevirtual #39                 // Method collection:(Lorg/graylog2/plugin/database/Persisted;)Lcom/mongodb/DBCollection;
      98: aload         4
     100: aload_3
     101: iconst_1
     102: iconst_0
     103: invokevirtual #51                 // Method com/mongodb/DBCollection.update:(Lcom/mongodb/DBObject;Lcom/mongodb/DBObject;ZZ)Lcom/mongodb/WriteResult;
     106: pop
     107: aload_1
     108: invokeinterface #40,  1           // InterfaceMethod org/graylog2/plugin/database/Persisted.getId:()Ljava/lang/String;
     113: areturn

  public <T extends org.graylog2.plugin.database.Persisted> java.lang.String saveWithoutValidation(T);
    Code:
       0: aload_0
       1: aload_1
       2: invokevirtual #52                 // Method save:(Lorg/graylog2/plugin/database/Persisted;)Ljava/lang/String;
       5: areturn
       6: astore_2
       7: aconst_null
       8: areturn
    Exception table:
       from    to  target type
           0     5     6   Class org/graylog2/plugin/database/ValidationException

  public <T extends org.graylog2.plugin.database.Persisted> java.util.Map<java.lang.String, java.util.List<org.graylog2.plugin.database.validators.ValidationResult>> validate(T, java.util.Map<java.lang.String, java.lang.Object>);
    Code:
       0: aload_0
       1: aload_1
       2: invokeinterface #53,  1           // InterfaceMethod org/graylog2/plugin/database/Persisted.getValidations:()Ljava/util/Map;
       7: aload_2
       8: invokevirtual #54                 // Method validate:(Ljava/util/Map;Ljava/util/Map;)Ljava/util/Map;
      11: areturn

  public java.util.Map<java.lang.String, java.util.List<org.graylog2.plugin.database.validators.ValidationResult>> validate(java.util.Map<java.lang.String, org.graylog2.plugin.database.validators.Validator>, java.util.Map<java.lang.String, java.lang.Object>);
    Code:
       0: aload_1
       1: ifnull        13
       4: aload_1
       5: invokeinterface #45,  1           // InterfaceMethod java/util/Map.isEmpty:()Z
      10: ifeq          17
      13: invokestatic  #55                 // Method java/util/Collections.emptyMap:()Ljava/util/Map;
      16: areturn
      17: new           #56                 // class java/util/HashMap
      20: dup
      21: invokespecial #57                 // Method java/util/HashMap."<init>":()V
      24: astore_3
      25: aload_1
      26: invokeinterface #58,  1           // InterfaceMethod java/util/Map.entrySet:()Ljava/util/Set;
      31: invokeinterface #59,  1           // InterfaceMethod java/util/Set.iterator:()Ljava/util/Iterator;
      36: astore        4
      38: aload         4
      40: invokeinterface #60,  1           // InterfaceMethod java/util/Iterator.hasNext:()Z
      45: ifeq          252
      48: aload         4
      50: invokeinterface #61,  1           // InterfaceMethod java/util/Iterator.next:()Ljava/lang/Object;
      55: checkcast     #62                 // class java/util/Map$Entry
      58: astore        5
      60: aload         5
      62: invokeinterface #63,  1           // InterfaceMethod java/util/Map$Entry.getValue:()Ljava/lang/Object;
      67: checkcast     #64                 // class org/graylog2/plugin/database/validators/Validator
      70: astore        6
      72: aload         5
      74: invokeinterface #65,  1           // InterfaceMethod java/util/Map$Entry.getKey:()Ljava/lang/Object;
      79: checkcast     #66                 // class java/lang/String
      82: astore        7
      84: aload         6
      86: aload_2
      87: aload         7
      89: invokeinterface #67,  2           // InterfaceMethod java/util/Map.get:(Ljava/lang/Object;)Ljava/lang/Object;
      94: invokeinterface #68,  2           // InterfaceMethod org/graylog2/plugin/database/validators/Validator.validate:(Ljava/lang/Object;)Lorg/graylog2/plugin/database/validators/ValidationResult;
      99: astore        8
     101: aload         8
     103: instanceof    #69                 // class org/graylog2/plugin/database/validators/ValidationResult$ValidationFailed
     106: ifeq          162
     109: getstatic     #70                 // Field LOG:Lorg/slf4j/Logger;
     112: ldc           #71                 // String Validation failure: [{}] on field [{}]
     114: aload         6
     116: invokevirtual #32                 // Method java/lang/Object.getClass:()Ljava/lang/Class;
     119: invokevirtual #28                 // Method java/lang/Class.getCanonicalName:()Ljava/lang/String;
     122: aload         7
     124: invokeinterface #72,  4           // InterfaceMethod org/slf4j/Logger.debug:(Ljava/lang/String;Ljava/lang/Object;Ljava/lang/Object;)V
     129: aload_3
     130: aload         7
     132: invokedynamic #73,  0             // InvokeDynamic #0:apply:()Ljava/util/function/Function;
     137: invokeinterface #74,  3           // InterfaceMethod java/util/Map.computeIfAbsent:(Ljava/lang/Object;Ljava/util/function/Function;)Ljava/lang/Object;
     142: pop
     143: aload_3
     144: aload         7
     146: invokeinterface #67,  2           // InterfaceMethod java/util/Map.get:(Ljava/lang/Object;)Ljava/lang/Object;
     151: checkcast     #75                 // class java/util/List
     154: aload         8
     156: invokeinterface #76,  2           // InterfaceMethod java/util/List.add:(Ljava/lang/Object;)Z
     161: pop
     162: goto          249
     165: astore        8
     167: new           #24                 // class java/lang/StringBuilder
     170: dup
     171: invokespecial #25                 // Method java/lang/StringBuilder."<init>":()V
     174: ldc           #78                 // String Error while trying to validate <
     176: invokevirtual #27                 // Method java/lang/StringBuilder.append:(Ljava/lang/String;)Ljava/lang/StringBuilder;
     179: aload         7
     181: invokevirtual #27                 // Method java/lang/StringBuilder.append:(Ljava/lang/String;)Ljava/lang/StringBuilder;
     184: ldc           #79                 // String >, got exception:
     186: invokevirtual #27                 // Method java/lang/StringBuilder.append:(Ljava/lang/String;)Ljava/lang/StringBuilder;
     189: aload         8
     191: invokevirtual #80                 // Method java/lang/StringBuilder.append:(Ljava/lang/Object;)Ljava/lang/StringBuilder;
     194: invokevirtual #29                 // Method java/lang/StringBuilder.toString:()Ljava/lang/String;
     197: astore        9
     199: getstatic     #70                 // Field LOG:Lorg/slf4j/Logger;
     202: aload         9
     204: invokeinterface #81,  2           // InterfaceMethod org/slf4j/Logger.debug:(Ljava/lang/String;)V
     209: aload_3
     210: aload         7
     212: invokedynamic #82,  0             // InvokeDynamic #1:apply:()Ljava/util/function/Function;
     217: invokeinterface #74,  3           // InterfaceMethod java/util/Map.computeIfAbsent:(Ljava/lang/Object;Ljava/util/function/Function;)Ljava/lang/Object;
     222: pop
     223: aload_3
     224: aload         7
     226: invokeinterface #67,  2           // InterfaceMethod java/util/Map.get:(Ljava/lang/Object;)Ljava/lang/Object;
     231: checkcast     #75                 // class java/util/List
     234: new           #69                 // class org/graylog2/plugin/database/validators/ValidationResult$ValidationFailed
     237: dup
     238: aload         9
     240: invokespecial #83                 // Method org/graylog2/plugin/database/validators/ValidationResult$ValidationFailed."<init>":(Ljava/lang/String;)V
     243: invokeinterface #76,  2           // InterfaceMethod java/util/List.add:(Ljava/lang/Object;)Z
     248: pop
     249: goto          38
     252: aload_3
     253: areturn
    Exception table:
       from    to  target type
          84   162   165   Class java/lang/Exception

  public <T extends org.graylog2.plugin.database.Persisted> java.util.Map<java.lang.String, java.util.List<org.graylog2.plugin.database.validators.ValidationResult>> validate(T);
    Code:
       0: aload_0
       1: aload_1
       2: aload_1
       3: invokeinterface #43,  1           // InterfaceMethod org/graylog2/plugin/database/Persisted.getFields:()Ljava/util/Map;
       8: invokevirtual #44                 // Method validate:(Lorg/graylog2/plugin/database/Persisted;Ljava/util/Map;)Ljava/util/Map;
      11: areturn

  protected <T extends org.graylog2.plugin.database.Persisted> void embed(T, java.lang.String, org.graylog2.plugin.database.EmbeddedPersistable) throws org.graylog2.plugin.database.ValidationException;
    Code:
       0: aload_0
       1: aload_1
       2: aload_2
       3: invokeinterface #84,  2           // InterfaceMethod org/graylog2/plugin/database/Persisted.getEmbeddedValidations:(Ljava/lang/String;)Ljava/util/Map;
       8: aload_3
       9: invokeinterface #85,  1           // InterfaceMethod org/graylog2/plugin/database/EmbeddedPersistable.getPersistedFields:()Ljava/util/Map;
      14: invokevirtual #54                 // Method validate:(Ljava/util/Map;Ljava/util/Map;)Ljava/util/Map;
      17: astore        4
      19: aload         4
      21: invokeinterface #45,  1           // InterfaceMethod java/util/Map.isEmpty:()Z
      26: ifne          39
      29: new           #46                 // class org/graylog2/plugin/database/ValidationException
      32: dup
      33: aload         4
      35: invokespecial #47                 // Method org/graylog2/plugin/database/ValidationException."<init>":(Ljava/util/Map;)V
      38: athrow
      39: aload_3
      40: invokeinterface #85,  1           // InterfaceMethod org/graylog2/plugin/database/EmbeddedPersistable.getPersistedFields:()Ljava/util/Map;
      45: invokestatic  #86                 // Method com/google/common/collect/Maps.newHashMap:(Ljava/util/Map;)Ljava/util/HashMap;
      48: astore        5
      50: aload_0
      51: aload         5
      53: invokespecial #50                 // Method fieldTransformations:(Ljava/util/Map;)V
      56: new           #4                  // class com/mongodb/BasicDBObject
      59: dup
      60: aload         5
      62: invokespecial #48                 // Method com/mongodb/BasicDBObject."<init>":(Ljava/util/Map;)V
      65: astore        6
      67: aload_0
      68: aload_1
      69: invokevirtual #39                 // Method collection:(Lorg/graylog2/plugin/database/Persisted;)Lcom/mongodb/DBCollection;
      72: new           #4                  // class com/mongodb/BasicDBObject
      75: dup
      76: ldc           #5                  // String _id
      78: new           #9                  // class org/bson/types/ObjectId
      81: dup
      82: aload_1
      83: invokeinterface #40,  1           // InterfaceMethod org/graylog2/plugin/database/Persisted.getId:()Ljava/lang/String;
      88: invokespecial #10                 // Method org/bson/types/ObjectId."<init>":(Ljava/lang/String;)V
      91: invokespecial #6                  // Method com/mongodb/BasicDBObject."<init>":(Ljava/lang/String;Ljava/lang/Object;)V
      94: new           #4                  // class com/mongodb/BasicDBObject
      97: dup
      98: ldc           #87                 // String $push
     100: new           #4                  // class com/mongodb/BasicDBObject
     103: dup
     104: aload_2
     105: aload         6
     107: invokespecial #6                  // Method com/mongodb/BasicDBObject."<init>":(Ljava/lang/String;Ljava/lang/Object;)V
     110: invokespecial #6                  // Method com/mongodb/BasicDBObject."<init>":(Ljava/lang/String;Ljava/lang/Object;)V
     113: invokevirtual #88                 // Method com/mongodb/DBCollection.update:(Lcom/mongodb/DBObject;Lcom/mongodb/DBObject;)Lcom/mongodb/WriteResult;
     116: pop
     117: return

  protected <T extends org.graylog2.plugin.database.Persisted> void removeEmbedded(T, java.lang.String, java.lang.String);
    Code:
       0: new           #4                  // class com/mongodb/BasicDBObject
       3: dup
       4: ldc           #89                 // String id
       6: aload_3
       7: invokespecial #6                  // Method com/mongodb/BasicDBObject."<init>":(Ljava/lang/String;Ljava/lang/Object;)V
      10: astore        4
      12: new           #4                  // class com/mongodb/BasicDBObject
      15: dup
      16: ldc           #5                  // String _id
      18: new           #9                  // class org/bson/types/ObjectId
      21: dup
      22: aload_1
      23: invokeinterface #40,  1           // InterfaceMethod org/graylog2/plugin/database/Persisted.getId:()Ljava/lang/String;
      28: invokespecial #10                 // Method org/bson/types/ObjectId."<init>":(Ljava/lang/String;)V
      31: invokespecial #6                  // Method com/mongodb/BasicDBObject."<init>":(Ljava/lang/String;Ljava/lang/Object;)V
      34: astore        5
      36: new           #4                  // class com/mongodb/BasicDBObject
      39: dup
      40: ldc           #90                 // String $pull
      42: new           #4                  // class com/mongodb/BasicDBObject
      45: dup
      46: aload_2
      47: aload         4
      49: invokespecial #6                  // Method com/mongodb/BasicDBObject."<init>":(Ljava/lang/String;Ljava/lang/Object;)V
      52: invokespecial #6                  // Method com/mongodb/BasicDBObject."<init>":(Ljava/lang/String;Ljava/lang/Object;)V
      55: astore        6
      57: aload_0
      58: aload_1
      59: invokevirtual #39                 // Method collection:(Lorg/graylog2/plugin/database/Persisted;)Lcom/mongodb/DBCollection;
      62: aload         5
      64: aload         6
      66: invokevirtual #88                 // Method com/mongodb/DBCollection.update:(Lcom/mongodb/DBObject;Lcom/mongodb/DBObject;)Lcom/mongodb/WriteResult;
      69: pop
      70: return

  protected <T extends org.graylog2.plugin.database.Persisted> void removeEmbedded(T, java.lang.String, java.lang.String, java.lang.String);
    Code:
       0: new           #4                  // class com/mongodb/BasicDBObject
       3: dup
       4: aload_2
       5: aload         4
       7: invokespecial #6                  // Method com/mongodb/BasicDBObject."<init>":(Ljava/lang/String;Ljava/lang/Object;)V
      10: astore        5
      12: new           #4                  // class com/mongodb/BasicDBObject
      15: dup
      16: ldc           #5                  // String _id
      18: new           #9                  // class org/bson/types/ObjectId
      21: dup
      22: aload_1
      23: invokeinterface #40,  1           // InterfaceMethod org/graylog2/plugin/database/Persisted.getId:()Ljava/lang/String;
      28: invokespecial #10                 // Method org/bson/types/ObjectId."<init>":(Ljava/lang/String;)V
      31: invokespecial #6                  // Method com/mongodb/BasicDBObject."<init>":(Ljava/lang/String;Ljava/lang/Object;)V
      34: astore        6
      36: new           #4                  // class com/mongodb/BasicDBObject
      39: dup
      40: ldc           #90                 // String $pull
      42: new           #4                  // class com/mongodb/BasicDBObject
      45: dup
      46: aload_3
      47: aload         5
      49: invokespecial #6                  // Method com/mongodb/BasicDBObject."<init>":(Ljava/lang/String;Ljava/lang/Object;)V
      52: invokespecial #6                  // Method com/mongodb/BasicDBObject."<init>":(Ljava/lang/String;Ljava/lang/Object;)V
      55: astore        7
      57: aload_0
      58: aload_1
      59: invokevirtual #39                 // Method collection:(Lorg/graylog2/plugin/database/Persisted;)Lcom/mongodb/DBCollection;
      62: aload         6
      64: aload         7
      66: invokevirtual #88                 // Method com/mongodb/DBCollection.update:(Lcom/mongodb/DBObject;Lcom/mongodb/DBObject;)Lcom/mongodb/WriteResult;
      69: pop
      70: return

  private void fieldTransformations(java.util.Map<java.lang.String, java.lang.Object>);
    Code:
       0: aload_1
       1: invokeinterface #58,  1           // InterfaceMethod java/util/Map.entrySet:()Ljava/util/Set;
       6: invokeinterface #59,  1           // InterfaceMethod java/util/Set.iterator:()Ljava/util/Iterator;
      11: astore_2
      12: aload_2
      13: invokeinterface #60,  1           // InterfaceMethod java/util/Iterator.hasNext:()Z
      18: ifeq          158
      21: aload_2
      22: invokeinterface #61,  1           // InterfaceMethod java/util/Iterator.next:()Ljava/lang/Object;
      27: checkcast     #62                 // class java/util/Map$Entry
      30: astore_3
      31: aload_3
      32: invokeinterface #63,  1           // InterfaceMethod java/util/Map$Entry.getValue:()Ljava/lang/Object;
      37: instanceof    #91                 // class java/util/Map
      40: ifeq          78
      43: aload_3
      44: aload_3
      45: invokeinterface #63,  1           // InterfaceMethod java/util/Map$Entry.getValue:()Ljava/lang/Object;
      50: checkcast     #91                 // class java/util/Map
      53: invokestatic  #86                 // Method com/google/common/collect/Maps.newHashMap:(Ljava/util/Map;)Ljava/util/HashMap;
      56: invokeinterface #92,  2           // InterfaceMethod java/util/Map$Entry.setValue:(Ljava/lang/Object;)Ljava/lang/Object;
      61: pop
      62: aload_0
      63: aload_3
      64: invokeinterface #63,  1           // InterfaceMethod java/util/Map$Entry.getValue:()Ljava/lang/Object;
      69: checkcast     #91                 // class java/util/Map
      72: invokespecial #50                 // Method fieldTransformations:(Ljava/util/Map;)V
      75: goto          12
      78: aload_3
      79: invokeinterface #63,  1           // InterfaceMethod java/util/Map$Entry.getValue:()Ljava/lang/Object;
      84: instanceof    #93                 // class org/joda/time/DateTime
      87: ifeq          118
      90: aload_1
      91: aload_3
      92: invokeinterface #65,  1           // InterfaceMethod java/util/Map$Entry.getKey:()Ljava/lang/Object;
      97: checkcast     #66                 // class java/lang/String
     100: aload_3
     101: invokeinterface #63,  1           // InterfaceMethod java/util/Map$Entry.getValue:()Ljava/lang/Object;
     106: checkcast     #93                 // class org/joda/time/DateTime
     109: invokevirtual #94                 // Method org/joda/time/DateTime.toDate:()Ljava/util/Date;
     112: invokeinterface #95,  3           // InterfaceMethod java/util/Map.put:(Ljava/lang/Object;Ljava/lang/Object;)Ljava/lang/Object;
     117: pop
     118: aload_3
     119: invokeinterface #63,  1           // InterfaceMethod java/util/Map$Entry.getValue:()Ljava/lang/Object;
     124: instanceof    #96                 // class org/graylog2/plugin/system/NodeId
     127: ifeq          155
     130: aload_1
     131: aload_3
     132: invokeinterface #65,  1           // InterfaceMethod java/util/Map$Entry.getKey:()Ljava/lang/Object;
     137: checkcast     #66                 // class java/lang/String
     140: aload_3
     141: invokeinterface #63,  1           // InterfaceMethod java/util/Map$Entry.getValue:()Ljava/lang/Object;
     146: invokevirtual #97                 // Method java/lang/Object.toString:()Ljava/lang/String;
     149: invokeinterface #95,  3           // InterfaceMethod java/util/Map.put:(Ljava/lang/Object;Ljava/lang/Object;)Ljava/lang/Object;
     154: pop
     155: goto          12
     158: return

  private static java.util.List lambda$validate$1(java.lang.String);
    Code:
       0: new           #98                 // class java/util/ArrayList
       3: dup
       4: invokespecial #99                 // Method java/util/ArrayList."<init>":()V
       7: areturn

  private static java.util.List lambda$validate$0(java.lang.String);
    Code:
       0: new           #98                 // class java/util/ArrayList
       3: dup
       4: invokespecial #99                 // Method java/util/ArrayList."<init>":()V
       7: areturn

  static {};
    Code:
       0: ldc           #100                // class org/graylog2/database/PersistedServiceImpl
       2: invokestatic  #101                // Method org/slf4j/LoggerFactory.getLogger:(Ljava/lang/Class;)Lorg/slf4j/Logger;
       5: putstatic     #70                 // Field LOG:Lorg/slf4j/Logger;
       8: return
}
