Compiled from "RemoteNamingStoreV1.java"
class org.jboss.naming.remote.protocol.v1.RemoteNamingStoreV1$MessageReceiver$1 implements java.lang.Runnable {
  final org.jboss.naming.remote.protocol.ProtocolCommand val$command;

  final java.io.DataInputStream val$dis;

  final int val$correlationId;

  final org.jboss.naming.remote.protocol.v1.RemoteNamingStoreV1$MessageReceiver this$1;

  org.jboss.naming.remote.protocol.v1.RemoteNamingStoreV1$MessageReceiver$1(org.jboss.naming.remote.protocol.v1.RemoteNamingStoreV1$MessageReceiver, org.jboss.naming.remote.protocol.ProtocolCommand, java.io.DataInputStream, int);
    Code:
       0: aload_0
       1: aload_1
       2: putfield      #1                  // Field this$1:Lorg/jboss/naming/remote/protocol/v1/RemoteNamingStoreV1$MessageReceiver;
       5: aload_0
       6: aload_2
       7: putfield      #2                  // Field val$command:Lorg/jboss/naming/remote/protocol/ProtocolCommand;
      10: aload_0
      11: aload_3
      12: putfield      #3                  // Field val$dis:Ljava/io/DataInputStream;
      15: aload_0
      16: iload         4
      18: putfield      #4                  // Field val$correlationId:I
      21: aload_0
      22: invokespecial #5                  // Method java/lang/Object."<init>":()V
      25: return

  public void run();
    Code:
       0: aload_0
       1: getfield      #2                  // Field val$command:Lorg/jboss/naming/remote/protocol/ProtocolCommand;
       4: aload_0
       5: getfield      #3                  // Field val$dis:Ljava/io/DataInputStream;
       8: aload_0
       9: getfield      #4                  // Field val$correlationId:I
      12: aload_0
      13: getfield      #1                  // Field this$1:Lorg/jboss/naming/remote/protocol/v1/RemoteNamingStoreV1$MessageReceiver;
      16: getfield      #6                  // Field org/jboss/naming/remote/protocol/v1/RemoteNamingStoreV1$MessageReceiver.this$0:Lorg/jboss/naming/remote/protocol/v1/RemoteNamingStoreV1;
      19: invokeinterface #7,  4            // InterfaceMethod org/jboss/naming/remote/protocol/ProtocolCommand.handleClientMessage:(Ljava/io/DataInput;ILorg/jboss/naming/remote/client/RemoteNamingStore;)V
      24: aload_0
      25: getfield      #3                  // Field val$dis:Ljava/io/DataInputStream;
      28: invokestatic  #8                  // Method org/xnio/IoUtils.safeClose:(Ljava/io/Closeable;)V
      31: goto          62
      34: astore_1
      35: invokestatic  #10                 // Method org/jboss/naming/remote/protocol/v1/RemoteNamingStoreV1.access$100:()Lorg/jboss/logging/Logger;
      38: aload_1
      39: invokevirtual #11                 // Method org/jboss/logging/Logger.error:(Ljava/lang/Object;)V
      42: aload_0
      43: getfield      #3                  // Field val$dis:Ljava/io/DataInputStream;
      46: invokestatic  #8                  // Method org/xnio/IoUtils.safeClose:(Ljava/io/Closeable;)V
      49: goto          62
      52: astore_2
      53: aload_0
      54: getfield      #3                  // Field val$dis:Ljava/io/DataInputStream;
      57: invokestatic  #8                  // Method org/xnio/IoUtils.safeClose:(Ljava/io/Closeable;)V
      60: aload_2
      61: athrow
      62: return
    Exception table:
       from    to  target type
           0    24    34   Class java/io/IOException
           0    24    52   any
          34    42    52   any
          52    53    52   any
}
