Compiled from "MailSessionFactory.java"
public class org.apache.naming.factory.MailSessionFactory implements javax.naming.spi.ObjectFactory {
  protected static final java.lang.String factoryType;

  public org.apache.naming.factory.MailSessionFactory();
    Code:
       0: aload_0
       1: invokespecial #1                  // Method java/lang/Object."<init>":()V
       4: return

  public java.lang.Object getObjectInstance(java.lang.Object, javax.naming.Name, javax.naming.Context, java.util.Hashtable<?, ?>) throws java.lang.Exception;
    Code:
       0: aload_1
       1: checkcast     #2                  // class javax/naming/Reference
       4: astore        5
       6: aload         5
       8: invokevirtual #3                  // Method javax/naming/Reference.getClassName:()Ljava/lang/String;
      11: ldc           #5                  // String javax.mail.Session
      13: invokevirtual #6                  // Method java/lang/String.equals:(Ljava/lang/Object;)Z
      16: ifne          21
      19: aconst_null
      20: areturn
      21: new           #7                  // class org/apache/naming/factory/MailSessionFactory$1
      24: dup
      25: aload_0
      26: aload         5
      28: invokespecial #8                  // Method org/apache/naming/factory/MailSessionFactory$1."<init>":(Lorg/apache/naming/factory/MailSessionFactory;Ljavax/naming/Reference;)V
      31: invokestatic  #9                  // Method java/security/AccessController.doPrivileged:(Ljava/security/PrivilegedAction;)Ljava/lang/Object;
      34: areturn
}
