Compiled from "JsonPathExpression.java"
public class org.apache.camel.jsonpath.JsonPathExpression extends org.apache.camel.support.ExpressionAdapter implements org.apache.camel.AfterPropertiesConfigured {
  private final java.lang.String expression;

  private org.apache.camel.jsonpath.JsonPathEngine engine;

  private java.lang.Class<?> resultType;

  private boolean suppressExceptions;

  private boolean allowSimple;

  private com.jayway.jsonpath.Option[] options;

  public org.apache.camel.jsonpath.JsonPathExpression(java.lang.String);
    Code:
       0: aload_0
       1: invokespecial #1                  // Method org/apache/camel/support/ExpressionAdapter."<init>":()V
       4: aload_0
       5: iconst_1
       6: putfield      #2                  // Field allowSimple:Z
       9: aload_0
      10: aload_1
      11: putfield      #3                  // Field expression:Ljava/lang/String;
      14: return

  public java.lang.Class<?> getResultType();
    Code:
       0: aload_0
       1: getfield      #4                  // Field resultType:Ljava/lang/Class;
       4: areturn

  public void setResultType(java.lang.Class<?>);
    Code:
       0: aload_0
       1: aload_1
       2: putfield      #4                  // Field resultType:Ljava/lang/Class;
       5: return

  public boolean isSuppressExceptions();
    Code:
       0: aload_0
       1: getfield      #5                  // Field suppressExceptions:Z
       4: ireturn

  public void setSuppressExceptions(boolean);
    Code:
       0: aload_0
       1: iload_1
       2: putfield      #5                  // Field suppressExceptions:Z
       5: return

  public boolean isAllowSimple();
    Code:
       0: aload_0
       1: getfield      #2                  // Field allowSimple:Z
       4: ireturn

  public void setAllowSimple(boolean);
    Code:
       0: aload_0
       1: iload_1
       2: putfield      #2                  // Field allowSimple:Z
       5: return

  public com.jayway.jsonpath.Option[] getOptions();
    Code:
       0: aload_0
       1: getfield      #6                  // Field options:[Lcom/jayway/jsonpath/Option;
       4: areturn

  public void setOptions(com.jayway.jsonpath.Option[]);
    Code:
       0: aload_0
       1: aload_1
       2: putfield      #6                  // Field options:[Lcom/jayway/jsonpath/Option;
       5: return

  public java.lang.Object evaluate(org.apache.camel.Exchange);
    Code:
       0: aload_0
       1: aload_1
       2: aload_0
       3: getfield      #7                  // Field engine:Lorg/apache/camel/jsonpath/JsonPathEngine;
       6: invokespecial #8                  // Method evaluateJsonPath:(Lorg/apache/camel/Exchange;Lorg/apache/camel/jsonpath/JsonPathEngine;)Ljava/lang/Object;
       9: astore_2
      10: aload_0
      11: getfield      #4                  // Field resultType:Ljava/lang/Class;
      14: ifnull        40
      17: aload_1
      18: invokeinterface #9,  1            // InterfaceMethod org/apache/camel/Exchange.getContext:()Lorg/apache/camel/CamelContext;
      23: invokeinterface #10,  1           // InterfaceMethod org/apache/camel/CamelContext.getTypeConverter:()Lorg/apache/camel/TypeConverter;
      28: aload_0
      29: getfield      #4                  // Field resultType:Ljava/lang/Class;
      32: aload_1
      33: aload_2
      34: invokeinterface #11,  4           // InterfaceMethod org/apache/camel/TypeConverter.convertTo:(Ljava/lang/Class;Lorg/apache/camel/Exchange;Ljava/lang/Object;)Ljava/lang/Object;
      39: areturn
      40: aload_2
      41: areturn
      42: astore_2
      43: new           #13                 // class org/apache/camel/ExpressionEvaluationException
      46: dup
      47: aload_0
      48: aload_1
      49: aload_2
      50: invokespecial #14                 // Method org/apache/camel/ExpressionEvaluationException."<init>":(Lorg/apache/camel/Expression;Lorg/apache/camel/Exchange;Ljava/lang/Throwable;)V
      53: athrow
    Exception table:
       from    to  target type
           0    39    42   Class java/lang/Exception
          40    41    42   Class java/lang/Exception

  public void afterPropertiesConfigured(org.apache.camel.CamelContext);
    Code:
       0: aload_0
       1: invokevirtual #15                 // Method init:()V
       4: return

  public void init();
    Code:
       0: aload_0
       1: new           #16                 // class org/apache/camel/jsonpath/JsonPathEngine
       4: dup
       5: aload_0
       6: getfield      #3                  // Field expression:Ljava/lang/String;
       9: aload_0
      10: getfield      #5                  // Field suppressExceptions:Z
      13: aload_0
      14: getfield      #2                  // Field allowSimple:Z
      17: aload_0
      18: getfield      #6                  // Field options:[Lcom/jayway/jsonpath/Option;
      21: invokespecial #17                 // Method org/apache/camel/jsonpath/JsonPathEngine."<init>":(Ljava/lang/String;ZZ[Lcom/jayway/jsonpath/Option;)V
      24: putfield      #7                  // Field engine:Lorg/apache/camel/jsonpath/JsonPathEngine;
      27: goto          44
      30: astore_1
      31: new           #18                 // class org/apache/camel/ExpressionIllegalSyntaxException
      34: dup
      35: aload_0
      36: getfield      #3                  // Field expression:Ljava/lang/String;
      39: aload_1
      40: invokespecial #19                 // Method org/apache/camel/ExpressionIllegalSyntaxException."<init>":(Ljava/lang/String;Ljava/lang/Throwable;)V
      43: athrow
      44: return
    Exception table:
       from    to  target type
           0    27    30   Class java/lang/Exception

  public java.lang.String toString();
    Code:
       0: new           #20                 // class java/lang/StringBuilder
       3: dup
       4: invokespecial #21                 // Method java/lang/StringBuilder."<init>":()V
       7: ldc           #22                 // String jsonpath[
       9: invokevirtual #23                 // Method java/lang/StringBuilder.append:(Ljava/lang/String;)Ljava/lang/StringBuilder;
      12: aload_0
      13: getfield      #3                  // Field expression:Ljava/lang/String;
      16: invokevirtual #23                 // Method java/lang/StringBuilder.append:(Ljava/lang/String;)Ljava/lang/StringBuilder;
      19: ldc           #24                 // String ]
      21: invokevirtual #23                 // Method java/lang/StringBuilder.append:(Ljava/lang/String;)Ljava/lang/StringBuilder;
      24: invokevirtual #25                 // Method java/lang/StringBuilder.toString:()Ljava/lang/String;
      27: areturn

  private java.lang.Object evaluateJsonPath(org.apache.camel.Exchange, org.apache.camel.jsonpath.JsonPathEngine) throws java.lang.Exception;
    Code:
       0: aload_2
       1: aload_1
       2: invokevirtual #26                 // Method org/apache/camel/jsonpath/JsonPathEngine.read:(Lorg/apache/camel/Exchange;)Ljava/lang/Object;
       5: areturn
}
