Compiled from "AsyncContextImpl.java"
class io.undertow.servlet.spec.AsyncContextImpl$4 implements java.lang.Runnable {
  final java.lang.Runnable val$run;

  final io.undertow.servlet.spec.AsyncContextImpl this$0;

  io.undertow.servlet.spec.AsyncContextImpl$4(io.undertow.servlet.spec.AsyncContextImpl, java.lang.Runnable);
    Code:
       0: aload_0
       1: aload_1
       2: putfield      #1                  // Field this$0:Lio/undertow/servlet/spec/AsyncContextImpl;
       5: aload_0
       6: aload_2
       7: putfield      #2                  // Field val$run:Ljava/lang/Runnable;
      10: aload_0
      11: invokespecial #3                  // Method java/lang/Object."<init>":()V
      14: return

  public void run();
    Code:
       0: aload_0
       1: getfield      #1                  // Field this$0:Lio/undertow/servlet/spec/AsyncContextImpl;
       4: getfield      #4                  // Field io/undertow/servlet/spec/AsyncContextImpl.servletRequestContext:Lio/undertow/servlet/handlers/ServletRequestContext;
       7: invokevirtual #5                  // Method io/undertow/servlet/handlers/ServletRequestContext.getCurrentServletContext:()Lio/undertow/servlet/spec/ServletContextImpl;
      10: aload_0
      11: getfield      #1                  // Field this$0:Lio/undertow/servlet/spec/AsyncContextImpl;
      14: getfield      #6                  // Field io/undertow/servlet/spec/AsyncContextImpl.exchange:Lio/undertow/server/HttpServerExchange;
      17: aload_0
      18: getfield      #2                  // Field val$run:Ljava/lang/Runnable;
      21: invokevirtual #7                  // Method io/undertow/servlet/spec/ServletContextImpl.invokeRunnable:(Lio/undertow/server/HttpServerExchange;Ljava/lang/Runnable;)V
      24: return
}
