Compiled from "HttpServletRequestImpl.java"
public final class io.undertow.servlet.spec.HttpServletRequestImpl implements jakarta.servlet.http.HttpServletRequest {
  public static final io.undertow.util.AttachmentKey<java.lang.Boolean> SECURE_REQUEST;

  static final io.undertow.util.AttachmentKey<java.lang.Boolean> REQUESTED_SESSION_ID_SET;

  static final io.undertow.util.AttachmentKey<java.lang.String> REQUESTED_SESSION_ID;

  private final io.undertow.server.HttpServerExchange exchange;

  private final io.undertow.servlet.spec.ServletContextImpl originalServletContext;

  private io.undertow.servlet.spec.ServletContextImpl servletContext;

  private java.util.Map<java.lang.String, java.lang.Object> attributes;

  private jakarta.servlet.ServletInputStream servletInputStream;

  private java.io.BufferedReader reader;

  private jakarta.servlet.http.Cookie[] cookies;

  private java.util.List<jakarta.servlet.http.Part> parts;

  private volatile boolean asyncStarted;

  private volatile io.undertow.servlet.spec.AsyncContextImpl asyncContext;

  private java.util.Map<java.lang.String, java.util.Deque<java.lang.String>> queryParameters;

  private io.undertow.server.handlers.form.FormData parsedFormData;

  private java.lang.RuntimeException formParsingException;

  private java.nio.charset.Charset characterEncoding;

  private boolean readStarted;

  private io.undertow.server.session.SessionConfig$SessionCookieSource sessionCookieSource;

  public io.undertow.servlet.spec.HttpServletRequestImpl(io.undertow.server.HttpServerExchange, io.undertow.servlet.spec.ServletContextImpl);
    Code:
       0: aload_0
       1: invokespecial #1                  // Method java/lang/Object."<init>":()V
       4: aload_0
       5: aconst_null
       6: putfield      #2                  // Field attributes:Ljava/util/Map;
       9: aload_0
      10: aconst_null
      11: putfield      #3                  // Field parts:Ljava/util/List;
      14: aload_0
      15: iconst_0
      16: putfield      #4                  // Field asyncStarted:Z
      19: aload_0
      20: aconst_null
      21: putfield      #5                  // Field asyncContext:Lio/undertow/servlet/spec/AsyncContextImpl;
      24: aload_0
      25: aload_1
      26: putfield      #6                  // Field exchange:Lio/undertow/server/HttpServerExchange;
      29: aload_0
      30: aload_2
      31: putfield      #7                  // Field servletContext:Lio/undertow/servlet/spec/ServletContextImpl;
      34: aload_0
      35: aload_2
      36: putfield      #8                  // Field originalServletContext:Lio/undertow/servlet/spec/ServletContextImpl;
      39: return

  public io.undertow.server.HttpServerExchange getExchange();
    Code:
       0: aload_0
       1: getfield      #6                  // Field exchange:Lio/undertow/server/HttpServerExchange;
       4: areturn

  public java.lang.String getAuthType();
    Code:
       0: aload_0
       1: getfield      #6                  // Field exchange:Lio/undertow/server/HttpServerExchange;
       4: invokevirtual #9                  // Method io/undertow/server/HttpServerExchange.getSecurityContext:()Lio/undertow/security/api/SecurityContext;
       7: astore_1
       8: aload_1
       9: ifnull        21
      12: aload_1
      13: invokeinterface #10,  1           // InterfaceMethod io/undertow/security/api/SecurityContext.getMechanismName:()Ljava/lang/String;
      18: goto          22
      21: aconst_null
      22: areturn

  public jakarta.servlet.http.Cookie[] getCookies();
    Code:
       0: aload_0
       1: getfield      #11                 // Field cookies:[Ljakarta/servlet/http/Cookie;
       4: ifnonnull     270
       7: aload_0
       8: getfield      #6                  // Field exchange:Lio/undertow/server/HttpServerExchange;
      11: invokevirtual #12                 // Method io/undertow/server/HttpServerExchange.requestCookies:()Ljava/lang/Iterable;
      14: astore_1
      15: iconst_0
      16: istore_2
      17: aload_1
      18: invokeinterface #13,  1           // InterfaceMethod java/lang/Iterable.iterator:()Ljava/util/Iterator;
      23: astore_3
      24: aload_3
      25: invokeinterface #14,  1           // InterfaceMethod java/util/Iterator.hasNext:()Z
      30: ifeq          50
      33: aload_3
      34: invokeinterface #15,  1           // InterfaceMethod java/util/Iterator.next:()Ljava/lang/Object;
      39: checkcast     #16                 // class io/undertow/server/handlers/Cookie
      42: astore        4
      44: iinc          2, 1
      47: goto          24
      50: iload_2
      51: ifne          56
      54: aconst_null
      55: areturn
      56: iload_2
      57: anewarray     #17                 // class jakarta/servlet/http/Cookie
      60: astore_3
      61: iconst_0
      62: istore        4
      64: aload_1
      65: invokeinterface #13,  1           // InterfaceMethod java/lang/Iterable.iterator:()Ljava/util/Iterator;
      70: astore        5
      72: aload         5
      74: invokeinterface #14,  1           // InterfaceMethod java/util/Iterator.hasNext:()Z
      79: ifeq          239
      82: aload         5
      84: invokeinterface #15,  1           // InterfaceMethod java/util/Iterator.next:()Ljava/lang/Object;
      89: checkcast     #16                 // class io/undertow/server/handlers/Cookie
      92: astore        6
      94: new           #17                 // class jakarta/servlet/http/Cookie
      97: dup
      98: aload         6
     100: invokeinterface #18,  1           // InterfaceMethod io/undertow/server/handlers/Cookie.getName:()Ljava/lang/String;
     105: aload         6
     107: invokeinterface #19,  1           // InterfaceMethod io/undertow/server/handlers/Cookie.getValue:()Ljava/lang/String;
     112: invokespecial #20                 // Method jakarta/servlet/http/Cookie."<init>":(Ljava/lang/String;Ljava/lang/String;)V
     115: astore        7
     117: aload         6
     119: invokeinterface #21,  1           // InterfaceMethod io/undertow/server/handlers/Cookie.getDomain:()Ljava/lang/String;
     124: ifnull        139
     127: aload         7
     129: aload         6
     131: invokeinterface #21,  1           // InterfaceMethod io/undertow/server/handlers/Cookie.getDomain:()Ljava/lang/String;
     136: invokevirtual #22                 // Method jakarta/servlet/http/Cookie.setDomain:(Ljava/lang/String;)V
     139: aload         7
     141: aload         6
     143: invokeinterface #23,  1           // InterfaceMethod io/undertow/server/handlers/Cookie.isHttpOnly:()Z
     148: invokevirtual #24                 // Method jakarta/servlet/http/Cookie.setHttpOnly:(Z)V
     151: aload         6
     153: invokeinterface #25,  1           // InterfaceMethod io/undertow/server/handlers/Cookie.getMaxAge:()Ljava/lang/Integer;
     158: ifnull        176
     161: aload         7
     163: aload         6
     165: invokeinterface #25,  1           // InterfaceMethod io/undertow/server/handlers/Cookie.getMaxAge:()Ljava/lang/Integer;
     170: invokevirtual #26                 // Method java/lang/Integer.intValue:()I
     173: invokevirtual #27                 // Method jakarta/servlet/http/Cookie.setMaxAge:(I)V
     176: aload         6
     178: invokeinterface #28,  1           // InterfaceMethod io/undertow/server/handlers/Cookie.getPath:()Ljava/lang/String;
     183: ifnull        198
     186: aload         7
     188: aload         6
     190: invokeinterface #28,  1           // InterfaceMethod io/undertow/server/handlers/Cookie.getPath:()Ljava/lang/String;
     195: invokevirtual #29                 // Method jakarta/servlet/http/Cookie.setPath:(Ljava/lang/String;)V
     198: aload         7
     200: aload         6
     202: invokeinterface #30,  1           // InterfaceMethod io/undertow/server/handlers/Cookie.isSecure:()Z
     207: invokevirtual #31                 // Method jakarta/servlet/http/Cookie.setSecure:(Z)V
     210: aload         7
     212: aload         6
     214: invokeinterface #32,  1           // InterfaceMethod io/undertow/server/handlers/Cookie.getVersion:()I
     219: invokevirtual #33                 // Method jakarta/servlet/http/Cookie.setVersion:(I)V
     222: aload_3
     223: iload         4
     225: iinc          4, 1
     228: aload         7
     230: aastore
     231: goto          236
     234: astore        7
     236: goto          72
     239: iload         4
     241: iload_2
     242: if_icmpge     265
     245: iload         4
     247: anewarray     #17                 // class jakarta/servlet/http/Cookie
     250: astore        5
     252: aload_3
     253: iconst_0
     254: aload         5
     256: iconst_0
     257: iload         4
     259: invokestatic  #35                 // Method java/lang/System.arraycopy:(Ljava/lang/Object;ILjava/lang/Object;II)V
     262: aload         5
     264: astore_3
     265: aload_0
     266: aload_3
     267: putfield      #11                 // Field cookies:[Ljakarta/servlet/http/Cookie;
     270: aload_0
     271: getfield      #11                 // Field cookies:[Ljakarta/servlet/http/Cookie;
     274: areturn
    Exception table:
       from    to  target type
          94   231   234   Class java/lang/IllegalArgumentException

  public long getDateHeader(java.lang.String);
    Code:
       0: aload_0
       1: getfield      #6                  // Field exchange:Lio/undertow/server/HttpServerExchange;
       4: invokevirtual #36                 // Method io/undertow/server/HttpServerExchange.getRequestHeaders:()Lio/undertow/util/HeaderMap;
       7: aload_1
       8: invokevirtual #37                 // Method io/undertow/util/HeaderMap.getFirst:(Ljava/lang/String;)Ljava/lang/String;
      11: astore_2
      12: aload_2
      13: ifnonnull     20
      16: ldc2_w        #38                 // long -1l
      19: lreturn
      20: aload_2
      21: invokestatic  #40                 // Method io/undertow/util/DateUtils.parseDate:(Ljava/lang/String;)Ljava/util/Date;
      24: astore_3
      25: aload_3
      26: ifnonnull     39
      29: getstatic     #41                 // Field io/undertow/servlet/UndertowServletMessages.MESSAGES:Lio/undertow/servlet/UndertowServletMessages;
      32: aload_2
      33: invokeinterface #42,  2           // InterfaceMethod io/undertow/servlet/UndertowServletMessages.headerCannotBeConvertedToDate:(Ljava/lang/String;)Ljava/lang/IllegalArgumentException;
      38: athrow
      39: aload_3
      40: invokevirtual #43                 // Method java/util/Date.getTime:()J
      43: lreturn

  public java.lang.String getHeader(java.lang.String);
    Code:
       0: aload_0
       1: getfield      #6                  // Field exchange:Lio/undertow/server/HttpServerExchange;
       4: invokevirtual #36                 // Method io/undertow/server/HttpServerExchange.getRequestHeaders:()Lio/undertow/util/HeaderMap;
       7: astore_2
       8: aload_2
       9: aload_1
      10: invokevirtual #37                 // Method io/undertow/util/HeaderMap.getFirst:(Ljava/lang/String;)Ljava/lang/String;
      13: areturn

  public java.lang.String getHeader(io.undertow.util.HttpString);
    Code:
       0: aload_0
       1: getfield      #6                  // Field exchange:Lio/undertow/server/HttpServerExchange;
       4: invokevirtual #36                 // Method io/undertow/server/HttpServerExchange.getRequestHeaders:()Lio/undertow/util/HeaderMap;
       7: astore_2
       8: aload_2
       9: aload_1
      10: invokevirtual #44                 // Method io/undertow/util/HeaderMap.getFirst:(Lio/undertow/util/HttpString;)Ljava/lang/String;
      13: areturn

  public java.util.Enumeration<java.lang.String> getHeaders(java.lang.String);
    Code:
       0: aload_0
       1: getfield      #6                  // Field exchange:Lio/undertow/server/HttpServerExchange;
       4: invokevirtual #36                 // Method io/undertow/server/HttpServerExchange.getRequestHeaders:()Lio/undertow/util/HeaderMap;
       7: aload_1
       8: invokevirtual #45                 // Method io/undertow/util/HeaderMap.get:(Ljava/lang/String;)Lio/undertow/util/HeaderValues;
      11: astore_2
      12: aload_2
      13: ifnonnull     20
      16: invokestatic  #46                 // Method io/undertow/servlet/util/EmptyEnumeration.instance:()Ljava/util/Enumeration;
      19: areturn
      20: new           #47                 // class io/undertow/servlet/util/IteratorEnumeration
      23: dup
      24: aload_2
      25: invokeinterface #48,  1           // InterfaceMethod java/util/List.iterator:()Ljava/util/Iterator;
      30: invokespecial #49                 // Method io/undertow/servlet/util/IteratorEnumeration."<init>":(Ljava/util/Iterator;)V
      33: areturn

  public java.util.Enumeration<java.lang.String> getHeaderNames();
    Code:
       0: new           #50                 // class java/util/HashSet
       3: dup
       4: invokespecial #51                 // Method java/util/HashSet."<init>":()V
       7: astore_1
       8: aload_0
       9: getfield      #6                  // Field exchange:Lio/undertow/server/HttpServerExchange;
      12: invokevirtual #36                 // Method io/undertow/server/HttpServerExchange.getRequestHeaders:()Lio/undertow/util/HeaderMap;
      15: invokevirtual #52                 // Method io/undertow/util/HeaderMap.getHeaderNames:()Ljava/util/Collection;
      18: invokeinterface #53,  1           // InterfaceMethod java/util/Collection.iterator:()Ljava/util/Iterator;
      23: astore_2
      24: aload_2
      25: invokeinterface #14,  1           // InterfaceMethod java/util/Iterator.hasNext:()Z
      30: ifeq          57
      33: aload_2
      34: invokeinterface #15,  1           // InterfaceMethod java/util/Iterator.next:()Ljava/lang/Object;
      39: checkcast     #54                 // class io/undertow/util/HttpString
      42: astore_3
      43: aload_1
      44: aload_3
      45: invokevirtual #55                 // Method io/undertow/util/HttpString.toString:()Ljava/lang/String;
      48: invokeinterface #56,  2           // InterfaceMethod java/util/Set.add:(Ljava/lang/Object;)Z
      53: pop
      54: goto          24
      57: new           #47                 // class io/undertow/servlet/util/IteratorEnumeration
      60: dup
      61: aload_1
      62: invokeinterface #57,  1           // InterfaceMethod java/util/Set.iterator:()Ljava/util/Iterator;
      67: invokespecial #49                 // Method io/undertow/servlet/util/IteratorEnumeration."<init>":(Ljava/util/Iterator;)V
      70: areturn

  public jakarta.servlet.http.HttpServletMapping getHttpServletMapping();
    Code:
       0: aload_0
       1: getfield      #6                  // Field exchange:Lio/undertow/server/HttpServerExchange;
       4: getstatic     #58                 // Field io/undertow/servlet/handlers/ServletRequestContext.ATTACHMENT_KEY:Lio/undertow/util/AttachmentKey;
       7: invokevirtual #59                 // Method io/undertow/server/HttpServerExchange.getAttachment:(Lio/undertow/util/AttachmentKey;)Ljava/lang/Object;
      10: checkcast     #60                 // class io/undertow/servlet/handlers/ServletRequestContext
      13: astore_1
      14: aload_1
      15: invokevirtual #61                 // Method io/undertow/servlet/handlers/ServletRequestContext.getOriginalServletPathMatch:()Lio/undertow/servlet/handlers/ServletPathMatch;
      18: astore_2
      19: aload_0
      20: invokevirtual #62                 // Method getDispatcherType:()Ljakarta/servlet/DispatcherType;
      23: astore_3
      24: aload_3
      25: getstatic     #63                 // Field jakarta/servlet/DispatcherType.FORWARD:Ljakarta/servlet/DispatcherType;
      28: if_acmpeq     52
      31: aload_3
      32: getstatic     #64                 // Field jakarta/servlet/DispatcherType.ERROR:Ljakarta/servlet/DispatcherType;
      35: if_acmpeq     52
      38: aload_3
      39: getstatic     #65                 // Field jakarta/servlet/DispatcherType.ASYNC:Ljakarta/servlet/DispatcherType;
      42: if_acmpeq     52
      45: aload_3
      46: getstatic     #66                 // Field jakarta/servlet/DispatcherType.REQUEST:Ljakarta/servlet/DispatcherType;
      49: if_acmpne     57
      52: aload_1
      53: invokevirtual #67                 // Method io/undertow/servlet/handlers/ServletRequestContext.getServletPathMatch:()Lio/undertow/servlet/handlers/ServletPathMatch;
      56: astore_2
      57: aload_2
      58: ifnull        276
      61: getstatic     #68                 // Field io/undertow/servlet/spec/HttpServletRequestImpl$1.$SwitchMap$jakarta$servlet$http$MappingMatch:[I
      64: aload_2
      65: invokevirtual #69                 // Method io/undertow/servlet/handlers/ServletPathMatch.getMappingMatch:()Ljakarta/servlet/http/MappingMatch;
      68: invokevirtual #70                 // Method jakarta/servlet/http/MappingMatch.ordinal:()I
      71: iaload
      72: tableswitch   { // 1 to 5
                     1: 108
                     2: 135
                     3: 135
                     4: 142
                     5: 181
               default: 239
          }
     108: aload_2
     109: invokevirtual #71                 // Method io/undertow/servlet/handlers/ServletPathMatch.getMatched:()Ljava/lang/String;
     112: astore        4
     114: aload         4
     116: ldc           #72                 // String /
     118: invokevirtual #73                 // Method java/lang/String.startsWith:(Ljava/lang/String;)Z
     121: ifeq          245
     124: aload         4
     126: iconst_1
     127: invokevirtual #74                 // Method java/lang/String.substring:(I)Ljava/lang/String;
     130: astore        4
     132: goto          245
     135: ldc           #75                 // String
     137: astore        4
     139: goto          245
     142: aload_2
     143: invokevirtual #76                 // Method io/undertow/servlet/handlers/ServletPathMatch.getRemaining:()Ljava/lang/String;
     146: astore        4
     148: aload         4
     150: ifnonnull     160
     153: ldc           #75                 // String
     155: astore        4
     157: goto          245
     160: aload         4
     162: ldc           #72                 // String /
     164: invokevirtual #73                 // Method java/lang/String.startsWith:(Ljava/lang/String;)Z
     167: ifeq          245
     170: aload         4
     172: iconst_1
     173: invokevirtual #74                 // Method java/lang/String.substring:(I)Ljava/lang/String;
     176: astore        4
     178: goto          245
     181: aload_2
     182: invokevirtual #71                 // Method io/undertow/servlet/handlers/ServletPathMatch.getMatched:()Ljava/lang/String;
     185: astore        5
     187: aload_2
     188: invokevirtual #77                 // Method io/undertow/servlet/handlers/ServletPathMatch.getMatchString:()Ljava/lang/String;
     191: astore        6
     193: aload         5
     195: ldc           #72                 // String /
     197: invokevirtual #73                 // Method java/lang/String.startsWith:(Ljava/lang/String;)Z
     200: ifeq          207
     203: iconst_1
     204: goto          208
     207: iconst_0
     208: istore        7
     210: aload         5
     212: invokevirtual #78                 // Method java/lang/String.length:()I
     215: aload         6
     217: invokevirtual #78                 // Method java/lang/String.length:()I
     220: isub
     221: iconst_1
     222: iadd
     223: istore        8
     225: aload         5
     227: iload         7
     229: iload         8
     231: invokevirtual #79                 // Method java/lang/String.substring:(II)Ljava/lang/String;
     234: astore        4
     236: goto          245
     239: aload_2
     240: invokevirtual #76                 // Method io/undertow/servlet/handlers/ServletPathMatch.getRemaining:()Ljava/lang/String;
     243: astore        4
     245: new           #80                 // class io/undertow/servlet/spec/MappingImpl
     248: dup
     249: aload         4
     251: aload_2
     252: invokevirtual #77                 // Method io/undertow/servlet/handlers/ServletPathMatch.getMatchString:()Ljava/lang/String;
     255: aload_2
     256: invokevirtual #69                 // Method io/undertow/servlet/handlers/ServletPathMatch.getMappingMatch:()Ljakarta/servlet/http/MappingMatch;
     259: aload_2
     260: invokevirtual #81                 // Method io/undertow/servlet/handlers/ServletPathMatch.getServletChain:()Lio/undertow/servlet/handlers/ServletChain;
     263: invokevirtual #82                 // Method io/undertow/servlet/handlers/ServletChain.getManagedServlet:()Lio/undertow/servlet/core/ManagedServlet;
     266: invokevirtual #83                 // Method io/undertow/servlet/core/ManagedServlet.getServletInfo:()Lio/undertow/servlet/api/ServletInfo;
     269: invokevirtual #84                 // Method io/undertow/servlet/api/ServletInfo.getName:()Ljava/lang/String;
     272: invokespecial #85                 // Method io/undertow/servlet/spec/MappingImpl."<init>":(Ljava/lang/String;Ljava/lang/String;Ljakarta/servlet/http/MappingMatch;Ljava/lang/String;)V
     275: areturn
     276: aconst_null
     277: areturn

  public int getIntHeader(java.lang.String);
    Code:
       0: aload_0
       1: aload_1
       2: invokevirtual #86                 // Method getHeader:(Ljava/lang/String;)Ljava/lang/String;
       5: astore_2
       6: aload_2
       7: ifnonnull     12
      10: iconst_m1
      11: ireturn
      12: aload_2
      13: invokestatic  #87                 // Method java/lang/Integer.parseInt:(Ljava/lang/String;)I
      16: ireturn

  public java.lang.String getMethod();
    Code:
       0: aload_0
       1: getfield      #6                  // Field exchange:Lio/undertow/server/HttpServerExchange;
       4: invokevirtual #88                 // Method io/undertow/server/HttpServerExchange.getRequestMethod:()Lio/undertow/util/HttpString;
       7: invokevirtual #55                 // Method io/undertow/util/HttpString.toString:()Ljava/lang/String;
      10: areturn

  public java.lang.String getPathInfo();
    Code:
       0: aload_0
       1: getfield      #6                  // Field exchange:Lio/undertow/server/HttpServerExchange;
       4: getstatic     #58                 // Field io/undertow/servlet/handlers/ServletRequestContext.ATTACHMENT_KEY:Lio/undertow/util/AttachmentKey;
       7: invokevirtual #59                 // Method io/undertow/server/HttpServerExchange.getAttachment:(Lio/undertow/util/AttachmentKey;)Ljava/lang/Object;
      10: checkcast     #60                 // class io/undertow/servlet/handlers/ServletRequestContext
      13: invokevirtual #67                 // Method io/undertow/servlet/handlers/ServletRequestContext.getServletPathMatch:()Lio/undertow/servlet/handlers/ServletPathMatch;
      16: astore_1
      17: aload_1
      18: ifnull        26
      21: aload_1
      22: invokevirtual #76                 // Method io/undertow/servlet/handlers/ServletPathMatch.getRemaining:()Ljava/lang/String;
      25: areturn
      26: aconst_null
      27: areturn

  public java.lang.String getPathTranslated();
    Code:
       0: aload_0
       1: getfield      #7                  // Field servletContext:Lio/undertow/servlet/spec/ServletContextImpl;
       4: aload_0
       5: invokevirtual #89                 // Method getPathInfo:()Ljava/lang/String;
       8: invokevirtual #90                 // Method io/undertow/servlet/spec/ServletContextImpl.getRealPath:(Ljava/lang/String;)Ljava/lang/String;
      11: areturn

  public java.lang.String getContextPath();
    Code:
       0: aload_0
       1: getfield      #7                  // Field servletContext:Lio/undertow/servlet/spec/ServletContextImpl;
       4: invokevirtual #91                 // Method io/undertow/servlet/spec/ServletContextImpl.getContextPath:()Ljava/lang/String;
       7: areturn

  public java.lang.String getQueryString();
    Code:
       0: aload_0
       1: getfield      #6                  // Field exchange:Lio/undertow/server/HttpServerExchange;
       4: invokevirtual #92                 // Method io/undertow/server/HttpServerExchange.getQueryString:()Ljava/lang/String;
       7: invokevirtual #93                 // Method java/lang/String.isEmpty:()Z
      10: ifeq          17
      13: aconst_null
      14: goto          24
      17: aload_0
      18: getfield      #6                  // Field exchange:Lio/undertow/server/HttpServerExchange;
      21: invokevirtual #92                 // Method io/undertow/server/HttpServerExchange.getQueryString:()Ljava/lang/String;
      24: areturn

  public java.lang.String getRemoteUser();
    Code:
       0: aload_0
       1: invokevirtual #94                 // Method getUserPrincipal:()Ljava/security/Principal;
       4: astore_1
       5: aload_1
       6: ifnull        18
       9: aload_1
      10: invokeinterface #95,  1           // InterfaceMethod java/security/Principal.getName:()Ljava/lang/String;
      15: goto          19
      18: aconst_null
      19: areturn

  public boolean isUserInRole(java.lang.String);
    Code:
       0: aload_1
       1: ifnonnull     6
       4: iconst_0
       5: ireturn
       6: aload_1
       7: ldc           #96                 // String *
       9: invokevirtual #97                 // Method java/lang/String.equals:(Ljava/lang/Object;)Z
      12: ifeq          17
      15: iconst_0
      16: ireturn
      17: aload_0
      18: getfield      #6                  // Field exchange:Lio/undertow/server/HttpServerExchange;
      21: invokevirtual #9                  // Method io/undertow/server/HttpServerExchange.getSecurityContext:()Lio/undertow/security/api/SecurityContext;
      24: astore_2
      25: aload_2
      26: ifnull        38
      29: aload_2
      30: invokeinterface #98,  1           // InterfaceMethod io/undertow/security/api/SecurityContext.getAuthenticatedAccount:()Lio/undertow/security/idm/Account;
      35: goto          39
      38: aconst_null
      39: astore_3
      40: aload_3
      41: ifnonnull     46
      44: iconst_0
      45: ireturn
      46: aload_0
      47: getfield      #6                  // Field exchange:Lio/undertow/server/HttpServerExchange;
      50: getstatic     #58                 // Field io/undertow/servlet/handlers/ServletRequestContext.ATTACHMENT_KEY:Lio/undertow/util/AttachmentKey;
      53: invokevirtual #59                 // Method io/undertow/server/HttpServerExchange.getAttachment:(Lio/undertow/util/AttachmentKey;)Ljava/lang/Object;
      56: checkcast     #60                 // class io/undertow/servlet/handlers/ServletRequestContext
      59: astore        4
      61: aload_1
      62: ldc           #99                 // String **
      64: invokevirtual #97                 // Method java/lang/String.equals:(Ljava/lang/Object;)Z
      67: ifeq          99
      70: aload         4
      72: invokevirtual #100                // Method io/undertow/servlet/handlers/ServletRequestContext.getDeployment:()Lio/undertow/servlet/api/Deployment;
      75: invokeinterface #101,  1          // InterfaceMethod io/undertow/servlet/api/Deployment.getDeploymentInfo:()Lio/undertow/servlet/api/DeploymentInfo;
      80: invokevirtual #102                // Method io/undertow/servlet/api/DeploymentInfo.getSecurityRoles:()Ljava/util/Set;
      83: astore        5
      85: aload         5
      87: ldc           #99                 // String **
      89: invokeinterface #103,  2          // InterfaceMethod java/util/Set.contains:(Ljava/lang/Object;)Z
      94: ifne          99
      97: iconst_1
      98: ireturn
      99: aload         4
     101: invokevirtual #104                // Method io/undertow/servlet/handlers/ServletRequestContext.getCurrentServlet:()Lio/undertow/servlet/handlers/ServletChain;
     104: astore        5
     106: aload_0
     107: getfield      #7                  // Field servletContext:Lio/undertow/servlet/spec/ServletContextImpl;
     110: invokevirtual #105                // Method io/undertow/servlet/spec/ServletContextImpl.getDeployment:()Lio/undertow/servlet/api/Deployment;
     113: astore        6
     115: aload         6
     117: invokeinterface #101,  1          // InterfaceMethod io/undertow/servlet/api/Deployment.getDeploymentInfo:()Lio/undertow/servlet/api/DeploymentInfo;
     122: invokevirtual #106                // Method io/undertow/servlet/api/DeploymentInfo.getAuthorizationManager:()Lio/undertow/servlet/api/AuthorizationManager;
     125: astore        7
     127: aload         7
     129: aload_1
     130: aload_3
     131: aload         5
     133: invokevirtual #82                 // Method io/undertow/servlet/handlers/ServletChain.getManagedServlet:()Lio/undertow/servlet/core/ManagedServlet;
     136: invokevirtual #83                 // Method io/undertow/servlet/core/ManagedServlet.getServletInfo:()Lio/undertow/servlet/api/ServletInfo;
     139: aload_0
     140: aload         6
     142: invokeinterface #107,  6          // InterfaceMethod io/undertow/servlet/api/AuthorizationManager.isUserInRole:(Ljava/lang/String;Lio/undertow/security/idm/Account;Lio/undertow/servlet/api/ServletInfo;Ljakarta/servlet/http/HttpServletRequest;Lio/undertow/servlet/api/Deployment;)Z
     147: ireturn

  public java.security.Principal getUserPrincipal();
    Code:
       0: aload_0
       1: getfield      #6                  // Field exchange:Lio/undertow/server/HttpServerExchange;
       4: invokevirtual #9                  // Method io/undertow/server/HttpServerExchange.getSecurityContext:()Lio/undertow/security/api/SecurityContext;
       7: astore_1
       8: aconst_null
       9: astore_2
      10: aconst_null
      11: astore_3
      12: aload_1
      13: ifnull        34
      16: aload_1
      17: invokeinterface #98,  1           // InterfaceMethod io/undertow/security/api/SecurityContext.getAuthenticatedAccount:()Lio/undertow/security/idm/Account;
      22: dup
      23: astore_3
      24: ifnull        34
      27: aload_3
      28: invokeinterface #108,  1          // InterfaceMethod io/undertow/security/idm/Account.getPrincipal:()Ljava/security/Principal;
      33: astore_2
      34: aload_2
      35: areturn

  public java.lang.String getRequestedSessionId();
    Code:
       0: aload_0
       1: getfield      #6                  // Field exchange:Lio/undertow/server/HttpServerExchange;
       4: getstatic     #109                // Field REQUESTED_SESSION_ID_SET:Lio/undertow/util/AttachmentKey;
       7: invokevirtual #59                 // Method io/undertow/server/HttpServerExchange.getAttachment:(Lio/undertow/util/AttachmentKey;)Ljava/lang/Object;
      10: checkcast     #110                // class java/lang/Boolean
      13: astore_1
      14: aload_1
      15: ifnull        39
      18: aload_1
      19: invokevirtual #111                // Method java/lang/Boolean.booleanValue:()Z
      22: ifeq          39
      25: aload_0
      26: getfield      #6                  // Field exchange:Lio/undertow/server/HttpServerExchange;
      29: getstatic     #112                // Field REQUESTED_SESSION_ID:Lio/undertow/util/AttachmentKey;
      32: invokevirtual #59                 // Method io/undertow/server/HttpServerExchange.getAttachment:(Lio/undertow/util/AttachmentKey;)Ljava/lang/Object;
      35: checkcast     #113                // class java/lang/String
      38: areturn
      39: aload_0
      40: getfield      #8                  // Field originalServletContext:Lio/undertow/servlet/spec/ServletContextImpl;
      43: invokevirtual #114                // Method io/undertow/servlet/spec/ServletContextImpl.getSessionConfig:()Lio/undertow/server/session/SessionConfig;
      46: astore_2
      47: aload_2
      48: instanceof    #115                // class io/undertow/servlet/spec/ServletContextImpl$ServletContextSessionConfig
      51: ifeq          71
      54: aload_2
      55: checkcast     #115                // class io/undertow/servlet/spec/ServletContextImpl$ServletContextSessionConfig
      58: invokevirtual #116                // Method io/undertow/servlet/spec/ServletContextImpl$ServletContextSessionConfig.getDelegate:()Lio/undertow/server/session/SessionConfig;
      61: aload_0
      62: getfield      #6                  // Field exchange:Lio/undertow/server/HttpServerExchange;
      65: invokeinterface #117,  2          // InterfaceMethod io/undertow/server/session/SessionConfig.findSessionId:(Lio/undertow/server/HttpServerExchange;)Ljava/lang/String;
      70: areturn
      71: aload_2
      72: aload_0
      73: getfield      #6                  // Field exchange:Lio/undertow/server/HttpServerExchange;
      76: invokeinterface #117,  2          // InterfaceMethod io/undertow/server/session/SessionConfig.findSessionId:(Lio/undertow/server/HttpServerExchange;)Ljava/lang/String;
      81: areturn

  public java.lang.String changeSessionId();
    Code:
       0: aload_0
       1: getfield      #7                  // Field servletContext:Lio/undertow/servlet/spec/ServletContextImpl;
       4: aload_0
       5: getfield      #8                  // Field originalServletContext:Lio/undertow/servlet/spec/ServletContextImpl;
       8: aload_0
       9: getfield      #6                  // Field exchange:Lio/undertow/server/HttpServerExchange;
      12: iconst_0
      13: invokevirtual #118                // Method io/undertow/servlet/spec/ServletContextImpl.getSession:(Lio/undertow/servlet/spec/ServletContextImpl;Lio/undertow/server/HttpServerExchange;Z)Lio/undertow/servlet/spec/HttpSessionImpl;
      16: astore_1
      17: aload_1
      18: ifnonnull     30
      21: getstatic     #41                 // Field io/undertow/servlet/UndertowServletMessages.MESSAGES:Lio/undertow/servlet/UndertowServletMessages;
      24: invokeinterface #119,  1          // InterfaceMethod io/undertow/servlet/UndertowServletMessages.noSession:()Ljava/lang/IllegalStateException;
      29: athrow
      30: aload_0
      31: getfield      #6                  // Field exchange:Lio/undertow/server/HttpServerExchange;
      34: getstatic     #58                 // Field io/undertow/servlet/handlers/ServletRequestContext.ATTACHMENT_KEY:Lio/undertow/util/AttachmentKey;
      37: invokevirtual #59                 // Method io/undertow/server/HttpServerExchange.getAttachment:(Lio/undertow/util/AttachmentKey;)Ljava/lang/Object;
      40: checkcast     #60                 // class io/undertow/servlet/handlers/ServletRequestContext
      43: invokevirtual #120                // Method io/undertow/servlet/handlers/ServletRequestContext.getServletResponse:()Ljakarta/servlet/ServletResponse;
      46: invokeinterface #121,  1          // InterfaceMethod jakarta/servlet/ServletResponse.isCommitted:()Z
      51: ifeq          91
      54: aload_0
      55: getfield      #7                  // Field servletContext:Lio/undertow/servlet/spec/ServletContextImpl;
      58: invokevirtual #105                // Method io/undertow/servlet/spec/ServletContextImpl.getDeployment:()Lio/undertow/servlet/api/Deployment;
      61: invokeinterface #101,  1          // InterfaceMethod io/undertow/servlet/api/Deployment.getDeploymentInfo:()Lio/undertow/servlet/api/DeploymentInfo;
      66: invokevirtual #122                // Method io/undertow/servlet/api/DeploymentInfo.isOrphanSessionAllowed:()Z
      69: ifne          81
      72: getstatic     #41                 // Field io/undertow/servlet/UndertowServletMessages.MESSAGES:Lio/undertow/servlet/UndertowServletMessages;
      75: invokeinterface #123,  1          // InterfaceMethod io/undertow/servlet/UndertowServletMessages.sessionIdChangeAfterResponseCommittedNotAllowed:()Ljava/lang/IllegalStateException;
      80: athrow
      81: getstatic     #124                // Field io/undertow/servlet/UndertowServletLogger.REQUEST_LOGGER:Lio/undertow/servlet/UndertowServletLogger;
      84: ldc           #125                // String Servlet container configured to permit session identifier changes after response was committed. This can result in a memory leak if session has no timeout.
      86: invokeinterface #126,  2          // InterfaceMethod io/undertow/servlet/UndertowServletLogger.debug:(Ljava/lang/Object;)V
      91: aload_1
      92: invokevirtual #127                // Method io/undertow/servlet/spec/HttpSessionImpl.getId:()Ljava/lang/String;
      95: astore_2
      96: invokestatic  #128                // Method java/lang/System.getSecurityManager:()Ljava/lang/SecurityManager;
      99: ifnonnull     110
     102: aload_1
     103: invokevirtual #129                // Method io/undertow/servlet/spec/HttpSessionImpl.getSession:()Lio/undertow/server/session/Session;
     106: astore_3
     107: goto          125
     110: new           #130                // class io/undertow/servlet/spec/HttpSessionImpl$UnwrapSessionAction
     113: dup
     114: aload_1
     115: invokespecial #131                // Method io/undertow/servlet/spec/HttpSessionImpl$UnwrapSessionAction."<init>":(Ljakarta/servlet/http/HttpSession;)V
     118: invokestatic  #132                // Method java/security/AccessController.doPrivileged:(Ljava/security/PrivilegedAction;)Ljava/lang/Object;
     121: checkcast     #133                // class io/undertow/server/session/Session
     124: astore_3
     125: aload_3
     126: aload_0
     127: getfield      #6                  // Field exchange:Lio/undertow/server/HttpServerExchange;
     130: aload_0
     131: getfield      #8                  // Field originalServletContext:Lio/undertow/servlet/spec/ServletContextImpl;
     134: invokevirtual #114                // Method io/undertow/servlet/spec/ServletContextImpl.getSessionConfig:()Lio/undertow/server/session/SessionConfig;
     137: invokeinterface #134,  3          // InterfaceMethod io/undertow/server/session/Session.changeSessionId:(Lio/undertow/server/HttpServerExchange;Lio/undertow/server/session/SessionConfig;)Ljava/lang/String;
     142: astore        4
     144: aload_0
     145: getfield      #7                  // Field servletContext:Lio/undertow/servlet/spec/ServletContextImpl;
     148: invokevirtual #105                // Method io/undertow/servlet/spec/ServletContextImpl.getDeployment:()Lio/undertow/servlet/api/Deployment;
     151: invokeinterface #135,  1          // InterfaceMethod io/undertow/servlet/api/Deployment.getApplicationListeners:()Lio/undertow/servlet/core/ApplicationListeners;
     156: aload_1
     157: aload_2
     158: invokevirtual #136                // Method io/undertow/servlet/core/ApplicationListeners.httpSessionIdChanged:(Ljakarta/servlet/http/HttpSession;Ljava/lang/String;)V
     161: aload         4
     163: areturn

  public java.lang.String getRequestId();
    Code:
       0: aload_0
       1: getfield      #6                  // Field exchange:Lio/undertow/server/HttpServerExchange;
       4: invokevirtual #137                // Method io/undertow/server/HttpServerExchange.getRequestId:()Ljava/lang/String;
       7: areturn

  public java.lang.String getProtocolRequestId();
    Code:
       0: aload_0
       1: getfield      #6                  // Field exchange:Lio/undertow/server/HttpServerExchange;
       4: invokevirtual #138                // Method io/undertow/server/HttpServerExchange.getConnection:()Lio/undertow/server/ServerConnection;
       7: invokevirtual #139                // Method io/undertow/server/ServerConnection.getProtocolRequestId:()Ljava/lang/String;
      10: areturn

  public jakarta.servlet.ServletConnection getServletConnection();
    Code:
       0: aload_0
       1: getfield      #6                  // Field exchange:Lio/undertow/server/HttpServerExchange;
       4: invokevirtual #138                // Method io/undertow/server/HttpServerExchange.getConnection:()Lio/undertow/server/ServerConnection;
       7: invokevirtual #140                // Method io/undertow/server/ServerConnection.getId:()J
      10: invokestatic  #141                // Method java/lang/Long.toString:(J)Ljava/lang/String;
      13: astore_1
      14: new           #142                // class io/undertow/servlet/spec/ServletConnectionImpl
      17: dup
      18: aload_1
      19: aload_0
      20: getfield      #6                  // Field exchange:Lio/undertow/server/HttpServerExchange;
      23: invokevirtual #143                // Method io/undertow/server/HttpServerExchange.getProtocol:()Lio/undertow/util/HttpString;
      26: invokevirtual #55                 // Method io/undertow/util/HttpString.toString:()Ljava/lang/String;
      29: aload_0
      30: invokevirtual #144                // Method isSecure:()Z
      33: invokespecial #145                // Method io/undertow/servlet/spec/ServletConnectionImpl."<init>":(Ljava/lang/String;Ljava/lang/String;Z)V
      36: areturn

  public java.lang.String getRequestURI();
    Code:
       0: aload_0
       1: getfield      #6                  // Field exchange:Lio/undertow/server/HttpServerExchange;
       4: invokevirtual #146                // Method io/undertow/server/HttpServerExchange.isHostIncludedInRequestURI:()Z
       7: ifeq          63
      10: aload_0
      11: getfield      #6                  // Field exchange:Lio/undertow/server/HttpServerExchange;
      14: invokevirtual #147                // Method io/undertow/server/HttpServerExchange.getRequestURI:()Ljava/lang/String;
      17: astore_1
      18: iconst_0
      19: istore_2
      20: iconst_0
      21: istore_3
      22: iload_3
      23: aload_1
      24: invokevirtual #78                 // Method java/lang/String.length:()I
      27: if_icmpge     60
      30: aload_1
      31: iload_3
      32: invokevirtual #148                // Method java/lang/String.charAt:(I)C
      35: bipush        47
      37: if_icmpne     54
      40: iinc          2, 1
      43: iload_2
      44: iconst_3
      45: if_icmpne     54
      48: aload_1
      49: iload_3
      50: invokevirtual #74                 // Method java/lang/String.substring:(I)Ljava/lang/String;
      53: areturn
      54: iinc          3, 1
      57: goto          22
      60: ldc           #72                 // String /
      62: areturn
      63: aload_0
      64: getfield      #6                  // Field exchange:Lio/undertow/server/HttpServerExchange;
      67: invokevirtual #147                // Method io/undertow/server/HttpServerExchange.getRequestURI:()Ljava/lang/String;
      70: areturn

  public java.lang.StringBuffer getRequestURL();
    Code:
       0: new           #149                // class java/lang/StringBuffer
       3: dup
       4: aload_0
       5: getfield      #6                  // Field exchange:Lio/undertow/server/HttpServerExchange;
       8: invokevirtual #150                // Method io/undertow/server/HttpServerExchange.getRequestURL:()Ljava/lang/String;
      11: invokespecial #151                // Method java/lang/StringBuffer."<init>":(Ljava/lang/String;)V
      14: areturn

  public java.lang.String getServletPath();
    Code:
       0: aload_0
       1: getfield      #6                  // Field exchange:Lio/undertow/server/HttpServerExchange;
       4: getstatic     #58                 // Field io/undertow/servlet/handlers/ServletRequestContext.ATTACHMENT_KEY:Lio/undertow/util/AttachmentKey;
       7: invokevirtual #59                 // Method io/undertow/server/HttpServerExchange.getAttachment:(Lio/undertow/util/AttachmentKey;)Ljava/lang/Object;
      10: checkcast     #60                 // class io/undertow/servlet/handlers/ServletRequestContext
      13: invokevirtual #67                 // Method io/undertow/servlet/handlers/ServletRequestContext.getServletPathMatch:()Lio/undertow/servlet/handlers/ServletPathMatch;
      16: astore_1
      17: aload_1
      18: ifnull        26
      21: aload_1
      22: invokevirtual #71                 // Method io/undertow/servlet/handlers/ServletPathMatch.getMatched:()Ljava/lang/String;
      25: areturn
      26: ldc           #75                 // String
      28: areturn

  public jakarta.servlet.http.HttpSession getSession(boolean);
    Code:
       0: aload_0
       1: getfield      #7                  // Field servletContext:Lio/undertow/servlet/spec/ServletContextImpl;
       4: aload_0
       5: getfield      #8                  // Field originalServletContext:Lio/undertow/servlet/spec/ServletContextImpl;
       8: aload_0
       9: getfield      #6                  // Field exchange:Lio/undertow/server/HttpServerExchange;
      12: iload_1
      13: invokevirtual #118                // Method io/undertow/servlet/spec/ServletContextImpl.getSession:(Lio/undertow/servlet/spec/ServletContextImpl;Lio/undertow/server/HttpServerExchange;Z)Lio/undertow/servlet/spec/HttpSessionImpl;
      16: areturn

  public jakarta.servlet.http.HttpSession getSession();
    Code:
       0: aload_0
       1: iconst_1
       2: invokevirtual #152                // Method getSession:(Z)Ljakarta/servlet/http/HttpSession;
       5: areturn

  public boolean isRequestedSessionIdValid();
    Code:
       0: aload_0
       1: getfield      #7                  // Field servletContext:Lio/undertow/servlet/spec/ServletContextImpl;
       4: aload_0
       5: getfield      #8                  // Field originalServletContext:Lio/undertow/servlet/spec/ServletContextImpl;
       8: aload_0
       9: getfield      #6                  // Field exchange:Lio/undertow/server/HttpServerExchange;
      12: iconst_0
      13: invokevirtual #118                // Method io/undertow/servlet/spec/ServletContextImpl.getSession:(Lio/undertow/servlet/spec/ServletContextImpl;Lio/undertow/server/HttpServerExchange;Z)Lio/undertow/servlet/spec/HttpSessionImpl;
      16: astore_1
      17: aload_1
      18: ifnonnull     23
      21: iconst_0
      22: ireturn
      23: aload_1
      24: invokevirtual #153                // Method io/undertow/servlet/spec/HttpSessionImpl.isInvalid:()Z
      27: ifeq          32
      30: iconst_0
      31: ireturn
      32: aload_1
      33: invokevirtual #127                // Method io/undertow/servlet/spec/HttpSessionImpl.getId:()Ljava/lang/String;
      36: aload_0
      37: invokevirtual #154                // Method getRequestedSessionId:()Ljava/lang/String;
      40: invokevirtual #97                 // Method java/lang/String.equals:(Ljava/lang/Object;)Z
      43: ireturn

  public boolean isRequestedSessionIdFromCookie();
    Code:
       0: aload_0
       1: invokevirtual #155                // Method sessionCookieSource:()Lio/undertow/server/session/SessionConfig$SessionCookieSource;
       4: getstatic     #156                // Field io/undertow/server/session/SessionConfig$SessionCookieSource.COOKIE:Lio/undertow/server/session/SessionConfig$SessionCookieSource;
       7: if_acmpne     14
      10: iconst_1
      11: goto          15
      14: iconst_0
      15: ireturn

  public boolean isRequestedSessionIdFromURL();
    Code:
       0: aload_0
       1: invokevirtual #155                // Method sessionCookieSource:()Lio/undertow/server/session/SessionConfig$SessionCookieSource;
       4: getstatic     #157                // Field io/undertow/server/session/SessionConfig$SessionCookieSource.URL:Lio/undertow/server/session/SessionConfig$SessionCookieSource;
       7: if_acmpne     14
      10: iconst_1
      11: goto          15
      14: iconst_0
      15: ireturn

  public boolean authenticate(jakarta.servlet.http.HttpServletResponse) throws java.io.IOException, jakarta.servlet.ServletException;
    Code:
       0: aload_1
       1: invokeinterface #158,  1          // InterfaceMethod jakarta/servlet/http/HttpServletResponse.isCommitted:()Z
       6: ifeq          18
       9: getstatic     #41                 // Field io/undertow/servlet/UndertowServletMessages.MESSAGES:Lio/undertow/servlet/UndertowServletMessages;
      12: invokeinterface #159,  1          // InterfaceMethod io/undertow/servlet/UndertowServletMessages.responseAlreadyCommited:()Ljava/lang/IllegalStateException;
      17: athrow
      18: aload_0
      19: getfield      #6                  // Field exchange:Lio/undertow/server/HttpServerExchange;
      22: invokevirtual #9                  // Method io/undertow/server/HttpServerExchange.getSecurityContext:()Lio/undertow/security/api/SecurityContext;
      25: astore_2
      26: aload_2
      27: ifnonnull     39
      30: getstatic     #41                 // Field io/undertow/servlet/UndertowServletMessages.MESSAGES:Lio/undertow/servlet/UndertowServletMessages;
      33: invokeinterface #160,  1          // InterfaceMethod io/undertow/servlet/UndertowServletMessages.noSecurityContextAvailable:()Ljakarta/servlet/ServletException;
      38: athrow
      39: aload_2
      40: invokeinterface #161,  1          // InterfaceMethod io/undertow/security/api/SecurityContext.setAuthenticationRequired:()V
      45: aload_2
      46: invokeinterface #162,  1          // InterfaceMethod io/undertow/security/api/SecurityContext.authenticate:()Z
      51: ifeq          74
      54: aload_2
      55: invokeinterface #163,  1          // InterfaceMethod io/undertow/security/api/SecurityContext.isAuthenticated:()Z
      60: ifeq          65
      63: iconst_1
      64: ireturn
      65: getstatic     #41                 // Field io/undertow/servlet/UndertowServletMessages.MESSAGES:Lio/undertow/servlet/UndertowServletMessages;
      68: invokeinterface #164,  1          // InterfaceMethod io/undertow/servlet/UndertowServletMessages.authenticationFailed:()Ljakarta/servlet/ServletException;
      73: athrow
      74: aload_0
      75: getfield      #6                  // Field exchange:Lio/undertow/server/HttpServerExchange;
      78: invokevirtual #165                // Method io/undertow/server/HttpServerExchange.isResponseStarted:()Z
      81: ifne          106
      84: aload_0
      85: getfield      #6                  // Field exchange:Lio/undertow/server/HttpServerExchange;
      88: invokevirtual #166                // Method io/undertow/server/HttpServerExchange.getStatusCode:()I
      91: sipush        200
      94: if_icmpne     106
      97: getstatic     #41                 // Field io/undertow/servlet/UndertowServletMessages.MESSAGES:Lio/undertow/servlet/UndertowServletMessages;
     100: invokeinterface #164,  1          // InterfaceMethod io/undertow/servlet/UndertowServletMessages.authenticationFailed:()Ljakarta/servlet/ServletException;
     105: athrow
     106: iconst_0
     107: ireturn

  public void login(java.lang.String, java.lang.String) throws jakarta.servlet.ServletException;
    Code:
       0: aload_1
       1: ifnull        8
       4: aload_2
       5: ifnonnull     17
       8: getstatic     #41                 // Field io/undertow/servlet/UndertowServletMessages.MESSAGES:Lio/undertow/servlet/UndertowServletMessages;
      11: invokeinterface #167,  1          // InterfaceMethod io/undertow/servlet/UndertowServletMessages.loginFailed:()Ljakarta/servlet/ServletException;
      16: athrow
      17: aload_0
      18: getfield      #6                  // Field exchange:Lio/undertow/server/HttpServerExchange;
      21: invokevirtual #9                  // Method io/undertow/server/HttpServerExchange.getSecurityContext:()Lio/undertow/security/api/SecurityContext;
      24: astore_3
      25: aload_3
      26: ifnonnull     38
      29: getstatic     #41                 // Field io/undertow/servlet/UndertowServletMessages.MESSAGES:Lio/undertow/servlet/UndertowServletMessages;
      32: invokeinterface #160,  1          // InterfaceMethod io/undertow/servlet/UndertowServletMessages.noSecurityContextAvailable:()Ljakarta/servlet/ServletException;
      37: athrow
      38: aload_3
      39: invokeinterface #163,  1          // InterfaceMethod io/undertow/security/api/SecurityContext.isAuthenticated:()Z
      44: ifeq          56
      47: getstatic     #41                 // Field io/undertow/servlet/UndertowServletMessages.MESSAGES:Lio/undertow/servlet/UndertowServletMessages;
      50: invokeinterface #168,  1          // InterfaceMethod io/undertow/servlet/UndertowServletMessages.userAlreadyLoggedIn:()Ljakarta/servlet/ServletException;
      55: athrow
      56: iconst_0
      57: istore        4
      59: aload_3
      60: aload_1
      61: aload_2
      62: invokeinterface #169,  3          // InterfaceMethod io/undertow/security/api/SecurityContext.login:(Ljava/lang/String;Ljava/lang/String;)Z
      67: istore        4
      69: goto          104
      72: astore        5
      74: aload         5
      76: invokevirtual #171                // Method java/lang/SecurityException.getCause:()Ljava/lang/Throwable;
      79: instanceof    #172                // class jakarta/servlet/ServletException
      82: ifeq          94
      85: aload         5
      87: invokevirtual #171                // Method java/lang/SecurityException.getCause:()Ljava/lang/Throwable;
      90: checkcast     #172                // class jakarta/servlet/ServletException
      93: athrow
      94: new           #172                // class jakarta/servlet/ServletException
      97: dup
      98: aload         5
     100: invokespecial #173                // Method jakarta/servlet/ServletException."<init>":(Ljava/lang/Throwable;)V
     103: athrow
     104: iload         4
     106: ifne          118
     109: getstatic     #41                 // Field io/undertow/servlet/UndertowServletMessages.MESSAGES:Lio/undertow/servlet/UndertowServletMessages;
     112: invokeinterface #167,  1          // InterfaceMethod io/undertow/servlet/UndertowServletMessages.loginFailed:()Ljakarta/servlet/ServletException;
     117: athrow
     118: return
    Exception table:
       from    to  target type
          59    69    72   Class java/lang/SecurityException

  public void logout() throws jakarta.servlet.ServletException;
    Code:
       0: aload_0
       1: getfield      #6                  // Field exchange:Lio/undertow/server/HttpServerExchange;
       4: invokevirtual #9                  // Method io/undertow/server/HttpServerExchange.getSecurityContext:()Lio/undertow/security/api/SecurityContext;
       7: astore_1
       8: aload_1
       9: ifnonnull     21
      12: getstatic     #41                 // Field io/undertow/servlet/UndertowServletMessages.MESSAGES:Lio/undertow/servlet/UndertowServletMessages;
      15: invokeinterface #160,  1          // InterfaceMethod io/undertow/servlet/UndertowServletMessages.noSecurityContextAvailable:()Ljakarta/servlet/ServletException;
      20: athrow
      21: aload_1
      22: invokeinterface #174,  1          // InterfaceMethod io/undertow/security/api/SecurityContext.logout:()V
      27: aload_0
      28: getfield      #7                  // Field servletContext:Lio/undertow/servlet/spec/ServletContextImpl;
      31: invokevirtual #105                // Method io/undertow/servlet/spec/ServletContextImpl.getDeployment:()Lio/undertow/servlet/api/Deployment;
      34: invokeinterface #101,  1          // InterfaceMethod io/undertow/servlet/api/Deployment.getDeploymentInfo:()Lio/undertow/servlet/api/DeploymentInfo;
      39: invokevirtual #175                // Method io/undertow/servlet/api/DeploymentInfo.isInvalidateSessionOnLogout:()Z
      42: ifeq          61
      45: aload_0
      46: iconst_0
      47: invokevirtual #152                // Method getSession:(Z)Ljakarta/servlet/http/HttpSession;
      50: astore_2
      51: aload_2
      52: ifnull        61
      55: aload_2
      56: invokeinterface #176,  1          // InterfaceMethod jakarta/servlet/http/HttpSession.invalidate:()V
      61: return

  public java.util.Collection<jakarta.servlet.http.Part> getParts() throws java.io.IOException, jakarta.servlet.ServletException;
    Code:
       0: aload_0
       1: invokevirtual #177                // Method verifyMultipartServlet:()V
       4: aload_0
       5: getfield      #3                  // Field parts:Ljava/util/List;
       8: ifnonnull     15
      11: aload_0
      12: invokevirtual #178                // Method loadParts:()V
      15: aload_0
      16: getfield      #3                  // Field parts:Ljava/util/List;
      19: areturn

  private void verifyMultipartServlet();
    Code:
       0: aload_0
       1: getfield      #6                  // Field exchange:Lio/undertow/server/HttpServerExchange;
       4: getstatic     #58                 // Field io/undertow/servlet/handlers/ServletRequestContext.ATTACHMENT_KEY:Lio/undertow/util/AttachmentKey;
       7: invokevirtual #59                 // Method io/undertow/server/HttpServerExchange.getAttachment:(Lio/undertow/util/AttachmentKey;)Ljava/lang/Object;
      10: checkcast     #60                 // class io/undertow/servlet/handlers/ServletRequestContext
      13: astore_1
      14: aload_1
      15: invokevirtual #67                 // Method io/undertow/servlet/handlers/ServletRequestContext.getServletPathMatch:()Lio/undertow/servlet/handlers/ServletPathMatch;
      18: invokevirtual #81                 // Method io/undertow/servlet/handlers/ServletPathMatch.getServletChain:()Lio/undertow/servlet/handlers/ServletChain;
      21: invokevirtual #82                 // Method io/undertow/servlet/handlers/ServletChain.getManagedServlet:()Lio/undertow/servlet/core/ManagedServlet;
      24: invokevirtual #179                // Method io/undertow/servlet/core/ManagedServlet.getMultipartConfig:()Ljakarta/servlet/MultipartConfigElement;
      27: astore_2
      28: aload_2
      29: ifnonnull     41
      32: getstatic     #41                 // Field io/undertow/servlet/UndertowServletMessages.MESSAGES:Lio/undertow/servlet/UndertowServletMessages;
      35: invokeinterface #180,  1          // InterfaceMethod io/undertow/servlet/UndertowServletMessages.multipartConfigNotPresent:()Ljava/lang/IllegalStateException;
      40: athrow
      41: return

  public jakarta.servlet.http.Part getPart(java.lang.String) throws java.io.IOException, jakarta.servlet.ServletException;
    Code:
       0: aload_0
       1: invokevirtual #177                // Method verifyMultipartServlet:()V
       4: aload_0
       5: getfield      #3                  // Field parts:Ljava/util/List;
       8: ifnonnull     15
      11: aload_0
      12: invokevirtual #178                // Method loadParts:()V
      15: aload_0
      16: getfield      #3                  // Field parts:Ljava/util/List;
      19: invokeinterface #48,  1           // InterfaceMethod java/util/List.iterator:()Ljava/util/Iterator;
      24: astore_2
      25: aload_2
      26: invokeinterface #14,  1           // InterfaceMethod java/util/Iterator.hasNext:()Z
      31: ifeq          62
      34: aload_2
      35: invokeinterface #15,  1           // InterfaceMethod java/util/Iterator.next:()Ljava/lang/Object;
      40: checkcast     #181                // class jakarta/servlet/http/Part
      43: astore_3
      44: aload_3
      45: invokeinterface #182,  1          // InterfaceMethod jakarta/servlet/http/Part.getName:()Ljava/lang/String;
      50: aload_1
      51: invokevirtual #97                 // Method java/lang/String.equals:(Ljava/lang/Object;)Z
      54: ifeq          59
      57: aload_3
      58: areturn
      59: goto          25
      62: aconst_null
      63: areturn

  public <T extends jakarta.servlet.http.HttpUpgradeHandler> T upgrade(java.lang.Class<T>) throws java.io.IOException;
    Code:
       0: aload_0
       1: getfield      #7                  // Field servletContext:Lio/undertow/servlet/spec/ServletContextImpl;
       4: invokevirtual #105                // Method io/undertow/servlet/spec/ServletContextImpl.getDeployment:()Lio/undertow/servlet/api/Deployment;
       7: invokeinterface #101,  1          // InterfaceMethod io/undertow/servlet/api/Deployment.getDeploymentInfo:()Lio/undertow/servlet/api/DeploymentInfo;
      12: invokevirtual #183                // Method io/undertow/servlet/api/DeploymentInfo.getClassIntrospecter:()Lio/undertow/servlet/api/ClassIntrospecter;
      15: aload_1
      16: invokeinterface #184,  2          // InterfaceMethod io/undertow/servlet/api/ClassIntrospecter.createInstanceFactory:(Ljava/lang/Class;)Lio/undertow/servlet/api/InstanceFactory;
      21: astore_2
      22: aload_2
      23: invokeinterface #185,  1          // InterfaceMethod io/undertow/servlet/api/InstanceFactory.createInstance:()Lio/undertow/servlet/api/InstanceHandle;
      28: astore_3
      29: aload_0
      30: getfield      #6                  // Field exchange:Lio/undertow/server/HttpServerExchange;
      33: new           #186                // class io/undertow/servlet/core/ServletUpgradeListener
      36: dup
      37: aload_3
      38: aload_0
      39: getfield      #7                  // Field servletContext:Lio/undertow/servlet/spec/ServletContextImpl;
      42: invokevirtual #105                // Method io/undertow/servlet/spec/ServletContextImpl.getDeployment:()Lio/undertow/servlet/api/Deployment;
      45: aload_0
      46: getfield      #6                  // Field exchange:Lio/undertow/server/HttpServerExchange;
      49: invokespecial #187                // Method io/undertow/servlet/core/ServletUpgradeListener."<init>":(Lio/undertow/servlet/api/InstanceHandle;Lio/undertow/servlet/api/Deployment;Lio/undertow/server/HttpServerExchange;)V
      52: invokevirtual #188                // Method io/undertow/server/HttpServerExchange.upgradeChannel:(Lio/undertow/server/HttpUpgradeListener;)Lio/undertow/server/HttpServerExchange;
      55: pop
      56: aload_3
      57: invokeinterface #189,  1          // InterfaceMethod io/undertow/servlet/api/InstanceHandle.getInstance:()Ljava/lang/Object;
      62: checkcast     #190                // class jakarta/servlet/http/HttpUpgradeHandler
      65: areturn
      66: astore_2
      67: new           #192                // class java/lang/RuntimeException
      70: dup
      71: aload_2
      72: invokespecial #193                // Method java/lang/RuntimeException."<init>":(Ljava/lang/Throwable;)V
      75: athrow
      76: astore_2
      77: new           #192                // class java/lang/RuntimeException
      80: dup
      81: aload_2
      82: invokespecial #193                // Method java/lang/RuntimeException."<init>":(Ljava/lang/Throwable;)V
      85: athrow
    Exception table:
       from    to  target type
           0    65    66   Class java/lang/InstantiationException
           0    65    76   Class java/lang/NoSuchMethodException

  private void loadParts() throws java.io.IOException, jakarta.servlet.ServletException;
    Code:
       0: aload_0
       1: getfield      #6                  // Field exchange:Lio/undertow/server/HttpServerExchange;
       4: getstatic     #58                 // Field io/undertow/servlet/handlers/ServletRequestContext.ATTACHMENT_KEY:Lio/undertow/util/AttachmentKey;
       7: invokevirtual #59                 // Method io/undertow/server/HttpServerExchange.getAttachment:(Lio/undertow/util/AttachmentKey;)Ljava/lang/Object;
      10: checkcast     #60                 // class io/undertow/servlet/handlers/ServletRequestContext
      13: astore_1
      14: aload_0
      15: getfield      #3                  // Field parts:Ljava/util/List;
      18: ifnonnull     191
      21: new           #195                // class java/util/ArrayList
      24: dup
      25: invokespecial #196                // Method java/util/ArrayList."<init>":()V
      28: astore_2
      29: aload_0
      30: getfield      #6                  // Field exchange:Lio/undertow/server/HttpServerExchange;
      33: invokevirtual #36                 // Method io/undertow/server/HttpServerExchange.getRequestHeaders:()Lio/undertow/util/HeaderMap;
      36: getstatic     #197                // Field io/undertow/util/Headers.CONTENT_TYPE:Lio/undertow/util/HttpString;
      39: invokevirtual #44                 // Method io/undertow/util/HeaderMap.getFirst:(Lio/undertow/util/HttpString;)Ljava/lang/String;
      42: astore_3
      43: aload_3
      44: ifnull        177
      47: aload_3
      48: ldc           #199                // String multipart/form-data
      50: invokevirtual #73                 // Method java/lang/String.startsWith:(Ljava/lang/String;)Z
      53: ifeq          177
      56: aload_0
      57: invokevirtual #200                // Method parseFormData:()Lio/undertow/server/handlers/form/FormData;
      60: astore        4
      62: aload         4
      64: ifnull        174
      67: aload         4
      69: invokevirtual #201                // Method io/undertow/server/handlers/form/FormData.iterator:()Ljava/util/Iterator;
      72: astore        5
      74: aload         5
      76: invokeinterface #14,  1           // InterfaceMethod java/util/Iterator.hasNext:()Z
      81: ifeq          174
      84: aload         5
      86: invokeinterface #15,  1           // InterfaceMethod java/util/Iterator.next:()Ljava/lang/Object;
      91: checkcast     #113                // class java/lang/String
      94: astore        6
      96: aload         4
      98: aload         6
     100: invokevirtual #202                // Method io/undertow/server/handlers/form/FormData.get:(Ljava/lang/String;)Ljava/util/Deque;
     103: invokeinterface #203,  1          // InterfaceMethod java/util/Deque.iterator:()Ljava/util/Iterator;
     108: astore        7
     110: aload         7
     112: invokeinterface #14,  1           // InterfaceMethod java/util/Iterator.hasNext:()Z
     117: ifeq          171
     120: aload         7
     122: invokeinterface #15,  1           // InterfaceMethod java/util/Iterator.next:()Ljava/lang/Object;
     127: checkcast     #204                // class io/undertow/server/handlers/form/FormData$FormValue
     130: astore        8
     132: aload_2
     133: new           #205                // class io/undertow/servlet/spec/PartImpl
     136: dup
     137: aload         6
     139: aload         8
     141: aload_1
     142: invokevirtual #61                 // Method io/undertow/servlet/handlers/ServletRequestContext.getOriginalServletPathMatch:()Lio/undertow/servlet/handlers/ServletPathMatch;
     145: invokevirtual #81                 // Method io/undertow/servlet/handlers/ServletPathMatch.getServletChain:()Lio/undertow/servlet/handlers/ServletChain;
     148: invokevirtual #82                 // Method io/undertow/servlet/handlers/ServletChain.getManagedServlet:()Lio/undertow/servlet/core/ManagedServlet;
     151: invokevirtual #179                // Method io/undertow/servlet/core/ManagedServlet.getMultipartConfig:()Ljakarta/servlet/MultipartConfigElement;
     154: aload_0
     155: getfield      #7                  // Field servletContext:Lio/undertow/servlet/spec/ServletContextImpl;
     158: aload_0
     159: invokespecial #206                // Method io/undertow/servlet/spec/PartImpl."<init>":(Ljava/lang/String;Lio/undertow/server/handlers/form/FormData$FormValue;Ljakarta/servlet/MultipartConfigElement;Lio/undertow/servlet/spec/ServletContextImpl;Lio/undertow/servlet/spec/HttpServletRequestImpl;)V
     162: invokeinterface #207,  2          // InterfaceMethod java/util/List.add:(Ljava/lang/Object;)Z
     167: pop
     168: goto          110
     171: goto          74
     174: goto          186
     177: getstatic     #41                 // Field io/undertow/servlet/UndertowServletMessages.MESSAGES:Lio/undertow/servlet/UndertowServletMessages;
     180: invokeinterface #208,  1          // InterfaceMethod io/undertow/servlet/UndertowServletMessages.notAMultiPartRequest:()Ljakarta/servlet/ServletException;
     185: athrow
     186: aload_0
     187: aload_2
     188: putfield      #3                  // Field parts:Ljava/util/List;
     191: return

  public java.lang.Object getAttribute(java.lang.String);
    Code:
       0: aload_0
       1: getfield      #2                  // Field attributes:Ljava/util/Map;
       4: ifnonnull     9
       7: aconst_null
       8: areturn
       9: aload_0
      10: getfield      #2                  // Field attributes:Ljava/util/Map;
      13: aload_1
      14: invokeinterface #209,  2          // InterfaceMethod java/util/Map.get:(Ljava/lang/Object;)Ljava/lang/Object;
      19: areturn

  public java.util.Enumeration<java.lang.String> getAttributeNames();
    Code:
       0: aload_0
       1: getfield      #2                  // Field attributes:Ljava/util/Map;
       4: ifnonnull     11
       7: invokestatic  #46                 // Method io/undertow/servlet/util/EmptyEnumeration.instance:()Ljava/util/Enumeration;
      10: areturn
      11: new           #47                 // class io/undertow/servlet/util/IteratorEnumeration
      14: dup
      15: aload_0
      16: getfield      #2                  // Field attributes:Ljava/util/Map;
      19: invokeinterface #210,  1          // InterfaceMethod java/util/Map.keySet:()Ljava/util/Set;
      24: invokeinterface #57,  1           // InterfaceMethod java/util/Set.iterator:()Ljava/util/Iterator;
      29: invokespecial #49                 // Method io/undertow/servlet/util/IteratorEnumeration."<init>":(Ljava/util/Iterator;)V
      32: areturn

  public java.lang.String getCharacterEncoding();
    Code:
       0: aload_0
       1: getfield      #211                // Field characterEncoding:Ljava/nio/charset/Charset;
       4: ifnull        15
       7: aload_0
       8: getfield      #211                // Field characterEncoding:Ljava/nio/charset/Charset;
      11: invokevirtual #212                // Method java/nio/charset/Charset.name:()Ljava/lang/String;
      14: areturn
      15: aload_0
      16: invokevirtual #213                // Method getCharacterEncodingFromHeader:()Ljava/lang/String;
      19: astore_1
      20: aload_1
      21: ifnull        26
      24: aload_1
      25: areturn
      26: aload_0
      27: getfield      #7                  // Field servletContext:Lio/undertow/servlet/spec/ServletContextImpl;
      30: invokevirtual #105                // Method io/undertow/servlet/spec/ServletContextImpl.getDeployment:()Lio/undertow/servlet/api/Deployment;
      33: invokeinterface #101,  1          // InterfaceMethod io/undertow/servlet/api/Deployment.getDeploymentInfo:()Lio/undertow/servlet/api/DeploymentInfo;
      38: invokevirtual #214                // Method io/undertow/servlet/api/DeploymentInfo.getDefaultRequestEncoding:()Ljava/lang/String;
      41: ifnull        60
      44: aload_0
      45: getfield      #7                  // Field servletContext:Lio/undertow/servlet/spec/ServletContextImpl;
      48: invokevirtual #105                // Method io/undertow/servlet/spec/ServletContextImpl.getDeployment:()Lio/undertow/servlet/api/Deployment;
      51: invokeinterface #101,  1          // InterfaceMethod io/undertow/servlet/api/Deployment.getDeploymentInfo:()Lio/undertow/servlet/api/DeploymentInfo;
      56: invokevirtual #214                // Method io/undertow/servlet/api/DeploymentInfo.getDefaultRequestEncoding:()Ljava/lang/String;
      59: areturn
      60: aload_0
      61: getfield      #7                  // Field servletContext:Lio/undertow/servlet/spec/ServletContextImpl;
      64: invokevirtual #105                // Method io/undertow/servlet/spec/ServletContextImpl.getDeployment:()Lio/undertow/servlet/api/Deployment;
      67: invokeinterface #101,  1          // InterfaceMethod io/undertow/servlet/api/Deployment.getDeploymentInfo:()Lio/undertow/servlet/api/DeploymentInfo;
      72: invokevirtual #215                // Method io/undertow/servlet/api/DeploymentInfo.getDefaultEncoding:()Ljava/lang/String;
      75: ifnull        94
      78: aload_0
      79: getfield      #7                  // Field servletContext:Lio/undertow/servlet/spec/ServletContextImpl;
      82: invokevirtual #105                // Method io/undertow/servlet/spec/ServletContextImpl.getDeployment:()Lio/undertow/servlet/api/Deployment;
      85: invokeinterface #101,  1          // InterfaceMethod io/undertow/servlet/api/Deployment.getDeploymentInfo:()Lio/undertow/servlet/api/DeploymentInfo;
      90: invokevirtual #215                // Method io/undertow/servlet/api/DeploymentInfo.getDefaultEncoding:()Ljava/lang/String;
      93: areturn
      94: aconst_null
      95: areturn

  private java.lang.String getCharacterEncodingFromHeader();
    Code:
       0: aload_0
       1: getfield      #6                  // Field exchange:Lio/undertow/server/HttpServerExchange;
       4: invokevirtual #36                 // Method io/undertow/server/HttpServerExchange.getRequestHeaders:()Lio/undertow/util/HeaderMap;
       7: getstatic     #197                // Field io/undertow/util/Headers.CONTENT_TYPE:Lio/undertow/util/HttpString;
      10: invokevirtual #44                 // Method io/undertow/util/HeaderMap.getFirst:(Lio/undertow/util/HttpString;)Ljava/lang/String;
      13: astore_1
      14: aload_1
      15: ifnonnull     20
      18: aconst_null
      19: areturn
      20: aload_1
      21: ldc           #216                // String charset
      23: invokestatic  #217                // Method io/undertow/util/Headers.extractQuotedValueFromHeader:(Ljava/lang/String;Ljava/lang/String;)Ljava/lang/String;
      26: areturn

  public void setCharacterEncoding(java.lang.String) throws java.io.UnsupportedEncodingException;
    Code:
       0: aload_0
       1: getfield      #218                // Field readStarted:Z
       4: ifeq          8
       7: return
       8: aload_0
       9: aload_1
      10: invokestatic  #219                // Method java/nio/charset/Charset.forName:(Ljava/lang/String;)Ljava/nio/charset/Charset;
      13: putfield      #211                // Field characterEncoding:Ljava/nio/charset/Charset;
      16: aload_0
      17: getfield      #6                  // Field exchange:Lio/undertow/server/HttpServerExchange;
      20: getstatic     #58                 // Field io/undertow/servlet/handlers/ServletRequestContext.ATTACHMENT_KEY:Lio/undertow/util/AttachmentKey;
      23: invokevirtual #59                 // Method io/undertow/server/HttpServerExchange.getAttachment:(Lio/undertow/util/AttachmentKey;)Ljava/lang/Object;
      26: checkcast     #60                 // class io/undertow/servlet/handlers/ServletRequestContext
      29: invokevirtual #61                 // Method io/undertow/servlet/handlers/ServletRequestContext.getOriginalServletPathMatch:()Lio/undertow/servlet/handlers/ServletPathMatch;
      32: invokevirtual #81                 // Method io/undertow/servlet/handlers/ServletPathMatch.getServletChain:()Lio/undertow/servlet/handlers/ServletChain;
      35: invokevirtual #82                 // Method io/undertow/servlet/handlers/ServletChain.getManagedServlet:()Lio/undertow/servlet/core/ManagedServlet;
      38: astore_2
      39: aload_2
      40: invokevirtual #220                // Method io/undertow/servlet/core/ManagedServlet.getFormParserFactory:()Lio/undertow/server/handlers/form/FormParserFactory;
      43: aload_0
      44: getfield      #6                  // Field exchange:Lio/undertow/server/HttpServerExchange;
      47: invokevirtual #221                // Method io/undertow/server/handlers/form/FormParserFactory.createParser:(Lio/undertow/server/HttpServerExchange;)Lio/undertow/server/handlers/form/FormDataParser;
      50: astore_3
      51: aload_3
      52: ifnull        62
      55: aload_3
      56: aload_1
      57: invokeinterface #222,  2          // InterfaceMethod io/undertow/server/handlers/form/FormDataParser.setCharacterEncoding:(Ljava/lang/String;)V
      62: goto          74
      65: astore_2
      66: new           #224                // class java/io/UnsupportedEncodingException
      69: dup
      70: invokespecial #225                // Method java/io/UnsupportedEncodingException."<init>":()V
      73: athrow
      74: return
    Exception table:
       from    to  target type
           8    62    65   Class java/nio/charset/UnsupportedCharsetException

  public int getContentLength();
    Code:
       0: aload_0
       1: invokevirtual #226                // Method getContentLengthLong:()J
       4: lstore_1
       5: lload_1
       6: ldc2_w        #228                // long 2147483647l
       9: lcmp
      10: ifle          15
      13: iconst_m1
      14: ireturn
      15: lload_1
      16: l2i
      17: ireturn

  public long getContentLengthLong();
    Code:
       0: aload_0
       1: getstatic     #230                // Field io/undertow/util/Headers.CONTENT_LENGTH:Lio/undertow/util/HttpString;
       4: invokevirtual #231                // Method getHeader:(Lio/undertow/util/HttpString;)Ljava/lang/String;
       7: astore_1
       8: aload_1
       9: ifnull        19
      12: aload_1
      13: invokevirtual #93                 // Method java/lang/String.isEmpty:()Z
      16: ifeq          23
      19: ldc2_w        #38                 // long -1l
      22: lreturn
      23: aload_1
      24: invokestatic  #232                // Method java/lang/Long.parseLong:(Ljava/lang/String;)J
      27: lreturn

  public java.lang.String getContentType();
    Code:
       0: aload_0
       1: getstatic     #197                // Field io/undertow/util/Headers.CONTENT_TYPE:Lio/undertow/util/HttpString;
       4: invokevirtual #231                // Method getHeader:(Lio/undertow/util/HttpString;)Ljava/lang/String;
       7: areturn

  public jakarta.servlet.ServletInputStream getInputStream() throws java.io.IOException;
    Code:
       0: aload_0
       1: getfield      #233                // Field reader:Ljava/io/BufferedReader;
       4: ifnull        16
       7: getstatic     #41                 // Field io/undertow/servlet/UndertowServletMessages.MESSAGES:Lio/undertow/servlet/UndertowServletMessages;
      10: invokeinterface #234,  1          // InterfaceMethod io/undertow/servlet/UndertowServletMessages.getReaderAlreadyCalled:()Ljava/lang/IllegalStateException;
      15: athrow
      16: aload_0
      17: getfield      #235                // Field servletInputStream:Ljakarta/servlet/ServletInputStream;
      20: ifnonnull     35
      23: aload_0
      24: new           #236                // class io/undertow/servlet/spec/ServletInputStreamImpl
      27: dup
      28: aload_0
      29: invokespecial #237                // Method io/undertow/servlet/spec/ServletInputStreamImpl."<init>":(Lio/undertow/servlet/spec/HttpServletRequestImpl;)V
      32: putfield      #235                // Field servletInputStream:Ljakarta/servlet/ServletInputStream;
      35: aload_0
      36: iconst_1
      37: putfield      #218                // Field readStarted:Z
      40: aload_0
      41: getfield      #235                // Field servletInputStream:Ljakarta/servlet/ServletInputStream;
      44: areturn

  public void closeAndDrainRequest() throws java.io.IOException;
    Code:
       0: aload_0
       1: getfield      #233                // Field reader:Ljava/io/BufferedReader;
       4: ifnull        14
       7: aload_0
       8: getfield      #233                // Field reader:Ljava/io/BufferedReader;
      11: invokevirtual #238                // Method java/io/BufferedReader.close:()V
      14: aload_0
      15: getfield      #235                // Field servletInputStream:Ljakarta/servlet/ServletInputStream;
      18: ifnonnull     33
      21: aload_0
      22: new           #236                // class io/undertow/servlet/spec/ServletInputStreamImpl
      25: dup
      26: aload_0
      27: invokespecial #237                // Method io/undertow/servlet/spec/ServletInputStreamImpl."<init>":(Lio/undertow/servlet/spec/HttpServletRequestImpl;)V
      30: putfield      #235                // Field servletInputStream:Ljakarta/servlet/ServletInputStream;
      33: aload_0
      34: getfield      #235                // Field servletInputStream:Ljakarta/servlet/ServletInputStream;
      37: invokevirtual #239                // Method jakarta/servlet/ServletInputStream.close:()V
      40: return

  public void freeResources() throws java.io.IOException;
    Code:
       0: aload_0
       1: getfield      #233                // Field reader:Ljava/io/BufferedReader;
       4: ifnull        14
       7: aload_0
       8: getfield      #233                // Field reader:Ljava/io/BufferedReader;
      11: invokevirtual #238                // Method java/io/BufferedReader.close:()V
      14: aload_0
      15: getfield      #235                // Field servletInputStream:Ljakarta/servlet/ServletInputStream;
      18: ifnull        28
      21: aload_0
      22: getfield      #235                // Field servletInputStream:Ljakarta/servlet/ServletInputStream;
      25: invokevirtual #239                // Method jakarta/servlet/ServletInputStream.close:()V
      28: aload_0
      29: invokevirtual #240                // Method clearAttributes:()V
      32: goto          42
      35: astore_1
      36: aload_0
      37: invokevirtual #240                // Method clearAttributes:()V
      40: aload_1
      41: athrow
      42: return
    Exception table:
       from    to  target type
           0    28    35   any

  public java.lang.String getParameter(java.lang.String);
    Code:
       0: aload_0
       1: getfield      #241                // Field queryParameters:Ljava/util/Map;
       4: ifnonnull     18
       7: aload_0
       8: aload_0
       9: getfield      #6                  // Field exchange:Lio/undertow/server/HttpServerExchange;
      12: invokevirtual #242                // Method io/undertow/server/HttpServerExchange.getQueryParameters:()Ljava/util/Map;
      15: putfield      #241                // Field queryParameters:Ljava/util/Map;
      18: aload_0
      19: getfield      #241                // Field queryParameters:Ljava/util/Map;
      22: aload_1
      23: invokeinterface #209,  2          // InterfaceMethod java/util/Map.get:(Ljava/lang/Object;)Ljava/lang/Object;
      28: checkcast     #243                // class java/util/Deque
      31: astore_2
      32: aload_2
      33: ifnonnull     79
      36: aload_0
      37: invokevirtual #200                // Method parseFormData:()Lio/undertow/server/handlers/form/FormData;
      40: astore_3
      41: aload_3
      42: ifnull        77
      45: aload_3
      46: aload_1
      47: invokevirtual #244                // Method io/undertow/server/handlers/form/FormData.getFirst:(Ljava/lang/String;)Lio/undertow/server/handlers/form/FormData$FormValue;
      50: astore        4
      52: aload         4
      54: ifnull        67
      57: aload         4
      59: invokeinterface #245,  1          // InterfaceMethod io/undertow/server/handlers/form/FormData$FormValue.isFileItem:()Z
      64: ifeq          69
      67: aconst_null
      68: areturn
      69: aload         4
      71: invokeinterface #246,  1          // InterfaceMethod io/undertow/server/handlers/form/FormData$FormValue.getValue:()Ljava/lang/String;
      76: areturn
      77: aconst_null
      78: areturn
      79: aload_2
      80: invokeinterface #247,  1          // InterfaceMethod java/util/Deque.getFirst:()Ljava/lang/Object;
      85: checkcast     #113                // class java/lang/String
      88: areturn

  public java.util.Enumeration<java.lang.String> getParameterNames();
    Code:
       0: aload_0
       1: getfield      #241                // Field queryParameters:Ljava/util/Map;
       4: ifnonnull     18
       7: aload_0
       8: aload_0
       9: getfield      #6                  // Field exchange:Lio/undertow/server/HttpServerExchange;
      12: invokevirtual #242                // Method io/undertow/server/HttpServerExchange.getQueryParameters:()Ljava/util/Map;
      15: putfield      #241                // Field queryParameters:Ljava/util/Map;
      18: new           #50                 // class java/util/HashSet
      21: dup
      22: aload_0
      23: getfield      #241                // Field queryParameters:Ljava/util/Map;
      26: invokeinterface #210,  1          // InterfaceMethod java/util/Map.keySet:()Ljava/util/Set;
      31: invokespecial #248                // Method java/util/HashSet."<init>":(Ljava/util/Collection;)V
      34: astore_1
      35: aload_0
      36: invokevirtual #200                // Method parseFormData:()Lio/undertow/server/handlers/form/FormData;
      39: astore_2
      40: aload_2
      41: ifnull        132
      44: aload_2
      45: invokevirtual #201                // Method io/undertow/server/handlers/form/FormData.iterator:()Ljava/util/Iterator;
      48: astore_3
      49: aload_3
      50: invokeinterface #14,  1           // InterfaceMethod java/util/Iterator.hasNext:()Z
      55: ifeq          132
      58: aload_3
      59: invokeinterface #15,  1           // InterfaceMethod java/util/Iterator.next:()Ljava/lang/Object;
      64: checkcast     #113                // class java/lang/String
      67: astore        4
      69: aload_2
      70: aload         4
      72: invokevirtual #202                // Method io/undertow/server/handlers/form/FormData.get:(Ljava/lang/String;)Ljava/util/Deque;
      75: invokeinterface #203,  1          // InterfaceMethod java/util/Deque.iterator:()Ljava/util/Iterator;
      80: astore        5
      82: aload         5
      84: invokeinterface #14,  1           // InterfaceMethod java/util/Iterator.hasNext:()Z
      89: ifeq          129
      92: aload         5
      94: invokeinterface #15,  1           // InterfaceMethod java/util/Iterator.next:()Ljava/lang/Object;
      99: checkcast     #204                // class io/undertow/server/handlers/form/FormData$FormValue
     102: astore        6
     104: aload         6
     106: invokeinterface #245,  1          // InterfaceMethod io/undertow/server/handlers/form/FormData$FormValue.isFileItem:()Z
     111: ifne          126
     114: aload_1
     115: aload         4
     117: invokeinterface #56,  2           // InterfaceMethod java/util/Set.add:(Ljava/lang/Object;)Z
     122: pop
     123: goto          129
     126: goto          82
     129: goto          49
     132: new           #47                 // class io/undertow/servlet/util/IteratorEnumeration
     135: dup
     136: aload_1
     137: invokeinterface #57,  1           // InterfaceMethod java/util/Set.iterator:()Ljava/util/Iterator;
     142: invokespecial #49                 // Method io/undertow/servlet/util/IteratorEnumeration."<init>":(Ljava/util/Iterator;)V
     145: areturn

  public java.lang.String[] getParameterValues(java.lang.String);
    Code:
       0: aload_0
       1: getfield      #241                // Field queryParameters:Ljava/util/Map;
       4: ifnonnull     18
       7: aload_0
       8: aload_0
       9: getfield      #6                  // Field exchange:Lio/undertow/server/HttpServerExchange;
      12: invokevirtual #242                // Method io/undertow/server/HttpServerExchange.getQueryParameters:()Ljava/util/Map;
      15: putfield      #241                // Field queryParameters:Ljava/util/Map;
      18: new           #195                // class java/util/ArrayList
      21: dup
      22: invokespecial #196                // Method java/util/ArrayList."<init>":()V
      25: astore_2
      26: aload_0
      27: getfield      #241                // Field queryParameters:Ljava/util/Map;
      30: aload_1
      31: invokeinterface #209,  2          // InterfaceMethod java/util/Map.get:(Ljava/lang/Object;)Ljava/lang/Object;
      36: checkcast     #243                // class java/util/Deque
      39: astore_3
      40: aload_3
      41: ifnull        86
      44: aload_3
      45: invokeinterface #203,  1          // InterfaceMethod java/util/Deque.iterator:()Ljava/util/Iterator;
      50: astore        4
      52: aload         4
      54: invokeinterface #14,  1           // InterfaceMethod java/util/Iterator.hasNext:()Z
      59: ifeq          86
      62: aload         4
      64: invokeinterface #15,  1           // InterfaceMethod java/util/Iterator.next:()Ljava/lang/Object;
      69: checkcast     #113                // class java/lang/String
      72: astore        5
      74: aload_2
      75: aload         5
      77: invokeinterface #207,  2          // InterfaceMethod java/util/List.add:(Ljava/lang/Object;)Z
      82: pop
      83: goto          52
      86: aload_0
      87: invokevirtual #200                // Method parseFormData:()Lio/undertow/server/handlers/form/FormData;
      90: astore        4
      92: aload         4
      94: ifnull        168
      97: aload         4
      99: aload_1
     100: invokevirtual #202                // Method io/undertow/server/handlers/form/FormData.get:(Ljava/lang/String;)Ljava/util/Deque;
     103: astore        5
     105: aload         5
     107: ifnull        168
     110: aload         5
     112: invokeinterface #203,  1          // InterfaceMethod java/util/Deque.iterator:()Ljava/util/Iterator;
     117: astore        6
     119: aload         6
     121: invokeinterface #14,  1           // InterfaceMethod java/util/Iterator.hasNext:()Z
     126: ifeq          168
     129: aload         6
     131: invokeinterface #15,  1           // InterfaceMethod java/util/Iterator.next:()Ljava/lang/Object;
     136: checkcast     #204                // class io/undertow/server/handlers/form/FormData$FormValue
     139: astore        7
     141: aload         7
     143: invokeinterface #245,  1          // InterfaceMethod io/undertow/server/handlers/form/FormData$FormValue.isFileItem:()Z
     148: ifne          165
     151: aload_2
     152: aload         7
     154: invokeinterface #246,  1          // InterfaceMethod io/undertow/server/handlers/form/FormData$FormValue.getValue:()Ljava/lang/String;
     159: invokeinterface #207,  2          // InterfaceMethod java/util/List.add:(Ljava/lang/Object;)Z
     164: pop
     165: goto          119
     168: aload_2
     169: invokeinterface #249,  1          // InterfaceMethod java/util/List.isEmpty:()Z
     174: ifeq          179
     177: aconst_null
     178: areturn
     179: aload_2
     180: aload_2
     181: invokeinterface #250,  1          // InterfaceMethod java/util/List.size:()I
     186: anewarray     #113                // class java/lang/String
     189: invokeinterface #251,  2          // InterfaceMethod java/util/List.toArray:([Ljava/lang/Object;)[Ljava/lang/Object;
     194: checkcast     #252                // class "[Ljava/lang/String;"
     197: areturn

  public java.util.Map<java.lang.String, java.lang.String[]> getParameterMap();
    Code:
       0: aload_0
       1: getfield      #241                // Field queryParameters:Ljava/util/Map;
       4: ifnonnull     18
       7: aload_0
       8: aload_0
       9: getfield      #6                  // Field exchange:Lio/undertow/server/HttpServerExchange;
      12: invokevirtual #242                // Method io/undertow/server/HttpServerExchange.getQueryParameters:()Ljava/util/Map;
      15: putfield      #241                // Field queryParameters:Ljava/util/Map;
      18: new           #253                // class java/util/HashMap
      21: dup
      22: invokespecial #254                // Method java/util/HashMap."<init>":()V
      25: astore_1
      26: aload_0
      27: getfield      #241                // Field queryParameters:Ljava/util/Map;
      30: invokeinterface #255,  1          // InterfaceMethod java/util/Map.entrySet:()Ljava/util/Set;
      35: invokeinterface #57,  1           // InterfaceMethod java/util/Set.iterator:()Ljava/util/Iterator;
      40: astore_2
      41: aload_2
      42: invokeinterface #14,  1           // InterfaceMethod java/util/Iterator.hasNext:()Z
      47: ifeq          95
      50: aload_2
      51: invokeinterface #15,  1           // InterfaceMethod java/util/Iterator.next:()Ljava/lang/Object;
      56: checkcast     #256                // class java/util/Map$Entry
      59: astore_3
      60: aload_1
      61: aload_3
      62: invokeinterface #257,  1          // InterfaceMethod java/util/Map$Entry.getKey:()Ljava/lang/Object;
      67: checkcast     #113                // class java/lang/String
      70: new           #195                // class java/util/ArrayList
      73: dup
      74: aload_3
      75: invokeinterface #258,  1          // InterfaceMethod java/util/Map$Entry.getValue:()Ljava/lang/Object;
      80: checkcast     #259                // class java/util/Collection
      83: invokespecial #260                // Method java/util/ArrayList."<init>":(Ljava/util/Collection;)V
      86: invokeinterface #261,  3          // InterfaceMethod java/util/Map.put:(Ljava/lang/Object;Ljava/lang/Object;)Ljava/lang/Object;
      91: pop
      92: goto          41
      95: aload_0
      96: invokevirtual #200                // Method parseFormData:()Lio/undertow/server/handlers/form/FormData;
      99: astore_2
     100: aload_2
     101: ifnull        309
     104: aload_2
     105: invokevirtual #201                // Method io/undertow/server/handlers/form/FormData.iterator:()Ljava/util/Iterator;
     108: astore_3
     109: aload_3
     110: invokeinterface #14,  1           // InterfaceMethod java/util/Iterator.hasNext:()Z
     115: ifeq          309
     118: aload_3
     119: invokeinterface #15,  1           // InterfaceMethod java/util/Iterator.next:()Ljava/lang/Object;
     124: checkcast     #113                // class java/lang/String
     127: astore        4
     129: aload_2
     130: aload         4
     132: invokevirtual #202                // Method io/undertow/server/handlers/form/FormData.get:(Ljava/lang/String;)Ljava/util/Deque;
     135: astore        5
     137: aload_1
     138: aload         4
     140: invokeinterface #262,  2          // InterfaceMethod java/util/Map.containsKey:(Ljava/lang/Object;)Z
     145: ifeq          221
     148: aload_1
     149: aload         4
     151: invokeinterface #209,  2          // InterfaceMethod java/util/Map.get:(Ljava/lang/Object;)Ljava/lang/Object;
     156: checkcast     #195                // class java/util/ArrayList
     159: astore        6
     161: aload         5
     163: invokeinterface #203,  1          // InterfaceMethod java/util/Deque.iterator:()Ljava/util/Iterator;
     168: astore        7
     170: aload         7
     172: invokeinterface #14,  1           // InterfaceMethod java/util/Iterator.hasNext:()Z
     177: ifeq          218
     180: aload         7
     182: invokeinterface #15,  1           // InterfaceMethod java/util/Iterator.next:()Ljava/lang/Object;
     187: checkcast     #204                // class io/undertow/server/handlers/form/FormData$FormValue
     190: astore        8
     192: aload         8
     194: invokeinterface #245,  1          // InterfaceMethod io/undertow/server/handlers/form/FormData$FormValue.isFileItem:()Z
     199: ifne          215
     202: aload         6
     204: aload         8
     206: invokeinterface #246,  1          // InterfaceMethod io/undertow/server/handlers/form/FormData$FormValue.getValue:()Ljava/lang/String;
     211: invokevirtual #263                // Method java/util/ArrayList.add:(Ljava/lang/Object;)Z
     214: pop
     215: goto          170
     218: goto          306
     221: new           #195                // class java/util/ArrayList
     224: dup
     225: invokespecial #196                // Method java/util/ArrayList."<init>":()V
     228: astore        6
     230: aload         5
     232: invokeinterface #203,  1          // InterfaceMethod java/util/Deque.iterator:()Ljava/util/Iterator;
     237: astore        7
     239: aload         7
     241: invokeinterface #14,  1           // InterfaceMethod java/util/Iterator.hasNext:()Z
     246: ifeq          287
     249: aload         7
     251: invokeinterface #15,  1           // InterfaceMethod java/util/Iterator.next:()Ljava/lang/Object;
     256: checkcast     #204                // class io/undertow/server/handlers/form/FormData$FormValue
     259: astore        8
     261: aload         8
     263: invokeinterface #245,  1          // InterfaceMethod io/undertow/server/handlers/form/FormData$FormValue.isFileItem:()Z
     268: ifne          284
     271: aload         6
     273: aload         8
     275: invokeinterface #246,  1          // InterfaceMethod io/undertow/server/handlers/form/FormData$FormValue.getValue:()Ljava/lang/String;
     280: invokevirtual #263                // Method java/util/ArrayList.add:(Ljava/lang/Object;)Z
     283: pop
     284: goto          239
     287: aload         6
     289: invokevirtual #264                // Method java/util/ArrayList.isEmpty:()Z
     292: ifne          306
     295: aload_1
     296: aload         4
     298: aload         6
     300: invokeinterface #261,  3          // InterfaceMethod java/util/Map.put:(Ljava/lang/Object;Ljava/lang/Object;)Ljava/lang/Object;
     305: pop
     306: goto          109
     309: new           #253                // class java/util/HashMap
     312: dup
     313: invokespecial #254                // Method java/util/HashMap."<init>":()V
     316: astore_3
     317: aload_1
     318: invokeinterface #255,  1          // InterfaceMethod java/util/Map.entrySet:()Ljava/util/Set;
     323: invokeinterface #57,  1           // InterfaceMethod java/util/Set.iterator:()Ljava/util/Iterator;
     328: astore        4
     330: aload         4
     332: invokeinterface #14,  1           // InterfaceMethod java/util/Iterator.hasNext:()Z
     337: ifeq          404
     340: aload         4
     342: invokeinterface #15,  1           // InterfaceMethod java/util/Iterator.next:()Ljava/lang/Object;
     347: checkcast     #256                // class java/util/Map$Entry
     350: astore        5
     352: aload_3
     353: aload         5
     355: invokeinterface #257,  1          // InterfaceMethod java/util/Map$Entry.getKey:()Ljava/lang/Object;
     360: checkcast     #113                // class java/lang/String
     363: aload         5
     365: invokeinterface #258,  1          // InterfaceMethod java/util/Map$Entry.getValue:()Ljava/lang/Object;
     370: checkcast     #195                // class java/util/ArrayList
     373: aload         5
     375: invokeinterface #258,  1          // InterfaceMethod java/util/Map$Entry.getValue:()Ljava/lang/Object;
     380: checkcast     #195                // class java/util/ArrayList
     383: invokevirtual #265                // Method java/util/ArrayList.size:()I
     386: anewarray     #113                // class java/lang/String
     389: invokevirtual #266                // Method java/util/ArrayList.toArray:([Ljava/lang/Object;)[Ljava/lang/Object;
     392: checkcast     #252                // class "[Ljava/lang/String;"
     395: invokeinterface #261,  3          // InterfaceMethod java/util/Map.put:(Ljava/lang/Object;Ljava/lang/Object;)Ljava/lang/Object;
     400: pop
     401: goto          330
     404: aload_3
     405: areturn

  private io.undertow.server.handlers.form.FormData parseFormData();
    Code:
       0: aload_0
       1: getfield      #267                // Field formParsingException:Ljava/lang/RuntimeException;
       4: ifnull        12
       7: aload_0
       8: getfield      #267                // Field formParsingException:Ljava/lang/RuntimeException;
      11: athrow
      12: aload_0
      13: getfield      #268                // Field parsedFormData:Lio/undertow/server/handlers/form/FormData;
      16: ifnonnull     121
      19: aload_0
      20: getfield      #218                // Field readStarted:Z
      23: ifeq          28
      26: aconst_null
      27: areturn
      28: aload_0
      29: getfield      #6                  // Field exchange:Lio/undertow/server/HttpServerExchange;
      32: getstatic     #58                 // Field io/undertow/servlet/handlers/ServletRequestContext.ATTACHMENT_KEY:Lio/undertow/util/AttachmentKey;
      35: invokevirtual #59                 // Method io/undertow/server/HttpServerExchange.getAttachment:(Lio/undertow/util/AttachmentKey;)Ljava/lang/Object;
      38: checkcast     #60                 // class io/undertow/servlet/handlers/ServletRequestContext
      41: invokevirtual #104                // Method io/undertow/servlet/handlers/ServletRequestContext.getCurrentServlet:()Lio/undertow/servlet/handlers/ServletChain;
      44: invokevirtual #82                 // Method io/undertow/servlet/handlers/ServletChain.getManagedServlet:()Lio/undertow/servlet/core/ManagedServlet;
      47: astore_1
      48: aload_1
      49: invokevirtual #220                // Method io/undertow/servlet/core/ManagedServlet.getFormParserFactory:()Lio/undertow/server/handlers/form/FormParserFactory;
      52: aload_0
      53: getfield      #6                  // Field exchange:Lio/undertow/server/HttpServerExchange;
      56: invokevirtual #221                // Method io/undertow/server/handlers/form/FormParserFactory.createParser:(Lio/undertow/server/HttpServerExchange;)Lio/undertow/server/handlers/form/FormDataParser;
      59: astore_2
      60: aload_2
      61: ifnonnull     66
      64: aconst_null
      65: areturn
      66: aload_0
      67: iconst_1
      68: putfield      #218                // Field readStarted:Z
      71: aload_0
      72: aload_2
      73: invokeinterface #269,  1          // InterfaceMethod io/undertow/server/handlers/form/FormDataParser.parseBlocking:()Lio/undertow/server/handlers/form/FormData;
      78: dup_x1
      79: putfield      #268                // Field parsedFormData:Lio/undertow/server/handlers/form/FormData;
      82: areturn
      83: astore_3
      84: aload_0
      85: new           #272                // class java/lang/IllegalStateException
      88: dup
      89: aload_3
      90: invokespecial #273                // Method java/lang/IllegalStateException."<init>":(Ljava/lang/Throwable;)V
      93: dup_x1
      94: putfield      #267                // Field formParsingException:Ljava/lang/RuntimeException;
      97: athrow
      98: astore_3
      99: aload_0
     100: aload_3
     101: dup_x1
     102: putfield      #267                // Field formParsingException:Ljava/lang/RuntimeException;
     105: athrow
     106: astore_3
     107: aload_0
     108: new           #192                // class java/lang/RuntimeException
     111: dup
     112: aload_3
     113: invokespecial #193                // Method java/lang/RuntimeException."<init>":(Ljava/lang/Throwable;)V
     116: dup_x1
     117: putfield      #267                // Field formParsingException:Ljava/lang/RuntimeException;
     120: athrow
     121: aload_0
     122: getfield      #268                // Field parsedFormData:Lio/undertow/server/handlers/form/FormData;
     125: areturn
    Exception table:
       from    to  target type
          71    82    83   Class io/undertow/server/RequestTooBigException
          71    82    83   Class io/undertow/server/handlers/form/MultiPartParserDefinition$FileTooLargeException
          71    82    98   Class java/lang/RuntimeException
          71    82   106   Class java/io/IOException

  public java.lang.String getProtocol();
    Code:
       0: aload_0
       1: getfield      #6                  // Field exchange:Lio/undertow/server/HttpServerExchange;
       4: invokevirtual #143                // Method io/undertow/server/HttpServerExchange.getProtocol:()Lio/undertow/util/HttpString;
       7: invokevirtual #55                 // Method io/undertow/util/HttpString.toString:()Ljava/lang/String;
      10: areturn

  public java.lang.String getScheme();
    Code:
       0: aload_0
       1: getfield      #6                  // Field exchange:Lio/undertow/server/HttpServerExchange;
       4: invokevirtual #275                // Method io/undertow/server/HttpServerExchange.getRequestScheme:()Ljava/lang/String;
       7: areturn

  public java.lang.String getServerName();
    Code:
       0: aload_0
       1: getfield      #6                  // Field exchange:Lio/undertow/server/HttpServerExchange;
       4: invokevirtual #276                // Method io/undertow/server/HttpServerExchange.getHostName:()Ljava/lang/String;
       7: areturn

  public int getServerPort();
    Code:
       0: aload_0
       1: getfield      #6                  // Field exchange:Lio/undertow/server/HttpServerExchange;
       4: invokevirtual #277                // Method io/undertow/server/HttpServerExchange.getHostPort:()I
       7: ireturn

  public java.io.BufferedReader getReader() throws java.io.IOException;
    Code:
       0: aload_0
       1: getfield      #233                // Field reader:Ljava/io/BufferedReader;
       4: ifnonnull     120
       7: aload_0
       8: getfield      #235                // Field servletInputStream:Ljakarta/servlet/ServletInputStream;
      11: ifnull        23
      14: getstatic     #41                 // Field io/undertow/servlet/UndertowServletMessages.MESSAGES:Lio/undertow/servlet/UndertowServletMessages;
      17: invokeinterface #278,  1          // InterfaceMethod io/undertow/servlet/UndertowServletMessages.getInputStreamAlreadyCalled:()Ljava/lang/IllegalStateException;
      22: athrow
      23: aconst_null
      24: astore_1
      25: aload_0
      26: getfield      #211                // Field characterEncoding:Ljava/nio/charset/Charset;
      29: ifnull        40
      32: aload_0
      33: getfield      #211                // Field characterEncoding:Ljava/nio/charset/Charset;
      36: astore_1
      37: goto          70
      40: aload_0
      41: invokevirtual #279                // Method getCharacterEncoding:()Ljava/lang/String;
      44: astore_2
      45: aload_2
      46: ifnull        70
      49: aload_2
      50: invokestatic  #219                // Method java/nio/charset/Charset.forName:(Ljava/lang/String;)Ljava/nio/charset/Charset;
      53: astore_1
      54: goto          70
      57: astore_3
      58: new           #224                // class java/io/UnsupportedEncodingException
      61: dup
      62: aload_3
      63: invokevirtual #280                // Method java/nio/charset/UnsupportedCharsetException.getMessage:()Ljava/lang/String;
      66: invokespecial #281                // Method java/io/UnsupportedEncodingException."<init>":(Ljava/lang/String;)V
      69: athrow
      70: aload_0
      71: new           #282                // class java/io/BufferedReader
      74: dup
      75: aload_1
      76: ifnonnull     99
      79: new           #283                // class java/io/InputStreamReader
      82: dup
      83: aload_0
      84: getfield      #6                  // Field exchange:Lio/undertow/server/HttpServerExchange;
      87: invokevirtual #284                // Method io/undertow/server/HttpServerExchange.getInputStream:()Ljava/io/InputStream;
      90: getstatic     #285                // Field java/nio/charset/StandardCharsets.ISO_8859_1:Ljava/nio/charset/Charset;
      93: invokespecial #286                // Method java/io/InputStreamReader."<init>":(Ljava/io/InputStream;Ljava/nio/charset/Charset;)V
      96: goto          114
      99: new           #283                // class java/io/InputStreamReader
     102: dup
     103: aload_0
     104: getfield      #6                  // Field exchange:Lio/undertow/server/HttpServerExchange;
     107: invokevirtual #284                // Method io/undertow/server/HttpServerExchange.getInputStream:()Ljava/io/InputStream;
     110: aload_1
     111: invokespecial #286                // Method java/io/InputStreamReader."<init>":(Ljava/io/InputStream;Ljava/nio/charset/Charset;)V
     114: invokespecial #287                // Method java/io/BufferedReader."<init>":(Ljava/io/Reader;)V
     117: putfield      #233                // Field reader:Ljava/io/BufferedReader;
     120: aload_0
     121: iconst_1
     122: putfield      #218                // Field readStarted:Z
     125: aload_0
     126: getfield      #233                // Field reader:Ljava/io/BufferedReader;
     129: areturn
    Exception table:
       from    to  target type
          49    54    57   Class java/nio/charset/UnsupportedCharsetException

  public java.lang.String getRemoteAddr();
    Code:
       0: aload_0
       1: getfield      #6                  // Field exchange:Lio/undertow/server/HttpServerExchange;
       4: invokevirtual #288                // Method io/undertow/server/HttpServerExchange.getSourceAddress:()Ljava/net/InetSocketAddress;
       7: astore_1
       8: aload_1
       9: ifnonnull     15
      12: ldc           #75                 // String
      14: areturn
      15: aload_1
      16: invokevirtual #289                // Method java/net/InetSocketAddress.getAddress:()Ljava/net/InetAddress;
      19: astore_2
      20: aload_2
      21: ifnonnull     29
      24: aload_1
      25: invokevirtual #290                // Method java/net/InetSocketAddress.getHostString:()Ljava/lang/String;
      28: areturn
      29: aload_2
      30: invokevirtual #291                // Method java/net/InetAddress.getHostAddress:()Ljava/lang/String;
      33: areturn

  public java.lang.String getRemoteHost();
    Code:
       0: aload_0
       1: getfield      #6                  // Field exchange:Lio/undertow/server/HttpServerExchange;
       4: invokevirtual #288                // Method io/undertow/server/HttpServerExchange.getSourceAddress:()Ljava/net/InetSocketAddress;
       7: astore_1
       8: aload_1
       9: ifnonnull     15
      12: ldc           #75                 // String
      14: areturn
      15: aload_1
      16: invokevirtual #290                // Method java/net/InetSocketAddress.getHostString:()Ljava/lang/String;
      19: areturn

  public void setAttribute(java.lang.String, java.lang.Object);
    Code:
       0: aload_2
       1: ifnonnull     10
       4: aload_0
       5: aload_1
       6: invokevirtual #292                // Method removeAttribute:(Ljava/lang/String;)V
       9: return
      10: aload_0
      11: getfield      #2                  // Field attributes:Ljava/util/Map;
      14: ifnonnull     28
      17: aload_0
      18: new           #253                // class java/util/HashMap
      21: dup
      22: invokespecial #254                // Method java/util/HashMap."<init>":()V
      25: putfield      #2                  // Field attributes:Ljava/util/Map;
      28: aload_0
      29: getfield      #2                  // Field attributes:Ljava/util/Map;
      32: aload_1
      33: aload_2
      34: invokeinterface #261,  3          // InterfaceMethod java/util/Map.put:(Ljava/lang/Object;Ljava/lang/Object;)Ljava/lang/Object;
      39: astore_3
      40: aload_3
      41: ifnull        65
      44: aload_0
      45: getfield      #7                  // Field servletContext:Lio/undertow/servlet/spec/ServletContextImpl;
      48: invokevirtual #105                // Method io/undertow/servlet/spec/ServletContextImpl.getDeployment:()Lio/undertow/servlet/api/Deployment;
      51: invokeinterface #135,  1          // InterfaceMethod io/undertow/servlet/api/Deployment.getApplicationListeners:()Lio/undertow/servlet/core/ApplicationListeners;
      56: aload_0
      57: aload_1
      58: aload_3
      59: invokevirtual #293                // Method io/undertow/servlet/core/ApplicationListeners.servletRequestAttributeReplaced:(Ljakarta/servlet/http/HttpServletRequest;Ljava/lang/String;Ljava/lang/Object;)V
      62: goto          83
      65: aload_0
      66: getfield      #7                  // Field servletContext:Lio/undertow/servlet/spec/ServletContextImpl;
      69: invokevirtual #105                // Method io/undertow/servlet/spec/ServletContextImpl.getDeployment:()Lio/undertow/servlet/api/Deployment;
      72: invokeinterface #135,  1          // InterfaceMethod io/undertow/servlet/api/Deployment.getApplicationListeners:()Lio/undertow/servlet/core/ApplicationListeners;
      77: aload_0
      78: aload_1
      79: aload_2
      80: invokevirtual #294                // Method io/undertow/servlet/core/ApplicationListeners.servletRequestAttributeAdded:(Ljakarta/servlet/http/HttpServletRequest;Ljava/lang/String;Ljava/lang/Object;)V
      83: return

  public void removeAttribute(java.lang.String);
    Code:
       0: aload_0
       1: getfield      #2                  // Field attributes:Ljava/util/Map;
       4: ifnonnull     8
       7: return
       8: aload_0
       9: getfield      #2                  // Field attributes:Ljava/util/Map;
      12: aload_1
      13: invokeinterface #295,  2          // InterfaceMethod java/util/Map.remove:(Ljava/lang/Object;)Ljava/lang/Object;
      18: astore_2
      19: aload_0
      20: getfield      #7                  // Field servletContext:Lio/undertow/servlet/spec/ServletContextImpl;
      23: invokevirtual #105                // Method io/undertow/servlet/spec/ServletContextImpl.getDeployment:()Lio/undertow/servlet/api/Deployment;
      26: invokeinterface #135,  1          // InterfaceMethod io/undertow/servlet/api/Deployment.getApplicationListeners:()Lio/undertow/servlet/core/ApplicationListeners;
      31: aload_0
      32: aload_1
      33: aload_2
      34: invokevirtual #296                // Method io/undertow/servlet/core/ApplicationListeners.servletRequestAttributeRemoved:(Ljakarta/servlet/http/HttpServletRequest;Ljava/lang/String;Ljava/lang/Object;)V
      37: return

  public java.util.Locale getLocale();
    Code:
       0: aload_0
       1: invokevirtual #297                // Method getLocales:()Ljava/util/Enumeration;
       4: invokeinterface #298,  1          // InterfaceMethod java/util/Enumeration.nextElement:()Ljava/lang/Object;
       9: checkcast     #299                // class java/util/Locale
      12: areturn

  public java.util.Enumeration<java.util.Locale> getLocales();
    Code:
       0: aload_0
       1: getfield      #6                  // Field exchange:Lio/undertow/server/HttpServerExchange;
       4: invokevirtual #36                 // Method io/undertow/server/HttpServerExchange.getRequestHeaders:()Lio/undertow/util/HeaderMap;
       7: getstatic     #300                // Field io/undertow/util/Headers.ACCEPT_LANGUAGE:Lio/undertow/util/HttpString;
      10: invokevirtual #301                // Method io/undertow/util/HeaderMap.get:(Lio/undertow/util/HttpString;)Lio/undertow/util/HeaderValues;
      13: astore_1
      14: aload_1
      15: invokestatic  #302                // Method io/undertow/util/LocaleUtils.getLocalesFromHeader:(Ljava/util/List;)Ljava/util/List;
      18: astore_2
      19: aload_2
      20: invokeinterface #249,  1          // InterfaceMethod java/util/List.isEmpty:()Z
      25: ifeq          47
      28: new           #47                 // class io/undertow/servlet/util/IteratorEnumeration
      31: dup
      32: invokestatic  #303                // Method java/util/Locale.getDefault:()Ljava/util/Locale;
      35: invokestatic  #304                // Method java/util/Collections.singletonList:(Ljava/lang/Object;)Ljava/util/List;
      38: invokeinterface #48,  1           // InterfaceMethod java/util/List.iterator:()Ljava/util/Iterator;
      43: invokespecial #49                 // Method io/undertow/servlet/util/IteratorEnumeration."<init>":(Ljava/util/Iterator;)V
      46: areturn
      47: new           #47                 // class io/undertow/servlet/util/IteratorEnumeration
      50: dup
      51: aload_2
      52: invokeinterface #48,  1           // InterfaceMethod java/util/List.iterator:()Ljava/util/Iterator;
      57: invokespecial #49                 // Method io/undertow/servlet/util/IteratorEnumeration."<init>":(Ljava/util/Iterator;)V
      60: areturn

  public boolean isSecure();
    Code:
       0: aload_0
       1: getfield      #6                  // Field exchange:Lio/undertow/server/HttpServerExchange;
       4: invokevirtual #305                // Method io/undertow/server/HttpServerExchange.isSecure:()Z
       7: ireturn

  public jakarta.servlet.RequestDispatcher getRequestDispatcher(java.lang.String);
    Code:
       0: aload_1
       1: ifnonnull     6
       4: aconst_null
       5: areturn
       6: aload_1
       7: ldc           #72                 // String /
       9: invokevirtual #73                 // Method java/lang/String.startsWith:(Ljava/lang/String;)Z
      12: ifeq          20
      15: aload_1
      16: astore_2
      17: goto          60
      20: aload_0
      21: getfield      #6                  // Field exchange:Lio/undertow/server/HttpServerExchange;
      24: invokevirtual #306                // Method io/undertow/server/HttpServerExchange.getRelativePath:()Ljava/lang/String;
      27: astore_3
      28: aload_3
      29: ldc           #72                 // String /
      31: invokevirtual #307                // Method java/lang/String.lastIndexOf:(Ljava/lang/String;)I
      34: istore        4
      36: iload         4
      38: iconst_m1
      39: if_icmpeq     52
      42: aload_3
      43: iconst_0
      44: iload         4
      46: iconst_1
      47: iadd
      48: invokevirtual #79                 // Method java/lang/String.substring:(II)Ljava/lang/String;
      51: astore_3
      52: aload_3
      53: aload_1
      54: invokedynamic #308,  0            // InvokeDynamic #0:makeConcatWithConstants:(Ljava/lang/String;Ljava/lang/String;)Ljava/lang/String;
      59: astore_2
      60: aload_0
      61: getfield      #7                  // Field servletContext:Lio/undertow/servlet/spec/ServletContextImpl;
      64: aload_2
      65: invokevirtual #309                // Method io/undertow/servlet/spec/ServletContextImpl.getRequestDispatcher:(Ljava/lang/String;)Ljakarta/servlet/RequestDispatcher;
      68: areturn

  public int getRemotePort();
    Code:
       0: aload_0
       1: getfield      #6                  // Field exchange:Lio/undertow/server/HttpServerExchange;
       4: invokevirtual #288                // Method io/undertow/server/HttpServerExchange.getSourceAddress:()Ljava/net/InetSocketAddress;
       7: invokevirtual #310                // Method java/net/InetSocketAddress.getPort:()I
      10: ireturn

  public java.lang.String getLocalName();
    Code:
       0: aload_0
       1: getfield      #6                  // Field exchange:Lio/undertow/server/HttpServerExchange;
       4: invokevirtual #311                // Method io/undertow/server/HttpServerExchange.getDestinationAddress:()Ljava/net/InetSocketAddress;
       7: invokevirtual #312                // Method java/net/InetSocketAddress.getHostName:()Ljava/lang/String;
      10: areturn

  public java.lang.String getLocalAddr();
    Code:
       0: aload_0
       1: getfield      #6                  // Field exchange:Lio/undertow/server/HttpServerExchange;
       4: invokevirtual #311                // Method io/undertow/server/HttpServerExchange.getDestinationAddress:()Ljava/net/InetSocketAddress;
       7: astore_1
       8: aload_1
       9: ifnonnull     15
      12: ldc           #75                 // String
      14: areturn
      15: aload_1
      16: invokevirtual #289                // Method java/net/InetSocketAddress.getAddress:()Ljava/net/InetAddress;
      19: astore_2
      20: aload_2
      21: ifnonnull     29
      24: aload_1
      25: invokevirtual #290                // Method java/net/InetSocketAddress.getHostString:()Ljava/lang/String;
      28: areturn
      29: aload_2
      30: invokevirtual #291                // Method java/net/InetAddress.getHostAddress:()Ljava/lang/String;
      33: areturn

  public int getLocalPort();
    Code:
       0: aload_0
       1: getfield      #6                  // Field exchange:Lio/undertow/server/HttpServerExchange;
       4: invokevirtual #311                // Method io/undertow/server/HttpServerExchange.getDestinationAddress:()Ljava/net/InetSocketAddress;
       7: invokevirtual #310                // Method java/net/InetSocketAddress.getPort:()I
      10: ireturn

  public io.undertow.servlet.spec.ServletContextImpl getServletContext();
    Code:
       0: aload_0
       1: getfield      #7                  // Field servletContext:Lio/undertow/servlet/spec/ServletContextImpl;
       4: areturn

  public jakarta.servlet.AsyncContext startAsync() throws java.lang.IllegalStateException;
    Code:
       0: aload_0
       1: invokevirtual #313                // Method isAsyncSupported:()Z
       4: ifne          16
       7: getstatic     #41                 // Field io/undertow/servlet/UndertowServletMessages.MESSAGES:Lio/undertow/servlet/UndertowServletMessages;
      10: invokeinterface #314,  1          // InterfaceMethod io/undertow/servlet/UndertowServletMessages.startAsyncNotAllowed:()Ljava/lang/IllegalStateException;
      15: athrow
      16: aload_0
      17: getfield      #4                  // Field asyncStarted:Z
      20: ifeq          32
      23: getstatic     #41                 // Field io/undertow/servlet/UndertowServletMessages.MESSAGES:Lio/undertow/servlet/UndertowServletMessages;
      26: invokeinterface #315,  1          // InterfaceMethod io/undertow/servlet/UndertowServletMessages.asyncAlreadyStarted:()Ljava/lang/IllegalStateException;
      31: athrow
      32: aload_0
      33: iconst_1
      34: putfield      #4                  // Field asyncStarted:Z
      37: aload_0
      38: getfield      #6                  // Field exchange:Lio/undertow/server/HttpServerExchange;
      41: getstatic     #58                 // Field io/undertow/servlet/handlers/ServletRequestContext.ATTACHMENT_KEY:Lio/undertow/util/AttachmentKey;
      44: invokevirtual #59                 // Method io/undertow/server/HttpServerExchange.getAttachment:(Lio/undertow/util/AttachmentKey;)Ljava/lang/Object;
      47: checkcast     #60                 // class io/undertow/servlet/handlers/ServletRequestContext
      50: astore_1
      51: aload_0
      52: new           #316                // class io/undertow/servlet/spec/AsyncContextImpl
      55: dup
      56: aload_0
      57: getfield      #6                  // Field exchange:Lio/undertow/server/HttpServerExchange;
      60: aload_1
      61: invokevirtual #317                // Method io/undertow/servlet/handlers/ServletRequestContext.getServletRequest:()Ljakarta/servlet/ServletRequest;
      64: aload_1
      65: invokevirtual #120                // Method io/undertow/servlet/handlers/ServletRequestContext.getServletResponse:()Ljakarta/servlet/ServletResponse;
      68: aload_1
      69: iconst_0
      70: aload_0
      71: getfield      #5                  // Field asyncContext:Lio/undertow/servlet/spec/AsyncContextImpl;
      74: invokespecial #318                // Method io/undertow/servlet/spec/AsyncContextImpl."<init>":(Lio/undertow/server/HttpServerExchange;Ljakarta/servlet/ServletRequest;Ljakarta/servlet/ServletResponse;Lio/undertow/servlet/handlers/ServletRequestContext;ZLio/undertow/servlet/spec/AsyncContextImpl;)V
      77: dup_x1
      78: putfield      #5                  // Field asyncContext:Lio/undertow/servlet/spec/AsyncContextImpl;
      81: areturn

  public jakarta.servlet.AsyncContext startAsync(jakarta.servlet.ServletRequest, jakarta.servlet.ServletResponse) throws java.lang.IllegalStateException;
    Code:
       0: aload_0
       1: getfield      #6                  // Field exchange:Lio/undertow/server/HttpServerExchange;
       4: getstatic     #58                 // Field io/undertow/servlet/handlers/ServletRequestContext.ATTACHMENT_KEY:Lio/undertow/util/AttachmentKey;
       7: invokevirtual #59                 // Method io/undertow/server/HttpServerExchange.getAttachment:(Lio/undertow/util/AttachmentKey;)Ljava/lang/Object;
      10: checkcast     #60                 // class io/undertow/servlet/handlers/ServletRequestContext
      13: astore_3
      14: aload_0
      15: getfield      #7                  // Field servletContext:Lio/undertow/servlet/spec/ServletContextImpl;
      18: invokevirtual #105                // Method io/undertow/servlet/spec/ServletContextImpl.getDeployment:()Lio/undertow/servlet/api/Deployment;
      21: invokeinterface #101,  1          // InterfaceMethod io/undertow/servlet/api/Deployment.getDeploymentInfo:()Lio/undertow/servlet/api/DeploymentInfo;
      26: invokevirtual #319                // Method io/undertow/servlet/api/DeploymentInfo.isAllowNonStandardWrappers:()Z
      29: ifne          82
      32: aload_3
      33: invokevirtual #320                // Method io/undertow/servlet/handlers/ServletRequestContext.getOriginalRequest:()Lio/undertow/servlet/spec/HttpServletRequestImpl;
      36: aload_1
      37: if_acmpeq     57
      40: aload_1
      41: instanceof    #321                // class jakarta/servlet/ServletRequestWrapper
      44: ifne          57
      47: getstatic     #41                 // Field io/undertow/servlet/UndertowServletMessages.MESSAGES:Lio/undertow/servlet/UndertowServletMessages;
      50: aload_1
      51: invokeinterface #322,  2          // InterfaceMethod io/undertow/servlet/UndertowServletMessages.requestWasNotOriginalOrWrapper:(Ljakarta/servlet/ServletRequest;)Ljava/lang/IllegalArgumentException;
      56: athrow
      57: aload_3
      58: invokevirtual #323                // Method io/undertow/servlet/handlers/ServletRequestContext.getOriginalResponse:()Lio/undertow/servlet/spec/HttpServletResponseImpl;
      61: aload_2
      62: if_acmpeq     82
      65: aload_2
      66: instanceof    #324                // class jakarta/servlet/ServletResponseWrapper
      69: ifne          82
      72: getstatic     #41                 // Field io/undertow/servlet/UndertowServletMessages.MESSAGES:Lio/undertow/servlet/UndertowServletMessages;
      75: aload_2
      76: invokeinterface #325,  2          // InterfaceMethod io/undertow/servlet/UndertowServletMessages.responseWasNotOriginalOrWrapper:(Ljakarta/servlet/ServletResponse;)Ljava/lang/IllegalArgumentException;
      81: athrow
      82: aload_0
      83: invokevirtual #313                // Method isAsyncSupported:()Z
      86: ifne          98
      89: getstatic     #41                 // Field io/undertow/servlet/UndertowServletMessages.MESSAGES:Lio/undertow/servlet/UndertowServletMessages;
      92: invokeinterface #314,  1          // InterfaceMethod io/undertow/servlet/UndertowServletMessages.startAsyncNotAllowed:()Ljava/lang/IllegalStateException;
      97: athrow
      98: aload_0
      99: getfield      #4                  // Field asyncStarted:Z
     102: ifeq          114
     105: getstatic     #41                 // Field io/undertow/servlet/UndertowServletMessages.MESSAGES:Lio/undertow/servlet/UndertowServletMessages;
     108: invokeinterface #315,  1          // InterfaceMethod io/undertow/servlet/UndertowServletMessages.asyncAlreadyStarted:()Ljava/lang/IllegalStateException;
     113: athrow
     114: aload_0
     115: iconst_1
     116: putfield      #4                  // Field asyncStarted:Z
     119: aload_3
     120: aload_1
     121: invokevirtual #326                // Method io/undertow/servlet/handlers/ServletRequestContext.setServletRequest:(Ljakarta/servlet/ServletRequest;)V
     124: aload_3
     125: aload_2
     126: invokevirtual #327                // Method io/undertow/servlet/handlers/ServletRequestContext.setServletResponse:(Ljakarta/servlet/ServletResponse;)V
     129: aload_0
     130: new           #316                // class io/undertow/servlet/spec/AsyncContextImpl
     133: dup
     134: aload_0
     135: getfield      #6                  // Field exchange:Lio/undertow/server/HttpServerExchange;
     138: aload_1
     139: aload_2
     140: aload_3
     141: iconst_1
     142: aload_0
     143: getfield      #5                  // Field asyncContext:Lio/undertow/servlet/spec/AsyncContextImpl;
     146: invokespecial #318                // Method io/undertow/servlet/spec/AsyncContextImpl."<init>":(Lio/undertow/server/HttpServerExchange;Ljakarta/servlet/ServletRequest;Ljakarta/servlet/ServletResponse;Lio/undertow/servlet/handlers/ServletRequestContext;ZLio/undertow/servlet/spec/AsyncContextImpl;)V
     149: dup_x1
     150: putfield      #5                  // Field asyncContext:Lio/undertow/servlet/spec/AsyncContextImpl;
     153: areturn

  public boolean isAsyncStarted();
    Code:
       0: aload_0
       1: getfield      #4                  // Field asyncStarted:Z
       4: ireturn

  public boolean isAsyncSupported();
    Code:
       0: aload_0
       1: getfield      #6                  // Field exchange:Lio/undertow/server/HttpServerExchange;
       4: getstatic     #58                 // Field io/undertow/servlet/handlers/ServletRequestContext.ATTACHMENT_KEY:Lio/undertow/util/AttachmentKey;
       7: invokevirtual #59                 // Method io/undertow/server/HttpServerExchange.getAttachment:(Lio/undertow/util/AttachmentKey;)Ljava/lang/Object;
      10: checkcast     #60                 // class io/undertow/servlet/handlers/ServletRequestContext
      13: invokevirtual #328                // Method io/undertow/servlet/handlers/ServletRequestContext.isAsyncSupported:()Z
      16: ireturn

  public io.undertow.servlet.spec.AsyncContextImpl getAsyncContext();
    Code:
       0: aload_0
       1: invokevirtual #329                // Method isAsyncStarted:()Z
       4: ifne          16
       7: getstatic     #41                 // Field io/undertow/servlet/UndertowServletMessages.MESSAGES:Lio/undertow/servlet/UndertowServletMessages;
      10: invokeinterface #330,  1          // InterfaceMethod io/undertow/servlet/UndertowServletMessages.asyncNotStarted:()Ljava/lang/IllegalStateException;
      15: athrow
      16: aload_0
      17: getfield      #5                  // Field asyncContext:Lio/undertow/servlet/spec/AsyncContextImpl;
      20: areturn

  public io.undertow.servlet.spec.AsyncContextImpl getAsyncContextInternal();
    Code:
       0: aload_0
       1: getfield      #5                  // Field asyncContext:Lio/undertow/servlet/spec/AsyncContextImpl;
       4: areturn

  public jakarta.servlet.DispatcherType getDispatcherType();
    Code:
       0: aload_0
       1: getfield      #6                  // Field exchange:Lio/undertow/server/HttpServerExchange;
       4: getstatic     #58                 // Field io/undertow/servlet/handlers/ServletRequestContext.ATTACHMENT_KEY:Lio/undertow/util/AttachmentKey;
       7: invokevirtual #59                 // Method io/undertow/server/HttpServerExchange.getAttachment:(Lio/undertow/util/AttachmentKey;)Ljava/lang/Object;
      10: checkcast     #60                 // class io/undertow/servlet/handlers/ServletRequestContext
      13: invokevirtual #331                // Method io/undertow/servlet/handlers/ServletRequestContext.getDispatcherType:()Ljakarta/servlet/DispatcherType;
      16: areturn

  public java.util.Map<java.lang.String, java.util.Deque<java.lang.String>> getQueryParameters();
    Code:
       0: aload_0
       1: getfield      #241                // Field queryParameters:Ljava/util/Map;
       4: ifnonnull     18
       7: aload_0
       8: aload_0
       9: getfield      #6                  // Field exchange:Lio/undertow/server/HttpServerExchange;
      12: invokevirtual #242                // Method io/undertow/server/HttpServerExchange.getQueryParameters:()Ljava/util/Map;
      15: putfield      #241                // Field queryParameters:Ljava/util/Map;
      18: aload_0
      19: getfield      #241                // Field queryParameters:Ljava/util/Map;
      22: areturn

  public void setQueryParameters(java.util.Map<java.lang.String, java.util.Deque<java.lang.String>>);
    Code:
       0: aload_0
       1: aload_1
       2: putfield      #241                // Field queryParameters:Ljava/util/Map;
       5: return

  public void setServletContext(io.undertow.servlet.spec.ServletContextImpl);
    Code:
       0: aload_0
       1: aload_1
       2: putfield      #7                  // Field servletContext:Lio/undertow/servlet/spec/ServletContextImpl;
       5: return

  void asyncRequestDispatched();
    Code:
       0: aload_0
       1: iconst_0
       2: putfield      #4                  // Field asyncStarted:Z
       5: return

  public java.lang.String getOriginalRequestURI();
    Code:
       0: aload_0
       1: ldc_w         #333                // String jakarta.servlet.forward.request_uri
       4: invokevirtual #334                // Method getAttribute:(Ljava/lang/String;)Ljava/lang/Object;
       7: checkcast     #113                // class java/lang/String
      10: astore_1
      11: aload_1
      12: ifnull        17
      15: aload_1
      16: areturn
      17: aload_0
      18: ldc_w         #336                // String jakarta.servlet.async.request_uri
      21: invokevirtual #334                // Method getAttribute:(Ljava/lang/String;)Ljava/lang/Object;
      24: checkcast     #113                // class java/lang/String
      27: astore_1
      28: aload_1
      29: ifnull        34
      32: aload_1
      33: areturn
      34: aload_0
      35: invokevirtual #337                // Method getRequestURI:()Ljava/lang/String;
      38: areturn

  public java.lang.String getOriginalServletPath();
    Code:
       0: aload_0
       1: ldc_w         #338                // String jakarta.servlet.forward.servlet_path
       4: invokevirtual #334                // Method getAttribute:(Ljava/lang/String;)Ljava/lang/Object;
       7: checkcast     #113                // class java/lang/String
      10: astore_1
      11: aload_1
      12: ifnull        17
      15: aload_1
      16: areturn
      17: aload_0
      18: ldc_w         #339                // String jakarta.servlet.async.servlet_path
      21: invokevirtual #334                // Method getAttribute:(Ljava/lang/String;)Ljava/lang/Object;
      24: checkcast     #113                // class java/lang/String
      27: astore_1
      28: aload_1
      29: ifnull        34
      32: aload_1
      33: areturn
      34: aload_0
      35: invokevirtual #340                // Method getServletPath:()Ljava/lang/String;
      38: areturn

  public java.lang.String getOriginalPathInfo();
    Code:
       0: aload_0
       1: ldc_w         #341                // String jakarta.servlet.forward.path_info
       4: invokevirtual #334                // Method getAttribute:(Ljava/lang/String;)Ljava/lang/Object;
       7: checkcast     #113                // class java/lang/String
      10: astore_1
      11: aload_1
      12: ifnull        17
      15: aload_1
      16: areturn
      17: aload_0
      18: ldc_w         #342                // String jakarta.servlet.async.path_info
      21: invokevirtual #334                // Method getAttribute:(Ljava/lang/String;)Ljava/lang/Object;
      24: checkcast     #113                // class java/lang/String
      27: astore_1
      28: aload_1
      29: ifnull        34
      32: aload_1
      33: areturn
      34: aload_0
      35: invokevirtual #89                 // Method getPathInfo:()Ljava/lang/String;
      38: areturn

  public java.lang.String getOriginalContextPath();
    Code:
       0: aload_0
       1: ldc_w         #343                // String jakarta.servlet.forward.context_path
       4: invokevirtual #334                // Method getAttribute:(Ljava/lang/String;)Ljava/lang/Object;
       7: checkcast     #113                // class java/lang/String
      10: astore_1
      11: aload_1
      12: ifnull        17
      15: aload_1
      16: areturn
      17: aload_0
      18: ldc_w         #344                // String jakarta.servlet.async.context_path
      21: invokevirtual #334                // Method getAttribute:(Ljava/lang/String;)Ljava/lang/Object;
      24: checkcast     #113                // class java/lang/String
      27: astore_1
      28: aload_1
      29: ifnull        34
      32: aload_1
      33: areturn
      34: aload_0
      35: invokevirtual #345                // Method getContextPath:()Ljava/lang/String;
      38: areturn

  public java.lang.String getOriginalQueryString();
    Code:
       0: aload_0
       1: ldc_w         #346                // String jakarta.servlet.forward.query_string
       4: invokevirtual #334                // Method getAttribute:(Ljava/lang/String;)Ljava/lang/Object;
       7: checkcast     #113                // class java/lang/String
      10: astore_1
      11: aload_1
      12: ifnull        17
      15: aload_1
      16: areturn
      17: aload_0
      18: ldc_w         #347                // String jakarta.servlet.async.query_string
      21: invokevirtual #334                // Method getAttribute:(Ljava/lang/String;)Ljava/lang/Object;
      24: checkcast     #113                // class java/lang/String
      27: astore_1
      28: aload_1
      29: ifnull        34
      32: aload_1
      33: areturn
      34: aload_0
      35: invokevirtual #348                // Method getQueryString:()Ljava/lang/String;
      38: areturn

  private io.undertow.server.session.SessionConfig$SessionCookieSource sessionCookieSource();
    Code:
       0: aload_0
       1: iconst_0
       2: invokevirtual #152                // Method getSession:(Z)Ljakarta/servlet/http/HttpSession;
       5: astore_1
       6: aload_1
       7: ifnonnull     14
      10: getstatic     #349                // Field io/undertow/server/session/SessionConfig$SessionCookieSource.NONE:Lio/undertow/server/session/SessionConfig$SessionCookieSource;
      13: areturn
      14: aload_0
      15: getfield      #350                // Field sessionCookieSource:Lio/undertow/server/session/SessionConfig$SessionCookieSource;
      18: ifnonnull     41
      21: aload_0
      22: aload_0
      23: getfield      #8                  // Field originalServletContext:Lio/undertow/servlet/spec/ServletContextImpl;
      26: invokevirtual #114                // Method io/undertow/servlet/spec/ServletContextImpl.getSessionConfig:()Lio/undertow/server/session/SessionConfig;
      29: aload_0
      30: getfield      #6                  // Field exchange:Lio/undertow/server/HttpServerExchange;
      33: invokeinterface #351,  2          // InterfaceMethod io/undertow/server/session/SessionConfig.sessionCookieSource:(Lio/undertow/server/HttpServerExchange;)Lio/undertow/server/session/SessionConfig$SessionCookieSource;
      38: putfield      #350                // Field sessionCookieSource:Lio/undertow/server/session/SessionConfig$SessionCookieSource;
      41: aload_0
      42: getfield      #350                // Field sessionCookieSource:Lio/undertow/server/session/SessionConfig$SessionCookieSource;
      45: areturn

  public java.lang.String toString();
    Code:
       0: aload_0
       1: invokevirtual #352                // Method getMethod:()Ljava/lang/String;
       4: aload_0
       5: invokevirtual #337                // Method getRequestURI:()Ljava/lang/String;
       8: invokedynamic #353,  0            // InvokeDynamic #1:makeConcatWithConstants:(Ljava/lang/String;Ljava/lang/String;)Ljava/lang/String;
      13: areturn

  public void clearAttributes();
    Code:
       0: aload_0
       1: getfield      #2                  // Field attributes:Ljava/util/Map;
       4: ifnull        16
       7: aload_0
       8: getfield      #2                  // Field attributes:Ljava/util/Map;
      11: invokeinterface #354,  1          // InterfaceMethod java/util/Map.clear:()V
      16: return

  public jakarta.servlet.http.PushBuilder newPushBuilder();
    Code:
       0: aload_0
       1: getfield      #6                  // Field exchange:Lio/undertow/server/HttpServerExchange;
       4: invokevirtual #138                // Method io/undertow/server/HttpServerExchange.getConnection:()Lio/undertow/server/ServerConnection;
       7: invokevirtual #355                // Method io/undertow/server/ServerConnection.isPushSupported:()Z
      10: ifeq          22
      13: new           #356                // class io/undertow/servlet/spec/PushBuilderImpl
      16: dup
      17: aload_0
      18: invokespecial #357                // Method io/undertow/servlet/spec/PushBuilderImpl."<init>":(Lio/undertow/servlet/spec/HttpServletRequestImpl;)V
      21: areturn
      22: aconst_null
      23: areturn

  public java.util.Map<java.lang.String, java.lang.String> getTrailerFields();
    Code:
       0: aload_0
       1: getfield      #6                  // Field exchange:Lio/undertow/server/HttpServerExchange;
       4: getstatic     #358                // Field io/undertow/server/protocol/http/HttpAttachments.REQUEST_TRAILERS:Lio/undertow/util/AttachmentKey;
       7: invokevirtual #59                 // Method io/undertow/server/HttpServerExchange.getAttachment:(Lio/undertow/util/AttachmentKey;)Ljava/lang/Object;
      10: checkcast     #359                // class io/undertow/util/HeaderMap
      13: astore_1
      14: aload_1
      15: ifnonnull     22
      18: invokestatic  #360                // Method java/util/Collections.emptyMap:()Ljava/util/Map;
      21: areturn
      22: new           #253                // class java/util/HashMap
      25: dup
      26: invokespecial #254                // Method java/util/HashMap."<init>":()V
      29: astore_2
      30: aload_1
      31: invokevirtual #361                // Method io/undertow/util/HeaderMap.iterator:()Ljava/util/Iterator;
      34: astore_3
      35: aload_3
      36: invokeinterface #14,  1           // InterfaceMethod java/util/Iterator.hasNext:()Z
      41: ifeq          84
      44: aload_3
      45: invokeinterface #15,  1           // InterfaceMethod java/util/Iterator.next:()Ljava/lang/Object;
      50: checkcast     #362                // class io/undertow/util/HeaderValues
      53: astore        4
      55: aload_2
      56: aload         4
      58: invokevirtual #363                // Method io/undertow/util/HeaderValues.getHeaderName:()Lio/undertow/util/HttpString;
      61: invokevirtual #55                 // Method io/undertow/util/HttpString.toString:()Ljava/lang/String;
      64: getstatic     #364                // Field java/util/Locale.ENGLISH:Ljava/util/Locale;
      67: invokevirtual #365                // Method java/lang/String.toLowerCase:(Ljava/util/Locale;)Ljava/lang/String;
      70: aload         4
      72: invokevirtual #366                // Method io/undertow/util/HeaderValues.getFirst:()Ljava/lang/String;
      75: invokeinterface #261,  3          // InterfaceMethod java/util/Map.put:(Ljava/lang/Object;Ljava/lang/Object;)Ljava/lang/Object;
      80: pop
      81: goto          35
      84: aload_2
      85: areturn

  public boolean isTrailerFieldsReady();
    Code:
       0: aload_0
       1: getfield      #6                  // Field exchange:Lio/undertow/server/HttpServerExchange;
       4: invokevirtual #367                // Method io/undertow/server/HttpServerExchange.isRequestComplete:()Z
       7: ifeq          12
      10: iconst_1
      11: ireturn
      12: aload_0
      13: getfield      #6                  // Field exchange:Lio/undertow/server/HttpServerExchange;
      16: invokevirtual #138                // Method io/undertow/server/HttpServerExchange.getConnection:()Lio/undertow/server/ServerConnection;
      19: invokevirtual #368                // Method io/undertow/server/ServerConnection.isRequestTrailerFieldsSupported:()Z
      22: ifne          29
      25: iconst_1
      26: goto          30
      29: iconst_0
      30: ireturn

  public jakarta.servlet.AsyncContext getAsyncContext();
    Code:
       0: aload_0
       1: invokevirtual #369                // Method getAsyncContext:()Lio/undertow/servlet/spec/AsyncContextImpl;
       4: areturn

  public jakarta.servlet.ServletContext getServletContext();
    Code:
       0: aload_0
       1: invokevirtual #370                // Method getServletContext:()Lio/undertow/servlet/spec/ServletContextImpl;
       4: areturn

  static {};
    Code:
       0: getstatic     #371                // Field io/undertow/server/HttpServerExchange.SECURE_REQUEST:Lio/undertow/util/AttachmentKey;
       3: putstatic     #372                // Field SECURE_REQUEST:Lio/undertow/util/AttachmentKey;
       6: ldc           #110                // class java/lang/Boolean
       8: invokestatic  #373                // Method io/undertow/util/AttachmentKey.create:(Ljava/lang/Class;)Lio/undertow/util/AttachmentKey;
      11: putstatic     #109                // Field REQUESTED_SESSION_ID_SET:Lio/undertow/util/AttachmentKey;
      14: ldc           #113                // class java/lang/String
      16: invokestatic  #373                // Method io/undertow/util/AttachmentKey.create:(Ljava/lang/Class;)Lio/undertow/util/AttachmentKey;
      19: putstatic     #112                // Field REQUESTED_SESSION_ID:Lio/undertow/util/AttachmentKey;
      22: return
}
