Compiled from "HtmlNumber.java"
class de.larmic.butterfaces.component.html.text.HtmlNumber$1 implements javax.faces.validator.Validator {
  final de.larmic.butterfaces.component.html.text.HtmlNumber this$0;

  de.larmic.butterfaces.component.html.text.HtmlNumber$1(de.larmic.butterfaces.component.html.text.HtmlNumber);
    Code:
       0: aload_0
       1: aload_1
       2: putfield      #1                  // Field this$0:Lde/larmic/butterfaces/component/html/text/HtmlNumber;
       5: aload_0
       6: invokespecial #2                  // Method java/lang/Object."<init>":()V
       9: return

  public void validate(javax.faces.context.FacesContext, javax.faces.component.UIComponent, java.lang.Object) throws javax.faces.validator.ValidatorException;
    Code:
       0: aload_3
       1: invokevirtual #3                  // Method java/lang/Object.toString:()Ljava/lang/String;
       4: invokestatic  #4                  // Method java/lang/Long.parseLong:(Ljava/lang/String;)J
       7: lstore        4
       9: aload_0
      10: getfield      #1                  // Field this$0:Lde/larmic/butterfaces/component/html/text/HtmlNumber;
      13: invokevirtual #5                  // Method de/larmic/butterfaces/component/html/text/HtmlNumber.getMin:()Ljava/lang/String;
      16: ifnull        84
      19: ldc           #6                  // String
      21: aload_0
      22: getfield      #1                  // Field this$0:Lde/larmic/butterfaces/component/html/text/HtmlNumber;
      25: invokevirtual #5                  // Method de/larmic/butterfaces/component/html/text/HtmlNumber.getMin:()Ljava/lang/String;
      28: invokevirtual #7                  // Method java/lang/String.equals:(Ljava/lang/Object;)Z
      31: ifne          84
      34: lload         4
      36: aload_0
      37: getfield      #1                  // Field this$0:Lde/larmic/butterfaces/component/html/text/HtmlNumber;
      40: invokevirtual #5                  // Method de/larmic/butterfaces/component/html/text/HtmlNumber.getMin:()Ljava/lang/String;
      43: invokestatic  #8                  // Method java/lang/Integer.valueOf:(Ljava/lang/String;)Ljava/lang/Integer;
      46: invokevirtual #9                  // Method java/lang/Integer.intValue:()I
      49: i2l
      50: lcmp
      51: ifge          84
      54: new           #10                 // class javax/faces/validator/ValidatorException
      57: dup
      58: new           #11                 // class javax/faces/application/FacesMessage
      61: dup
      62: ldc           #12                 // String Number is to small
      64: ldc           #13                 // String %s is to small
      66: iconst_1
      67: anewarray     #14                 // class java/lang/Object
      70: dup
      71: iconst_0
      72: aload_3
      73: aastore
      74: invokestatic  #15                 // Method java/lang/String.format:(Ljava/lang/String;[Ljava/lang/Object;)Ljava/lang/String;
      77: invokespecial #16                 // Method javax/faces/application/FacesMessage."<init>":(Ljava/lang/String;Ljava/lang/String;)V
      80: invokespecial #17                 // Method javax/faces/validator/ValidatorException."<init>":(Ljavax/faces/application/FacesMessage;)V
      83: athrow
      84: aload_0
      85: getfield      #1                  // Field this$0:Lde/larmic/butterfaces/component/html/text/HtmlNumber;
      88: invokevirtual #18                 // Method de/larmic/butterfaces/component/html/text/HtmlNumber.getMax:()Ljava/lang/String;
      91: ifnull        159
      94: ldc           #6                  // String
      96: aload_0
      97: getfield      #1                  // Field this$0:Lde/larmic/butterfaces/component/html/text/HtmlNumber;
     100: invokevirtual #18                 // Method de/larmic/butterfaces/component/html/text/HtmlNumber.getMax:()Ljava/lang/String;
     103: invokevirtual #7                  // Method java/lang/String.equals:(Ljava/lang/Object;)Z
     106: ifne          159
     109: lload         4
     111: aload_0
     112: getfield      #1                  // Field this$0:Lde/larmic/butterfaces/component/html/text/HtmlNumber;
     115: invokevirtual #18                 // Method de/larmic/butterfaces/component/html/text/HtmlNumber.getMax:()Ljava/lang/String;
     118: invokestatic  #8                  // Method java/lang/Integer.valueOf:(Ljava/lang/String;)Ljava/lang/Integer;
     121: invokevirtual #9                  // Method java/lang/Integer.intValue:()I
     124: i2l
     125: lcmp
     126: ifle          159
     129: new           #10                 // class javax/faces/validator/ValidatorException
     132: dup
     133: new           #11                 // class javax/faces/application/FacesMessage
     136: dup
     137: ldc           #19                 // String Number is to big
     139: ldc           #20                 // String %s is to big
     141: iconst_1
     142: anewarray     #14                 // class java/lang/Object
     145: dup
     146: iconst_0
     147: aload_3
     148: aastore
     149: invokestatic  #15                 // Method java/lang/String.format:(Ljava/lang/String;[Ljava/lang/Object;)Ljava/lang/String;
     152: invokespecial #16                 // Method javax/faces/application/FacesMessage."<init>":(Ljava/lang/String;Ljava/lang/String;)V
     155: invokespecial #17                 // Method javax/faces/validator/ValidatorException."<init>":(Ljavax/faces/application/FacesMessage;)V
     158: athrow
     159: goto          194
     162: astore        4
     164: new           #10                 // class javax/faces/validator/ValidatorException
     167: dup
     168: new           #11                 // class javax/faces/application/FacesMessage
     171: dup
     172: ldc           #22                 // String No number
     174: ldc           #23                 // String %s is no number
     176: iconst_1
     177: anewarray     #14                 // class java/lang/Object
     180: dup
     181: iconst_0
     182: aload_3
     183: aastore
     184: invokestatic  #15                 // Method java/lang/String.format:(Ljava/lang/String;[Ljava/lang/Object;)Ljava/lang/String;
     187: invokespecial #16                 // Method javax/faces/application/FacesMessage."<init>":(Ljava/lang/String;Ljava/lang/String;)V
     190: invokespecial #17                 // Method javax/faces/validator/ValidatorException."<init>":(Ljavax/faces/application/FacesMessage;)V
     193: athrow
     194: return
    Exception table:
       from    to  target type
           0   159   162   Class java/lang/NumberFormatException
}
