Compiled from "Converter.java"
public interface org.apache.kafka.connect.storage.Converter {
  public abstract void configure(java.util.Map<java.lang.String, ?>, boolean);

  public abstract byte[] fromConnectData(java.lang.String, org.apache.kafka.connect.data.Schema, java.lang.Object);

  public default byte[] fromConnectData(java.lang.String, org.apache.kafka.common.header.Headers, org.apache.kafka.connect.data.Schema, java.lang.Object);
    Code:
       0: aload_0
       1: aload_1
       2: aload_3
       3: aload         4
       5: invokeinterface #1,  4            // InterfaceMethod fromConnectData:(Ljava/lang/String;Lorg/apache/kafka/connect/data/Schema;Ljava/lang/Object;)[B
      10: areturn

  public abstract org.apache.kafka.connect.data.SchemaAndValue toConnectData(java.lang.String, byte[]);

  public default org.apache.kafka.connect.data.SchemaAndValue toConnectData(java.lang.String, org.apache.kafka.common.header.Headers, byte[]);
    Code:
       0: aload_0
       1: aload_1
       2: aload_3
       3: invokeinterface #2,  3            // InterfaceMethod toConnectData:(Ljava/lang/String;[B)Lorg/apache/kafka/connect/data/SchemaAndValue;
       8: areturn
}
