Compiled from "DefaultNioDatagramChannelConfig.java"
class org.jboss.netty.channel.socket.nio.DefaultNioDatagramChannelConfig extends org.jboss.netty.channel.socket.DefaultDatagramChannelConfig implements org.jboss.netty.channel.socket.nio.NioDatagramChannelConfig {
  private static final org.jboss.netty.logging.InternalLogger logger;

  private volatile int writeBufferHighWaterMark;

  private volatile int writeBufferLowWaterMark;

  private volatile int writeSpinCount;

  private final java.nio.channels.DatagramChannel channel;

  org.jboss.netty.channel.socket.nio.DefaultNioDatagramChannelConfig(java.nio.channels.DatagramChannel);
    Code:
       0: aload_0
       1: aload_1
       2: invokevirtual #1                  // Method java/nio/channels/DatagramChannel.socket:()Ljava/net/DatagramSocket;
       5: invokespecial #2                  // Method org/jboss/netty/channel/socket/DefaultDatagramChannelConfig."<init>":(Ljava/net/DatagramSocket;)V
       8: aload_0
       9: ldc           #3                  // int 65536
      11: putfield      #4                  // Field writeBufferHighWaterMark:I
      14: aload_0
      15: ldc           #5                  // int 32768
      17: putfield      #6                  // Field writeBufferLowWaterMark:I
      20: aload_0
      21: bipush        16
      23: putfield      #7                  // Field writeSpinCount:I
      26: aload_0
      27: aload_1
      28: putfield      #8                  // Field channel:Ljava/nio/channels/DatagramChannel;
      31: return

  public void setOptions(java.util.Map<java.lang.String, java.lang.Object>);
    Code:
       0: aload_0
       1: aload_1
       2: invokespecial #9                  // Method org/jboss/netty/channel/socket/DefaultDatagramChannelConfig.setOptions:(Ljava/util/Map;)V
       5: aload_0
       6: invokevirtual #10                 // Method getWriteBufferHighWaterMark:()I
       9: aload_0
      10: invokevirtual #11                 // Method getWriteBufferLowWaterMark:()I
      13: if_icmpge     47
      16: aload_0
      17: aload_0
      18: invokevirtual #10                 // Method getWriteBufferHighWaterMark:()I
      21: iconst_1
      22: iushr
      23: invokespecial #12                 // Method setWriteBufferLowWaterMark0:(I)V
      26: getstatic     #13                 // Field logger:Lorg/jboss/netty/logging/InternalLogger;
      29: invokeinterface #14,  1           // InterfaceMethod org/jboss/netty/logging/InternalLogger.isWarnEnabled:()Z
      34: ifeq          47
      37: getstatic     #13                 // Field logger:Lorg/jboss/netty/logging/InternalLogger;
      40: ldc           #15                 // String writeBufferLowWaterMark cannot be greater than writeBufferHighWaterMark; setting to the half of the writeBufferHighWaterMark.
      42: invokeinterface #16,  2           // InterfaceMethod org/jboss/netty/logging/InternalLogger.warn:(Ljava/lang/String;)V
      47: return

  public boolean setOption(java.lang.String, java.lang.Object);
    Code:
       0: aload_0
       1: aload_1
       2: aload_2
       3: invokespecial #17                 // Method org/jboss/netty/channel/socket/DefaultDatagramChannelConfig.setOption:(Ljava/lang/String;Ljava/lang/Object;)Z
       6: ifeq          11
       9: iconst_1
      10: ireturn
      11: ldc           #18                 // String writeBufferHighWaterMark
      13: aload_1
      14: invokevirtual #19                 // Method java/lang/String.equals:(Ljava/lang/Object;)Z
      17: ifeq          31
      20: aload_0
      21: aload_2
      22: invokestatic  #20                 // Method org/jboss/netty/util/internal/ConversionUtil.toInt:(Ljava/lang/Object;)I
      25: invokespecial #21                 // Method setWriteBufferHighWaterMark0:(I)V
      28: goto          73
      31: ldc           #22                 // String writeBufferLowWaterMark
      33: aload_1
      34: invokevirtual #19                 // Method java/lang/String.equals:(Ljava/lang/Object;)Z
      37: ifeq          51
      40: aload_0
      41: aload_2
      42: invokestatic  #20                 // Method org/jboss/netty/util/internal/ConversionUtil.toInt:(Ljava/lang/Object;)I
      45: invokespecial #12                 // Method setWriteBufferLowWaterMark0:(I)V
      48: goto          73
      51: ldc           #23                 // String writeSpinCount
      53: aload_1
      54: invokevirtual #19                 // Method java/lang/String.equals:(Ljava/lang/Object;)Z
      57: ifeq          71
      60: aload_0
      61: aload_2
      62: invokestatic  #20                 // Method org/jboss/netty/util/internal/ConversionUtil.toInt:(Ljava/lang/Object;)I
      65: invokevirtual #24                 // Method setWriteSpinCount:(I)V
      68: goto          73
      71: iconst_0
      72: ireturn
      73: iconst_1
      74: ireturn

  public int getWriteBufferHighWaterMark();
    Code:
       0: aload_0
       1: getfield      #4                  // Field writeBufferHighWaterMark:I
       4: ireturn

  public void setWriteBufferHighWaterMark(int);
    Code:
       0: iload_1
       1: aload_0
       2: invokevirtual #11                 // Method getWriteBufferLowWaterMark:()I
       5: if_icmpge     47
       8: new           #25                 // class java/lang/IllegalArgumentException
      11: dup
      12: new           #26                 // class java/lang/StringBuilder
      15: dup
      16: invokespecial #27                 // Method java/lang/StringBuilder."<init>":()V
      19: ldc           #28                 // String writeBufferHighWaterMark cannot be less than writeBufferLowWaterMark (
      21: invokevirtual #29                 // Method java/lang/StringBuilder.append:(Ljava/lang/String;)Ljava/lang/StringBuilder;
      24: aload_0
      25: invokevirtual #11                 // Method getWriteBufferLowWaterMark:()I
      28: invokevirtual #30                 // Method java/lang/StringBuilder.append:(I)Ljava/lang/StringBuilder;
      31: ldc           #31                 // String ):
      33: invokevirtual #29                 // Method java/lang/StringBuilder.append:(Ljava/lang/String;)Ljava/lang/StringBuilder;
      36: iload_1
      37: invokevirtual #30                 // Method java/lang/StringBuilder.append:(I)Ljava/lang/StringBuilder;
      40: invokevirtual #32                 // Method java/lang/StringBuilder.toString:()Ljava/lang/String;
      43: invokespecial #33                 // Method java/lang/IllegalArgumentException."<init>":(Ljava/lang/String;)V
      46: athrow
      47: aload_0
      48: iload_1
      49: invokespecial #21                 // Method setWriteBufferHighWaterMark0:(I)V
      52: return

  private void setWriteBufferHighWaterMark0(int);
    Code:
       0: iload_1
       1: ifge          31
       4: new           #25                 // class java/lang/IllegalArgumentException
       7: dup
       8: new           #26                 // class java/lang/StringBuilder
      11: dup
      12: invokespecial #27                 // Method java/lang/StringBuilder."<init>":()V
      15: ldc           #34                 // String writeBufferHighWaterMark:
      17: invokevirtual #29                 // Method java/lang/StringBuilder.append:(Ljava/lang/String;)Ljava/lang/StringBuilder;
      20: iload_1
      21: invokevirtual #30                 // Method java/lang/StringBuilder.append:(I)Ljava/lang/StringBuilder;
      24: invokevirtual #32                 // Method java/lang/StringBuilder.toString:()Ljava/lang/String;
      27: invokespecial #33                 // Method java/lang/IllegalArgumentException."<init>":(Ljava/lang/String;)V
      30: athrow
      31: aload_0
      32: iload_1
      33: putfield      #4                  // Field writeBufferHighWaterMark:I
      36: return

  public int getWriteBufferLowWaterMark();
    Code:
       0: aload_0
       1: getfield      #6                  // Field writeBufferLowWaterMark:I
       4: ireturn

  public void setWriteBufferLowWaterMark(int);
    Code:
       0: iload_1
       1: aload_0
       2: invokevirtual #10                 // Method getWriteBufferHighWaterMark:()I
       5: if_icmple     47
       8: new           #25                 // class java/lang/IllegalArgumentException
      11: dup
      12: new           #26                 // class java/lang/StringBuilder
      15: dup
      16: invokespecial #27                 // Method java/lang/StringBuilder."<init>":()V
      19: ldc           #35                 // String writeBufferLowWaterMark cannot be greater than writeBufferHighWaterMark (
      21: invokevirtual #29                 // Method java/lang/StringBuilder.append:(Ljava/lang/String;)Ljava/lang/StringBuilder;
      24: aload_0
      25: invokevirtual #10                 // Method getWriteBufferHighWaterMark:()I
      28: invokevirtual #30                 // Method java/lang/StringBuilder.append:(I)Ljava/lang/StringBuilder;
      31: ldc           #31                 // String ):
      33: invokevirtual #29                 // Method java/lang/StringBuilder.append:(Ljava/lang/String;)Ljava/lang/StringBuilder;
      36: iload_1
      37: invokevirtual #30                 // Method java/lang/StringBuilder.append:(I)Ljava/lang/StringBuilder;
      40: invokevirtual #32                 // Method java/lang/StringBuilder.toString:()Ljava/lang/String;
      43: invokespecial #33                 // Method java/lang/IllegalArgumentException."<init>":(Ljava/lang/String;)V
      46: athrow
      47: aload_0
      48: iload_1
      49: invokespecial #12                 // Method setWriteBufferLowWaterMark0:(I)V
      52: return

  private void setWriteBufferLowWaterMark0(int);
    Code:
       0: iload_1
       1: ifge          31
       4: new           #25                 // class java/lang/IllegalArgumentException
       7: dup
       8: new           #26                 // class java/lang/StringBuilder
      11: dup
      12: invokespecial #27                 // Method java/lang/StringBuilder."<init>":()V
      15: ldc           #36                 // String writeBufferLowWaterMark:
      17: invokevirtual #29                 // Method java/lang/StringBuilder.append:(Ljava/lang/String;)Ljava/lang/StringBuilder;
      20: iload_1
      21: invokevirtual #30                 // Method java/lang/StringBuilder.append:(I)Ljava/lang/StringBuilder;
      24: invokevirtual #32                 // Method java/lang/StringBuilder.toString:()Ljava/lang/String;
      27: invokespecial #33                 // Method java/lang/IllegalArgumentException."<init>":(Ljava/lang/String;)V
      30: athrow
      31: aload_0
      32: iload_1
      33: putfield      #6                  // Field writeBufferLowWaterMark:I
      36: return

  public int getWriteSpinCount();
    Code:
       0: aload_0
       1: getfield      #7                  // Field writeSpinCount:I
       4: ireturn

  public void setWriteSpinCount(int);
    Code:
       0: iload_1
       1: ifgt          14
       4: new           #25                 // class java/lang/IllegalArgumentException
       7: dup
       8: ldc           #37                 // String writeSpinCount must be a positive integer.
      10: invokespecial #33                 // Method java/lang/IllegalArgumentException."<init>":(Ljava/lang/String;)V
      13: athrow
      14: aload_0
      15: iload_1
      16: putfield      #7                  // Field writeSpinCount:I
      19: return

  public void setNetworkInterface(java.net.NetworkInterface);
    Code:
       0: invokestatic  #38                 // Method org/jboss/netty/util/internal/DetectionUtil.javaVersion:()I
       3: bipush        7
       5: if_icmpge     16
       8: new           #39                 // class java/lang/UnsupportedOperationException
      11: dup
      12: invokespecial #40                 // Method java/lang/UnsupportedOperationException."<init>":()V
      15: athrow
      16: aload_0
      17: getfield      #8                  // Field channel:Ljava/nio/channels/DatagramChannel;
      20: getstatic     #41                 // Field java/net/StandardSocketOptions.IP_MULTICAST_IF:Ljava/net/SocketOption;
      23: aload_1
      24: invokevirtual #42                 // Method java/nio/channels/DatagramChannel.setOption:(Ljava/net/SocketOption;Ljava/lang/Object;)Ljava/nio/channels/DatagramChannel;
      27: pop
      28: goto          41
      31: astore_2
      32: new           #44                 // class org/jboss/netty/channel/ChannelException
      35: dup
      36: aload_2
      37: invokespecial #45                 // Method org/jboss/netty/channel/ChannelException."<init>":(Ljava/lang/Throwable;)V
      40: athrow
      41: return
    Exception table:
       from    to  target type
          16    28    31   Class java/io/IOException

  public java.net.NetworkInterface getNetworkInterface();
    Code:
       0: invokestatic  #38                 // Method org/jboss/netty/util/internal/DetectionUtil.javaVersion:()I
       3: bipush        7
       5: if_icmpge     16
       8: new           #39                 // class java/lang/UnsupportedOperationException
      11: dup
      12: invokespecial #40                 // Method java/lang/UnsupportedOperationException."<init>":()V
      15: athrow
      16: aload_0
      17: getfield      #8                  // Field channel:Ljava/nio/channels/DatagramChannel;
      20: getstatic     #41                 // Field java/net/StandardSocketOptions.IP_MULTICAST_IF:Ljava/net/SocketOption;
      23: invokevirtual #46                 // Method java/nio/channels/DatagramChannel.getOption:(Ljava/net/SocketOption;)Ljava/lang/Object;
      26: checkcast     #47                 // class java/net/NetworkInterface
      29: areturn
      30: astore_1
      31: new           #44                 // class org/jboss/netty/channel/ChannelException
      34: dup
      35: aload_1
      36: invokespecial #45                 // Method org/jboss/netty/channel/ChannelException."<init>":(Ljava/lang/Throwable;)V
      39: athrow
    Exception table:
       from    to  target type
          16    29    30   Class java/io/IOException

  public int getTimeToLive();
    Code:
       0: invokestatic  #38                 // Method org/jboss/netty/util/internal/DetectionUtil.javaVersion:()I
       3: bipush        7
       5: if_icmpge     16
       8: new           #39                 // class java/lang/UnsupportedOperationException
      11: dup
      12: invokespecial #40                 // Method java/lang/UnsupportedOperationException."<init>":()V
      15: athrow
      16: aload_0
      17: getfield      #8                  // Field channel:Ljava/nio/channels/DatagramChannel;
      20: getstatic     #48                 // Field java/net/StandardSocketOptions.IP_MULTICAST_TTL:Ljava/net/SocketOption;
      23: invokevirtual #46                 // Method java/nio/channels/DatagramChannel.getOption:(Ljava/net/SocketOption;)Ljava/lang/Object;
      26: checkcast     #49                 // class java/lang/Integer
      29: invokevirtual #50                 // Method java/lang/Integer.intValue:()I
      32: ireturn
      33: astore_1
      34: new           #44                 // class org/jboss/netty/channel/ChannelException
      37: dup
      38: aload_1
      39: invokespecial #45                 // Method org/jboss/netty/channel/ChannelException."<init>":(Ljava/lang/Throwable;)V
      42: athrow
    Exception table:
       from    to  target type
          16    32    33   Class java/io/IOException

  public void setTimeToLive(int);
    Code:
       0: invokestatic  #38                 // Method org/jboss/netty/util/internal/DetectionUtil.javaVersion:()I
       3: bipush        7
       5: if_icmpge     16
       8: new           #39                 // class java/lang/UnsupportedOperationException
      11: dup
      12: invokespecial #40                 // Method java/lang/UnsupportedOperationException."<init>":()V
      15: athrow
      16: aload_0
      17: getfield      #8                  // Field channel:Ljava/nio/channels/DatagramChannel;
      20: getstatic     #48                 // Field java/net/StandardSocketOptions.IP_MULTICAST_TTL:Ljava/net/SocketOption;
      23: iload_1
      24: invokestatic  #51                 // Method java/lang/Integer.valueOf:(I)Ljava/lang/Integer;
      27: invokevirtual #42                 // Method java/nio/channels/DatagramChannel.setOption:(Ljava/net/SocketOption;Ljava/lang/Object;)Ljava/nio/channels/DatagramChannel;
      30: pop
      31: goto          44
      34: astore_2
      35: new           #44                 // class org/jboss/netty/channel/ChannelException
      38: dup
      39: aload_2
      40: invokespecial #45                 // Method org/jboss/netty/channel/ChannelException."<init>":(Ljava/lang/Throwable;)V
      43: athrow
      44: return
    Exception table:
       from    to  target type
          16    31    34   Class java/io/IOException

  public java.net.InetAddress getInterface();
    Code:
       0: aload_0
       1: invokevirtual #52                 // Method getNetworkInterface:()Ljava/net/NetworkInterface;
       4: astore_1
       5: aload_1
       6: ifnonnull     11
       9: aconst_null
      10: areturn
      11: aload_1
      12: invokevirtual #53                 // Method java/net/NetworkInterface.getInetAddresses:()Ljava/util/Enumeration;
      15: astore_2
      16: aload_2
      17: invokeinterface #54,  1           // InterfaceMethod java/util/Enumeration.hasMoreElements:()Z
      22: ifeq          35
      25: aload_2
      26: invokeinterface #55,  1           // InterfaceMethod java/util/Enumeration.nextElement:()Ljava/lang/Object;
      31: checkcast     #56                 // class java/net/InetAddress
      34: areturn
      35: aconst_null
      36: areturn

  public void setInterface(java.net.InetAddress);
    Code:
       0: aload_0
       1: aload_1
       2: invokestatic  #57                 // Method java/net/NetworkInterface.getByInetAddress:(Ljava/net/InetAddress;)Ljava/net/NetworkInterface;
       5: invokevirtual #58                 // Method setNetworkInterface:(Ljava/net/NetworkInterface;)V
       8: goto          21
      11: astore_2
      12: new           #44                 // class org/jboss/netty/channel/ChannelException
      15: dup
      16: aload_2
      17: invokespecial #45                 // Method org/jboss/netty/channel/ChannelException."<init>":(Ljava/lang/Throwable;)V
      20: athrow
      21: return
    Exception table:
       from    to  target type
           0     8    11   Class java/net/SocketException

  public boolean isLoopbackModeDisabled();
    Code:
       0: invokestatic  #38                 // Method org/jboss/netty/util/internal/DetectionUtil.javaVersion:()I
       3: bipush        7
       5: if_icmpge     16
       8: new           #39                 // class java/lang/UnsupportedOperationException
      11: dup
      12: invokespecial #40                 // Method java/lang/UnsupportedOperationException."<init>":()V
      15: athrow
      16: aload_0
      17: getfield      #8                  // Field channel:Ljava/nio/channels/DatagramChannel;
      20: getstatic     #60                 // Field java/net/StandardSocketOptions.IP_MULTICAST_LOOP:Ljava/net/SocketOption;
      23: invokevirtual #46                 // Method java/nio/channels/DatagramChannel.getOption:(Ljava/net/SocketOption;)Ljava/lang/Object;
      26: checkcast     #61                 // class java/lang/Boolean
      29: invokevirtual #62                 // Method java/lang/Boolean.booleanValue:()Z
      32: ireturn
      33: astore_1
      34: new           #44                 // class org/jboss/netty/channel/ChannelException
      37: dup
      38: aload_1
      39: invokespecial #45                 // Method org/jboss/netty/channel/ChannelException."<init>":(Ljava/lang/Throwable;)V
      42: athrow
    Exception table:
       from    to  target type
          16    32    33   Class java/io/IOException

  public void setLoopbackModeDisabled(boolean);
    Code:
       0: invokestatic  #38                 // Method org/jboss/netty/util/internal/DetectionUtil.javaVersion:()I
       3: bipush        7
       5: if_icmpge     16
       8: new           #39                 // class java/lang/UnsupportedOperationException
      11: dup
      12: invokespecial #40                 // Method java/lang/UnsupportedOperationException."<init>":()V
      15: athrow
      16: aload_0
      17: getfield      #8                  // Field channel:Ljava/nio/channels/DatagramChannel;
      20: getstatic     #60                 // Field java/net/StandardSocketOptions.IP_MULTICAST_LOOP:Ljava/net/SocketOption;
      23: iload_1
      24: invokestatic  #63                 // Method java/lang/Boolean.valueOf:(Z)Ljava/lang/Boolean;
      27: invokevirtual #42                 // Method java/nio/channels/DatagramChannel.setOption:(Ljava/net/SocketOption;Ljava/lang/Object;)Ljava/nio/channels/DatagramChannel;
      30: pop
      31: goto          44
      34: astore_2
      35: new           #44                 // class org/jboss/netty/channel/ChannelException
      38: dup
      39: aload_2
      40: invokespecial #45                 // Method org/jboss/netty/channel/ChannelException."<init>":(Ljava/lang/Throwable;)V
      43: athrow
      44: return
    Exception table:
       from    to  target type
          16    31    34   Class java/io/IOException

  static {};
    Code:
       0: ldc_w         #64                 // class org/jboss/netty/channel/socket/nio/DefaultNioDatagramChannelConfig
       3: invokestatic  #65                 // Method org/jboss/netty/logging/InternalLoggerFactory.getInstance:(Ljava/lang/Class;)Lorg/jboss/netty/logging/InternalLogger;
       6: putstatic     #13                 // Field logger:Lorg/jboss/netty/logging/InternalLogger;
       9: return
}
