Compiled from "NioDatagramChannel.java"
public class org.jboss.netty.channel.socket.nio.NioDatagramChannel extends org.jboss.netty.channel.socket.nio.AbstractNioChannel<java.nio.channels.DatagramChannel> implements org.jboss.netty.channel.socket.DatagramChannel {
  private final org.jboss.netty.channel.socket.nio.NioDatagramChannelConfig config;

  private java.util.Map<java.net.InetAddress, java.util.List<java.nio.channels.MembershipKey>> memberships;

  org.jboss.netty.channel.socket.nio.NioDatagramChannel(org.jboss.netty.channel.ChannelFactory, org.jboss.netty.channel.ChannelPipeline, org.jboss.netty.channel.ChannelSink, org.jboss.netty.channel.socket.nio.NioDatagramWorker, org.jboss.netty.channel.socket.InternetProtocolFamily);
    Code:
       0: aload_0
       1: aconst_null
       2: aload_1
       3: aload_2
       4: aload_3
       5: aload         4
       7: aload         5
       9: invokestatic  #1                  // Method openNonBlockingChannel:(Lorg/jboss/netty/channel/socket/InternetProtocolFamily;)Ljava/nio/channels/DatagramChannel;
      12: invokespecial #2                  // Method org/jboss/netty/channel/socket/nio/AbstractNioChannel."<init>":(Lorg/jboss/netty/channel/Channel;Lorg/jboss/netty/channel/ChannelFactory;Lorg/jboss/netty/channel/ChannelPipeline;Lorg/jboss/netty/channel/ChannelSink;Lorg/jboss/netty/channel/socket/nio/AbstractNioWorker;Ljava/nio/channels/SelectableChannel;)V
      15: aload_0
      16: new           #3                  // class org/jboss/netty/channel/socket/nio/DefaultNioDatagramChannelConfig
      19: dup
      20: aload_0
      21: getfield      #4                  // Field channel:Ljava/nio/channels/SelectableChannel;
      24: checkcast     #5                  // class java/nio/channels/DatagramChannel
      27: invokespecial #6                  // Method org/jboss/netty/channel/socket/nio/DefaultNioDatagramChannelConfig."<init>":(Ljava/nio/channels/DatagramChannel;)V
      30: putfield      #7                  // Field config:Lorg/jboss/netty/channel/socket/nio/NioDatagramChannelConfig;
      33: aload_0
      34: invokestatic  #8                  // Method org/jboss/netty/channel/Channels.fireChannelOpen:(Lorg/jboss/netty/channel/Channel;)V
      37: return

  private static java.nio.channels.DatagramChannel openNonBlockingChannel(org.jboss.netty.channel.socket.InternetProtocolFamily);
    Code:
       0: invokestatic  #9                  // Method org/jboss/netty/util/internal/DetectionUtil.javaVersion:()I
       3: bipush        7
       5: if_icmplt     12
       8: aload_0
       9: ifnonnull     19
      12: invokestatic  #10                 // Method java/nio/channels/DatagramChannel.open:()Ljava/nio/channels/DatagramChannel;
      15: astore_1
      16: goto          82
      19: getstatic     #11                 // Field org/jboss/netty/channel/socket/nio/NioDatagramChannel$1.$SwitchMap$org$jboss$netty$channel$socket$InternetProtocolFamily:[I
      22: aload_0
      23: invokevirtual #12                 // Method org/jboss/netty/channel/socket/InternetProtocolFamily.ordinal:()I
      26: iaload
      27: lookupswitch  { // 2
                     1: 52
                     2: 63
               default: 74
          }
      52: aload_0
      53: invokestatic  #13                 // Method org/jboss/netty/channel/socket/nio/ProtocolFamilyConverter.convert:(Lorg/jboss/netty/channel/socket/InternetProtocolFamily;)Ljava/net/ProtocolFamily;
      56: invokestatic  #14                 // Method java/nio/channels/DatagramChannel.open:(Ljava/net/ProtocolFamily;)Ljava/nio/channels/DatagramChannel;
      59: astore_1
      60: goto          82
      63: aload_0
      64: invokestatic  #13                 // Method org/jboss/netty/channel/socket/nio/ProtocolFamilyConverter.convert:(Lorg/jboss/netty/channel/socket/InternetProtocolFamily;)Ljava/net/ProtocolFamily;
      67: invokestatic  #14                 // Method java/nio/channels/DatagramChannel.open:(Ljava/net/ProtocolFamily;)Ljava/nio/channels/DatagramChannel;
      70: astore_1
      71: goto          82
      74: new           #15                 // class java/lang/IllegalArgumentException
      77: dup
      78: invokespecial #16                 // Method java/lang/IllegalArgumentException."<init>":()V
      81: athrow
      82: aload_1
      83: iconst_0
      84: invokevirtual #17                 // Method java/nio/channels/DatagramChannel.configureBlocking:(Z)Ljava/nio/channels/SelectableChannel;
      87: pop
      88: aload_1
      89: areturn
      90: astore_1
      91: new           #19                 // class org/jboss/netty/channel/ChannelException
      94: dup
      95: ldc           #20                 // String Failed to open a DatagramChannel.
      97: aload_1
      98: invokespecial #21                 // Method org/jboss/netty/channel/ChannelException."<init>":(Ljava/lang/String;Ljava/lang/Throwable;)V
     101: athrow
    Exception table:
       from    to  target type
           0    89    90   Class java/io/IOException

  public org.jboss.netty.channel.socket.nio.NioDatagramWorker getWorker();
    Code:
       0: aload_0
       1: invokespecial #22                 // Method org/jboss/netty/channel/socket/nio/AbstractNioChannel.getWorker:()Lorg/jboss/netty/channel/socket/nio/AbstractNioWorker;
       4: checkcast     #23                 // class org/jboss/netty/channel/socket/nio/NioDatagramWorker
       7: areturn

  public boolean isBound();
    Code:
       0: aload_0
       1: invokevirtual #24                 // Method isOpen:()Z
       4: ifeq          27
       7: aload_0
       8: getfield      #4                  // Field channel:Ljava/nio/channels/SelectableChannel;
      11: checkcast     #5                  // class java/nio/channels/DatagramChannel
      14: invokevirtual #25                 // Method java/nio/channels/DatagramChannel.socket:()Ljava/net/DatagramSocket;
      17: invokevirtual #26                 // Method java/net/DatagramSocket.isBound:()Z
      20: ifeq          27
      23: iconst_1
      24: goto          28
      27: iconst_0
      28: ireturn

  public boolean isConnected();
    Code:
       0: aload_0
       1: getfield      #4                  // Field channel:Ljava/nio/channels/SelectableChannel;
       4: checkcast     #5                  // class java/nio/channels/DatagramChannel
       7: invokevirtual #27                 // Method java/nio/channels/DatagramChannel.isConnected:()Z
      10: ireturn

  protected boolean setClosed();
    Code:
       0: aload_0
       1: invokespecial #28                 // Method org/jboss/netty/channel/socket/nio/AbstractNioChannel.setClosed:()Z
       4: ireturn

  public org.jboss.netty.channel.socket.nio.NioDatagramChannelConfig getConfig();
    Code:
       0: aload_0
       1: getfield      #7                  // Field config:Lorg/jboss/netty/channel/socket/nio/NioDatagramChannelConfig;
       4: areturn

  java.nio.channels.DatagramChannel getDatagramChannel();
    Code:
       0: aload_0
       1: getfield      #4                  // Field channel:Ljava/nio/channels/SelectableChannel;
       4: checkcast     #5                  // class java/nio/channels/DatagramChannel
       7: areturn

  public org.jboss.netty.channel.ChannelFuture joinGroup(java.net.InetAddress);
    Code:
       0: aload_0
       1: aload_1
       2: aload_0
       3: invokevirtual #29                 // Method getLocalAddress:()Ljava/net/InetSocketAddress;
       6: invokevirtual #30                 // Method java/net/InetSocketAddress.getAddress:()Ljava/net/InetAddress;
       9: invokestatic  #31                 // Method java/net/NetworkInterface.getByInetAddress:(Ljava/net/InetAddress;)Ljava/net/NetworkInterface;
      12: aconst_null
      13: invokevirtual #32                 // Method joinGroup:(Ljava/net/InetAddress;Ljava/net/NetworkInterface;Ljava/net/InetAddress;)Lorg/jboss/netty/channel/ChannelFuture;
      16: areturn
      17: astore_2
      18: aload_0
      19: aload_2
      20: invokestatic  #34                 // Method org/jboss/netty/channel/Channels.failedFuture:(Lorg/jboss/netty/channel/Channel;Ljava/lang/Throwable;)Lorg/jboss/netty/channel/ChannelFuture;
      23: areturn
    Exception table:
       from    to  target type
           0    16    17   Class java/net/SocketException

  public org.jboss.netty.channel.ChannelFuture joinGroup(java.net.InetSocketAddress, java.net.NetworkInterface);
    Code:
       0: aload_0
       1: aload_1
       2: invokevirtual #30                 // Method java/net/InetSocketAddress.getAddress:()Ljava/net/InetAddress;
       5: aload_2
       6: aconst_null
       7: invokevirtual #32                 // Method joinGroup:(Ljava/net/InetAddress;Ljava/net/NetworkInterface;Ljava/net/InetAddress;)Lorg/jboss/netty/channel/ChannelFuture;
      10: areturn

  public org.jboss.netty.channel.ChannelFuture joinGroup(java.net.InetAddress, java.net.NetworkInterface, java.net.InetAddress);
    Code:
       0: invokestatic  #9                  // Method org/jboss/netty/util/internal/DetectionUtil.javaVersion:()I
       3: bipush        7
       5: if_icmpge     16
       8: new           #35                 // class java/lang/UnsupportedOperationException
      11: dup
      12: invokespecial #36                 // Method java/lang/UnsupportedOperationException."<init>":()V
      15: athrow
      16: aload_1
      17: ifnonnull     30
      20: new           #37                 // class java/lang/NullPointerException
      23: dup
      24: ldc           #38                 // String multicastAddress
      26: invokespecial #39                 // Method java/lang/NullPointerException."<init>":(Ljava/lang/String;)V
      29: athrow
      30: aload_2
      31: ifnonnull     44
      34: new           #37                 // class java/lang/NullPointerException
      37: dup
      38: ldc           #40                 // String networkInterface
      40: invokespecial #39                 // Method java/lang/NullPointerException."<init>":(Ljava/lang/String;)V
      43: athrow
      44: aload_3
      45: ifnonnull     65
      48: aload_0
      49: getfield      #4                  // Field channel:Ljava/nio/channels/SelectableChannel;
      52: checkcast     #5                  // class java/nio/channels/DatagramChannel
      55: aload_1
      56: aload_2
      57: invokevirtual #41                 // Method java/nio/channels/DatagramChannel.join:(Ljava/net/InetAddress;Ljava/net/NetworkInterface;)Ljava/nio/channels/MembershipKey;
      60: astore        4
      62: goto          80
      65: aload_0
      66: getfield      #4                  // Field channel:Ljava/nio/channels/SelectableChannel;
      69: checkcast     #5                  // class java/nio/channels/DatagramChannel
      72: aload_1
      73: aload_2
      74: aload_3
      75: invokevirtual #42                 // Method java/nio/channels/DatagramChannel.join:(Ljava/net/InetAddress;Ljava/net/NetworkInterface;Ljava/net/InetAddress;)Ljava/nio/channels/MembershipKey;
      78: astore        4
      80: aload_0
      81: dup
      82: astore        5
      84: monitorenter
      85: aload_0
      86: getfield      #43                 // Field memberships:Ljava/util/Map;
      89: ifnonnull     103
      92: aload_0
      93: new           #44                 // class java/util/HashMap
      96: dup
      97: invokespecial #45                 // Method java/util/HashMap."<init>":()V
     100: putfield      #43                 // Field memberships:Ljava/util/Map;
     103: aload_0
     104: getfield      #43                 // Field memberships:Ljava/util/Map;
     107: aload_1
     108: invokeinterface #46,  2           // InterfaceMethod java/util/Map.get:(Ljava/lang/Object;)Ljava/lang/Object;
     113: checkcast     #47                 // class java/util/List
     116: astore        6
     118: aload         6
     120: ifnonnull     145
     123: new           #48                 // class java/util/ArrayList
     126: dup
     127: invokespecial #49                 // Method java/util/ArrayList."<init>":()V
     130: astore        6
     132: aload_0
     133: getfield      #43                 // Field memberships:Ljava/util/Map;
     136: aload_1
     137: aload         6
     139: invokeinterface #50,  3           // InterfaceMethod java/util/Map.put:(Ljava/lang/Object;Ljava/lang/Object;)Ljava/lang/Object;
     144: pop
     145: aload         6
     147: aload         4
     149: invokeinterface #51,  2           // InterfaceMethod java/util/List.add:(Ljava/lang/Object;)Z
     154: pop
     155: aload         5
     157: monitorexit
     158: goto          169
     161: astore        7
     163: aload         5
     165: monitorexit
     166: aload         7
     168: athrow
     169: goto          181
     172: astore        4
     174: aload_0
     175: aload         4
     177: invokestatic  #34                 // Method org/jboss/netty/channel/Channels.failedFuture:(Lorg/jboss/netty/channel/Channel;Ljava/lang/Throwable;)Lorg/jboss/netty/channel/ChannelFuture;
     180: areturn
     181: aload_0
     182: invokestatic  #53                 // Method org/jboss/netty/channel/Channels.succeededFuture:(Lorg/jboss/netty/channel/Channel;)Lorg/jboss/netty/channel/ChannelFuture;
     185: areturn
    Exception table:
       from    to  target type
          85   158   161   any
         161   166   161   any
          44   169   172   Class java/lang/Throwable

  public org.jboss.netty.channel.ChannelFuture leaveGroup(java.net.InetAddress);
    Code:
       0: aload_0
       1: aload_1
       2: aload_0
       3: invokevirtual #29                 // Method getLocalAddress:()Ljava/net/InetSocketAddress;
       6: invokevirtual #30                 // Method java/net/InetSocketAddress.getAddress:()Ljava/net/InetAddress;
       9: invokestatic  #31                 // Method java/net/NetworkInterface.getByInetAddress:(Ljava/net/InetAddress;)Ljava/net/NetworkInterface;
      12: aconst_null
      13: invokevirtual #54                 // Method leaveGroup:(Ljava/net/InetAddress;Ljava/net/NetworkInterface;Ljava/net/InetAddress;)Lorg/jboss/netty/channel/ChannelFuture;
      16: areturn
      17: astore_2
      18: aload_0
      19: aload_2
      20: invokestatic  #34                 // Method org/jboss/netty/channel/Channels.failedFuture:(Lorg/jboss/netty/channel/Channel;Ljava/lang/Throwable;)Lorg/jboss/netty/channel/ChannelFuture;
      23: areturn
    Exception table:
       from    to  target type
           0    16    17   Class java/net/SocketException

  public org.jboss.netty.channel.ChannelFuture leaveGroup(java.net.InetSocketAddress, java.net.NetworkInterface);
    Code:
       0: aload_0
       1: aload_1
       2: invokevirtual #30                 // Method java/net/InetSocketAddress.getAddress:()Ljava/net/InetAddress;
       5: aload_2
       6: aconst_null
       7: invokevirtual #54                 // Method leaveGroup:(Ljava/net/InetAddress;Ljava/net/NetworkInterface;Ljava/net/InetAddress;)Lorg/jboss/netty/channel/ChannelFuture;
      10: areturn

  public org.jboss.netty.channel.ChannelFuture leaveGroup(java.net.InetAddress, java.net.NetworkInterface, java.net.InetAddress);
    Code:
       0: invokestatic  #9                  // Method org/jboss/netty/util/internal/DetectionUtil.javaVersion:()I
       3: bipush        7
       5: if_icmpge     16
       8: new           #35                 // class java/lang/UnsupportedOperationException
      11: dup
      12: invokespecial #36                 // Method java/lang/UnsupportedOperationException."<init>":()V
      15: athrow
      16: aload_1
      17: ifnonnull     30
      20: new           #37                 // class java/lang/NullPointerException
      23: dup
      24: ldc           #38                 // String multicastAddress
      26: invokespecial #39                 // Method java/lang/NullPointerException."<init>":(Ljava/lang/String;)V
      29: athrow
      30: aload_2
      31: ifnonnull     44
      34: new           #37                 // class java/lang/NullPointerException
      37: dup
      38: ldc           #40                 // String networkInterface
      40: invokespecial #39                 // Method java/lang/NullPointerException."<init>":(Ljava/lang/String;)V
      43: athrow
      44: aload_0
      45: dup
      46: astore        4
      48: monitorenter
      49: aload_0
      50: getfield      #43                 // Field memberships:Ljava/util/Map;
      53: ifnull        183
      56: aload_0
      57: getfield      #43                 // Field memberships:Ljava/util/Map;
      60: aload_1
      61: invokeinterface #46,  2           // InterfaceMethod java/util/Map.get:(Ljava/lang/Object;)Ljava/lang/Object;
      66: checkcast     #47                 // class java/util/List
      69: astore        5
      71: aload         5
      73: ifnull        183
      76: aload         5
      78: invokeinterface #55,  1           // InterfaceMethod java/util/List.iterator:()Ljava/util/Iterator;
      83: astore        6
      85: aload         6
      87: invokeinterface #56,  1           // InterfaceMethod java/util/Iterator.hasNext:()Z
      92: ifeq          162
      95: aload         6
      97: invokeinterface #57,  1           // InterfaceMethod java/util/Iterator.next:()Ljava/lang/Object;
     102: checkcast     #58                 // class java/nio/channels/MembershipKey
     105: astore        7
     107: aload_2
     108: aload         7
     110: invokevirtual #59                 // Method java/nio/channels/MembershipKey.networkInterface:()Ljava/net/NetworkInterface;
     113: invokevirtual #60                 // Method java/net/NetworkInterface.equals:(Ljava/lang/Object;)Z
     116: ifeq          159
     119: aload_3
     120: ifnonnull     131
     123: aload         7
     125: invokevirtual #61                 // Method java/nio/channels/MembershipKey.sourceAddress:()Ljava/net/InetAddress;
     128: ifnull        147
     131: aload_3
     132: ifnull        159
     135: aload_3
     136: aload         7
     138: invokevirtual #61                 // Method java/nio/channels/MembershipKey.sourceAddress:()Ljava/net/InetAddress;
     141: invokevirtual #62                 // Method java/net/InetAddress.equals:(Ljava/lang/Object;)Z
     144: ifeq          159
     147: aload         7
     149: invokevirtual #63                 // Method java/nio/channels/MembershipKey.drop:()V
     152: aload         6
     154: invokeinterface #64,  1           // InterfaceMethod java/util/Iterator.remove:()V
     159: goto          85
     162: aload         5
     164: invokeinterface #65,  1           // InterfaceMethod java/util/List.isEmpty:()Z
     169: ifeq          183
     172: aload_0
     173: getfield      #43                 // Field memberships:Ljava/util/Map;
     176: aload_1
     177: invokeinterface #66,  2           // InterfaceMethod java/util/Map.remove:(Ljava/lang/Object;)Ljava/lang/Object;
     182: pop
     183: aload         4
     185: monitorexit
     186: goto          197
     189: astore        8
     191: aload         4
     193: monitorexit
     194: aload         8
     196: athrow
     197: aload_0
     198: invokestatic  #53                 // Method org/jboss/netty/channel/Channels.succeededFuture:(Lorg/jboss/netty/channel/Channel;)Lorg/jboss/netty/channel/ChannelFuture;
     201: areturn
    Exception table:
       from    to  target type
          49   186   189   any
         189   194   189   any

  public org.jboss.netty.channel.ChannelFuture block(java.net.InetAddress, java.net.NetworkInterface, java.net.InetAddress);
    Code:
       0: invokestatic  #9                  // Method org/jboss/netty/util/internal/DetectionUtil.javaVersion:()I
       3: bipush        7
       5: if_icmpge     16
       8: new           #35                 // class java/lang/UnsupportedOperationException
      11: dup
      12: invokespecial #36                 // Method java/lang/UnsupportedOperationException."<init>":()V
      15: athrow
      16: aload_1
      17: ifnonnull     30
      20: new           #37                 // class java/lang/NullPointerException
      23: dup
      24: ldc           #38                 // String multicastAddress
      26: invokespecial #39                 // Method java/lang/NullPointerException."<init>":(Ljava/lang/String;)V
      29: athrow
      30: aload_3
      31: ifnonnull     44
      34: new           #37                 // class java/lang/NullPointerException
      37: dup
      38: ldc           #67                 // String sourceToBlock
      40: invokespecial #39                 // Method java/lang/NullPointerException."<init>":(Ljava/lang/String;)V
      43: athrow
      44: aload_2
      45: ifnonnull     58
      48: new           #37                 // class java/lang/NullPointerException
      51: dup
      52: ldc           #40                 // String networkInterface
      54: invokespecial #39                 // Method java/lang/NullPointerException."<init>":(Ljava/lang/String;)V
      57: athrow
      58: aload_0
      59: dup
      60: astore        4
      62: monitorenter
      63: aload_0
      64: getfield      #43                 // Field memberships:Ljava/util/Map;
      67: ifnull        153
      70: aload_0
      71: getfield      #43                 // Field memberships:Ljava/util/Map;
      74: aload_1
      75: invokeinterface #46,  2           // InterfaceMethod java/util/Map.get:(Ljava/lang/Object;)Ljava/lang/Object;
      80: checkcast     #47                 // class java/util/List
      83: astore        5
      85: aload         5
      87: invokeinterface #68,  1           // InterfaceMethod java/util/List.iterator:()Ljava/util/Iterator;
      92: astore        6
      94: aload         6
      96: invokeinterface #56,  1           // InterfaceMethod java/util/Iterator.hasNext:()Z
     101: ifeq          153
     104: aload         6
     106: invokeinterface #57,  1           // InterfaceMethod java/util/Iterator.next:()Ljava/lang/Object;
     111: checkcast     #58                 // class java/nio/channels/MembershipKey
     114: astore        7
     116: aload_2
     117: aload         7
     119: invokevirtual #59                 // Method java/nio/channels/MembershipKey.networkInterface:()Ljava/net/NetworkInterface;
     122: invokevirtual #60                 // Method java/net/NetworkInterface.equals:(Ljava/lang/Object;)Z
     125: ifeq          150
     128: aload         7
     130: aload_3
     131: invokevirtual #69                 // Method java/nio/channels/MembershipKey.block:(Ljava/net/InetAddress;)Ljava/nio/channels/MembershipKey;
     134: pop
     135: goto          150
     138: astore        8
     140: aload_0
     141: aload         8
     143: invokestatic  #34                 // Method org/jboss/netty/channel/Channels.failedFuture:(Lorg/jboss/netty/channel/Channel;Ljava/lang/Throwable;)Lorg/jboss/netty/channel/ChannelFuture;
     146: aload         4
     148: monitorexit
     149: areturn
     150: goto          94
     153: aload         4
     155: monitorexit
     156: goto          167
     159: astore        9
     161: aload         4
     163: monitorexit
     164: aload         9
     166: athrow
     167: aload_0
     168: invokestatic  #53                 // Method org/jboss/netty/channel/Channels.succeededFuture:(Lorg/jboss/netty/channel/Channel;)Lorg/jboss/netty/channel/ChannelFuture;
     171: areturn
    Exception table:
       from    to  target type
         128   135   138   Class java/io/IOException
          63   149   159   any
         150   156   159   any
         159   164   159   any

  public org.jboss.netty.channel.ChannelFuture block(java.net.InetAddress, java.net.InetAddress);
    Code:
       0: aload_0
       1: aload_1
       2: aload_0
       3: invokevirtual #29                 // Method getLocalAddress:()Ljava/net/InetSocketAddress;
       6: invokevirtual #30                 // Method java/net/InetSocketAddress.getAddress:()Ljava/net/InetAddress;
       9: invokestatic  #31                 // Method java/net/NetworkInterface.getByInetAddress:(Ljava/net/InetAddress;)Ljava/net/NetworkInterface;
      12: aload_2
      13: invokevirtual #70                 // Method block:(Ljava/net/InetAddress;Ljava/net/NetworkInterface;Ljava/net/InetAddress;)Lorg/jboss/netty/channel/ChannelFuture;
      16: pop
      17: goto          27
      20: astore_3
      21: aload_0
      22: aload_3
      23: invokestatic  #34                 // Method org/jboss/netty/channel/Channels.failedFuture:(Lorg/jboss/netty/channel/Channel;Ljava/lang/Throwable;)Lorg/jboss/netty/channel/ChannelFuture;
      26: areturn
      27: aload_0
      28: invokestatic  #53                 // Method org/jboss/netty/channel/Channels.succeededFuture:(Lorg/jboss/netty/channel/Channel;)Lorg/jboss/netty/channel/ChannelFuture;
      31: areturn
    Exception table:
       from    to  target type
           0    17    20   Class java/net/SocketException

  java.net.InetSocketAddress getLocalSocketAddress() throws java.lang.Exception;
    Code:
       0: aload_0
       1: getfield      #4                  // Field channel:Ljava/nio/channels/SelectableChannel;
       4: checkcast     #5                  // class java/nio/channels/DatagramChannel
       7: invokevirtual #25                 // Method java/nio/channels/DatagramChannel.socket:()Ljava/net/DatagramSocket;
      10: invokevirtual #71                 // Method java/net/DatagramSocket.getLocalSocketAddress:()Ljava/net/SocketAddress;
      13: checkcast     #72                 // class java/net/InetSocketAddress
      16: areturn

  java.net.InetSocketAddress getRemoteSocketAddress() throws java.lang.Exception;
    Code:
       0: aload_0
       1: getfield      #4                  // Field channel:Ljava/nio/channels/SelectableChannel;
       4: checkcast     #5                  // class java/nio/channels/DatagramChannel
       7: invokevirtual #25                 // Method java/nio/channels/DatagramChannel.socket:()Ljava/net/DatagramSocket;
      10: invokevirtual #73                 // Method java/net/DatagramSocket.getRemoteSocketAddress:()Ljava/net/SocketAddress;
      13: checkcast     #72                 // class java/net/InetSocketAddress
      16: areturn

  public org.jboss.netty.channel.ChannelFuture write(java.lang.Object, java.net.SocketAddress);
    Code:
       0: aload_2
       1: ifnull        15
       4: aload_2
       5: aload_0
       6: invokevirtual #74                 // Method getRemoteAddress:()Ljava/net/InetSocketAddress;
       9: invokevirtual #75                 // Method java/lang/Object.equals:(Ljava/lang/Object;)Z
      12: ifeq          22
      15: aload_0
      16: aload_1
      17: aconst_null
      18: invokespecial #76                 // Method org/jboss/netty/channel/socket/nio/AbstractNioChannel.write:(Ljava/lang/Object;Ljava/net/SocketAddress;)Lorg/jboss/netty/channel/ChannelFuture;
      21: areturn
      22: aload_0
      23: aload_1
      24: aload_2
      25: invokespecial #76                 // Method org/jboss/netty/channel/socket/nio/AbstractNioChannel.write:(Ljava/lang/Object;Ljava/net/SocketAddress;)Lorg/jboss/netty/channel/ChannelFuture;
      28: areturn

  public org.jboss.netty.channel.socket.nio.NioChannelConfig getConfig();
    Code:
       0: aload_0
       1: invokevirtual #77                 // Method getConfig:()Lorg/jboss/netty/channel/socket/nio/NioDatagramChannelConfig;
       4: areturn

  public java.net.InetSocketAddress getRemoteAddress();
    Code:
       0: aload_0
       1: invokespecial #78                 // Method org/jboss/netty/channel/socket/nio/AbstractNioChannel.getRemoteAddress:()Ljava/net/InetSocketAddress;
       4: areturn

  public java.net.InetSocketAddress getLocalAddress();
    Code:
       0: aload_0
       1: invokespecial #79                 // Method org/jboss/netty/channel/socket/nio/AbstractNioChannel.getLocalAddress:()Ljava/net/InetSocketAddress;
       4: areturn

  public org.jboss.netty.channel.socket.nio.AbstractNioWorker getWorker();
    Code:
       0: aload_0
       1: invokevirtual #80                 // Method getWorker:()Lorg/jboss/netty/channel/socket/nio/NioDatagramWorker;
       4: areturn

  public org.jboss.netty.channel.ChannelConfig getConfig();
    Code:
       0: aload_0
       1: invokevirtual #77                 // Method getConfig:()Lorg/jboss/netty/channel/socket/nio/NioDatagramChannelConfig;
       4: areturn

  public org.jboss.netty.channel.socket.DatagramChannelConfig getConfig();
    Code:
       0: aload_0
       1: invokevirtual #77                 // Method getConfig:()Lorg/jboss/netty/channel/socket/nio/NioDatagramChannelConfig;
       4: areturn
}
