Compiled from "ShareableWorkerPool.java"
public final class org.jboss.netty.channel.socket.nio.ShareableWorkerPool<E extends org.jboss.netty.channel.socket.Worker> implements org.jboss.netty.channel.socket.nio.WorkerPool<E> {
  private final org.jboss.netty.channel.socket.nio.WorkerPool<E> wrapped;

  public org.jboss.netty.channel.socket.nio.ShareableWorkerPool(org.jboss.netty.channel.socket.nio.WorkerPool<E>);
    Code:
       0: aload_0
       1: invokespecial #1                  // Method java/lang/Object."<init>":()V
       4: aload_0
       5: aload_1
       6: putfield      #2                  // Field wrapped:Lorg/jboss/netty/channel/socket/nio/WorkerPool;
       9: return

  public E nextWorker();
    Code:
       0: aload_0
       1: getfield      #2                  // Field wrapped:Lorg/jboss/netty/channel/socket/nio/WorkerPool;
       4: invokeinterface #3,  1            // InterfaceMethod org/jboss/netty/channel/socket/nio/WorkerPool.nextWorker:()Lorg/jboss/netty/channel/socket/Worker;
       9: areturn

  public void rebuildSelectors();
    Code:
       0: aload_0
       1: getfield      #2                  // Field wrapped:Lorg/jboss/netty/channel/socket/nio/WorkerPool;
       4: invokeinterface #4,  1            // InterfaceMethod org/jboss/netty/channel/socket/nio/WorkerPool.rebuildSelectors:()V
       9: return

  public void destroy();
    Code:
       0: aload_0
       1: getfield      #2                  // Field wrapped:Lorg/jboss/netty/channel/socket/nio/WorkerPool;
       4: invokeinterface #5,  1            // InterfaceMethod org/jboss/netty/channel/socket/nio/WorkerPool.shutdown:()V
       9: aload_0
      10: getfield      #2                  // Field wrapped:Lorg/jboss/netty/channel/socket/nio/WorkerPool;
      13: instanceof    #6                  // class org/jboss/netty/util/ExternalResourceReleasable
      16: ifeq          31
      19: aload_0
      20: getfield      #2                  // Field wrapped:Lorg/jboss/netty/channel/socket/nio/WorkerPool;
      23: checkcast     #6                  // class org/jboss/netty/util/ExternalResourceReleasable
      26: invokeinterface #7,  1            // InterfaceMethod org/jboss/netty/util/ExternalResourceReleasable.releaseExternalResources:()V
      31: return

  public void shutdown();
    Code:
       0: return
}
