Compiled from "ManifestCommonDefImpl.java"
abstract class org.jboss.shrinkwrap.descriptor.impl.base.spec.se.manifest.ManifestCommonDefImpl<T> implements org.jboss.shrinkwrap.descriptor.api.spec.se.manifest.ManifestCommonDef<T> {
  org.jboss.shrinkwrap.descriptor.impl.base.spec.se.manifest.ManifestCommonDefImpl();
    Code:
       0: aload_0
       1: invokespecial #1                  // Method java/lang/Object."<init>":()V
       4: return

  abstract T getDescriptor();

  abstract org.jboss.shrinkwrap.descriptor.impl.base.spec.se.manifest.ManifestModel getManifestModel();

  abstract void includeAttribute(java.util.jar.Attributes$Name, java.lang.String);

  abstract java.lang.String findAttribute(java.util.jar.Attributes$Name);

  void includeAttribute(java.lang.String, java.lang.String);
    Code:
       0: aload_0
       1: new           #2                  // class java/util/jar/Attributes$Name
       4: dup
       5: aload_1
       6: invokespecial #3                  // Method java/util/jar/Attributes$Name."<init>":(Ljava/lang/String;)V
       9: aload_2
      10: invokevirtual #4                  // Method includeAttribute:(Ljava/util/jar/Attributes$Name;Ljava/lang/String;)V
      13: return

  public T version(java.lang.String);
    Code:
       0: aload_0
       1: getstatic     #5                  // Field java/util/jar/Attributes$Name.MANIFEST_VERSION:Ljava/util/jar/Attributes$Name;
       4: aload_1
       5: invokevirtual #4                  // Method includeAttribute:(Ljava/util/jar/Attributes$Name;Ljava/lang/String;)V
       8: aload_0
       9: invokevirtual #6                  // Method getDescriptor:()Ljava/lang/Object;
      12: areturn

  public T signatureVersion(java.lang.String);
    Code:
       0: aload_0
       1: getstatic     #7                  // Field java/util/jar/Attributes$Name.SIGNATURE_VERSION:Ljava/util/jar/Attributes$Name;
       4: aload_1
       5: invokevirtual #4                  // Method includeAttribute:(Ljava/util/jar/Attributes$Name;Ljava/lang/String;)V
       8: aload_0
       9: invokevirtual #6                  // Method getDescriptor:()Ljava/lang/Object;
      12: areturn

  public T mainClass(java.lang.String);
    Code:
       0: aload_0
       1: getstatic     #8                  // Field java/util/jar/Attributes$Name.MAIN_CLASS:Ljava/util/jar/Attributes$Name;
       4: aload_1
       5: invokevirtual #4                  // Method includeAttribute:(Ljava/util/jar/Attributes$Name;Ljava/lang/String;)V
       8: aload_0
       9: invokevirtual #6                  // Method getDescriptor:()Ljava/lang/Object;
      12: areturn

  public T implementationTitle(java.lang.String);
    Code:
       0: aload_0
       1: getstatic     #9                  // Field java/util/jar/Attributes$Name.IMPLEMENTATION_TITLE:Ljava/util/jar/Attributes$Name;
       4: aload_1
       5: invokevirtual #4                  // Method includeAttribute:(Ljava/util/jar/Attributes$Name;Ljava/lang/String;)V
       8: aload_0
       9: invokevirtual #6                  // Method getDescriptor:()Ljava/lang/Object;
      12: areturn

  public T implementationVendor(java.lang.String);
    Code:
       0: aload_0
       1: getstatic     #10                 // Field java/util/jar/Attributes$Name.IMPLEMENTATION_VENDOR:Ljava/util/jar/Attributes$Name;
       4: aload_1
       5: invokevirtual #4                  // Method includeAttribute:(Ljava/util/jar/Attributes$Name;Ljava/lang/String;)V
       8: aload_0
       9: invokevirtual #6                  // Method getDescriptor:()Ljava/lang/Object;
      12: areturn

  public T implementationVendorId(java.lang.String);
    Code:
       0: aload_0
       1: getstatic     #11                 // Field java/util/jar/Attributes$Name.IMPLEMENTATION_VENDOR_ID:Ljava/util/jar/Attributes$Name;
       4: aload_1
       5: invokevirtual #4                  // Method includeAttribute:(Ljava/util/jar/Attributes$Name;Ljava/lang/String;)V
       8: aload_0
       9: invokevirtual #6                  // Method getDescriptor:()Ljava/lang/Object;
      12: areturn

  public T implementationUrl(java.lang.String);
    Code:
       0: aload_0
       1: getstatic     #12                 // Field java/util/jar/Attributes$Name.IMPLEMENTATION_URL:Ljava/util/jar/Attributes$Name;
       4: aload_1
       5: invokevirtual #4                  // Method includeAttribute:(Ljava/util/jar/Attributes$Name;Ljava/lang/String;)V
       8: aload_0
       9: invokevirtual #6                  // Method getDescriptor:()Ljava/lang/Object;
      12: areturn

  public T specificationTitle(java.lang.String);
    Code:
       0: aload_0
       1: getstatic     #13                 // Field java/util/jar/Attributes$Name.SPECIFICATION_TITLE:Ljava/util/jar/Attributes$Name;
       4: aload_1
       5: invokevirtual #4                  // Method includeAttribute:(Ljava/util/jar/Attributes$Name;Ljava/lang/String;)V
       8: aload_0
       9: invokevirtual #6                  // Method getDescriptor:()Ljava/lang/Object;
      12: areturn

  public T specificationVersion(java.lang.String);
    Code:
       0: aload_0
       1: getstatic     #14                 // Field java/util/jar/Attributes$Name.SPECIFICATION_VERSION:Ljava/util/jar/Attributes$Name;
       4: aload_1
       5: invokevirtual #4                  // Method includeAttribute:(Ljava/util/jar/Attributes$Name;Ljava/lang/String;)V
       8: aload_0
       9: invokevirtual #6                  // Method getDescriptor:()Ljava/lang/Object;
      12: areturn

  public T specificationVendor(java.lang.String);
    Code:
       0: aload_0
       1: getstatic     #15                 // Field java/util/jar/Attributes$Name.SPECIFICATION_VENDOR:Ljava/util/jar/Attributes$Name;
       4: aload_1
       5: invokevirtual #4                  // Method includeAttribute:(Ljava/util/jar/Attributes$Name;Ljava/lang/String;)V
       8: aload_0
       9: invokevirtual #6                  // Method getDescriptor:()Ljava/lang/Object;
      12: areturn

  public T sealed();
    Code:
       0: aload_0
       1: getstatic     #16                 // Field java/util/jar/Attributes$Name.SEALED:Ljava/util/jar/Attributes$Name;
       4: getstatic     #17                 // Field TRUE:Ljava/lang/String;
       7: invokevirtual #4                  // Method includeAttribute:(Ljava/util/jar/Attributes$Name;Ljava/lang/String;)V
      10: aload_0
      11: invokevirtual #6                  // Method getDescriptor:()Ljava/lang/Object;
      14: areturn

  public T notSealed();
    Code:
       0: aload_0
       1: getstatic     #16                 // Field java/util/jar/Attributes$Name.SEALED:Ljava/util/jar/Attributes$Name;
       4: getstatic     #18                 // Field FALSE:Ljava/lang/String;
       7: invokevirtual #4                  // Method includeAttribute:(Ljava/util/jar/Attributes$Name;Ljava/lang/String;)V
      10: aload_0
      11: invokevirtual #6                  // Method getDescriptor:()Ljava/lang/Object;
      14: areturn

  public T createdBy(java.lang.String);
    Code:
       0: aload_0
       1: getstatic     #19                 // Field CREATED_BY:Ljava/util/jar/Attributes$Name;
       4: aload_1
       5: invokevirtual #4                  // Method includeAttribute:(Ljava/util/jar/Attributes$Name;Ljava/lang/String;)V
       8: aload_0
       9: invokevirtual #6                  // Method getDescriptor:()Ljava/lang/Object;
      12: areturn

  public T addToClassPath(java.lang.String);
    Code:
       0: aload_0
       1: getstatic     #20                 // Field java/util/jar/Attributes$Name.CLASS_PATH:Ljava/util/jar/Attributes$Name;
       4: invokevirtual #21                 // Method findAttribute:(Ljava/util/jar/Attributes$Name;)Ljava/lang/String;
       7: astore_2
       8: aload_1
       9: astore_3
      10: aload_2
      11: ifnull        38
      14: new           #22                 // class java/lang/StringBuilder
      17: dup
      18: invokespecial #23                 // Method java/lang/StringBuilder."<init>":()V
      21: aload_2
      22: invokevirtual #24                 // Method java/lang/StringBuilder.append:(Ljava/lang/String;)Ljava/lang/StringBuilder;
      25: ldc           #25                 // String
      27: invokevirtual #24                 // Method java/lang/StringBuilder.append:(Ljava/lang/String;)Ljava/lang/StringBuilder;
      30: aload_3
      31: invokevirtual #24                 // Method java/lang/StringBuilder.append:(Ljava/lang/String;)Ljava/lang/StringBuilder;
      34: invokevirtual #26                 // Method java/lang/StringBuilder.toString:()Ljava/lang/String;
      37: astore_3
      38: aload_0
      39: getstatic     #20                 // Field java/util/jar/Attributes$Name.CLASS_PATH:Ljava/util/jar/Attributes$Name;
      42: aload_3
      43: invokevirtual #4                  // Method includeAttribute:(Ljava/util/jar/Attributes$Name;Ljava/lang/String;)V
      46: aload_0
      47: invokevirtual #6                  // Method getDescriptor:()Ljava/lang/Object;
      50: areturn

  public T attribute(java.lang.String, java.lang.String);
    Code:
       0: aload_0
       1: aload_1
       2: aload_2
       3: invokevirtual #27                 // Method includeAttribute:(Ljava/lang/String;Ljava/lang/String;)V
       6: aload_0
       7: invokevirtual #6                  // Method getDescriptor:()Ljava/lang/Object;
      10: areturn

  public T implementationVersion(java.lang.String);
    Code:
       0: aload_0
       1: getstatic     #28                 // Field java/util/jar/Attributes$Name.IMPLEMENTATION_VERSION:Ljava/util/jar/Attributes$Name;
       4: aload_1
       5: invokevirtual #4                  // Method includeAttribute:(Ljava/util/jar/Attributes$Name;Ljava/lang/String;)V
       8: aload_0
       9: invokevirtual #6                  // Method getDescriptor:()Ljava/lang/Object;
      12: areturn

  public final java.lang.String exportAsString() throws org.jboss.shrinkwrap.descriptor.api.DescriptorExportException;
    Code:
       0: new           #29                 // class java/io/ByteArrayOutputStream
       3: dup
       4: invokespecial #30                 // Method java/io/ByteArrayOutputStream."<init>":()V
       7: astore_1
       8: aload_0
       9: aload_1
      10: invokevirtual #31                 // Method exportTo:(Ljava/io/OutputStream;)V
      13: aload_1
      14: ldc           #32                 // String UTF-8
      16: invokevirtual #33                 // Method java/io/ByteArrayOutputStream.toString:(Ljava/lang/String;)Ljava/lang/String;
      19: areturn
      20: astore_1
      21: new           #35                 // class org/jboss/shrinkwrap/descriptor/api/DescriptorExportException
      24: dup
      25: ldc           #36                 // String Inconsistent encoding used during export
      27: aload_1
      28: invokespecial #37                 // Method org/jboss/shrinkwrap/descriptor/api/DescriptorExportException."<init>":(Ljava/lang/String;Ljava/lang/Throwable;)V
      31: athrow
    Exception table:
       from    to  target type
           0    19    20   Class java/io/UnsupportedEncodingException

  public void exportTo(java.io.OutputStream) throws org.jboss.shrinkwrap.descriptor.api.DescriptorExportException, java.lang.IllegalArgumentException;
    Code:
       0: aload_1
       1: ifnonnull     14
       4: new           #38                 // class java/lang/IllegalArgumentException
       7: dup
       8: ldc           #39                 // String Can not export to null stream
      10: invokespecial #40                 // Method java/lang/IllegalArgumentException."<init>":(Ljava/lang/String;)V
      13: athrow
      14: aload_0
      15: invokevirtual #41                 // Method getManifestModel:()Lorg/jboss/shrinkwrap/descriptor/impl/base/spec/se/manifest/ManifestModel;
      18: aload_1
      19: invokevirtual #42                 // Method org/jboss/shrinkwrap/descriptor/impl/base/spec/se/manifest/ManifestModel.write:(Ljava/io/OutputStream;)V
      22: goto          39
      25: astore_2
      26: new           #35                 // class org/jboss/shrinkwrap/descriptor/api/DescriptorExportException
      29: dup
      30: aload_2
      31: invokevirtual #44                 // Method java/io/IOException.getMessage:()Ljava/lang/String;
      34: aload_2
      35: invokespecial #37                 // Method org/jboss/shrinkwrap/descriptor/api/DescriptorExportException."<init>":(Ljava/lang/String;Ljava/lang/Throwable;)V
      38: athrow
      39: return
    Exception table:
       from    to  target type
          14    22    25   Class java/io/IOException
}
