Compiled from "NetFlowUdpInput.java"
public class org.graylog.plugins.netflow.inputs.NetFlowUdpInput extends org.graylog2.plugin.inputs.MessageInput {
  private static final java.lang.String NAME;

  public org.graylog.plugins.netflow.inputs.NetFlowUdpInput(com.codahale.metrics.MetricRegistry, org.graylog2.plugin.configuration.Configuration, org.graylog.plugins.netflow.transport.NetFlowUdpTransport$Factory, org.graylog.plugins.netflow.codecs.NetFlowCodec$Factory, org.graylog2.plugin.LocalMetricRegistry, org.graylog.plugins.netflow.inputs.NetFlowUdpInput$Config, org.graylog.plugins.netflow.inputs.NetFlowUdpInput$Descriptor, org.graylog2.plugin.ServerStatus);
    Code:
       0: aload_0
       1: aload_1
       2: aload_2
       3: aload_3
       4: aload_2
       5: invokeinterface #1,  2            // InterfaceMethod org/graylog/plugins/netflow/transport/NetFlowUdpTransport$Factory.create:(Lorg/graylog2/plugin/configuration/Configuration;)Lorg/graylog/plugins/netflow/transport/NetFlowUdpTransport;
      10: aload         5
      12: aload         4
      14: aload_2
      15: invokeinterface #2,  2            // InterfaceMethod org/graylog/plugins/netflow/codecs/NetFlowCodec$Factory.create:(Lorg/graylog2/plugin/configuration/Configuration;)Lorg/graylog/plugins/netflow/codecs/NetFlowCodec;
      20: aload         6
      22: aload         7
      24: aload         8
      26: invokespecial #3                  // Method org/graylog2/plugin/inputs/MessageInput."<init>":(Lcom/codahale/metrics/MetricRegistry;Lorg/graylog2/plugin/configuration/Configuration;Lorg/graylog2/plugin/inputs/transports/Transport;Lorg/graylog2/plugin/LocalMetricRegistry;Lorg/graylog2/plugin/inputs/codecs/Codec;Lorg/graylog2/plugin/inputs/MessageInput$Config;Lorg/graylog2/plugin/inputs/MessageInput$Descriptor;Lorg/graylog2/plugin/ServerStatus;)V
      29: return
}
