Compiled from "Util.java"
class org.apache.tomcat.websocket.Util$TypeResult {
  private final java.lang.Class<?> clazz;

  private final int index;

  private int dimension;

  public org.apache.tomcat.websocket.Util$TypeResult(java.lang.Class<?>, int, int);
    Code:
       0: aload_0
       1: invokespecial #1                  // Method java/lang/Object."<init>":()V
       4: aload_0
       5: aload_1
       6: putfield      #2                  // Field clazz:Ljava/lang/Class;
       9: aload_0
      10: iload_2
      11: putfield      #3                  // Field index:I
      14: aload_0
      15: iload_3
      16: putfield      #4                  // Field dimension:I
      19: return

  public java.lang.Class<?> getClazz();
    Code:
       0: aload_0
       1: getfield      #2                  // Field clazz:Ljava/lang/Class;
       4: areturn

  public int getIndex();
    Code:
       0: aload_0
       1: getfield      #3                  // Field index:I
       4: ireturn

  public int getDimension();
    Code:
       0: aload_0
       1: getfield      #4                  // Field dimension:I
       4: ireturn

  public void incrementDimension(int);
    Code:
       0: aload_0
       1: dup
       2: getfield      #4                  // Field dimension:I
       5: iload_1
       6: iadd
       7: putfield      #4                  // Field dimension:I
      10: return
}
