Compiled from "AbstractEpollServerChannel.java"
public abstract class io.netty.channel.epoll.AbstractEpollServerChannel extends io.netty.channel.epoll.AbstractEpollChannel implements io.netty.channel.ServerChannel {
  private static final io.netty.channel.ChannelMetadata METADATA;

  protected io.netty.channel.epoll.AbstractEpollServerChannel(int);
    Code:
       0: aload_0
       1: new           #1                  // class io/netty/channel/epoll/LinuxSocket
       4: dup
       5: iload_1
       6: invokespecial #2                  // Method io/netty/channel/epoll/LinuxSocket."<init>":(I)V
       9: iconst_0
      10: invokespecial #3                  // Method "<init>":(Lio/netty/channel/epoll/LinuxSocket;Z)V
      13: return

  io.netty.channel.epoll.AbstractEpollServerChannel(io.netty.channel.epoll.LinuxSocket);
    Code:
       0: aload_0
       1: aload_1
       2: aload_1
       3: invokestatic  #4                  // Method isSoErrorZero:(Lio/netty/channel/unix/Socket;)Z
       6: invokespecial #3                  // Method "<init>":(Lio/netty/channel/epoll/LinuxSocket;Z)V
       9: return

  io.netty.channel.epoll.AbstractEpollServerChannel(io.netty.channel.epoll.LinuxSocket, boolean);
    Code:
       0: aload_0
       1: aconst_null
       2: aload_1
       3: iload_2
       4: invokespecial #5                  // Method io/netty/channel/epoll/AbstractEpollChannel."<init>":(Lio/netty/channel/Channel;Lio/netty/channel/epoll/LinuxSocket;Z)V
       7: return

  public io.netty.channel.ChannelMetadata metadata();
    Code:
       0: getstatic     #6                  // Field METADATA:Lio/netty/channel/ChannelMetadata;
       3: areturn

  protected boolean isCompatible(io.netty.channel.EventLoop);
    Code:
       0: aload_1
       1: instanceof    #7                  // class io/netty/channel/epoll/EpollEventLoop
       4: ireturn

  protected java.net.InetSocketAddress remoteAddress0();
    Code:
       0: aconst_null
       1: areturn

  protected io.netty.channel.epoll.AbstractEpollChannel$AbstractEpollUnsafe newUnsafe();
    Code:
       0: new           #8                  // class io/netty/channel/epoll/AbstractEpollServerChannel$EpollServerSocketUnsafe
       3: dup
       4: aload_0
       5: invokespecial #9                  // Method io/netty/channel/epoll/AbstractEpollServerChannel$EpollServerSocketUnsafe."<init>":(Lio/netty/channel/epoll/AbstractEpollServerChannel;)V
       8: areturn

  protected void doWrite(io.netty.channel.ChannelOutboundBuffer) throws java.lang.Exception;
    Code:
       0: new           #10                 // class java/lang/UnsupportedOperationException
       3: dup
       4: invokespecial #11                 // Method java/lang/UnsupportedOperationException."<init>":()V
       7: athrow

  protected java.lang.Object filterOutboundMessage(java.lang.Object) throws java.lang.Exception;
    Code:
       0: new           #10                 // class java/lang/UnsupportedOperationException
       3: dup
       4: invokespecial #11                 // Method java/lang/UnsupportedOperationException."<init>":()V
       7: athrow

  abstract io.netty.channel.Channel newChildChannel(int, byte[], int, int) throws java.lang.Exception;

  protected boolean doConnect(java.net.SocketAddress, java.net.SocketAddress) throws java.lang.Exception;
    Code:
       0: new           #10                 // class java/lang/UnsupportedOperationException
       3: dup
       4: invokespecial #11                 // Method java/lang/UnsupportedOperationException."<init>":()V
       7: athrow

  protected java.net.SocketAddress remoteAddress0();
    Code:
       0: aload_0
       1: invokevirtual #12                 // Method remoteAddress0:()Ljava/net/InetSocketAddress;
       4: areturn

  public boolean isOpen();
    Code:
       0: aload_0
       1: invokespecial #13                 // Method io/netty/channel/epoll/AbstractEpollChannel.isOpen:()Z
       4: ireturn

  public boolean isActive();
    Code:
       0: aload_0
       1: invokespecial #14                 // Method io/netty/channel/epoll/AbstractEpollChannel.isActive:()Z
       4: ireturn

  protected io.netty.channel.AbstractChannel$AbstractUnsafe newUnsafe();
    Code:
       0: aload_0
       1: invokevirtual #15                 // Method newUnsafe:()Lio/netty/channel/epoll/AbstractEpollChannel$AbstractEpollUnsafe;
       4: areturn

  static {};
    Code:
       0: new           #16                 // class io/netty/channel/ChannelMetadata
       3: dup
       4: iconst_0
       5: bipush        16
       7: invokespecial #17                 // Method io/netty/channel/ChannelMetadata."<init>":(ZI)V
      10: putstatic     #6                  // Field METADATA:Lio/netty/channel/ChannelMetadata;
      13: return
}
