Compiled from "JGroupsExtension.java"
public class org.jboss.as.clustering.jgroups.subsystem.JGroupsExtension implements org.jboss.as.controller.Extension {
  public static final java.lang.String SUBSYSTEM_NAME;

  public org.jboss.as.clustering.jgroups.subsystem.JGroupsExtension();
    Code:
       0: aload_0
       1: invokespecial #1                  // Method java/lang/Object."<init>":()V
       4: return

  public void initialize(org.jboss.as.controller.ExtensionContext);
    Code:
       0: aload_1
       1: ldc           #3                  // String jgroups
       3: getstatic     #4                  // Field org/jboss/as/clustering/jgroups/subsystem/JGroupsModel.CURRENT:Lorg/jboss/as/clustering/jgroups/subsystem/JGroupsModel;
       6: invokevirtual #5                  // Method org/jboss/as/clustering/jgroups/subsystem/JGroupsModel.getVersion:()Lorg/jboss/as/controller/ModelVersion;
       9: invokeinterface #6,  3            // InterfaceMethod org/jboss/as/controller/ExtensionContext.registerSubsystem:(Ljava/lang/String;Lorg/jboss/as/controller/ModelVersion;)Lorg/jboss/as/controller/SubsystemRegistration;
      14: astore_2
      15: new           #7                  // class org/jboss/as/clustering/jgroups/subsystem/JGroupsSubsystemResourceDefinition
      18: dup
      19: aload_1
      20: invokeinterface #8,  1            // InterfaceMethod org/jboss/as/controller/ExtensionContext.isRuntimeOnlyRegistrationValid:()Z
      25: invokespecial #9                  // Method org/jboss/as/clustering/jgroups/subsystem/JGroupsSubsystemResourceDefinition."<init>":(Z)V
      28: aload_2
      29: invokevirtual #10                 // Method org/jboss/as/clustering/jgroups/subsystem/JGroupsSubsystemResourceDefinition.register:(Lorg/jboss/as/controller/SubsystemRegistration;)V
      32: aload_2
      33: new           #11                 // class org/jboss/as/clustering/jgroups/subsystem/JGroupsSubsystemXMLWriter
      36: dup
      37: invokespecial #12                 // Method org/jboss/as/clustering/jgroups/subsystem/JGroupsSubsystemXMLWriter."<init>":()V
      40: invokeinterface #13,  2           // InterfaceMethod org/jboss/as/controller/SubsystemRegistration.registerXMLElementWriter:(Lorg/jboss/staxmapper/XMLElementWriter;)V
      45: aload_1
      46: invokeinterface #14,  1           // InterfaceMethod org/jboss/as/controller/ExtensionContext.isRegisterTransformers:()Z
      51: ifeq          109
      54: getstatic     #4                  // Field org/jboss/as/clustering/jgroups/subsystem/JGroupsModel.CURRENT:Lorg/jboss/as/clustering/jgroups/subsystem/JGroupsModel;
      57: invokestatic  #15                 // Method java/util/EnumSet.of:(Ljava/lang/Enum;)Ljava/util/EnumSet;
      60: invokestatic  #16                 // Method java/util/EnumSet.complementOf:(Ljava/util/EnumSet;)Ljava/util/EnumSet;
      63: invokevirtual #17                 // Method java/util/EnumSet.iterator:()Ljava/util/Iterator;
      66: astore_3
      67: aload_3
      68: invokeinterface #18,  1           // InterfaceMethod java/util/Iterator.hasNext:()Z
      73: ifeq          109
      76: aload_3
      77: invokeinterface #19,  1           // InterfaceMethod java/util/Iterator.next:()Ljava/lang/Object;
      82: checkcast     #20                 // class org/jboss/as/clustering/jgroups/subsystem/JGroupsModel
      85: astore        4
      87: aload         4
      89: invokevirtual #5                  // Method org/jboss/as/clustering/jgroups/subsystem/JGroupsModel.getVersion:()Lorg/jboss/as/controller/ModelVersion;
      92: astore        5
      94: aload         5
      96: invokestatic  #21                 // Method org/jboss/as/clustering/jgroups/subsystem/JGroupsSubsystemResourceDefinition.buildTransformers:(Lorg/jboss/as/controller/ModelVersion;)Lorg/jboss/as/controller/transform/description/TransformationDescription;
      99: aload_2
     100: aload         5
     102: invokestatic  #22                 // Method org/jboss/as/controller/transform/description/TransformationDescription$Tools.register:(Lorg/jboss/as/controller/transform/description/TransformationDescription;Lorg/jboss/as/controller/SubsystemRegistration;Lorg/jboss/as/controller/ModelVersionRange;)Lorg/jboss/as/controller/transform/TransformersSubRegistration;
     105: pop
     106: goto          67
     109: return

  public void initializeParsers(org.jboss.as.controller.parsing.ExtensionParsingContext);
    Code:
       0: invokestatic  #23                 // Method org/jboss/as/clustering/jgroups/subsystem/JGroupsSchema.values:()[Lorg/jboss/as/clustering/jgroups/subsystem/JGroupsSchema;
       3: astore_2
       4: aload_2
       5: arraylength
       6: istore_3
       7: iconst_0
       8: istore        4
      10: iload         4
      12: iload_3
      13: if_icmpge     50
      16: aload_2
      17: iload         4
      19: aaload
      20: astore        5
      22: aload_1
      23: ldc           #3                  // String jgroups
      25: aload         5
      27: invokevirtual #24                 // Method org/jboss/as/clustering/jgroups/subsystem/JGroupsSchema.getNamespaceUri:()Ljava/lang/String;
      30: new           #25                 // class org/jboss/as/clustering/jgroups/subsystem/JGroupsSubsystemXMLReader
      33: dup
      34: aload         5
      36: invokespecial #26                 // Method org/jboss/as/clustering/jgroups/subsystem/JGroupsSubsystemXMLReader."<init>":(Lorg/jboss/as/clustering/jgroups/subsystem/JGroupsSchema;)V
      39: invokeinterface #27,  4           // InterfaceMethod org/jboss/as/controller/parsing/ExtensionParsingContext.setSubsystemXmlMapping:(Ljava/lang/String;Ljava/lang/String;Lorg/jboss/staxmapper/XMLElementReader;)V
      44: iinc          4, 1
      47: goto          10
      50: return

  static {};
    Code:
       0: new           #28                 // class org/jboss/as/clustering/jgroups/LogFactory
       3: dup
       4: invokespecial #29                 // Method org/jboss/as/clustering/jgroups/LogFactory."<init>":()V
       7: invokestatic  #30                 // Method org/jgroups/logging/LogFactory.setCustomLogFactory:(Lorg/jgroups/logging/CustomLogFactory;)V
      10: return
}
