Compiled from "RemoteSiteResourceDefinition.java"
final class org.jboss.as.clustering.jgroups.subsystem.RemoteSiteResourceDefinition$1 implements org.jboss.as.controller.transform.description.AttributeConverter {
  org.jboss.as.clustering.jgroups.subsystem.RemoteSiteResourceDefinition$1();
    Code:
       0: aload_0
       1: invokespecial #1                  // Method java/lang/Object."<init>":()V
       4: return

  public void convertOperationParameter(org.jboss.as.controller.PathAddress, java.lang.String, org.jboss.dmr.ModelNode, org.jboss.dmr.ModelNode, org.jboss.as.controller.transform.TransformationContext);
    Code:
       0: return

  public void convertResourceAttribute(org.jboss.as.controller.PathAddress, java.lang.String, org.jboss.dmr.ModelNode, org.jboss.as.controller.transform.TransformationContext);
    Code:
       0: aload         4
       2: aload_1
       3: invokeinterface #2,  2            // InterfaceMethod org/jboss/as/controller/transform/TransformationContext.readResourceFromRoot:(Lorg/jboss/as/controller/PathAddress;)Lorg/jboss/as/controller/registry/Resource;
       8: invokeinterface #3,  1            // InterfaceMethod org/jboss/as/controller/registry/Resource.getModel:()Lorg/jboss/dmr/ModelNode;
      13: astore        5
      15: aload         5
      17: getstatic     #4                  // Field org/jboss/as/clustering/jgroups/subsystem/RemoteSiteResourceDefinition$Attribute.CHANNEL:Lorg/jboss/as/clustering/jgroups/subsystem/RemoteSiteResourceDefinition$Attribute;
      20: invokevirtual #5                  // Method org/jboss/as/clustering/jgroups/subsystem/RemoteSiteResourceDefinition$Attribute.getDefinition:()Lorg/jboss/as/controller/AttributeDefinition;
      23: invokevirtual #6                  // Method org/jboss/as/controller/AttributeDefinition.getName:()Ljava/lang/String;
      26: invokevirtual #7                  // Method org/jboss/dmr/ModelNode.get:(Ljava/lang/String;)Lorg/jboss/dmr/ModelNode;
      29: invokevirtual #8                  // Method org/jboss/dmr/ModelNode.asString:()Ljava/lang/String;
      32: astore        6
      34: getstatic     #9                  // Field org/jboss/as/clustering/jgroups/subsystem/RemoteSiteResourceDefinition$DeprecatedAttribute.STACK:Lorg/jboss/as/clustering/jgroups/subsystem/RemoteSiteResourceDefinition$DeprecatedAttribute;
      37: invokevirtual #10                 // Method org/jboss/as/clustering/jgroups/subsystem/RemoteSiteResourceDefinition$DeprecatedAttribute.getDefinition:()Lorg/jboss/as/controller/AttributeDefinition;
      40: invokevirtual #6                  // Method org/jboss/as/controller/AttributeDefinition.getName:()Ljava/lang/String;
      43: aload_2
      44: invokevirtual #11                 // Method java/lang/String.equals:(Ljava/lang/Object;)Z
      47: ifeq          181
      50: aload_1
      51: iconst_0
      52: aload_1
      53: invokevirtual #12                 // Method org/jboss/as/controller/PathAddress.size:()I
      56: iconst_3
      57: isub
      58: invokevirtual #13                 // Method org/jboss/as/controller/PathAddress.subAddress:(II)Lorg/jboss/as/controller/PathAddress;
      61: astore        7
      63: aload         7
      65: iconst_1
      66: anewarray     #14                 // class org/jboss/as/controller/PathElement
      69: dup
      70: iconst_0
      71: aload         6
      73: invokestatic  #15                 // Method org/jboss/as/clustering/jgroups/subsystem/ChannelResourceDefinition.pathElement:(Ljava/lang/String;)Lorg/jboss/as/controller/PathElement;
      76: aastore
      77: invokevirtual #16                 // Method org/jboss/as/controller/PathAddress.append:([Lorg/jboss/as/controller/PathElement;)Lorg/jboss/as/controller/PathAddress;
      80: astore        8
      82: aload         4
      84: aload         8
      86: invokeinterface #2,  2            // InterfaceMethod org/jboss/as/controller/transform/TransformationContext.readResourceFromRoot:(Lorg/jboss/as/controller/PathAddress;)Lorg/jboss/as/controller/registry/Resource;
      91: invokeinterface #3,  1            // InterfaceMethod org/jboss/as/controller/registry/Resource.getModel:()Lorg/jboss/dmr/ModelNode;
      96: astore        9
      98: aload         9
     100: getstatic     #17                 // Field org/jboss/as/clustering/jgroups/subsystem/ChannelResourceDefinition$Attribute.STACK:Lorg/jboss/as/clustering/jgroups/subsystem/ChannelResourceDefinition$Attribute;
     103: invokevirtual #18                 // Method org/jboss/as/clustering/jgroups/subsystem/ChannelResourceDefinition$Attribute.getDefinition:()Lorg/jboss/as/controller/AttributeDefinition;
     106: invokevirtual #6                  // Method org/jboss/as/controller/AttributeDefinition.getName:()Ljava/lang/String;
     109: invokevirtual #19                 // Method org/jboss/dmr/ModelNode.hasDefined:(Ljava/lang/String;)Z
     112: ifeq          140
     115: aload_3
     116: aload         9
     118: getstatic     #17                 // Field org/jboss/as/clustering/jgroups/subsystem/ChannelResourceDefinition$Attribute.STACK:Lorg/jboss/as/clustering/jgroups/subsystem/ChannelResourceDefinition$Attribute;
     121: invokevirtual #18                 // Method org/jboss/as/clustering/jgroups/subsystem/ChannelResourceDefinition$Attribute.getDefinition:()Lorg/jboss/as/controller/AttributeDefinition;
     124: invokevirtual #6                  // Method org/jboss/as/controller/AttributeDefinition.getName:()Ljava/lang/String;
     127: invokevirtual #7                  // Method org/jboss/dmr/ModelNode.get:(Ljava/lang/String;)Lorg/jboss/dmr/ModelNode;
     130: invokevirtual #8                  // Method org/jboss/dmr/ModelNode.asString:()Ljava/lang/String;
     133: invokevirtual #20                 // Method org/jboss/dmr/ModelNode.set:(Ljava/lang/String;)Lorg/jboss/dmr/ModelNode;
     136: pop
     137: goto          178
     140: aload         4
     142: aload         7
     144: invokeinterface #2,  2            // InterfaceMethod org/jboss/as/controller/transform/TransformationContext.readResourceFromRoot:(Lorg/jboss/as/controller/PathAddress;)Lorg/jboss/as/controller/registry/Resource;
     149: invokeinterface #3,  1            // InterfaceMethod org/jboss/as/controller/registry/Resource.getModel:()Lorg/jboss/dmr/ModelNode;
     154: astore        10
     156: aload_3
     157: aload         10
     159: getstatic     #21                 // Field org/jboss/as/clustering/jgroups/subsystem/JGroupsSubsystemResourceDefinition$Attribute.DEFAULT_STACK:Lorg/jboss/as/clustering/jgroups/subsystem/JGroupsSubsystemResourceDefinition$Attribute;
     162: invokevirtual #22                 // Method org/jboss/as/clustering/jgroups/subsystem/JGroupsSubsystemResourceDefinition$Attribute.getDefinition:()Lorg/jboss/as/controller/AttributeDefinition;
     165: invokevirtual #6                  // Method org/jboss/as/controller/AttributeDefinition.getName:()Ljava/lang/String;
     168: invokevirtual #7                  // Method org/jboss/dmr/ModelNode.get:(Ljava/lang/String;)Lorg/jboss/dmr/ModelNode;
     171: invokevirtual #8                  // Method org/jboss/dmr/ModelNode.asString:()Ljava/lang/String;
     174: invokevirtual #20                 // Method org/jboss/dmr/ModelNode.set:(Ljava/lang/String;)Lorg/jboss/dmr/ModelNode;
     177: pop
     178: goto          215
     181: getstatic     #23                 // Field org/jboss/as/clustering/jgroups/subsystem/RemoteSiteResourceDefinition$DeprecatedAttribute.CLUSTER:Lorg/jboss/as/clustering/jgroups/subsystem/RemoteSiteResourceDefinition$DeprecatedAttribute;
     184: invokevirtual #10                 // Method org/jboss/as/clustering/jgroups/subsystem/RemoteSiteResourceDefinition$DeprecatedAttribute.getDefinition:()Lorg/jboss/as/controller/AttributeDefinition;
     187: invokevirtual #6                  // Method org/jboss/as/controller/AttributeDefinition.getName:()Ljava/lang/String;
     190: aload_2
     191: invokevirtual #11                 // Method java/lang/String.equals:(Ljava/lang/Object;)Z
     194: ifeq          207
     197: aload_3
     198: aload         6
     200: invokevirtual #20                 // Method org/jboss/dmr/ModelNode.set:(Ljava/lang/String;)Lorg/jboss/dmr/ModelNode;
     203: pop
     204: goto          215
     207: new           #24                 // class java/lang/IllegalStateException
     210: dup
     211: invokespecial #25                 // Method java/lang/IllegalStateException."<init>":()V
     214: athrow
     215: return
}
