Compiled from "TransportConfigurationBuilder.java"
public class org.jboss.as.clustering.jgroups.subsystem.TransportConfigurationBuilder extends org.jboss.as.clustering.jgroups.subsystem.AbstractProtocolConfigurationBuilder<org.wildfly.clustering.jgroups.spi.TransportConfiguration> implements org.wildfly.clustering.jgroups.spi.TransportConfiguration {
  private org.wildfly.clustering.service.ValueDependency<org.jboss.as.network.SocketBinding> diagnosticsSocketBinding;

  private org.wildfly.clustering.jgroups.spi.TransportConfiguration$Topology topology;

  public org.jboss.as.clustering.jgroups.subsystem.TransportConfigurationBuilder(java.lang.String, java.lang.String);
    Code:
       0: aload_0
       1: aload_1
       2: aload_2
       3: invokespecial #1                  // Method org/jboss/as/clustering/jgroups/subsystem/AbstractProtocolConfigurationBuilder."<init>":(Ljava/lang/String;Ljava/lang/String;)V
       6: aload_0
       7: aconst_null
       8: putfield      #2                  // Field topology:Lorg/wildfly/clustering/jgroups/spi/TransportConfiguration$Topology;
      11: return

  public org.jboss.msc.service.ServiceBuilder<org.wildfly.clustering.jgroups.spi.TransportConfiguration> build(org.jboss.msc.service.ServiceTarget);
    Code:
       0: aload_0
       1: aload_1
       2: invokespecial #3                  // Method org/jboss/as/clustering/jgroups/subsystem/AbstractProtocolConfigurationBuilder.build:(Lorg/jboss/msc/service/ServiceTarget;)Lorg/jboss/msc/service/ServiceBuilder;
       5: astore_2
       6: aload_0
       7: getfield      #4                  // Field diagnosticsSocketBinding:Lorg/wildfly/clustering/service/ValueDependency;
      10: ifnull        24
      13: aload_0
      14: getfield      #4                  // Field diagnosticsSocketBinding:Lorg/wildfly/clustering/service/ValueDependency;
      17: aload_2
      18: invokeinterface #5,  2            // InterfaceMethod org/wildfly/clustering/service/ValueDependency.register:(Lorg/jboss/msc/service/ServiceBuilder;)Lorg/jboss/msc/service/ServiceBuilder;
      23: pop
      24: aload_2
      25: areturn

  public org.wildfly.clustering.jgroups.spi.TransportConfiguration getValue();
    Code:
       0: aload_0
       1: areturn

  public org.wildfly.clustering.service.Builder<org.wildfly.clustering.jgroups.spi.TransportConfiguration> configure(org.jboss.as.controller.OperationContext, org.jboss.dmr.ModelNode) throws org.jboss.as.controller.OperationFailedException;
    Code:
       0: getstatic     #6                  // Field org/jboss/as/clustering/jgroups/subsystem/TransportResourceDefinition$Attribute.MACHINE:Lorg/jboss/as/clustering/jgroups/subsystem/TransportResourceDefinition$Attribute;
       3: invokevirtual #7                  // Method org/jboss/as/clustering/jgroups/subsystem/TransportResourceDefinition$Attribute.getDefinition:()Lorg/jboss/as/controller/AttributeDefinition;
       6: aload_1
       7: aload_2
       8: invokevirtual #8                  // Method org/jboss/as/controller/AttributeDefinition.resolveModelAttribute:(Lorg/jboss/as/controller/OperationContext;Lorg/jboss/dmr/ModelNode;)Lorg/jboss/dmr/ModelNode;
      11: invokestatic  #9                  // Method org/jboss/as/clustering/dmr/ModelNodes.asString:(Lorg/jboss/dmr/ModelNode;)Ljava/lang/String;
      14: astore_3
      15: getstatic     #10                 // Field org/jboss/as/clustering/jgroups/subsystem/TransportResourceDefinition$Attribute.RACK:Lorg/jboss/as/clustering/jgroups/subsystem/TransportResourceDefinition$Attribute;
      18: invokevirtual #7                  // Method org/jboss/as/clustering/jgroups/subsystem/TransportResourceDefinition$Attribute.getDefinition:()Lorg/jboss/as/controller/AttributeDefinition;
      21: aload_1
      22: aload_2
      23: invokevirtual #8                  // Method org/jboss/as/controller/AttributeDefinition.resolveModelAttribute:(Lorg/jboss/as/controller/OperationContext;Lorg/jboss/dmr/ModelNode;)Lorg/jboss/dmr/ModelNode;
      26: invokestatic  #9                  // Method org/jboss/as/clustering/dmr/ModelNodes.asString:(Lorg/jboss/dmr/ModelNode;)Ljava/lang/String;
      29: astore        4
      31: getstatic     #11                 // Field org/jboss/as/clustering/jgroups/subsystem/TransportResourceDefinition$Attribute.SITE:Lorg/jboss/as/clustering/jgroups/subsystem/TransportResourceDefinition$Attribute;
      34: invokevirtual #7                  // Method org/jboss/as/clustering/jgroups/subsystem/TransportResourceDefinition$Attribute.getDefinition:()Lorg/jboss/as/controller/AttributeDefinition;
      37: aload_1
      38: aload_2
      39: invokevirtual #8                  // Method org/jboss/as/controller/AttributeDefinition.resolveModelAttribute:(Lorg/jboss/as/controller/OperationContext;Lorg/jboss/dmr/ModelNode;)Lorg/jboss/dmr/ModelNode;
      42: invokestatic  #9                  // Method org/jboss/as/clustering/dmr/ModelNodes.asString:(Lorg/jboss/dmr/ModelNode;)Ljava/lang/String;
      45: astore        5
      47: aload         5
      49: ifnonnull     61
      52: aload         4
      54: ifnonnull     61
      57: aload_3
      58: ifnull        78
      61: aload_0
      62: new           #12                 // class org/jboss/as/clustering/jgroups/subsystem/TransportConfigurationBuilder$1
      65: dup
      66: aload_0
      67: aload_3
      68: aload         4
      70: aload         5
      72: invokespecial #13                 // Method org/jboss/as/clustering/jgroups/subsystem/TransportConfigurationBuilder$1."<init>":(Lorg/jboss/as/clustering/jgroups/subsystem/TransportConfigurationBuilder;Ljava/lang/String;Ljava/lang/String;Ljava/lang/String;)V
      75: putfield      #2                  // Field topology:Lorg/wildfly/clustering/jgroups/spi/TransportConfiguration$Topology;
      78: getstatic     #14                 // Field org/jboss/as/clustering/jgroups/subsystem/TransportResourceDefinition$Attribute.DIAGNOSTICS_SOCKET_BINDING:Lorg/jboss/as/clustering/jgroups/subsystem/TransportResourceDefinition$Attribute;
      81: invokevirtual #7                  // Method org/jboss/as/clustering/jgroups/subsystem/TransportResourceDefinition$Attribute.getDefinition:()Lorg/jboss/as/controller/AttributeDefinition;
      84: aload_1
      85: aload_2
      86: invokevirtual #8                  // Method org/jboss/as/controller/AttributeDefinition.resolveModelAttribute:(Lorg/jboss/as/controller/OperationContext;Lorg/jboss/dmr/ModelNode;)Lorg/jboss/dmr/ModelNode;
      89: invokestatic  #9                  // Method org/jboss/as/clustering/dmr/ModelNodes.asString:(Lorg/jboss/dmr/ModelNode;)Ljava/lang/String;
      92: astore        6
      94: aload         6
      96: ifnull        118
      99: aload_0
     100: new           #15                 // class org/jboss/as/clustering/controller/CapabilityDependency
     103: dup
     104: aload_1
     105: getstatic     #16                 // Field org/jboss/as/clustering/controller/RequiredCapability.SOCKET_BINDING:Lorg/jboss/as/clustering/controller/RequiredCapability;
     108: aload         6
     110: ldc           #17                 // class org/jboss/as/network/SocketBinding
     112: invokespecial #18                 // Method org/jboss/as/clustering/controller/CapabilityDependency."<init>":(Lorg/jboss/as/controller/OperationContext;Lorg/jboss/as/clustering/controller/Requirement;Ljava/lang/String;Ljava/lang/Class;)V
     115: putfield      #4                  // Field diagnosticsSocketBinding:Lorg/wildfly/clustering/service/ValueDependency;
     118: invokestatic  #19                 // Method org/jboss/as/clustering/jgroups/subsystem/ThreadPoolResourceDefinition.values:()[Lorg/jboss/as/clustering/jgroups/subsystem/ThreadPoolResourceDefinition;
     121: astore        7
     123: aload         7
     125: arraylength
     126: istore        8
     128: iconst_0
     129: istore        9
     131: iload         9
     133: iload         8
     135: if_icmpge     470
     138: aload         7
     140: iload         9
     142: aaload
     143: astore        10
     145: aload         10
     147: invokevirtual #20                 // Method org/jboss/as/clustering/jgroups/subsystem/ThreadPoolResourceDefinition.getPrefix:()Ljava/lang/String;
     150: astore        11
     152: aload_2
     153: aload         10
     155: invokevirtual #21                 // Method org/jboss/as/clustering/jgroups/subsystem/ThreadPoolResourceDefinition.getPathElement:()Lorg/jboss/as/controller/PathElement;
     158: invokevirtual #22                 // Method org/jboss/as/controller/PathElement.getKeyValuePair:()[Ljava/lang/String;
     161: invokevirtual #23                 // Method org/jboss/dmr/ModelNode.get:([Ljava/lang/String;)Lorg/jboss/dmr/ModelNode;
     164: astore        12
     166: aload_0
     167: invokevirtual #24                 // Method getProperties:()Ljava/util/Map;
     170: new           #25                 // class java/lang/StringBuilder
     173: dup
     174: invokespecial #26                 // Method java/lang/StringBuilder."<init>":()V
     177: aload         11
     179: invokevirtual #27                 // Method java/lang/StringBuilder.append:(Ljava/lang/String;)Ljava/lang/StringBuilder;
     182: ldc           #28                 // String .min_threads
     184: invokevirtual #27                 // Method java/lang/StringBuilder.append:(Ljava/lang/String;)Ljava/lang/StringBuilder;
     187: invokevirtual #29                 // Method java/lang/StringBuilder.toString:()Ljava/lang/String;
     190: aload         10
     192: invokevirtual #30                 // Method org/jboss/as/clustering/jgroups/subsystem/ThreadPoolResourceDefinition.getMinThreads:()Lorg/jboss/as/clustering/controller/Attribute;
     195: invokeinterface #31,  1           // InterfaceMethod org/jboss/as/clustering/controller/Attribute.getDefinition:()Ljava/lang/Object;
     200: checkcast     #32                 // class org/jboss/as/controller/AttributeDefinition
     203: aload_1
     204: aload         12
     206: invokevirtual #8                  // Method org/jboss/as/controller/AttributeDefinition.resolveModelAttribute:(Lorg/jboss/as/controller/OperationContext;Lorg/jboss/dmr/ModelNode;)Lorg/jboss/dmr/ModelNode;
     209: invokevirtual #33                 // Method org/jboss/dmr/ModelNode.asString:()Ljava/lang/String;
     212: invokeinterface #34,  3           // InterfaceMethod java/util/Map.put:(Ljava/lang/Object;Ljava/lang/Object;)Ljava/lang/Object;
     217: pop
     218: aload_0
     219: invokevirtual #24                 // Method getProperties:()Ljava/util/Map;
     222: new           #25                 // class java/lang/StringBuilder
     225: dup
     226: invokespecial #26                 // Method java/lang/StringBuilder."<init>":()V
     229: aload         11
     231: invokevirtual #27                 // Method java/lang/StringBuilder.append:(Ljava/lang/String;)Ljava/lang/StringBuilder;
     234: ldc           #35                 // String .max_threads
     236: invokevirtual #27                 // Method java/lang/StringBuilder.append:(Ljava/lang/String;)Ljava/lang/StringBuilder;
     239: invokevirtual #29                 // Method java/lang/StringBuilder.toString:()Ljava/lang/String;
     242: aload         10
     244: invokevirtual #36                 // Method org/jboss/as/clustering/jgroups/subsystem/ThreadPoolResourceDefinition.getMaxThreads:()Lorg/jboss/as/clustering/controller/Attribute;
     247: invokeinterface #31,  1           // InterfaceMethod org/jboss/as/clustering/controller/Attribute.getDefinition:()Ljava/lang/Object;
     252: checkcast     #32                 // class org/jboss/as/controller/AttributeDefinition
     255: aload_1
     256: aload         12
     258: invokevirtual #8                  // Method org/jboss/as/controller/AttributeDefinition.resolveModelAttribute:(Lorg/jboss/as/controller/OperationContext;Lorg/jboss/dmr/ModelNode;)Lorg/jboss/dmr/ModelNode;
     261: invokevirtual #33                 // Method org/jboss/dmr/ModelNode.asString:()Ljava/lang/String;
     264: invokeinterface #34,  3           // InterfaceMethod java/util/Map.put:(Ljava/lang/Object;Ljava/lang/Object;)Ljava/lang/Object;
     269: pop
     270: aload         10
     272: invokevirtual #37                 // Method org/jboss/as/clustering/jgroups/subsystem/ThreadPoolResourceDefinition.getQueueLength:()Lorg/jboss/as/clustering/controller/Attribute;
     275: invokeinterface #31,  1           // InterfaceMethod org/jboss/as/clustering/controller/Attribute.getDefinition:()Ljava/lang/Object;
     280: checkcast     #32                 // class org/jboss/as/controller/AttributeDefinition
     283: aload_1
     284: aload         12
     286: invokevirtual #8                  // Method org/jboss/as/controller/AttributeDefinition.resolveModelAttribute:(Lorg/jboss/as/controller/OperationContext;Lorg/jboss/dmr/ModelNode;)Lorg/jboss/dmr/ModelNode;
     289: invokevirtual #38                 // Method org/jboss/dmr/ModelNode.asInt:()I
     292: istore        13
     294: aload         10
     296: getstatic     #39                 // Field org/jboss/as/clustering/jgroups/subsystem/ThreadPoolResourceDefinition.TIMER:Lorg/jboss/as/clustering/jgroups/subsystem/ThreadPoolResourceDefinition;
     299: if_acmpeq     345
     302: aload_0
     303: invokevirtual #24                 // Method getProperties:()Ljava/util/Map;
     306: new           #25                 // class java/lang/StringBuilder
     309: dup
     310: invokespecial #26                 // Method java/lang/StringBuilder."<init>":()V
     313: aload         11
     315: invokevirtual #27                 // Method java/lang/StringBuilder.append:(Ljava/lang/String;)Ljava/lang/StringBuilder;
     318: ldc           #40                 // String .queue_enabled
     320: invokevirtual #27                 // Method java/lang/StringBuilder.append:(Ljava/lang/String;)Ljava/lang/StringBuilder;
     323: invokevirtual #29                 // Method java/lang/StringBuilder.toString:()Ljava/lang/String;
     326: iload         13
     328: ifle          335
     331: iconst_1
     332: goto          336
     335: iconst_0
     336: invokestatic  #41                 // Method java/lang/String.valueOf:(Z)Ljava/lang/String;
     339: invokeinterface #34,  3           // InterfaceMethod java/util/Map.put:(Ljava/lang/Object;Ljava/lang/Object;)Ljava/lang/Object;
     344: pop
     345: aload_0
     346: invokevirtual #24                 // Method getProperties:()Ljava/util/Map;
     349: new           #25                 // class java/lang/StringBuilder
     352: dup
     353: invokespecial #26                 // Method java/lang/StringBuilder."<init>":()V
     356: aload         11
     358: invokevirtual #27                 // Method java/lang/StringBuilder.append:(Ljava/lang/String;)Ljava/lang/StringBuilder;
     361: ldc           #42                 // String .queue_max_size
     363: invokevirtual #27                 // Method java/lang/StringBuilder.append:(Ljava/lang/String;)Ljava/lang/StringBuilder;
     366: invokevirtual #29                 // Method java/lang/StringBuilder.toString:()Ljava/lang/String;
     369: iload         13
     371: invokestatic  #43                 // Method java/lang/String.valueOf:(I)Ljava/lang/String;
     374: invokeinterface #34,  3           // InterfaceMethod java/util/Map.put:(Ljava/lang/Object;Ljava/lang/Object;)Ljava/lang/Object;
     379: pop
     380: aload_0
     381: invokevirtual #24                 // Method getProperties:()Ljava/util/Map;
     384: new           #25                 // class java/lang/StringBuilder
     387: dup
     388: invokespecial #26                 // Method java/lang/StringBuilder."<init>":()V
     391: aload         11
     393: invokevirtual #27                 // Method java/lang/StringBuilder.append:(Ljava/lang/String;)Ljava/lang/StringBuilder;
     396: ldc           #44                 // String .keep_alive_time
     398: invokevirtual #27                 // Method java/lang/StringBuilder.append:(Ljava/lang/String;)Ljava/lang/StringBuilder;
     401: invokevirtual #29                 // Method java/lang/StringBuilder.toString:()Ljava/lang/String;
     404: aload         10
     406: invokevirtual #45                 // Method org/jboss/as/clustering/jgroups/subsystem/ThreadPoolResourceDefinition.getKeepAliveTime:()Lorg/jboss/as/clustering/controller/Attribute;
     409: invokeinterface #31,  1           // InterfaceMethod org/jboss/as/clustering/controller/Attribute.getDefinition:()Ljava/lang/Object;
     414: checkcast     #32                 // class org/jboss/as/controller/AttributeDefinition
     417: aload_1
     418: aload         12
     420: invokevirtual #8                  // Method org/jboss/as/controller/AttributeDefinition.resolveModelAttribute:(Lorg/jboss/as/controller/OperationContext;Lorg/jboss/dmr/ModelNode;)Lorg/jboss/dmr/ModelNode;
     423: invokevirtual #33                 // Method org/jboss/dmr/ModelNode.asString:()Ljava/lang/String;
     426: invokeinterface #34,  3           // InterfaceMethod java/util/Map.put:(Ljava/lang/Object;Ljava/lang/Object;)Ljava/lang/Object;
     431: pop
     432: aload_0
     433: invokevirtual #24                 // Method getProperties:()Ljava/util/Map;
     436: new           #25                 // class java/lang/StringBuilder
     439: dup
     440: invokespecial #26                 // Method java/lang/StringBuilder."<init>":()V
     443: aload         11
     445: invokevirtual #27                 // Method java/lang/StringBuilder.append:(Ljava/lang/String;)Ljava/lang/StringBuilder;
     448: ldc           #46                 // String .rejection_policy
     450: invokevirtual #27                 // Method java/lang/StringBuilder.append:(Ljava/lang/String;)Ljava/lang/StringBuilder;
     453: invokevirtual #29                 // Method java/lang/StringBuilder.toString:()Ljava/lang/String;
     456: ldc           #47                 // String abort
     458: invokeinterface #34,  3           // InterfaceMethod java/util/Map.put:(Ljava/lang/Object;Ljava/lang/Object;)Ljava/lang/Object;
     463: pop
     464: iinc          9, 1
     467: goto          131
     470: aload_0
     471: aload_1
     472: aload_2
     473: invokespecial #48                 // Method org/jboss/as/clustering/jgroups/subsystem/AbstractProtocolConfigurationBuilder.configure:(Lorg/jboss/as/controller/OperationContext;Lorg/jboss/dmr/ModelNode;)Lorg/wildfly/clustering/service/Builder;
     476: areturn

  public boolean isShared();
    Code:
       0: iconst_0
       1: ireturn

  public org.jboss.as.network.SocketBinding getDiagnosticsSocketBinding();
    Code:
       0: aload_0
       1: getfield      #4                  // Field diagnosticsSocketBinding:Lorg/wildfly/clustering/service/ValueDependency;
       4: ifnull        22
       7: aload_0
       8: getfield      #4                  // Field diagnosticsSocketBinding:Lorg/wildfly/clustering/service/ValueDependency;
      11: invokeinterface #49,  1           // InterfaceMethod org/wildfly/clustering/service/ValueDependency.getValue:()Ljava/lang/Object;
      16: checkcast     #17                 // class org/jboss/as/network/SocketBinding
      19: goto          23
      22: aconst_null
      23: areturn

  public org.wildfly.clustering.jgroups.spi.TransportConfiguration$Topology getTopology();
    Code:
       0: aload_0
       1: getfield      #2                  // Field topology:Lorg/wildfly/clustering/jgroups/spi/TransportConfiguration$Topology;
       4: areturn

  public java.lang.Object getValue() throws java.lang.IllegalStateException, java.lang.IllegalArgumentException;
    Code:
       0: aload_0
       1: invokevirtual #50                 // Method getValue:()Lorg/wildfly/clustering/jgroups/spi/TransportConfiguration;
       4: areturn
}
