Compiled from "ClientCnxnSocketNetty.java"
class org.apache.zookeeper.ClientCnxnSocketNetty$WakeupPacket {
  private static final org.apache.zookeeper.ClientCnxn$Packet instance;

  protected org.apache.zookeeper.ClientCnxnSocketNetty$WakeupPacket();
    Code:
       0: aload_0
       1: invokespecial #1                  // Method java/lang/Object."<init>":()V
       4: return

  public static org.apache.zookeeper.ClientCnxn$Packet getInstance();
    Code:
       0: getstatic     #2                  // Field instance:Lorg/apache/zookeeper/ClientCnxn$Packet;
       3: areturn

  static {};
    Code:
       0: new           #3                  // class org/apache/zookeeper/ClientCnxn$Packet
       3: dup
       4: aconst_null
       5: aconst_null
       6: aconst_null
       7: aconst_null
       8: aconst_null
       9: invokespecial #4                  // Method org/apache/zookeeper/ClientCnxn$Packet."<init>":(Lorg/apache/zookeeper/proto/RequestHeader;Lorg/apache/zookeeper/proto/ReplyHeader;Lorg/apache/jute/Record;Lorg/apache/jute/Record;Lorg/apache/zookeeper/ZooKeeper$WatchRegistration;)V
      12: putstatic     #2                  // Field instance:Lorg/apache/zookeeper/ClientCnxn$Packet;
      15: return
}
