Compiled from "SubjectActions.java"
class org.jboss.security.plugins.SubjectActions$GetSubjectAction implements java.security.PrivilegedAction<javax.security.auth.Subject> {
  static java.security.PrivilegedAction<javax.security.auth.Subject> ACTION;

  private org.jboss.security.plugins.SubjectActions$GetSubjectAction();
    Code:
       0: aload_0
       1: invokespecial #1                  // Method java/lang/Object."<init>":()V
       4: return

  public javax.security.auth.Subject run();
    Code:
       0: aconst_null
       1: astore_1
       2: ldc           #3                  // String javax.security.auth.Subject.container
       4: invokestatic  #4                  // Method javax/security/jacc/PolicyContext.getContext:(Ljava/lang/String;)Ljava/lang/Object;
       7: checkcast     #5                  // class javax/security/auth/Subject
      10: astore_1
      11: goto          29
      14: astore_2
      15: invokestatic  #7                  // Method org/jboss/security/plugins/SubjectActions.getSecurityContext:()Lorg/jboss/security/SecurityContext;
      18: astore_3
      19: aload_3
      20: invokeinterface #8,  1            // InterfaceMethod org/jboss/security/SecurityContext.getUtil:()Lorg/jboss/security/SecurityContextUtil;
      25: invokevirtual #9                  // Method org/jboss/security/SecurityContextUtil.getSubject:()Ljavax/security/auth/Subject;
      28: astore_1
      29: aload_1
      30: areturn
    Exception table:
       from    to  target type
           2    11    14   Class javax/security/jacc/PolicyContextException

  public java.lang.Object run();
    Code:
       0: aload_0
       1: invokevirtual #10                 // Method run:()Ljavax/security/auth/Subject;
       4: areturn

  static {};
    Code:
       0: new           #11                 // class org/jboss/security/plugins/SubjectActions$GetSubjectAction
       3: dup
       4: invokespecial #12                 // Method "<init>":()V
       7: putstatic     #13                 // Field ACTION:Ljava/security/PrivilegedAction;
      10: return
}
