public class org.bouncycastle.crypto.params.KDFParameters implements org.bouncycastle.crypto.DerivationParameters {
  byte[] iv;

  byte[] shared;

  public org.bouncycastle.crypto.params.KDFParameters(byte[], byte[]);
    Code:
       0: aload_0
       1: invokespecial #21                 // Method java/lang/Object."<init>":()V
       4: aload_0
       5: aload_1
       6: putfield      #20                 // Field shared:[B
       9: aload_0
      10: aload_2
      11: putfield      #19                 // Field iv:[B
      14: return

  public byte[] getSharedSecret();
    Code:
       0: aload_0
       1: getfield      #20                 // Field shared:[B
       4: areturn

  public byte[] getIV();
    Code:
       0: aload_0
       1: getfield      #19                 // Field iv:[B
       4: areturn
}
