Compiled from "GridFilesystem.java"
public class org.infinispan.io.GridFilesystem {
  private static final org.infinispan.util.logging.Log log;

  protected final org.infinispan.Cache<java.lang.String, byte[]> data;

  protected final org.infinispan.Cache<java.lang.String, org.infinispan.io.GridFile$Metadata> metadata;

  protected final int defaultChunkSize;

  public org.infinispan.io.GridFilesystem(org.infinispan.Cache<java.lang.String, byte[]>, org.infinispan.Cache<java.lang.String, org.infinispan.io.GridFile$Metadata>, int);
    Code:
       0: aload_0
       1: invokespecial #1                  // Method java/lang/Object."<init>":()V
       4: aload_2
       5: invokeinterface #2,  1            // InterfaceMethod org/infinispan/Cache.getCacheConfiguration:()Lorg/infinispan/configuration/cache/Configuration;
      10: invokevirtual #3                  // Method org/infinispan/configuration/cache/Configuration.clustering:()Lorg/infinispan/configuration/cache/ClusteringConfiguration;
      13: invokevirtual #4                  // Method org/infinispan/configuration/cache/ClusteringConfiguration.cacheMode:()Lorg/infinispan/configuration/cache/CacheMode;
      16: invokevirtual #5                  // Method org/infinispan/configuration/cache/CacheMode.isClustered:()Z
      19: ifeq          48
      22: aload_2
      23: invokeinterface #2,  1            // InterfaceMethod org/infinispan/Cache.getCacheConfiguration:()Lorg/infinispan/configuration/cache/Configuration;
      28: invokevirtual #3                  // Method org/infinispan/configuration/cache/Configuration.clustering:()Lorg/infinispan/configuration/cache/ClusteringConfiguration;
      31: invokevirtual #4                  // Method org/infinispan/configuration/cache/ClusteringConfiguration.cacheMode:()Lorg/infinispan/configuration/cache/CacheMode;
      34: invokevirtual #6                  // Method org/infinispan/configuration/cache/CacheMode.isSynchronous:()Z
      37: ifne          48
      40: getstatic     #7                  // Field log:Lorg/infinispan/util/logging/Log;
      43: invokeinterface #8,  1            // InterfaceMethod org/infinispan/util/logging/Log.warnGridFSMetadataCacheRequiresSync:()V
      48: aload_0
      49: aload_1
      50: putfield      #9                  // Field data:Lorg/infinispan/Cache;
      53: aload_0
      54: aload_2
      55: putfield      #10                 // Field metadata:Lorg/infinispan/Cache;
      58: aload_0
      59: getstatic     #11                 // Field org/infinispan/io/ModularArithmetic.CANNOT_ASSUME_DENOM_IS_POWER_OF_TWO:Z
      62: ifeq          69
      65: iload_3
      66: goto          73
      69: iload_3
      70: invokestatic  #12                 // Method org/infinispan/commons/util/Util.findNextHighestPowerOfTwo:(I)I
      73: putfield      #13                 // Field defaultChunkSize:I
      76: return

  public org.infinispan.io.GridFilesystem(org.infinispan.Cache<java.lang.String, byte[]>, org.infinispan.Cache<java.lang.String, org.infinispan.io.GridFile$Metadata>);
    Code:
       0: aload_0
       1: aload_1
       2: aload_2
       3: getstatic     #11                 // Field org/infinispan/io/ModularArithmetic.CANNOT_ASSUME_DENOM_IS_POWER_OF_TWO:Z
       6: ifeq          15
       9: sipush        8000
      12: goto          18
      15: sipush        8192
      18: invokespecial #14                 // Method "<init>":(Lorg/infinispan/Cache;Lorg/infinispan/Cache;I)V
      21: return

  public java.io.File getFile(java.lang.String);
    Code:
       0: aload_0
       1: aload_1
       2: aload_0
       3: getfield      #13                 // Field defaultChunkSize:I
       6: invokevirtual #15                 // Method getFile:(Ljava/lang/String;I)Ljava/io/File;
       9: areturn

  public java.io.File getFile(java.lang.String, int);
    Code:
       0: new           #16                 // class org/infinispan/io/GridFile
       3: dup
       4: aload_1
       5: aload_0
       6: getfield      #10                 // Field metadata:Lorg/infinispan/Cache;
       9: iload_2
      10: aload_0
      11: invokespecial #17                 // Method org/infinispan/io/GridFile."<init>":(Ljava/lang/String;Lorg/infinispan/Cache;ILorg/infinispan/io/GridFilesystem;)V
      14: areturn

  public java.io.File getFile(java.lang.String, java.lang.String);
    Code:
       0: aload_0
       1: aload_1
       2: aload_2
       3: aload_0
       4: getfield      #13                 // Field defaultChunkSize:I
       7: invokevirtual #18                 // Method getFile:(Ljava/lang/String;Ljava/lang/String;I)Ljava/io/File;
      10: areturn

  public java.io.File getFile(java.lang.String, java.lang.String, int);
    Code:
       0: new           #16                 // class org/infinispan/io/GridFile
       3: dup
       4: aload_1
       5: aload_2
       6: aload_0
       7: getfield      #10                 // Field metadata:Lorg/infinispan/Cache;
      10: iload_3
      11: aload_0
      12: invokespecial #19                 // Method org/infinispan/io/GridFile."<init>":(Ljava/lang/String;Ljava/lang/String;Lorg/infinispan/Cache;ILorg/infinispan/io/GridFilesystem;)V
      15: areturn

  public java.io.File getFile(java.io.File, java.lang.String);
    Code:
       0: aload_0
       1: aload_1
       2: aload_2
       3: aload_0
       4: getfield      #13                 // Field defaultChunkSize:I
       7: invokevirtual #20                 // Method getFile:(Ljava/io/File;Ljava/lang/String;I)Ljava/io/File;
      10: areturn

  public java.io.File getFile(java.io.File, java.lang.String, int);
    Code:
       0: new           #16                 // class org/infinispan/io/GridFile
       3: dup
       4: aload_1
       5: aload_2
       6: aload_0
       7: getfield      #10                 // Field metadata:Lorg/infinispan/Cache;
      10: iload_3
      11: aload_0
      12: invokespecial #21                 // Method org/infinispan/io/GridFile."<init>":(Ljava/io/File;Ljava/lang/String;Lorg/infinispan/Cache;ILorg/infinispan/io/GridFilesystem;)V
      15: areturn

  public java.io.OutputStream getOutput(java.lang.String) throws java.io.IOException;
    Code:
       0: aload_0
       1: aload_1
       2: iconst_0
       3: aload_0
       4: getfield      #13                 // Field defaultChunkSize:I
       7: invokevirtual #22                 // Method getOutput:(Ljava/lang/String;ZI)Ljava/io/OutputStream;
      10: areturn

  public java.io.OutputStream getOutput(java.lang.String, boolean) throws java.io.IOException;
    Code:
       0: aload_0
       1: aload_1
       2: iload_2
       3: aload_0
       4: getfield      #13                 // Field defaultChunkSize:I
       7: invokevirtual #22                 // Method getOutput:(Ljava/lang/String;ZI)Ljava/io/OutputStream;
      10: areturn

  public java.io.OutputStream getOutput(java.lang.String, boolean, int) throws java.io.IOException;
    Code:
       0: aload_0
       1: aload_1
       2: iload_3
       3: invokevirtual #15                 // Method getFile:(Ljava/lang/String;I)Ljava/io/File;
       6: checkcast     #16                 // class org/infinispan/io/GridFile
       9: astore        4
      11: aload_0
      12: aload         4
      14: invokespecial #23                 // Method checkIsNotDirectory:(Lorg/infinispan/io/GridFile;)V
      17: aload_0
      18: aload         4
      20: invokespecial #24                 // Method createIfNeeded:(Lorg/infinispan/io/GridFile;)V
      23: new           #25                 // class org/infinispan/io/GridOutputStream
      26: dup
      27: aload         4
      29: iload_2
      30: aload_0
      31: getfield      #9                  // Field data:Lorg/infinispan/Cache;
      34: invokespecial #26                 // Method org/infinispan/io/GridOutputStream."<init>":(Lorg/infinispan/io/GridFile;ZLorg/infinispan/Cache;)V
      37: areturn

  public java.io.OutputStream getOutput(org.infinispan.io.GridFile) throws java.io.IOException;
    Code:
       0: aload_0
       1: aload_1
       2: invokespecial #23                 // Method checkIsNotDirectory:(Lorg/infinispan/io/GridFile;)V
       5: aload_0
       6: aload_1
       7: invokespecial #24                 // Method createIfNeeded:(Lorg/infinispan/io/GridFile;)V
      10: new           #25                 // class org/infinispan/io/GridOutputStream
      13: dup
      14: aload_1
      15: iconst_0
      16: aload_0
      17: getfield      #9                  // Field data:Lorg/infinispan/Cache;
      20: invokespecial #26                 // Method org/infinispan/io/GridOutputStream."<init>":(Lorg/infinispan/io/GridFile;ZLorg/infinispan/Cache;)V
      23: areturn

  private void checkIsNotDirectory(org.infinispan.io.GridFile) throws java.io.FileNotFoundException;
    Code:
       0: aload_1
       1: invokevirtual #27                 // Method org/infinispan/io/GridFile.isDirectory:()Z
       4: ifeq          34
       7: new           #28                 // class java/io/FileNotFoundException
      10: dup
      11: new           #29                 // class java/lang/StringBuilder
      14: dup
      15: invokespecial #30                 // Method java/lang/StringBuilder."<init>":()V
      18: aload_1
      19: invokevirtual #31                 // Method java/lang/StringBuilder.append:(Ljava/lang/Object;)Ljava/lang/StringBuilder;
      22: ldc           #32                 // String  is a directory.
      24: invokevirtual #33                 // Method java/lang/StringBuilder.append:(Ljava/lang/String;)Ljava/lang/StringBuilder;
      27: invokevirtual #34                 // Method java/lang/StringBuilder.toString:()Ljava/lang/String;
      30: invokespecial #35                 // Method java/io/FileNotFoundException."<init>":(Ljava/lang/String;)V
      33: athrow
      34: return

  private void createIfNeeded(org.infinispan.io.GridFile) throws java.io.IOException;
    Code:
       0: aload_1
       1: invokevirtual #36                 // Method org/infinispan/io/GridFile.exists:()Z
       4: ifne          46
       7: aload_1
       8: invokevirtual #37                 // Method org/infinispan/io/GridFile.createNewFile:()Z
      11: ifne          46
      14: new           #38                 // class java/io/IOException
      17: dup
      18: new           #29                 // class java/lang/StringBuilder
      21: dup
      22: invokespecial #30                 // Method java/lang/StringBuilder."<init>":()V
      25: ldc           #39                 // String creation of
      27: invokevirtual #33                 // Method java/lang/StringBuilder.append:(Ljava/lang/String;)Ljava/lang/StringBuilder;
      30: aload_1
      31: invokevirtual #31                 // Method java/lang/StringBuilder.append:(Ljava/lang/Object;)Ljava/lang/StringBuilder;
      34: ldc           #40                 // String  failed
      36: invokevirtual #33                 // Method java/lang/StringBuilder.append:(Ljava/lang/String;)Ljava/lang/StringBuilder;
      39: invokevirtual #34                 // Method java/lang/StringBuilder.toString:()Ljava/lang/String;
      42: invokespecial #41                 // Method java/io/IOException."<init>":(Ljava/lang/String;)V
      45: athrow
      46: return

  public java.io.InputStream getInput(java.lang.String) throws java.io.FileNotFoundException;
    Code:
       0: aload_0
       1: aload_1
       2: invokevirtual #42                 // Method getFile:(Ljava/lang/String;)Ljava/io/File;
       5: checkcast     #16                 // class org/infinispan/io/GridFile
       8: astore_2
       9: aload_0
      10: aload_2
      11: invokespecial #43                 // Method checkFileIsReadable:(Lorg/infinispan/io/GridFile;)V
      14: new           #44                 // class org/infinispan/io/GridInputStream
      17: dup
      18: aload_2
      19: aload_0
      20: getfield      #9                  // Field data:Lorg/infinispan/Cache;
      23: invokespecial #45                 // Method org/infinispan/io/GridInputStream."<init>":(Lorg/infinispan/io/GridFile;Lorg/infinispan/Cache;)V
      26: areturn

  private void checkFileIsReadable(org.infinispan.io.GridFile) throws java.io.FileNotFoundException;
    Code:
       0: aload_0
       1: aload_1
       2: invokespecial #46                 // Method checkFileExists:(Lorg/infinispan/io/GridFile;)V
       5: aload_0
       6: aload_1
       7: invokespecial #23                 // Method checkIsNotDirectory:(Lorg/infinispan/io/GridFile;)V
      10: return

  private void checkFileExists(org.infinispan.io.GridFile) throws java.io.FileNotFoundException;
    Code:
       0: aload_1
       1: invokevirtual #36                 // Method org/infinispan/io/GridFile.exists:()Z
       4: ifne          19
       7: new           #28                 // class java/io/FileNotFoundException
      10: dup
      11: aload_1
      12: invokevirtual #47                 // Method org/infinispan/io/GridFile.getPath:()Ljava/lang/String;
      15: invokespecial #35                 // Method java/io/FileNotFoundException."<init>":(Ljava/lang/String;)V
      18: athrow
      19: return

  public java.io.InputStream getInput(java.io.File) throws java.io.FileNotFoundException;
    Code:
       0: aload_1
       1: ifnull        15
       4: aload_0
       5: aload_1
       6: invokevirtual #48                 // Method java/io/File.getPath:()Ljava/lang/String;
       9: invokevirtual #49                 // Method getInput:(Ljava/lang/String;)Ljava/io/InputStream;
      12: goto          16
      15: aconst_null
      16: areturn

  public org.infinispan.io.ReadableGridFileChannel getReadableChannel(java.lang.String) throws java.io.FileNotFoundException;
    Code:
       0: aload_0
       1: aload_1
       2: invokevirtual #42                 // Method getFile:(Ljava/lang/String;)Ljava/io/File;
       5: checkcast     #16                 // class org/infinispan/io/GridFile
       8: astore_2
       9: aload_0
      10: aload_2
      11: invokespecial #43                 // Method checkFileIsReadable:(Lorg/infinispan/io/GridFile;)V
      14: new           #50                 // class org/infinispan/io/ReadableGridFileChannel
      17: dup
      18: aload_2
      19: aload_0
      20: getfield      #9                  // Field data:Lorg/infinispan/Cache;
      23: invokespecial #51                 // Method org/infinispan/io/ReadableGridFileChannel."<init>":(Lorg/infinispan/io/GridFile;Lorg/infinispan/Cache;)V
      26: areturn

  public org.infinispan.io.WritableGridFileChannel getWritableChannel(java.lang.String) throws java.io.IOException;
    Code:
       0: aload_0
       1: aload_1
       2: iconst_0
       3: invokevirtual #52                 // Method getWritableChannel:(Ljava/lang/String;Z)Lorg/infinispan/io/WritableGridFileChannel;
       6: areturn

  public org.infinispan.io.WritableGridFileChannel getWritableChannel(java.lang.String, boolean) throws java.io.IOException;
    Code:
       0: aload_0
       1: aload_1
       2: iload_2
       3: aload_0
       4: getfield      #13                 // Field defaultChunkSize:I
       7: invokevirtual #53                 // Method getWritableChannel:(Ljava/lang/String;ZI)Lorg/infinispan/io/WritableGridFileChannel;
      10: areturn

  public org.infinispan.io.WritableGridFileChannel getWritableChannel(java.lang.String, boolean, int) throws java.io.IOException;
    Code:
       0: aload_0
       1: aload_1
       2: iload_3
       3: invokevirtual #15                 // Method getFile:(Ljava/lang/String;I)Ljava/io/File;
       6: checkcast     #16                 // class org/infinispan/io/GridFile
       9: astore        4
      11: aload_0
      12: aload         4
      14: invokespecial #23                 // Method checkIsNotDirectory:(Lorg/infinispan/io/GridFile;)V
      17: aload_0
      18: aload         4
      20: invokespecial #24                 // Method createIfNeeded:(Lorg/infinispan/io/GridFile;)V
      23: new           #54                 // class org/infinispan/io/WritableGridFileChannel
      26: dup
      27: aload         4
      29: aload_0
      30: getfield      #9                  // Field data:Lorg/infinispan/Cache;
      33: iload_2
      34: invokespecial #55                 // Method org/infinispan/io/WritableGridFileChannel."<init>":(Lorg/infinispan/io/GridFile;Lorg/infinispan/Cache;Z)V
      37: areturn

  void remove(java.lang.String);
    Code:
       0: aload_1
       1: ifnonnull     5
       4: return
       5: aload_0
       6: getfield      #10                 // Field metadata:Lorg/infinispan/Cache;
       9: aload_1
      10: invokeinterface #56,  2           // InterfaceMethod org/infinispan/Cache.get:(Ljava/lang/Object;)Ljava/lang/Object;
      15: checkcast     #57                 // class org/infinispan/io/GridFile$Metadata
      18: astore_2
      19: aload_2
      20: ifnonnull     24
      23: return
      24: aload_2
      25: invokevirtual #58                 // Method org/infinispan/io/GridFile$Metadata.getLength:()I
      28: aload_2
      29: invokevirtual #59                 // Method org/infinispan/io/GridFile$Metadata.getChunkSize:()I
      32: idiv
      33: iconst_1
      34: iadd
      35: istore_3
      36: iconst_0
      37: istore        4
      39: iload         4
      41: iload_3
      42: if_icmpge     67
      45: aload_0
      46: getfield      #9                  // Field data:Lorg/infinispan/Cache;
      49: aload_1
      50: iload         4
      52: invokestatic  #60                 // Method org/infinispan/io/FileChunkMapper.getChunkKey:(Ljava/lang/String;I)Ljava/lang/String;
      55: invokeinterface #61,  2           // InterfaceMethod org/infinispan/Cache.remove:(Ljava/lang/Object;)Ljava/lang/Object;
      60: pop
      61: iinc          4, 1
      64: goto          39
      67: return

  static {};
    Code:
       0: ldc           #62                 // class org/infinispan/io/GridFilesystem
       2: invokestatic  #63                 // Method org/infinispan/util/logging/LogFactory.getLog:(Ljava/lang/Class;)Lorg/infinispan/util/logging/Log;
       5: putstatic     #7                  // Field log:Lorg/infinispan/util/logging/Log;
       8: return
}
