Compiled from "ImmutableMarshalledValueByteStream.java"
public final class org.infinispan.io.ImmutableMarshalledValueByteStream extends org.infinispan.io.MarshalledValueByteStream {
  private final byte[] bytes;

  public org.infinispan.io.ImmutableMarshalledValueByteStream(byte[]);
    Code:
       0: aload_0
       1: invokespecial #1                  // Method org/infinispan/io/MarshalledValueByteStream."<init>":()V
       4: aload_0
       5: aload_1
       6: putfield      #2                  // Field bytes:[B
       9: return

  public int size();
    Code:
       0: aload_0
       1: getfield      #2                  // Field bytes:[B
       4: arraylength
       5: ireturn

  public byte[] getRaw();
    Code:
       0: aload_0
       1: getfield      #2                  // Field bytes:[B
       4: areturn

  public void write(int) throws java.io.IOException;
    Code:
       0: new           #3                  // class java/lang/UnsupportedOperationException
       3: dup
       4: ldc           #4                  // String Immutable
       6: invokespecial #5                  // Method java/lang/UnsupportedOperationException."<init>":(Ljava/lang/String;)V
       9: athrow

  public boolean equals(java.lang.Object);
    Code:
       0: aload_1
       1: instanceof    #6                  // class org/infinispan/io/MarshalledValueByteStream
       4: ifeq          84
       7: aload_1
       8: checkcast     #6                  // class org/infinispan/io/MarshalledValueByteStream
      11: astore_2
      12: aload_0
      13: aload_2
      14: if_acmpne     19
      17: iconst_1
      18: ireturn
      19: aload_2
      20: invokevirtual #7                  // Method org/infinispan/io/MarshalledValueByteStream.getRaw:()[B
      23: astore_3
      24: aload_0
      25: getfield      #2                  // Field bytes:[B
      28: aload_3
      29: if_acmpne     34
      32: iconst_1
      33: ireturn
      34: aload_0
      35: invokevirtual #8                  // Method size:()I
      38: aload_2
      39: invokevirtual #9                  // Method org/infinispan/io/MarshalledValueByteStream.size:()I
      42: if_icmpeq     47
      45: iconst_0
      46: ireturn
      47: iconst_0
      48: istore        4
      50: iload         4
      52: aload_0
      53: getfield      #2                  // Field bytes:[B
      56: arraylength
      57: if_icmpge     82
      60: aload_0
      61: getfield      #2                  // Field bytes:[B
      64: iload         4
      66: baload
      67: aload_3
      68: iload         4
      70: baload
      71: if_icmpeq     76
      74: iconst_0
      75: ireturn
      76: iinc          4, 1
      79: goto          50
      82: iconst_1
      83: ireturn
      84: iconst_0
      85: ireturn

  public int hashCode();
    Code:
       0: new           #3                  // class java/lang/UnsupportedOperationException
       3: dup
       4: invokespecial #10                 // Method java/lang/UnsupportedOperationException."<init>":()V
       7: athrow
}
