Compiled from "StandardMatchingStrategy.java"
final class org.modelmapper.convention.StandardMatchingStrategy implements org.modelmapper.spi.MatchingStrategy {
  org.modelmapper.convention.StandardMatchingStrategy();
    Code:
       0: aload_0
       1: invokespecial #14                 // Method java/lang/Object."<init>":()V
       4: return

  public boolean matches(org.modelmapper.spi.PropertyNameInfo);
    Code:
       0: new           #9                  // class org/modelmapper/convention/StandardMatchingStrategy$Matcher
       3: dup
       4: aload_1
       5: invokespecial #21                 // Method org/modelmapper/convention/StandardMatchingStrategy$Matcher."<init>":(Lorg/modelmapper/spi/PropertyNameInfo;)V
       8: invokevirtual #25                 // Method org/modelmapper/convention/StandardMatchingStrategy$Matcher.match:()Z
      11: ireturn

  public boolean isExact();
    Code:
       0: iconst_0
       1: ireturn

  public java.lang.String toString();
    Code:
       0: ldc           #32                 // String Standard
       2: areturn
}
