Compiled from "MonitoredQueuedThreadPool.java"
public class org.eclipse.jetty.util.thread.MonitoredQueuedThreadPool extends org.eclipse.jetty.util.thread.QueuedThreadPool {
  private final org.eclipse.jetty.util.statistic.CounterStatistic queueStats;

  private final org.eclipse.jetty.util.statistic.SampleStatistic queueLatencyStats;

  private final org.eclipse.jetty.util.statistic.SampleStatistic taskLatencyStats;

  private final org.eclipse.jetty.util.statistic.CounterStatistic threadStats;

  public org.eclipse.jetty.util.thread.MonitoredQueuedThreadPool();
    Code:
       0: aload_0
       1: sipush        256
       4: invokespecial #5                  // Method "<init>":(I)V
       7: return

  public org.eclipse.jetty.util.thread.MonitoredQueuedThreadPool(int);
    Code:
       0: aload_0
       1: iload_1
       2: iload_1
       3: ldc           #6                  // int 86400000
       5: new           #7                  // class org/eclipse/jetty/util/BlockingArrayQueue
       8: dup
       9: iload_1
      10: sipush        256
      13: invokespecial #8                  // Method org/eclipse/jetty/util/BlockingArrayQueue."<init>":(II)V
      16: invokespecial #9                  // Method "<init>":(IIILjava/util/concurrent/BlockingQueue;)V
      19: return

  public org.eclipse.jetty.util.thread.MonitoredQueuedThreadPool(int, int, int, java.util.concurrent.BlockingQueue<java.lang.Runnable>);
    Code:
       0: aload_0
       1: iload_1
       2: iload_2
       3: iload_3
       4: aload         4
       6: invokespecial #10                 // Method org/eclipse/jetty/util/thread/QueuedThreadPool."<init>":(IIILjava/util/concurrent/BlockingQueue;)V
       9: aload_0
      10: new           #11                 // class org/eclipse/jetty/util/statistic/CounterStatistic
      13: dup
      14: invokespecial #12                 // Method org/eclipse/jetty/util/statistic/CounterStatistic."<init>":()V
      17: putfield      #4                  // Field queueStats:Lorg/eclipse/jetty/util/statistic/CounterStatistic;
      20: aload_0
      21: new           #13                 // class org/eclipse/jetty/util/statistic/SampleStatistic
      24: dup
      25: invokespecial #14                 // Method org/eclipse/jetty/util/statistic/SampleStatistic."<init>":()V
      28: putfield      #2                  // Field queueLatencyStats:Lorg/eclipse/jetty/util/statistic/SampleStatistic;
      31: aload_0
      32: new           #13                 // class org/eclipse/jetty/util/statistic/SampleStatistic
      35: dup
      36: invokespecial #14                 // Method org/eclipse/jetty/util/statistic/SampleStatistic."<init>":()V
      39: putfield      #1                  // Field taskLatencyStats:Lorg/eclipse/jetty/util/statistic/SampleStatistic;
      42: aload_0
      43: new           #11                 // class org/eclipse/jetty/util/statistic/CounterStatistic
      46: dup
      47: invokespecial #12                 // Method org/eclipse/jetty/util/statistic/CounterStatistic."<init>":()V
      50: putfield      #3                  // Field threadStats:Lorg/eclipse/jetty/util/statistic/CounterStatistic;
      53: aload_0
      54: aload_0
      55: getfield      #4                  // Field queueStats:Lorg/eclipse/jetty/util/statistic/CounterStatistic;
      58: invokevirtual #15                 // Method addBean:(Ljava/lang/Object;)Z
      61: pop
      62: aload_0
      63: aload_0
      64: getfield      #2                  // Field queueLatencyStats:Lorg/eclipse/jetty/util/statistic/SampleStatistic;
      67: invokevirtual #15                 // Method addBean:(Ljava/lang/Object;)Z
      70: pop
      71: aload_0
      72: aload_0
      73: getfield      #1                  // Field taskLatencyStats:Lorg/eclipse/jetty/util/statistic/SampleStatistic;
      76: invokevirtual #15                 // Method addBean:(Ljava/lang/Object;)Z
      79: pop
      80: aload_0
      81: aload_0
      82: getfield      #3                  // Field threadStats:Lorg/eclipse/jetty/util/statistic/CounterStatistic;
      85: invokevirtual #15                 // Method addBean:(Ljava/lang/Object;)Z
      88: pop
      89: return

  public void execute(java.lang.Runnable);
    Code:
       0: aload_0
       1: getfield      #4                  // Field queueStats:Lorg/eclipse/jetty/util/statistic/CounterStatistic;
       4: invokevirtual #16                 // Method org/eclipse/jetty/util/statistic/CounterStatistic.increment:()J
       7: pop2
       8: invokestatic  #17                 // Method java/lang/System.nanoTime:()J
      11: lstore_2
      12: aload_0
      13: new           #18                 // class org/eclipse/jetty/util/thread/MonitoredQueuedThreadPool$1
      16: dup
      17: aload_0
      18: lload_2
      19: aload_1
      20: invokespecial #19                 // Method org/eclipse/jetty/util/thread/MonitoredQueuedThreadPool$1."<init>":(Lorg/eclipse/jetty/util/thread/MonitoredQueuedThreadPool;JLjava/lang/Runnable;)V
      23: invokespecial #20                 // Method org/eclipse/jetty/util/thread/QueuedThreadPool.execute:(Ljava/lang/Runnable;)V
      26: return

  public void reset();
    Code:
       0: aload_0
       1: getfield      #4                  // Field queueStats:Lorg/eclipse/jetty/util/statistic/CounterStatistic;
       4: invokevirtual #21                 // Method org/eclipse/jetty/util/statistic/CounterStatistic.reset:()V
       7: aload_0
       8: getfield      #2                  // Field queueLatencyStats:Lorg/eclipse/jetty/util/statistic/SampleStatistic;
      11: invokevirtual #22                 // Method org/eclipse/jetty/util/statistic/SampleStatistic.reset:()V
      14: aload_0
      15: getfield      #1                  // Field taskLatencyStats:Lorg/eclipse/jetty/util/statistic/SampleStatistic;
      18: invokevirtual #22                 // Method org/eclipse/jetty/util/statistic/SampleStatistic.reset:()V
      21: aload_0
      22: getfield      #3                  // Field threadStats:Lorg/eclipse/jetty/util/statistic/CounterStatistic;
      25: lconst_0
      26: invokevirtual #23                 // Method org/eclipse/jetty/util/statistic/CounterStatistic.reset:(J)V
      29: return

  public long getTasks();
    Code:
       0: aload_0
       1: getfield      #1                  // Field taskLatencyStats:Lorg/eclipse/jetty/util/statistic/SampleStatistic;
       4: invokevirtual #24                 // Method org/eclipse/jetty/util/statistic/SampleStatistic.getCount:()J
       7: lreturn

  public int getMaxBusyThreads();
    Code:
       0: aload_0
       1: getfield      #3                  // Field threadStats:Lorg/eclipse/jetty/util/statistic/CounterStatistic;
       4: invokevirtual #25                 // Method org/eclipse/jetty/util/statistic/CounterStatistic.getMax:()J
       7: l2i
       8: ireturn

  public int getMaxQueueSize();
    Code:
       0: aload_0
       1: getfield      #4                  // Field queueStats:Lorg/eclipse/jetty/util/statistic/CounterStatistic;
       4: invokevirtual #25                 // Method org/eclipse/jetty/util/statistic/CounterStatistic.getMax:()J
       7: l2i
       8: ireturn

  public long getAverageQueueLatency();
    Code:
       0: aload_0
       1: getfield      #2                  // Field queueLatencyStats:Lorg/eclipse/jetty/util/statistic/SampleStatistic;
       4: invokevirtual #26                 // Method org/eclipse/jetty/util/statistic/SampleStatistic.getMean:()D
       7: d2l
       8: lreturn

  public long getMaxQueueLatency();
    Code:
       0: aload_0
       1: getfield      #2                  // Field queueLatencyStats:Lorg/eclipse/jetty/util/statistic/SampleStatistic;
       4: invokevirtual #27                 // Method org/eclipse/jetty/util/statistic/SampleStatistic.getMax:()J
       7: lreturn

  public long getAverageTaskLatency();
    Code:
       0: aload_0
       1: getfield      #1                  // Field taskLatencyStats:Lorg/eclipse/jetty/util/statistic/SampleStatistic;
       4: invokevirtual #26                 // Method org/eclipse/jetty/util/statistic/SampleStatistic.getMean:()D
       7: d2l
       8: lreturn

  public long getMaxTaskLatency();
    Code:
       0: aload_0
       1: getfield      #1                  // Field taskLatencyStats:Lorg/eclipse/jetty/util/statistic/SampleStatistic;
       4: invokevirtual #27                 // Method org/eclipse/jetty/util/statistic/SampleStatistic.getMax:()J
       7: lreturn

  static org.eclipse.jetty.util.statistic.CounterStatistic access$000(org.eclipse.jetty.util.thread.MonitoredQueuedThreadPool);
    Code:
       0: aload_0
       1: getfield      #4                  // Field queueStats:Lorg/eclipse/jetty/util/statistic/CounterStatistic;
       4: areturn

  static org.eclipse.jetty.util.statistic.CounterStatistic access$100(org.eclipse.jetty.util.thread.MonitoredQueuedThreadPool);
    Code:
       0: aload_0
       1: getfield      #3                  // Field threadStats:Lorg/eclipse/jetty/util/statistic/CounterStatistic;
       4: areturn

  static org.eclipse.jetty.util.statistic.SampleStatistic access$200(org.eclipse.jetty.util.thread.MonitoredQueuedThreadPool);
    Code:
       0: aload_0
       1: getfield      #2                  // Field queueLatencyStats:Lorg/eclipse/jetty/util/statistic/SampleStatistic;
       4: areturn

  static org.eclipse.jetty.util.statistic.SampleStatistic access$300(org.eclipse.jetty.util.thread.MonitoredQueuedThreadPool);
    Code:
       0: aload_0
       1: getfield      #1                  // Field taskLatencyStats:Lorg/eclipse/jetty/util/statistic/SampleStatistic;
       4: areturn
}
