Compiled from "JGroupsBroadcastGroupConfiguration.java"
final class org.hornetq.api.core.JGroupsBroadcastGroupConfiguration$JGroupsBroadcastEndpoint$JGroupsReceiver extends org.jgroups.ReceiverAdapter {
  private final java.util.concurrent.BlockingQueue<byte[]> dequeue;

  private org.hornetq.api.core.JGroupsBroadcastGroupConfiguration$JGroupsBroadcastEndpoint$JGroupsReceiver();
    Code:
       0: aload_0
       1: invokespecial #2                  // Method org/jgroups/ReceiverAdapter."<init>":()V
       4: aload_0
       5: new           #3                  // class java/util/concurrent/LinkedBlockingDeque
       8: dup
       9: invokespecial #4                  // Method java/util/concurrent/LinkedBlockingDeque."<init>":()V
      12: putfield      #5                  // Field dequeue:Ljava/util/concurrent/BlockingQueue;
      15: return

  public void receive(org.jgroups.Message);
    Code:
       0: aload_0
       1: getfield      #5                  // Field dequeue:Ljava/util/concurrent/BlockingQueue;
       4: aload_1
       5: invokevirtual #6                  // Method org/jgroups/Message.getBuffer:()[B
       8: invokeinterface #7,  2            // InterfaceMethod java/util/concurrent/BlockingQueue.add:(Ljava/lang/Object;)Z
      13: pop
      14: return

  public byte[] receiveBroadcast() throws java.lang.Exception;
    Code:
       0: aload_0
       1: getfield      #5                  // Field dequeue:Ljava/util/concurrent/BlockingQueue;
       4: invokeinterface #8,  1            // InterfaceMethod java/util/concurrent/BlockingQueue.take:()Ljava/lang/Object;
       9: checkcast     #9                  // class "[B"
      12: areturn

  public byte[] receiveBroadcast(long, java.util.concurrent.TimeUnit) throws java.lang.Exception;
    Code:
       0: aload_0
       1: getfield      #5                  // Field dequeue:Ljava/util/concurrent/BlockingQueue;
       4: lload_1
       5: aload_3
       6: invokeinterface #10,  4           // InterfaceMethod java/util/concurrent/BlockingQueue.poll:(JLjava/util/concurrent/TimeUnit;)Ljava/lang/Object;
      11: checkcast     #9                  // class "[B"
      14: areturn

  org.hornetq.api.core.JGroupsBroadcastGroupConfiguration$JGroupsBroadcastEndpoint$JGroupsReceiver(org.hornetq.api.core.JGroupsBroadcastGroupConfiguration$1);
    Code:
       0: aload_0
       1: invokespecial #1                  // Method "<init>":()V
       4: return
}
