Compiled from "BSON.java"
public class org.bson.BSON {
  public static final byte EOO;

  public static final byte NUMBER;

  public static final byte STRING;

  public static final byte OBJECT;

  public static final byte ARRAY;

  public static final byte BINARY;

  public static final byte UNDEFINED;

  public static final byte OID;

  public static final byte BOOLEAN;

  public static final byte DATE;

  public static final byte NULL;

  public static final byte REGEX;

  public static final byte REF;

  public static final byte CODE;

  public static final byte SYMBOL;

  public static final byte CODE_W_SCOPE;

  public static final byte NUMBER_INT;

  public static final byte TIMESTAMP;

  public static final byte NUMBER_LONG;

  public static final byte MINKEY;

  public static final byte MAXKEY;

  public static final byte B_GENERAL;

  public static final byte B_FUNC;

  public static final byte B_BINARY;

  public static final byte B_UUID;

  private static final int FLAG_GLOBAL;

  private static final int[] FLAG_LOOKUP;

  private static volatile boolean encodeHooks;

  private static volatile boolean decodeHooks;

  private static final org.bson.util.ClassMap<java.util.List<org.bson.Transformer>> encodingHooks;

  private static final org.bson.util.ClassMap<java.util.List<org.bson.Transformer>> decodingHooks;

  public org.bson.BSON();
    Code:
       0: aload_0
       1: invokespecial #1                  // Method java/lang/Object."<init>":()V
       4: return

  public static boolean hasEncodeHooks();
    Code:
       0: getstatic     #2                  // Field encodeHooks:Z
       3: ireturn

  public static boolean hasDecodeHooks();
    Code:
       0: getstatic     #3                  // Field decodeHooks:Z
       3: ireturn

  public static void addEncodingHook(java.lang.Class<?>, org.bson.Transformer);
    Code:
       0: iconst_1
       1: putstatic     #2                  // Field encodeHooks:Z
       4: getstatic     #4                  // Field encodingHooks:Lorg/bson/util/ClassMap;
       7: aload_0
       8: invokevirtual #5                  // Method org/bson/util/ClassMap.get:(Ljava/lang/Object;)Ljava/lang/Object;
      11: checkcast     #6                  // class java/util/List
      14: astore_2
      15: aload_2
      16: ifnonnull     36
      19: new           #7                  // class java/util/concurrent/CopyOnWriteArrayList
      22: dup
      23: invokespecial #8                  // Method java/util/concurrent/CopyOnWriteArrayList."<init>":()V
      26: astore_2
      27: getstatic     #4                  // Field encodingHooks:Lorg/bson/util/ClassMap;
      30: aload_0
      31: aload_2
      32: invokevirtual #9                  // Method org/bson/util/ClassMap.put:(Ljava/lang/Class;Ljava/lang/Object;)Ljava/lang/Object;
      35: pop
      36: aload_2
      37: aload_1
      38: invokeinterface #10,  2           // InterfaceMethod java/util/List.add:(Ljava/lang/Object;)Z
      43: pop
      44: return

  public static void addDecodingHook(java.lang.Class<?>, org.bson.Transformer);
    Code:
       0: iconst_1
       1: putstatic     #3                  // Field decodeHooks:Z
       4: getstatic     #11                 // Field decodingHooks:Lorg/bson/util/ClassMap;
       7: aload_0
       8: invokevirtual #5                  // Method org/bson/util/ClassMap.get:(Ljava/lang/Object;)Ljava/lang/Object;
      11: checkcast     #6                  // class java/util/List
      14: astore_2
      15: aload_2
      16: ifnonnull     36
      19: new           #7                  // class java/util/concurrent/CopyOnWriteArrayList
      22: dup
      23: invokespecial #8                  // Method java/util/concurrent/CopyOnWriteArrayList."<init>":()V
      26: astore_2
      27: getstatic     #11                 // Field decodingHooks:Lorg/bson/util/ClassMap;
      30: aload_0
      31: aload_2
      32: invokevirtual #9                  // Method org/bson/util/ClassMap.put:(Ljava/lang/Class;Ljava/lang/Object;)Ljava/lang/Object;
      35: pop
      36: aload_2
      37: aload_1
      38: invokeinterface #10,  2           // InterfaceMethod java/util/List.add:(Ljava/lang/Object;)Z
      43: pop
      44: return

  public static java.lang.Object applyEncodingHooks(java.lang.Object);
    Code:
       0: aload_0
       1: astore_1
       2: invokestatic  #12                 // Method hasEncodeHooks:()Z
       5: ifeq          21
       8: aload_0
       9: ifnull        21
      12: getstatic     #4                  // Field encodingHooks:Lorg/bson/util/ClassMap;
      15: invokevirtual #13                 // Method org/bson/util/ClassMap.size:()I
      18: ifne          23
      21: aload_1
      22: areturn
      23: getstatic     #4                  // Field encodingHooks:Lorg/bson/util/ClassMap;
      26: aload_0
      27: invokevirtual #14                 // Method java/lang/Object.getClass:()Ljava/lang/Class;
      30: invokevirtual #5                  // Method org/bson/util/ClassMap.get:(Ljava/lang/Object;)Ljava/lang/Object;
      33: checkcast     #6                  // class java/util/List
      36: astore_2
      37: aload_2
      38: ifnull        80
      41: aload_2
      42: invokeinterface #15,  1           // InterfaceMethod java/util/List.iterator:()Ljava/util/Iterator;
      47: astore_3
      48: aload_3
      49: invokeinterface #16,  1           // InterfaceMethod java/util/Iterator.hasNext:()Z
      54: ifeq          80
      57: aload_3
      58: invokeinterface #17,  1           // InterfaceMethod java/util/Iterator.next:()Ljava/lang/Object;
      63: checkcast     #18                 // class org/bson/Transformer
      66: astore        4
      68: aload         4
      70: aload_0
      71: invokeinterface #19,  2           // InterfaceMethod org/bson/Transformer.transform:(Ljava/lang/Object;)Ljava/lang/Object;
      76: astore_1
      77: goto          48
      80: aload_1
      81: areturn

  public static java.lang.Object applyDecodingHooks(java.lang.Object);
    Code:
       0: aload_0
       1: astore_1
       2: invokestatic  #20                 // Method hasDecodeHooks:()Z
       5: ifeq          21
       8: aload_0
       9: ifnull        21
      12: getstatic     #11                 // Field decodingHooks:Lorg/bson/util/ClassMap;
      15: invokevirtual #13                 // Method org/bson/util/ClassMap.size:()I
      18: ifne          23
      21: aload_1
      22: areturn
      23: getstatic     #11                 // Field decodingHooks:Lorg/bson/util/ClassMap;
      26: aload_0
      27: invokevirtual #14                 // Method java/lang/Object.getClass:()Ljava/lang/Class;
      30: invokevirtual #5                  // Method org/bson/util/ClassMap.get:(Ljava/lang/Object;)Ljava/lang/Object;
      33: checkcast     #6                  // class java/util/List
      36: astore_2
      37: aload_2
      38: ifnull        80
      41: aload_2
      42: invokeinterface #15,  1           // InterfaceMethod java/util/List.iterator:()Ljava/util/Iterator;
      47: astore_3
      48: aload_3
      49: invokeinterface #16,  1           // InterfaceMethod java/util/Iterator.hasNext:()Z
      54: ifeq          80
      57: aload_3
      58: invokeinterface #17,  1           // InterfaceMethod java/util/Iterator.next:()Ljava/lang/Object;
      63: checkcast     #18                 // class org/bson/Transformer
      66: astore        4
      68: aload         4
      70: aload_0
      71: invokeinterface #19,  2           // InterfaceMethod org/bson/Transformer.transform:(Ljava/lang/Object;)Ljava/lang/Object;
      76: astore_1
      77: goto          48
      80: aload_1
      81: areturn

  public static java.util.List<org.bson.Transformer> getEncodingHooks(java.lang.Class<?>);
    Code:
       0: getstatic     #4                  // Field encodingHooks:Lorg/bson/util/ClassMap;
       3: aload_0
       4: invokevirtual #5                  // Method org/bson/util/ClassMap.get:(Ljava/lang/Object;)Ljava/lang/Object;
       7: checkcast     #6                  // class java/util/List
      10: areturn

  public static void clearEncodingHooks();
    Code:
       0: iconst_0
       1: putstatic     #2                  // Field encodeHooks:Z
       4: getstatic     #4                  // Field encodingHooks:Lorg/bson/util/ClassMap;
       7: invokevirtual #21                 // Method org/bson/util/ClassMap.clear:()V
      10: return

  public static void removeEncodingHooks(java.lang.Class<?>);
    Code:
       0: getstatic     #4                  // Field encodingHooks:Lorg/bson/util/ClassMap;
       3: aload_0
       4: invokevirtual #22                 // Method org/bson/util/ClassMap.remove:(Ljava/lang/Object;)Ljava/lang/Object;
       7: pop
       8: return

  public static void removeEncodingHook(java.lang.Class<?>, org.bson.Transformer);
    Code:
       0: aload_0
       1: invokestatic  #23                 // Method getEncodingHooks:(Ljava/lang/Class;)Ljava/util/List;
       4: aload_1
       5: invokeinterface #24,  2           // InterfaceMethod java/util/List.remove:(Ljava/lang/Object;)Z
      10: pop
      11: return

  public static java.util.List<org.bson.Transformer> getDecodingHooks(java.lang.Class<?>);
    Code:
       0: getstatic     #11                 // Field decodingHooks:Lorg/bson/util/ClassMap;
       3: aload_0
       4: invokevirtual #5                  // Method org/bson/util/ClassMap.get:(Ljava/lang/Object;)Ljava/lang/Object;
       7: checkcast     #6                  // class java/util/List
      10: areturn

  public static void clearDecodingHooks();
    Code:
       0: iconst_0
       1: putstatic     #3                  // Field decodeHooks:Z
       4: getstatic     #11                 // Field decodingHooks:Lorg/bson/util/ClassMap;
       7: invokevirtual #21                 // Method org/bson/util/ClassMap.clear:()V
      10: return

  public static void removeDecodingHooks(java.lang.Class<?>);
    Code:
       0: getstatic     #11                 // Field decodingHooks:Lorg/bson/util/ClassMap;
       3: aload_0
       4: invokevirtual #22                 // Method org/bson/util/ClassMap.remove:(Ljava/lang/Object;)Ljava/lang/Object;
       7: pop
       8: return

  public static void removeDecodingHook(java.lang.Class<?>, org.bson.Transformer);
    Code:
       0: aload_0
       1: invokestatic  #25                 // Method getDecodingHooks:(Ljava/lang/Class;)Ljava/util/List;
       4: aload_1
       5: invokeinterface #24,  2           // InterfaceMethod java/util/List.remove:(Ljava/lang/Object;)Z
      10: pop
      11: return

  public static void clearAllHooks();
    Code:
       0: invokestatic  #26                 // Method clearEncodingHooks:()V
       3: invokestatic  #27                 // Method clearDecodingHooks:()V
       6: return

  public static byte[] encode(org.bson.BSONObject);
    Code:
       0: new           #28                 // class org/bson/BasicBSONEncoder
       3: dup
       4: invokespecial #29                 // Method org/bson/BasicBSONEncoder."<init>":()V
       7: aload_0
       8: invokevirtual #30                 // Method org/bson/BasicBSONEncoder.encode:(Lorg/bson/BSONObject;)[B
      11: areturn

  public static org.bson.BSONObject decode(byte[]);
    Code:
       0: new           #31                 // class org/bson/BasicBSONDecoder
       3: dup
       4: invokespecial #32                 // Method org/bson/BasicBSONDecoder."<init>":()V
       7: aload_0
       8: invokevirtual #33                 // Method org/bson/BasicBSONDecoder.readObject:([B)Lorg/bson/BSONObject;
      11: areturn

  public static int regexFlags(java.lang.String);
    Code:
       0: iconst_0
       1: istore_1
       2: aload_0
       3: ifnonnull     8
       6: iload_1
       7: ireturn
       8: aload_0
       9: invokevirtual #34                 // Method java/lang/String.toLowerCase:()Ljava/lang/String;
      12: invokevirtual #35                 // Method java/lang/String.toCharArray:()[C
      15: astore_2
      16: aload_2
      17: arraylength
      18: istore_3
      19: iconst_0
      20: istore        4
      22: iload         4
      24: iload_3
      25: if_icmpge     48
      28: aload_2
      29: iload         4
      31: caload
      32: istore        5
      34: iload_1
      35: iload         5
      37: invokestatic  #36                 // Method regexFlag:(C)I
      40: ior
      41: istore_1
      42: iinc          4, 1
      45: goto          22
      48: iload_1
      49: ireturn

  public static int regexFlag(char);
    Code:
       0: getstatic     #37                 // Field FLAG_LOOKUP:[I
       3: iload_0
       4: iaload
       5: istore_1
       6: iload_1
       7: ifne          34
      10: new           #38                 // class java/lang/IllegalArgumentException
      13: dup
      14: ldc           #39                 // String Unrecognized flag [%c]
      16: iconst_1
      17: anewarray     #40                 // class java/lang/Object
      20: dup
      21: iconst_0
      22: iload_0
      23: invokestatic  #41                 // Method java/lang/Character.valueOf:(C)Ljava/lang/Character;
      26: aastore
      27: invokestatic  #42                 // Method java/lang/String.format:(Ljava/lang/String;[Ljava/lang/Object;)Ljava/lang/String;
      30: invokespecial #43                 // Method java/lang/IllegalArgumentException."<init>":(Ljava/lang/String;)V
      33: athrow
      34: iload_1
      35: ireturn

  public static java.lang.String regexFlags(int);
    Code:
       0: iload_0
       1: istore_1
       2: new           #44                 // class java/lang/StringBuilder
       5: dup
       6: invokespecial #45                 // Method java/lang/StringBuilder."<init>":()V
       9: astore_2
      10: iconst_0
      11: istore_3
      12: iload_3
      13: getstatic     #37                 // Field FLAG_LOOKUP:[I
      16: arraylength
      17: if_icmpge     51
      20: iload_1
      21: getstatic     #37                 // Field FLAG_LOOKUP:[I
      24: iload_3
      25: iaload
      26: iand
      27: ifle          45
      30: aload_2
      31: iload_3
      32: i2c
      33: invokevirtual #46                 // Method java/lang/StringBuilder.append:(C)Ljava/lang/StringBuilder;
      36: pop
      37: iload_1
      38: getstatic     #37                 // Field FLAG_LOOKUP:[I
      41: iload_3
      42: iaload
      43: isub
      44: istore_1
      45: iinc          3, 1
      48: goto          12
      51: iload_1
      52: ifle          65
      55: new           #38                 // class java/lang/IllegalArgumentException
      58: dup
      59: ldc           #47                 // String Some flags could not be recognized.
      61: invokespecial #43                 // Method java/lang/IllegalArgumentException."<init>":(Ljava/lang/String;)V
      64: athrow
      65: aload_2
      66: invokevirtual #48                 // Method java/lang/StringBuilder.toString:()Ljava/lang/String;
      69: areturn

  public static int toInt(java.lang.Object);
    Code:
       0: aload_0
       1: ifnonnull     14
       4: new           #38                 // class java/lang/IllegalArgumentException
       7: dup
       8: ldc           #49                 // String Argument shouldn\'t be null
      10: invokespecial #43                 // Method java/lang/IllegalArgumentException."<init>":(Ljava/lang/String;)V
      13: athrow
      14: aload_0
      15: instanceof    #50                 // class java/lang/Number
      18: ifeq          29
      21: aload_0
      22: checkcast     #50                 // class java/lang/Number
      25: invokevirtual #51                 // Method java/lang/Number.intValue:()I
      28: ireturn
      29: aload_0
      30: instanceof    #52                 // class java/lang/Boolean
      33: ifeq          52
      36: aload_0
      37: checkcast     #52                 // class java/lang/Boolean
      40: invokevirtual #53                 // Method java/lang/Boolean.booleanValue:()Z
      43: ifeq          50
      46: iconst_1
      47: goto          51
      50: iconst_0
      51: ireturn
      52: new           #38                 // class java/lang/IllegalArgumentException
      55: dup
      56: new           #44                 // class java/lang/StringBuilder
      59: dup
      60: invokespecial #45                 // Method java/lang/StringBuilder."<init>":()V
      63: ldc           #54                 // String Can\'t convert:
      65: invokevirtual #55                 // Method java/lang/StringBuilder.append:(Ljava/lang/String;)Ljava/lang/StringBuilder;
      68: aload_0
      69: invokevirtual #14                 // Method java/lang/Object.getClass:()Ljava/lang/Class;
      72: invokevirtual #56                 // Method java/lang/Class.getName:()Ljava/lang/String;
      75: invokevirtual #55                 // Method java/lang/StringBuilder.append:(Ljava/lang/String;)Ljava/lang/StringBuilder;
      78: ldc           #57                 // String  to int
      80: invokevirtual #55                 // Method java/lang/StringBuilder.append:(Ljava/lang/String;)Ljava/lang/StringBuilder;
      83: invokevirtual #48                 // Method java/lang/StringBuilder.toString:()Ljava/lang/String;
      86: invokespecial #43                 // Method java/lang/IllegalArgumentException."<init>":(Ljava/lang/String;)V
      89: athrow

  static {};
    Code:
       0: ldc           #59                 // int 65535
       2: newarray       int
       4: putstatic     #37                 // Field FLAG_LOOKUP:[I
       7: getstatic     #37                 // Field FLAG_LOOKUP:[I
      10: bipush        103
      12: sipush        256
      15: iastore
      16: getstatic     #37                 // Field FLAG_LOOKUP:[I
      19: bipush        105
      21: iconst_2
      22: iastore
      23: getstatic     #37                 // Field FLAG_LOOKUP:[I
      26: bipush        109
      28: bipush        8
      30: iastore
      31: getstatic     #37                 // Field FLAG_LOOKUP:[I
      34: bipush        115
      36: bipush        32
      38: iastore
      39: getstatic     #37                 // Field FLAG_LOOKUP:[I
      42: bipush        99
      44: sipush        128
      47: iastore
      48: getstatic     #37                 // Field FLAG_LOOKUP:[I
      51: bipush        120
      53: iconst_4
      54: iastore
      55: getstatic     #37                 // Field FLAG_LOOKUP:[I
      58: bipush        100
      60: iconst_1
      61: iastore
      62: getstatic     #37                 // Field FLAG_LOOKUP:[I
      65: bipush        116
      67: bipush        16
      69: iastore
      70: getstatic     #37                 // Field FLAG_LOOKUP:[I
      73: bipush        117
      75: bipush        64
      77: iastore
      78: iconst_0
      79: putstatic     #2                  // Field encodeHooks:Z
      82: iconst_0
      83: putstatic     #3                  // Field decodeHooks:Z
      86: new           #62                 // class org/bson/util/ClassMap
      89: dup
      90: invokespecial #63                 // Method org/bson/util/ClassMap."<init>":()V
      93: putstatic     #4                  // Field encodingHooks:Lorg/bson/util/ClassMap;
      96: new           #62                 // class org/bson/util/ClassMap
      99: dup
     100: invokespecial #63                 // Method org/bson/util/ClassMap."<init>":()V
     103: putstatic     #11                 // Field decodingHooks:Lorg/bson/util/ClassMap;
     106: return
}
