Compiled from "Scopes.java"
public final class org.sonar.api.resources.Scopes {
  public static final java.lang.String PROJECT;

  public static final java.lang.String DIRECTORY;

  public static final java.lang.String FILE;

  public static final java.lang.String PROGRAM_UNIT;

  public static final java.lang.String BLOCK_UNIT;

  public static final java.lang.String[] SORTED_SCOPES;

  private org.sonar.api.resources.Scopes();
    Code:
       0: aload_0
       1: invokespecial #28                 // Method java/lang/Object."<init>":()V
       4: return

  public static boolean isProject(org.sonar.api.resources.Resource);
    Code:
       0: ldc           #9                  // String PRJ
       2: aload_0
       3: invokevirtual #38                 // Method org/sonar/api/resources/Resource.getScope:()Ljava/lang/String;
       6: invokestatic  #44                 // Method org/sonar/api/internal/apachecommons/lang/StringUtils.equals:(Ljava/lang/String;Ljava/lang/String;)Z
       9: ireturn

  public static boolean isDirectory(org.sonar.api.resources.Resource);
    Code:
       0: ldc           #12                 // String DIR
       2: aload_0
       3: invokevirtual #38                 // Method org/sonar/api/resources/Resource.getScope:()Ljava/lang/String;
       6: invokestatic  #44                 // Method org/sonar/api/internal/apachecommons/lang/StringUtils.equals:(Ljava/lang/String;Ljava/lang/String;)Z
       9: ireturn

  public static boolean isFile(org.sonar.api.resources.Resource);
    Code:
       0: ldc           #15                 // String FIL
       2: aload_0
       3: invokevirtual #38                 // Method org/sonar/api/resources/Resource.getScope:()Ljava/lang/String;
       6: invokestatic  #44                 // Method org/sonar/api/internal/apachecommons/lang/StringUtils.equals:(Ljava/lang/String;Ljava/lang/String;)Z
       9: ireturn

  public static boolean isProgramUnit(org.sonar.api.resources.Resource);
    Code:
       0: ldc           #18                 // String PGU
       2: aload_0
       3: invokevirtual #38                 // Method org/sonar/api/resources/Resource.getScope:()Ljava/lang/String;
       6: invokestatic  #44                 // Method org/sonar/api/internal/apachecommons/lang/StringUtils.equals:(Ljava/lang/String;Ljava/lang/String;)Z
       9: ireturn

  public static boolean isBlockUnit(org.sonar.api.resources.Resource);
    Code:
       0: ldc           #22                 // String BLU
       2: aload_0
       3: invokevirtual #38                 // Method org/sonar/api/resources/Resource.getScope:()Ljava/lang/String;
       6: invokestatic  #44                 // Method org/sonar/api/internal/apachecommons/lang/StringUtils.equals:(Ljava/lang/String;Ljava/lang/String;)Z
       9: ireturn

  public static boolean isHigherThan(org.sonar.api.resources.Resource, java.lang.String);
    Code:
       0: aload_0
       1: invokevirtual #38                 // Method org/sonar/api/resources/Resource.getScope:()Ljava/lang/String;
       4: aload_1
       5: invokestatic  #54                 // Method isHigherThan:(Ljava/lang/String;Ljava/lang/String;)Z
       8: ireturn

  public static boolean isHigherThan(java.lang.String, java.lang.String);
    Code:
       0: getstatic     #57                 // Field SORTED_SCOPES:[Ljava/lang/String;
       3: aload_0
       4: invokestatic  #63                 // Method org/sonar/api/internal/apachecommons/lang/ArrayUtils.indexOf:([Ljava/lang/Object;Ljava/lang/Object;)I
       7: istore_2
       8: getstatic     #57                 // Field SORTED_SCOPES:[Ljava/lang/String;
      11: aload_1
      12: invokestatic  #63                 // Method org/sonar/api/internal/apachecommons/lang/ArrayUtils.indexOf:([Ljava/lang/Object;Ljava/lang/Object;)I
      15: istore_3
      16: iload_2
      17: iload_3
      18: if_icmpge     25
      21: iconst_1
      22: goto          26
      25: iconst_0
      26: ireturn

  public static boolean isHigherThanOrEquals(org.sonar.api.resources.Resource, java.lang.String);
    Code:
       0: aload_0
       1: invokevirtual #38                 // Method org/sonar/api/resources/Resource.getScope:()Ljava/lang/String;
       4: aload_1
       5: invokestatic  #70                 // Method isHigherThanOrEquals:(Ljava/lang/String;Ljava/lang/String;)Z
       8: ireturn

  public static boolean isHigherThanOrEquals(java.lang.String, java.lang.String);
    Code:
       0: getstatic     #57                 // Field SORTED_SCOPES:[Ljava/lang/String;
       3: aload_0
       4: invokestatic  #63                 // Method org/sonar/api/internal/apachecommons/lang/ArrayUtils.indexOf:([Ljava/lang/Object;Ljava/lang/Object;)I
       7: istore_2
       8: getstatic     #57                 // Field SORTED_SCOPES:[Ljava/lang/String;
      11: aload_1
      12: invokestatic  #63                 // Method org/sonar/api/internal/apachecommons/lang/ArrayUtils.indexOf:([Ljava/lang/Object;Ljava/lang/Object;)I
      15: istore_3
      16: iload_2
      17: iload_3
      18: if_icmpgt     25
      21: iconst_1
      22: goto          26
      25: iconst_0
      26: ireturn

  static {};
    Code:
       0: iconst_5
       1: anewarray     #73                 // class java/lang/String
       4: dup
       5: iconst_0
       6: ldc           #9                  // String PRJ
       8: aastore
       9: dup
      10: iconst_1
      11: ldc           #12                 // String DIR
      13: aastore
      14: dup
      15: iconst_2
      16: ldc           #15                 // String FIL
      18: aastore
      19: dup
      20: iconst_3
      21: ldc           #18                 // String PGU
      23: aastore
      24: dup
      25: iconst_4
      26: ldc           #22                 // String BLU
      28: aastore
      29: putstatic     #57                 // Field SORTED_SCOPES:[Ljava/lang/String;
      32: return
}
