Compiled from "RegexRequestURLBuilder.java"
public class org.opensaml.saml.metadata.resolver.impl.RegexRequestURLBuilder implements com.google.common.base.Function<java.lang.String, java.lang.String> {
  private final org.slf4j.Logger log;

  private java.util.regex.Pattern pattern;

  private java.lang.String template;

  public org.opensaml.saml.metadata.resolver.impl.RegexRequestURLBuilder(java.lang.String, java.lang.String);
    Code:
       0: aload_0
       1: invokespecial #1                  // Method java/lang/Object."<init>":()V
       4: aload_0
       5: ldc_w         #2                  // class org/opensaml/saml/metadata/resolver/impl/RegexRequestURLBuilder
       8: invokestatic  #3                  // Method org/slf4j/LoggerFactory.getLogger:(Ljava/lang/Class;)Lorg/slf4j/Logger;
      11: putfield      #4                  // Field log:Lorg/slf4j/Logger;
      14: aload_1
      15: invokestatic  #5                  // Method net/shibboleth/utilities/java/support/primitive/StringSupport.trimOrNull:(Ljava/lang/String;)Ljava/lang/String;
      18: ldc           #6                  // String Regex was null or empty
      20: invokestatic  #7                  // Method net/shibboleth/utilities/java/support/logic/Constraint.isNotNull:(Ljava/lang/Object;Ljava/lang/String;)Ljava/lang/Object;
      23: checkcast     #8                  // class java/lang/String
      26: astore_3
      27: aload_0
      28: aload_3
      29: invokestatic  #9                  // Method java/util/regex/Pattern.compile:(Ljava/lang/String;)Ljava/util/regex/Pattern;
      32: putfield      #10                 // Field pattern:Ljava/util/regex/Pattern;
      35: aload_0
      36: aload_2
      37: invokestatic  #5                  // Method net/shibboleth/utilities/java/support/primitive/StringSupport.trimOrNull:(Ljava/lang/String;)Ljava/lang/String;
      40: ldc           #11                 // String Replacement template was null or empty
      42: invokestatic  #7                  // Method net/shibboleth/utilities/java/support/logic/Constraint.isNotNull:(Ljava/lang/Object;Ljava/lang/String;)Ljava/lang/Object;
      45: checkcast     #8                  // class java/lang/String
      48: putfield      #12                 // Field template:Ljava/lang/String;
      51: return

  public java.lang.String apply(java.lang.String);
    Code:
       0: aload_1
       1: ldc           #13                 // String Entity ID was null
       3: invokestatic  #7                  // Method net/shibboleth/utilities/java/support/logic/Constraint.isNotNull:(Ljava/lang/Object;Ljava/lang/String;)Ljava/lang/Object;
       6: pop
       7: aload_0
       8: getfield      #10                 // Field pattern:Ljava/util/regex/Pattern;
      11: aload_1
      12: invokevirtual #14                 // Method java/util/regex/Pattern.matcher:(Ljava/lang/CharSequence;)Ljava/util/regex/Matcher;
      15: astore_2
      16: aload_2
      17: invokevirtual #15                 // Method java/util/regex/Matcher.matches:()Z
      20: ifeq          67
      23: aload_2
      24: aload_0
      25: getfield      #12                 // Field template:Ljava/lang/String;
      28: invokevirtual #16                 // Method java/util/regex/Matcher.replaceAll:(Ljava/lang/String;)Ljava/lang/String;
      31: astore_3
      32: aload_0
      33: getfield      #4                  // Field log:Lorg/slf4j/Logger;
      36: ldc           #17                 // String Regular expression \'{}\' matched successfully against entity ID \'{}\', returning \'{}\'
      38: iconst_3
      39: anewarray     #18                 // class java/lang/Object
      42: dup
      43: iconst_0
      44: aload_0
      45: getfield      #10                 // Field pattern:Ljava/util/regex/Pattern;
      48: invokevirtual #19                 // Method java/util/regex/Pattern.pattern:()Ljava/lang/String;
      51: aastore
      52: dup
      53: iconst_1
      54: aload_1
      55: aastore
      56: dup
      57: iconst_2
      58: aload_3
      59: aastore
      60: invokeinterface #20,  3           // InterfaceMethod org/slf4j/Logger.debug:(Ljava/lang/String;[Ljava/lang/Object;)V
      65: aload_3
      66: areturn
      67: aload_0
      68: getfield      #4                  // Field log:Lorg/slf4j/Logger;
      71: ldc           #21                 // String Regular expression \'{}\' did not match against entity ID \'{}\', returning null
      73: aload_0
      74: getfield      #10                 // Field pattern:Ljava/util/regex/Pattern;
      77: invokevirtual #19                 // Method java/util/regex/Pattern.pattern:()Ljava/lang/String;
      80: aload_1
      81: invokeinterface #22,  4           // InterfaceMethod org/slf4j/Logger.debug:(Ljava/lang/String;Ljava/lang/Object;Ljava/lang/Object;)V
      86: aconst_null
      87: areturn
      88: astore_2
      89: aload_0
      90: getfield      #4                  // Field log:Lorg/slf4j/Logger;
      93: ldc           #24                 // String Error evaluating regular expression \'{}\' against entity ID \'{}\'
      95: iconst_3
      96: anewarray     #18                 // class java/lang/Object
      99: dup
     100: iconst_0
     101: aload_0
     102: getfield      #10                 // Field pattern:Ljava/util/regex/Pattern;
     105: invokevirtual #19                 // Method java/util/regex/Pattern.pattern:()Ljava/lang/String;
     108: aastore
     109: dup
     110: iconst_1
     111: aload_1
     112: aastore
     113: dup
     114: iconst_2
     115: aload_2
     116: aastore
     117: invokeinterface #25,  3           // InterfaceMethod org/slf4j/Logger.warn:(Ljava/lang/String;[Ljava/lang/Object;)V
     122: aconst_null
     123: areturn
    Exception table:
       from    to  target type
           7    66    88   Class java/lang/Throwable
          67    87    88   Class java/lang/Throwable

  public java.lang.Object apply(java.lang.Object);
    Code:
       0: aload_0
       1: aload_1
       2: checkcast     #8                  // class java/lang/String
       5: invokevirtual #26                 // Method apply:(Ljava/lang/String;)Ljava/lang/String;
       8: areturn
}
