Compiled from "MetastoreFactory.java"
public class org.apache.bookkeeper.metastore.MetastoreFactory {
  public org.apache.bookkeeper.metastore.MetastoreFactory();
    Code:
       0: aload_0
       1: invokespecial #1                  // Method java/lang/Object."<init>":()V
       4: return

  public static org.apache.bookkeeper.metastore.MetaStore createMetaStore(java.lang.String) throws org.apache.bookkeeper.metastore.MetastoreException;
    Code:
       0: aload_0
       1: ldc           #2                  // class org/apache/bookkeeper/metastore/MetaStore
       3: invokestatic  #3                  // Method org/apache/bookkeeper/common/util/ReflectionUtils.newInstance:(Ljava/lang/String;Ljava/lang/Class;)Ljava/lang/Object;
       6: checkcast     #2                  // class org/apache/bookkeeper/metastore/MetaStore
       9: areturn
      10: astore_1
      11: new           #5                  // class org/apache/bookkeeper/metastore/MetastoreException
      14: dup
      15: new           #6                  // class java/lang/StringBuilder
      18: dup
      19: invokespecial #7                  // Method java/lang/StringBuilder."<init>":()V
      22: ldc           #8                  // String Failed to instantiate metastore :
      24: invokevirtual #9                  // Method java/lang/StringBuilder.append:(Ljava/lang/String;)Ljava/lang/StringBuilder;
      27: aload_0
      28: invokevirtual #9                  // Method java/lang/StringBuilder.append:(Ljava/lang/String;)Ljava/lang/StringBuilder;
      31: invokevirtual #10                 // Method java/lang/StringBuilder.toString:()Ljava/lang/String;
      34: invokespecial #11                 // Method org/apache/bookkeeper/metastore/MetastoreException."<init>":(Ljava/lang/String;)V
      37: athrow
    Exception table:
       from    to  target type
           0     9    10   Class java/lang/Throwable
}
