Compiled from "BeanComponentDefinitionBuilder.java"
public class org.springframework.data.config.BeanComponentDefinitionBuilder {
  private final org.w3c.dom.Element defaultSource;

  private final org.springframework.beans.factory.xml.ParserContext context;

  public org.springframework.data.config.BeanComponentDefinitionBuilder(org.w3c.dom.Element, org.springframework.beans.factory.xml.ParserContext);
    Code:
       0: aload_0
       1: invokespecial #1                  // Method java/lang/Object."<init>":()V
       4: aload_1
       5: ldc           #2                  // String DefaultSource must not be null!
       7: invokestatic  #3                  // Method org/springframework/util/Assert.notNull:(Ljava/lang/Object;Ljava/lang/String;)V
      10: aload_2
      11: ldc           #4                  // String Context must not be null!
      13: invokestatic  #3                  // Method org/springframework/util/Assert.notNull:(Ljava/lang/Object;Ljava/lang/String;)V
      16: aload_0
      17: aload_1
      18: putfield      #5                  // Field defaultSource:Lorg/w3c/dom/Element;
      21: aload_0
      22: aload_2
      23: putfield      #6                  // Field context:Lorg/springframework/beans/factory/xml/ParserContext;
      26: return

  public org.springframework.beans.factory.parsing.BeanComponentDefinition getComponent(org.springframework.beans.factory.support.BeanDefinitionBuilder);
    Code:
       0: aload_1
       1: ldc           #7                  // String Builder must not be null!
       3: invokestatic  #3                  // Method org/springframework/util/Assert.notNull:(Ljava/lang/Object;Ljava/lang/String;)V
       6: aload_1
       7: invokevirtual #8                  // Method org/springframework/beans/factory/support/BeanDefinitionBuilder.getRawBeanDefinition:()Lorg/springframework/beans/factory/support/AbstractBeanDefinition;
      10: astore_2
      11: aload_2
      12: aload_0
      13: getfield      #6                  // Field context:Lorg/springframework/beans/factory/xml/ParserContext;
      16: invokevirtual #9                  // Method org/springframework/beans/factory/xml/ParserContext.getRegistry:()Lorg/springframework/beans/factory/support/BeanDefinitionRegistry;
      19: aload_0
      20: getfield      #6                  // Field context:Lorg/springframework/beans/factory/xml/ParserContext;
      23: invokevirtual #10                 // Method org/springframework/beans/factory/xml/ParserContext.isNested:()Z
      26: invokestatic  #11                 // Method org/springframework/beans/factory/support/BeanDefinitionReaderUtils.generateBeanName:(Lorg/springframework/beans/factory/config/BeanDefinition;Lorg/springframework/beans/factory/support/BeanDefinitionRegistry;Z)Ljava/lang/String;
      29: astore_3
      30: aload_0
      31: aload_1
      32: aload_3
      33: invokevirtual #12                 // Method getComponent:(Lorg/springframework/beans/factory/support/BeanDefinitionBuilder;Ljava/lang/String;)Lorg/springframework/beans/factory/parsing/BeanComponentDefinition;
      36: areturn

  public org.springframework.beans.factory.parsing.BeanComponentDefinition getComponentIdButFallback(org.springframework.beans.factory.support.BeanDefinitionBuilder, java.lang.String);
    Code:
       0: aload_2
       1: ldc           #13                 // String Fallback component id must not be null or empty!
       3: invokestatic  #14                 // Method org/springframework/util/Assert.hasText:(Ljava/lang/String;Ljava/lang/String;)V
       6: aload_0
       7: getfield      #5                  // Field defaultSource:Lorg/w3c/dom/Element;
      10: ldc           #15                 // String id
      12: invokeinterface #16,  2           // InterfaceMethod org/w3c/dom/Element.getAttribute:(Ljava/lang/String;)Ljava/lang/String;
      17: astore_3
      18: aload_0
      19: aload_1
      20: aload_3
      21: invokestatic  #17                 // Method org/springframework/util/StringUtils.hasText:(Ljava/lang/String;)Z
      24: ifeq          31
      27: aload_3
      28: goto          32
      31: aload_2
      32: invokevirtual #12                 // Method getComponent:(Lorg/springframework/beans/factory/support/BeanDefinitionBuilder;Ljava/lang/String;)Lorg/springframework/beans/factory/parsing/BeanComponentDefinition;
      35: areturn

  public org.springframework.beans.factory.parsing.BeanComponentDefinition getComponent(org.springframework.beans.factory.support.BeanDefinitionBuilder, java.lang.String);
    Code:
       0: aload_0
       1: aload_1
       2: aload_2
       3: aload_0
       4: getfield      #5                  // Field defaultSource:Lorg/w3c/dom/Element;
       7: invokevirtual #18                 // Method getComponent:(Lorg/springframework/beans/factory/support/BeanDefinitionBuilder;Ljava/lang/String;Ljava/lang/Object;)Lorg/springframework/beans/factory/parsing/BeanComponentDefinition;
      10: areturn

  public org.springframework.beans.factory.parsing.BeanComponentDefinition getComponent(org.springframework.beans.factory.support.BeanDefinitionBuilder, java.lang.String, java.lang.Object);
    Code:
       0: aload_1
       1: ldc           #7                  // String Builder must not be null!
       3: invokestatic  #3                  // Method org/springframework/util/Assert.notNull:(Ljava/lang/Object;Ljava/lang/String;)V
       6: aload_2
       7: ldc           #19                 // String Name of bean must not be null or empty!
       9: invokestatic  #14                 // Method org/springframework/util/Assert.hasText:(Ljava/lang/String;Ljava/lang/String;)V
      12: aload_1
      13: invokevirtual #8                  // Method org/springframework/beans/factory/support/BeanDefinitionBuilder.getRawBeanDefinition:()Lorg/springframework/beans/factory/support/AbstractBeanDefinition;
      16: astore        4
      18: aload         4
      20: aload_0
      21: getfield      #6                  // Field context:Lorg/springframework/beans/factory/xml/ParserContext;
      24: aload_3
      25: invokevirtual #20                 // Method org/springframework/beans/factory/xml/ParserContext.extractSource:(Ljava/lang/Object;)Ljava/lang/Object;
      28: invokevirtual #21                 // Method org/springframework/beans/factory/support/AbstractBeanDefinition.setSource:(Ljava/lang/Object;)V
      31: new           #22                 // class org/springframework/beans/factory/parsing/BeanComponentDefinition
      34: dup
      35: aload         4
      37: aload_2
      38: invokespecial #23                 // Method org/springframework/beans/factory/parsing/BeanComponentDefinition."<init>":(Lorg/springframework/beans/factory/config/BeanDefinition;Ljava/lang/String;)V
      41: areturn
}
