Compiled from "NoopDiscoveryClientAutoConfiguration.java"
public class org.springframework.cloud.client.discovery.noop.NoopDiscoveryClientAutoConfiguration$Boot15PortFinderConfiguration {
  protected org.springframework.cloud.client.discovery.noop.NoopDiscoveryClientAutoConfiguration$Boot15PortFinderConfiguration();
    Code:
       0: aload_0
       1: invokespecial #1                  // Method java/lang/Object."<init>":()V
       4: return

  public org.springframework.cloud.client.discovery.noop.NoopDiscoveryClientAutoConfiguration$PortFinder portFinder(org.springframework.context.ApplicationContext);
    Code:
       0: new           #2                  // class org/springframework/cloud/client/discovery/noop/NoopDiscoveryClientAutoConfiguration$Boot15PortFinderConfiguration$1
       3: dup
       4: aload_0
       5: invokespecial #3                  // Method org/springframework/cloud/client/discovery/noop/NoopDiscoveryClientAutoConfiguration$Boot15PortFinderConfiguration$1."<init>":(Lorg/springframework/cloud/client/discovery/noop/NoopDiscoveryClientAutoConfiguration$Boot15PortFinderConfiguration;)V
       8: areturn
}
