Compiled from "SimpleBrokerMessageHandler.java"
class org.springframework.messaging.simp.broker.SimpleBrokerMessageHandler$HeartbeatTask implements java.lang.Runnable {
  final org.springframework.messaging.simp.broker.SimpleBrokerMessageHandler this$0;

  private org.springframework.messaging.simp.broker.SimpleBrokerMessageHandler$HeartbeatTask(org.springframework.messaging.simp.broker.SimpleBrokerMessageHandler);
    Code:
       0: aload_0
       1: aload_1
       2: putfield      #2                  // Field this$0:Lorg/springframework/messaging/simp/broker/SimpleBrokerMessageHandler;
       5: aload_0
       6: invokespecial #3                  // Method java/lang/Object."<init>":()V
       9: return

  public void run();
    Code:
       0: invokestatic  #4                  // Method java/lang/System.currentTimeMillis:()J
       3: lstore_1
       4: aload_0
       5: getfield      #2                  // Field this$0:Lorg/springframework/messaging/simp/broker/SimpleBrokerMessageHandler;
       8: invokestatic  #5                  // Method org/springframework/messaging/simp/broker/SimpleBrokerMessageHandler.access$100:(Lorg/springframework/messaging/simp/broker/SimpleBrokerMessageHandler;)Ljava/util/Map;
      11: invokeinterface #6,  1            // InterfaceMethod java/util/Map.values:()Ljava/util/Collection;
      16: invokeinterface #7,  1            // InterfaceMethod java/util/Collection.iterator:()Ljava/util/Iterator;
      21: astore_3
      22: aload_3
      23: invokeinterface #8,  1            // InterfaceMethod java/util/Iterator.hasNext:()Z
      28: ifeq          193
      31: aload_3
      32: invokeinterface #9,  1            // InterfaceMethod java/util/Iterator.next:()Ljava/lang/Object;
      37: checkcast     #10                 // class org/springframework/messaging/simp/broker/SimpleBrokerMessageHandler$SessionInfo
      40: astore        4
      42: aload         4
      44: invokevirtual #11                 // Method org/springframework/messaging/simp/broker/SimpleBrokerMessageHandler$SessionInfo.getReadInterval:()J
      47: lconst_0
      48: lcmp
      49: ifle          86
      52: lload_1
      53: aload         4
      55: invokevirtual #12                 // Method org/springframework/messaging/simp/broker/SimpleBrokerMessageHandler$SessionInfo.getLastReadTime:()J
      58: lsub
      59: aload         4
      61: invokevirtual #11                 // Method org/springframework/messaging/simp/broker/SimpleBrokerMessageHandler$SessionInfo.getReadInterval:()J
      64: lcmp
      65: ifle          86
      68: aload_0
      69: getfield      #2                  // Field this$0:Lorg/springframework/messaging/simp/broker/SimpleBrokerMessageHandler;
      72: aload         4
      74: invokevirtual #13                 // Method org/springframework/messaging/simp/broker/SimpleBrokerMessageHandler$SessionInfo.getSessionId:()Ljava/lang/String;
      77: aload         4
      79: invokevirtual #14                 // Method org/springframework/messaging/simp/broker/SimpleBrokerMessageHandler$SessionInfo.getUser:()Ljava/security/Principal;
      82: aconst_null
      83: invokestatic  #15                 // Method org/springframework/messaging/simp/broker/SimpleBrokerMessageHandler.access$200:(Lorg/springframework/messaging/simp/broker/SimpleBrokerMessageHandler;Ljava/lang/String;Ljava/security/Principal;Lorg/springframework/messaging/Message;)V
      86: aload         4
      88: invokevirtual #16                 // Method org/springframework/messaging/simp/broker/SimpleBrokerMessageHandler$SessionInfo.getWriteInterval:()J
      91: lconst_0
      92: lcmp
      93: ifle          190
      96: lload_1
      97: aload         4
      99: invokevirtual #17                 // Method org/springframework/messaging/simp/broker/SimpleBrokerMessageHandler$SessionInfo.getLastWriteTime:()J
     102: lsub
     103: aload         4
     105: invokevirtual #16                 // Method org/springframework/messaging/simp/broker/SimpleBrokerMessageHandler$SessionInfo.getWriteInterval:()J
     108: lcmp
     109: ifle          190
     112: getstatic     #18                 // Field org/springframework/messaging/simp/SimpMessageType.HEARTBEAT:Lorg/springframework/messaging/simp/SimpMessageType;
     115: invokestatic  #19                 // Method org/springframework/messaging/simp/SimpMessageHeaderAccessor.create:(Lorg/springframework/messaging/simp/SimpMessageType;)Lorg/springframework/messaging/simp/SimpMessageHeaderAccessor;
     118: astore        5
     120: aload         5
     122: aload         4
     124: invokevirtual #13                 // Method org/springframework/messaging/simp/broker/SimpleBrokerMessageHandler$SessionInfo.getSessionId:()Ljava/lang/String;
     127: invokevirtual #20                 // Method org/springframework/messaging/simp/SimpMessageHeaderAccessor.setSessionId:(Ljava/lang/String;)V
     130: aload         4
     132: invokevirtual #14                 // Method org/springframework/messaging/simp/broker/SimpleBrokerMessageHandler$SessionInfo.getUser:()Ljava/security/Principal;
     135: astore        6
     137: aload         6
     139: ifnull        149
     142: aload         5
     144: aload         6
     146: invokevirtual #21                 // Method org/springframework/messaging/simp/SimpMessageHeaderAccessor.setUser:(Ljava/security/Principal;)V
     149: aload_0
     150: getfield      #2                  // Field this$0:Lorg/springframework/messaging/simp/broker/SimpleBrokerMessageHandler;
     153: aload         5
     155: invokestatic  #22                 // Method org/springframework/messaging/simp/broker/SimpleBrokerMessageHandler.access$300:(Lorg/springframework/messaging/simp/broker/SimpleBrokerMessageHandler;Lorg/springframework/messaging/simp/SimpMessageHeaderAccessor;)V
     158: aload         5
     160: iconst_1
     161: invokevirtual #23                 // Method org/springframework/messaging/simp/SimpMessageHeaderAccessor.setLeaveMutable:(Z)V
     164: aload         5
     166: invokevirtual #24                 // Method org/springframework/messaging/simp/SimpMessageHeaderAccessor.getMessageHeaders:()Lorg/springframework/messaging/MessageHeaders;
     169: astore        7
     171: aload         4
     173: invokevirtual #25                 // Method org/springframework/messaging/simp/broker/SimpleBrokerMessageHandler$SessionInfo.getClientOutboundChannel:()Lorg/springframework/messaging/MessageChannel;
     176: invokestatic  #26                 // Method org/springframework/messaging/simp/broker/SimpleBrokerMessageHandler.access$400:()[B
     179: aload         7
     181: invokestatic  #27                 // Method org/springframework/messaging/support/MessageBuilder.createMessage:(Ljava/lang/Object;Lorg/springframework/messaging/MessageHeaders;)Lorg/springframework/messaging/Message;
     184: invokeinterface #28,  2           // InterfaceMethod org/springframework/messaging/MessageChannel.send:(Lorg/springframework/messaging/Message;)Z
     189: pop
     190: goto          22
     193: return

  org.springframework.messaging.simp.broker.SimpleBrokerMessageHandler$HeartbeatTask(org.springframework.messaging.simp.broker.SimpleBrokerMessageHandler, org.springframework.messaging.simp.broker.SimpleBrokerMessageHandler$1);
    Code:
       0: aload_0
       1: aload_1
       2: invokespecial #1                  // Method "<init>":(Lorg/springframework/messaging/simp/broker/SimpleBrokerMessageHandler;)V
       5: return
}
