Compiled from "IncorrectResultSetColumnCountException.java"
public class org.springframework.jdbc.IncorrectResultSetColumnCountException extends org.springframework.dao.DataRetrievalFailureException {
  private int expectedCount;

  private int actualCount;

  public org.springframework.jdbc.IncorrectResultSetColumnCountException(int, int);
    Code:
       0: aload_0
       1: new           #1                  // class java/lang/StringBuilder
       4: dup
       5: invokespecial #2                  // Method java/lang/StringBuilder."<init>":()V
       8: ldc           #3                  // String Incorrect column count: expected
      10: invokevirtual #4                  // Method java/lang/StringBuilder.append:(Ljava/lang/String;)Ljava/lang/StringBuilder;
      13: iload_1
      14: invokevirtual #5                  // Method java/lang/StringBuilder.append:(I)Ljava/lang/StringBuilder;
      17: ldc           #6                  // String , actual
      19: invokevirtual #4                  // Method java/lang/StringBuilder.append:(Ljava/lang/String;)Ljava/lang/StringBuilder;
      22: iload_2
      23: invokevirtual #5                  // Method java/lang/StringBuilder.append:(I)Ljava/lang/StringBuilder;
      26: invokevirtual #7                  // Method java/lang/StringBuilder.toString:()Ljava/lang/String;
      29: invokespecial #8                  // Method org/springframework/dao/DataRetrievalFailureException."<init>":(Ljava/lang/String;)V
      32: aload_0
      33: iload_1
      34: putfield      #9                  // Field expectedCount:I
      37: aload_0
      38: iload_2
      39: putfield      #10                 // Field actualCount:I
      42: return

  public org.springframework.jdbc.IncorrectResultSetColumnCountException(java.lang.String, int, int);
    Code:
       0: aload_0
       1: aload_1
       2: invokespecial #8                  // Method org/springframework/dao/DataRetrievalFailureException."<init>":(Ljava/lang/String;)V
       5: aload_0
       6: iload_2
       7: putfield      #9                  // Field expectedCount:I
      10: aload_0
      11: iload_3
      12: putfield      #10                 // Field actualCount:I
      15: return

  public int getExpectedCount();
    Code:
       0: aload_0
       1: getfield      #9                  // Field expectedCount:I
       4: ireturn

  public int getActualCount();
    Code:
       0: aload_0
       1: getfield      #10                 // Field actualCount:I
       4: ireturn
}
