Compiled from "OAuthMediator.java"
public class org.wso2.carbon.identity.oauth.mediator.OAuthMediator extends org.apache.synapse.mediators.AbstractMediator {
  private static final org.apache.commons.logging.Log log;

  private java.lang.String remoteServiceUrl;

  private java.lang.String username;

  private java.lang.String password;

  org.apache.axis2.context.ConfigurationContext cfgCtx;

  private java.lang.String clientRepository;

  private java.lang.String axis2xml;

  public static final java.lang.String DEFAULT_CLIENT_REPO;

  public static final java.lang.String DEFAULT_AXIS2_XML;

  public org.wso2.carbon.identity.oauth.mediator.OAuthMediator();
    Code:
       0: aload_0
       1: invokespecial #1                  // Method org/apache/synapse/mediators/AbstractMediator."<init>":()V
       4: aload_0
       5: aconst_null
       6: putfield      #2                  // Field cfgCtx:Lorg/apache/axis2/context/ConfigurationContext;
       9: aload_0
      10: aconst_null
      11: putfield      #3                  // Field clientRepository:Ljava/lang/String;
      14: aload_0
      15: aconst_null
      16: putfield      #4                  // Field axis2xml:Ljava/lang/String;
      19: return

  public void init(org.apache.synapse.core.SynapseEnvironment);
    Code:
       0: aload_0
       1: aload_0
       2: getfield      #3                  // Field clientRepository:Ljava/lang/String;
       5: ifnull        15
       8: aload_0
       9: getfield      #3                  // Field clientRepository:Ljava/lang/String;
      12: goto          17
      15: ldc           #6                  // String ./samples/axis2Client/client_repo
      17: aload_0
      18: getfield      #4                  // Field axis2xml:Ljava/lang/String;
      21: ifnull        31
      24: aload_0
      25: getfield      #4                  // Field axis2xml:Ljava/lang/String;
      28: goto          33
      31: ldc           #7                  // String ./samples/axis2Client/client_repo/conf/axis2.xml
      33: invokestatic  #8                  // Method org/apache/axis2/context/ConfigurationContextFactory.createConfigurationContextFromFileSystem:(Ljava/lang/String;Ljava/lang/String;)Lorg/apache/axis2/context/ConfigurationContext;
      36: putfield      #2                  // Field cfgCtx:Lorg/apache/axis2/context/ConfigurationContext;
      39: goto          86
      42: astore_2
      43: new           #10                 // class java/lang/StringBuilder
      46: dup
      47: invokespecial #11                 // Method java/lang/StringBuilder."<init>":()V
      50: ldc           #12                 // String Error initializing OAuth mediator :
      52: invokevirtual #13                 // Method java/lang/StringBuilder.append:(Ljava/lang/String;)Ljava/lang/StringBuilder;
      55: aload_2
      56: invokevirtual #14                 // Method org/apache/axis2/AxisFault.getMessage:()Ljava/lang/String;
      59: invokevirtual #13                 // Method java/lang/StringBuilder.append:(Ljava/lang/String;)Ljava/lang/StringBuilder;
      62: invokevirtual #15                 // Method java/lang/StringBuilder.toString:()Ljava/lang/String;
      65: astore_3
      66: getstatic     #16                 // Field log:Lorg/apache/commons/logging/Log;
      69: aload_3
      70: aload_2
      71: invokeinterface #17,  3           // InterfaceMethod org/apache/commons/logging/Log.error:(Ljava/lang/Object;Ljava/lang/Throwable;)V
      76: new           #18                 // class org/apache/synapse/SynapseException
      79: dup
      80: aload_3
      81: aload_2
      82: invokespecial #19                 // Method org/apache/synapse/SynapseException."<init>":(Ljava/lang/String;Ljava/lang/Throwable;)V
      85: athrow
      86: return
    Exception table:
       from    to  target type
           0    39    42   Class org/apache/axis2/AxisFault

  public boolean mediate(org.apache.synapse.MessageContext);
    Code:
       0: aload_1
       1: invokeinterface #20,  1           // InterfaceMethod org/apache/synapse/MessageContext.getEnvironment:()Lorg/apache/synapse/core/SynapseEnvironment;
       6: invokeinterface #21,  1           // InterfaceMethod org/apache/synapse/core/SynapseEnvironment.isDebuggerEnabled:()Z
      11: ifeq          24
      14: aload_0
      15: aload_1
      16: invokespecial #22                 // Method org/apache/synapse/mediators/AbstractMediator.divertMediationRoute:(Lorg/apache/synapse/MessageContext;)Z
      19: ifeq          24
      22: iconst_1
      23: ireturn
      24: aload_0
      25: aload_1
      26: invokespecial #23                 // Method validateRequest:(Lorg/apache/synapse/MessageContext;)Z
      29: istore_2
      30: iload_2
      31: ifeq          40
      34: aload_0
      35: aload_1
      36: invokespecial #24                 // Method handleOAuth2:(Lorg/apache/synapse/MessageContext;)Z
      39: ireturn
      40: aload_0
      41: aload_1
      42: invokespecial #25                 // Method handleOAuth1a:(Lorg/apache/synapse/MessageContext;)Z
      45: ireturn

  private boolean validateRequest(org.apache.synapse.MessageContext);
    Code:
       0: iconst_0
       1: istore_2
       2: aconst_null
       3: astore_3
       4: aload_1
       5: checkcast     #26                 // class org/apache/synapse/core/axis2/Axis2MessageContext
       8: invokevirtual #27                 // Method org/apache/synapse/core/axis2/Axis2MessageContext.getAxis2MessageContext:()Lorg/apache/axis2/context/MessageContext;
      11: astore        4
      13: aload         4
      15: ldc           #29                 // String TRANSPORT_HEADERS
      17: invokevirtual #30                 // Method org/apache/axis2/context/MessageContext.getProperty:(Ljava/lang/String;)Ljava/lang/Object;
      20: checkcast     #31                 // class java/util/Map
      23: astore        5
      25: aload         5
      27: ldc           #32                 // String Authorization
      29: invokeinterface #33,  2           // InterfaceMethod java/util/Map.get:(Ljava/lang/Object;)Ljava/lang/Object;
      34: checkcast     #34                 // class java/lang/String
      37: astore        6
      39: aload         6
      41: ifnonnull     54
      44: new           #18                 // class org/apache/synapse/SynapseException
      47: dup
      48: ldc           #35                 // String Not a valid OAuth Request
      50: invokespecial #36                 // Method org/apache/synapse/SynapseException."<init>":(Ljava/lang/String;)V
      53: athrow
      54: aload         6
      56: ifnull        98
      59: aload         6
      61: ldc           #38                 // String Bearer
      63: invokevirtual #39                 // Method java/lang/String.startsWith:(Ljava/lang/String;)Z
      66: ifeq          98
      69: iconst_1
      70: istore_2
      71: aload         6
      73: invokevirtual #40                 // Method java/lang/String.length:()I
      76: ldc           #38                 // String Bearer
      78: invokevirtual #40                 // Method java/lang/String.length:()I
      81: if_icmple     98
      84: aload         6
      86: ldc           #38                 // String Bearer
      88: invokevirtual #40                 // Method java/lang/String.length:()I
      91: invokevirtual #41                 // Method java/lang/String.substring:(I)Ljava/lang/String;
      94: invokevirtual #42                 // Method java/lang/String.trim:()Ljava/lang/String;
      97: astore_3
      98: iload_2
      99: iconst_1
     100: if_icmpne     117
     103: aload_3
     104: ifnonnull     117
     107: new           #18                 // class org/apache/synapse/SynapseException
     110: dup
     111: ldc           #43                 // String Invalid or empty OAuth 2.0 token
     113: invokespecial #36                 // Method org/apache/synapse/SynapseException."<init>":(Ljava/lang/String;)V
     116: athrow
     117: iload_2
     118: ireturn

  private boolean handleOAuth2(org.apache.synapse.MessageContext);
    Code:
       0: getstatic     #16                 // Field log:Lorg/apache/commons/logging/Log;
       3: ldc           #44                 // String Validating the OAuth 2.0 Request
       5: invokeinterface #45,  2           // InterfaceMethod org/apache/commons/logging/Log.debug:(Ljava/lang/Object;)V
      10: new           #46                 // class org/wso2/carbon/identity/oauth/mediator/OAuth2TokenValidationServiceClient
      13: dup
      14: aload_0
      15: invokevirtual #47                 // Method getRemoteServiceUrl:()Ljava/lang/String;
      18: aload_0
      19: invokevirtual #48                 // Method getUsername:()Ljava/lang/String;
      22: aload_0
      23: invokevirtual #49                 // Method getPassword:()Ljava/lang/String;
      26: aload_0
      27: getfield      #2                  // Field cfgCtx:Lorg/apache/axis2/context/ConfigurationContext;
      30: invokespecial #50                 // Method org/wso2/carbon/identity/oauth/mediator/OAuth2TokenValidationServiceClient."<init>":(Ljava/lang/String;Ljava/lang/String;Ljava/lang/String;Lorg/apache/axis2/context/ConfigurationContext;)V
      33: astore        4
      35: aload_1
      36: checkcast     #26                 // class org/apache/synapse/core/axis2/Axis2MessageContext
      39: invokevirtual #27                 // Method org/apache/synapse/core/axis2/Axis2MessageContext.getAxis2MessageContext:()Lorg/apache/axis2/context/MessageContext;
      42: astore        5
      44: aload         5
      46: ldc           #29                 // String TRANSPORT_HEADERS
      48: invokevirtual #30                 // Method org/apache/axis2/context/MessageContext.getProperty:(Ljava/lang/String;)Ljava/lang/Object;
      51: checkcast     #31                 // class java/util/Map
      54: astore_3
      55: aload_3
      56: ldc           #32                 // String Authorization
      58: invokeinterface #33,  2           // InterfaceMethod java/util/Map.get:(Ljava/lang/Object;)Ljava/lang/Object;
      63: checkcast     #34                 // class java/lang/String
      66: astore        6
      68: aload         6
      70: bipush        7
      72: invokevirtual #41                 // Method java/lang/String.substring:(I)Ljava/lang/String;
      75: invokevirtual #42                 // Method java/lang/String.trim:()Ljava/lang/String;
      78: astore        7
      80: new           #51                 // class java/util/ArrayList
      83: dup
      84: invokespecial #52                 // Method java/util/ArrayList."<init>":()V
      87: astore        8
      89: iconst_0
      90: istore        9
      92: aload_1
      93: new           #10                 // class java/lang/StringBuilder
      96: dup
      97: invokespecial #11                 // Method java/lang/StringBuilder."<init>":()V
     100: ldc           #53                 // String oauth_context_param_key_
     102: invokevirtual #13                 // Method java/lang/StringBuilder.append:(Ljava/lang/String;)Ljava/lang/StringBuilder;
     105: iload         9
     107: invokevirtual #54                 // Method java/lang/StringBuilder.append:(I)Ljava/lang/StringBuilder;
     110: invokevirtual #15                 // Method java/lang/StringBuilder.toString:()Ljava/lang/String;
     113: invokeinterface #55,  2           // InterfaceMethod org/apache/synapse/MessageContext.getProperty:(Ljava/lang/String;)Ljava/lang/Object;
     118: ifnull        383
     121: aload_1
     122: new           #10                 // class java/lang/StringBuilder
     125: dup
     126: invokespecial #11                 // Method java/lang/StringBuilder."<init>":()V
     129: ldc           #53                 // String oauth_context_param_key_
     131: invokevirtual #13                 // Method java/lang/StringBuilder.append:(Ljava/lang/String;)Ljava/lang/StringBuilder;
     134: iload         9
     136: invokevirtual #54                 // Method java/lang/StringBuilder.append:(I)Ljava/lang/StringBuilder;
     139: invokevirtual #15                 // Method java/lang/StringBuilder.toString:()Ljava/lang/String;
     142: invokeinterface #55,  2           // InterfaceMethod org/apache/synapse/MessageContext.getProperty:(Ljava/lang/String;)Ljava/lang/Object;
     147: instanceof    #34                 // class java/lang/String
     150: ifeq          383
     153: aload_1
     154: new           #10                 // class java/lang/StringBuilder
     157: dup
     158: invokespecial #11                 // Method java/lang/StringBuilder."<init>":()V
     161: ldc           #53                 // String oauth_context_param_key_
     163: invokevirtual #13                 // Method java/lang/StringBuilder.append:(Ljava/lang/String;)Ljava/lang/StringBuilder;
     166: iload         9
     168: invokevirtual #54                 // Method java/lang/StringBuilder.append:(I)Ljava/lang/StringBuilder;
     171: invokevirtual #15                 // Method java/lang/StringBuilder.toString:()Ljava/lang/String;
     174: invokeinterface #55,  2           // InterfaceMethod org/apache/synapse/MessageContext.getProperty:(Ljava/lang/String;)Ljava/lang/Object;
     179: ldc           #56                 // String
     181: invokevirtual #57                 // Method java/lang/Object.equals:(Ljava/lang/Object;)Z
     184: ifne          383
     187: aload_1
     188: new           #10                 // class java/lang/StringBuilder
     191: dup
     192: invokespecial #11                 // Method java/lang/StringBuilder."<init>":()V
     195: ldc           #58                 // String oauth_context_param_value_
     197: invokevirtual #13                 // Method java/lang/StringBuilder.append:(Ljava/lang/String;)Ljava/lang/StringBuilder;
     200: iload         9
     202: invokevirtual #54                 // Method java/lang/StringBuilder.append:(I)Ljava/lang/StringBuilder;
     205: invokevirtual #15                 // Method java/lang/StringBuilder.toString:()Ljava/lang/String;
     208: invokeinterface #55,  2           // InterfaceMethod org/apache/synapse/MessageContext.getProperty:(Ljava/lang/String;)Ljava/lang/Object;
     213: ifnull        383
     216: aload_1
     217: new           #10                 // class java/lang/StringBuilder
     220: dup
     221: invokespecial #11                 // Method java/lang/StringBuilder."<init>":()V
     224: ldc           #58                 // String oauth_context_param_value_
     226: invokevirtual #13                 // Method java/lang/StringBuilder.append:(Ljava/lang/String;)Ljava/lang/StringBuilder;
     229: iload         9
     231: invokevirtual #54                 // Method java/lang/StringBuilder.append:(I)Ljava/lang/StringBuilder;
     234: invokevirtual #15                 // Method java/lang/StringBuilder.toString:()Ljava/lang/String;
     237: invokeinterface #55,  2           // InterfaceMethod org/apache/synapse/MessageContext.getProperty:(Ljava/lang/String;)Ljava/lang/Object;
     242: instanceof    #34                 // class java/lang/String
     245: ifeq          383
     248: aload_1
     249: new           #10                 // class java/lang/StringBuilder
     252: dup
     253: invokespecial #11                 // Method java/lang/StringBuilder."<init>":()V
     256: ldc           #58                 // String oauth_context_param_value_
     258: invokevirtual #13                 // Method java/lang/StringBuilder.append:(Ljava/lang/String;)Ljava/lang/StringBuilder;
     261: iload         9
     263: invokevirtual #54                 // Method java/lang/StringBuilder.append:(I)Ljava/lang/StringBuilder;
     266: invokevirtual #15                 // Method java/lang/StringBuilder.toString:()Ljava/lang/String;
     269: invokeinterface #55,  2           // InterfaceMethod org/apache/synapse/MessageContext.getProperty:(Ljava/lang/String;)Ljava/lang/Object;
     274: ldc           #56                 // String
     276: invokevirtual #57                 // Method java/lang/Object.equals:(Ljava/lang/Object;)Z
     279: ifne          383
     282: aload_1
     283: new           #10                 // class java/lang/StringBuilder
     286: dup
     287: invokespecial #11                 // Method java/lang/StringBuilder."<init>":()V
     290: ldc           #53                 // String oauth_context_param_key_
     292: invokevirtual #13                 // Method java/lang/StringBuilder.append:(Ljava/lang/String;)Ljava/lang/StringBuilder;
     295: iload         9
     297: invokevirtual #54                 // Method java/lang/StringBuilder.append:(I)Ljava/lang/StringBuilder;
     300: invokevirtual #15                 // Method java/lang/StringBuilder.toString:()Ljava/lang/String;
     303: invokeinterface #55,  2           // InterfaceMethod org/apache/synapse/MessageContext.getProperty:(Ljava/lang/String;)Ljava/lang/Object;
     308: checkcast     #34                 // class java/lang/String
     311: astore        10
     313: aload_1
     314: new           #10                 // class java/lang/StringBuilder
     317: dup
     318: invokespecial #11                 // Method java/lang/StringBuilder."<init>":()V
     321: ldc           #58                 // String oauth_context_param_value_
     323: invokevirtual #13                 // Method java/lang/StringBuilder.append:(Ljava/lang/String;)Ljava/lang/StringBuilder;
     326: iload         9
     328: invokevirtual #54                 // Method java/lang/StringBuilder.append:(I)Ljava/lang/StringBuilder;
     331: invokevirtual #15                 // Method java/lang/StringBuilder.toString:()Ljava/lang/String;
     334: invokeinterface #55,  2           // InterfaceMethod org/apache/synapse/MessageContext.getProperty:(Ljava/lang/String;)Ljava/lang/Object;
     339: checkcast     #34                 // class java/lang/String
     342: astore        11
     344: new           #59                 // class org/wso2/carbon/identity/oauth2/stub/dto/OAuth2TokenValidationRequestDTO_TokenValidationContextParam
     347: dup
     348: invokespecial #60                 // Method org/wso2/carbon/identity/oauth2/stub/dto/OAuth2TokenValidationRequestDTO_TokenValidationContextParam."<init>":()V
     351: astore        12
     353: aload         12
     355: aload         10
     357: invokevirtual #61                 // Method org/wso2/carbon/identity/oauth2/stub/dto/OAuth2TokenValidationRequestDTO_TokenValidationContextParam.setKey:(Ljava/lang/String;)V
     360: aload         12
     362: aload         11
     364: invokevirtual #62                 // Method org/wso2/carbon/identity/oauth2/stub/dto/OAuth2TokenValidationRequestDTO_TokenValidationContextParam.setValue:(Ljava/lang/String;)V
     367: aload         8
     369: aload         12
     371: invokeinterface #63,  2           // InterfaceMethod java/util/List.add:(Ljava/lang/Object;)Z
     376: pop
     377: iinc          9, 1
     380: goto          92
     383: aload         4
     385: aload         7
     387: aload         8
     389: invokevirtual #64                 // Method org/wso2/carbon/identity/oauth/mediator/OAuth2TokenValidationServiceClient.validateAuthenticationRequest:(Ljava/lang/String;Ljava/util/List;)Lorg/wso2/carbon/identity/oauth2/stub/dto/OAuth2TokenValidationResponseDTO;
     392: astore_2
     393: goto          420
     396: astore        4
     398: getstatic     #16                 // Field log:Lorg/apache/commons/logging/Log;
     401: ldc           #66                 // String Error occured while validating oauth access token
     403: aload         4
     405: invokeinterface #17,  3           // InterfaceMethod org/apache/commons/logging/Log.error:(Ljava/lang/Object;Ljava/lang/Throwable;)V
     410: new           #18                 // class org/apache/synapse/SynapseException
     413: dup
     414: ldc           #67                 // String Error occured while validating oauth 2.0 access token
     416: invokespecial #36                 // Method org/apache/synapse/SynapseException."<init>":(Ljava/lang/String;)V
     419: athrow
     420: aload_2
     421: invokevirtual #68                 // Method org/wso2/carbon/identity/oauth2/stub/dto/OAuth2TokenValidationResponseDTO.getValid:()Z
     424: ifne          437
     427: new           #18                 // class org/apache/synapse/SynapseException
     430: dup
     431: ldc           #69                 // String OAuth 2.0 authentication failed
     433: invokespecial #36                 // Method org/apache/synapse/SynapseException."<init>":(Ljava/lang/String;)V
     436: athrow
     437: aload_2
     438: invokevirtual #70                 // Method org/wso2/carbon/identity/oauth2/stub/dto/OAuth2TokenValidationResponseDTO.getAuthorizationContextToken:()Lorg/wso2/carbon/identity/oauth2/stub/dto/OAuth2TokenValidationResponseDTO_AuthorizationContextToken;
     441: ifnull        460
     444: aload_3
     445: ldc           #71                 // String X-JWT-Assertion
     447: aload_2
     448: invokevirtual #70                 // Method org/wso2/carbon/identity/oauth2/stub/dto/OAuth2TokenValidationResponseDTO.getAuthorizationContextToken:()Lorg/wso2/carbon/identity/oauth2/stub/dto/OAuth2TokenValidationResponseDTO_AuthorizationContextToken;
     451: invokevirtual #72                 // Method org/wso2/carbon/identity/oauth2/stub/dto/OAuth2TokenValidationResponseDTO_AuthorizationContextToken.getTokenString:()Ljava/lang/String;
     454: invokeinterface #73,  3           // InterfaceMethod java/util/Map.put:(Ljava/lang/Object;Ljava/lang/Object;)Ljava/lang/Object;
     459: pop
     460: aload_1
     461: ldc           #74                 // String oauth2_scope_validation_enabled
     463: invokeinterface #55,  2           // InterfaceMethod org/apache/synapse/MessageContext.getProperty:(Ljava/lang/String;)Ljava/lang/Object;
     468: ifnull        619
     471: aload_1
     472: ldc           #74                 // String oauth2_scope_validation_enabled
     474: invokeinterface #55,  2           // InterfaceMethod org/apache/synapse/MessageContext.getProperty:(Ljava/lang/String;)Ljava/lang/Object;
     479: checkcast     #34                 // class java/lang/String
     482: invokestatic  #75                 // Method java/lang/Boolean.parseBoolean:(Ljava/lang/String;)Z
     485: ifeq          619
     488: aload_2
     489: invokevirtual #76                 // Method org/wso2/carbon/identity/oauth2/stub/dto/OAuth2TokenValidationResponseDTO.getScope:()[Ljava/lang/String;
     492: astore        4
     494: aload         4
     496: ifnull        599
     499: aload_1
     500: ldc           #77                 // String scope
     502: invokeinterface #55,  2           // InterfaceMethod org/apache/synapse/MessageContext.getProperty:(Ljava/lang/String;)Ljava/lang/Object;
     507: checkcast     #34                 // class java/lang/String
     510: astore        5
     512: aload         5
     514: ifnonnull     530
     517: aload_1
     518: ldc           #78                 // String SYNAPSE_REST_API
     520: invokeinterface #55,  2           // InterfaceMethod org/apache/synapse/MessageContext.getProperty:(Ljava/lang/String;)Ljava/lang/Object;
     525: checkcast     #34                 // class java/lang/String
     528: astore        5
     530: aload         5
     532: ifnonnull     550
     535: aload_1
     536: checkcast     #26                 // class org/apache/synapse/core/axis2/Axis2MessageContext
     539: invokevirtual #27                 // Method org/apache/synapse/core/axis2/Axis2MessageContext.getAxis2MessageContext:()Lorg/apache/axis2/context/MessageContext;
     542: invokevirtual #79                 // Method org/apache/axis2/context/MessageContext.getAxisService:()Lorg/apache/axis2/description/AxisService;
     545: invokevirtual #80                 // Method org/apache/axis2/description/AxisService.getName:()Ljava/lang/String;
     548: astore        5
     550: new           #51                 // class java/util/ArrayList
     553: dup
     554: aload         4
     556: invokestatic  #81                 // Method java/util/Arrays.asList:([Ljava/lang/Object;)Ljava/util/List;
     559: invokespecial #82                 // Method java/util/ArrayList."<init>":(Ljava/util/Collection;)V
     562: astore        6
     564: aload         6
     566: aload         5
     568: invokeinterface #83,  2           // InterfaceMethod java/util/List.contains:(Ljava/lang/Object;)Z
     573: ifne          596
     576: getstatic     #16                 // Field log:Lorg/apache/commons/logging/Log;
     579: ldc           #84                 // String Valid Scope is not match for given access token. OAuth2 scope validation is failed.
     581: invokeinterface #45,  2           // InterfaceMethod org/apache/commons/logging/Log.debug:(Ljava/lang/Object;)V
     586: new           #18                 // class org/apache/synapse/SynapseException
     589: dup
     590: ldc           #69                 // String OAuth 2.0 authentication failed
     592: invokespecial #36                 // Method org/apache/synapse/SynapseException."<init>":(Ljava/lang/String;)V
     595: athrow
     596: goto          619
     599: getstatic     #16                 // Field log:Lorg/apache/commons/logging/Log;
     602: ldc           #85                 // String Scope is null for given access token.  OAuth2 scope validation is failed.
     604: invokeinterface #45,  2           // InterfaceMethod org/apache/commons/logging/Log.debug:(Ljava/lang/Object;)V
     609: new           #18                 // class org/apache/synapse/SynapseException
     612: dup
     613: ldc           #69                 // String OAuth 2.0 authentication failed
     615: invokespecial #36                 // Method org/apache/synapse/SynapseException."<init>":(Ljava/lang/String;)V
     618: athrow
     619: iconst_1
     620: ireturn
    Exception table:
       from    to  target type
          10   393   396   Class java/lang/Exception

  private boolean handleOAuth1a(org.apache.synapse.MessageContext);
    Code:
       0: getstatic     #16                 // Field log:Lorg/apache/commons/logging/Log;
       3: ldc           #86                 // String Validating the OAuth 1.0a Request
       5: invokeinterface #45,  2           // InterfaceMethod org/apache/commons/logging/Log.debug:(Ljava/lang/Object;)V
      10: aconst_null
      11: astore_2
      12: aconst_null
      13: astore_3
      14: aconst_null
      15: astore        4
      17: iconst_0
      18: istore        5
      20: aload_0
      21: aload_1
      22: invokespecial #87                 // Method populateOauthConsumerData:(Lorg/apache/synapse/MessageContext;)Lorg/wso2/carbon/identity/oauth/stub/types/Parameters;
      25: astore        6
      27: new           #88                 // class org/wso2/carbon/identity/oauth/mediator/OAuthServiceClient
      30: dup
      31: aload_0
      32: invokevirtual #47                 // Method getRemoteServiceUrl:()Ljava/lang/String;
      35: aload_3
      36: invokespecial #89                 // Method org/wso2/carbon/identity/oauth/mediator/OAuthServiceClient."<init>":(Ljava/lang/String;Lorg/apache/axis2/context/ConfigurationContext;)V
      39: astore_2
      40: aload         6
      42: ifnull        143
      45: aload         6
      47: invokevirtual #90                 // Method org/wso2/carbon/identity/oauth/stub/types/Parameters.getOauthToken:()Ljava/lang/String;
      50: ifnonnull     143
      53: new           #91                 // class org/wso2/carbon/identity/oauth/stub/dto/OAuthConsumerDTO
      56: dup
      57: invokespecial #92                 // Method org/wso2/carbon/identity/oauth/stub/dto/OAuthConsumerDTO."<init>":()V
      60: astore        4
      62: aload         4
      64: aload         6
      66: invokevirtual #93                 // Method org/wso2/carbon/identity/oauth/stub/types/Parameters.getBaseString:()Ljava/lang/String;
      69: invokevirtual #94                 // Method org/wso2/carbon/identity/oauth/stub/dto/OAuthConsumerDTO.setBaseString:(Ljava/lang/String;)V
      72: aload         4
      74: aload         6
      76: invokevirtual #95                 // Method org/wso2/carbon/identity/oauth/stub/types/Parameters.getHttpMethod:()Ljava/lang/String;
      79: invokevirtual #96                 // Method org/wso2/carbon/identity/oauth/stub/dto/OAuthConsumerDTO.setHttpMethod:(Ljava/lang/String;)V
      82: aload         4
      84: aload         6
      86: invokevirtual #97                 // Method org/wso2/carbon/identity/oauth/stub/types/Parameters.getOauthConsumerKey:()Ljava/lang/String;
      89: invokevirtual #98                 // Method org/wso2/carbon/identity/oauth/stub/dto/OAuthConsumerDTO.setOauthConsumerKey:(Ljava/lang/String;)V
      92: aload         4
      94: aload         6
      96: invokevirtual #99                 // Method org/wso2/carbon/identity/oauth/stub/types/Parameters.getOauthNonce:()Ljava/lang/String;
      99: invokevirtual #100                // Method org/wso2/carbon/identity/oauth/stub/dto/OAuthConsumerDTO.setOauthNonce:(Ljava/lang/String;)V
     102: aload         4
     104: aload         6
     106: invokevirtual #101                // Method org/wso2/carbon/identity/oauth/stub/types/Parameters.getOauthSignature:()Ljava/lang/String;
     109: invokevirtual #102                // Method org/wso2/carbon/identity/oauth/stub/dto/OAuthConsumerDTO.setOauthSignature:(Ljava/lang/String;)V
     112: aload         4
     114: aload         6
     116: invokevirtual #103                // Method org/wso2/carbon/identity/oauth/stub/types/Parameters.getOauthSignatureMethod:()Ljava/lang/String;
     119: invokevirtual #104                // Method org/wso2/carbon/identity/oauth/stub/dto/OAuthConsumerDTO.setOauthSignatureMethod:(Ljava/lang/String;)V
     122: aload         4
     124: aload         6
     126: invokevirtual #105                // Method org/wso2/carbon/identity/oauth/stub/types/Parameters.getOauthTimeStamp:()Ljava/lang/String;
     129: invokevirtual #106                // Method org/wso2/carbon/identity/oauth/stub/dto/OAuthConsumerDTO.setOauthTimeStamp:(Ljava/lang/String;)V
     132: aload_2
     133: aload         4
     135: invokevirtual #107                // Method org/wso2/carbon/identity/oauth/mediator/OAuthServiceClient.isOAuthConsumerValid:(Lorg/wso2/carbon/identity/oauth/stub/dto/OAuthConsumerDTO;)Z
     138: istore        5
     140: goto          151
     143: aload_2
     144: aload         6
     146: invokevirtual #108                // Method org/wso2/carbon/identity/oauth/mediator/OAuthServiceClient.validateAuthenticationRequest:(Lorg/wso2/carbon/identity/oauth/stub/types/Parameters;)Z
     149: istore        5
     151: iload         5
     153: ifne          166
     156: new           #18                 // class org/apache/synapse/SynapseException
     159: dup
     160: ldc           #109                // String OAuth authentication failed
     162: invokespecial #36                 // Method org/apache/synapse/SynapseException."<init>":(Ljava/lang/String;)V
     165: athrow
     166: iconst_1
     167: ireturn
     168: astore        6
     170: getstatic     #16                 // Field log:Lorg/apache/commons/logging/Log;
     173: ldc           #110                // String Error occured while validating oauth consumer
     175: aload         6
     177: invokeinterface #17,  3           // InterfaceMethod org/apache/commons/logging/Log.error:(Ljava/lang/Object;Ljava/lang/Throwable;)V
     182: new           #18                 // class org/apache/synapse/SynapseException
     185: dup
     186: ldc           #110                // String Error occured while validating oauth consumer
     188: invokespecial #36                 // Method org/apache/synapse/SynapseException."<init>":(Ljava/lang/String;)V
     191: athrow
    Exception table:
       from    to  target type
          20   167   168   Class java/lang/Exception

  private org.wso2.carbon.identity.oauth.stub.types.Parameters populateOauthConsumerData(org.apache.synapse.MessageContext);
    Code:
       0: aload_1
       1: checkcast     #26                 // class org/apache/synapse/core/axis2/Axis2MessageContext
       4: invokevirtual #27                 // Method org/apache/synapse/core/axis2/Axis2MessageContext.getAxis2MessageContext:()Lorg/apache/axis2/context/MessageContext;
       7: astore_2
       8: aload_2
       9: ldc           #29                 // String TRANSPORT_HEADERS
      11: invokevirtual #30                 // Method org/apache/axis2/context/MessageContext.getProperty:(Ljava/lang/String;)Ljava/lang/Object;
      14: checkcast     #31                 // class java/util/Map
      17: astore_3
      18: aload_3
      19: ldc           #32                 // String Authorization
      21: invokeinterface #33,  2           // InterfaceMethod java/util/Map.get:(Ljava/lang/Object;)Ljava/lang/Object;
      26: checkcast     #34                 // class java/lang/String
      29: astore        4
      31: aload_2
      32: ldc           #112                // String REST_URL_POSTFIX
      34: invokevirtual #30                 // Method org/apache/axis2/context/MessageContext.getProperty:(Ljava/lang/String;)Ljava/lang/Object;
      37: checkcast     #34                 // class java/lang/String
      40: astore        5
      42: aconst_null
      43: astore        6
      45: ldc           #113                // String ,
      47: astore        7
      49: iconst_0
      50: istore        8
      52: new           #114                // class org/wso2/carbon/identity/oauth/stub/types/Parameters
      55: dup
      56: invokespecial #115                // Method org/wso2/carbon/identity/oauth/stub/types/Parameters."<init>":()V
      59: astore        6
      61: aconst_null
      62: astore        9
      64: aload         5
      66: ldc           #116                // String ?
      68: invokevirtual #117                // Method java/lang/String.indexOf:(Ljava/lang/String;)I
      71: iconst_m1
      72: if_icmple     112
      75: aload         5
      77: astore        10
      79: aload         5
      81: aload         5
      83: ldc           #116                // String ?
      85: invokevirtual #117                // Method java/lang/String.indexOf:(Ljava/lang/String;)I
      88: iconst_1
      89: iadd
      90: invokevirtual #41                 // Method java/lang/String.substring:(I)Ljava/lang/String;
      93: astore        5
      95: aload         10
      97: iconst_0
      98: aload         10
     100: ldc           #116                // String ?
     102: invokevirtual #117                // Method java/lang/String.indexOf:(Ljava/lang/String;)I
     105: iconst_1
     106: iadd
     107: invokevirtual #118                // Method java/lang/String.substring:(II)Ljava/lang/String;
     110: astore        9
     112: aload         4
     114: ifnonnull     128
     117: iconst_1
     118: istore        8
     120: aload         5
     122: astore        4
     124: ldc           #119                // String &
     126: astore        7
     128: new           #120                // class java/lang/StringBuffer
     131: dup
     132: invokespecial #121                // Method java/lang/StringBuffer."<init>":()V
     135: astore        10
     137: aload         4
     139: ifnull        696
     142: aload         4
     144: ldc           #122                // String OAuth
     146: invokevirtual #39                 // Method java/lang/String.startsWith:(Ljava/lang/String;)Z
     149: ifeq          166
     152: aload         4
     154: aload         4
     156: ldc           #123                // String o
     158: invokevirtual #117                // Method java/lang/String.indexOf:(Ljava/lang/String;)I
     161: invokevirtual #41                 // Method java/lang/String.substring:(I)Ljava/lang/String;
     164: astore        4
     166: aload         4
     168: aload         7
     170: invokevirtual #124                // Method java/lang/String.split:(Ljava/lang/String;)[Ljava/lang/String;
     173: astore        11
     175: aload         11
     177: ifnull        696
     180: aload         11
     182: arraylength
     183: ifle          696
     186: aload         11
     188: astore        12
     190: aload         12
     192: arraylength
     193: istore        13
     195: iconst_0
     196: istore        14
     198: iload         14
     200: iload         13
     202: if_icmpge     696
     205: aload         12
     207: iload         14
     209: aaload
     210: astore        15
     212: aload         15
     214: ldc           #125                // String =
     216: invokevirtual #124                // Method java/lang/String.split:(Ljava/lang/String;)[Ljava/lang/String;
     219: astore        16
     221: aload         16
     223: ifnull        690
     226: aload         16
     228: arraylength
     229: ifle          690
     232: ldc           #126                // String oauth_consumer_key
     234: aload         16
     236: iconst_0
     237: aaload
     238: invokevirtual #42                 // Method java/lang/String.trim:()Ljava/lang/String;
     241: invokevirtual #127                // Method java/lang/String.equals:(Ljava/lang/Object;)Z
     244: ifeq          266
     247: aload         6
     249: aload_0
     250: aload         16
     252: iconst_1
     253: aaload
     254: invokevirtual #42                 // Method java/lang/String.trim:()Ljava/lang/String;
     257: invokespecial #128                // Method removeLeadingAndTrailingQuatation:(Ljava/lang/String;)Ljava/lang/String;
     260: invokevirtual #129                // Method org/wso2/carbon/identity/oauth/stub/types/Parameters.setOauthConsumerKey:(Ljava/lang/String;)V
     263: goto          690
     266: ldc           #130                // String oauth_nonce
     268: aload         16
     270: iconst_0
     271: aaload
     272: invokevirtual #42                 // Method java/lang/String.trim:()Ljava/lang/String;
     275: invokevirtual #127                // Method java/lang/String.equals:(Ljava/lang/Object;)Z
     278: ifeq          300
     281: aload         6
     283: aload_0
     284: aload         16
     286: iconst_1
     287: aaload
     288: invokevirtual #42                 // Method java/lang/String.trim:()Ljava/lang/String;
     291: invokespecial #128                // Method removeLeadingAndTrailingQuatation:(Ljava/lang/String;)Ljava/lang/String;
     294: invokevirtual #131                // Method org/wso2/carbon/identity/oauth/stub/types/Parameters.setOauthNonce:(Ljava/lang/String;)V
     297: goto          690
     300: ldc           #132                // String oauth_signature
     302: aload         16
     304: iconst_0
     305: aaload
     306: invokevirtual #42                 // Method java/lang/String.trim:()Ljava/lang/String;
     309: invokevirtual #127                // Method java/lang/String.equals:(Ljava/lang/Object;)Z
     312: ifeq          334
     315: aload         6
     317: aload_0
     318: aload         16
     320: iconst_1
     321: aaload
     322: invokevirtual #42                 // Method java/lang/String.trim:()Ljava/lang/String;
     325: invokespecial #128                // Method removeLeadingAndTrailingQuatation:(Ljava/lang/String;)Ljava/lang/String;
     328: invokevirtual #133                // Method org/wso2/carbon/identity/oauth/stub/types/Parameters.setOauthSignature:(Ljava/lang/String;)V
     331: goto          690
     334: ldc           #134                // String oauth_signature_method
     336: aload         16
     338: iconst_0
     339: aaload
     340: invokevirtual #42                 // Method java/lang/String.trim:()Ljava/lang/String;
     343: invokevirtual #127                // Method java/lang/String.equals:(Ljava/lang/Object;)Z
     346: ifeq          368
     349: aload         6
     351: aload_0
     352: aload         16
     354: iconst_1
     355: aaload
     356: invokevirtual #42                 // Method java/lang/String.trim:()Ljava/lang/String;
     359: invokespecial #128                // Method removeLeadingAndTrailingQuatation:(Ljava/lang/String;)Ljava/lang/String;
     362: invokevirtual #135                // Method org/wso2/carbon/identity/oauth/stub/types/Parameters.setOauthSignatureMethod:(Ljava/lang/String;)V
     365: goto          690
     368: ldc           #136                // String oauth_timestamp
     370: aload         16
     372: iconst_0
     373: aaload
     374: invokevirtual #42                 // Method java/lang/String.trim:()Ljava/lang/String;
     377: invokevirtual #127                // Method java/lang/String.equals:(Ljava/lang/Object;)Z
     380: ifeq          402
     383: aload         6
     385: aload_0
     386: aload         16
     388: iconst_1
     389: aaload
     390: invokevirtual #42                 // Method java/lang/String.trim:()Ljava/lang/String;
     393: invokespecial #128                // Method removeLeadingAndTrailingQuatation:(Ljava/lang/String;)Ljava/lang/String;
     396: invokevirtual #137                // Method org/wso2/carbon/identity/oauth/stub/types/Parameters.setOauthTimeStamp:(Ljava/lang/String;)V
     399: goto          690
     402: ldc           #138                // String oauth_callback
     404: aload         16
     406: iconst_0
     407: aaload
     408: invokevirtual #42                 // Method java/lang/String.trim:()Ljava/lang/String;
     411: invokevirtual #127                // Method java/lang/String.equals:(Ljava/lang/Object;)Z
     414: ifeq          436
     417: aload         6
     419: aload_0
     420: aload         16
     422: iconst_1
     423: aaload
     424: invokevirtual #42                 // Method java/lang/String.trim:()Ljava/lang/String;
     427: invokespecial #128                // Method removeLeadingAndTrailingQuatation:(Ljava/lang/String;)Ljava/lang/String;
     430: invokevirtual #139                // Method org/wso2/carbon/identity/oauth/stub/types/Parameters.setOauthCallback:(Ljava/lang/String;)V
     433: goto          690
     436: ldc           #77                 // String scope
     438: aload         16
     440: iconst_0
     441: aaload
     442: invokevirtual #42                 // Method java/lang/String.trim:()Ljava/lang/String;
     445: invokevirtual #127                // Method java/lang/String.equals:(Ljava/lang/Object;)Z
     448: ifeq          470
     451: aload         6
     453: aload_0
     454: aload         16
     456: iconst_1
     457: aaload
     458: invokevirtual #42                 // Method java/lang/String.trim:()Ljava/lang/String;
     461: invokespecial #128                // Method removeLeadingAndTrailingQuatation:(Ljava/lang/String;)Ljava/lang/String;
     464: invokevirtual #140                // Method org/wso2/carbon/identity/oauth/stub/types/Parameters.setScope:(Ljava/lang/String;)V
     467: goto          690
     470: ldc           #141                // String xoauth_displayname
     472: aload         16
     474: iconst_0
     475: aaload
     476: invokevirtual #42                 // Method java/lang/String.trim:()Ljava/lang/String;
     479: invokevirtual #127                // Method java/lang/String.equals:(Ljava/lang/Object;)Z
     482: ifeq          504
     485: aload         6
     487: aload_0
     488: aload         16
     490: iconst_1
     491: aaload
     492: invokevirtual #42                 // Method java/lang/String.trim:()Ljava/lang/String;
     495: invokespecial #128                // Method removeLeadingAndTrailingQuatation:(Ljava/lang/String;)Ljava/lang/String;
     498: invokevirtual #142                // Method org/wso2/carbon/identity/oauth/stub/types/Parameters.setDisplayName:(Ljava/lang/String;)V
     501: goto          690
     504: ldc           #143                // String oauth_token
     506: aload         16
     508: iconst_0
     509: aaload
     510: invokevirtual #42                 // Method java/lang/String.trim:()Ljava/lang/String;
     513: invokevirtual #127                // Method java/lang/String.equals:(Ljava/lang/Object;)Z
     516: ifeq          538
     519: aload         6
     521: aload_0
     522: aload         16
     524: iconst_1
     525: aaload
     526: invokevirtual #42                 // Method java/lang/String.trim:()Ljava/lang/String;
     529: invokespecial #128                // Method removeLeadingAndTrailingQuatation:(Ljava/lang/String;)Ljava/lang/String;
     532: invokevirtual #144                // Method org/wso2/carbon/identity/oauth/stub/types/Parameters.setOauthToken:(Ljava/lang/String;)V
     535: goto          690
     538: ldc           #145                // String oauth_verifier
     540: aload         16
     542: iconst_0
     543: aaload
     544: invokevirtual #42                 // Method java/lang/String.trim:()Ljava/lang/String;
     547: invokevirtual #127                // Method java/lang/String.equals:(Ljava/lang/Object;)Z
     550: ifeq          572
     553: aload         6
     555: aload_0
     556: aload         16
     558: iconst_1
     559: aaload
     560: invokevirtual #42                 // Method java/lang/String.trim:()Ljava/lang/String;
     563: invokespecial #128                // Method removeLeadingAndTrailingQuatation:(Ljava/lang/String;)Ljava/lang/String;
     566: invokevirtual #146                // Method org/wso2/carbon/identity/oauth/stub/types/Parameters.setOauthTokenVerifier:(Ljava/lang/String;)V
     569: goto          690
     572: ldc           #147                // String oauth_token_secret
     574: aload         16
     576: iconst_0
     577: aaload
     578: invokevirtual #42                 // Method java/lang/String.trim:()Ljava/lang/String;
     581: invokevirtual #127                // Method java/lang/String.equals:(Ljava/lang/Object;)Z
     584: ifeq          606
     587: aload         6
     589: aload_0
     590: aload         16
     592: iconst_1
     593: aaload
     594: invokevirtual #42                 // Method java/lang/String.trim:()Ljava/lang/String;
     597: invokespecial #128                // Method removeLeadingAndTrailingQuatation:(Ljava/lang/String;)Ljava/lang/String;
     600: invokevirtual #148                // Method org/wso2/carbon/identity/oauth/stub/types/Parameters.setOauthTokenSecret:(Ljava/lang/String;)V
     603: goto          690
     606: ldc           #149                // String oauth_version
     608: aload         16
     610: iconst_0
     611: aaload
     612: invokevirtual #42                 // Method java/lang/String.trim:()Ljava/lang/String;
     615: invokevirtual #127                // Method java/lang/String.equals:(Ljava/lang/Object;)Z
     618: ifeq          640
     621: aload         6
     623: aload_0
     624: aload         16
     626: iconst_1
     627: aaload
     628: invokevirtual #42                 // Method java/lang/String.trim:()Ljava/lang/String;
     631: invokespecial #128                // Method removeLeadingAndTrailingQuatation:(Ljava/lang/String;)Ljava/lang/String;
     634: invokevirtual #150                // Method org/wso2/carbon/identity/oauth/stub/types/Parameters.setVersion:(Ljava/lang/String;)V
     637: goto          690
     640: aload         10
     642: new           #10                 // class java/lang/StringBuilder
     645: dup
     646: invokespecial #11                 // Method java/lang/StringBuilder."<init>":()V
     649: aload         16
     651: iconst_0
     652: aaload
     653: invokevirtual #42                 // Method java/lang/String.trim:()Ljava/lang/String;
     656: invokevirtual #13                 // Method java/lang/StringBuilder.append:(Ljava/lang/String;)Ljava/lang/StringBuilder;
     659: ldc           #125                // String =
     661: invokevirtual #13                 // Method java/lang/StringBuilder.append:(Ljava/lang/String;)Ljava/lang/StringBuilder;
     664: aload_0
     665: aload         16
     667: iconst_1
     668: aaload
     669: invokevirtual #42                 // Method java/lang/String.trim:()Ljava/lang/String;
     672: invokespecial #128                // Method removeLeadingAndTrailingQuatation:(Ljava/lang/String;)Ljava/lang/String;
     675: invokevirtual #13                 // Method java/lang/StringBuilder.append:(Ljava/lang/String;)Ljava/lang/StringBuilder;
     678: ldc           #119                // String &
     680: invokevirtual #13                 // Method java/lang/StringBuilder.append:(Ljava/lang/String;)Ljava/lang/StringBuilder;
     683: invokevirtual #15                 // Method java/lang/StringBuilder.toString:()Ljava/lang/String;
     686: invokevirtual #151                // Method java/lang/StringBuffer.append:(Ljava/lang/String;)Ljava/lang/StringBuffer;
     689: pop
     690: iinc          14, 1
     693: goto          198
     696: aload         10
     698: invokevirtual #152                // Method java/lang/StringBuffer.toString:()Ljava/lang/String;
     701: astore        11
     703: iload         8
     705: ifne          730
     708: new           #10                 // class java/lang/StringBuilder
     711: dup
     712: invokespecial #11                 // Method java/lang/StringBuilder."<init>":()V
     715: aload         5
     717: invokevirtual #13                 // Method java/lang/StringBuilder.append:(Ljava/lang/String;)Ljava/lang/StringBuilder;
     720: ldc           #119                // String &
     722: invokevirtual #13                 // Method java/lang/StringBuilder.append:(Ljava/lang/String;)Ljava/lang/StringBuilder;
     725: invokevirtual #15                 // Method java/lang/StringBuilder.toString:()Ljava/lang/String;
     728: astore        11
     730: aload_1
     731: ldc           #77                 // String scope
     733: invokeinterface #55,  2           // InterfaceMethod org/apache/synapse/MessageContext.getProperty:(Ljava/lang/String;)Ljava/lang/Object;
     738: checkcast     #34                 // class java/lang/String
     741: astore        12
     743: aload         12
     745: ifnonnull     758
     748: new           #18                 // class org/apache/synapse/SynapseException
     751: dup
     752: ldc           #153                // String Unable to find SCOPE value in Synapse Message Context
     754: invokespecial #36                 // Method org/apache/synapse/SynapseException."<init>":(Ljava/lang/String;)V
     757: athrow
     758: aload         6
     760: aload         12
     762: invokevirtual #140                // Method org/wso2/carbon/identity/oauth/stub/types/Parameters.setScope:(Ljava/lang/String;)V
     765: aload         6
     767: aload_2
     768: ldc           #154                // String HTTP_METHOD
     770: invokevirtual #30                 // Method org/apache/axis2/context/MessageContext.getProperty:(Ljava/lang/String;)Ljava/lang/Object;
     773: checkcast     #34                 // class java/lang/String
     776: invokevirtual #155                // Method org/wso2/carbon/identity/oauth/stub/types/Parameters.setHttpMethod:(Ljava/lang/String;)V
     779: aload_2
     780: ldc           #156                // String SERVICE_PREFIX
     782: invokevirtual #30                 // Method org/apache/axis2/context/MessageContext.getProperty:(Ljava/lang/String;)Ljava/lang/Object;
     785: checkcast     #34                 // class java/lang/String
     788: astore        13
     790: aload         11
     792: invokevirtual #40                 // Method java/lang/String.length:()I
     795: iconst_1
     796: if_icmple     843
     799: aload         6
     801: new           #10                 // class java/lang/StringBuilder
     804: dup
     805: invokespecial #11                 // Method java/lang/StringBuilder."<init>":()V
     808: aload         13
     810: invokevirtual #13                 // Method java/lang/StringBuilder.append:(Ljava/lang/String;)Ljava/lang/StringBuilder;
     813: aload         9
     815: invokevirtual #13                 // Method java/lang/StringBuilder.append:(Ljava/lang/String;)Ljava/lang/StringBuilder;
     818: aload         11
     820: iconst_0
     821: aload         11
     823: invokevirtual #40                 // Method java/lang/String.length:()I
     826: iconst_1
     827: isub
     828: invokevirtual #118                // Method java/lang/String.substring:(II)Ljava/lang/String;
     831: invokevirtual #13                 // Method java/lang/StringBuilder.append:(Ljava/lang/String;)Ljava/lang/StringBuilder;
     834: invokevirtual #15                 // Method java/lang/StringBuilder.toString:()Ljava/lang/String;
     837: invokevirtual #157                // Method org/wso2/carbon/identity/oauth/stub/types/Parameters.setBaseString:(Ljava/lang/String;)V
     840: goto          850
     843: aload         6
     845: aload         13
     847: invokevirtual #157                // Method org/wso2/carbon/identity/oauth/stub/types/Parameters.setBaseString:(Ljava/lang/String;)V
     850: aload         6
     852: areturn

  private java.lang.String removeLeadingAndTrailingQuatation(java.lang.String);
    Code:
       0: aload_1
       1: astore_2
       2: aload_1
       3: ldc           #158                // String \"
       5: invokevirtual #39                 // Method java/lang/String.startsWith:(Ljava/lang/String;)Z
       8: ifne          20
      11: aload_1
      12: ldc           #158                // String \"
      14: invokevirtual #159                // Method java/lang/String.endsWith:(Ljava/lang/String;)Z
      17: ifeq          29
      20: aload_1
      21: ldc           #158                // String \"
      23: ldc           #56                 // String
      25: invokevirtual #160                // Method java/lang/String.replace:(Ljava/lang/CharSequence;Ljava/lang/CharSequence;)Ljava/lang/String;
      28: astore_2
      29: aload_2
      30: invokevirtual #42                 // Method java/lang/String.trim:()Ljava/lang/String;
      33: areturn

  public java.lang.String getPassword();
    Code:
       0: aload_0
       1: getfield      #161                // Field password:Ljava/lang/String;
       4: areturn

  public void setPassword(java.lang.String);
    Code:
       0: aload_0
       1: aload_1
       2: putfield      #161                // Field password:Ljava/lang/String;
       5: return

  public java.lang.String getUsername();
    Code:
       0: aload_0
       1: getfield      #162                // Field username:Ljava/lang/String;
       4: areturn

  public void setUsername(java.lang.String);
    Code:
       0: aload_0
       1: aload_1
       2: putfield      #162                // Field username:Ljava/lang/String;
       5: return

  public java.lang.String getRemoteServiceUrl();
    Code:
       0: aload_0
       1: getfield      #163                // Field remoteServiceUrl:Ljava/lang/String;
       4: ifnull        45
       7: aload_0
       8: getfield      #163                // Field remoteServiceUrl:Ljava/lang/String;
      11: ldc           #164                // String /
      13: invokevirtual #159                // Method java/lang/String.endsWith:(Ljava/lang/String;)Z
      16: ifne          45
      19: new           #10                 // class java/lang/StringBuilder
      22: dup
      23: invokespecial #11                 // Method java/lang/StringBuilder."<init>":()V
      26: aload_0
      27: dup_x1
      28: getfield      #163                // Field remoteServiceUrl:Ljava/lang/String;
      31: invokevirtual #13                 // Method java/lang/StringBuilder.append:(Ljava/lang/String;)Ljava/lang/StringBuilder;
      34: ldc           #164                // String /
      36: invokevirtual #13                 // Method java/lang/StringBuilder.append:(Ljava/lang/String;)Ljava/lang/StringBuilder;
      39: invokevirtual #15                 // Method java/lang/StringBuilder.toString:()Ljava/lang/String;
      42: putfield      #163                // Field remoteServiceUrl:Ljava/lang/String;
      45: aload_0
      46: getfield      #163                // Field remoteServiceUrl:Ljava/lang/String;
      49: areturn

  public void setRemoteServiceUrl(java.lang.String);
    Code:
       0: aload_0
       1: aload_1
       2: putfield      #163                // Field remoteServiceUrl:Ljava/lang/String;
       5: return

  public boolean isContentAware();
    Code:
       0: iconst_0
       1: ireturn

  static {};
    Code:
       0: ldc           #5                  // class org/wso2/carbon/identity/oauth/mediator/OAuthMediator
       2: invokestatic  #165                // Method org/apache/commons/logging/LogFactory.getLog:(Ljava/lang/Class;)Lorg/apache/commons/logging/Log;
       5: putstatic     #16                 // Field log:Lorg/apache/commons/logging/Log;
       8: return
}
