Compiled from "VirtualBeanPropertyWriter.java"
public abstract class io.dekorate.deps.jackson.databind.ser.VirtualBeanPropertyWriter extends io.dekorate.deps.jackson.databind.ser.BeanPropertyWriter implements java.io.Serializable {
  private static final long serialVersionUID;

  protected io.dekorate.deps.jackson.databind.ser.VirtualBeanPropertyWriter(io.dekorate.deps.jackson.databind.introspect.BeanPropertyDefinition, io.dekorate.deps.jackson.databind.util.Annotations, io.dekorate.deps.jackson.databind.JavaType);
    Code:
       0: aload_0
       1: aload_1
       2: aload_2
       3: aload_3
       4: aconst_null
       5: aconst_null
       6: aconst_null
       7: aload_1
       8: invokevirtual #27                 // Method io/dekorate/deps/jackson/databind/introspect/BeanPropertyDefinition.findInclusion:()Lio/dekorate/deps/jackson/annotation/JsonInclude$Value;
      11: invokespecial #30                 // Method "<init>":(Lio/dekorate/deps/jackson/databind/introspect/BeanPropertyDefinition;Lio/dekorate/deps/jackson/databind/util/Annotations;Lio/dekorate/deps/jackson/databind/JavaType;Lio/dekorate/deps/jackson/databind/JsonSerializer;Lio/dekorate/deps/jackson/databind/jsontype/TypeSerializer;Lio/dekorate/deps/jackson/databind/JavaType;Lio/dekorate/deps/jackson/annotation/JsonInclude$Value;)V
      14: return

  protected io.dekorate.deps.jackson.databind.ser.VirtualBeanPropertyWriter();
    Code:
       0: aload_0
       1: invokespecial #41                 // Method io/dekorate/deps/jackson/databind/ser/BeanPropertyWriter."<init>":()V
       4: return

  protected io.dekorate.deps.jackson.databind.ser.VirtualBeanPropertyWriter(io.dekorate.deps.jackson.databind.introspect.BeanPropertyDefinition, io.dekorate.deps.jackson.databind.util.Annotations, io.dekorate.deps.jackson.databind.JavaType, io.dekorate.deps.jackson.databind.JsonSerializer<?>, io.dekorate.deps.jackson.databind.jsontype.TypeSerializer, io.dekorate.deps.jackson.databind.JavaType, io.dekorate.deps.jackson.annotation.JsonInclude$Value, java.lang.Class<?>[]);
    Code:
       0: aload_0
       1: aload_1
       2: aload_1
       3: invokevirtual #47                 // Method io/dekorate/deps/jackson/databind/introspect/BeanPropertyDefinition.getPrimaryMember:()Lio/dekorate/deps/jackson/databind/introspect/AnnotatedMember;
       6: aload_2
       7: aload_3
       8: aload         4
      10: aload         5
      12: aload         6
      14: aload         7
      16: invokestatic  #51                 // Method _suppressNulls:(Lio/dekorate/deps/jackson/annotation/JsonInclude$Value;)Z
      19: aload         7
      21: invokestatic  #55                 // Method _suppressableValue:(Lio/dekorate/deps/jackson/annotation/JsonInclude$Value;)Ljava/lang/Object;
      24: aload         8
      26: invokespecial #58                 // Method io/dekorate/deps/jackson/databind/ser/BeanPropertyWriter."<init>":(Lio/dekorate/deps/jackson/databind/introspect/BeanPropertyDefinition;Lio/dekorate/deps/jackson/databind/introspect/AnnotatedMember;Lio/dekorate/deps/jackson/databind/util/Annotations;Lio/dekorate/deps/jackson/databind/JavaType;Lio/dekorate/deps/jackson/databind/JsonSerializer;Lio/dekorate/deps/jackson/databind/jsontype/TypeSerializer;Lio/dekorate/deps/jackson/databind/JavaType;ZLjava/lang/Object;[Ljava/lang/Class;)V
      29: return

  protected io.dekorate.deps.jackson.databind.ser.VirtualBeanPropertyWriter(io.dekorate.deps.jackson.databind.introspect.BeanPropertyDefinition, io.dekorate.deps.jackson.databind.util.Annotations, io.dekorate.deps.jackson.databind.JavaType, io.dekorate.deps.jackson.databind.JsonSerializer<?>, io.dekorate.deps.jackson.databind.jsontype.TypeSerializer, io.dekorate.deps.jackson.databind.JavaType, io.dekorate.deps.jackson.annotation.JsonInclude$Value);
    Code:
       0: aload_0
       1: aload_1
       2: aload_2
       3: aload_3
       4: aload         4
       6: aload         5
       8: aload         6
      10: aload         7
      12: aconst_null
      13: invokespecial #73                 // Method "<init>":(Lio/dekorate/deps/jackson/databind/introspect/BeanPropertyDefinition;Lio/dekorate/deps/jackson/databind/util/Annotations;Lio/dekorate/deps/jackson/databind/JavaType;Lio/dekorate/deps/jackson/databind/JsonSerializer;Lio/dekorate/deps/jackson/databind/jsontype/TypeSerializer;Lio/dekorate/deps/jackson/databind/JavaType;Lio/dekorate/deps/jackson/annotation/JsonInclude$Value;[Ljava/lang/Class;)V
      16: return

  protected io.dekorate.deps.jackson.databind.ser.VirtualBeanPropertyWriter(io.dekorate.deps.jackson.databind.ser.VirtualBeanPropertyWriter);
    Code:
       0: aload_0
       1: aload_1
       2: invokespecial #77                 // Method io/dekorate/deps/jackson/databind/ser/BeanPropertyWriter."<init>":(Lio/dekorate/deps/jackson/databind/ser/BeanPropertyWriter;)V
       5: return

  protected io.dekorate.deps.jackson.databind.ser.VirtualBeanPropertyWriter(io.dekorate.deps.jackson.databind.ser.VirtualBeanPropertyWriter, io.dekorate.deps.jackson.databind.PropertyName);
    Code:
       0: aload_0
       1: aload_1
       2: aload_2
       3: invokespecial #82                 // Method io/dekorate/deps/jackson/databind/ser/BeanPropertyWriter."<init>":(Lio/dekorate/deps/jackson/databind/ser/BeanPropertyWriter;Lio/dekorate/deps/jackson/databind/PropertyName;)V
       6: return

  protected static boolean _suppressNulls(io.dekorate.deps.jackson.annotation.JsonInclude$Value);
    Code:
       0: aload_0
       1: ifnonnull     6
       4: iconst_0
       5: ireturn
       6: aload_0
       7: invokevirtual #88                 // Method io/dekorate/deps/jackson/annotation/JsonInclude$Value.getValueInclusion:()Lio/dekorate/deps/jackson/annotation/JsonInclude$Include;
      10: astore_1
      11: aload_1
      12: getstatic     #92                 // Field io/dekorate/deps/jackson/annotation/JsonInclude$Include.ALWAYS:Lio/dekorate/deps/jackson/annotation/JsonInclude$Include;
      15: if_acmpeq     29
      18: aload_1
      19: getstatic     #95                 // Field io/dekorate/deps/jackson/annotation/JsonInclude$Include.USE_DEFAULTS:Lio/dekorate/deps/jackson/annotation/JsonInclude$Include;
      22: if_acmpeq     29
      25: iconst_1
      26: goto          30
      29: iconst_0
      30: ireturn

  protected static java.lang.Object _suppressableValue(io.dekorate.deps.jackson.annotation.JsonInclude$Value);
    Code:
       0: aload_0
       1: ifnonnull     9
       4: iconst_0
       5: invokestatic  #102                // Method java/lang/Boolean.valueOf:(Z)Ljava/lang/Boolean;
       8: areturn
       9: aload_0
      10: invokevirtual #88                 // Method io/dekorate/deps/jackson/annotation/JsonInclude$Value.getValueInclusion:()Lio/dekorate/deps/jackson/annotation/JsonInclude$Include;
      13: astore_1
      14: aload_1
      15: getstatic     #92                 // Field io/dekorate/deps/jackson/annotation/JsonInclude$Include.ALWAYS:Lio/dekorate/deps/jackson/annotation/JsonInclude$Include;
      18: if_acmpeq     35
      21: aload_1
      22: getstatic     #105                // Field io/dekorate/deps/jackson/annotation/JsonInclude$Include.NON_NULL:Lio/dekorate/deps/jackson/annotation/JsonInclude$Include;
      25: if_acmpeq     35
      28: aload_1
      29: getstatic     #95                 // Field io/dekorate/deps/jackson/annotation/JsonInclude$Include.USE_DEFAULTS:Lio/dekorate/deps/jackson/annotation/JsonInclude$Include;
      32: if_acmpne     37
      35: aconst_null
      36: areturn
      37: getstatic     #109                // Field MARKER_FOR_EMPTY:Ljava/lang/Object;
      40: areturn

  public boolean isVirtual();
    Code:
       0: iconst_1
       1: ireturn

  protected abstract java.lang.Object value(java.lang.Object, io.dekorate.deps.jackson.core.JsonGenerator, io.dekorate.deps.jackson.databind.SerializerProvider) throws java.lang.Exception;

  public abstract io.dekorate.deps.jackson.databind.ser.VirtualBeanPropertyWriter withConfig(io.dekorate.deps.jackson.databind.cfg.MapperConfig<?>, io.dekorate.deps.jackson.databind.introspect.AnnotatedClass, io.dekorate.deps.jackson.databind.introspect.BeanPropertyDefinition, io.dekorate.deps.jackson.databind.JavaType);

  public void serializeAsField(java.lang.Object, io.dekorate.deps.jackson.core.JsonGenerator, io.dekorate.deps.jackson.databind.SerializerProvider) throws java.lang.Exception;
    Code:
       0: aload_0
       1: aload_1
       2: aload_2
       3: aload_3
       4: invokevirtual #122                // Method value:(Ljava/lang/Object;Lio/dekorate/deps/jackson/core/JsonGenerator;Lio/dekorate/deps/jackson/databind/SerializerProvider;)Ljava/lang/Object;
       7: astore        4
       9: aload         4
      11: ifnonnull     40
      14: aload_0
      15: getfield      #125                // Field _nullSerializer:Lio/dekorate/deps/jackson/databind/JsonSerializer;
      18: ifnull        39
      21: aload_2
      22: aload_0
      23: getfield      #129                // Field _name:Lio/dekorate/deps/jackson/core/io/SerializedString;
      26: invokevirtual #135                // Method io/dekorate/deps/jackson/core/JsonGenerator.writeFieldName:(Lio/dekorate/deps/jackson/core/SerializableString;)V
      29: aload_0
      30: getfield      #125                // Field _nullSerializer:Lio/dekorate/deps/jackson/databind/JsonSerializer;
      33: aconst_null
      34: aload_2
      35: aload_3
      36: invokevirtual #140                // Method io/dekorate/deps/jackson/databind/JsonSerializer.serialize:(Ljava/lang/Object;Lio/dekorate/deps/jackson/core/JsonGenerator;Lio/dekorate/deps/jackson/databind/SerializerProvider;)V
      39: return
      40: aload_0
      41: getfield      #145                // Field _serializer:Lio/dekorate/deps/jackson/databind/JsonSerializer;
      44: astore        5
      46: aload         5
      48: ifnonnull     89
      51: aload         4
      53: invokevirtual #149                // Method java/lang/Object.getClass:()Ljava/lang/Class;
      56: astore        6
      58: aload_0
      59: getfield      #153                // Field _dynamicSerializers:Lio/dekorate/deps/jackson/databind/ser/impl/PropertySerializerMap;
      62: astore        7
      64: aload         7
      66: aload         6
      68: invokevirtual #159                // Method io/dekorate/deps/jackson/databind/ser/impl/PropertySerializerMap.serializerFor:(Ljava/lang/Class;)Lio/dekorate/deps/jackson/databind/JsonSerializer;
      71: astore        5
      73: aload         5
      75: ifnonnull     89
      78: aload_0
      79: aload         7
      81: aload         6
      83: aload_3
      84: invokevirtual #163                // Method _findAndAddDynamic:(Lio/dekorate/deps/jackson/databind/ser/impl/PropertySerializerMap;Ljava/lang/Class;Lio/dekorate/deps/jackson/databind/SerializerProvider;)Lio/dekorate/deps/jackson/databind/JsonSerializer;
      87: astore        5
      89: aload_0
      90: getfield      #165                // Field _suppressableValue:Ljava/lang/Object;
      93: ifnull        131
      96: getstatic     #109                // Field MARKER_FOR_EMPTY:Ljava/lang/Object;
      99: aload_0
     100: getfield      #165                // Field _suppressableValue:Ljava/lang/Object;
     103: if_acmpne     118
     106: aload         5
     108: aload_3
     109: aload         4
     111: invokevirtual #169                // Method io/dekorate/deps/jackson/databind/JsonSerializer.isEmpty:(Lio/dekorate/deps/jackson/databind/SerializerProvider;Ljava/lang/Object;)Z
     114: ifeq          131
     117: return
     118: aload_0
     119: getfield      #165                // Field _suppressableValue:Ljava/lang/Object;
     122: aload         4
     124: invokevirtual #173                // Method java/lang/Object.equals:(Ljava/lang/Object;)Z
     127: ifeq          131
     130: return
     131: aload         4
     133: aload_1
     134: if_acmpne     150
     137: aload_0
     138: aload_1
     139: aload_2
     140: aload_3
     141: aload         5
     143: invokevirtual #177                // Method _handleSelfReference:(Ljava/lang/Object;Lio/dekorate/deps/jackson/core/JsonGenerator;Lio/dekorate/deps/jackson/databind/SerializerProvider;Lio/dekorate/deps/jackson/databind/JsonSerializer;)Z
     146: ifeq          150
     149: return
     150: aload_2
     151: aload_0
     152: getfield      #129                // Field _name:Lio/dekorate/deps/jackson/core/io/SerializedString;
     155: invokevirtual #135                // Method io/dekorate/deps/jackson/core/JsonGenerator.writeFieldName:(Lio/dekorate/deps/jackson/core/SerializableString;)V
     158: aload_0
     159: getfield      #180                // Field _typeSerializer:Lio/dekorate/deps/jackson/databind/jsontype/TypeSerializer;
     162: ifnonnull     177
     165: aload         5
     167: aload         4
     169: aload_2
     170: aload_3
     171: invokevirtual #140                // Method io/dekorate/deps/jackson/databind/JsonSerializer.serialize:(Ljava/lang/Object;Lio/dekorate/deps/jackson/core/JsonGenerator;Lio/dekorate/deps/jackson/databind/SerializerProvider;)V
     174: goto          190
     177: aload         5
     179: aload         4
     181: aload_2
     182: aload_3
     183: aload_0
     184: getfield      #180                // Field _typeSerializer:Lio/dekorate/deps/jackson/databind/jsontype/TypeSerializer;
     187: invokevirtual #184                // Method io/dekorate/deps/jackson/databind/JsonSerializer.serializeWithType:(Ljava/lang/Object;Lio/dekorate/deps/jackson/core/JsonGenerator;Lio/dekorate/deps/jackson/databind/SerializerProvider;Lio/dekorate/deps/jackson/databind/jsontype/TypeSerializer;)V
     190: return

  public void serializeAsElement(java.lang.Object, io.dekorate.deps.jackson.core.JsonGenerator, io.dekorate.deps.jackson.databind.SerializerProvider) throws java.lang.Exception;
    Code:
       0: aload_0
       1: aload_1
       2: aload_2
       3: aload_3
       4: invokevirtual #122                // Method value:(Ljava/lang/Object;Lio/dekorate/deps/jackson/core/JsonGenerator;Lio/dekorate/deps/jackson/databind/SerializerProvider;)Ljava/lang/Object;
       7: astore        4
       9: aload         4
      11: ifnonnull     39
      14: aload_0
      15: getfield      #125                // Field _nullSerializer:Lio/dekorate/deps/jackson/databind/JsonSerializer;
      18: ifnull        34
      21: aload_0
      22: getfield      #125                // Field _nullSerializer:Lio/dekorate/deps/jackson/databind/JsonSerializer;
      25: aconst_null
      26: aload_2
      27: aload_3
      28: invokevirtual #140                // Method io/dekorate/deps/jackson/databind/JsonSerializer.serialize:(Ljava/lang/Object;Lio/dekorate/deps/jackson/core/JsonGenerator;Lio/dekorate/deps/jackson/databind/SerializerProvider;)V
      31: goto          38
      34: aload_2
      35: invokevirtual #198                // Method io/dekorate/deps/jackson/core/JsonGenerator.writeNull:()V
      38: return
      39: aload_0
      40: getfield      #145                // Field _serializer:Lio/dekorate/deps/jackson/databind/JsonSerializer;
      43: astore        5
      45: aload         5
      47: ifnonnull     88
      50: aload         4
      52: invokevirtual #149                // Method java/lang/Object.getClass:()Ljava/lang/Class;
      55: astore        6
      57: aload_0
      58: getfield      #153                // Field _dynamicSerializers:Lio/dekorate/deps/jackson/databind/ser/impl/PropertySerializerMap;
      61: astore        7
      63: aload         7
      65: aload         6
      67: invokevirtual #159                // Method io/dekorate/deps/jackson/databind/ser/impl/PropertySerializerMap.serializerFor:(Ljava/lang/Class;)Lio/dekorate/deps/jackson/databind/JsonSerializer;
      70: astore        5
      72: aload         5
      74: ifnonnull     88
      77: aload_0
      78: aload         7
      80: aload         6
      82: aload_3
      83: invokevirtual #163                // Method _findAndAddDynamic:(Lio/dekorate/deps/jackson/databind/ser/impl/PropertySerializerMap;Ljava/lang/Class;Lio/dekorate/deps/jackson/databind/SerializerProvider;)Lio/dekorate/deps/jackson/databind/JsonSerializer;
      86: astore        5
      88: aload_0
      89: getfield      #165                // Field _suppressableValue:Ljava/lang/Object;
      92: ifnull        144
      95: getstatic     #109                // Field MARKER_FOR_EMPTY:Ljava/lang/Object;
      98: aload_0
      99: getfield      #165                // Field _suppressableValue:Ljava/lang/Object;
     102: if_acmpne     124
     105: aload         5
     107: aload_3
     108: aload         4
     110: invokevirtual #169                // Method io/dekorate/deps/jackson/databind/JsonSerializer.isEmpty:(Lio/dekorate/deps/jackson/databind/SerializerProvider;Ljava/lang/Object;)Z
     113: ifeq          144
     116: aload_0
     117: aload_1
     118: aload_2
     119: aload_3
     120: invokevirtual #201                // Method serializeAsPlaceholder:(Ljava/lang/Object;Lio/dekorate/deps/jackson/core/JsonGenerator;Lio/dekorate/deps/jackson/databind/SerializerProvider;)V
     123: return
     124: aload_0
     125: getfield      #165                // Field _suppressableValue:Ljava/lang/Object;
     128: aload         4
     130: invokevirtual #173                // Method java/lang/Object.equals:(Ljava/lang/Object;)Z
     133: ifeq          144
     136: aload_0
     137: aload_1
     138: aload_2
     139: aload_3
     140: invokevirtual #201                // Method serializeAsPlaceholder:(Ljava/lang/Object;Lio/dekorate/deps/jackson/core/JsonGenerator;Lio/dekorate/deps/jackson/databind/SerializerProvider;)V
     143: return
     144: aload         4
     146: aload_1
     147: if_acmpne     163
     150: aload_0
     151: aload_1
     152: aload_2
     153: aload_3
     154: aload         5
     156: invokevirtual #177                // Method _handleSelfReference:(Ljava/lang/Object;Lio/dekorate/deps/jackson/core/JsonGenerator;Lio/dekorate/deps/jackson/databind/SerializerProvider;Lio/dekorate/deps/jackson/databind/JsonSerializer;)Z
     159: ifeq          163
     162: return
     163: aload_0
     164: getfield      #180                // Field _typeSerializer:Lio/dekorate/deps/jackson/databind/jsontype/TypeSerializer;
     167: ifnonnull     182
     170: aload         5
     172: aload         4
     174: aload_2
     175: aload_3
     176: invokevirtual #140                // Method io/dekorate/deps/jackson/databind/JsonSerializer.serialize:(Ljava/lang/Object;Lio/dekorate/deps/jackson/core/JsonGenerator;Lio/dekorate/deps/jackson/databind/SerializerProvider;)V
     179: goto          195
     182: aload         5
     184: aload         4
     186: aload_2
     187: aload_3
     188: aload_0
     189: getfield      #180                // Field _typeSerializer:Lio/dekorate/deps/jackson/databind/jsontype/TypeSerializer;
     192: invokevirtual #184                // Method io/dekorate/deps/jackson/databind/JsonSerializer.serializeWithType:(Ljava/lang/Object;Lio/dekorate/deps/jackson/core/JsonGenerator;Lio/dekorate/deps/jackson/databind/SerializerProvider;Lio/dekorate/deps/jackson/databind/jsontype/TypeSerializer;)V
     195: return
}
