Compiled from "JDBCReader.java"
class org.hibernate.cfg.reveng.JDBCReader$ForeignKeysInfo {
  final java.util.Map dependentTables;

  final java.util.Map dependentColumns;

  final java.util.Map referencedColumns;

  private final org.hibernate.mapping.Table referencedTable;

  public org.hibernate.cfg.reveng.JDBCReader$ForeignKeysInfo(org.hibernate.mapping.Table, java.util.Map, java.util.Map, java.util.Map);
    Code:
       0: aload_0
       1: invokespecial #1                  // Method java/lang/Object."<init>":()V
       4: aload_0
       5: aload_1
       6: putfield      #2                  // Field referencedTable:Lorg/hibernate/mapping/Table;
       9: aload_0
      10: aload_2
      11: putfield      #3                  // Field dependentTables:Ljava/util/Map;
      14: aload_0
      15: aload_3
      16: putfield      #4                  // Field dependentColumns:Ljava/util/Map;
      19: aload_0
      20: aload         4
      22: putfield      #5                  // Field referencedColumns:Ljava/util/Map;
      25: return

  java.util.Map process(org.hibernate.cfg.reveng.ReverseEngineeringStrategy);
    Code:
       0: new           #6                  // class java/util/HashMap
       3: dup
       4: invokespecial #7                  // Method java/util/HashMap."<init>":()V
       7: astore_2
       8: aload_0
       9: getfield      #3                  // Field dependentTables:Ljava/util/Map;
      12: invokeinterface #8,  1            // InterfaceMethod java/util/Map.entrySet:()Ljava/util/Set;
      17: invokeinterface #9,  1            // InterfaceMethod java/util/Set.iterator:()Ljava/util/Iterator;
      22: astore_3
      23: aload_3
      24: invokeinterface #10,  1           // InterfaceMethod java/util/Iterator.hasNext:()Z
      29: ifeq          149
      32: aload_3
      33: invokeinterface #11,  1           // InterfaceMethod java/util/Iterator.next:()Ljava/lang/Object;
      38: checkcast     #12                 // class java/util/Map$Entry
      41: astore        4
      43: aload         4
      45: invokeinterface #13,  1           // InterfaceMethod java/util/Map$Entry.getKey:()Ljava/lang/Object;
      50: checkcast     #14                 // class java/lang/String
      53: astore        5
      55: aload         4
      57: invokeinterface #15,  1           // InterfaceMethod java/util/Map$Entry.getValue:()Ljava/lang/Object;
      62: checkcast     #16                 // class org/hibernate/mapping/Table
      65: astore        6
      67: aload_0
      68: getfield      #4                  // Field dependentColumns:Ljava/util/Map;
      71: aload         5
      73: invokeinterface #17,  2           // InterfaceMethod java/util/Map.get:(Ljava/lang/Object;)Ljava/lang/Object;
      78: checkcast     #18                 // class java/util/List
      81: astore        7
      83: aload_0
      84: getfield      #5                  // Field referencedColumns:Ljava/util/Map;
      87: aload         5
      89: invokeinterface #17,  2           // InterfaceMethod java/util/Map.get:(Ljava/lang/Object;)Ljava/lang/Object;
      94: checkcast     #18                 // class java/util/List
      97: astore        8
      99: aload_1
     100: aload_0
     101: getfield      #2                  // Field referencedTable:Lorg/hibernate/mapping/Table;
     104: invokestatic  #19                 // Method org/hibernate/cfg/reveng/TableIdentifier.create:(Lorg/hibernate/mapping/Table;)Lorg/hibernate/cfg/reveng/TableIdentifier;
     107: invokeinterface #20,  2           // InterfaceMethod org/hibernate/cfg/reveng/ReverseEngineeringStrategy.tableToClassName:(Lorg/hibernate/cfg/reveng/TableIdentifier;)Ljava/lang/String;
     112: astore        9
     114: aload         6
     116: aload         5
     118: aload         7
     120: aload         9
     122: aload         8
     124: invokevirtual #21                 // Method org/hibernate/mapping/Table.createForeignKey:(Ljava/lang/String;Ljava/util/List;Ljava/lang/String;Ljava/util/List;)Lorg/hibernate/mapping/ForeignKey;
     127: astore        10
     129: aload         10
     131: aload_0
     132: getfield      #2                  // Field referencedTable:Lorg/hibernate/mapping/Table;
     135: invokevirtual #22                 // Method org/hibernate/mapping/ForeignKey.setReferencedTable:(Lorg/hibernate/mapping/Table;)V
     138: aload_2
     139: aload         9
     141: aload         10
     143: invokestatic  #23                 // Method org/hibernate/cfg/reveng/JDBCReader.access$000:(Ljava/util/Map;Ljava/lang/String;Ljava/lang/Object;)V
     146: goto          23
     149: aload_2
     150: areturn
}
