Compiled from "TableFilter.java"
public class org.hibernate.cfg.reveng.TableFilter$Matcher {
  private static final int EQUALS;

  private static final int ENDSWITH;

  private static final int STARTSWITH;

  private static final int SUBSTRING;

  private static final int ANY;

  final int mode;

  final java.lang.String value;

  final java.lang.String matchValue;

  org.hibernate.cfg.reveng.TableFilter$Matcher(java.lang.String);
    Code:
       0: aload_0
       1: invokespecial #1                  // Method java/lang/Object."<init>":()V
       4: aload_0
       5: aload_1
       6: putfield      #2                  // Field matchValue:Ljava/lang/String;
       9: ldc           #3                  // String .*
      11: aload_1
      12: invokevirtual #4                  // Method java/lang/String.equals:(Ljava/lang/Object;)Z
      15: ifeq          31
      18: aload_0
      19: iconst_5
      20: putfield      #5                  // Field mode:I
      23: aload_0
      24: aconst_null
      25: putfield      #6                  // Field value:Ljava/lang/String;
      28: goto          148
      31: aload_1
      32: invokevirtual #7                  // Method java/lang/String.length:()I
      35: iconst_4
      36: if_icmple     80
      39: aload_1
      40: ldc           #3                  // String .*
      42: invokevirtual #8                  // Method java/lang/String.startsWith:(Ljava/lang/String;)Z
      45: ifeq          80
      48: aload_1
      49: ldc           #3                  // String .*
      51: invokevirtual #9                  // Method java/lang/String.endsWith:(Ljava/lang/String;)Z
      54: ifeq          80
      57: aload_0
      58: iconst_4
      59: putfield      #5                  // Field mode:I
      62: aload_0
      63: aload_1
      64: iconst_2
      65: aload_1
      66: invokevirtual #7                  // Method java/lang/String.length:()I
      69: iconst_2
      70: isub
      71: invokevirtual #10                 // Method java/lang/String.substring:(II)Ljava/lang/String;
      74: putfield      #6                  // Field value:Ljava/lang/String;
      77: goto          148
      80: aload_1
      81: ldc           #3                  // String .*
      83: invokevirtual #9                  // Method java/lang/String.endsWith:(Ljava/lang/String;)Z
      86: ifeq          112
      89: aload_0
      90: iconst_3
      91: putfield      #5                  // Field mode:I
      94: aload_0
      95: aload_1
      96: iconst_0
      97: aload_1
      98: invokevirtual #7                  // Method java/lang/String.length:()I
     101: iconst_2
     102: isub
     103: invokevirtual #10                 // Method java/lang/String.substring:(II)Ljava/lang/String;
     106: putfield      #6                  // Field value:Ljava/lang/String;
     109: goto          148
     112: aload_1
     113: ldc           #3                  // String .*
     115: invokevirtual #8                  // Method java/lang/String.startsWith:(Ljava/lang/String;)Z
     118: ifeq          138
     121: aload_0
     122: iconst_2
     123: putfield      #5                  // Field mode:I
     126: aload_0
     127: aload_1
     128: iconst_2
     129: invokevirtual #11                 // Method java/lang/String.substring:(I)Ljava/lang/String;
     132: putfield      #6                  // Field value:Ljava/lang/String;
     135: goto          148
     138: aload_0
     139: iconst_1
     140: putfield      #5                  // Field mode:I
     143: aload_0
     144: aload_1
     145: putfield      #6                  // Field value:Ljava/lang/String;
     148: return

  boolean match(java.lang.String);
    Code:
       0: aload_0
       1: getfield      #5                  // Field mode:I
       4: tableswitch   { // 1 to 5
                     1: 42
                     2: 51
                     3: 60
                     4: 69
                     5: 40
               default: 86
          }
      40: iconst_1
      41: ireturn
      42: aload_0
      43: getfield      #6                  // Field value:Ljava/lang/String;
      46: aload_1
      47: invokevirtual #4                  // Method java/lang/String.equals:(Ljava/lang/Object;)Z
      50: ireturn
      51: aload_1
      52: aload_0
      53: getfield      #6                  // Field value:Ljava/lang/String;
      56: invokevirtual #9                  // Method java/lang/String.endsWith:(Ljava/lang/String;)Z
      59: ireturn
      60: aload_1
      61: aload_0
      62: getfield      #6                  // Field value:Ljava/lang/String;
      65: invokevirtual #8                  // Method java/lang/String.startsWith:(Ljava/lang/String;)Z
      68: ireturn
      69: aload_1
      70: aload_0
      71: getfield      #6                  // Field value:Ljava/lang/String;
      74: invokevirtual #12                 // Method java/lang/String.indexOf:(Ljava/lang/String;)I
      77: iflt          84
      80: iconst_1
      81: goto          85
      84: iconst_0
      85: ireturn
      86: new           #13                 // class java/lang/IllegalStateException
      89: dup
      90: invokespecial #14                 // Method java/lang/IllegalStateException."<init>":()V
      93: athrow

  public java.lang.String toString();
    Code:
       0: aload_0
       1: getfield      #2                  // Field matchValue:Ljava/lang/String;
       4: areturn
}
