Compiled from "Producer.scala"
public abstract class akka.camel.ProducerSupport$class {
  public static void preStart(akka.camel.ProducerSupport);
    Code:
       0: aload_0
       1: invokeinterface #13,  1           // InterfaceMethod akka/camel/ProducerSupport.akka$camel$ProducerSupport$$super$preStart:()V
       6: aload_0
       7: invokestatic  #16                 // Method akka$camel$ProducerSupport$$register:(Lakka/camel/ProducerSupport;)V
      10: return

  public static void akka$camel$ProducerSupport$$register(akka.camel.ProducerSupport);
    Code:
       0: getstatic     #24                 // Field akka/actor/package$.MODULE$:Lakka/actor/package$;
       3: aload_0
       4: invokeinterface #28,  1           // InterfaceMethod akka/camel/ProducerSupport.camel:()Lakka/camel/Camel;
       9: invokeinterface #34,  1           // InterfaceMethod akka/camel/Camel.supervisor:()Lakka/actor/ActorRef;
      14: invokevirtual #38                 // Method akka/actor/package$.actorRef2Scala:(Lakka/actor/ActorRef;)Lakka/actor/ScalaActorRef;
      17: new           #40                 // class akka/camel/internal/CamelSupervisor$Register
      20: dup
      21: aload_0
      22: invokeinterface #43,  1           // InterfaceMethod akka/camel/ProducerSupport.self:()Lakka/actor/ActorRef;
      27: aload_0
      28: invokeinterface #47,  1           // InterfaceMethod akka/camel/ProducerSupport.endpointUri:()Ljava/lang/String;
      33: getstatic     #52                 // Field akka/camel/internal/CamelSupervisor$Register$.MODULE$:Lakka/camel/internal/CamelSupervisor$Register$;
      36: invokevirtual #56                 // Method akka/camel/internal/CamelSupervisor$Register$.apply$default$3:()Lscala/Option;
      39: invokespecial #60                 // Method akka/camel/internal/CamelSupervisor$Register."<init>":(Lakka/actor/ActorRef;Ljava/lang/String;Lscala/Option;)V
      42: aload_0
      43: invokeinterface #43,  1           // InterfaceMethod akka/camel/ProducerSupport.self:()Lakka/actor/ActorRef;
      48: invokeinterface #66,  3           // InterfaceMethod akka/actor/ScalaActorRef.$bang:(Ljava/lang/Object;Lakka/actor/ActorRef;)V
      53: return

  public static boolean oneway(akka.camel.ProducerSupport);
    Code:
       0: iconst_0
       1: ireturn

  public static scala.collection.immutable.Set headersToCopy(akka.camel.ProducerSupport);
    Code:
       0: aload_0
       1: invokeinterface #74,  1           // InterfaceMethod akka/camel/ProducerSupport.akka$camel$ProducerSupport$$headersToCopyDefault:()Lscala/collection/immutable/Set;
       6: areturn

  public static scala.PartialFunction produce(akka.camel.ProducerSupport);
    Code:
       0: new           #78                 // class akka/camel/ProducerSupport$$anonfun$produce$1
       3: dup
       4: aload_0
       5: invokespecial #80                 // Method akka/camel/ProducerSupport$$anonfun$produce$1."<init>":(Lakka/camel/ProducerSupport;)V
       8: areturn

  public static java.lang.Object transformOutgoingMessage(akka.camel.ProducerSupport, java.lang.Object);
    Code:
       0: aload_1
       1: areturn

  public static java.lang.Object transformResponse(akka.camel.ProducerSupport, java.lang.Object);
    Code:
       0: aload_1
       1: areturn

  public static void routeResponse(akka.camel.ProducerSupport, java.lang.Object);
    Code:
       0: aload_0
       1: invokeinterface #90,  1           // InterfaceMethod akka/camel/ProducerSupport.oneway:()Z
       6: ifne          39
       9: getstatic     #24                 // Field akka/actor/package$.MODULE$:Lakka/actor/package$;
      12: aload_0
      13: invokeinterface #93,  1           // InterfaceMethod akka/camel/ProducerSupport.sender:()Lakka/actor/ActorRef;
      18: invokevirtual #38                 // Method akka/actor/package$.actorRef2Scala:(Lakka/actor/ActorRef;)Lakka/actor/ScalaActorRef;
      21: aload_0
      22: aload_1
      23: invokeinterface #96,  2           // InterfaceMethod akka/camel/ProducerSupport.transformResponse:(Ljava/lang/Object;)Ljava/lang/Object;
      28: aload_0
      29: invokeinterface #43,  1           // InterfaceMethod akka/camel/ProducerSupport.self:()Lakka/actor/ActorRef;
      34: invokeinterface #66,  3           // InterfaceMethod akka/actor/ScalaActorRef.$bang:(Ljava/lang/Object;Lakka/actor/ActorRef;)V
      39: return

  public static void $init$(akka.camel.ProducerSupport);
    Code:
       0: aload_0
       1: getstatic     #102                // Field scala/package$.MODULE$:Lscala/package$;
       4: invokevirtual #106                // Method scala/package$.Vector:()Lscala/collection/immutable/Vector$;
       7: invokevirtual #112                // Method scala/collection/immutable/Vector$.empty:()Lscala/collection/immutable/Vector;
      10: invokeinterface #116,  2          // InterfaceMethod akka/camel/ProducerSupport.akka$camel$ProducerSupport$$messages_$eq:(Lscala/collection/immutable/Vector;)V
      15: aload_0
      16: getstatic     #121                // Field scala/None$.MODULE$:Lscala/None$;
      19: invokeinterface #125,  2          // InterfaceMethod akka/camel/ProducerSupport.akka$camel$ProducerSupport$$producerChild_$eq:(Lscala/Option;)V
      24: aload_0
      25: getstatic     #130                // Field scala/Predef$.MODULE$:Lscala/Predef$;
      28: invokevirtual #134                // Method scala/Predef$.Set:()Lscala/collection/immutable/Set$;
      31: getstatic     #130                // Field scala/Predef$.MODULE$:Lscala/Predef$;
      34: iconst_1
      35: anewarray     #136                // class java/lang/String
      38: dup
      39: iconst_0
      40: getstatic     #141                // Field akka/camel/CamelMessage$.MODULE$:Lakka/camel/CamelMessage$;
      43: invokevirtual #144                // Method akka/camel/CamelMessage$.MessageExchangeId:()Ljava/lang/String;
      46: aastore
      47: checkcast     #146                // class "[Ljava/lang/Object;"
      50: invokevirtual #150                // Method scala/Predef$.wrapRefArray:([Ljava/lang/Object;)Lscala/collection/mutable/WrappedArray;
      53: invokevirtual #156                // Method scala/collection/immutable/Set$.apply:(Lscala/collection/Seq;)Lscala/collection/GenTraversable;
      56: checkcast     #158                // class scala/collection/immutable/Set
      59: invokeinterface #162,  2          // InterfaceMethod akka/camel/ProducerSupport.akka$camel$ProducerSupport$_setter_$akka$camel$ProducerSupport$$headersToCopyDefault_$eq:(Lscala/collection/immutable/Set;)V
      64: return
}
