Compiled from "CreateUserRequest.java"
final class software.amazon.awssdk.services.workdocs.model.CreateUserRequest$BuilderImpl extends software.amazon.awssdk.services.workdocs.model.WorkDocsRequest$BuilderImpl implements software.amazon.awssdk.services.workdocs.model.CreateUserRequest$Builder {
  private java.lang.String organizationId;

  private java.lang.String username;

  private java.lang.String emailAddress;

  private java.lang.String givenName;

  private java.lang.String surname;

  private java.lang.String password;

  private java.lang.String timeZoneId;

  private software.amazon.awssdk.services.workdocs.model.StorageRuleType storageRule;

  private java.lang.String authenticationToken;

  private software.amazon.awssdk.services.workdocs.model.CreateUserRequest$BuilderImpl();
    Code:
       0: aload_0
       1: invokespecial #12                 // Method software/amazon/awssdk/services/workdocs/model/WorkDocsRequest$BuilderImpl."<init>":()V
       4: return

  private software.amazon.awssdk.services.workdocs.model.CreateUserRequest$BuilderImpl(software.amazon.awssdk.services.workdocs.model.CreateUserRequest);
    Code:
       0: aload_0
       1: aload_1
       2: invokespecial #13                 // Method software/amazon/awssdk/services/workdocs/model/WorkDocsRequest$BuilderImpl."<init>":(Lsoftware/amazon/awssdk/services/workdocs/model/WorkDocsRequest;)V
       5: aload_0
       6: aload_1
       7: invokestatic  #14                 // Method software/amazon/awssdk/services/workdocs/model/CreateUserRequest.access$1100:(Lsoftware/amazon/awssdk/services/workdocs/model/CreateUserRequest;)Ljava/lang/String;
      10: invokevirtual #15                 // Method organizationId:(Ljava/lang/String;)Lsoftware/amazon/awssdk/services/workdocs/model/CreateUserRequest$Builder;
      13: pop
      14: aload_0
      15: aload_1
      16: invokestatic  #16                 // Method software/amazon/awssdk/services/workdocs/model/CreateUserRequest.access$1200:(Lsoftware/amazon/awssdk/services/workdocs/model/CreateUserRequest;)Ljava/lang/String;
      19: invokevirtual #17                 // Method username:(Ljava/lang/String;)Lsoftware/amazon/awssdk/services/workdocs/model/CreateUserRequest$Builder;
      22: pop
      23: aload_0
      24: aload_1
      25: invokestatic  #18                 // Method software/amazon/awssdk/services/workdocs/model/CreateUserRequest.access$1300:(Lsoftware/amazon/awssdk/services/workdocs/model/CreateUserRequest;)Ljava/lang/String;
      28: invokevirtual #19                 // Method emailAddress:(Ljava/lang/String;)Lsoftware/amazon/awssdk/services/workdocs/model/CreateUserRequest$Builder;
      31: pop
      32: aload_0
      33: aload_1
      34: invokestatic  #20                 // Method software/amazon/awssdk/services/workdocs/model/CreateUserRequest.access$1400:(Lsoftware/amazon/awssdk/services/workdocs/model/CreateUserRequest;)Ljava/lang/String;
      37: invokevirtual #21                 // Method givenName:(Ljava/lang/String;)Lsoftware/amazon/awssdk/services/workdocs/model/CreateUserRequest$Builder;
      40: pop
      41: aload_0
      42: aload_1
      43: invokestatic  #22                 // Method software/amazon/awssdk/services/workdocs/model/CreateUserRequest.access$1500:(Lsoftware/amazon/awssdk/services/workdocs/model/CreateUserRequest;)Ljava/lang/String;
      46: invokevirtual #23                 // Method surname:(Ljava/lang/String;)Lsoftware/amazon/awssdk/services/workdocs/model/CreateUserRequest$Builder;
      49: pop
      50: aload_0
      51: aload_1
      52: invokestatic  #24                 // Method software/amazon/awssdk/services/workdocs/model/CreateUserRequest.access$1600:(Lsoftware/amazon/awssdk/services/workdocs/model/CreateUserRequest;)Ljava/lang/String;
      55: invokevirtual #25                 // Method password:(Ljava/lang/String;)Lsoftware/amazon/awssdk/services/workdocs/model/CreateUserRequest$Builder;
      58: pop
      59: aload_0
      60: aload_1
      61: invokestatic  #26                 // Method software/amazon/awssdk/services/workdocs/model/CreateUserRequest.access$1700:(Lsoftware/amazon/awssdk/services/workdocs/model/CreateUserRequest;)Ljava/lang/String;
      64: invokevirtual #27                 // Method timeZoneId:(Ljava/lang/String;)Lsoftware/amazon/awssdk/services/workdocs/model/CreateUserRequest$Builder;
      67: pop
      68: aload_0
      69: aload_1
      70: invokestatic  #28                 // Method software/amazon/awssdk/services/workdocs/model/CreateUserRequest.access$1800:(Lsoftware/amazon/awssdk/services/workdocs/model/CreateUserRequest;)Lsoftware/amazon/awssdk/services/workdocs/model/StorageRuleType;
      73: invokevirtual #29                 // Method storageRule:(Lsoftware/amazon/awssdk/services/workdocs/model/StorageRuleType;)Lsoftware/amazon/awssdk/services/workdocs/model/CreateUserRequest$Builder;
      76: pop
      77: aload_0
      78: aload_1
      79: invokestatic  #30                 // Method software/amazon/awssdk/services/workdocs/model/CreateUserRequest.access$1900:(Lsoftware/amazon/awssdk/services/workdocs/model/CreateUserRequest;)Ljava/lang/String;
      82: invokevirtual #31                 // Method authenticationToken:(Ljava/lang/String;)Lsoftware/amazon/awssdk/services/workdocs/model/CreateUserRequest$Builder;
      85: pop
      86: return

  public final java.lang.String getOrganizationId();
    Code:
       0: aload_0
       1: getfield      #11                 // Field organizationId:Ljava/lang/String;
       4: areturn

  public final void setOrganizationId(java.lang.String);
    Code:
       0: aload_0
       1: aload_1
       2: putfield      #11                 // Field organizationId:Ljava/lang/String;
       5: return

  public final software.amazon.awssdk.services.workdocs.model.CreateUserRequest$Builder organizationId(java.lang.String);
    Code:
       0: aload_0
       1: aload_1
       2: putfield      #11                 // Field organizationId:Ljava/lang/String;
       5: aload_0
       6: areturn

  public final java.lang.String getUsername();
    Code:
       0: aload_0
       1: getfield      #10                 // Field username:Ljava/lang/String;
       4: areturn

  public final void setUsername(java.lang.String);
    Code:
       0: aload_0
       1: aload_1
       2: putfield      #10                 // Field username:Ljava/lang/String;
       5: return

  public final software.amazon.awssdk.services.workdocs.model.CreateUserRequest$Builder username(java.lang.String);
    Code:
       0: aload_0
       1: aload_1
       2: putfield      #10                 // Field username:Ljava/lang/String;
       5: aload_0
       6: areturn

  public final java.lang.String getEmailAddress();
    Code:
       0: aload_0
       1: getfield      #9                  // Field emailAddress:Ljava/lang/String;
       4: areturn

  public final void setEmailAddress(java.lang.String);
    Code:
       0: aload_0
       1: aload_1
       2: putfield      #9                  // Field emailAddress:Ljava/lang/String;
       5: return

  public final software.amazon.awssdk.services.workdocs.model.CreateUserRequest$Builder emailAddress(java.lang.String);
    Code:
       0: aload_0
       1: aload_1
       2: putfield      #9                  // Field emailAddress:Ljava/lang/String;
       5: aload_0
       6: areturn

  public final java.lang.String getGivenName();
    Code:
       0: aload_0
       1: getfield      #8                  // Field givenName:Ljava/lang/String;
       4: areturn

  public final void setGivenName(java.lang.String);
    Code:
       0: aload_0
       1: aload_1
       2: putfield      #8                  // Field givenName:Ljava/lang/String;
       5: return

  public final software.amazon.awssdk.services.workdocs.model.CreateUserRequest$Builder givenName(java.lang.String);
    Code:
       0: aload_0
       1: aload_1
       2: putfield      #8                  // Field givenName:Ljava/lang/String;
       5: aload_0
       6: areturn

  public final java.lang.String getSurname();
    Code:
       0: aload_0
       1: getfield      #7                  // Field surname:Ljava/lang/String;
       4: areturn

  public final void setSurname(java.lang.String);
    Code:
       0: aload_0
       1: aload_1
       2: putfield      #7                  // Field surname:Ljava/lang/String;
       5: return

  public final software.amazon.awssdk.services.workdocs.model.CreateUserRequest$Builder surname(java.lang.String);
    Code:
       0: aload_0
       1: aload_1
       2: putfield      #7                  // Field surname:Ljava/lang/String;
       5: aload_0
       6: areturn

  public final java.lang.String getPassword();
    Code:
       0: aload_0
       1: getfield      #6                  // Field password:Ljava/lang/String;
       4: areturn

  public final void setPassword(java.lang.String);
    Code:
       0: aload_0
       1: aload_1
       2: putfield      #6                  // Field password:Ljava/lang/String;
       5: return

  public final software.amazon.awssdk.services.workdocs.model.CreateUserRequest$Builder password(java.lang.String);
    Code:
       0: aload_0
       1: aload_1
       2: putfield      #6                  // Field password:Ljava/lang/String;
       5: aload_0
       6: areturn

  public final java.lang.String getTimeZoneId();
    Code:
       0: aload_0
       1: getfield      #5                  // Field timeZoneId:Ljava/lang/String;
       4: areturn

  public final void setTimeZoneId(java.lang.String);
    Code:
       0: aload_0
       1: aload_1
       2: putfield      #5                  // Field timeZoneId:Ljava/lang/String;
       5: return

  public final software.amazon.awssdk.services.workdocs.model.CreateUserRequest$Builder timeZoneId(java.lang.String);
    Code:
       0: aload_0
       1: aload_1
       2: putfield      #5                  // Field timeZoneId:Ljava/lang/String;
       5: aload_0
       6: areturn

  public final software.amazon.awssdk.services.workdocs.model.StorageRuleType$Builder getStorageRule();
    Code:
       0: aload_0
       1: getfield      #4                  // Field storageRule:Lsoftware/amazon/awssdk/services/workdocs/model/StorageRuleType;
       4: ifnull        17
       7: aload_0
       8: getfield      #4                  // Field storageRule:Lsoftware/amazon/awssdk/services/workdocs/model/StorageRuleType;
      11: invokevirtual #32                 // Method software/amazon/awssdk/services/workdocs/model/StorageRuleType.toBuilder:()Lsoftware/amazon/awssdk/services/workdocs/model/StorageRuleType$Builder;
      14: goto          18
      17: aconst_null
      18: areturn

  public final void setStorageRule(software.amazon.awssdk.services.workdocs.model.StorageRuleType$BuilderImpl);
    Code:
       0: aload_0
       1: aload_1
       2: ifnull        12
       5: aload_1
       6: invokevirtual #33                 // Method software/amazon/awssdk/services/workdocs/model/StorageRuleType$BuilderImpl.build:()Lsoftware/amazon/awssdk/services/workdocs/model/StorageRuleType;
       9: goto          13
      12: aconst_null
      13: putfield      #4                  // Field storageRule:Lsoftware/amazon/awssdk/services/workdocs/model/StorageRuleType;
      16: return

  public final software.amazon.awssdk.services.workdocs.model.CreateUserRequest$Builder storageRule(software.amazon.awssdk.services.workdocs.model.StorageRuleType);
    Code:
       0: aload_0
       1: aload_1
       2: putfield      #4                  // Field storageRule:Lsoftware/amazon/awssdk/services/workdocs/model/StorageRuleType;
       5: aload_0
       6: areturn

  public final java.lang.String getAuthenticationToken();
    Code:
       0: aload_0
       1: getfield      #3                  // Field authenticationToken:Ljava/lang/String;
       4: areturn

  public final void setAuthenticationToken(java.lang.String);
    Code:
       0: aload_0
       1: aload_1
       2: putfield      #3                  // Field authenticationToken:Ljava/lang/String;
       5: return

  public final software.amazon.awssdk.services.workdocs.model.CreateUserRequest$Builder authenticationToken(java.lang.String);
    Code:
       0: aload_0
       1: aload_1
       2: putfield      #3                  // Field authenticationToken:Ljava/lang/String;
       5: aload_0
       6: areturn

  public software.amazon.awssdk.services.workdocs.model.CreateUserRequest$Builder overrideConfiguration(software.amazon.awssdk.awscore.AwsRequestOverrideConfiguration);
    Code:
       0: aload_0
       1: aload_1
       2: invokespecial #34                 // Method software/amazon/awssdk/services/workdocs/model/WorkDocsRequest$BuilderImpl.overrideConfiguration:(Lsoftware/amazon/awssdk/awscore/AwsRequestOverrideConfiguration;)Lsoftware/amazon/awssdk/awscore/AwsRequest$Builder;
       5: pop
       6: aload_0
       7: areturn

  public software.amazon.awssdk.services.workdocs.model.CreateUserRequest$Builder overrideConfiguration(java.util.function.Consumer<software.amazon.awssdk.awscore.AwsRequestOverrideConfiguration$Builder>);
    Code:
       0: aload_0
       1: aload_1
       2: invokespecial #35                 // Method software/amazon/awssdk/services/workdocs/model/WorkDocsRequest$BuilderImpl.overrideConfiguration:(Ljava/util/function/Consumer;)Lsoftware/amazon/awssdk/awscore/AwsRequest$Builder;
       5: pop
       6: aload_0
       7: areturn

  public software.amazon.awssdk.services.workdocs.model.CreateUserRequest build();
    Code:
       0: new           #36                 // class software/amazon/awssdk/services/workdocs/model/CreateUserRequest
       3: dup
       4: aload_0
       5: aconst_null
       6: invokespecial #37                 // Method software/amazon/awssdk/services/workdocs/model/CreateUserRequest."<init>":(Lsoftware/amazon/awssdk/services/workdocs/model/CreateUserRequest$BuilderImpl;Lsoftware/amazon/awssdk/services/workdocs/model/CreateUserRequest$1;)V
       9: areturn

  public java.util.List<software.amazon.awssdk.core.SdkField<?>> sdkFields();
    Code:
       0: invokestatic  #38                 // Method software/amazon/awssdk/services/workdocs/model/CreateUserRequest.access$2100:()Ljava/util/List;
       3: areturn

  public software.amazon.awssdk.services.workdocs.model.WorkDocsRequest build();
    Code:
       0: aload_0
       1: invokevirtual #39                 // Method build:()Lsoftware/amazon/awssdk/services/workdocs/model/CreateUserRequest;
       4: areturn

  public software.amazon.awssdk.awscore.AwsRequest build();
    Code:
       0: aload_0
       1: invokevirtual #39                 // Method build:()Lsoftware/amazon/awssdk/services/workdocs/model/CreateUserRequest;
       4: areturn

  public software.amazon.awssdk.awscore.AwsRequest$Builder overrideConfiguration(java.util.function.Consumer);
    Code:
       0: aload_0
       1: aload_1
       2: invokevirtual #40                 // Method overrideConfiguration:(Ljava/util/function/Consumer;)Lsoftware/amazon/awssdk/services/workdocs/model/CreateUserRequest$Builder;
       5: areturn

  public software.amazon.awssdk.awscore.AwsRequest$Builder overrideConfiguration(software.amazon.awssdk.awscore.AwsRequestOverrideConfiguration);
    Code:
       0: aload_0
       1: aload_1
       2: invokevirtual #41                 // Method overrideConfiguration:(Lsoftware/amazon/awssdk/awscore/AwsRequestOverrideConfiguration;)Lsoftware/amazon/awssdk/services/workdocs/model/CreateUserRequest$Builder;
       5: areturn

  public software.amazon.awssdk.core.SdkRequest build();
    Code:
       0: aload_0
       1: invokevirtual #39                 // Method build:()Lsoftware/amazon/awssdk/services/workdocs/model/CreateUserRequest;
       4: areturn

  public java.lang.Object build();
    Code:
       0: aload_0
       1: invokevirtual #39                 // Method build:()Lsoftware/amazon/awssdk/services/workdocs/model/CreateUserRequest;
       4: areturn

  static java.lang.String access$000(software.amazon.awssdk.services.workdocs.model.CreateUserRequest$BuilderImpl);
    Code:
       0: aload_0
       1: getfield      #11                 // Field organizationId:Ljava/lang/String;
       4: areturn

  static java.lang.String access$100(software.amazon.awssdk.services.workdocs.model.CreateUserRequest$BuilderImpl);
    Code:
       0: aload_0
       1: getfield      #10                 // Field username:Ljava/lang/String;
       4: areturn

  static java.lang.String access$200(software.amazon.awssdk.services.workdocs.model.CreateUserRequest$BuilderImpl);
    Code:
       0: aload_0
       1: getfield      #9                  // Field emailAddress:Ljava/lang/String;
       4: areturn

  static java.lang.String access$300(software.amazon.awssdk.services.workdocs.model.CreateUserRequest$BuilderImpl);
    Code:
       0: aload_0
       1: getfield      #8                  // Field givenName:Ljava/lang/String;
       4: areturn

  static java.lang.String access$400(software.amazon.awssdk.services.workdocs.model.CreateUserRequest$BuilderImpl);
    Code:
       0: aload_0
       1: getfield      #7                  // Field surname:Ljava/lang/String;
       4: areturn

  static java.lang.String access$500(software.amazon.awssdk.services.workdocs.model.CreateUserRequest$BuilderImpl);
    Code:
       0: aload_0
       1: getfield      #6                  // Field password:Ljava/lang/String;
       4: areturn

  static java.lang.String access$600(software.amazon.awssdk.services.workdocs.model.CreateUserRequest$BuilderImpl);
    Code:
       0: aload_0
       1: getfield      #5                  // Field timeZoneId:Ljava/lang/String;
       4: areturn

  static software.amazon.awssdk.services.workdocs.model.StorageRuleType access$700(software.amazon.awssdk.services.workdocs.model.CreateUserRequest$BuilderImpl);
    Code:
       0: aload_0
       1: getfield      #4                  // Field storageRule:Lsoftware/amazon/awssdk/services/workdocs/model/StorageRuleType;
       4: areturn

  static java.lang.String access$800(software.amazon.awssdk.services.workdocs.model.CreateUserRequest$BuilderImpl);
    Code:
       0: aload_0
       1: getfield      #3                  // Field authenticationToken:Ljava/lang/String;
       4: areturn

  software.amazon.awssdk.services.workdocs.model.CreateUserRequest$BuilderImpl(software.amazon.awssdk.services.workdocs.model.CreateUserRequest, software.amazon.awssdk.services.workdocs.model.CreateUserRequest$1);
    Code:
       0: aload_0
       1: aload_1
       2: invokespecial #2                  // Method "<init>":(Lsoftware/amazon/awssdk/services/workdocs/model/CreateUserRequest;)V
       5: return

  software.amazon.awssdk.services.workdocs.model.CreateUserRequest$BuilderImpl(software.amazon.awssdk.services.workdocs.model.CreateUserRequest$1);
    Code:
       0: aload_0
       1: invokespecial #1                  // Method "<init>":()V
       4: return
}
