Compiled from "CreateCommentRequest.java"
public interface software.amazon.awssdk.services.workdocs.model.CreateCommentRequest$Builder extends software.amazon.awssdk.services.workdocs.model.WorkDocsRequest$Builder, software.amazon.awssdk.core.SdkPojo, software.amazon.awssdk.utils.builder.CopyableBuilder<software.amazon.awssdk.services.workdocs.model.CreateCommentRequest$Builder, software.amazon.awssdk.services.workdocs.model.CreateCommentRequest> {
  public abstract software.amazon.awssdk.services.workdocs.model.CreateCommentRequest$Builder authenticationToken(java.lang.String);

  public abstract software.amazon.awssdk.services.workdocs.model.CreateCommentRequest$Builder documentId(java.lang.String);

  public abstract software.amazon.awssdk.services.workdocs.model.CreateCommentRequest$Builder versionId(java.lang.String);

  public abstract software.amazon.awssdk.services.workdocs.model.CreateCommentRequest$Builder parentId(java.lang.String);

  public abstract software.amazon.awssdk.services.workdocs.model.CreateCommentRequest$Builder threadId(java.lang.String);

  public abstract software.amazon.awssdk.services.workdocs.model.CreateCommentRequest$Builder text(java.lang.String);

  public abstract software.amazon.awssdk.services.workdocs.model.CreateCommentRequest$Builder visibility(java.lang.String);

  public abstract software.amazon.awssdk.services.workdocs.model.CreateCommentRequest$Builder visibility(software.amazon.awssdk.services.workdocs.model.CommentVisibilityType);

  public abstract software.amazon.awssdk.services.workdocs.model.CreateCommentRequest$Builder notifyCollaborators(java.lang.Boolean);

  public abstract software.amazon.awssdk.services.workdocs.model.CreateCommentRequest$Builder overrideConfiguration(software.amazon.awssdk.awscore.AwsRequestOverrideConfiguration);

  public abstract software.amazon.awssdk.services.workdocs.model.CreateCommentRequest$Builder overrideConfiguration(java.util.function.Consumer<software.amazon.awssdk.awscore.AwsRequestOverrideConfiguration$Builder>);

  public default software.amazon.awssdk.awscore.AwsRequest$Builder overrideConfiguration(java.util.function.Consumer);
    Code:
       0: aload_0
       1: aload_1
       2: invokeinterface #1,  2            // InterfaceMethod overrideConfiguration:(Ljava/util/function/Consumer;)Lsoftware/amazon/awssdk/services/workdocs/model/CreateCommentRequest$Builder;
       7: areturn

  public default software.amazon.awssdk.awscore.AwsRequest$Builder overrideConfiguration(software.amazon.awssdk.awscore.AwsRequestOverrideConfiguration);
    Code:
       0: aload_0
       1: aload_1
       2: invokeinterface #2,  2            // InterfaceMethod overrideConfiguration:(Lsoftware/amazon/awssdk/awscore/AwsRequestOverrideConfiguration;)Lsoftware/amazon/awssdk/services/workdocs/model/CreateCommentRequest$Builder;
       7: areturn
}
