Compiled from "InitiateDocumentVersionUploadRequest.java"
final class software.amazon.awssdk.services.workdocs.model.InitiateDocumentVersionUploadRequest$BuilderImpl extends software.amazon.awssdk.services.workdocs.model.WorkDocsRequest$BuilderImpl implements software.amazon.awssdk.services.workdocs.model.InitiateDocumentVersionUploadRequest$Builder {
  private java.lang.String authenticationToken;

  private java.lang.String id;

  private java.lang.String name;

  private java.time.Instant contentCreatedTimestamp;

  private java.time.Instant contentModifiedTimestamp;

  private java.lang.String contentType;

  private java.lang.Long documentSizeInBytes;

  private java.lang.String parentFolderId;

  private software.amazon.awssdk.services.workdocs.model.InitiateDocumentVersionUploadRequest$BuilderImpl();
    Code:
       0: aload_0
       1: invokespecial #11                 // Method software/amazon/awssdk/services/workdocs/model/WorkDocsRequest$BuilderImpl."<init>":()V
       4: return

  private software.amazon.awssdk.services.workdocs.model.InitiateDocumentVersionUploadRequest$BuilderImpl(software.amazon.awssdk.services.workdocs.model.InitiateDocumentVersionUploadRequest);
    Code:
       0: aload_0
       1: aload_1
       2: invokespecial #12                 // Method software/amazon/awssdk/services/workdocs/model/WorkDocsRequest$BuilderImpl."<init>":(Lsoftware/amazon/awssdk/services/workdocs/model/WorkDocsRequest;)V
       5: aload_0
       6: aload_1
       7: invokestatic  #13                 // Method software/amazon/awssdk/services/workdocs/model/InitiateDocumentVersionUploadRequest.access$1000:(Lsoftware/amazon/awssdk/services/workdocs/model/InitiateDocumentVersionUploadRequest;)Ljava/lang/String;
      10: invokevirtual #14                 // Method authenticationToken:(Ljava/lang/String;)Lsoftware/amazon/awssdk/services/workdocs/model/InitiateDocumentVersionUploadRequest$Builder;
      13: pop
      14: aload_0
      15: aload_1
      16: invokestatic  #15                 // Method software/amazon/awssdk/services/workdocs/model/InitiateDocumentVersionUploadRequest.access$1100:(Lsoftware/amazon/awssdk/services/workdocs/model/InitiateDocumentVersionUploadRequest;)Ljava/lang/String;
      19: invokevirtual #16                 // Method id:(Ljava/lang/String;)Lsoftware/amazon/awssdk/services/workdocs/model/InitiateDocumentVersionUploadRequest$Builder;
      22: pop
      23: aload_0
      24: aload_1
      25: invokestatic  #17                 // Method software/amazon/awssdk/services/workdocs/model/InitiateDocumentVersionUploadRequest.access$1200:(Lsoftware/amazon/awssdk/services/workdocs/model/InitiateDocumentVersionUploadRequest;)Ljava/lang/String;
      28: invokevirtual #18                 // Method name:(Ljava/lang/String;)Lsoftware/amazon/awssdk/services/workdocs/model/InitiateDocumentVersionUploadRequest$Builder;
      31: pop
      32: aload_0
      33: aload_1
      34: invokestatic  #19                 // Method software/amazon/awssdk/services/workdocs/model/InitiateDocumentVersionUploadRequest.access$1300:(Lsoftware/amazon/awssdk/services/workdocs/model/InitiateDocumentVersionUploadRequest;)Ljava/time/Instant;
      37: invokevirtual #20                 // Method contentCreatedTimestamp:(Ljava/time/Instant;)Lsoftware/amazon/awssdk/services/workdocs/model/InitiateDocumentVersionUploadRequest$Builder;
      40: pop
      41: aload_0
      42: aload_1
      43: invokestatic  #21                 // Method software/amazon/awssdk/services/workdocs/model/InitiateDocumentVersionUploadRequest.access$1400:(Lsoftware/amazon/awssdk/services/workdocs/model/InitiateDocumentVersionUploadRequest;)Ljava/time/Instant;
      46: invokevirtual #22                 // Method contentModifiedTimestamp:(Ljava/time/Instant;)Lsoftware/amazon/awssdk/services/workdocs/model/InitiateDocumentVersionUploadRequest$Builder;
      49: pop
      50: aload_0
      51: aload_1
      52: invokestatic  #23                 // Method software/amazon/awssdk/services/workdocs/model/InitiateDocumentVersionUploadRequest.access$1500:(Lsoftware/amazon/awssdk/services/workdocs/model/InitiateDocumentVersionUploadRequest;)Ljava/lang/String;
      55: invokevirtual #24                 // Method contentType:(Ljava/lang/String;)Lsoftware/amazon/awssdk/services/workdocs/model/InitiateDocumentVersionUploadRequest$Builder;
      58: pop
      59: aload_0
      60: aload_1
      61: invokestatic  #25                 // Method software/amazon/awssdk/services/workdocs/model/InitiateDocumentVersionUploadRequest.access$1600:(Lsoftware/amazon/awssdk/services/workdocs/model/InitiateDocumentVersionUploadRequest;)Ljava/lang/Long;
      64: invokevirtual #26                 // Method documentSizeInBytes:(Ljava/lang/Long;)Lsoftware/amazon/awssdk/services/workdocs/model/InitiateDocumentVersionUploadRequest$Builder;
      67: pop
      68: aload_0
      69: aload_1
      70: invokestatic  #27                 // Method software/amazon/awssdk/services/workdocs/model/InitiateDocumentVersionUploadRequest.access$1700:(Lsoftware/amazon/awssdk/services/workdocs/model/InitiateDocumentVersionUploadRequest;)Ljava/lang/String;
      73: invokevirtual #28                 // Method parentFolderId:(Ljava/lang/String;)Lsoftware/amazon/awssdk/services/workdocs/model/InitiateDocumentVersionUploadRequest$Builder;
      76: pop
      77: return

  public final java.lang.String getAuthenticationToken();
    Code:
       0: aload_0
       1: getfield      #10                 // Field authenticationToken:Ljava/lang/String;
       4: areturn

  public final void setAuthenticationToken(java.lang.String);
    Code:
       0: aload_0
       1: aload_1
       2: putfield      #10                 // Field authenticationToken:Ljava/lang/String;
       5: return

  public final software.amazon.awssdk.services.workdocs.model.InitiateDocumentVersionUploadRequest$Builder authenticationToken(java.lang.String);
    Code:
       0: aload_0
       1: aload_1
       2: putfield      #10                 // Field authenticationToken:Ljava/lang/String;
       5: aload_0
       6: areturn

  public final java.lang.String getId();
    Code:
       0: aload_0
       1: getfield      #9                  // Field id:Ljava/lang/String;
       4: areturn

  public final void setId(java.lang.String);
    Code:
       0: aload_0
       1: aload_1
       2: putfield      #9                  // Field id:Ljava/lang/String;
       5: return

  public final software.amazon.awssdk.services.workdocs.model.InitiateDocumentVersionUploadRequest$Builder id(java.lang.String);
    Code:
       0: aload_0
       1: aload_1
       2: putfield      #9                  // Field id:Ljava/lang/String;
       5: aload_0
       6: areturn

  public final java.lang.String getName();
    Code:
       0: aload_0
       1: getfield      #8                  // Field name:Ljava/lang/String;
       4: areturn

  public final void setName(java.lang.String);
    Code:
       0: aload_0
       1: aload_1
       2: putfield      #8                  // Field name:Ljava/lang/String;
       5: return

  public final software.amazon.awssdk.services.workdocs.model.InitiateDocumentVersionUploadRequest$Builder name(java.lang.String);
    Code:
       0: aload_0
       1: aload_1
       2: putfield      #8                  // Field name:Ljava/lang/String;
       5: aload_0
       6: areturn

  public final java.time.Instant getContentCreatedTimestamp();
    Code:
       0: aload_0
       1: getfield      #7                  // Field contentCreatedTimestamp:Ljava/time/Instant;
       4: areturn

  public final void setContentCreatedTimestamp(java.time.Instant);
    Code:
       0: aload_0
       1: aload_1
       2: putfield      #7                  // Field contentCreatedTimestamp:Ljava/time/Instant;
       5: return

  public final software.amazon.awssdk.services.workdocs.model.InitiateDocumentVersionUploadRequest$Builder contentCreatedTimestamp(java.time.Instant);
    Code:
       0: aload_0
       1: aload_1
       2: putfield      #7                  // Field contentCreatedTimestamp:Ljava/time/Instant;
       5: aload_0
       6: areturn

  public final java.time.Instant getContentModifiedTimestamp();
    Code:
       0: aload_0
       1: getfield      #6                  // Field contentModifiedTimestamp:Ljava/time/Instant;
       4: areturn

  public final void setContentModifiedTimestamp(java.time.Instant);
    Code:
       0: aload_0
       1: aload_1
       2: putfield      #6                  // Field contentModifiedTimestamp:Ljava/time/Instant;
       5: return

  public final software.amazon.awssdk.services.workdocs.model.InitiateDocumentVersionUploadRequest$Builder contentModifiedTimestamp(java.time.Instant);
    Code:
       0: aload_0
       1: aload_1
       2: putfield      #6                  // Field contentModifiedTimestamp:Ljava/time/Instant;
       5: aload_0
       6: areturn

  public final java.lang.String getContentType();
    Code:
       0: aload_0
       1: getfield      #5                  // Field contentType:Ljava/lang/String;
       4: areturn

  public final void setContentType(java.lang.String);
    Code:
       0: aload_0
       1: aload_1
       2: putfield      #5                  // Field contentType:Ljava/lang/String;
       5: return

  public final software.amazon.awssdk.services.workdocs.model.InitiateDocumentVersionUploadRequest$Builder contentType(java.lang.String);
    Code:
       0: aload_0
       1: aload_1
       2: putfield      #5                  // Field contentType:Ljava/lang/String;
       5: aload_0
       6: areturn

  public final java.lang.Long getDocumentSizeInBytes();
    Code:
       0: aload_0
       1: getfield      #4                  // Field documentSizeInBytes:Ljava/lang/Long;
       4: areturn

  public final void setDocumentSizeInBytes(java.lang.Long);
    Code:
       0: aload_0
       1: aload_1
       2: putfield      #4                  // Field documentSizeInBytes:Ljava/lang/Long;
       5: return

  public final software.amazon.awssdk.services.workdocs.model.InitiateDocumentVersionUploadRequest$Builder documentSizeInBytes(java.lang.Long);
    Code:
       0: aload_0
       1: aload_1
       2: putfield      #4                  // Field documentSizeInBytes:Ljava/lang/Long;
       5: aload_0
       6: areturn

  public final java.lang.String getParentFolderId();
    Code:
       0: aload_0
       1: getfield      #3                  // Field parentFolderId:Ljava/lang/String;
       4: areturn

  public final void setParentFolderId(java.lang.String);
    Code:
       0: aload_0
       1: aload_1
       2: putfield      #3                  // Field parentFolderId:Ljava/lang/String;
       5: return

  public final software.amazon.awssdk.services.workdocs.model.InitiateDocumentVersionUploadRequest$Builder parentFolderId(java.lang.String);
    Code:
       0: aload_0
       1: aload_1
       2: putfield      #3                  // Field parentFolderId:Ljava/lang/String;
       5: aload_0
       6: areturn

  public software.amazon.awssdk.services.workdocs.model.InitiateDocumentVersionUploadRequest$Builder overrideConfiguration(software.amazon.awssdk.awscore.AwsRequestOverrideConfiguration);
    Code:
       0: aload_0
       1: aload_1
       2: invokespecial #29                 // Method software/amazon/awssdk/services/workdocs/model/WorkDocsRequest$BuilderImpl.overrideConfiguration:(Lsoftware/amazon/awssdk/awscore/AwsRequestOverrideConfiguration;)Lsoftware/amazon/awssdk/awscore/AwsRequest$Builder;
       5: pop
       6: aload_0
       7: areturn

  public software.amazon.awssdk.services.workdocs.model.InitiateDocumentVersionUploadRequest$Builder overrideConfiguration(java.util.function.Consumer<software.amazon.awssdk.awscore.AwsRequestOverrideConfiguration$Builder>);
    Code:
       0: aload_0
       1: aload_1
       2: invokespecial #30                 // Method software/amazon/awssdk/services/workdocs/model/WorkDocsRequest$BuilderImpl.overrideConfiguration:(Ljava/util/function/Consumer;)Lsoftware/amazon/awssdk/awscore/AwsRequest$Builder;
       5: pop
       6: aload_0
       7: areturn

  public software.amazon.awssdk.services.workdocs.model.InitiateDocumentVersionUploadRequest build();
    Code:
       0: new           #31                 // class software/amazon/awssdk/services/workdocs/model/InitiateDocumentVersionUploadRequest
       3: dup
       4: aload_0
       5: aconst_null
       6: invokespecial #32                 // Method software/amazon/awssdk/services/workdocs/model/InitiateDocumentVersionUploadRequest."<init>":(Lsoftware/amazon/awssdk/services/workdocs/model/InitiateDocumentVersionUploadRequest$BuilderImpl;Lsoftware/amazon/awssdk/services/workdocs/model/InitiateDocumentVersionUploadRequest$1;)V
       9: areturn

  public java.util.List<software.amazon.awssdk.core.SdkField<?>> sdkFields();
    Code:
       0: invokestatic  #33                 // Method software/amazon/awssdk/services/workdocs/model/InitiateDocumentVersionUploadRequest.access$1900:()Ljava/util/List;
       3: areturn

  public software.amazon.awssdk.services.workdocs.model.WorkDocsRequest build();
    Code:
       0: aload_0
       1: invokevirtual #34                 // Method build:()Lsoftware/amazon/awssdk/services/workdocs/model/InitiateDocumentVersionUploadRequest;
       4: areturn

  public software.amazon.awssdk.awscore.AwsRequest build();
    Code:
       0: aload_0
       1: invokevirtual #34                 // Method build:()Lsoftware/amazon/awssdk/services/workdocs/model/InitiateDocumentVersionUploadRequest;
       4: areturn

  public software.amazon.awssdk.awscore.AwsRequest$Builder overrideConfiguration(java.util.function.Consumer);
    Code:
       0: aload_0
       1: aload_1
       2: invokevirtual #35                 // Method overrideConfiguration:(Ljava/util/function/Consumer;)Lsoftware/amazon/awssdk/services/workdocs/model/InitiateDocumentVersionUploadRequest$Builder;
       5: areturn

  public software.amazon.awssdk.awscore.AwsRequest$Builder overrideConfiguration(software.amazon.awssdk.awscore.AwsRequestOverrideConfiguration);
    Code:
       0: aload_0
       1: aload_1
       2: invokevirtual #36                 // Method overrideConfiguration:(Lsoftware/amazon/awssdk/awscore/AwsRequestOverrideConfiguration;)Lsoftware/amazon/awssdk/services/workdocs/model/InitiateDocumentVersionUploadRequest$Builder;
       5: areturn

  public software.amazon.awssdk.core.SdkRequest build();
    Code:
       0: aload_0
       1: invokevirtual #34                 // Method build:()Lsoftware/amazon/awssdk/services/workdocs/model/InitiateDocumentVersionUploadRequest;
       4: areturn

  public java.lang.Object build();
    Code:
       0: aload_0
       1: invokevirtual #34                 // Method build:()Lsoftware/amazon/awssdk/services/workdocs/model/InitiateDocumentVersionUploadRequest;
       4: areturn

  static java.lang.String access$000(software.amazon.awssdk.services.workdocs.model.InitiateDocumentVersionUploadRequest$BuilderImpl);
    Code:
       0: aload_0
       1: getfield      #10                 // Field authenticationToken:Ljava/lang/String;
       4: areturn

  static java.lang.String access$100(software.amazon.awssdk.services.workdocs.model.InitiateDocumentVersionUploadRequest$BuilderImpl);
    Code:
       0: aload_0
       1: getfield      #9                  // Field id:Ljava/lang/String;
       4: areturn

  static java.lang.String access$200(software.amazon.awssdk.services.workdocs.model.InitiateDocumentVersionUploadRequest$BuilderImpl);
    Code:
       0: aload_0
       1: getfield      #8                  // Field name:Ljava/lang/String;
       4: areturn

  static java.time.Instant access$300(software.amazon.awssdk.services.workdocs.model.InitiateDocumentVersionUploadRequest$BuilderImpl);
    Code:
       0: aload_0
       1: getfield      #7                  // Field contentCreatedTimestamp:Ljava/time/Instant;
       4: areturn

  static java.time.Instant access$400(software.amazon.awssdk.services.workdocs.model.InitiateDocumentVersionUploadRequest$BuilderImpl);
    Code:
       0: aload_0
       1: getfield      #6                  // Field contentModifiedTimestamp:Ljava/time/Instant;
       4: areturn

  static java.lang.String access$500(software.amazon.awssdk.services.workdocs.model.InitiateDocumentVersionUploadRequest$BuilderImpl);
    Code:
       0: aload_0
       1: getfield      #5                  // Field contentType:Ljava/lang/String;
       4: areturn

  static java.lang.Long access$600(software.amazon.awssdk.services.workdocs.model.InitiateDocumentVersionUploadRequest$BuilderImpl);
    Code:
       0: aload_0
       1: getfield      #4                  // Field documentSizeInBytes:Ljava/lang/Long;
       4: areturn

  static java.lang.String access$700(software.amazon.awssdk.services.workdocs.model.InitiateDocumentVersionUploadRequest$BuilderImpl);
    Code:
       0: aload_0
       1: getfield      #3                  // Field parentFolderId:Ljava/lang/String;
       4: areturn

  software.amazon.awssdk.services.workdocs.model.InitiateDocumentVersionUploadRequest$BuilderImpl(software.amazon.awssdk.services.workdocs.model.InitiateDocumentVersionUploadRequest, software.amazon.awssdk.services.workdocs.model.InitiateDocumentVersionUploadRequest$1);
    Code:
       0: aload_0
       1: aload_1
       2: invokespecial #2                  // Method "<init>":(Lsoftware/amazon/awssdk/services/workdocs/model/InitiateDocumentVersionUploadRequest;)V
       5: return

  software.amazon.awssdk.services.workdocs.model.InitiateDocumentVersionUploadRequest$BuilderImpl(software.amazon.awssdk.services.workdocs.model.InitiateDocumentVersionUploadRequest$1);
    Code:
       0: aload_0
       1: invokespecial #1                  // Method "<init>":()V
       4: return
}
