Compiled from "SqlDialectLookup.java"
final class org.springframework.boot.autoconfigure.jooq.SqlDialectLookup {
  private static final org.apache.commons.logging.Log logger;

  private org.springframework.boot.autoconfigure.jooq.SqlDialectLookup();
    Code:
       0: aload_0
       1: invokespecial #1                  // Method java/lang/Object."<init>":()V
       4: return

  static org.jooq.SQLDialect getDialect(javax.sql.DataSource);
    Code:
       0: aload_0
       1: ifnonnull     8
       4: getstatic     #2                  // Field org/jooq/SQLDialect.DEFAULT:Lorg/jooq/SQLDialect;
       7: areturn
       8: aload_0
       9: invokedynamic #3,  0              // InvokeDynamic #0:processMetaData:()Lorg/springframework/jdbc/support/DatabaseMetaDataCallback;
      14: invokestatic  #4                  // Method org/springframework/jdbc/support/JdbcUtils.extractDatabaseMetaData:(Ljavax/sql/DataSource;Lorg/springframework/jdbc/support/DatabaseMetaDataCallback;)Ljava/lang/Object;
      17: checkcast     #5                  // class java/lang/String
      20: astore_1
      21: aload_1
      22: invokestatic  #6                  // Method org/jooq/tools/jdbc/JDBCUtils.dialect:(Ljava/lang/String;)Lorg/jooq/SQLDialect;
      25: astore_2
      26: aload_2
      27: ifnull        32
      30: aload_2
      31: areturn
      32: goto          47
      35: astore_1
      36: getstatic     #8                  // Field logger:Lorg/apache/commons/logging/Log;
      39: ldc           #9                  // String Unable to determine jdbc url from datasource
      41: aload_1
      42: invokeinterface #10,  3           // InterfaceMethod org/apache/commons/logging/Log.warn:(Ljava/lang/Object;Ljava/lang/Throwable;)V
      47: getstatic     #2                  // Field org/jooq/SQLDialect.DEFAULT:Lorg/jooq/SQLDialect;
      50: areturn
    Exception table:
       from    to  target type
           8    31    35   Class org/springframework/jdbc/support/MetaDataAccessException

  static {};
    Code:
       0: ldc           #11                 // class org/springframework/boot/autoconfigure/jooq/SqlDialectLookup
       2: invokestatic  #12                 // Method org/apache/commons/logging/LogFactory.getLog:(Ljava/lang/Class;)Lorg/apache/commons/logging/Log;
       5: putstatic     #8                  // Field logger:Lorg/apache/commons/logging/Log;
       8: return
}
