Compiled from "SystemApi.java"
public class org.sonarsource.sonarlint.core.serverapi.system.SystemApi {
  private static final org.sonarsource.sonarlint.core.commons.log.SonarLintLogger LOG;

  private final org.sonarsource.sonarlint.core.serverapi.ServerApiHelper helper;

  public org.sonarsource.sonarlint.core.serverapi.system.SystemApi(org.sonarsource.sonarlint.core.serverapi.ServerApiHelper);
    Code:
       0: aload_0
       1: invokespecial #32                 // Method java/lang/Object."<init>":()V
       4: aload_0
       5: aload_1
       6: putfield      #34                 // Field helper:Lorg/sonarsource/sonarlint/core/serverapi/ServerApiHelper;
       9: return

  public java.util.concurrent.CompletableFuture<org.sonarsource.sonarlint.core.serverapi.system.ServerInfo> getStatus();
    Code:
       0: aload_0
       1: getfield      #34                 // Field helper:Lorg/sonarsource/sonarlint/core/serverapi/ServerApiHelper;
       4: ldc           #41                 // String api/system/status
       6: invokevirtual #45                 // Method org/sonarsource/sonarlint/core/serverapi/ServerApiHelper.getAsync:(Ljava/lang/String;)Ljava/util/concurrent/CompletableFuture;
       9: invokedynamic #64,  0             // InvokeDynamic #0:apply:()Lorg/sonarsource/sonarlint/core/serverapi/ServerApiHelper$IOFunction;
      14: invokedynamic #74,  0             // InvokeDynamic #1:accept:()Ljava/util/function/LongConsumer;
      19: invokestatic  #78                 // Method org/sonarsource/sonarlint/core/serverapi/ServerApiHelper.processTimed:(Ljava/util/concurrent/CompletableFuture;Lorg/sonarsource/sonarlint/core/serverapi/ServerApiHelper$IOFunction;Ljava/util/function/LongConsumer;)Ljava/util/concurrent/CompletableFuture;
      22: areturn

  public org.sonarsource.sonarlint.core.serverapi.system.ServerInfo getStatusSync();
    Code:
       0: aload_0
       1: invokevirtual #84                 // Method getStatus:()Ljava/util/concurrent/CompletableFuture;
       4: invokevirtual #90                 // Method java/util/concurrent/CompletableFuture.get:()Ljava/lang/Object;
       7: checkcast     #92                 // class org/sonarsource/sonarlint/core/serverapi/system/ServerInfo
      10: areturn
      11: astore_1
      12: new           #94                 // class java/lang/IllegalStateException
      15: dup
      16: ldc           #96                 // String Unable to get server status
      18: aload_1
      19: invokespecial #99                 // Method java/lang/IllegalStateException."<init>":(Ljava/lang/String;Ljava/lang/Throwable;)V
      22: athrow
    Exception table:
       from    to  target type
           0    10    11   Class java/lang/Exception

  private static void lambda$getStatus$1(long);
    Code:
       0: getstatic     #103                // Field LOG:Lorg/sonarsource/sonarlint/core/commons/log/SonarLintLogger;
       3: ldc           #105                // String Downloaded server infos in {}ms
       5: lload_0
       6: invokestatic  #111                // Method java/lang/Long.valueOf:(J)Ljava/lang/Long;
       9: invokevirtual #117                // Method org/sonarsource/sonarlint/core/commons/log/SonarLintLogger.debug:(Ljava/lang/String;Ljava/lang/Object;)V
      12: return

  private static org.sonarsource.sonarlint.core.serverapi.system.ServerInfo lambda$getStatus$0(org.sonarsource.sonarlint.core.commons.http.HttpClient$Response) throws java.io.IOException;
    Code:
       0: aload_0
       1: invokeinterface #125,  1          // InterfaceMethod org/sonarsource/sonarlint/core/commons/http/HttpClient$Response.bodyAsString:()Ljava/lang/String;
       6: astore_1
       7: new           #127                // class org/sonarsource/sonarlint/shaded/com/google/gson/Gson
      10: dup
      11: invokespecial #128                // Method org/sonarsource/sonarlint/shaded/com/google/gson/Gson."<init>":()V
      14: aload_1
      15: ldc           #7                  // class org/sonarsource/sonarlint/core/serverapi/system/SystemApi$SystemStatus
      17: invokevirtual #132                // Method org/sonarsource/sonarlint/shaded/com/google/gson/Gson.fromJson:(Ljava/lang/String;Ljava/lang/Class;)Ljava/lang/Object;
      20: checkcast     #7                  // class org/sonarsource/sonarlint/core/serverapi/system/SystemApi$SystemStatus
      23: astore_2
      24: new           #92                 // class org/sonarsource/sonarlint/core/serverapi/system/ServerInfo
      27: dup
      28: aload_2
      29: getfield      #136                // Field org/sonarsource/sonarlint/core/serverapi/system/SystemApi$SystemStatus.id:Ljava/lang/String;
      32: aload_2
      33: getfield      #139                // Field org/sonarsource/sonarlint/core/serverapi/system/SystemApi$SystemStatus.status:Ljava/lang/String;
      36: aload_2
      37: getfield      #142                // Field org/sonarsource/sonarlint/core/serverapi/system/SystemApi$SystemStatus.version:Ljava/lang/String;
      40: invokespecial #145                // Method org/sonarsource/sonarlint/core/serverapi/system/ServerInfo."<init>":(Ljava/lang/String;Ljava/lang/String;Ljava/lang/String;)V
      43: areturn
      44: astore_2
      45: new           #94                 // class java/lang/IllegalStateException
      48: dup
      49: aload_1
      50: invokedynamic #159,  0            // InvokeDynamic #2:makeConcatWithConstants:(Ljava/lang/String;)Ljava/lang/String;
      55: aload_2
      56: invokespecial #99                 // Method java/lang/IllegalStateException."<init>":(Ljava/lang/String;Ljava/lang/Throwable;)V
      59: athrow
    Exception table:
       from    to  target type
           7    43    44   Class java/lang/Exception

  static {};
    Code:
       0: invokestatic  #167                // Method org/sonarsource/sonarlint/core/commons/log/SonarLintLogger.get:()Lorg/sonarsource/sonarlint/core/commons/log/SonarLintLogger;
       3: putstatic     #103                // Field LOG:Lorg/sonarsource/sonarlint/core/commons/log/SonarLintLogger;
       6: return
}
