Compiled from "WebExpressionVoter.java"
public class org.springframework.security.web.access.expression.WebExpressionVoter implements org.springframework.security.access.AccessDecisionVoter<org.springframework.security.web.FilterInvocation> {
  private org.springframework.security.access.expression.SecurityExpressionHandler<org.springframework.security.web.FilterInvocation> expressionHandler;

  static final boolean $assertionsDisabled;

  public org.springframework.security.web.access.expression.WebExpressionVoter();
    Code:
       0: aload_0
       1: invokespecial #1                  // Method java/lang/Object."<init>":()V
       4: aload_0
       5: new           #2                  // class org/springframework/security/web/access/expression/DefaultWebSecurityExpressionHandler
       8: dup
       9: invokespecial #3                  // Method org/springframework/security/web/access/expression/DefaultWebSecurityExpressionHandler."<init>":()V
      12: putfield      #4                  // Field expressionHandler:Lorg/springframework/security/access/expression/SecurityExpressionHandler;
      15: return

  public int vote(org.springframework.security.core.Authentication, org.springframework.security.web.FilterInvocation, java.util.Collection<org.springframework.security.access.ConfigAttribute>);
    Code:
       0: getstatic     #5                  // Field $assertionsDisabled:Z
       3: ifne          18
       6: aload_1
       7: ifnonnull     18
      10: new           #6                  // class java/lang/AssertionError
      13: dup
      14: invokespecial #7                  // Method java/lang/AssertionError."<init>":()V
      17: athrow
      18: getstatic     #5                  // Field $assertionsDisabled:Z
      21: ifne          36
      24: aload_2
      25: ifnonnull     36
      28: new           #6                  // class java/lang/AssertionError
      31: dup
      32: invokespecial #7                  // Method java/lang/AssertionError."<init>":()V
      35: athrow
      36: getstatic     #5                  // Field $assertionsDisabled:Z
      39: ifne          54
      42: aload_3
      43: ifnonnull     54
      46: new           #6                  // class java/lang/AssertionError
      49: dup
      50: invokespecial #7                  // Method java/lang/AssertionError."<init>":()V
      53: athrow
      54: aload_0
      55: aload_3
      56: invokespecial #8                  // Method findConfigAttribute:(Ljava/util/Collection;)Lorg/springframework/security/web/access/expression/WebExpressionConfigAttribute;
      59: astore        4
      61: aload         4
      63: ifnonnull     68
      66: iconst_0
      67: ireturn
      68: aload_0
      69: getfield      #4                  // Field expressionHandler:Lorg/springframework/security/access/expression/SecurityExpressionHandler;
      72: aload_1
      73: aload_2
      74: invokeinterface #10,  3           // InterfaceMethod org/springframework/security/access/expression/SecurityExpressionHandler.createEvaluationContext:(Lorg/springframework/security/core/Authentication;Ljava/lang/Object;)Lorg/springframework/expression/EvaluationContext;
      79: astore        5
      81: aload         4
      83: aload         5
      85: aload_2
      86: invokevirtual #11                 // Method org/springframework/security/web/access/expression/WebExpressionConfigAttribute.postProcess:(Lorg/springframework/expression/EvaluationContext;Lorg/springframework/security/web/FilterInvocation;)Lorg/springframework/expression/EvaluationContext;
      89: astore        5
      91: aload         4
      93: invokevirtual #12                 // Method org/springframework/security/web/access/expression/WebExpressionConfigAttribute.getAuthorizeExpression:()Lorg/springframework/expression/Expression;
      96: aload         5
      98: invokestatic  #13                 // Method org/springframework/security/access/expression/ExpressionUtils.evaluateAsBoolean:(Lorg/springframework/expression/Expression;Lorg/springframework/expression/EvaluationContext;)Z
     101: ifeq          108
     104: iconst_1
     105: goto          109
     108: iconst_m1
     109: ireturn

  private org.springframework.security.web.access.expression.WebExpressionConfigAttribute findConfigAttribute(java.util.Collection<org.springframework.security.access.ConfigAttribute>);
    Code:
       0: aload_1
       1: invokeinterface #14,  1           // InterfaceMethod java/util/Collection.iterator:()Ljava/util/Iterator;
       6: astore_2
       7: aload_2
       8: invokeinterface #15,  1           // InterfaceMethod java/util/Iterator.hasNext:()Z
      13: ifeq          41
      16: aload_2
      17: invokeinterface #16,  1           // InterfaceMethod java/util/Iterator.next:()Ljava/lang/Object;
      22: checkcast     #17                 // class org/springframework/security/access/ConfigAttribute
      25: astore_3
      26: aload_3
      27: instanceof    #18                 // class org/springframework/security/web/access/expression/WebExpressionConfigAttribute
      30: ifeq          38
      33: aload_3
      34: checkcast     #18                 // class org/springframework/security/web/access/expression/WebExpressionConfigAttribute
      37: areturn
      38: goto          7
      41: aconst_null
      42: areturn

  public boolean supports(org.springframework.security.access.ConfigAttribute);
    Code:
       0: aload_1
       1: instanceof    #18                 // class org/springframework/security/web/access/expression/WebExpressionConfigAttribute
       4: ireturn

  public boolean supports(java.lang.Class<?>);
    Code:
       0: ldc           #19                 // class org/springframework/security/web/FilterInvocation
       2: aload_1
       3: invokevirtual #20                 // Method java/lang/Class.isAssignableFrom:(Ljava/lang/Class;)Z
       6: ireturn

  public void setExpressionHandler(org.springframework.security.access.expression.SecurityExpressionHandler<org.springframework.security.web.FilterInvocation>);
    Code:
       0: aload_0
       1: aload_1
       2: putfield      #4                  // Field expressionHandler:Lorg/springframework/security/access/expression/SecurityExpressionHandler;
       5: return

  public int vote(org.springframework.security.core.Authentication, java.lang.Object, java.util.Collection);
    Code:
       0: aload_0
       1: aload_1
       2: aload_2
       3: checkcast     #19                 // class org/springframework/security/web/FilterInvocation
       6: aload_3
       7: invokevirtual #21                 // Method vote:(Lorg/springframework/security/core/Authentication;Lorg/springframework/security/web/FilterInvocation;Ljava/util/Collection;)I
      10: ireturn

  static {};
    Code:
       0: ldc           #22                 // class org/springframework/security/web/access/expression/WebExpressionVoter
       2: invokevirtual #23                 // Method java/lang/Class.desiredAssertionStatus:()Z
       5: ifne          12
       8: iconst_1
       9: goto          13
      12: iconst_0
      13: putstatic     #5                  // Field $assertionsDisabled:Z
      16: return
}
