Compiled from "AbstractHeaderElementIterator.java"
abstract class org.apache.hc.core5.http.message.AbstractHeaderElementIterator<T> implements java.util.Iterator<T> {
  private final java.util.Iterator<org.apache.hc.core5.http.Header> headerIt;

  private T currentElement;

  private java.lang.CharSequence buffer;

  private org.apache.hc.core5.http.message.ParserCursor cursor;

  org.apache.hc.core5.http.message.AbstractHeaderElementIterator(java.util.Iterator<org.apache.hc.core5.http.Header>);
    Code:
       0: aload_0
       1: invokespecial #1                  // Method java/lang/Object."<init>":()V
       4: aload_0
       5: aload_1
       6: ldc           #2                  // String Header iterator
       8: invokestatic  #3                  // Method org/apache/hc/core5/util/Args.notNull:(Ljava/lang/Object;Ljava/lang/String;)Ljava/lang/Object;
      11: checkcast     #4                  // class java/util/Iterator
      14: putfield      #5                  // Field headerIt:Ljava/util/Iterator;
      17: return

  private void bufferHeaderValue();
    Code:
       0: aload_0
       1: aconst_null
       2: putfield      #6                  // Field cursor:Lorg/apache/hc/core5/http/message/ParserCursor;
       5: aload_0
       6: aconst_null
       7: putfield      #7                  // Field buffer:Ljava/lang/CharSequence;
      10: aload_0
      11: getfield      #5                  // Field headerIt:Ljava/util/Iterator;
      14: invokeinterface #8,  1            // InterfaceMethod java/util/Iterator.hasNext:()Z
      19: ifeq          133
      22: aload_0
      23: getfield      #5                  // Field headerIt:Ljava/util/Iterator;
      26: invokeinterface #9,  1            // InterfaceMethod java/util/Iterator.next:()Ljava/lang/Object;
      31: checkcast     #10                 // class org/apache/hc/core5/http/Header
      34: astore_1
      35: aload_1
      36: instanceof    #11                 // class org/apache/hc/core5/http/FormattedHeader
      39: ifeq          95
      42: aload_0
      43: aload_1
      44: checkcast     #11                 // class org/apache/hc/core5/http/FormattedHeader
      47: invokeinterface #12,  1           // InterfaceMethod org/apache/hc/core5/http/FormattedHeader.getBuffer:()Lorg/apache/hc/core5/util/CharArrayBuffer;
      52: putfield      #7                  // Field buffer:Ljava/lang/CharSequence;
      55: aload_0
      56: new           #13                 // class org/apache/hc/core5/http/message/ParserCursor
      59: dup
      60: iconst_0
      61: aload_0
      62: getfield      #7                  // Field buffer:Ljava/lang/CharSequence;
      65: invokeinterface #14,  1           // InterfaceMethod java/lang/CharSequence.length:()I
      70: invokespecial #15                 // Method org/apache/hc/core5/http/message/ParserCursor."<init>":(II)V
      73: putfield      #6                  // Field cursor:Lorg/apache/hc/core5/http/message/ParserCursor;
      76: aload_0
      77: getfield      #6                  // Field cursor:Lorg/apache/hc/core5/http/message/ParserCursor;
      80: aload_1
      81: checkcast     #11                 // class org/apache/hc/core5/http/FormattedHeader
      84: invokeinterface #16,  1           // InterfaceMethod org/apache/hc/core5/http/FormattedHeader.getValuePos:()I
      89: invokevirtual #17                 // Method org/apache/hc/core5/http/message/ParserCursor.updatePos:(I)V
      92: goto          133
      95: aload_1
      96: invokeinterface #18,  1           // InterfaceMethod org/apache/hc/core5/http/Header.getValue:()Ljava/lang/String;
     101: astore_2
     102: aload_2
     103: ifnull        130
     106: aload_0
     107: aload_2
     108: putfield      #7                  // Field buffer:Ljava/lang/CharSequence;
     111: aload_0
     112: new           #13                 // class org/apache/hc/core5/http/message/ParserCursor
     115: dup
     116: iconst_0
     117: aload_2
     118: invokevirtual #19                 // Method java/lang/String.length:()I
     121: invokespecial #15                 // Method org/apache/hc/core5/http/message/ParserCursor."<init>":(II)V
     124: putfield      #6                  // Field cursor:Lorg/apache/hc/core5/http/message/ParserCursor;
     127: goto          133
     130: goto          10
     133: return

  abstract T parseHeaderElement(java.lang.CharSequence, org.apache.hc.core5.http.message.ParserCursor);

  private void parseNextElement();
    Code:
       0: aload_0
       1: getfield      #5                  // Field headerIt:Ljava/util/Iterator;
       4: invokeinterface #8,  1            // InterfaceMethod java/util/Iterator.hasNext:()Z
       9: ifne          19
      12: aload_0
      13: getfield      #6                  // Field cursor:Lorg/apache/hc/core5/http/message/ParserCursor;
      16: ifnull        106
      19: aload_0
      20: getfield      #6                  // Field cursor:Lorg/apache/hc/core5/http/message/ParserCursor;
      23: ifnull        36
      26: aload_0
      27: getfield      #6                  // Field cursor:Lorg/apache/hc/core5/http/message/ParserCursor;
      30: invokevirtual #20                 // Method org/apache/hc/core5/http/message/ParserCursor.atEnd:()Z
      33: ifeq          40
      36: aload_0
      37: invokespecial #21                 // Method bufferHeaderValue:()V
      40: aload_0
      41: getfield      #6                  // Field cursor:Lorg/apache/hc/core5/http/message/ParserCursor;
      44: ifnull        0
      47: aload_0
      48: getfield      #6                  // Field cursor:Lorg/apache/hc/core5/http/message/ParserCursor;
      51: invokevirtual #20                 // Method org/apache/hc/core5/http/message/ParserCursor.atEnd:()Z
      54: ifne          83
      57: aload_0
      58: aload_0
      59: getfield      #7                  // Field buffer:Ljava/lang/CharSequence;
      62: aload_0
      63: getfield      #6                  // Field cursor:Lorg/apache/hc/core5/http/message/ParserCursor;
      66: invokevirtual #22                 // Method parseHeaderElement:(Ljava/lang/CharSequence;Lorg/apache/hc/core5/http/message/ParserCursor;)Ljava/lang/Object;
      69: astore_1
      70: aload_1
      71: ifnull        80
      74: aload_0
      75: aload_1
      76: putfield      #23                 // Field currentElement:Ljava/lang/Object;
      79: return
      80: goto          47
      83: aload_0
      84: getfield      #6                  // Field cursor:Lorg/apache/hc/core5/http/message/ParserCursor;
      87: invokevirtual #20                 // Method org/apache/hc/core5/http/message/ParserCursor.atEnd:()Z
      90: ifeq          0
      93: aload_0
      94: aconst_null
      95: putfield      #6                  // Field cursor:Lorg/apache/hc/core5/http/message/ParserCursor;
      98: aload_0
      99: aconst_null
     100: putfield      #7                  // Field buffer:Ljava/lang/CharSequence;
     103: goto          0
     106: return

  public boolean hasNext();
    Code:
       0: aload_0
       1: getfield      #23                 // Field currentElement:Ljava/lang/Object;
       4: ifnonnull     11
       7: aload_0
       8: invokespecial #24                 // Method parseNextElement:()V
      11: aload_0
      12: getfield      #23                 // Field currentElement:Ljava/lang/Object;
      15: ifnull        22
      18: iconst_1
      19: goto          23
      22: iconst_0
      23: ireturn

  public T next() throws java.util.NoSuchElementException;
    Code:
       0: aload_0
       1: getfield      #23                 // Field currentElement:Ljava/lang/Object;
       4: ifnonnull     11
       7: aload_0
       8: invokespecial #24                 // Method parseNextElement:()V
      11: aload_0
      12: getfield      #23                 // Field currentElement:Ljava/lang/Object;
      15: ifnonnull     28
      18: new           #25                 // class java/util/NoSuchElementException
      21: dup
      22: ldc           #26                 // String No more header elements available
      24: invokespecial #27                 // Method java/util/NoSuchElementException."<init>":(Ljava/lang/String;)V
      27: athrow
      28: aload_0
      29: getfield      #23                 // Field currentElement:Ljava/lang/Object;
      32: astore_1
      33: aload_0
      34: aconst_null
      35: putfield      #23                 // Field currentElement:Ljava/lang/Object;
      38: aload_1
      39: areturn

  public void remove() throws java.lang.UnsupportedOperationException;
    Code:
       0: new           #28                 // class java/lang/UnsupportedOperationException
       3: dup
       4: ldc           #29                 // String Remove not supported
       6: invokespecial #30                 // Method java/lang/UnsupportedOperationException."<init>":(Ljava/lang/String;)V
       9: athrow
}
