Compiled from "HorizontalPodAutoscalerSpecFluentImpl.java"
public class io.fabric8.kubernetes.api.model.autoscaling.v2beta1.HorizontalPodAutoscalerSpecFluentImpl<A extends io.fabric8.kubernetes.api.model.autoscaling.v2beta1.HorizontalPodAutoscalerSpecFluent<A>> extends io.fabric8.kubernetes.api.builder.BaseFluent<A> implements io.fabric8.kubernetes.api.model.autoscaling.v2beta1.HorizontalPodAutoscalerSpecFluent<A> {
  private java.lang.Integer maxReplicas;

  private java.util.List<io.fabric8.kubernetes.api.model.autoscaling.v2beta1.MetricSpecBuilder> metrics;

  private java.lang.Integer minReplicas;

  private io.fabric8.kubernetes.api.model.autoscaling.v2beta1.CrossVersionObjectReferenceBuilder scaleTargetRef;

  public io.fabric8.kubernetes.api.model.autoscaling.v2beta1.HorizontalPodAutoscalerSpecFluentImpl();
    Code:
       0: aload_0
       1: invokespecial #1                  // Method io/fabric8/kubernetes/api/builder/BaseFluent."<init>":()V
       4: aload_0
       5: new           #2                  // class java/util/ArrayList
       8: dup
       9: invokespecial #3                  // Method java/util/ArrayList."<init>":()V
      12: putfield      #4                  // Field metrics:Ljava/util/List;
      15: return

  public io.fabric8.kubernetes.api.model.autoscaling.v2beta1.HorizontalPodAutoscalerSpecFluentImpl(io.fabric8.kubernetes.api.model.autoscaling.v2beta1.HorizontalPodAutoscalerSpec);
    Code:
       0: aload_0
       1: invokespecial #1                  // Method io/fabric8/kubernetes/api/builder/BaseFluent."<init>":()V
       4: aload_0
       5: new           #2                  // class java/util/ArrayList
       8: dup
       9: invokespecial #3                  // Method java/util/ArrayList."<init>":()V
      12: putfield      #4                  // Field metrics:Ljava/util/List;
      15: aload_0
      16: aload_1
      17: invokevirtual #5                  // Method io/fabric8/kubernetes/api/model/autoscaling/v2beta1/HorizontalPodAutoscalerSpec.getMaxReplicas:()Ljava/lang/Integer;
      20: invokevirtual #6                  // Method withMaxReplicas:(Ljava/lang/Integer;)Lio/fabric8/kubernetes/api/model/autoscaling/v2beta1/HorizontalPodAutoscalerSpecFluent;
      23: pop
      24: aload_0
      25: aload_1
      26: invokevirtual #7                  // Method io/fabric8/kubernetes/api/model/autoscaling/v2beta1/HorizontalPodAutoscalerSpec.getMetrics:()Ljava/util/List;
      29: invokevirtual #8                  // Method withMetrics:(Ljava/util/List;)Lio/fabric8/kubernetes/api/model/autoscaling/v2beta1/HorizontalPodAutoscalerSpecFluent;
      32: pop
      33: aload_0
      34: aload_1
      35: invokevirtual #9                  // Method io/fabric8/kubernetes/api/model/autoscaling/v2beta1/HorizontalPodAutoscalerSpec.getMinReplicas:()Ljava/lang/Integer;
      38: invokevirtual #10                 // Method withMinReplicas:(Ljava/lang/Integer;)Lio/fabric8/kubernetes/api/model/autoscaling/v2beta1/HorizontalPodAutoscalerSpecFluent;
      41: pop
      42: aload_0
      43: aload_1
      44: invokevirtual #11                 // Method io/fabric8/kubernetes/api/model/autoscaling/v2beta1/HorizontalPodAutoscalerSpec.getScaleTargetRef:()Lio/fabric8/kubernetes/api/model/autoscaling/v2beta1/CrossVersionObjectReference;
      47: invokevirtual #12                 // Method withScaleTargetRef:(Lio/fabric8/kubernetes/api/model/autoscaling/v2beta1/CrossVersionObjectReference;)Lio/fabric8/kubernetes/api/model/autoscaling/v2beta1/HorizontalPodAutoscalerSpecFluent;
      50: pop
      51: return

  public java.lang.Integer getMaxReplicas();
    Code:
       0: aload_0
       1: getfield      #13                 // Field maxReplicas:Ljava/lang/Integer;
       4: areturn

  public A withMaxReplicas(java.lang.Integer);
    Code:
       0: aload_0
       1: aload_1
       2: putfield      #13                 // Field maxReplicas:Ljava/lang/Integer;
       5: aload_0
       6: areturn

  public java.lang.Boolean hasMaxReplicas();
    Code:
       0: aload_0
       1: getfield      #13                 // Field maxReplicas:Ljava/lang/Integer;
       4: ifnull        11
       7: iconst_1
       8: goto          12
      11: iconst_0
      12: invokestatic  #14                 // Method java/lang/Boolean.valueOf:(Z)Ljava/lang/Boolean;
      15: areturn

  public A addToMetrics(int, io.fabric8.kubernetes.api.model.autoscaling.v2beta1.MetricSpec);
    Code:
       0: aload_0
       1: getfield      #4                  // Field metrics:Ljava/util/List;
       4: ifnonnull     18
       7: aload_0
       8: new           #2                  // class java/util/ArrayList
      11: dup
      12: invokespecial #3                  // Method java/util/ArrayList."<init>":()V
      15: putfield      #4                  // Field metrics:Ljava/util/List;
      18: new           #15                 // class io/fabric8/kubernetes/api/model/autoscaling/v2beta1/MetricSpecBuilder
      21: dup
      22: aload_2
      23: invokespecial #16                 // Method io/fabric8/kubernetes/api/model/autoscaling/v2beta1/MetricSpecBuilder."<init>":(Lio/fabric8/kubernetes/api/model/autoscaling/v2beta1/MetricSpec;)V
      26: astore_3
      27: aload_0
      28: getfield      #17                 // Field _visitables:Lio/fabric8/kubernetes/api/builder/VisitableMap;
      31: ldc           #18                 // String metrics
      33: invokevirtual #19                 // Method io/fabric8/kubernetes/api/builder/VisitableMap.get:(Ljava/lang/Object;)Ljava/util/List;
      36: iload_1
      37: iflt          44
      40: iload_1
      41: goto          58
      44: aload_0
      45: getfield      #17                 // Field _visitables:Lio/fabric8/kubernetes/api/builder/VisitableMap;
      48: ldc           #18                 // String metrics
      50: invokevirtual #19                 // Method io/fabric8/kubernetes/api/builder/VisitableMap.get:(Ljava/lang/Object;)Ljava/util/List;
      53: invokeinterface #20,  1           // InterfaceMethod java/util/List.size:()I
      58: aload_3
      59: invokeinterface #21,  3           // InterfaceMethod java/util/List.add:(ILjava/lang/Object;)V
      64: aload_0
      65: getfield      #4                  // Field metrics:Ljava/util/List;
      68: iload_1
      69: iflt          76
      72: iload_1
      73: goto          85
      76: aload_0
      77: getfield      #4                  // Field metrics:Ljava/util/List;
      80: invokeinterface #20,  1           // InterfaceMethod java/util/List.size:()I
      85: aload_3
      86: invokeinterface #21,  3           // InterfaceMethod java/util/List.add:(ILjava/lang/Object;)V
      91: aload_0
      92: areturn

  public A setToMetrics(int, io.fabric8.kubernetes.api.model.autoscaling.v2beta1.MetricSpec);
    Code:
       0: aload_0
       1: getfield      #4                  // Field metrics:Ljava/util/List;
       4: ifnonnull     18
       7: aload_0
       8: new           #2                  // class java/util/ArrayList
      11: dup
      12: invokespecial #3                  // Method java/util/ArrayList."<init>":()V
      15: putfield      #4                  // Field metrics:Ljava/util/List;
      18: new           #15                 // class io/fabric8/kubernetes/api/model/autoscaling/v2beta1/MetricSpecBuilder
      21: dup
      22: aload_2
      23: invokespecial #16                 // Method io/fabric8/kubernetes/api/model/autoscaling/v2beta1/MetricSpecBuilder."<init>":(Lio/fabric8/kubernetes/api/model/autoscaling/v2beta1/MetricSpec;)V
      26: astore_3
      27: iload_1
      28: iflt          49
      31: iload_1
      32: aload_0
      33: getfield      #17                 // Field _visitables:Lio/fabric8/kubernetes/api/builder/VisitableMap;
      36: ldc           #18                 // String metrics
      38: invokevirtual #19                 // Method io/fabric8/kubernetes/api/builder/VisitableMap.get:(Ljava/lang/Object;)Ljava/util/List;
      41: invokeinterface #20,  1           // InterfaceMethod java/util/List.size:()I
      46: if_icmplt     68
      49: aload_0
      50: getfield      #17                 // Field _visitables:Lio/fabric8/kubernetes/api/builder/VisitableMap;
      53: ldc           #18                 // String metrics
      55: invokevirtual #19                 // Method io/fabric8/kubernetes/api/builder/VisitableMap.get:(Ljava/lang/Object;)Ljava/util/List;
      58: aload_3
      59: invokeinterface #22,  2           // InterfaceMethod java/util/List.add:(Ljava/lang/Object;)Z
      64: pop
      65: goto          85
      68: aload_0
      69: getfield      #17                 // Field _visitables:Lio/fabric8/kubernetes/api/builder/VisitableMap;
      72: ldc           #18                 // String metrics
      74: invokevirtual #19                 // Method io/fabric8/kubernetes/api/builder/VisitableMap.get:(Ljava/lang/Object;)Ljava/util/List;
      77: iload_1
      78: aload_3
      79: invokeinterface #23,  3           // InterfaceMethod java/util/List.set:(ILjava/lang/Object;)Ljava/lang/Object;
      84: pop
      85: iload_1
      86: iflt          102
      89: iload_1
      90: aload_0
      91: getfield      #4                  // Field metrics:Ljava/util/List;
      94: invokeinterface #20,  1           // InterfaceMethod java/util/List.size:()I
      99: if_icmplt     116
     102: aload_0
     103: getfield      #4                  // Field metrics:Ljava/util/List;
     106: aload_3
     107: invokeinterface #22,  2           // InterfaceMethod java/util/List.add:(Ljava/lang/Object;)Z
     112: pop
     113: goto          128
     116: aload_0
     117: getfield      #4                  // Field metrics:Ljava/util/List;
     120: iload_1
     121: aload_3
     122: invokeinterface #23,  3           // InterfaceMethod java/util/List.set:(ILjava/lang/Object;)Ljava/lang/Object;
     127: pop
     128: aload_0
     129: areturn

  public A addToMetrics(io.fabric8.kubernetes.api.model.autoscaling.v2beta1.MetricSpec...);
    Code:
       0: aload_0
       1: getfield      #4                  // Field metrics:Ljava/util/List;
       4: ifnonnull     18
       7: aload_0
       8: new           #2                  // class java/util/ArrayList
      11: dup
      12: invokespecial #3                  // Method java/util/ArrayList."<init>":()V
      15: putfield      #4                  // Field metrics:Ljava/util/List;
      18: aload_1
      19: astore_2
      20: aload_2
      21: arraylength
      22: istore_3
      23: iconst_0
      24: istore        4
      26: iload         4
      28: iload_3
      29: if_icmpge     84
      32: aload_2
      33: iload         4
      35: aaload
      36: astore        5
      38: new           #15                 // class io/fabric8/kubernetes/api/model/autoscaling/v2beta1/MetricSpecBuilder
      41: dup
      42: aload         5
      44: invokespecial #16                 // Method io/fabric8/kubernetes/api/model/autoscaling/v2beta1/MetricSpecBuilder."<init>":(Lio/fabric8/kubernetes/api/model/autoscaling/v2beta1/MetricSpec;)V
      47: astore        6
      49: aload_0
      50: getfield      #17                 // Field _visitables:Lio/fabric8/kubernetes/api/builder/VisitableMap;
      53: ldc           #18                 // String metrics
      55: invokevirtual #19                 // Method io/fabric8/kubernetes/api/builder/VisitableMap.get:(Ljava/lang/Object;)Ljava/util/List;
      58: aload         6
      60: invokeinterface #22,  2           // InterfaceMethod java/util/List.add:(Ljava/lang/Object;)Z
      65: pop
      66: aload_0
      67: getfield      #4                  // Field metrics:Ljava/util/List;
      70: aload         6
      72: invokeinterface #22,  2           // InterfaceMethod java/util/List.add:(Ljava/lang/Object;)Z
      77: pop
      78: iinc          4, 1
      81: goto          26
      84: aload_0
      85: areturn

  public A addAllToMetrics(java.util.Collection<io.fabric8.kubernetes.api.model.autoscaling.v2beta1.MetricSpec>);
    Code:
       0: aload_0
       1: getfield      #4                  // Field metrics:Ljava/util/List;
       4: ifnonnull     18
       7: aload_0
       8: new           #2                  // class java/util/ArrayList
      11: dup
      12: invokespecial #3                  // Method java/util/ArrayList."<init>":()V
      15: putfield      #4                  // Field metrics:Ljava/util/List;
      18: aload_1
      19: invokeinterface #24,  1           // InterfaceMethod java/util/Collection.iterator:()Ljava/util/Iterator;
      24: astore_2
      25: aload_2
      26: invokeinterface #25,  1           // InterfaceMethod java/util/Iterator.hasNext:()Z
      31: ifeq          86
      34: aload_2
      35: invokeinterface #26,  1           // InterfaceMethod java/util/Iterator.next:()Ljava/lang/Object;
      40: checkcast     #27                 // class io/fabric8/kubernetes/api/model/autoscaling/v2beta1/MetricSpec
      43: astore_3
      44: new           #15                 // class io/fabric8/kubernetes/api/model/autoscaling/v2beta1/MetricSpecBuilder
      47: dup
      48: aload_3
      49: invokespecial #16                 // Method io/fabric8/kubernetes/api/model/autoscaling/v2beta1/MetricSpecBuilder."<init>":(Lio/fabric8/kubernetes/api/model/autoscaling/v2beta1/MetricSpec;)V
      52: astore        4
      54: aload_0
      55: getfield      #17                 // Field _visitables:Lio/fabric8/kubernetes/api/builder/VisitableMap;
      58: ldc           #18                 // String metrics
      60: invokevirtual #19                 // Method io/fabric8/kubernetes/api/builder/VisitableMap.get:(Ljava/lang/Object;)Ljava/util/List;
      63: aload         4
      65: invokeinterface #22,  2           // InterfaceMethod java/util/List.add:(Ljava/lang/Object;)Z
      70: pop
      71: aload_0
      72: getfield      #4                  // Field metrics:Ljava/util/List;
      75: aload         4
      77: invokeinterface #22,  2           // InterfaceMethod java/util/List.add:(Ljava/lang/Object;)Z
      82: pop
      83: goto          25
      86: aload_0
      87: areturn

  public A removeFromMetrics(io.fabric8.kubernetes.api.model.autoscaling.v2beta1.MetricSpec...);
    Code:
       0: aload_1
       1: astore_2
       2: aload_2
       3: arraylength
       4: istore_3
       5: iconst_0
       6: istore        4
       8: iload         4
      10: iload_3
      11: if_icmpge     73
      14: aload_2
      15: iload         4
      17: aaload
      18: astore        5
      20: new           #15                 // class io/fabric8/kubernetes/api/model/autoscaling/v2beta1/MetricSpecBuilder
      23: dup
      24: aload         5
      26: invokespecial #16                 // Method io/fabric8/kubernetes/api/model/autoscaling/v2beta1/MetricSpecBuilder."<init>":(Lio/fabric8/kubernetes/api/model/autoscaling/v2beta1/MetricSpec;)V
      29: astore        6
      31: aload_0
      32: getfield      #17                 // Field _visitables:Lio/fabric8/kubernetes/api/builder/VisitableMap;
      35: ldc           #18                 // String metrics
      37: invokevirtual #19                 // Method io/fabric8/kubernetes/api/builder/VisitableMap.get:(Ljava/lang/Object;)Ljava/util/List;
      40: aload         6
      42: invokeinterface #28,  2           // InterfaceMethod java/util/List.remove:(Ljava/lang/Object;)Z
      47: pop
      48: aload_0
      49: getfield      #4                  // Field metrics:Ljava/util/List;
      52: ifnull        67
      55: aload_0
      56: getfield      #4                  // Field metrics:Ljava/util/List;
      59: aload         6
      61: invokeinterface #28,  2           // InterfaceMethod java/util/List.remove:(Ljava/lang/Object;)Z
      66: pop
      67: iinc          4, 1
      70: goto          8
      73: aload_0
      74: areturn

  public A removeAllFromMetrics(java.util.Collection<io.fabric8.kubernetes.api.model.autoscaling.v2beta1.MetricSpec>);
    Code:
       0: aload_1
       1: invokeinterface #24,  1           // InterfaceMethod java/util/Collection.iterator:()Ljava/util/Iterator;
       6: astore_2
       7: aload_2
       8: invokeinterface #25,  1           // InterfaceMethod java/util/Iterator.hasNext:()Z
      13: ifeq          75
      16: aload_2
      17: invokeinterface #26,  1           // InterfaceMethod java/util/Iterator.next:()Ljava/lang/Object;
      22: checkcast     #27                 // class io/fabric8/kubernetes/api/model/autoscaling/v2beta1/MetricSpec
      25: astore_3
      26: new           #15                 // class io/fabric8/kubernetes/api/model/autoscaling/v2beta1/MetricSpecBuilder
      29: dup
      30: aload_3
      31: invokespecial #16                 // Method io/fabric8/kubernetes/api/model/autoscaling/v2beta1/MetricSpecBuilder."<init>":(Lio/fabric8/kubernetes/api/model/autoscaling/v2beta1/MetricSpec;)V
      34: astore        4
      36: aload_0
      37: getfield      #17                 // Field _visitables:Lio/fabric8/kubernetes/api/builder/VisitableMap;
      40: ldc           #18                 // String metrics
      42: invokevirtual #19                 // Method io/fabric8/kubernetes/api/builder/VisitableMap.get:(Ljava/lang/Object;)Ljava/util/List;
      45: aload         4
      47: invokeinterface #28,  2           // InterfaceMethod java/util/List.remove:(Ljava/lang/Object;)Z
      52: pop
      53: aload_0
      54: getfield      #4                  // Field metrics:Ljava/util/List;
      57: ifnull        72
      60: aload_0
      61: getfield      #4                  // Field metrics:Ljava/util/List;
      64: aload         4
      66: invokeinterface #28,  2           // InterfaceMethod java/util/List.remove:(Ljava/lang/Object;)Z
      71: pop
      72: goto          7
      75: aload_0
      76: areturn

  public A removeMatchingFromMetrics(io.fabric8.kubernetes.api.builder.Predicate<io.fabric8.kubernetes.api.model.autoscaling.v2beta1.MetricSpecBuilder>);
    Code:
       0: aload_0
       1: getfield      #4                  // Field metrics:Ljava/util/List;
       4: ifnonnull     9
       7: aload_0
       8: areturn
       9: aload_0
      10: getfield      #4                  // Field metrics:Ljava/util/List;
      13: invokeinterface #29,  1           // InterfaceMethod java/util/List.iterator:()Ljava/util/Iterator;
      18: astore_2
      19: aload_0
      20: getfield      #17                 // Field _visitables:Lio/fabric8/kubernetes/api/builder/VisitableMap;
      23: ldc           #18                 // String metrics
      25: invokevirtual #19                 // Method io/fabric8/kubernetes/api/builder/VisitableMap.get:(Ljava/lang/Object;)Ljava/util/List;
      28: astore_3
      29: aload_2
      30: invokeinterface #25,  1           // InterfaceMethod java/util/Iterator.hasNext:()Z
      35: ifeq          81
      38: aload_2
      39: invokeinterface #26,  1           // InterfaceMethod java/util/Iterator.next:()Ljava/lang/Object;
      44: checkcast     #15                 // class io/fabric8/kubernetes/api/model/autoscaling/v2beta1/MetricSpecBuilder
      47: astore        4
      49: aload_1
      50: aload         4
      52: invokeinterface #30,  2           // InterfaceMethod io/fabric8/kubernetes/api/builder/Predicate.apply:(Ljava/lang/Object;)Ljava/lang/Boolean;
      57: invokevirtual #31                 // Method java/lang/Boolean.booleanValue:()Z
      60: ifeq          78
      63: aload_3
      64: aload         4
      66: invokeinterface #28,  2           // InterfaceMethod java/util/List.remove:(Ljava/lang/Object;)Z
      71: pop
      72: aload_2
      73: invokeinterface #32,  1           // InterfaceMethod java/util/Iterator.remove:()V
      78: goto          29
      81: aload_0
      82: areturn

  public java.util.List<io.fabric8.kubernetes.api.model.autoscaling.v2beta1.MetricSpec> getMetrics();
    Code:
       0: aload_0
       1: getfield      #4                  // Field metrics:Ljava/util/List;
       4: invokestatic  #33                 // Method build:(Ljava/util/List;)Ljava/util/ArrayList;
       7: areturn

  public java.util.List<io.fabric8.kubernetes.api.model.autoscaling.v2beta1.MetricSpec> buildMetrics();
    Code:
       0: aload_0
       1: getfield      #4                  // Field metrics:Ljava/util/List;
       4: invokestatic  #33                 // Method build:(Ljava/util/List;)Ljava/util/ArrayList;
       7: areturn

  public io.fabric8.kubernetes.api.model.autoscaling.v2beta1.MetricSpec buildMetric(int);
    Code:
       0: aload_0
       1: getfield      #4                  // Field metrics:Ljava/util/List;
       4: iload_1
       5: invokeinterface #34,  2           // InterfaceMethod java/util/List.get:(I)Ljava/lang/Object;
      10: checkcast     #15                 // class io/fabric8/kubernetes/api/model/autoscaling/v2beta1/MetricSpecBuilder
      13: invokevirtual #35                 // Method io/fabric8/kubernetes/api/model/autoscaling/v2beta1/MetricSpecBuilder.build:()Lio/fabric8/kubernetes/api/model/autoscaling/v2beta1/MetricSpec;
      16: areturn

  public io.fabric8.kubernetes.api.model.autoscaling.v2beta1.MetricSpec buildFirstMetric();
    Code:
       0: aload_0
       1: getfield      #4                  // Field metrics:Ljava/util/List;
       4: iconst_0
       5: invokeinterface #34,  2           // InterfaceMethod java/util/List.get:(I)Ljava/lang/Object;
      10: checkcast     #15                 // class io/fabric8/kubernetes/api/model/autoscaling/v2beta1/MetricSpecBuilder
      13: invokevirtual #35                 // Method io/fabric8/kubernetes/api/model/autoscaling/v2beta1/MetricSpecBuilder.build:()Lio/fabric8/kubernetes/api/model/autoscaling/v2beta1/MetricSpec;
      16: areturn

  public io.fabric8.kubernetes.api.model.autoscaling.v2beta1.MetricSpec buildLastMetric();
    Code:
       0: aload_0
       1: getfield      #4                  // Field metrics:Ljava/util/List;
       4: aload_0
       5: getfield      #4                  // Field metrics:Ljava/util/List;
       8: invokeinterface #20,  1           // InterfaceMethod java/util/List.size:()I
      13: iconst_1
      14: isub
      15: invokeinterface #34,  2           // InterfaceMethod java/util/List.get:(I)Ljava/lang/Object;
      20: checkcast     #15                 // class io/fabric8/kubernetes/api/model/autoscaling/v2beta1/MetricSpecBuilder
      23: invokevirtual #35                 // Method io/fabric8/kubernetes/api/model/autoscaling/v2beta1/MetricSpecBuilder.build:()Lio/fabric8/kubernetes/api/model/autoscaling/v2beta1/MetricSpec;
      26: areturn

  public io.fabric8.kubernetes.api.model.autoscaling.v2beta1.MetricSpec buildMatchingMetric(io.fabric8.kubernetes.api.builder.Predicate<io.fabric8.kubernetes.api.model.autoscaling.v2beta1.MetricSpecBuilder>);
    Code:
       0: aload_0
       1: getfield      #4                  // Field metrics:Ljava/util/List;
       4: invokeinterface #29,  1           // InterfaceMethod java/util/List.iterator:()Ljava/util/Iterator;
       9: astore_2
      10: aload_2
      11: invokeinterface #25,  1           // InterfaceMethod java/util/Iterator.hasNext:()Z
      16: ifeq          50
      19: aload_2
      20: invokeinterface #26,  1           // InterfaceMethod java/util/Iterator.next:()Ljava/lang/Object;
      25: checkcast     #15                 // class io/fabric8/kubernetes/api/model/autoscaling/v2beta1/MetricSpecBuilder
      28: astore_3
      29: aload_1
      30: aload_3
      31: invokeinterface #30,  2           // InterfaceMethod io/fabric8/kubernetes/api/builder/Predicate.apply:(Ljava/lang/Object;)Ljava/lang/Boolean;
      36: invokevirtual #31                 // Method java/lang/Boolean.booleanValue:()Z
      39: ifeq          47
      42: aload_3
      43: invokevirtual #35                 // Method io/fabric8/kubernetes/api/model/autoscaling/v2beta1/MetricSpecBuilder.build:()Lio/fabric8/kubernetes/api/model/autoscaling/v2beta1/MetricSpec;
      46: areturn
      47: goto          10
      50: aconst_null
      51: areturn

  public java.lang.Boolean hasMatchingMetric(io.fabric8.kubernetes.api.builder.Predicate<io.fabric8.kubernetes.api.model.autoscaling.v2beta1.MetricSpecBuilder>);
    Code:
       0: aload_0
       1: getfield      #4                  // Field metrics:Ljava/util/List;
       4: invokeinterface #29,  1           // InterfaceMethod java/util/List.iterator:()Ljava/util/Iterator;
       9: astore_2
      10: aload_2
      11: invokeinterface #25,  1           // InterfaceMethod java/util/Iterator.hasNext:()Z
      16: ifeq          50
      19: aload_2
      20: invokeinterface #26,  1           // InterfaceMethod java/util/Iterator.next:()Ljava/lang/Object;
      25: checkcast     #15                 // class io/fabric8/kubernetes/api/model/autoscaling/v2beta1/MetricSpecBuilder
      28: astore_3
      29: aload_1
      30: aload_3
      31: invokeinterface #30,  2           // InterfaceMethod io/fabric8/kubernetes/api/builder/Predicate.apply:(Ljava/lang/Object;)Ljava/lang/Boolean;
      36: invokevirtual #31                 // Method java/lang/Boolean.booleanValue:()Z
      39: ifeq          47
      42: iconst_1
      43: invokestatic  #14                 // Method java/lang/Boolean.valueOf:(Z)Ljava/lang/Boolean;
      46: areturn
      47: goto          10
      50: iconst_0
      51: invokestatic  #14                 // Method java/lang/Boolean.valueOf:(Z)Ljava/lang/Boolean;
      54: areturn

  public A withMetrics(java.util.List<io.fabric8.kubernetes.api.model.autoscaling.v2beta1.MetricSpec>);
    Code:
       0: aload_0
       1: getfield      #4                  // Field metrics:Ljava/util/List;
       4: ifnull        26
       7: aload_0
       8: getfield      #17                 // Field _visitables:Lio/fabric8/kubernetes/api/builder/VisitableMap;
      11: ldc           #18                 // String metrics
      13: invokevirtual #19                 // Method io/fabric8/kubernetes/api/builder/VisitableMap.get:(Ljava/lang/Object;)Ljava/util/List;
      16: aload_0
      17: getfield      #4                  // Field metrics:Ljava/util/List;
      20: invokeinterface #36,  2           // InterfaceMethod java/util/List.removeAll:(Ljava/util/Collection;)Z
      25: pop
      26: aload_1
      27: ifnull        86
      30: aload_0
      31: new           #2                  // class java/util/ArrayList
      34: dup
      35: invokespecial #3                  // Method java/util/ArrayList."<init>":()V
      38: putfield      #4                  // Field metrics:Ljava/util/List;
      41: aload_1
      42: invokeinterface #29,  1           // InterfaceMethod java/util/List.iterator:()Ljava/util/Iterator;
      47: astore_2
      48: aload_2
      49: invokeinterface #25,  1           // InterfaceMethod java/util/Iterator.hasNext:()Z
      54: ifeq          83
      57: aload_2
      58: invokeinterface #26,  1           // InterfaceMethod java/util/Iterator.next:()Ljava/lang/Object;
      63: checkcast     #27                 // class io/fabric8/kubernetes/api/model/autoscaling/v2beta1/MetricSpec
      66: astore_3
      67: aload_0
      68: iconst_1
      69: anewarray     #27                 // class io/fabric8/kubernetes/api/model/autoscaling/v2beta1/MetricSpec
      72: dup
      73: iconst_0
      74: aload_3
      75: aastore
      76: invokevirtual #37                 // Method addToMetrics:([Lio/fabric8/kubernetes/api/model/autoscaling/v2beta1/MetricSpec;)Lio/fabric8/kubernetes/api/model/autoscaling/v2beta1/HorizontalPodAutoscalerSpecFluent;
      79: pop
      80: goto          48
      83: goto          91
      86: aload_0
      87: aconst_null
      88: putfield      #4                  // Field metrics:Ljava/util/List;
      91: aload_0
      92: areturn

  public A withMetrics(io.fabric8.kubernetes.api.model.autoscaling.v2beta1.MetricSpec...);
    Code:
       0: aload_0
       1: getfield      #4                  // Field metrics:Ljava/util/List;
       4: ifnull        16
       7: aload_0
       8: getfield      #4                  // Field metrics:Ljava/util/List;
      11: invokeinterface #38,  1           // InterfaceMethod java/util/List.clear:()V
      16: aload_1
      17: ifnull        60
      20: aload_1
      21: astore_2
      22: aload_2
      23: arraylength
      24: istore_3
      25: iconst_0
      26: istore        4
      28: iload         4
      30: iload_3
      31: if_icmpge     60
      34: aload_2
      35: iload         4
      37: aaload
      38: astore        5
      40: aload_0
      41: iconst_1
      42: anewarray     #27                 // class io/fabric8/kubernetes/api/model/autoscaling/v2beta1/MetricSpec
      45: dup
      46: iconst_0
      47: aload         5
      49: aastore
      50: invokevirtual #37                 // Method addToMetrics:([Lio/fabric8/kubernetes/api/model/autoscaling/v2beta1/MetricSpec;)Lio/fabric8/kubernetes/api/model/autoscaling/v2beta1/HorizontalPodAutoscalerSpecFluent;
      53: pop
      54: iinc          4, 1
      57: goto          28
      60: aload_0
      61: areturn

  public java.lang.Boolean hasMetrics();
    Code:
       0: aload_0
       1: getfield      #4                  // Field metrics:Ljava/util/List;
       4: ifnull        23
       7: aload_0
       8: getfield      #4                  // Field metrics:Ljava/util/List;
      11: invokeinterface #39,  1           // InterfaceMethod java/util/List.isEmpty:()Z
      16: ifne          23
      19: iconst_1
      20: goto          24
      23: iconst_0
      24: invokestatic  #14                 // Method java/lang/Boolean.valueOf:(Z)Ljava/lang/Boolean;
      27: areturn

  public io.fabric8.kubernetes.api.model.autoscaling.v2beta1.HorizontalPodAutoscalerSpecFluent$MetricsNested<A> addNewMetric();
    Code:
       0: new           #40                 // class io/fabric8/kubernetes/api/model/autoscaling/v2beta1/HorizontalPodAutoscalerSpecFluentImpl$MetricsNestedImpl
       3: dup
       4: aload_0
       5: invokespecial #41                 // Method io/fabric8/kubernetes/api/model/autoscaling/v2beta1/HorizontalPodAutoscalerSpecFluentImpl$MetricsNestedImpl."<init>":(Lio/fabric8/kubernetes/api/model/autoscaling/v2beta1/HorizontalPodAutoscalerSpecFluentImpl;)V
       8: areturn

  public io.fabric8.kubernetes.api.model.autoscaling.v2beta1.HorizontalPodAutoscalerSpecFluent$MetricsNested<A> addNewMetricLike(io.fabric8.kubernetes.api.model.autoscaling.v2beta1.MetricSpec);
    Code:
       0: new           #40                 // class io/fabric8/kubernetes/api/model/autoscaling/v2beta1/HorizontalPodAutoscalerSpecFluentImpl$MetricsNestedImpl
       3: dup
       4: aload_0
       5: iconst_m1
       6: aload_1
       7: invokespecial #42                 // Method io/fabric8/kubernetes/api/model/autoscaling/v2beta1/HorizontalPodAutoscalerSpecFluentImpl$MetricsNestedImpl."<init>":(Lio/fabric8/kubernetes/api/model/autoscaling/v2beta1/HorizontalPodAutoscalerSpecFluentImpl;ILio/fabric8/kubernetes/api/model/autoscaling/v2beta1/MetricSpec;)V
      10: areturn

  public io.fabric8.kubernetes.api.model.autoscaling.v2beta1.HorizontalPodAutoscalerSpecFluent$MetricsNested<A> setNewMetricLike(int, io.fabric8.kubernetes.api.model.autoscaling.v2beta1.MetricSpec);
    Code:
       0: new           #40                 // class io/fabric8/kubernetes/api/model/autoscaling/v2beta1/HorizontalPodAutoscalerSpecFluentImpl$MetricsNestedImpl
       3: dup
       4: aload_0
       5: iload_1
       6: aload_2
       7: invokespecial #42                 // Method io/fabric8/kubernetes/api/model/autoscaling/v2beta1/HorizontalPodAutoscalerSpecFluentImpl$MetricsNestedImpl."<init>":(Lio/fabric8/kubernetes/api/model/autoscaling/v2beta1/HorizontalPodAutoscalerSpecFluentImpl;ILio/fabric8/kubernetes/api/model/autoscaling/v2beta1/MetricSpec;)V
      10: areturn

  public io.fabric8.kubernetes.api.model.autoscaling.v2beta1.HorizontalPodAutoscalerSpecFluent$MetricsNested<A> editMetric(int);
    Code:
       0: aload_0
       1: getfield      #4                  // Field metrics:Ljava/util/List;
       4: invokeinterface #20,  1           // InterfaceMethod java/util/List.size:()I
       9: iload_1
      10: if_icmpgt     23
      13: new           #43                 // class java/lang/RuntimeException
      16: dup
      17: ldc           #44                 // String Can\'t edit metrics. Index exceeds size.
      19: invokespecial #45                 // Method java/lang/RuntimeException."<init>":(Ljava/lang/String;)V
      22: athrow
      23: aload_0
      24: iload_1
      25: aload_0
      26: iload_1
      27: invokevirtual #46                 // Method buildMetric:(I)Lio/fabric8/kubernetes/api/model/autoscaling/v2beta1/MetricSpec;
      30: invokevirtual #47                 // Method setNewMetricLike:(ILio/fabric8/kubernetes/api/model/autoscaling/v2beta1/MetricSpec;)Lio/fabric8/kubernetes/api/model/autoscaling/v2beta1/HorizontalPodAutoscalerSpecFluent$MetricsNested;
      33: areturn

  public io.fabric8.kubernetes.api.model.autoscaling.v2beta1.HorizontalPodAutoscalerSpecFluent$MetricsNested<A> editFirstMetric();
    Code:
       0: aload_0
       1: getfield      #4                  // Field metrics:Ljava/util/List;
       4: invokeinterface #20,  1           // InterfaceMethod java/util/List.size:()I
       9: ifne          22
      12: new           #43                 // class java/lang/RuntimeException
      15: dup
      16: ldc           #48                 // String Can\'t edit first metrics. The list is empty.
      18: invokespecial #45                 // Method java/lang/RuntimeException."<init>":(Ljava/lang/String;)V
      21: athrow
      22: aload_0
      23: iconst_0
      24: aload_0
      25: iconst_0
      26: invokevirtual #46                 // Method buildMetric:(I)Lio/fabric8/kubernetes/api/model/autoscaling/v2beta1/MetricSpec;
      29: invokevirtual #47                 // Method setNewMetricLike:(ILio/fabric8/kubernetes/api/model/autoscaling/v2beta1/MetricSpec;)Lio/fabric8/kubernetes/api/model/autoscaling/v2beta1/HorizontalPodAutoscalerSpecFluent$MetricsNested;
      32: areturn

  public io.fabric8.kubernetes.api.model.autoscaling.v2beta1.HorizontalPodAutoscalerSpecFluent$MetricsNested<A> editLastMetric();
    Code:
       0: aload_0
       1: getfield      #4                  // Field metrics:Ljava/util/List;
       4: invokeinterface #20,  1           // InterfaceMethod java/util/List.size:()I
       9: iconst_1
      10: isub
      11: istore_1
      12: iload_1
      13: ifge          26
      16: new           #43                 // class java/lang/RuntimeException
      19: dup
      20: ldc           #49                 // String Can\'t edit last metrics. The list is empty.
      22: invokespecial #45                 // Method java/lang/RuntimeException."<init>":(Ljava/lang/String;)V
      25: athrow
      26: aload_0
      27: iload_1
      28: aload_0
      29: iload_1
      30: invokevirtual #46                 // Method buildMetric:(I)Lio/fabric8/kubernetes/api/model/autoscaling/v2beta1/MetricSpec;
      33: invokevirtual #47                 // Method setNewMetricLike:(ILio/fabric8/kubernetes/api/model/autoscaling/v2beta1/MetricSpec;)Lio/fabric8/kubernetes/api/model/autoscaling/v2beta1/HorizontalPodAutoscalerSpecFluent$MetricsNested;
      36: areturn

  public io.fabric8.kubernetes.api.model.autoscaling.v2beta1.HorizontalPodAutoscalerSpecFluent$MetricsNested<A> editMatchingMetric(io.fabric8.kubernetes.api.builder.Predicate<io.fabric8.kubernetes.api.model.autoscaling.v2beta1.MetricSpecBuilder>);
    Code:
       0: iconst_m1
       1: istore_2
       2: iconst_0
       3: istore_3
       4: iload_3
       5: aload_0
       6: getfield      #4                  // Field metrics:Ljava/util/List;
       9: invokeinterface #20,  1           // InterfaceMethod java/util/List.size:()I
      14: if_icmpge     50
      17: aload_1
      18: aload_0
      19: getfield      #4                  // Field metrics:Ljava/util/List;
      22: iload_3
      23: invokeinterface #34,  2           // InterfaceMethod java/util/List.get:(I)Ljava/lang/Object;
      28: invokeinterface #30,  2           // InterfaceMethod io/fabric8/kubernetes/api/builder/Predicate.apply:(Ljava/lang/Object;)Ljava/lang/Boolean;
      33: invokevirtual #31                 // Method java/lang/Boolean.booleanValue:()Z
      36: ifeq          44
      39: iload_3
      40: istore_2
      41: goto          50
      44: iinc          3, 1
      47: goto          4
      50: iload_2
      51: ifge          64
      54: new           #43                 // class java/lang/RuntimeException
      57: dup
      58: ldc           #50                 // String Can\'t edit matching metrics. No match found.
      60: invokespecial #45                 // Method java/lang/RuntimeException."<init>":(Ljava/lang/String;)V
      63: athrow
      64: aload_0
      65: iload_2
      66: aload_0
      67: iload_2
      68: invokevirtual #46                 // Method buildMetric:(I)Lio/fabric8/kubernetes/api/model/autoscaling/v2beta1/MetricSpec;
      71: invokevirtual #47                 // Method setNewMetricLike:(ILio/fabric8/kubernetes/api/model/autoscaling/v2beta1/MetricSpec;)Lio/fabric8/kubernetes/api/model/autoscaling/v2beta1/HorizontalPodAutoscalerSpecFluent$MetricsNested;
      74: areturn

  public java.lang.Integer getMinReplicas();
    Code:
       0: aload_0
       1: getfield      #51                 // Field minReplicas:Ljava/lang/Integer;
       4: areturn

  public A withMinReplicas(java.lang.Integer);
    Code:
       0: aload_0
       1: aload_1
       2: putfield      #51                 // Field minReplicas:Ljava/lang/Integer;
       5: aload_0
       6: areturn

  public java.lang.Boolean hasMinReplicas();
    Code:
       0: aload_0
       1: getfield      #51                 // Field minReplicas:Ljava/lang/Integer;
       4: ifnull        11
       7: iconst_1
       8: goto          12
      11: iconst_0
      12: invokestatic  #14                 // Method java/lang/Boolean.valueOf:(Z)Ljava/lang/Boolean;
      15: areturn

  public io.fabric8.kubernetes.api.model.autoscaling.v2beta1.CrossVersionObjectReference getScaleTargetRef();
    Code:
       0: aload_0
       1: getfield      #52                 // Field scaleTargetRef:Lio/fabric8/kubernetes/api/model/autoscaling/v2beta1/CrossVersionObjectReferenceBuilder;
       4: ifnull        17
       7: aload_0
       8: getfield      #52                 // Field scaleTargetRef:Lio/fabric8/kubernetes/api/model/autoscaling/v2beta1/CrossVersionObjectReferenceBuilder;
      11: invokevirtual #53                 // Method io/fabric8/kubernetes/api/model/autoscaling/v2beta1/CrossVersionObjectReferenceBuilder.build:()Lio/fabric8/kubernetes/api/model/autoscaling/v2beta1/CrossVersionObjectReference;
      14: goto          18
      17: aconst_null
      18: areturn

  public io.fabric8.kubernetes.api.model.autoscaling.v2beta1.CrossVersionObjectReference buildScaleTargetRef();
    Code:
       0: aload_0
       1: getfield      #52                 // Field scaleTargetRef:Lio/fabric8/kubernetes/api/model/autoscaling/v2beta1/CrossVersionObjectReferenceBuilder;
       4: ifnull        17
       7: aload_0
       8: getfield      #52                 // Field scaleTargetRef:Lio/fabric8/kubernetes/api/model/autoscaling/v2beta1/CrossVersionObjectReferenceBuilder;
      11: invokevirtual #53                 // Method io/fabric8/kubernetes/api/model/autoscaling/v2beta1/CrossVersionObjectReferenceBuilder.build:()Lio/fabric8/kubernetes/api/model/autoscaling/v2beta1/CrossVersionObjectReference;
      14: goto          18
      17: aconst_null
      18: areturn

  public A withScaleTargetRef(io.fabric8.kubernetes.api.model.autoscaling.v2beta1.CrossVersionObjectReference);
    Code:
       0: aload_0
       1: getfield      #17                 // Field _visitables:Lio/fabric8/kubernetes/api/builder/VisitableMap;
       4: ldc           #54                 // String scaleTargetRef
       6: invokevirtual #19                 // Method io/fabric8/kubernetes/api/builder/VisitableMap.get:(Ljava/lang/Object;)Ljava/util/List;
       9: aload_0
      10: getfield      #52                 // Field scaleTargetRef:Lio/fabric8/kubernetes/api/model/autoscaling/v2beta1/CrossVersionObjectReferenceBuilder;
      13: invokeinterface #28,  2           // InterfaceMethod java/util/List.remove:(Ljava/lang/Object;)Z
      18: pop
      19: aload_1
      20: ifnull        54
      23: aload_0
      24: new           #55                 // class io/fabric8/kubernetes/api/model/autoscaling/v2beta1/CrossVersionObjectReferenceBuilder
      27: dup
      28: aload_1
      29: invokespecial #56                 // Method io/fabric8/kubernetes/api/model/autoscaling/v2beta1/CrossVersionObjectReferenceBuilder."<init>":(Lio/fabric8/kubernetes/api/model/autoscaling/v2beta1/CrossVersionObjectReference;)V
      32: putfield      #52                 // Field scaleTargetRef:Lio/fabric8/kubernetes/api/model/autoscaling/v2beta1/CrossVersionObjectReferenceBuilder;
      35: aload_0
      36: getfield      #17                 // Field _visitables:Lio/fabric8/kubernetes/api/builder/VisitableMap;
      39: ldc           #54                 // String scaleTargetRef
      41: invokevirtual #19                 // Method io/fabric8/kubernetes/api/builder/VisitableMap.get:(Ljava/lang/Object;)Ljava/util/List;
      44: aload_0
      45: getfield      #52                 // Field scaleTargetRef:Lio/fabric8/kubernetes/api/model/autoscaling/v2beta1/CrossVersionObjectReferenceBuilder;
      48: invokeinterface #22,  2           // InterfaceMethod java/util/List.add:(Ljava/lang/Object;)Z
      53: pop
      54: aload_0
      55: areturn

  public java.lang.Boolean hasScaleTargetRef();
    Code:
       0: aload_0
       1: getfield      #52                 // Field scaleTargetRef:Lio/fabric8/kubernetes/api/model/autoscaling/v2beta1/CrossVersionObjectReferenceBuilder;
       4: ifnull        11
       7: iconst_1
       8: goto          12
      11: iconst_0
      12: invokestatic  #14                 // Method java/lang/Boolean.valueOf:(Z)Ljava/lang/Boolean;
      15: areturn

  public A withNewScaleTargetRef(java.lang.String, java.lang.String, java.lang.String);
    Code:
       0: aload_0
       1: new           #57                 // class io/fabric8/kubernetes/api/model/autoscaling/v2beta1/CrossVersionObjectReference
       4: dup
       5: aload_1
       6: aload_2
       7: aload_3
       8: invokespecial #58                 // Method io/fabric8/kubernetes/api/model/autoscaling/v2beta1/CrossVersionObjectReference."<init>":(Ljava/lang/String;Ljava/lang/String;Ljava/lang/String;)V
      11: invokevirtual #12                 // Method withScaleTargetRef:(Lio/fabric8/kubernetes/api/model/autoscaling/v2beta1/CrossVersionObjectReference;)Lio/fabric8/kubernetes/api/model/autoscaling/v2beta1/HorizontalPodAutoscalerSpecFluent;
      14: areturn

  public io.fabric8.kubernetes.api.model.autoscaling.v2beta1.HorizontalPodAutoscalerSpecFluent$ScaleTargetRefNested<A> withNewScaleTargetRef();
    Code:
       0: new           #59                 // class io/fabric8/kubernetes/api/model/autoscaling/v2beta1/HorizontalPodAutoscalerSpecFluentImpl$ScaleTargetRefNestedImpl
       3: dup
       4: aload_0
       5: invokespecial #60                 // Method io/fabric8/kubernetes/api/model/autoscaling/v2beta1/HorizontalPodAutoscalerSpecFluentImpl$ScaleTargetRefNestedImpl."<init>":(Lio/fabric8/kubernetes/api/model/autoscaling/v2beta1/HorizontalPodAutoscalerSpecFluentImpl;)V
       8: areturn

  public io.fabric8.kubernetes.api.model.autoscaling.v2beta1.HorizontalPodAutoscalerSpecFluent$ScaleTargetRefNested<A> withNewScaleTargetRefLike(io.fabric8.kubernetes.api.model.autoscaling.v2beta1.CrossVersionObjectReference);
    Code:
       0: new           #59                 // class io/fabric8/kubernetes/api/model/autoscaling/v2beta1/HorizontalPodAutoscalerSpecFluentImpl$ScaleTargetRefNestedImpl
       3: dup
       4: aload_0
       5: aload_1
       6: invokespecial #61                 // Method io/fabric8/kubernetes/api/model/autoscaling/v2beta1/HorizontalPodAutoscalerSpecFluentImpl$ScaleTargetRefNestedImpl."<init>":(Lio/fabric8/kubernetes/api/model/autoscaling/v2beta1/HorizontalPodAutoscalerSpecFluentImpl;Lio/fabric8/kubernetes/api/model/autoscaling/v2beta1/CrossVersionObjectReference;)V
       9: areturn

  public io.fabric8.kubernetes.api.model.autoscaling.v2beta1.HorizontalPodAutoscalerSpecFluent$ScaleTargetRefNested<A> editScaleTargetRef();
    Code:
       0: aload_0
       1: aload_0
       2: invokevirtual #62                 // Method getScaleTargetRef:()Lio/fabric8/kubernetes/api/model/autoscaling/v2beta1/CrossVersionObjectReference;
       5: invokevirtual #63                 // Method withNewScaleTargetRefLike:(Lio/fabric8/kubernetes/api/model/autoscaling/v2beta1/CrossVersionObjectReference;)Lio/fabric8/kubernetes/api/model/autoscaling/v2beta1/HorizontalPodAutoscalerSpecFluent$ScaleTargetRefNested;
       8: areturn

  public io.fabric8.kubernetes.api.model.autoscaling.v2beta1.HorizontalPodAutoscalerSpecFluent$ScaleTargetRefNested<A> editOrNewScaleTargetRef();
    Code:
       0: aload_0
       1: aload_0
       2: invokevirtual #62                 // Method getScaleTargetRef:()Lio/fabric8/kubernetes/api/model/autoscaling/v2beta1/CrossVersionObjectReference;
       5: ifnull        15
       8: aload_0
       9: invokevirtual #62                 // Method getScaleTargetRef:()Lio/fabric8/kubernetes/api/model/autoscaling/v2beta1/CrossVersionObjectReference;
      12: goto          25
      15: new           #55                 // class io/fabric8/kubernetes/api/model/autoscaling/v2beta1/CrossVersionObjectReferenceBuilder
      18: dup
      19: invokespecial #64                 // Method io/fabric8/kubernetes/api/model/autoscaling/v2beta1/CrossVersionObjectReferenceBuilder."<init>":()V
      22: invokevirtual #53                 // Method io/fabric8/kubernetes/api/model/autoscaling/v2beta1/CrossVersionObjectReferenceBuilder.build:()Lio/fabric8/kubernetes/api/model/autoscaling/v2beta1/CrossVersionObjectReference;
      25: invokevirtual #63                 // Method withNewScaleTargetRefLike:(Lio/fabric8/kubernetes/api/model/autoscaling/v2beta1/CrossVersionObjectReference;)Lio/fabric8/kubernetes/api/model/autoscaling/v2beta1/HorizontalPodAutoscalerSpecFluent$ScaleTargetRefNested;
      28: areturn

  public io.fabric8.kubernetes.api.model.autoscaling.v2beta1.HorizontalPodAutoscalerSpecFluent$ScaleTargetRefNested<A> editOrNewScaleTargetRefLike(io.fabric8.kubernetes.api.model.autoscaling.v2beta1.CrossVersionObjectReference);
    Code:
       0: aload_0
       1: aload_0
       2: invokevirtual #62                 // Method getScaleTargetRef:()Lio/fabric8/kubernetes/api/model/autoscaling/v2beta1/CrossVersionObjectReference;
       5: ifnull        15
       8: aload_0
       9: invokevirtual #62                 // Method getScaleTargetRef:()Lio/fabric8/kubernetes/api/model/autoscaling/v2beta1/CrossVersionObjectReference;
      12: goto          16
      15: aload_1
      16: invokevirtual #63                 // Method withNewScaleTargetRefLike:(Lio/fabric8/kubernetes/api/model/autoscaling/v2beta1/CrossVersionObjectReference;)Lio/fabric8/kubernetes/api/model/autoscaling/v2beta1/HorizontalPodAutoscalerSpecFluent$ScaleTargetRefNested;
      19: areturn

  public boolean equals(java.lang.Object);
    Code:
       0: aload_0
       1: aload_1
       2: if_acmpne     7
       5: iconst_1
       6: ireturn
       7: aload_1
       8: ifnull        22
      11: aload_0
      12: invokevirtual #65                 // Method java/lang/Object.getClass:()Ljava/lang/Class;
      15: aload_1
      16: invokevirtual #65                 // Method java/lang/Object.getClass:()Ljava/lang/Class;
      19: if_acmpeq     24
      22: iconst_0
      23: ireturn
      24: aload_1
      25: checkcast     #66                 // class io/fabric8/kubernetes/api/model/autoscaling/v2beta1/HorizontalPodAutoscalerSpecFluentImpl
      28: astore_2
      29: aload_0
      30: getfield      #13                 // Field maxReplicas:Ljava/lang/Integer;
      33: ifnull        53
      36: aload_0
      37: getfield      #13                 // Field maxReplicas:Ljava/lang/Integer;
      40: aload_2
      41: getfield      #13                 // Field maxReplicas:Ljava/lang/Integer;
      44: invokevirtual #67                 // Method java/lang/Integer.equals:(Ljava/lang/Object;)Z
      47: ifne          62
      50: goto          60
      53: aload_2
      54: getfield      #13                 // Field maxReplicas:Ljava/lang/Integer;
      57: ifnull        62
      60: iconst_0
      61: ireturn
      62: aload_0
      63: getfield      #4                  // Field metrics:Ljava/util/List;
      66: ifnull        88
      69: aload_0
      70: getfield      #4                  // Field metrics:Ljava/util/List;
      73: aload_2
      74: getfield      #4                  // Field metrics:Ljava/util/List;
      77: invokeinterface #68,  2           // InterfaceMethod java/util/List.equals:(Ljava/lang/Object;)Z
      82: ifne          97
      85: goto          95
      88: aload_2
      89: getfield      #4                  // Field metrics:Ljava/util/List;
      92: ifnull        97
      95: iconst_0
      96: ireturn
      97: aload_0
      98: getfield      #51                 // Field minReplicas:Ljava/lang/Integer;
     101: ifnull        121
     104: aload_0
     105: getfield      #51                 // Field minReplicas:Ljava/lang/Integer;
     108: aload_2
     109: getfield      #51                 // Field minReplicas:Ljava/lang/Integer;
     112: invokevirtual #67                 // Method java/lang/Integer.equals:(Ljava/lang/Object;)Z
     115: ifne          130
     118: goto          128
     121: aload_2
     122: getfield      #51                 // Field minReplicas:Ljava/lang/Integer;
     125: ifnull        130
     128: iconst_0
     129: ireturn
     130: aload_0
     131: getfield      #52                 // Field scaleTargetRef:Lio/fabric8/kubernetes/api/model/autoscaling/v2beta1/CrossVersionObjectReferenceBuilder;
     134: ifnull        154
     137: aload_0
     138: getfield      #52                 // Field scaleTargetRef:Lio/fabric8/kubernetes/api/model/autoscaling/v2beta1/CrossVersionObjectReferenceBuilder;
     141: aload_2
     142: getfield      #52                 // Field scaleTargetRef:Lio/fabric8/kubernetes/api/model/autoscaling/v2beta1/CrossVersionObjectReferenceBuilder;
     145: invokevirtual #69                 // Method io/fabric8/kubernetes/api/model/autoscaling/v2beta1/CrossVersionObjectReferenceBuilder.equals:(Ljava/lang/Object;)Z
     148: ifne          163
     151: goto          161
     154: aload_2
     155: getfield      #52                 // Field scaleTargetRef:Lio/fabric8/kubernetes/api/model/autoscaling/v2beta1/CrossVersionObjectReferenceBuilder;
     158: ifnull        163
     161: iconst_0
     162: ireturn
     163: iconst_1
     164: ireturn
}
