Compiled from "MetricStatusFluentImpl.java"
public class io.fabric8.kubernetes.api.model.autoscaling.v2beta1.MetricStatusFluentImpl<A extends io.fabric8.kubernetes.api.model.autoscaling.v2beta1.MetricStatusFluent<A>> extends io.fabric8.kubernetes.api.builder.BaseFluent<A> implements io.fabric8.kubernetes.api.model.autoscaling.v2beta1.MetricStatusFluent<A> {
  private io.fabric8.kubernetes.api.model.autoscaling.v2beta1.ExternalMetricStatusBuilder external;

  private io.fabric8.kubernetes.api.model.autoscaling.v2beta1.ObjectMetricStatusBuilder object;

  private io.fabric8.kubernetes.api.model.autoscaling.v2beta1.PodsMetricStatusBuilder pods;

  private io.fabric8.kubernetes.api.model.autoscaling.v2beta1.ResourceMetricStatusBuilder resource;

  private java.lang.String type;

  public io.fabric8.kubernetes.api.model.autoscaling.v2beta1.MetricStatusFluentImpl();
    Code:
       0: aload_0
       1: invokespecial #1                  // Method io/fabric8/kubernetes/api/builder/BaseFluent."<init>":()V
       4: return

  public io.fabric8.kubernetes.api.model.autoscaling.v2beta1.MetricStatusFluentImpl(io.fabric8.kubernetes.api.model.autoscaling.v2beta1.MetricStatus);
    Code:
       0: aload_0
       1: invokespecial #1                  // Method io/fabric8/kubernetes/api/builder/BaseFluent."<init>":()V
       4: aload_0
       5: aload_1
       6: invokevirtual #2                  // Method io/fabric8/kubernetes/api/model/autoscaling/v2beta1/MetricStatus.getExternal:()Lio/fabric8/kubernetes/api/model/autoscaling/v2beta1/ExternalMetricStatus;
       9: invokevirtual #3                  // Method withExternal:(Lio/fabric8/kubernetes/api/model/autoscaling/v2beta1/ExternalMetricStatus;)Lio/fabric8/kubernetes/api/model/autoscaling/v2beta1/MetricStatusFluent;
      12: pop
      13: aload_0
      14: aload_1
      15: invokevirtual #4                  // Method io/fabric8/kubernetes/api/model/autoscaling/v2beta1/MetricStatus.getObject:()Lio/fabric8/kubernetes/api/model/autoscaling/v2beta1/ObjectMetricStatus;
      18: invokevirtual #5                  // Method withObject:(Lio/fabric8/kubernetes/api/model/autoscaling/v2beta1/ObjectMetricStatus;)Lio/fabric8/kubernetes/api/model/autoscaling/v2beta1/MetricStatusFluent;
      21: pop
      22: aload_0
      23: aload_1
      24: invokevirtual #6                  // Method io/fabric8/kubernetes/api/model/autoscaling/v2beta1/MetricStatus.getPods:()Lio/fabric8/kubernetes/api/model/autoscaling/v2beta1/PodsMetricStatus;
      27: invokevirtual #7                  // Method withPods:(Lio/fabric8/kubernetes/api/model/autoscaling/v2beta1/PodsMetricStatus;)Lio/fabric8/kubernetes/api/model/autoscaling/v2beta1/MetricStatusFluent;
      30: pop
      31: aload_0
      32: aload_1
      33: invokevirtual #8                  // Method io/fabric8/kubernetes/api/model/autoscaling/v2beta1/MetricStatus.getResource:()Lio/fabric8/kubernetes/api/model/autoscaling/v2beta1/ResourceMetricStatus;
      36: invokevirtual #9                  // Method withResource:(Lio/fabric8/kubernetes/api/model/autoscaling/v2beta1/ResourceMetricStatus;)Lio/fabric8/kubernetes/api/model/autoscaling/v2beta1/MetricStatusFluent;
      39: pop
      40: aload_0
      41: aload_1
      42: invokevirtual #10                 // Method io/fabric8/kubernetes/api/model/autoscaling/v2beta1/MetricStatus.getType:()Ljava/lang/String;
      45: invokevirtual #11                 // Method withType:(Ljava/lang/String;)Lio/fabric8/kubernetes/api/model/autoscaling/v2beta1/MetricStatusFluent;
      48: pop
      49: return

  public io.fabric8.kubernetes.api.model.autoscaling.v2beta1.ExternalMetricStatus getExternal();
    Code:
       0: aload_0
       1: getfield      #12                 // Field external:Lio/fabric8/kubernetes/api/model/autoscaling/v2beta1/ExternalMetricStatusBuilder;
       4: ifnull        17
       7: aload_0
       8: getfield      #12                 // Field external:Lio/fabric8/kubernetes/api/model/autoscaling/v2beta1/ExternalMetricStatusBuilder;
      11: invokevirtual #13                 // Method io/fabric8/kubernetes/api/model/autoscaling/v2beta1/ExternalMetricStatusBuilder.build:()Lio/fabric8/kubernetes/api/model/autoscaling/v2beta1/ExternalMetricStatus;
      14: goto          18
      17: aconst_null
      18: areturn

  public io.fabric8.kubernetes.api.model.autoscaling.v2beta1.ExternalMetricStatus buildExternal();
    Code:
       0: aload_0
       1: getfield      #12                 // Field external:Lio/fabric8/kubernetes/api/model/autoscaling/v2beta1/ExternalMetricStatusBuilder;
       4: ifnull        17
       7: aload_0
       8: getfield      #12                 // Field external:Lio/fabric8/kubernetes/api/model/autoscaling/v2beta1/ExternalMetricStatusBuilder;
      11: invokevirtual #13                 // Method io/fabric8/kubernetes/api/model/autoscaling/v2beta1/ExternalMetricStatusBuilder.build:()Lio/fabric8/kubernetes/api/model/autoscaling/v2beta1/ExternalMetricStatus;
      14: goto          18
      17: aconst_null
      18: areturn

  public A withExternal(io.fabric8.kubernetes.api.model.autoscaling.v2beta1.ExternalMetricStatus);
    Code:
       0: aload_0
       1: getfield      #14                 // Field _visitables:Lio/fabric8/kubernetes/api/builder/VisitableMap;
       4: ldc           #15                 // String external
       6: invokevirtual #16                 // Method io/fabric8/kubernetes/api/builder/VisitableMap.get:(Ljava/lang/Object;)Ljava/util/List;
       9: aload_0
      10: getfield      #12                 // Field external:Lio/fabric8/kubernetes/api/model/autoscaling/v2beta1/ExternalMetricStatusBuilder;
      13: invokeinterface #17,  2           // InterfaceMethod java/util/List.remove:(Ljava/lang/Object;)Z
      18: pop
      19: aload_1
      20: ifnull        54
      23: aload_0
      24: new           #18                 // class io/fabric8/kubernetes/api/model/autoscaling/v2beta1/ExternalMetricStatusBuilder
      27: dup
      28: aload_1
      29: invokespecial #19                 // Method io/fabric8/kubernetes/api/model/autoscaling/v2beta1/ExternalMetricStatusBuilder."<init>":(Lio/fabric8/kubernetes/api/model/autoscaling/v2beta1/ExternalMetricStatus;)V
      32: putfield      #12                 // Field external:Lio/fabric8/kubernetes/api/model/autoscaling/v2beta1/ExternalMetricStatusBuilder;
      35: aload_0
      36: getfield      #14                 // Field _visitables:Lio/fabric8/kubernetes/api/builder/VisitableMap;
      39: ldc           #15                 // String external
      41: invokevirtual #16                 // Method io/fabric8/kubernetes/api/builder/VisitableMap.get:(Ljava/lang/Object;)Ljava/util/List;
      44: aload_0
      45: getfield      #12                 // Field external:Lio/fabric8/kubernetes/api/model/autoscaling/v2beta1/ExternalMetricStatusBuilder;
      48: invokeinterface #20,  2           // InterfaceMethod java/util/List.add:(Ljava/lang/Object;)Z
      53: pop
      54: aload_0
      55: areturn

  public java.lang.Boolean hasExternal();
    Code:
       0: aload_0
       1: getfield      #12                 // Field external:Lio/fabric8/kubernetes/api/model/autoscaling/v2beta1/ExternalMetricStatusBuilder;
       4: ifnull        11
       7: iconst_1
       8: goto          12
      11: iconst_0
      12: invokestatic  #21                 // Method java/lang/Boolean.valueOf:(Z)Ljava/lang/Boolean;
      15: areturn

  public io.fabric8.kubernetes.api.model.autoscaling.v2beta1.MetricStatusFluent$ExternalNested<A> withNewExternal();
    Code:
       0: new           #22                 // class io/fabric8/kubernetes/api/model/autoscaling/v2beta1/MetricStatusFluentImpl$ExternalNestedImpl
       3: dup
       4: aload_0
       5: invokespecial #23                 // Method io/fabric8/kubernetes/api/model/autoscaling/v2beta1/MetricStatusFluentImpl$ExternalNestedImpl."<init>":(Lio/fabric8/kubernetes/api/model/autoscaling/v2beta1/MetricStatusFluentImpl;)V
       8: areturn

  public io.fabric8.kubernetes.api.model.autoscaling.v2beta1.MetricStatusFluent$ExternalNested<A> withNewExternalLike(io.fabric8.kubernetes.api.model.autoscaling.v2beta1.ExternalMetricStatus);
    Code:
       0: new           #22                 // class io/fabric8/kubernetes/api/model/autoscaling/v2beta1/MetricStatusFluentImpl$ExternalNestedImpl
       3: dup
       4: aload_0
       5: aload_1
       6: invokespecial #24                 // Method io/fabric8/kubernetes/api/model/autoscaling/v2beta1/MetricStatusFluentImpl$ExternalNestedImpl."<init>":(Lio/fabric8/kubernetes/api/model/autoscaling/v2beta1/MetricStatusFluentImpl;Lio/fabric8/kubernetes/api/model/autoscaling/v2beta1/ExternalMetricStatus;)V
       9: areturn

  public io.fabric8.kubernetes.api.model.autoscaling.v2beta1.MetricStatusFluent$ExternalNested<A> editExternal();
    Code:
       0: aload_0
       1: aload_0
       2: invokevirtual #25                 // Method getExternal:()Lio/fabric8/kubernetes/api/model/autoscaling/v2beta1/ExternalMetricStatus;
       5: invokevirtual #26                 // Method withNewExternalLike:(Lio/fabric8/kubernetes/api/model/autoscaling/v2beta1/ExternalMetricStatus;)Lio/fabric8/kubernetes/api/model/autoscaling/v2beta1/MetricStatusFluent$ExternalNested;
       8: areturn

  public io.fabric8.kubernetes.api.model.autoscaling.v2beta1.MetricStatusFluent$ExternalNested<A> editOrNewExternal();
    Code:
       0: aload_0
       1: aload_0
       2: invokevirtual #25                 // Method getExternal:()Lio/fabric8/kubernetes/api/model/autoscaling/v2beta1/ExternalMetricStatus;
       5: ifnull        15
       8: aload_0
       9: invokevirtual #25                 // Method getExternal:()Lio/fabric8/kubernetes/api/model/autoscaling/v2beta1/ExternalMetricStatus;
      12: goto          25
      15: new           #18                 // class io/fabric8/kubernetes/api/model/autoscaling/v2beta1/ExternalMetricStatusBuilder
      18: dup
      19: invokespecial #27                 // Method io/fabric8/kubernetes/api/model/autoscaling/v2beta1/ExternalMetricStatusBuilder."<init>":()V
      22: invokevirtual #13                 // Method io/fabric8/kubernetes/api/model/autoscaling/v2beta1/ExternalMetricStatusBuilder.build:()Lio/fabric8/kubernetes/api/model/autoscaling/v2beta1/ExternalMetricStatus;
      25: invokevirtual #26                 // Method withNewExternalLike:(Lio/fabric8/kubernetes/api/model/autoscaling/v2beta1/ExternalMetricStatus;)Lio/fabric8/kubernetes/api/model/autoscaling/v2beta1/MetricStatusFluent$ExternalNested;
      28: areturn

  public io.fabric8.kubernetes.api.model.autoscaling.v2beta1.MetricStatusFluent$ExternalNested<A> editOrNewExternalLike(io.fabric8.kubernetes.api.model.autoscaling.v2beta1.ExternalMetricStatus);
    Code:
       0: aload_0
       1: aload_0
       2: invokevirtual #25                 // Method getExternal:()Lio/fabric8/kubernetes/api/model/autoscaling/v2beta1/ExternalMetricStatus;
       5: ifnull        15
       8: aload_0
       9: invokevirtual #25                 // Method getExternal:()Lio/fabric8/kubernetes/api/model/autoscaling/v2beta1/ExternalMetricStatus;
      12: goto          16
      15: aload_1
      16: invokevirtual #26                 // Method withNewExternalLike:(Lio/fabric8/kubernetes/api/model/autoscaling/v2beta1/ExternalMetricStatus;)Lio/fabric8/kubernetes/api/model/autoscaling/v2beta1/MetricStatusFluent$ExternalNested;
      19: areturn

  public io.fabric8.kubernetes.api.model.autoscaling.v2beta1.ObjectMetricStatus getObject();
    Code:
       0: aload_0
       1: getfield      #28                 // Field object:Lio/fabric8/kubernetes/api/model/autoscaling/v2beta1/ObjectMetricStatusBuilder;
       4: ifnull        17
       7: aload_0
       8: getfield      #28                 // Field object:Lio/fabric8/kubernetes/api/model/autoscaling/v2beta1/ObjectMetricStatusBuilder;
      11: invokevirtual #29                 // Method io/fabric8/kubernetes/api/model/autoscaling/v2beta1/ObjectMetricStatusBuilder.build:()Lio/fabric8/kubernetes/api/model/autoscaling/v2beta1/ObjectMetricStatus;
      14: goto          18
      17: aconst_null
      18: areturn

  public io.fabric8.kubernetes.api.model.autoscaling.v2beta1.ObjectMetricStatus buildObject();
    Code:
       0: aload_0
       1: getfield      #28                 // Field object:Lio/fabric8/kubernetes/api/model/autoscaling/v2beta1/ObjectMetricStatusBuilder;
       4: ifnull        17
       7: aload_0
       8: getfield      #28                 // Field object:Lio/fabric8/kubernetes/api/model/autoscaling/v2beta1/ObjectMetricStatusBuilder;
      11: invokevirtual #29                 // Method io/fabric8/kubernetes/api/model/autoscaling/v2beta1/ObjectMetricStatusBuilder.build:()Lio/fabric8/kubernetes/api/model/autoscaling/v2beta1/ObjectMetricStatus;
      14: goto          18
      17: aconst_null
      18: areturn

  public A withObject(io.fabric8.kubernetes.api.model.autoscaling.v2beta1.ObjectMetricStatus);
    Code:
       0: aload_0
       1: getfield      #14                 // Field _visitables:Lio/fabric8/kubernetes/api/builder/VisitableMap;
       4: ldc           #30                 // String object
       6: invokevirtual #16                 // Method io/fabric8/kubernetes/api/builder/VisitableMap.get:(Ljava/lang/Object;)Ljava/util/List;
       9: aload_0
      10: getfield      #28                 // Field object:Lio/fabric8/kubernetes/api/model/autoscaling/v2beta1/ObjectMetricStatusBuilder;
      13: invokeinterface #17,  2           // InterfaceMethod java/util/List.remove:(Ljava/lang/Object;)Z
      18: pop
      19: aload_1
      20: ifnull        54
      23: aload_0
      24: new           #31                 // class io/fabric8/kubernetes/api/model/autoscaling/v2beta1/ObjectMetricStatusBuilder
      27: dup
      28: aload_1
      29: invokespecial #32                 // Method io/fabric8/kubernetes/api/model/autoscaling/v2beta1/ObjectMetricStatusBuilder."<init>":(Lio/fabric8/kubernetes/api/model/autoscaling/v2beta1/ObjectMetricStatus;)V
      32: putfield      #28                 // Field object:Lio/fabric8/kubernetes/api/model/autoscaling/v2beta1/ObjectMetricStatusBuilder;
      35: aload_0
      36: getfield      #14                 // Field _visitables:Lio/fabric8/kubernetes/api/builder/VisitableMap;
      39: ldc           #30                 // String object
      41: invokevirtual #16                 // Method io/fabric8/kubernetes/api/builder/VisitableMap.get:(Ljava/lang/Object;)Ljava/util/List;
      44: aload_0
      45: getfield      #28                 // Field object:Lio/fabric8/kubernetes/api/model/autoscaling/v2beta1/ObjectMetricStatusBuilder;
      48: invokeinterface #20,  2           // InterfaceMethod java/util/List.add:(Ljava/lang/Object;)Z
      53: pop
      54: aload_0
      55: areturn

  public java.lang.Boolean hasObject();
    Code:
       0: aload_0
       1: getfield      #28                 // Field object:Lio/fabric8/kubernetes/api/model/autoscaling/v2beta1/ObjectMetricStatusBuilder;
       4: ifnull        11
       7: iconst_1
       8: goto          12
      11: iconst_0
      12: invokestatic  #21                 // Method java/lang/Boolean.valueOf:(Z)Ljava/lang/Boolean;
      15: areturn

  public io.fabric8.kubernetes.api.model.autoscaling.v2beta1.MetricStatusFluent$ObjectNested<A> withNewObject();
    Code:
       0: new           #33                 // class io/fabric8/kubernetes/api/model/autoscaling/v2beta1/MetricStatusFluentImpl$ObjectNestedImpl
       3: dup
       4: aload_0
       5: invokespecial #34                 // Method io/fabric8/kubernetes/api/model/autoscaling/v2beta1/MetricStatusFluentImpl$ObjectNestedImpl."<init>":(Lio/fabric8/kubernetes/api/model/autoscaling/v2beta1/MetricStatusFluentImpl;)V
       8: areturn

  public io.fabric8.kubernetes.api.model.autoscaling.v2beta1.MetricStatusFluent$ObjectNested<A> withNewObjectLike(io.fabric8.kubernetes.api.model.autoscaling.v2beta1.ObjectMetricStatus);
    Code:
       0: new           #33                 // class io/fabric8/kubernetes/api/model/autoscaling/v2beta1/MetricStatusFluentImpl$ObjectNestedImpl
       3: dup
       4: aload_0
       5: aload_1
       6: invokespecial #35                 // Method io/fabric8/kubernetes/api/model/autoscaling/v2beta1/MetricStatusFluentImpl$ObjectNestedImpl."<init>":(Lio/fabric8/kubernetes/api/model/autoscaling/v2beta1/MetricStatusFluentImpl;Lio/fabric8/kubernetes/api/model/autoscaling/v2beta1/ObjectMetricStatus;)V
       9: areturn

  public io.fabric8.kubernetes.api.model.autoscaling.v2beta1.MetricStatusFluent$ObjectNested<A> editObject();
    Code:
       0: aload_0
       1: aload_0
       2: invokevirtual #36                 // Method getObject:()Lio/fabric8/kubernetes/api/model/autoscaling/v2beta1/ObjectMetricStatus;
       5: invokevirtual #37                 // Method withNewObjectLike:(Lio/fabric8/kubernetes/api/model/autoscaling/v2beta1/ObjectMetricStatus;)Lio/fabric8/kubernetes/api/model/autoscaling/v2beta1/MetricStatusFluent$ObjectNested;
       8: areturn

  public io.fabric8.kubernetes.api.model.autoscaling.v2beta1.MetricStatusFluent$ObjectNested<A> editOrNewObject();
    Code:
       0: aload_0
       1: aload_0
       2: invokevirtual #36                 // Method getObject:()Lio/fabric8/kubernetes/api/model/autoscaling/v2beta1/ObjectMetricStatus;
       5: ifnull        15
       8: aload_0
       9: invokevirtual #36                 // Method getObject:()Lio/fabric8/kubernetes/api/model/autoscaling/v2beta1/ObjectMetricStatus;
      12: goto          25
      15: new           #31                 // class io/fabric8/kubernetes/api/model/autoscaling/v2beta1/ObjectMetricStatusBuilder
      18: dup
      19: invokespecial #38                 // Method io/fabric8/kubernetes/api/model/autoscaling/v2beta1/ObjectMetricStatusBuilder."<init>":()V
      22: invokevirtual #29                 // Method io/fabric8/kubernetes/api/model/autoscaling/v2beta1/ObjectMetricStatusBuilder.build:()Lio/fabric8/kubernetes/api/model/autoscaling/v2beta1/ObjectMetricStatus;
      25: invokevirtual #37                 // Method withNewObjectLike:(Lio/fabric8/kubernetes/api/model/autoscaling/v2beta1/ObjectMetricStatus;)Lio/fabric8/kubernetes/api/model/autoscaling/v2beta1/MetricStatusFluent$ObjectNested;
      28: areturn

  public io.fabric8.kubernetes.api.model.autoscaling.v2beta1.MetricStatusFluent$ObjectNested<A> editOrNewObjectLike(io.fabric8.kubernetes.api.model.autoscaling.v2beta1.ObjectMetricStatus);
    Code:
       0: aload_0
       1: aload_0
       2: invokevirtual #36                 // Method getObject:()Lio/fabric8/kubernetes/api/model/autoscaling/v2beta1/ObjectMetricStatus;
       5: ifnull        15
       8: aload_0
       9: invokevirtual #36                 // Method getObject:()Lio/fabric8/kubernetes/api/model/autoscaling/v2beta1/ObjectMetricStatus;
      12: goto          16
      15: aload_1
      16: invokevirtual #37                 // Method withNewObjectLike:(Lio/fabric8/kubernetes/api/model/autoscaling/v2beta1/ObjectMetricStatus;)Lio/fabric8/kubernetes/api/model/autoscaling/v2beta1/MetricStatusFluent$ObjectNested;
      19: areturn

  public io.fabric8.kubernetes.api.model.autoscaling.v2beta1.PodsMetricStatus getPods();
    Code:
       0: aload_0
       1: getfield      #39                 // Field pods:Lio/fabric8/kubernetes/api/model/autoscaling/v2beta1/PodsMetricStatusBuilder;
       4: ifnull        17
       7: aload_0
       8: getfield      #39                 // Field pods:Lio/fabric8/kubernetes/api/model/autoscaling/v2beta1/PodsMetricStatusBuilder;
      11: invokevirtual #40                 // Method io/fabric8/kubernetes/api/model/autoscaling/v2beta1/PodsMetricStatusBuilder.build:()Lio/fabric8/kubernetes/api/model/autoscaling/v2beta1/PodsMetricStatus;
      14: goto          18
      17: aconst_null
      18: areturn

  public io.fabric8.kubernetes.api.model.autoscaling.v2beta1.PodsMetricStatus buildPods();
    Code:
       0: aload_0
       1: getfield      #39                 // Field pods:Lio/fabric8/kubernetes/api/model/autoscaling/v2beta1/PodsMetricStatusBuilder;
       4: ifnull        17
       7: aload_0
       8: getfield      #39                 // Field pods:Lio/fabric8/kubernetes/api/model/autoscaling/v2beta1/PodsMetricStatusBuilder;
      11: invokevirtual #40                 // Method io/fabric8/kubernetes/api/model/autoscaling/v2beta1/PodsMetricStatusBuilder.build:()Lio/fabric8/kubernetes/api/model/autoscaling/v2beta1/PodsMetricStatus;
      14: goto          18
      17: aconst_null
      18: areturn

  public A withPods(io.fabric8.kubernetes.api.model.autoscaling.v2beta1.PodsMetricStatus);
    Code:
       0: aload_0
       1: getfield      #14                 // Field _visitables:Lio/fabric8/kubernetes/api/builder/VisitableMap;
       4: ldc           #41                 // String pods
       6: invokevirtual #16                 // Method io/fabric8/kubernetes/api/builder/VisitableMap.get:(Ljava/lang/Object;)Ljava/util/List;
       9: aload_0
      10: getfield      #39                 // Field pods:Lio/fabric8/kubernetes/api/model/autoscaling/v2beta1/PodsMetricStatusBuilder;
      13: invokeinterface #17,  2           // InterfaceMethod java/util/List.remove:(Ljava/lang/Object;)Z
      18: pop
      19: aload_1
      20: ifnull        54
      23: aload_0
      24: new           #42                 // class io/fabric8/kubernetes/api/model/autoscaling/v2beta1/PodsMetricStatusBuilder
      27: dup
      28: aload_1
      29: invokespecial #43                 // Method io/fabric8/kubernetes/api/model/autoscaling/v2beta1/PodsMetricStatusBuilder."<init>":(Lio/fabric8/kubernetes/api/model/autoscaling/v2beta1/PodsMetricStatus;)V
      32: putfield      #39                 // Field pods:Lio/fabric8/kubernetes/api/model/autoscaling/v2beta1/PodsMetricStatusBuilder;
      35: aload_0
      36: getfield      #14                 // Field _visitables:Lio/fabric8/kubernetes/api/builder/VisitableMap;
      39: ldc           #41                 // String pods
      41: invokevirtual #16                 // Method io/fabric8/kubernetes/api/builder/VisitableMap.get:(Ljava/lang/Object;)Ljava/util/List;
      44: aload_0
      45: getfield      #39                 // Field pods:Lio/fabric8/kubernetes/api/model/autoscaling/v2beta1/PodsMetricStatusBuilder;
      48: invokeinterface #20,  2           // InterfaceMethod java/util/List.add:(Ljava/lang/Object;)Z
      53: pop
      54: aload_0
      55: areturn

  public java.lang.Boolean hasPods();
    Code:
       0: aload_0
       1: getfield      #39                 // Field pods:Lio/fabric8/kubernetes/api/model/autoscaling/v2beta1/PodsMetricStatusBuilder;
       4: ifnull        11
       7: iconst_1
       8: goto          12
      11: iconst_0
      12: invokestatic  #21                 // Method java/lang/Boolean.valueOf:(Z)Ljava/lang/Boolean;
      15: areturn

  public io.fabric8.kubernetes.api.model.autoscaling.v2beta1.MetricStatusFluent$PodsNested<A> withNewPods();
    Code:
       0: new           #44                 // class io/fabric8/kubernetes/api/model/autoscaling/v2beta1/MetricStatusFluentImpl$PodsNestedImpl
       3: dup
       4: aload_0
       5: invokespecial #45                 // Method io/fabric8/kubernetes/api/model/autoscaling/v2beta1/MetricStatusFluentImpl$PodsNestedImpl."<init>":(Lio/fabric8/kubernetes/api/model/autoscaling/v2beta1/MetricStatusFluentImpl;)V
       8: areturn

  public io.fabric8.kubernetes.api.model.autoscaling.v2beta1.MetricStatusFluent$PodsNested<A> withNewPodsLike(io.fabric8.kubernetes.api.model.autoscaling.v2beta1.PodsMetricStatus);
    Code:
       0: new           #44                 // class io/fabric8/kubernetes/api/model/autoscaling/v2beta1/MetricStatusFluentImpl$PodsNestedImpl
       3: dup
       4: aload_0
       5: aload_1
       6: invokespecial #46                 // Method io/fabric8/kubernetes/api/model/autoscaling/v2beta1/MetricStatusFluentImpl$PodsNestedImpl."<init>":(Lio/fabric8/kubernetes/api/model/autoscaling/v2beta1/MetricStatusFluentImpl;Lio/fabric8/kubernetes/api/model/autoscaling/v2beta1/PodsMetricStatus;)V
       9: areturn

  public io.fabric8.kubernetes.api.model.autoscaling.v2beta1.MetricStatusFluent$PodsNested<A> editPods();
    Code:
       0: aload_0
       1: aload_0
       2: invokevirtual #47                 // Method getPods:()Lio/fabric8/kubernetes/api/model/autoscaling/v2beta1/PodsMetricStatus;
       5: invokevirtual #48                 // Method withNewPodsLike:(Lio/fabric8/kubernetes/api/model/autoscaling/v2beta1/PodsMetricStatus;)Lio/fabric8/kubernetes/api/model/autoscaling/v2beta1/MetricStatusFluent$PodsNested;
       8: areturn

  public io.fabric8.kubernetes.api.model.autoscaling.v2beta1.MetricStatusFluent$PodsNested<A> editOrNewPods();
    Code:
       0: aload_0
       1: aload_0
       2: invokevirtual #47                 // Method getPods:()Lio/fabric8/kubernetes/api/model/autoscaling/v2beta1/PodsMetricStatus;
       5: ifnull        15
       8: aload_0
       9: invokevirtual #47                 // Method getPods:()Lio/fabric8/kubernetes/api/model/autoscaling/v2beta1/PodsMetricStatus;
      12: goto          25
      15: new           #42                 // class io/fabric8/kubernetes/api/model/autoscaling/v2beta1/PodsMetricStatusBuilder
      18: dup
      19: invokespecial #49                 // Method io/fabric8/kubernetes/api/model/autoscaling/v2beta1/PodsMetricStatusBuilder."<init>":()V
      22: invokevirtual #40                 // Method io/fabric8/kubernetes/api/model/autoscaling/v2beta1/PodsMetricStatusBuilder.build:()Lio/fabric8/kubernetes/api/model/autoscaling/v2beta1/PodsMetricStatus;
      25: invokevirtual #48                 // Method withNewPodsLike:(Lio/fabric8/kubernetes/api/model/autoscaling/v2beta1/PodsMetricStatus;)Lio/fabric8/kubernetes/api/model/autoscaling/v2beta1/MetricStatusFluent$PodsNested;
      28: areturn

  public io.fabric8.kubernetes.api.model.autoscaling.v2beta1.MetricStatusFluent$PodsNested<A> editOrNewPodsLike(io.fabric8.kubernetes.api.model.autoscaling.v2beta1.PodsMetricStatus);
    Code:
       0: aload_0
       1: aload_0
       2: invokevirtual #47                 // Method getPods:()Lio/fabric8/kubernetes/api/model/autoscaling/v2beta1/PodsMetricStatus;
       5: ifnull        15
       8: aload_0
       9: invokevirtual #47                 // Method getPods:()Lio/fabric8/kubernetes/api/model/autoscaling/v2beta1/PodsMetricStatus;
      12: goto          16
      15: aload_1
      16: invokevirtual #48                 // Method withNewPodsLike:(Lio/fabric8/kubernetes/api/model/autoscaling/v2beta1/PodsMetricStatus;)Lio/fabric8/kubernetes/api/model/autoscaling/v2beta1/MetricStatusFluent$PodsNested;
      19: areturn

  public io.fabric8.kubernetes.api.model.autoscaling.v2beta1.ResourceMetricStatus getResource();
    Code:
       0: aload_0
       1: getfield      #50                 // Field resource:Lio/fabric8/kubernetes/api/model/autoscaling/v2beta1/ResourceMetricStatusBuilder;
       4: ifnull        17
       7: aload_0
       8: getfield      #50                 // Field resource:Lio/fabric8/kubernetes/api/model/autoscaling/v2beta1/ResourceMetricStatusBuilder;
      11: invokevirtual #51                 // Method io/fabric8/kubernetes/api/model/autoscaling/v2beta1/ResourceMetricStatusBuilder.build:()Lio/fabric8/kubernetes/api/model/autoscaling/v2beta1/ResourceMetricStatus;
      14: goto          18
      17: aconst_null
      18: areturn

  public io.fabric8.kubernetes.api.model.autoscaling.v2beta1.ResourceMetricStatus buildResource();
    Code:
       0: aload_0
       1: getfield      #50                 // Field resource:Lio/fabric8/kubernetes/api/model/autoscaling/v2beta1/ResourceMetricStatusBuilder;
       4: ifnull        17
       7: aload_0
       8: getfield      #50                 // Field resource:Lio/fabric8/kubernetes/api/model/autoscaling/v2beta1/ResourceMetricStatusBuilder;
      11: invokevirtual #51                 // Method io/fabric8/kubernetes/api/model/autoscaling/v2beta1/ResourceMetricStatusBuilder.build:()Lio/fabric8/kubernetes/api/model/autoscaling/v2beta1/ResourceMetricStatus;
      14: goto          18
      17: aconst_null
      18: areturn

  public A withResource(io.fabric8.kubernetes.api.model.autoscaling.v2beta1.ResourceMetricStatus);
    Code:
       0: aload_0
       1: getfield      #14                 // Field _visitables:Lio/fabric8/kubernetes/api/builder/VisitableMap;
       4: ldc           #52                 // String resource
       6: invokevirtual #16                 // Method io/fabric8/kubernetes/api/builder/VisitableMap.get:(Ljava/lang/Object;)Ljava/util/List;
       9: aload_0
      10: getfield      #50                 // Field resource:Lio/fabric8/kubernetes/api/model/autoscaling/v2beta1/ResourceMetricStatusBuilder;
      13: invokeinterface #17,  2           // InterfaceMethod java/util/List.remove:(Ljava/lang/Object;)Z
      18: pop
      19: aload_1
      20: ifnull        54
      23: aload_0
      24: new           #53                 // class io/fabric8/kubernetes/api/model/autoscaling/v2beta1/ResourceMetricStatusBuilder
      27: dup
      28: aload_1
      29: invokespecial #54                 // Method io/fabric8/kubernetes/api/model/autoscaling/v2beta1/ResourceMetricStatusBuilder."<init>":(Lio/fabric8/kubernetes/api/model/autoscaling/v2beta1/ResourceMetricStatus;)V
      32: putfield      #50                 // Field resource:Lio/fabric8/kubernetes/api/model/autoscaling/v2beta1/ResourceMetricStatusBuilder;
      35: aload_0
      36: getfield      #14                 // Field _visitables:Lio/fabric8/kubernetes/api/builder/VisitableMap;
      39: ldc           #52                 // String resource
      41: invokevirtual #16                 // Method io/fabric8/kubernetes/api/builder/VisitableMap.get:(Ljava/lang/Object;)Ljava/util/List;
      44: aload_0
      45: getfield      #50                 // Field resource:Lio/fabric8/kubernetes/api/model/autoscaling/v2beta1/ResourceMetricStatusBuilder;
      48: invokeinterface #20,  2           // InterfaceMethod java/util/List.add:(Ljava/lang/Object;)Z
      53: pop
      54: aload_0
      55: areturn

  public java.lang.Boolean hasResource();
    Code:
       0: aload_0
       1: getfield      #50                 // Field resource:Lio/fabric8/kubernetes/api/model/autoscaling/v2beta1/ResourceMetricStatusBuilder;
       4: ifnull        11
       7: iconst_1
       8: goto          12
      11: iconst_0
      12: invokestatic  #21                 // Method java/lang/Boolean.valueOf:(Z)Ljava/lang/Boolean;
      15: areturn

  public io.fabric8.kubernetes.api.model.autoscaling.v2beta1.MetricStatusFluent$ResourceNested<A> withNewResource();
    Code:
       0: new           #55                 // class io/fabric8/kubernetes/api/model/autoscaling/v2beta1/MetricStatusFluentImpl$ResourceNestedImpl
       3: dup
       4: aload_0
       5: invokespecial #56                 // Method io/fabric8/kubernetes/api/model/autoscaling/v2beta1/MetricStatusFluentImpl$ResourceNestedImpl."<init>":(Lio/fabric8/kubernetes/api/model/autoscaling/v2beta1/MetricStatusFluentImpl;)V
       8: areturn

  public io.fabric8.kubernetes.api.model.autoscaling.v2beta1.MetricStatusFluent$ResourceNested<A> withNewResourceLike(io.fabric8.kubernetes.api.model.autoscaling.v2beta1.ResourceMetricStatus);
    Code:
       0: new           #55                 // class io/fabric8/kubernetes/api/model/autoscaling/v2beta1/MetricStatusFluentImpl$ResourceNestedImpl
       3: dup
       4: aload_0
       5: aload_1
       6: invokespecial #57                 // Method io/fabric8/kubernetes/api/model/autoscaling/v2beta1/MetricStatusFluentImpl$ResourceNestedImpl."<init>":(Lio/fabric8/kubernetes/api/model/autoscaling/v2beta1/MetricStatusFluentImpl;Lio/fabric8/kubernetes/api/model/autoscaling/v2beta1/ResourceMetricStatus;)V
       9: areturn

  public io.fabric8.kubernetes.api.model.autoscaling.v2beta1.MetricStatusFluent$ResourceNested<A> editResource();
    Code:
       0: aload_0
       1: aload_0
       2: invokevirtual #58                 // Method getResource:()Lio/fabric8/kubernetes/api/model/autoscaling/v2beta1/ResourceMetricStatus;
       5: invokevirtual #59                 // Method withNewResourceLike:(Lio/fabric8/kubernetes/api/model/autoscaling/v2beta1/ResourceMetricStatus;)Lio/fabric8/kubernetes/api/model/autoscaling/v2beta1/MetricStatusFluent$ResourceNested;
       8: areturn

  public io.fabric8.kubernetes.api.model.autoscaling.v2beta1.MetricStatusFluent$ResourceNested<A> editOrNewResource();
    Code:
       0: aload_0
       1: aload_0
       2: invokevirtual #58                 // Method getResource:()Lio/fabric8/kubernetes/api/model/autoscaling/v2beta1/ResourceMetricStatus;
       5: ifnull        15
       8: aload_0
       9: invokevirtual #58                 // Method getResource:()Lio/fabric8/kubernetes/api/model/autoscaling/v2beta1/ResourceMetricStatus;
      12: goto          25
      15: new           #53                 // class io/fabric8/kubernetes/api/model/autoscaling/v2beta1/ResourceMetricStatusBuilder
      18: dup
      19: invokespecial #60                 // Method io/fabric8/kubernetes/api/model/autoscaling/v2beta1/ResourceMetricStatusBuilder."<init>":()V
      22: invokevirtual #51                 // Method io/fabric8/kubernetes/api/model/autoscaling/v2beta1/ResourceMetricStatusBuilder.build:()Lio/fabric8/kubernetes/api/model/autoscaling/v2beta1/ResourceMetricStatus;
      25: invokevirtual #59                 // Method withNewResourceLike:(Lio/fabric8/kubernetes/api/model/autoscaling/v2beta1/ResourceMetricStatus;)Lio/fabric8/kubernetes/api/model/autoscaling/v2beta1/MetricStatusFluent$ResourceNested;
      28: areturn

  public io.fabric8.kubernetes.api.model.autoscaling.v2beta1.MetricStatusFluent$ResourceNested<A> editOrNewResourceLike(io.fabric8.kubernetes.api.model.autoscaling.v2beta1.ResourceMetricStatus);
    Code:
       0: aload_0
       1: aload_0
       2: invokevirtual #58                 // Method getResource:()Lio/fabric8/kubernetes/api/model/autoscaling/v2beta1/ResourceMetricStatus;
       5: ifnull        15
       8: aload_0
       9: invokevirtual #58                 // Method getResource:()Lio/fabric8/kubernetes/api/model/autoscaling/v2beta1/ResourceMetricStatus;
      12: goto          16
      15: aload_1
      16: invokevirtual #59                 // Method withNewResourceLike:(Lio/fabric8/kubernetes/api/model/autoscaling/v2beta1/ResourceMetricStatus;)Lio/fabric8/kubernetes/api/model/autoscaling/v2beta1/MetricStatusFluent$ResourceNested;
      19: areturn

  public java.lang.String getType();
    Code:
       0: aload_0
       1: getfield      #61                 // Field type:Ljava/lang/String;
       4: areturn

  public A withType(java.lang.String);
    Code:
       0: aload_0
       1: aload_1
       2: putfield      #61                 // Field type:Ljava/lang/String;
       5: aload_0
       6: areturn

  public java.lang.Boolean hasType();
    Code:
       0: aload_0
       1: getfield      #61                 // Field type:Ljava/lang/String;
       4: ifnull        11
       7: iconst_1
       8: goto          12
      11: iconst_0
      12: invokestatic  #21                 // Method java/lang/Boolean.valueOf:(Z)Ljava/lang/Boolean;
      15: areturn

  public A withNewType(java.lang.String);
    Code:
       0: aload_0
       1: new           #62                 // class java/lang/String
       4: dup
       5: aload_1
       6: invokespecial #63                 // Method java/lang/String."<init>":(Ljava/lang/String;)V
       9: invokevirtual #11                 // Method withType:(Ljava/lang/String;)Lio/fabric8/kubernetes/api/model/autoscaling/v2beta1/MetricStatusFluent;
      12: areturn

  public A withNewType(java.lang.StringBuilder);
    Code:
       0: aload_0
       1: new           #62                 // class java/lang/String
       4: dup
       5: aload_1
       6: invokespecial #64                 // Method java/lang/String."<init>":(Ljava/lang/StringBuilder;)V
       9: invokevirtual #11                 // Method withType:(Ljava/lang/String;)Lio/fabric8/kubernetes/api/model/autoscaling/v2beta1/MetricStatusFluent;
      12: areturn

  public A withNewType(java.lang.StringBuffer);
    Code:
       0: aload_0
       1: new           #62                 // class java/lang/String
       4: dup
       5: aload_1
       6: invokespecial #65                 // Method java/lang/String."<init>":(Ljava/lang/StringBuffer;)V
       9: invokevirtual #11                 // Method withType:(Ljava/lang/String;)Lio/fabric8/kubernetes/api/model/autoscaling/v2beta1/MetricStatusFluent;
      12: areturn

  public boolean equals(java.lang.Object);
    Code:
       0: aload_0
       1: aload_1
       2: if_acmpne     7
       5: iconst_1
       6: ireturn
       7: aload_1
       8: ifnull        22
      11: aload_0
      12: invokevirtual #66                 // Method java/lang/Object.getClass:()Ljava/lang/Class;
      15: aload_1
      16: invokevirtual #66                 // Method java/lang/Object.getClass:()Ljava/lang/Class;
      19: if_acmpeq     24
      22: iconst_0
      23: ireturn
      24: aload_1
      25: checkcast     #67                 // class io/fabric8/kubernetes/api/model/autoscaling/v2beta1/MetricStatusFluentImpl
      28: astore_2
      29: aload_0
      30: getfield      #12                 // Field external:Lio/fabric8/kubernetes/api/model/autoscaling/v2beta1/ExternalMetricStatusBuilder;
      33: ifnull        53
      36: aload_0
      37: getfield      #12                 // Field external:Lio/fabric8/kubernetes/api/model/autoscaling/v2beta1/ExternalMetricStatusBuilder;
      40: aload_2
      41: getfield      #12                 // Field external:Lio/fabric8/kubernetes/api/model/autoscaling/v2beta1/ExternalMetricStatusBuilder;
      44: invokevirtual #68                 // Method io/fabric8/kubernetes/api/model/autoscaling/v2beta1/ExternalMetricStatusBuilder.equals:(Ljava/lang/Object;)Z
      47: ifne          62
      50: goto          60
      53: aload_2
      54: getfield      #12                 // Field external:Lio/fabric8/kubernetes/api/model/autoscaling/v2beta1/ExternalMetricStatusBuilder;
      57: ifnull        62
      60: iconst_0
      61: ireturn
      62: aload_0
      63: getfield      #28                 // Field object:Lio/fabric8/kubernetes/api/model/autoscaling/v2beta1/ObjectMetricStatusBuilder;
      66: ifnull        86
      69: aload_0
      70: getfield      #28                 // Field object:Lio/fabric8/kubernetes/api/model/autoscaling/v2beta1/ObjectMetricStatusBuilder;
      73: aload_2
      74: getfield      #28                 // Field object:Lio/fabric8/kubernetes/api/model/autoscaling/v2beta1/ObjectMetricStatusBuilder;
      77: invokevirtual #69                 // Method io/fabric8/kubernetes/api/model/autoscaling/v2beta1/ObjectMetricStatusBuilder.equals:(Ljava/lang/Object;)Z
      80: ifne          95
      83: goto          93
      86: aload_2
      87: getfield      #28                 // Field object:Lio/fabric8/kubernetes/api/model/autoscaling/v2beta1/ObjectMetricStatusBuilder;
      90: ifnull        95
      93: iconst_0
      94: ireturn
      95: aload_0
      96: getfield      #39                 // Field pods:Lio/fabric8/kubernetes/api/model/autoscaling/v2beta1/PodsMetricStatusBuilder;
      99: ifnull        119
     102: aload_0
     103: getfield      #39                 // Field pods:Lio/fabric8/kubernetes/api/model/autoscaling/v2beta1/PodsMetricStatusBuilder;
     106: aload_2
     107: getfield      #39                 // Field pods:Lio/fabric8/kubernetes/api/model/autoscaling/v2beta1/PodsMetricStatusBuilder;
     110: invokevirtual #70                 // Method io/fabric8/kubernetes/api/model/autoscaling/v2beta1/PodsMetricStatusBuilder.equals:(Ljava/lang/Object;)Z
     113: ifne          128
     116: goto          126
     119: aload_2
     120: getfield      #39                 // Field pods:Lio/fabric8/kubernetes/api/model/autoscaling/v2beta1/PodsMetricStatusBuilder;
     123: ifnull        128
     126: iconst_0
     127: ireturn
     128: aload_0
     129: getfield      #50                 // Field resource:Lio/fabric8/kubernetes/api/model/autoscaling/v2beta1/ResourceMetricStatusBuilder;
     132: ifnull        152
     135: aload_0
     136: getfield      #50                 // Field resource:Lio/fabric8/kubernetes/api/model/autoscaling/v2beta1/ResourceMetricStatusBuilder;
     139: aload_2
     140: getfield      #50                 // Field resource:Lio/fabric8/kubernetes/api/model/autoscaling/v2beta1/ResourceMetricStatusBuilder;
     143: invokevirtual #71                 // Method io/fabric8/kubernetes/api/model/autoscaling/v2beta1/ResourceMetricStatusBuilder.equals:(Ljava/lang/Object;)Z
     146: ifne          161
     149: goto          159
     152: aload_2
     153: getfield      #50                 // Field resource:Lio/fabric8/kubernetes/api/model/autoscaling/v2beta1/ResourceMetricStatusBuilder;
     156: ifnull        161
     159: iconst_0
     160: ireturn
     161: aload_0
     162: getfield      #61                 // Field type:Ljava/lang/String;
     165: ifnull        185
     168: aload_0
     169: getfield      #61                 // Field type:Ljava/lang/String;
     172: aload_2
     173: getfield      #61                 // Field type:Ljava/lang/String;
     176: invokevirtual #72                 // Method java/lang/String.equals:(Ljava/lang/Object;)Z
     179: ifne          194
     182: goto          192
     185: aload_2
     186: getfield      #61                 // Field type:Ljava/lang/String;
     189: ifnull        194
     192: iconst_0
     193: ireturn
     194: iconst_1
     195: ireturn
}
