Compiled from "PositionalParameterRegistration.java"
public class org.hibernate.procedure.internal.PositionalParameterRegistration<T> extends org.hibernate.procedure.internal.AbstractParameterRegistrationImpl<T> {
  org.hibernate.procedure.internal.PositionalParameterRegistration(org.hibernate.procedure.internal.ProcedureCallImpl, java.lang.Integer, javax.persistence.ParameterMode, java.lang.Class<T>);
    Code:
       0: aload_0
       1: aload_1
       2: aload_2
       3: aload_3
       4: aload         4
       6: invokespecial #1                  // Method org/hibernate/procedure/internal/AbstractParameterRegistrationImpl."<init>":(Lorg/hibernate/procedure/internal/ProcedureCallImpl;Ljava/lang/Integer;Ljavax/persistence/ParameterMode;Ljava/lang/Class;)V
       9: return

  org.hibernate.procedure.internal.PositionalParameterRegistration(org.hibernate.procedure.internal.ProcedureCallImpl, java.lang.Integer, javax.persistence.ParameterMode, java.lang.Class<T>, org.hibernate.type.Type);
    Code:
       0: aload_0
       1: aload_1
       2: aload_2
       3: aload_3
       4: aload         4
       6: aload         5
       8: invokespecial #2                  // Method org/hibernate/procedure/internal/AbstractParameterRegistrationImpl."<init>":(Lorg/hibernate/procedure/internal/ProcedureCallImpl;Ljava/lang/Integer;Ljavax/persistence/ParameterMode;Ljava/lang/Class;Lorg/hibernate/type/Type;)V
      11: return
}
