Compiled from "HttpRequestFutureTask.java"
public class org.apache.http.impl.client.HttpRequestFutureTask<V> extends java.util.concurrent.FutureTask<V> {
  private final org.apache.http.client.methods.HttpUriRequest request;

  private final org.apache.http.impl.client.HttpRequestTaskCallable<V> callable;

  public org.apache.http.impl.client.HttpRequestFutureTask(org.apache.http.client.methods.HttpUriRequest, org.apache.http.impl.client.HttpRequestTaskCallable<V>);
    Code:
       0: aload_0
       1: aload_2
       2: invokespecial #1                  // Method java/util/concurrent/FutureTask."<init>":(Ljava/util/concurrent/Callable;)V
       5: aload_0
       6: aload_1
       7: putfield      #2                  // Field request:Lorg/apache/http/client/methods/HttpUriRequest;
      10: aload_0
      11: aload_2
      12: putfield      #3                  // Field callable:Lorg/apache/http/impl/client/HttpRequestTaskCallable;
      15: return

  public boolean cancel(boolean);
    Code:
       0: aload_0
       1: getfield      #3                  // Field callable:Lorg/apache/http/impl/client/HttpRequestTaskCallable;
       4: invokevirtual #4                  // Method org/apache/http/impl/client/HttpRequestTaskCallable.cancel:()V
       7: iload_1
       8: ifeq          20
      11: aload_0
      12: getfield      #2                  // Field request:Lorg/apache/http/client/methods/HttpUriRequest;
      15: invokeinterface #5,  1            // InterfaceMethod org/apache/http/client/methods/HttpUriRequest.abort:()V
      20: aload_0
      21: iload_1
      22: invokespecial #6                  // Method java/util/concurrent/FutureTask.cancel:(Z)Z
      25: ireturn

  public long scheduledTime();
    Code:
       0: aload_0
       1: getfield      #3                  // Field callable:Lorg/apache/http/impl/client/HttpRequestTaskCallable;
       4: invokevirtual #7                  // Method org/apache/http/impl/client/HttpRequestTaskCallable.getScheduled:()J
       7: lreturn

  public long startedTime();
    Code:
       0: aload_0
       1: getfield      #3                  // Field callable:Lorg/apache/http/impl/client/HttpRequestTaskCallable;
       4: invokevirtual #8                  // Method org/apache/http/impl/client/HttpRequestTaskCallable.getStarted:()J
       7: lreturn

  public long endedTime();
    Code:
       0: aload_0
       1: invokevirtual #9                  // Method isDone:()Z
       4: ifeq          15
       7: aload_0
       8: getfield      #3                  // Field callable:Lorg/apache/http/impl/client/HttpRequestTaskCallable;
      11: invokevirtual #10                 // Method org/apache/http/impl/client/HttpRequestTaskCallable.getEnded:()J
      14: lreturn
      15: new           #11                 // class java/lang/IllegalStateException
      18: dup
      19: ldc           #12                 // String Task is not done yet
      21: invokespecial #13                 // Method java/lang/IllegalStateException."<init>":(Ljava/lang/String;)V
      24: athrow

  public long requestDuration();
    Code:
       0: aload_0
       1: invokevirtual #9                  // Method isDone:()Z
       4: ifeq          17
       7: aload_0
       8: invokevirtual #14                 // Method endedTime:()J
      11: aload_0
      12: invokevirtual #15                 // Method startedTime:()J
      15: lsub
      16: lreturn
      17: new           #11                 // class java/lang/IllegalStateException
      20: dup
      21: ldc           #12                 // String Task is not done yet
      23: invokespecial #13                 // Method java/lang/IllegalStateException."<init>":(Ljava/lang/String;)V
      26: athrow

  public long taskDuration();
    Code:
       0: aload_0
       1: invokevirtual #9                  // Method isDone:()Z
       4: ifeq          17
       7: aload_0
       8: invokevirtual #14                 // Method endedTime:()J
      11: aload_0
      12: invokevirtual #16                 // Method scheduledTime:()J
      15: lsub
      16: lreturn
      17: new           #11                 // class java/lang/IllegalStateException
      20: dup
      21: ldc           #12                 // String Task is not done yet
      23: invokespecial #13                 // Method java/lang/IllegalStateException."<init>":(Ljava/lang/String;)V
      26: athrow

  public java.lang.String toString();
    Code:
       0: aload_0
       1: getfield      #2                  // Field request:Lorg/apache/http/client/methods/HttpUriRequest;
       4: invokeinterface #17,  1           // InterfaceMethod org/apache/http/client/methods/HttpUriRequest.getRequestLine:()Lorg/apache/http/RequestLine;
       9: invokeinterface #18,  1           // InterfaceMethod org/apache/http/RequestLine.getUri:()Ljava/lang/String;
      14: areturn
}
