Compiled from "AbstractADBDataSource.java"
public abstract class org.apache.axis2.databinding.AbstractADBDataSource extends org.apache.axiom.om.ds.AbstractPushOMDataSource implements org.apache.axiom.om.QNameAwareOMDataSource {
  protected javax.xml.namespace.QName parentQName;

  public org.apache.axis2.databinding.AbstractADBDataSource(javax.xml.namespace.QName);
    Code:
       0: aload_0
       1: invokespecial #1                  // Method org/apache/axiom/om/ds/AbstractPushOMDataSource."<init>":()V
       4: aload_0
       5: aload_1
       6: putfield      #2                  // Field parentQName:Ljavax/xml/namespace/QName;
       9: return

  public final java.lang.String getLocalName();
    Code:
       0: aload_0
       1: getfield      #2                  // Field parentQName:Ljavax/xml/namespace/QName;
       4: invokevirtual #3                  // Method javax/xml/namespace/QName.getLocalPart:()Ljava/lang/String;
       7: areturn

  public final java.lang.String getNamespaceURI();
    Code:
       0: aload_0
       1: getfield      #2                  // Field parentQName:Ljavax/xml/namespace/QName;
       4: invokevirtual #4                  // Method javax/xml/namespace/QName.getNamespaceURI:()Ljava/lang/String;
       7: areturn

  public final java.lang.String getPrefix();
    Code:
       0: aload_0
       1: getfield      #2                  // Field parentQName:Ljavax/xml/namespace/QName;
       4: invokevirtual #5                  // Method javax/xml/namespace/QName.getPrefix:()Ljava/lang/String;
       7: areturn

  public boolean isDestructiveWrite();
    Code:
       0: iconst_0
       1: ireturn

  public org.apache.axiom.om.OMDataSourceExt copy();
    Code:
       0: aconst_null
       1: areturn
}
