Compiled from "ADBException.java"
public class org.apache.axis2.databinding.ADBException extends org.apache.axis2.databinding.DataBindException {
  public org.apache.axis2.databinding.ADBException();
    Code:
       0: aload_0
       1: invokespecial #1                  // Method org/apache/axis2/databinding/DataBindException."<init>":()V
       4: return

  public org.apache.axis2.databinding.ADBException(java.lang.String);
    Code:
       0: aload_0
       1: aload_1
       2: invokespecial #2                  // Method org/apache/axis2/databinding/DataBindException."<init>":(Ljava/lang/String;)V
       5: return

  public org.apache.axis2.databinding.ADBException(java.lang.Throwable);
    Code:
       0: aload_0
       1: aload_1
       2: invokespecial #3                  // Method org/apache/axis2/databinding/DataBindException."<init>":(Ljava/lang/Throwable;)V
       5: return

  public org.apache.axis2.databinding.ADBException(java.lang.String, java.lang.Throwable);
    Code:
       0: aload_0
       1: aload_1
       2: aload_2
       3: invokespecial #4                  // Method org/apache/axis2/databinding/DataBindException."<init>":(Ljava/lang/String;Ljava/lang/Throwable;)V
       6: return

  public org.apache.axis2.databinding.ADBException(java.lang.String, javax.xml.stream.Location, java.lang.Throwable);
    Code:
       0: aload_0
       1: aload_1
       2: aload_2
       3: aload_3
       4: invokespecial #5                  // Method org/apache/axis2/databinding/DataBindException."<init>":(Ljava/lang/String;Ljavax/xml/stream/Location;Ljava/lang/Throwable;)V
       7: return

  public org.apache.axis2.databinding.ADBException(java.lang.String, javax.xml.stream.Location);
    Code:
       0: aload_0
       1: aload_1
       2: aload_2
       3: invokespecial #6                  // Method org/apache/axis2/databinding/DataBindException."<init>":(Ljava/lang/String;Ljavax/xml/stream/Location;)V
       6: return
}
