Compiled from "InProcessTransport.java"
class io.grpc.inprocess.InProcessTransport$4 extends io.grpc.internal.NoopClientStream {
  final io.grpc.internal.StatsTraceContext val$statsTraceCtx;

  final io.grpc.Status val$status;

  final io.grpc.inprocess.InProcessTransport this$0;

  io.grpc.inprocess.InProcessTransport$4(io.grpc.inprocess.InProcessTransport, io.grpc.internal.StatsTraceContext, io.grpc.Status);
    Code:
       0: aload_0
       1: aload_1
       2: putfield      #1                  // Field this$0:Lio/grpc/inprocess/InProcessTransport;
       5: aload_0
       6: aload_2
       7: putfield      #2                  // Field val$statsTraceCtx:Lio/grpc/internal/StatsTraceContext;
      10: aload_0
      11: aload_3
      12: putfield      #3                  // Field val$status:Lio/grpc/Status;
      15: aload_0
      16: invokespecial #4                  // Method io/grpc/internal/NoopClientStream."<init>":()V
      19: return

  public void start(io.grpc.internal.ClientStreamListener);
    Code:
       0: aload_0
       1: getfield      #2                  // Field val$statsTraceCtx:Lio/grpc/internal/StatsTraceContext;
       4: invokevirtual #5                  // Method io/grpc/internal/StatsTraceContext.clientOutboundHeaders:()V
       7: aload_0
       8: getfield      #2                  // Field val$statsTraceCtx:Lio/grpc/internal/StatsTraceContext;
      11: aload_0
      12: getfield      #3                  // Field val$status:Lio/grpc/Status;
      15: invokevirtual #6                  // Method io/grpc/internal/StatsTraceContext.streamClosed:(Lio/grpc/Status;)V
      18: aload_1
      19: aload_0
      20: getfield      #3                  // Field val$status:Lio/grpc/Status;
      23: getstatic     #7                  // Field io/grpc/internal/ClientStreamListener$RpcProgress.PROCESSED:Lio/grpc/internal/ClientStreamListener$RpcProgress;
      26: new           #8                  // class io/grpc/Metadata
      29: dup
      30: invokespecial #9                  // Method io/grpc/Metadata."<init>":()V
      33: invokeinterface #10,  4           // InterfaceMethod io/grpc/internal/ClientStreamListener.closed:(Lio/grpc/Status;Lio/grpc/internal/ClientStreamListener$RpcProgress;Lio/grpc/Metadata;)V
      38: return
}
