Compiled from "InProcessTransport.java"
class io.grpc.inprocess.InProcessTransport$SingleMessageProducer implements io.grpc.internal.StreamListener$MessageProducer {
  private java.io.InputStream message;

  private io.grpc.inprocess.InProcessTransport$SingleMessageProducer(java.io.InputStream);
    Code:
       0: aload_0
       1: invokespecial #2                  // Method java/lang/Object."<init>":()V
       4: aload_0
       5: aload_1
       6: putfield      #3                  // Field message:Ljava/io/InputStream;
       9: return

  public java.io.InputStream next();
    Code:
       0: aload_0
       1: getfield      #3                  // Field message:Ljava/io/InputStream;
       4: astore_1
       5: aload_0
       6: aconst_null
       7: putfield      #3                  // Field message:Ljava/io/InputStream;
      10: aload_1
      11: areturn

  io.grpc.inprocess.InProcessTransport$SingleMessageProducer(java.io.InputStream, io.grpc.inprocess.InProcessTransport$1);
    Code:
       0: aload_0
       1: aload_1
       2: invokespecial #1                  // Method "<init>":(Ljava/io/InputStream;)V
       5: return
}
