Compiled from "InProcessTransport.java"
class io.grpc.inprocess.InProcessTransport$InProcessStream$InProcessServerStream implements io.grpc.internal.ServerStream {
  final io.grpc.internal.StatsTraceContext statsTraceCtx;

  private io.grpc.internal.ClientStreamListener clientStreamListener;

  private int clientRequested;

  private java.util.ArrayDeque<io.grpc.internal.StreamListener$MessageProducer> clientReceiveQueue;

  private io.grpc.Status clientNotifyStatus;

  private io.grpc.Metadata clientNotifyTrailers;

  private boolean closed;

  private int outboundSeqNo;

  final io.grpc.inprocess.InProcessTransport$InProcessStream this$1;

  io.grpc.inprocess.InProcessTransport$InProcessStream$InProcessServerStream(io.grpc.MethodDescriptor<?, ?>, io.grpc.Metadata);
    Code:
       0: aload_0
       1: aload_1
       2: putfield      #4                  // Field this$1:Lio/grpc/inprocess/InProcessTransport$InProcessStream;
       5: aload_0
       6: invokespecial #5                  // Method java/lang/Object."<init>":()V
       9: aload_0
      10: new           #6                  // class java/util/ArrayDeque
      13: dup
      14: invokespecial #7                  // Method java/util/ArrayDeque."<init>":()V
      17: putfield      #8                  // Field clientReceiveQueue:Ljava/util/ArrayDeque;
      20: aload_0
      21: aload_1
      22: getfield      #9                  // Field io/grpc/inprocess/InProcessTransport$InProcessStream.this$0:Lio/grpc/inprocess/InProcessTransport;
      25: invokestatic  #10                 // Method io/grpc/inprocess/InProcessTransport.access$1100:(Lio/grpc/inprocess/InProcessTransport;)Ljava/util/List;
      28: aload_2
      29: invokevirtual #11                 // Method io/grpc/MethodDescriptor.getFullMethodName:()Ljava/lang/String;
      32: aload_3
      33: invokestatic  #12                 // Method io/grpc/internal/StatsTraceContext.newServerContext:(Ljava/util/List;Ljava/lang/String;Lio/grpc/Metadata;)Lio/grpc/internal/StatsTraceContext;
      36: putfield      #13                 // Field statsTraceCtx:Lio/grpc/internal/StatsTraceContext;
      39: return

  private synchronized void setListener(io.grpc.internal.ClientStreamListener);
    Code:
       0: aload_0
       1: aload_1
       2: putfield      #14                 // Field clientStreamListener:Lio/grpc/internal/ClientStreamListener;
       5: return

  public void setListener(io.grpc.internal.ServerStreamListener);
    Code:
       0: aload_0
       1: getfield      #4                  // Field this$1:Lio/grpc/inprocess/InProcessTransport$InProcessStream;
       4: invokestatic  #15                 // Method io/grpc/inprocess/InProcessTransport$InProcessStream.access$700:(Lio/grpc/inprocess/InProcessTransport$InProcessStream;)Lio/grpc/inprocess/InProcessTransport$InProcessStream$InProcessClientStream;
       7: aload_1
       8: invokestatic  #16                 // Method io/grpc/inprocess/InProcessTransport$InProcessStream$InProcessClientStream.access$1200:(Lio/grpc/inprocess/InProcessTransport$InProcessStream$InProcessClientStream;Lio/grpc/internal/ServerStreamListener;)V
      11: return

  public void request(int);
    Code:
       0: aload_0
       1: getfield      #4                  // Field this$1:Lio/grpc/inprocess/InProcessTransport$InProcessStream;
       4: invokestatic  #15                 // Method io/grpc/inprocess/InProcessTransport$InProcessStream.access$700:(Lio/grpc/inprocess/InProcessTransport$InProcessStream;)Lio/grpc/inprocess/InProcessTransport$InProcessStream$InProcessClientStream;
       7: iload_1
       8: invokestatic  #17                 // Method io/grpc/inprocess/InProcessTransport$InProcessStream$InProcessClientStream.access$1300:(Lio/grpc/inprocess/InProcessTransport$InProcessStream$InProcessClientStream;I)Z
      11: istore_2
      12: iload_2
      13: ifeq          48
      16: aload_0
      17: dup
      18: astore_3
      19: monitorenter
      20: aload_0
      21: getfield      #18                 // Field closed:Z
      24: ifne          36
      27: aload_0
      28: getfield      #14                 // Field clientStreamListener:Lio/grpc/internal/ClientStreamListener;
      31: invokeinterface #19,  1           // InterfaceMethod io/grpc/internal/ClientStreamListener.onReady:()V
      36: aload_3
      37: monitorexit
      38: goto          48
      41: astore        4
      43: aload_3
      44: monitorexit
      45: aload         4
      47: athrow
      48: return
    Exception table:
       from    to  target type
          20    38    41   any
          41    45    41   any

  private synchronized boolean clientRequested(int);
    Code:
       0: aload_0
       1: getfield      #18                 // Field closed:Z
       4: ifeq          9
       7: iconst_0
       8: ireturn
       9: aload_0
      10: getfield      #20                 // Field clientRequested:I
      13: ifle          20
      16: iconst_1
      17: goto          21
      20: iconst_0
      21: istore_2
      22: aload_0
      23: dup
      24: getfield      #20                 // Field clientRequested:I
      27: iload_1
      28: iadd
      29: putfield      #20                 // Field clientRequested:I
      32: aload_0
      33: getfield      #20                 // Field clientRequested:I
      36: ifle          81
      39: aload_0
      40: getfield      #8                  // Field clientReceiveQueue:Ljava/util/ArrayDeque;
      43: invokevirtual #21                 // Method java/util/ArrayDeque.isEmpty:()Z
      46: ifne          81
      49: aload_0
      50: dup
      51: getfield      #20                 // Field clientRequested:I
      54: iconst_1
      55: isub
      56: putfield      #20                 // Field clientRequested:I
      59: aload_0
      60: getfield      #14                 // Field clientStreamListener:Lio/grpc/internal/ClientStreamListener;
      63: aload_0
      64: getfield      #8                  // Field clientReceiveQueue:Ljava/util/ArrayDeque;
      67: invokevirtual #22                 // Method java/util/ArrayDeque.poll:()Ljava/lang/Object;
      70: checkcast     #23                 // class io/grpc/internal/StreamListener$MessageProducer
      73: invokeinterface #24,  2           // InterfaceMethod io/grpc/internal/ClientStreamListener.messagesAvailable:(Lio/grpc/internal/StreamListener$MessageProducer;)V
      78: goto          32
      81: aload_0
      82: getfield      #18                 // Field closed:Z
      85: ifeq          90
      88: iconst_0
      89: ireturn
      90: aload_0
      91: getfield      #8                  // Field clientReceiveQueue:Ljava/util/ArrayDeque;
      94: invokevirtual #21                 // Method java/util/ArrayDeque.isEmpty:()Z
      97: ifeq          166
     100: aload_0
     101: getfield      #25                 // Field clientNotifyStatus:Lio/grpc/Status;
     104: ifnull        166
     107: aload_0
     108: iconst_1
     109: putfield      #18                 // Field closed:Z
     112: aload_0
     113: getfield      #4                  // Field this$1:Lio/grpc/inprocess/InProcessTransport$InProcessStream;
     116: invokestatic  #15                 // Method io/grpc/inprocess/InProcessTransport$InProcessStream.access$700:(Lio/grpc/inprocess/InProcessTransport$InProcessStream;)Lio/grpc/inprocess/InProcessTransport$InProcessStream$InProcessClientStream;
     119: getfield      #26                 // Field io/grpc/inprocess/InProcessTransport$InProcessStream$InProcessClientStream.statsTraceCtx:Lio/grpc/internal/StatsTraceContext;
     122: aload_0
     123: getfield      #27                 // Field clientNotifyTrailers:Lio/grpc/Metadata;
     126: invokevirtual #28                 // Method io/grpc/internal/StatsTraceContext.clientInboundTrailers:(Lio/grpc/Metadata;)V
     129: aload_0
     130: getfield      #4                  // Field this$1:Lio/grpc/inprocess/InProcessTransport$InProcessStream;
     133: invokestatic  #15                 // Method io/grpc/inprocess/InProcessTransport$InProcessStream.access$700:(Lio/grpc/inprocess/InProcessTransport$InProcessStream;)Lio/grpc/inprocess/InProcessTransport$InProcessStream$InProcessClientStream;
     136: getfield      #26                 // Field io/grpc/inprocess/InProcessTransport$InProcessStream$InProcessClientStream.statsTraceCtx:Lio/grpc/internal/StatsTraceContext;
     139: aload_0
     140: getfield      #25                 // Field clientNotifyStatus:Lio/grpc/Status;
     143: invokevirtual #29                 // Method io/grpc/internal/StatsTraceContext.streamClosed:(Lio/grpc/Status;)V
     146: aload_0
     147: getfield      #14                 // Field clientStreamListener:Lio/grpc/internal/ClientStreamListener;
     150: aload_0
     151: getfield      #25                 // Field clientNotifyStatus:Lio/grpc/Status;
     154: getstatic     #30                 // Field io/grpc/internal/ClientStreamListener$RpcProgress.PROCESSED:Lio/grpc/internal/ClientStreamListener$RpcProgress;
     157: aload_0
     158: getfield      #27                 // Field clientNotifyTrailers:Lio/grpc/Metadata;
     161: invokeinterface #31,  4           // InterfaceMethod io/grpc/internal/ClientStreamListener.closed:(Lio/grpc/Status;Lio/grpc/internal/ClientStreamListener$RpcProgress;Lio/grpc/Metadata;)V
     166: aload_0
     167: getfield      #20                 // Field clientRequested:I
     170: ifle          177
     173: iconst_1
     174: goto          178
     177: iconst_0
     178: istore_3
     179: iload_2
     180: ifne          191
     183: iload_3
     184: ifeq          191
     187: iconst_1
     188: goto          192
     191: iconst_0
     192: ireturn

  private void clientCancelled(io.grpc.Status);
    Code:
       0: aload_0
       1: aload_1
       2: invokespecial #32                 // Method internalCancel:(Lio/grpc/Status;)Z
       5: pop
       6: return

  public synchronized void writeMessage(java.io.InputStream);
    Code:
       0: aload_0
       1: getfield      #18                 // Field closed:Z
       4: ifeq          8
       7: return
       8: aload_0
       9: getfield      #13                 // Field statsTraceCtx:Lio/grpc/internal/StatsTraceContext;
      12: aload_0
      13: getfield      #33                 // Field outboundSeqNo:I
      16: invokevirtual #34                 // Method io/grpc/internal/StatsTraceContext.outboundMessage:(I)V
      19: aload_0
      20: getfield      #13                 // Field statsTraceCtx:Lio/grpc/internal/StatsTraceContext;
      23: aload_0
      24: getfield      #33                 // Field outboundSeqNo:I
      27: ldc2_w        #35                 // long -1l
      30: ldc2_w        #35                 // long -1l
      33: invokevirtual #37                 // Method io/grpc/internal/StatsTraceContext.outboundMessageSent:(IJJ)V
      36: aload_0
      37: getfield      #4                  // Field this$1:Lio/grpc/inprocess/InProcessTransport$InProcessStream;
      40: invokestatic  #15                 // Method io/grpc/inprocess/InProcessTransport$InProcessStream.access$700:(Lio/grpc/inprocess/InProcessTransport$InProcessStream;)Lio/grpc/inprocess/InProcessTransport$InProcessStream$InProcessClientStream;
      43: getfield      #26                 // Field io/grpc/inprocess/InProcessTransport$InProcessStream$InProcessClientStream.statsTraceCtx:Lio/grpc/internal/StatsTraceContext;
      46: aload_0
      47: getfield      #33                 // Field outboundSeqNo:I
      50: invokevirtual #38                 // Method io/grpc/internal/StatsTraceContext.inboundMessage:(I)V
      53: aload_0
      54: getfield      #4                  // Field this$1:Lio/grpc/inprocess/InProcessTransport$InProcessStream;
      57: invokestatic  #15                 // Method io/grpc/inprocess/InProcessTransport$InProcessStream.access$700:(Lio/grpc/inprocess/InProcessTransport$InProcessStream;)Lio/grpc/inprocess/InProcessTransport$InProcessStream$InProcessClientStream;
      60: getfield      #26                 // Field io/grpc/inprocess/InProcessTransport$InProcessStream$InProcessClientStream.statsTraceCtx:Lio/grpc/internal/StatsTraceContext;
      63: aload_0
      64: getfield      #33                 // Field outboundSeqNo:I
      67: ldc2_w        #35                 // long -1l
      70: ldc2_w        #35                 // long -1l
      73: invokevirtual #39                 // Method io/grpc/internal/StatsTraceContext.inboundMessageRead:(IJJ)V
      76: aload_0
      77: dup
      78: getfield      #33                 // Field outboundSeqNo:I
      81: iconst_1
      82: iadd
      83: putfield      #33                 // Field outboundSeqNo:I
      86: new           #40                 // class io/grpc/inprocess/InProcessTransport$SingleMessageProducer
      89: dup
      90: aload_1
      91: aconst_null
      92: invokespecial #41                 // Method io/grpc/inprocess/InProcessTransport$SingleMessageProducer."<init>":(Ljava/io/InputStream;Lio/grpc/inprocess/InProcessTransport$1;)V
      95: astore_2
      96: aload_0
      97: getfield      #20                 // Field clientRequested:I
     100: ifle          126
     103: aload_0
     104: dup
     105: getfield      #20                 // Field clientRequested:I
     108: iconst_1
     109: isub
     110: putfield      #20                 // Field clientRequested:I
     113: aload_0
     114: getfield      #14                 // Field clientStreamListener:Lio/grpc/internal/ClientStreamListener;
     117: aload_2
     118: invokeinterface #24,  2           // InterfaceMethod io/grpc/internal/ClientStreamListener.messagesAvailable:(Lio/grpc/internal/StreamListener$MessageProducer;)V
     123: goto          135
     126: aload_0
     127: getfield      #8                  // Field clientReceiveQueue:Ljava/util/ArrayDeque;
     130: aload_2
     131: invokevirtual #42                 // Method java/util/ArrayDeque.add:(Ljava/lang/Object;)Z
     134: pop
     135: return

  public void flush();
    Code:
       0: return

  public synchronized boolean isReady();
    Code:
       0: aload_0
       1: getfield      #18                 // Field closed:Z
       4: ifeq          9
       7: iconst_0
       8: ireturn
       9: aload_0
      10: getfield      #20                 // Field clientRequested:I
      13: ifle          20
      16: iconst_1
      17: goto          21
      20: iconst_0
      21: ireturn

  public void writeHeaders(io.grpc.Metadata);
    Code:
       0: aload_0
       1: getfield      #4                  // Field this$1:Lio/grpc/inprocess/InProcessTransport$InProcessStream;
       4: getfield      #9                  // Field io/grpc/inprocess/InProcessTransport$InProcessStream.this$0:Lio/grpc/inprocess/InProcessTransport;
       7: invokestatic  #43                 // Method io/grpc/inprocess/InProcessTransport.access$1500:(Lio/grpc/inprocess/InProcessTransport;)I
      10: ldc           #45                 // int 2147483647
      12: if_icmpeq     109
      15: aload_1
      16: invokestatic  #46                 // Method io/grpc/inprocess/InProcessTransport.access$1600:(Lio/grpc/Metadata;)I
      19: istore_2
      20: iload_2
      21: aload_0
      22: getfield      #4                  // Field this$1:Lio/grpc/inprocess/InProcessTransport$InProcessStream;
      25: getfield      #9                  // Field io/grpc/inprocess/InProcessTransport$InProcessStream.this$0:Lio/grpc/inprocess/InProcessTransport;
      28: invokestatic  #43                 // Method io/grpc/inprocess/InProcessTransport.access$1500:(Lio/grpc/inprocess/InProcessTransport;)I
      31: if_icmple     109
      34: getstatic     #47                 // Field io/grpc/Status.CANCELLED:Lio/grpc/Status;
      37: ldc           #48                 // String Client cancelled the RPC
      39: invokevirtual #49                 // Method io/grpc/Status.withDescription:(Ljava/lang/String;)Lio/grpc/Status;
      42: astore_3
      43: aload_0
      44: getfield      #4                  // Field this$1:Lio/grpc/inprocess/InProcessTransport$InProcessStream;
      47: invokestatic  #15                 // Method io/grpc/inprocess/InProcessTransport$InProcessStream.access$700:(Lio/grpc/inprocess/InProcessTransport$InProcessStream;)Lio/grpc/inprocess/InProcessTransport$InProcessStream$InProcessClientStream;
      50: aload_3
      51: aload_3
      52: invokestatic  #50                 // Method io/grpc/inprocess/InProcessTransport$InProcessStream$InProcessClientStream.access$1700:(Lio/grpc/inprocess/InProcessTransport$InProcessStream$InProcessClientStream;Lio/grpc/Status;Lio/grpc/Status;)V
      55: getstatic     #51                 // Field io/grpc/Status.RESOURCE_EXHAUSTED:Lio/grpc/Status;
      58: ldc           #52                 // String Response header metadata larger than %d: %d
      60: iconst_2
      61: anewarray     #53                 // class java/lang/Object
      64: dup
      65: iconst_0
      66: aload_0
      67: getfield      #4                  // Field this$1:Lio/grpc/inprocess/InProcessTransport$InProcessStream;
      70: getfield      #9                  // Field io/grpc/inprocess/InProcessTransport$InProcessStream.this$0:Lio/grpc/inprocess/InProcessTransport;
      73: invokestatic  #43                 // Method io/grpc/inprocess/InProcessTransport.access$1500:(Lio/grpc/inprocess/InProcessTransport;)I
      76: invokestatic  #54                 // Method java/lang/Integer.valueOf:(I)Ljava/lang/Integer;
      79: aastore
      80: dup
      81: iconst_1
      82: iload_2
      83: invokestatic  #54                 // Method java/lang/Integer.valueOf:(I)Ljava/lang/Integer;
      86: aastore
      87: invokestatic  #55                 // Method java/lang/String.format:(Ljava/lang/String;[Ljava/lang/Object;)Ljava/lang/String;
      90: invokevirtual #49                 // Method io/grpc/Status.withDescription:(Ljava/lang/String;)Lio/grpc/Status;
      93: astore        4
      95: aload_0
      96: aload         4
      98: new           #56                 // class io/grpc/Metadata
     101: dup
     102: invokespecial #57                 // Method io/grpc/Metadata."<init>":()V
     105: invokespecial #58                 // Method notifyClientClose:(Lio/grpc/Status;Lio/grpc/Metadata;)V
     108: return
     109: aload_0
     110: dup
     111: astore_2
     112: monitorenter
     113: aload_0
     114: getfield      #18                 // Field closed:Z
     117: ifeq          123
     120: aload_2
     121: monitorexit
     122: return
     123: aload_0
     124: getfield      #4                  // Field this$1:Lio/grpc/inprocess/InProcessTransport$InProcessStream;
     127: invokestatic  #15                 // Method io/grpc/inprocess/InProcessTransport$InProcessStream.access$700:(Lio/grpc/inprocess/InProcessTransport$InProcessStream;)Lio/grpc/inprocess/InProcessTransport$InProcessStream$InProcessClientStream;
     130: getfield      #26                 // Field io/grpc/inprocess/InProcessTransport$InProcessStream$InProcessClientStream.statsTraceCtx:Lio/grpc/internal/StatsTraceContext;
     133: invokevirtual #59                 // Method io/grpc/internal/StatsTraceContext.clientInboundHeaders:()V
     136: aload_0
     137: getfield      #14                 // Field clientStreamListener:Lio/grpc/internal/ClientStreamListener;
     140: aload_1
     141: invokeinterface #60,  2           // InterfaceMethod io/grpc/internal/ClientStreamListener.headersRead:(Lio/grpc/Metadata;)V
     146: aload_2
     147: monitorexit
     148: goto          158
     151: astore        5
     153: aload_2
     154: monitorexit
     155: aload         5
     157: athrow
     158: return
    Exception table:
       from    to  target type
         113   122   151   any
         123   148   151   any
         151   155   151   any

  public void close(io.grpc.Status, io.grpc.Metadata);
    Code:
       0: aload_0
       1: getfield      #4                  // Field this$1:Lio/grpc/inprocess/InProcessTransport$InProcessStream;
       4: invokestatic  #15                 // Method io/grpc/inprocess/InProcessTransport$InProcessStream.access$700:(Lio/grpc/inprocess/InProcessTransport$InProcessStream;)Lio/grpc/inprocess/InProcessTransport$InProcessStream$InProcessClientStream;
       7: getstatic     #61                 // Field io/grpc/Status.OK:Lio/grpc/Status;
      10: aload_1
      11: invokestatic  #50                 // Method io/grpc/inprocess/InProcessTransport$InProcessStream$InProcessClientStream.access$1700:(Lio/grpc/inprocess/InProcessTransport$InProcessStream$InProcessClientStream;Lio/grpc/Status;Lio/grpc/Status;)V
      14: aload_0
      15: getfield      #4                  // Field this$1:Lio/grpc/inprocess/InProcessTransport$InProcessStream;
      18: getfield      #9                  // Field io/grpc/inprocess/InProcessTransport$InProcessStream.this$0:Lio/grpc/inprocess/InProcessTransport;
      21: invokestatic  #43                 // Method io/grpc/inprocess/InProcessTransport.access$1500:(Lio/grpc/inprocess/InProcessTransport;)I
      24: ldc           #45                 // int 2147483647
      26: if_icmpeq     119
      29: aload_1
      30: invokevirtual #62                 // Method io/grpc/Status.getDescription:()Ljava/lang/String;
      33: ifnonnull     40
      36: iconst_0
      37: goto          47
      40: aload_1
      41: invokevirtual #62                 // Method io/grpc/Status.getDescription:()Ljava/lang/String;
      44: invokevirtual #63                 // Method java/lang/String.length:()I
      47: istore_3
      48: aload_2
      49: invokestatic  #46                 // Method io/grpc/inprocess/InProcessTransport.access$1600:(Lio/grpc/Metadata;)I
      52: iload_3
      53: iadd
      54: istore        4
      56: iload         4
      58: aload_0
      59: getfield      #4                  // Field this$1:Lio/grpc/inprocess/InProcessTransport$InProcessStream;
      62: getfield      #9                  // Field io/grpc/inprocess/InProcessTransport$InProcessStream.this$0:Lio/grpc/inprocess/InProcessTransport;
      65: invokestatic  #43                 // Method io/grpc/inprocess/InProcessTransport.access$1500:(Lio/grpc/inprocess/InProcessTransport;)I
      68: if_icmple     119
      71: getstatic     #51                 // Field io/grpc/Status.RESOURCE_EXHAUSTED:Lio/grpc/Status;
      74: ldc           #52                 // String Response header metadata larger than %d: %d
      76: iconst_2
      77: anewarray     #53                 // class java/lang/Object
      80: dup
      81: iconst_0
      82: aload_0
      83: getfield      #4                  // Field this$1:Lio/grpc/inprocess/InProcessTransport$InProcessStream;
      86: getfield      #9                  // Field io/grpc/inprocess/InProcessTransport$InProcessStream.this$0:Lio/grpc/inprocess/InProcessTransport;
      89: invokestatic  #43                 // Method io/grpc/inprocess/InProcessTransport.access$1500:(Lio/grpc/inprocess/InProcessTransport;)I
      92: invokestatic  #54                 // Method java/lang/Integer.valueOf:(I)Ljava/lang/Integer;
      95: aastore
      96: dup
      97: iconst_1
      98: iload         4
     100: invokestatic  #54                 // Method java/lang/Integer.valueOf:(I)Ljava/lang/Integer;
     103: aastore
     104: invokestatic  #55                 // Method java/lang/String.format:(Ljava/lang/String;[Ljava/lang/Object;)Ljava/lang/String;
     107: invokevirtual #49                 // Method io/grpc/Status.withDescription:(Ljava/lang/String;)Lio/grpc/Status;
     110: astore_1
     111: new           #56                 // class io/grpc/Metadata
     114: dup
     115: invokespecial #57                 // Method io/grpc/Metadata."<init>":()V
     118: astore_2
     119: aload_0
     120: aload_1
     121: aload_2
     122: invokespecial #58                 // Method notifyClientClose:(Lio/grpc/Status;Lio/grpc/Metadata;)V
     125: return

  private void notifyClientClose(io.grpc.Status, io.grpc.Metadata);
    Code:
       0: aload_1
       1: aload_0
       2: getfield      #4                  // Field this$1:Lio/grpc/inprocess/InProcessTransport$InProcessStream;
       5: getfield      #9                  // Field io/grpc/inprocess/InProcessTransport$InProcessStream.this$0:Lio/grpc/inprocess/InProcessTransport;
       8: invokestatic  #64                 // Method io/grpc/inprocess/InProcessTransport.access$1800:(Lio/grpc/inprocess/InProcessTransport;)Z
      11: invokestatic  #65                 // Method io/grpc/inprocess/InProcessTransport.access$1900:(Lio/grpc/Status;Z)Lio/grpc/Status;
      14: astore_3
      15: aload_0
      16: dup
      17: astore        4
      19: monitorenter
      20: aload_0
      21: getfield      #18                 // Field closed:Z
      24: ifeq          31
      27: aload         4
      29: monitorexit
      30: return
      31: aload_0
      32: getfield      #8                  // Field clientReceiveQueue:Ljava/util/ArrayDeque;
      35: invokevirtual #21                 // Method java/util/ArrayDeque.isEmpty:()Z
      38: ifeq          91
      41: aload_0
      42: iconst_1
      43: putfield      #18                 // Field closed:Z
      46: aload_0
      47: getfield      #4                  // Field this$1:Lio/grpc/inprocess/InProcessTransport$InProcessStream;
      50: invokestatic  #15                 // Method io/grpc/inprocess/InProcessTransport$InProcessStream.access$700:(Lio/grpc/inprocess/InProcessTransport$InProcessStream;)Lio/grpc/inprocess/InProcessTransport$InProcessStream$InProcessClientStream;
      53: getfield      #26                 // Field io/grpc/inprocess/InProcessTransport$InProcessStream$InProcessClientStream.statsTraceCtx:Lio/grpc/internal/StatsTraceContext;
      56: aload_2
      57: invokevirtual #28                 // Method io/grpc/internal/StatsTraceContext.clientInboundTrailers:(Lio/grpc/Metadata;)V
      60: aload_0
      61: getfield      #4                  // Field this$1:Lio/grpc/inprocess/InProcessTransport$InProcessStream;
      64: invokestatic  #15                 // Method io/grpc/inprocess/InProcessTransport$InProcessStream.access$700:(Lio/grpc/inprocess/InProcessTransport$InProcessStream;)Lio/grpc/inprocess/InProcessTransport$InProcessStream$InProcessClientStream;
      67: getfield      #26                 // Field io/grpc/inprocess/InProcessTransport$InProcessStream$InProcessClientStream.statsTraceCtx:Lio/grpc/internal/StatsTraceContext;
      70: aload_3
      71: invokevirtual #29                 // Method io/grpc/internal/StatsTraceContext.streamClosed:(Lio/grpc/Status;)V
      74: aload_0
      75: getfield      #14                 // Field clientStreamListener:Lio/grpc/internal/ClientStreamListener;
      78: aload_3
      79: getstatic     #30                 // Field io/grpc/internal/ClientStreamListener$RpcProgress.PROCESSED:Lio/grpc/internal/ClientStreamListener$RpcProgress;
      82: aload_2
      83: invokeinterface #31,  4           // InterfaceMethod io/grpc/internal/ClientStreamListener.closed:(Lio/grpc/Status;Lio/grpc/internal/ClientStreamListener$RpcProgress;Lio/grpc/Metadata;)V
      88: goto          101
      91: aload_0
      92: aload_3
      93: putfield      #25                 // Field clientNotifyStatus:Lio/grpc/Status;
      96: aload_0
      97: aload_2
      98: putfield      #27                 // Field clientNotifyTrailers:Lio/grpc/Metadata;
     101: aload         4
     103: monitorexit
     104: goto          115
     107: astore        5
     109: aload         4
     111: monitorexit
     112: aload         5
     114: athrow
     115: aload_0
     116: getfield      #4                  // Field this$1:Lio/grpc/inprocess/InProcessTransport$InProcessStream;
     119: invokestatic  #66                 // Method io/grpc/inprocess/InProcessTransport$InProcessStream.access$2000:(Lio/grpc/inprocess/InProcessTransport$InProcessStream;)V
     122: return
    Exception table:
       from    to  target type
          20    30   107   any
          31   104   107   any
         107   112   107   any

  public void cancel(io.grpc.Status);
    Code:
       0: aload_0
       1: getstatic     #47                 // Field io/grpc/Status.CANCELLED:Lio/grpc/Status;
       4: ldc           #67                 // String server cancelled stream
       6: invokevirtual #49                 // Method io/grpc/Status.withDescription:(Ljava/lang/String;)Lio/grpc/Status;
       9: invokespecial #32                 // Method internalCancel:(Lio/grpc/Status;)Z
      12: ifne          16
      15: return
      16: aload_0
      17: getfield      #4                  // Field this$1:Lio/grpc/inprocess/InProcessTransport$InProcessStream;
      20: invokestatic  #15                 // Method io/grpc/inprocess/InProcessTransport$InProcessStream.access$700:(Lio/grpc/inprocess/InProcessTransport$InProcessStream;)Lio/grpc/inprocess/InProcessTransport$InProcessStream$InProcessClientStream;
      23: aload_1
      24: aload_1
      25: invokestatic  #50                 // Method io/grpc/inprocess/InProcessTransport$InProcessStream$InProcessClientStream.access$1700:(Lio/grpc/inprocess/InProcessTransport$InProcessStream$InProcessClientStream;Lio/grpc/Status;Lio/grpc/Status;)V
      28: aload_0
      29: getfield      #4                  // Field this$1:Lio/grpc/inprocess/InProcessTransport$InProcessStream;
      32: invokestatic  #66                 // Method io/grpc/inprocess/InProcessTransport$InProcessStream.access$2000:(Lio/grpc/inprocess/InProcessTransport$InProcessStream;)V
      35: return

  private synchronized boolean internalCancel(io.grpc.Status);
    Code:
       0: aload_0
       1: getfield      #18                 // Field closed:Z
       4: ifeq          9
       7: iconst_0
       8: ireturn
       9: aload_0
      10: iconst_1
      11: putfield      #18                 // Field closed:Z
      14: aload_0
      15: getfield      #8                  // Field clientReceiveQueue:Ljava/util/ArrayDeque;
      18: invokevirtual #22                 // Method java/util/ArrayDeque.poll:()Ljava/lang/Object;
      21: checkcast     #23                 // class io/grpc/internal/StreamListener$MessageProducer
      24: dup
      25: astore_2
      26: ifnull        68
      29: aload_2
      30: invokeinterface #68,  1           // InterfaceMethod io/grpc/internal/StreamListener$MessageProducer.next:()Ljava/io/InputStream;
      35: dup
      36: astore_3
      37: ifnull        65
      40: aload_3
      41: invokevirtual #69                 // Method java/io/InputStream.close:()V
      44: goto          29
      47: astore        4
      49: invokestatic  #71                 // Method io/grpc/inprocess/InProcessTransport.access$2100:()Ljava/util/logging/Logger;
      52: getstatic     #72                 // Field java/util/logging/Level.WARNING:Ljava/util/logging/Level;
      55: ldc           #73                 // String Exception closing stream
      57: aload         4
      59: invokevirtual #74                 // Method java/util/logging/Logger.log:(Ljava/util/logging/Level;Ljava/lang/String;Ljava/lang/Throwable;)V
      62: goto          29
      65: goto          14
      68: aload_0
      69: getfield      #4                  // Field this$1:Lio/grpc/inprocess/InProcessTransport$InProcessStream;
      72: invokestatic  #15                 // Method io/grpc/inprocess/InProcessTransport$InProcessStream.access$700:(Lio/grpc/inprocess/InProcessTransport$InProcessStream;)Lio/grpc/inprocess/InProcessTransport$InProcessStream$InProcessClientStream;
      75: getfield      #26                 // Field io/grpc/inprocess/InProcessTransport$InProcessStream$InProcessClientStream.statsTraceCtx:Lio/grpc/internal/StatsTraceContext;
      78: aload_1
      79: invokevirtual #29                 // Method io/grpc/internal/StatsTraceContext.streamClosed:(Lio/grpc/Status;)V
      82: aload_0
      83: getfield      #14                 // Field clientStreamListener:Lio/grpc/internal/ClientStreamListener;
      86: aload_1
      87: getstatic     #30                 // Field io/grpc/internal/ClientStreamListener$RpcProgress.PROCESSED:Lio/grpc/internal/ClientStreamListener$RpcProgress;
      90: new           #56                 // class io/grpc/Metadata
      93: dup
      94: invokespecial #57                 // Method io/grpc/Metadata."<init>":()V
      97: invokeinterface #31,  4           // InterfaceMethod io/grpc/internal/ClientStreamListener.closed:(Lio/grpc/Status;Lio/grpc/internal/ClientStreamListener$RpcProgress;Lio/grpc/Metadata;)V
     102: iconst_1
     103: ireturn
    Exception table:
       from    to  target type
          40    44    47   Class java/lang/Throwable

  public void setMessageCompression(boolean);
    Code:
       0: return

  public void optimizeForDirectExecutor();
    Code:
       0: return

  public void setCompressor(io.grpc.Compressor);
    Code:
       0: return

  public void setDecompressor(io.grpc.Decompressor);
    Code:
       0: return

  public io.grpc.Attributes getAttributes();
    Code:
       0: aload_0
       1: getfield      #4                  // Field this$1:Lio/grpc/inprocess/InProcessTransport$InProcessStream;
       4: getfield      #9                  // Field io/grpc/inprocess/InProcessTransport$InProcessStream.this$0:Lio/grpc/inprocess/InProcessTransport;
       7: invokestatic  #75                 // Method io/grpc/inprocess/InProcessTransport.access$400:(Lio/grpc/inprocess/InProcessTransport;)Lio/grpc/Attributes;
      10: areturn

  public java.lang.String getAuthority();
    Code:
       0: aload_0
       1: getfield      #4                  // Field this$1:Lio/grpc/inprocess/InProcessTransport$InProcessStream;
       4: invokestatic  #76                 // Method io/grpc/inprocess/InProcessTransport$InProcessStream.access$2200:(Lio/grpc/inprocess/InProcessTransport$InProcessStream;)Ljava/lang/String;
       7: areturn

  public io.grpc.internal.StatsTraceContext statsTraceContext();
    Code:
       0: aload_0
       1: getfield      #13                 // Field statsTraceCtx:Lio/grpc/internal/StatsTraceContext;
       4: areturn

  public int streamId();
    Code:
       0: iconst_m1
       1: ireturn

  static boolean access$2400(io.grpc.inprocess.InProcessTransport$InProcessStream$InProcessServerStream, int);
    Code:
       0: aload_0
       1: iload_1
       2: invokespecial #3                  // Method clientRequested:(I)Z
       5: ireturn

  static void access$2500(io.grpc.inprocess.InProcessTransport$InProcessStream$InProcessServerStream, io.grpc.Status);
    Code:
       0: aload_0
       1: aload_1
       2: invokespecial #2                  // Method clientCancelled:(Lio/grpc/Status;)V
       5: return

  static void access$2600(io.grpc.inprocess.InProcessTransport$InProcessStream$InProcessServerStream, io.grpc.internal.ClientStreamListener);
    Code:
       0: aload_0
       1: aload_1
       2: invokespecial #1                  // Method setListener:(Lio/grpc/internal/ClientStreamListener;)V
       5: return
}
