Compiled from "Argument.kt"
public final class io.vertx.kotlin.core.cli.ArgumentKt {
  public static final io.vertx.core.cli.Argument argumentOf(java.lang.String, java.lang.String, java.lang.String, java.lang.Boolean, java.lang.Integer, java.lang.Boolean, java.lang.Boolean);
    Code:
       0: new           #10                 // class io/vertx/core/cli/Argument
       3: dup
       4: invokespecial #14                 // Method io/vertx/core/cli/Argument."<init>":()V
       7: astore        7
       9: iconst_0
      10: istore        8
      12: iconst_0
      13: istore        9
      15: aload         7
      17: astore        10
      19: iconst_0
      20: istore        11
      22: aload_0
      23: ifnull        33
      26: aload         10
      28: aload_0
      29: invokevirtual #18                 // Method io/vertx/core/cli/Argument.setArgName:(Ljava/lang/String;)Lio/vertx/core/cli/Argument;
      32: pop
      33: aload_1
      34: ifnull        44
      37: aload         10
      39: aload_1
      40: invokevirtual #21                 // Method io/vertx/core/cli/Argument.setDefaultValue:(Ljava/lang/String;)Lio/vertx/core/cli/Argument;
      43: pop
      44: aload_2
      45: ifnull        55
      48: aload         10
      50: aload_2
      51: invokevirtual #24                 // Method io/vertx/core/cli/Argument.setDescription:(Ljava/lang/String;)Lio/vertx/core/cli/Argument;
      54: pop
      55: aload_3
      56: ifnull        69
      59: aload         10
      61: aload_3
      62: invokevirtual #30                 // Method java/lang/Boolean.booleanValue:()Z
      65: invokevirtual #34                 // Method io/vertx/core/cli/Argument.setHidden:(Z)Lio/vertx/core/cli/Argument;
      68: pop
      69: aload         4
      71: ifnull        85
      74: aload         10
      76: aload         4
      78: invokevirtual #40                 // Method java/lang/Integer.intValue:()I
      81: invokevirtual #44                 // Method io/vertx/core/cli/Argument.setIndex:(I)Lio/vertx/core/cli/Argument;
      84: pop
      85: aload         5
      87: ifnull        101
      90: aload         10
      92: aload         5
      94: invokevirtual #30                 // Method java/lang/Boolean.booleanValue:()Z
      97: invokevirtual #47                 // Method io/vertx/core/cli/Argument.setMultiValued:(Z)Lio/vertx/core/cli/Argument;
     100: pop
     101: aload         6
     103: ifnull        117
     106: aload         10
     108: aload         6
     110: invokevirtual #30                 // Method java/lang/Boolean.booleanValue:()Z
     113: invokevirtual #50                 // Method io/vertx/core/cli/Argument.setRequired:(Z)Lio/vertx/core/cli/Argument;
     116: pop
     117: nop
     118: aload         7
     120: areturn

  public static io.vertx.core.cli.Argument argumentOf$default(java.lang.String, java.lang.String, java.lang.String, java.lang.Boolean, java.lang.Integer, java.lang.Boolean, java.lang.Boolean, int, java.lang.Object);
    Code:
       0: iload         7
       2: iconst_1
       3: iand
       4: ifeq          12
       7: aconst_null
       8: checkcast     #66                 // class java/lang/String
      11: astore_0
      12: iload         7
      14: iconst_2
      15: iand
      16: ifeq          24
      19: aconst_null
      20: checkcast     #66                 // class java/lang/String
      23: astore_1
      24: iload         7
      26: iconst_4
      27: iand
      28: ifeq          36
      31: aconst_null
      32: checkcast     #66                 // class java/lang/String
      35: astore_2
      36: iload         7
      38: bipush        8
      40: iand
      41: ifeq          49
      44: aconst_null
      45: checkcast     #26                 // class java/lang/Boolean
      48: astore_3
      49: iload         7
      51: bipush        16
      53: iand
      54: ifeq          63
      57: aconst_null
      58: checkcast     #36                 // class java/lang/Integer
      61: astore        4
      63: iload         7
      65: bipush        32
      67: iand
      68: ifeq          77
      71: aconst_null
      72: checkcast     #26                 // class java/lang/Boolean
      75: astore        5
      77: iload         7
      79: bipush        64
      81: iand
      82: ifeq          91
      85: aconst_null
      86: checkcast     #26                 // class java/lang/Boolean
      89: astore        6
      91: aload_0
      92: aload_1
      93: aload_2
      94: aload_3
      95: aload         4
      97: aload         5
      99: aload         6
     101: invokestatic  #70                 // Method argumentOf:(Ljava/lang/String;Ljava/lang/String;Ljava/lang/String;Ljava/lang/Boolean;Ljava/lang/Integer;Ljava/lang/Boolean;Ljava/lang/Boolean;)Lio/vertx/core/cli/Argument;
     104: areturn

  public static final io.vertx.core.cli.Argument Argument(java.lang.String, java.lang.String, java.lang.String, java.lang.Boolean, java.lang.Integer, java.lang.Boolean, java.lang.Boolean);
    Code:
       0: new           #10                 // class io/vertx/core/cli/Argument
       3: dup
       4: invokespecial #14                 // Method io/vertx/core/cli/Argument."<init>":()V
       7: astore        7
       9: iconst_0
      10: istore        8
      12: iconst_0
      13: istore        9
      15: aload         7
      17: astore        10
      19: iconst_0
      20: istore        11
      22: aload_0
      23: ifnull        33
      26: aload         10
      28: aload_0
      29: invokevirtual #18                 // Method io/vertx/core/cli/Argument.setArgName:(Ljava/lang/String;)Lio/vertx/core/cli/Argument;
      32: pop
      33: aload_1
      34: ifnull        44
      37: aload         10
      39: aload_1
      40: invokevirtual #21                 // Method io/vertx/core/cli/Argument.setDefaultValue:(Ljava/lang/String;)Lio/vertx/core/cli/Argument;
      43: pop
      44: aload_2
      45: ifnull        55
      48: aload         10
      50: aload_2
      51: invokevirtual #24                 // Method io/vertx/core/cli/Argument.setDescription:(Ljava/lang/String;)Lio/vertx/core/cli/Argument;
      54: pop
      55: aload_3
      56: ifnull        69
      59: aload         10
      61: aload_3
      62: invokevirtual #30                 // Method java/lang/Boolean.booleanValue:()Z
      65: invokevirtual #34                 // Method io/vertx/core/cli/Argument.setHidden:(Z)Lio/vertx/core/cli/Argument;
      68: pop
      69: aload         4
      71: ifnull        85
      74: aload         10
      76: aload         4
      78: invokevirtual #40                 // Method java/lang/Integer.intValue:()I
      81: invokevirtual #44                 // Method io/vertx/core/cli/Argument.setIndex:(I)Lio/vertx/core/cli/Argument;
      84: pop
      85: aload         5
      87: ifnull        101
      90: aload         10
      92: aload         5
      94: invokevirtual #30                 // Method java/lang/Boolean.booleanValue:()Z
      97: invokevirtual #47                 // Method io/vertx/core/cli/Argument.setMultiValued:(Z)Lio/vertx/core/cli/Argument;
     100: pop
     101: aload         6
     103: ifnull        117
     106: aload         10
     108: aload         6
     110: invokevirtual #30                 // Method java/lang/Boolean.booleanValue:()Z
     113: invokevirtual #50                 // Method io/vertx/core/cli/Argument.setRequired:(Z)Lio/vertx/core/cli/Argument;
     116: pop
     117: nop
     118: aload         7
     120: areturn

  public static io.vertx.core.cli.Argument Argument$default(java.lang.String, java.lang.String, java.lang.String, java.lang.Boolean, java.lang.Integer, java.lang.Boolean, java.lang.Boolean, int, java.lang.Object);
    Code:
       0: iload         7
       2: iconst_1
       3: iand
       4: ifeq          12
       7: aconst_null
       8: checkcast     #66                 // class java/lang/String
      11: astore_0
      12: iload         7
      14: iconst_2
      15: iand
      16: ifeq          24
      19: aconst_null
      20: checkcast     #66                 // class java/lang/String
      23: astore_1
      24: iload         7
      26: iconst_4
      27: iand
      28: ifeq          36
      31: aconst_null
      32: checkcast     #66                 // class java/lang/String
      35: astore_2
      36: iload         7
      38: bipush        8
      40: iand
      41: ifeq          49
      44: aconst_null
      45: checkcast     #26                 // class java/lang/Boolean
      48: astore_3
      49: iload         7
      51: bipush        16
      53: iand
      54: ifeq          63
      57: aconst_null
      58: checkcast     #36                 // class java/lang/Integer
      61: astore        4
      63: iload         7
      65: bipush        32
      67: iand
      68: ifeq          77
      71: aconst_null
      72: checkcast     #26                 // class java/lang/Boolean
      75: astore        5
      77: iload         7
      79: bipush        64
      81: iand
      82: ifeq          91
      85: aconst_null
      86: checkcast     #26                 // class java/lang/Boolean
      89: astore        6
      91: aload_0
      92: aload_1
      93: aload_2
      94: aload_3
      95: aload         4
      97: aload         5
      99: aload         6
     101: invokestatic  #83                 // Method Argument:(Ljava/lang/String;Ljava/lang/String;Ljava/lang/String;Ljava/lang/Boolean;Ljava/lang/Integer;Ljava/lang/Boolean;Ljava/lang/Boolean;)Lio/vertx/core/cli/Argument;
     104: areturn
}
