public final class org.bouncycastle.pqc.crypto.xmss.XMSSMTSignature implements org.bouncycastle.pqc.crypto.xmss.XMSSStoreableObjectInterface,org.bouncycastle.util.Encodable {
  private final org.bouncycastle.pqc.crypto.xmss.XMSSMTParameters params;

  private final long index;

  private final byte[] random;

  private final java.util.List<org.bouncycastle.pqc.crypto.xmss.XMSSReducedSignature> reducedSignatures;

  private org.bouncycastle.pqc.crypto.xmss.XMSSMTSignature(org.bouncycastle.pqc.crypto.xmss.XMSSMTSignature$Builder);
    Code:
       0: aload_0
       1: invokespecial #160                // Method java/lang/Object."<init>":()V
       4: aload_0
       5: aload_1
       6: invokestatic  #175                // Method org/bouncycastle/pqc/crypto/xmss/XMSSMTSignature$Builder.access$000:(Lorg/bouncycastle/pqc/crypto/xmss/XMSSMTSignature$Builder;)Lorg/bouncycastle/pqc/crypto/xmss/XMSSMTParameters;
       9: putfield      #156                // Field params:Lorg/bouncycastle/pqc/crypto/xmss/XMSSMTParameters;
      12: aload_0
      13: getfield      #156                // Field params:Lorg/bouncycastle/pqc/crypto/xmss/XMSSMTParameters;
      16: ifnonnull     29
      19: new           #82                 // class java/lang/NullPointerException
      22: dup
      23: ldc           #2                  // String params == null
      25: invokespecial #159                // Method java/lang/NullPointerException."<init>":(Ljava/lang/String;)V
      28: athrow
      29: aload_0
      30: getfield      #156                // Field params:Lorg/bouncycastle/pqc/crypto/xmss/XMSSMTParameters;
      33: invokevirtual #166                // Method org/bouncycastle/pqc/crypto/xmss/XMSSMTParameters.getTreeDigestSize:()I
      36: istore_2
      37: aload_1
      38: invokestatic  #172                // Method org/bouncycastle/pqc/crypto/xmss/XMSSMTSignature$Builder.access$100:(Lorg/bouncycastle/pqc/crypto/xmss/XMSSMTSignature$Builder;)[B
      41: astore_3
      42: aload_3
      43: ifnull        284
      46: aload_0
      47: getfield      #156                // Field params:Lorg/bouncycastle/pqc/crypto/xmss/XMSSMTParameters;
      50: invokevirtual #167                // Method org/bouncycastle/pqc/crypto/xmss/XMSSMTParameters.getWOTSPlus:()Lorg/bouncycastle/pqc/crypto/xmss/WOTSPlus;
      53: invokevirtual #162                // Method org/bouncycastle/pqc/crypto/xmss/WOTSPlus.getParams:()Lorg/bouncycastle/pqc/crypto/xmss/WOTSPlusParameters;
      56: invokevirtual #163                // Method org/bouncycastle/pqc/crypto/xmss/WOTSPlusParameters.getLen:()I
      59: istore        4
      61: aload_0
      62: getfield      #156                // Field params:Lorg/bouncycastle/pqc/crypto/xmss/XMSSMTParameters;
      65: invokevirtual #164                // Method org/bouncycastle/pqc/crypto/xmss/XMSSMTParameters.getHeight:()I
      68: i2d
      69: ldc2_w        #77                 // double 8.0d
      72: ddiv
      73: invokestatic  #158                // Method java/lang/Math.ceil:(D)D
      76: d2i
      77: istore        5
      79: iload_2
      80: istore        6
      82: aload_0
      83: getfield      #156                // Field params:Lorg/bouncycastle/pqc/crypto/xmss/XMSSMTParameters;
      86: invokevirtual #164                // Method org/bouncycastle/pqc/crypto/xmss/XMSSMTParameters.getHeight:()I
      89: aload_0
      90: getfield      #156                // Field params:Lorg/bouncycastle/pqc/crypto/xmss/XMSSMTParameters;
      93: invokevirtual #165                // Method org/bouncycastle/pqc/crypto/xmss/XMSSMTParameters.getLayers:()I
      96: idiv
      97: iload         4
      99: iadd
     100: iload_2
     101: imul
     102: istore        7
     104: iload         7
     106: aload_0
     107: getfield      #156                // Field params:Lorg/bouncycastle/pqc/crypto/xmss/XMSSMTParameters;
     110: invokevirtual #165                // Method org/bouncycastle/pqc/crypto/xmss/XMSSMTParameters.getLayers:()I
     113: imul
     114: istore        8
     116: iload         5
     118: iload         6
     120: iadd
     121: iload         8
     123: iadd
     124: istore        9
     126: aload_3
     127: arraylength
     128: iload         9
     130: if_icmpeq     143
     133: new           #80                 // class java/lang/IllegalArgumentException
     136: dup
     137: ldc           #3                  // String signature has wrong size
     139: invokespecial #157                // Method java/lang/IllegalArgumentException."<init>":(Ljava/lang/String;)V
     142: athrow
     143: iconst_0
     144: istore        10
     146: aload_0
     147: aload_3
     148: iload         10
     150: iload         5
     152: invokestatic  #183                // Method org/bouncycastle/pqc/crypto/xmss/XMSSUtil.bytesToXBigEndian:([BII)J
     155: putfield      #153                // Field index:J
     158: aload_0
     159: getfield      #156                // Field params:Lorg/bouncycastle/pqc/crypto/xmss/XMSSMTParameters;
     162: invokevirtual #164                // Method org/bouncycastle/pqc/crypto/xmss/XMSSMTParameters.getHeight:()I
     165: aload_0
     166: getfield      #153                // Field index:J
     169: invokestatic  #180                // Method org/bouncycastle/pqc/crypto/xmss/XMSSUtil.isIndexValid:(IJ)Z
     172: ifne          185
     175: new           #80                 // class java/lang/IllegalArgumentException
     178: dup
     179: ldc           #1                  // String index out of bounds
     181: invokespecial #157                // Method java/lang/IllegalArgumentException."<init>":(Ljava/lang/String;)V
     184: athrow
     185: iload         10
     187: iload         5
     189: iadd
     190: istore        10
     192: aload_0
     193: aload_3
     194: iload         10
     196: iload         6
     198: invokestatic  #184                // Method org/bouncycastle/pqc/crypto/xmss/XMSSUtil.extractBytesAtOffset:([BII)[B
     201: putfield      #154                // Field random:[B
     204: iload         10
     206: iload         6
     208: iadd
     209: istore        10
     211: aload_0
     212: new           #84                 // class java/util/ArrayList
     215: dup
     216: invokespecial #161                // Method java/util/ArrayList."<init>":()V
     219: putfield      #155                // Field reducedSignatures:Ljava/util/List;
     222: iload         10
     224: aload_3
     225: arraylength
     226: if_icmpge     281
     229: new           #94                 // class org/bouncycastle/pqc/crypto/xmss/XMSSReducedSignature$Builder
     232: dup
     233: aload_0
     234: getfield      #156                // Field params:Lorg/bouncycastle/pqc/crypto/xmss/XMSSMTParameters;
     237: invokevirtual #168                // Method org/bouncycastle/pqc/crypto/xmss/XMSSMTParameters.getXMSSParameters:()Lorg/bouncycastle/pqc/crypto/xmss/XMSSParameters;
     240: invokespecial #177                // Method org/bouncycastle/pqc/crypto/xmss/XMSSReducedSignature$Builder."<init>":(Lorg/bouncycastle/pqc/crypto/xmss/XMSSParameters;)V
     243: aload_3
     244: iload         10
     246: iload         7
     248: invokestatic  #184                // Method org/bouncycastle/pqc/crypto/xmss/XMSSUtil.extractBytesAtOffset:([BII)[B
     251: invokevirtual #179                // Method org/bouncycastle/pqc/crypto/xmss/XMSSReducedSignature$Builder.withReducedSignature:([B)Lorg/bouncycastle/pqc/crypto/xmss/XMSSReducedSignature$Builder;
     254: invokevirtual #178                // Method org/bouncycastle/pqc/crypto/xmss/XMSSReducedSignature$Builder.build:()Lorg/bouncycastle/pqc/crypto/xmss/XMSSReducedSignature;
     257: astore        11
     259: aload_0
     260: getfield      #155                // Field reducedSignatures:Ljava/util/List;
     263: aload         11
     265: invokeinterface #188,  2          // InterfaceMethod java/util/List.add:(Ljava/lang/Object;)Z
     270: pop
     271: iload         10
     273: iload         7
     275: iadd
     276: istore        10
     278: goto          222
     281: goto          367
     284: aload_0
     285: aload_1
     286: invokestatic  #171                // Method org/bouncycastle/pqc/crypto/xmss/XMSSMTSignature$Builder.access$200:(Lorg/bouncycastle/pqc/crypto/xmss/XMSSMTSignature$Builder;)J
     289: putfield      #153                // Field index:J
     292: aload_1
     293: invokestatic  #173                // Method org/bouncycastle/pqc/crypto/xmss/XMSSMTSignature$Builder.access$300:(Lorg/bouncycastle/pqc/crypto/xmss/XMSSMTSignature$Builder;)[B
     296: astore        4
     298: aload         4
     300: ifnull        329
     303: aload         4
     305: arraylength
     306: iload_2
     307: if_icmpeq     320
     310: new           #80                 // class java/lang/IllegalArgumentException
     313: dup
     314: ldc           #4                  // String size of random needs to be equal to size of digest
     316: invokespecial #157                // Method java/lang/IllegalArgumentException."<init>":(Ljava/lang/String;)V
     319: athrow
     320: aload_0
     321: aload         4
     323: putfield      #154                // Field random:[B
     326: goto          336
     329: aload_0
     330: iload_2
     331: newarray       byte
     333: putfield      #154                // Field random:[B
     336: aload_1
     337: invokestatic  #174                // Method org/bouncycastle/pqc/crypto/xmss/XMSSMTSignature$Builder.access$400:(Lorg/bouncycastle/pqc/crypto/xmss/XMSSMTSignature$Builder;)Ljava/util/List;
     340: astore        5
     342: aload         5
     344: ifnull        356
     347: aload_0
     348: aload         5
     350: putfield      #155                // Field reducedSignatures:Ljava/util/List;
     353: goto          367
     356: aload_0
     357: new           #84                 // class java/util/ArrayList
     360: dup
     361: invokespecial #161                // Method java/util/ArrayList."<init>":()V
     364: putfield      #155                // Field reducedSignatures:Ljava/util/List;
     367: return

  public byte[] getEncoded() throws java.io.IOException;
    Code:
       0: aload_0
       1: invokevirtual #169                // Method toByteArray:()[B
       4: areturn

  public byte[] toByteArray();
    Code:
       0: aload_0
       1: getfield      #156                // Field params:Lorg/bouncycastle/pqc/crypto/xmss/XMSSMTParameters;
       4: invokevirtual #166                // Method org/bouncycastle/pqc/crypto/xmss/XMSSMTParameters.getTreeDigestSize:()I
       7: istore_1
       8: aload_0
       9: getfield      #156                // Field params:Lorg/bouncycastle/pqc/crypto/xmss/XMSSMTParameters;
      12: invokevirtual #167                // Method org/bouncycastle/pqc/crypto/xmss/XMSSMTParameters.getWOTSPlus:()Lorg/bouncycastle/pqc/crypto/xmss/WOTSPlus;
      15: invokevirtual #162                // Method org/bouncycastle/pqc/crypto/xmss/WOTSPlus.getParams:()Lorg/bouncycastle/pqc/crypto/xmss/WOTSPlusParameters;
      18: invokevirtual #163                // Method org/bouncycastle/pqc/crypto/xmss/WOTSPlusParameters.getLen:()I
      21: istore_2
      22: aload_0
      23: getfield      #156                // Field params:Lorg/bouncycastle/pqc/crypto/xmss/XMSSMTParameters;
      26: invokevirtual #164                // Method org/bouncycastle/pqc/crypto/xmss/XMSSMTParameters.getHeight:()I
      29: i2d
      30: ldc2_w        #77                 // double 8.0d
      33: ddiv
      34: invokestatic  #158                // Method java/lang/Math.ceil:(D)D
      37: d2i
      38: istore_3
      39: iload_1
      40: istore        4
      42: aload_0
      43: getfield      #156                // Field params:Lorg/bouncycastle/pqc/crypto/xmss/XMSSMTParameters;
      46: invokevirtual #164                // Method org/bouncycastle/pqc/crypto/xmss/XMSSMTParameters.getHeight:()I
      49: aload_0
      50: getfield      #156                // Field params:Lorg/bouncycastle/pqc/crypto/xmss/XMSSMTParameters;
      53: invokevirtual #165                // Method org/bouncycastle/pqc/crypto/xmss/XMSSMTParameters.getLayers:()I
      56: idiv
      57: iload_2
      58: iadd
      59: iload_1
      60: imul
      61: istore        5
      63: iload         5
      65: aload_0
      66: getfield      #156                // Field params:Lorg/bouncycastle/pqc/crypto/xmss/XMSSMTParameters;
      69: invokevirtual #165                // Method org/bouncycastle/pqc/crypto/xmss/XMSSMTParameters.getLayers:()I
      72: imul
      73: istore        6
      75: iload_3
      76: iload         4
      78: iadd
      79: iload         6
      81: iadd
      82: istore        7
      84: iload         7
      86: newarray       byte
      88: astore        8
      90: iconst_0
      91: istore        9
      93: aload_0
      94: getfield      #153                // Field index:J
      97: iload_3
      98: invokestatic  #181                // Method org/bouncycastle/pqc/crypto/xmss/XMSSUtil.toBytesBigEndian:(JI)[B
     101: astore        10
     103: aload         8
     105: aload         10
     107: iload         9
     109: invokestatic  #185                // Method org/bouncycastle/pqc/crypto/xmss/XMSSUtil.copyBytesAtOffset:([B[BI)V
     112: iload         9
     114: iload_3
     115: iadd
     116: istore        9
     118: aload         8
     120: aload_0
     121: getfield      #154                // Field random:[B
     124: iload         9
     126: invokestatic  #185                // Method org/bouncycastle/pqc/crypto/xmss/XMSSUtil.copyBytesAtOffset:([B[BI)V
     129: iload         9
     131: iload         4
     133: iadd
     134: istore        9
     136: aload_0
     137: getfield      #155                // Field reducedSignatures:Ljava/util/List;
     140: invokeinterface #189,  1          // InterfaceMethod java/util/List.iterator:()Ljava/util/Iterator;
     145: astore        11
     147: aload         11
     149: invokeinterface #186,  1          // InterfaceMethod java/util/Iterator.hasNext:()Z
     154: ifeq          195
     157: aload         11
     159: invokeinterface #187,  1          // InterfaceMethod java/util/Iterator.next:()Ljava/lang/Object;
     164: checkcast     #93                 // class org/bouncycastle/pqc/crypto/xmss/XMSSReducedSignature
     167: astore        12
     169: aload         12
     171: invokevirtual #176                // Method org/bouncycastle/pqc/crypto/xmss/XMSSReducedSignature.toByteArray:()[B
     174: astore        13
     176: aload         8
     178: aload         13
     180: iload         9
     182: invokestatic  #185                // Method org/bouncycastle/pqc/crypto/xmss/XMSSUtil.copyBytesAtOffset:([B[BI)V
     185: iload         9
     187: iload         5
     189: iadd
     190: istore        9
     192: goto          147
     195: aload         8
     197: areturn

  public long getIndex();
    Code:
       0: aload_0
       1: getfield      #153                // Field index:J
       4: lreturn

  public byte[] getRandom();
    Code:
       0: aload_0
       1: getfield      #154                // Field random:[B
       4: invokestatic  #182                // Method org/bouncycastle/pqc/crypto/xmss/XMSSUtil.cloneArray:([B)[B
       7: areturn

  public java.util.List<org.bouncycastle.pqc.crypto.xmss.XMSSReducedSignature> getReducedSignatures();
    Code:
       0: aload_0
       1: getfield      #155                // Field reducedSignatures:Ljava/util/List;
       4: areturn

  org.bouncycastle.pqc.crypto.xmss.XMSSMTSignature(org.bouncycastle.pqc.crypto.xmss.XMSSMTSignature$Builder, org.bouncycastle.pqc.crypto.xmss.XMSSMTSignature$1);
    Code:
       0: aload_0
       1: aload_1
       2: invokespecial #170                // Method "<init>":(Lorg/bouncycastle/pqc/crypto/xmss/XMSSMTSignature$Builder;)V
       5: return
}
