Compiled from "TypedProperties.java"
final class org.apache.activemq.artemis.utils.TypedProperties$IntValue extends org.apache.activemq.artemis.utils.TypedProperties$PropertyValue {
  final int val;

  public org.apache.activemq.artemis.utils.TypedProperties$IntValue(int);
    Code:
       0: aload_0
       1: aconst_null
       2: invokespecial #1                  // Method org/apache/activemq/artemis/utils/TypedProperties$PropertyValue."<init>":(Lorg/apache/activemq/artemis/utils/TypedProperties$1;)V
       5: aload_0
       6: iload_1
       7: putfield      #2                  // Field val:I
      10: return

  public org.apache.activemq.artemis.utils.TypedProperties$IntValue(org.apache.activemq.artemis.api.core.ActiveMQBuffer);
    Code:
       0: aload_0
       1: aconst_null
       2: invokespecial #1                  // Method org/apache/activemq/artemis/utils/TypedProperties$PropertyValue."<init>":(Lorg/apache/activemq/artemis/utils/TypedProperties$1;)V
       5: aload_0
       6: aload_1
       7: invokeinterface #3,  1            // InterfaceMethod org/apache/activemq/artemis/api/core/ActiveMQBuffer.readInt:()I
      12: putfield      #2                  // Field val:I
      15: return

  public java.lang.Object getValue();
    Code:
       0: aload_0
       1: getfield      #2                  // Field val:I
       4: invokestatic  #4                  // Method java/lang/Integer.valueOf:(I)Ljava/lang/Integer;
       7: areturn

  public void write(org.apache.activemq.artemis.api.core.ActiveMQBuffer);
    Code:
       0: aload_1
       1: bipush        6
       3: invokeinterface #6,  2            // InterfaceMethod org/apache/activemq/artemis/api/core/ActiveMQBuffer.writeByte:(B)V
       8: aload_1
       9: aload_0
      10: getfield      #2                  // Field val:I
      13: invokeinterface #7,  2            // InterfaceMethod org/apache/activemq/artemis/api/core/ActiveMQBuffer.writeInt:(I)V
      18: return

  public int encodeSize();
    Code:
       0: iconst_5
       1: ireturn
}
