Compiled from "TypedProperties.java"
final class org.apache.activemq.artemis.utils.TypedProperties$CharValue extends org.apache.activemq.artemis.utils.TypedProperties$PropertyValue {
  final char val;

  public org.apache.activemq.artemis.utils.TypedProperties$CharValue(char);
    Code:
       0: aload_0
       1: aconst_null
       2: invokespecial #1                  // Method org/apache/activemq/artemis/utils/TypedProperties$PropertyValue."<init>":(Lorg/apache/activemq/artemis/utils/TypedProperties$1;)V
       5: aload_0
       6: iload_1
       7: putfield      #2                  // Field val:C
      10: return

  public org.apache.activemq.artemis.utils.TypedProperties$CharValue(org.apache.activemq.artemis.api.core.ActiveMQBuffer);
    Code:
       0: aload_0
       1: aconst_null
       2: invokespecial #1                  // Method org/apache/activemq/artemis/utils/TypedProperties$PropertyValue."<init>":(Lorg/apache/activemq/artemis/utils/TypedProperties$1;)V
       5: aload_0
       6: aload_1
       7: invokeinterface #3,  1            // InterfaceMethod org/apache/activemq/artemis/api/core/ActiveMQBuffer.readShort:()S
      12: i2c
      13: putfield      #2                  // Field val:C
      16: return

  public java.lang.Object getValue();
    Code:
       0: aload_0
       1: getfield      #2                  // Field val:C
       4: invokestatic  #4                  // Method java/lang/Character.valueOf:(C)Ljava/lang/Character;
       7: areturn

  public void write(org.apache.activemq.artemis.api.core.ActiveMQBuffer);
    Code:
       0: aload_1
       1: bipush        11
       3: invokeinterface #6,  2            // InterfaceMethod org/apache/activemq/artemis/api/core/ActiveMQBuffer.writeByte:(B)V
       8: aload_1
       9: aload_0
      10: getfield      #2                  // Field val:C
      13: i2s
      14: invokeinterface #7,  2            // InterfaceMethod org/apache/activemq/artemis/api/core/ActiveMQBuffer.writeShort:(S)V
      19: return

  public int encodeSize();
    Code:
       0: iconst_3
       1: ireturn
}
