Compiled from "ModuleTypeImpl.java"
public class org.jboss.shrinkwrap.descriptor.impl.jbossmodule13.ModuleTypeImpl<T> implements org.jboss.shrinkwrap.descriptor.api.Child<T>, org.jboss.shrinkwrap.descriptor.api.jbossmodule13.ModuleType<T> {
  private T t;

  private org.jboss.shrinkwrap.descriptor.spi.node.Node childNode;

  public org.jboss.shrinkwrap.descriptor.impl.jbossmodule13.ModuleTypeImpl(T, java.lang.String, org.jboss.shrinkwrap.descriptor.spi.node.Node);
    Code:
       0: aload_0
       1: invokespecial #1                  // Method java/lang/Object."<init>":()V
       4: aload_0
       5: aload_1
       6: putfield      #2                  // Field t:Ljava/lang/Object;
       9: aload_0
      10: aload_3
      11: aload_2
      12: invokevirtual #3                  // Method org/jboss/shrinkwrap/descriptor/spi/node/Node.createChild:(Ljava/lang/String;)Lorg/jboss/shrinkwrap/descriptor/spi/node/Node;
      15: putfield      #4                  // Field childNode:Lorg/jboss/shrinkwrap/descriptor/spi/node/Node;
      18: return

  public org.jboss.shrinkwrap.descriptor.impl.jbossmodule13.ModuleTypeImpl(T, java.lang.String, org.jboss.shrinkwrap.descriptor.spi.node.Node, org.jboss.shrinkwrap.descriptor.spi.node.Node);
    Code:
       0: aload_0
       1: invokespecial #1                  // Method java/lang/Object."<init>":()V
       4: aload_0
       5: aload_1
       6: putfield      #2                  // Field t:Ljava/lang/Object;
       9: aload_0
      10: aload         4
      12: putfield      #4                  // Field childNode:Lorg/jboss/shrinkwrap/descriptor/spi/node/Node;
      15: return

  public T up();
    Code:
       0: aload_0
       1: getfield      #2                  // Field t:Ljava/lang/Object;
       4: areturn

  public org.jboss.shrinkwrap.descriptor.api.jbossmodule13.FilterType<org.jboss.shrinkwrap.descriptor.api.jbossmodule13.ModuleType<T>> getOrCreateExports();
    Code:
       0: aload_0
       1: getfield      #4                  // Field childNode:Lorg/jboss/shrinkwrap/descriptor/spi/node/Node;
       4: ldc           #5                  // String exports
       6: invokevirtual #6                  // Method org/jboss/shrinkwrap/descriptor/spi/node/Node.getOrCreate:(Ljava/lang/String;)Lorg/jboss/shrinkwrap/descriptor/spi/node/Node;
       9: astore_1
      10: new           #7                  // class org/jboss/shrinkwrap/descriptor/impl/jbossmodule13/FilterTypeImpl
      13: dup
      14: aload_0
      15: ldc           #5                  // String exports
      17: aload_0
      18: getfield      #4                  // Field childNode:Lorg/jboss/shrinkwrap/descriptor/spi/node/Node;
      21: aload_1
      22: invokespecial #8                  // Method org/jboss/shrinkwrap/descriptor/impl/jbossmodule13/FilterTypeImpl."<init>":(Ljava/lang/Object;Ljava/lang/String;Lorg/jboss/shrinkwrap/descriptor/spi/node/Node;Lorg/jboss/shrinkwrap/descriptor/spi/node/Node;)V
      25: astore_2
      26: aload_2
      27: areturn

  public org.jboss.shrinkwrap.descriptor.api.jbossmodule13.ModuleType<T> removeExports();
    Code:
       0: aload_0
       1: getfield      #4                  // Field childNode:Lorg/jboss/shrinkwrap/descriptor/spi/node/Node;
       4: ldc           #5                  // String exports
       6: invokevirtual #9                  // Method org/jboss/shrinkwrap/descriptor/spi/node/Node.removeChildren:(Ljava/lang/String;)Ljava/util/List;
       9: pop
      10: aload_0
      11: areturn

  public org.jboss.shrinkwrap.descriptor.api.jbossmodule13.DependenciesType<org.jboss.shrinkwrap.descriptor.api.jbossmodule13.ModuleType<T>> getOrCreateDependencies();
    Code:
       0: aload_0
       1: getfield      #4                  // Field childNode:Lorg/jboss/shrinkwrap/descriptor/spi/node/Node;
       4: ldc           #10                 // String dependencies
       6: invokevirtual #6                  // Method org/jboss/shrinkwrap/descriptor/spi/node/Node.getOrCreate:(Ljava/lang/String;)Lorg/jboss/shrinkwrap/descriptor/spi/node/Node;
       9: astore_1
      10: new           #11                 // class org/jboss/shrinkwrap/descriptor/impl/jbossmodule13/DependenciesTypeImpl
      13: dup
      14: aload_0
      15: ldc           #10                 // String dependencies
      17: aload_0
      18: getfield      #4                  // Field childNode:Lorg/jboss/shrinkwrap/descriptor/spi/node/Node;
      21: aload_1
      22: invokespecial #12                 // Method org/jboss/shrinkwrap/descriptor/impl/jbossmodule13/DependenciesTypeImpl."<init>":(Ljava/lang/Object;Ljava/lang/String;Lorg/jboss/shrinkwrap/descriptor/spi/node/Node;Lorg/jboss/shrinkwrap/descriptor/spi/node/Node;)V
      25: astore_2
      26: aload_2
      27: areturn

  public org.jboss.shrinkwrap.descriptor.api.jbossmodule13.ModuleType<T> removeDependencies();
    Code:
       0: aload_0
       1: getfield      #4                  // Field childNode:Lorg/jboss/shrinkwrap/descriptor/spi/node/Node;
       4: ldc           #10                 // String dependencies
       6: invokevirtual #9                  // Method org/jboss/shrinkwrap/descriptor/spi/node/Node.removeChildren:(Ljava/lang/String;)Ljava/util/List;
       9: pop
      10: aload_0
      11: areturn

  public org.jboss.shrinkwrap.descriptor.api.jbossmodule13.ResourcesType<org.jboss.shrinkwrap.descriptor.api.jbossmodule13.ModuleType<T>> getOrCreateResources();
    Code:
       0: aload_0
       1: getfield      #4                  // Field childNode:Lorg/jboss/shrinkwrap/descriptor/spi/node/Node;
       4: ldc           #13                 // String resources
       6: invokevirtual #6                  // Method org/jboss/shrinkwrap/descriptor/spi/node/Node.getOrCreate:(Ljava/lang/String;)Lorg/jboss/shrinkwrap/descriptor/spi/node/Node;
       9: astore_1
      10: new           #14                 // class org/jboss/shrinkwrap/descriptor/impl/jbossmodule13/ResourcesTypeImpl
      13: dup
      14: aload_0
      15: ldc           #13                 // String resources
      17: aload_0
      18: getfield      #4                  // Field childNode:Lorg/jboss/shrinkwrap/descriptor/spi/node/Node;
      21: aload_1
      22: invokespecial #15                 // Method org/jboss/shrinkwrap/descriptor/impl/jbossmodule13/ResourcesTypeImpl."<init>":(Ljava/lang/Object;Ljava/lang/String;Lorg/jboss/shrinkwrap/descriptor/spi/node/Node;Lorg/jboss/shrinkwrap/descriptor/spi/node/Node;)V
      25: astore_2
      26: aload_2
      27: areturn

  public org.jboss.shrinkwrap.descriptor.api.jbossmodule13.ModuleType<T> removeResources();
    Code:
       0: aload_0
       1: getfield      #4                  // Field childNode:Lorg/jboss/shrinkwrap/descriptor/spi/node/Node;
       4: ldc           #13                 // String resources
       6: invokevirtual #9                  // Method org/jboss/shrinkwrap/descriptor/spi/node/Node.removeChildren:(Ljava/lang/String;)Ljava/util/List;
       9: pop
      10: aload_0
      11: areturn

  public org.jboss.shrinkwrap.descriptor.api.jbossmodule13.ClassNameType<org.jboss.shrinkwrap.descriptor.api.jbossmodule13.ModuleType<T>> getOrCreateMainClass();
    Code:
       0: aload_0
       1: getfield      #4                  // Field childNode:Lorg/jboss/shrinkwrap/descriptor/spi/node/Node;
       4: ldc           #16                 // String main-class
       6: invokevirtual #6                  // Method org/jboss/shrinkwrap/descriptor/spi/node/Node.getOrCreate:(Ljava/lang/String;)Lorg/jboss/shrinkwrap/descriptor/spi/node/Node;
       9: astore_1
      10: new           #17                 // class org/jboss/shrinkwrap/descriptor/impl/jbossmodule13/ClassNameTypeImpl
      13: dup
      14: aload_0
      15: ldc           #16                 // String main-class
      17: aload_0
      18: getfield      #4                  // Field childNode:Lorg/jboss/shrinkwrap/descriptor/spi/node/Node;
      21: aload_1
      22: invokespecial #18                 // Method org/jboss/shrinkwrap/descriptor/impl/jbossmodule13/ClassNameTypeImpl."<init>":(Ljava/lang/Object;Ljava/lang/String;Lorg/jboss/shrinkwrap/descriptor/spi/node/Node;Lorg/jboss/shrinkwrap/descriptor/spi/node/Node;)V
      25: astore_2
      26: aload_2
      27: areturn

  public org.jboss.shrinkwrap.descriptor.api.jbossmodule13.ModuleType<T> removeMainClass();
    Code:
       0: aload_0
       1: getfield      #4                  // Field childNode:Lorg/jboss/shrinkwrap/descriptor/spi/node/Node;
       4: ldc           #16                 // String main-class
       6: invokevirtual #9                  // Method org/jboss/shrinkwrap/descriptor/spi/node/Node.removeChildren:(Ljava/lang/String;)Ljava/util/List;
       9: pop
      10: aload_0
      11: areturn

  public org.jboss.shrinkwrap.descriptor.api.jbossmodule13.PropertyListType<org.jboss.shrinkwrap.descriptor.api.jbossmodule13.ModuleType<T>> getOrCreateProperties();
    Code:
       0: aload_0
       1: getfield      #4                  // Field childNode:Lorg/jboss/shrinkwrap/descriptor/spi/node/Node;
       4: ldc           #19                 // String properties
       6: invokevirtual #6                  // Method org/jboss/shrinkwrap/descriptor/spi/node/Node.getOrCreate:(Ljava/lang/String;)Lorg/jboss/shrinkwrap/descriptor/spi/node/Node;
       9: astore_1
      10: new           #20                 // class org/jboss/shrinkwrap/descriptor/impl/jbossmodule13/PropertyListTypeImpl
      13: dup
      14: aload_0
      15: ldc           #19                 // String properties
      17: aload_0
      18: getfield      #4                  // Field childNode:Lorg/jboss/shrinkwrap/descriptor/spi/node/Node;
      21: aload_1
      22: invokespecial #21                 // Method org/jboss/shrinkwrap/descriptor/impl/jbossmodule13/PropertyListTypeImpl."<init>":(Ljava/lang/Object;Ljava/lang/String;Lorg/jboss/shrinkwrap/descriptor/spi/node/Node;Lorg/jboss/shrinkwrap/descriptor/spi/node/Node;)V
      25: astore_2
      26: aload_2
      27: areturn

  public org.jboss.shrinkwrap.descriptor.api.jbossmodule13.ModuleType<T> removeProperties();
    Code:
       0: aload_0
       1: getfield      #4                  // Field childNode:Lorg/jboss/shrinkwrap/descriptor/spi/node/Node;
       4: ldc           #19                 // String properties
       6: invokevirtual #9                  // Method org/jboss/shrinkwrap/descriptor/spi/node/Node.removeChildren:(Ljava/lang/String;)Ljava/util/List;
       9: pop
      10: aload_0
      11: areturn

  public org.jboss.shrinkwrap.descriptor.api.jbossmodule13.PermissionsType<org.jboss.shrinkwrap.descriptor.api.jbossmodule13.ModuleType<T>> getOrCreatePermissions();
    Code:
       0: aload_0
       1: getfield      #4                  // Field childNode:Lorg/jboss/shrinkwrap/descriptor/spi/node/Node;
       4: ldc           #22                 // String permissions
       6: invokevirtual #6                  // Method org/jboss/shrinkwrap/descriptor/spi/node/Node.getOrCreate:(Ljava/lang/String;)Lorg/jboss/shrinkwrap/descriptor/spi/node/Node;
       9: astore_1
      10: new           #23                 // class org/jboss/shrinkwrap/descriptor/impl/jbossmodule13/PermissionsTypeImpl
      13: dup
      14: aload_0
      15: ldc           #22                 // String permissions
      17: aload_0
      18: getfield      #4                  // Field childNode:Lorg/jboss/shrinkwrap/descriptor/spi/node/Node;
      21: aload_1
      22: invokespecial #24                 // Method org/jboss/shrinkwrap/descriptor/impl/jbossmodule13/PermissionsTypeImpl."<init>":(Ljava/lang/Object;Ljava/lang/String;Lorg/jboss/shrinkwrap/descriptor/spi/node/Node;Lorg/jboss/shrinkwrap/descriptor/spi/node/Node;)V
      25: astore_2
      26: aload_2
      27: areturn

  public org.jboss.shrinkwrap.descriptor.api.jbossmodule13.ModuleType<T> removePermissions();
    Code:
       0: aload_0
       1: getfield      #4                  // Field childNode:Lorg/jboss/shrinkwrap/descriptor/spi/node/Node;
       4: ldc           #22                 // String permissions
       6: invokevirtual #9                  // Method org/jboss/shrinkwrap/descriptor/spi/node/Node.removeChildren:(Ljava/lang/String;)Ljava/util/List;
       9: pop
      10: aload_0
      11: areturn

  public org.jboss.shrinkwrap.descriptor.api.jbossmodule13.ModuleType<T> name(java.lang.String);
    Code:
       0: aload_0
       1: getfield      #4                  // Field childNode:Lorg/jboss/shrinkwrap/descriptor/spi/node/Node;
       4: ldc           #25                 // String name
       6: aload_1
       7: invokevirtual #26                 // Method org/jboss/shrinkwrap/descriptor/spi/node/Node.attribute:(Ljava/lang/String;Ljava/lang/String;)Lorg/jboss/shrinkwrap/descriptor/spi/node/Node;
      10: pop
      11: aload_0
      12: areturn

  public java.lang.String getName();
    Code:
       0: aload_0
       1: getfield      #4                  // Field childNode:Lorg/jboss/shrinkwrap/descriptor/spi/node/Node;
       4: ldc           #25                 // String name
       6: invokevirtual #27                 // Method org/jboss/shrinkwrap/descriptor/spi/node/Node.getAttribute:(Ljava/lang/String;)Ljava/lang/String;
       9: areturn

  public org.jboss.shrinkwrap.descriptor.api.jbossmodule13.ModuleType<T> removeName();
    Code:
       0: aload_0
       1: getfield      #4                  // Field childNode:Lorg/jboss/shrinkwrap/descriptor/spi/node/Node;
       4: ldc           #25                 // String name
       6: invokevirtual #28                 // Method org/jboss/shrinkwrap/descriptor/spi/node/Node.removeAttribute:(Ljava/lang/String;)Ljava/lang/String;
       9: pop
      10: aload_0
      11: areturn

  public org.jboss.shrinkwrap.descriptor.api.jbossmodule13.ModuleType<T> slot(java.lang.String);
    Code:
       0: aload_0
       1: getfield      #4                  // Field childNode:Lorg/jboss/shrinkwrap/descriptor/spi/node/Node;
       4: ldc           #29                 // String slot
       6: aload_1
       7: invokevirtual #26                 // Method org/jboss/shrinkwrap/descriptor/spi/node/Node.attribute:(Ljava/lang/String;Ljava/lang/String;)Lorg/jboss/shrinkwrap/descriptor/spi/node/Node;
      10: pop
      11: aload_0
      12: areturn

  public java.lang.String getSlot();
    Code:
       0: aload_0
       1: getfield      #4                  // Field childNode:Lorg/jboss/shrinkwrap/descriptor/spi/node/Node;
       4: ldc           #29                 // String slot
       6: invokevirtual #27                 // Method org/jboss/shrinkwrap/descriptor/spi/node/Node.getAttribute:(Ljava/lang/String;)Ljava/lang/String;
       9: areturn

  public org.jboss.shrinkwrap.descriptor.api.jbossmodule13.ModuleType<T> removeSlot();
    Code:
       0: aload_0
       1: getfield      #4                  // Field childNode:Lorg/jboss/shrinkwrap/descriptor/spi/node/Node;
       4: ldc           #29                 // String slot
       6: invokevirtual #28                 // Method org/jboss/shrinkwrap/descriptor/spi/node/Node.removeAttribute:(Ljava/lang/String;)Ljava/lang/String;
       9: pop
      10: aload_0
      11: areturn
}
