Compiled from "collation.java"
public class org.apache.jena.sparql.function.library.collation extends org.apache.jena.sparql.function.FunctionBase2 {
  public org.apache.jena.sparql.function.library.collation();
    Code:
       0: aload_0
       1: invokespecial #1                  // Method org/apache/jena/sparql/function/FunctionBase2."<init>":()V
       4: return

  public org.apache.jena.sparql.expr.NodeValue exec(org.apache.jena.sparql.expr.NodeValue, org.apache.jena.sparql.expr.NodeValue);
    Code:
       0: aload_1
       1: invokevirtual #2                  // Method org/apache/jena/sparql/expr/NodeValue.asNode:()Lorg/apache/jena/graph/Node;
       4: invokestatic  #3                  // Method org/apache/jena/sparql/expr/nodevalue/NodeFunctions.str:(Lorg/apache/jena/graph/Node;)Ljava/lang/String;
       7: astore_3
       8: aload_2
       9: aload_3
      10: invokestatic  #4                  // Method org/apache/jena/sparql/expr/nodevalue/NodeFunctions.sortKey:(Lorg/apache/jena/sparql/expr/NodeValue;Ljava/lang/String;)Lorg/apache/jena/sparql/expr/NodeValue;
      13: areturn
}
