Compiled from "PicketBoxSecurityIntegration.java"
public class org.jboss.jca.core.security.picketbox.PicketBoxSecurityIntegration implements org.jboss.jca.core.spi.security.SecurityIntegration {
  public org.jboss.jca.core.security.picketbox.PicketBoxSecurityIntegration();
    Code:
       0: aload_0
       1: invokespecial #1                  // Method java/lang/Object."<init>":()V
       4: return

  public org.jboss.jca.core.spi.security.SecurityContext createSecurityContext(java.lang.String) throws java.lang.Exception;
    Code:
       0: aload_1
       1: invokestatic  #2                  // Method org/jboss/security/SecurityContextFactory.createSecurityContext:(Ljava/lang/String;)Lorg/jboss/security/SecurityContext;
       4: astore_2
       5: new           #3                  // class org/jboss/jca/core/security/picketbox/PicketBoxSecurityContext
       8: dup
       9: aload_2
      10: invokespecial #4                  // Method org/jboss/jca/core/security/picketbox/PicketBoxSecurityContext."<init>":(Lorg/jboss/security/SecurityContext;)V
      13: areturn

  public org.jboss.jca.core.spi.security.SecurityContext getSecurityContext();
    Code:
       0: invokestatic  #5                  // Method org/jboss/security/SecurityContextAssociation.getSecurityContext:()Lorg/jboss/security/SecurityContext;
       3: astore_1
       4: aload_1
       5: ifnonnull     10
       8: aconst_null
       9: areturn
      10: new           #3                  // class org/jboss/jca/core/security/picketbox/PicketBoxSecurityContext
      13: dup
      14: aload_1
      15: invokespecial #4                  // Method org/jboss/jca/core/security/picketbox/PicketBoxSecurityContext."<init>":(Lorg/jboss/security/SecurityContext;)V
      18: areturn

  public void setSecurityContext(org.jboss.jca.core.spi.security.SecurityContext);
    Code:
       0: aload_1
       1: ifnonnull     11
       4: aconst_null
       5: invokestatic  #6                  // Method org/jboss/security/SecurityContextAssociation.setSecurityContext:(Lorg/jboss/security/SecurityContext;)V
       8: goto          60
      11: aload_1
      12: instanceof    #3                  // class org/jboss/jca/core/security/picketbox/PicketBoxSecurityContext
      15: ifeq          33
      18: aload_1
      19: checkcast     #3                  // class org/jboss/jca/core/security/picketbox/PicketBoxSecurityContext
      22: astore_2
      23: aload_2
      24: invokevirtual #7                  // Method org/jboss/jca/core/security/picketbox/PicketBoxSecurityContext.getDelegator:()Lorg/jboss/security/SecurityContext;
      27: invokestatic  #6                  // Method org/jboss/security/SecurityContextAssociation.setSecurityContext:(Lorg/jboss/security/SecurityContext;)V
      30: goto          60
      33: new           #8                  // class java/lang/IllegalArgumentException
      36: dup
      37: new           #9                  // class java/lang/StringBuilder
      40: dup
      41: invokespecial #10                 // Method java/lang/StringBuilder."<init>":()V
      44: ldc           #11                 // String Invalid SecurityContext:
      46: invokevirtual #12                 // Method java/lang/StringBuilder.append:(Ljava/lang/String;)Ljava/lang/StringBuilder;
      49: aload_1
      50: invokevirtual #13                 // Method java/lang/StringBuilder.append:(Ljava/lang/Object;)Ljava/lang/StringBuilder;
      53: invokevirtual #14                 // Method java/lang/StringBuilder.toString:()Ljava/lang/String;
      56: invokespecial #15                 // Method java/lang/IllegalArgumentException."<init>":(Ljava/lang/String;)V
      59: athrow
      60: return

  public javax.security.auth.callback.CallbackHandler createCallbackHandler();
    Code:
       0: new           #16                 // class org/jboss/jca/core/security/picketbox/PicketBoxCallbackHandler
       3: dup
       4: invokespecial #17                 // Method org/jboss/jca/core/security/picketbox/PicketBoxCallbackHandler."<init>":()V
       7: areturn

  public javax.security.auth.callback.CallbackHandler createCallbackHandler(org.jboss.jca.core.spi.security.Callback);
    Code:
       0: new           #16                 // class org/jboss/jca/core/security/picketbox/PicketBoxCallbackHandler
       3: dup
       4: aload_1
       5: invokespecial #18                 // Method org/jboss/jca/core/security/picketbox/PicketBoxCallbackHandler."<init>":(Lorg/jboss/jca/core/spi/security/Callback;)V
       8: areturn
}
