Compiled from "OracleDBRecordReader.java"
public class org.apache.hadoop.mapreduce.lib.db.OracleDBRecordReader<T extends org.apache.hadoop.mapreduce.lib.db.DBWritable> extends org.apache.hadoop.mapreduce.lib.db.DBRecordReader<T> {
  public static final java.lang.String SESSION_TIMEZONE_KEY;

  private static final org.slf4j.Logger LOG;

  public org.apache.hadoop.mapreduce.lib.db.OracleDBRecordReader(org.apache.hadoop.mapreduce.lib.db.DBInputFormat$DBInputSplit, java.lang.Class<T>, org.apache.hadoop.conf.Configuration, java.sql.Connection, org.apache.hadoop.mapreduce.lib.db.DBConfiguration, java.lang.String, java.lang.String[], java.lang.String) throws java.sql.SQLException;
    Code:
       0: aload_0
       1: aload_1
       2: aload_2
       3: aload_3
       4: aload         4
       6: aload         5
       8: aload         6
      10: aload         7
      12: aload         8
      14: invokespecial #1                  // Method org/apache/hadoop/mapreduce/lib/db/DBRecordReader."<init>":(Lorg/apache/hadoop/mapreduce/lib/db/DBInputFormat$DBInputSplit;Ljava/lang/Class;Lorg/apache/hadoop/conf/Configuration;Ljava/sql/Connection;Lorg/apache/hadoop/mapreduce/lib/db/DBConfiguration;Ljava/lang/String;[Ljava/lang/String;Ljava/lang/String;)V
      17: aload_3
      18: aload         4
      20: invokestatic  #2                  // Method setSessionTimeZone:(Lorg/apache/hadoop/conf/Configuration;Ljava/sql/Connection;)V
      23: return

  protected java.lang.String getSelectQuery();
    Code:
       0: new           #3                  // class java/lang/StringBuilder
       3: dup
       4: invokespecial #4                  // Method java/lang/StringBuilder."<init>":()V
       7: astore_1
       8: aload_0
       9: invokevirtual #5                  // Method getDBConf:()Lorg/apache/hadoop/mapreduce/lib/db/DBConfiguration;
      12: astore_2
      13: aload_0
      14: invokevirtual #6                  // Method getConditions:()Ljava/lang/String;
      17: astore_3
      18: aload_0
      19: invokevirtual #7                  // Method getTableName:()Ljava/lang/String;
      22: astore        4
      24: aload_0
      25: invokevirtual #8                  // Method getFieldNames:()[Ljava/lang/String;
      28: astore        5
      30: aload_2
      31: invokevirtual #9                  // Method org/apache/hadoop/mapreduce/lib/db/DBConfiguration.getInputQuery:()Ljava/lang/String;
      34: ifnonnull     156
      37: aload_1
      38: ldc           #10                 // String SELECT
      40: invokevirtual #11                 // Method java/lang/StringBuilder.append:(Ljava/lang/String;)Ljava/lang/StringBuilder;
      43: pop
      44: iconst_0
      45: istore        6
      47: iload         6
      49: aload         5
      51: arraylength
      52: if_icmpge     88
      55: aload_1
      56: aload         5
      58: iload         6
      60: aaload
      61: invokevirtual #11                 // Method java/lang/StringBuilder.append:(Ljava/lang/String;)Ljava/lang/StringBuilder;
      64: pop
      65: iload         6
      67: aload         5
      69: arraylength
      70: iconst_1
      71: isub
      72: if_icmpeq     82
      75: aload_1
      76: ldc           #12                 // String ,
      78: invokevirtual #11                 // Method java/lang/StringBuilder.append:(Ljava/lang/String;)Ljava/lang/StringBuilder;
      81: pop
      82: iinc          6, 1
      85: goto          47
      88: aload_1
      89: ldc           #13                 // String  FROM
      91: invokevirtual #11                 // Method java/lang/StringBuilder.append:(Ljava/lang/String;)Ljava/lang/StringBuilder;
      94: aload         4
      96: invokevirtual #11                 // Method java/lang/StringBuilder.append:(Ljava/lang/String;)Ljava/lang/StringBuilder;
      99: pop
     100: aload_3
     101: ifnull        122
     104: aload_3
     105: invokevirtual #14                 // Method java/lang/String.length:()I
     108: ifle          122
     111: aload_1
     112: ldc           #15                 // String  WHERE
     114: invokevirtual #11                 // Method java/lang/StringBuilder.append:(Ljava/lang/String;)Ljava/lang/StringBuilder;
     117: aload_3
     118: invokevirtual #11                 // Method java/lang/StringBuilder.append:(Ljava/lang/String;)Ljava/lang/StringBuilder;
     121: pop
     122: aload_2
     123: invokevirtual #16                 // Method org/apache/hadoop/mapreduce/lib/db/DBConfiguration.getInputOrderBy:()Ljava/lang/String;
     126: astore        6
     128: aload         6
     130: ifnull        153
     133: aload         6
     135: invokevirtual #14                 // Method java/lang/String.length:()I
     138: ifle          153
     141: aload_1
     142: ldc           #17                 // String  ORDER BY
     144: invokevirtual #11                 // Method java/lang/StringBuilder.append:(Ljava/lang/String;)Ljava/lang/StringBuilder;
     147: aload         6
     149: invokevirtual #11                 // Method java/lang/StringBuilder.append:(Ljava/lang/String;)Ljava/lang/StringBuilder;
     152: pop
     153: goto          165
     156: aload_1
     157: aload_2
     158: invokevirtual #9                  // Method org/apache/hadoop/mapreduce/lib/db/DBConfiguration.getInputQuery:()Ljava/lang/String;
     161: invokevirtual #11                 // Method java/lang/StringBuilder.append:(Ljava/lang/String;)Ljava/lang/StringBuilder;
     164: pop
     165: aload_0
     166: invokevirtual #18                 // Method getSplit:()Lorg/apache/hadoop/mapreduce/lib/db/DBInputFormat$DBInputSplit;
     169: astore        6
     171: aload         6
     173: invokevirtual #19                 // Method org/apache/hadoop/mapreduce/lib/db/DBInputFormat$DBInputSplit.getLength:()J
     176: lconst_0
     177: lcmp
     178: ifle          239
     181: aload_1
     182: invokevirtual #20                 // Method java/lang/StringBuilder.toString:()Ljava/lang/String;
     185: astore        7
     187: new           #3                  // class java/lang/StringBuilder
     190: dup
     191: invokespecial #4                  // Method java/lang/StringBuilder."<init>":()V
     194: astore_1
     195: aload_1
     196: ldc           #21                 // String SELECT * FROM (SELECT a.*,ROWNUM dbif_rno FROM (
     198: invokevirtual #11                 // Method java/lang/StringBuilder.append:(Ljava/lang/String;)Ljava/lang/StringBuilder;
     201: pop
     202: aload_1
     203: aload         7
     205: invokevirtual #11                 // Method java/lang/StringBuilder.append:(Ljava/lang/String;)Ljava/lang/StringBuilder;
     208: pop
     209: aload_1
     210: ldc           #22                 // String  ) a WHERE rownum <=
     212: invokevirtual #11                 // Method java/lang/StringBuilder.append:(Ljava/lang/String;)Ljava/lang/StringBuilder;
     215: aload         6
     217: invokevirtual #23                 // Method org/apache/hadoop/mapreduce/lib/db/DBInputFormat$DBInputSplit.getEnd:()J
     220: invokevirtual #24                 // Method java/lang/StringBuilder.append:(J)Ljava/lang/StringBuilder;
     223: pop
     224: aload_1
     225: ldc           #25                 // String  ) WHERE dbif_rno >
     227: invokevirtual #11                 // Method java/lang/StringBuilder.append:(Ljava/lang/String;)Ljava/lang/StringBuilder;
     230: aload         6
     232: invokevirtual #26                 // Method org/apache/hadoop/mapreduce/lib/db/DBInputFormat$DBInputSplit.getStart:()J
     235: invokevirtual #24                 // Method java/lang/StringBuilder.append:(J)Ljava/lang/StringBuilder;
     238: pop
     239: goto          244
     242: astore        6
     244: aload_1
     245: invokevirtual #20                 // Method java/lang/StringBuilder.toString:()Ljava/lang/String;
     248: areturn
    Exception table:
       from    to  target type
         165   239   242   Class java/io/IOException

  public static void setSessionTimeZone(org.apache.hadoop.conf.Configuration, java.sql.Connection) throws java.sql.SQLException;
    Code:
       0: aload_1
       1: invokevirtual #28                 // Method java/lang/Object.getClass:()Ljava/lang/Class;
       4: ldc           #29                 // String setSessionTimeZone
       6: iconst_1
       7: anewarray     #30                 // class java/lang/Class
      10: dup
      11: iconst_0
      12: ldc           #31                 // class java/lang/String
      14: aastore
      15: invokevirtual #32                 // Method java/lang/Class.getMethod:(Ljava/lang/String;[Ljava/lang/Class;)Ljava/lang/reflect/Method;
      18: astore_2
      19: goto          66
      22: astore_3
      23: getstatic     #34                 // Field LOG:Lorg/slf4j/Logger;
      26: new           #3                  // class java/lang/StringBuilder
      29: dup
      30: invokespecial #4                  // Method java/lang/StringBuilder."<init>":()V
      33: ldc           #35                 // String Could not find method setSessionTimeZone in
      35: invokevirtual #11                 // Method java/lang/StringBuilder.append:(Ljava/lang/String;)Ljava/lang/StringBuilder;
      38: aload_1
      39: invokevirtual #28                 // Method java/lang/Object.getClass:()Ljava/lang/Class;
      42: invokevirtual #36                 // Method java/lang/Class.getName:()Ljava/lang/String;
      45: invokevirtual #11                 // Method java/lang/StringBuilder.append:(Ljava/lang/String;)Ljava/lang/StringBuilder;
      48: invokevirtual #20                 // Method java/lang/StringBuilder.toString:()Ljava/lang/String;
      51: aload_3
      52: invokeinterface #37,  3           // InterfaceMethod org/slf4j/Logger.error:(Ljava/lang/String;Ljava/lang/Throwable;)V
      57: new           #38                 // class java/sql/SQLException
      60: dup
      61: aload_3
      62: invokespecial #39                 // Method java/sql/SQLException."<init>":(Ljava/lang/Throwable;)V
      65: athrow
      66: aload_0
      67: ldc           #41                 // String oracle.sessionTimeZone
      69: ldc           #42                 // String GMT
      71: invokevirtual #43                 // Method org/apache/hadoop/conf/Configuration.get:(Ljava/lang/String;Ljava/lang/String;)Ljava/lang/String;
      74: astore_3
      75: aload_2
      76: iconst_1
      77: invokevirtual #44                 // Method java/lang/reflect/Method.setAccessible:(Z)V
      80: aload_2
      81: aload_1
      82: iconst_1
      83: anewarray     #45                 // class java/lang/Object
      86: dup
      87: iconst_0
      88: aload_3
      89: aastore
      90: invokevirtual #46                 // Method java/lang/reflect/Method.invoke:(Ljava/lang/Object;[Ljava/lang/Object;)Ljava/lang/Object;
      93: pop
      94: getstatic     #34                 // Field LOG:Lorg/slf4j/Logger;
      97: new           #3                  // class java/lang/StringBuilder
     100: dup
     101: invokespecial #4                  // Method java/lang/StringBuilder."<init>":()V
     104: ldc           #47                 // String Time zone has been set to
     106: invokevirtual #11                 // Method java/lang/StringBuilder.append:(Ljava/lang/String;)Ljava/lang/StringBuilder;
     109: aload_3
     110: invokevirtual #11                 // Method java/lang/StringBuilder.append:(Ljava/lang/String;)Ljava/lang/StringBuilder;
     113: invokevirtual #20                 // Method java/lang/StringBuilder.toString:()Ljava/lang/String;
     116: invokeinterface #48,  2           // InterfaceMethod org/slf4j/Logger.info:(Ljava/lang/String;)V
     121: goto          210
     124: astore        4
     126: getstatic     #34                 // Field LOG:Lorg/slf4j/Logger;
     129: new           #3                  // class java/lang/StringBuilder
     132: dup
     133: invokespecial #4                  // Method java/lang/StringBuilder."<init>":()V
     136: ldc           #49                 // String Time zone
     138: invokevirtual #11                 // Method java/lang/StringBuilder.append:(Ljava/lang/String;)Ljava/lang/StringBuilder;
     141: aload_3
     142: invokevirtual #11                 // Method java/lang/StringBuilder.append:(Ljava/lang/String;)Ljava/lang/StringBuilder;
     145: ldc           #50                 // String  could not be set on Oracle database.
     147: invokevirtual #11                 // Method java/lang/StringBuilder.append:(Ljava/lang/String;)Ljava/lang/StringBuilder;
     150: invokevirtual #20                 // Method java/lang/StringBuilder.toString:()Ljava/lang/String;
     153: invokeinterface #51,  2           // InterfaceMethod org/slf4j/Logger.warn:(Ljava/lang/String;)V
     158: getstatic     #34                 // Field LOG:Lorg/slf4j/Logger;
     161: ldc           #52                 // String Setting default time zone: GMT
     163: invokeinterface #51,  2           // InterfaceMethod org/slf4j/Logger.warn:(Ljava/lang/String;)V
     168: aload_2
     169: aload_1
     170: iconst_1
     171: anewarray     #45                 // class java/lang/Object
     174: dup
     175: iconst_0
     176: ldc           #42                 // String GMT
     178: aastore
     179: invokevirtual #46                 // Method java/lang/reflect/Method.invoke:(Ljava/lang/Object;[Ljava/lang/Object;)Ljava/lang/Object;
     182: pop
     183: goto          210
     186: astore        5
     188: getstatic     #34                 // Field LOG:Lorg/slf4j/Logger;
     191: ldc           #53                 // String Could not set time zone for oracle connection
     193: aload         5
     195: invokeinterface #37,  3           // InterfaceMethod org/slf4j/Logger.error:(Ljava/lang/String;Ljava/lang/Throwable;)V
     200: new           #38                 // class java/sql/SQLException
     203: dup
     204: aload         4
     206: invokespecial #39                 // Method java/sql/SQLException."<init>":(Ljava/lang/Throwable;)V
     209: athrow
     210: return
    Exception table:
       from    to  target type
           0    19    22   Class java/lang/Exception
          75   121   124   Class java/lang/Exception
         168   183   186   Class java/lang/Exception

  static {};
    Code:
       0: ldc           #40                 // class org/apache/hadoop/mapreduce/lib/db/OracleDBRecordReader
       2: invokestatic  #54                 // Method org/slf4j/LoggerFactory.getLogger:(Ljava/lang/Class;)Lorg/slf4j/Logger;
       5: putstatic     #34                 // Field LOG:Lorg/slf4j/Logger;
       8: return
}
