Compiled from "SubscriptionStateHandler.java"
class io.mantisrx.server.worker.SubscriptionStateHandler {
  private static final org.slf4j.Logger logger;

  private final java.util.concurrent.atomic.AtomicReference<java.util.concurrent.ScheduledFuture> timedOutExitFutureRef;

  private final java.lang.String jobId;

  private final io.mantisrx.server.master.client.MantisMasterClientApi masterClientApi;

  private final java.util.concurrent.ScheduledThreadPoolExecutor executor;

  private final long subscriptionTimeoutSecs;

  private final long minRuntimeSecs;

  private long startedAt;

  io.mantisrx.server.worker.SubscriptionStateHandler(java.lang.String, io.mantisrx.server.master.client.MantisMasterClientApi, long, long);
    Code:
       0: aload_0
       1: invokespecial #1                  // Method java/lang/Object."<init>":()V
       4: aload_0
       5: new           #2                  // class java/util/concurrent/atomic/AtomicReference
       8: dup
       9: invokespecial #3                  // Method java/util/concurrent/atomic/AtomicReference."<init>":()V
      12: putfield      #4                  // Field timedOutExitFutureRef:Ljava/util/concurrent/atomic/AtomicReference;
      15: aload_0
      16: invokestatic  #5                  // Method java/lang/System.currentTimeMillis:()J
      19: putfield      #6                  // Field startedAt:J
      22: aload_0
      23: aload_1
      24: putfield      #7                  // Field jobId:Ljava/lang/String;
      27: aload_0
      28: aload_2
      29: putfield      #8                  // Field masterClientApi:Lio/mantisrx/server/master/client/MantisMasterClientApi;
      32: aload_0
      33: lload_3
      34: putfield      #9                  // Field subscriptionTimeoutSecs:J
      37: aload_0
      38: lload         5
      40: putfield      #10                 // Field minRuntimeSecs:J
      43: aload_0
      44: aload_0
      45: getfield      #9                  // Field subscriptionTimeoutSecs:J
      48: lconst_0
      49: lcmp
      50: ifle          64
      53: new           #11                 // class java/util/concurrent/ScheduledThreadPoolExecutor
      56: dup
      57: iconst_1
      58: invokespecial #12                 // Method java/util/concurrent/ScheduledThreadPoolExecutor."<init>":(I)V
      61: goto          65
      64: aconst_null
      65: putfield      #13                 // Field executor:Ljava/util/concurrent/ScheduledThreadPoolExecutor;
      68: return

  void start();
    Code:
       0: aload_0
       1: invokestatic  #5                  // Method java/lang/System.currentTimeMillis:()J
       4: putfield      #6                  // Field startedAt:J
       7: aload_0
       8: invokevirtual #14                 // Method setIsUnsubscribed:()V
      11: return

  private long evalSubscriberTimeoutSecs();
    Code:
       0: aload_0
       1: getfield      #10                 // Field minRuntimeSecs:J
       4: invokestatic  #5                  // Method java/lang/System.currentTimeMillis:()J
       7: aload_0
       8: getfield      #6                  // Field startedAt:J
      11: lsub
      12: ldc2_w        #15                 // long 1000l
      15: ldiv
      16: lsub
      17: aload_0
      18: getfield      #9                  // Field subscriptionTimeoutSecs:J
      21: invokestatic  #17                 // Method java/lang/Math.max:(JJ)J
      24: lreturn

  synchronized void setIsUnsubscribed();
    Code:
       0: aload_0
       1: getfield      #13                 // Field executor:Ljava/util/concurrent/ScheduledThreadPoolExecutor;
       4: ifnonnull     8
       7: return
       8: aload_0
       9: getfield      #4                  // Field timedOutExitFutureRef:Ljava/util/concurrent/atomic/AtomicReference;
      12: invokevirtual #18                 // Method java/util/concurrent/atomic/AtomicReference.get:()Ljava/lang/Object;
      15: ifnonnull     87
      18: aload_0
      19: getfield      #4                  // Field timedOutExitFutureRef:Ljava/util/concurrent/atomic/AtomicReference;
      22: aload_0
      23: getfield      #13                 // Field executor:Ljava/util/concurrent/ScheduledThreadPoolExecutor;
      26: aload_0
      27: invokedynamic #19,  0             // InvokeDynamic #0:run:(Lio/mantisrx/server/worker/SubscriptionStateHandler;)Ljava/lang/Runnable;
      32: aload_0
      33: invokespecial #20                 // Method evalSubscriberTimeoutSecs:()J
      36: getstatic     #21                 // Field java/util/concurrent/TimeUnit.SECONDS:Ljava/util/concurrent/TimeUnit;
      39: invokevirtual #22                 // Method java/util/concurrent/ScheduledThreadPoolExecutor.schedule:(Ljava/lang/Runnable;JLjava/util/concurrent/TimeUnit;)Ljava/util/concurrent/ScheduledFuture;
      42: invokevirtual #23                 // Method java/util/concurrent/atomic/AtomicReference.set:(Ljava/lang/Object;)V
      45: getstatic     #24                 // Field logger:Lorg/slf4j/Logger;
      48: new           #25                 // class java/lang/StringBuilder
      51: dup
      52: invokespecial #26                 // Method java/lang/StringBuilder."<init>":()V
      55: ldc           #27                 // String Setup future job kill (in
      57: invokevirtual #28                 // Method java/lang/StringBuilder.append:(Ljava/lang/String;)Ljava/lang/StringBuilder;
      60: aload_0
      61: getfield      #9                  // Field subscriptionTimeoutSecs:J
      64: invokevirtual #29                 // Method java/lang/StringBuilder.append:(J)Ljava/lang/StringBuilder;
      67: ldc           #30                 // String  secs) upon no subscribers for ephemeral job
      69: invokevirtual #28                 // Method java/lang/StringBuilder.append:(Ljava/lang/String;)Ljava/lang/StringBuilder;
      72: aload_0
      73: getfield      #7                  // Field jobId:Ljava/lang/String;
      76: invokevirtual #28                 // Method java/lang/StringBuilder.append:(Ljava/lang/String;)Ljava/lang/StringBuilder;
      79: invokevirtual #31                 // Method java/lang/StringBuilder.toString:()Ljava/lang/String;
      82: invokeinterface #32,  2           // InterfaceMethod org/slf4j/Logger.info:(Ljava/lang/String;)V
      87: return

  synchronized void setIsSubscribed();
    Code:
       0: aload_0
       1: getfield      #13                 // Field executor:Ljava/util/concurrent/ScheduledThreadPoolExecutor;
       4: ifnonnull     8
       7: return
       8: aload_0
       9: getfield      #4                  // Field timedOutExitFutureRef:Ljava/util/concurrent/atomic/AtomicReference;
      12: aconst_null
      13: invokevirtual #33                 // Method java/util/concurrent/atomic/AtomicReference.getAndSet:(Ljava/lang/Object;)Ljava/lang/Object;
      16: checkcast     #34                 // class java/util/concurrent/ScheduledFuture
      19: astore_1
      20: aload_1
      21: ifnull        80
      24: aload_1
      25: invokeinterface #35,  1           // InterfaceMethod java/util/concurrent/ScheduledFuture.isCancelled:()Z
      30: ifne          80
      33: aload_1
      34: invokeinterface #36,  1           // InterfaceMethod java/util/concurrent/ScheduledFuture.isDone:()Z
      39: ifne          80
      42: getstatic     #24                 // Field logger:Lorg/slf4j/Logger;
      45: new           #25                 // class java/lang/StringBuilder
      48: dup
      49: invokespecial #26                 // Method java/lang/StringBuilder."<init>":()V
      52: ldc           #37                 // String Cancelled future kill upon active subscriptions of ephemeral job
      54: invokevirtual #28                 // Method java/lang/StringBuilder.append:(Ljava/lang/String;)Ljava/lang/StringBuilder;
      57: aload_0
      58: getfield      #7                  // Field jobId:Ljava/lang/String;
      61: invokevirtual #28                 // Method java/lang/StringBuilder.append:(Ljava/lang/String;)Ljava/lang/StringBuilder;
      64: invokevirtual #31                 // Method java/lang/StringBuilder.toString:()Ljava/lang/String;
      67: invokeinterface #32,  2           // InterfaceMethod org/slf4j/Logger.info:(Ljava/lang/String;)V
      72: aload_1
      73: iconst_1
      74: invokeinterface #38,  2           // InterfaceMethod java/util/concurrent/ScheduledFuture.cancel:(Z)Z
      79: pop
      80: return

  private void lambda$setIsUnsubscribed$0();
    Code:
       0: new           #2                  // class java/util/concurrent/atomic/AtomicReference
       3: dup
       4: invokespecial #3                  // Method java/util/concurrent/atomic/AtomicReference."<init>":()V
       7: astore_1
       8: getstatic     #24                 // Field logger:Lorg/slf4j/Logger;
      11: ldc           #39                 // String Calling master to kill due to subscription timeout
      13: invokeinterface #32,  2           // InterfaceMethod org/slf4j/Logger.info:(Ljava/lang/String;)V
      18: aload_0
      19: getfield      #8                  // Field masterClientApi:Lio/mantisrx/server/master/client/MantisMasterClientApi;
      22: aload_0
      23: getfield      #7                  // Field jobId:Ljava/lang/String;
      26: ldc           #40                 // String MantisWorker
      28: new           #25                 // class java/lang/StringBuilder
      31: dup
      32: invokespecial #26                 // Method java/lang/StringBuilder."<init>":()V
      35: ldc           #41                 // String No subscriptions for
      37: invokevirtual #28                 // Method java/lang/StringBuilder.append:(Ljava/lang/String;)Ljava/lang/StringBuilder;
      40: aload_0
      41: getfield      #9                  // Field subscriptionTimeoutSecs:J
      44: invokevirtual #29                 // Method java/lang/StringBuilder.append:(J)Ljava/lang/StringBuilder;
      47: ldc           #42                 // String  secs
      49: invokevirtual #28                 // Method java/lang/StringBuilder.append:(Ljava/lang/String;)Ljava/lang/StringBuilder;
      52: invokevirtual #31                 // Method java/lang/StringBuilder.toString:()Ljava/lang/String;
      55: invokevirtual #43                 // Method io/mantisrx/server/master/client/MantisMasterClientApi.killJob:(Ljava/lang/String;Ljava/lang/String;Ljava/lang/String;)Lrx/Observable;
      58: invokevirtual #44                 // Method rx/Observable.subscribe:()Lrx/Subscription;
      61: astore_2
      62: ldc2_w        #45                 // long 60000l
      65: invokestatic  #47                 // Method java/lang/Thread.sleep:(J)V
      68: goto          83
      71: astore_3
      72: getstatic     #24                 // Field logger:Lorg/slf4j/Logger;
      75: ldc           #49                 // String Interrupted while waiting to kill job upon timeout, cancelling
      77: invokeinterface #32,  2           // InterfaceMethod org/slf4j/Logger.info:(Ljava/lang/String;)V
      82: return
      83: aload_2
      84: invokeinterface #50,  1           // InterfaceMethod rx/Subscription.unsubscribe:()V
      89: goto          8
    Exception table:
       from    to  target type
          62    68    71   Class java/lang/InterruptedException

  static {};
    Code:
       0: ldc           #51                 // class io/mantisrx/server/worker/SubscriptionStateHandler
       2: invokestatic  #52                 // Method org/slf4j/LoggerFactory.getLogger:(Ljava/lang/Class;)Lorg/slf4j/Logger;
       5: putstatic     #24                 // Field logger:Lorg/slf4j/Logger;
       8: return
}
