Compiled from "SequenceNotFoundException.java"
public class net.sf.derquinsej.hib3.seq.SequenceNotFoundException extends java.lang.RuntimeException {
  private static final long serialVersionUID;

  private final java.lang.String id;

  public net.sf.derquinsej.hib3.seq.SequenceNotFoundException(java.lang.String);
    Code:
       0: aload_0
       1: invokespecial #1                  // Method java/lang/RuntimeException."<init>":()V
       4: aload_0
       5: aload_1
       6: putfield      #2                  // Field id:Ljava/lang/String;
       9: return

  public java.lang.String getId();
    Code:
       0: aload_0
       1: getfield      #2                  // Field id:Ljava/lang/String;
       4: areturn

  public java.lang.String getMessage();
    Code:
       0: new           #3                  // class java/lang/StringBuilder
       3: dup
       4: invokespecial #4                  // Method java/lang/StringBuilder."<init>":()V
       7: ldc           #5                  // String Sequence not found: [
       9: invokevirtual #6                  // Method java/lang/StringBuilder.append:(Ljava/lang/String;)Ljava/lang/StringBuilder;
      12: aload_0
      13: getfield      #2                  // Field id:Ljava/lang/String;
      16: invokevirtual #6                  // Method java/lang/StringBuilder.append:(Ljava/lang/String;)Ljava/lang/StringBuilder;
      19: bipush        93
      21: invokevirtual #7                  // Method java/lang/StringBuilder.append:(C)Ljava/lang/StringBuilder;
      24: invokevirtual #8                  // Method java/lang/StringBuilder.toString:()Ljava/lang/String;
      27: areturn
}
