Compiled from "DsXaPool.java"
public final class org.jboss.jca.common.api.metadata.ds.DsXaPool$Tag extends java.lang.Enum<org.jboss.jca.common.api.metadata.ds.DsXaPool$Tag> {
  public static final org.jboss.jca.common.api.metadata.ds.DsXaPool$Tag UNKNOWN;

  public static final org.jboss.jca.common.api.metadata.ds.DsXaPool$Tag MIN_POOL_SIZE;

  public static final org.jboss.jca.common.api.metadata.ds.DsXaPool$Tag INITIAL_POOL_SIZE;

  public static final org.jboss.jca.common.api.metadata.ds.DsXaPool$Tag MAX_POOL_SIZE;

  public static final org.jboss.jca.common.api.metadata.ds.DsXaPool$Tag PREFILL;

  public static final org.jboss.jca.common.api.metadata.ds.DsXaPool$Tag FAIR;

  public static final org.jboss.jca.common.api.metadata.ds.DsXaPool$Tag USE_STRICT_MIN;

  public static final org.jboss.jca.common.api.metadata.ds.DsXaPool$Tag FLUSH_STRATEGY;

  public static final org.jboss.jca.common.api.metadata.ds.DsXaPool$Tag ALLOW_MULTIPLE_USERS;

  public static final org.jboss.jca.common.api.metadata.ds.DsXaPool$Tag CAPACITY;

  public static final org.jboss.jca.common.api.metadata.ds.DsXaPool$Tag CONNECTION_LISTENER;

  public static final org.jboss.jca.common.api.metadata.ds.DsXaPool$Tag IS_SAME_RM_OVERRIDE;

  public static final org.jboss.jca.common.api.metadata.ds.DsXaPool$Tag INTERLEAVING;

  public static final org.jboss.jca.common.api.metadata.ds.DsXaPool$Tag PAD_XID;

  public static final org.jboss.jca.common.api.metadata.ds.DsXaPool$Tag WRAP_XA_RESOURCE;

  public static final org.jboss.jca.common.api.metadata.ds.DsXaPool$Tag NO_TX_SEPARATE_POOLS;

  private java.lang.String name;

  private static final java.util.Map<java.lang.String, org.jboss.jca.common.api.metadata.ds.DsXaPool$Tag> MAP;

  private static final org.jboss.jca.common.api.metadata.ds.DsXaPool$Tag[] $VALUES;

  public static org.jboss.jca.common.api.metadata.ds.DsXaPool$Tag[] values();
    Code:
       0: getstatic     #1                  // Field $VALUES:[Lorg/jboss/jca/common/api/metadata/ds/DsXaPool$Tag;
       3: invokevirtual #2                  // Method "[Lorg/jboss/jca/common/api/metadata/ds/DsXaPool$Tag;".clone:()Ljava/lang/Object;
       6: checkcast     #3                  // class "[Lorg/jboss/jca/common/api/metadata/ds/DsXaPool$Tag;"
       9: areturn

  public static org.jboss.jca.common.api.metadata.ds.DsXaPool$Tag valueOf(java.lang.String);
    Code:
       0: ldc_w         #4                  // class org/jboss/jca/common/api/metadata/ds/DsXaPool$Tag
       3: aload_0
       4: invokestatic  #5                  // Method java/lang/Enum.valueOf:(Ljava/lang/Class;Ljava/lang/String;)Ljava/lang/Enum;
       7: checkcast     #4                  // class org/jboss/jca/common/api/metadata/ds/DsXaPool$Tag
      10: areturn

  private org.jboss.jca.common.api.metadata.ds.DsXaPool$Tag(java.lang.String);
    Code:
       0: aload_0
       1: aload_1
       2: iload_2
       3: invokespecial #6                  // Method java/lang/Enum."<init>":(Ljava/lang/String;I)V
       6: aload_0
       7: aload_3
       8: putfield      #7                  // Field name:Ljava/lang/String;
      11: return

  public java.lang.String getLocalName();
    Code:
       0: aload_0
       1: getfield      #7                  // Field name:Ljava/lang/String;
       4: areturn

  public java.lang.String toString();
    Code:
       0: aload_0
       1: getfield      #7                  // Field name:Ljava/lang/String;
       4: areturn

  org.jboss.jca.common.api.metadata.ds.DsXaPool$Tag value(java.lang.String);
    Code:
       0: aload_0
       1: aload_1
       2: putfield      #7                  // Field name:Ljava/lang/String;
       5: aload_0
       6: areturn

  public static org.jboss.jca.common.api.metadata.ds.DsXaPool$Tag forName(java.lang.String);
    Code:
       0: getstatic     #8                  // Field MAP:Ljava/util/Map;
       3: aload_0
       4: invokeinterface #9,  2            // InterfaceMethod java/util/Map.get:(Ljava/lang/Object;)Ljava/lang/Object;
       9: checkcast     #4                  // class org/jboss/jca/common/api/metadata/ds/DsXaPool$Tag
      12: astore_1
      13: aload_1
      14: ifnonnull     27
      17: getstatic     #10                 // Field UNKNOWN:Lorg/jboss/jca/common/api/metadata/ds/DsXaPool$Tag;
      20: aload_0
      21: invokevirtual #11                 // Method value:(Ljava/lang/String;)Lorg/jboss/jca/common/api/metadata/ds/DsXaPool$Tag;
      24: goto          28
      27: aload_1
      28: areturn

  static {};
    Code:
       0: new           #4                  // class org/jboss/jca/common/api/metadata/ds/DsXaPool$Tag
       3: dup
       4: ldc           #12                 // String UNKNOWN
       6: iconst_0
       7: aconst_null
       8: invokespecial #13                 // Method "<init>":(Ljava/lang/String;ILjava/lang/String;)V
      11: putstatic     #10                 // Field UNKNOWN:Lorg/jboss/jca/common/api/metadata/ds/DsXaPool$Tag;
      14: new           #4                  // class org/jboss/jca/common/api/metadata/ds/DsXaPool$Tag
      17: dup
      18: ldc           #14                 // String MIN_POOL_SIZE
      20: iconst_1
      21: ldc           #15                 // String min-pool-size
      23: invokespecial #13                 // Method "<init>":(Ljava/lang/String;ILjava/lang/String;)V
      26: putstatic     #16                 // Field MIN_POOL_SIZE:Lorg/jboss/jca/common/api/metadata/ds/DsXaPool$Tag;
      29: new           #4                  // class org/jboss/jca/common/api/metadata/ds/DsXaPool$Tag
      32: dup
      33: ldc           #17                 // String INITIAL_POOL_SIZE
      35: iconst_2
      36: ldc           #18                 // String initial-pool-size
      38: invokespecial #13                 // Method "<init>":(Ljava/lang/String;ILjava/lang/String;)V
      41: putstatic     #19                 // Field INITIAL_POOL_SIZE:Lorg/jboss/jca/common/api/metadata/ds/DsXaPool$Tag;
      44: new           #4                  // class org/jboss/jca/common/api/metadata/ds/DsXaPool$Tag
      47: dup
      48: ldc           #20                 // String MAX_POOL_SIZE
      50: iconst_3
      51: ldc           #21                 // String max-pool-size
      53: invokespecial #13                 // Method "<init>":(Ljava/lang/String;ILjava/lang/String;)V
      56: putstatic     #22                 // Field MAX_POOL_SIZE:Lorg/jboss/jca/common/api/metadata/ds/DsXaPool$Tag;
      59: new           #4                  // class org/jboss/jca/common/api/metadata/ds/DsXaPool$Tag
      62: dup
      63: ldc           #23                 // String PREFILL
      65: iconst_4
      66: ldc           #24                 // String prefill
      68: invokespecial #13                 // Method "<init>":(Ljava/lang/String;ILjava/lang/String;)V
      71: putstatic     #25                 // Field PREFILL:Lorg/jboss/jca/common/api/metadata/ds/DsXaPool$Tag;
      74: new           #4                  // class org/jboss/jca/common/api/metadata/ds/DsXaPool$Tag
      77: dup
      78: ldc           #26                 // String FAIR
      80: iconst_5
      81: ldc           #27                 // String fair
      83: invokespecial #13                 // Method "<init>":(Ljava/lang/String;ILjava/lang/String;)V
      86: putstatic     #28                 // Field FAIR:Lorg/jboss/jca/common/api/metadata/ds/DsXaPool$Tag;
      89: new           #4                  // class org/jboss/jca/common/api/metadata/ds/DsXaPool$Tag
      92: dup
      93: ldc           #29                 // String USE_STRICT_MIN
      95: bipush        6
      97: ldc           #30                 // String use-strict-min
      99: invokespecial #13                 // Method "<init>":(Ljava/lang/String;ILjava/lang/String;)V
     102: putstatic     #31                 // Field USE_STRICT_MIN:Lorg/jboss/jca/common/api/metadata/ds/DsXaPool$Tag;
     105: new           #4                  // class org/jboss/jca/common/api/metadata/ds/DsXaPool$Tag
     108: dup
     109: ldc           #32                 // String FLUSH_STRATEGY
     111: bipush        7
     113: ldc           #33                 // String flush-strategy
     115: invokespecial #13                 // Method "<init>":(Ljava/lang/String;ILjava/lang/String;)V
     118: putstatic     #34                 // Field FLUSH_STRATEGY:Lorg/jboss/jca/common/api/metadata/ds/DsXaPool$Tag;
     121: new           #4                  // class org/jboss/jca/common/api/metadata/ds/DsXaPool$Tag
     124: dup
     125: ldc           #35                 // String ALLOW_MULTIPLE_USERS
     127: bipush        8
     129: ldc           #36                 // String allow-multiple-users
     131: invokespecial #13                 // Method "<init>":(Ljava/lang/String;ILjava/lang/String;)V
     134: putstatic     #37                 // Field ALLOW_MULTIPLE_USERS:Lorg/jboss/jca/common/api/metadata/ds/DsXaPool$Tag;
     137: new           #4                  // class org/jboss/jca/common/api/metadata/ds/DsXaPool$Tag
     140: dup
     141: ldc           #38                 // String CAPACITY
     143: bipush        9
     145: ldc           #39                 // String capacity
     147: invokespecial #13                 // Method "<init>":(Ljava/lang/String;ILjava/lang/String;)V
     150: putstatic     #40                 // Field CAPACITY:Lorg/jboss/jca/common/api/metadata/ds/DsXaPool$Tag;
     153: new           #4                  // class org/jboss/jca/common/api/metadata/ds/DsXaPool$Tag
     156: dup
     157: ldc           #41                 // String CONNECTION_LISTENER
     159: bipush        10
     161: ldc           #42                 // String connection-listener
     163: invokespecial #13                 // Method "<init>":(Ljava/lang/String;ILjava/lang/String;)V
     166: putstatic     #43                 // Field CONNECTION_LISTENER:Lorg/jboss/jca/common/api/metadata/ds/DsXaPool$Tag;
     169: new           #4                  // class org/jboss/jca/common/api/metadata/ds/DsXaPool$Tag
     172: dup
     173: ldc           #44                 // String IS_SAME_RM_OVERRIDE
     175: bipush        11
     177: ldc           #45                 // String is-same-rm-override
     179: invokespecial #13                 // Method "<init>":(Ljava/lang/String;ILjava/lang/String;)V
     182: putstatic     #46                 // Field IS_SAME_RM_OVERRIDE:Lorg/jboss/jca/common/api/metadata/ds/DsXaPool$Tag;
     185: new           #4                  // class org/jboss/jca/common/api/metadata/ds/DsXaPool$Tag
     188: dup
     189: ldc           #47                 // String INTERLEAVING
     191: bipush        12
     193: ldc           #48                 // String interleaving
     195: invokespecial #13                 // Method "<init>":(Ljava/lang/String;ILjava/lang/String;)V
     198: putstatic     #49                 // Field INTERLEAVING:Lorg/jboss/jca/common/api/metadata/ds/DsXaPool$Tag;
     201: new           #4                  // class org/jboss/jca/common/api/metadata/ds/DsXaPool$Tag
     204: dup
     205: ldc           #50                 // String PAD_XID
     207: bipush        13
     209: ldc           #51                 // String pad-xid
     211: invokespecial #13                 // Method "<init>":(Ljava/lang/String;ILjava/lang/String;)V
     214: putstatic     #52                 // Field PAD_XID:Lorg/jboss/jca/common/api/metadata/ds/DsXaPool$Tag;
     217: new           #4                  // class org/jboss/jca/common/api/metadata/ds/DsXaPool$Tag
     220: dup
     221: ldc           #53                 // String WRAP_XA_RESOURCE
     223: bipush        14
     225: ldc           #54                 // String wrap-xa-resource
     227: invokespecial #13                 // Method "<init>":(Ljava/lang/String;ILjava/lang/String;)V
     230: putstatic     #55                 // Field WRAP_XA_RESOURCE:Lorg/jboss/jca/common/api/metadata/ds/DsXaPool$Tag;
     233: new           #4                  // class org/jboss/jca/common/api/metadata/ds/DsXaPool$Tag
     236: dup
     237: ldc           #56                 // String NO_TX_SEPARATE_POOLS
     239: bipush        15
     241: ldc           #57                 // String no-tx-separate-pools
     243: invokespecial #13                 // Method "<init>":(Ljava/lang/String;ILjava/lang/String;)V
     246: putstatic     #58                 // Field NO_TX_SEPARATE_POOLS:Lorg/jboss/jca/common/api/metadata/ds/DsXaPool$Tag;
     249: bipush        16
     251: anewarray     #4                  // class org/jboss/jca/common/api/metadata/ds/DsXaPool$Tag
     254: dup
     255: iconst_0
     256: getstatic     #10                 // Field UNKNOWN:Lorg/jboss/jca/common/api/metadata/ds/DsXaPool$Tag;
     259: aastore
     260: dup
     261: iconst_1
     262: getstatic     #16                 // Field MIN_POOL_SIZE:Lorg/jboss/jca/common/api/metadata/ds/DsXaPool$Tag;
     265: aastore
     266: dup
     267: iconst_2
     268: getstatic     #19                 // Field INITIAL_POOL_SIZE:Lorg/jboss/jca/common/api/metadata/ds/DsXaPool$Tag;
     271: aastore
     272: dup
     273: iconst_3
     274: getstatic     #22                 // Field MAX_POOL_SIZE:Lorg/jboss/jca/common/api/metadata/ds/DsXaPool$Tag;
     277: aastore
     278: dup
     279: iconst_4
     280: getstatic     #25                 // Field PREFILL:Lorg/jboss/jca/common/api/metadata/ds/DsXaPool$Tag;
     283: aastore
     284: dup
     285: iconst_5
     286: getstatic     #28                 // Field FAIR:Lorg/jboss/jca/common/api/metadata/ds/DsXaPool$Tag;
     289: aastore
     290: dup
     291: bipush        6
     293: getstatic     #31                 // Field USE_STRICT_MIN:Lorg/jboss/jca/common/api/metadata/ds/DsXaPool$Tag;
     296: aastore
     297: dup
     298: bipush        7
     300: getstatic     #34                 // Field FLUSH_STRATEGY:Lorg/jboss/jca/common/api/metadata/ds/DsXaPool$Tag;
     303: aastore
     304: dup
     305: bipush        8
     307: getstatic     #37                 // Field ALLOW_MULTIPLE_USERS:Lorg/jboss/jca/common/api/metadata/ds/DsXaPool$Tag;
     310: aastore
     311: dup
     312: bipush        9
     314: getstatic     #40                 // Field CAPACITY:Lorg/jboss/jca/common/api/metadata/ds/DsXaPool$Tag;
     317: aastore
     318: dup
     319: bipush        10
     321: getstatic     #43                 // Field CONNECTION_LISTENER:Lorg/jboss/jca/common/api/metadata/ds/DsXaPool$Tag;
     324: aastore
     325: dup
     326: bipush        11
     328: getstatic     #46                 // Field IS_SAME_RM_OVERRIDE:Lorg/jboss/jca/common/api/metadata/ds/DsXaPool$Tag;
     331: aastore
     332: dup
     333: bipush        12
     335: getstatic     #49                 // Field INTERLEAVING:Lorg/jboss/jca/common/api/metadata/ds/DsXaPool$Tag;
     338: aastore
     339: dup
     340: bipush        13
     342: getstatic     #52                 // Field PAD_XID:Lorg/jboss/jca/common/api/metadata/ds/DsXaPool$Tag;
     345: aastore
     346: dup
     347: bipush        14
     349: getstatic     #55                 // Field WRAP_XA_RESOURCE:Lorg/jboss/jca/common/api/metadata/ds/DsXaPool$Tag;
     352: aastore
     353: dup
     354: bipush        15
     356: getstatic     #58                 // Field NO_TX_SEPARATE_POOLS:Lorg/jboss/jca/common/api/metadata/ds/DsXaPool$Tag;
     359: aastore
     360: putstatic     #1                  // Field $VALUES:[Lorg/jboss/jca/common/api/metadata/ds/DsXaPool$Tag;
     363: new           #59                 // class java/util/HashMap
     366: dup
     367: invokespecial #60                 // Method java/util/HashMap."<init>":()V
     370: astore_0
     371: invokestatic  #61                 // Method values:()[Lorg/jboss/jca/common/api/metadata/ds/DsXaPool$Tag;
     374: astore_1
     375: aload_1
     376: arraylength
     377: istore_2
     378: iconst_0
     379: istore_3
     380: iload_3
     381: iload_2
     382: if_icmpge     419
     385: aload_1
     386: iload_3
     387: aaload
     388: astore        4
     390: aload         4
     392: invokevirtual #62                 // Method getLocalName:()Ljava/lang/String;
     395: astore        5
     397: aload         5
     399: ifnull        413
     402: aload_0
     403: aload         5
     405: aload         4
     407: invokeinterface #63,  3           // InterfaceMethod java/util/Map.put:(Ljava/lang/Object;Ljava/lang/Object;)Ljava/lang/Object;
     412: pop
     413: iinc          3, 1
     416: goto          380
     419: aload_0
     420: putstatic     #8                  // Field MAP:Ljava/util/Map;
     423: return
}
