Compiled from "AmmoniteFrontEnd.scala"
public final class ammonite.repl.AmmoniteFrontEnd$$anonfun$5 extends scala.runtime.AbstractFunction1<ammonite.terminal.TermState, ammonite.terminal.TermAction> implements scala.Serializable {
  public static final long serialVersionUID;

  public final ammonite.terminal.TermAction apply(ammonite.terminal.TermState);
    Code:
       0: aload_1
       1: astore_2
       2: getstatic     #25                 // Field ammonite/terminal/TermState$.MODULE$:Lammonite/terminal/TermState$;
       5: aload_2
       6: invokevirtual #29                 // Method ammonite/terminal/TermState$.unapply:(Lammonite/terminal/TermState;)Lscala/Option;
       9: astore_3
      10: aload_3
      11: invokevirtual #35                 // Method scala/Option.isEmpty:()Z
      14: ifeq          26
      17: new           #37                 // class scala/MatchError
      20: dup
      21: aload_2
      22: invokespecial #41                 // Method scala/MatchError."<init>":(Ljava/lang/Object;)V
      25: athrow
      26: aload_3
      27: invokevirtual #45                 // Method scala/Option.get:()Ljava/lang/Object;
      30: checkcast     #47                 // class scala/Tuple4
      33: invokevirtual #50                 // Method scala/Tuple4._1:()Ljava/lang/Object;
      36: checkcast     #52                 // class ammonite/terminal/LazyList
      39: astore        4
      41: aload_3
      42: invokevirtual #45                 // Method scala/Option.get:()Ljava/lang/Object;
      45: checkcast     #47                 // class scala/Tuple4
      48: invokevirtual #55                 // Method scala/Tuple4._2:()Ljava/lang/Object;
      51: checkcast     #57                 // class scala/collection/immutable/Vector
      54: astore        5
      56: aload_3
      57: invokevirtual #45                 // Method scala/Option.get:()Ljava/lang/Object;
      60: checkcast     #47                 // class scala/Tuple4
      63: invokevirtual #60                 // Method scala/Tuple4._3:()Ljava/lang/Object;
      66: invokestatic  #66                 // Method scala/runtime/BoxesRunTime.unboxToInt:(Ljava/lang/Object;)I
      69: istore        6
      71: getstatic     #71                 // Field ammonite/terminal/filters/BasicFilters$.MODULE$:Lammonite/terminal/filters/BasicFilters$;
      74: aload         5
      76: iload         6
      78: aload         4
      80: invokevirtual #75                 // Method ammonite/terminal/filters/BasicFilters$.injectNewLine:(Lscala/collection/immutable/Vector;ILammonite/terminal/LazyList;)Lammonite/terminal/TermState;
      83: astore        7
      85: aload         7
      87: areturn

  public final java.lang.Object apply(java.lang.Object);
    Code:
       0: aload_0
       1: aload_1
       2: checkcast     #87                 // class ammonite/terminal/TermState
       5: invokevirtual #90                 // Method apply:(Lammonite/terminal/TermState;)Lammonite/terminal/TermAction;
       8: areturn

  public ammonite.repl.AmmoniteFrontEnd$$anonfun$5(ammonite.repl.AmmoniteFrontEnd);
    Code:
       0: aload_0
       1: invokespecial #96                 // Method scala/runtime/AbstractFunction1."<init>":()V
       4: return
}
