Compiled from "Highlighter.scala"
public final class ammonite.repl.Highlighter$$anonfun$defaultHighlightIndices$1 extends scala.runtime.AbstractPartialFunction<fastparse.core.Parser<?, java.lang.Object, java.lang.String>, fansi.Attrs> implements scala.Serializable {
  public static final long serialVersionUID;

  private final fansi.Attrs comment$1;

  private final fansi.Attrs type$1;

  private final fansi.Attrs literal$1;

  private final fansi.Attrs keyword$1;

  private final fansi.Attrs reset$1;

  public final <A1 extends fastparse.core.Parser<?, java.lang.Object, java.lang.String>, B1> B1 applyOrElse(A1, scala.Function1<A1, B1>);
    Code:
       0: aload_1
       1: astore_3
       2: getstatic     #31                 // Field scalaparse/Scala$.MODULE$:Lscalaparse/Scala$;
       5: invokevirtual #35                 // Method scalaparse/Scala$.Literals:()Lscalaparse/syntax/Literals$Literals$;
       8: invokevirtual #41                 // Method scalaparse/syntax/Literals$Literals$.Expr:()Lscalaparse/syntax/Literals$Literals$Expr$;
      11: invokevirtual #47                 // Method scalaparse/syntax/Literals$Literals$Expr$.Interp:()Lfastparse/core/Parser;
      14: aload_3
      15: astore        4
      17: dup
      18: ifnonnull     30
      21: pop
      22: aload         4
      24: ifnull        38
      27: goto          44
      30: aload         4
      32: invokevirtual #53                 // Method java/lang/Object.equals:(Ljava/lang/Object;)Z
      35: ifeq          44
      38: iconst_1
      39: istore        5
      41: goto          89
      44: getstatic     #31                 // Field scalaparse/Scala$.MODULE$:Lscalaparse/Scala$;
      47: invokevirtual #35                 // Method scalaparse/Scala$.Literals:()Lscalaparse/syntax/Literals$Literals$;
      50: invokevirtual #57                 // Method scalaparse/syntax/Literals$Literals$.Pat:()Lscalaparse/syntax/Literals$Literals$Pat$;
      53: invokevirtual #60                 // Method scalaparse/syntax/Literals$Literals$Pat$.Interp:()Lfastparse/core/Parser;
      56: aload_3
      57: astore        6
      59: dup
      60: ifnonnull     72
      63: pop
      64: aload         6
      66: ifnull        80
      69: goto          86
      72: aload         6
      74: invokevirtual #53                 // Method java/lang/Object.equals:(Ljava/lang/Object;)Z
      77: ifeq          86
      80: iconst_1
      81: istore        5
      83: goto          89
      86: iconst_0
      87: istore        5
      89: iload         5
      91: ifeq          103
      94: aload_0
      95: getfield      #62                 // Field reset$1:Lfansi/Attrs;
      98: astore        7
     100: goto          319
     103: getstatic     #31                 // Field scalaparse/Scala$.MODULE$:Lscalaparse/Scala$;
     106: invokevirtual #35                 // Method scalaparse/Scala$.Literals:()Lscalaparse/syntax/Literals$Literals$;
     109: invokevirtual #65                 // Method scalaparse/syntax/Literals$Literals$.Comment:()Lfastparse/core/Parser;
     112: aload_3
     113: astore        8
     115: dup
     116: ifnonnull     128
     119: pop
     120: aload         8
     122: ifnull        136
     125: goto          145
     128: aload         8
     130: invokevirtual #53                 // Method java/lang/Object.equals:(Ljava/lang/Object;)Z
     133: ifeq          145
     136: aload_0
     137: getfield      #67                 // Field comment$1:Lfansi/Attrs;
     140: astore        7
     142: goto          319
     145: getstatic     #31                 // Field scalaparse/Scala$.MODULE$:Lscalaparse/Scala$;
     148: invokevirtual #70                 // Method scalaparse/Scala$.ExprLiteral:()Lfastparse/core/Parser;
     151: aload_3
     152: astore        9
     154: dup
     155: ifnonnull     167
     158: pop
     159: aload         9
     161: ifnull        175
     164: goto          184
     167: aload         9
     169: invokevirtual #53                 // Method java/lang/Object.equals:(Ljava/lang/Object;)Z
     172: ifeq          184
     175: aload_0
     176: getfield      #72                 // Field literal$1:Lfansi/Attrs;
     179: astore        7
     181: goto          319
     184: getstatic     #31                 // Field scalaparse/Scala$.MODULE$:Lscalaparse/Scala$;
     187: invokevirtual #75                 // Method scalaparse/Scala$.TypeId:()Lfastparse/core/Parser;
     190: aload_3
     191: astore        10
     193: dup
     194: ifnonnull     206
     197: pop
     198: aload         10
     200: ifnull        214
     203: goto          223
     206: aload         10
     208: invokevirtual #53                 // Method java/lang/Object.equals:(Ljava/lang/Object;)Z
     211: ifeq          223
     214: aload_0
     215: getfield      #77                 // Field type$1:Lfansi/Attrs;
     218: astore        7
     220: goto          319
     223: getstatic     #82                 // Field ammonite/repl/Highlighter$BackTicked$.MODULE$:Lammonite/repl/Highlighter$BackTicked$;
     226: aload_3
     227: invokevirtual #86                 // Method ammonite/repl/Highlighter$BackTicked$.unapplySeq:(Ljava/lang/Object;)Lscala/Option;
     230: astore        11
     232: aload         11
     234: invokevirtual #92                 // Method scala/Option.isEmpty:()Z
     237: ifne          310
     240: aload         11
     242: invokevirtual #96                 // Method scala/Option.get:()Ljava/lang/Object;
     245: ifnull        310
     248: aload         11
     250: invokevirtual #96                 // Method scala/Option.get:()Ljava/lang/Object;
     253: checkcast     #98                 // class scala/collection/LinearSeqOptimized
     256: iconst_1
     257: invokeinterface #102,  2          // InterfaceMethod scala/collection/LinearSeqOptimized.lengthCompare:(I)I
     262: iconst_0
     263: if_icmpne     310
     266: aload         11
     268: invokevirtual #96                 // Method scala/Option.get:()Ljava/lang/Object;
     271: checkcast     #98                 // class scala/collection/LinearSeqOptimized
     274: iconst_0
     275: invokeinterface #106,  2          // InterfaceMethod scala/collection/LinearSeqOptimized.apply:(I)Ljava/lang/Object;
     280: checkcast     #108                // class java/lang/String
     283: astore        12
     285: getstatic     #113                // Field scalaparse/syntax/Identifiers$.MODULE$:Lscalaparse/syntax/Identifiers$;
     288: invokevirtual #117                // Method scalaparse/syntax/Identifiers$.alphaKeywords:()Lscala/collection/Seq;
     291: aload         12
     293: invokeinterface #122,  2          // InterfaceMethod scala/collection/Seq.contains:(Ljava/lang/Object;)Z
     298: ifeq          310
     301: aload_0
     302: getfield      #124                // Field keyword$1:Lfansi/Attrs;
     305: astore        7
     307: goto          319
     310: aload_2
     311: aload_1
     312: invokeinterface #129,  2          // InterfaceMethod scala/Function1.apply:(Ljava/lang/Object;)Ljava/lang/Object;
     317: astore        7
     319: aload         7
     321: areturn

  public final boolean isDefinedAt(fastparse.core.Parser<?, java.lang.Object, java.lang.String>);
    Code:
       0: aload_1
       1: astore_2
       2: getstatic     #31                 // Field scalaparse/Scala$.MODULE$:Lscalaparse/Scala$;
       5: invokevirtual #35                 // Method scalaparse/Scala$.Literals:()Lscalaparse/syntax/Literals$Literals$;
       8: invokevirtual #41                 // Method scalaparse/syntax/Literals$Literals$.Expr:()Lscalaparse/syntax/Literals$Literals$Expr$;
      11: invokevirtual #47                 // Method scalaparse/syntax/Literals$Literals$Expr$.Interp:()Lfastparse/core/Parser;
      14: aload_2
      15: astore_3
      16: dup
      17: ifnonnull     28
      20: pop
      21: aload_3
      22: ifnull        35
      25: goto          41
      28: aload_3
      29: invokevirtual #53                 // Method java/lang/Object.equals:(Ljava/lang/Object;)Z
      32: ifeq          41
      35: iconst_1
      36: istore        4
      38: goto          86
      41: getstatic     #31                 // Field scalaparse/Scala$.MODULE$:Lscalaparse/Scala$;
      44: invokevirtual #35                 // Method scalaparse/Scala$.Literals:()Lscalaparse/syntax/Literals$Literals$;
      47: invokevirtual #57                 // Method scalaparse/syntax/Literals$Literals$.Pat:()Lscalaparse/syntax/Literals$Literals$Pat$;
      50: invokevirtual #60                 // Method scalaparse/syntax/Literals$Literals$Pat$.Interp:()Lfastparse/core/Parser;
      53: aload_2
      54: astore        5
      56: dup
      57: ifnonnull     69
      60: pop
      61: aload         5
      63: ifnull        77
      66: goto          83
      69: aload         5
      71: invokevirtual #53                 // Method java/lang/Object.equals:(Ljava/lang/Object;)Z
      74: ifeq          83
      77: iconst_1
      78: istore        4
      80: goto          86
      83: iconst_0
      84: istore        4
      86: iload         4
      88: ifeq          97
      91: iconst_1
      92: istore        6
      94: goto          295
      97: getstatic     #31                 // Field scalaparse/Scala$.MODULE$:Lscalaparse/Scala$;
     100: invokevirtual #35                 // Method scalaparse/Scala$.Literals:()Lscalaparse/syntax/Literals$Literals$;
     103: invokevirtual #65                 // Method scalaparse/syntax/Literals$Literals$.Comment:()Lfastparse/core/Parser;
     106: aload_2
     107: astore        7
     109: dup
     110: ifnonnull     122
     113: pop
     114: aload         7
     116: ifnull        130
     119: goto          136
     122: aload         7
     124: invokevirtual #53                 // Method java/lang/Object.equals:(Ljava/lang/Object;)Z
     127: ifeq          136
     130: iconst_1
     131: istore        6
     133: goto          295
     136: getstatic     #31                 // Field scalaparse/Scala$.MODULE$:Lscalaparse/Scala$;
     139: invokevirtual #70                 // Method scalaparse/Scala$.ExprLiteral:()Lfastparse/core/Parser;
     142: aload_2
     143: astore        8
     145: dup
     146: ifnonnull     158
     149: pop
     150: aload         8
     152: ifnull        166
     155: goto          172
     158: aload         8
     160: invokevirtual #53                 // Method java/lang/Object.equals:(Ljava/lang/Object;)Z
     163: ifeq          172
     166: iconst_1
     167: istore        6
     169: goto          295
     172: getstatic     #31                 // Field scalaparse/Scala$.MODULE$:Lscalaparse/Scala$;
     175: invokevirtual #75                 // Method scalaparse/Scala$.TypeId:()Lfastparse/core/Parser;
     178: aload_2
     179: astore        9
     181: dup
     182: ifnonnull     194
     185: pop
     186: aload         9
     188: ifnull        202
     191: goto          208
     194: aload         9
     196: invokevirtual #53                 // Method java/lang/Object.equals:(Ljava/lang/Object;)Z
     199: ifeq          208
     202: iconst_1
     203: istore        6
     205: goto          295
     208: getstatic     #82                 // Field ammonite/repl/Highlighter$BackTicked$.MODULE$:Lammonite/repl/Highlighter$BackTicked$;
     211: aload_2
     212: invokevirtual #86                 // Method ammonite/repl/Highlighter$BackTicked$.unapplySeq:(Ljava/lang/Object;)Lscala/Option;
     215: astore        10
     217: aload         10
     219: invokevirtual #92                 // Method scala/Option.isEmpty:()Z
     222: ifne          292
     225: aload         10
     227: invokevirtual #96                 // Method scala/Option.get:()Ljava/lang/Object;
     230: ifnull        292
     233: aload         10
     235: invokevirtual #96                 // Method scala/Option.get:()Ljava/lang/Object;
     238: checkcast     #98                 // class scala/collection/LinearSeqOptimized
     241: iconst_1
     242: invokeinterface #102,  2          // InterfaceMethod scala/collection/LinearSeqOptimized.lengthCompare:(I)I
     247: iconst_0
     248: if_icmpne     292
     251: aload         10
     253: invokevirtual #96                 // Method scala/Option.get:()Ljava/lang/Object;
     256: checkcast     #98                 // class scala/collection/LinearSeqOptimized
     259: iconst_0
     260: invokeinterface #106,  2          // InterfaceMethod scala/collection/LinearSeqOptimized.apply:(I)Ljava/lang/Object;
     265: checkcast     #108                // class java/lang/String
     268: astore        11
     270: getstatic     #113                // Field scalaparse/syntax/Identifiers$.MODULE$:Lscalaparse/syntax/Identifiers$;
     273: invokevirtual #117                // Method scalaparse/syntax/Identifiers$.alphaKeywords:()Lscala/collection/Seq;
     276: aload         11
     278: invokeinterface #122,  2          // InterfaceMethod scala/collection/Seq.contains:(Ljava/lang/Object;)Z
     283: ifeq          292
     286: iconst_1
     287: istore        6
     289: goto          295
     292: iconst_0
     293: istore        6
     295: iload         6
     297: ireturn

  public final boolean isDefinedAt(java.lang.Object);
    Code:
       0: aload_0
       1: aload_1
       2: checkcast     #139                // class fastparse/core/Parser
       5: invokevirtual #143                // Method isDefinedAt:(Lfastparse/core/Parser;)Z
       8: ireturn

  public final java.lang.Object applyOrElse(java.lang.Object, scala.Function1);
    Code:
       0: aload_0
       1: aload_1
       2: checkcast     #139                // class fastparse/core/Parser
       5: aload_2
       6: invokevirtual #148                // Method applyOrElse:(Lfastparse/core/Parser;Lscala/Function1;)Ljava/lang/Object;
       9: areturn

  public ammonite.repl.Highlighter$$anonfun$defaultHighlightIndices$1(fansi.Attrs, fansi.Attrs, fansi.Attrs, fansi.Attrs, fansi.Attrs);
    Code:
       0: aload_0
       1: aload_1
       2: putfield      #67                 // Field comment$1:Lfansi/Attrs;
       5: aload_0
       6: aload_2
       7: putfield      #77                 // Field type$1:Lfansi/Attrs;
      10: aload_0
      11: aload_3
      12: putfield      #72                 // Field literal$1:Lfansi/Attrs;
      15: aload_0
      16: aload         4
      18: putfield      #124                // Field keyword$1:Lfansi/Attrs;
      21: aload_0
      22: aload         5
      24: putfield      #62                 // Field reset$1:Lfansi/Attrs;
      27: aload_0
      28: invokespecial #153                // Method scala/runtime/AbstractPartialFunction."<init>":()V
      31: return
}
