Compiled from "Highlighter.scala"
public class ammonite.repl.Highlighter$BackTicked$ {
  public static final ammonite.repl.Highlighter$BackTicked$ MODULE$;

  public static {};
    Code:
       0: new           #2                  // class ammonite/repl/Highlighter$BackTicked$
       3: invokespecial #12                 // Method "<init>":()V
       6: return

  public scala.Option<scala.collection.immutable.List<java.lang.String>> unapplySeq(java.lang.Object);
    Code:
       0: new           #16                 // class scala/collection/immutable/StringOps
       3: dup
       4: getstatic     #21                 // Field scala/Predef$.MODULE$:Lscala/Predef$;
       7: ldc           #23                 // String `([^`]+)`
       9: invokevirtual #27                 // Method scala/Predef$.augmentString:(Ljava/lang/String;)Ljava/lang/String;
      12: invokespecial #30                 // Method scala/collection/immutable/StringOps."<init>":(Ljava/lang/String;)V
      15: invokevirtual #34                 // Method scala/collection/immutable/StringOps.r:()Lscala/util/matching/Regex;
      18: aload_1
      19: invokevirtual #38                 // Method java/lang/Object.toString:()Ljava/lang/String;
      22: invokevirtual #43                 // Method scala/util/matching/Regex.unapplySeq:(Ljava/lang/CharSequence;)Lscala/Option;
      25: areturn

  public ammonite.repl.Highlighter$BackTicked$();
    Code:
       0: aload_0
       1: invokespecial #47                 // Method java/lang/Object."<init>":()V
       4: aload_0
       5: putstatic     #49                 // Field MODULE$:Lammonite/repl/Highlighter$BackTicked$;
       8: return
}
