Compiled from "AeshConsoleImpl.java"
class org.jboss.aesh.console.AeshConsoleImpl$AeshConsoleCallbackImpl extends org.jboss.aesh.console.AeshConsoleCallback {
  private final org.jboss.aesh.console.AeshConsoleImpl console;

  private org.jboss.aesh.console.command.CommandResult result;

  final org.jboss.aesh.console.AeshConsoleImpl this$0;

  org.jboss.aesh.console.AeshConsoleImpl$AeshConsoleCallbackImpl(org.jboss.aesh.console.AeshConsoleImpl, org.jboss.aesh.console.AeshConsoleImpl);
    Code:
       0: aload_0
       1: aload_1
       2: putfield      #1                  // Field this$0:Lorg/jboss/aesh/console/AeshConsoleImpl;
       5: aload_0
       6: invokespecial #2                  // Method org/jboss/aesh/console/AeshConsoleCallback."<init>":()V
       9: aload_0
      10: aload_2
      11: putfield      #3                  // Field console:Lorg/jboss/aesh/console/AeshConsoleImpl;
      14: return

  public int execute(org.jboss.aesh.console.ConsoleOperation) throws java.lang.InterruptedException;
    Code:
       0: aload_1
       1: ifnull        508
       4: aload_1
       5: invokevirtual #4                  // Method org/jboss/aesh/console/ConsoleOperation.getBuffer:()Ljava/lang/String;
       8: invokevirtual #5                  // Method java/lang/String.trim:()Ljava/lang/String;
      11: invokevirtual #6                  // Method java/lang/String.length:()I
      14: ifle          508
      17: aconst_null
      18: astore_2
      19: aload_1
      20: invokevirtual #4                  // Method org/jboss/aesh/console/ConsoleOperation.getBuffer:()Ljava/lang/String;
      23: invokestatic  #7                  // Method org/jboss/aesh/parser/Parser.findAllWords:(Ljava/lang/String;)Lorg/jboss/aesh/parser/AeshLine;
      26: astore_3
      27: aload_0
      28: getfield      #1                  // Field this$0:Lorg/jboss/aesh/console/AeshConsoleImpl;
      31: aload_3
      32: aload_1
      33: invokevirtual #4                  // Method org/jboss/aesh/console/ConsoleOperation.getBuffer:()Ljava/lang/String;
      36: invokestatic  #8                  // Method org/jboss/aesh/console/AeshConsoleImpl.access$100:(Lorg/jboss/aesh/console/AeshConsoleImpl;Lorg/jboss/aesh/parser/AeshLine;Ljava/lang/String;)Lorg/jboss/aesh/console/command/container/CommandContainer;
      39: astore        4
      41: aconst_null
      42: astore        5
      44: aload         4
      46: invokeinterface #9,  1            // InterfaceMethod org/jboss/aesh/console/command/container/CommandContainer.getParser:()Lorg/jboss/aesh/cl/parser/CommandLineParser;
      51: invokeinterface #10,  1           // InterfaceMethod org/jboss/aesh/cl/parser/CommandLineParser.getProcessedCommand:()Lorg/jboss/aesh/cl/internal/ProcessedCommand;
      56: invokevirtual #11                 // Method org/jboss/aesh/cl/internal/ProcessedCommand.getResultHandler:()Lorg/jboss/aesh/cl/result/ResultHandler;
      59: astore_2
      60: aload         4
      62: aload_3
      63: aload_0
      64: getfield      #1                  // Field this$0:Lorg/jboss/aesh/console/AeshConsoleImpl;
      67: invokestatic  #12                 // Method org/jboss/aesh/console/AeshConsoleImpl.access$200:(Lorg/jboss/aesh/console/AeshConsoleImpl;)Lorg/jboss/aesh/console/InvocationProviders;
      70: aload_0
      71: getfield      #1                  // Field this$0:Lorg/jboss/aesh/console/AeshConsoleImpl;
      74: invokevirtual #13                 // Method org/jboss/aesh/console/AeshConsoleImpl.getAeshContext:()Lorg/jboss/aesh/console/AeshContext;
      77: aload_0
      78: getfield      #1                  // Field this$0:Lorg/jboss/aesh/console/AeshConsoleImpl;
      81: invokestatic  #14                 // Method org/jboss/aesh/console/AeshConsoleImpl.access$500:(Lorg/jboss/aesh/console/AeshConsoleImpl;)Lorg/jboss/aesh/console/command/invocation/CommandInvocationServices;
      84: aload_0
      85: getfield      #1                  // Field this$0:Lorg/jboss/aesh/console/AeshConsoleImpl;
      88: invokestatic  #15                 // Method org/jboss/aesh/console/AeshConsoleImpl.access$400:(Lorg/jboss/aesh/console/AeshConsoleImpl;)Ljava/lang/String;
      91: invokevirtual #16                 // Method org/jboss/aesh/console/command/invocation/CommandInvocationServices.getCommandInvocationProvider:(Ljava/lang/String;)Lorg/jboss/aesh/console/command/invocation/CommandInvocationProvider;
      94: new           #17                 // class org/jboss/aesh/console/command/invocation/AeshCommandInvocation
      97: dup
      98: aload_0
      99: getfield      #3                  // Field console:Lorg/jboss/aesh/console/AeshConsoleImpl;
     102: aload_1
     103: invokevirtual #18                 // Method org/jboss/aesh/console/ConsoleOperation.getControlOperator:()Lorg/jboss/aesh/console/operator/ControlOperator;
     106: aload_1
     107: invokevirtual #19                 // Method org/jboss/aesh/console/ConsoleOperation.getPid:()I
     110: aload_0
     111: invokespecial #20                 // Method org/jboss/aesh/console/command/invocation/AeshCommandInvocation."<init>":(Lorg/jboss/aesh/console/AeshConsoleImpl;Lorg/jboss/aesh/console/operator/ControlOperator;ILorg/jboss/aesh/console/ConsoleCallback;)V
     114: invokeinterface #21,  2           // InterfaceMethod org/jboss/aesh/console/command/invocation/CommandInvocationProvider.enhanceCommandInvocation:(Lorg/jboss/aesh/console/command/invocation/CommandInvocation;)Lorg/jboss/aesh/console/command/invocation/CommandInvocation;
     119: invokeinterface #22,  5           // InterfaceMethod org/jboss/aesh/console/command/container/CommandContainer.executeCommand:(Lorg/jboss/aesh/parser/AeshLine;Lorg/jboss/aesh/console/InvocationProviders;Lorg/jboss/aesh/console/AeshContext;Lorg/jboss/aesh/console/command/invocation/CommandInvocation;)Lorg/jboss/aesh/console/command/container/CommandContainerResult;
     124: astore        6
     126: aload_0
     127: aload         6
     129: invokevirtual #23                 // Method org/jboss/aesh/console/command/container/CommandContainerResult.getCommandResult:()Lorg/jboss/aesh/console/command/CommandResult;
     132: putfield      #24                 // Field result:Lorg/jboss/aesh/console/command/CommandResult;
     135: aload_0
     136: getfield      #24                 // Field result:Lorg/jboss/aesh/console/command/CommandResult;
     139: getstatic     #25                 // Field org/jboss/aesh/console/command/CommandResult.SUCCESS:Lorg/jboss/aesh/console/command/CommandResult;
     142: if_acmpne     158
     145: aload_2
     146: ifnull        158
     149: aload_2
     150: invokeinterface #26,  1           // InterfaceMethod org/jboss/aesh/cl/result/ResultHandler.onSuccess:()V
     155: goto          172
     158: aload_2
     159: ifnull        172
     162: aload_2
     163: aload_0
     164: getfield      #24                 // Field result:Lorg/jboss/aesh/console/command/CommandResult;
     167: invokeinterface #27,  2           // InterfaceMethod org/jboss/aesh/cl/result/ResultHandler.onFailure:(Lorg/jboss/aesh/console/command/CommandResult;)V
     172: aload         4
     174: ifnull        267
     177: aload         5
     179: ifnull        204
     182: aload         4
     184: invokeinterface #28,  1           // InterfaceMethod org/jboss/aesh/console/command/container/CommandContainer.close:()V
     189: goto          267
     192: astore        6
     194: aload         5
     196: aload         6
     198: invokevirtual #30                 // Method java/lang/Throwable.addSuppressed:(Ljava/lang/Throwable;)V
     201: goto          267
     204: aload         4
     206: invokeinterface #28,  1           // InterfaceMethod org/jboss/aesh/console/command/container/CommandContainer.close:()V
     211: goto          267
     214: astore        6
     216: aload         6
     218: astore        5
     220: aload         6
     222: athrow
     223: astore        7
     225: aload         4
     227: ifnull        264
     230: aload         5
     232: ifnull        257
     235: aload         4
     237: invokeinterface #28,  1           // InterfaceMethod org/jboss/aesh/console/command/container/CommandContainer.close:()V
     242: goto          264
     245: astore        8
     247: aload         5
     249: aload         8
     251: invokevirtual #30                 // Method java/lang/Throwable.addSuppressed:(Ljava/lang/Throwable;)V
     254: goto          264
     257: aload         4
     259: invokeinterface #28,  1           // InterfaceMethod org/jboss/aesh/console/command/container/CommandContainer.close:()V
     264: aload         7
     266: athrow
     267: goto          505
     270: astore        4
     272: aload_0
     273: getfield      #1                  // Field this$0:Lorg/jboss/aesh/console/AeshConsoleImpl;
     276: invokevirtual #34                 // Method org/jboss/aesh/console/AeshConsoleImpl.getShell:()Lorg/jboss/aesh/terminal/Shell;
     279: invokeinterface #35,  1           // InterfaceMethod org/jboss/aesh/terminal/Shell.out:()Ljava/io/PrintStream;
     284: aload         4
     286: invokevirtual #36                 // Method java/lang/Exception.getMessage:()Ljava/lang/String;
     289: invokevirtual #37                 // Method java/io/PrintStream.println:(Ljava/lang/String;)V
     292: aload_0
     293: getstatic     #38                 // Field org/jboss/aesh/console/command/CommandResult.FAILURE:Lorg/jboss/aesh/console/command/CommandResult;
     296: putfield      #24                 // Field result:Lorg/jboss/aesh/console/command/CommandResult;
     299: aload_2
     300: ifnull        315
     303: aload_2
     304: aload_0
     305: getfield      #24                 // Field result:Lorg/jboss/aesh/console/command/CommandResult;
     308: aload         4
     310: invokeinterface #39,  3           // InterfaceMethod org/jboss/aesh/cl/result/ResultHandler.onValidationFailure:(Lorg/jboss/aesh/console/command/CommandResult;Ljava/lang/Exception;)V
     315: goto          505
     318: astore        4
     320: aload_0
     321: getfield      #1                  // Field this$0:Lorg/jboss/aesh/console/AeshConsoleImpl;
     324: invokevirtual #34                 // Method org/jboss/aesh/console/AeshConsoleImpl.getShell:()Lorg/jboss/aesh/terminal/Shell;
     327: invokeinterface #35,  1           // InterfaceMethod org/jboss/aesh/terminal/Shell.out:()Ljava/io/PrintStream;
     332: aload         4
     334: invokevirtual #41                 // Method org/jboss/aesh/console/command/CommandNotFoundException.getMessage:()Ljava/lang/String;
     337: invokevirtual #37                 // Method java/io/PrintStream.println:(Ljava/lang/String;)V
     340: aload_0
     341: getstatic     #38                 // Field org/jboss/aesh/console/command/CommandResult.FAILURE:Lorg/jboss/aesh/console/command/CommandResult;
     344: putfield      #24                 // Field result:Lorg/jboss/aesh/console/command/CommandResult;
     347: aload_0
     348: getfield      #1                  // Field this$0:Lorg/jboss/aesh/console/AeshConsoleImpl;
     351: invokestatic  #42                 // Method org/jboss/aesh/console/AeshConsoleImpl.access$600:(Lorg/jboss/aesh/console/AeshConsoleImpl;)Lorg/jboss/aesh/console/settings/CommandNotFoundHandler;
     354: ifnull        380
     357: aload_0
     358: getfield      #1                  // Field this$0:Lorg/jboss/aesh/console/AeshConsoleImpl;
     361: invokestatic  #42                 // Method org/jboss/aesh/console/AeshConsoleImpl.access$600:(Lorg/jboss/aesh/console/AeshConsoleImpl;)Lorg/jboss/aesh/console/settings/CommandNotFoundHandler;
     364: aload_1
     365: invokevirtual #4                  // Method org/jboss/aesh/console/ConsoleOperation.getBuffer:()Ljava/lang/String;
     368: aload_0
     369: getfield      #1                  // Field this$0:Lorg/jboss/aesh/console/AeshConsoleImpl;
     372: invokevirtual #34                 // Method org/jboss/aesh/console/AeshConsoleImpl.getShell:()Lorg/jboss/aesh/terminal/Shell;
     375: invokeinterface #43,  3           // InterfaceMethod org/jboss/aesh/console/settings/CommandNotFoundHandler.handleCommandNotFound:(Ljava/lang/String;Lorg/jboss/aesh/terminal/Shell;)V
     380: goto          505
     383: astore        4
     385: aload         4
     387: instanceof    #45                 // class java/lang/InterruptedException
     390: ifeq          399
     393: aload         4
     395: checkcast     #45                 // class java/lang/InterruptedException
     398: athrow
     399: invokestatic  #46                 // Method org/jboss/aesh/console/AeshConsoleImpl.access$300:()Ljava/util/logging/Logger;
     402: getstatic     #47                 // Field java/util/logging/Level.SEVERE:Ljava/util/logging/Level;
     405: new           #48                 // class java/lang/StringBuilder
     408: dup
     409: invokespecial #49                 // Method java/lang/StringBuilder."<init>":()V
     412: ldc           #50                 // String Exception when parsing/running:
     414: invokevirtual #51                 // Method java/lang/StringBuilder.append:(Ljava/lang/String;)Ljava/lang/StringBuilder;
     417: aload_1
     418: invokevirtual #4                  // Method org/jboss/aesh/console/ConsoleOperation.getBuffer:()Ljava/lang/String;
     421: invokevirtual #51                 // Method java/lang/StringBuilder.append:(Ljava/lang/String;)Ljava/lang/StringBuilder;
     424: invokevirtual #52                 // Method java/lang/StringBuilder.toString:()Ljava/lang/String;
     427: aload         4
     429: invokevirtual #53                 // Method java/util/logging/Logger.log:(Ljava/util/logging/Level;Ljava/lang/String;Ljava/lang/Throwable;)V
     432: aload_0
     433: getfield      #1                  // Field this$0:Lorg/jboss/aesh/console/AeshConsoleImpl;
     436: invokevirtual #34                 // Method org/jboss/aesh/console/AeshConsoleImpl.getShell:()Lorg/jboss/aesh/terminal/Shell;
     439: invokeinterface #35,  1           // InterfaceMethod org/jboss/aesh/terminal/Shell.out:()Ljava/io/PrintStream;
     444: new           #48                 // class java/lang/StringBuilder
     447: dup
     448: invokespecial #49                 // Method java/lang/StringBuilder."<init>":()V
     451: ldc           #50                 // String Exception when parsing/running:
     453: invokevirtual #51                 // Method java/lang/StringBuilder.append:(Ljava/lang/String;)Ljava/lang/StringBuilder;
     456: aload_1
     457: invokevirtual #4                  // Method org/jboss/aesh/console/ConsoleOperation.getBuffer:()Ljava/lang/String;
     460: invokevirtual #51                 // Method java/lang/StringBuilder.append:(Ljava/lang/String;)Ljava/lang/StringBuilder;
     463: ldc           #54                 // String ,
     465: invokevirtual #51                 // Method java/lang/StringBuilder.append:(Ljava/lang/String;)Ljava/lang/StringBuilder;
     468: aload         4
     470: invokevirtual #36                 // Method java/lang/Exception.getMessage:()Ljava/lang/String;
     473: invokevirtual #51                 // Method java/lang/StringBuilder.append:(Ljava/lang/String;)Ljava/lang/StringBuilder;
     476: invokevirtual #52                 // Method java/lang/StringBuilder.toString:()Ljava/lang/String;
     479: invokevirtual #37                 // Method java/io/PrintStream.println:(Ljava/lang/String;)V
     482: aload_0
     483: getstatic     #38                 // Field org/jboss/aesh/console/command/CommandResult.FAILURE:Lorg/jboss/aesh/console/command/CommandResult;
     486: putfield      #24                 // Field result:Lorg/jboss/aesh/console/command/CommandResult;
     489: aload_2
     490: ifnull        505
     493: aload_2
     494: aload_0
     495: getfield      #24                 // Field result:Lorg/jboss/aesh/console/command/CommandResult;
     498: aload         4
     500: invokeinterface #39,  3           // InterfaceMethod org/jboss/aesh/cl/result/ResultHandler.onValidationFailure:(Lorg/jboss/aesh/console/command/CommandResult;Ljava/lang/Exception;)V
     505: goto          536
     508: aload_1
     509: ifnull        522
     512: aload_0
     513: getstatic     #38                 // Field org/jboss/aesh/console/command/CommandResult.FAILURE:Lorg/jboss/aesh/console/command/CommandResult;
     516: putfield      #24                 // Field result:Lorg/jboss/aesh/console/command/CommandResult;
     519: goto          536
     522: aload_0
     523: getfield      #1                  // Field this$0:Lorg/jboss/aesh/console/AeshConsoleImpl;
     526: invokevirtual #55                 // Method org/jboss/aesh/console/AeshConsoleImpl.stop:()V
     529: aload_0
     530: getstatic     #38                 // Field org/jboss/aesh/console/command/CommandResult.FAILURE:Lorg/jboss/aesh/console/command/CommandResult;
     533: putfield      #24                 // Field result:Lorg/jboss/aesh/console/command/CommandResult;
     536: aload_0
     537: getfield      #24                 // Field result:Lorg/jboss/aesh/console/command/CommandResult;
     540: getstatic     #25                 // Field org/jboss/aesh/console/command/CommandResult.SUCCESS:Lorg/jboss/aesh/console/command/CommandResult;
     543: if_acmpne     548
     546: iconst_0
     547: ireturn
     548: iconst_1
     549: ireturn
    Exception table:
       from    to  target type
         182   189   192   Class java/lang/Throwable
          44   172   214   Class java/lang/Throwable
          44   172   223   any
         235   242   245   Class java/lang/Throwable
         214   225   223   any
          27   267   270   Class org/jboss/aesh/cl/parser/CommandLineParserException
          27   267   270   Class org/jboss/aesh/cl/validator/CommandValidatorException
          27   267   270   Class org/jboss/aesh/cl/validator/OptionValidatorException
          27   267   318   Class org/jboss/aesh/console/command/CommandNotFoundException
          27   267   383   Class java/lang/Exception
}
