Compiled from "LabelChainResult.java"
public class cn.com.antcloud.api.provider.bot.v1_0_0.model.LabelChainResult {
  private java.lang.String labelId;

  private java.lang.String assetId;

  private java.lang.String txHash;

  private java.lang.String errorCode;

  private java.lang.String errorMsg;

  public cn.com.antcloud.api.provider.bot.v1_0_0.model.LabelChainResult();
    Code:
       0: aload_0
       1: invokespecial #1                  // Method java/lang/Object."<init>":()V
       4: return

  public java.lang.String getLabelId();
    Code:
       0: aload_0
       1: getfield      #2                  // Field labelId:Ljava/lang/String;
       4: areturn

  public void setLabelId(java.lang.String);
    Code:
       0: aload_0
       1: aload_1
       2: putfield      #2                  // Field labelId:Ljava/lang/String;
       5: return

  public java.lang.String getAssetId();
    Code:
       0: aload_0
       1: getfield      #3                  // Field assetId:Ljava/lang/String;
       4: areturn

  public void setAssetId(java.lang.String);
    Code:
       0: aload_0
       1: aload_1
       2: putfield      #3                  // Field assetId:Ljava/lang/String;
       5: return

  public java.lang.String getTxHash();
    Code:
       0: aload_0
       1: getfield      #4                  // Field txHash:Ljava/lang/String;
       4: areturn

  public void setTxHash(java.lang.String);
    Code:
       0: aload_0
       1: aload_1
       2: putfield      #4                  // Field txHash:Ljava/lang/String;
       5: return

  public java.lang.String getErrorCode();
    Code:
       0: aload_0
       1: getfield      #5                  // Field errorCode:Ljava/lang/String;
       4: areturn

  public void setErrorCode(java.lang.String);
    Code:
       0: aload_0
       1: aload_1
       2: putfield      #5                  // Field errorCode:Ljava/lang/String;
       5: return

  public java.lang.String getErrorMsg();
    Code:
       0: aload_0
       1: getfield      #6                  // Field errorMsg:Ljava/lang/String;
       4: areturn

  public void setErrorMsg(java.lang.String);
    Code:
       0: aload_0
       1: aload_1
       2: putfield      #6                  // Field errorMsg:Ljava/lang/String;
       5: return
}
