Compiled from "LexersTestCase.java"
class juzu.impl.common.LexersTestCase$1Assert {
  final java.util.Iterator<juzu.request.RequestParameter> i;

  final juzu.impl.common.LexersTestCase this$0;

  juzu.impl.common.LexersTestCase$1Assert(juzu.impl.common.LexersTestCase, java.lang.String);
    Code:
       0: aload_0
       1: aload_1
       2: putfield      #1                  // Field this$0:Ljuzu/impl/common/LexersTestCase;
       5: aload_0
       6: invokespecial #2                  // Method java/lang/Object."<init>":()V
       9: aload_0
      10: aload_2
      11: iconst_0
      12: aload_2
      13: invokevirtual #3                  // Method java/lang/String.length:()I
      16: invokestatic  #4                  // Method juzu/impl/common/Lexers.queryParser:(Ljava/lang/CharSequence;II)Ljava/util/Iterator;
      19: putfield      #5                  // Field i:Ljava/util/Iterator;
      22: return

  juzu.impl.common.LexersTestCase$1Assert assertParameter(java.lang.String, java.lang.String...);
    Code:
       0: aload_1
       1: aload_2
       2: invokestatic  #6                  // Method juzu/request/RequestParameter.create:(Ljava/lang/String;[Ljava/lang/String;)Ljuzu/request/RequestParameter;
       5: astore_3
       6: aload_0
       7: getfield      #5                  // Field i:Ljava/util/Iterator;
      10: invokeinterface #7,  1            // InterfaceMethod java/util/Iterator.hasNext:()Z
      15: ifeq          41
      18: aload_0
      19: getfield      #5                  // Field i:Ljava/util/Iterator;
      22: invokeinterface #8,  1            // InterfaceMethod java/util/Iterator.next:()Ljava/lang/Object;
      27: checkcast     #9                  // class juzu/request/RequestParameter
      30: astore        4
      32: aload_3
      33: aload         4
      35: invokestatic  #10                 // Method juzu/test/AbstractTestCase.assertEquals:(Ljava/util/List;Ljava/lang/Iterable;)V
      38: goto          64
      41: new           #11                 // class java/lang/StringBuilder
      44: dup
      45: invokespecial #12                 // Method java/lang/StringBuilder."<init>":()V
      48: ldc           #13                 // String Was expecting another parameter equals to
      50: invokevirtual #14                 // Method java/lang/StringBuilder.append:(Ljava/lang/String;)Ljava/lang/StringBuilder;
      53: aload_3
      54: invokevirtual #15                 // Method java/lang/StringBuilder.append:(Ljava/lang/Object;)Ljava/lang/StringBuilder;
      57: invokevirtual #16                 // Method java/lang/StringBuilder.toString:()Ljava/lang/String;
      60: invokestatic  #17                 // Method juzu/test/AbstractTestCase.failure:(Ljava/lang/String;)Ljunit/framework/AssertionFailedError;
      63: athrow
      64: aload_0
      65: areturn

  void assertDone();
    Code:
       0: aload_0
       1: getfield      #5                  // Field i:Ljava/util/Iterator;
       4: invokeinterface #7,  1            // InterfaceMethod java/util/Iterator.hasNext:()Z
       9: ifeq          41
      12: new           #11                 // class java/lang/StringBuilder
      15: dup
      16: invokespecial #12                 // Method java/lang/StringBuilder."<init>":()V
      19: ldc           #18                 // String Was not expecting those parameters
      21: invokevirtual #14                 // Method java/lang/StringBuilder.append:(Ljava/lang/String;)Ljava/lang/StringBuilder;
      24: aload_0
      25: getfield      #5                  // Field i:Ljava/util/Iterator;
      28: invokestatic  #19                 // Method juzu/impl/common/Tools.list:(Ljava/util/Iterator;)Ljava/util/ArrayList;
      31: invokevirtual #15                 // Method java/lang/StringBuilder.append:(Ljava/lang/Object;)Ljava/lang/StringBuilder;
      34: invokevirtual #16                 // Method java/lang/StringBuilder.toString:()Ljava/lang/String;
      37: invokestatic  #17                 // Method juzu/test/AbstractTestCase.failure:(Ljava/lang/String;)Ljunit/framework/AssertionFailedError;
      40: athrow
      41: return
}
