Compiled from "EntryViews.java"
final class org.infinispan.functional.impl.EntryViews$ReadWriteSnapshotView<K, V> implements org.infinispan.commons.api.functional.EntryView$ReadWriteEntryView<K, V> {
  final K key;

  final V value;

  final org.infinispan.metadata.Metadata metadata;

  public org.infinispan.functional.impl.EntryViews$ReadWriteSnapshotView(K, V, org.infinispan.metadata.Metadata);
    Code:
       0: aload_0
       1: invokespecial #1                  // Method java/lang/Object."<init>":()V
       4: aload_0
       5: aload_1
       6: putfield      #2                  // Field key:Ljava/lang/Object;
       9: aload_0
      10: aload_2
      11: putfield      #3                  // Field value:Ljava/lang/Object;
      14: aload_0
      15: aload_3
      16: putfield      #4                  // Field metadata:Lorg/infinispan/metadata/Metadata;
      19: return

  public K key();
    Code:
       0: aload_0
       1: getfield      #2                  // Field key:Ljava/lang/Object;
       4: areturn

  public V get() throws java.util.NoSuchElementException;
    Code:
       0: aload_0
       1: getfield      #3                  // Field value:Ljava/lang/Object;
       4: ifnonnull     17
       7: new           #5                  // class java/util/NoSuchElementException
      10: dup
      11: ldc           #6                  // String No value present
      13: invokespecial #7                  // Method java/util/NoSuchElementException."<init>":(Ljava/lang/String;)V
      16: athrow
      17: aload_0
      18: getfield      #3                  // Field value:Ljava/lang/Object;
      21: areturn

  public java.util.Optional<V> find();
    Code:
       0: aload_0
       1: getfield      #3                  // Field value:Ljava/lang/Object;
       4: invokestatic  #8                  // Method java/util/Optional.ofNullable:(Ljava/lang/Object;)Ljava/util/Optional;
       7: areturn

  public <T> java.util.Optional<T> findMetaParam(java.lang.Class<T>);
    Code:
       0: aload_0
       1: getfield      #4                  // Field metadata:Lorg/infinispan/metadata/Metadata;
       4: instanceof    #9                  // class org/infinispan/functional/impl/MetaParamsInternalMetadata
       7: ifeq          24
      10: aload_0
      11: getfield      #4                  // Field metadata:Lorg/infinispan/metadata/Metadata;
      14: checkcast     #9                  // class org/infinispan/functional/impl/MetaParamsInternalMetadata
      17: astore_2
      18: aload_2
      19: aload_1
      20: invokevirtual #10                 // Method org/infinispan/functional/impl/MetaParamsInternalMetadata.findMetaParam:(Ljava/lang/Class;)Ljava/util/Optional;
      23: areturn
      24: invokestatic  #11                 // Method java/util/Optional.empty:()Ljava/util/Optional;
      27: areturn

  public java.lang.Void set(V, org.infinispan.commons.api.functional.MetaParam$Writable...);
    Code:
       0: new           #12                 // class java/lang/IllegalStateException
       3: dup
       4: ldc           #13                 // String A read-write entry view cannot be modified outside the scope of a lambda
       6: invokespecial #14                 // Method java/lang/IllegalStateException."<init>":(Ljava/lang/String;)V
       9: athrow

  public java.lang.Void remove();
    Code:
       0: new           #12                 // class java/lang/IllegalStateException
       3: dup
       4: ldc           #13                 // String A read-write entry view cannot be modified outside the scope of a lambda
       6: invokespecial #14                 // Method java/lang/IllegalStateException."<init>":(Ljava/lang/String;)V
       9: athrow

  public java.lang.String toString();
    Code:
       0: new           #15                 // class java/lang/StringBuilder
       3: dup
       4: invokespecial #16                 // Method java/lang/StringBuilder."<init>":()V
       7: ldc           #17                 // String ReadWriteSnapshotView{key=
       9: invokevirtual #18                 // Method java/lang/StringBuilder.append:(Ljava/lang/String;)Ljava/lang/StringBuilder;
      12: aload_0
      13: getfield      #2                  // Field key:Ljava/lang/Object;
      16: invokevirtual #19                 // Method java/lang/StringBuilder.append:(Ljava/lang/Object;)Ljava/lang/StringBuilder;
      19: ldc           #20                 // String , value=
      21: invokevirtual #18                 // Method java/lang/StringBuilder.append:(Ljava/lang/String;)Ljava/lang/StringBuilder;
      24: aload_0
      25: getfield      #3                  // Field value:Ljava/lang/Object;
      28: invokevirtual #19                 // Method java/lang/StringBuilder.append:(Ljava/lang/Object;)Ljava/lang/StringBuilder;
      31: ldc           #21                 // String , metadata=
      33: invokevirtual #18                 // Method java/lang/StringBuilder.append:(Ljava/lang/String;)Ljava/lang/StringBuilder;
      36: aload_0
      37: getfield      #4                  // Field metadata:Lorg/infinispan/metadata/Metadata;
      40: invokevirtual #19                 // Method java/lang/StringBuilder.append:(Ljava/lang/Object;)Ljava/lang/StringBuilder;
      43: bipush        125
      45: invokevirtual #22                 // Method java/lang/StringBuilder.append:(C)Ljava/lang/StringBuilder;
      48: invokevirtual #23                 // Method java/lang/StringBuilder.toString:()Ljava/lang/String;
      51: areturn
}
