Compiled from "AbstractDataSourcePoolMetadata.java"
public abstract class org.springframework.boot.autoconfigure.jdbc.metadata.AbstractDataSourcePoolMetadata<T extends javax.sql.DataSource> implements org.springframework.boot.autoconfigure.jdbc.metadata.DataSourcePoolMetadata {
  private final T dataSource;

  protected org.springframework.boot.autoconfigure.jdbc.metadata.AbstractDataSourcePoolMetadata(T);
    Code:
       0: aload_0
       1: invokespecial #1                  // Method java/lang/Object."<init>":()V
       4: aload_0
       5: aload_1
       6: putfield      #2                  // Field dataSource:Ljavax/sql/DataSource;
       9: return

  public java.lang.Float getUsage();
    Code:
       0: aload_0
       1: invokevirtual #3                  // Method getMax:()Ljava/lang/Integer;
       4: astore_1
       5: aload_0
       6: invokevirtual #4                  // Method getActive:()Ljava/lang/Integer;
       9: astore_2
      10: aload_1
      11: ifnull        18
      14: aload_2
      15: ifnonnull     20
      18: aconst_null
      19: areturn
      20: aload_1
      21: invokevirtual #5                  // Method java/lang/Integer.intValue:()I
      24: ifge          33
      27: ldc           #6                  // float -1.0f
      29: invokestatic  #7                  // Method java/lang/Float.valueOf:(F)Ljava/lang/Float;
      32: areturn
      33: aload_2
      34: invokevirtual #5                  // Method java/lang/Integer.intValue:()I
      37: ifne          45
      40: fconst_0
      41: invokestatic  #7                  // Method java/lang/Float.valueOf:(F)Ljava/lang/Float;
      44: areturn
      45: aload_2
      46: invokevirtual #5                  // Method java/lang/Integer.intValue:()I
      49: i2f
      50: aload_1
      51: invokevirtual #5                  // Method java/lang/Integer.intValue:()I
      54: i2f
      55: fdiv
      56: invokestatic  #7                  // Method java/lang/Float.valueOf:(F)Ljava/lang/Float;
      59: areturn

  protected final T getDataSource();
    Code:
       0: aload_0
       1: getfield      #2                  // Field dataSource:Ljavax/sql/DataSource;
       4: areturn
}
