Compiled from "Reflections.java"
public class org.reflections.Reflections {
  public static org.slf4j.Logger log;

  protected final transient org.reflections.Configuration configuration;

  protected org.reflections.Store store;

  public org.reflections.Reflections(org.reflections.Configuration);
    Code:
       0: aload_0
       1: invokespecial #2                  // Method java/lang/Object."<init>":()V
       4: aload_0
       5: aload_1
       6: putfield      #3                  // Field configuration:Lorg/reflections/Configuration;
       9: aload_0
      10: new           #4                  // class org/reflections/Store
      13: dup
      14: aload_1
      15: invokespecial #5                  // Method org/reflections/Store."<init>":(Lorg/reflections/Configuration;)V
      18: putfield      #6                  // Field store:Lorg/reflections/Store;
      21: aload_1
      22: invokeinterface #7,  1            // InterfaceMethod org/reflections/Configuration.getScanners:()Ljava/util/Set;
      27: ifnull        122
      30: aload_1
      31: invokeinterface #7,  1            // InterfaceMethod org/reflections/Configuration.getScanners:()Ljava/util/Set;
      36: invokeinterface #8,  1            // InterfaceMethod java/util/Set.isEmpty:()Z
      41: ifne          122
      44: aload_1
      45: invokeinterface #7,  1            // InterfaceMethod org/reflections/Configuration.getScanners:()Ljava/util/Set;
      50: invokeinterface #9,  1            // InterfaceMethod java/util/Set.iterator:()Ljava/util/Iterator;
      55: astore_2
      56: aload_2
      57: invokeinterface #10,  1           // InterfaceMethod java/util/Iterator.hasNext:()Z
      62: ifeq          105
      65: aload_2
      66: invokeinterface #11,  1           // InterfaceMethod java/util/Iterator.next:()Ljava/lang/Object;
      71: checkcast     #12                 // class org/reflections/scanners/Scanner
      74: astore_3
      75: aload_3
      76: aload_1
      77: invokeinterface #13,  2           // InterfaceMethod org/reflections/scanners/Scanner.setConfiguration:(Lorg/reflections/Configuration;)V
      82: aload_3
      83: aload_0
      84: getfield      #6                  // Field store:Lorg/reflections/Store;
      87: aload_3
      88: invokevirtual #14                 // Method java/lang/Object.getClass:()Ljava/lang/Class;
      91: invokevirtual #15                 // Method java/lang/Class.getSimpleName:()Ljava/lang/String;
      94: invokevirtual #16                 // Method org/reflections/Store.getOrCreate:(Ljava/lang/String;)Lcom/google/common/collect/Multimap;
      97: invokeinterface #17,  2           // InterfaceMethod org/reflections/scanners/Scanner.setStore:(Lcom/google/common/collect/Multimap;)V
     102: goto          56
     105: aload_0
     106: invokevirtual #18                 // Method scan:()V
     109: aload_1
     110: invokeinterface #19,  1           // InterfaceMethod org/reflections/Configuration.shouldExpandSuperTypes:()Z
     115: ifeq          122
     118: aload_0
     119: invokevirtual #20                 // Method expandSuperTypes:()V
     122: return

  public org.reflections.Reflections(java.lang.String, org.reflections.scanners.Scanner...);
    Code:
       0: aload_0
       1: iconst_2
       2: anewarray     #21                 // class java/lang/Object
       5: dup
       6: iconst_0
       7: aload_1
       8: aastore
       9: dup
      10: iconst_1
      11: aload_2
      12: aastore
      13: invokespecial #22                 // Method "<init>":([Ljava/lang/Object;)V
      16: return

  public org.reflections.Reflections(java.lang.Object...);
    Code:
       0: aload_0
       1: aload_1
       2: invokestatic  #23                 // Method org/reflections/util/ConfigurationBuilder.build:([Ljava/lang/Object;)Lorg/reflections/util/ConfigurationBuilder;
       5: invokespecial #24                 // Method "<init>":(Lorg/reflections/Configuration;)V
       8: return

  protected org.reflections.Reflections();
    Code:
       0: aload_0
       1: invokespecial #2                  // Method java/lang/Object."<init>":()V
       4: aload_0
       5: new           #25                 // class org/reflections/util/ConfigurationBuilder
       8: dup
       9: invokespecial #26                 // Method org/reflections/util/ConfigurationBuilder."<init>":()V
      12: putfield      #3                  // Field configuration:Lorg/reflections/Configuration;
      15: aload_0
      16: new           #4                  // class org/reflections/Store
      19: dup
      20: aload_0
      21: getfield      #3                  // Field configuration:Lorg/reflections/Configuration;
      24: invokespecial #5                  // Method org/reflections/Store."<init>":(Lorg/reflections/Configuration;)V
      27: putfield      #6                  // Field store:Lorg/reflections/Store;
      30: return

  protected void scan();
    Code:
       0: aload_0
       1: getfield      #3                  // Field configuration:Lorg/reflections/Configuration;
       4: invokeinterface #27,  1           // InterfaceMethod org/reflections/Configuration.getUrls:()Ljava/util/Set;
       9: ifnull        29
      12: aload_0
      13: getfield      #3                  // Field configuration:Lorg/reflections/Configuration;
      16: invokeinterface #27,  1           // InterfaceMethod org/reflections/Configuration.getUrls:()Ljava/util/Set;
      21: invokeinterface #8,  1            // InterfaceMethod java/util/Set.isEmpty:()Z
      26: ifeq          46
      29: getstatic     #28                 // Field log:Lorg/slf4j/Logger;
      32: ifnull        45
      35: getstatic     #28                 // Field log:Lorg/slf4j/Logger;
      38: ldc           #29                 // String given scan urls are empty. set urls in the configuration
      40: invokeinterface #30,  2           // InterfaceMethod org/slf4j/Logger.warn:(Ljava/lang/String;)V
      45: return
      46: getstatic     #28                 // Field log:Lorg/slf4j/Logger;
      49: ifnull        106
      52: getstatic     #28                 // Field log:Lorg/slf4j/Logger;
      55: invokeinterface #31,  1           // InterfaceMethod org/slf4j/Logger.isDebugEnabled:()Z
      60: ifeq          106
      63: getstatic     #28                 // Field log:Lorg/slf4j/Logger;
      66: new           #32                 // class java/lang/StringBuilder
      69: dup
      70: invokespecial #33                 // Method java/lang/StringBuilder."<init>":()V
      73: ldc           #34                 // String going to scan these urls:\n
      75: invokevirtual #35                 // Method java/lang/StringBuilder.append:(Ljava/lang/String;)Ljava/lang/StringBuilder;
      78: ldc           #36                 // String \n
      80: invokestatic  #37                 // Method com/google/common/base/Joiner.on:(Ljava/lang/String;)Lcom/google/common/base/Joiner;
      83: aload_0
      84: getfield      #3                  // Field configuration:Lorg/reflections/Configuration;
      87: invokeinterface #27,  1           // InterfaceMethod org/reflections/Configuration.getUrls:()Ljava/util/Set;
      92: invokevirtual #38                 // Method com/google/common/base/Joiner.join:(Ljava/lang/Iterable;)Ljava/lang/String;
      95: invokevirtual #35                 // Method java/lang/StringBuilder.append:(Ljava/lang/String;)Ljava/lang/StringBuilder;
      98: invokevirtual #39                 // Method java/lang/StringBuilder.toString:()Ljava/lang/String;
     101: invokeinterface #40,  2           // InterfaceMethod org/slf4j/Logger.debug:(Ljava/lang/String;)V
     106: invokestatic  #41                 // Method java/lang/System.currentTimeMillis:()J
     109: lstore_1
     110: iconst_0
     111: istore_3
     112: aload_0
     113: getfield      #3                  // Field configuration:Lorg/reflections/Configuration;
     116: invokeinterface #42,  1           // InterfaceMethod org/reflections/Configuration.getExecutorService:()Ljava/util/concurrent/ExecutorService;
     121: astore        4
     123: invokestatic  #43                 // Method com/google/common/collect/Lists.newArrayList:()Ljava/util/ArrayList;
     126: astore        5
     128: aload_0
     129: getfield      #3                  // Field configuration:Lorg/reflections/Configuration;
     132: invokeinterface #27,  1           // InterfaceMethod org/reflections/Configuration.getUrls:()Ljava/util/Set;
     137: invokeinterface #9,  1            // InterfaceMethod java/util/Set.iterator:()Ljava/util/Iterator;
     142: astore        6
     144: aload         6
     146: invokeinterface #10,  1           // InterfaceMethod java/util/Iterator.hasNext:()Z
     151: ifeq          245
     154: aload         6
     156: invokeinterface #11,  1           // InterfaceMethod java/util/Iterator.next:()Ljava/lang/Object;
     161: checkcast     #44                 // class java/net/URL
     164: astore        7
     166: aload         4
     168: ifnull        199
     171: aload         5
     173: aload         4
     175: new           #45                 // class org/reflections/Reflections$1
     178: dup
     179: aload_0
     180: aload         7
     182: invokespecial #46                 // Method org/reflections/Reflections$1."<init>":(Lorg/reflections/Reflections;Ljava/net/URL;)V
     185: invokeinterface #47,  2           // InterfaceMethod java/util/concurrent/ExecutorService.submit:(Ljava/lang/Runnable;)Ljava/util/concurrent/Future;
     190: invokeinterface #48,  2           // InterfaceMethod java/util/List.add:(Ljava/lang/Object;)Z
     195: pop
     196: goto          205
     199: aload_0
     200: aload         7
     202: invokevirtual #49                 // Method scan:(Ljava/net/URL;)V
     205: iinc          3, 1
     208: goto          242
     211: astore        8
     213: getstatic     #28                 // Field log:Lorg/slf4j/Logger;
     216: ifnull        242
     219: getstatic     #28                 // Field log:Lorg/slf4j/Logger;
     222: invokeinterface #51,  1           // InterfaceMethod org/slf4j/Logger.isWarnEnabled:()Z
     227: ifeq          242
     230: getstatic     #28                 // Field log:Lorg/slf4j/Logger;
     233: ldc           #52                 // String could not create Vfs.Dir from url. ignoring the exception and continuing
     235: aload         8
     237: invokeinterface #53,  3           // InterfaceMethod org/slf4j/Logger.warn:(Ljava/lang/String;Ljava/lang/Throwable;)V
     242: goto          144
     245: aload         4
     247: ifnull        307
     250: aload         5
     252: invokeinterface #54,  1           // InterfaceMethod java/util/List.iterator:()Ljava/util/Iterator;
     257: astore        6
     259: aload         6
     261: invokeinterface #10,  1           // InterfaceMethod java/util/Iterator.hasNext:()Z
     266: ifeq          307
     269: aload         6
     271: invokeinterface #11,  1           // InterfaceMethod java/util/Iterator.next:()Ljava/lang/Object;
     276: checkcast     #55                 // class java/util/concurrent/Future
     279: astore        7
     281: aload         7
     283: invokeinterface #56,  1           // InterfaceMethod java/util/concurrent/Future.get:()Ljava/lang/Object;
     288: pop
     289: goto          304
     292: astore        8
     294: new           #58                 // class java/lang/RuntimeException
     297: dup
     298: aload         8
     300: invokespecial #59                 // Method java/lang/RuntimeException."<init>":(Ljava/lang/Throwable;)V
     303: athrow
     304: goto          259
     307: invokestatic  #41                 // Method java/lang/System.currentTimeMillis:()J
     310: lload_1
     311: lsub
     312: lstore_1
     313: aload         4
     315: ifnull        325
     318: aload         4
     320: invokeinterface #60,  1           // InterfaceMethod java/util/concurrent/ExecutorService.shutdown:()V
     325: getstatic     #28                 // Field log:Lorg/slf4j/Logger;
     328: ifnull        510
     331: iconst_0
     332: istore        6
     334: iconst_0
     335: istore        7
     337: aload_0
     338: getfield      #6                  // Field store:Lorg/reflections/Store;
     341: invokevirtual #61                 // Method org/reflections/Store.keySet:()Ljava/util/Set;
     344: invokeinterface #9,  1            // InterfaceMethod java/util/Set.iterator:()Ljava/util/Iterator;
     349: astore        8
     351: aload         8
     353: invokeinterface #10,  1           // InterfaceMethod java/util/Iterator.hasNext:()Z
     358: ifeq          419
     361: aload         8
     363: invokeinterface #11,  1           // InterfaceMethod java/util/Iterator.next:()Ljava/lang/Object;
     368: checkcast     #62                 // class java/lang/String
     371: astore        9
     373: iload         6
     375: aload_0
     376: getfield      #6                  // Field store:Lorg/reflections/Store;
     379: aload         9
     381: invokevirtual #63                 // Method org/reflections/Store.get:(Ljava/lang/String;)Lcom/google/common/collect/Multimap;
     384: invokeinterface #64,  1           // InterfaceMethod com/google/common/collect/Multimap.keySet:()Ljava/util/Set;
     389: invokeinterface #65,  1           // InterfaceMethod java/util/Set.size:()I
     394: iadd
     395: istore        6
     397: iload         7
     399: aload_0
     400: getfield      #6                  // Field store:Lorg/reflections/Store;
     403: aload         9
     405: invokevirtual #63                 // Method org/reflections/Store.get:(Ljava/lang/String;)Lcom/google/common/collect/Multimap;
     408: invokeinterface #66,  1           // InterfaceMethod com/google/common/collect/Multimap.size:()I
     413: iadd
     414: istore        7
     416: goto          351
     419: getstatic     #28                 // Field log:Lorg/slf4j/Logger;
     422: ldc           #67                 // String Reflections took %d ms to scan %d urls, producing %d keys and %d values %s
     424: iconst_5
     425: anewarray     #21                 // class java/lang/Object
     428: dup
     429: iconst_0
     430: lload_1
     431: invokestatic  #68                 // Method java/lang/Long.valueOf:(J)Ljava/lang/Long;
     434: aastore
     435: dup
     436: iconst_1
     437: iload_3
     438: invokestatic  #69                 // Method java/lang/Integer.valueOf:(I)Ljava/lang/Integer;
     441: aastore
     442: dup
     443: iconst_2
     444: iload         6
     446: invokestatic  #69                 // Method java/lang/Integer.valueOf:(I)Ljava/lang/Integer;
     449: aastore
     450: dup
     451: iconst_3
     452: iload         7
     454: invokestatic  #69                 // Method java/lang/Integer.valueOf:(I)Ljava/lang/Integer;
     457: aastore
     458: dup
     459: iconst_4
     460: aload         4
     462: ifnull        499
     465: aload         4
     467: instanceof    #70                 // class java/util/concurrent/ThreadPoolExecutor
     470: ifeq          499
     473: ldc           #71                 // String [using %d cores]
     475: iconst_1
     476: anewarray     #21                 // class java/lang/Object
     479: dup
     480: iconst_0
     481: aload         4
     483: checkcast     #70                 // class java/util/concurrent/ThreadPoolExecutor
     486: invokevirtual #72                 // Method java/util/concurrent/ThreadPoolExecutor.getMaximumPoolSize:()I
     489: invokestatic  #69                 // Method java/lang/Integer.valueOf:(I)Ljava/lang/Integer;
     492: aastore
     493: invokestatic  #73                 // Method java/lang/String.format:(Ljava/lang/String;[Ljava/lang/Object;)Ljava/lang/String;
     496: goto          501
     499: ldc           #74                 // String
     501: aastore
     502: invokestatic  #73                 // Method java/lang/String.format:(Ljava/lang/String;[Ljava/lang/Object;)Ljava/lang/String;
     505: invokeinterface #75,  2           // InterfaceMethod org/slf4j/Logger.info:(Ljava/lang/String;)V
     510: return
    Exception table:
       from    to  target type
         166   208   211   Class org/reflections/ReflectionsException
         281   289   292   Class java/lang/Exception

  protected void scan(java.net.URL);
    Code:
       0: aload_1
       1: invokestatic  #76                 // Method org/reflections/vfs/Vfs.fromURL:(Ljava/net/URL;)Lorg/reflections/vfs/Vfs$Dir;
       4: astore_2
       5: aload_2
       6: invokeinterface #77,  1           // InterfaceMethod org/reflections/vfs/Vfs$Dir.getFiles:()Ljava/lang/Iterable;
      11: invokeinterface #78,  1           // InterfaceMethod java/lang/Iterable.iterator:()Ljava/util/Iterator;
      16: astore_3
      17: aload_3
      18: invokeinterface #10,  1           // InterfaceMethod java/util/Iterator.hasNext:()Z
      23: ifeq          266
      26: aload_3
      27: invokeinterface #11,  1           // InterfaceMethod java/util/Iterator.next:()Ljava/lang/Object;
      32: checkcast     #79                 // class org/reflections/vfs/Vfs$File
      35: astore        4
      37: aload_0
      38: getfield      #3                  // Field configuration:Lorg/reflections/Configuration;
      41: invokeinterface #80,  1           // InterfaceMethod org/reflections/Configuration.getInputsFilter:()Lcom/google/common/base/Predicate;
      46: astore        5
      48: aload         4
      50: invokeinterface #81,  1           // InterfaceMethod org/reflections/vfs/Vfs$File.getRelativePath:()Ljava/lang/String;
      55: astore        6
      57: aload         6
      59: bipush        47
      61: bipush        46
      63: invokevirtual #82                 // Method java/lang/String.replace:(CC)Ljava/lang/String;
      66: astore        7
      68: aload         5
      70: ifnull        97
      73: aload         5
      75: aload         6
      77: invokeinterface #83,  2           // InterfaceMethod com/google/common/base/Predicate.apply:(Ljava/lang/Object;)Z
      82: ifne          97
      85: aload         5
      87: aload         7
      89: invokeinterface #83,  2           // InterfaceMethod com/google/common/base/Predicate.apply:(Ljava/lang/Object;)Z
      94: ifeq          263
      97: aconst_null
      98: astore        8
     100: aload_0
     101: getfield      #3                  // Field configuration:Lorg/reflections/Configuration;
     104: invokeinterface #7,  1            // InterfaceMethod org/reflections/Configuration.getScanners:()Ljava/util/Set;
     109: invokeinterface #9,  1            // InterfaceMethod java/util/Set.iterator:()Ljava/util/Iterator;
     114: astore        9
     116: aload         9
     118: invokeinterface #10,  1           // InterfaceMethod java/util/Iterator.hasNext:()Z
     123: ifeq          263
     126: aload         9
     128: invokeinterface #11,  1           // InterfaceMethod java/util/Iterator.next:()Ljava/lang/Object;
     133: checkcast     #12                 // class org/reflections/scanners/Scanner
     136: astore        10
     138: aload         10
     140: aload         6
     142: invokeinterface #84,  2           // InterfaceMethod org/reflections/scanners/Scanner.acceptsInput:(Ljava/lang/String;)Z
     147: ifne          162
     150: aload         10
     152: aload         7
     154: invokeinterface #85,  2           // InterfaceMethod org/reflections/scanners/Scanner.acceptResult:(Ljava/lang/String;)Z
     159: ifeq          175
     162: aload         10
     164: aload         4
     166: aload         8
     168: invokeinterface #86,  3           // InterfaceMethod org/reflections/scanners/Scanner.scan:(Lorg/reflections/vfs/Vfs$File;Ljava/lang/Object;)Ljava/lang/Object;
     173: astore        8
     175: goto          260
     178: astore        11
     180: getstatic     #28                 // Field log:Lorg/slf4j/Logger;
     183: ifnull        260
     186: getstatic     #28                 // Field log:Lorg/slf4j/Logger;
     189: invokeinterface #31,  1           // InterfaceMethod org/slf4j/Logger.isDebugEnabled:()Z
     194: ifeq          260
     197: getstatic     #28                 // Field log:Lorg/slf4j/Logger;
     200: new           #32                 // class java/lang/StringBuilder
     203: dup
     204: invokespecial #33                 // Method java/lang/StringBuilder."<init>":()V
     207: ldc           #87                 // String could not scan file
     209: invokevirtual #35                 // Method java/lang/StringBuilder.append:(Ljava/lang/String;)Ljava/lang/StringBuilder;
     212: aload         4
     214: invokeinterface #81,  1           // InterfaceMethod org/reflections/vfs/Vfs$File.getRelativePath:()Ljava/lang/String;
     219: invokevirtual #35                 // Method java/lang/StringBuilder.append:(Ljava/lang/String;)Ljava/lang/StringBuilder;
     222: ldc           #88                 // String  in url
     224: invokevirtual #35                 // Method java/lang/StringBuilder.append:(Ljava/lang/String;)Ljava/lang/StringBuilder;
     227: aload_1
     228: invokevirtual #89                 // Method java/net/URL.toExternalForm:()Ljava/lang/String;
     231: invokevirtual #35                 // Method java/lang/StringBuilder.append:(Ljava/lang/String;)Ljava/lang/StringBuilder;
     234: ldc           #90                 // String  with scanner
     236: invokevirtual #35                 // Method java/lang/StringBuilder.append:(Ljava/lang/String;)Ljava/lang/StringBuilder;
     239: aload         10
     241: invokevirtual #14                 // Method java/lang/Object.getClass:()Ljava/lang/Class;
     244: invokevirtual #15                 // Method java/lang/Class.getSimpleName:()Ljava/lang/String;
     247: invokevirtual #35                 // Method java/lang/StringBuilder.append:(Ljava/lang/String;)Ljava/lang/StringBuilder;
     250: invokevirtual #39                 // Method java/lang/StringBuilder.toString:()Ljava/lang/String;
     253: aload         11
     255: invokeinterface #91,  3           // InterfaceMethod org/slf4j/Logger.debug:(Ljava/lang/String;Ljava/lang/Throwable;)V
     260: goto          116
     263: goto          17
     266: aload_2
     267: invokeinterface #92,  1           // InterfaceMethod org/reflections/vfs/Vfs$Dir.close:()V
     272: goto          286
     275: astore        12
     277: aload_2
     278: invokeinterface #92,  1           // InterfaceMethod org/reflections/vfs/Vfs$Dir.close:()V
     283: aload         12
     285: athrow
     286: return
    Exception table:
       from    to  target type
         138   175   178   Class java/lang/Exception
           5   266   275   any
         275   277   275   any

  public static org.reflections.Reflections collect();
    Code:
       0: ldc           #93                 // String META-INF/reflections/
       2: new           #94                 // class org/reflections/util/FilterBuilder
       5: dup
       6: invokespecial #95                 // Method org/reflections/util/FilterBuilder."<init>":()V
       9: ldc           #96                 // String .*-reflections.xml
      11: invokevirtual #97                 // Method org/reflections/util/FilterBuilder.include:(Ljava/lang/String;)Lorg/reflections/util/FilterBuilder;
      14: iconst_0
      15: anewarray     #98                 // class org/reflections/serializers/Serializer
      18: invokestatic  #99                 // Method collect:(Ljava/lang/String;Lcom/google/common/base/Predicate;[Lorg/reflections/serializers/Serializer;)Lorg/reflections/Reflections;
      21: areturn

  public static org.reflections.Reflections collect(java.lang.String, com.google.common.base.Predicate<java.lang.String>, org.reflections.serializers.Serializer...);
    Code:
       0: aload_2
       1: ifnull        16
       4: aload_2
       5: arraylength
       6: iconst_1
       7: if_icmpne     16
      10: aload_2
      11: iconst_0
      12: aaload
      13: goto          23
      16: new           #100                // class org/reflections/serializers/XmlSerializer
      19: dup
      20: invokespecial #101                // Method org/reflections/serializers/XmlSerializer."<init>":()V
      23: astore_3
      24: aload_0
      25: iconst_0
      26: anewarray     #102                // class java/lang/ClassLoader
      29: invokestatic  #103                // Method org/reflections/util/ClasspathHelper.forPackage:(Ljava/lang/String;[Ljava/lang/ClassLoader;)Ljava/util/Collection;
      32: astore        4
      34: aload         4
      36: invokeinterface #104,  1          // InterfaceMethod java/util/Collection.isEmpty:()Z
      41: ifeq          46
      44: aconst_null
      45: areturn
      46: invokestatic  #41                 // Method java/lang/System.currentTimeMillis:()J
      49: lstore        5
      51: new           #105                // class org/reflections/Reflections
      54: dup
      55: invokespecial #106                // Method "<init>":()V
      58: astore        7
      60: aload         4
      62: aload_0
      63: aload_1
      64: invokestatic  #107                // Method org/reflections/vfs/Vfs.findFiles:(Ljava/util/Collection;Ljava/lang/String;Lcom/google/common/base/Predicate;)Ljava/lang/Iterable;
      67: astore        8
      69: aload         8
      71: invokeinterface #78,  1           // InterfaceMethod java/lang/Iterable.iterator:()Ljava/util/Iterator;
      76: astore        9
      78: aload         9
      80: invokeinterface #10,  1           // InterfaceMethod java/util/Iterator.hasNext:()Z
      85: ifeq          179
      88: aload         9
      90: invokeinterface #11,  1           // InterfaceMethod java/util/Iterator.next:()Ljava/lang/Object;
      95: checkcast     #79                 // class org/reflections/vfs/Vfs$File
      98: astore        10
     100: aconst_null
     101: astore        11
     103: aload         10
     105: invokeinterface #108,  1          // InterfaceMethod org/reflections/vfs/Vfs$File.openInputStream:()Ljava/io/InputStream;
     110: astore        11
     112: aload         7
     114: aload_3
     115: aload         11
     117: invokeinterface #109,  2          // InterfaceMethod org/reflections/serializers/Serializer.read:(Ljava/io/InputStream;)Lorg/reflections/Reflections;
     122: invokevirtual #110                // Method merge:(Lorg/reflections/Reflections;)Lorg/reflections/Reflections;
     125: pop
     126: aload         11
     128: invokestatic  #111                // Method org/reflections/util/Utils.close:(Ljava/io/InputStream;)V
     131: goto          176
     134: astore        12
     136: new           #50                 // class org/reflections/ReflectionsException
     139: dup
     140: new           #32                 // class java/lang/StringBuilder
     143: dup
     144: invokespecial #33                 // Method java/lang/StringBuilder."<init>":()V
     147: ldc           #113                // String could not merge
     149: invokevirtual #35                 // Method java/lang/StringBuilder.append:(Ljava/lang/String;)Ljava/lang/StringBuilder;
     152: aload         10
     154: invokevirtual #114                // Method java/lang/StringBuilder.append:(Ljava/lang/Object;)Ljava/lang/StringBuilder;
     157: invokevirtual #39                 // Method java/lang/StringBuilder.toString:()Ljava/lang/String;
     160: aload         12
     162: invokespecial #115                // Method org/reflections/ReflectionsException."<init>":(Ljava/lang/String;Ljava/lang/Throwable;)V
     165: athrow
     166: astore        13
     168: aload         11
     170: invokestatic  #111                // Method org/reflections/util/Utils.close:(Ljava/io/InputStream;)V
     173: aload         13
     175: athrow
     176: goto          78
     179: getstatic     #28                 // Field log:Lorg/slf4j/Logger;
     182: ifnull        367
     185: aload         7
     187: invokevirtual #116                // Method getStore:()Lorg/reflections/Store;
     190: astore        9
     192: iconst_0
     193: istore        10
     195: iconst_0
     196: istore        11
     198: aload         9
     200: invokevirtual #61                 // Method org/reflections/Store.keySet:()Ljava/util/Set;
     203: invokeinterface #9,  1            // InterfaceMethod java/util/Set.iterator:()Ljava/util/Iterator;
     208: astore        12
     210: aload         12
     212: invokeinterface #10,  1           // InterfaceMethod java/util/Iterator.hasNext:()Z
     217: ifeq          274
     220: aload         12
     222: invokeinterface #11,  1           // InterfaceMethod java/util/Iterator.next:()Ljava/lang/Object;
     227: checkcast     #62                 // class java/lang/String
     230: astore        13
     232: iload         10
     234: aload         9
     236: aload         13
     238: invokevirtual #63                 // Method org/reflections/Store.get:(Ljava/lang/String;)Lcom/google/common/collect/Multimap;
     241: invokeinterface #64,  1           // InterfaceMethod com/google/common/collect/Multimap.keySet:()Ljava/util/Set;
     246: invokeinterface #65,  1           // InterfaceMethod java/util/Set.size:()I
     251: iadd
     252: istore        10
     254: iload         11
     256: aload         9
     258: aload         13
     260: invokevirtual #63                 // Method org/reflections/Store.get:(Ljava/lang/String;)Lcom/google/common/collect/Multimap;
     263: invokeinterface #66,  1           // InterfaceMethod com/google/common/collect/Multimap.size:()I
     268: iadd
     269: istore        11
     271: goto          210
     274: getstatic     #28                 // Field log:Lorg/slf4j/Logger;
     277: ldc           #117                // String Reflections took %d ms to collect %d url%s, producing %d keys and %d values [%s]
     279: bipush        6
     281: anewarray     #21                 // class java/lang/Object
     284: dup
     285: iconst_0
     286: invokestatic  #41                 // Method java/lang/System.currentTimeMillis:()J
     289: lload         5
     291: lsub
     292: invokestatic  #68                 // Method java/lang/Long.valueOf:(J)Ljava/lang/Long;
     295: aastore
     296: dup
     297: iconst_1
     298: aload         4
     300: invokeinterface #118,  1          // InterfaceMethod java/util/Collection.size:()I
     305: invokestatic  #69                 // Method java/lang/Integer.valueOf:(I)Ljava/lang/Integer;
     308: aastore
     309: dup
     310: iconst_2
     311: aload         4
     313: invokeinterface #118,  1          // InterfaceMethod java/util/Collection.size:()I
     318: iconst_1
     319: if_icmple     327
     322: ldc           #119                // String s
     324: goto          329
     327: ldc           #74                 // String
     329: aastore
     330: dup
     331: iconst_3
     332: iload         10
     334: invokestatic  #69                 // Method java/lang/Integer.valueOf:(I)Ljava/lang/Integer;
     337: aastore
     338: dup
     339: iconst_4
     340: iload         11
     342: invokestatic  #69                 // Method java/lang/Integer.valueOf:(I)Ljava/lang/Integer;
     345: aastore
     346: dup
     347: iconst_5
     348: ldc           #120                // String ,
     350: invokestatic  #37                 // Method com/google/common/base/Joiner.on:(Ljava/lang/String;)Lcom/google/common/base/Joiner;
     353: aload         4
     355: invokevirtual #38                 // Method com/google/common/base/Joiner.join:(Ljava/lang/Iterable;)Ljava/lang/String;
     358: aastore
     359: invokestatic  #73                 // Method java/lang/String.format:(Ljava/lang/String;[Ljava/lang/Object;)Ljava/lang/String;
     362: invokeinterface #75,  2           // InterfaceMethod org/slf4j/Logger.info:(Ljava/lang/String;)V
     367: aload         7
     369: areturn
    Exception table:
       from    to  target type
         103   126   134   Class java/io/IOException
         103   126   166   any
         134   168   166   any

  public org.reflections.Reflections collect(java.io.InputStream);
    Code:
       0: aload_0
       1: aload_0
       2: getfield      #3                  // Field configuration:Lorg/reflections/Configuration;
       5: invokeinterface #121,  1          // InterfaceMethod org/reflections/Configuration.getSerializer:()Lorg/reflections/serializers/Serializer;
      10: aload_1
      11: invokeinterface #109,  2          // InterfaceMethod org/reflections/serializers/Serializer.read:(Ljava/io/InputStream;)Lorg/reflections/Reflections;
      16: invokevirtual #110                // Method merge:(Lorg/reflections/Reflections;)Lorg/reflections/Reflections;
      19: pop
      20: getstatic     #28                 // Field log:Lorg/slf4j/Logger;
      23: ifnull        67
      26: getstatic     #28                 // Field log:Lorg/slf4j/Logger;
      29: new           #32                 // class java/lang/StringBuilder
      32: dup
      33: invokespecial #33                 // Method java/lang/StringBuilder."<init>":()V
      36: ldc           #122                // String Reflections collected metadata from input stream using serializer
      38: invokevirtual #35                 // Method java/lang/StringBuilder.append:(Ljava/lang/String;)Ljava/lang/StringBuilder;
      41: aload_0
      42: getfield      #3                  // Field configuration:Lorg/reflections/Configuration;
      45: invokeinterface #121,  1          // InterfaceMethod org/reflections/Configuration.getSerializer:()Lorg/reflections/serializers/Serializer;
      50: invokevirtual #14                 // Method java/lang/Object.getClass:()Ljava/lang/Class;
      53: invokevirtual #123                // Method java/lang/Class.getName:()Ljava/lang/String;
      56: invokevirtual #35                 // Method java/lang/StringBuilder.append:(Ljava/lang/String;)Ljava/lang/StringBuilder;
      59: invokevirtual #39                 // Method java/lang/StringBuilder.toString:()Ljava/lang/String;
      62: invokeinterface #75,  2           // InterfaceMethod org/slf4j/Logger.info:(Ljava/lang/String;)V
      67: goto          82
      70: astore_2
      71: new           #50                 // class org/reflections/ReflectionsException
      74: dup
      75: ldc           #124                // String could not merge input stream
      77: aload_2
      78: invokespecial #115                // Method org/reflections/ReflectionsException."<init>":(Ljava/lang/String;Ljava/lang/Throwable;)V
      81: athrow
      82: aload_0
      83: areturn
    Exception table:
       from    to  target type
           0    67    70   Class java/lang/Exception

  public org.reflections.Reflections collect(java.io.File);
    Code:
       0: aconst_null
       1: astore_2
       2: new           #125                // class java/io/FileInputStream
       5: dup
       6: aload_1
       7: invokespecial #126                // Method java/io/FileInputStream."<init>":(Ljava/io/File;)V
      10: astore_2
      11: aload_0
      12: aload_2
      13: invokevirtual #127                // Method collect:(Ljava/io/InputStream;)Lorg/reflections/Reflections;
      16: astore_3
      17: aload_2
      18: invokestatic  #111                // Method org/reflections/util/Utils.close:(Ljava/io/InputStream;)V
      21: aload_3
      22: areturn
      23: astore_3
      24: new           #50                 // class org/reflections/ReflectionsException
      27: dup
      28: new           #32                 // class java/lang/StringBuilder
      31: dup
      32: invokespecial #33                 // Method java/lang/StringBuilder."<init>":()V
      35: ldc           #129                // String could not obtain input stream from file
      37: invokevirtual #35                 // Method java/lang/StringBuilder.append:(Ljava/lang/String;)Ljava/lang/StringBuilder;
      40: aload_1
      41: invokevirtual #114                // Method java/lang/StringBuilder.append:(Ljava/lang/Object;)Ljava/lang/StringBuilder;
      44: invokevirtual #39                 // Method java/lang/StringBuilder.toString:()Ljava/lang/String;
      47: aload_3
      48: invokespecial #115                // Method org/reflections/ReflectionsException."<init>":(Ljava/lang/String;Ljava/lang/Throwable;)V
      51: athrow
      52: astore        4
      54: aload_2
      55: invokestatic  #111                // Method org/reflections/util/Utils.close:(Ljava/io/InputStream;)V
      58: aload         4
      60: athrow
    Exception table:
       from    to  target type
           2    17    23   Class java/io/FileNotFoundException
           2    17    52   any
          23    54    52   any

  public org.reflections.Reflections merge(org.reflections.Reflections);
    Code:
       0: aload_1
       1: getfield      #6                  // Field store:Lorg/reflections/Store;
       4: ifnull        150
       7: aload_1
       8: getfield      #6                  // Field store:Lorg/reflections/Store;
      11: invokevirtual #61                 // Method org/reflections/Store.keySet:()Ljava/util/Set;
      14: invokeinterface #9,  1            // InterfaceMethod java/util/Set.iterator:()Ljava/util/Iterator;
      19: astore_2
      20: aload_2
      21: invokeinterface #10,  1           // InterfaceMethod java/util/Iterator.hasNext:()Z
      26: ifeq          150
      29: aload_2
      30: invokeinterface #11,  1           // InterfaceMethod java/util/Iterator.next:()Ljava/lang/Object;
      35: checkcast     #62                 // class java/lang/String
      38: astore_3
      39: aload_1
      40: getfield      #6                  // Field store:Lorg/reflections/Store;
      43: aload_3
      44: invokevirtual #63                 // Method org/reflections/Store.get:(Ljava/lang/String;)Lcom/google/common/collect/Multimap;
      47: astore        4
      49: aload         4
      51: invokeinterface #64,  1           // InterfaceMethod com/google/common/collect/Multimap.keySet:()Ljava/util/Set;
      56: invokeinterface #9,  1            // InterfaceMethod java/util/Set.iterator:()Ljava/util/Iterator;
      61: astore        5
      63: aload         5
      65: invokeinterface #10,  1           // InterfaceMethod java/util/Iterator.hasNext:()Z
      70: ifeq          147
      73: aload         5
      75: invokeinterface #11,  1           // InterfaceMethod java/util/Iterator.next:()Ljava/lang/Object;
      80: checkcast     #62                 // class java/lang/String
      83: astore        6
      85: aload         4
      87: aload         6
      89: invokeinterface #130,  2          // InterfaceMethod com/google/common/collect/Multimap.get:(Ljava/lang/Object;)Ljava/util/Collection;
      94: invokeinterface #131,  1          // InterfaceMethod java/util/Collection.iterator:()Ljava/util/Iterator;
      99: astore        7
     101: aload         7
     103: invokeinterface #10,  1           // InterfaceMethod java/util/Iterator.hasNext:()Z
     108: ifeq          144
     111: aload         7
     113: invokeinterface #11,  1           // InterfaceMethod java/util/Iterator.next:()Ljava/lang/Object;
     118: checkcast     #62                 // class java/lang/String
     121: astore        8
     123: aload_0
     124: getfield      #6                  // Field store:Lorg/reflections/Store;
     127: aload_3
     128: invokevirtual #16                 // Method org/reflections/Store.getOrCreate:(Ljava/lang/String;)Lcom/google/common/collect/Multimap;
     131: aload         6
     133: aload         8
     135: invokeinterface #132,  3          // InterfaceMethod com/google/common/collect/Multimap.put:(Ljava/lang/Object;Ljava/lang/Object;)Z
     140: pop
     141: goto          101
     144: goto          63
     147: goto          20
     150: aload_0
     151: areturn

  public void expandSuperTypes();
    Code:
       0: aload_0
       1: getfield      #6                  // Field store:Lorg/reflections/Store;
       4: invokevirtual #61                 // Method org/reflections/Store.keySet:()Ljava/util/Set;
       7: ldc           #133                // class org/reflections/scanners/SubTypesScanner
       9: invokestatic  #134                // Method index:(Ljava/lang/Class;)Ljava/lang/String;
      12: invokeinterface #135,  2          // InterfaceMethod java/util/Set.contains:(Ljava/lang/Object;)Z
      17: ifeq          120
      20: aload_0
      21: getfield      #6                  // Field store:Lorg/reflections/Store;
      24: ldc           #133                // class org/reflections/scanners/SubTypesScanner
      26: invokestatic  #134                // Method index:(Ljava/lang/Class;)Ljava/lang/String;
      29: invokevirtual #63                 // Method org/reflections/Store.get:(Ljava/lang/String;)Lcom/google/common/collect/Multimap;
      32: astore_1
      33: aload_1
      34: invokeinterface #64,  1           // InterfaceMethod com/google/common/collect/Multimap.keySet:()Ljava/util/Set;
      39: aload_1
      40: invokeinterface #136,  1          // InterfaceMethod com/google/common/collect/Multimap.values:()Ljava/util/Collection;
      45: invokestatic  #137                // Method com/google/common/collect/Sets.newHashSet:(Ljava/lang/Iterable;)Ljava/util/HashSet;
      48: invokestatic  #138                // Method com/google/common/collect/Sets.difference:(Ljava/util/Set;Ljava/util/Set;)Lcom/google/common/collect/Sets$SetView;
      51: astore_2
      52: invokestatic  #139                // Method com/google/common/collect/HashMultimap.create:()Lcom/google/common/collect/HashMultimap;
      55: astore_3
      56: aload_2
      57: invokevirtual #140                // Method com/google/common/collect/Sets$SetView.iterator:()Lcom/google/common/collect/UnmodifiableIterator;
      60: astore        4
      62: aload         4
      64: invokeinterface #10,  1           // InterfaceMethod java/util/Iterator.hasNext:()Z
      69: ifeq          112
      72: aload         4
      74: invokeinterface #11,  1           // InterfaceMethod java/util/Iterator.next:()Ljava/lang/Object;
      79: checkcast     #62                 // class java/lang/String
      82: astore        5
      84: aload         5
      86: iconst_0
      87: anewarray     #102                // class java/lang/ClassLoader
      90: invokestatic  #141                // Method org/reflections/ReflectionUtils.forName:(Ljava/lang/String;[Ljava/lang/ClassLoader;)Ljava/lang/Class;
      93: astore        6
      95: aload         6
      97: ifnull        109
     100: aload_0
     101: aload_3
     102: aload         5
     104: aload         6
     106: invokespecial #142                // Method expandSupertypes:(Lcom/google/common/collect/Multimap;Ljava/lang/String;Ljava/lang/Class;)V
     109: goto          62
     112: aload_1
     113: aload_3
     114: invokeinterface #143,  2          // InterfaceMethod com/google/common/collect/Multimap.putAll:(Lcom/google/common/collect/Multimap;)Z
     119: pop
     120: return

  private void expandSupertypes(com.google.common.collect.Multimap<java.lang.String, java.lang.String>, java.lang.String, java.lang.Class<?>);
    Code:
       0: aload_3
       1: invokestatic  #144                // Method org/reflections/ReflectionUtils.getSuperTypes:(Ljava/lang/Class;)Ljava/util/Set;
       4: invokeinterface #9,  1            // InterfaceMethod java/util/Set.iterator:()Ljava/util/Iterator;
       9: astore        4
      11: aload         4
      13: invokeinterface #10,  1           // InterfaceMethod java/util/Iterator.hasNext:()Z
      18: ifeq          85
      21: aload         4
      23: invokeinterface #11,  1           // InterfaceMethod java/util/Iterator.next:()Ljava/lang/Object;
      28: checkcast     #145                // class java/lang/Class
      31: astore        5
      33: aload_1
      34: aload         5
      36: invokevirtual #123                // Method java/lang/Class.getName:()Ljava/lang/String;
      39: aload_2
      40: invokeinterface #132,  3          // InterfaceMethod com/google/common/collect/Multimap.put:(Ljava/lang/Object;Ljava/lang/Object;)Z
      45: ifeq          82
      48: getstatic     #28                 // Field log:Lorg/slf4j/Logger;
      51: ifnull        70
      54: getstatic     #28                 // Field log:Lorg/slf4j/Logger;
      57: ldc           #146                // String expanded subtype {} -> {}
      59: aload         5
      61: invokevirtual #123                // Method java/lang/Class.getName:()Ljava/lang/String;
      64: aload_2
      65: invokeinterface #147,  4          // InterfaceMethod org/slf4j/Logger.debug:(Ljava/lang/String;Ljava/lang/Object;Ljava/lang/Object;)V
      70: aload_0
      71: aload_1
      72: aload         5
      74: invokevirtual #123                // Method java/lang/Class.getName:()Ljava/lang/String;
      77: aload         5
      79: invokespecial #142                // Method expandSupertypes:(Lcom/google/common/collect/Multimap;Ljava/lang/String;Ljava/lang/Class;)V
      82: goto          11
      85: return

  public <T> java.util.Set<java.lang.Class<? extends T>> getSubTypesOf(java.lang.Class<T>);
    Code:
       0: aload_0
       1: getfield      #6                  // Field store:Lorg/reflections/Store;
       4: ldc           #133                // class org/reflections/scanners/SubTypesScanner
       6: invokestatic  #134                // Method index:(Ljava/lang/Class;)Ljava/lang/String;
       9: iconst_1
      10: anewarray     #62                 // class java/lang/String
      13: dup
      14: iconst_0
      15: aload_1
      16: invokevirtual #123                // Method java/lang/Class.getName:()Ljava/lang/String;
      19: aastore
      20: invokestatic  #148                // Method java/util/Arrays.asList:([Ljava/lang/Object;)Ljava/util/List;
      23: invokevirtual #149                // Method org/reflections/Store.getAll:(Ljava/lang/String;Ljava/lang/Iterable;)Ljava/lang/Iterable;
      26: aload_0
      27: invokespecial #1                  // Method loaders:()[Ljava/lang/ClassLoader;
      30: invokestatic  #150                // Method org/reflections/ReflectionUtils.forNames:(Ljava/lang/Iterable;[Ljava/lang/ClassLoader;)Ljava/util/List;
      33: invokestatic  #137                // Method com/google/common/collect/Sets.newHashSet:(Ljava/lang/Iterable;)Ljava/util/HashSet;
      36: areturn

  public java.util.Set<java.lang.Class<?>> getTypesAnnotatedWith(java.lang.Class<? extends java.lang.annotation.Annotation>);
    Code:
       0: aload_0
       1: aload_1
       2: iconst_0
       3: invokevirtual #151                // Method getTypesAnnotatedWith:(Ljava/lang/Class;Z)Ljava/util/Set;
       6: areturn

  public java.util.Set<java.lang.Class<?>> getTypesAnnotatedWith(java.lang.Class<? extends java.lang.annotation.Annotation>, boolean);
    Code:
       0: aload_0
       1: getfield      #6                  // Field store:Lorg/reflections/Store;
       4: ldc           #152                // class org/reflections/scanners/TypeAnnotationsScanner
       6: invokestatic  #134                // Method index:(Ljava/lang/Class;)Ljava/lang/String;
       9: iconst_1
      10: anewarray     #62                 // class java/lang/String
      13: dup
      14: iconst_0
      15: aload_1
      16: invokevirtual #123                // Method java/lang/Class.getName:()Ljava/lang/String;
      19: aastore
      20: invokevirtual #153                // Method org/reflections/Store.get:(Ljava/lang/String;[Ljava/lang/String;)Ljava/lang/Iterable;
      23: astore_3
      24: aload_0
      25: aload_3
      26: aload_1
      27: ldc           #154                // class java/lang/annotation/Inherited
      29: invokevirtual #155                // Method java/lang/Class.isAnnotationPresent:(Ljava/lang/Class;)Z
      32: iload_2
      33: invokevirtual #156                // Method getAllAnnotated:(Ljava/lang/Iterable;ZZ)Ljava/lang/Iterable;
      36: astore        4
      38: aload_3
      39: aload_0
      40: invokespecial #1                  // Method loaders:()[Ljava/lang/ClassLoader;
      43: invokestatic  #150                // Method org/reflections/ReflectionUtils.forNames:(Ljava/lang/Iterable;[Ljava/lang/ClassLoader;)Ljava/util/List;
      46: aload         4
      48: aload_0
      49: invokespecial #1                  // Method loaders:()[Ljava/lang/ClassLoader;
      52: invokestatic  #150                // Method org/reflections/ReflectionUtils.forNames:(Ljava/lang/Iterable;[Ljava/lang/ClassLoader;)Ljava/util/List;
      55: invokestatic  #157                // Method com/google/common/collect/Iterables.concat:(Ljava/lang/Iterable;Ljava/lang/Iterable;)Ljava/lang/Iterable;
      58: invokestatic  #137                // Method com/google/common/collect/Sets.newHashSet:(Ljava/lang/Iterable;)Ljava/util/HashSet;
      61: areturn

  public java.util.Set<java.lang.Class<?>> getTypesAnnotatedWith(java.lang.annotation.Annotation);
    Code:
       0: aload_0
       1: aload_1
       2: iconst_0
       3: invokevirtual #158                // Method getTypesAnnotatedWith:(Ljava/lang/annotation/Annotation;Z)Ljava/util/Set;
       6: areturn

  public java.util.Set<java.lang.Class<?>> getTypesAnnotatedWith(java.lang.annotation.Annotation, boolean);
    Code:
       0: aload_0
       1: getfield      #6                  // Field store:Lorg/reflections/Store;
       4: ldc           #152                // class org/reflections/scanners/TypeAnnotationsScanner
       6: invokestatic  #134                // Method index:(Ljava/lang/Class;)Ljava/lang/String;
       9: iconst_1
      10: anewarray     #62                 // class java/lang/String
      13: dup
      14: iconst_0
      15: aload_1
      16: invokeinterface #159,  1          // InterfaceMethod java/lang/annotation/Annotation.annotationType:()Ljava/lang/Class;
      21: invokevirtual #123                // Method java/lang/Class.getName:()Ljava/lang/String;
      24: aastore
      25: invokevirtual #153                // Method org/reflections/Store.get:(Ljava/lang/String;[Ljava/lang/String;)Ljava/lang/Iterable;
      28: astore_3
      29: aload_3
      30: aload_0
      31: invokespecial #1                  // Method loaders:()[Ljava/lang/ClassLoader;
      34: invokestatic  #150                // Method org/reflections/ReflectionUtils.forNames:(Ljava/lang/Iterable;[Ljava/lang/ClassLoader;)Ljava/util/List;
      37: iconst_1
      38: anewarray     #160                // class com/google/common/base/Predicate
      41: dup
      42: iconst_0
      43: aload_1
      44: invokestatic  #161                // Method org/reflections/ReflectionUtils.withAnnotation:(Ljava/lang/annotation/Annotation;)Lcom/google/common/base/Predicate;
      47: aastore
      48: invokestatic  #162                // Method org/reflections/ReflectionUtils.filter:(Ljava/lang/Iterable;[Lcom/google/common/base/Predicate;)Ljava/util/Set;
      51: astore        4
      53: aload_0
      54: aload         4
      56: invokestatic  #163                // Method org/reflections/util/Utils.names:(Ljava/lang/Iterable;)Ljava/util/List;
      59: aload_1
      60: invokeinterface #159,  1          // InterfaceMethod java/lang/annotation/Annotation.annotationType:()Ljava/lang/Class;
      65: ldc           #154                // class java/lang/annotation/Inherited
      67: invokevirtual #155                // Method java/lang/Class.isAnnotationPresent:(Ljava/lang/Class;)Z
      70: iload_2
      71: invokevirtual #156                // Method getAllAnnotated:(Ljava/lang/Iterable;ZZ)Ljava/lang/Iterable;
      74: astore        5
      76: aload         4
      78: aload         5
      80: iconst_1
      81: anewarray     #160                // class com/google/common/base/Predicate
      84: dup
      85: iconst_0
      86: aload_3
      87: invokestatic  #137                // Method com/google/common/collect/Sets.newHashSet:(Ljava/lang/Iterable;)Ljava/util/HashSet;
      90: invokestatic  #164                // Method com/google/common/base/Predicates.in:(Ljava/util/Collection;)Lcom/google/common/base/Predicate;
      93: invokestatic  #165                // Method com/google/common/base/Predicates.not:(Lcom/google/common/base/Predicate;)Lcom/google/common/base/Predicate;
      96: aastore
      97: invokestatic  #162                // Method org/reflections/ReflectionUtils.filter:(Ljava/lang/Iterable;[Lcom/google/common/base/Predicate;)Ljava/util/Set;
     100: aload_0
     101: invokespecial #1                  // Method loaders:()[Ljava/lang/ClassLoader;
     104: invokestatic  #150                // Method org/reflections/ReflectionUtils.forNames:(Ljava/lang/Iterable;[Ljava/lang/ClassLoader;)Ljava/util/List;
     107: invokestatic  #157                // Method com/google/common/collect/Iterables.concat:(Ljava/lang/Iterable;Ljava/lang/Iterable;)Ljava/lang/Iterable;
     110: invokestatic  #137                // Method com/google/common/collect/Sets.newHashSet:(Ljava/lang/Iterable;)Ljava/util/HashSet;
     113: areturn

  protected java.lang.Iterable<java.lang.String> getAllAnnotated(java.lang.Iterable<java.lang.String>, boolean, boolean);
    Code:
       0: iload_3
       1: ifeq          63
       4: iload_2
       5: ifeq          61
       8: aload_0
       9: getfield      #6                  // Field store:Lorg/reflections/Store;
      12: ldc           #133                // class org/reflections/scanners/SubTypesScanner
      14: invokestatic  #134                // Method index:(Ljava/lang/Class;)Ljava/lang/String;
      17: aload_1
      18: iconst_1
      19: anewarray     #160                // class com/google/common/base/Predicate
      22: dup
      23: iconst_0
      24: new           #166                // class org/reflections/Reflections$2
      27: dup
      28: aload_0
      29: invokespecial #167                // Method org/reflections/Reflections$2."<init>":(Lorg/reflections/Reflections;)V
      32: aastore
      33: invokestatic  #162                // Method org/reflections/ReflectionUtils.filter:(Ljava/lang/Iterable;[Lcom/google/common/base/Predicate;)Ljava/util/Set;
      36: invokevirtual #168                // Method org/reflections/Store.get:(Ljava/lang/String;Ljava/lang/Iterable;)Ljava/lang/Iterable;
      39: astore        4
      41: aload         4
      43: aload_0
      44: getfield      #6                  // Field store:Lorg/reflections/Store;
      47: ldc           #133                // class org/reflections/scanners/SubTypesScanner
      49: invokestatic  #134                // Method index:(Ljava/lang/Class;)Ljava/lang/String;
      52: aload         4
      54: invokevirtual #149                // Method org/reflections/Store.getAll:(Ljava/lang/String;Ljava/lang/Iterable;)Ljava/lang/Iterable;
      57: invokestatic  #157                // Method com/google/common/collect/Iterables.concat:(Ljava/lang/Iterable;Ljava/lang/Iterable;)Ljava/lang/Iterable;
      60: areturn
      61: aload_1
      62: areturn
      63: aload_1
      64: aload_0
      65: getfield      #6                  // Field store:Lorg/reflections/Store;
      68: ldc           #152                // class org/reflections/scanners/TypeAnnotationsScanner
      70: invokestatic  #134                // Method index:(Ljava/lang/Class;)Ljava/lang/String;
      73: aload_1
      74: invokevirtual #149                // Method org/reflections/Store.getAll:(Ljava/lang/String;Ljava/lang/Iterable;)Ljava/lang/Iterable;
      77: invokestatic  #157                // Method com/google/common/collect/Iterables.concat:(Ljava/lang/Iterable;Ljava/lang/Iterable;)Ljava/lang/Iterable;
      80: astore        4
      82: aload         4
      84: aload_0
      85: getfield      #6                  // Field store:Lorg/reflections/Store;
      88: ldc           #133                // class org/reflections/scanners/SubTypesScanner
      90: invokestatic  #134                // Method index:(Ljava/lang/Class;)Ljava/lang/String;
      93: aload         4
      95: invokevirtual #149                // Method org/reflections/Store.getAll:(Ljava/lang/String;Ljava/lang/Iterable;)Ljava/lang/Iterable;
      98: invokestatic  #157                // Method com/google/common/collect/Iterables.concat:(Ljava/lang/Iterable;Ljava/lang/Iterable;)Ljava/lang/Iterable;
     101: areturn

  public java.util.Set<java.lang.reflect.Method> getMethodsAnnotatedWith(java.lang.Class<? extends java.lang.annotation.Annotation>);
    Code:
       0: aload_0
       1: getfield      #6                  // Field store:Lorg/reflections/Store;
       4: ldc           #169                // class org/reflections/scanners/MethodAnnotationsScanner
       6: invokestatic  #134                // Method index:(Ljava/lang/Class;)Ljava/lang/String;
       9: iconst_1
      10: anewarray     #62                 // class java/lang/String
      13: dup
      14: iconst_0
      15: aload_1
      16: invokevirtual #123                // Method java/lang/Class.getName:()Ljava/lang/String;
      19: aastore
      20: invokevirtual #153                // Method org/reflections/Store.get:(Ljava/lang/String;[Ljava/lang/String;)Ljava/lang/Iterable;
      23: astore_2
      24: aload_2
      25: aload_0
      26: invokespecial #1                  // Method loaders:()[Ljava/lang/ClassLoader;
      29: invokestatic  #170                // Method org/reflections/util/Utils.getMethodsFromDescriptors:(Ljava/lang/Iterable;[Ljava/lang/ClassLoader;)Ljava/util/Set;
      32: areturn

  public java.util.Set<java.lang.reflect.Method> getMethodsAnnotatedWith(java.lang.annotation.Annotation);
    Code:
       0: aload_0
       1: aload_1
       2: invokeinterface #159,  1          // InterfaceMethod java/lang/annotation/Annotation.annotationType:()Ljava/lang/Class;
       7: invokevirtual #171                // Method getMethodsAnnotatedWith:(Ljava/lang/Class;)Ljava/util/Set;
      10: iconst_1
      11: anewarray     #160                // class com/google/common/base/Predicate
      14: dup
      15: iconst_0
      16: aload_1
      17: invokestatic  #161                // Method org/reflections/ReflectionUtils.withAnnotation:(Ljava/lang/annotation/Annotation;)Lcom/google/common/base/Predicate;
      20: aastore
      21: invokestatic  #162                // Method org/reflections/ReflectionUtils.filter:(Ljava/lang/Iterable;[Lcom/google/common/base/Predicate;)Ljava/util/Set;
      24: areturn

  public java.util.Set<java.lang.reflect.Method> getMethodsMatchParams(java.lang.Class<?>...);
    Code:
       0: aload_0
       1: getfield      #6                  // Field store:Lorg/reflections/Store;
       4: ldc           #172                // class org/reflections/scanners/MethodParameterScanner
       6: invokestatic  #134                // Method index:(Ljava/lang/Class;)Ljava/lang/String;
       9: iconst_1
      10: anewarray     #62                 // class java/lang/String
      13: dup
      14: iconst_0
      15: aload_1
      16: invokestatic  #173                // Method org/reflections/util/Utils.names:([Ljava/lang/Class;)Ljava/util/List;
      19: invokevirtual #174                // Method java/lang/Object.toString:()Ljava/lang/String;
      22: aastore
      23: invokevirtual #153                // Method org/reflections/Store.get:(Ljava/lang/String;[Ljava/lang/String;)Ljava/lang/Iterable;
      26: aload_0
      27: invokespecial #1                  // Method loaders:()[Ljava/lang/ClassLoader;
      30: invokestatic  #170                // Method org/reflections/util/Utils.getMethodsFromDescriptors:(Ljava/lang/Iterable;[Ljava/lang/ClassLoader;)Ljava/util/Set;
      33: areturn

  public java.util.Set<java.lang.reflect.Method> getMethodsReturn(java.lang.Class);
    Code:
       0: aload_0
       1: getfield      #6                  // Field store:Lorg/reflections/Store;
       4: ldc           #172                // class org/reflections/scanners/MethodParameterScanner
       6: invokestatic  #134                // Method index:(Ljava/lang/Class;)Ljava/lang/String;
       9: iconst_1
      10: anewarray     #145                // class java/lang/Class
      13: dup
      14: iconst_0
      15: aload_1
      16: aastore
      17: invokestatic  #173                // Method org/reflections/util/Utils.names:([Ljava/lang/Class;)Ljava/util/List;
      20: invokevirtual #168                // Method org/reflections/Store.get:(Ljava/lang/String;Ljava/lang/Iterable;)Ljava/lang/Iterable;
      23: aload_0
      24: invokespecial #1                  // Method loaders:()[Ljava/lang/ClassLoader;
      27: invokestatic  #170                // Method org/reflections/util/Utils.getMethodsFromDescriptors:(Ljava/lang/Iterable;[Ljava/lang/ClassLoader;)Ljava/util/Set;
      30: areturn

  public java.util.Set<java.lang.reflect.Method> getMethodsWithAnyParamAnnotated(java.lang.Class<? extends java.lang.annotation.Annotation>);
    Code:
       0: aload_0
       1: getfield      #6                  // Field store:Lorg/reflections/Store;
       4: ldc           #172                // class org/reflections/scanners/MethodParameterScanner
       6: invokestatic  #134                // Method index:(Ljava/lang/Class;)Ljava/lang/String;
       9: iconst_1
      10: anewarray     #62                 // class java/lang/String
      13: dup
      14: iconst_0
      15: aload_1
      16: invokevirtual #123                // Method java/lang/Class.getName:()Ljava/lang/String;
      19: aastore
      20: invokevirtual #153                // Method org/reflections/Store.get:(Ljava/lang/String;[Ljava/lang/String;)Ljava/lang/Iterable;
      23: aload_0
      24: invokespecial #1                  // Method loaders:()[Ljava/lang/ClassLoader;
      27: invokestatic  #170                // Method org/reflections/util/Utils.getMethodsFromDescriptors:(Ljava/lang/Iterable;[Ljava/lang/ClassLoader;)Ljava/util/Set;
      30: areturn

  public java.util.Set<java.lang.reflect.Method> getMethodsWithAnyParamAnnotated(java.lang.annotation.Annotation);
    Code:
       0: aload_0
       1: aload_1
       2: invokeinterface #159,  1          // InterfaceMethod java/lang/annotation/Annotation.annotationType:()Ljava/lang/Class;
       7: invokevirtual #175                // Method getMethodsWithAnyParamAnnotated:(Ljava/lang/Class;)Ljava/util/Set;
      10: iconst_1
      11: anewarray     #160                // class com/google/common/base/Predicate
      14: dup
      15: iconst_0
      16: aload_1
      17: invokestatic  #176                // Method org/reflections/ReflectionUtils.withAnyParameterAnnotation:(Ljava/lang/annotation/Annotation;)Lcom/google/common/base/Predicate;
      20: aastore
      21: invokestatic  #162                // Method org/reflections/ReflectionUtils.filter:(Ljava/lang/Iterable;[Lcom/google/common/base/Predicate;)Ljava/util/Set;
      24: areturn

  public java.util.Set<java.lang.reflect.Constructor> getConstructorsAnnotatedWith(java.lang.Class<? extends java.lang.annotation.Annotation>);
    Code:
       0: aload_0
       1: getfield      #6                  // Field store:Lorg/reflections/Store;
       4: ldc           #169                // class org/reflections/scanners/MethodAnnotationsScanner
       6: invokestatic  #134                // Method index:(Ljava/lang/Class;)Ljava/lang/String;
       9: iconst_1
      10: anewarray     #62                 // class java/lang/String
      13: dup
      14: iconst_0
      15: aload_1
      16: invokevirtual #123                // Method java/lang/Class.getName:()Ljava/lang/String;
      19: aastore
      20: invokevirtual #153                // Method org/reflections/Store.get:(Ljava/lang/String;[Ljava/lang/String;)Ljava/lang/Iterable;
      23: astore_2
      24: aload_2
      25: aload_0
      26: invokespecial #1                  // Method loaders:()[Ljava/lang/ClassLoader;
      29: invokestatic  #177                // Method org/reflections/util/Utils.getConstructorsFromDescriptors:(Ljava/lang/Iterable;[Ljava/lang/ClassLoader;)Ljava/util/Set;
      32: areturn

  public java.util.Set<java.lang.reflect.Constructor> getConstructorsAnnotatedWith(java.lang.annotation.Annotation);
    Code:
       0: aload_0
       1: aload_1
       2: invokeinterface #159,  1          // InterfaceMethod java/lang/annotation/Annotation.annotationType:()Ljava/lang/Class;
       7: invokevirtual #178                // Method getConstructorsAnnotatedWith:(Ljava/lang/Class;)Ljava/util/Set;
      10: iconst_1
      11: anewarray     #160                // class com/google/common/base/Predicate
      14: dup
      15: iconst_0
      16: aload_1
      17: invokestatic  #161                // Method org/reflections/ReflectionUtils.withAnnotation:(Ljava/lang/annotation/Annotation;)Lcom/google/common/base/Predicate;
      20: aastore
      21: invokestatic  #162                // Method org/reflections/ReflectionUtils.filter:(Ljava/lang/Iterable;[Lcom/google/common/base/Predicate;)Ljava/util/Set;
      24: areturn

  public java.util.Set<java.lang.reflect.Constructor> getConstructorsMatchParams(java.lang.Class<?>...);
    Code:
       0: aload_0
       1: getfield      #6                  // Field store:Lorg/reflections/Store;
       4: ldc           #172                // class org/reflections/scanners/MethodParameterScanner
       6: invokestatic  #134                // Method index:(Ljava/lang/Class;)Ljava/lang/String;
       9: iconst_1
      10: anewarray     #62                 // class java/lang/String
      13: dup
      14: iconst_0
      15: aload_1
      16: invokestatic  #173                // Method org/reflections/util/Utils.names:([Ljava/lang/Class;)Ljava/util/List;
      19: invokevirtual #174                // Method java/lang/Object.toString:()Ljava/lang/String;
      22: aastore
      23: invokevirtual #153                // Method org/reflections/Store.get:(Ljava/lang/String;[Ljava/lang/String;)Ljava/lang/Iterable;
      26: aload_0
      27: invokespecial #1                  // Method loaders:()[Ljava/lang/ClassLoader;
      30: invokestatic  #177                // Method org/reflections/util/Utils.getConstructorsFromDescriptors:(Ljava/lang/Iterable;[Ljava/lang/ClassLoader;)Ljava/util/Set;
      33: areturn

  public java.util.Set<java.lang.reflect.Constructor> getConstructorsWithAnyParamAnnotated(java.lang.Class<? extends java.lang.annotation.Annotation>);
    Code:
       0: aload_0
       1: getfield      #6                  // Field store:Lorg/reflections/Store;
       4: ldc           #172                // class org/reflections/scanners/MethodParameterScanner
       6: invokestatic  #134                // Method index:(Ljava/lang/Class;)Ljava/lang/String;
       9: iconst_1
      10: anewarray     #62                 // class java/lang/String
      13: dup
      14: iconst_0
      15: aload_1
      16: invokevirtual #123                // Method java/lang/Class.getName:()Ljava/lang/String;
      19: aastore
      20: invokevirtual #153                // Method org/reflections/Store.get:(Ljava/lang/String;[Ljava/lang/String;)Ljava/lang/Iterable;
      23: aload_0
      24: invokespecial #1                  // Method loaders:()[Ljava/lang/ClassLoader;
      27: invokestatic  #177                // Method org/reflections/util/Utils.getConstructorsFromDescriptors:(Ljava/lang/Iterable;[Ljava/lang/ClassLoader;)Ljava/util/Set;
      30: areturn

  public java.util.Set<java.lang.reflect.Constructor> getConstructorsWithAnyParamAnnotated(java.lang.annotation.Annotation);
    Code:
       0: aload_0
       1: aload_1
       2: invokeinterface #159,  1          // InterfaceMethod java/lang/annotation/Annotation.annotationType:()Ljava/lang/Class;
       7: invokevirtual #179                // Method getConstructorsWithAnyParamAnnotated:(Ljava/lang/Class;)Ljava/util/Set;
      10: iconst_1
      11: anewarray     #160                // class com/google/common/base/Predicate
      14: dup
      15: iconst_0
      16: aload_1
      17: invokestatic  #176                // Method org/reflections/ReflectionUtils.withAnyParameterAnnotation:(Ljava/lang/annotation/Annotation;)Lcom/google/common/base/Predicate;
      20: aastore
      21: invokestatic  #162                // Method org/reflections/ReflectionUtils.filter:(Ljava/lang/Iterable;[Lcom/google/common/base/Predicate;)Ljava/util/Set;
      24: areturn

  public java.util.Set<java.lang.reflect.Field> getFieldsAnnotatedWith(java.lang.Class<? extends java.lang.annotation.Annotation>);
    Code:
       0: invokestatic  #180                // Method com/google/common/collect/Sets.newHashSet:()Ljava/util/HashSet;
       3: astore_2
       4: aload_0
       5: getfield      #6                  // Field store:Lorg/reflections/Store;
       8: ldc           #181                // class org/reflections/scanners/FieldAnnotationsScanner
      10: invokestatic  #134                // Method index:(Ljava/lang/Class;)Ljava/lang/String;
      13: iconst_1
      14: anewarray     #62                 // class java/lang/String
      17: dup
      18: iconst_0
      19: aload_1
      20: invokevirtual #123                // Method java/lang/Class.getName:()Ljava/lang/String;
      23: aastore
      24: invokevirtual #153                // Method org/reflections/Store.get:(Ljava/lang/String;[Ljava/lang/String;)Ljava/lang/Iterable;
      27: invokeinterface #78,  1           // InterfaceMethod java/lang/Iterable.iterator:()Ljava/util/Iterator;
      32: astore_3
      33: aload_3
      34: invokeinterface #10,  1           // InterfaceMethod java/util/Iterator.hasNext:()Z
      39: ifeq          72
      42: aload_3
      43: invokeinterface #11,  1           // InterfaceMethod java/util/Iterator.next:()Ljava/lang/Object;
      48: checkcast     #62                 // class java/lang/String
      51: astore        4
      53: aload_2
      54: aload         4
      56: aload_0
      57: invokespecial #1                  // Method loaders:()[Ljava/lang/ClassLoader;
      60: invokestatic  #182                // Method org/reflections/util/Utils.getFieldFromString:(Ljava/lang/String;[Ljava/lang/ClassLoader;)Ljava/lang/reflect/Field;
      63: invokeinterface #183,  2          // InterfaceMethod java/util/Set.add:(Ljava/lang/Object;)Z
      68: pop
      69: goto          33
      72: aload_2
      73: areturn

  public java.util.Set<java.lang.reflect.Field> getFieldsAnnotatedWith(java.lang.annotation.Annotation);
    Code:
       0: aload_0
       1: aload_1
       2: invokeinterface #159,  1          // InterfaceMethod java/lang/annotation/Annotation.annotationType:()Ljava/lang/Class;
       7: invokevirtual #184                // Method getFieldsAnnotatedWith:(Ljava/lang/Class;)Ljava/util/Set;
      10: iconst_1
      11: anewarray     #160                // class com/google/common/base/Predicate
      14: dup
      15: iconst_0
      16: aload_1
      17: invokestatic  #161                // Method org/reflections/ReflectionUtils.withAnnotation:(Ljava/lang/annotation/Annotation;)Lcom/google/common/base/Predicate;
      20: aastore
      21: invokestatic  #162                // Method org/reflections/ReflectionUtils.filter:(Ljava/lang/Iterable;[Lcom/google/common/base/Predicate;)Ljava/util/Set;
      24: areturn

  public java.util.Set<java.lang.String> getResources(com.google.common.base.Predicate<java.lang.String>);
    Code:
       0: aload_0
       1: getfield      #6                  // Field store:Lorg/reflections/Store;
       4: ldc           #185                // class org/reflections/scanners/ResourcesScanner
       6: invokestatic  #134                // Method index:(Ljava/lang/Class;)Ljava/lang/String;
       9: invokevirtual #63                 // Method org/reflections/Store.get:(Ljava/lang/String;)Lcom/google/common/collect/Multimap;
      12: invokeinterface #64,  1           // InterfaceMethod com/google/common/collect/Multimap.keySet:()Ljava/util/Set;
      17: aload_1
      18: invokestatic  #186                // Method com/google/common/collect/Iterables.filter:(Ljava/lang/Iterable;Lcom/google/common/base/Predicate;)Ljava/lang/Iterable;
      21: astore_2
      22: aload_0
      23: getfield      #6                  // Field store:Lorg/reflections/Store;
      26: ldc           #185                // class org/reflections/scanners/ResourcesScanner
      28: invokestatic  #134                // Method index:(Ljava/lang/Class;)Ljava/lang/String;
      31: aload_2
      32: invokevirtual #168                // Method org/reflections/Store.get:(Ljava/lang/String;Ljava/lang/Iterable;)Ljava/lang/Iterable;
      35: invokestatic  #137                // Method com/google/common/collect/Sets.newHashSet:(Ljava/lang/Iterable;)Ljava/util/HashSet;
      38: areturn

  public java.util.Set<java.lang.String> getResources(java.util.regex.Pattern);
    Code:
       0: aload_0
       1: new           #187                // class org/reflections/Reflections$3
       4: dup
       5: aload_0
       6: aload_1
       7: invokespecial #188                // Method org/reflections/Reflections$3."<init>":(Lorg/reflections/Reflections;Ljava/util/regex/Pattern;)V
      10: invokevirtual #189                // Method getResources:(Lcom/google/common/base/Predicate;)Ljava/util/Set;
      13: areturn

  public java.util.List<java.lang.String> getMethodParamNames(java.lang.reflect.Method);
    Code:
       0: aload_0
       1: getfield      #6                  // Field store:Lorg/reflections/Store;
       4: ldc           #190                // class org/reflections/scanners/MethodParameterNamesScanner
       6: invokestatic  #134                // Method index:(Ljava/lang/Class;)Ljava/lang/String;
       9: iconst_1
      10: anewarray     #62                 // class java/lang/String
      13: dup
      14: iconst_0
      15: aload_1
      16: invokestatic  #191                // Method org/reflections/util/Utils.name:(Ljava/lang/reflect/Method;)Ljava/lang/String;
      19: aastore
      20: invokevirtual #153                // Method org/reflections/Store.get:(Ljava/lang/String;[Ljava/lang/String;)Ljava/lang/Iterable;
      23: astore_2
      24: aload_2
      25: invokestatic  #192                // Method com/google/common/collect/Iterables.isEmpty:(Ljava/lang/Iterable;)Z
      28: ifne          49
      31: aload_2
      32: invokestatic  #193                // Method com/google/common/collect/Iterables.getOnlyElement:(Ljava/lang/Iterable;)Ljava/lang/Object;
      35: checkcast     #62                 // class java/lang/String
      38: ldc           #120                // String ,
      40: invokevirtual #194                // Method java/lang/String.split:(Ljava/lang/String;)[Ljava/lang/String;
      43: invokestatic  #148                // Method java/util/Arrays.asList:([Ljava/lang/Object;)Ljava/util/List;
      46: goto          56
      49: iconst_0
      50: anewarray     #62                 // class java/lang/String
      53: invokestatic  #148                // Method java/util/Arrays.asList:([Ljava/lang/Object;)Ljava/util/List;
      56: areturn

  public java.util.List<java.lang.String> getConstructorParamNames(java.lang.reflect.Constructor);
    Code:
       0: aload_0
       1: getfield      #6                  // Field store:Lorg/reflections/Store;
       4: ldc           #190                // class org/reflections/scanners/MethodParameterNamesScanner
       6: invokestatic  #134                // Method index:(Ljava/lang/Class;)Ljava/lang/String;
       9: iconst_1
      10: anewarray     #62                 // class java/lang/String
      13: dup
      14: iconst_0
      15: aload_1
      16: invokestatic  #195                // Method org/reflections/util/Utils.name:(Ljava/lang/reflect/Constructor;)Ljava/lang/String;
      19: aastore
      20: invokevirtual #153                // Method org/reflections/Store.get:(Ljava/lang/String;[Ljava/lang/String;)Ljava/lang/Iterable;
      23: astore_2
      24: aload_2
      25: invokestatic  #192                // Method com/google/common/collect/Iterables.isEmpty:(Ljava/lang/Iterable;)Z
      28: ifne          49
      31: aload_2
      32: invokestatic  #193                // Method com/google/common/collect/Iterables.getOnlyElement:(Ljava/lang/Iterable;)Ljava/lang/Object;
      35: checkcast     #62                 // class java/lang/String
      38: ldc           #120                // String ,
      40: invokevirtual #194                // Method java/lang/String.split:(Ljava/lang/String;)[Ljava/lang/String;
      43: invokestatic  #148                // Method java/util/Arrays.asList:([Ljava/lang/Object;)Ljava/util/List;
      46: goto          56
      49: iconst_0
      50: anewarray     #62                 // class java/lang/String
      53: invokestatic  #148                // Method java/util/Arrays.asList:([Ljava/lang/Object;)Ljava/util/List;
      56: areturn

  public java.util.Set<java.lang.reflect.Member> getFieldUsage(java.lang.reflect.Field);
    Code:
       0: aload_0
       1: getfield      #6                  // Field store:Lorg/reflections/Store;
       4: ldc           #196                // class org/reflections/scanners/MemberUsageScanner
       6: invokestatic  #134                // Method index:(Ljava/lang/Class;)Ljava/lang/String;
       9: iconst_1
      10: anewarray     #62                 // class java/lang/String
      13: dup
      14: iconst_0
      15: aload_1
      16: invokestatic  #197                // Method org/reflections/util/Utils.name:(Ljava/lang/reflect/Field;)Ljava/lang/String;
      19: aastore
      20: invokevirtual #153                // Method org/reflections/Store.get:(Ljava/lang/String;[Ljava/lang/String;)Ljava/lang/Iterable;
      23: iconst_0
      24: anewarray     #102                // class java/lang/ClassLoader
      27: invokestatic  #198                // Method org/reflections/util/Utils.getMembersFromDescriptors:(Ljava/lang/Iterable;[Ljava/lang/ClassLoader;)Ljava/util/Set;
      30: areturn

  public java.util.Set<java.lang.reflect.Member> getMethodUsage(java.lang.reflect.Method);
    Code:
       0: aload_0
       1: getfield      #6                  // Field store:Lorg/reflections/Store;
       4: ldc           #196                // class org/reflections/scanners/MemberUsageScanner
       6: invokestatic  #134                // Method index:(Ljava/lang/Class;)Ljava/lang/String;
       9: iconst_1
      10: anewarray     #62                 // class java/lang/String
      13: dup
      14: iconst_0
      15: aload_1
      16: invokestatic  #191                // Method org/reflections/util/Utils.name:(Ljava/lang/reflect/Method;)Ljava/lang/String;
      19: aastore
      20: invokevirtual #153                // Method org/reflections/Store.get:(Ljava/lang/String;[Ljava/lang/String;)Ljava/lang/Iterable;
      23: iconst_0
      24: anewarray     #102                // class java/lang/ClassLoader
      27: invokestatic  #198                // Method org/reflections/util/Utils.getMembersFromDescriptors:(Ljava/lang/Iterable;[Ljava/lang/ClassLoader;)Ljava/util/Set;
      30: areturn

  public java.util.Set<java.lang.reflect.Member> getConstructorUsage(java.lang.reflect.Constructor);
    Code:
       0: aload_0
       1: getfield      #6                  // Field store:Lorg/reflections/Store;
       4: ldc           #196                // class org/reflections/scanners/MemberUsageScanner
       6: invokestatic  #134                // Method index:(Ljava/lang/Class;)Ljava/lang/String;
       9: iconst_1
      10: anewarray     #62                 // class java/lang/String
      13: dup
      14: iconst_0
      15: aload_1
      16: invokestatic  #195                // Method org/reflections/util/Utils.name:(Ljava/lang/reflect/Constructor;)Ljava/lang/String;
      19: aastore
      20: invokevirtual #153                // Method org/reflections/Store.get:(Ljava/lang/String;[Ljava/lang/String;)Ljava/lang/Iterable;
      23: iconst_0
      24: anewarray     #102                // class java/lang/ClassLoader
      27: invokestatic  #198                // Method org/reflections/util/Utils.getMembersFromDescriptors:(Ljava/lang/Iterable;[Ljava/lang/ClassLoader;)Ljava/util/Set;
      30: areturn

  public java.util.Set<java.lang.String> getAllTypes();
    Code:
       0: aload_0
       1: getfield      #6                  // Field store:Lorg/reflections/Store;
       4: ldc           #133                // class org/reflections/scanners/SubTypesScanner
       6: invokestatic  #134                // Method index:(Ljava/lang/Class;)Ljava/lang/String;
       9: ldc           #21                 // class java/lang/Object
      11: invokevirtual #123                // Method java/lang/Class.getName:()Ljava/lang/String;
      14: invokevirtual #199                // Method org/reflections/Store.getAll:(Ljava/lang/String;Ljava/lang/String;)Ljava/lang/Iterable;
      17: invokestatic  #137                // Method com/google/common/collect/Sets.newHashSet:(Ljava/lang/Iterable;)Ljava/util/HashSet;
      20: astore_1
      21: aload_1
      22: invokeinterface #8,  1            // InterfaceMethod java/util/Set.isEmpty:()Z
      27: ifeq          40
      30: new           #50                 // class org/reflections/ReflectionsException
      33: dup
      34: ldc           #200                // String Couldn\'t find subtypes of Object. Make sure SubTypesScanner initialized to include Object class - new SubTypesScanner(false)
      36: invokespecial #201                // Method org/reflections/ReflectionsException."<init>":(Ljava/lang/String;)V
      39: athrow
      40: aload_1
      41: areturn

  public org.reflections.Store getStore();
    Code:
       0: aload_0
       1: getfield      #6                  // Field store:Lorg/reflections/Store;
       4: areturn

  public org.reflections.Configuration getConfiguration();
    Code:
       0: aload_0
       1: getfield      #3                  // Field configuration:Lorg/reflections/Configuration;
       4: areturn

  public java.io.File save(java.lang.String);
    Code:
       0: aload_0
       1: aload_1
       2: aload_0
       3: getfield      #3                  // Field configuration:Lorg/reflections/Configuration;
       6: invokeinterface #121,  1          // InterfaceMethod org/reflections/Configuration.getSerializer:()Lorg/reflections/serializers/Serializer;
      11: invokevirtual #202                // Method save:(Ljava/lang/String;Lorg/reflections/serializers/Serializer;)Ljava/io/File;
      14: areturn

  public java.io.File save(java.lang.String, org.reflections.serializers.Serializer);
    Code:
       0: aload_2
       1: aload_0
       2: aload_1
       3: invokeinterface #203,  3          // InterfaceMethod org/reflections/serializers/Serializer.save:(Lorg/reflections/Reflections;Ljava/lang/String;)Ljava/io/File;
       8: astore_3
       9: getstatic     #28                 // Field log:Lorg/slf4j/Logger;
      12: ifnull        60
      15: getstatic     #28                 // Field log:Lorg/slf4j/Logger;
      18: new           #32                 // class java/lang/StringBuilder
      21: dup
      22: invokespecial #33                 // Method java/lang/StringBuilder."<init>":()V
      25: ldc           #204                // String Reflections successfully saved in
      27: invokevirtual #35                 // Method java/lang/StringBuilder.append:(Ljava/lang/String;)Ljava/lang/StringBuilder;
      30: aload_3
      31: invokevirtual #205                // Method java/io/File.getAbsolutePath:()Ljava/lang/String;
      34: invokevirtual #35                 // Method java/lang/StringBuilder.append:(Ljava/lang/String;)Ljava/lang/StringBuilder;
      37: ldc           #206                // String  using
      39: invokevirtual #35                 // Method java/lang/StringBuilder.append:(Ljava/lang/String;)Ljava/lang/StringBuilder;
      42: aload_2
      43: invokevirtual #14                 // Method java/lang/Object.getClass:()Ljava/lang/Class;
      46: invokevirtual #15                 // Method java/lang/Class.getSimpleName:()Ljava/lang/String;
      49: invokevirtual #35                 // Method java/lang/StringBuilder.append:(Ljava/lang/String;)Ljava/lang/StringBuilder;
      52: invokevirtual #39                 // Method java/lang/StringBuilder.toString:()Ljava/lang/String;
      55: invokeinterface #75,  2           // InterfaceMethod org/slf4j/Logger.info:(Ljava/lang/String;)V
      60: aload_3
      61: areturn

  private static java.lang.String index(java.lang.Class<? extends org.reflections.scanners.Scanner>);
    Code:
       0: aload_0
       1: invokevirtual #15                 // Method java/lang/Class.getSimpleName:()Ljava/lang/String;
       4: areturn

  private java.lang.ClassLoader[] loaders();
    Code:
       0: aload_0
       1: getfield      #3                  // Field configuration:Lorg/reflections/Configuration;
       4: invokeinterface #207,  1          // InterfaceMethod org/reflections/Configuration.getClassLoaders:()[Ljava/lang/ClassLoader;
       9: areturn

  static java.lang.ClassLoader[] access$000(org.reflections.Reflections);
    Code:
       0: aload_0
       1: invokespecial #1                  // Method loaders:()[Ljava/lang/ClassLoader;
       4: areturn

  static {};
    Code:
       0: ldc           #105                // class org/reflections/Reflections
       2: invokestatic  #208                // Method org/reflections/util/Utils.findLogger:(Ljava/lang/Class;)Lorg/slf4j/Logger;
       5: putstatic     #28                 // Field log:Lorg/slf4j/Logger;
       8: return
}
