Compiled from "points.kt"
public final class org.jetbrains.kotlinx.ggdsl.letsplot.layers.PointsContext extends org.jetbrains.kotlinx.ggdsl.dsl.LayerContext {
  private java.util.Map<java.lang.String, java.util.List<java.lang.Object>> data;

  private final org.jetbrains.kotlinx.ggdsl.letsplot.XAes x;

  private final org.jetbrains.kotlinx.ggdsl.letsplot.YAes y;

  private final org.jetbrains.kotlinx.ggdsl.letsplot.ShapeAes symbol;

  private final org.jetbrains.kotlinx.ggdsl.letsplot.SizeAes size;

  private final org.jetbrains.kotlinx.ggdsl.letsplot.ColorAes color;

  private final org.jetbrains.kotlinx.ggdsl.letsplot.AlphaAes alpha;

  private final org.jetbrains.kotlinx.ggdsl.letsplot.StrokeAes borderWidth;

  private final org.jetbrains.kotlinx.ggdsl.letsplot.FillAes fillColor;

  public org.jetbrains.kotlinx.ggdsl.letsplot.layers.PointsContext(java.util.Map<java.lang.String, java.util.List<java.lang.Object>>);
    Code:
       0: aload_1
       1: ldc           #10                 // String data
       3: invokestatic  #16                 // Method kotlin/jvm/internal/Intrinsics.checkNotNullParameter:(Ljava/lang/Object;Ljava/lang/String;)V
       6: aload_0
       7: invokespecial #19                 // Method org/jetbrains/kotlinx/ggdsl/dsl/LayerContext."<init>":()V
      10: aload_0
      11: aload_1
      12: putfield      #22                 // Field data:Ljava/util/Map;
      15: aload_0
      16: new           #24                 // class org/jetbrains/kotlinx/ggdsl/letsplot/XAes
      19: dup
      20: aload_0
      21: checkcast     #26                 // class org/jetbrains/kotlinx/ggdsl/dsl/BindingContext
      24: invokespecial #29                 // Method org/jetbrains/kotlinx/ggdsl/letsplot/XAes."<init>":(Lorg/jetbrains/kotlinx/ggdsl/dsl/BindingContext;)V
      27: putfield      #33                 // Field x:Lorg/jetbrains/kotlinx/ggdsl/letsplot/XAes;
      30: aload_0
      31: new           #35                 // class org/jetbrains/kotlinx/ggdsl/letsplot/YAes
      34: dup
      35: aload_0
      36: checkcast     #26                 // class org/jetbrains/kotlinx/ggdsl/dsl/BindingContext
      39: invokespecial #36                 // Method org/jetbrains/kotlinx/ggdsl/letsplot/YAes."<init>":(Lorg/jetbrains/kotlinx/ggdsl/dsl/BindingContext;)V
      42: putfield      #40                 // Field y:Lorg/jetbrains/kotlinx/ggdsl/letsplot/YAes;
      45: aload_0
      46: new           #42                 // class org/jetbrains/kotlinx/ggdsl/letsplot/ShapeAes
      49: dup
      50: aload_0
      51: checkcast     #26                 // class org/jetbrains/kotlinx/ggdsl/dsl/BindingContext
      54: invokespecial #43                 // Method org/jetbrains/kotlinx/ggdsl/letsplot/ShapeAes."<init>":(Lorg/jetbrains/kotlinx/ggdsl/dsl/BindingContext;)V
      57: putfield      #47                 // Field symbol:Lorg/jetbrains/kotlinx/ggdsl/letsplot/ShapeAes;
      60: aload_0
      61: new           #49                 // class org/jetbrains/kotlinx/ggdsl/letsplot/SizeAes
      64: dup
      65: aload_0
      66: checkcast     #26                 // class org/jetbrains/kotlinx/ggdsl/dsl/BindingContext
      69: invokespecial #50                 // Method org/jetbrains/kotlinx/ggdsl/letsplot/SizeAes."<init>":(Lorg/jetbrains/kotlinx/ggdsl/dsl/BindingContext;)V
      72: putfield      #54                 // Field size:Lorg/jetbrains/kotlinx/ggdsl/letsplot/SizeAes;
      75: aload_0
      76: new           #56                 // class org/jetbrains/kotlinx/ggdsl/letsplot/ColorAes
      79: dup
      80: aload_0
      81: checkcast     #26                 // class org/jetbrains/kotlinx/ggdsl/dsl/BindingContext
      84: invokespecial #57                 // Method org/jetbrains/kotlinx/ggdsl/letsplot/ColorAes."<init>":(Lorg/jetbrains/kotlinx/ggdsl/dsl/BindingContext;)V
      87: putfield      #61                 // Field color:Lorg/jetbrains/kotlinx/ggdsl/letsplot/ColorAes;
      90: aload_0
      91: new           #63                 // class org/jetbrains/kotlinx/ggdsl/letsplot/AlphaAes
      94: dup
      95: aload_0
      96: checkcast     #26                 // class org/jetbrains/kotlinx/ggdsl/dsl/BindingContext
      99: invokespecial #64                 // Method org/jetbrains/kotlinx/ggdsl/letsplot/AlphaAes."<init>":(Lorg/jetbrains/kotlinx/ggdsl/dsl/BindingContext;)V
     102: putfield      #68                 // Field alpha:Lorg/jetbrains/kotlinx/ggdsl/letsplot/AlphaAes;
     105: aload_0
     106: new           #70                 // class org/jetbrains/kotlinx/ggdsl/letsplot/StrokeAes
     109: dup
     110: aload_0
     111: checkcast     #26                 // class org/jetbrains/kotlinx/ggdsl/dsl/BindingContext
     114: invokespecial #71                 // Method org/jetbrains/kotlinx/ggdsl/letsplot/StrokeAes."<init>":(Lorg/jetbrains/kotlinx/ggdsl/dsl/BindingContext;)V
     117: putfield      #75                 // Field borderWidth:Lorg/jetbrains/kotlinx/ggdsl/letsplot/StrokeAes;
     120: aload_0
     121: new           #77                 // class org/jetbrains/kotlinx/ggdsl/letsplot/FillAes
     124: dup
     125: aload_0
     126: checkcast     #26                 // class org/jetbrains/kotlinx/ggdsl/dsl/BindingContext
     129: invokespecial #78                 // Method org/jetbrains/kotlinx/ggdsl/letsplot/FillAes."<init>":(Lorg/jetbrains/kotlinx/ggdsl/dsl/BindingContext;)V
     132: putfield      #82                 // Field fillColor:Lorg/jetbrains/kotlinx/ggdsl/letsplot/FillAes;
     135: return

  public java.util.Map<java.lang.String, java.util.List<java.lang.Object>> getData();
    Code:
       0: aload_0
       1: getfield      #22                 // Field data:Ljava/util/Map;
       4: areturn

  public void setData(java.util.Map<java.lang.String, java.util.List<java.lang.Object>>);
    Code:
       0: aload_1
       1: ldc           #90                 // String <set-?>
       3: invokestatic  #16                 // Method kotlin/jvm/internal/Intrinsics.checkNotNullParameter:(Ljava/lang/Object;Ljava/lang/String;)V
       6: aload_0
       7: aload_1
       8: putfield      #22                 // Field data:Ljava/util/Map;
      11: return

  public final org.jetbrains.kotlinx.ggdsl.letsplot.XAes getX();
    Code:
       0: aload_0
       1: getfield      #33                 // Field x:Lorg/jetbrains/kotlinx/ggdsl/letsplot/XAes;
       4: areturn

  public final org.jetbrains.kotlinx.ggdsl.letsplot.YAes getY();
    Code:
       0: aload_0
       1: getfield      #40                 // Field y:Lorg/jetbrains/kotlinx/ggdsl/letsplot/YAes;
       4: areturn

  public final org.jetbrains.kotlinx.ggdsl.letsplot.ShapeAes getSymbol();
    Code:
       0: aload_0
       1: getfield      #47                 // Field symbol:Lorg/jetbrains/kotlinx/ggdsl/letsplot/ShapeAes;
       4: areturn

  public final org.jetbrains.kotlinx.ggdsl.letsplot.SizeAes getSize();
    Code:
       0: aload_0
       1: getfield      #54                 // Field size:Lorg/jetbrains/kotlinx/ggdsl/letsplot/SizeAes;
       4: areturn

  public final org.jetbrains.kotlinx.ggdsl.letsplot.ColorAes getColor();
    Code:
       0: aload_0
       1: getfield      #61                 // Field color:Lorg/jetbrains/kotlinx/ggdsl/letsplot/ColorAes;
       4: areturn

  public final org.jetbrains.kotlinx.ggdsl.letsplot.AlphaAes getAlpha();
    Code:
       0: aload_0
       1: getfield      #68                 // Field alpha:Lorg/jetbrains/kotlinx/ggdsl/letsplot/AlphaAes;
       4: areturn

  public final org.jetbrains.kotlinx.ggdsl.letsplot.StrokeAes getBorderWidth();
    Code:
       0: aload_0
       1: getfield      #75                 // Field borderWidth:Lorg/jetbrains/kotlinx/ggdsl/letsplot/StrokeAes;
       4: areturn

  public final org.jetbrains.kotlinx.ggdsl.letsplot.FillAes getFillColor();
    Code:
       0: aload_0
       1: getfield      #82                 // Field fillColor:Lorg/jetbrains/kotlinx/ggdsl/letsplot/FillAes;
       4: areturn
}
