Compiled from "IdManager.java"
public class edu.indiana.lib.osid.component.id.IdManager implements org.osid.id.IdManager {
  private static final org.slf4j.Logger log;

  org.osid.OsidContext context;

  java.util.Properties configuration;

  public edu.indiana.lib.osid.component.id.IdManager();
    Code:
       0: aload_0
       1: invokespecial #1                  // Method java/lang/Object."<init>":()V
       4: aload_0
       5: aconst_null
       6: putfield      #2                  // Field context:Lorg/osid/OsidContext;
       9: aload_0
      10: aconst_null
      11: putfield      #3                  // Field configuration:Ljava/util/Properties;
      14: return

  public org.osid.OsidContext getOsidContext() throws org.osid.id.IdException;
    Code:
       0: aconst_null
       1: areturn

  public void assignOsidContext(org.osid.OsidContext) throws org.osid.id.IdException;
    Code:
       0: return

  public void assignConfiguration(java.util.Properties) throws org.osid.id.IdException;
    Code:
       0: return

  public org.osid.shared.Id createId() throws org.osid.id.IdException;
    Code:
       0: new           #4                  // class edu/indiana/lib/osid/component/id/Id
       3: dup
       4: invokespecial #5                  // Method edu/indiana/lib/osid/component/id/Id."<init>":()V
       7: areturn
       8: astore_1
       9: new           #7                  // class org/osid/id/IdException
      12: dup
      13: aload_1
      14: invokevirtual #8                  // Method org/osid/shared/SharedException.getMessage:()Ljava/lang/String;
      17: invokespecial #9                  // Method org/osid/id/IdException."<init>":(Ljava/lang/String;)V
      20: athrow
    Exception table:
       from    to  target type
           0     7     8   Class org/osid/shared/SharedException

  public org.osid.shared.Id getId(java.lang.String) throws org.osid.id.IdException;
    Code:
       0: aload_1
       1: ifnonnull     14
       4: new           #7                  // class org/osid/id/IdException
       7: dup
       8: ldc           #10                 // String Null argument
      10: invokespecial #9                  // Method org/osid/id/IdException."<init>":(Ljava/lang/String;)V
      13: athrow
      14: new           #4                  // class edu/indiana/lib/osid/component/id/Id
      17: dup
      18: aload_1
      19: invokespecial #11                 // Method edu/indiana/lib/osid/component/id/Id."<init>":(Ljava/lang/String;)V
      22: areturn
      23: astore_2
      24: new           #7                  // class org/osid/id/IdException
      27: dup
      28: aload_2
      29: invokevirtual #8                  // Method org/osid/shared/SharedException.getMessage:()Ljava/lang/String;
      32: invokespecial #9                  // Method org/osid/id/IdException."<init>":(Ljava/lang/String;)V
      35: athrow
    Exception table:
       from    to  target type
          14    22    23   Class org/osid/shared/SharedException

  public void osidVersion_2_0() throws org.osid.id.IdException;
    Code:
       0: return

  static {};
    Code:
       0: ldc           #12                 // class edu/indiana/lib/osid/component/id/IdManager
       2: invokestatic  #13                 // Method org/slf4j/LoggerFactory.getLogger:(Ljava/lang/Class;)Lorg/slf4j/Logger;
       5: putstatic     #14                 // Field log:Lorg/slf4j/Logger;
       8: return
}
