Compiled from "LogLevel.java"
public final class io.mosip.kernel.logger.logback.constant.LogLevel extends java.lang.Enum<io.mosip.kernel.logger.logback.constant.LogLevel> {
  public static final io.mosip.kernel.logger.logback.constant.LogLevel DEBUG;

  public static final io.mosip.kernel.logger.logback.constant.LogLevel TRACE;

  public static final io.mosip.kernel.logger.logback.constant.LogLevel ERROR;

  public static final io.mosip.kernel.logger.logback.constant.LogLevel WARN;

  public static final io.mosip.kernel.logger.logback.constant.LogLevel INFO;

  private final java.lang.String level;

  private static final io.mosip.kernel.logger.logback.constant.LogLevel[] $VALUES;

  public static io.mosip.kernel.logger.logback.constant.LogLevel[] values();
    Code:
       0: getstatic     #1                  // Field $VALUES:[Lio/mosip/kernel/logger/logback/constant/LogLevel;
       3: invokevirtual #2                  // Method "[Lio/mosip/kernel/logger/logback/constant/LogLevel;".clone:()Ljava/lang/Object;
       6: checkcast     #3                  // class "[Lio/mosip/kernel/logger/logback/constant/LogLevel;"
       9: areturn

  public static io.mosip.kernel.logger.logback.constant.LogLevel valueOf(java.lang.String);
    Code:
       0: ldc           #4                  // class io/mosip/kernel/logger/logback/constant/LogLevel
       2: aload_0
       3: invokestatic  #5                  // Method java/lang/Enum.valueOf:(Ljava/lang/Class;Ljava/lang/String;)Ljava/lang/Enum;
       6: checkcast     #4                  // class io/mosip/kernel/logger/logback/constant/LogLevel
       9: areturn

  private io.mosip.kernel.logger.logback.constant.LogLevel(java.lang.String);
    Code:
       0: aload_0
       1: aload_1
       2: iload_2
       3: invokespecial #6                  // Method java/lang/Enum."<init>":(Ljava/lang/String;I)V
       6: aload_0
       7: aload_3
       8: putfield      #7                  // Field level:Ljava/lang/String;
      11: return

  public java.lang.String getLevel();
    Code:
       0: aload_0
       1: getfield      #7                  // Field level:Ljava/lang/String;
       4: areturn

  static {};
    Code:
       0: new           #4                  // class io/mosip/kernel/logger/logback/constant/LogLevel
       3: dup
       4: ldc           #8                  // String DEBUG
       6: iconst_0
       7: ldc           #8                  // String DEBUG
       9: invokespecial #9                  // Method "<init>":(Ljava/lang/String;ILjava/lang/String;)V
      12: putstatic     #10                 // Field DEBUG:Lio/mosip/kernel/logger/logback/constant/LogLevel;
      15: new           #4                  // class io/mosip/kernel/logger/logback/constant/LogLevel
      18: dup
      19: ldc           #11                 // String TRACE
      21: iconst_1
      22: ldc           #11                 // String TRACE
      24: invokespecial #9                  // Method "<init>":(Ljava/lang/String;ILjava/lang/String;)V
      27: putstatic     #12                 // Field TRACE:Lio/mosip/kernel/logger/logback/constant/LogLevel;
      30: new           #4                  // class io/mosip/kernel/logger/logback/constant/LogLevel
      33: dup
      34: ldc           #13                 // String ERROR
      36: iconst_2
      37: ldc           #13                 // String ERROR
      39: invokespecial #9                  // Method "<init>":(Ljava/lang/String;ILjava/lang/String;)V
      42: putstatic     #14                 // Field ERROR:Lio/mosip/kernel/logger/logback/constant/LogLevel;
      45: new           #4                  // class io/mosip/kernel/logger/logback/constant/LogLevel
      48: dup
      49: ldc           #15                 // String WARN
      51: iconst_3
      52: ldc           #15                 // String WARN
      54: invokespecial #9                  // Method "<init>":(Ljava/lang/String;ILjava/lang/String;)V
      57: putstatic     #16                 // Field WARN:Lio/mosip/kernel/logger/logback/constant/LogLevel;
      60: new           #4                  // class io/mosip/kernel/logger/logback/constant/LogLevel
      63: dup
      64: ldc           #17                 // String INFO
      66: iconst_4
      67: ldc           #17                 // String INFO
      69: invokespecial #9                  // Method "<init>":(Ljava/lang/String;ILjava/lang/String;)V
      72: putstatic     #18                 // Field INFO:Lio/mosip/kernel/logger/logback/constant/LogLevel;
      75: iconst_5
      76: anewarray     #4                  // class io/mosip/kernel/logger/logback/constant/LogLevel
      79: dup
      80: iconst_0
      81: getstatic     #10                 // Field DEBUG:Lio/mosip/kernel/logger/logback/constant/LogLevel;
      84: aastore
      85: dup
      86: iconst_1
      87: getstatic     #12                 // Field TRACE:Lio/mosip/kernel/logger/logback/constant/LogLevel;
      90: aastore
      91: dup
      92: iconst_2
      93: getstatic     #14                 // Field ERROR:Lio/mosip/kernel/logger/logback/constant/LogLevel;
      96: aastore
      97: dup
      98: iconst_3
      99: getstatic     #16                 // Field WARN:Lio/mosip/kernel/logger/logback/constant/LogLevel;
     102: aastore
     103: dup
     104: iconst_4
     105: getstatic     #18                 // Field INFO:Lio/mosip/kernel/logger/logback/constant/LogLevel;
     108: aastore
     109: putstatic     #1                  // Field $VALUES:[Lio/mosip/kernel/logger/logback/constant/LogLevel;
     112: return
}
