Compiled from "DistributableCache.java"
public class org.jboss.as.ejb3.cache.distributable.DistributableCache<K, V extends org.jboss.as.ejb3.cache.Identifiable<K> & org.jboss.as.ejb3.cache.Contextual<org.wildfly.clustering.ee.Batch>> implements org.jboss.as.ejb3.cache.Cache<K, V> {
  private final org.wildfly.clustering.ejb.BeanManager<java.util.UUID, K, V, org.wildfly.clustering.ee.Batch> manager;

  private final org.jboss.as.ejb3.cache.StatefulObjectFactory<V> factory;

  private final org.wildfly.clustering.ejb.RemoveListener<V> listener;

  public org.jboss.as.ejb3.cache.distributable.DistributableCache(org.wildfly.clustering.ejb.BeanManager<java.util.UUID, K, V, org.wildfly.clustering.ee.Batch>, org.jboss.as.ejb3.cache.StatefulObjectFactory<V>);
    Code:
       0: aload_0
       1: invokespecial #1                  // Method java/lang/Object."<init>":()V
       4: aload_0
       5: aload_1
       6: putfield      #2                  // Field manager:Lorg/wildfly/clustering/ejb/BeanManager;
       9: aload_0
      10: aload_2
      11: putfield      #3                  // Field factory:Lorg/jboss/as/ejb3/cache/StatefulObjectFactory;
      14: aload_0
      15: new           #4                  // class org/jboss/as/ejb3/cache/distributable/RemoveListenerAdapter
      18: dup
      19: aload_2
      20: invokespecial #5                  // Method org/jboss/as/ejb3/cache/distributable/RemoveListenerAdapter."<init>":(Lorg/jboss/as/ejb3/cache/StatefulObjectFactory;)V
      23: putfield      #6                  // Field listener:Lorg/wildfly/clustering/ejb/RemoveListener;
      26: return

  public org.jboss.ejb.client.Affinity getStrictAffinity();
    Code:
       0: aload_0
       1: getfield      #2                  // Field manager:Lorg/wildfly/clustering/ejb/BeanManager;
       4: invokeinterface #7,  1            // InterfaceMethod org/wildfly/clustering/ejb/BeanManager.getBatcher:()Lorg/wildfly/clustering/ee/Batcher;
       9: invokeinterface #8,  1            // InterfaceMethod org/wildfly/clustering/ee/Batcher.createBatch:()Lorg/wildfly/clustering/ee/Batch;
      14: astore_1
      15: aconst_null
      16: astore_2
      17: aload_0
      18: getfield      #2                  // Field manager:Lorg/wildfly/clustering/ejb/BeanManager;
      21: invokeinterface #9,  1            // InterfaceMethod org/wildfly/clustering/ejb/BeanManager.getStrictAffinity:()Lorg/jboss/ejb/client/Affinity;
      26: astore_3
      27: aload_1
      28: ifnull        61
      31: aload_2
      32: ifnull        55
      35: aload_1
      36: invokeinterface #10,  1           // InterfaceMethod org/wildfly/clustering/ee/Batch.close:()V
      41: goto          61
      44: astore        4
      46: aload_2
      47: aload         4
      49: invokevirtual #12                 // Method java/lang/Throwable.addSuppressed:(Ljava/lang/Throwable;)V
      52: goto          61
      55: aload_1
      56: invokeinterface #10,  1           // InterfaceMethod org/wildfly/clustering/ee/Batch.close:()V
      61: aload_3
      62: areturn
      63: astore_3
      64: aload_3
      65: astore_2
      66: aload_3
      67: athrow
      68: astore        5
      70: aload_1
      71: ifnull        104
      74: aload_2
      75: ifnull        98
      78: aload_1
      79: invokeinterface #10,  1           // InterfaceMethod org/wildfly/clustering/ee/Batch.close:()V
      84: goto          104
      87: astore        6
      89: aload_2
      90: aload         6
      92: invokevirtual #12                 // Method java/lang/Throwable.addSuppressed:(Ljava/lang/Throwable;)V
      95: goto          104
      98: aload_1
      99: invokeinterface #10,  1           // InterfaceMethod org/wildfly/clustering/ee/Batch.close:()V
     104: aload         5
     106: athrow
    Exception table:
       from    to  target type
          35    41    44   Class java/lang/Throwable
          17    27    63   Class java/lang/Throwable
          17    27    68   any
          78    84    87   Class java/lang/Throwable
          63    70    68   any

  public org.jboss.ejb.client.Affinity getWeakAffinity(K);
    Code:
       0: aload_0
       1: getfield      #2                  // Field manager:Lorg/wildfly/clustering/ejb/BeanManager;
       4: invokeinterface #7,  1            // InterfaceMethod org/wildfly/clustering/ejb/BeanManager.getBatcher:()Lorg/wildfly/clustering/ee/Batcher;
       9: invokeinterface #8,  1            // InterfaceMethod org/wildfly/clustering/ee/Batcher.createBatch:()Lorg/wildfly/clustering/ee/Batch;
      14: astore_2
      15: aconst_null
      16: astore_3
      17: aload_0
      18: getfield      #2                  // Field manager:Lorg/wildfly/clustering/ejb/BeanManager;
      21: aload_1
      22: invokeinterface #13,  2           // InterfaceMethod org/wildfly/clustering/ejb/BeanManager.getWeakAffinity:(Ljava/lang/Object;)Lorg/jboss/ejb/client/Affinity;
      27: astore        4
      29: aload_2
      30: ifnull        63
      33: aload_3
      34: ifnull        57
      37: aload_2
      38: invokeinterface #10,  1           // InterfaceMethod org/wildfly/clustering/ee/Batch.close:()V
      43: goto          63
      46: astore        5
      48: aload_3
      49: aload         5
      51: invokevirtual #12                 // Method java/lang/Throwable.addSuppressed:(Ljava/lang/Throwable;)V
      54: goto          63
      57: aload_2
      58: invokeinterface #10,  1           // InterfaceMethod org/wildfly/clustering/ee/Batch.close:()V
      63: aload         4
      65: areturn
      66: astore        4
      68: aload         4
      70: astore_3
      71: aload         4
      73: athrow
      74: astore        6
      76: aload_2
      77: ifnull        110
      80: aload_3
      81: ifnull        104
      84: aload_2
      85: invokeinterface #10,  1           // InterfaceMethod org/wildfly/clustering/ee/Batch.close:()V
      90: goto          110
      93: astore        7
      95: aload_3
      96: aload         7
      98: invokevirtual #12                 // Method java/lang/Throwable.addSuppressed:(Ljava/lang/Throwable;)V
     101: goto          110
     104: aload_2
     105: invokeinterface #10,  1           // InterfaceMethod org/wildfly/clustering/ee/Batch.close:()V
     110: aload         6
     112: athrow
    Exception table:
       from    to  target type
          37    43    46   Class java/lang/Throwable
          17    29    66   Class java/lang/Throwable
          17    29    74   any
          84    90    93   Class java/lang/Throwable
          66    76    74   any

  public K createIdentifier();
    Code:
       0: aload_0
       1: getfield      #2                  // Field manager:Lorg/wildfly/clustering/ejb/BeanManager;
       4: invokeinterface #14,  1           // InterfaceMethod org/wildfly/clustering/ejb/BeanManager.getBeanIdentifierFactory:()Lorg/wildfly/clustering/ejb/IdentifierFactory;
       9: invokeinterface #15,  1           // InterfaceMethod org/wildfly/clustering/ejb/IdentifierFactory.createIdentifier:()Ljava/lang/Object;
      14: areturn

  public V create();
    Code:
       0: iconst_0
       1: istore_1
       2: iconst_0
       3: istore_2
       4: getstatic     #16                 // Field CURRENT_GROUP:Ljava/lang/ThreadLocal;
       7: invokevirtual #17                 // Method java/lang/ThreadLocal.get:()Ljava/lang/Object;
      10: checkcast     #18                 // class java/util/UUID
      13: astore_3
      14: aload_0
      15: getfield      #2                  // Field manager:Lorg/wildfly/clustering/ejb/BeanManager;
      18: invokeinterface #7,  1            // InterfaceMethod org/wildfly/clustering/ejb/BeanManager.getBatcher:()Lorg/wildfly/clustering/ee/Batcher;
      23: invokeinterface #8,  1            // InterfaceMethod org/wildfly/clustering/ee/Batcher.createBatch:()Lorg/wildfly/clustering/ee/Batch;
      28: astore        4
      30: aload_3
      31: ifnonnull     61
      34: iconst_1
      35: istore_1
      36: aload_0
      37: getfield      #2                  // Field manager:Lorg/wildfly/clustering/ejb/BeanManager;
      40: invokeinterface #19,  1           // InterfaceMethod org/wildfly/clustering/ejb/BeanManager.getGroupIdentifierFactory:()Lorg/wildfly/clustering/ejb/IdentifierFactory;
      45: invokeinterface #15,  1           // InterfaceMethod org/wildfly/clustering/ejb/IdentifierFactory.createIdentifier:()Ljava/lang/Object;
      50: checkcast     #18                 // class java/util/UUID
      53: astore_3
      54: getstatic     #16                 // Field CURRENT_GROUP:Ljava/lang/ThreadLocal;
      57: aload_3
      58: invokevirtual #20                 // Method java/lang/ThreadLocal.set:(Ljava/lang/Object;)V
      61: aload_0
      62: getfield      #3                  // Field factory:Lorg/jboss/as/ejb3/cache/StatefulObjectFactory;
      65: invokeinterface #21,  1           // InterfaceMethod org/jboss/as/ejb3/cache/StatefulObjectFactory.createInstance:()Ljava/lang/Object;
      70: checkcast     #22                 // class org/jboss/as/ejb3/cache/Identifiable
      73: astore        5
      75: aload         5
      77: invokeinterface #23,  1           // InterfaceMethod org/jboss/as/ejb3/cache/Identifiable.getId:()Ljava/lang/Object;
      82: astore        6
      84: aload_0
      85: getfield      #2                  // Field manager:Lorg/wildfly/clustering/ejb/BeanManager;
      88: aload         6
      90: aload_3
      91: aload         5
      93: invokeinterface #24,  4           // InterfaceMethod org/wildfly/clustering/ejb/BeanManager.createBean:(Ljava/lang/Object;Ljava/lang/Object;Ljava/lang/Object;)Lorg/wildfly/clustering/ejb/Bean;
      98: invokeinterface #25,  1           // InterfaceMethod org/wildfly/clustering/ejb/Bean.close:()V
     103: iconst_1
     104: istore_2
     105: aload         5
     107: astore        7
     109: iload_1
     110: ifeq          119
     113: getstatic     #16                 // Field CURRENT_GROUP:Ljava/lang/ThreadLocal;
     116: invokevirtual #26                 // Method java/lang/ThreadLocal.remove:()V
     119: iload_2
     120: ifeq          133
     123: aload         4
     125: invokeinterface #10,  1           // InterfaceMethod org/wildfly/clustering/ee/Batch.close:()V
     130: goto          140
     133: aload         4
     135: invokeinterface #27,  1           // InterfaceMethod org/wildfly/clustering/ee/Batch.discard:()V
     140: aload         7
     142: areturn
     143: astore        8
     145: iload_1
     146: ifeq          155
     149: getstatic     #16                 // Field CURRENT_GROUP:Ljava/lang/ThreadLocal;
     152: invokevirtual #26                 // Method java/lang/ThreadLocal.remove:()V
     155: aload         8
     157: athrow
     158: astore        9
     160: iload_2
     161: ifeq          174
     164: aload         4
     166: invokeinterface #10,  1           // InterfaceMethod org/wildfly/clustering/ee/Batch.close:()V
     171: goto          181
     174: aload         4
     176: invokeinterface #27,  1           // InterfaceMethod org/wildfly/clustering/ee/Batch.discard:()V
     181: aload         9
     183: athrow
    Exception table:
       from    to  target type
          61   109   143   any
         143   145   143   any
          30   119   158   any
         143   160   158   any

  public V get(K);
    Code:
       0: aload_0
       1: getfield      #2                  // Field manager:Lorg/wildfly/clustering/ejb/BeanManager;
       4: invokeinterface #7,  1            // InterfaceMethod org/wildfly/clustering/ejb/BeanManager.getBatcher:()Lorg/wildfly/clustering/ee/Batcher;
       9: invokeinterface #8,  1            // InterfaceMethod org/wildfly/clustering/ee/Batcher.createBatch:()Lorg/wildfly/clustering/ee/Batch;
      14: astore_2
      15: aload_0
      16: getfield      #2                  // Field manager:Lorg/wildfly/clustering/ejb/BeanManager;
      19: aload_1
      20: invokeinterface #28,  2           // InterfaceMethod org/wildfly/clustering/ejb/BeanManager.findBean:(Ljava/lang/Object;)Lorg/wildfly/clustering/ejb/Bean;
      25: astore_3
      26: aload_3
      27: ifnonnull     38
      30: aload_2
      31: invokeinterface #10,  1           // InterfaceMethod org/wildfly/clustering/ee/Batch.close:()V
      36: aconst_null
      37: areturn
      38: aload_3
      39: invokeinterface #29,  1           // InterfaceMethod org/wildfly/clustering/ejb/Bean.acquire:()Ljava/lang/Object;
      44: checkcast     #22                 // class org/jboss/as/ejb3/cache/Identifiable
      47: astore        4
      49: aload         4
      51: checkcast     #30                 // class org/jboss/as/ejb3/cache/Contextual
      54: aload_2
      55: invokeinterface #31,  2           // InterfaceMethod org/jboss/as/ejb3/cache/Contextual.setCacheContext:(Ljava/lang/Object;)V
      60: aload         4
      62: areturn
      63: astore_3
      64: aload_2
      65: invokeinterface #27,  1           // InterfaceMethod org/wildfly/clustering/ee/Batch.discard:()V
      70: aload_3
      71: athrow
    Exception table:
       from    to  target type
          15    37    63   Class java/lang/RuntimeException
          15    37    63   Class java/lang/Error
          38    62    63   Class java/lang/RuntimeException
          38    62    63   Class java/lang/Error

  public void release(V);
    Code:
       0: aload_0
       1: getfield      #2                  // Field manager:Lorg/wildfly/clustering/ejb/BeanManager;
       4: invokeinterface #7,  1            // InterfaceMethod org/wildfly/clustering/ejb/BeanManager.getBatcher:()Lorg/wildfly/clustering/ee/Batcher;
       9: aload_1
      10: checkcast     #30                 // class org/jboss/as/ejb3/cache/Contextual
      13: invokeinterface #34,  1           // InterfaceMethod org/jboss/as/ejb3/cache/Contextual.getCacheContext:()Ljava/lang/Object;
      18: checkcast     #35                 // class org/wildfly/clustering/ee/Batch
      21: invokeinterface #36,  2           // InterfaceMethod org/wildfly/clustering/ee/Batcher.resumeBatch:(Lorg/wildfly/clustering/ee/Batch;)Lorg/wildfly/clustering/ee/BatchContext;
      26: astore_2
      27: aconst_null
      28: astore_3
      29: aload_1
      30: checkcast     #30                 // class org/jboss/as/ejb3/cache/Contextual
      33: invokeinterface #34,  1           // InterfaceMethod org/jboss/as/ejb3/cache/Contextual.getCacheContext:()Ljava/lang/Object;
      38: checkcast     #35                 // class org/wildfly/clustering/ee/Batch
      41: astore        4
      43: aconst_null
      44: astore        5
      46: aload_0
      47: getfield      #2                  // Field manager:Lorg/wildfly/clustering/ejb/BeanManager;
      50: aload_1
      51: invokeinterface #23,  1           // InterfaceMethod org/jboss/as/ejb3/cache/Identifiable.getId:()Ljava/lang/Object;
      56: invokeinterface #28,  2           // InterfaceMethod org/wildfly/clustering/ejb/BeanManager.findBean:(Ljava/lang/Object;)Lorg/wildfly/clustering/ejb/Bean;
      61: astore        6
      63: aload         6
      65: ifnull        85
      68: aload         6
      70: invokeinterface #37,  1           // InterfaceMethod org/wildfly/clustering/ejb/Bean.release:()Z
      75: ifeq          85
      78: aload         6
      80: invokeinterface #25,  1           // InterfaceMethod org/wildfly/clustering/ejb/Bean.close:()V
      85: aload         4
      87: ifnull        180
      90: aload         5
      92: ifnull        117
      95: aload         4
      97: invokeinterface #10,  1           // InterfaceMethod org/wildfly/clustering/ee/Batch.close:()V
     102: goto          180
     105: astore        6
     107: aload         5
     109: aload         6
     111: invokevirtual #12                 // Method java/lang/Throwable.addSuppressed:(Ljava/lang/Throwable;)V
     114: goto          180
     117: aload         4
     119: invokeinterface #10,  1           // InterfaceMethod org/wildfly/clustering/ee/Batch.close:()V
     124: goto          180
     127: astore        6
     129: aload         6
     131: astore        5
     133: aload         6
     135: athrow
     136: astore        7
     138: aload         4
     140: ifnull        177
     143: aload         5
     145: ifnull        170
     148: aload         4
     150: invokeinterface #10,  1           // InterfaceMethod org/wildfly/clustering/ee/Batch.close:()V
     155: goto          177
     158: astore        8
     160: aload         5
     162: aload         8
     164: invokevirtual #12                 // Method java/lang/Throwable.addSuppressed:(Ljava/lang/Throwable;)V
     167: goto          177
     170: aload         4
     172: invokeinterface #10,  1           // InterfaceMethod org/wildfly/clustering/ee/Batch.close:()V
     177: aload         7
     179: athrow
     180: aload_2
     181: ifnull        264
     184: aload_3
     185: ifnull        208
     188: aload_2
     189: invokeinterface #38,  1           // InterfaceMethod org/wildfly/clustering/ee/BatchContext.close:()V
     194: goto          264
     197: astore        4
     199: aload_3
     200: aload         4
     202: invokevirtual #12                 // Method java/lang/Throwable.addSuppressed:(Ljava/lang/Throwable;)V
     205: goto          264
     208: aload_2
     209: invokeinterface #38,  1           // InterfaceMethod org/wildfly/clustering/ee/BatchContext.close:()V
     214: goto          264
     217: astore        4
     219: aload         4
     221: astore_3
     222: aload         4
     224: athrow
     225: astore        9
     227: aload_2
     228: ifnull        261
     231: aload_3
     232: ifnull        255
     235: aload_2
     236: invokeinterface #38,  1           // InterfaceMethod org/wildfly/clustering/ee/BatchContext.close:()V
     241: goto          261
     244: astore        10
     246: aload_3
     247: aload         10
     249: invokevirtual #12                 // Method java/lang/Throwable.addSuppressed:(Ljava/lang/Throwable;)V
     252: goto          261
     255: aload_2
     256: invokeinterface #38,  1           // InterfaceMethod org/wildfly/clustering/ee/BatchContext.close:()V
     261: aload         9
     263: athrow
     264: return
    Exception table:
       from    to  target type
          95   102   105   Class java/lang/Throwable
          46    85   127   Class java/lang/Throwable
          46    85   136   any
         148   155   158   Class java/lang/Throwable
         127   138   136   any
         188   194   197   Class java/lang/Throwable
          29   180   217   Class java/lang/Throwable
          29   180   225   any
         235   241   244   Class java/lang/Throwable
         217   227   225   any

  public void remove(K);
    Code:
       0: aload_0
       1: getfield      #2                  // Field manager:Lorg/wildfly/clustering/ejb/BeanManager;
       4: invokeinterface #7,  1            // InterfaceMethod org/wildfly/clustering/ejb/BeanManager.getBatcher:()Lorg/wildfly/clustering/ee/Batcher;
       9: invokeinterface #8,  1            // InterfaceMethod org/wildfly/clustering/ee/Batcher.createBatch:()Lorg/wildfly/clustering/ee/Batch;
      14: astore_2
      15: aconst_null
      16: astore_3
      17: aload_0
      18: getfield      #2                  // Field manager:Lorg/wildfly/clustering/ejb/BeanManager;
      21: aload_1
      22: invokeinterface #28,  2           // InterfaceMethod org/wildfly/clustering/ejb/BeanManager.findBean:(Ljava/lang/Object;)Lorg/wildfly/clustering/ejb/Bean;
      27: astore        4
      29: aload         4
      31: ifnull        45
      34: aload         4
      36: aload_0
      37: getfield      #6                  // Field listener:Lorg/wildfly/clustering/ejb/RemoveListener;
      40: invokeinterface #39,  2           // InterfaceMethod org/wildfly/clustering/ejb/Bean.remove:(Lorg/wildfly/clustering/ejb/RemoveListener;)V
      45: aload_2
      46: ifnull        129
      49: aload_3
      50: ifnull        73
      53: aload_2
      54: invokeinterface #10,  1           // InterfaceMethod org/wildfly/clustering/ee/Batch.close:()V
      59: goto          129
      62: astore        4
      64: aload_3
      65: aload         4
      67: invokevirtual #12                 // Method java/lang/Throwable.addSuppressed:(Ljava/lang/Throwable;)V
      70: goto          129
      73: aload_2
      74: invokeinterface #10,  1           // InterfaceMethod org/wildfly/clustering/ee/Batch.close:()V
      79: goto          129
      82: astore        4
      84: aload         4
      86: astore_3
      87: aload         4
      89: athrow
      90: astore        5
      92: aload_2
      93: ifnull        126
      96: aload_3
      97: ifnull        120
     100: aload_2
     101: invokeinterface #10,  1           // InterfaceMethod org/wildfly/clustering/ee/Batch.close:()V
     106: goto          126
     109: astore        6
     111: aload_3
     112: aload         6
     114: invokevirtual #12                 // Method java/lang/Throwable.addSuppressed:(Ljava/lang/Throwable;)V
     117: goto          126
     120: aload_2
     121: invokeinterface #10,  1           // InterfaceMethod org/wildfly/clustering/ee/Batch.close:()V
     126: aload         5
     128: athrow
     129: return
    Exception table:
       from    to  target type
          53    59    62   Class java/lang/Throwable
          17    45    82   Class java/lang/Throwable
          17    45    90   any
         100   106   109   Class java/lang/Throwable
          82    92    90   any

  public void discard(V);
    Code:
       0: aload_0
       1: getfield      #2                  // Field manager:Lorg/wildfly/clustering/ejb/BeanManager;
       4: invokeinterface #7,  1            // InterfaceMethod org/wildfly/clustering/ejb/BeanManager.getBatcher:()Lorg/wildfly/clustering/ee/Batcher;
       9: aload_1
      10: checkcast     #30                 // class org/jboss/as/ejb3/cache/Contextual
      13: invokeinterface #34,  1           // InterfaceMethod org/jboss/as/ejb3/cache/Contextual.getCacheContext:()Ljava/lang/Object;
      18: checkcast     #35                 // class org/wildfly/clustering/ee/Batch
      21: invokeinterface #36,  2           // InterfaceMethod org/wildfly/clustering/ee/Batcher.resumeBatch:(Lorg/wildfly/clustering/ee/Batch;)Lorg/wildfly/clustering/ee/BatchContext;
      26: astore_2
      27: aconst_null
      28: astore_3
      29: aload_1
      30: checkcast     #30                 // class org/jboss/as/ejb3/cache/Contextual
      33: invokeinterface #34,  1           // InterfaceMethod org/jboss/as/ejb3/cache/Contextual.getCacheContext:()Ljava/lang/Object;
      38: checkcast     #35                 // class org/wildfly/clustering/ee/Batch
      41: astore        4
      43: aconst_null
      44: astore        5
      46: aload_0
      47: getfield      #2                  // Field manager:Lorg/wildfly/clustering/ejb/BeanManager;
      50: aload_1
      51: invokeinterface #23,  1           // InterfaceMethod org/jboss/as/ejb3/cache/Identifiable.getId:()Ljava/lang/Object;
      56: invokeinterface #28,  2           // InterfaceMethod org/wildfly/clustering/ejb/BeanManager.findBean:(Ljava/lang/Object;)Lorg/wildfly/clustering/ejb/Bean;
      61: astore        6
      63: aload         6
      65: ifnull        76
      68: aload         6
      70: aconst_null
      71: invokeinterface #39,  2           // InterfaceMethod org/wildfly/clustering/ejb/Bean.remove:(Lorg/wildfly/clustering/ejb/RemoveListener;)V
      76: aload         4
      78: ifnull        171
      81: aload         5
      83: ifnull        108
      86: aload         4
      88: invokeinterface #10,  1           // InterfaceMethod org/wildfly/clustering/ee/Batch.close:()V
      93: goto          171
      96: astore        6
      98: aload         5
     100: aload         6
     102: invokevirtual #12                 // Method java/lang/Throwable.addSuppressed:(Ljava/lang/Throwable;)V
     105: goto          171
     108: aload         4
     110: invokeinterface #10,  1           // InterfaceMethod org/wildfly/clustering/ee/Batch.close:()V
     115: goto          171
     118: astore        6
     120: aload         6
     122: astore        5
     124: aload         6
     126: athrow
     127: astore        7
     129: aload         4
     131: ifnull        168
     134: aload         5
     136: ifnull        161
     139: aload         4
     141: invokeinterface #10,  1           // InterfaceMethod org/wildfly/clustering/ee/Batch.close:()V
     146: goto          168
     149: astore        8
     151: aload         5
     153: aload         8
     155: invokevirtual #12                 // Method java/lang/Throwable.addSuppressed:(Ljava/lang/Throwable;)V
     158: goto          168
     161: aload         4
     163: invokeinterface #10,  1           // InterfaceMethod org/wildfly/clustering/ee/Batch.close:()V
     168: aload         7
     170: athrow
     171: aload_2
     172: ifnull        255
     175: aload_3
     176: ifnull        199
     179: aload_2
     180: invokeinterface #38,  1           // InterfaceMethod org/wildfly/clustering/ee/BatchContext.close:()V
     185: goto          255
     188: astore        4
     190: aload_3
     191: aload         4
     193: invokevirtual #12                 // Method java/lang/Throwable.addSuppressed:(Ljava/lang/Throwable;)V
     196: goto          255
     199: aload_2
     200: invokeinterface #38,  1           // InterfaceMethod org/wildfly/clustering/ee/BatchContext.close:()V
     205: goto          255
     208: astore        4
     210: aload         4
     212: astore_3
     213: aload         4
     215: athrow
     216: astore        9
     218: aload_2
     219: ifnull        252
     222: aload_3
     223: ifnull        246
     226: aload_2
     227: invokeinterface #38,  1           // InterfaceMethod org/wildfly/clustering/ee/BatchContext.close:()V
     232: goto          252
     235: astore        10
     237: aload_3
     238: aload         10
     240: invokevirtual #12                 // Method java/lang/Throwable.addSuppressed:(Ljava/lang/Throwable;)V
     243: goto          252
     246: aload_2
     247: invokeinterface #38,  1           // InterfaceMethod org/wildfly/clustering/ee/BatchContext.close:()V
     252: aload         9
     254: athrow
     255: return
    Exception table:
       from    to  target type
          86    93    96   Class java/lang/Throwable
          46    76   118   Class java/lang/Throwable
          46    76   127   any
         139   146   149   Class java/lang/Throwable
         118   129   127   any
         179   185   188   Class java/lang/Throwable
          29   171   208   Class java/lang/Throwable
          29   171   216   any
         226   232   235   Class java/lang/Throwable
         208   218   216   any

  public boolean contains(K);
    Code:
       0: aload_0
       1: getfield      #2                  // Field manager:Lorg/wildfly/clustering/ejb/BeanManager;
       4: invokeinterface #7,  1            // InterfaceMethod org/wildfly/clustering/ejb/BeanManager.getBatcher:()Lorg/wildfly/clustering/ee/Batcher;
       9: invokeinterface #8,  1            // InterfaceMethod org/wildfly/clustering/ee/Batcher.createBatch:()Lorg/wildfly/clustering/ee/Batch;
      14: astore_2
      15: aconst_null
      16: astore_3
      17: aload_0
      18: getfield      #2                  // Field manager:Lorg/wildfly/clustering/ejb/BeanManager;
      21: aload_1
      22: invokeinterface #40,  2           // InterfaceMethod org/wildfly/clustering/ejb/BeanManager.containsBean:(Ljava/lang/Object;)Z
      27: istore        4
      29: aload_2
      30: ifnull        63
      33: aload_3
      34: ifnull        57
      37: aload_2
      38: invokeinterface #10,  1           // InterfaceMethod org/wildfly/clustering/ee/Batch.close:()V
      43: goto          63
      46: astore        5
      48: aload_3
      49: aload         5
      51: invokevirtual #12                 // Method java/lang/Throwable.addSuppressed:(Ljava/lang/Throwable;)V
      54: goto          63
      57: aload_2
      58: invokeinterface #10,  1           // InterfaceMethod org/wildfly/clustering/ee/Batch.close:()V
      63: iload         4
      65: ireturn
      66: astore        4
      68: aload         4
      70: astore_3
      71: aload         4
      73: athrow
      74: astore        6
      76: aload_2
      77: ifnull        110
      80: aload_3
      81: ifnull        104
      84: aload_2
      85: invokeinterface #10,  1           // InterfaceMethod org/wildfly/clustering/ee/Batch.close:()V
      90: goto          110
      93: astore        7
      95: aload_3
      96: aload         7
      98: invokevirtual #12                 // Method java/lang/Throwable.addSuppressed:(Ljava/lang/Throwable;)V
     101: goto          110
     104: aload_2
     105: invokeinterface #10,  1           // InterfaceMethod org/wildfly/clustering/ee/Batch.close:()V
     110: aload         6
     112: athrow
    Exception table:
       from    to  target type
          37    43    46   Class java/lang/Throwable
          17    29    66   Class java/lang/Throwable
          17    29    74   any
          84    90    93   Class java/lang/Throwable
          66    76    74   any

  public void start();
    Code:
       0: aload_0
       1: getfield      #2                  // Field manager:Lorg/wildfly/clustering/ejb/BeanManager;
       4: invokeinterface #41,  1           // InterfaceMethod org/wildfly/clustering/ejb/BeanManager.start:()V
       9: return

  public void stop();
    Code:
       0: aload_0
       1: getfield      #2                  // Field manager:Lorg/wildfly/clustering/ejb/BeanManager;
       4: invokeinterface #42,  1           // InterfaceMethod org/wildfly/clustering/ejb/BeanManager.stop:()V
       9: return

  public int getCacheSize();
    Code:
       0: aload_0
       1: getfield      #2                  // Field manager:Lorg/wildfly/clustering/ejb/BeanManager;
       4: invokeinterface #43,  1           // InterfaceMethod org/wildfly/clustering/ejb/BeanManager.getActiveCount:()I
       9: ireturn

  public int getPassivatedCount();
    Code:
       0: aload_0
       1: getfield      #2                  // Field manager:Lorg/wildfly/clustering/ejb/BeanManager;
       4: invokeinterface #44,  1           // InterfaceMethod org/wildfly/clustering/ejb/BeanManager.getPassiveCount:()I
       9: ireturn

  public int getTotalSize();
    Code:
       0: aload_0
       1: getfield      #2                  // Field manager:Lorg/wildfly/clustering/ejb/BeanManager;
       4: invokeinterface #43,  1           // InterfaceMethod org/wildfly/clustering/ejb/BeanManager.getActiveCount:()I
       9: aload_0
      10: getfield      #2                  // Field manager:Lorg/wildfly/clustering/ejb/BeanManager;
      13: invokeinterface #44,  1           // InterfaceMethod org/wildfly/clustering/ejb/BeanManager.getPassiveCount:()I
      18: iadd
      19: ireturn
}
