Compiled from "DynamicType.java"
public class org.modelmapper.internal.bytebuddy.dynamic.DynamicType$Builder$AbstractBase$Adapter$MethodMatchAdapter extends org.modelmapper.internal.bytebuddy.dynamic.DynamicType$Builder$MethodDefinition$ImplementationDefinition$AbstractBase<U> {
  private final org.modelmapper.internal.bytebuddy.matcher.LatentMatcher<? super org.modelmapper.internal.bytebuddy.description.method.MethodDescription> matcher;

  final org.modelmapper.internal.bytebuddy.dynamic.DynamicType$Builder$AbstractBase$Adapter this$0;

  protected org.modelmapper.internal.bytebuddy.dynamic.DynamicType$Builder$AbstractBase$Adapter$MethodMatchAdapter(org.modelmapper.internal.bytebuddy.matcher.LatentMatcher<? super org.modelmapper.internal.bytebuddy.description.method.MethodDescription>);
    Code:
       0: aload_0
       1: aload_1
       2: putfield      #61                 // Field this$0:Lorg/modelmapper/internal/bytebuddy/dynamic/DynamicType$Builder$AbstractBase$Adapter;
       5: aload_0
       6: invokespecial #64                 // Method org/modelmapper/internal/bytebuddy/dynamic/DynamicType$Builder$MethodDefinition$ImplementationDefinition$AbstractBase."<init>":()V
       9: aload_0
      10: aload_2
      11: putfield      #66                 // Field matcher:Lorg/modelmapper/internal/bytebuddy/matcher/LatentMatcher;
      14: return

  public org.modelmapper.internal.bytebuddy.dynamic.DynamicType$Builder$MethodDefinition$ReceiverTypeDefinition<U> intercept(org.modelmapper.internal.bytebuddy.implementation.Implementation);
    Code:
       0: aload_0
       1: new           #45                 // class org/modelmapper/internal/bytebuddy/dynamic/scaffold/MethodRegistry$Handler$ForImplementation
       4: dup
       5: aload_1
       6: invokespecial #74                 // Method org/modelmapper/internal/bytebuddy/dynamic/scaffold/MethodRegistry$Handler$ForImplementation."<init>":(Lorg/modelmapper/internal/bytebuddy/implementation/Implementation;)V
       9: invokespecial #78                 // Method materialize:(Lorg/modelmapper/internal/bytebuddy/dynamic/scaffold/MethodRegistry$Handler;)Lorg/modelmapper/internal/bytebuddy/dynamic/DynamicType$Builder$MethodDefinition$ReceiverTypeDefinition;
      12: areturn

  public org.modelmapper.internal.bytebuddy.dynamic.DynamicType$Builder$MethodDefinition$ReceiverTypeDefinition<U> withoutCode();
    Code:
       0: aload_0
       1: getstatic     #86                 // Field org/modelmapper/internal/bytebuddy/dynamic/scaffold/MethodRegistry$Handler$ForAbstractMethod.INSTANCE:Lorg/modelmapper/internal/bytebuddy/dynamic/scaffold/MethodRegistry$Handler$ForAbstractMethod;
       4: invokespecial #78                 // Method materialize:(Lorg/modelmapper/internal/bytebuddy/dynamic/scaffold/MethodRegistry$Handler;)Lorg/modelmapper/internal/bytebuddy/dynamic/DynamicType$Builder$MethodDefinition$ReceiverTypeDefinition;
       7: areturn

  public org.modelmapper.internal.bytebuddy.dynamic.DynamicType$Builder$MethodDefinition$ReceiverTypeDefinition<U> defaultValue(org.modelmapper.internal.bytebuddy.description.annotation.AnnotationValue<?, ?>);
    Code:
       0: aload_0
       1: new           #48                 // class org/modelmapper/internal/bytebuddy/dynamic/scaffold/MethodRegistry$Handler$ForAnnotationValue
       4: dup
       5: aload_1
       6: invokespecial #91                 // Method org/modelmapper/internal/bytebuddy/dynamic/scaffold/MethodRegistry$Handler$ForAnnotationValue."<init>":(Lorg/modelmapper/internal/bytebuddy/description/annotation/AnnotationValue;)V
       9: invokespecial #78                 // Method materialize:(Lorg/modelmapper/internal/bytebuddy/dynamic/scaffold/MethodRegistry$Handler;)Lorg/modelmapper/internal/bytebuddy/dynamic/DynamicType$Builder$MethodDefinition$ReceiverTypeDefinition;
      12: areturn

  private org.modelmapper.internal.bytebuddy.dynamic.DynamicType$Builder$MethodDefinition$ReceiverTypeDefinition<U> materialize(org.modelmapper.internal.bytebuddy.dynamic.scaffold.MethodRegistry$Handler);
    Code:
       0: new           #23                 // class org/modelmapper/internal/bytebuddy/dynamic/DynamicType$Builder$AbstractBase$Adapter$MethodMatchAdapter$AnnotationAdapter
       3: dup
       4: aload_0
       5: aload_1
       6: invokespecial #97                 // Method org/modelmapper/internal/bytebuddy/dynamic/DynamicType$Builder$AbstractBase$Adapter$MethodMatchAdapter$AnnotationAdapter."<init>":(Lorg/modelmapper/internal/bytebuddy/dynamic/DynamicType$Builder$AbstractBase$Adapter$MethodMatchAdapter;Lorg/modelmapper/internal/bytebuddy/dynamic/scaffold/MethodRegistry$Handler;)V
       9: areturn

  static org.modelmapper.internal.bytebuddy.matcher.LatentMatcher access$100(org.modelmapper.internal.bytebuddy.dynamic.DynamicType$Builder$AbstractBase$Adapter$MethodMatchAdapter);
    Code:
       0: aload_0
       1: getfield      #66                 // Field matcher:Lorg/modelmapper/internal/bytebuddy/matcher/LatentMatcher;
       4: areturn

  public boolean equals(java.lang.Object);
    Code:
       0: aload_0
       1: aload_1
       2: if_acmpne     7
       5: iconst_1
       6: ireturn
       7: aload_1
       8: ifnonnull     13
      11: iconst_0
      12: ireturn
      13: aload_0
      14: invokevirtual #110                // Method java/lang/Object.getClass:()Ljava/lang/Class;
      17: aload_1
      18: invokevirtual #110                // Method java/lang/Object.getClass:()Ljava/lang/Class;
      21: if_acmpeq     26
      24: iconst_0
      25: ireturn
      26: aload_0
      27: getfield      #66                 // Field matcher:Lorg/modelmapper/internal/bytebuddy/matcher/LatentMatcher;
      30: aload_1
      31: checkcast     #2                  // class org/modelmapper/internal/bytebuddy/dynamic/DynamicType$Builder$AbstractBase$Adapter$MethodMatchAdapter
      34: getfield      #66                 // Field matcher:Lorg/modelmapper/internal/bytebuddy/matcher/LatentMatcher;
      37: invokeinterface #114,  2          // InterfaceMethod org/modelmapper/internal/bytebuddy/matcher/LatentMatcher.equals:(Ljava/lang/Object;)Z
      42: ifne          47
      45: iconst_0
      46: ireturn
      47: aload_0
      48: getfield      #61                 // Field this$0:Lorg/modelmapper/internal/bytebuddy/dynamic/DynamicType$Builder$AbstractBase$Adapter;
      51: aload_1
      52: checkcast     #2                  // class org/modelmapper/internal/bytebuddy/dynamic/DynamicType$Builder$AbstractBase$Adapter$MethodMatchAdapter
      55: getfield      #61                 // Field this$0:Lorg/modelmapper/internal/bytebuddy/dynamic/DynamicType$Builder$AbstractBase$Adapter;
      58: invokevirtual #115                // Method org/modelmapper/internal/bytebuddy/dynamic/DynamicType$Builder$AbstractBase$Adapter.equals:(Ljava/lang/Object;)Z
      61: ifne          66
      64: iconst_0
      65: ireturn
      66: iconst_1
      67: ireturn

  public int hashCode();
    Code:
       0: bipush        17
       2: bipush        31
       4: imul
       5: aload_0
       6: getfield      #66                 // Field matcher:Lorg/modelmapper/internal/bytebuddy/matcher/LatentMatcher;
       9: invokeinterface #119,  1          // InterfaceMethod org/modelmapper/internal/bytebuddy/matcher/LatentMatcher.hashCode:()I
      14: iadd
      15: bipush        31
      17: imul
      18: aload_0
      19: getfield      #61                 // Field this$0:Lorg/modelmapper/internal/bytebuddy/dynamic/DynamicType$Builder$AbstractBase$Adapter;
      22: invokevirtual #120                // Method org/modelmapper/internal/bytebuddy/dynamic/DynamicType$Builder$AbstractBase$Adapter.hashCode:()I
      25: iadd
      26: ireturn
}
