Compiled from "DynamicType.java"
public abstract class org.modelmapper.internal.bytebuddy.dynamic.DynamicType$Builder$TypeVariableDefinition$AbstractBase<U> extends org.modelmapper.internal.bytebuddy.dynamic.DynamicType$Builder$AbstractBase$Delegator<U> implements org.modelmapper.internal.bytebuddy.dynamic.DynamicType$Builder$TypeVariableDefinition<U> {
  public org.modelmapper.internal.bytebuddy.dynamic.DynamicType$Builder$TypeVariableDefinition$AbstractBase();
    Code:
       0: aload_0
       1: invokespecial #27                 // Method org/modelmapper/internal/bytebuddy/dynamic/DynamicType$Builder$AbstractBase$Delegator."<init>":()V
       4: return

  public org.modelmapper.internal.bytebuddy.dynamic.DynamicType$Builder$TypeVariableDefinition<U> annotateTypeVariable(java.lang.annotation.Annotation...);
    Code:
       0: aload_0
       1: aload_1
       2: invokestatic  #38                 // Method java/util/Arrays.asList:([Ljava/lang/Object;)Ljava/util/List;
       5: invokevirtual #41                 // Method annotateTypeVariable:(Ljava/util/List;)Lorg/modelmapper/internal/bytebuddy/dynamic/DynamicType$Builder$TypeVariableDefinition;
       8: areturn

  public org.modelmapper.internal.bytebuddy.dynamic.DynamicType$Builder$TypeVariableDefinition<U> annotateTypeVariable(java.util.List<? extends java.lang.annotation.Annotation>);
    Code:
       0: aload_0
       1: new           #20                 // class org/modelmapper/internal/bytebuddy/description/annotation/AnnotationList$ForLoadedAnnotations
       4: dup
       5: aload_1
       6: invokespecial #46                 // Method org/modelmapper/internal/bytebuddy/description/annotation/AnnotationList$ForLoadedAnnotations."<init>":(Ljava/util/List;)V
       9: invokevirtual #49                 // Method annotateTypeVariable:(Ljava/util/Collection;)Lorg/modelmapper/internal/bytebuddy/dynamic/DynamicType$Builder$TypeVariableDefinition;
      12: areturn

  public org.modelmapper.internal.bytebuddy.dynamic.DynamicType$Builder$TypeVariableDefinition<U> annotateTypeVariable(org.modelmapper.internal.bytebuddy.description.annotation.AnnotationDescription...);
    Code:
       0: aload_0
       1: aload_1
       2: invokestatic  #38                 // Method java/util/Arrays.asList:([Ljava/lang/Object;)Ljava/util/List;
       5: invokevirtual #49                 // Method annotateTypeVariable:(Ljava/util/Collection;)Lorg/modelmapper/internal/bytebuddy/dynamic/DynamicType$Builder$TypeVariableDefinition;
       8: areturn
}
