Compiled from "MmContentTypeImpl.java"
public class org.mobicents.slee.resource.diameter.rf.events.avp.MmContentTypeImpl extends org.mobicents.slee.resource.diameter.base.events.avp.GroupedAvpImpl implements net.java.slee.resource.diameter.rf.events.avp.MmContentType {
  public org.mobicents.slee.resource.diameter.rf.events.avp.MmContentTypeImpl();
    Code:
       0: aload_0
       1: invokespecial #1                  // Method org/mobicents/slee/resource/diameter/base/events/avp/GroupedAvpImpl."<init>":()V
       4: return

  public org.mobicents.slee.resource.diameter.rf.events.avp.MmContentTypeImpl(int, long, int, int, byte[]);
    Code:
       0: aload_0
       1: iload_1
       2: lload_2
       3: iload         4
       5: iload         5
       7: aload         6
       9: invokespecial #2                  // Method org/mobicents/slee/resource/diameter/base/events/avp/GroupedAvpImpl."<init>":(IJII[B)V
      12: return

  public net.java.slee.resource.diameter.rf.events.avp.AdditionalContentInformation[] getAdditionalContentInformations();
    Code:
       0: aload_0
       1: sipush        1205
       4: ldc2_w        #3                  // long 10415l
       7: ldc_w         #5                  // class net/java/slee/resource/diameter/rf/events/avp/AdditionalContentInformation
      10: invokevirtual #6                  // Method getAvpsAsCustom:(IJLjava/lang/Class;)[Ljava/lang/Object;
      13: checkcast     #7                  // class "[Lnet/java/slee/resource/diameter/rf/events/avp/AdditionalContentInformation;"
      16: checkcast     #7                  // class "[Lnet/java/slee/resource/diameter/rf/events/avp/AdditionalContentInformation;"
      19: areturn

  public java.lang.String getAdditionalTypeInformation();
    Code:
       0: aload_0
       1: sipush        1205
       4: ldc2_w        #3                  // long 10415l
       7: invokevirtual #8                  // Method getAvpAsUTF8String:(IJ)Ljava/lang/String;
      10: areturn

  public long getContentSize();
    Code:
       0: aload_0
       1: sipush        1206
       4: ldc2_w        #3                  // long 10415l
       7: invokevirtual #9                  // Method getAvpAsUnsigned32:(IJ)J
      10: lreturn

  public int getTypeNumber();
    Code:
       0: aload_0
       1: sipush        1204
       4: ldc2_w        #3                  // long 10415l
       7: invokevirtual #10                 // Method getAvpAsInteger32:(IJ)I
      10: ireturn

  public boolean hasAdditionalTypeInformation();
    Code:
       0: aload_0
       1: sipush        1205
       4: ldc2_w        #3                  // long 10415l
       7: invokevirtual #11                 // Method hasAvp:(IJ)Z
      10: ireturn

  public boolean hasContentSize();
    Code:
       0: aload_0
       1: sipush        1206
       4: ldc2_w        #3                  // long 10415l
       7: invokevirtual #11                 // Method hasAvp:(IJ)Z
      10: ireturn

  public boolean hasTypeNumber();
    Code:
       0: aload_0
       1: sipush        1204
       4: ldc2_w        #3                  // long 10415l
       7: invokevirtual #11                 // Method hasAvp:(IJ)Z
      10: ireturn

  public void setAdditionalContentInformation(net.java.slee.resource.diameter.rf.events.avp.AdditionalContentInformation);
    Code:
       0: aload_0
       1: sipush        1207
       4: ldc2_w        #3                  // long 10415l
       7: aload_1
       8: invokeinterface #12,  1           // InterfaceMethod net/java/slee/resource/diameter/rf/events/avp/AdditionalContentInformation.byteArrayValue:()[B
      13: invokevirtual #13                 // Method addAvp:(IJLjava/lang/Object;)V
      16: return

  public void setAdditionalContentInformations(net.java.slee.resource.diameter.rf.events.avp.AdditionalContentInformation[]);
    Code:
       0: aload_1
       1: astore_2
       2: aload_2
       3: arraylength
       4: istore_3
       5: iconst_0
       6: istore        4
       8: iload         4
      10: iload_3
      11: if_icmpge     32
      14: aload_2
      15: iload         4
      17: aaload
      18: astore        5
      20: aload_0
      21: aload         5
      23: invokevirtual #14                 // Method setAdditionalContentInformation:(Lnet/java/slee/resource/diameter/rf/events/avp/AdditionalContentInformation;)V
      26: iinc          4, 1
      29: goto          8
      32: return

  public void setAdditionalTypeInformation(java.lang.String);
    Code:
       0: aload_0
       1: sipush        1205
       4: ldc2_w        #3                  // long 10415l
       7: aload_1
       8: invokevirtual #13                 // Method addAvp:(IJLjava/lang/Object;)V
      11: return

  public void setContentSize(long);
    Code:
       0: aload_0
       1: sipush        1206
       4: ldc2_w        #3                  // long 10415l
       7: lload_1
       8: invokestatic  #15                 // Method java/lang/Long.valueOf:(J)Ljava/lang/Long;
      11: invokevirtual #13                 // Method addAvp:(IJLjava/lang/Object;)V
      14: return

  public void setTypeNumber(int);
    Code:
       0: aload_0
       1: sipush        1204
       4: ldc2_w        #3                  // long 10415l
       7: iload_1
       8: invokestatic  #16                 // Method java/lang/Integer.valueOf:(I)Ljava/lang/Integer;
      11: invokevirtual #13                 // Method addAvp:(IJLjava/lang/Object;)V
      14: return
}
