Compiled from "ReversePathTree.java"
abstract class org.sonarsource.sonarlint.core.util.ReversePathTree$AbstractNode implements org.sonarsource.sonarlint.core.util.ReversePathTree$Node {
  private boolean terminal;

  private org.sonarsource.sonarlint.core.util.ReversePathTree$AbstractNode();
    Code:
       0: aload_0
       1: invokespecial #17                 // Method java/lang/Object."<init>":()V
       4: return

  public final boolean isTerminal();
    Code:
       0: aload_0
       1: getfield      #23                 // Field terminal:Z
       4: ireturn

  public final void setTerminal(boolean);
    Code:
       0: aload_0
       1: iload_1
       2: putfield      #23                 // Field terminal:Z
       5: return
}
