Compiled from "ReplicationGranularity.java"
public final class org.jboss.metadata.web.jboss.ReplicationGranularity extends java.lang.Enum<org.jboss.metadata.web.jboss.ReplicationGranularity> {
  public static final org.jboss.metadata.web.jboss.ReplicationGranularity SESSION;

  public static final org.jboss.metadata.web.jboss.ReplicationGranularity ATTRIBUTE;

  private static final org.jboss.metadata.web.jboss.ReplicationGranularity[] $VALUES;

  public static org.jboss.metadata.web.jboss.ReplicationGranularity[] values();
    Code:
       0: getstatic     #1                  // Field $VALUES:[Lorg/jboss/metadata/web/jboss/ReplicationGranularity;
       3: invokevirtual #2                  // Method "[Lorg/jboss/metadata/web/jboss/ReplicationGranularity;".clone:()Ljava/lang/Object;
       6: checkcast     #3                  // class "[Lorg/jboss/metadata/web/jboss/ReplicationGranularity;"
       9: areturn

  public static org.jboss.metadata.web.jboss.ReplicationGranularity valueOf(java.lang.String);
    Code:
       0: ldc           #4                  // class org/jboss/metadata/web/jboss/ReplicationGranularity
       2: aload_0
       3: invokestatic  #5                  // Method java/lang/Enum.valueOf:(Ljava/lang/Class;Ljava/lang/String;)Ljava/lang/Enum;
       6: checkcast     #4                  // class org/jboss/metadata/web/jboss/ReplicationGranularity
       9: areturn

  private org.jboss.metadata.web.jboss.ReplicationGranularity();
    Code:
       0: aload_0
       1: aload_1
       2: iload_2
       3: invokespecial #6                  // Method java/lang/Enum."<init>":(Ljava/lang/String;I)V
       6: return

  public static org.jboss.metadata.web.jboss.ReplicationGranularity fromString(java.lang.String);
    Code:
       0: aload_0
       1: ifnonnull     10
       4: getstatic     #7                  // Field SESSION:Lorg/jboss/metadata/web/jboss/ReplicationGranularity;
       7: goto          19
      10: ldc           #4                  // class org/jboss/metadata/web/jboss/ReplicationGranularity
      12: aload_0
      13: invokestatic  #5                  // Method java/lang/Enum.valueOf:(Ljava/lang/Class;Ljava/lang/String;)Ljava/lang/Enum;
      16: checkcast     #4                  // class org/jboss/metadata/web/jboss/ReplicationGranularity
      19: areturn

  static {};
    Code:
       0: new           #4                  // class org/jboss/metadata/web/jboss/ReplicationGranularity
       3: dup
       4: ldc           #8                  // String SESSION
       6: iconst_0
       7: invokespecial #9                  // Method "<init>":(Ljava/lang/String;I)V
      10: putstatic     #7                  // Field SESSION:Lorg/jboss/metadata/web/jboss/ReplicationGranularity;
      13: new           #4                  // class org/jboss/metadata/web/jboss/ReplicationGranularity
      16: dup
      17: ldc           #10                 // String ATTRIBUTE
      19: iconst_1
      20: invokespecial #9                  // Method "<init>":(Ljava/lang/String;I)V
      23: putstatic     #11                 // Field ATTRIBUTE:Lorg/jboss/metadata/web/jboss/ReplicationGranularity;
      26: iconst_2
      27: anewarray     #4                  // class org/jboss/metadata/web/jboss/ReplicationGranularity
      30: dup
      31: iconst_0
      32: getstatic     #7                  // Field SESSION:Lorg/jboss/metadata/web/jboss/ReplicationGranularity;
      35: aastore
      36: dup
      37: iconst_1
      38: getstatic     #11                 // Field ATTRIBUTE:Lorg/jboss/metadata/web/jboss/ReplicationGranularity;
      41: aastore
      42: putstatic     #1                  // Field $VALUES:[Lorg/jboss/metadata/web/jboss/ReplicationGranularity;
      45: return
}
