Compiled from "TypeSerializerBase.java"
public abstract class org.codehaus.jackson.map.jsontype.impl.TypeSerializerBase extends org.codehaus.jackson.map.TypeSerializer {
  protected final org.codehaus.jackson.map.jsontype.TypeIdResolver _idResolver;

  protected final org.codehaus.jackson.map.BeanProperty _property;

  protected org.codehaus.jackson.map.jsontype.impl.TypeSerializerBase(org.codehaus.jackson.map.jsontype.TypeIdResolver, org.codehaus.jackson.map.BeanProperty);
    Code:
       0: aload_0
       1: invokespecial #1                  // Method org/codehaus/jackson/map/TypeSerializer."<init>":()V
       4: aload_0
       5: aload_1
       6: putfield      #2                  // Field _idResolver:Lorg/codehaus/jackson/map/jsontype/TypeIdResolver;
       9: aload_0
      10: aload_2
      11: putfield      #3                  // Field _property:Lorg/codehaus/jackson/map/BeanProperty;
      14: return

  public abstract org.codehaus.jackson.annotate.JsonTypeInfo$As getTypeInclusion();

  public java.lang.String getPropertyName();
    Code:
       0: aconst_null
       1: areturn

  public org.codehaus.jackson.map.jsontype.TypeIdResolver getTypeIdResolver();
    Code:
       0: aload_0
       1: getfield      #2                  // Field _idResolver:Lorg/codehaus/jackson/map/jsontype/TypeIdResolver;
       4: areturn
}
