Compiled from "SAMLInit.java"
public class org.webswing.server.services.security.modules.saml2.com.lastpass.saml.SAMLInit {
  protected org.webswing.server.services.security.modules.saml2.com.lastpass.saml.SAMLInit();
    Code:
       0: aload_0
       1: invokespecial #1                  // Method java/lang/Object."<init>":()V
       4: return

  public static void initialize() throws org.webswing.server.services.security.modules.saml2.com.lastpass.saml.SAMLException;
    Code:
       0: invokestatic  #2                  // Method org/opensaml/DefaultBootstrap.bootstrap:()V
       3: goto          16
       6: astore_0
       7: new           #4                  // class org/webswing/server/services/security/modules/saml2/com/lastpass/saml/SAMLException
      10: dup
      11: aload_0
      12: invokespecial #5                  // Method org/webswing/server/services/security/modules/saml2/com/lastpass/saml/SAMLException."<init>":(Ljava/lang/Throwable;)V
      15: athrow
      16: return
    Exception table:
       from    to  target type
           0     3     6   Class org/opensaml/xml/ConfigurationException
}
