Compiled from "DataTransferProtos.java"
public final class org.apache.hadoop.hdfs.protocol.proto.DataTransferProtos$BlockOpResponseProto$Builder extends com.google.protobuf.GeneratedMessage$Builder<org.apache.hadoop.hdfs.protocol.proto.DataTransferProtos$BlockOpResponseProto$Builder> implements org.apache.hadoop.hdfs.protocol.proto.DataTransferProtos$BlockOpResponseProtoOrBuilder {
  private int bitField0_;

  private org.apache.hadoop.hdfs.protocol.proto.DataTransferProtos$Status status_;

  private java.lang.Object firstBadLink_;

  private org.apache.hadoop.hdfs.protocol.proto.DataTransferProtos$OpBlockChecksumResponseProto checksumResponse_;

  private com.google.protobuf.SingleFieldBuilder<org.apache.hadoop.hdfs.protocol.proto.DataTransferProtos$OpBlockChecksumResponseProto, org.apache.hadoop.hdfs.protocol.proto.DataTransferProtos$OpBlockChecksumResponseProto$Builder, org.apache.hadoop.hdfs.protocol.proto.DataTransferProtos$OpBlockChecksumResponseProtoOrBuilder> checksumResponseBuilder_;

  private org.apache.hadoop.hdfs.protocol.proto.DataTransferProtos$ReadOpChecksumInfoProto readOpChecksumInfo_;

  private com.google.protobuf.SingleFieldBuilder<org.apache.hadoop.hdfs.protocol.proto.DataTransferProtos$ReadOpChecksumInfoProto, org.apache.hadoop.hdfs.protocol.proto.DataTransferProtos$ReadOpChecksumInfoProto$Builder, org.apache.hadoop.hdfs.protocol.proto.DataTransferProtos$ReadOpChecksumInfoProtoOrBuilder> readOpChecksumInfoBuilder_;

  private java.lang.Object message_;

  private int shortCircuitAccessVersion_;

  public static final com.google.protobuf.Descriptors$Descriptor getDescriptor();
    Code:
       0: invokestatic  #3                  // Method org/apache/hadoop/hdfs/protocol/proto/DataTransferProtos.access$28300:()Lcom/google/protobuf/Descriptors$Descriptor;
       3: areturn

  protected com.google.protobuf.GeneratedMessage$FieldAccessorTable internalGetFieldAccessorTable();
    Code:
       0: invokestatic  #4                  // Method org/apache/hadoop/hdfs/protocol/proto/DataTransferProtos.access$28400:()Lcom/google/protobuf/GeneratedMessage$FieldAccessorTable;
       3: ldc           #5                  // class org/apache/hadoop/hdfs/protocol/proto/DataTransferProtos$BlockOpResponseProto
       5: ldc           #6                  // class org/apache/hadoop/hdfs/protocol/proto/DataTransferProtos$BlockOpResponseProto$Builder
       7: invokevirtual #7                  // Method com/google/protobuf/GeneratedMessage$FieldAccessorTable.ensureFieldAccessorsInitialized:(Ljava/lang/Class;Ljava/lang/Class;)Lcom/google/protobuf/GeneratedMessage$FieldAccessorTable;
      10: areturn

  private org.apache.hadoop.hdfs.protocol.proto.DataTransferProtos$BlockOpResponseProto$Builder();
    Code:
       0: aload_0
       1: invokespecial #8                  // Method com/google/protobuf/GeneratedMessage$Builder."<init>":()V
       4: aload_0
       5: getstatic     #9                  // Field org/apache/hadoop/hdfs/protocol/proto/DataTransferProtos$Status.SUCCESS:Lorg/apache/hadoop/hdfs/protocol/proto/DataTransferProtos$Status;
       8: putfield      #10                 // Field status_:Lorg/apache/hadoop/hdfs/protocol/proto/DataTransferProtos$Status;
      11: aload_0
      12: ldc           #11                 // String
      14: putfield      #12                 // Field firstBadLink_:Ljava/lang/Object;
      17: aload_0
      18: invokestatic  #13                 // Method org/apache/hadoop/hdfs/protocol/proto/DataTransferProtos$OpBlockChecksumResponseProto.getDefaultInstance:()Lorg/apache/hadoop/hdfs/protocol/proto/DataTransferProtos$OpBlockChecksumResponseProto;
      21: putfield      #14                 // Field checksumResponse_:Lorg/apache/hadoop/hdfs/protocol/proto/DataTransferProtos$OpBlockChecksumResponseProto;
      24: aload_0
      25: invokestatic  #15                 // Method org/apache/hadoop/hdfs/protocol/proto/DataTransferProtos$ReadOpChecksumInfoProto.getDefaultInstance:()Lorg/apache/hadoop/hdfs/protocol/proto/DataTransferProtos$ReadOpChecksumInfoProto;
      28: putfield      #16                 // Field readOpChecksumInfo_:Lorg/apache/hadoop/hdfs/protocol/proto/DataTransferProtos$ReadOpChecksumInfoProto;
      31: aload_0
      32: ldc           #11                 // String
      34: putfield      #17                 // Field message_:Ljava/lang/Object;
      37: aload_0
      38: invokespecial #18                 // Method maybeForceBuilderInitialization:()V
      41: return

  private org.apache.hadoop.hdfs.protocol.proto.DataTransferProtos$BlockOpResponseProto$Builder(com.google.protobuf.GeneratedMessage$BuilderParent);
    Code:
       0: aload_0
       1: aload_1
       2: invokespecial #19                 // Method com/google/protobuf/GeneratedMessage$Builder."<init>":(Lcom/google/protobuf/GeneratedMessage$BuilderParent;)V
       5: aload_0
       6: getstatic     #9                  // Field org/apache/hadoop/hdfs/protocol/proto/DataTransferProtos$Status.SUCCESS:Lorg/apache/hadoop/hdfs/protocol/proto/DataTransferProtos$Status;
       9: putfield      #10                 // Field status_:Lorg/apache/hadoop/hdfs/protocol/proto/DataTransferProtos$Status;
      12: aload_0
      13: ldc           #11                 // String
      15: putfield      #12                 // Field firstBadLink_:Ljava/lang/Object;
      18: aload_0
      19: invokestatic  #13                 // Method org/apache/hadoop/hdfs/protocol/proto/DataTransferProtos$OpBlockChecksumResponseProto.getDefaultInstance:()Lorg/apache/hadoop/hdfs/protocol/proto/DataTransferProtos$OpBlockChecksumResponseProto;
      22: putfield      #14                 // Field checksumResponse_:Lorg/apache/hadoop/hdfs/protocol/proto/DataTransferProtos$OpBlockChecksumResponseProto;
      25: aload_0
      26: invokestatic  #15                 // Method org/apache/hadoop/hdfs/protocol/proto/DataTransferProtos$ReadOpChecksumInfoProto.getDefaultInstance:()Lorg/apache/hadoop/hdfs/protocol/proto/DataTransferProtos$ReadOpChecksumInfoProto;
      29: putfield      #16                 // Field readOpChecksumInfo_:Lorg/apache/hadoop/hdfs/protocol/proto/DataTransferProtos$ReadOpChecksumInfoProto;
      32: aload_0
      33: ldc           #11                 // String
      35: putfield      #17                 // Field message_:Ljava/lang/Object;
      38: aload_0
      39: invokespecial #18                 // Method maybeForceBuilderInitialization:()V
      42: return

  private void maybeForceBuilderInitialization();
    Code:
       0: invokestatic  #20                 // Method org/apache/hadoop/hdfs/protocol/proto/DataTransferProtos$BlockOpResponseProto.access$28800:()Z
       3: ifeq          16
       6: aload_0
       7: invokespecial #21                 // Method getChecksumResponseFieldBuilder:()Lcom/google/protobuf/SingleFieldBuilder;
      10: pop
      11: aload_0
      12: invokespecial #22                 // Method getReadOpChecksumInfoFieldBuilder:()Lcom/google/protobuf/SingleFieldBuilder;
      15: pop
      16: return

  private static org.apache.hadoop.hdfs.protocol.proto.DataTransferProtos$BlockOpResponseProto$Builder create();
    Code:
       0: new           #6                  // class org/apache/hadoop/hdfs/protocol/proto/DataTransferProtos$BlockOpResponseProto$Builder
       3: dup
       4: invokespecial #23                 // Method "<init>":()V
       7: areturn

  public org.apache.hadoop.hdfs.protocol.proto.DataTransferProtos$BlockOpResponseProto$Builder clear();
    Code:
       0: aload_0
       1: invokespecial #24                 // Method com/google/protobuf/GeneratedMessage$Builder.clear:()Lcom/google/protobuf/GeneratedMessage$Builder;
       4: pop
       5: aload_0
       6: getstatic     #9                  // Field org/apache/hadoop/hdfs/protocol/proto/DataTransferProtos$Status.SUCCESS:Lorg/apache/hadoop/hdfs/protocol/proto/DataTransferProtos$Status;
       9: putfield      #10                 // Field status_:Lorg/apache/hadoop/hdfs/protocol/proto/DataTransferProtos$Status;
      12: aload_0
      13: aload_0
      14: getfield      #25                 // Field bitField0_:I
      17: bipush        -2
      19: iand
      20: putfield      #25                 // Field bitField0_:I
      23: aload_0
      24: ldc           #11                 // String
      26: putfield      #12                 // Field firstBadLink_:Ljava/lang/Object;
      29: aload_0
      30: aload_0
      31: getfield      #25                 // Field bitField0_:I
      34: bipush        -3
      36: iand
      37: putfield      #25                 // Field bitField0_:I
      40: aload_0
      41: getfield      #26                 // Field checksumResponseBuilder_:Lcom/google/protobuf/SingleFieldBuilder;
      44: ifnonnull     57
      47: aload_0
      48: invokestatic  #13                 // Method org/apache/hadoop/hdfs/protocol/proto/DataTransferProtos$OpBlockChecksumResponseProto.getDefaultInstance:()Lorg/apache/hadoop/hdfs/protocol/proto/DataTransferProtos$OpBlockChecksumResponseProto;
      51: putfield      #14                 // Field checksumResponse_:Lorg/apache/hadoop/hdfs/protocol/proto/DataTransferProtos$OpBlockChecksumResponseProto;
      54: goto          65
      57: aload_0
      58: getfield      #26                 // Field checksumResponseBuilder_:Lcom/google/protobuf/SingleFieldBuilder;
      61: invokevirtual #27                 // Method com/google/protobuf/SingleFieldBuilder.clear:()Lcom/google/protobuf/SingleFieldBuilder;
      64: pop
      65: aload_0
      66: aload_0
      67: getfield      #25                 // Field bitField0_:I
      70: bipush        -5
      72: iand
      73: putfield      #25                 // Field bitField0_:I
      76: aload_0
      77: getfield      #28                 // Field readOpChecksumInfoBuilder_:Lcom/google/protobuf/SingleFieldBuilder;
      80: ifnonnull     93
      83: aload_0
      84: invokestatic  #15                 // Method org/apache/hadoop/hdfs/protocol/proto/DataTransferProtos$ReadOpChecksumInfoProto.getDefaultInstance:()Lorg/apache/hadoop/hdfs/protocol/proto/DataTransferProtos$ReadOpChecksumInfoProto;
      87: putfield      #16                 // Field readOpChecksumInfo_:Lorg/apache/hadoop/hdfs/protocol/proto/DataTransferProtos$ReadOpChecksumInfoProto;
      90: goto          101
      93: aload_0
      94: getfield      #28                 // Field readOpChecksumInfoBuilder_:Lcom/google/protobuf/SingleFieldBuilder;
      97: invokevirtual #27                 // Method com/google/protobuf/SingleFieldBuilder.clear:()Lcom/google/protobuf/SingleFieldBuilder;
     100: pop
     101: aload_0
     102: aload_0
     103: getfield      #25                 // Field bitField0_:I
     106: bipush        -9
     108: iand
     109: putfield      #25                 // Field bitField0_:I
     112: aload_0
     113: ldc           #11                 // String
     115: putfield      #17                 // Field message_:Ljava/lang/Object;
     118: aload_0
     119: aload_0
     120: getfield      #25                 // Field bitField0_:I
     123: bipush        -17
     125: iand
     126: putfield      #25                 // Field bitField0_:I
     129: aload_0
     130: iconst_0
     131: putfield      #29                 // Field shortCircuitAccessVersion_:I
     134: aload_0
     135: aload_0
     136: getfield      #25                 // Field bitField0_:I
     139: bipush        -33
     141: iand
     142: putfield      #25                 // Field bitField0_:I
     145: aload_0
     146: areturn

  public org.apache.hadoop.hdfs.protocol.proto.DataTransferProtos$BlockOpResponseProto$Builder clone();
    Code:
       0: invokestatic  #2                  // Method create:()Lorg/apache/hadoop/hdfs/protocol/proto/DataTransferProtos$BlockOpResponseProto$Builder;
       3: aload_0
       4: invokevirtual #30                 // Method buildPartial:()Lorg/apache/hadoop/hdfs/protocol/proto/DataTransferProtos$BlockOpResponseProto;
       7: invokevirtual #31                 // Method mergeFrom:(Lorg/apache/hadoop/hdfs/protocol/proto/DataTransferProtos$BlockOpResponseProto;)Lorg/apache/hadoop/hdfs/protocol/proto/DataTransferProtos$BlockOpResponseProto$Builder;
      10: areturn

  public com.google.protobuf.Descriptors$Descriptor getDescriptorForType();
    Code:
       0: invokestatic  #3                  // Method org/apache/hadoop/hdfs/protocol/proto/DataTransferProtos.access$28300:()Lcom/google/protobuf/Descriptors$Descriptor;
       3: areturn

  public org.apache.hadoop.hdfs.protocol.proto.DataTransferProtos$BlockOpResponseProto getDefaultInstanceForType();
    Code:
       0: invokestatic  #32                 // Method org/apache/hadoop/hdfs/protocol/proto/DataTransferProtos$BlockOpResponseProto.getDefaultInstance:()Lorg/apache/hadoop/hdfs/protocol/proto/DataTransferProtos$BlockOpResponseProto;
       3: areturn

  public org.apache.hadoop.hdfs.protocol.proto.DataTransferProtos$BlockOpResponseProto build();
    Code:
       0: aload_0
       1: invokevirtual #30                 // Method buildPartial:()Lorg/apache/hadoop/hdfs/protocol/proto/DataTransferProtos$BlockOpResponseProto;
       4: astore_1
       5: aload_1
       6: invokevirtual #33                 // Method org/apache/hadoop/hdfs/protocol/proto/DataTransferProtos$BlockOpResponseProto.isInitialized:()Z
       9: ifne          17
      12: aload_1
      13: invokestatic  #34                 // Method newUninitializedMessageException:(Lcom/google/protobuf/Message;)Lcom/google/protobuf/UninitializedMessageException;
      16: athrow
      17: aload_1
      18: areturn

  public org.apache.hadoop.hdfs.protocol.proto.DataTransferProtos$BlockOpResponseProto buildPartial();
    Code:
       0: new           #5                  // class org/apache/hadoop/hdfs/protocol/proto/DataTransferProtos$BlockOpResponseProto
       3: dup
       4: aload_0
       5: aconst_null
       6: invokespecial #35                 // Method org/apache/hadoop/hdfs/protocol/proto/DataTransferProtos$BlockOpResponseProto."<init>":(Lcom/google/protobuf/GeneratedMessage$Builder;Lorg/apache/hadoop/hdfs/protocol/proto/DataTransferProtos$1;)V
       9: astore_1
      10: aload_0
      11: getfield      #25                 // Field bitField0_:I
      14: istore_2
      15: iconst_0
      16: istore_3
      17: iload_2
      18: iconst_1
      19: iand
      20: iconst_1
      21: if_icmpne     28
      24: iload_3
      25: iconst_1
      26: ior
      27: istore_3
      28: aload_1
      29: aload_0
      30: getfield      #10                 // Field status_:Lorg/apache/hadoop/hdfs/protocol/proto/DataTransferProtos$Status;
      33: invokestatic  #36                 // Method org/apache/hadoop/hdfs/protocol/proto/DataTransferProtos$BlockOpResponseProto.access$29002:(Lorg/apache/hadoop/hdfs/protocol/proto/DataTransferProtos$BlockOpResponseProto;Lorg/apache/hadoop/hdfs/protocol/proto/DataTransferProtos$Status;)Lorg/apache/hadoop/hdfs/protocol/proto/DataTransferProtos$Status;
      36: pop
      37: iload_2
      38: iconst_2
      39: iand
      40: iconst_2
      41: if_icmpne     48
      44: iload_3
      45: iconst_2
      46: ior
      47: istore_3
      48: aload_1
      49: aload_0
      50: getfield      #12                 // Field firstBadLink_:Ljava/lang/Object;
      53: invokestatic  #37                 // Method org/apache/hadoop/hdfs/protocol/proto/DataTransferProtos$BlockOpResponseProto.access$29102:(Lorg/apache/hadoop/hdfs/protocol/proto/DataTransferProtos$BlockOpResponseProto;Ljava/lang/Object;)Ljava/lang/Object;
      56: pop
      57: iload_2
      58: iconst_4
      59: iand
      60: iconst_4
      61: if_icmpne     68
      64: iload_3
      65: iconst_4
      66: ior
      67: istore_3
      68: aload_0
      69: getfield      #26                 // Field checksumResponseBuilder_:Lcom/google/protobuf/SingleFieldBuilder;
      72: ifnonnull     87
      75: aload_1
      76: aload_0
      77: getfield      #14                 // Field checksumResponse_:Lorg/apache/hadoop/hdfs/protocol/proto/DataTransferProtos$OpBlockChecksumResponseProto;
      80: invokestatic  #38                 // Method org/apache/hadoop/hdfs/protocol/proto/DataTransferProtos$BlockOpResponseProto.access$29202:(Lorg/apache/hadoop/hdfs/protocol/proto/DataTransferProtos$BlockOpResponseProto;Lorg/apache/hadoop/hdfs/protocol/proto/DataTransferProtos$OpBlockChecksumResponseProto;)Lorg/apache/hadoop/hdfs/protocol/proto/DataTransferProtos$OpBlockChecksumResponseProto;
      83: pop
      84: goto          102
      87: aload_1
      88: aload_0
      89: getfield      #26                 // Field checksumResponseBuilder_:Lcom/google/protobuf/SingleFieldBuilder;
      92: invokevirtual #39                 // Method com/google/protobuf/SingleFieldBuilder.build:()Lcom/google/protobuf/GeneratedMessage;
      95: checkcast     #40                 // class org/apache/hadoop/hdfs/protocol/proto/DataTransferProtos$OpBlockChecksumResponseProto
      98: invokestatic  #38                 // Method org/apache/hadoop/hdfs/protocol/proto/DataTransferProtos$BlockOpResponseProto.access$29202:(Lorg/apache/hadoop/hdfs/protocol/proto/DataTransferProtos$BlockOpResponseProto;Lorg/apache/hadoop/hdfs/protocol/proto/DataTransferProtos$OpBlockChecksumResponseProto;)Lorg/apache/hadoop/hdfs/protocol/proto/DataTransferProtos$OpBlockChecksumResponseProto;
     101: pop
     102: iload_2
     103: bipush        8
     105: iand
     106: bipush        8
     108: if_icmpne     116
     111: iload_3
     112: bipush        8
     114: ior
     115: istore_3
     116: aload_0
     117: getfield      #28                 // Field readOpChecksumInfoBuilder_:Lcom/google/protobuf/SingleFieldBuilder;
     120: ifnonnull     135
     123: aload_1
     124: aload_0
     125: getfield      #16                 // Field readOpChecksumInfo_:Lorg/apache/hadoop/hdfs/protocol/proto/DataTransferProtos$ReadOpChecksumInfoProto;
     128: invokestatic  #41                 // Method org/apache/hadoop/hdfs/protocol/proto/DataTransferProtos$BlockOpResponseProto.access$29302:(Lorg/apache/hadoop/hdfs/protocol/proto/DataTransferProtos$BlockOpResponseProto;Lorg/apache/hadoop/hdfs/protocol/proto/DataTransferProtos$ReadOpChecksumInfoProto;)Lorg/apache/hadoop/hdfs/protocol/proto/DataTransferProtos$ReadOpChecksumInfoProto;
     131: pop
     132: goto          150
     135: aload_1
     136: aload_0
     137: getfield      #28                 // Field readOpChecksumInfoBuilder_:Lcom/google/protobuf/SingleFieldBuilder;
     140: invokevirtual #39                 // Method com/google/protobuf/SingleFieldBuilder.build:()Lcom/google/protobuf/GeneratedMessage;
     143: checkcast     #42                 // class org/apache/hadoop/hdfs/protocol/proto/DataTransferProtos$ReadOpChecksumInfoProto
     146: invokestatic  #41                 // Method org/apache/hadoop/hdfs/protocol/proto/DataTransferProtos$BlockOpResponseProto.access$29302:(Lorg/apache/hadoop/hdfs/protocol/proto/DataTransferProtos$BlockOpResponseProto;Lorg/apache/hadoop/hdfs/protocol/proto/DataTransferProtos$ReadOpChecksumInfoProto;)Lorg/apache/hadoop/hdfs/protocol/proto/DataTransferProtos$ReadOpChecksumInfoProto;
     149: pop
     150: iload_2
     151: bipush        16
     153: iand
     154: bipush        16
     156: if_icmpne     164
     159: iload_3
     160: bipush        16
     162: ior
     163: istore_3
     164: aload_1
     165: aload_0
     166: getfield      #17                 // Field message_:Ljava/lang/Object;
     169: invokestatic  #43                 // Method org/apache/hadoop/hdfs/protocol/proto/DataTransferProtos$BlockOpResponseProto.access$29402:(Lorg/apache/hadoop/hdfs/protocol/proto/DataTransferProtos$BlockOpResponseProto;Ljava/lang/Object;)Ljava/lang/Object;
     172: pop
     173: iload_2
     174: bipush        32
     176: iand
     177: bipush        32
     179: if_icmpne     187
     182: iload_3
     183: bipush        32
     185: ior
     186: istore_3
     187: aload_1
     188: aload_0
     189: getfield      #29                 // Field shortCircuitAccessVersion_:I
     192: invokestatic  #44                 // Method org/apache/hadoop/hdfs/protocol/proto/DataTransferProtos$BlockOpResponseProto.access$29502:(Lorg/apache/hadoop/hdfs/protocol/proto/DataTransferProtos$BlockOpResponseProto;I)I
     195: pop
     196: aload_1
     197: iload_3
     198: invokestatic  #45                 // Method org/apache/hadoop/hdfs/protocol/proto/DataTransferProtos$BlockOpResponseProto.access$29602:(Lorg/apache/hadoop/hdfs/protocol/proto/DataTransferProtos$BlockOpResponseProto;I)I
     201: pop
     202: aload_0
     203: invokevirtual #46                 // Method onBuilt:()V
     206: aload_1
     207: areturn

  public org.apache.hadoop.hdfs.protocol.proto.DataTransferProtos$BlockOpResponseProto$Builder mergeFrom(com.google.protobuf.Message);
    Code:
       0: aload_1
       1: instanceof    #5                  // class org/apache/hadoop/hdfs/protocol/proto/DataTransferProtos$BlockOpResponseProto
       4: ifeq          16
       7: aload_0
       8: aload_1
       9: checkcast     #5                  // class org/apache/hadoop/hdfs/protocol/proto/DataTransferProtos$BlockOpResponseProto
      12: invokevirtual #31                 // Method mergeFrom:(Lorg/apache/hadoop/hdfs/protocol/proto/DataTransferProtos$BlockOpResponseProto;)Lorg/apache/hadoop/hdfs/protocol/proto/DataTransferProtos$BlockOpResponseProto$Builder;
      15: areturn
      16: aload_0
      17: aload_1
      18: invokespecial #47                 // Method com/google/protobuf/GeneratedMessage$Builder.mergeFrom:(Lcom/google/protobuf/Message;)Lcom/google/protobuf/AbstractMessage$Builder;
      21: pop
      22: aload_0
      23: areturn

  public org.apache.hadoop.hdfs.protocol.proto.DataTransferProtos$BlockOpResponseProto$Builder mergeFrom(org.apache.hadoop.hdfs.protocol.proto.DataTransferProtos$BlockOpResponseProto);
    Code:
       0: aload_1
       1: invokestatic  #32                 // Method org/apache/hadoop/hdfs/protocol/proto/DataTransferProtos$BlockOpResponseProto.getDefaultInstance:()Lorg/apache/hadoop/hdfs/protocol/proto/DataTransferProtos$BlockOpResponseProto;
       4: if_acmpne     9
       7: aload_0
       8: areturn
       9: aload_1
      10: invokevirtual #48                 // Method org/apache/hadoop/hdfs/protocol/proto/DataTransferProtos$BlockOpResponseProto.hasStatus:()Z
      13: ifeq          25
      16: aload_0
      17: aload_1
      18: invokevirtual #49                 // Method org/apache/hadoop/hdfs/protocol/proto/DataTransferProtos$BlockOpResponseProto.getStatus:()Lorg/apache/hadoop/hdfs/protocol/proto/DataTransferProtos$Status;
      21: invokevirtual #50                 // Method setStatus:(Lorg/apache/hadoop/hdfs/protocol/proto/DataTransferProtos$Status;)Lorg/apache/hadoop/hdfs/protocol/proto/DataTransferProtos$BlockOpResponseProto$Builder;
      24: pop
      25: aload_1
      26: invokevirtual #51                 // Method org/apache/hadoop/hdfs/protocol/proto/DataTransferProtos$BlockOpResponseProto.hasFirstBadLink:()Z
      29: ifeq          54
      32: aload_0
      33: dup
      34: getfield      #25                 // Field bitField0_:I
      37: iconst_2
      38: ior
      39: putfield      #25                 // Field bitField0_:I
      42: aload_0
      43: aload_1
      44: invokestatic  #52                 // Method org/apache/hadoop/hdfs/protocol/proto/DataTransferProtos$BlockOpResponseProto.access$29100:(Lorg/apache/hadoop/hdfs/protocol/proto/DataTransferProtos$BlockOpResponseProto;)Ljava/lang/Object;
      47: putfield      #12                 // Field firstBadLink_:Ljava/lang/Object;
      50: aload_0
      51: invokevirtual #53                 // Method onChanged:()V
      54: aload_1
      55: invokevirtual #54                 // Method org/apache/hadoop/hdfs/protocol/proto/DataTransferProtos$BlockOpResponseProto.hasChecksumResponse:()Z
      58: ifeq          70
      61: aload_0
      62: aload_1
      63: invokevirtual #55                 // Method org/apache/hadoop/hdfs/protocol/proto/DataTransferProtos$BlockOpResponseProto.getChecksumResponse:()Lorg/apache/hadoop/hdfs/protocol/proto/DataTransferProtos$OpBlockChecksumResponseProto;
      66: invokevirtual #56                 // Method mergeChecksumResponse:(Lorg/apache/hadoop/hdfs/protocol/proto/DataTransferProtos$OpBlockChecksumResponseProto;)Lorg/apache/hadoop/hdfs/protocol/proto/DataTransferProtos$BlockOpResponseProto$Builder;
      69: pop
      70: aload_1
      71: invokevirtual #57                 // Method org/apache/hadoop/hdfs/protocol/proto/DataTransferProtos$BlockOpResponseProto.hasReadOpChecksumInfo:()Z
      74: ifeq          86
      77: aload_0
      78: aload_1
      79: invokevirtual #58                 // Method org/apache/hadoop/hdfs/protocol/proto/DataTransferProtos$BlockOpResponseProto.getReadOpChecksumInfo:()Lorg/apache/hadoop/hdfs/protocol/proto/DataTransferProtos$ReadOpChecksumInfoProto;
      82: invokevirtual #59                 // Method mergeReadOpChecksumInfo:(Lorg/apache/hadoop/hdfs/protocol/proto/DataTransferProtos$ReadOpChecksumInfoProto;)Lorg/apache/hadoop/hdfs/protocol/proto/DataTransferProtos$BlockOpResponseProto$Builder;
      85: pop
      86: aload_1
      87: invokevirtual #60                 // Method org/apache/hadoop/hdfs/protocol/proto/DataTransferProtos$BlockOpResponseProto.hasMessage:()Z
      90: ifeq          116
      93: aload_0
      94: dup
      95: getfield      #25                 // Field bitField0_:I
      98: bipush        16
     100: ior
     101: putfield      #25                 // Field bitField0_:I
     104: aload_0
     105: aload_1
     106: invokestatic  #61                 // Method org/apache/hadoop/hdfs/protocol/proto/DataTransferProtos$BlockOpResponseProto.access$29400:(Lorg/apache/hadoop/hdfs/protocol/proto/DataTransferProtos$BlockOpResponseProto;)Ljava/lang/Object;
     109: putfield      #17                 // Field message_:Ljava/lang/Object;
     112: aload_0
     113: invokevirtual #53                 // Method onChanged:()V
     116: aload_1
     117: invokevirtual #62                 // Method org/apache/hadoop/hdfs/protocol/proto/DataTransferProtos$BlockOpResponseProto.hasShortCircuitAccessVersion:()Z
     120: ifeq          132
     123: aload_0
     124: aload_1
     125: invokevirtual #63                 // Method org/apache/hadoop/hdfs/protocol/proto/DataTransferProtos$BlockOpResponseProto.getShortCircuitAccessVersion:()I
     128: invokevirtual #64                 // Method setShortCircuitAccessVersion:(I)Lorg/apache/hadoop/hdfs/protocol/proto/DataTransferProtos$BlockOpResponseProto$Builder;
     131: pop
     132: aload_0
     133: aload_1
     134: invokevirtual #65                 // Method org/apache/hadoop/hdfs/protocol/proto/DataTransferProtos$BlockOpResponseProto.getUnknownFields:()Lcom/google/protobuf/UnknownFieldSet;
     137: invokevirtual #66                 // Method mergeUnknownFields:(Lcom/google/protobuf/UnknownFieldSet;)Lcom/google/protobuf/GeneratedMessage$Builder;
     140: pop
     141: aload_0
     142: areturn

  public final boolean isInitialized();
    Code:
       0: aload_0
       1: invokevirtual #67                 // Method hasStatus:()Z
       4: ifne          9
       7: iconst_0
       8: ireturn
       9: aload_0
      10: invokevirtual #68                 // Method hasChecksumResponse:()Z
      13: ifeq          28
      16: aload_0
      17: invokevirtual #69                 // Method getChecksumResponse:()Lorg/apache/hadoop/hdfs/protocol/proto/DataTransferProtos$OpBlockChecksumResponseProto;
      20: invokevirtual #70                 // Method org/apache/hadoop/hdfs/protocol/proto/DataTransferProtos$OpBlockChecksumResponseProto.isInitialized:()Z
      23: ifne          28
      26: iconst_0
      27: ireturn
      28: aload_0
      29: invokevirtual #71                 // Method hasReadOpChecksumInfo:()Z
      32: ifeq          47
      35: aload_0
      36: invokevirtual #72                 // Method getReadOpChecksumInfo:()Lorg/apache/hadoop/hdfs/protocol/proto/DataTransferProtos$ReadOpChecksumInfoProto;
      39: invokevirtual #73                 // Method org/apache/hadoop/hdfs/protocol/proto/DataTransferProtos$ReadOpChecksumInfoProto.isInitialized:()Z
      42: ifne          47
      45: iconst_0
      46: ireturn
      47: iconst_1
      48: ireturn

  public org.apache.hadoop.hdfs.protocol.proto.DataTransferProtos$BlockOpResponseProto$Builder mergeFrom(com.google.protobuf.CodedInputStream, com.google.protobuf.ExtensionRegistryLite) throws java.io.IOException;
    Code:
       0: aconst_null
       1: astore_3
       2: getstatic     #74                 // Field org/apache/hadoop/hdfs/protocol/proto/DataTransferProtos$BlockOpResponseProto.PARSER:Lcom/google/protobuf/Parser;
       5: aload_1
       6: aload_2
       7: invokeinterface #75,  3           // InterfaceMethod com/google/protobuf/Parser.parsePartialFrom:(Lcom/google/protobuf/CodedInputStream;Lcom/google/protobuf/ExtensionRegistryLite;)Ljava/lang/Object;
      12: checkcast     #5                  // class org/apache/hadoop/hdfs/protocol/proto/DataTransferProtos$BlockOpResponseProto
      15: astore_3
      16: aload_3
      17: ifnull        58
      20: aload_0
      21: aload_3
      22: invokevirtual #31                 // Method mergeFrom:(Lorg/apache/hadoop/hdfs/protocol/proto/DataTransferProtos$BlockOpResponseProto;)Lorg/apache/hadoop/hdfs/protocol/proto/DataTransferProtos$BlockOpResponseProto$Builder;
      25: pop
      26: goto          58
      29: astore        4
      31: aload         4
      33: invokevirtual #77                 // Method com/google/protobuf/InvalidProtocolBufferException.getUnfinishedMessage:()Lcom/google/protobuf/MessageLite;
      36: checkcast     #5                  // class org/apache/hadoop/hdfs/protocol/proto/DataTransferProtos$BlockOpResponseProto
      39: astore_3
      40: aload         4
      42: athrow
      43: astore        5
      45: aload_3
      46: ifnull        55
      49: aload_0
      50: aload_3
      51: invokevirtual #31                 // Method mergeFrom:(Lorg/apache/hadoop/hdfs/protocol/proto/DataTransferProtos$BlockOpResponseProto;)Lorg/apache/hadoop/hdfs/protocol/proto/DataTransferProtos$BlockOpResponseProto$Builder;
      54: pop
      55: aload         5
      57: athrow
      58: aload_0
      59: areturn
    Exception table:
       from    to  target type
           2    16    29   Class com/google/protobuf/InvalidProtocolBufferException
           2    16    43   any
          29    45    43   any

  public boolean hasStatus();
    Code:
       0: aload_0
       1: getfield      #25                 // Field bitField0_:I
       4: iconst_1
       5: iand
       6: iconst_1
       7: if_icmpne     14
      10: iconst_1
      11: goto          15
      14: iconst_0
      15: ireturn

  public org.apache.hadoop.hdfs.protocol.proto.DataTransferProtos$Status getStatus();
    Code:
       0: aload_0
       1: getfield      #10                 // Field status_:Lorg/apache/hadoop/hdfs/protocol/proto/DataTransferProtos$Status;
       4: areturn

  public org.apache.hadoop.hdfs.protocol.proto.DataTransferProtos$BlockOpResponseProto$Builder setStatus(org.apache.hadoop.hdfs.protocol.proto.DataTransferProtos$Status);
    Code:
       0: aload_1
       1: ifnonnull     12
       4: new           #78                 // class java/lang/NullPointerException
       7: dup
       8: invokespecial #79                 // Method java/lang/NullPointerException."<init>":()V
      11: athrow
      12: aload_0
      13: dup
      14: getfield      #25                 // Field bitField0_:I
      17: iconst_1
      18: ior
      19: putfield      #25                 // Field bitField0_:I
      22: aload_0
      23: aload_1
      24: putfield      #10                 // Field status_:Lorg/apache/hadoop/hdfs/protocol/proto/DataTransferProtos$Status;
      27: aload_0
      28: invokevirtual #53                 // Method onChanged:()V
      31: aload_0
      32: areturn

  public org.apache.hadoop.hdfs.protocol.proto.DataTransferProtos$BlockOpResponseProto$Builder clearStatus();
    Code:
       0: aload_0
       1: aload_0
       2: getfield      #25                 // Field bitField0_:I
       5: bipush        -2
       7: iand
       8: putfield      #25                 // Field bitField0_:I
      11: aload_0
      12: getstatic     #9                  // Field org/apache/hadoop/hdfs/protocol/proto/DataTransferProtos$Status.SUCCESS:Lorg/apache/hadoop/hdfs/protocol/proto/DataTransferProtos$Status;
      15: putfield      #10                 // Field status_:Lorg/apache/hadoop/hdfs/protocol/proto/DataTransferProtos$Status;
      18: aload_0
      19: invokevirtual #53                 // Method onChanged:()V
      22: aload_0
      23: areturn

  public boolean hasFirstBadLink();
    Code:
       0: aload_0
       1: getfield      #25                 // Field bitField0_:I
       4: iconst_2
       5: iand
       6: iconst_2
       7: if_icmpne     14
      10: iconst_1
      11: goto          15
      14: iconst_0
      15: ireturn

  public java.lang.String getFirstBadLink();
    Code:
       0: aload_0
       1: getfield      #12                 // Field firstBadLink_:Ljava/lang/Object;
       4: astore_1
       5: aload_1
       6: instanceof    #80                 // class java/lang/String
       9: ifne          27
      12: aload_1
      13: checkcast     #81                 // class com/google/protobuf/ByteString
      16: invokevirtual #82                 // Method com/google/protobuf/ByteString.toStringUtf8:()Ljava/lang/String;
      19: astore_2
      20: aload_0
      21: aload_2
      22: putfield      #12                 // Field firstBadLink_:Ljava/lang/Object;
      25: aload_2
      26: areturn
      27: aload_1
      28: checkcast     #80                 // class java/lang/String
      31: areturn

  public com.google.protobuf.ByteString getFirstBadLinkBytes();
    Code:
       0: aload_0
       1: getfield      #12                 // Field firstBadLink_:Ljava/lang/Object;
       4: astore_1
       5: aload_1
       6: instanceof    #80                 // class java/lang/String
       9: ifeq          27
      12: aload_1
      13: checkcast     #80                 // class java/lang/String
      16: invokestatic  #83                 // Method com/google/protobuf/ByteString.copyFromUtf8:(Ljava/lang/String;)Lcom/google/protobuf/ByteString;
      19: astore_2
      20: aload_0
      21: aload_2
      22: putfield      #12                 // Field firstBadLink_:Ljava/lang/Object;
      25: aload_2
      26: areturn
      27: aload_1
      28: checkcast     #81                 // class com/google/protobuf/ByteString
      31: areturn

  public org.apache.hadoop.hdfs.protocol.proto.DataTransferProtos$BlockOpResponseProto$Builder setFirstBadLink(java.lang.String);
    Code:
       0: aload_1
       1: ifnonnull     12
       4: new           #78                 // class java/lang/NullPointerException
       7: dup
       8: invokespecial #79                 // Method java/lang/NullPointerException."<init>":()V
      11: athrow
      12: aload_0
      13: dup
      14: getfield      #25                 // Field bitField0_:I
      17: iconst_2
      18: ior
      19: putfield      #25                 // Field bitField0_:I
      22: aload_0
      23: aload_1
      24: putfield      #12                 // Field firstBadLink_:Ljava/lang/Object;
      27: aload_0
      28: invokevirtual #53                 // Method onChanged:()V
      31: aload_0
      32: areturn

  public org.apache.hadoop.hdfs.protocol.proto.DataTransferProtos$BlockOpResponseProto$Builder clearFirstBadLink();
    Code:
       0: aload_0
       1: aload_0
       2: getfield      #25                 // Field bitField0_:I
       5: bipush        -3
       7: iand
       8: putfield      #25                 // Field bitField0_:I
      11: aload_0
      12: invokestatic  #32                 // Method org/apache/hadoop/hdfs/protocol/proto/DataTransferProtos$BlockOpResponseProto.getDefaultInstance:()Lorg/apache/hadoop/hdfs/protocol/proto/DataTransferProtos$BlockOpResponseProto;
      15: invokevirtual #84                 // Method org/apache/hadoop/hdfs/protocol/proto/DataTransferProtos$BlockOpResponseProto.getFirstBadLink:()Ljava/lang/String;
      18: putfield      #12                 // Field firstBadLink_:Ljava/lang/Object;
      21: aload_0
      22: invokevirtual #53                 // Method onChanged:()V
      25: aload_0
      26: areturn

  public org.apache.hadoop.hdfs.protocol.proto.DataTransferProtos$BlockOpResponseProto$Builder setFirstBadLinkBytes(com.google.protobuf.ByteString);
    Code:
       0: aload_1
       1: ifnonnull     12
       4: new           #78                 // class java/lang/NullPointerException
       7: dup
       8: invokespecial #79                 // Method java/lang/NullPointerException."<init>":()V
      11: athrow
      12: aload_0
      13: dup
      14: getfield      #25                 // Field bitField0_:I
      17: iconst_2
      18: ior
      19: putfield      #25                 // Field bitField0_:I
      22: aload_0
      23: aload_1
      24: putfield      #12                 // Field firstBadLink_:Ljava/lang/Object;
      27: aload_0
      28: invokevirtual #53                 // Method onChanged:()V
      31: aload_0
      32: areturn

  public boolean hasChecksumResponse();
    Code:
       0: aload_0
       1: getfield      #25                 // Field bitField0_:I
       4: iconst_4
       5: iand
       6: iconst_4
       7: if_icmpne     14
      10: iconst_1
      11: goto          15
      14: iconst_0
      15: ireturn

  public org.apache.hadoop.hdfs.protocol.proto.DataTransferProtos$OpBlockChecksumResponseProto getChecksumResponse();
    Code:
       0: aload_0
       1: getfield      #26                 // Field checksumResponseBuilder_:Lcom/google/protobuf/SingleFieldBuilder;
       4: ifnonnull     12
       7: aload_0
       8: getfield      #14                 // Field checksumResponse_:Lorg/apache/hadoop/hdfs/protocol/proto/DataTransferProtos$OpBlockChecksumResponseProto;
      11: areturn
      12: aload_0
      13: getfield      #26                 // Field checksumResponseBuilder_:Lcom/google/protobuf/SingleFieldBuilder;
      16: invokevirtual #85                 // Method com/google/protobuf/SingleFieldBuilder.getMessage:()Lcom/google/protobuf/GeneratedMessage;
      19: checkcast     #40                 // class org/apache/hadoop/hdfs/protocol/proto/DataTransferProtos$OpBlockChecksumResponseProto
      22: areturn

  public org.apache.hadoop.hdfs.protocol.proto.DataTransferProtos$BlockOpResponseProto$Builder setChecksumResponse(org.apache.hadoop.hdfs.protocol.proto.DataTransferProtos$OpBlockChecksumResponseProto);
    Code:
       0: aload_0
       1: getfield      #26                 // Field checksumResponseBuilder_:Lcom/google/protobuf/SingleFieldBuilder;
       4: ifnonnull     31
       7: aload_1
       8: ifnonnull     19
      11: new           #78                 // class java/lang/NullPointerException
      14: dup
      15: invokespecial #79                 // Method java/lang/NullPointerException."<init>":()V
      18: athrow
      19: aload_0
      20: aload_1
      21: putfield      #14                 // Field checksumResponse_:Lorg/apache/hadoop/hdfs/protocol/proto/DataTransferProtos$OpBlockChecksumResponseProto;
      24: aload_0
      25: invokevirtual #53                 // Method onChanged:()V
      28: goto          40
      31: aload_0
      32: getfield      #26                 // Field checksumResponseBuilder_:Lcom/google/protobuf/SingleFieldBuilder;
      35: aload_1
      36: invokevirtual #86                 // Method com/google/protobuf/SingleFieldBuilder.setMessage:(Lcom/google/protobuf/GeneratedMessage;)Lcom/google/protobuf/SingleFieldBuilder;
      39: pop
      40: aload_0
      41: dup
      42: getfield      #25                 // Field bitField0_:I
      45: iconst_4
      46: ior
      47: putfield      #25                 // Field bitField0_:I
      50: aload_0
      51: areturn

  public org.apache.hadoop.hdfs.protocol.proto.DataTransferProtos$BlockOpResponseProto$Builder setChecksumResponse(org.apache.hadoop.hdfs.protocol.proto.DataTransferProtos$OpBlockChecksumResponseProto$Builder);
    Code:
       0: aload_0
       1: getfield      #26                 // Field checksumResponseBuilder_:Lcom/google/protobuf/SingleFieldBuilder;
       4: ifnonnull     22
       7: aload_0
       8: aload_1
       9: invokevirtual #87                 // Method org/apache/hadoop/hdfs/protocol/proto/DataTransferProtos$OpBlockChecksumResponseProto$Builder.build:()Lorg/apache/hadoop/hdfs/protocol/proto/DataTransferProtos$OpBlockChecksumResponseProto;
      12: putfield      #14                 // Field checksumResponse_:Lorg/apache/hadoop/hdfs/protocol/proto/DataTransferProtos$OpBlockChecksumResponseProto;
      15: aload_0
      16: invokevirtual #53                 // Method onChanged:()V
      19: goto          34
      22: aload_0
      23: getfield      #26                 // Field checksumResponseBuilder_:Lcom/google/protobuf/SingleFieldBuilder;
      26: aload_1
      27: invokevirtual #87                 // Method org/apache/hadoop/hdfs/protocol/proto/DataTransferProtos$OpBlockChecksumResponseProto$Builder.build:()Lorg/apache/hadoop/hdfs/protocol/proto/DataTransferProtos$OpBlockChecksumResponseProto;
      30: invokevirtual #86                 // Method com/google/protobuf/SingleFieldBuilder.setMessage:(Lcom/google/protobuf/GeneratedMessage;)Lcom/google/protobuf/SingleFieldBuilder;
      33: pop
      34: aload_0
      35: dup
      36: getfield      #25                 // Field bitField0_:I
      39: iconst_4
      40: ior
      41: putfield      #25                 // Field bitField0_:I
      44: aload_0
      45: areturn

  public org.apache.hadoop.hdfs.protocol.proto.DataTransferProtos$BlockOpResponseProto$Builder mergeChecksumResponse(org.apache.hadoop.hdfs.protocol.proto.DataTransferProtos$OpBlockChecksumResponseProto);
    Code:
       0: aload_0
       1: getfield      #26                 // Field checksumResponseBuilder_:Lcom/google/protobuf/SingleFieldBuilder;
       4: ifnonnull     60
       7: aload_0
       8: getfield      #25                 // Field bitField0_:I
      11: iconst_4
      12: iand
      13: iconst_4
      14: if_icmpne     48
      17: aload_0
      18: getfield      #14                 // Field checksumResponse_:Lorg/apache/hadoop/hdfs/protocol/proto/DataTransferProtos$OpBlockChecksumResponseProto;
      21: invokestatic  #13                 // Method org/apache/hadoop/hdfs/protocol/proto/DataTransferProtos$OpBlockChecksumResponseProto.getDefaultInstance:()Lorg/apache/hadoop/hdfs/protocol/proto/DataTransferProtos$OpBlockChecksumResponseProto;
      24: if_acmpeq     48
      27: aload_0
      28: aload_0
      29: getfield      #14                 // Field checksumResponse_:Lorg/apache/hadoop/hdfs/protocol/proto/DataTransferProtos$OpBlockChecksumResponseProto;
      32: invokestatic  #88                 // Method org/apache/hadoop/hdfs/protocol/proto/DataTransferProtos$OpBlockChecksumResponseProto.newBuilder:(Lorg/apache/hadoop/hdfs/protocol/proto/DataTransferProtos$OpBlockChecksumResponseProto;)Lorg/apache/hadoop/hdfs/protocol/proto/DataTransferProtos$OpBlockChecksumResponseProto$Builder;
      35: aload_1
      36: invokevirtual #89                 // Method org/apache/hadoop/hdfs/protocol/proto/DataTransferProtos$OpBlockChecksumResponseProto$Builder.mergeFrom:(Lorg/apache/hadoop/hdfs/protocol/proto/DataTransferProtos$OpBlockChecksumResponseProto;)Lorg/apache/hadoop/hdfs/protocol/proto/DataTransferProtos$OpBlockChecksumResponseProto$Builder;
      39: invokevirtual #90                 // Method org/apache/hadoop/hdfs/protocol/proto/DataTransferProtos$OpBlockChecksumResponseProto$Builder.buildPartial:()Lorg/apache/hadoop/hdfs/protocol/proto/DataTransferProtos$OpBlockChecksumResponseProto;
      42: putfield      #14                 // Field checksumResponse_:Lorg/apache/hadoop/hdfs/protocol/proto/DataTransferProtos$OpBlockChecksumResponseProto;
      45: goto          53
      48: aload_0
      49: aload_1
      50: putfield      #14                 // Field checksumResponse_:Lorg/apache/hadoop/hdfs/protocol/proto/DataTransferProtos$OpBlockChecksumResponseProto;
      53: aload_0
      54: invokevirtual #53                 // Method onChanged:()V
      57: goto          69
      60: aload_0
      61: getfield      #26                 // Field checksumResponseBuilder_:Lcom/google/protobuf/SingleFieldBuilder;
      64: aload_1
      65: invokevirtual #91                 // Method com/google/protobuf/SingleFieldBuilder.mergeFrom:(Lcom/google/protobuf/GeneratedMessage;)Lcom/google/protobuf/SingleFieldBuilder;
      68: pop
      69: aload_0
      70: dup
      71: getfield      #25                 // Field bitField0_:I
      74: iconst_4
      75: ior
      76: putfield      #25                 // Field bitField0_:I
      79: aload_0
      80: areturn

  public org.apache.hadoop.hdfs.protocol.proto.DataTransferProtos$BlockOpResponseProto$Builder clearChecksumResponse();
    Code:
       0: aload_0
       1: getfield      #26                 // Field checksumResponseBuilder_:Lcom/google/protobuf/SingleFieldBuilder;
       4: ifnonnull     21
       7: aload_0
       8: invokestatic  #13                 // Method org/apache/hadoop/hdfs/protocol/proto/DataTransferProtos$OpBlockChecksumResponseProto.getDefaultInstance:()Lorg/apache/hadoop/hdfs/protocol/proto/DataTransferProtos$OpBlockChecksumResponseProto;
      11: putfield      #14                 // Field checksumResponse_:Lorg/apache/hadoop/hdfs/protocol/proto/DataTransferProtos$OpBlockChecksumResponseProto;
      14: aload_0
      15: invokevirtual #53                 // Method onChanged:()V
      18: goto          29
      21: aload_0
      22: getfield      #26                 // Field checksumResponseBuilder_:Lcom/google/protobuf/SingleFieldBuilder;
      25: invokevirtual #27                 // Method com/google/protobuf/SingleFieldBuilder.clear:()Lcom/google/protobuf/SingleFieldBuilder;
      28: pop
      29: aload_0
      30: aload_0
      31: getfield      #25                 // Field bitField0_:I
      34: bipush        -5
      36: iand
      37: putfield      #25                 // Field bitField0_:I
      40: aload_0
      41: areturn

  public org.apache.hadoop.hdfs.protocol.proto.DataTransferProtos$OpBlockChecksumResponseProto$Builder getChecksumResponseBuilder();
    Code:
       0: aload_0
       1: dup
       2: getfield      #25                 // Field bitField0_:I
       5: iconst_4
       6: ior
       7: putfield      #25                 // Field bitField0_:I
      10: aload_0
      11: invokevirtual #53                 // Method onChanged:()V
      14: aload_0
      15: invokespecial #21                 // Method getChecksumResponseFieldBuilder:()Lcom/google/protobuf/SingleFieldBuilder;
      18: invokevirtual #92                 // Method com/google/protobuf/SingleFieldBuilder.getBuilder:()Lcom/google/protobuf/GeneratedMessage$Builder;
      21: checkcast     #93                 // class org/apache/hadoop/hdfs/protocol/proto/DataTransferProtos$OpBlockChecksumResponseProto$Builder
      24: areturn

  public org.apache.hadoop.hdfs.protocol.proto.DataTransferProtos$OpBlockChecksumResponseProtoOrBuilder getChecksumResponseOrBuilder();
    Code:
       0: aload_0
       1: getfield      #26                 // Field checksumResponseBuilder_:Lcom/google/protobuf/SingleFieldBuilder;
       4: ifnull        18
       7: aload_0
       8: getfield      #26                 // Field checksumResponseBuilder_:Lcom/google/protobuf/SingleFieldBuilder;
      11: invokevirtual #94                 // Method com/google/protobuf/SingleFieldBuilder.getMessageOrBuilder:()Lcom/google/protobuf/MessageOrBuilder;
      14: checkcast     #95                 // class org/apache/hadoop/hdfs/protocol/proto/DataTransferProtos$OpBlockChecksumResponseProtoOrBuilder
      17: areturn
      18: aload_0
      19: getfield      #14                 // Field checksumResponse_:Lorg/apache/hadoop/hdfs/protocol/proto/DataTransferProtos$OpBlockChecksumResponseProto;
      22: areturn

  private com.google.protobuf.SingleFieldBuilder<org.apache.hadoop.hdfs.protocol.proto.DataTransferProtos$OpBlockChecksumResponseProto, org.apache.hadoop.hdfs.protocol.proto.DataTransferProtos$OpBlockChecksumResponseProto$Builder, org.apache.hadoop.hdfs.protocol.proto.DataTransferProtos$OpBlockChecksumResponseProtoOrBuilder> getChecksumResponseFieldBuilder();
    Code:
       0: aload_0
       1: getfield      #26                 // Field checksumResponseBuilder_:Lcom/google/protobuf/SingleFieldBuilder;
       4: ifnonnull     35
       7: aload_0
       8: new           #96                 // class com/google/protobuf/SingleFieldBuilder
      11: dup
      12: aload_0
      13: getfield      #14                 // Field checksumResponse_:Lorg/apache/hadoop/hdfs/protocol/proto/DataTransferProtos$OpBlockChecksumResponseProto;
      16: aload_0
      17: invokevirtual #97                 // Method getParentForChildren:()Lcom/google/protobuf/GeneratedMessage$BuilderParent;
      20: aload_0
      21: invokevirtual #98                 // Method isClean:()Z
      24: invokespecial #99                 // Method com/google/protobuf/SingleFieldBuilder."<init>":(Lcom/google/protobuf/GeneratedMessage;Lcom/google/protobuf/GeneratedMessage$BuilderParent;Z)V
      27: putfield      #26                 // Field checksumResponseBuilder_:Lcom/google/protobuf/SingleFieldBuilder;
      30: aload_0
      31: aconst_null
      32: putfield      #14                 // Field checksumResponse_:Lorg/apache/hadoop/hdfs/protocol/proto/DataTransferProtos$OpBlockChecksumResponseProto;
      35: aload_0
      36: getfield      #26                 // Field checksumResponseBuilder_:Lcom/google/protobuf/SingleFieldBuilder;
      39: areturn

  public boolean hasReadOpChecksumInfo();
    Code:
       0: aload_0
       1: getfield      #25                 // Field bitField0_:I
       4: bipush        8
       6: iand
       7: bipush        8
       9: if_icmpne     16
      12: iconst_1
      13: goto          17
      16: iconst_0
      17: ireturn

  public org.apache.hadoop.hdfs.protocol.proto.DataTransferProtos$ReadOpChecksumInfoProto getReadOpChecksumInfo();
    Code:
       0: aload_0
       1: getfield      #28                 // Field readOpChecksumInfoBuilder_:Lcom/google/protobuf/SingleFieldBuilder;
       4: ifnonnull     12
       7: aload_0
       8: getfield      #16                 // Field readOpChecksumInfo_:Lorg/apache/hadoop/hdfs/protocol/proto/DataTransferProtos$ReadOpChecksumInfoProto;
      11: areturn
      12: aload_0
      13: getfield      #28                 // Field readOpChecksumInfoBuilder_:Lcom/google/protobuf/SingleFieldBuilder;
      16: invokevirtual #85                 // Method com/google/protobuf/SingleFieldBuilder.getMessage:()Lcom/google/protobuf/GeneratedMessage;
      19: checkcast     #42                 // class org/apache/hadoop/hdfs/protocol/proto/DataTransferProtos$ReadOpChecksumInfoProto
      22: areturn

  public org.apache.hadoop.hdfs.protocol.proto.DataTransferProtos$BlockOpResponseProto$Builder setReadOpChecksumInfo(org.apache.hadoop.hdfs.protocol.proto.DataTransferProtos$ReadOpChecksumInfoProto);
    Code:
       0: aload_0
       1: getfield      #28                 // Field readOpChecksumInfoBuilder_:Lcom/google/protobuf/SingleFieldBuilder;
       4: ifnonnull     31
       7: aload_1
       8: ifnonnull     19
      11: new           #78                 // class java/lang/NullPointerException
      14: dup
      15: invokespecial #79                 // Method java/lang/NullPointerException."<init>":()V
      18: athrow
      19: aload_0
      20: aload_1
      21: putfield      #16                 // Field readOpChecksumInfo_:Lorg/apache/hadoop/hdfs/protocol/proto/DataTransferProtos$ReadOpChecksumInfoProto;
      24: aload_0
      25: invokevirtual #53                 // Method onChanged:()V
      28: goto          40
      31: aload_0
      32: getfield      #28                 // Field readOpChecksumInfoBuilder_:Lcom/google/protobuf/SingleFieldBuilder;
      35: aload_1
      36: invokevirtual #86                 // Method com/google/protobuf/SingleFieldBuilder.setMessage:(Lcom/google/protobuf/GeneratedMessage;)Lcom/google/protobuf/SingleFieldBuilder;
      39: pop
      40: aload_0
      41: dup
      42: getfield      #25                 // Field bitField0_:I
      45: bipush        8
      47: ior
      48: putfield      #25                 // Field bitField0_:I
      51: aload_0
      52: areturn

  public org.apache.hadoop.hdfs.protocol.proto.DataTransferProtos$BlockOpResponseProto$Builder setReadOpChecksumInfo(org.apache.hadoop.hdfs.protocol.proto.DataTransferProtos$ReadOpChecksumInfoProto$Builder);
    Code:
       0: aload_0
       1: getfield      #28                 // Field readOpChecksumInfoBuilder_:Lcom/google/protobuf/SingleFieldBuilder;
       4: ifnonnull     22
       7: aload_0
       8: aload_1
       9: invokevirtual #100                // Method org/apache/hadoop/hdfs/protocol/proto/DataTransferProtos$ReadOpChecksumInfoProto$Builder.build:()Lorg/apache/hadoop/hdfs/protocol/proto/DataTransferProtos$ReadOpChecksumInfoProto;
      12: putfield      #16                 // Field readOpChecksumInfo_:Lorg/apache/hadoop/hdfs/protocol/proto/DataTransferProtos$ReadOpChecksumInfoProto;
      15: aload_0
      16: invokevirtual #53                 // Method onChanged:()V
      19: goto          34
      22: aload_0
      23: getfield      #28                 // Field readOpChecksumInfoBuilder_:Lcom/google/protobuf/SingleFieldBuilder;
      26: aload_1
      27: invokevirtual #100                // Method org/apache/hadoop/hdfs/protocol/proto/DataTransferProtos$ReadOpChecksumInfoProto$Builder.build:()Lorg/apache/hadoop/hdfs/protocol/proto/DataTransferProtos$ReadOpChecksumInfoProto;
      30: invokevirtual #86                 // Method com/google/protobuf/SingleFieldBuilder.setMessage:(Lcom/google/protobuf/GeneratedMessage;)Lcom/google/protobuf/SingleFieldBuilder;
      33: pop
      34: aload_0
      35: dup
      36: getfield      #25                 // Field bitField0_:I
      39: bipush        8
      41: ior
      42: putfield      #25                 // Field bitField0_:I
      45: aload_0
      46: areturn

  public org.apache.hadoop.hdfs.protocol.proto.DataTransferProtos$BlockOpResponseProto$Builder mergeReadOpChecksumInfo(org.apache.hadoop.hdfs.protocol.proto.DataTransferProtos$ReadOpChecksumInfoProto);
    Code:
       0: aload_0
       1: getfield      #28                 // Field readOpChecksumInfoBuilder_:Lcom/google/protobuf/SingleFieldBuilder;
       4: ifnonnull     62
       7: aload_0
       8: getfield      #25                 // Field bitField0_:I
      11: bipush        8
      13: iand
      14: bipush        8
      16: if_icmpne     50
      19: aload_0
      20: getfield      #16                 // Field readOpChecksumInfo_:Lorg/apache/hadoop/hdfs/protocol/proto/DataTransferProtos$ReadOpChecksumInfoProto;
      23: invokestatic  #15                 // Method org/apache/hadoop/hdfs/protocol/proto/DataTransferProtos$ReadOpChecksumInfoProto.getDefaultInstance:()Lorg/apache/hadoop/hdfs/protocol/proto/DataTransferProtos$ReadOpChecksumInfoProto;
      26: if_acmpeq     50
      29: aload_0
      30: aload_0
      31: getfield      #16                 // Field readOpChecksumInfo_:Lorg/apache/hadoop/hdfs/protocol/proto/DataTransferProtos$ReadOpChecksumInfoProto;
      34: invokestatic  #101                // Method org/apache/hadoop/hdfs/protocol/proto/DataTransferProtos$ReadOpChecksumInfoProto.newBuilder:(Lorg/apache/hadoop/hdfs/protocol/proto/DataTransferProtos$ReadOpChecksumInfoProto;)Lorg/apache/hadoop/hdfs/protocol/proto/DataTransferProtos$ReadOpChecksumInfoProto$Builder;
      37: aload_1
      38: invokevirtual #102                // Method org/apache/hadoop/hdfs/protocol/proto/DataTransferProtos$ReadOpChecksumInfoProto$Builder.mergeFrom:(Lorg/apache/hadoop/hdfs/protocol/proto/DataTransferProtos$ReadOpChecksumInfoProto;)Lorg/apache/hadoop/hdfs/protocol/proto/DataTransferProtos$ReadOpChecksumInfoProto$Builder;
      41: invokevirtual #103                // Method org/apache/hadoop/hdfs/protocol/proto/DataTransferProtos$ReadOpChecksumInfoProto$Builder.buildPartial:()Lorg/apache/hadoop/hdfs/protocol/proto/DataTransferProtos$ReadOpChecksumInfoProto;
      44: putfield      #16                 // Field readOpChecksumInfo_:Lorg/apache/hadoop/hdfs/protocol/proto/DataTransferProtos$ReadOpChecksumInfoProto;
      47: goto          55
      50: aload_0
      51: aload_1
      52: putfield      #16                 // Field readOpChecksumInfo_:Lorg/apache/hadoop/hdfs/protocol/proto/DataTransferProtos$ReadOpChecksumInfoProto;
      55: aload_0
      56: invokevirtual #53                 // Method onChanged:()V
      59: goto          71
      62: aload_0
      63: getfield      #28                 // Field readOpChecksumInfoBuilder_:Lcom/google/protobuf/SingleFieldBuilder;
      66: aload_1
      67: invokevirtual #91                 // Method com/google/protobuf/SingleFieldBuilder.mergeFrom:(Lcom/google/protobuf/GeneratedMessage;)Lcom/google/protobuf/SingleFieldBuilder;
      70: pop
      71: aload_0
      72: dup
      73: getfield      #25                 // Field bitField0_:I
      76: bipush        8
      78: ior
      79: putfield      #25                 // Field bitField0_:I
      82: aload_0
      83: areturn

  public org.apache.hadoop.hdfs.protocol.proto.DataTransferProtos$BlockOpResponseProto$Builder clearReadOpChecksumInfo();
    Code:
       0: aload_0
       1: getfield      #28                 // Field readOpChecksumInfoBuilder_:Lcom/google/protobuf/SingleFieldBuilder;
       4: ifnonnull     21
       7: aload_0
       8: invokestatic  #15                 // Method org/apache/hadoop/hdfs/protocol/proto/DataTransferProtos$ReadOpChecksumInfoProto.getDefaultInstance:()Lorg/apache/hadoop/hdfs/protocol/proto/DataTransferProtos$ReadOpChecksumInfoProto;
      11: putfield      #16                 // Field readOpChecksumInfo_:Lorg/apache/hadoop/hdfs/protocol/proto/DataTransferProtos$ReadOpChecksumInfoProto;
      14: aload_0
      15: invokevirtual #53                 // Method onChanged:()V
      18: goto          29
      21: aload_0
      22: getfield      #28                 // Field readOpChecksumInfoBuilder_:Lcom/google/protobuf/SingleFieldBuilder;
      25: invokevirtual #27                 // Method com/google/protobuf/SingleFieldBuilder.clear:()Lcom/google/protobuf/SingleFieldBuilder;
      28: pop
      29: aload_0
      30: aload_0
      31: getfield      #25                 // Field bitField0_:I
      34: bipush        -9
      36: iand
      37: putfield      #25                 // Field bitField0_:I
      40: aload_0
      41: areturn

  public org.apache.hadoop.hdfs.protocol.proto.DataTransferProtos$ReadOpChecksumInfoProto$Builder getReadOpChecksumInfoBuilder();
    Code:
       0: aload_0
       1: dup
       2: getfield      #25                 // Field bitField0_:I
       5: bipush        8
       7: ior
       8: putfield      #25                 // Field bitField0_:I
      11: aload_0
      12: invokevirtual #53                 // Method onChanged:()V
      15: aload_0
      16: invokespecial #22                 // Method getReadOpChecksumInfoFieldBuilder:()Lcom/google/protobuf/SingleFieldBuilder;
      19: invokevirtual #92                 // Method com/google/protobuf/SingleFieldBuilder.getBuilder:()Lcom/google/protobuf/GeneratedMessage$Builder;
      22: checkcast     #104                // class org/apache/hadoop/hdfs/protocol/proto/DataTransferProtos$ReadOpChecksumInfoProto$Builder
      25: areturn

  public org.apache.hadoop.hdfs.protocol.proto.DataTransferProtos$ReadOpChecksumInfoProtoOrBuilder getReadOpChecksumInfoOrBuilder();
    Code:
       0: aload_0
       1: getfield      #28                 // Field readOpChecksumInfoBuilder_:Lcom/google/protobuf/SingleFieldBuilder;
       4: ifnull        18
       7: aload_0
       8: getfield      #28                 // Field readOpChecksumInfoBuilder_:Lcom/google/protobuf/SingleFieldBuilder;
      11: invokevirtual #94                 // Method com/google/protobuf/SingleFieldBuilder.getMessageOrBuilder:()Lcom/google/protobuf/MessageOrBuilder;
      14: checkcast     #105                // class org/apache/hadoop/hdfs/protocol/proto/DataTransferProtos$ReadOpChecksumInfoProtoOrBuilder
      17: areturn
      18: aload_0
      19: getfield      #16                 // Field readOpChecksumInfo_:Lorg/apache/hadoop/hdfs/protocol/proto/DataTransferProtos$ReadOpChecksumInfoProto;
      22: areturn

  private com.google.protobuf.SingleFieldBuilder<org.apache.hadoop.hdfs.protocol.proto.DataTransferProtos$ReadOpChecksumInfoProto, org.apache.hadoop.hdfs.protocol.proto.DataTransferProtos$ReadOpChecksumInfoProto$Builder, org.apache.hadoop.hdfs.protocol.proto.DataTransferProtos$ReadOpChecksumInfoProtoOrBuilder> getReadOpChecksumInfoFieldBuilder();
    Code:
       0: aload_0
       1: getfield      #28                 // Field readOpChecksumInfoBuilder_:Lcom/google/protobuf/SingleFieldBuilder;
       4: ifnonnull     35
       7: aload_0
       8: new           #96                 // class com/google/protobuf/SingleFieldBuilder
      11: dup
      12: aload_0
      13: getfield      #16                 // Field readOpChecksumInfo_:Lorg/apache/hadoop/hdfs/protocol/proto/DataTransferProtos$ReadOpChecksumInfoProto;
      16: aload_0
      17: invokevirtual #97                 // Method getParentForChildren:()Lcom/google/protobuf/GeneratedMessage$BuilderParent;
      20: aload_0
      21: invokevirtual #98                 // Method isClean:()Z
      24: invokespecial #99                 // Method com/google/protobuf/SingleFieldBuilder."<init>":(Lcom/google/protobuf/GeneratedMessage;Lcom/google/protobuf/GeneratedMessage$BuilderParent;Z)V
      27: putfield      #28                 // Field readOpChecksumInfoBuilder_:Lcom/google/protobuf/SingleFieldBuilder;
      30: aload_0
      31: aconst_null
      32: putfield      #16                 // Field readOpChecksumInfo_:Lorg/apache/hadoop/hdfs/protocol/proto/DataTransferProtos$ReadOpChecksumInfoProto;
      35: aload_0
      36: getfield      #28                 // Field readOpChecksumInfoBuilder_:Lcom/google/protobuf/SingleFieldBuilder;
      39: areturn

  public boolean hasMessage();
    Code:
       0: aload_0
       1: getfield      #25                 // Field bitField0_:I
       4: bipush        16
       6: iand
       7: bipush        16
       9: if_icmpne     16
      12: iconst_1
      13: goto          17
      16: iconst_0
      17: ireturn

  public java.lang.String getMessage();
    Code:
       0: aload_0
       1: getfield      #17                 // Field message_:Ljava/lang/Object;
       4: astore_1
       5: aload_1
       6: instanceof    #80                 // class java/lang/String
       9: ifne          27
      12: aload_1
      13: checkcast     #81                 // class com/google/protobuf/ByteString
      16: invokevirtual #82                 // Method com/google/protobuf/ByteString.toStringUtf8:()Ljava/lang/String;
      19: astore_2
      20: aload_0
      21: aload_2
      22: putfield      #17                 // Field message_:Ljava/lang/Object;
      25: aload_2
      26: areturn
      27: aload_1
      28: checkcast     #80                 // class java/lang/String
      31: areturn

  public com.google.protobuf.ByteString getMessageBytes();
    Code:
       0: aload_0
       1: getfield      #17                 // Field message_:Ljava/lang/Object;
       4: astore_1
       5: aload_1
       6: instanceof    #80                 // class java/lang/String
       9: ifeq          27
      12: aload_1
      13: checkcast     #80                 // class java/lang/String
      16: invokestatic  #83                 // Method com/google/protobuf/ByteString.copyFromUtf8:(Ljava/lang/String;)Lcom/google/protobuf/ByteString;
      19: astore_2
      20: aload_0
      21: aload_2
      22: putfield      #17                 // Field message_:Ljava/lang/Object;
      25: aload_2
      26: areturn
      27: aload_1
      28: checkcast     #81                 // class com/google/protobuf/ByteString
      31: areturn

  public org.apache.hadoop.hdfs.protocol.proto.DataTransferProtos$BlockOpResponseProto$Builder setMessage(java.lang.String);
    Code:
       0: aload_1
       1: ifnonnull     12
       4: new           #78                 // class java/lang/NullPointerException
       7: dup
       8: invokespecial #79                 // Method java/lang/NullPointerException."<init>":()V
      11: athrow
      12: aload_0
      13: dup
      14: getfield      #25                 // Field bitField0_:I
      17: bipush        16
      19: ior
      20: putfield      #25                 // Field bitField0_:I
      23: aload_0
      24: aload_1
      25: putfield      #17                 // Field message_:Ljava/lang/Object;
      28: aload_0
      29: invokevirtual #53                 // Method onChanged:()V
      32: aload_0
      33: areturn

  public org.apache.hadoop.hdfs.protocol.proto.DataTransferProtos$BlockOpResponseProto$Builder clearMessage();
    Code:
       0: aload_0
       1: aload_0
       2: getfield      #25                 // Field bitField0_:I
       5: bipush        -17
       7: iand
       8: putfield      #25                 // Field bitField0_:I
      11: aload_0
      12: invokestatic  #32                 // Method org/apache/hadoop/hdfs/protocol/proto/DataTransferProtos$BlockOpResponseProto.getDefaultInstance:()Lorg/apache/hadoop/hdfs/protocol/proto/DataTransferProtos$BlockOpResponseProto;
      15: invokevirtual #106                // Method org/apache/hadoop/hdfs/protocol/proto/DataTransferProtos$BlockOpResponseProto.getMessage:()Ljava/lang/String;
      18: putfield      #17                 // Field message_:Ljava/lang/Object;
      21: aload_0
      22: invokevirtual #53                 // Method onChanged:()V
      25: aload_0
      26: areturn

  public org.apache.hadoop.hdfs.protocol.proto.DataTransferProtos$BlockOpResponseProto$Builder setMessageBytes(com.google.protobuf.ByteString);
    Code:
       0: aload_1
       1: ifnonnull     12
       4: new           #78                 // class java/lang/NullPointerException
       7: dup
       8: invokespecial #79                 // Method java/lang/NullPointerException."<init>":()V
      11: athrow
      12: aload_0
      13: dup
      14: getfield      #25                 // Field bitField0_:I
      17: bipush        16
      19: ior
      20: putfield      #25                 // Field bitField0_:I
      23: aload_0
      24: aload_1
      25: putfield      #17                 // Field message_:Ljava/lang/Object;
      28: aload_0
      29: invokevirtual #53                 // Method onChanged:()V
      32: aload_0
      33: areturn

  public boolean hasShortCircuitAccessVersion();
    Code:
       0: aload_0
       1: getfield      #25                 // Field bitField0_:I
       4: bipush        32
       6: iand
       7: bipush        32
       9: if_icmpne     16
      12: iconst_1
      13: goto          17
      16: iconst_0
      17: ireturn

  public int getShortCircuitAccessVersion();
    Code:
       0: aload_0
       1: getfield      #29                 // Field shortCircuitAccessVersion_:I
       4: ireturn

  public org.apache.hadoop.hdfs.protocol.proto.DataTransferProtos$BlockOpResponseProto$Builder setShortCircuitAccessVersion(int);
    Code:
       0: aload_0
       1: dup
       2: getfield      #25                 // Field bitField0_:I
       5: bipush        32
       7: ior
       8: putfield      #25                 // Field bitField0_:I
      11: aload_0
      12: iload_1
      13: putfield      #29                 // Field shortCircuitAccessVersion_:I
      16: aload_0
      17: invokevirtual #53                 // Method onChanged:()V
      20: aload_0
      21: areturn

  public org.apache.hadoop.hdfs.protocol.proto.DataTransferProtos$BlockOpResponseProto$Builder clearShortCircuitAccessVersion();
    Code:
       0: aload_0
       1: aload_0
       2: getfield      #25                 // Field bitField0_:I
       5: bipush        -33
       7: iand
       8: putfield      #25                 // Field bitField0_:I
      11: aload_0
      12: iconst_0
      13: putfield      #29                 // Field shortCircuitAccessVersion_:I
      16: aload_0
      17: invokevirtual #53                 // Method onChanged:()V
      20: aload_0
      21: areturn

  public com.google.protobuf.GeneratedMessage$Builder clear();
    Code:
       0: aload_0
       1: invokevirtual #107                // Method clear:()Lorg/apache/hadoop/hdfs/protocol/proto/DataTransferProtos$BlockOpResponseProto$Builder;
       4: areturn

  public com.google.protobuf.GeneratedMessage$Builder clone();
    Code:
       0: aload_0
       1: invokevirtual #108                // Method clone:()Lorg/apache/hadoop/hdfs/protocol/proto/DataTransferProtos$BlockOpResponseProto$Builder;
       4: areturn

  public com.google.protobuf.AbstractMessage$Builder mergeFrom(com.google.protobuf.CodedInputStream, com.google.protobuf.ExtensionRegistryLite) throws java.io.IOException;
    Code:
       0: aload_0
       1: aload_1
       2: aload_2
       3: invokevirtual #109                // Method mergeFrom:(Lcom/google/protobuf/CodedInputStream;Lcom/google/protobuf/ExtensionRegistryLite;)Lorg/apache/hadoop/hdfs/protocol/proto/DataTransferProtos$BlockOpResponseProto$Builder;
       6: areturn

  public com.google.protobuf.AbstractMessage$Builder mergeFrom(com.google.protobuf.Message);
    Code:
       0: aload_0
       1: aload_1
       2: invokevirtual #110                // Method mergeFrom:(Lcom/google/protobuf/Message;)Lorg/apache/hadoop/hdfs/protocol/proto/DataTransferProtos$BlockOpResponseProto$Builder;
       5: areturn

  public com.google.protobuf.AbstractMessage$Builder clear();
    Code:
       0: aload_0
       1: invokevirtual #107                // Method clear:()Lorg/apache/hadoop/hdfs/protocol/proto/DataTransferProtos$BlockOpResponseProto$Builder;
       4: areturn

  public com.google.protobuf.AbstractMessage$Builder clone();
    Code:
       0: aload_0
       1: invokevirtual #108                // Method clone:()Lorg/apache/hadoop/hdfs/protocol/proto/DataTransferProtos$BlockOpResponseProto$Builder;
       4: areturn

  public com.google.protobuf.Message$Builder mergeFrom(com.google.protobuf.CodedInputStream, com.google.protobuf.ExtensionRegistryLite) throws java.io.IOException;
    Code:
       0: aload_0
       1: aload_1
       2: aload_2
       3: invokevirtual #109                // Method mergeFrom:(Lcom/google/protobuf/CodedInputStream;Lcom/google/protobuf/ExtensionRegistryLite;)Lorg/apache/hadoop/hdfs/protocol/proto/DataTransferProtos$BlockOpResponseProto$Builder;
       6: areturn

  public com.google.protobuf.Message$Builder clone();
    Code:
       0: aload_0
       1: invokevirtual #108                // Method clone:()Lorg/apache/hadoop/hdfs/protocol/proto/DataTransferProtos$BlockOpResponseProto$Builder;
       4: areturn

  public com.google.protobuf.Message buildPartial();
    Code:
       0: aload_0
       1: invokevirtual #30                 // Method buildPartial:()Lorg/apache/hadoop/hdfs/protocol/proto/DataTransferProtos$BlockOpResponseProto;
       4: areturn

  public com.google.protobuf.Message build();
    Code:
       0: aload_0
       1: invokevirtual #111                // Method build:()Lorg/apache/hadoop/hdfs/protocol/proto/DataTransferProtos$BlockOpResponseProto;
       4: areturn

  public com.google.protobuf.Message$Builder mergeFrom(com.google.protobuf.Message);
    Code:
       0: aload_0
       1: aload_1
       2: invokevirtual #110                // Method mergeFrom:(Lcom/google/protobuf/Message;)Lorg/apache/hadoop/hdfs/protocol/proto/DataTransferProtos$BlockOpResponseProto$Builder;
       5: areturn

  public com.google.protobuf.Message$Builder clear();
    Code:
       0: aload_0
       1: invokevirtual #107                // Method clear:()Lorg/apache/hadoop/hdfs/protocol/proto/DataTransferProtos$BlockOpResponseProto$Builder;
       4: areturn

  public com.google.protobuf.MessageLite$Builder mergeFrom(com.google.protobuf.CodedInputStream, com.google.protobuf.ExtensionRegistryLite) throws java.io.IOException;
    Code:
       0: aload_0
       1: aload_1
       2: aload_2
       3: invokevirtual #109                // Method mergeFrom:(Lcom/google/protobuf/CodedInputStream;Lcom/google/protobuf/ExtensionRegistryLite;)Lorg/apache/hadoop/hdfs/protocol/proto/DataTransferProtos$BlockOpResponseProto$Builder;
       6: areturn

  public com.google.protobuf.MessageLite$Builder clone();
    Code:
       0: aload_0
       1: invokevirtual #108                // Method clone:()Lorg/apache/hadoop/hdfs/protocol/proto/DataTransferProtos$BlockOpResponseProto$Builder;
       4: areturn

  public com.google.protobuf.MessageLite buildPartial();
    Code:
       0: aload_0
       1: invokevirtual #30                 // Method buildPartial:()Lorg/apache/hadoop/hdfs/protocol/proto/DataTransferProtos$BlockOpResponseProto;
       4: areturn

  public com.google.protobuf.MessageLite build();
    Code:
       0: aload_0
       1: invokevirtual #111                // Method build:()Lorg/apache/hadoop/hdfs/protocol/proto/DataTransferProtos$BlockOpResponseProto;
       4: areturn

  public com.google.protobuf.MessageLite$Builder clear();
    Code:
       0: aload_0
       1: invokevirtual #107                // Method clear:()Lorg/apache/hadoop/hdfs/protocol/proto/DataTransferProtos$BlockOpResponseProto$Builder;
       4: areturn

  public com.google.protobuf.MessageLite getDefaultInstanceForType();
    Code:
       0: aload_0
       1: invokevirtual #112                // Method getDefaultInstanceForType:()Lorg/apache/hadoop/hdfs/protocol/proto/DataTransferProtos$BlockOpResponseProto;
       4: areturn

  public com.google.protobuf.Message getDefaultInstanceForType();
    Code:
       0: aload_0
       1: invokevirtual #112                // Method getDefaultInstanceForType:()Lorg/apache/hadoop/hdfs/protocol/proto/DataTransferProtos$BlockOpResponseProto;
       4: areturn

  public com.google.protobuf.AbstractMessageLite$Builder mergeFrom(com.google.protobuf.CodedInputStream, com.google.protobuf.ExtensionRegistryLite) throws java.io.IOException;
    Code:
       0: aload_0
       1: aload_1
       2: aload_2
       3: invokevirtual #109                // Method mergeFrom:(Lcom/google/protobuf/CodedInputStream;Lcom/google/protobuf/ExtensionRegistryLite;)Lorg/apache/hadoop/hdfs/protocol/proto/DataTransferProtos$BlockOpResponseProto$Builder;
       6: areturn

  public com.google.protobuf.AbstractMessageLite$Builder clone();
    Code:
       0: aload_0
       1: invokevirtual #108                // Method clone:()Lorg/apache/hadoop/hdfs/protocol/proto/DataTransferProtos$BlockOpResponseProto$Builder;
       4: areturn

  public java.lang.Object clone() throws java.lang.CloneNotSupportedException;
    Code:
       0: aload_0
       1: invokevirtual #108                // Method clone:()Lorg/apache/hadoop/hdfs/protocol/proto/DataTransferProtos$BlockOpResponseProto$Builder;
       4: areturn

  static org.apache.hadoop.hdfs.protocol.proto.DataTransferProtos$BlockOpResponseProto$Builder access$28600();
    Code:
       0: invokestatic  #2                  // Method create:()Lorg/apache/hadoop/hdfs/protocol/proto/DataTransferProtos$BlockOpResponseProto$Builder;
       3: areturn

  org.apache.hadoop.hdfs.protocol.proto.DataTransferProtos$BlockOpResponseProto$Builder(com.google.protobuf.GeneratedMessage$BuilderParent, org.apache.hadoop.hdfs.protocol.proto.DataTransferProtos$1);
    Code:
       0: aload_0
       1: aload_1
       2: invokespecial #1                  // Method "<init>":(Lcom/google/protobuf/GeneratedMessage$BuilderParent;)V
       5: return
}
