Compiled from "EncryptionZonesProtos.java"
public final class org.apache.hadoop.hdfs.protocol.proto.EncryptionZonesProtos$ZoneReencryptionStatusProto$Builder extends com.google.protobuf.GeneratedMessage$Builder<org.apache.hadoop.hdfs.protocol.proto.EncryptionZonesProtos$ZoneReencryptionStatusProto$Builder> implements org.apache.hadoop.hdfs.protocol.proto.EncryptionZonesProtos$ZoneReencryptionStatusProtoOrBuilder {
  private int bitField0_;

  private long id_;

  private java.lang.Object path_;

  private org.apache.hadoop.hdfs.protocol.proto.EncryptionZonesProtos$ReencryptionStateProto state_;

  private java.lang.Object ezKeyVersionName_;

  private long submissionTime_;

  private boolean canceled_;

  private long numReencrypted_;

  private long numFailures_;

  private long completionTime_;

  private java.lang.Object lastFile_;

  public static final com.google.protobuf.Descriptors$Descriptor getDescriptor();
    Code:
       0: invokestatic  #3                  // Method org/apache/hadoop/hdfs/protocol/proto/EncryptionZonesProtos.access$7600:()Lcom/google/protobuf/Descriptors$Descriptor;
       3: areturn

  protected com.google.protobuf.GeneratedMessage$FieldAccessorTable internalGetFieldAccessorTable();
    Code:
       0: invokestatic  #4                  // Method org/apache/hadoop/hdfs/protocol/proto/EncryptionZonesProtos.access$7700:()Lcom/google/protobuf/GeneratedMessage$FieldAccessorTable;
       3: ldc           #5                  // class org/apache/hadoop/hdfs/protocol/proto/EncryptionZonesProtos$ZoneReencryptionStatusProto
       5: ldc           #6                  // class org/apache/hadoop/hdfs/protocol/proto/EncryptionZonesProtos$ZoneReencryptionStatusProto$Builder
       7: invokevirtual #7                  // Method com/google/protobuf/GeneratedMessage$FieldAccessorTable.ensureFieldAccessorsInitialized:(Ljava/lang/Class;Ljava/lang/Class;)Lcom/google/protobuf/GeneratedMessage$FieldAccessorTable;
      10: areturn

  private org.apache.hadoop.hdfs.protocol.proto.EncryptionZonesProtos$ZoneReencryptionStatusProto$Builder();
    Code:
       0: aload_0
       1: invokespecial #8                  // Method com/google/protobuf/GeneratedMessage$Builder."<init>":()V
       4: aload_0
       5: ldc           #9                  // String
       7: putfield      #10                 // Field path_:Ljava/lang/Object;
      10: aload_0
      11: getstatic     #11                 // Field org/apache/hadoop/hdfs/protocol/proto/EncryptionZonesProtos$ReencryptionStateProto.SUBMITTED:Lorg/apache/hadoop/hdfs/protocol/proto/EncryptionZonesProtos$ReencryptionStateProto;
      14: putfield      #12                 // Field state_:Lorg/apache/hadoop/hdfs/protocol/proto/EncryptionZonesProtos$ReencryptionStateProto;
      17: aload_0
      18: ldc           #9                  // String
      20: putfield      #13                 // Field ezKeyVersionName_:Ljava/lang/Object;
      23: aload_0
      24: ldc           #9                  // String
      26: putfield      #14                 // Field lastFile_:Ljava/lang/Object;
      29: aload_0
      30: invokespecial #15                 // Method maybeForceBuilderInitialization:()V
      33: return

  private org.apache.hadoop.hdfs.protocol.proto.EncryptionZonesProtos$ZoneReencryptionStatusProto$Builder(com.google.protobuf.GeneratedMessage$BuilderParent);
    Code:
       0: aload_0
       1: aload_1
       2: invokespecial #16                 // Method com/google/protobuf/GeneratedMessage$Builder."<init>":(Lcom/google/protobuf/GeneratedMessage$BuilderParent;)V
       5: aload_0
       6: ldc           #9                  // String
       8: putfield      #10                 // Field path_:Ljava/lang/Object;
      11: aload_0
      12: getstatic     #11                 // Field org/apache/hadoop/hdfs/protocol/proto/EncryptionZonesProtos$ReencryptionStateProto.SUBMITTED:Lorg/apache/hadoop/hdfs/protocol/proto/EncryptionZonesProtos$ReencryptionStateProto;
      15: putfield      #12                 // Field state_:Lorg/apache/hadoop/hdfs/protocol/proto/EncryptionZonesProtos$ReencryptionStateProto;
      18: aload_0
      19: ldc           #9                  // String
      21: putfield      #13                 // Field ezKeyVersionName_:Ljava/lang/Object;
      24: aload_0
      25: ldc           #9                  // String
      27: putfield      #14                 // Field lastFile_:Ljava/lang/Object;
      30: aload_0
      31: invokespecial #15                 // Method maybeForceBuilderInitialization:()V
      34: return

  private void maybeForceBuilderInitialization();
    Code:
       0: invokestatic  #17                 // Method org/apache/hadoop/hdfs/protocol/proto/EncryptionZonesProtos$ZoneReencryptionStatusProto.access$8100:()Z
       3: ifeq          6
       6: return

  private static org.apache.hadoop.hdfs.protocol.proto.EncryptionZonesProtos$ZoneReencryptionStatusProto$Builder create();
    Code:
       0: new           #6                  // class org/apache/hadoop/hdfs/protocol/proto/EncryptionZonesProtos$ZoneReencryptionStatusProto$Builder
       3: dup
       4: invokespecial #18                 // Method "<init>":()V
       7: areturn

  public org.apache.hadoop.hdfs.protocol.proto.EncryptionZonesProtos$ZoneReencryptionStatusProto$Builder clear();
    Code:
       0: aload_0
       1: invokespecial #19                 // Method com/google/protobuf/GeneratedMessage$Builder.clear:()Lcom/google/protobuf/GeneratedMessage$Builder;
       4: pop
       5: aload_0
       6: lconst_0
       7: putfield      #20                 // Field id_:J
      10: aload_0
      11: aload_0
      12: getfield      #21                 // Field bitField0_:I
      15: bipush        -2
      17: iand
      18: putfield      #21                 // Field bitField0_:I
      21: aload_0
      22: ldc           #9                  // String
      24: putfield      #10                 // Field path_:Ljava/lang/Object;
      27: aload_0
      28: aload_0
      29: getfield      #21                 // Field bitField0_:I
      32: bipush        -3
      34: iand
      35: putfield      #21                 // Field bitField0_:I
      38: aload_0
      39: getstatic     #11                 // Field org/apache/hadoop/hdfs/protocol/proto/EncryptionZonesProtos$ReencryptionStateProto.SUBMITTED:Lorg/apache/hadoop/hdfs/protocol/proto/EncryptionZonesProtos$ReencryptionStateProto;
      42: putfield      #12                 // Field state_:Lorg/apache/hadoop/hdfs/protocol/proto/EncryptionZonesProtos$ReencryptionStateProto;
      45: aload_0
      46: aload_0
      47: getfield      #21                 // Field bitField0_:I
      50: bipush        -5
      52: iand
      53: putfield      #21                 // Field bitField0_:I
      56: aload_0
      57: ldc           #9                  // String
      59: putfield      #13                 // Field ezKeyVersionName_:Ljava/lang/Object;
      62: aload_0
      63: aload_0
      64: getfield      #21                 // Field bitField0_:I
      67: bipush        -9
      69: iand
      70: putfield      #21                 // Field bitField0_:I
      73: aload_0
      74: lconst_0
      75: putfield      #22                 // Field submissionTime_:J
      78: aload_0
      79: aload_0
      80: getfield      #21                 // Field bitField0_:I
      83: bipush        -17
      85: iand
      86: putfield      #21                 // Field bitField0_:I
      89: aload_0
      90: iconst_0
      91: putfield      #23                 // Field canceled_:Z
      94: aload_0
      95: aload_0
      96: getfield      #21                 // Field bitField0_:I
      99: bipush        -33
     101: iand
     102: putfield      #21                 // Field bitField0_:I
     105: aload_0
     106: lconst_0
     107: putfield      #24                 // Field numReencrypted_:J
     110: aload_0
     111: aload_0
     112: getfield      #21                 // Field bitField0_:I
     115: bipush        -65
     117: iand
     118: putfield      #21                 // Field bitField0_:I
     121: aload_0
     122: lconst_0
     123: putfield      #25                 // Field numFailures_:J
     126: aload_0
     127: aload_0
     128: getfield      #21                 // Field bitField0_:I
     131: sipush        -129
     134: iand
     135: putfield      #21                 // Field bitField0_:I
     138: aload_0
     139: lconst_0
     140: putfield      #26                 // Field completionTime_:J
     143: aload_0
     144: aload_0
     145: getfield      #21                 // Field bitField0_:I
     148: sipush        -257
     151: iand
     152: putfield      #21                 // Field bitField0_:I
     155: aload_0
     156: ldc           #9                  // String
     158: putfield      #14                 // Field lastFile_:Ljava/lang/Object;
     161: aload_0
     162: aload_0
     163: getfield      #21                 // Field bitField0_:I
     166: sipush        -513
     169: iand
     170: putfield      #21                 // Field bitField0_:I
     173: aload_0
     174: areturn

  public org.apache.hadoop.hdfs.protocol.proto.EncryptionZonesProtos$ZoneReencryptionStatusProto$Builder clone();
    Code:
       0: invokestatic  #2                  // Method create:()Lorg/apache/hadoop/hdfs/protocol/proto/EncryptionZonesProtos$ZoneReencryptionStatusProto$Builder;
       3: aload_0
       4: invokevirtual #27                 // Method buildPartial:()Lorg/apache/hadoop/hdfs/protocol/proto/EncryptionZonesProtos$ZoneReencryptionStatusProto;
       7: invokevirtual #28                 // Method mergeFrom:(Lorg/apache/hadoop/hdfs/protocol/proto/EncryptionZonesProtos$ZoneReencryptionStatusProto;)Lorg/apache/hadoop/hdfs/protocol/proto/EncryptionZonesProtos$ZoneReencryptionStatusProto$Builder;
      10: areturn

  public com.google.protobuf.Descriptors$Descriptor getDescriptorForType();
    Code:
       0: invokestatic  #3                  // Method org/apache/hadoop/hdfs/protocol/proto/EncryptionZonesProtos.access$7600:()Lcom/google/protobuf/Descriptors$Descriptor;
       3: areturn

  public org.apache.hadoop.hdfs.protocol.proto.EncryptionZonesProtos$ZoneReencryptionStatusProto getDefaultInstanceForType();
    Code:
       0: invokestatic  #29                 // Method org/apache/hadoop/hdfs/protocol/proto/EncryptionZonesProtos$ZoneReencryptionStatusProto.getDefaultInstance:()Lorg/apache/hadoop/hdfs/protocol/proto/EncryptionZonesProtos$ZoneReencryptionStatusProto;
       3: areturn

  public org.apache.hadoop.hdfs.protocol.proto.EncryptionZonesProtos$ZoneReencryptionStatusProto build();
    Code:
       0: aload_0
       1: invokevirtual #27                 // Method buildPartial:()Lorg/apache/hadoop/hdfs/protocol/proto/EncryptionZonesProtos$ZoneReencryptionStatusProto;
       4: astore_1
       5: aload_1
       6: invokevirtual #30                 // Method org/apache/hadoop/hdfs/protocol/proto/EncryptionZonesProtos$ZoneReencryptionStatusProto.isInitialized:()Z
       9: ifne          17
      12: aload_1
      13: invokestatic  #31                 // Method newUninitializedMessageException:(Lcom/google/protobuf/Message;)Lcom/google/protobuf/UninitializedMessageException;
      16: athrow
      17: aload_1
      18: areturn

  public org.apache.hadoop.hdfs.protocol.proto.EncryptionZonesProtos$ZoneReencryptionStatusProto buildPartial();
    Code:
       0: new           #5                  // class org/apache/hadoop/hdfs/protocol/proto/EncryptionZonesProtos$ZoneReencryptionStatusProto
       3: dup
       4: aload_0
       5: aconst_null
       6: invokespecial #32                 // Method org/apache/hadoop/hdfs/protocol/proto/EncryptionZonesProtos$ZoneReencryptionStatusProto."<init>":(Lcom/google/protobuf/GeneratedMessage$Builder;Lorg/apache/hadoop/hdfs/protocol/proto/EncryptionZonesProtos$1;)V
       9: astore_1
      10: aload_0
      11: getfield      #21                 // Field bitField0_:I
      14: istore_2
      15: iconst_0
      16: istore_3
      17: iload_2
      18: iconst_1
      19: iand
      20: iconst_1
      21: if_icmpne     28
      24: iload_3
      25: iconst_1
      26: ior
      27: istore_3
      28: aload_1
      29: aload_0
      30: getfield      #20                 // Field id_:J
      33: invokestatic  #33                 // Method org/apache/hadoop/hdfs/protocol/proto/EncryptionZonesProtos$ZoneReencryptionStatusProto.access$8302:(Lorg/apache/hadoop/hdfs/protocol/proto/EncryptionZonesProtos$ZoneReencryptionStatusProto;J)J
      36: pop2
      37: iload_2
      38: iconst_2
      39: iand
      40: iconst_2
      41: if_icmpne     48
      44: iload_3
      45: iconst_2
      46: ior
      47: istore_3
      48: aload_1
      49: aload_0
      50: getfield      #10                 // Field path_:Ljava/lang/Object;
      53: invokestatic  #34                 // Method org/apache/hadoop/hdfs/protocol/proto/EncryptionZonesProtos$ZoneReencryptionStatusProto.access$8402:(Lorg/apache/hadoop/hdfs/protocol/proto/EncryptionZonesProtos$ZoneReencryptionStatusProto;Ljava/lang/Object;)Ljava/lang/Object;
      56: pop
      57: iload_2
      58: iconst_4
      59: iand
      60: iconst_4
      61: if_icmpne     68
      64: iload_3
      65: iconst_4
      66: ior
      67: istore_3
      68: aload_1
      69: aload_0
      70: getfield      #12                 // Field state_:Lorg/apache/hadoop/hdfs/protocol/proto/EncryptionZonesProtos$ReencryptionStateProto;
      73: invokestatic  #35                 // Method org/apache/hadoop/hdfs/protocol/proto/EncryptionZonesProtos$ZoneReencryptionStatusProto.access$8502:(Lorg/apache/hadoop/hdfs/protocol/proto/EncryptionZonesProtos$ZoneReencryptionStatusProto;Lorg/apache/hadoop/hdfs/protocol/proto/EncryptionZonesProtos$ReencryptionStateProto;)Lorg/apache/hadoop/hdfs/protocol/proto/EncryptionZonesProtos$ReencryptionStateProto;
      76: pop
      77: iload_2
      78: bipush        8
      80: iand
      81: bipush        8
      83: if_icmpne     91
      86: iload_3
      87: bipush        8
      89: ior
      90: istore_3
      91: aload_1
      92: aload_0
      93: getfield      #13                 // Field ezKeyVersionName_:Ljava/lang/Object;
      96: invokestatic  #36                 // Method org/apache/hadoop/hdfs/protocol/proto/EncryptionZonesProtos$ZoneReencryptionStatusProto.access$8602:(Lorg/apache/hadoop/hdfs/protocol/proto/EncryptionZonesProtos$ZoneReencryptionStatusProto;Ljava/lang/Object;)Ljava/lang/Object;
      99: pop
     100: iload_2
     101: bipush        16
     103: iand
     104: bipush        16
     106: if_icmpne     114
     109: iload_3
     110: bipush        16
     112: ior
     113: istore_3
     114: aload_1
     115: aload_0
     116: getfield      #22                 // Field submissionTime_:J
     119: invokestatic  #37                 // Method org/apache/hadoop/hdfs/protocol/proto/EncryptionZonesProtos$ZoneReencryptionStatusProto.access$8702:(Lorg/apache/hadoop/hdfs/protocol/proto/EncryptionZonesProtos$ZoneReencryptionStatusProto;J)J
     122: pop2
     123: iload_2
     124: bipush        32
     126: iand
     127: bipush        32
     129: if_icmpne     137
     132: iload_3
     133: bipush        32
     135: ior
     136: istore_3
     137: aload_1
     138: aload_0
     139: getfield      #23                 // Field canceled_:Z
     142: invokestatic  #38                 // Method org/apache/hadoop/hdfs/protocol/proto/EncryptionZonesProtos$ZoneReencryptionStatusProto.access$8802:(Lorg/apache/hadoop/hdfs/protocol/proto/EncryptionZonesProtos$ZoneReencryptionStatusProto;Z)Z
     145: pop
     146: iload_2
     147: bipush        64
     149: iand
     150: bipush        64
     152: if_icmpne     160
     155: iload_3
     156: bipush        64
     158: ior
     159: istore_3
     160: aload_1
     161: aload_0
     162: getfield      #24                 // Field numReencrypted_:J
     165: invokestatic  #39                 // Method org/apache/hadoop/hdfs/protocol/proto/EncryptionZonesProtos$ZoneReencryptionStatusProto.access$8902:(Lorg/apache/hadoop/hdfs/protocol/proto/EncryptionZonesProtos$ZoneReencryptionStatusProto;J)J
     168: pop2
     169: iload_2
     170: sipush        128
     173: iand
     174: sipush        128
     177: if_icmpne     186
     180: iload_3
     181: sipush        128
     184: ior
     185: istore_3
     186: aload_1
     187: aload_0
     188: getfield      #25                 // Field numFailures_:J
     191: invokestatic  #40                 // Method org/apache/hadoop/hdfs/protocol/proto/EncryptionZonesProtos$ZoneReencryptionStatusProto.access$9002:(Lorg/apache/hadoop/hdfs/protocol/proto/EncryptionZonesProtos$ZoneReencryptionStatusProto;J)J
     194: pop2
     195: iload_2
     196: sipush        256
     199: iand
     200: sipush        256
     203: if_icmpne     212
     206: iload_3
     207: sipush        256
     210: ior
     211: istore_3
     212: aload_1
     213: aload_0
     214: getfield      #26                 // Field completionTime_:J
     217: invokestatic  #41                 // Method org/apache/hadoop/hdfs/protocol/proto/EncryptionZonesProtos$ZoneReencryptionStatusProto.access$9102:(Lorg/apache/hadoop/hdfs/protocol/proto/EncryptionZonesProtos$ZoneReencryptionStatusProto;J)J
     220: pop2
     221: iload_2
     222: sipush        512
     225: iand
     226: sipush        512
     229: if_icmpne     238
     232: iload_3
     233: sipush        512
     236: ior
     237: istore_3
     238: aload_1
     239: aload_0
     240: getfield      #14                 // Field lastFile_:Ljava/lang/Object;
     243: invokestatic  #42                 // Method org/apache/hadoop/hdfs/protocol/proto/EncryptionZonesProtos$ZoneReencryptionStatusProto.access$9202:(Lorg/apache/hadoop/hdfs/protocol/proto/EncryptionZonesProtos$ZoneReencryptionStatusProto;Ljava/lang/Object;)Ljava/lang/Object;
     246: pop
     247: aload_1
     248: iload_3
     249: invokestatic  #43                 // Method org/apache/hadoop/hdfs/protocol/proto/EncryptionZonesProtos$ZoneReencryptionStatusProto.access$9302:(Lorg/apache/hadoop/hdfs/protocol/proto/EncryptionZonesProtos$ZoneReencryptionStatusProto;I)I
     252: pop
     253: aload_0
     254: invokevirtual #44                 // Method onBuilt:()V
     257: aload_1
     258: areturn

  public org.apache.hadoop.hdfs.protocol.proto.EncryptionZonesProtos$ZoneReencryptionStatusProto$Builder mergeFrom(com.google.protobuf.Message);
    Code:
       0: aload_1
       1: instanceof    #5                  // class org/apache/hadoop/hdfs/protocol/proto/EncryptionZonesProtos$ZoneReencryptionStatusProto
       4: ifeq          16
       7: aload_0
       8: aload_1
       9: checkcast     #5                  // class org/apache/hadoop/hdfs/protocol/proto/EncryptionZonesProtos$ZoneReencryptionStatusProto
      12: invokevirtual #28                 // Method mergeFrom:(Lorg/apache/hadoop/hdfs/protocol/proto/EncryptionZonesProtos$ZoneReencryptionStatusProto;)Lorg/apache/hadoop/hdfs/protocol/proto/EncryptionZonesProtos$ZoneReencryptionStatusProto$Builder;
      15: areturn
      16: aload_0
      17: aload_1
      18: invokespecial #45                 // Method com/google/protobuf/GeneratedMessage$Builder.mergeFrom:(Lcom/google/protobuf/Message;)Lcom/google/protobuf/AbstractMessage$Builder;
      21: pop
      22: aload_0
      23: areturn

  public org.apache.hadoop.hdfs.protocol.proto.EncryptionZonesProtos$ZoneReencryptionStatusProto$Builder mergeFrom(org.apache.hadoop.hdfs.protocol.proto.EncryptionZonesProtos$ZoneReencryptionStatusProto);
    Code:
       0: aload_1
       1: invokestatic  #29                 // Method org/apache/hadoop/hdfs/protocol/proto/EncryptionZonesProtos$ZoneReencryptionStatusProto.getDefaultInstance:()Lorg/apache/hadoop/hdfs/protocol/proto/EncryptionZonesProtos$ZoneReencryptionStatusProto;
       4: if_acmpne     9
       7: aload_0
       8: areturn
       9: aload_1
      10: invokevirtual #46                 // Method org/apache/hadoop/hdfs/protocol/proto/EncryptionZonesProtos$ZoneReencryptionStatusProto.hasId:()Z
      13: ifeq          25
      16: aload_0
      17: aload_1
      18: invokevirtual #47                 // Method org/apache/hadoop/hdfs/protocol/proto/EncryptionZonesProtos$ZoneReencryptionStatusProto.getId:()J
      21: invokevirtual #48                 // Method setId:(J)Lorg/apache/hadoop/hdfs/protocol/proto/EncryptionZonesProtos$ZoneReencryptionStatusProto$Builder;
      24: pop
      25: aload_1
      26: invokevirtual #49                 // Method org/apache/hadoop/hdfs/protocol/proto/EncryptionZonesProtos$ZoneReencryptionStatusProto.hasPath:()Z
      29: ifeq          54
      32: aload_0
      33: dup
      34: getfield      #21                 // Field bitField0_:I
      37: iconst_2
      38: ior
      39: putfield      #21                 // Field bitField0_:I
      42: aload_0
      43: aload_1
      44: invokestatic  #50                 // Method org/apache/hadoop/hdfs/protocol/proto/EncryptionZonesProtos$ZoneReencryptionStatusProto.access$8400:(Lorg/apache/hadoop/hdfs/protocol/proto/EncryptionZonesProtos$ZoneReencryptionStatusProto;)Ljava/lang/Object;
      47: putfield      #10                 // Field path_:Ljava/lang/Object;
      50: aload_0
      51: invokevirtual #51                 // Method onChanged:()V
      54: aload_1
      55: invokevirtual #52                 // Method org/apache/hadoop/hdfs/protocol/proto/EncryptionZonesProtos$ZoneReencryptionStatusProto.hasState:()Z
      58: ifeq          70
      61: aload_0
      62: aload_1
      63: invokevirtual #53                 // Method org/apache/hadoop/hdfs/protocol/proto/EncryptionZonesProtos$ZoneReencryptionStatusProto.getState:()Lorg/apache/hadoop/hdfs/protocol/proto/EncryptionZonesProtos$ReencryptionStateProto;
      66: invokevirtual #54                 // Method setState:(Lorg/apache/hadoop/hdfs/protocol/proto/EncryptionZonesProtos$ReencryptionStateProto;)Lorg/apache/hadoop/hdfs/protocol/proto/EncryptionZonesProtos$ZoneReencryptionStatusProto$Builder;
      69: pop
      70: aload_1
      71: invokevirtual #55                 // Method org/apache/hadoop/hdfs/protocol/proto/EncryptionZonesProtos$ZoneReencryptionStatusProto.hasEzKeyVersionName:()Z
      74: ifeq          100
      77: aload_0
      78: dup
      79: getfield      #21                 // Field bitField0_:I
      82: bipush        8
      84: ior
      85: putfield      #21                 // Field bitField0_:I
      88: aload_0
      89: aload_1
      90: invokestatic  #56                 // Method org/apache/hadoop/hdfs/protocol/proto/EncryptionZonesProtos$ZoneReencryptionStatusProto.access$8600:(Lorg/apache/hadoop/hdfs/protocol/proto/EncryptionZonesProtos$ZoneReencryptionStatusProto;)Ljava/lang/Object;
      93: putfield      #13                 // Field ezKeyVersionName_:Ljava/lang/Object;
      96: aload_0
      97: invokevirtual #51                 // Method onChanged:()V
     100: aload_1
     101: invokevirtual #57                 // Method org/apache/hadoop/hdfs/protocol/proto/EncryptionZonesProtos$ZoneReencryptionStatusProto.hasSubmissionTime:()Z
     104: ifeq          116
     107: aload_0
     108: aload_1
     109: invokevirtual #58                 // Method org/apache/hadoop/hdfs/protocol/proto/EncryptionZonesProtos$ZoneReencryptionStatusProto.getSubmissionTime:()J
     112: invokevirtual #59                 // Method setSubmissionTime:(J)Lorg/apache/hadoop/hdfs/protocol/proto/EncryptionZonesProtos$ZoneReencryptionStatusProto$Builder;
     115: pop
     116: aload_1
     117: invokevirtual #60                 // Method org/apache/hadoop/hdfs/protocol/proto/EncryptionZonesProtos$ZoneReencryptionStatusProto.hasCanceled:()Z
     120: ifeq          132
     123: aload_0
     124: aload_1
     125: invokevirtual #61                 // Method org/apache/hadoop/hdfs/protocol/proto/EncryptionZonesProtos$ZoneReencryptionStatusProto.getCanceled:()Z
     128: invokevirtual #62                 // Method setCanceled:(Z)Lorg/apache/hadoop/hdfs/protocol/proto/EncryptionZonesProtos$ZoneReencryptionStatusProto$Builder;
     131: pop
     132: aload_1
     133: invokevirtual #63                 // Method org/apache/hadoop/hdfs/protocol/proto/EncryptionZonesProtos$ZoneReencryptionStatusProto.hasNumReencrypted:()Z
     136: ifeq          148
     139: aload_0
     140: aload_1
     141: invokevirtual #64                 // Method org/apache/hadoop/hdfs/protocol/proto/EncryptionZonesProtos$ZoneReencryptionStatusProto.getNumReencrypted:()J
     144: invokevirtual #65                 // Method setNumReencrypted:(J)Lorg/apache/hadoop/hdfs/protocol/proto/EncryptionZonesProtos$ZoneReencryptionStatusProto$Builder;
     147: pop
     148: aload_1
     149: invokevirtual #66                 // Method org/apache/hadoop/hdfs/protocol/proto/EncryptionZonesProtos$ZoneReencryptionStatusProto.hasNumFailures:()Z
     152: ifeq          164
     155: aload_0
     156: aload_1
     157: invokevirtual #67                 // Method org/apache/hadoop/hdfs/protocol/proto/EncryptionZonesProtos$ZoneReencryptionStatusProto.getNumFailures:()J
     160: invokevirtual #68                 // Method setNumFailures:(J)Lorg/apache/hadoop/hdfs/protocol/proto/EncryptionZonesProtos$ZoneReencryptionStatusProto$Builder;
     163: pop
     164: aload_1
     165: invokevirtual #69                 // Method org/apache/hadoop/hdfs/protocol/proto/EncryptionZonesProtos$ZoneReencryptionStatusProto.hasCompletionTime:()Z
     168: ifeq          180
     171: aload_0
     172: aload_1
     173: invokevirtual #70                 // Method org/apache/hadoop/hdfs/protocol/proto/EncryptionZonesProtos$ZoneReencryptionStatusProto.getCompletionTime:()J
     176: invokevirtual #71                 // Method setCompletionTime:(J)Lorg/apache/hadoop/hdfs/protocol/proto/EncryptionZonesProtos$ZoneReencryptionStatusProto$Builder;
     179: pop
     180: aload_1
     181: invokevirtual #72                 // Method org/apache/hadoop/hdfs/protocol/proto/EncryptionZonesProtos$ZoneReencryptionStatusProto.hasLastFile:()Z
     184: ifeq          211
     187: aload_0
     188: dup
     189: getfield      #21                 // Field bitField0_:I
     192: sipush        512
     195: ior
     196: putfield      #21                 // Field bitField0_:I
     199: aload_0
     200: aload_1
     201: invokestatic  #73                 // Method org/apache/hadoop/hdfs/protocol/proto/EncryptionZonesProtos$ZoneReencryptionStatusProto.access$9200:(Lorg/apache/hadoop/hdfs/protocol/proto/EncryptionZonesProtos$ZoneReencryptionStatusProto;)Ljava/lang/Object;
     204: putfield      #14                 // Field lastFile_:Ljava/lang/Object;
     207: aload_0
     208: invokevirtual #51                 // Method onChanged:()V
     211: aload_0
     212: aload_1
     213: invokevirtual #74                 // Method org/apache/hadoop/hdfs/protocol/proto/EncryptionZonesProtos$ZoneReencryptionStatusProto.getUnknownFields:()Lcom/google/protobuf/UnknownFieldSet;
     216: invokevirtual #75                 // Method mergeUnknownFields:(Lcom/google/protobuf/UnknownFieldSet;)Lcom/google/protobuf/GeneratedMessage$Builder;
     219: pop
     220: aload_0
     221: areturn

  public final boolean isInitialized();
    Code:
       0: aload_0
       1: invokevirtual #76                 // Method hasId:()Z
       4: ifne          9
       7: iconst_0
       8: ireturn
       9: aload_0
      10: invokevirtual #77                 // Method hasPath:()Z
      13: ifne          18
      16: iconst_0
      17: ireturn
      18: aload_0
      19: invokevirtual #78                 // Method hasState:()Z
      22: ifne          27
      25: iconst_0
      26: ireturn
      27: aload_0
      28: invokevirtual #79                 // Method hasEzKeyVersionName:()Z
      31: ifne          36
      34: iconst_0
      35: ireturn
      36: aload_0
      37: invokevirtual #80                 // Method hasSubmissionTime:()Z
      40: ifne          45
      43: iconst_0
      44: ireturn
      45: aload_0
      46: invokevirtual #81                 // Method hasCanceled:()Z
      49: ifne          54
      52: iconst_0
      53: ireturn
      54: aload_0
      55: invokevirtual #82                 // Method hasNumReencrypted:()Z
      58: ifne          63
      61: iconst_0
      62: ireturn
      63: aload_0
      64: invokevirtual #83                 // Method hasNumFailures:()Z
      67: ifne          72
      70: iconst_0
      71: ireturn
      72: iconst_1
      73: ireturn

  public org.apache.hadoop.hdfs.protocol.proto.EncryptionZonesProtos$ZoneReencryptionStatusProto$Builder mergeFrom(com.google.protobuf.CodedInputStream, com.google.protobuf.ExtensionRegistryLite) throws java.io.IOException;
    Code:
       0: aconst_null
       1: astore_3
       2: getstatic     #84                 // Field org/apache/hadoop/hdfs/protocol/proto/EncryptionZonesProtos$ZoneReencryptionStatusProto.PARSER:Lcom/google/protobuf/Parser;
       5: aload_1
       6: aload_2
       7: invokeinterface #85,  3           // InterfaceMethod com/google/protobuf/Parser.parsePartialFrom:(Lcom/google/protobuf/CodedInputStream;Lcom/google/protobuf/ExtensionRegistryLite;)Ljava/lang/Object;
      12: checkcast     #5                  // class org/apache/hadoop/hdfs/protocol/proto/EncryptionZonesProtos$ZoneReencryptionStatusProto
      15: astore_3
      16: aload_3
      17: ifnull        58
      20: aload_0
      21: aload_3
      22: invokevirtual #28                 // Method mergeFrom:(Lorg/apache/hadoop/hdfs/protocol/proto/EncryptionZonesProtos$ZoneReencryptionStatusProto;)Lorg/apache/hadoop/hdfs/protocol/proto/EncryptionZonesProtos$ZoneReencryptionStatusProto$Builder;
      25: pop
      26: goto          58
      29: astore        4
      31: aload         4
      33: invokevirtual #87                 // Method com/google/protobuf/InvalidProtocolBufferException.getUnfinishedMessage:()Lcom/google/protobuf/MessageLite;
      36: checkcast     #5                  // class org/apache/hadoop/hdfs/protocol/proto/EncryptionZonesProtos$ZoneReencryptionStatusProto
      39: astore_3
      40: aload         4
      42: athrow
      43: astore        5
      45: aload_3
      46: ifnull        55
      49: aload_0
      50: aload_3
      51: invokevirtual #28                 // Method mergeFrom:(Lorg/apache/hadoop/hdfs/protocol/proto/EncryptionZonesProtos$ZoneReencryptionStatusProto;)Lorg/apache/hadoop/hdfs/protocol/proto/EncryptionZonesProtos$ZoneReencryptionStatusProto$Builder;
      54: pop
      55: aload         5
      57: athrow
      58: aload_0
      59: areturn
    Exception table:
       from    to  target type
           2    16    29   Class com/google/protobuf/InvalidProtocolBufferException
           2    16    43   any
          29    45    43   any

  public boolean hasId();
    Code:
       0: aload_0
       1: getfield      #21                 // Field bitField0_:I
       4: iconst_1
       5: iand
       6: iconst_1
       7: if_icmpne     14
      10: iconst_1
      11: goto          15
      14: iconst_0
      15: ireturn

  public long getId();
    Code:
       0: aload_0
       1: getfield      #20                 // Field id_:J
       4: lreturn

  public org.apache.hadoop.hdfs.protocol.proto.EncryptionZonesProtos$ZoneReencryptionStatusProto$Builder setId(long);
    Code:
       0: aload_0
       1: dup
       2: getfield      #21                 // Field bitField0_:I
       5: iconst_1
       6: ior
       7: putfield      #21                 // Field bitField0_:I
      10: aload_0
      11: lload_1
      12: putfield      #20                 // Field id_:J
      15: aload_0
      16: invokevirtual #51                 // Method onChanged:()V
      19: aload_0
      20: areturn

  public org.apache.hadoop.hdfs.protocol.proto.EncryptionZonesProtos$ZoneReencryptionStatusProto$Builder clearId();
    Code:
       0: aload_0
       1: aload_0
       2: getfield      #21                 // Field bitField0_:I
       5: bipush        -2
       7: iand
       8: putfield      #21                 // Field bitField0_:I
      11: aload_0
      12: lconst_0
      13: putfield      #20                 // Field id_:J
      16: aload_0
      17: invokevirtual #51                 // Method onChanged:()V
      20: aload_0
      21: areturn

  public boolean hasPath();
    Code:
       0: aload_0
       1: getfield      #21                 // Field bitField0_:I
       4: iconst_2
       5: iand
       6: iconst_2
       7: if_icmpne     14
      10: iconst_1
      11: goto          15
      14: iconst_0
      15: ireturn

  public java.lang.String getPath();
    Code:
       0: aload_0
       1: getfield      #10                 // Field path_:Ljava/lang/Object;
       4: astore_1
       5: aload_1
       6: instanceof    #88                 // class java/lang/String
       9: ifne          27
      12: aload_1
      13: checkcast     #89                 // class com/google/protobuf/ByteString
      16: invokevirtual #90                 // Method com/google/protobuf/ByteString.toStringUtf8:()Ljava/lang/String;
      19: astore_2
      20: aload_0
      21: aload_2
      22: putfield      #10                 // Field path_:Ljava/lang/Object;
      25: aload_2
      26: areturn
      27: aload_1
      28: checkcast     #88                 // class java/lang/String
      31: areturn

  public com.google.protobuf.ByteString getPathBytes();
    Code:
       0: aload_0
       1: getfield      #10                 // Field path_:Ljava/lang/Object;
       4: astore_1
       5: aload_1
       6: instanceof    #88                 // class java/lang/String
       9: ifeq          27
      12: aload_1
      13: checkcast     #88                 // class java/lang/String
      16: invokestatic  #91                 // Method com/google/protobuf/ByteString.copyFromUtf8:(Ljava/lang/String;)Lcom/google/protobuf/ByteString;
      19: astore_2
      20: aload_0
      21: aload_2
      22: putfield      #10                 // Field path_:Ljava/lang/Object;
      25: aload_2
      26: areturn
      27: aload_1
      28: checkcast     #89                 // class com/google/protobuf/ByteString
      31: areturn

  public org.apache.hadoop.hdfs.protocol.proto.EncryptionZonesProtos$ZoneReencryptionStatusProto$Builder setPath(java.lang.String);
    Code:
       0: aload_1
       1: ifnonnull     12
       4: new           #92                 // class java/lang/NullPointerException
       7: dup
       8: invokespecial #93                 // Method java/lang/NullPointerException."<init>":()V
      11: athrow
      12: aload_0
      13: dup
      14: getfield      #21                 // Field bitField0_:I
      17: iconst_2
      18: ior
      19: putfield      #21                 // Field bitField0_:I
      22: aload_0
      23: aload_1
      24: putfield      #10                 // Field path_:Ljava/lang/Object;
      27: aload_0
      28: invokevirtual #51                 // Method onChanged:()V
      31: aload_0
      32: areturn

  public org.apache.hadoop.hdfs.protocol.proto.EncryptionZonesProtos$ZoneReencryptionStatusProto$Builder clearPath();
    Code:
       0: aload_0
       1: aload_0
       2: getfield      #21                 // Field bitField0_:I
       5: bipush        -3
       7: iand
       8: putfield      #21                 // Field bitField0_:I
      11: aload_0
      12: invokestatic  #29                 // Method org/apache/hadoop/hdfs/protocol/proto/EncryptionZonesProtos$ZoneReencryptionStatusProto.getDefaultInstance:()Lorg/apache/hadoop/hdfs/protocol/proto/EncryptionZonesProtos$ZoneReencryptionStatusProto;
      15: invokevirtual #94                 // Method org/apache/hadoop/hdfs/protocol/proto/EncryptionZonesProtos$ZoneReencryptionStatusProto.getPath:()Ljava/lang/String;
      18: putfield      #10                 // Field path_:Ljava/lang/Object;
      21: aload_0
      22: invokevirtual #51                 // Method onChanged:()V
      25: aload_0
      26: areturn

  public org.apache.hadoop.hdfs.protocol.proto.EncryptionZonesProtos$ZoneReencryptionStatusProto$Builder setPathBytes(com.google.protobuf.ByteString);
    Code:
       0: aload_1
       1: ifnonnull     12
       4: new           #92                 // class java/lang/NullPointerException
       7: dup
       8: invokespecial #93                 // Method java/lang/NullPointerException."<init>":()V
      11: athrow
      12: aload_0
      13: dup
      14: getfield      #21                 // Field bitField0_:I
      17: iconst_2
      18: ior
      19: putfield      #21                 // Field bitField0_:I
      22: aload_0
      23: aload_1
      24: putfield      #10                 // Field path_:Ljava/lang/Object;
      27: aload_0
      28: invokevirtual #51                 // Method onChanged:()V
      31: aload_0
      32: areturn

  public boolean hasState();
    Code:
       0: aload_0
       1: getfield      #21                 // Field bitField0_:I
       4: iconst_4
       5: iand
       6: iconst_4
       7: if_icmpne     14
      10: iconst_1
      11: goto          15
      14: iconst_0
      15: ireturn

  public org.apache.hadoop.hdfs.protocol.proto.EncryptionZonesProtos$ReencryptionStateProto getState();
    Code:
       0: aload_0
       1: getfield      #12                 // Field state_:Lorg/apache/hadoop/hdfs/protocol/proto/EncryptionZonesProtos$ReencryptionStateProto;
       4: areturn

  public org.apache.hadoop.hdfs.protocol.proto.EncryptionZonesProtos$ZoneReencryptionStatusProto$Builder setState(org.apache.hadoop.hdfs.protocol.proto.EncryptionZonesProtos$ReencryptionStateProto);
    Code:
       0: aload_1
       1: ifnonnull     12
       4: new           #92                 // class java/lang/NullPointerException
       7: dup
       8: invokespecial #93                 // Method java/lang/NullPointerException."<init>":()V
      11: athrow
      12: aload_0
      13: dup
      14: getfield      #21                 // Field bitField0_:I
      17: iconst_4
      18: ior
      19: putfield      #21                 // Field bitField0_:I
      22: aload_0
      23: aload_1
      24: putfield      #12                 // Field state_:Lorg/apache/hadoop/hdfs/protocol/proto/EncryptionZonesProtos$ReencryptionStateProto;
      27: aload_0
      28: invokevirtual #51                 // Method onChanged:()V
      31: aload_0
      32: areturn

  public org.apache.hadoop.hdfs.protocol.proto.EncryptionZonesProtos$ZoneReencryptionStatusProto$Builder clearState();
    Code:
       0: aload_0
       1: aload_0
       2: getfield      #21                 // Field bitField0_:I
       5: bipush        -5
       7: iand
       8: putfield      #21                 // Field bitField0_:I
      11: aload_0
      12: getstatic     #11                 // Field org/apache/hadoop/hdfs/protocol/proto/EncryptionZonesProtos$ReencryptionStateProto.SUBMITTED:Lorg/apache/hadoop/hdfs/protocol/proto/EncryptionZonesProtos$ReencryptionStateProto;
      15: putfield      #12                 // Field state_:Lorg/apache/hadoop/hdfs/protocol/proto/EncryptionZonesProtos$ReencryptionStateProto;
      18: aload_0
      19: invokevirtual #51                 // Method onChanged:()V
      22: aload_0
      23: areturn

  public boolean hasEzKeyVersionName();
    Code:
       0: aload_0
       1: getfield      #21                 // Field bitField0_:I
       4: bipush        8
       6: iand
       7: bipush        8
       9: if_icmpne     16
      12: iconst_1
      13: goto          17
      16: iconst_0
      17: ireturn

  public java.lang.String getEzKeyVersionName();
    Code:
       0: aload_0
       1: getfield      #13                 // Field ezKeyVersionName_:Ljava/lang/Object;
       4: astore_1
       5: aload_1
       6: instanceof    #88                 // class java/lang/String
       9: ifne          27
      12: aload_1
      13: checkcast     #89                 // class com/google/protobuf/ByteString
      16: invokevirtual #90                 // Method com/google/protobuf/ByteString.toStringUtf8:()Ljava/lang/String;
      19: astore_2
      20: aload_0
      21: aload_2
      22: putfield      #13                 // Field ezKeyVersionName_:Ljava/lang/Object;
      25: aload_2
      26: areturn
      27: aload_1
      28: checkcast     #88                 // class java/lang/String
      31: areturn

  public com.google.protobuf.ByteString getEzKeyVersionNameBytes();
    Code:
       0: aload_0
       1: getfield      #13                 // Field ezKeyVersionName_:Ljava/lang/Object;
       4: astore_1
       5: aload_1
       6: instanceof    #88                 // class java/lang/String
       9: ifeq          27
      12: aload_1
      13: checkcast     #88                 // class java/lang/String
      16: invokestatic  #91                 // Method com/google/protobuf/ByteString.copyFromUtf8:(Ljava/lang/String;)Lcom/google/protobuf/ByteString;
      19: astore_2
      20: aload_0
      21: aload_2
      22: putfield      #13                 // Field ezKeyVersionName_:Ljava/lang/Object;
      25: aload_2
      26: areturn
      27: aload_1
      28: checkcast     #89                 // class com/google/protobuf/ByteString
      31: areturn

  public org.apache.hadoop.hdfs.protocol.proto.EncryptionZonesProtos$ZoneReencryptionStatusProto$Builder setEzKeyVersionName(java.lang.String);
    Code:
       0: aload_1
       1: ifnonnull     12
       4: new           #92                 // class java/lang/NullPointerException
       7: dup
       8: invokespecial #93                 // Method java/lang/NullPointerException."<init>":()V
      11: athrow
      12: aload_0
      13: dup
      14: getfield      #21                 // Field bitField0_:I
      17: bipush        8
      19: ior
      20: putfield      #21                 // Field bitField0_:I
      23: aload_0
      24: aload_1
      25: putfield      #13                 // Field ezKeyVersionName_:Ljava/lang/Object;
      28: aload_0
      29: invokevirtual #51                 // Method onChanged:()V
      32: aload_0
      33: areturn

  public org.apache.hadoop.hdfs.protocol.proto.EncryptionZonesProtos$ZoneReencryptionStatusProto$Builder clearEzKeyVersionName();
    Code:
       0: aload_0
       1: aload_0
       2: getfield      #21                 // Field bitField0_:I
       5: bipush        -9
       7: iand
       8: putfield      #21                 // Field bitField0_:I
      11: aload_0
      12: invokestatic  #29                 // Method org/apache/hadoop/hdfs/protocol/proto/EncryptionZonesProtos$ZoneReencryptionStatusProto.getDefaultInstance:()Lorg/apache/hadoop/hdfs/protocol/proto/EncryptionZonesProtos$ZoneReencryptionStatusProto;
      15: invokevirtual #95                 // Method org/apache/hadoop/hdfs/protocol/proto/EncryptionZonesProtos$ZoneReencryptionStatusProto.getEzKeyVersionName:()Ljava/lang/String;
      18: putfield      #13                 // Field ezKeyVersionName_:Ljava/lang/Object;
      21: aload_0
      22: invokevirtual #51                 // Method onChanged:()V
      25: aload_0
      26: areturn

  public org.apache.hadoop.hdfs.protocol.proto.EncryptionZonesProtos$ZoneReencryptionStatusProto$Builder setEzKeyVersionNameBytes(com.google.protobuf.ByteString);
    Code:
       0: aload_1
       1: ifnonnull     12
       4: new           #92                 // class java/lang/NullPointerException
       7: dup
       8: invokespecial #93                 // Method java/lang/NullPointerException."<init>":()V
      11: athrow
      12: aload_0
      13: dup
      14: getfield      #21                 // Field bitField0_:I
      17: bipush        8
      19: ior
      20: putfield      #21                 // Field bitField0_:I
      23: aload_0
      24: aload_1
      25: putfield      #13                 // Field ezKeyVersionName_:Ljava/lang/Object;
      28: aload_0
      29: invokevirtual #51                 // Method onChanged:()V
      32: aload_0
      33: areturn

  public boolean hasSubmissionTime();
    Code:
       0: aload_0
       1: getfield      #21                 // Field bitField0_:I
       4: bipush        16
       6: iand
       7: bipush        16
       9: if_icmpne     16
      12: iconst_1
      13: goto          17
      16: iconst_0
      17: ireturn

  public long getSubmissionTime();
    Code:
       0: aload_0
       1: getfield      #22                 // Field submissionTime_:J
       4: lreturn

  public org.apache.hadoop.hdfs.protocol.proto.EncryptionZonesProtos$ZoneReencryptionStatusProto$Builder setSubmissionTime(long);
    Code:
       0: aload_0
       1: dup
       2: getfield      #21                 // Field bitField0_:I
       5: bipush        16
       7: ior
       8: putfield      #21                 // Field bitField0_:I
      11: aload_0
      12: lload_1
      13: putfield      #22                 // Field submissionTime_:J
      16: aload_0
      17: invokevirtual #51                 // Method onChanged:()V
      20: aload_0
      21: areturn

  public org.apache.hadoop.hdfs.protocol.proto.EncryptionZonesProtos$ZoneReencryptionStatusProto$Builder clearSubmissionTime();
    Code:
       0: aload_0
       1: aload_0
       2: getfield      #21                 // Field bitField0_:I
       5: bipush        -17
       7: iand
       8: putfield      #21                 // Field bitField0_:I
      11: aload_0
      12: lconst_0
      13: putfield      #22                 // Field submissionTime_:J
      16: aload_0
      17: invokevirtual #51                 // Method onChanged:()V
      20: aload_0
      21: areturn

  public boolean hasCanceled();
    Code:
       0: aload_0
       1: getfield      #21                 // Field bitField0_:I
       4: bipush        32
       6: iand
       7: bipush        32
       9: if_icmpne     16
      12: iconst_1
      13: goto          17
      16: iconst_0
      17: ireturn

  public boolean getCanceled();
    Code:
       0: aload_0
       1: getfield      #23                 // Field canceled_:Z
       4: ireturn

  public org.apache.hadoop.hdfs.protocol.proto.EncryptionZonesProtos$ZoneReencryptionStatusProto$Builder setCanceled(boolean);
    Code:
       0: aload_0
       1: dup
       2: getfield      #21                 // Field bitField0_:I
       5: bipush        32
       7: ior
       8: putfield      #21                 // Field bitField0_:I
      11: aload_0
      12: iload_1
      13: putfield      #23                 // Field canceled_:Z
      16: aload_0
      17: invokevirtual #51                 // Method onChanged:()V
      20: aload_0
      21: areturn

  public org.apache.hadoop.hdfs.protocol.proto.EncryptionZonesProtos$ZoneReencryptionStatusProto$Builder clearCanceled();
    Code:
       0: aload_0
       1: aload_0
       2: getfield      #21                 // Field bitField0_:I
       5: bipush        -33
       7: iand
       8: putfield      #21                 // Field bitField0_:I
      11: aload_0
      12: iconst_0
      13: putfield      #23                 // Field canceled_:Z
      16: aload_0
      17: invokevirtual #51                 // Method onChanged:()V
      20: aload_0
      21: areturn

  public boolean hasNumReencrypted();
    Code:
       0: aload_0
       1: getfield      #21                 // Field bitField0_:I
       4: bipush        64
       6: iand
       7: bipush        64
       9: if_icmpne     16
      12: iconst_1
      13: goto          17
      16: iconst_0
      17: ireturn

  public long getNumReencrypted();
    Code:
       0: aload_0
       1: getfield      #24                 // Field numReencrypted_:J
       4: lreturn

  public org.apache.hadoop.hdfs.protocol.proto.EncryptionZonesProtos$ZoneReencryptionStatusProto$Builder setNumReencrypted(long);
    Code:
       0: aload_0
       1: dup
       2: getfield      #21                 // Field bitField0_:I
       5: bipush        64
       7: ior
       8: putfield      #21                 // Field bitField0_:I
      11: aload_0
      12: lload_1
      13: putfield      #24                 // Field numReencrypted_:J
      16: aload_0
      17: invokevirtual #51                 // Method onChanged:()V
      20: aload_0
      21: areturn

  public org.apache.hadoop.hdfs.protocol.proto.EncryptionZonesProtos$ZoneReencryptionStatusProto$Builder clearNumReencrypted();
    Code:
       0: aload_0
       1: aload_0
       2: getfield      #21                 // Field bitField0_:I
       5: bipush        -65
       7: iand
       8: putfield      #21                 // Field bitField0_:I
      11: aload_0
      12: lconst_0
      13: putfield      #24                 // Field numReencrypted_:J
      16: aload_0
      17: invokevirtual #51                 // Method onChanged:()V
      20: aload_0
      21: areturn

  public boolean hasNumFailures();
    Code:
       0: aload_0
       1: getfield      #21                 // Field bitField0_:I
       4: sipush        128
       7: iand
       8: sipush        128
      11: if_icmpne     18
      14: iconst_1
      15: goto          19
      18: iconst_0
      19: ireturn

  public long getNumFailures();
    Code:
       0: aload_0
       1: getfield      #25                 // Field numFailures_:J
       4: lreturn

  public org.apache.hadoop.hdfs.protocol.proto.EncryptionZonesProtos$ZoneReencryptionStatusProto$Builder setNumFailures(long);
    Code:
       0: aload_0
       1: dup
       2: getfield      #21                 // Field bitField0_:I
       5: sipush        128
       8: ior
       9: putfield      #21                 // Field bitField0_:I
      12: aload_0
      13: lload_1
      14: putfield      #25                 // Field numFailures_:J
      17: aload_0
      18: invokevirtual #51                 // Method onChanged:()V
      21: aload_0
      22: areturn

  public org.apache.hadoop.hdfs.protocol.proto.EncryptionZonesProtos$ZoneReencryptionStatusProto$Builder clearNumFailures();
    Code:
       0: aload_0
       1: aload_0
       2: getfield      #21                 // Field bitField0_:I
       5: sipush        -129
       8: iand
       9: putfield      #21                 // Field bitField0_:I
      12: aload_0
      13: lconst_0
      14: putfield      #25                 // Field numFailures_:J
      17: aload_0
      18: invokevirtual #51                 // Method onChanged:()V
      21: aload_0
      22: areturn

  public boolean hasCompletionTime();
    Code:
       0: aload_0
       1: getfield      #21                 // Field bitField0_:I
       4: sipush        256
       7: iand
       8: sipush        256
      11: if_icmpne     18
      14: iconst_1
      15: goto          19
      18: iconst_0
      19: ireturn

  public long getCompletionTime();
    Code:
       0: aload_0
       1: getfield      #26                 // Field completionTime_:J
       4: lreturn

  public org.apache.hadoop.hdfs.protocol.proto.EncryptionZonesProtos$ZoneReencryptionStatusProto$Builder setCompletionTime(long);
    Code:
       0: aload_0
       1: dup
       2: getfield      #21                 // Field bitField0_:I
       5: sipush        256
       8: ior
       9: putfield      #21                 // Field bitField0_:I
      12: aload_0
      13: lload_1
      14: putfield      #26                 // Field completionTime_:J
      17: aload_0
      18: invokevirtual #51                 // Method onChanged:()V
      21: aload_0
      22: areturn

  public org.apache.hadoop.hdfs.protocol.proto.EncryptionZonesProtos$ZoneReencryptionStatusProto$Builder clearCompletionTime();
    Code:
       0: aload_0
       1: aload_0
       2: getfield      #21                 // Field bitField0_:I
       5: sipush        -257
       8: iand
       9: putfield      #21                 // Field bitField0_:I
      12: aload_0
      13: lconst_0
      14: putfield      #26                 // Field completionTime_:J
      17: aload_0
      18: invokevirtual #51                 // Method onChanged:()V
      21: aload_0
      22: areturn

  public boolean hasLastFile();
    Code:
       0: aload_0
       1: getfield      #21                 // Field bitField0_:I
       4: sipush        512
       7: iand
       8: sipush        512
      11: if_icmpne     18
      14: iconst_1
      15: goto          19
      18: iconst_0
      19: ireturn

  public java.lang.String getLastFile();
    Code:
       0: aload_0
       1: getfield      #14                 // Field lastFile_:Ljava/lang/Object;
       4: astore_1
       5: aload_1
       6: instanceof    #88                 // class java/lang/String
       9: ifne          27
      12: aload_1
      13: checkcast     #89                 // class com/google/protobuf/ByteString
      16: invokevirtual #90                 // Method com/google/protobuf/ByteString.toStringUtf8:()Ljava/lang/String;
      19: astore_2
      20: aload_0
      21: aload_2
      22: putfield      #14                 // Field lastFile_:Ljava/lang/Object;
      25: aload_2
      26: areturn
      27: aload_1
      28: checkcast     #88                 // class java/lang/String
      31: areturn

  public com.google.protobuf.ByteString getLastFileBytes();
    Code:
       0: aload_0
       1: getfield      #14                 // Field lastFile_:Ljava/lang/Object;
       4: astore_1
       5: aload_1
       6: instanceof    #88                 // class java/lang/String
       9: ifeq          27
      12: aload_1
      13: checkcast     #88                 // class java/lang/String
      16: invokestatic  #91                 // Method com/google/protobuf/ByteString.copyFromUtf8:(Ljava/lang/String;)Lcom/google/protobuf/ByteString;
      19: astore_2
      20: aload_0
      21: aload_2
      22: putfield      #14                 // Field lastFile_:Ljava/lang/Object;
      25: aload_2
      26: areturn
      27: aload_1
      28: checkcast     #89                 // class com/google/protobuf/ByteString
      31: areturn

  public org.apache.hadoop.hdfs.protocol.proto.EncryptionZonesProtos$ZoneReencryptionStatusProto$Builder setLastFile(java.lang.String);
    Code:
       0: aload_1
       1: ifnonnull     12
       4: new           #92                 // class java/lang/NullPointerException
       7: dup
       8: invokespecial #93                 // Method java/lang/NullPointerException."<init>":()V
      11: athrow
      12: aload_0
      13: dup
      14: getfield      #21                 // Field bitField0_:I
      17: sipush        512
      20: ior
      21: putfield      #21                 // Field bitField0_:I
      24: aload_0
      25: aload_1
      26: putfield      #14                 // Field lastFile_:Ljava/lang/Object;
      29: aload_0
      30: invokevirtual #51                 // Method onChanged:()V
      33: aload_0
      34: areturn

  public org.apache.hadoop.hdfs.protocol.proto.EncryptionZonesProtos$ZoneReencryptionStatusProto$Builder clearLastFile();
    Code:
       0: aload_0
       1: aload_0
       2: getfield      #21                 // Field bitField0_:I
       5: sipush        -513
       8: iand
       9: putfield      #21                 // Field bitField0_:I
      12: aload_0
      13: invokestatic  #29                 // Method org/apache/hadoop/hdfs/protocol/proto/EncryptionZonesProtos$ZoneReencryptionStatusProto.getDefaultInstance:()Lorg/apache/hadoop/hdfs/protocol/proto/EncryptionZonesProtos$ZoneReencryptionStatusProto;
      16: invokevirtual #96                 // Method org/apache/hadoop/hdfs/protocol/proto/EncryptionZonesProtos$ZoneReencryptionStatusProto.getLastFile:()Ljava/lang/String;
      19: putfield      #14                 // Field lastFile_:Ljava/lang/Object;
      22: aload_0
      23: invokevirtual #51                 // Method onChanged:()V
      26: aload_0
      27: areturn

  public org.apache.hadoop.hdfs.protocol.proto.EncryptionZonesProtos$ZoneReencryptionStatusProto$Builder setLastFileBytes(com.google.protobuf.ByteString);
    Code:
       0: aload_1
       1: ifnonnull     12
       4: new           #92                 // class java/lang/NullPointerException
       7: dup
       8: invokespecial #93                 // Method java/lang/NullPointerException."<init>":()V
      11: athrow
      12: aload_0
      13: dup
      14: getfield      #21                 // Field bitField0_:I
      17: sipush        512
      20: ior
      21: putfield      #21                 // Field bitField0_:I
      24: aload_0
      25: aload_1
      26: putfield      #14                 // Field lastFile_:Ljava/lang/Object;
      29: aload_0
      30: invokevirtual #51                 // Method onChanged:()V
      33: aload_0
      34: areturn

  public com.google.protobuf.GeneratedMessage$Builder clear();
    Code:
       0: aload_0
       1: invokevirtual #97                 // Method clear:()Lorg/apache/hadoop/hdfs/protocol/proto/EncryptionZonesProtos$ZoneReencryptionStatusProto$Builder;
       4: areturn

  public com.google.protobuf.GeneratedMessage$Builder clone();
    Code:
       0: aload_0
       1: invokevirtual #98                 // Method clone:()Lorg/apache/hadoop/hdfs/protocol/proto/EncryptionZonesProtos$ZoneReencryptionStatusProto$Builder;
       4: areturn

  public com.google.protobuf.AbstractMessage$Builder mergeFrom(com.google.protobuf.CodedInputStream, com.google.protobuf.ExtensionRegistryLite) throws java.io.IOException;
    Code:
       0: aload_0
       1: aload_1
       2: aload_2
       3: invokevirtual #99                 // Method mergeFrom:(Lcom/google/protobuf/CodedInputStream;Lcom/google/protobuf/ExtensionRegistryLite;)Lorg/apache/hadoop/hdfs/protocol/proto/EncryptionZonesProtos$ZoneReencryptionStatusProto$Builder;
       6: areturn

  public com.google.protobuf.AbstractMessage$Builder mergeFrom(com.google.protobuf.Message);
    Code:
       0: aload_0
       1: aload_1
       2: invokevirtual #100                // Method mergeFrom:(Lcom/google/protobuf/Message;)Lorg/apache/hadoop/hdfs/protocol/proto/EncryptionZonesProtos$ZoneReencryptionStatusProto$Builder;
       5: areturn

  public com.google.protobuf.AbstractMessage$Builder clear();
    Code:
       0: aload_0
       1: invokevirtual #97                 // Method clear:()Lorg/apache/hadoop/hdfs/protocol/proto/EncryptionZonesProtos$ZoneReencryptionStatusProto$Builder;
       4: areturn

  public com.google.protobuf.AbstractMessage$Builder clone();
    Code:
       0: aload_0
       1: invokevirtual #98                 // Method clone:()Lorg/apache/hadoop/hdfs/protocol/proto/EncryptionZonesProtos$ZoneReencryptionStatusProto$Builder;
       4: areturn

  public com.google.protobuf.Message$Builder mergeFrom(com.google.protobuf.CodedInputStream, com.google.protobuf.ExtensionRegistryLite) throws java.io.IOException;
    Code:
       0: aload_0
       1: aload_1
       2: aload_2
       3: invokevirtual #99                 // Method mergeFrom:(Lcom/google/protobuf/CodedInputStream;Lcom/google/protobuf/ExtensionRegistryLite;)Lorg/apache/hadoop/hdfs/protocol/proto/EncryptionZonesProtos$ZoneReencryptionStatusProto$Builder;
       6: areturn

  public com.google.protobuf.Message$Builder clone();
    Code:
       0: aload_0
       1: invokevirtual #98                 // Method clone:()Lorg/apache/hadoop/hdfs/protocol/proto/EncryptionZonesProtos$ZoneReencryptionStatusProto$Builder;
       4: areturn

  public com.google.protobuf.Message buildPartial();
    Code:
       0: aload_0
       1: invokevirtual #27                 // Method buildPartial:()Lorg/apache/hadoop/hdfs/protocol/proto/EncryptionZonesProtos$ZoneReencryptionStatusProto;
       4: areturn

  public com.google.protobuf.Message build();
    Code:
       0: aload_0
       1: invokevirtual #101                // Method build:()Lorg/apache/hadoop/hdfs/protocol/proto/EncryptionZonesProtos$ZoneReencryptionStatusProto;
       4: areturn

  public com.google.protobuf.Message$Builder mergeFrom(com.google.protobuf.Message);
    Code:
       0: aload_0
       1: aload_1
       2: invokevirtual #100                // Method mergeFrom:(Lcom/google/protobuf/Message;)Lorg/apache/hadoop/hdfs/protocol/proto/EncryptionZonesProtos$ZoneReencryptionStatusProto$Builder;
       5: areturn

  public com.google.protobuf.Message$Builder clear();
    Code:
       0: aload_0
       1: invokevirtual #97                 // Method clear:()Lorg/apache/hadoop/hdfs/protocol/proto/EncryptionZonesProtos$ZoneReencryptionStatusProto$Builder;
       4: areturn

  public com.google.protobuf.MessageLite$Builder mergeFrom(com.google.protobuf.CodedInputStream, com.google.protobuf.ExtensionRegistryLite) throws java.io.IOException;
    Code:
       0: aload_0
       1: aload_1
       2: aload_2
       3: invokevirtual #99                 // Method mergeFrom:(Lcom/google/protobuf/CodedInputStream;Lcom/google/protobuf/ExtensionRegistryLite;)Lorg/apache/hadoop/hdfs/protocol/proto/EncryptionZonesProtos$ZoneReencryptionStatusProto$Builder;
       6: areturn

  public com.google.protobuf.MessageLite$Builder clone();
    Code:
       0: aload_0
       1: invokevirtual #98                 // Method clone:()Lorg/apache/hadoop/hdfs/protocol/proto/EncryptionZonesProtos$ZoneReencryptionStatusProto$Builder;
       4: areturn

  public com.google.protobuf.MessageLite buildPartial();
    Code:
       0: aload_0
       1: invokevirtual #27                 // Method buildPartial:()Lorg/apache/hadoop/hdfs/protocol/proto/EncryptionZonesProtos$ZoneReencryptionStatusProto;
       4: areturn

  public com.google.protobuf.MessageLite build();
    Code:
       0: aload_0
       1: invokevirtual #101                // Method build:()Lorg/apache/hadoop/hdfs/protocol/proto/EncryptionZonesProtos$ZoneReencryptionStatusProto;
       4: areturn

  public com.google.protobuf.MessageLite$Builder clear();
    Code:
       0: aload_0
       1: invokevirtual #97                 // Method clear:()Lorg/apache/hadoop/hdfs/protocol/proto/EncryptionZonesProtos$ZoneReencryptionStatusProto$Builder;
       4: areturn

  public com.google.protobuf.MessageLite getDefaultInstanceForType();
    Code:
       0: aload_0
       1: invokevirtual #102                // Method getDefaultInstanceForType:()Lorg/apache/hadoop/hdfs/protocol/proto/EncryptionZonesProtos$ZoneReencryptionStatusProto;
       4: areturn

  public com.google.protobuf.Message getDefaultInstanceForType();
    Code:
       0: aload_0
       1: invokevirtual #102                // Method getDefaultInstanceForType:()Lorg/apache/hadoop/hdfs/protocol/proto/EncryptionZonesProtos$ZoneReencryptionStatusProto;
       4: areturn

  public com.google.protobuf.AbstractMessageLite$Builder mergeFrom(com.google.protobuf.CodedInputStream, com.google.protobuf.ExtensionRegistryLite) throws java.io.IOException;
    Code:
       0: aload_0
       1: aload_1
       2: aload_2
       3: invokevirtual #99                 // Method mergeFrom:(Lcom/google/protobuf/CodedInputStream;Lcom/google/protobuf/ExtensionRegistryLite;)Lorg/apache/hadoop/hdfs/protocol/proto/EncryptionZonesProtos$ZoneReencryptionStatusProto$Builder;
       6: areturn

  public com.google.protobuf.AbstractMessageLite$Builder clone();
    Code:
       0: aload_0
       1: invokevirtual #98                 // Method clone:()Lorg/apache/hadoop/hdfs/protocol/proto/EncryptionZonesProtos$ZoneReencryptionStatusProto$Builder;
       4: areturn

  public java.lang.Object clone() throws java.lang.CloneNotSupportedException;
    Code:
       0: aload_0
       1: invokevirtual #98                 // Method clone:()Lorg/apache/hadoop/hdfs/protocol/proto/EncryptionZonesProtos$ZoneReencryptionStatusProto$Builder;
       4: areturn

  static org.apache.hadoop.hdfs.protocol.proto.EncryptionZonesProtos$ZoneReencryptionStatusProto$Builder access$7900();
    Code:
       0: invokestatic  #2                  // Method create:()Lorg/apache/hadoop/hdfs/protocol/proto/EncryptionZonesProtos$ZoneReencryptionStatusProto$Builder;
       3: areturn

  org.apache.hadoop.hdfs.protocol.proto.EncryptionZonesProtos$ZoneReencryptionStatusProto$Builder(com.google.protobuf.GeneratedMessage$BuilderParent, org.apache.hadoop.hdfs.protocol.proto.EncryptionZonesProtos$1);
    Code:
       0: aload_0
       1: aload_1
       2: invokespecial #1                  // Method "<init>":(Lcom/google/protobuf/GeneratedMessage$BuilderParent;)V
       5: return
}
