Compiled from "HdfsProtos.java"
public final class org.apache.hadoop.hdfs.protocol.proto.HdfsProtos$SnapshottableDirectoryStatusProto$Builder extends com.google.protobuf.GeneratedMessage$Builder<org.apache.hadoop.hdfs.protocol.proto.HdfsProtos$SnapshottableDirectoryStatusProto$Builder> implements org.apache.hadoop.hdfs.protocol.proto.HdfsProtos$SnapshottableDirectoryStatusProtoOrBuilder {
  private int bitField0_;

  private org.apache.hadoop.hdfs.protocol.proto.HdfsProtos$HdfsFileStatusProto dirStatus_;

  private com.google.protobuf.SingleFieldBuilder<org.apache.hadoop.hdfs.protocol.proto.HdfsProtos$HdfsFileStatusProto, org.apache.hadoop.hdfs.protocol.proto.HdfsProtos$HdfsFileStatusProto$Builder, org.apache.hadoop.hdfs.protocol.proto.HdfsProtos$HdfsFileStatusProtoOrBuilder> dirStatusBuilder_;

  private int snapshotQuota_;

  private int snapshotNumber_;

  private com.google.protobuf.ByteString parentFullpath_;

  public static final com.google.protobuf.Descriptors$Descriptor getDescriptor();
    Code:
       0: invokestatic  #3                  // Method org/apache/hadoop/hdfs/protocol/proto/HdfsProtos.access$45800:()Lcom/google/protobuf/Descriptors$Descriptor;
       3: areturn

  protected com.google.protobuf.GeneratedMessage$FieldAccessorTable internalGetFieldAccessorTable();
    Code:
       0: invokestatic  #4                  // Method org/apache/hadoop/hdfs/protocol/proto/HdfsProtos.access$45900:()Lcom/google/protobuf/GeneratedMessage$FieldAccessorTable;
       3: ldc           #5                  // class org/apache/hadoop/hdfs/protocol/proto/HdfsProtos$SnapshottableDirectoryStatusProto
       5: ldc           #6                  // class org/apache/hadoop/hdfs/protocol/proto/HdfsProtos$SnapshottableDirectoryStatusProto$Builder
       7: invokevirtual #7                  // Method com/google/protobuf/GeneratedMessage$FieldAccessorTable.ensureFieldAccessorsInitialized:(Ljava/lang/Class;Ljava/lang/Class;)Lcom/google/protobuf/GeneratedMessage$FieldAccessorTable;
      10: areturn

  private org.apache.hadoop.hdfs.protocol.proto.HdfsProtos$SnapshottableDirectoryStatusProto$Builder();
    Code:
       0: aload_0
       1: invokespecial #8                  // Method com/google/protobuf/GeneratedMessage$Builder."<init>":()V
       4: aload_0
       5: invokestatic  #9                  // Method org/apache/hadoop/hdfs/protocol/proto/HdfsProtos$HdfsFileStatusProto.getDefaultInstance:()Lorg/apache/hadoop/hdfs/protocol/proto/HdfsProtos$HdfsFileStatusProto;
       8: putfield      #10                 // Field dirStatus_:Lorg/apache/hadoop/hdfs/protocol/proto/HdfsProtos$HdfsFileStatusProto;
      11: aload_0
      12: getstatic     #11                 // Field com/google/protobuf/ByteString.EMPTY:Lcom/google/protobuf/ByteString;
      15: putfield      #12                 // Field parentFullpath_:Lcom/google/protobuf/ByteString;
      18: aload_0
      19: invokespecial #13                 // Method maybeForceBuilderInitialization:()V
      22: return

  private org.apache.hadoop.hdfs.protocol.proto.HdfsProtos$SnapshottableDirectoryStatusProto$Builder(com.google.protobuf.GeneratedMessage$BuilderParent);
    Code:
       0: aload_0
       1: aload_1
       2: invokespecial #14                 // Method com/google/protobuf/GeneratedMessage$Builder."<init>":(Lcom/google/protobuf/GeneratedMessage$BuilderParent;)V
       5: aload_0
       6: invokestatic  #9                  // Method org/apache/hadoop/hdfs/protocol/proto/HdfsProtos$HdfsFileStatusProto.getDefaultInstance:()Lorg/apache/hadoop/hdfs/protocol/proto/HdfsProtos$HdfsFileStatusProto;
       9: putfield      #10                 // Field dirStatus_:Lorg/apache/hadoop/hdfs/protocol/proto/HdfsProtos$HdfsFileStatusProto;
      12: aload_0
      13: getstatic     #11                 // Field com/google/protobuf/ByteString.EMPTY:Lcom/google/protobuf/ByteString;
      16: putfield      #12                 // Field parentFullpath_:Lcom/google/protobuf/ByteString;
      19: aload_0
      20: invokespecial #13                 // Method maybeForceBuilderInitialization:()V
      23: return

  private void maybeForceBuilderInitialization();
    Code:
       0: invokestatic  #15                 // Method org/apache/hadoop/hdfs/protocol/proto/HdfsProtos$SnapshottableDirectoryStatusProto.access$46300:()Z
       3: ifeq          11
       6: aload_0
       7: invokespecial #16                 // Method getDirStatusFieldBuilder:()Lcom/google/protobuf/SingleFieldBuilder;
      10: pop
      11: return

  private static org.apache.hadoop.hdfs.protocol.proto.HdfsProtos$SnapshottableDirectoryStatusProto$Builder create();
    Code:
       0: new           #6                  // class org/apache/hadoop/hdfs/protocol/proto/HdfsProtos$SnapshottableDirectoryStatusProto$Builder
       3: dup
       4: invokespecial #17                 // Method "<init>":()V
       7: areturn

  public org.apache.hadoop.hdfs.protocol.proto.HdfsProtos$SnapshottableDirectoryStatusProto$Builder clear();
    Code:
       0: aload_0
       1: invokespecial #18                 // Method com/google/protobuf/GeneratedMessage$Builder.clear:()Lcom/google/protobuf/GeneratedMessage$Builder;
       4: pop
       5: aload_0
       6: getfield      #19                 // Field dirStatusBuilder_:Lcom/google/protobuf/SingleFieldBuilder;
       9: ifnonnull     22
      12: aload_0
      13: invokestatic  #9                  // Method org/apache/hadoop/hdfs/protocol/proto/HdfsProtos$HdfsFileStatusProto.getDefaultInstance:()Lorg/apache/hadoop/hdfs/protocol/proto/HdfsProtos$HdfsFileStatusProto;
      16: putfield      #10                 // Field dirStatus_:Lorg/apache/hadoop/hdfs/protocol/proto/HdfsProtos$HdfsFileStatusProto;
      19: goto          30
      22: aload_0
      23: getfield      #19                 // Field dirStatusBuilder_:Lcom/google/protobuf/SingleFieldBuilder;
      26: invokevirtual #20                 // Method com/google/protobuf/SingleFieldBuilder.clear:()Lcom/google/protobuf/SingleFieldBuilder;
      29: pop
      30: aload_0
      31: aload_0
      32: getfield      #21                 // Field bitField0_:I
      35: bipush        -2
      37: iand
      38: putfield      #21                 // Field bitField0_:I
      41: aload_0
      42: iconst_0
      43: putfield      #22                 // Field snapshotQuota_:I
      46: aload_0
      47: aload_0
      48: getfield      #21                 // Field bitField0_:I
      51: bipush        -3
      53: iand
      54: putfield      #21                 // Field bitField0_:I
      57: aload_0
      58: iconst_0
      59: putfield      #23                 // Field snapshotNumber_:I
      62: aload_0
      63: aload_0
      64: getfield      #21                 // Field bitField0_:I
      67: bipush        -5
      69: iand
      70: putfield      #21                 // Field bitField0_:I
      73: aload_0
      74: getstatic     #11                 // Field com/google/protobuf/ByteString.EMPTY:Lcom/google/protobuf/ByteString;
      77: putfield      #12                 // Field parentFullpath_:Lcom/google/protobuf/ByteString;
      80: aload_0
      81: aload_0
      82: getfield      #21                 // Field bitField0_:I
      85: bipush        -9
      87: iand
      88: putfield      #21                 // Field bitField0_:I
      91: aload_0
      92: areturn

  public org.apache.hadoop.hdfs.protocol.proto.HdfsProtos$SnapshottableDirectoryStatusProto$Builder clone();
    Code:
       0: invokestatic  #2                  // Method create:()Lorg/apache/hadoop/hdfs/protocol/proto/HdfsProtos$SnapshottableDirectoryStatusProto$Builder;
       3: aload_0
       4: invokevirtual #24                 // Method buildPartial:()Lorg/apache/hadoop/hdfs/protocol/proto/HdfsProtos$SnapshottableDirectoryStatusProto;
       7: invokevirtual #25                 // Method mergeFrom:(Lorg/apache/hadoop/hdfs/protocol/proto/HdfsProtos$SnapshottableDirectoryStatusProto;)Lorg/apache/hadoop/hdfs/protocol/proto/HdfsProtos$SnapshottableDirectoryStatusProto$Builder;
      10: areturn

  public com.google.protobuf.Descriptors$Descriptor getDescriptorForType();
    Code:
       0: invokestatic  #3                  // Method org/apache/hadoop/hdfs/protocol/proto/HdfsProtos.access$45800:()Lcom/google/protobuf/Descriptors$Descriptor;
       3: areturn

  public org.apache.hadoop.hdfs.protocol.proto.HdfsProtos$SnapshottableDirectoryStatusProto getDefaultInstanceForType();
    Code:
       0: invokestatic  #26                 // Method org/apache/hadoop/hdfs/protocol/proto/HdfsProtos$SnapshottableDirectoryStatusProto.getDefaultInstance:()Lorg/apache/hadoop/hdfs/protocol/proto/HdfsProtos$SnapshottableDirectoryStatusProto;
       3: areturn

  public org.apache.hadoop.hdfs.protocol.proto.HdfsProtos$SnapshottableDirectoryStatusProto build();
    Code:
       0: aload_0
       1: invokevirtual #24                 // Method buildPartial:()Lorg/apache/hadoop/hdfs/protocol/proto/HdfsProtos$SnapshottableDirectoryStatusProto;
       4: astore_1
       5: aload_1
       6: invokevirtual #27                 // Method org/apache/hadoop/hdfs/protocol/proto/HdfsProtos$SnapshottableDirectoryStatusProto.isInitialized:()Z
       9: ifne          17
      12: aload_1
      13: invokestatic  #28                 // Method newUninitializedMessageException:(Lcom/google/protobuf/Message;)Lcom/google/protobuf/UninitializedMessageException;
      16: athrow
      17: aload_1
      18: areturn

  public org.apache.hadoop.hdfs.protocol.proto.HdfsProtos$SnapshottableDirectoryStatusProto buildPartial();
    Code:
       0: new           #5                  // class org/apache/hadoop/hdfs/protocol/proto/HdfsProtos$SnapshottableDirectoryStatusProto
       3: dup
       4: aload_0
       5: aconst_null
       6: invokespecial #29                 // Method org/apache/hadoop/hdfs/protocol/proto/HdfsProtos$SnapshottableDirectoryStatusProto."<init>":(Lcom/google/protobuf/GeneratedMessage$Builder;Lorg/apache/hadoop/hdfs/protocol/proto/HdfsProtos$1;)V
       9: astore_1
      10: aload_0
      11: getfield      #21                 // Field bitField0_:I
      14: istore_2
      15: iconst_0
      16: istore_3
      17: iload_2
      18: iconst_1
      19: iand
      20: iconst_1
      21: if_icmpne     28
      24: iload_3
      25: iconst_1
      26: ior
      27: istore_3
      28: aload_0
      29: getfield      #19                 // Field dirStatusBuilder_:Lcom/google/protobuf/SingleFieldBuilder;
      32: ifnonnull     47
      35: aload_1
      36: aload_0
      37: getfield      #10                 // Field dirStatus_:Lorg/apache/hadoop/hdfs/protocol/proto/HdfsProtos$HdfsFileStatusProto;
      40: invokestatic  #30                 // Method org/apache/hadoop/hdfs/protocol/proto/HdfsProtos$SnapshottableDirectoryStatusProto.access$46502:(Lorg/apache/hadoop/hdfs/protocol/proto/HdfsProtos$SnapshottableDirectoryStatusProto;Lorg/apache/hadoop/hdfs/protocol/proto/HdfsProtos$HdfsFileStatusProto;)Lorg/apache/hadoop/hdfs/protocol/proto/HdfsProtos$HdfsFileStatusProto;
      43: pop
      44: goto          62
      47: aload_1
      48: aload_0
      49: getfield      #19                 // Field dirStatusBuilder_:Lcom/google/protobuf/SingleFieldBuilder;
      52: invokevirtual #31                 // Method com/google/protobuf/SingleFieldBuilder.build:()Lcom/google/protobuf/GeneratedMessage;
      55: checkcast     #32                 // class org/apache/hadoop/hdfs/protocol/proto/HdfsProtos$HdfsFileStatusProto
      58: invokestatic  #30                 // Method org/apache/hadoop/hdfs/protocol/proto/HdfsProtos$SnapshottableDirectoryStatusProto.access$46502:(Lorg/apache/hadoop/hdfs/protocol/proto/HdfsProtos$SnapshottableDirectoryStatusProto;Lorg/apache/hadoop/hdfs/protocol/proto/HdfsProtos$HdfsFileStatusProto;)Lorg/apache/hadoop/hdfs/protocol/proto/HdfsProtos$HdfsFileStatusProto;
      61: pop
      62: iload_2
      63: iconst_2
      64: iand
      65: iconst_2
      66: if_icmpne     73
      69: iload_3
      70: iconst_2
      71: ior
      72: istore_3
      73: aload_1
      74: aload_0
      75: getfield      #22                 // Field snapshotQuota_:I
      78: invokestatic  #33                 // Method org/apache/hadoop/hdfs/protocol/proto/HdfsProtos$SnapshottableDirectoryStatusProto.access$46602:(Lorg/apache/hadoop/hdfs/protocol/proto/HdfsProtos$SnapshottableDirectoryStatusProto;I)I
      81: pop
      82: iload_2
      83: iconst_4
      84: iand
      85: iconst_4
      86: if_icmpne     93
      89: iload_3
      90: iconst_4
      91: ior
      92: istore_3
      93: aload_1
      94: aload_0
      95: getfield      #23                 // Field snapshotNumber_:I
      98: invokestatic  #34                 // Method org/apache/hadoop/hdfs/protocol/proto/HdfsProtos$SnapshottableDirectoryStatusProto.access$46702:(Lorg/apache/hadoop/hdfs/protocol/proto/HdfsProtos$SnapshottableDirectoryStatusProto;I)I
     101: pop
     102: iload_2
     103: bipush        8
     105: iand
     106: bipush        8
     108: if_icmpne     116
     111: iload_3
     112: bipush        8
     114: ior
     115: istore_3
     116: aload_1
     117: aload_0
     118: getfield      #12                 // Field parentFullpath_:Lcom/google/protobuf/ByteString;
     121: invokestatic  #35                 // Method org/apache/hadoop/hdfs/protocol/proto/HdfsProtos$SnapshottableDirectoryStatusProto.access$46802:(Lorg/apache/hadoop/hdfs/protocol/proto/HdfsProtos$SnapshottableDirectoryStatusProto;Lcom/google/protobuf/ByteString;)Lcom/google/protobuf/ByteString;
     124: pop
     125: aload_1
     126: iload_3
     127: invokestatic  #36                 // Method org/apache/hadoop/hdfs/protocol/proto/HdfsProtos$SnapshottableDirectoryStatusProto.access$46902:(Lorg/apache/hadoop/hdfs/protocol/proto/HdfsProtos$SnapshottableDirectoryStatusProto;I)I
     130: pop
     131: aload_0
     132: invokevirtual #37                 // Method onBuilt:()V
     135: aload_1
     136: areturn

  public org.apache.hadoop.hdfs.protocol.proto.HdfsProtos$SnapshottableDirectoryStatusProto$Builder mergeFrom(com.google.protobuf.Message);
    Code:
       0: aload_1
       1: instanceof    #5                  // class org/apache/hadoop/hdfs/protocol/proto/HdfsProtos$SnapshottableDirectoryStatusProto
       4: ifeq          16
       7: aload_0
       8: aload_1
       9: checkcast     #5                  // class org/apache/hadoop/hdfs/protocol/proto/HdfsProtos$SnapshottableDirectoryStatusProto
      12: invokevirtual #25                 // Method mergeFrom:(Lorg/apache/hadoop/hdfs/protocol/proto/HdfsProtos$SnapshottableDirectoryStatusProto;)Lorg/apache/hadoop/hdfs/protocol/proto/HdfsProtos$SnapshottableDirectoryStatusProto$Builder;
      15: areturn
      16: aload_0
      17: aload_1
      18: invokespecial #38                 // Method com/google/protobuf/GeneratedMessage$Builder.mergeFrom:(Lcom/google/protobuf/Message;)Lcom/google/protobuf/AbstractMessage$Builder;
      21: pop
      22: aload_0
      23: areturn

  public org.apache.hadoop.hdfs.protocol.proto.HdfsProtos$SnapshottableDirectoryStatusProto$Builder mergeFrom(org.apache.hadoop.hdfs.protocol.proto.HdfsProtos$SnapshottableDirectoryStatusProto);
    Code:
       0: aload_1
       1: invokestatic  #26                 // Method org/apache/hadoop/hdfs/protocol/proto/HdfsProtos$SnapshottableDirectoryStatusProto.getDefaultInstance:()Lorg/apache/hadoop/hdfs/protocol/proto/HdfsProtos$SnapshottableDirectoryStatusProto;
       4: if_acmpne     9
       7: aload_0
       8: areturn
       9: aload_1
      10: invokevirtual #39                 // Method org/apache/hadoop/hdfs/protocol/proto/HdfsProtos$SnapshottableDirectoryStatusProto.hasDirStatus:()Z
      13: ifeq          25
      16: aload_0
      17: aload_1
      18: invokevirtual #40                 // Method org/apache/hadoop/hdfs/protocol/proto/HdfsProtos$SnapshottableDirectoryStatusProto.getDirStatus:()Lorg/apache/hadoop/hdfs/protocol/proto/HdfsProtos$HdfsFileStatusProto;
      21: invokevirtual #41                 // Method mergeDirStatus:(Lorg/apache/hadoop/hdfs/protocol/proto/HdfsProtos$HdfsFileStatusProto;)Lorg/apache/hadoop/hdfs/protocol/proto/HdfsProtos$SnapshottableDirectoryStatusProto$Builder;
      24: pop
      25: aload_1
      26: invokevirtual #42                 // Method org/apache/hadoop/hdfs/protocol/proto/HdfsProtos$SnapshottableDirectoryStatusProto.hasSnapshotQuota:()Z
      29: ifeq          41
      32: aload_0
      33: aload_1
      34: invokevirtual #43                 // Method org/apache/hadoop/hdfs/protocol/proto/HdfsProtos$SnapshottableDirectoryStatusProto.getSnapshotQuota:()I
      37: invokevirtual #44                 // Method setSnapshotQuota:(I)Lorg/apache/hadoop/hdfs/protocol/proto/HdfsProtos$SnapshottableDirectoryStatusProto$Builder;
      40: pop
      41: aload_1
      42: invokevirtual #45                 // Method org/apache/hadoop/hdfs/protocol/proto/HdfsProtos$SnapshottableDirectoryStatusProto.hasSnapshotNumber:()Z
      45: ifeq          57
      48: aload_0
      49: aload_1
      50: invokevirtual #46                 // Method org/apache/hadoop/hdfs/protocol/proto/HdfsProtos$SnapshottableDirectoryStatusProto.getSnapshotNumber:()I
      53: invokevirtual #47                 // Method setSnapshotNumber:(I)Lorg/apache/hadoop/hdfs/protocol/proto/HdfsProtos$SnapshottableDirectoryStatusProto$Builder;
      56: pop
      57: aload_1
      58: invokevirtual #48                 // Method org/apache/hadoop/hdfs/protocol/proto/HdfsProtos$SnapshottableDirectoryStatusProto.hasParentFullpath:()Z
      61: ifeq          73
      64: aload_0
      65: aload_1
      66: invokevirtual #49                 // Method org/apache/hadoop/hdfs/protocol/proto/HdfsProtos$SnapshottableDirectoryStatusProto.getParentFullpath:()Lcom/google/protobuf/ByteString;
      69: invokevirtual #50                 // Method setParentFullpath:(Lcom/google/protobuf/ByteString;)Lorg/apache/hadoop/hdfs/protocol/proto/HdfsProtos$SnapshottableDirectoryStatusProto$Builder;
      72: pop
      73: aload_0
      74: aload_1
      75: invokevirtual #51                 // Method org/apache/hadoop/hdfs/protocol/proto/HdfsProtos$SnapshottableDirectoryStatusProto.getUnknownFields:()Lcom/google/protobuf/UnknownFieldSet;
      78: invokevirtual #52                 // Method mergeUnknownFields:(Lcom/google/protobuf/UnknownFieldSet;)Lcom/google/protobuf/GeneratedMessage$Builder;
      81: pop
      82: aload_0
      83: areturn

  public final boolean isInitialized();
    Code:
       0: aload_0
       1: invokevirtual #53                 // Method hasDirStatus:()Z
       4: ifne          9
       7: iconst_0
       8: ireturn
       9: aload_0
      10: invokevirtual #54                 // Method hasSnapshotQuota:()Z
      13: ifne          18
      16: iconst_0
      17: ireturn
      18: aload_0
      19: invokevirtual #55                 // Method hasSnapshotNumber:()Z
      22: ifne          27
      25: iconst_0
      26: ireturn
      27: aload_0
      28: invokevirtual #56                 // Method hasParentFullpath:()Z
      31: ifne          36
      34: iconst_0
      35: ireturn
      36: aload_0
      37: invokevirtual #57                 // Method getDirStatus:()Lorg/apache/hadoop/hdfs/protocol/proto/HdfsProtos$HdfsFileStatusProto;
      40: invokevirtual #58                 // Method org/apache/hadoop/hdfs/protocol/proto/HdfsProtos$HdfsFileStatusProto.isInitialized:()Z
      43: ifne          48
      46: iconst_0
      47: ireturn
      48: iconst_1
      49: ireturn

  public org.apache.hadoop.hdfs.protocol.proto.HdfsProtos$SnapshottableDirectoryStatusProto$Builder mergeFrom(com.google.protobuf.CodedInputStream, com.google.protobuf.ExtensionRegistryLite) throws java.io.IOException;
    Code:
       0: aconst_null
       1: astore_3
       2: getstatic     #59                 // Field org/apache/hadoop/hdfs/protocol/proto/HdfsProtos$SnapshottableDirectoryStatusProto.PARSER:Lcom/google/protobuf/Parser;
       5: aload_1
       6: aload_2
       7: invokeinterface #60,  3           // InterfaceMethod com/google/protobuf/Parser.parsePartialFrom:(Lcom/google/protobuf/CodedInputStream;Lcom/google/protobuf/ExtensionRegistryLite;)Ljava/lang/Object;
      12: checkcast     #5                  // class org/apache/hadoop/hdfs/protocol/proto/HdfsProtos$SnapshottableDirectoryStatusProto
      15: astore_3
      16: aload_3
      17: ifnull        58
      20: aload_0
      21: aload_3
      22: invokevirtual #25                 // Method mergeFrom:(Lorg/apache/hadoop/hdfs/protocol/proto/HdfsProtos$SnapshottableDirectoryStatusProto;)Lorg/apache/hadoop/hdfs/protocol/proto/HdfsProtos$SnapshottableDirectoryStatusProto$Builder;
      25: pop
      26: goto          58
      29: astore        4
      31: aload         4
      33: invokevirtual #62                 // Method com/google/protobuf/InvalidProtocolBufferException.getUnfinishedMessage:()Lcom/google/protobuf/MessageLite;
      36: checkcast     #5                  // class org/apache/hadoop/hdfs/protocol/proto/HdfsProtos$SnapshottableDirectoryStatusProto
      39: astore_3
      40: aload         4
      42: athrow
      43: astore        5
      45: aload_3
      46: ifnull        55
      49: aload_0
      50: aload_3
      51: invokevirtual #25                 // Method mergeFrom:(Lorg/apache/hadoop/hdfs/protocol/proto/HdfsProtos$SnapshottableDirectoryStatusProto;)Lorg/apache/hadoop/hdfs/protocol/proto/HdfsProtos$SnapshottableDirectoryStatusProto$Builder;
      54: pop
      55: aload         5
      57: athrow
      58: aload_0
      59: areturn
    Exception table:
       from    to  target type
           2    16    29   Class com/google/protobuf/InvalidProtocolBufferException
           2    16    43   any
          29    45    43   any

  public boolean hasDirStatus();
    Code:
       0: aload_0
       1: getfield      #21                 // Field bitField0_:I
       4: iconst_1
       5: iand
       6: iconst_1
       7: if_icmpne     14
      10: iconst_1
      11: goto          15
      14: iconst_0
      15: ireturn

  public org.apache.hadoop.hdfs.protocol.proto.HdfsProtos$HdfsFileStatusProto getDirStatus();
    Code:
       0: aload_0
       1: getfield      #19                 // Field dirStatusBuilder_:Lcom/google/protobuf/SingleFieldBuilder;
       4: ifnonnull     12
       7: aload_0
       8: getfield      #10                 // Field dirStatus_:Lorg/apache/hadoop/hdfs/protocol/proto/HdfsProtos$HdfsFileStatusProto;
      11: areturn
      12: aload_0
      13: getfield      #19                 // Field dirStatusBuilder_:Lcom/google/protobuf/SingleFieldBuilder;
      16: invokevirtual #63                 // Method com/google/protobuf/SingleFieldBuilder.getMessage:()Lcom/google/protobuf/GeneratedMessage;
      19: checkcast     #32                 // class org/apache/hadoop/hdfs/protocol/proto/HdfsProtos$HdfsFileStatusProto
      22: areturn

  public org.apache.hadoop.hdfs.protocol.proto.HdfsProtos$SnapshottableDirectoryStatusProto$Builder setDirStatus(org.apache.hadoop.hdfs.protocol.proto.HdfsProtos$HdfsFileStatusProto);
    Code:
       0: aload_0
       1: getfield      #19                 // Field dirStatusBuilder_:Lcom/google/protobuf/SingleFieldBuilder;
       4: ifnonnull     31
       7: aload_1
       8: ifnonnull     19
      11: new           #64                 // class java/lang/NullPointerException
      14: dup
      15: invokespecial #65                 // Method java/lang/NullPointerException."<init>":()V
      18: athrow
      19: aload_0
      20: aload_1
      21: putfield      #10                 // Field dirStatus_:Lorg/apache/hadoop/hdfs/protocol/proto/HdfsProtos$HdfsFileStatusProto;
      24: aload_0
      25: invokevirtual #66                 // Method onChanged:()V
      28: goto          40
      31: aload_0
      32: getfield      #19                 // Field dirStatusBuilder_:Lcom/google/protobuf/SingleFieldBuilder;
      35: aload_1
      36: invokevirtual #67                 // Method com/google/protobuf/SingleFieldBuilder.setMessage:(Lcom/google/protobuf/GeneratedMessage;)Lcom/google/protobuf/SingleFieldBuilder;
      39: pop
      40: aload_0
      41: dup
      42: getfield      #21                 // Field bitField0_:I
      45: iconst_1
      46: ior
      47: putfield      #21                 // Field bitField0_:I
      50: aload_0
      51: areturn

  public org.apache.hadoop.hdfs.protocol.proto.HdfsProtos$SnapshottableDirectoryStatusProto$Builder setDirStatus(org.apache.hadoop.hdfs.protocol.proto.HdfsProtos$HdfsFileStatusProto$Builder);
    Code:
       0: aload_0
       1: getfield      #19                 // Field dirStatusBuilder_:Lcom/google/protobuf/SingleFieldBuilder;
       4: ifnonnull     22
       7: aload_0
       8: aload_1
       9: invokevirtual #68                 // Method org/apache/hadoop/hdfs/protocol/proto/HdfsProtos$HdfsFileStatusProto$Builder.build:()Lorg/apache/hadoop/hdfs/protocol/proto/HdfsProtos$HdfsFileStatusProto;
      12: putfield      #10                 // Field dirStatus_:Lorg/apache/hadoop/hdfs/protocol/proto/HdfsProtos$HdfsFileStatusProto;
      15: aload_0
      16: invokevirtual #66                 // Method onChanged:()V
      19: goto          34
      22: aload_0
      23: getfield      #19                 // Field dirStatusBuilder_:Lcom/google/protobuf/SingleFieldBuilder;
      26: aload_1
      27: invokevirtual #68                 // Method org/apache/hadoop/hdfs/protocol/proto/HdfsProtos$HdfsFileStatusProto$Builder.build:()Lorg/apache/hadoop/hdfs/protocol/proto/HdfsProtos$HdfsFileStatusProto;
      30: invokevirtual #67                 // Method com/google/protobuf/SingleFieldBuilder.setMessage:(Lcom/google/protobuf/GeneratedMessage;)Lcom/google/protobuf/SingleFieldBuilder;
      33: pop
      34: aload_0
      35: dup
      36: getfield      #21                 // Field bitField0_:I
      39: iconst_1
      40: ior
      41: putfield      #21                 // Field bitField0_:I
      44: aload_0
      45: areturn

  public org.apache.hadoop.hdfs.protocol.proto.HdfsProtos$SnapshottableDirectoryStatusProto$Builder mergeDirStatus(org.apache.hadoop.hdfs.protocol.proto.HdfsProtos$HdfsFileStatusProto);
    Code:
       0: aload_0
       1: getfield      #19                 // Field dirStatusBuilder_:Lcom/google/protobuf/SingleFieldBuilder;
       4: ifnonnull     60
       7: aload_0
       8: getfield      #21                 // Field bitField0_:I
      11: iconst_1
      12: iand
      13: iconst_1
      14: if_icmpne     48
      17: aload_0
      18: getfield      #10                 // Field dirStatus_:Lorg/apache/hadoop/hdfs/protocol/proto/HdfsProtos$HdfsFileStatusProto;
      21: invokestatic  #9                  // Method org/apache/hadoop/hdfs/protocol/proto/HdfsProtos$HdfsFileStatusProto.getDefaultInstance:()Lorg/apache/hadoop/hdfs/protocol/proto/HdfsProtos$HdfsFileStatusProto;
      24: if_acmpeq     48
      27: aload_0
      28: aload_0
      29: getfield      #10                 // Field dirStatus_:Lorg/apache/hadoop/hdfs/protocol/proto/HdfsProtos$HdfsFileStatusProto;
      32: invokestatic  #69                 // Method org/apache/hadoop/hdfs/protocol/proto/HdfsProtos$HdfsFileStatusProto.newBuilder:(Lorg/apache/hadoop/hdfs/protocol/proto/HdfsProtos$HdfsFileStatusProto;)Lorg/apache/hadoop/hdfs/protocol/proto/HdfsProtos$HdfsFileStatusProto$Builder;
      35: aload_1
      36: invokevirtual #70                 // Method org/apache/hadoop/hdfs/protocol/proto/HdfsProtos$HdfsFileStatusProto$Builder.mergeFrom:(Lorg/apache/hadoop/hdfs/protocol/proto/HdfsProtos$HdfsFileStatusProto;)Lorg/apache/hadoop/hdfs/protocol/proto/HdfsProtos$HdfsFileStatusProto$Builder;
      39: invokevirtual #71                 // Method org/apache/hadoop/hdfs/protocol/proto/HdfsProtos$HdfsFileStatusProto$Builder.buildPartial:()Lorg/apache/hadoop/hdfs/protocol/proto/HdfsProtos$HdfsFileStatusProto;
      42: putfield      #10                 // Field dirStatus_:Lorg/apache/hadoop/hdfs/protocol/proto/HdfsProtos$HdfsFileStatusProto;
      45: goto          53
      48: aload_0
      49: aload_1
      50: putfield      #10                 // Field dirStatus_:Lorg/apache/hadoop/hdfs/protocol/proto/HdfsProtos$HdfsFileStatusProto;
      53: aload_0
      54: invokevirtual #66                 // Method onChanged:()V
      57: goto          69
      60: aload_0
      61: getfield      #19                 // Field dirStatusBuilder_:Lcom/google/protobuf/SingleFieldBuilder;
      64: aload_1
      65: invokevirtual #72                 // Method com/google/protobuf/SingleFieldBuilder.mergeFrom:(Lcom/google/protobuf/GeneratedMessage;)Lcom/google/protobuf/SingleFieldBuilder;
      68: pop
      69: aload_0
      70: dup
      71: getfield      #21                 // Field bitField0_:I
      74: iconst_1
      75: ior
      76: putfield      #21                 // Field bitField0_:I
      79: aload_0
      80: areturn

  public org.apache.hadoop.hdfs.protocol.proto.HdfsProtos$SnapshottableDirectoryStatusProto$Builder clearDirStatus();
    Code:
       0: aload_0
       1: getfield      #19                 // Field dirStatusBuilder_:Lcom/google/protobuf/SingleFieldBuilder;
       4: ifnonnull     21
       7: aload_0
       8: invokestatic  #9                  // Method org/apache/hadoop/hdfs/protocol/proto/HdfsProtos$HdfsFileStatusProto.getDefaultInstance:()Lorg/apache/hadoop/hdfs/protocol/proto/HdfsProtos$HdfsFileStatusProto;
      11: putfield      #10                 // Field dirStatus_:Lorg/apache/hadoop/hdfs/protocol/proto/HdfsProtos$HdfsFileStatusProto;
      14: aload_0
      15: invokevirtual #66                 // Method onChanged:()V
      18: goto          29
      21: aload_0
      22: getfield      #19                 // Field dirStatusBuilder_:Lcom/google/protobuf/SingleFieldBuilder;
      25: invokevirtual #20                 // Method com/google/protobuf/SingleFieldBuilder.clear:()Lcom/google/protobuf/SingleFieldBuilder;
      28: pop
      29: aload_0
      30: aload_0
      31: getfield      #21                 // Field bitField0_:I
      34: bipush        -2
      36: iand
      37: putfield      #21                 // Field bitField0_:I
      40: aload_0
      41: areturn

  public org.apache.hadoop.hdfs.protocol.proto.HdfsProtos$HdfsFileStatusProto$Builder getDirStatusBuilder();
    Code:
       0: aload_0
       1: dup
       2: getfield      #21                 // Field bitField0_:I
       5: iconst_1
       6: ior
       7: putfield      #21                 // Field bitField0_:I
      10: aload_0
      11: invokevirtual #66                 // Method onChanged:()V
      14: aload_0
      15: invokespecial #16                 // Method getDirStatusFieldBuilder:()Lcom/google/protobuf/SingleFieldBuilder;
      18: invokevirtual #73                 // Method com/google/protobuf/SingleFieldBuilder.getBuilder:()Lcom/google/protobuf/GeneratedMessage$Builder;
      21: checkcast     #74                 // class org/apache/hadoop/hdfs/protocol/proto/HdfsProtos$HdfsFileStatusProto$Builder
      24: areturn

  public org.apache.hadoop.hdfs.protocol.proto.HdfsProtos$HdfsFileStatusProtoOrBuilder getDirStatusOrBuilder();
    Code:
       0: aload_0
       1: getfield      #19                 // Field dirStatusBuilder_:Lcom/google/protobuf/SingleFieldBuilder;
       4: ifnull        18
       7: aload_0
       8: getfield      #19                 // Field dirStatusBuilder_:Lcom/google/protobuf/SingleFieldBuilder;
      11: invokevirtual #75                 // Method com/google/protobuf/SingleFieldBuilder.getMessageOrBuilder:()Lcom/google/protobuf/MessageOrBuilder;
      14: checkcast     #76                 // class org/apache/hadoop/hdfs/protocol/proto/HdfsProtos$HdfsFileStatusProtoOrBuilder
      17: areturn
      18: aload_0
      19: getfield      #10                 // Field dirStatus_:Lorg/apache/hadoop/hdfs/protocol/proto/HdfsProtos$HdfsFileStatusProto;
      22: areturn

  private com.google.protobuf.SingleFieldBuilder<org.apache.hadoop.hdfs.protocol.proto.HdfsProtos$HdfsFileStatusProto, org.apache.hadoop.hdfs.protocol.proto.HdfsProtos$HdfsFileStatusProto$Builder, org.apache.hadoop.hdfs.protocol.proto.HdfsProtos$HdfsFileStatusProtoOrBuilder> getDirStatusFieldBuilder();
    Code:
       0: aload_0
       1: getfield      #19                 // Field dirStatusBuilder_:Lcom/google/protobuf/SingleFieldBuilder;
       4: ifnonnull     35
       7: aload_0
       8: new           #77                 // class com/google/protobuf/SingleFieldBuilder
      11: dup
      12: aload_0
      13: getfield      #10                 // Field dirStatus_:Lorg/apache/hadoop/hdfs/protocol/proto/HdfsProtos$HdfsFileStatusProto;
      16: aload_0
      17: invokevirtual #78                 // Method getParentForChildren:()Lcom/google/protobuf/GeneratedMessage$BuilderParent;
      20: aload_0
      21: invokevirtual #79                 // Method isClean:()Z
      24: invokespecial #80                 // Method com/google/protobuf/SingleFieldBuilder."<init>":(Lcom/google/protobuf/GeneratedMessage;Lcom/google/protobuf/GeneratedMessage$BuilderParent;Z)V
      27: putfield      #19                 // Field dirStatusBuilder_:Lcom/google/protobuf/SingleFieldBuilder;
      30: aload_0
      31: aconst_null
      32: putfield      #10                 // Field dirStatus_:Lorg/apache/hadoop/hdfs/protocol/proto/HdfsProtos$HdfsFileStatusProto;
      35: aload_0
      36: getfield      #19                 // Field dirStatusBuilder_:Lcom/google/protobuf/SingleFieldBuilder;
      39: areturn

  public boolean hasSnapshotQuota();
    Code:
       0: aload_0
       1: getfield      #21                 // Field bitField0_:I
       4: iconst_2
       5: iand
       6: iconst_2
       7: if_icmpne     14
      10: iconst_1
      11: goto          15
      14: iconst_0
      15: ireturn

  public int getSnapshotQuota();
    Code:
       0: aload_0
       1: getfield      #22                 // Field snapshotQuota_:I
       4: ireturn

  public org.apache.hadoop.hdfs.protocol.proto.HdfsProtos$SnapshottableDirectoryStatusProto$Builder setSnapshotQuota(int);
    Code:
       0: aload_0
       1: dup
       2: getfield      #21                 // Field bitField0_:I
       5: iconst_2
       6: ior
       7: putfield      #21                 // Field bitField0_:I
      10: aload_0
      11: iload_1
      12: putfield      #22                 // Field snapshotQuota_:I
      15: aload_0
      16: invokevirtual #66                 // Method onChanged:()V
      19: aload_0
      20: areturn

  public org.apache.hadoop.hdfs.protocol.proto.HdfsProtos$SnapshottableDirectoryStatusProto$Builder clearSnapshotQuota();
    Code:
       0: aload_0
       1: aload_0
       2: getfield      #21                 // Field bitField0_:I
       5: bipush        -3
       7: iand
       8: putfield      #21                 // Field bitField0_:I
      11: aload_0
      12: iconst_0
      13: putfield      #22                 // Field snapshotQuota_:I
      16: aload_0
      17: invokevirtual #66                 // Method onChanged:()V
      20: aload_0
      21: areturn

  public boolean hasSnapshotNumber();
    Code:
       0: aload_0
       1: getfield      #21                 // Field bitField0_:I
       4: iconst_4
       5: iand
       6: iconst_4
       7: if_icmpne     14
      10: iconst_1
      11: goto          15
      14: iconst_0
      15: ireturn

  public int getSnapshotNumber();
    Code:
       0: aload_0
       1: getfield      #23                 // Field snapshotNumber_:I
       4: ireturn

  public org.apache.hadoop.hdfs.protocol.proto.HdfsProtos$SnapshottableDirectoryStatusProto$Builder setSnapshotNumber(int);
    Code:
       0: aload_0
       1: dup
       2: getfield      #21                 // Field bitField0_:I
       5: iconst_4
       6: ior
       7: putfield      #21                 // Field bitField0_:I
      10: aload_0
      11: iload_1
      12: putfield      #23                 // Field snapshotNumber_:I
      15: aload_0
      16: invokevirtual #66                 // Method onChanged:()V
      19: aload_0
      20: areturn

  public org.apache.hadoop.hdfs.protocol.proto.HdfsProtos$SnapshottableDirectoryStatusProto$Builder clearSnapshotNumber();
    Code:
       0: aload_0
       1: aload_0
       2: getfield      #21                 // Field bitField0_:I
       5: bipush        -5
       7: iand
       8: putfield      #21                 // Field bitField0_:I
      11: aload_0
      12: iconst_0
      13: putfield      #23                 // Field snapshotNumber_:I
      16: aload_0
      17: invokevirtual #66                 // Method onChanged:()V
      20: aload_0
      21: areturn

  public boolean hasParentFullpath();
    Code:
       0: aload_0
       1: getfield      #21                 // Field bitField0_:I
       4: bipush        8
       6: iand
       7: bipush        8
       9: if_icmpne     16
      12: iconst_1
      13: goto          17
      16: iconst_0
      17: ireturn

  public com.google.protobuf.ByteString getParentFullpath();
    Code:
       0: aload_0
       1: getfield      #12                 // Field parentFullpath_:Lcom/google/protobuf/ByteString;
       4: areturn

  public org.apache.hadoop.hdfs.protocol.proto.HdfsProtos$SnapshottableDirectoryStatusProto$Builder setParentFullpath(com.google.protobuf.ByteString);
    Code:
       0: aload_1
       1: ifnonnull     12
       4: new           #64                 // class java/lang/NullPointerException
       7: dup
       8: invokespecial #65                 // Method java/lang/NullPointerException."<init>":()V
      11: athrow
      12: aload_0
      13: dup
      14: getfield      #21                 // Field bitField0_:I
      17: bipush        8
      19: ior
      20: putfield      #21                 // Field bitField0_:I
      23: aload_0
      24: aload_1
      25: putfield      #12                 // Field parentFullpath_:Lcom/google/protobuf/ByteString;
      28: aload_0
      29: invokevirtual #66                 // Method onChanged:()V
      32: aload_0
      33: areturn

  public org.apache.hadoop.hdfs.protocol.proto.HdfsProtos$SnapshottableDirectoryStatusProto$Builder clearParentFullpath();
    Code:
       0: aload_0
       1: aload_0
       2: getfield      #21                 // Field bitField0_:I
       5: bipush        -9
       7: iand
       8: putfield      #21                 // Field bitField0_:I
      11: aload_0
      12: invokestatic  #26                 // Method org/apache/hadoop/hdfs/protocol/proto/HdfsProtos$SnapshottableDirectoryStatusProto.getDefaultInstance:()Lorg/apache/hadoop/hdfs/protocol/proto/HdfsProtos$SnapshottableDirectoryStatusProto;
      15: invokevirtual #49                 // Method org/apache/hadoop/hdfs/protocol/proto/HdfsProtos$SnapshottableDirectoryStatusProto.getParentFullpath:()Lcom/google/protobuf/ByteString;
      18: putfield      #12                 // Field parentFullpath_:Lcom/google/protobuf/ByteString;
      21: aload_0
      22: invokevirtual #66                 // Method onChanged:()V
      25: aload_0
      26: areturn

  public com.google.protobuf.GeneratedMessage$Builder clear();
    Code:
       0: aload_0
       1: invokevirtual #81                 // Method clear:()Lorg/apache/hadoop/hdfs/protocol/proto/HdfsProtos$SnapshottableDirectoryStatusProto$Builder;
       4: areturn

  public com.google.protobuf.GeneratedMessage$Builder clone();
    Code:
       0: aload_0
       1: invokevirtual #82                 // Method clone:()Lorg/apache/hadoop/hdfs/protocol/proto/HdfsProtos$SnapshottableDirectoryStatusProto$Builder;
       4: areturn

  public com.google.protobuf.AbstractMessage$Builder mergeFrom(com.google.protobuf.CodedInputStream, com.google.protobuf.ExtensionRegistryLite) throws java.io.IOException;
    Code:
       0: aload_0
       1: aload_1
       2: aload_2
       3: invokevirtual #83                 // Method mergeFrom:(Lcom/google/protobuf/CodedInputStream;Lcom/google/protobuf/ExtensionRegistryLite;)Lorg/apache/hadoop/hdfs/protocol/proto/HdfsProtos$SnapshottableDirectoryStatusProto$Builder;
       6: areturn

  public com.google.protobuf.AbstractMessage$Builder mergeFrom(com.google.protobuf.Message);
    Code:
       0: aload_0
       1: aload_1
       2: invokevirtual #84                 // Method mergeFrom:(Lcom/google/protobuf/Message;)Lorg/apache/hadoop/hdfs/protocol/proto/HdfsProtos$SnapshottableDirectoryStatusProto$Builder;
       5: areturn

  public com.google.protobuf.AbstractMessage$Builder clear();
    Code:
       0: aload_0
       1: invokevirtual #81                 // Method clear:()Lorg/apache/hadoop/hdfs/protocol/proto/HdfsProtos$SnapshottableDirectoryStatusProto$Builder;
       4: areturn

  public com.google.protobuf.AbstractMessage$Builder clone();
    Code:
       0: aload_0
       1: invokevirtual #82                 // Method clone:()Lorg/apache/hadoop/hdfs/protocol/proto/HdfsProtos$SnapshottableDirectoryStatusProto$Builder;
       4: areturn

  public com.google.protobuf.Message$Builder mergeFrom(com.google.protobuf.CodedInputStream, com.google.protobuf.ExtensionRegistryLite) throws java.io.IOException;
    Code:
       0: aload_0
       1: aload_1
       2: aload_2
       3: invokevirtual #83                 // Method mergeFrom:(Lcom/google/protobuf/CodedInputStream;Lcom/google/protobuf/ExtensionRegistryLite;)Lorg/apache/hadoop/hdfs/protocol/proto/HdfsProtos$SnapshottableDirectoryStatusProto$Builder;
       6: areturn

  public com.google.protobuf.Message$Builder clone();
    Code:
       0: aload_0
       1: invokevirtual #82                 // Method clone:()Lorg/apache/hadoop/hdfs/protocol/proto/HdfsProtos$SnapshottableDirectoryStatusProto$Builder;
       4: areturn

  public com.google.protobuf.Message buildPartial();
    Code:
       0: aload_0
       1: invokevirtual #24                 // Method buildPartial:()Lorg/apache/hadoop/hdfs/protocol/proto/HdfsProtos$SnapshottableDirectoryStatusProto;
       4: areturn

  public com.google.protobuf.Message build();
    Code:
       0: aload_0
       1: invokevirtual #85                 // Method build:()Lorg/apache/hadoop/hdfs/protocol/proto/HdfsProtos$SnapshottableDirectoryStatusProto;
       4: areturn

  public com.google.protobuf.Message$Builder mergeFrom(com.google.protobuf.Message);
    Code:
       0: aload_0
       1: aload_1
       2: invokevirtual #84                 // Method mergeFrom:(Lcom/google/protobuf/Message;)Lorg/apache/hadoop/hdfs/protocol/proto/HdfsProtos$SnapshottableDirectoryStatusProto$Builder;
       5: areturn

  public com.google.protobuf.Message$Builder clear();
    Code:
       0: aload_0
       1: invokevirtual #81                 // Method clear:()Lorg/apache/hadoop/hdfs/protocol/proto/HdfsProtos$SnapshottableDirectoryStatusProto$Builder;
       4: areturn

  public com.google.protobuf.MessageLite$Builder mergeFrom(com.google.protobuf.CodedInputStream, com.google.protobuf.ExtensionRegistryLite) throws java.io.IOException;
    Code:
       0: aload_0
       1: aload_1
       2: aload_2
       3: invokevirtual #83                 // Method mergeFrom:(Lcom/google/protobuf/CodedInputStream;Lcom/google/protobuf/ExtensionRegistryLite;)Lorg/apache/hadoop/hdfs/protocol/proto/HdfsProtos$SnapshottableDirectoryStatusProto$Builder;
       6: areturn

  public com.google.protobuf.MessageLite$Builder clone();
    Code:
       0: aload_0
       1: invokevirtual #82                 // Method clone:()Lorg/apache/hadoop/hdfs/protocol/proto/HdfsProtos$SnapshottableDirectoryStatusProto$Builder;
       4: areturn

  public com.google.protobuf.MessageLite buildPartial();
    Code:
       0: aload_0
       1: invokevirtual #24                 // Method buildPartial:()Lorg/apache/hadoop/hdfs/protocol/proto/HdfsProtos$SnapshottableDirectoryStatusProto;
       4: areturn

  public com.google.protobuf.MessageLite build();
    Code:
       0: aload_0
       1: invokevirtual #85                 // Method build:()Lorg/apache/hadoop/hdfs/protocol/proto/HdfsProtos$SnapshottableDirectoryStatusProto;
       4: areturn

  public com.google.protobuf.MessageLite$Builder clear();
    Code:
       0: aload_0
       1: invokevirtual #81                 // Method clear:()Lorg/apache/hadoop/hdfs/protocol/proto/HdfsProtos$SnapshottableDirectoryStatusProto$Builder;
       4: areturn

  public com.google.protobuf.MessageLite getDefaultInstanceForType();
    Code:
       0: aload_0
       1: invokevirtual #86                 // Method getDefaultInstanceForType:()Lorg/apache/hadoop/hdfs/protocol/proto/HdfsProtos$SnapshottableDirectoryStatusProto;
       4: areturn

  public com.google.protobuf.Message getDefaultInstanceForType();
    Code:
       0: aload_0
       1: invokevirtual #86                 // Method getDefaultInstanceForType:()Lorg/apache/hadoop/hdfs/protocol/proto/HdfsProtos$SnapshottableDirectoryStatusProto;
       4: areturn

  public com.google.protobuf.AbstractMessageLite$Builder mergeFrom(com.google.protobuf.CodedInputStream, com.google.protobuf.ExtensionRegistryLite) throws java.io.IOException;
    Code:
       0: aload_0
       1: aload_1
       2: aload_2
       3: invokevirtual #83                 // Method mergeFrom:(Lcom/google/protobuf/CodedInputStream;Lcom/google/protobuf/ExtensionRegistryLite;)Lorg/apache/hadoop/hdfs/protocol/proto/HdfsProtos$SnapshottableDirectoryStatusProto$Builder;
       6: areturn

  public com.google.protobuf.AbstractMessageLite$Builder clone();
    Code:
       0: aload_0
       1: invokevirtual #82                 // Method clone:()Lorg/apache/hadoop/hdfs/protocol/proto/HdfsProtos$SnapshottableDirectoryStatusProto$Builder;
       4: areturn

  public java.lang.Object clone() throws java.lang.CloneNotSupportedException;
    Code:
       0: aload_0
       1: invokevirtual #82                 // Method clone:()Lorg/apache/hadoop/hdfs/protocol/proto/HdfsProtos$SnapshottableDirectoryStatusProto$Builder;
       4: areturn

  static org.apache.hadoop.hdfs.protocol.proto.HdfsProtos$SnapshottableDirectoryStatusProto$Builder access$46100();
    Code:
       0: invokestatic  #2                  // Method create:()Lorg/apache/hadoop/hdfs/protocol/proto/HdfsProtos$SnapshottableDirectoryStatusProto$Builder;
       3: areturn

  org.apache.hadoop.hdfs.protocol.proto.HdfsProtos$SnapshottableDirectoryStatusProto$Builder(com.google.protobuf.GeneratedMessage$BuilderParent, org.apache.hadoop.hdfs.protocol.proto.HdfsProtos$1);
    Code:
       0: aload_0
       1: aload_1
       2: invokespecial #1                  // Method "<init>":(Lcom/google/protobuf/GeneratedMessage$BuilderParent;)V
       5: return
}
