Compiled from "JsonParserFactoryImpl.java"
class org.glassfish.json.JsonParserFactoryImpl implements javax.json.stream.JsonParserFactory {
  private final java.util.Map<java.lang.String, ?> config;

  private final org.glassfish.json.api.BufferPool bufferPool;

  org.glassfish.json.JsonParserFactoryImpl(org.glassfish.json.api.BufferPool);
    Code:
       0: aload_0
       1: invokespecial #1                  // Method java/lang/Object."<init>":()V
       4: aload_0
       5: invokestatic  #2                  // Method java/util/Collections.emptyMap:()Ljava/util/Map;
       8: putfield      #3                  // Field config:Ljava/util/Map;
      11: aload_0
      12: aload_1
      13: putfield      #4                  // Field bufferPool:Lorg/glassfish/json/api/BufferPool;
      16: return

  public javax.json.stream.JsonParser createParser(java.io.Reader);
    Code:
       0: new           #5                  // class org/glassfish/json/JsonParserImpl
       3: dup
       4: aload_1
       5: aload_0
       6: getfield      #4                  // Field bufferPool:Lorg/glassfish/json/api/BufferPool;
       9: invokespecial #6                  // Method org/glassfish/json/JsonParserImpl."<init>":(Ljava/io/Reader;Lorg/glassfish/json/api/BufferPool;)V
      12: areturn

  public javax.json.stream.JsonParser createParser(java.io.InputStream);
    Code:
       0: new           #5                  // class org/glassfish/json/JsonParserImpl
       3: dup
       4: aload_1
       5: aload_0
       6: getfield      #4                  // Field bufferPool:Lorg/glassfish/json/api/BufferPool;
       9: invokespecial #7                  // Method org/glassfish/json/JsonParserImpl."<init>":(Ljava/io/InputStream;Lorg/glassfish/json/api/BufferPool;)V
      12: areturn

  public javax.json.stream.JsonParser createParser(java.io.InputStream, java.nio.charset.Charset);
    Code:
       0: new           #5                  // class org/glassfish/json/JsonParserImpl
       3: dup
       4: aload_1
       5: aload_2
       6: aload_0
       7: getfield      #4                  // Field bufferPool:Lorg/glassfish/json/api/BufferPool;
      10: invokespecial #8                  // Method org/glassfish/json/JsonParserImpl."<init>":(Ljava/io/InputStream;Ljava/nio/charset/Charset;Lorg/glassfish/json/api/BufferPool;)V
      13: areturn

  public javax.json.stream.JsonParser createParser(javax.json.JsonArray);
    Code:
       0: new           #9                  // class org/glassfish/json/JsonStructureParser
       3: dup
       4: aload_1
       5: invokespecial #10                 // Method org/glassfish/json/JsonStructureParser."<init>":(Ljavax/json/JsonArray;)V
       8: areturn

  public java.util.Map<java.lang.String, ?> getConfigInUse();
    Code:
       0: aload_0
       1: getfield      #3                  // Field config:Ljava/util/Map;
       4: areturn

  public javax.json.stream.JsonParser createParser(javax.json.JsonObject);
    Code:
       0: new           #9                  // class org/glassfish/json/JsonStructureParser
       3: dup
       4: aload_1
       5: invokespecial #11                 // Method org/glassfish/json/JsonStructureParser."<init>":(Ljavax/json/JsonObject;)V
       8: areturn
}
