Compiled from "SourceFile.java"
public class org.sonar.squid.api.SourceFile extends org.sonar.squid.api.SourceCode {
  private java.util.Set<java.lang.Integer> noSonarTagLines;

  public org.sonar.squid.api.SourceFile(java.lang.String);
    Code:
       0: aload_0
       1: aload_1
       2: invokespecial #1                  // Method org/sonar/squid/api/SourceCode."<init>":(Ljava/lang/String;)V
       5: aload_0
       6: new           #2                  // class java/util/HashSet
       9: dup
      10: invokespecial #3                  // Method java/util/HashSet."<init>":()V
      13: putfield      #4                  // Field noSonarTagLines:Ljava/util/Set;
      16: aload_0
      17: iconst_1
      18: invokevirtual #5                  // Method setStartAtLine:(I)V
      21: return

  public org.sonar.squid.api.SourceFile(java.lang.String, java.lang.String);
    Code:
       0: aload_0
       1: aload_1
       2: aload_2
       3: invokespecial #6                  // Method org/sonar/squid/api/SourceCode."<init>":(Ljava/lang/String;Ljava/lang/String;)V
       6: aload_0
       7: new           #2                  // class java/util/HashSet
      10: dup
      11: invokespecial #3                  // Method java/util/HashSet."<init>":()V
      14: putfield      #4                  // Field noSonarTagLines:Ljava/util/Set;
      17: aload_0
      18: iconst_1
      19: invokevirtual #5                  // Method setStartAtLine:(I)V
      22: return

  public java.util.Set<java.lang.Integer> getNoSonarTagLines();
    Code:
       0: aload_0
       1: getfield      #4                  // Field noSonarTagLines:Ljava/util/Set;
       4: areturn

  public boolean hasNoSonarTagAtLine(int);
    Code:
       0: aload_0
       1: getfield      #4                  // Field noSonarTagLines:Ljava/util/Set;
       4: iload_1
       5: invokestatic  #7                  // Method java/lang/Integer.valueOf:(I)Ljava/lang/Integer;
       8: invokeinterface #8,  2            // InterfaceMethod java/util/Set.contains:(Ljava/lang/Object;)Z
      13: ireturn

  public void addNoSonarTagLines(java.util.Set<java.lang.Integer>);
    Code:
       0: aload_0
       1: getfield      #4                  // Field noSonarTagLines:Ljava/util/Set;
       4: aload_1
       5: invokeinterface #9,  2            // InterfaceMethod java/util/Set.addAll:(Ljava/util/Collection;)Z
      10: pop
      11: return

  public void addNoSonarTagLine(int);
    Code:
       0: aload_0
       1: getfield      #4                  // Field noSonarTagLines:Ljava/util/Set;
       4: iload_1
       5: invokestatic  #7                  // Method java/lang/Integer.valueOf:(I)Ljava/lang/Integer;
       8: invokeinterface #10,  2           // InterfaceMethod java/util/Set.add:(Ljava/lang/Object;)Z
      13: pop
      14: return
}
