Compiled from "Model.java"
public class org.apache.maven.model.Model extends org.apache.maven.model.ModelBase implements java.io.Serializable,java.lang.Cloneable {
  private java.lang.String modelVersion;

  private org.apache.maven.model.Parent parent;

  private java.lang.String groupId;

  private java.lang.String artifactId;

  private java.lang.String version;

  private java.lang.String packaging;

  private java.lang.String name;

  private java.lang.String description;

  private java.lang.String url;

  private java.lang.String inceptionYear;

  private org.apache.maven.model.Organization organization;

  private java.util.List<org.apache.maven.model.License> licenses;

  private java.util.List<org.apache.maven.model.Developer> developers;

  private java.util.List<org.apache.maven.model.Contributor> contributors;

  private java.util.List<org.apache.maven.model.MailingList> mailingLists;

  private org.apache.maven.model.Prerequisites prerequisites;

  private org.apache.maven.model.Scm scm;

  private org.apache.maven.model.IssueManagement issueManagement;

  private org.apache.maven.model.CiManagement ciManagement;

  private org.apache.maven.model.Build build;

  private java.util.List<org.apache.maven.model.Profile> profiles;

  private java.lang.String modelEncoding;

  private java.io.File pomFile;

  public org.apache.maven.model.Model();
    Code:
       0: aload_0
       1: invokespecial #1                  // Method org/apache/maven/model/ModelBase."<init>":()V
       4: aload_0
       5: ldc           #2                  // String jar
       7: putfield      #3                  // Field packaging:Ljava/lang/String;
      10: aload_0
      11: ldc           #4                  // String UTF-8
      13: putfield      #5                  // Field modelEncoding:Ljava/lang/String;
      16: return

  public void addContributor(org.apache.maven.model.Contributor);
    Code:
       0: aload_0
       1: invokevirtual #6                  // Method getContributors:()Ljava/util/List;
       4: aload_1
       5: invokeinterface #7,  2            // InterfaceMethod java/util/List.add:(Ljava/lang/Object;)Z
      10: pop
      11: return

  public void addDeveloper(org.apache.maven.model.Developer);
    Code:
       0: aload_0
       1: invokevirtual #8                  // Method getDevelopers:()Ljava/util/List;
       4: aload_1
       5: invokeinterface #7,  2            // InterfaceMethod java/util/List.add:(Ljava/lang/Object;)Z
      10: pop
      11: return

  public void addLicense(org.apache.maven.model.License);
    Code:
       0: aload_0
       1: invokevirtual #9                  // Method getLicenses:()Ljava/util/List;
       4: aload_1
       5: invokeinterface #7,  2            // InterfaceMethod java/util/List.add:(Ljava/lang/Object;)Z
      10: pop
      11: return

  public void addMailingList(org.apache.maven.model.MailingList);
    Code:
       0: aload_0
       1: invokevirtual #10                 // Method getMailingLists:()Ljava/util/List;
       4: aload_1
       5: invokeinterface #7,  2            // InterfaceMethod java/util/List.add:(Ljava/lang/Object;)Z
      10: pop
      11: return

  public void addProfile(org.apache.maven.model.Profile);
    Code:
       0: aload_0
       1: invokevirtual #11                 // Method getProfiles:()Ljava/util/List;
       4: aload_1
       5: invokeinterface #7,  2            // InterfaceMethod java/util/List.add:(Ljava/lang/Object;)Z
      10: pop
      11: return

  public org.apache.maven.model.Model clone();
    Code:
       0: aload_0
       1: invokespecial #12                 // Method org/apache/maven/model/ModelBase.clone:()Lorg/apache/maven/model/ModelBase;
       4: checkcast     #13                 // class org/apache/maven/model/Model
       7: astore_1
       8: aload_0
       9: getfield      #14                 // Field parent:Lorg/apache/maven/model/Parent;
      12: ifnull        26
      15: aload_1
      16: aload_0
      17: getfield      #14                 // Field parent:Lorg/apache/maven/model/Parent;
      20: invokevirtual #15                 // Method org/apache/maven/model/Parent.clone:()Lorg/apache/maven/model/Parent;
      23: putfield      #14                 // Field parent:Lorg/apache/maven/model/Parent;
      26: aload_0
      27: getfield      #16                 // Field organization:Lorg/apache/maven/model/Organization;
      30: ifnull        44
      33: aload_1
      34: aload_0
      35: getfield      #16                 // Field organization:Lorg/apache/maven/model/Organization;
      38: invokevirtual #17                 // Method org/apache/maven/model/Organization.clone:()Lorg/apache/maven/model/Organization;
      41: putfield      #16                 // Field organization:Lorg/apache/maven/model/Organization;
      44: aload_0
      45: getfield      #18                 // Field licenses:Ljava/util/List;
      48: ifnull        108
      51: aload_1
      52: new           #19                 // class java/util/ArrayList
      55: dup
      56: invokespecial #20                 // Method java/util/ArrayList."<init>":()V
      59: putfield      #18                 // Field licenses:Ljava/util/List;
      62: aload_0
      63: getfield      #18                 // Field licenses:Ljava/util/List;
      66: invokeinterface #21,  1           // InterfaceMethod java/util/List.iterator:()Ljava/util/Iterator;
      71: astore_2
      72: aload_2
      73: invokeinterface #22,  1           // InterfaceMethod java/util/Iterator.hasNext:()Z
      78: ifeq          108
      81: aload_2
      82: invokeinterface #23,  1           // InterfaceMethod java/util/Iterator.next:()Ljava/lang/Object;
      87: checkcast     #24                 // class org/apache/maven/model/License
      90: astore_3
      91: aload_1
      92: getfield      #18                 // Field licenses:Ljava/util/List;
      95: aload_3
      96: invokevirtual #25                 // Method org/apache/maven/model/License.clone:()Lorg/apache/maven/model/License;
      99: invokeinterface #7,  2            // InterfaceMethod java/util/List.add:(Ljava/lang/Object;)Z
     104: pop
     105: goto          72
     108: aload_0
     109: getfield      #26                 // Field developers:Ljava/util/List;
     112: ifnull        172
     115: aload_1
     116: new           #19                 // class java/util/ArrayList
     119: dup
     120: invokespecial #20                 // Method java/util/ArrayList."<init>":()V
     123: putfield      #26                 // Field developers:Ljava/util/List;
     126: aload_0
     127: getfield      #26                 // Field developers:Ljava/util/List;
     130: invokeinterface #21,  1           // InterfaceMethod java/util/List.iterator:()Ljava/util/Iterator;
     135: astore_2
     136: aload_2
     137: invokeinterface #22,  1           // InterfaceMethod java/util/Iterator.hasNext:()Z
     142: ifeq          172
     145: aload_2
     146: invokeinterface #23,  1           // InterfaceMethod java/util/Iterator.next:()Ljava/lang/Object;
     151: checkcast     #27                 // class org/apache/maven/model/Developer
     154: astore_3
     155: aload_1
     156: getfield      #26                 // Field developers:Ljava/util/List;
     159: aload_3
     160: invokevirtual #28                 // Method org/apache/maven/model/Developer.clone:()Lorg/apache/maven/model/Developer;
     163: invokeinterface #7,  2            // InterfaceMethod java/util/List.add:(Ljava/lang/Object;)Z
     168: pop
     169: goto          136
     172: aload_0
     173: getfield      #29                 // Field contributors:Ljava/util/List;
     176: ifnull        236
     179: aload_1
     180: new           #19                 // class java/util/ArrayList
     183: dup
     184: invokespecial #20                 // Method java/util/ArrayList."<init>":()V
     187: putfield      #29                 // Field contributors:Ljava/util/List;
     190: aload_0
     191: getfield      #29                 // Field contributors:Ljava/util/List;
     194: invokeinterface #21,  1           // InterfaceMethod java/util/List.iterator:()Ljava/util/Iterator;
     199: astore_2
     200: aload_2
     201: invokeinterface #22,  1           // InterfaceMethod java/util/Iterator.hasNext:()Z
     206: ifeq          236
     209: aload_2
     210: invokeinterface #23,  1           // InterfaceMethod java/util/Iterator.next:()Ljava/lang/Object;
     215: checkcast     #30                 // class org/apache/maven/model/Contributor
     218: astore_3
     219: aload_1
     220: getfield      #29                 // Field contributors:Ljava/util/List;
     223: aload_3
     224: invokevirtual #31                 // Method org/apache/maven/model/Contributor.clone:()Lorg/apache/maven/model/Contributor;
     227: invokeinterface #7,  2            // InterfaceMethod java/util/List.add:(Ljava/lang/Object;)Z
     232: pop
     233: goto          200
     236: aload_0
     237: getfield      #32                 // Field mailingLists:Ljava/util/List;
     240: ifnull        300
     243: aload_1
     244: new           #19                 // class java/util/ArrayList
     247: dup
     248: invokespecial #20                 // Method java/util/ArrayList."<init>":()V
     251: putfield      #32                 // Field mailingLists:Ljava/util/List;
     254: aload_0
     255: getfield      #32                 // Field mailingLists:Ljava/util/List;
     258: invokeinterface #21,  1           // InterfaceMethod java/util/List.iterator:()Ljava/util/Iterator;
     263: astore_2
     264: aload_2
     265: invokeinterface #22,  1           // InterfaceMethod java/util/Iterator.hasNext:()Z
     270: ifeq          300
     273: aload_2
     274: invokeinterface #23,  1           // InterfaceMethod java/util/Iterator.next:()Ljava/lang/Object;
     279: checkcast     #33                 // class org/apache/maven/model/MailingList
     282: astore_3
     283: aload_1
     284: getfield      #32                 // Field mailingLists:Ljava/util/List;
     287: aload_3
     288: invokevirtual #34                 // Method org/apache/maven/model/MailingList.clone:()Lorg/apache/maven/model/MailingList;
     291: invokeinterface #7,  2            // InterfaceMethod java/util/List.add:(Ljava/lang/Object;)Z
     296: pop
     297: goto          264
     300: aload_0
     301: getfield      #35                 // Field prerequisites:Lorg/apache/maven/model/Prerequisites;
     304: ifnull        318
     307: aload_1
     308: aload_0
     309: getfield      #35                 // Field prerequisites:Lorg/apache/maven/model/Prerequisites;
     312: invokevirtual #36                 // Method org/apache/maven/model/Prerequisites.clone:()Lorg/apache/maven/model/Prerequisites;
     315: putfield      #35                 // Field prerequisites:Lorg/apache/maven/model/Prerequisites;
     318: aload_0
     319: getfield      #37                 // Field scm:Lorg/apache/maven/model/Scm;
     322: ifnull        336
     325: aload_1
     326: aload_0
     327: getfield      #37                 // Field scm:Lorg/apache/maven/model/Scm;
     330: invokevirtual #38                 // Method org/apache/maven/model/Scm.clone:()Lorg/apache/maven/model/Scm;
     333: putfield      #37                 // Field scm:Lorg/apache/maven/model/Scm;
     336: aload_0
     337: getfield      #39                 // Field issueManagement:Lorg/apache/maven/model/IssueManagement;
     340: ifnull        354
     343: aload_1
     344: aload_0
     345: getfield      #39                 // Field issueManagement:Lorg/apache/maven/model/IssueManagement;
     348: invokevirtual #40                 // Method org/apache/maven/model/IssueManagement.clone:()Lorg/apache/maven/model/IssueManagement;
     351: putfield      #39                 // Field issueManagement:Lorg/apache/maven/model/IssueManagement;
     354: aload_0
     355: getfield      #41                 // Field ciManagement:Lorg/apache/maven/model/CiManagement;
     358: ifnull        372
     361: aload_1
     362: aload_0
     363: getfield      #41                 // Field ciManagement:Lorg/apache/maven/model/CiManagement;
     366: invokevirtual #42                 // Method org/apache/maven/model/CiManagement.clone:()Lorg/apache/maven/model/CiManagement;
     369: putfield      #41                 // Field ciManagement:Lorg/apache/maven/model/CiManagement;
     372: aload_0
     373: getfield      #43                 // Field build:Lorg/apache/maven/model/Build;
     376: ifnull        390
     379: aload_1
     380: aload_0
     381: getfield      #43                 // Field build:Lorg/apache/maven/model/Build;
     384: invokevirtual #44                 // Method org/apache/maven/model/Build.clone:()Lorg/apache/maven/model/Build;
     387: putfield      #43                 // Field build:Lorg/apache/maven/model/Build;
     390: aload_0
     391: getfield      #45                 // Field profiles:Ljava/util/List;
     394: ifnull        454
     397: aload_1
     398: new           #19                 // class java/util/ArrayList
     401: dup
     402: invokespecial #20                 // Method java/util/ArrayList."<init>":()V
     405: putfield      #45                 // Field profiles:Ljava/util/List;
     408: aload_0
     409: getfield      #45                 // Field profiles:Ljava/util/List;
     412: invokeinterface #21,  1           // InterfaceMethod java/util/List.iterator:()Ljava/util/Iterator;
     417: astore_2
     418: aload_2
     419: invokeinterface #22,  1           // InterfaceMethod java/util/Iterator.hasNext:()Z
     424: ifeq          454
     427: aload_2
     428: invokeinterface #23,  1           // InterfaceMethod java/util/Iterator.next:()Ljava/lang/Object;
     433: checkcast     #46                 // class org/apache/maven/model/Profile
     436: astore_3
     437: aload_1
     438: getfield      #45                 // Field profiles:Ljava/util/List;
     441: aload_3
     442: invokevirtual #47                 // Method org/apache/maven/model/Profile.clone:()Lorg/apache/maven/model/Profile;
     445: invokeinterface #7,  2            // InterfaceMethod java/util/List.add:(Ljava/lang/Object;)Z
     450: pop
     451: goto          418
     454: aload_0
     455: aload_1
     456: invokespecial #48                 // Method cloneHook:(Lorg/apache/maven/model/Model;)V
     459: aload_1
     460: areturn
     461: astore_1
     462: new           #50                 // class java/lang/UnsupportedOperationException
     465: dup
     466: new           #51                 // class java/lang/StringBuilder
     469: dup
     470: invokespecial #52                 // Method java/lang/StringBuilder."<init>":()V
     473: aload_0
     474: invokevirtual #53                 // Method java/lang/Object.getClass:()Ljava/lang/Class;
     477: invokevirtual #54                 // Method java/lang/Class.getName:()Ljava/lang/String;
     480: invokevirtual #55                 // Method java/lang/StringBuilder.append:(Ljava/lang/String;)Ljava/lang/StringBuilder;
     483: ldc           #56                 // String  does not support clone()
     485: invokevirtual #55                 // Method java/lang/StringBuilder.append:(Ljava/lang/String;)Ljava/lang/StringBuilder;
     488: invokevirtual #57                 // Method java/lang/StringBuilder.toString:()Ljava/lang/String;
     491: invokespecial #58                 // Method java/lang/UnsupportedOperationException."<init>":(Ljava/lang/String;)V
     494: aload_1
     495: invokevirtual #59                 // Method java/lang/UnsupportedOperationException.initCause:(Ljava/lang/Throwable;)Ljava/lang/Throwable;
     498: checkcast     #60                 // class java/lang/RuntimeException
     501: athrow
    Exception table:
       from    to  target type
           0   460   461   Class java/lang/Exception

  public java.lang.String getArtifactId();
    Code:
       0: aload_0
       1: getfield      #61                 // Field artifactId:Ljava/lang/String;
       4: areturn

  public org.apache.maven.model.Build getBuild();
    Code:
       0: aload_0
       1: getfield      #43                 // Field build:Lorg/apache/maven/model/Build;
       4: areturn

  public org.apache.maven.model.CiManagement getCiManagement();
    Code:
       0: aload_0
       1: getfield      #41                 // Field ciManagement:Lorg/apache/maven/model/CiManagement;
       4: areturn

  public java.util.List<org.apache.maven.model.Contributor> getContributors();
    Code:
       0: aload_0
       1: getfield      #29                 // Field contributors:Ljava/util/List;
       4: ifnonnull     18
       7: aload_0
       8: new           #19                 // class java/util/ArrayList
      11: dup
      12: invokespecial #20                 // Method java/util/ArrayList."<init>":()V
      15: putfield      #29                 // Field contributors:Ljava/util/List;
      18: aload_0
      19: getfield      #29                 // Field contributors:Ljava/util/List;
      22: areturn

  public java.lang.String getDescription();
    Code:
       0: aload_0
       1: getfield      #62                 // Field description:Ljava/lang/String;
       4: areturn

  public java.util.List<org.apache.maven.model.Developer> getDevelopers();
    Code:
       0: aload_0
       1: getfield      #26                 // Field developers:Ljava/util/List;
       4: ifnonnull     18
       7: aload_0
       8: new           #19                 // class java/util/ArrayList
      11: dup
      12: invokespecial #20                 // Method java/util/ArrayList."<init>":()V
      15: putfield      #26                 // Field developers:Ljava/util/List;
      18: aload_0
      19: getfield      #26                 // Field developers:Ljava/util/List;
      22: areturn

  public java.lang.String getGroupId();
    Code:
       0: aload_0
       1: getfield      #63                 // Field groupId:Ljava/lang/String;
       4: areturn

  public java.lang.String getInceptionYear();
    Code:
       0: aload_0
       1: getfield      #64                 // Field inceptionYear:Ljava/lang/String;
       4: areturn

  public org.apache.maven.model.IssueManagement getIssueManagement();
    Code:
       0: aload_0
       1: getfield      #39                 // Field issueManagement:Lorg/apache/maven/model/IssueManagement;
       4: areturn

  public java.util.List<org.apache.maven.model.License> getLicenses();
    Code:
       0: aload_0
       1: getfield      #18                 // Field licenses:Ljava/util/List;
       4: ifnonnull     18
       7: aload_0
       8: new           #19                 // class java/util/ArrayList
      11: dup
      12: invokespecial #20                 // Method java/util/ArrayList."<init>":()V
      15: putfield      #18                 // Field licenses:Ljava/util/List;
      18: aload_0
      19: getfield      #18                 // Field licenses:Ljava/util/List;
      22: areturn

  public java.util.List<org.apache.maven.model.MailingList> getMailingLists();
    Code:
       0: aload_0
       1: getfield      #32                 // Field mailingLists:Ljava/util/List;
       4: ifnonnull     18
       7: aload_0
       8: new           #19                 // class java/util/ArrayList
      11: dup
      12: invokespecial #20                 // Method java/util/ArrayList."<init>":()V
      15: putfield      #32                 // Field mailingLists:Ljava/util/List;
      18: aload_0
      19: getfield      #32                 // Field mailingLists:Ljava/util/List;
      22: areturn

  public java.lang.String getModelEncoding();
    Code:
       0: aload_0
       1: getfield      #5                  // Field modelEncoding:Ljava/lang/String;
       4: areturn

  public java.lang.String getModelVersion();
    Code:
       0: aload_0
       1: getfield      #65                 // Field modelVersion:Ljava/lang/String;
       4: areturn

  public java.lang.String getName();
    Code:
       0: aload_0
       1: getfield      #66                 // Field name:Ljava/lang/String;
       4: areturn

  public org.apache.maven.model.Organization getOrganization();
    Code:
       0: aload_0
       1: getfield      #16                 // Field organization:Lorg/apache/maven/model/Organization;
       4: areturn

  public java.lang.String getPackaging();
    Code:
       0: aload_0
       1: getfield      #3                  // Field packaging:Ljava/lang/String;
       4: areturn

  public org.apache.maven.model.Parent getParent();
    Code:
       0: aload_0
       1: getfield      #14                 // Field parent:Lorg/apache/maven/model/Parent;
       4: areturn

  public org.apache.maven.model.Prerequisites getPrerequisites();
    Code:
       0: aload_0
       1: getfield      #35                 // Field prerequisites:Lorg/apache/maven/model/Prerequisites;
       4: areturn

  public java.util.List<org.apache.maven.model.Profile> getProfiles();
    Code:
       0: aload_0
       1: getfield      #45                 // Field profiles:Ljava/util/List;
       4: ifnonnull     18
       7: aload_0
       8: new           #19                 // class java/util/ArrayList
      11: dup
      12: invokespecial #20                 // Method java/util/ArrayList."<init>":()V
      15: putfield      #45                 // Field profiles:Ljava/util/List;
      18: aload_0
      19: getfield      #45                 // Field profiles:Ljava/util/List;
      22: areturn

  public org.apache.maven.model.Scm getScm();
    Code:
       0: aload_0
       1: getfield      #37                 // Field scm:Lorg/apache/maven/model/Scm;
       4: areturn

  public java.lang.String getUrl();
    Code:
       0: aload_0
       1: getfield      #67                 // Field url:Ljava/lang/String;
       4: areturn

  public java.lang.String getVersion();
    Code:
       0: aload_0
       1: getfield      #68                 // Field version:Ljava/lang/String;
       4: areturn

  public void removeContributor(org.apache.maven.model.Contributor);
    Code:
       0: aload_0
       1: invokevirtual #6                  // Method getContributors:()Ljava/util/List;
       4: aload_1
       5: invokeinterface #69,  2           // InterfaceMethod java/util/List.remove:(Ljava/lang/Object;)Z
      10: pop
      11: return

  public void removeDeveloper(org.apache.maven.model.Developer);
    Code:
       0: aload_0
       1: invokevirtual #8                  // Method getDevelopers:()Ljava/util/List;
       4: aload_1
       5: invokeinterface #69,  2           // InterfaceMethod java/util/List.remove:(Ljava/lang/Object;)Z
      10: pop
      11: return

  public void removeLicense(org.apache.maven.model.License);
    Code:
       0: aload_0
       1: invokevirtual #9                  // Method getLicenses:()Ljava/util/List;
       4: aload_1
       5: invokeinterface #69,  2           // InterfaceMethod java/util/List.remove:(Ljava/lang/Object;)Z
      10: pop
      11: return

  public void removeMailingList(org.apache.maven.model.MailingList);
    Code:
       0: aload_0
       1: invokevirtual #10                 // Method getMailingLists:()Ljava/util/List;
       4: aload_1
       5: invokeinterface #69,  2           // InterfaceMethod java/util/List.remove:(Ljava/lang/Object;)Z
      10: pop
      11: return

  public void removeProfile(org.apache.maven.model.Profile);
    Code:
       0: aload_0
       1: invokevirtual #11                 // Method getProfiles:()Ljava/util/List;
       4: aload_1
       5: invokeinterface #69,  2           // InterfaceMethod java/util/List.remove:(Ljava/lang/Object;)Z
      10: pop
      11: return

  public void setArtifactId(java.lang.String);
    Code:
       0: aload_0
       1: aload_1
       2: putfield      #61                 // Field artifactId:Ljava/lang/String;
       5: return

  public void setBuild(org.apache.maven.model.Build);
    Code:
       0: aload_0
       1: aload_1
       2: putfield      #43                 // Field build:Lorg/apache/maven/model/Build;
       5: return

  public void setCiManagement(org.apache.maven.model.CiManagement);
    Code:
       0: aload_0
       1: aload_1
       2: putfield      #41                 // Field ciManagement:Lorg/apache/maven/model/CiManagement;
       5: return

  public void setContributors(java.util.List<org.apache.maven.model.Contributor>);
    Code:
       0: aload_0
       1: aload_1
       2: putfield      #29                 // Field contributors:Ljava/util/List;
       5: return

  public void setDescription(java.lang.String);
    Code:
       0: aload_0
       1: aload_1
       2: putfield      #62                 // Field description:Ljava/lang/String;
       5: return

  public void setDevelopers(java.util.List<org.apache.maven.model.Developer>);
    Code:
       0: aload_0
       1: aload_1
       2: putfield      #26                 // Field developers:Ljava/util/List;
       5: return

  public void setGroupId(java.lang.String);
    Code:
       0: aload_0
       1: aload_1
       2: putfield      #63                 // Field groupId:Ljava/lang/String;
       5: return

  public void setInceptionYear(java.lang.String);
    Code:
       0: aload_0
       1: aload_1
       2: putfield      #64                 // Field inceptionYear:Ljava/lang/String;
       5: return

  public void setIssueManagement(org.apache.maven.model.IssueManagement);
    Code:
       0: aload_0
       1: aload_1
       2: putfield      #39                 // Field issueManagement:Lorg/apache/maven/model/IssueManagement;
       5: return

  public void setLicenses(java.util.List<org.apache.maven.model.License>);
    Code:
       0: aload_0
       1: aload_1
       2: putfield      #18                 // Field licenses:Ljava/util/List;
       5: return

  public void setMailingLists(java.util.List<org.apache.maven.model.MailingList>);
    Code:
       0: aload_0
       1: aload_1
       2: putfield      #32                 // Field mailingLists:Ljava/util/List;
       5: return

  public void setModelEncoding(java.lang.String);
    Code:
       0: aload_0
       1: aload_1
       2: putfield      #5                  // Field modelEncoding:Ljava/lang/String;
       5: return

  public void setModelVersion(java.lang.String);
    Code:
       0: aload_0
       1: aload_1
       2: putfield      #65                 // Field modelVersion:Ljava/lang/String;
       5: return

  public void setName(java.lang.String);
    Code:
       0: aload_0
       1: aload_1
       2: putfield      #66                 // Field name:Ljava/lang/String;
       5: return

  public void setOrganization(org.apache.maven.model.Organization);
    Code:
       0: aload_0
       1: aload_1
       2: putfield      #16                 // Field organization:Lorg/apache/maven/model/Organization;
       5: return

  public void setPackaging(java.lang.String);
    Code:
       0: aload_0
       1: aload_1
       2: putfield      #3                  // Field packaging:Ljava/lang/String;
       5: return

  public void setParent(org.apache.maven.model.Parent);
    Code:
       0: aload_0
       1: aload_1
       2: putfield      #14                 // Field parent:Lorg/apache/maven/model/Parent;
       5: return

  public void setPrerequisites(org.apache.maven.model.Prerequisites);
    Code:
       0: aload_0
       1: aload_1
       2: putfield      #35                 // Field prerequisites:Lorg/apache/maven/model/Prerequisites;
       5: return

  public void setProfiles(java.util.List<org.apache.maven.model.Profile>);
    Code:
       0: aload_0
       1: aload_1
       2: putfield      #45                 // Field profiles:Ljava/util/List;
       5: return

  public void setScm(org.apache.maven.model.Scm);
    Code:
       0: aload_0
       1: aload_1
       2: putfield      #37                 // Field scm:Lorg/apache/maven/model/Scm;
       5: return

  public void setUrl(java.lang.String);
    Code:
       0: aload_0
       1: aload_1
       2: putfield      #67                 // Field url:Ljava/lang/String;
       5: return

  public void setVersion(java.lang.String);
    Code:
       0: aload_0
       1: aload_1
       2: putfield      #68                 // Field version:Ljava/lang/String;
       5: return

  private void cloneHook(org.apache.maven.model.Model);
    Code:
       0: aload_1
       1: aload_0
       2: getfield      #70                 // Field pomFile:Ljava/io/File;
       5: putfield      #70                 // Field pomFile:Ljava/io/File;
       8: return

  public java.io.File getPomFile();
    Code:
       0: aload_0
       1: getfield      #70                 // Field pomFile:Ljava/io/File;
       4: areturn

  public void setPomFile(java.io.File);
    Code:
       0: aload_0
       1: aload_1
       2: ifnull        12
       5: aload_1
       6: invokevirtual #71                 // Method java/io/File.getAbsoluteFile:()Ljava/io/File;
       9: goto          13
      12: aconst_null
      13: putfield      #70                 // Field pomFile:Ljava/io/File;
      16: return

  public java.io.File getProjectDirectory();
    Code:
       0: aload_0
       1: getfield      #70                 // Field pomFile:Ljava/io/File;
       4: ifnull        17
       7: aload_0
       8: getfield      #70                 // Field pomFile:Ljava/io/File;
      11: invokevirtual #72                 // Method java/io/File.getParentFile:()Ljava/io/File;
      14: goto          18
      17: aconst_null
      18: areturn

  public java.lang.String getId();
    Code:
       0: new           #51                 // class java/lang/StringBuilder
       3: dup
       4: bipush        64
       6: invokespecial #73                 // Method java/lang/StringBuilder."<init>":(I)V
       9: astore_1
      10: aload_1
      11: aload_0
      12: invokevirtual #74                 // Method getGroupId:()Ljava/lang/String;
      15: ifnonnull     23
      18: ldc           #75                 // String [inherited]
      20: goto          27
      23: aload_0
      24: invokevirtual #74                 // Method getGroupId:()Ljava/lang/String;
      27: invokevirtual #55                 // Method java/lang/StringBuilder.append:(Ljava/lang/String;)Ljava/lang/StringBuilder;
      30: pop
      31: aload_1
      32: ldc           #76                 // String :
      34: invokevirtual #55                 // Method java/lang/StringBuilder.append:(Ljava/lang/String;)Ljava/lang/StringBuilder;
      37: pop
      38: aload_1
      39: aload_0
      40: invokevirtual #77                 // Method getArtifactId:()Ljava/lang/String;
      43: invokevirtual #55                 // Method java/lang/StringBuilder.append:(Ljava/lang/String;)Ljava/lang/StringBuilder;
      46: pop
      47: aload_1
      48: ldc           #76                 // String :
      50: invokevirtual #55                 // Method java/lang/StringBuilder.append:(Ljava/lang/String;)Ljava/lang/StringBuilder;
      53: pop
      54: aload_1
      55: aload_0
      56: invokevirtual #78                 // Method getPackaging:()Ljava/lang/String;
      59: invokevirtual #55                 // Method java/lang/StringBuilder.append:(Ljava/lang/String;)Ljava/lang/StringBuilder;
      62: pop
      63: aload_1
      64: ldc           #76                 // String :
      66: invokevirtual #55                 // Method java/lang/StringBuilder.append:(Ljava/lang/String;)Ljava/lang/StringBuilder;
      69: pop
      70: aload_1
      71: aload_0
      72: invokevirtual #79                 // Method getVersion:()Ljava/lang/String;
      75: ifnonnull     83
      78: ldc           #75                 // String [inherited]
      80: goto          87
      83: aload_0
      84: invokevirtual #79                 // Method getVersion:()Ljava/lang/String;
      87: invokevirtual #55                 // Method java/lang/StringBuilder.append:(Ljava/lang/String;)Ljava/lang/StringBuilder;
      90: pop
      91: aload_1
      92: invokevirtual #57                 // Method java/lang/StringBuilder.toString:()Ljava/lang/String;
      95: areturn

  public java.lang.String toString();
    Code:
       0: aload_0
       1: invokevirtual #80                 // Method getId:()Ljava/lang/String;
       4: areturn

  public org.apache.maven.model.ModelBase clone();
    Code:
       0: aload_0
       1: invokevirtual #81                 // Method clone:()Lorg/apache/maven/model/Model;
       4: areturn

  public java.lang.Object clone() throws java.lang.CloneNotSupportedException;
    Code:
       0: aload_0
       1: invokevirtual #81                 // Method clone:()Lorg/apache/maven/model/Model;
       4: areturn
}
