Compiled from "DefaultHttpConnectionManager.java"
public class org.apache.axis2.transport.http.server.DefaultHttpConnectionManager implements org.apache.axis2.transport.http.server.HttpConnectionManager {
  private static org.apache.commons.logging.Log LOG;

  private final org.apache.axis2.context.ConfigurationContext configurationContext;

  private final java.util.concurrent.Executor executor;

  private final org.apache.axis2.transport.http.server.WorkerFactory workerfactory;

  private final org.apache.http.params.HttpParams params;

  private final java.util.List processors;

  private org.apache.axis2.transport.http.server.HttpFactory httpFactory;

  public org.apache.axis2.transport.http.server.DefaultHttpConnectionManager(org.apache.axis2.context.ConfigurationContext, java.util.concurrent.Executor, org.apache.axis2.transport.http.server.WorkerFactory, org.apache.http.params.HttpParams);
    Code:
       0: aload_0
       1: invokespecial #2                  // Method java/lang/Object."<init>":()V
       4: aload_0
       5: aconst_null
       6: putfield      #3                  // Field httpFactory:Lorg/apache/axis2/transport/http/server/HttpFactory;
       9: aload_1
      10: ifnonnull     23
      13: new           #4                  // class java/lang/IllegalArgumentException
      16: dup
      17: ldc           #5                  // String Configuration context may not be null
      19: invokespecial #6                  // Method java/lang/IllegalArgumentException."<init>":(Ljava/lang/String;)V
      22: athrow
      23: aload_2
      24: ifnonnull     37
      27: new           #4                  // class java/lang/IllegalArgumentException
      30: dup
      31: ldc           #7                  // String Executor may not be null
      33: invokespecial #6                  // Method java/lang/IllegalArgumentException."<init>":(Ljava/lang/String;)V
      36: athrow
      37: aload_3
      38: ifnonnull     51
      41: new           #4                  // class java/lang/IllegalArgumentException
      44: dup
      45: ldc           #8                  // String Worker factory may not be null
      47: invokespecial #6                  // Method java/lang/IllegalArgumentException."<init>":(Ljava/lang/String;)V
      50: athrow
      51: aload         4
      53: ifnonnull     66
      56: new           #4                  // class java/lang/IllegalArgumentException
      59: dup
      60: ldc           #9                  // String HTTP parameters may not be null
      62: invokespecial #6                  // Method java/lang/IllegalArgumentException."<init>":(Ljava/lang/String;)V
      65: athrow
      66: aload_0
      67: aload_1
      68: putfield      #10                 // Field configurationContext:Lorg/apache/axis2/context/ConfigurationContext;
      71: aload_0
      72: aload_2
      73: putfield      #11                 // Field executor:Ljava/util/concurrent/Executor;
      76: aload_0
      77: aload_3
      78: putfield      #12                 // Field workerfactory:Lorg/apache/axis2/transport/http/server/WorkerFactory;
      81: aload_0
      82: aload         4
      84: putfield      #13                 // Field params:Lorg/apache/http/params/HttpParams;
      87: aload_0
      88: new           #14                 // class java/util/LinkedList
      91: dup
      92: invokespecial #15                 // Method java/util/LinkedList."<init>":()V
      95: putfield      #16                 // Field processors:Ljava/util/List;
      98: return

  public org.apache.axis2.transport.http.server.DefaultHttpConnectionManager(org.apache.axis2.context.ConfigurationContext, java.util.concurrent.Executor, org.apache.axis2.transport.http.server.WorkerFactory, org.apache.http.params.HttpParams, org.apache.axis2.transport.http.server.HttpFactory);
    Code:
       0: aload_0
       1: aload_1
       2: aload_2
       3: aload_3
       4: aload         4
       6: invokespecial #17                 // Method "<init>":(Lorg/apache/axis2/context/ConfigurationContext;Ljava/util/concurrent/Executor;Lorg/apache/axis2/transport/http/server/WorkerFactory;Lorg/apache/http/params/HttpParams;)V
       9: aload_0
      10: aload         5
      12: putfield      #3                  // Field httpFactory:Lorg/apache/axis2/transport/http/server/HttpFactory;
      15: return

  private synchronized void cleanup();
    Code:
       0: aload_0
       1: getfield      #16                 // Field processors:Ljava/util/List;
       4: invokeinterface #18,  1           // InterfaceMethod java/util/List.iterator:()Ljava/util/Iterator;
       9: astore_1
      10: aload_1
      11: invokeinterface #19,  1           // InterfaceMethod java/util/Iterator.hasNext:()Z
      16: ifeq          47
      19: aload_1
      20: invokeinterface #20,  1           // InterfaceMethod java/util/Iterator.next:()Ljava/lang/Object;
      25: checkcast     #21                 // class org/apache/axis2/transport/http/server/IOProcessor
      28: astore_2
      29: aload_2
      30: invokeinterface #22,  1           // InterfaceMethod org/apache/axis2/transport/http/server/IOProcessor.isDestroyed:()Z
      35: ifeq          44
      38: aload_1
      39: invokeinterface #23,  1           // InterfaceMethod java/util/Iterator.remove:()V
      44: goto          10
      47: return

  private synchronized void addProcessor(org.apache.axis2.transport.http.server.IOProcessor);
    Code:
       0: aload_1
       1: ifnonnull     14
       4: new           #24                 // class java/lang/NullPointerException
       7: dup
       8: ldc           #25                 // String The processor can\'t be null
      10: invokespecial #26                 // Method java/lang/NullPointerException."<init>":(Ljava/lang/String;)V
      13: athrow
      14: aload_0
      15: getfield      #16                 // Field processors:Ljava/util/List;
      18: aload_1
      19: invokeinterface #27,  2           // InterfaceMethod java/util/List.add:(Ljava/lang/Object;)Z
      24: pop
      25: return

  synchronized void removeProcessor(org.apache.axis2.transport.http.server.IOProcessor) throws java.lang.NullPointerException;
    Code:
       0: aload_1
       1: ifnonnull     14
       4: new           #24                 // class java/lang/NullPointerException
       7: dup
       8: ldc           #25                 // String The processor can\'t be null
      10: invokespecial #26                 // Method java/lang/NullPointerException."<init>":(Ljava/lang/String;)V
      13: athrow
      14: aload_0
      15: getfield      #16                 // Field processors:Ljava/util/List;
      18: aload_1
      19: invokeinterface #28,  2           // InterfaceMethod java/util/List.remove:(Ljava/lang/Object;)Z
      24: pop
      25: return

  public void process(org.apache.axis2.transport.http.server.AxisHttpConnection);
    Code:
       0: aload_1
       1: ifnonnull     14
       4: new           #4                  // class java/lang/IllegalArgumentException
       7: dup
       8: ldc           #29                 // String HTTP connection may not be null
      10: invokespecial #6                  // Method java/lang/IllegalArgumentException."<init>":(Ljava/lang/String;)V
      13: athrow
      14: aload_0
      15: invokespecial #30                 // Method cleanup:()V
      18: aload_0
      19: getfield      #3                  // Field httpFactory:Lorg/apache/axis2/transport/http/server/HttpFactory;
      22: ifnull        53
      25: aload_0
      26: getfield      #3                  // Field httpFactory:Lorg/apache/axis2/transport/http/server/HttpFactory;
      29: invokevirtual #31                 // Method org/apache/axis2/transport/http/server/HttpFactory.newHttpProcessor:()Lorg/apache/http/protocol/HttpProcessor;
      32: astore_2
      33: aload_0
      34: getfield      #3                  // Field httpFactory:Lorg/apache/axis2/transport/http/server/HttpFactory;
      37: invokevirtual #32                 // Method org/apache/axis2/transport/http/server/HttpFactory.newConnStrategy:()Lorg/apache/http/ConnectionReuseStrategy;
      40: astore_3
      41: aload_0
      42: getfield      #3                  // Field httpFactory:Lorg/apache/axis2/transport/http/server/HttpFactory;
      45: invokevirtual #33                 // Method org/apache/axis2/transport/http/server/HttpFactory.newResponseFactory:()Lorg/apache/http/HttpResponseFactory;
      48: astore        4
      50: goto          154
      53: new           #34                 // class org/apache/http/protocol/BasicHttpProcessor
      56: dup
      57: invokespecial #35                 // Method org/apache/http/protocol/BasicHttpProcessor."<init>":()V
      60: astore        5
      62: aload         5
      64: new           #36                 // class org/apache/axis2/transport/http/server/RequestSessionCookie
      67: dup
      68: invokespecial #37                 // Method org/apache/axis2/transport/http/server/RequestSessionCookie."<init>":()V
      71: invokevirtual #38                 // Method org/apache/http/protocol/BasicHttpProcessor.addInterceptor:(Lorg/apache/http/HttpRequestInterceptor;)V
      74: aload         5
      76: new           #39                 // class org/apache/http/protocol/ResponseDate
      79: dup
      80: invokespecial #40                 // Method org/apache/http/protocol/ResponseDate."<init>":()V
      83: invokevirtual #41                 // Method org/apache/http/protocol/BasicHttpProcessor.addInterceptor:(Lorg/apache/http/HttpResponseInterceptor;)V
      86: aload         5
      88: new           #42                 // class org/apache/http/protocol/ResponseServer
      91: dup
      92: invokespecial #43                 // Method org/apache/http/protocol/ResponseServer."<init>":()V
      95: invokevirtual #41                 // Method org/apache/http/protocol/BasicHttpProcessor.addInterceptor:(Lorg/apache/http/HttpResponseInterceptor;)V
      98: aload         5
     100: new           #44                 // class org/apache/http/protocol/ResponseContent
     103: dup
     104: invokespecial #45                 // Method org/apache/http/protocol/ResponseContent."<init>":()V
     107: invokevirtual #41                 // Method org/apache/http/protocol/BasicHttpProcessor.addInterceptor:(Lorg/apache/http/HttpResponseInterceptor;)V
     110: aload         5
     112: new           #46                 // class org/apache/http/protocol/ResponseConnControl
     115: dup
     116: invokespecial #47                 // Method org/apache/http/protocol/ResponseConnControl."<init>":()V
     119: invokevirtual #41                 // Method org/apache/http/protocol/BasicHttpProcessor.addInterceptor:(Lorg/apache/http/HttpResponseInterceptor;)V
     122: aload         5
     124: new           #48                 // class org/apache/axis2/transport/http/server/ResponseSessionCookie
     127: dup
     128: invokespecial #49                 // Method org/apache/axis2/transport/http/server/ResponseSessionCookie."<init>":()V
     131: invokevirtual #41                 // Method org/apache/http/protocol/BasicHttpProcessor.addInterceptor:(Lorg/apache/http/HttpResponseInterceptor;)V
     134: aload         5
     136: astore_2
     137: new           #50                 // class org/apache/http/impl/DefaultConnectionReuseStrategy
     140: dup
     141: invokespecial #51                 // Method org/apache/http/impl/DefaultConnectionReuseStrategy."<init>":()V
     144: astore_3
     145: new           #52                 // class org/apache/http/impl/DefaultHttpResponseFactory
     148: dup
     149: invokespecial #53                 // Method org/apache/http/impl/DefaultHttpResponseFactory."<init>":()V
     152: astore        4
     154: new           #54                 // class org/apache/axis2/transport/http/server/AxisHttpService
     157: dup
     158: aload_2
     159: aload_3
     160: aload         4
     162: aload_0
     163: getfield      #10                 // Field configurationContext:Lorg/apache/axis2/context/ConfigurationContext;
     166: aload_0
     167: getfield      #12                 // Field workerfactory:Lorg/apache/axis2/transport/http/server/WorkerFactory;
     170: invokeinterface #55,  1           // InterfaceMethod org/apache/axis2/transport/http/server/WorkerFactory.newWorker:()Lorg/apache/axis2/transport/http/server/Worker;
     175: invokespecial #56                 // Method org/apache/axis2/transport/http/server/AxisHttpService."<init>":(Lorg/apache/http/protocol/HttpProcessor;Lorg/apache/http/ConnectionReuseStrategy;Lorg/apache/http/HttpResponseFactory;Lorg/apache/axis2/context/ConfigurationContext;Lorg/apache/axis2/transport/http/server/Worker;)V
     178: astore        5
     180: aload         5
     182: aload_0
     183: getfield      #13                 // Field params:Lorg/apache/http/params/HttpParams;
     186: invokevirtual #57                 // Method org/apache/axis2/transport/http/server/AxisHttpService.setParams:(Lorg/apache/http/params/HttpParams;)V
     189: new           #58                 // class org/apache/axis2/transport/http/server/DefaultHttpConnectionManager$1
     192: dup
     193: aload_0
     194: invokespecial #59                 // Method org/apache/axis2/transport/http/server/DefaultHttpConnectionManager$1."<init>":(Lorg/apache/axis2/transport/http/server/DefaultHttpConnectionManager;)V
     197: astore        6
     199: new           #60                 // class org/apache/axis2/transport/http/server/HttpServiceProcessor
     202: dup
     203: aload         5
     205: aload_1
     206: aload         6
     208: invokespecial #61                 // Method org/apache/axis2/transport/http/server/HttpServiceProcessor."<init>":(Lorg/apache/axis2/transport/http/server/AxisHttpService;Lorg/apache/axis2/transport/http/server/AxisHttpConnection;Lorg/apache/axis2/transport/http/server/IOProcessorCallback;)V
     211: astore        7
     213: aload_0
     214: aload         7
     216: invokespecial #62                 // Method addProcessor:(Lorg/apache/axis2/transport/http/server/IOProcessor;)V
     219: aload_0
     220: getfield      #11                 // Field executor:Ljava/util/concurrent/Executor;
     223: aload         7
     225: invokeinterface #63,  2           // InterfaceMethod java/util/concurrent/Executor.execute:(Ljava/lang/Runnable;)V
     230: return

  public synchronized void shutdown();
    Code:
       0: iconst_0
       1: istore_1
       2: iload_1
       3: aload_0
       4: getfield      #16                 // Field processors:Ljava/util/List;
       7: invokeinterface #64,  1           // InterfaceMethod java/util/List.size:()I
      12: if_icmpge     41
      15: aload_0
      16: getfield      #16                 // Field processors:Ljava/util/List;
      19: iload_1
      20: invokeinterface #65,  2           // InterfaceMethod java/util/List.get:(I)Ljava/lang/Object;
      25: checkcast     #21                 // class org/apache/axis2/transport/http/server/IOProcessor
      28: astore_2
      29: aload_2
      30: invokeinterface #66,  1           // InterfaceMethod org/apache/axis2/transport/http/server/IOProcessor.destroy:()V
      35: iinc          1, 1
      38: goto          2
      41: aload_0
      42: getfield      #16                 // Field processors:Ljava/util/List;
      45: invokeinterface #67,  1           // InterfaceMethod java/util/List.clear:()V
      50: return

  static org.apache.commons.logging.Log access$000();
    Code:
       0: getstatic     #1                  // Field LOG:Lorg/apache/commons/logging/Log;
       3: areturn

  static {};
    Code:
       0: ldc           #68                 // class org/apache/axis2/transport/http/server/DefaultHttpConnectionManager
       2: invokestatic  #69                 // Method org/apache/commons/logging/LogFactory.getLog:(Ljava/lang/Class;)Lorg/apache/commons/logging/Log;
       5: putstatic     #1                  // Field LOG:Lorg/apache/commons/logging/Log;
       8: return
}
