Compiled from "OWLAutoCompleter.java"
class org.protege.editor.owl.ui.clsdescriptioneditor.OWLAutoCompleter$2 extends java.awt.event.ComponentAdapter {
  final org.protege.editor.owl.ui.clsdescriptioneditor.OWLAutoCompleter this$0;

  org.protege.editor.owl.ui.clsdescriptioneditor.OWLAutoCompleter$2(org.protege.editor.owl.ui.clsdescriptioneditor.OWLAutoCompleter);
    Code:
       0: aload_0
       1: aload_1
       2: putfield      #1                  // Field this$0:Lorg/protege/editor/owl/ui/clsdescriptioneditor/OWLAutoCompleter;
       5: aload_0
       6: invokespecial #2                  // Method java/awt/event/ComponentAdapter."<init>":()V
       9: return

  public void componentHidden(java.awt.event.ComponentEvent);
    Code:
       0: aload_0
       1: getfield      #1                  // Field this$0:Lorg/protege/editor/owl/ui/clsdescriptioneditor/OWLAutoCompleter;
       4: invokestatic  #3                  // Method org/protege/editor/owl/ui/clsdescriptioneditor/OWLAutoCompleter.access$600:(Lorg/protege/editor/owl/ui/clsdescriptioneditor/OWLAutoCompleter;)V
       7: return

  public void componentResized(java.awt.event.ComponentEvent);
    Code:
       0: aload_0
       1: getfield      #1                  // Field this$0:Lorg/protege/editor/owl/ui/clsdescriptioneditor/OWLAutoCompleter;
       4: invokestatic  #3                  // Method org/protege/editor/owl/ui/clsdescriptioneditor/OWLAutoCompleter.access$600:(Lorg/protege/editor/owl/ui/clsdescriptioneditor/OWLAutoCompleter;)V
       7: return

  public void componentMoved(java.awt.event.ComponentEvent);
    Code:
       0: aload_0
       1: getfield      #1                  // Field this$0:Lorg/protege/editor/owl/ui/clsdescriptioneditor/OWLAutoCompleter;
       4: invokestatic  #3                  // Method org/protege/editor/owl/ui/clsdescriptioneditor/OWLAutoCompleter.access$600:(Lorg/protege/editor/owl/ui/clsdescriptioneditor/OWLAutoCompleter;)V
       7: return
}
