Compiled from "StatsNamedContainer.java"
final class org.hibernate.stat.internal.StatsNamedContainer<V> {
  private final java.util.concurrent.ConcurrentHashMap<java.lang.String, V> map;

  org.hibernate.stat.internal.StatsNamedContainer();
    Code:
       0: aload_0
       1: invokespecial #1                  // Method java/lang/Object."<init>":()V
       4: aload_0
       5: new           #2                  // class java/util/concurrent/ConcurrentHashMap
       8: dup
       9: invokespecial #3                  // Method java/util/concurrent/ConcurrentHashMap."<init>":()V
      12: putfield      #4                  // Field map:Ljava/util/concurrent/ConcurrentHashMap;
      15: return

  public void clear();
    Code:
       0: aload_0
       1: getfield      #4                  // Field map:Ljava/util/concurrent/ConcurrentHashMap;
       4: invokevirtual #5                  // Method java/util/concurrent/ConcurrentHashMap.clear:()V
       7: return

  public java.lang.String[] keysAsArray();
    Code:
       0: aload_0
       1: getfield      #4                  // Field map:Ljava/util/concurrent/ConcurrentHashMap;
       4: invokevirtual #6                  // Method java/util/concurrent/ConcurrentHashMap.keySet:()Ljava/util/concurrent/ConcurrentHashMap$KeySetView;
       7: iconst_0
       8: anewarray     #7                  // class java/lang/String
      11: invokevirtual #8                  // Method java/util/concurrent/ConcurrentHashMap$KeySetView.toArray:([Ljava/lang/Object;)[Ljava/lang/Object;
      14: checkcast     #9                  // class "[Ljava/lang/String;"
      17: areturn

  public V getOrCompute(java.lang.String, java.util.function.Function<java.lang.String, V>);
    Code:
       0: aload_0
       1: getfield      #4                  // Field map:Ljava/util/concurrent/ConcurrentHashMap;
       4: aload_1
       5: invokevirtual #10                 // Method java/util/concurrent/ConcurrentHashMap.get:(Ljava/lang/Object;)Ljava/lang/Object;
       8: astore_3
       9: aload_3
      10: ifnull        15
      13: aload_3
      14: areturn
      15: aload_2
      16: aload_1
      17: invokeinterface #11,  2           // InterfaceMethod java/util/function/Function.apply:(Ljava/lang/Object;)Ljava/lang/Object;
      22: astore        4
      24: aload         4
      26: ifnonnull     31
      29: aconst_null
      30: areturn
      31: aload_0
      32: getfield      #4                  // Field map:Ljava/util/concurrent/ConcurrentHashMap;
      35: aload_1
      36: aload         4
      38: invokevirtual #12                 // Method java/util/concurrent/ConcurrentHashMap.putIfAbsent:(Ljava/lang/Object;Ljava/lang/Object;)Ljava/lang/Object;
      41: astore        5
      43: aload         5
      45: ifnonnull     51
      48: aload         4
      50: areturn
      51: aload         5
      53: areturn

  public V get(java.lang.String);
    Code:
       0: aload_0
       1: getfield      #4                  // Field map:Ljava/util/concurrent/ConcurrentHashMap;
       4: aload_1
       5: invokevirtual #10                 // Method java/util/concurrent/ConcurrentHashMap.get:(Ljava/lang/Object;)Ljava/lang/Object;
       8: areturn
}
