Compiled from "BinlogHelper.java"
class io.grpc.protobuf.services.BinlogHelper$1$1 extends io.grpc.ForwardingClientCall$SimpleForwardingClientCall<ReqT, RespT> {
  final io.grpc.Deadline val$deadline;

  final java.util.concurrent.atomic.AtomicLong val$seq;

  final java.lang.String val$methodName;

  final java.lang.String val$authority;

  final io.grpc.MethodDescriptor val$method;

  final io.grpc.protobuf.services.BinlogHelper$1 this$1;

  io.grpc.protobuf.services.BinlogHelper$1$1(io.grpc.protobuf.services.BinlogHelper$1, io.grpc.ClientCall, io.grpc.Deadline, java.util.concurrent.atomic.AtomicLong, java.lang.String, java.lang.String, io.grpc.MethodDescriptor);
    Code:
       0: aload_0
       1: aload_1
       2: putfield      #1                  // Field this$1:Lio/grpc/protobuf/services/BinlogHelper$1;
       5: aload_0
       6: aload_3
       7: putfield      #2                  // Field val$deadline:Lio/grpc/Deadline;
      10: aload_0
      11: aload         4
      13: putfield      #3                  // Field val$seq:Ljava/util/concurrent/atomic/AtomicLong;
      16: aload_0
      17: aload         5
      19: putfield      #4                  // Field val$methodName:Ljava/lang/String;
      22: aload_0
      23: aload         6
      25: putfield      #5                  // Field val$authority:Ljava/lang/String;
      28: aload_0
      29: aload         7
      31: putfield      #6                  // Field val$method:Lio/grpc/MethodDescriptor;
      34: aload_0
      35: aload_2
      36: invokespecial #7                  // Method io/grpc/ForwardingClientCall$SimpleForwardingClientCall."<init>":(Lio/grpc/ClientCall;)V
      39: return

  public void start(io.grpc.ClientCall$Listener<RespT>, io.grpc.Metadata);
    Code:
       0: aload_0
       1: getfield      #2                  // Field val$deadline:Lio/grpc/Deadline;
       4: ifnonnull     11
       7: aconst_null
       8: goto          24
      11: aload_0
      12: getfield      #2                  // Field val$deadline:Lio/grpc/Deadline;
      15: getstatic     #8                  // Field java/util/concurrent/TimeUnit.NANOSECONDS:Ljava/util/concurrent/TimeUnit;
      18: invokevirtual #9                  // Method io/grpc/Deadline.timeRemaining:(Ljava/util/concurrent/TimeUnit;)J
      21: invokestatic  #10                 // Method com/google/protobuf/util/Durations.fromNanos:(J)Lcom/google/protobuf/Duration;
      24: astore_3
      25: aload_0
      26: getfield      #1                  // Field this$1:Lio/grpc/protobuf/services/BinlogHelper$1;
      29: getfield      #11                 // Field io/grpc/protobuf/services/BinlogHelper$1.this$0:Lio/grpc/protobuf/services/BinlogHelper;
      32: getfield      #12                 // Field io/grpc/protobuf/services/BinlogHelper.writer:Lio/grpc/protobuf/services/BinlogHelper$SinkWriter;
      35: aload_0
      36: getfield      #3                  // Field val$seq:Ljava/util/concurrent/atomic/AtomicLong;
      39: invokevirtual #13                 // Method java/util/concurrent/atomic/AtomicLong.getAndIncrement:()J
      42: aload_0
      43: getfield      #4                  // Field val$methodName:Ljava/lang/String;
      46: aload_0
      47: getfield      #5                  // Field val$authority:Ljava/lang/String;
      50: aload_3
      51: aload_2
      52: getstatic     #14                 // Field io/grpc/binarylog/v1/GrpcLogEntry$Logger.LOGGER_CLIENT:Lio/grpc/binarylog/v1/GrpcLogEntry$Logger;
      55: aload_0
      56: getfield      #1                  // Field this$1:Lio/grpc/protobuf/services/BinlogHelper$1;
      59: getfield      #15                 // Field io/grpc/protobuf/services/BinlogHelper$1.val$callId:J
      62: aconst_null
      63: invokevirtual #16                 // Method io/grpc/protobuf/services/BinlogHelper$SinkWriter.logClientHeader:(JLjava/lang/String;Ljava/lang/String;Lcom/google/protobuf/Duration;Lio/grpc/Metadata;Lio/grpc/binarylog/v1/GrpcLogEntry$Logger;JLjava/net/SocketAddress;)V
      66: new           #17                 // class io/grpc/protobuf/services/BinlogHelper$1$1$1
      69: dup
      70: aload_0
      71: aload_1
      72: invokespecial #18                 // Method io/grpc/protobuf/services/BinlogHelper$1$1$1."<init>":(Lio/grpc/protobuf/services/BinlogHelper$1$1;Lio/grpc/ClientCall$Listener;)V
      75: astore        4
      77: aload_0
      78: aload         4
      80: aload_2
      81: invokespecial #19                 // Method io/grpc/ForwardingClientCall$SimpleForwardingClientCall.start:(Lio/grpc/ClientCall$Listener;Lio/grpc/Metadata;)V
      84: return

  public void sendMessage(ReqT);
    Code:
       0: aload_0
       1: getfield      #1                  // Field this$1:Lio/grpc/protobuf/services/BinlogHelper$1;
       4: getfield      #11                 // Field io/grpc/protobuf/services/BinlogHelper$1.this$0:Lio/grpc/protobuf/services/BinlogHelper;
       7: getfield      #12                 // Field io/grpc/protobuf/services/BinlogHelper.writer:Lio/grpc/protobuf/services/BinlogHelper$SinkWriter;
      10: aload_0
      11: getfield      #3                  // Field val$seq:Ljava/util/concurrent/atomic/AtomicLong;
      14: invokevirtual #13                 // Method java/util/concurrent/atomic/AtomicLong.getAndIncrement:()J
      17: getstatic     #20                 // Field io/grpc/binarylog/v1/GrpcLogEntry$EventType.EVENT_TYPE_CLIENT_MESSAGE:Lio/grpc/binarylog/v1/GrpcLogEntry$EventType;
      20: aload_0
      21: getfield      #6                  // Field val$method:Lio/grpc/MethodDescriptor;
      24: invokevirtual #21                 // Method io/grpc/MethodDescriptor.getRequestMarshaller:()Lio/grpc/MethodDescriptor$Marshaller;
      27: aload_1
      28: getstatic     #14                 // Field io/grpc/binarylog/v1/GrpcLogEntry$Logger.LOGGER_CLIENT:Lio/grpc/binarylog/v1/GrpcLogEntry$Logger;
      31: aload_0
      32: getfield      #1                  // Field this$1:Lio/grpc/protobuf/services/BinlogHelper$1;
      35: getfield      #15                 // Field io/grpc/protobuf/services/BinlogHelper$1.val$callId:J
      38: invokevirtual #22                 // Method io/grpc/protobuf/services/BinlogHelper$SinkWriter.logRpcMessage:(JLio/grpc/binarylog/v1/GrpcLogEntry$EventType;Lio/grpc/MethodDescriptor$Marshaller;Ljava/lang/Object;Lio/grpc/binarylog/v1/GrpcLogEntry$Logger;J)V
      41: aload_0
      42: aload_1
      43: invokespecial #23                 // Method io/grpc/ForwardingClientCall$SimpleForwardingClientCall.sendMessage:(Ljava/lang/Object;)V
      46: return

  public void halfClose();
    Code:
       0: aload_0
       1: getfield      #1                  // Field this$1:Lio/grpc/protobuf/services/BinlogHelper$1;
       4: getfield      #11                 // Field io/grpc/protobuf/services/BinlogHelper$1.this$0:Lio/grpc/protobuf/services/BinlogHelper;
       7: getfield      #12                 // Field io/grpc/protobuf/services/BinlogHelper.writer:Lio/grpc/protobuf/services/BinlogHelper$SinkWriter;
      10: aload_0
      11: getfield      #3                  // Field val$seq:Ljava/util/concurrent/atomic/AtomicLong;
      14: invokevirtual #13                 // Method java/util/concurrent/atomic/AtomicLong.getAndIncrement:()J
      17: getstatic     #14                 // Field io/grpc/binarylog/v1/GrpcLogEntry$Logger.LOGGER_CLIENT:Lio/grpc/binarylog/v1/GrpcLogEntry$Logger;
      20: aload_0
      21: getfield      #1                  // Field this$1:Lio/grpc/protobuf/services/BinlogHelper$1;
      24: getfield      #15                 // Field io/grpc/protobuf/services/BinlogHelper$1.val$callId:J
      27: invokevirtual #24                 // Method io/grpc/protobuf/services/BinlogHelper$SinkWriter.logHalfClose:(JLio/grpc/binarylog/v1/GrpcLogEntry$Logger;J)V
      30: aload_0
      31: invokespecial #25                 // Method io/grpc/ForwardingClientCall$SimpleForwardingClientCall.halfClose:()V
      34: return

  public void cancel(java.lang.String, java.lang.Throwable);
    Code:
       0: aload_0
       1: getfield      #1                  // Field this$1:Lio/grpc/protobuf/services/BinlogHelper$1;
       4: getfield      #11                 // Field io/grpc/protobuf/services/BinlogHelper$1.this$0:Lio/grpc/protobuf/services/BinlogHelper;
       7: getfield      #12                 // Field io/grpc/protobuf/services/BinlogHelper.writer:Lio/grpc/protobuf/services/BinlogHelper$SinkWriter;
      10: aload_0
      11: getfield      #3                  // Field val$seq:Ljava/util/concurrent/atomic/AtomicLong;
      14: invokevirtual #13                 // Method java/util/concurrent/atomic/AtomicLong.getAndIncrement:()J
      17: getstatic     #14                 // Field io/grpc/binarylog/v1/GrpcLogEntry$Logger.LOGGER_CLIENT:Lio/grpc/binarylog/v1/GrpcLogEntry$Logger;
      20: aload_0
      21: getfield      #1                  // Field this$1:Lio/grpc/protobuf/services/BinlogHelper$1;
      24: getfield      #15                 // Field io/grpc/protobuf/services/BinlogHelper$1.val$callId:J
      27: invokevirtual #26                 // Method io/grpc/protobuf/services/BinlogHelper$SinkWriter.logCancel:(JLio/grpc/binarylog/v1/GrpcLogEntry$Logger;J)V
      30: aload_0
      31: aload_1
      32: aload_2
      33: invokespecial #27                 // Method io/grpc/ForwardingClientCall$SimpleForwardingClientCall.cancel:(Ljava/lang/String;Ljava/lang/Throwable;)V
      36: return
}
