Compiled from "AbstractInstant.java"
public abstract class org.joda.time.base.AbstractInstant implements org.joda.time.ReadableInstant {
  protected org.joda.time.base.AbstractInstant();
    Code:
       0: aload_0
       1: invokespecial #1                  // Method java/lang/Object."<init>":()V
       4: return

  public org.joda.time.DateTimeZone getZone();
    Code:
       0: aload_0
       1: invokevirtual #2                  // Method getChronology:()Lorg/joda/time/Chronology;
       4: invokevirtual #3                  // Method org/joda/time/Chronology.getZone:()Lorg/joda/time/DateTimeZone;
       7: areturn

  public int get(org.joda.time.DateTimeFieldType);
    Code:
       0: aload_1
       1: ifnonnull     14
       4: new           #4                  // class java/lang/IllegalArgumentException
       7: dup
       8: ldc           #5                  // String The DateTimeFieldType must not be null
      10: invokespecial #6                  // Method java/lang/IllegalArgumentException."<init>":(Ljava/lang/String;)V
      13: athrow
      14: aload_1
      15: aload_0
      16: invokevirtual #2                  // Method getChronology:()Lorg/joda/time/Chronology;
      19: invokevirtual #7                  // Method org/joda/time/DateTimeFieldType.getField:(Lorg/joda/time/Chronology;)Lorg/joda/time/DateTimeField;
      22: aload_0
      23: invokevirtual #8                  // Method getMillis:()J
      26: invokevirtual #9                  // Method org/joda/time/DateTimeField.get:(J)I
      29: ireturn

  public boolean isSupported(org.joda.time.DateTimeFieldType);
    Code:
       0: aload_1
       1: ifnonnull     6
       4: iconst_0
       5: ireturn
       6: aload_1
       7: aload_0
       8: invokevirtual #2                  // Method getChronology:()Lorg/joda/time/Chronology;
      11: invokevirtual #7                  // Method org/joda/time/DateTimeFieldType.getField:(Lorg/joda/time/Chronology;)Lorg/joda/time/DateTimeField;
      14: invokevirtual #10                 // Method org/joda/time/DateTimeField.isSupported:()Z
      17: ireturn

  public int get(org.joda.time.DateTimeField);
    Code:
       0: aload_1
       1: ifnonnull     14
       4: new           #4                  // class java/lang/IllegalArgumentException
       7: dup
       8: ldc           #11                 // String The DateTimeField must not be null
      10: invokespecial #6                  // Method java/lang/IllegalArgumentException."<init>":(Ljava/lang/String;)V
      13: athrow
      14: aload_1
      15: aload_0
      16: invokevirtual #8                  // Method getMillis:()J
      19: invokevirtual #9                  // Method org/joda/time/DateTimeField.get:(J)I
      22: ireturn

  public org.joda.time.Instant toInstant();
    Code:
       0: new           #12                 // class org/joda/time/Instant
       3: dup
       4: aload_0
       5: invokevirtual #8                  // Method getMillis:()J
       8: invokespecial #13                 // Method org/joda/time/Instant."<init>":(J)V
      11: areturn

  public org.joda.time.DateTime toDateTime();
    Code:
       0: new           #14                 // class org/joda/time/DateTime
       3: dup
       4: aload_0
       5: invokevirtual #8                  // Method getMillis:()J
       8: aload_0
       9: invokevirtual #15                 // Method getZone:()Lorg/joda/time/DateTimeZone;
      12: invokespecial #16                 // Method org/joda/time/DateTime."<init>":(JLorg/joda/time/DateTimeZone;)V
      15: areturn

  public org.joda.time.DateTime toDateTimeISO();
    Code:
       0: new           #14                 // class org/joda/time/DateTime
       3: dup
       4: aload_0
       5: invokevirtual #8                  // Method getMillis:()J
       8: aload_0
       9: invokevirtual #15                 // Method getZone:()Lorg/joda/time/DateTimeZone;
      12: invokestatic  #17                 // Method org/joda/time/chrono/ISOChronology.getInstance:(Lorg/joda/time/DateTimeZone;)Lorg/joda/time/chrono/ISOChronology;
      15: invokespecial #18                 // Method org/joda/time/DateTime."<init>":(JLorg/joda/time/Chronology;)V
      18: areturn

  public org.joda.time.DateTime toDateTime(org.joda.time.DateTimeZone);
    Code:
       0: aload_0
       1: invokevirtual #2                  // Method getChronology:()Lorg/joda/time/Chronology;
       4: invokestatic  #19                 // Method org/joda/time/DateTimeUtils.getChronology:(Lorg/joda/time/Chronology;)Lorg/joda/time/Chronology;
       7: astore_2
       8: aload_2
       9: aload_1
      10: invokevirtual #20                 // Method org/joda/time/Chronology.withZone:(Lorg/joda/time/DateTimeZone;)Lorg/joda/time/Chronology;
      13: astore_2
      14: new           #14                 // class org/joda/time/DateTime
      17: dup
      18: aload_0
      19: invokevirtual #8                  // Method getMillis:()J
      22: aload_2
      23: invokespecial #18                 // Method org/joda/time/DateTime."<init>":(JLorg/joda/time/Chronology;)V
      26: areturn

  public org.joda.time.DateTime toDateTime(org.joda.time.Chronology);
    Code:
       0: new           #14                 // class org/joda/time/DateTime
       3: dup
       4: aload_0
       5: invokevirtual #8                  // Method getMillis:()J
       8: aload_1
       9: invokespecial #18                 // Method org/joda/time/DateTime."<init>":(JLorg/joda/time/Chronology;)V
      12: areturn

  public org.joda.time.MutableDateTime toMutableDateTime();
    Code:
       0: new           #21                 // class org/joda/time/MutableDateTime
       3: dup
       4: aload_0
       5: invokevirtual #8                  // Method getMillis:()J
       8: aload_0
       9: invokevirtual #15                 // Method getZone:()Lorg/joda/time/DateTimeZone;
      12: invokespecial #22                 // Method org/joda/time/MutableDateTime."<init>":(JLorg/joda/time/DateTimeZone;)V
      15: areturn

  public org.joda.time.MutableDateTime toMutableDateTimeISO();
    Code:
       0: new           #21                 // class org/joda/time/MutableDateTime
       3: dup
       4: aload_0
       5: invokevirtual #8                  // Method getMillis:()J
       8: aload_0
       9: invokevirtual #15                 // Method getZone:()Lorg/joda/time/DateTimeZone;
      12: invokestatic  #17                 // Method org/joda/time/chrono/ISOChronology.getInstance:(Lorg/joda/time/DateTimeZone;)Lorg/joda/time/chrono/ISOChronology;
      15: invokespecial #23                 // Method org/joda/time/MutableDateTime."<init>":(JLorg/joda/time/Chronology;)V
      18: areturn

  public org.joda.time.MutableDateTime toMutableDateTime(org.joda.time.DateTimeZone);
    Code:
       0: aload_0
       1: invokevirtual #2                  // Method getChronology:()Lorg/joda/time/Chronology;
       4: invokestatic  #19                 // Method org/joda/time/DateTimeUtils.getChronology:(Lorg/joda/time/Chronology;)Lorg/joda/time/Chronology;
       7: astore_2
       8: aload_2
       9: aload_1
      10: invokevirtual #20                 // Method org/joda/time/Chronology.withZone:(Lorg/joda/time/DateTimeZone;)Lorg/joda/time/Chronology;
      13: astore_2
      14: new           #21                 // class org/joda/time/MutableDateTime
      17: dup
      18: aload_0
      19: invokevirtual #8                  // Method getMillis:()J
      22: aload_2
      23: invokespecial #23                 // Method org/joda/time/MutableDateTime."<init>":(JLorg/joda/time/Chronology;)V
      26: areturn

  public org.joda.time.MutableDateTime toMutableDateTime(org.joda.time.Chronology);
    Code:
       0: new           #21                 // class org/joda/time/MutableDateTime
       3: dup
       4: aload_0
       5: invokevirtual #8                  // Method getMillis:()J
       8: aload_1
       9: invokespecial #23                 // Method org/joda/time/MutableDateTime."<init>":(JLorg/joda/time/Chronology;)V
      12: areturn

  public java.util.Date toDate();
    Code:
       0: new           #24                 // class java/util/Date
       3: dup
       4: aload_0
       5: invokevirtual #8                  // Method getMillis:()J
       8: invokespecial #25                 // Method java/util/Date."<init>":(J)V
      11: areturn

  public boolean equals(java.lang.Object);
    Code:
       0: aload_0
       1: aload_1
       2: if_acmpne     7
       5: iconst_1
       6: ireturn
       7: aload_1
       8: instanceof    #26                 // class org/joda/time/ReadableInstant
      11: ifne          16
      14: iconst_0
      15: ireturn
      16: aload_1
      17: checkcast     #26                 // class org/joda/time/ReadableInstant
      20: astore_2
      21: aload_0
      22: invokevirtual #8                  // Method getMillis:()J
      25: aload_2
      26: invokeinterface #27,  1           // InterfaceMethod org/joda/time/ReadableInstant.getMillis:()J
      31: lcmp
      32: ifne          55
      35: aload_0
      36: invokevirtual #2                  // Method getChronology:()Lorg/joda/time/Chronology;
      39: aload_2
      40: invokeinterface #28,  1           // InterfaceMethod org/joda/time/ReadableInstant.getChronology:()Lorg/joda/time/Chronology;
      45: invokestatic  #29                 // Method org/joda/time/field/FieldUtils.equals:(Ljava/lang/Object;Ljava/lang/Object;)Z
      48: ifeq          55
      51: iconst_1
      52: goto          56
      55: iconst_0
      56: ireturn

  public int hashCode();
    Code:
       0: aload_0
       1: invokevirtual #8                  // Method getMillis:()J
       4: aload_0
       5: invokevirtual #8                  // Method getMillis:()J
       8: bipush        32
      10: lushr
      11: lxor
      12: l2i
      13: aload_0
      14: invokevirtual #2                  // Method getChronology:()Lorg/joda/time/Chronology;
      17: invokevirtual #30                 // Method java/lang/Object.hashCode:()I
      20: iadd
      21: ireturn

  public int compareTo(org.joda.time.ReadableInstant);
    Code:
       0: aload_0
       1: aload_1
       2: if_acmpne     7
       5: iconst_0
       6: ireturn
       7: aload_1
       8: invokeinterface #27,  1           // InterfaceMethod org/joda/time/ReadableInstant.getMillis:()J
      13: lstore_2
      14: aload_0
      15: invokevirtual #8                  // Method getMillis:()J
      18: lstore        4
      20: lload         4
      22: lload_2
      23: lcmp
      24: ifne          29
      27: iconst_0
      28: ireturn
      29: lload         4
      31: lload_2
      32: lcmp
      33: ifge          38
      36: iconst_m1
      37: ireturn
      38: iconst_1
      39: ireturn

  public boolean isAfter(long);
    Code:
       0: aload_0
       1: invokevirtual #8                  // Method getMillis:()J
       4: lload_1
       5: lcmp
       6: ifle          13
       9: iconst_1
      10: goto          14
      13: iconst_0
      14: ireturn

  public boolean isAfterNow();
    Code:
       0: aload_0
       1: invokestatic  #31                 // Method org/joda/time/DateTimeUtils.currentTimeMillis:()J
       4: invokevirtual #32                 // Method isAfter:(J)Z
       7: ireturn

  public boolean isAfter(org.joda.time.ReadableInstant);
    Code:
       0: aload_1
       1: invokestatic  #33                 // Method org/joda/time/DateTimeUtils.getInstantMillis:(Lorg/joda/time/ReadableInstant;)J
       4: lstore_2
       5: aload_0
       6: lload_2
       7: invokevirtual #32                 // Method isAfter:(J)Z
      10: ireturn

  public boolean isBefore(long);
    Code:
       0: aload_0
       1: invokevirtual #8                  // Method getMillis:()J
       4: lload_1
       5: lcmp
       6: ifge          13
       9: iconst_1
      10: goto          14
      13: iconst_0
      14: ireturn

  public boolean isBeforeNow();
    Code:
       0: aload_0
       1: invokestatic  #31                 // Method org/joda/time/DateTimeUtils.currentTimeMillis:()J
       4: invokevirtual #34                 // Method isBefore:(J)Z
       7: ireturn

  public boolean isBefore(org.joda.time.ReadableInstant);
    Code:
       0: aload_1
       1: invokestatic  #33                 // Method org/joda/time/DateTimeUtils.getInstantMillis:(Lorg/joda/time/ReadableInstant;)J
       4: lstore_2
       5: aload_0
       6: lload_2
       7: invokevirtual #34                 // Method isBefore:(J)Z
      10: ireturn

  public boolean isEqual(long);
    Code:
       0: aload_0
       1: invokevirtual #8                  // Method getMillis:()J
       4: lload_1
       5: lcmp
       6: ifne          13
       9: iconst_1
      10: goto          14
      13: iconst_0
      14: ireturn

  public boolean isEqualNow();
    Code:
       0: aload_0
       1: invokestatic  #31                 // Method org/joda/time/DateTimeUtils.currentTimeMillis:()J
       4: invokevirtual #35                 // Method isEqual:(J)Z
       7: ireturn

  public boolean isEqual(org.joda.time.ReadableInstant);
    Code:
       0: aload_1
       1: invokestatic  #33                 // Method org/joda/time/DateTimeUtils.getInstantMillis:(Lorg/joda/time/ReadableInstant;)J
       4: lstore_2
       5: aload_0
       6: lload_2
       7: invokevirtual #35                 // Method isEqual:(J)Z
      10: ireturn

  public java.lang.String toString();
    Code:
       0: invokestatic  #36                 // Method org/joda/time/format/ISODateTimeFormat.dateTime:()Lorg/joda/time/format/DateTimeFormatter;
       3: aload_0
       4: invokevirtual #37                 // Method org/joda/time/format/DateTimeFormatter.print:(Lorg/joda/time/ReadableInstant;)Ljava/lang/String;
       7: areturn

  public java.lang.String toString(org.joda.time.format.DateTimeFormatter);
    Code:
       0: aload_1
       1: ifnonnull     9
       4: aload_0
       5: invokevirtual #38                 // Method toString:()Ljava/lang/String;
       8: areturn
       9: aload_1
      10: aload_0
      11: invokevirtual #37                 // Method org/joda/time/format/DateTimeFormatter.print:(Lorg/joda/time/ReadableInstant;)Ljava/lang/String;
      14: areturn

  public int compareTo(java.lang.Object);
    Code:
       0: aload_0
       1: aload_1
       2: checkcast     #26                 // class org/joda/time/ReadableInstant
       5: invokevirtual #39                 // Method compareTo:(Lorg/joda/time/ReadableInstant;)I
       8: ireturn
}
