Compiled from "ResponseBodyEmitterReturnValueHandler.java"
class org.springframework.web.servlet.mvc.method.annotation.ResponseBodyEmitterReturnValueHandler$HttpMessageConvertingHandler implements org.springframework.web.servlet.mvc.method.annotation.ResponseBodyEmitter$Handler {
  private final org.springframework.http.server.ServerHttpResponse outputMessage;

  private final org.springframework.web.context.request.async.DeferredResult<?> deferredResult;

  final org.springframework.web.servlet.mvc.method.annotation.ResponseBodyEmitterReturnValueHandler this$0;

  public org.springframework.web.servlet.mvc.method.annotation.ResponseBodyEmitterReturnValueHandler$HttpMessageConvertingHandler(org.springframework.http.server.ServerHttpResponse, org.springframework.web.context.request.async.DeferredResult<?>);
    Code:
       0: aload_0
       1: aload_1
       2: putfield      #1                  // Field this$0:Lorg/springframework/web/servlet/mvc/method/annotation/ResponseBodyEmitterReturnValueHandler;
       5: aload_0
       6: invokespecial #2                  // Method java/lang/Object."<init>":()V
       9: aload_0
      10: aload_2
      11: putfield      #3                  // Field outputMessage:Lorg/springframework/http/server/ServerHttpResponse;
      14: aload_0
      15: aload_3
      16: putfield      #4                  // Field deferredResult:Lorg/springframework/web/context/request/async/DeferredResult;
      19: return

  public void send(java.lang.Object, org.springframework.http.MediaType) throws java.io.IOException;
    Code:
       0: aload_0
       1: aload_1
       2: aload_2
       3: invokespecial #5                  // Method sendInternal:(Ljava/lang/Object;Lorg/springframework/http/MediaType;)V
       6: return

  private <T> void sendInternal(T, org.springframework.http.MediaType) throws java.io.IOException;
    Code:
       0: invokestatic  #6                  // Method org/springframework/web/servlet/mvc/method/annotation/ResponseBodyEmitterReturnValueHandler.access$000:()Lorg/apache/commons/logging/Log;
       3: invokeinterface #7,  1            // InterfaceMethod org/apache/commons/logging/Log.isTraceEnabled:()Z
       8: ifeq          43
      11: invokestatic  #6                  // Method org/springframework/web/servlet/mvc/method/annotation/ResponseBodyEmitterReturnValueHandler.access$000:()Lorg/apache/commons/logging/Log;
      14: new           #8                  // class java/lang/StringBuilder
      17: dup
      18: invokespecial #9                  // Method java/lang/StringBuilder."<init>":()V
      21: ldc           #10                 // String Writing [
      23: invokevirtual #11                 // Method java/lang/StringBuilder.append:(Ljava/lang/String;)Ljava/lang/StringBuilder;
      26: aload_1
      27: invokevirtual #12                 // Method java/lang/StringBuilder.append:(Ljava/lang/Object;)Ljava/lang/StringBuilder;
      30: ldc           #13                 // String ]
      32: invokevirtual #11                 // Method java/lang/StringBuilder.append:(Ljava/lang/String;)Ljava/lang/StringBuilder;
      35: invokevirtual #14                 // Method java/lang/StringBuilder.toString:()Ljava/lang/String;
      38: invokeinterface #15,  2           // InterfaceMethod org/apache/commons/logging/Log.trace:(Ljava/lang/Object;)V
      43: aload_0
      44: getfield      #1                  // Field this$0:Lorg/springframework/web/servlet/mvc/method/annotation/ResponseBodyEmitterReturnValueHandler;
      47: invokestatic  #16                 // Method org/springframework/web/servlet/mvc/method/annotation/ResponseBodyEmitterReturnValueHandler.access$100:(Lorg/springframework/web/servlet/mvc/method/annotation/ResponseBodyEmitterReturnValueHandler;)Ljava/util/List;
      50: invokeinterface #17,  1           // InterfaceMethod java/util/List.iterator:()Ljava/util/Iterator;
      55: astore_3
      56: aload_3
      57: invokeinterface #18,  1           // InterfaceMethod java/util/Iterator.hasNext:()Z
      62: ifeq          117
      65: aload_3
      66: invokeinterface #19,  1           // InterfaceMethod java/util/Iterator.next:()Ljava/lang/Object;
      71: checkcast     #20                 // class org/springframework/http/converter/HttpMessageConverter
      74: astore        4
      76: aload         4
      78: aload_1
      79: invokevirtual #21                 // Method java/lang/Object.getClass:()Ljava/lang/Class;
      82: aload_2
      83: invokeinterface #22,  3           // InterfaceMethod org/springframework/http/converter/HttpMessageConverter.canWrite:(Ljava/lang/Class;Lorg/springframework/http/MediaType;)Z
      88: ifeq          114
      91: aload         4
      93: aload_1
      94: aload_2
      95: aload_0
      96: getfield      #3                  // Field outputMessage:Lorg/springframework/http/server/ServerHttpResponse;
      99: invokeinterface #23,  4           // InterfaceMethod org/springframework/http/converter/HttpMessageConverter.write:(Ljava/lang/Object;Lorg/springframework/http/MediaType;Lorg/springframework/http/HttpOutputMessage;)V
     104: aload_0
     105: getfield      #3                  // Field outputMessage:Lorg/springframework/http/server/ServerHttpResponse;
     108: invokeinterface #24,  1           // InterfaceMethod org/springframework/http/server/ServerHttpResponse.flush:()V
     113: return
     114: goto          56
     117: new           #25                 // class java/lang/IllegalArgumentException
     120: dup
     121: new           #8                  // class java/lang/StringBuilder
     124: dup
     125: invokespecial #9                  // Method java/lang/StringBuilder."<init>":()V
     128: ldc           #26                 // String No suitable converter for
     130: invokevirtual #11                 // Method java/lang/StringBuilder.append:(Ljava/lang/String;)Ljava/lang/StringBuilder;
     133: aload_1
     134: invokevirtual #21                 // Method java/lang/Object.getClass:()Ljava/lang/Class;
     137: invokevirtual #12                 // Method java/lang/StringBuilder.append:(Ljava/lang/Object;)Ljava/lang/StringBuilder;
     140: invokevirtual #14                 // Method java/lang/StringBuilder.toString:()Ljava/lang/String;
     143: invokespecial #27                 // Method java/lang/IllegalArgumentException."<init>":(Ljava/lang/String;)V
     146: athrow

  public void complete();
    Code:
       0: aload_0
       1: getfield      #4                  // Field deferredResult:Lorg/springframework/web/context/request/async/DeferredResult;
       4: aconst_null
       5: invokevirtual #28                 // Method org/springframework/web/context/request/async/DeferredResult.setResult:(Ljava/lang/Object;)Z
       8: pop
       9: return

  public void completeWithError(java.lang.Throwable);
    Code:
       0: aload_0
       1: getfield      #4                  // Field deferredResult:Lorg/springframework/web/context/request/async/DeferredResult;
       4: aload_1
       5: invokevirtual #29                 // Method org/springframework/web/context/request/async/DeferredResult.setErrorResult:(Ljava/lang/Object;)Z
       8: pop
       9: return

  public void onTimeout(java.lang.Runnable);
    Code:
       0: aload_0
       1: getfield      #4                  // Field deferredResult:Lorg/springframework/web/context/request/async/DeferredResult;
       4: aload_1
       5: invokevirtual #30                 // Method org/springframework/web/context/request/async/DeferredResult.onTimeout:(Ljava/lang/Runnable;)V
       8: return

  public void onError(java.util.function.Consumer<java.lang.Throwable>);
    Code:
       0: aload_0
       1: getfield      #4                  // Field deferredResult:Lorg/springframework/web/context/request/async/DeferredResult;
       4: aload_1
       5: invokevirtual #31                 // Method org/springframework/web/context/request/async/DeferredResult.onError:(Ljava/util/function/Consumer;)V
       8: return

  public void onCompletion(java.lang.Runnable);
    Code:
       0: aload_0
       1: getfield      #4                  // Field deferredResult:Lorg/springframework/web/context/request/async/DeferredResult;
       4: aload_1
       5: invokevirtual #32                 // Method org/springframework/web/context/request/async/DeferredResult.onCompletion:(Ljava/lang/Runnable;)V
       8: return
}
