Compiled from "LocalConnectionProvider.java"
class org.jboss.remoting3.LocalConnectionProvider$1 implements org.jboss.remoting3.spi.ConnectionHandlerFactory {
  final org.jboss.remoting3.LocalConnectionProvider this$0;

  org.jboss.remoting3.LocalConnectionProvider$1(org.jboss.remoting3.LocalConnectionProvider);
    Code:
       0: aload_0
       1: aload_1
       2: putfield      #1                  // Field this$0:Lorg/jboss/remoting3/LocalConnectionProvider;
       5: aload_0
       6: invokespecial #2                  // Method java/lang/Object."<init>":()V
       9: return

  public org.jboss.remoting3.spi.ConnectionHandler createInstance(org.jboss.remoting3.spi.ConnectionHandlerContext);
    Code:
       0: new           #3                  // class org/jboss/remoting3/LocalConnectionProvider$LoopbackConnectionHandler
       3: dup
       4: aload_0
       5: getfield      #1                  // Field this$0:Lorg/jboss/remoting3/LocalConnectionProvider;
       8: aload_1
       9: invokespecial #4                  // Method org/jboss/remoting3/LocalConnectionProvider$LoopbackConnectionHandler."<init>":(Lorg/jboss/remoting3/LocalConnectionProvider;Lorg/jboss/remoting3/spi/ConnectionHandlerContext;)V
      12: areturn
}
