Compiled from "FileUploadBase.java"
public class org.apache.commons.fileupload.FileUploadBase$FileSizeLimitExceededException extends org.apache.commons.fileupload.FileUploadBase$SizeException {
  private static final long serialVersionUID;

  private java.lang.String fileName;

  private java.lang.String fieldName;

  public org.apache.commons.fileupload.FileUploadBase$FileSizeLimitExceededException(java.lang.String, long, long);
    Code:
       0: aload_0
       1: aload_1
       2: lload_2
       3: lload         4
       5: invokespecial #1                  // Method org/apache/commons/fileupload/FileUploadBase$SizeException."<init>":(Ljava/lang/String;JJ)V
       8: return

  public java.lang.String getFileName();
    Code:
       0: aload_0
       1: getfield      #2                  // Field fileName:Ljava/lang/String;
       4: areturn

  public void setFileName(java.lang.String);
    Code:
       0: aload_0
       1: aload_1
       2: putfield      #2                  // Field fileName:Ljava/lang/String;
       5: return

  public java.lang.String getFieldName();
    Code:
       0: aload_0
       1: getfield      #3                  // Field fieldName:Ljava/lang/String;
       4: areturn

  public void setFieldName(java.lang.String);
    Code:
       0: aload_0
       1: aload_1
       2: putfield      #3                  // Field fieldName:Ljava/lang/String;
       5: return

  public long getPermittedSize();
    Code:
       0: aload_0
       1: invokespecial #4                  // Method org/apache/commons/fileupload/FileUploadBase$SizeException.getPermittedSize:()J
       4: lreturn

  public long getActualSize();
    Code:
       0: aload_0
       1: invokespecial #5                  // Method org/apache/commons/fileupload/FileUploadBase$SizeException.getActualSize:()J
       4: lreturn
}
