Compiled from "SortedSetCollectionInitializor.java"
public class org.hibernate.envers.internal.entities.mapper.relation.lazy.initializor.SortedSetCollectionInitializor extends org.hibernate.envers.internal.entities.mapper.relation.lazy.initializor.BasicCollectionInitializor<java.util.SortedSet> {
  private final java.util.Comparator comparator;

  public org.hibernate.envers.internal.entities.mapper.relation.lazy.initializor.SortedSetCollectionInitializor(org.hibernate.envers.boot.internal.EnversService, org.hibernate.envers.internal.reader.AuditReaderImplementor, org.hibernate.envers.internal.entities.mapper.relation.query.RelationQueryGenerator, java.lang.Object, java.lang.Number, boolean, java.lang.Class<? extends java.util.SortedSet>, org.hibernate.envers.internal.entities.mapper.relation.MiddleComponentData, java.util.Comparator);
    Code:
       0: aload_0
       1: aload_1
       2: aload_2
       3: aload_3
       4: aload         4
       6: aload         5
       8: iload         6
      10: aload         7
      12: aload         8
      14: invokespecial #1                  // Method org/hibernate/envers/internal/entities/mapper/relation/lazy/initializor/BasicCollectionInitializor."<init>":(Lorg/hibernate/envers/boot/internal/EnversService;Lorg/hibernate/envers/internal/reader/AuditReaderImplementor;Lorg/hibernate/envers/internal/entities/mapper/relation/query/RelationQueryGenerator;Ljava/lang/Object;Ljava/lang/Number;ZLjava/lang/Class;Lorg/hibernate/envers/internal/entities/mapper/relation/MiddleComponentData;)V
      17: aload_0
      18: aload         9
      20: putfield      #2                  // Field comparator:Ljava/util/Comparator;
      23: return

  protected java.util.SortedSet initializeCollection(int);
    Code:
       0: aload_0
       1: getfield      #2                  // Field comparator:Ljava/util/Comparator;
       4: ifnonnull     16
       7: aload_0
       8: iload_1
       9: invokespecial #3                  // Method org/hibernate/envers/internal/entities/mapper/relation/lazy/initializor/BasicCollectionInitializor.initializeCollection:(I)Ljava/util/Collection;
      12: checkcast     #4                  // class java/util/SortedSet
      15: areturn
      16: aload_0
      17: getfield      #5                  // Field collectionClass:Ljava/lang/Class;
      20: iconst_1
      21: anewarray     #6                  // class java/lang/Class
      24: dup
      25: iconst_0
      26: ldc           #7                  // class java/util/Comparator
      28: aastore
      29: invokevirtual #8                  // Method java/lang/Class.getConstructor:([Ljava/lang/Class;)Ljava/lang/reflect/Constructor;
      32: iconst_1
      33: anewarray     #9                  // class java/lang/Object
      36: dup
      37: iconst_0
      38: aload_0
      39: getfield      #2                  // Field comparator:Ljava/util/Comparator;
      42: aastore
      43: invokevirtual #10                 // Method java/lang/reflect/Constructor.newInstance:([Ljava/lang/Object;)Ljava/lang/Object;
      46: checkcast     #4                  // class java/util/SortedSet
      49: areturn
      50: astore_2
      51: new           #12                 // class org/hibernate/envers/exception/AuditException
      54: dup
      55: aload_2
      56: invokespecial #13                 // Method org/hibernate/envers/exception/AuditException."<init>":(Ljava/lang/Throwable;)V
      59: athrow
      60: astore_2
      61: new           #12                 // class org/hibernate/envers/exception/AuditException
      64: dup
      65: aload_2
      66: invokespecial #13                 // Method org/hibernate/envers/exception/AuditException."<init>":(Ljava/lang/Throwable;)V
      69: athrow
      70: astore_2
      71: new           #12                 // class org/hibernate/envers/exception/AuditException
      74: dup
      75: aload_2
      76: invokespecial #13                 // Method org/hibernate/envers/exception/AuditException."<init>":(Ljava/lang/Throwable;)V
      79: athrow
      80: astore_2
      81: new           #12                 // class org/hibernate/envers/exception/AuditException
      84: dup
      85: aload_2
      86: invokespecial #13                 // Method org/hibernate/envers/exception/AuditException."<init>":(Ljava/lang/Throwable;)V
      89: athrow
    Exception table:
       from    to  target type
          16    49    50   Class java/lang/InstantiationException
          16    49    60   Class java/lang/IllegalAccessException
          16    49    70   Class java/lang/NoSuchMethodException
          16    49    80   Class java/lang/reflect/InvocationTargetException

  protected java.util.Collection initializeCollection(int);
    Code:
       0: aload_0
       1: iload_1
       2: invokevirtual #17                 // Method initializeCollection:(I)Ljava/util/SortedSet;
       5: areturn

  protected java.lang.Object initializeCollection(int);
    Code:
       0: aload_0
       1: iload_1
       2: invokevirtual #17                 // Method initializeCollection:(I)Ljava/util/SortedSet;
       5: areturn
}
