Compiled from "Internal.java"
public class kotlin.reflect.jvm.internal.impl.protobuf.Internal {
  public static final byte[] EMPTY_BYTE_ARRAY;

  public static final java.nio.ByteBuffer EMPTY_BYTE_BUFFER;

  public static boolean isValidUtf8(byte[]);
    Code:
       0: aload_0
       1: invokestatic  #18                 // Method kotlin/reflect/jvm/internal/impl/protobuf/Utf8.isValidUtf8:([B)Z
       4: ireturn

  public static java.lang.String toStringUtf8(byte[]);
    Code:
       0: new           #7                  // class java/lang/String
       3: dup
       4: aload_0
       5: ldc           #1                  // String UTF-8
       7: invokespecial #16                 // Method java/lang/String."<init>":([BLjava/lang/String;)V
      10: areturn
      11: astore_1
      12: new           #6                  // class java/lang/RuntimeException
      15: dup
      16: ldc           #2                  // String UTF-8 not supported?
      18: aload_1
      19: invokespecial #15                 // Method java/lang/RuntimeException."<init>":(Ljava/lang/String;Ljava/lang/Throwable;)V
      22: athrow
    Exception table:
       from    to  target type
           0    10    11   Class java/io/UnsupportedEncodingException

  static {};
    Code:
       0: iconst_0
       1: newarray       byte
       3: putstatic     #13                 // Field EMPTY_BYTE_ARRAY:[B
       6: getstatic     #13                 // Field EMPTY_BYTE_ARRAY:[B
       9: invokestatic  #17                 // Method java/nio/ByteBuffer.wrap:([B)Ljava/nio/ByteBuffer;
      12: putstatic     #14                 // Field EMPTY_BYTE_BUFFER:Ljava/nio/ByteBuffer;
      15: return
}
