Compiled from "TableSorter.java"
public class groovy.inspect.swingui.TableSorter extends groovy.inspect.swingui.TableMap {
  int[] indexes;

  java.util.Vector sortingColumns;

  boolean ascending;

  int lastSortedColumn;

  public groovy.inspect.swingui.TableSorter();
    Code:
       0: aload_0
       1: invokespecial #19                 // Method groovy/inspect/swingui/TableMap."<init>":()V
       4: aload_0
       5: new           #21                 // class java/util/Vector
       8: dup
       9: invokespecial #22                 // Method java/util/Vector."<init>":()V
      12: putfield      #24                 // Field sortingColumns:Ljava/util/Vector;
      15: aload_0
      16: iconst_1
      17: putfield      #26                 // Field ascending:Z
      20: aload_0
      21: iconst_m1
      22: putfield      #28                 // Field lastSortedColumn:I
      25: aload_0
      26: iconst_0
      27: newarray       int
      29: putfield      #30                 // Field indexes:[I
      32: return

  public groovy.inspect.swingui.TableSorter(javax.swing.table.TableModel);
    Code:
       0: aload_0
       1: invokespecial #19                 // Method groovy/inspect/swingui/TableMap."<init>":()V
       4: aload_0
       5: new           #21                 // class java/util/Vector
       8: dup
       9: invokespecial #22                 // Method java/util/Vector."<init>":()V
      12: putfield      #24                 // Field sortingColumns:Ljava/util/Vector;
      15: aload_0
      16: iconst_1
      17: putfield      #26                 // Field ascending:Z
      20: aload_0
      21: iconst_m1
      22: putfield      #28                 // Field lastSortedColumn:I
      25: aload_0
      26: aload_1
      27: invokevirtual #36                 // Method setModel:(Ljavax/swing/table/TableModel;)V
      30: return

  public void setModel(javax.swing.table.TableModel);
    Code:
       0: aload_0
       1: aload_1
       2: invokespecial #39                 // Method groovy/inspect/swingui/TableMap.setModel:(Ljavax/swing/table/TableModel;)V
       5: aload_0
       6: invokevirtual #42                 // Method reallocateIndexes:()V
       9: return

  public int compareRowsByColumn(int, int, int);
    Code:
       0: aload_0
       1: getfield      #46                 // Field model:Ljavax/swing/table/TableModel;
       4: iload_3
       5: invokeinterface #52,  2           // InterfaceMethod javax/swing/table/TableModel.getColumnClass:(I)Ljava/lang/Class;
      10: astore        4
      12: aload_0
      13: getfield      #46                 // Field model:Ljavax/swing/table/TableModel;
      16: astore        5
      18: aload         5
      20: iload_1
      21: iload_3
      22: invokeinterface #56,  3           // InterfaceMethod javax/swing/table/TableModel.getValueAt:(II)Ljava/lang/Object;
      27: astore        6
      29: aload         5
      31: iload_2
      32: iload_3
      33: invokeinterface #56,  3           // InterfaceMethod javax/swing/table/TableModel.getValueAt:(II)Ljava/lang/Object;
      38: astore        7
      40: aload         6
      42: ifnonnull     52
      45: aload         7
      47: ifnonnull     52
      50: iconst_0
      51: ireturn
      52: aload         6
      54: ifnonnull     59
      57: iconst_m1
      58: ireturn
      59: aload         7
      61: ifnonnull     66
      64: iconst_1
      65: ireturn
      66: aload         4
      68: invokevirtual #64                 // Method java/lang/Class.getSuperclass:()Ljava/lang/Class;
      71: ldc           #66                 // class java/lang/Number
      73: if_acmpne     85
      76: aload         5
      78: iload_1
      79: iload_3
      80: iload_2
      81: invokestatic  #70                 // Method compareNumbers:(Ljavax/swing/table/TableModel;III)I
      84: ireturn
      85: aload         4
      87: ldc           #72                 // class java/util/Date
      89: if_acmpne     101
      92: aload         5
      94: iload_1
      95: iload_3
      96: iload_2
      97: invokestatic  #75                 // Method compareDates:(Ljavax/swing/table/TableModel;III)I
     100: ireturn
     101: aload         4
     103: ldc           #77                 // class java/lang/String
     105: if_acmpne     117
     108: aload         5
     110: iload_1
     111: iload_3
     112: iload_2
     113: invokestatic  #80                 // Method compareStrings:(Ljavax/swing/table/TableModel;III)I
     116: ireturn
     117: aload         4
     119: ldc           #82                 // class java/lang/Boolean
     121: if_acmpne     133
     124: aload         5
     126: iload_1
     127: iload_3
     128: iload_2
     129: invokestatic  #85                 // Method compareBooleans:(Ljavax/swing/table/TableModel;III)I
     132: ireturn
     133: aload         5
     135: iload_1
     136: iload_3
     137: iload_2
     138: invokestatic  #88                 // Method compareObjects:(Ljavax/swing/table/TableModel;III)I
     141: ireturn

  private static int compareObjects(javax.swing.table.TableModel, int, int, int);
    Code:
       0: aload_0
       1: iload_1
       2: iload_2
       3: invokeinterface #56,  3           // InterfaceMethod javax/swing/table/TableModel.getValueAt:(II)Ljava/lang/Object;
       8: astore        4
      10: aload         4
      12: invokevirtual #101                // Method java/lang/Object.toString:()Ljava/lang/String;
      15: astore        5
      17: aload_0
      18: iload_3
      19: iload_2
      20: invokeinterface #56,  3           // InterfaceMethod javax/swing/table/TableModel.getValueAt:(II)Ljava/lang/Object;
      25: astore        6
      27: aload         6
      29: invokevirtual #101                // Method java/lang/Object.toString:()Ljava/lang/String;
      32: astore        7
      34: aload         5
      36: aload         7
      38: invokevirtual #105                // Method java/lang/String.compareTo:(Ljava/lang/String;)I
      41: istore        8
      43: iload         8
      45: ifge          50
      48: iconst_m1
      49: ireturn
      50: iload         8
      52: ifle          57
      55: iconst_1
      56: ireturn
      57: iconst_0
      58: ireturn

  private static int compareBooleans(javax.swing.table.TableModel, int, int, int);
    Code:
       0: aload_0
       1: iload_1
       2: iload_2
       3: invokeinterface #56,  3           // InterfaceMethod javax/swing/table/TableModel.getValueAt:(II)Ljava/lang/Object;
       8: checkcast     #82                 // class java/lang/Boolean
      11: astore        4
      13: aload         4
      15: invokevirtual #115                // Method java/lang/Boolean.booleanValue:()Z
      18: istore        5
      20: aload_0
      21: iload_3
      22: iload_2
      23: invokeinterface #56,  3           // InterfaceMethod javax/swing/table/TableModel.getValueAt:(II)Ljava/lang/Object;
      28: checkcast     #82                 // class java/lang/Boolean
      31: astore        6
      33: aload         6
      35: invokevirtual #115                // Method java/lang/Boolean.booleanValue:()Z
      38: istore        7
      40: iload         5
      42: iload         7
      44: if_icmpne     49
      47: iconst_0
      48: ireturn
      49: iload         5
      51: ifeq          56
      54: iconst_1
      55: ireturn
      56: iconst_m1
      57: ireturn

  private static int compareStrings(javax.swing.table.TableModel, int, int, int);
    Code:
       0: aload_0
       1: iload_1
       2: iload_2
       3: invokeinterface #56,  3           // InterfaceMethod javax/swing/table/TableModel.getValueAt:(II)Ljava/lang/Object;
       8: checkcast     #77                 // class java/lang/String
      11: astore        4
      13: aload_0
      14: iload_3
      15: iload_2
      16: invokeinterface #56,  3           // InterfaceMethod javax/swing/table/TableModel.getValueAt:(II)Ljava/lang/Object;
      21: checkcast     #77                 // class java/lang/String
      24: astore        5
      26: aload         4
      28: aload         5
      30: invokevirtual #105                // Method java/lang/String.compareTo:(Ljava/lang/String;)I
      33: istore        6
      35: iload         6
      37: ifge          42
      40: iconst_m1
      41: ireturn
      42: iload         6
      44: ifle          49
      47: iconst_1
      48: ireturn
      49: iconst_0
      50: ireturn

  private static int compareDates(javax.swing.table.TableModel, int, int, int);
    Code:
       0: aload_0
       1: iload_1
       2: iload_2
       3: invokeinterface #56,  3           // InterfaceMethod javax/swing/table/TableModel.getValueAt:(II)Ljava/lang/Object;
       8: checkcast     #72                 // class java/util/Date
      11: astore        4
      13: aload         4
      15: invokevirtual #124                // Method java/util/Date.getTime:()J
      18: lstore        5
      20: aload_0
      21: iload_3
      22: iload_2
      23: invokeinterface #56,  3           // InterfaceMethod javax/swing/table/TableModel.getValueAt:(II)Ljava/lang/Object;
      28: checkcast     #72                 // class java/util/Date
      31: astore        7
      33: aload         7
      35: invokevirtual #124                // Method java/util/Date.getTime:()J
      38: lstore        8
      40: lload         5
      42: lload         8
      44: lcmp
      45: ifge          50
      48: iconst_m1
      49: ireturn
      50: lload         5
      52: lload         8
      54: lcmp
      55: ifle          60
      58: iconst_1
      59: ireturn
      60: iconst_0
      61: ireturn

  private static int compareNumbers(javax.swing.table.TableModel, int, int, int);
    Code:
       0: aload_0
       1: iload_1
       2: iload_2
       3: invokeinterface #56,  3           // InterfaceMethod javax/swing/table/TableModel.getValueAt:(II)Ljava/lang/Object;
       8: checkcast     #66                 // class java/lang/Number
      11: astore        4
      13: aload         4
      15: invokevirtual #134                // Method java/lang/Number.doubleValue:()D
      18: dstore        5
      20: aload_0
      21: iload_3
      22: iload_2
      23: invokeinterface #56,  3           // InterfaceMethod javax/swing/table/TableModel.getValueAt:(II)Ljava/lang/Object;
      28: checkcast     #66                 // class java/lang/Number
      31: astore        7
      33: aload         7
      35: invokevirtual #134                // Method java/lang/Number.doubleValue:()D
      38: dstore        8
      40: dload         5
      42: dload         8
      44: dcmpg
      45: ifge          50
      48: iconst_m1
      49: ireturn
      50: dload         5
      52: dload         8
      54: dcmpl
      55: ifle          60
      58: iconst_1
      59: ireturn
      60: iconst_0
      61: ireturn

  public int compare(int, int);
    Code:
       0: iconst_0
       1: istore_3
       2: iload_3
       3: aload_0
       4: getfield      #24                 // Field sortingColumns:Ljava/util/Vector;
       7: invokevirtual #142                // Method java/util/Vector.size:()I
      10: if_icmpge     66
      13: aload_0
      14: getfield      #24                 // Field sortingColumns:Ljava/util/Vector;
      17: iload_3
      18: invokevirtual #146                // Method java/util/Vector.elementAt:(I)Ljava/lang/Object;
      21: checkcast     #148                // class java/lang/Integer
      24: astore        4
      26: aload_0
      27: iload_1
      28: iload_2
      29: aload         4
      31: invokevirtual #151                // Method java/lang/Integer.intValue:()I
      34: invokevirtual #153                // Method compareRowsByColumn:(III)I
      37: istore        5
      39: iload         5
      41: ifeq          60
      44: aload_0
      45: getfield      #26                 // Field ascending:Z
      48: ifeq          56
      51: iload         5
      53: goto          59
      56: iload         5
      58: ineg
      59: ireturn
      60: iinc          3, 1
      63: goto          2
      66: iconst_0
      67: ireturn

  public void reallocateIndexes();
    Code:
       0: aload_0
       1: getfield      #46                 // Field model:Ljavax/swing/table/TableModel;
       4: invokeinterface #158,  1          // InterfaceMethod javax/swing/table/TableModel.getRowCount:()I
       9: istore_1
      10: aload_0
      11: iload_1
      12: newarray       int
      14: putfield      #30                 // Field indexes:[I
      17: iconst_0
      18: istore_2
      19: iload_2
      20: iload_1
      21: if_icmpge     37
      24: aload_0
      25: getfield      #30                 // Field indexes:[I
      28: iload_2
      29: iload_2
      30: iastore
      31: iinc          2, 1
      34: goto          19
      37: return

  public void tableChanged(javax.swing.event.TableModelEvent);
    Code:
       0: aload_0
       1: invokevirtual #42                 // Method reallocateIndexes:()V
       4: aload_0
       5: aload_1
       6: invokespecial #164                // Method groovy/inspect/swingui/TableMap.tableChanged:(Ljavax/swing/event/TableModelEvent;)V
       9: return

  public void checkModel();
    Code:
       0: aload_0
       1: getfield      #30                 // Field indexes:[I
       4: arraylength
       5: aload_0
       6: getfield      #46                 // Field model:Ljavax/swing/table/TableModel;
       9: invokeinterface #158,  1          // InterfaceMethod javax/swing/table/TableModel.getRowCount:()I
      14: if_icmpeq     25
      17: getstatic     #173                // Field java/lang/System.err:Ljava/io/PrintStream;
      20: ldc           #175                // String Sorter not informed of a change in model.
      22: invokevirtual #181                // Method java/io/PrintStream.println:(Ljava/lang/String;)V
      25: return

  public void sort(java.lang.Object);
    Code:
       0: aload_0
       1: invokevirtual #185                // Method checkModel:()V
       4: aload_0
       5: aload_0
       6: getfield      #30                 // Field indexes:[I
       9: invokevirtual #190                // Method "[I".clone:()Ljava/lang/Object;
      12: checkcast     #186                // class "[I"
      15: checkcast     #186                // class "[I"
      18: aload_0
      19: getfield      #30                 // Field indexes:[I
      22: iconst_0
      23: aload_0
      24: getfield      #30                 // Field indexes:[I
      27: arraylength
      28: invokevirtual #194                // Method shuttlesort:([I[III)V
      31: return

  public void n2sort();
    Code:
       0: iconst_0
       1: istore_1
       2: iload_1
       3: aload_0
       4: invokevirtual #197                // Method getRowCount:()I
       7: if_icmpge     60
      10: iload_1
      11: iconst_1
      12: iadd
      13: istore_2
      14: iload_2
      15: aload_0
      16: invokevirtual #197                // Method getRowCount:()I
      19: if_icmpge     54
      22: aload_0
      23: aload_0
      24: getfield      #30                 // Field indexes:[I
      27: iload_1
      28: iaload
      29: aload_0
      30: getfield      #30                 // Field indexes:[I
      33: iload_2
      34: iaload
      35: invokevirtual #199                // Method compare:(II)I
      38: iconst_m1
      39: if_icmpne     48
      42: aload_0
      43: iload_1
      44: iload_2
      45: invokevirtual #203                // Method swap:(II)V
      48: iinc          2, 1
      51: goto          14
      54: iinc          1, 1
      57: goto          2
      60: return

  public void shuttlesort(int[], int[], int, int);
    Code:
       0: iload         4
       2: iload_3
       3: isub
       4: iconst_2
       5: if_icmpge     9
       8: return
       9: iload_3
      10: iload         4
      12: iadd
      13: iconst_2
      14: idiv
      15: istore        5
      17: aload_0
      18: aload_2
      19: aload_1
      20: iload_3
      21: iload         5
      23: invokevirtual #194                // Method shuttlesort:([I[III)V
      26: aload_0
      27: aload_2
      28: aload_1
      29: iload         5
      31: iload         4
      33: invokevirtual #194                // Method shuttlesort:([I[III)V
      36: iload_3
      37: istore        6
      39: iload         5
      41: istore        7
      43: iload         4
      45: iload_3
      46: isub
      47: iconst_4
      48: if_icmplt     80
      51: aload_0
      52: aload_1
      53: iload         5
      55: iconst_1
      56: isub
      57: iaload
      58: aload_1
      59: iload         5
      61: iaload
      62: invokevirtual #199                // Method compare:(II)I
      65: ifgt          80
      68: aload_1
      69: iload_3
      70: aload_2
      71: iload_3
      72: iload         4
      74: iload_3
      75: isub
      76: invokestatic  #209                // Method java/lang/System.arraycopy:(Ljava/lang/Object;ILjava/lang/Object;II)V
      79: return
      80: iload_3
      81: istore        8
      83: iload         8
      85: iload         4
      87: if_icmpge     150
      90: iload         7
      92: iload         4
      94: if_icmpge     119
      97: iload         6
      99: iload         5
     101: if_icmpge     133
     104: aload_0
     105: aload_1
     106: iload         6
     108: iaload
     109: aload_1
     110: iload         7
     112: iaload
     113: invokevirtual #199                // Method compare:(II)I
     116: ifgt          133
     119: aload_2
     120: iload         8
     122: aload_1
     123: iload         6
     125: iinc          6, 1
     128: iaload
     129: iastore
     130: goto          144
     133: aload_2
     134: iload         8
     136: aload_1
     137: iload         7
     139: iinc          7, 1
     142: iaload
     143: iastore
     144: iinc          8, 1
     147: goto          83
     150: return

  public void swap(int, int);
    Code:
       0: aload_0
       1: getfield      #30                 // Field indexes:[I
       4: iload_1
       5: iaload
       6: istore_3
       7: aload_0
       8: getfield      #30                 // Field indexes:[I
      11: iload_1
      12: aload_0
      13: getfield      #30                 // Field indexes:[I
      16: iload_2
      17: iaload
      18: iastore
      19: aload_0
      20: getfield      #30                 // Field indexes:[I
      23: iload_2
      24: iload_3
      25: iastore
      26: return

  public java.lang.Object getValueAt(int, int);
    Code:
       0: aload_0
       1: invokevirtual #185                // Method checkModel:()V
       4: aload_0
       5: getfield      #46                 // Field model:Ljavax/swing/table/TableModel;
       8: aload_0
       9: getfield      #30                 // Field indexes:[I
      12: iload_1
      13: iaload
      14: iload_2
      15: invokeinterface #56,  3           // InterfaceMethod javax/swing/table/TableModel.getValueAt:(II)Ljava/lang/Object;
      20: areturn

  public void setValueAt(java.lang.Object, int, int);
    Code:
       0: aload_0
       1: invokevirtual #185                // Method checkModel:()V
       4: aload_0
       5: getfield      #46                 // Field model:Ljavax/swing/table/TableModel;
       8: aload_1
       9: aload_0
      10: getfield      #30                 // Field indexes:[I
      13: iload_2
      14: iaload
      15: iload_3
      16: invokeinterface #223,  4          // InterfaceMethod javax/swing/table/TableModel.setValueAt:(Ljava/lang/Object;II)V
      21: return

  public void sortByColumn(int);
    Code:
       0: aload_0
       1: iload_1
       2: iconst_1
       3: invokevirtual #229                // Method sortByColumn:(IZ)V
       6: return

  public void sortByColumn(int, boolean);
    Code:
       0: aload_0
       1: iload_2
       2: putfield      #26                 // Field ascending:Z
       5: aload_0
       6: getfield      #24                 // Field sortingColumns:Ljava/util/Vector;
       9: invokevirtual #232                // Method java/util/Vector.removeAllElements:()V
      12: aload_0
      13: getfield      #24                 // Field sortingColumns:Ljava/util/Vector;
      16: iload_1
      17: invokestatic  #236                // Method java/lang/Integer.valueOf:(I)Ljava/lang/Integer;
      20: invokevirtual #239                // Method java/util/Vector.addElement:(Ljava/lang/Object;)V
      23: aload_0
      24: aload_0
      25: invokevirtual #241                // Method sort:(Ljava/lang/Object;)V
      28: aload_0
      29: new           #243                // class javax/swing/event/TableModelEvent
      32: dup
      33: aload_0
      34: invokespecial #245                // Method javax/swing/event/TableModelEvent."<init>":(Ljavax/swing/table/TableModel;)V
      37: invokespecial #164                // Method groovy/inspect/swingui/TableMap.tableChanged:(Ljavax/swing/event/TableModelEvent;)V
      40: return

  public void addMouseListenerToHeaderInTable(javax.swing.JTable);
    Code:
       0: aload_0
       1: astore_2
       2: aload_1
       3: astore_3
       4: aload_3
       5: iconst_0
       6: invokevirtual #253                // Method javax/swing/JTable.setColumnSelectionAllowed:(Z)V
       9: new           #7                  // class groovy/inspect/swingui/TableSorter$1
      12: dup
      13: aload_0
      14: aload_3
      15: aload_2
      16: invokespecial #256                // Method groovy/inspect/swingui/TableSorter$1."<init>":(Lgroovy/inspect/swingui/TableSorter;Ljavax/swing/JTable;Lgroovy/inspect/swingui/TableSorter;)V
      19: astore        4
      21: aload_3
      22: invokevirtual #260                // Method javax/swing/JTable.getTableHeader:()Ljavax/swing/table/JTableHeader;
      25: astore        5
      27: aload         5
      29: aload         4
      31: invokevirtual #266                // Method javax/swing/table/JTableHeader.addMouseListener:(Ljava/awt/event/MouseListener;)V
      34: return
}
