Compiled from "ScriptToTreeNodeAdapter.groovy"
class groovy.inspect.swingui.TreeNodeBuildingVisitor extends org.codehaus.groovy.ast.CodeVisitorSupport implements groovy.lang.GroovyObject {
  private java.lang.Object currentNode;

  private final java.lang.Object adapter;

  private static org.codehaus.groovy.reflection.ClassInfo $staticClassInfo;

  public static transient boolean __$stMC;

  private transient groovy.lang.MetaClass metaClass;

  private static org.codehaus.groovy.reflection.ClassInfo $staticClassInfo$;

  private static java.lang.ref.SoftReference $callSiteArray;

  private groovy.inspect.swingui.TreeNodeBuildingVisitor(java.lang.Object);
    Code:
       0: invokestatic  #187                // Method $getCallSiteArray:()[Lorg/codehaus/groovy/runtime/callsite/CallSite;
       3: astore_2
       4: aload_0
       5: invokespecial #190                // Method org/codehaus/groovy/ast/CodeVisitorSupport."<init>":()V
       8: aload_0
       9: invokevirtual #194                // Method $getStaticMetaClass:()Lgroovy/lang/MetaClass;
      12: astore_3
      13: aload_3
      14: aload_0
      15: swap
      16: putfield      #196                // Field metaClass:Lgroovy/lang/MetaClass;
      19: aload_3
      20: pop
      21: aload_1
      22: invokestatic  #202                // Method org/codehaus/groovy/runtime/typehandling/DefaultTypeTransformation.booleanUnbox:(Ljava/lang/Object;)Z
      25: ifne          32
      28: iconst_1
      29: goto          33
      32: iconst_0
      33: ifeq          53
      36: aload_2
      37: ldc           #203                // int 0
      39: aaload
      40: ldc           #205                // class java/lang/IllegalArgumentException
      42: ldc           #207                // String Null: adapter
      44: invokeinterface #213,  3          // InterfaceMethod org/codehaus/groovy/runtime/callsite/CallSite.callConstructor:(Ljava/lang/Object;Ljava/lang/Object;)Ljava/lang/Object;
      49: checkcast     #215                // class java/lang/Throwable
      52: athrow
      53: aload_1
      54: astore        4
      56: aload         4
      58: aload_0
      59: swap
      60: putfield      #217                // Field adapter:Ljava/lang/Object;
      63: aload         4
      65: pop
      66: return

  private void addNode(java.lang.Object, java.lang.Class, groovy.lang.Closure);
    Code:
       0: invokestatic  #187                // Method $getCallSiteArray:()[Lorg/codehaus/groovy/runtime/callsite/CallSite;
       3: astore        4
       5: aload         4
       7: ldc           #222                // int 1
       9: aaload
      10: aload_2
      11: invokeinterface #226,  2          // InterfaceMethod org/codehaus/groovy/runtime/callsite/CallSite.call:(Ljava/lang/Object;)Ljava/lang/Object;
      16: aload         4
      18: ldc           #227                // int 2
      20: aaload
      21: aload         4
      23: ldc           #228                // int 3
      25: aaload
      26: aload_1
      27: invokeinterface #226,  2          // InterfaceMethod org/codehaus/groovy/runtime/callsite/CallSite.call:(Ljava/lang/Object;)Ljava/lang/Object;
      32: invokeinterface #226,  2          // InterfaceMethod org/codehaus/groovy/runtime/callsite/CallSite.call:(Ljava/lang/Object;)Ljava/lang/Object;
      37: invokestatic  #234                // Method org/codehaus/groovy/runtime/ScriptBytecodeAdapter.compareEqual:(Ljava/lang/Object;Ljava/lang/Object;)Z
      40: ifeq          202
      43: aload_0
      44: getfield      #236                // Field currentNode:Ljava/lang/Object;
      47: aconst_null
      48: invokestatic  #234                // Method org/codehaus/groovy/runtime/ScriptBytecodeAdapter.compareEqual:(Ljava/lang/Object;Ljava/lang/Object;)Z
      51: ifeq          97
      54: aload         4
      56: ldc           #237                // int 4
      58: aaload
      59: aload_0
      60: getfield      #217                // Field adapter:Ljava/lang/Object;
      63: aload_1
      64: invokeinterface #239,  3          // InterfaceMethod org/codehaus/groovy/runtime/callsite/CallSite.call:(Ljava/lang/Object;Ljava/lang/Object;)Ljava/lang/Object;
      69: astore        5
      71: aload         5
      73: aload_0
      74: swap
      75: putfield      #236                // Field currentNode:Ljava/lang/Object;
      78: aload         5
      80: pop
      81: aload         4
      83: ldc           #240                // int 5
      85: aaload
      86: aload_3
      87: aload_1
      88: invokeinterface #239,  3          // InterfaceMethod org/codehaus/groovy/runtime/callsite/CallSite.call:(Ljava/lang/Object;Ljava/lang/Object;)Ljava/lang/Object;
      93: pop
      94: goto          199
      97: aload_0
      98: getfield      #236                // Field currentNode:Ljava/lang/Object;
     101: astore        6
     103: aload         6
     105: pop
     106: aload         4
     108: ldc           #241                // int 6
     110: aaload
     111: aload_0
     112: getfield      #217                // Field adapter:Ljava/lang/Object;
     115: aload_1
     116: invokeinterface #239,  3          // InterfaceMethod org/codehaus/groovy/runtime/callsite/CallSite.call:(Ljava/lang/Object;Ljava/lang/Object;)Ljava/lang/Object;
     121: astore        7
     123: aload         7
     125: aload_0
     126: swap
     127: putfield      #236                // Field currentNode:Ljava/lang/Object;
     130: aload         7
     132: pop
     133: aload         4
     135: ldc           #242                // int 7
     137: aaload
     138: aload         6
     140: aload_0
     141: getfield      #236                // Field currentNode:Ljava/lang/Object;
     144: invokeinterface #239,  3          // InterfaceMethod org/codehaus/groovy/runtime/callsite/CallSite.call:(Ljava/lang/Object;Ljava/lang/Object;)Ljava/lang/Object;
     149: pop
     150: aload         6
     152: astore        8
     154: aload         8
     156: aconst_null
     157: aload_0
     158: getfield      #236                // Field currentNode:Ljava/lang/Object;
     161: ldc           #244                // String parent
     163: checkcast     #246                // class java/lang/String
     166: invokestatic  #250                // Method org/codehaus/groovy/runtime/ScriptBytecodeAdapter.setProperty:(Ljava/lang/Object;Ljava/lang/Class;Ljava/lang/Object;Ljava/lang/String;)V
     169: aload         8
     171: pop
     172: aload         4
     174: ldc           #251                // int 8
     176: aaload
     177: aload_3
     178: aload_1
     179: invokeinterface #239,  3          // InterfaceMethod org/codehaus/groovy/runtime/callsite/CallSite.call:(Ljava/lang/Object;Ljava/lang/Object;)Ljava/lang/Object;
     184: pop
     185: aload         6
     187: astore        9
     189: aload         9
     191: aload_0
     192: swap
     193: putfield      #236                // Field currentNode:Ljava/lang/Object;
     196: aload         9
     198: pop
     199: goto          215
     202: aload         4
     204: ldc           #252                // int 9
     206: aaload
     207: aload_3
     208: aload_1
     209: invokeinterface #239,  3          // InterfaceMethod org/codehaus/groovy/runtime/callsite/CallSite.call:(Ljava/lang/Object;Ljava/lang/Object;)Ljava/lang/Object;
     214: pop
     215: return

  public void visitBlockStatement(org.codehaus.groovy.ast.stmt.BlockStatement);
    Code:
       0: invokestatic  #187                // Method $getCallSiteArray:()[Lorg/codehaus/groovy/runtime/callsite/CallSite;
       3: astore_2
       4: aload_2
       5: ldc_w         #261                // int 10
       8: aaload
       9: aload_0
      10: aload_1
      11: ldc_w         #263                // class org/codehaus/groovy/ast/stmt/BlockStatement
      14: new           #9                  // class groovy/inspect/swingui/TreeNodeBuildingVisitor$_visitBlockStatement_closure1
      17: dup
      18: aload_0
      19: aload_0
      20: invokespecial #266                // Method groovy/inspect/swingui/TreeNodeBuildingVisitor$_visitBlockStatement_closure1."<init>":(Ljava/lang/Object;Ljava/lang/Object;)V
      23: invokeinterface #270,  5          // InterfaceMethod org/codehaus/groovy/runtime/callsite/CallSite.callCurrent:(Lgroovy/lang/GroovyObject;Ljava/lang/Object;Ljava/lang/Object;Ljava/lang/Object;)Ljava/lang/Object;
      28: pop
      29: return

  public void visitForLoop(org.codehaus.groovy.ast.stmt.ForStatement);
    Code:
       0: invokestatic  #187                // Method $getCallSiteArray:()[Lorg/codehaus/groovy/runtime/callsite/CallSite;
       3: astore_2
       4: aload_2
       5: ldc_w         #274                // int 11
       8: aaload
       9: aload_0
      10: aload_1
      11: ldc_w         #276                // class org/codehaus/groovy/ast/stmt/ForStatement
      14: new           #12                 // class groovy/inspect/swingui/TreeNodeBuildingVisitor$_visitForLoop_closure2
      17: dup
      18: aload_0
      19: aload_0
      20: invokespecial #277                // Method groovy/inspect/swingui/TreeNodeBuildingVisitor$_visitForLoop_closure2."<init>":(Ljava/lang/Object;Ljava/lang/Object;)V
      23: invokeinterface #270,  5          // InterfaceMethod org/codehaus/groovy/runtime/callsite/CallSite.callCurrent:(Lgroovy/lang/GroovyObject;Ljava/lang/Object;Ljava/lang/Object;Ljava/lang/Object;)Ljava/lang/Object;
      28: pop
      29: return

  public void visitWhileLoop(org.codehaus.groovy.ast.stmt.WhileStatement);
    Code:
       0: invokestatic  #187                // Method $getCallSiteArray:()[Lorg/codehaus/groovy/runtime/callsite/CallSite;
       3: astore_2
       4: aload_2
       5: ldc_w         #281                // int 12
       8: aaload
       9: aload_0
      10: aload_1
      11: ldc_w         #283                // class org/codehaus/groovy/ast/stmt/WhileStatement
      14: new           #15                 // class groovy/inspect/swingui/TreeNodeBuildingVisitor$_visitWhileLoop_closure3
      17: dup
      18: aload_0
      19: aload_0
      20: invokespecial #284                // Method groovy/inspect/swingui/TreeNodeBuildingVisitor$_visitWhileLoop_closure3."<init>":(Ljava/lang/Object;Ljava/lang/Object;)V
      23: invokeinterface #270,  5          // InterfaceMethod org/codehaus/groovy/runtime/callsite/CallSite.callCurrent:(Lgroovy/lang/GroovyObject;Ljava/lang/Object;Ljava/lang/Object;Ljava/lang/Object;)Ljava/lang/Object;
      28: pop
      29: return

  public void visitDoWhileLoop(org.codehaus.groovy.ast.stmt.DoWhileStatement);
    Code:
       0: invokestatic  #187                // Method $getCallSiteArray:()[Lorg/codehaus/groovy/runtime/callsite/CallSite;
       3: astore_2
       4: aload_2
       5: ldc_w         #288                // int 13
       8: aaload
       9: aload_0
      10: aload_1
      11: ldc_w         #290                // class org/codehaus/groovy/ast/stmt/DoWhileStatement
      14: new           #18                 // class groovy/inspect/swingui/TreeNodeBuildingVisitor$_visitDoWhileLoop_closure4
      17: dup
      18: aload_0
      19: aload_0
      20: invokespecial #291                // Method groovy/inspect/swingui/TreeNodeBuildingVisitor$_visitDoWhileLoop_closure4."<init>":(Ljava/lang/Object;Ljava/lang/Object;)V
      23: invokeinterface #270,  5          // InterfaceMethod org/codehaus/groovy/runtime/callsite/CallSite.callCurrent:(Lgroovy/lang/GroovyObject;Ljava/lang/Object;Ljava/lang/Object;Ljava/lang/Object;)Ljava/lang/Object;
      28: pop
      29: return

  public void visitIfElse(org.codehaus.groovy.ast.stmt.IfStatement);
    Code:
       0: invokestatic  #187                // Method $getCallSiteArray:()[Lorg/codehaus/groovy/runtime/callsite/CallSite;
       3: astore_2
       4: aload_2
       5: ldc_w         #295                // int 14
       8: aaload
       9: aload_0
      10: aload_1
      11: ldc_w         #297                // class org/codehaus/groovy/ast/stmt/IfStatement
      14: new           #21                 // class groovy/inspect/swingui/TreeNodeBuildingVisitor$_visitIfElse_closure5
      17: dup
      18: aload_0
      19: aload_0
      20: invokespecial #298                // Method groovy/inspect/swingui/TreeNodeBuildingVisitor$_visitIfElse_closure5."<init>":(Ljava/lang/Object;Ljava/lang/Object;)V
      23: invokeinterface #270,  5          // InterfaceMethod org/codehaus/groovy/runtime/callsite/CallSite.callCurrent:(Lgroovy/lang/GroovyObject;Ljava/lang/Object;Ljava/lang/Object;Ljava/lang/Object;)Ljava/lang/Object;
      28: pop
      29: return

  public void visitExpressionStatement(org.codehaus.groovy.ast.stmt.ExpressionStatement);
    Code:
       0: invokestatic  #187                // Method $getCallSiteArray:()[Lorg/codehaus/groovy/runtime/callsite/CallSite;
       3: astore_2
       4: aload_2
       5: ldc_w         #302                // int 15
       8: aaload
       9: aload_0
      10: aload_1
      11: ldc_w         #304                // class org/codehaus/groovy/ast/stmt/ExpressionStatement
      14: new           #24                 // class groovy/inspect/swingui/TreeNodeBuildingVisitor$_visitExpressionStatement_closure6
      17: dup
      18: aload_0
      19: aload_0
      20: invokespecial #305                // Method groovy/inspect/swingui/TreeNodeBuildingVisitor$_visitExpressionStatement_closure6."<init>":(Ljava/lang/Object;Ljava/lang/Object;)V
      23: invokeinterface #270,  5          // InterfaceMethod org/codehaus/groovy/runtime/callsite/CallSite.callCurrent:(Lgroovy/lang/GroovyObject;Ljava/lang/Object;Ljava/lang/Object;Ljava/lang/Object;)Ljava/lang/Object;
      28: pop
      29: return

  public void visitReturnStatement(org.codehaus.groovy.ast.stmt.ReturnStatement);
    Code:
       0: invokestatic  #187                // Method $getCallSiteArray:()[Lorg/codehaus/groovy/runtime/callsite/CallSite;
       3: astore_2
       4: aload_2
       5: ldc_w         #309                // int 16
       8: aaload
       9: aload_0
      10: aload_1
      11: ldc_w         #311                // class org/codehaus/groovy/ast/stmt/ReturnStatement
      14: new           #27                 // class groovy/inspect/swingui/TreeNodeBuildingVisitor$_visitReturnStatement_closure7
      17: dup
      18: aload_0
      19: aload_0
      20: invokespecial #312                // Method groovy/inspect/swingui/TreeNodeBuildingVisitor$_visitReturnStatement_closure7."<init>":(Ljava/lang/Object;Ljava/lang/Object;)V
      23: invokeinterface #270,  5          // InterfaceMethod org/codehaus/groovy/runtime/callsite/CallSite.callCurrent:(Lgroovy/lang/GroovyObject;Ljava/lang/Object;Ljava/lang/Object;Ljava/lang/Object;)Ljava/lang/Object;
      28: pop
      29: return

  public void visitAssertStatement(org.codehaus.groovy.ast.stmt.AssertStatement);
    Code:
       0: invokestatic  #187                // Method $getCallSiteArray:()[Lorg/codehaus/groovy/runtime/callsite/CallSite;
       3: astore_2
       4: aload_2
       5: ldc_w         #316                // int 17
       8: aaload
       9: aload_0
      10: aload_1
      11: ldc_w         #318                // class org/codehaus/groovy/ast/stmt/AssertStatement
      14: new           #30                 // class groovy/inspect/swingui/TreeNodeBuildingVisitor$_visitAssertStatement_closure8
      17: dup
      18: aload_0
      19: aload_0
      20: invokespecial #319                // Method groovy/inspect/swingui/TreeNodeBuildingVisitor$_visitAssertStatement_closure8."<init>":(Ljava/lang/Object;Ljava/lang/Object;)V
      23: invokeinterface #270,  5          // InterfaceMethod org/codehaus/groovy/runtime/callsite/CallSite.callCurrent:(Lgroovy/lang/GroovyObject;Ljava/lang/Object;Ljava/lang/Object;Ljava/lang/Object;)Ljava/lang/Object;
      28: pop
      29: return

  public void visitTryCatchFinally(org.codehaus.groovy.ast.stmt.TryCatchStatement);
    Code:
       0: invokestatic  #187                // Method $getCallSiteArray:()[Lorg/codehaus/groovy/runtime/callsite/CallSite;
       3: astore_2
       4: aload_2
       5: ldc_w         #323                // int 18
       8: aaload
       9: aload_0
      10: aload_1
      11: ldc_w         #325                // class org/codehaus/groovy/ast/stmt/TryCatchStatement
      14: new           #33                 // class groovy/inspect/swingui/TreeNodeBuildingVisitor$_visitTryCatchFinally_closure9
      17: dup
      18: aload_0
      19: aload_0
      20: invokespecial #326                // Method groovy/inspect/swingui/TreeNodeBuildingVisitor$_visitTryCatchFinally_closure9."<init>":(Ljava/lang/Object;Ljava/lang/Object;)V
      23: invokeinterface #270,  5          // InterfaceMethod org/codehaus/groovy/runtime/callsite/CallSite.callCurrent:(Lgroovy/lang/GroovyObject;Ljava/lang/Object;Ljava/lang/Object;Ljava/lang/Object;)Ljava/lang/Object;
      28: pop
      29: return

  protected void visitEmptyStatement(org.codehaus.groovy.ast.stmt.EmptyStatement);
    Code:
       0: invokestatic  #187                // Method $getCallSiteArray:()[Lorg/codehaus/groovy/runtime/callsite/CallSite;
       3: astore_2
       4: aload_2
       5: ldc_w         #330                // int 19
       8: aaload
       9: aload_0
      10: aload_1
      11: ldc_w         #332                // class org/codehaus/groovy/ast/stmt/EmptyStatement
      14: new           #36                 // class groovy/inspect/swingui/TreeNodeBuildingVisitor$_visitEmptyStatement_closure10
      17: dup
      18: aload_0
      19: aload_0
      20: invokespecial #333                // Method groovy/inspect/swingui/TreeNodeBuildingVisitor$_visitEmptyStatement_closure10."<init>":(Ljava/lang/Object;Ljava/lang/Object;)V
      23: invokeinterface #270,  5          // InterfaceMethod org/codehaus/groovy/runtime/callsite/CallSite.callCurrent:(Lgroovy/lang/GroovyObject;Ljava/lang/Object;Ljava/lang/Object;Ljava/lang/Object;)Ljava/lang/Object;
      28: pop
      29: return

  public void visitSwitch(org.codehaus.groovy.ast.stmt.SwitchStatement);
    Code:
       0: invokestatic  #187                // Method $getCallSiteArray:()[Lorg/codehaus/groovy/runtime/callsite/CallSite;
       3: astore_2
       4: aload_2
       5: ldc_w         #337                // int 20
       8: aaload
       9: aload_0
      10: aload_1
      11: ldc_w         #339                // class org/codehaus/groovy/ast/stmt/SwitchStatement
      14: new           #39                 // class groovy/inspect/swingui/TreeNodeBuildingVisitor$_visitSwitch_closure11
      17: dup
      18: aload_0
      19: aload_0
      20: invokespecial #340                // Method groovy/inspect/swingui/TreeNodeBuildingVisitor$_visitSwitch_closure11."<init>":(Ljava/lang/Object;Ljava/lang/Object;)V
      23: invokeinterface #270,  5          // InterfaceMethod org/codehaus/groovy/runtime/callsite/CallSite.callCurrent:(Lgroovy/lang/GroovyObject;Ljava/lang/Object;Ljava/lang/Object;Ljava/lang/Object;)Ljava/lang/Object;
      28: pop
      29: return

  public void visitCaseStatement(org.codehaus.groovy.ast.stmt.CaseStatement);
    Code:
       0: invokestatic  #187                // Method $getCallSiteArray:()[Lorg/codehaus/groovy/runtime/callsite/CallSite;
       3: astore_2
       4: aload_2
       5: ldc_w         #344                // int 21
       8: aaload
       9: aload_0
      10: aload_1
      11: ldc_w         #346                // class org/codehaus/groovy/ast/stmt/CaseStatement
      14: new           #42                 // class groovy/inspect/swingui/TreeNodeBuildingVisitor$_visitCaseStatement_closure12
      17: dup
      18: aload_0
      19: aload_0
      20: invokespecial #347                // Method groovy/inspect/swingui/TreeNodeBuildingVisitor$_visitCaseStatement_closure12."<init>":(Ljava/lang/Object;Ljava/lang/Object;)V
      23: invokeinterface #270,  5          // InterfaceMethod org/codehaus/groovy/runtime/callsite/CallSite.callCurrent:(Lgroovy/lang/GroovyObject;Ljava/lang/Object;Ljava/lang/Object;Ljava/lang/Object;)Ljava/lang/Object;
      28: pop
      29: return

  public void visitBreakStatement(org.codehaus.groovy.ast.stmt.BreakStatement);
    Code:
       0: invokestatic  #187                // Method $getCallSiteArray:()[Lorg/codehaus/groovy/runtime/callsite/CallSite;
       3: astore_2
       4: aload_2
       5: ldc_w         #351                // int 22
       8: aaload
       9: aload_0
      10: aload_1
      11: ldc_w         #353                // class org/codehaus/groovy/ast/stmt/BreakStatement
      14: new           #45                 // class groovy/inspect/swingui/TreeNodeBuildingVisitor$_visitBreakStatement_closure13
      17: dup
      18: aload_0
      19: aload_0
      20: invokespecial #354                // Method groovy/inspect/swingui/TreeNodeBuildingVisitor$_visitBreakStatement_closure13."<init>":(Ljava/lang/Object;Ljava/lang/Object;)V
      23: invokeinterface #270,  5          // InterfaceMethod org/codehaus/groovy/runtime/callsite/CallSite.callCurrent:(Lgroovy/lang/GroovyObject;Ljava/lang/Object;Ljava/lang/Object;Ljava/lang/Object;)Ljava/lang/Object;
      28: pop
      29: return

  public void visitContinueStatement(org.codehaus.groovy.ast.stmt.ContinueStatement);
    Code:
       0: invokestatic  #187                // Method $getCallSiteArray:()[Lorg/codehaus/groovy/runtime/callsite/CallSite;
       3: astore_2
       4: aload_2
       5: ldc_w         #358                // int 23
       8: aaload
       9: aload_0
      10: aload_1
      11: ldc_w         #360                // class org/codehaus/groovy/ast/stmt/ContinueStatement
      14: new           #48                 // class groovy/inspect/swingui/TreeNodeBuildingVisitor$_visitContinueStatement_closure14
      17: dup
      18: aload_0
      19: aload_0
      20: invokespecial #361                // Method groovy/inspect/swingui/TreeNodeBuildingVisitor$_visitContinueStatement_closure14."<init>":(Ljava/lang/Object;Ljava/lang/Object;)V
      23: invokeinterface #270,  5          // InterfaceMethod org/codehaus/groovy/runtime/callsite/CallSite.callCurrent:(Lgroovy/lang/GroovyObject;Ljava/lang/Object;Ljava/lang/Object;Ljava/lang/Object;)Ljava/lang/Object;
      28: pop
      29: return

  public void visitSynchronizedStatement(org.codehaus.groovy.ast.stmt.SynchronizedStatement);
    Code:
       0: invokestatic  #187                // Method $getCallSiteArray:()[Lorg/codehaus/groovy/runtime/callsite/CallSite;
       3: astore_2
       4: aload_2
       5: ldc_w         #365                // int 24
       8: aaload
       9: aload_0
      10: aload_1
      11: ldc_w         #367                // class org/codehaus/groovy/ast/stmt/SynchronizedStatement
      14: new           #51                 // class groovy/inspect/swingui/TreeNodeBuildingVisitor$_visitSynchronizedStatement_closure15
      17: dup
      18: aload_0
      19: aload_0
      20: invokespecial #368                // Method groovy/inspect/swingui/TreeNodeBuildingVisitor$_visitSynchronizedStatement_closure15."<init>":(Ljava/lang/Object;Ljava/lang/Object;)V
      23: invokeinterface #270,  5          // InterfaceMethod org/codehaus/groovy/runtime/callsite/CallSite.callCurrent:(Lgroovy/lang/GroovyObject;Ljava/lang/Object;Ljava/lang/Object;Ljava/lang/Object;)Ljava/lang/Object;
      28: pop
      29: return

  public void visitThrowStatement(org.codehaus.groovy.ast.stmt.ThrowStatement);
    Code:
       0: invokestatic  #187                // Method $getCallSiteArray:()[Lorg/codehaus/groovy/runtime/callsite/CallSite;
       3: astore_2
       4: aload_2
       5: ldc_w         #372                // int 25
       8: aaload
       9: aload_0
      10: aload_1
      11: ldc_w         #374                // class org/codehaus/groovy/ast/stmt/ThrowStatement
      14: new           #54                 // class groovy/inspect/swingui/TreeNodeBuildingVisitor$_visitThrowStatement_closure16
      17: dup
      18: aload_0
      19: aload_0
      20: invokespecial #375                // Method groovy/inspect/swingui/TreeNodeBuildingVisitor$_visitThrowStatement_closure16."<init>":(Ljava/lang/Object;Ljava/lang/Object;)V
      23: invokeinterface #270,  5          // InterfaceMethod org/codehaus/groovy/runtime/callsite/CallSite.callCurrent:(Lgroovy/lang/GroovyObject;Ljava/lang/Object;Ljava/lang/Object;Ljava/lang/Object;)Ljava/lang/Object;
      28: pop
      29: return

  public void visitMethodCallExpression(org.codehaus.groovy.ast.expr.MethodCallExpression);
    Code:
       0: invokestatic  #187                // Method $getCallSiteArray:()[Lorg/codehaus/groovy/runtime/callsite/CallSite;
       3: astore_2
       4: aload_2
       5: ldc_w         #379                // int 26
       8: aaload
       9: aload_0
      10: aload_1
      11: ldc_w         #381                // class org/codehaus/groovy/ast/expr/MethodCallExpression
      14: new           #57                 // class groovy/inspect/swingui/TreeNodeBuildingVisitor$_visitMethodCallExpression_closure17
      17: dup
      18: aload_0
      19: aload_0
      20: invokespecial #382                // Method groovy/inspect/swingui/TreeNodeBuildingVisitor$_visitMethodCallExpression_closure17."<init>":(Ljava/lang/Object;Ljava/lang/Object;)V
      23: invokeinterface #270,  5          // InterfaceMethod org/codehaus/groovy/runtime/callsite/CallSite.callCurrent:(Lgroovy/lang/GroovyObject;Ljava/lang/Object;Ljava/lang/Object;Ljava/lang/Object;)Ljava/lang/Object;
      28: pop
      29: return

  public void visitStaticMethodCallExpression(org.codehaus.groovy.ast.expr.StaticMethodCallExpression);
    Code:
       0: invokestatic  #187                // Method $getCallSiteArray:()[Lorg/codehaus/groovy/runtime/callsite/CallSite;
       3: astore_2
       4: aload_2
       5: ldc_w         #386                // int 27
       8: aaload
       9: aload_0
      10: aload_1
      11: ldc_w         #388                // class org/codehaus/groovy/ast/expr/StaticMethodCallExpression
      14: new           #60                 // class groovy/inspect/swingui/TreeNodeBuildingVisitor$_visitStaticMethodCallExpression_closure18
      17: dup
      18: aload_0
      19: aload_0
      20: invokespecial #389                // Method groovy/inspect/swingui/TreeNodeBuildingVisitor$_visitStaticMethodCallExpression_closure18."<init>":(Ljava/lang/Object;Ljava/lang/Object;)V
      23: invokeinterface #270,  5          // InterfaceMethod org/codehaus/groovy/runtime/callsite/CallSite.callCurrent:(Lgroovy/lang/GroovyObject;Ljava/lang/Object;Ljava/lang/Object;Ljava/lang/Object;)Ljava/lang/Object;
      28: pop
      29: return

  public void visitConstructorCallExpression(org.codehaus.groovy.ast.expr.ConstructorCallExpression);
    Code:
       0: invokestatic  #187                // Method $getCallSiteArray:()[Lorg/codehaus/groovy/runtime/callsite/CallSite;
       3: astore_2
       4: aload_2
       5: ldc_w         #393                // int 28
       8: aaload
       9: aload_0
      10: aload_1
      11: ldc_w         #395                // class org/codehaus/groovy/ast/expr/ConstructorCallExpression
      14: new           #63                 // class groovy/inspect/swingui/TreeNodeBuildingVisitor$_visitConstructorCallExpression_closure19
      17: dup
      18: aload_0
      19: aload_0
      20: invokespecial #396                // Method groovy/inspect/swingui/TreeNodeBuildingVisitor$_visitConstructorCallExpression_closure19."<init>":(Ljava/lang/Object;Ljava/lang/Object;)V
      23: invokeinterface #270,  5          // InterfaceMethod org/codehaus/groovy/runtime/callsite/CallSite.callCurrent:(Lgroovy/lang/GroovyObject;Ljava/lang/Object;Ljava/lang/Object;Ljava/lang/Object;)Ljava/lang/Object;
      28: pop
      29: return

  public void visitBinaryExpression(org.codehaus.groovy.ast.expr.BinaryExpression);
    Code:
       0: invokestatic  #187                // Method $getCallSiteArray:()[Lorg/codehaus/groovy/runtime/callsite/CallSite;
       3: astore_2
       4: aload_2
       5: ldc_w         #400                // int 29
       8: aaload
       9: aload_0
      10: aload_1
      11: ldc_w         #402                // class org/codehaus/groovy/ast/expr/BinaryExpression
      14: new           #66                 // class groovy/inspect/swingui/TreeNodeBuildingVisitor$_visitBinaryExpression_closure20
      17: dup
      18: aload_0
      19: aload_0
      20: invokespecial #403                // Method groovy/inspect/swingui/TreeNodeBuildingVisitor$_visitBinaryExpression_closure20."<init>":(Ljava/lang/Object;Ljava/lang/Object;)V
      23: invokeinterface #270,  5          // InterfaceMethod org/codehaus/groovy/runtime/callsite/CallSite.callCurrent:(Lgroovy/lang/GroovyObject;Ljava/lang/Object;Ljava/lang/Object;Ljava/lang/Object;)Ljava/lang/Object;
      28: pop
      29: return

  public void visitTernaryExpression(org.codehaus.groovy.ast.expr.TernaryExpression);
    Code:
       0: invokestatic  #187                // Method $getCallSiteArray:()[Lorg/codehaus/groovy/runtime/callsite/CallSite;
       3: astore_2
       4: aload_2
       5: ldc_w         #407                // int 30
       8: aaload
       9: aload_0
      10: aload_1
      11: ldc_w         #409                // class org/codehaus/groovy/ast/expr/TernaryExpression
      14: new           #69                 // class groovy/inspect/swingui/TreeNodeBuildingVisitor$_visitTernaryExpression_closure21
      17: dup
      18: aload_0
      19: aload_0
      20: invokespecial #410                // Method groovy/inspect/swingui/TreeNodeBuildingVisitor$_visitTernaryExpression_closure21."<init>":(Ljava/lang/Object;Ljava/lang/Object;)V
      23: invokeinterface #270,  5          // InterfaceMethod org/codehaus/groovy/runtime/callsite/CallSite.callCurrent:(Lgroovy/lang/GroovyObject;Ljava/lang/Object;Ljava/lang/Object;Ljava/lang/Object;)Ljava/lang/Object;
      28: pop
      29: return

  public void visitShortTernaryExpression(org.codehaus.groovy.ast.expr.ElvisOperatorExpression);
    Code:
       0: invokestatic  #187                // Method $getCallSiteArray:()[Lorg/codehaus/groovy/runtime/callsite/CallSite;
       3: astore_2
       4: aload_2
       5: ldc_w         #414                // int 31
       8: aaload
       9: aload_0
      10: aload_1
      11: ldc_w         #416                // class org/codehaus/groovy/ast/expr/ElvisOperatorExpression
      14: new           #72                 // class groovy/inspect/swingui/TreeNodeBuildingVisitor$_visitShortTernaryExpression_closure22
      17: dup
      18: aload_0
      19: aload_0
      20: invokespecial #417                // Method groovy/inspect/swingui/TreeNodeBuildingVisitor$_visitShortTernaryExpression_closure22."<init>":(Ljava/lang/Object;Ljava/lang/Object;)V
      23: invokeinterface #270,  5          // InterfaceMethod org/codehaus/groovy/runtime/callsite/CallSite.callCurrent:(Lgroovy/lang/GroovyObject;Ljava/lang/Object;Ljava/lang/Object;Ljava/lang/Object;)Ljava/lang/Object;
      28: pop
      29: return

  public void visitPostfixExpression(org.codehaus.groovy.ast.expr.PostfixExpression);
    Code:
       0: invokestatic  #187                // Method $getCallSiteArray:()[Lorg/codehaus/groovy/runtime/callsite/CallSite;
       3: astore_2
       4: aload_2
       5: ldc_w         #421                // int 32
       8: aaload
       9: aload_0
      10: aload_1
      11: ldc_w         #423                // class org/codehaus/groovy/ast/expr/PostfixExpression
      14: new           #75                 // class groovy/inspect/swingui/TreeNodeBuildingVisitor$_visitPostfixExpression_closure23
      17: dup
      18: aload_0
      19: aload_0
      20: invokespecial #424                // Method groovy/inspect/swingui/TreeNodeBuildingVisitor$_visitPostfixExpression_closure23."<init>":(Ljava/lang/Object;Ljava/lang/Object;)V
      23: invokeinterface #270,  5          // InterfaceMethod org/codehaus/groovy/runtime/callsite/CallSite.callCurrent:(Lgroovy/lang/GroovyObject;Ljava/lang/Object;Ljava/lang/Object;Ljava/lang/Object;)Ljava/lang/Object;
      28: pop
      29: return

  public void visitPrefixExpression(org.codehaus.groovy.ast.expr.PrefixExpression);
    Code:
       0: invokestatic  #187                // Method $getCallSiteArray:()[Lorg/codehaus/groovy/runtime/callsite/CallSite;
       3: astore_2
       4: aload_2
       5: ldc_w         #428                // int 33
       8: aaload
       9: aload_0
      10: aload_1
      11: ldc_w         #430                // class org/codehaus/groovy/ast/expr/PrefixExpression
      14: new           #78                 // class groovy/inspect/swingui/TreeNodeBuildingVisitor$_visitPrefixExpression_closure24
      17: dup
      18: aload_0
      19: aload_0
      20: invokespecial #431                // Method groovy/inspect/swingui/TreeNodeBuildingVisitor$_visitPrefixExpression_closure24."<init>":(Ljava/lang/Object;Ljava/lang/Object;)V
      23: invokeinterface #270,  5          // InterfaceMethod org/codehaus/groovy/runtime/callsite/CallSite.callCurrent:(Lgroovy/lang/GroovyObject;Ljava/lang/Object;Ljava/lang/Object;Ljava/lang/Object;)Ljava/lang/Object;
      28: pop
      29: return

  public void visitBooleanExpression(org.codehaus.groovy.ast.expr.BooleanExpression);
    Code:
       0: invokestatic  #187                // Method $getCallSiteArray:()[Lorg/codehaus/groovy/runtime/callsite/CallSite;
       3: astore_2
       4: aload_2
       5: ldc_w         #435                // int 34
       8: aaload
       9: aload_0
      10: aload_1
      11: ldc_w         #437                // class org/codehaus/groovy/ast/expr/BooleanExpression
      14: new           #81                 // class groovy/inspect/swingui/TreeNodeBuildingVisitor$_visitBooleanExpression_closure25
      17: dup
      18: aload_0
      19: aload_0
      20: invokespecial #438                // Method groovy/inspect/swingui/TreeNodeBuildingVisitor$_visitBooleanExpression_closure25."<init>":(Ljava/lang/Object;Ljava/lang/Object;)V
      23: invokeinterface #270,  5          // InterfaceMethod org/codehaus/groovy/runtime/callsite/CallSite.callCurrent:(Lgroovy/lang/GroovyObject;Ljava/lang/Object;Ljava/lang/Object;Ljava/lang/Object;)Ljava/lang/Object;
      28: pop
      29: return

  public void visitNotExpression(org.codehaus.groovy.ast.expr.NotExpression);
    Code:
       0: invokestatic  #187                // Method $getCallSiteArray:()[Lorg/codehaus/groovy/runtime/callsite/CallSite;
       3: astore_2
       4: aload_2
       5: ldc_w         #442                // int 35
       8: aaload
       9: aload_0
      10: aload_1
      11: ldc_w         #444                // class org/codehaus/groovy/ast/expr/NotExpression
      14: new           #84                 // class groovy/inspect/swingui/TreeNodeBuildingVisitor$_visitNotExpression_closure26
      17: dup
      18: aload_0
      19: aload_0
      20: invokespecial #445                // Method groovy/inspect/swingui/TreeNodeBuildingVisitor$_visitNotExpression_closure26."<init>":(Ljava/lang/Object;Ljava/lang/Object;)V
      23: invokeinterface #270,  5          // InterfaceMethod org/codehaus/groovy/runtime/callsite/CallSite.callCurrent:(Lgroovy/lang/GroovyObject;Ljava/lang/Object;Ljava/lang/Object;Ljava/lang/Object;)Ljava/lang/Object;
      28: pop
      29: return

  public void visitClosureExpression(org.codehaus.groovy.ast.expr.ClosureExpression);
    Code:
       0: invokestatic  #187                // Method $getCallSiteArray:()[Lorg/codehaus/groovy/runtime/callsite/CallSite;
       3: astore_2
       4: aload_2
       5: ldc_w         #449                // int 36
       8: aaload
       9: aload_0
      10: aload_1
      11: ldc_w         #451                // class org/codehaus/groovy/ast/expr/ClosureExpression
      14: new           #87                 // class groovy/inspect/swingui/TreeNodeBuildingVisitor$_visitClosureExpression_closure27
      17: dup
      18: aload_0
      19: aload_0
      20: invokespecial #452                // Method groovy/inspect/swingui/TreeNodeBuildingVisitor$_visitClosureExpression_closure27."<init>":(Ljava/lang/Object;Ljava/lang/Object;)V
      23: invokeinterface #270,  5          // InterfaceMethod org/codehaus/groovy/runtime/callsite/CallSite.callCurrent:(Lgroovy/lang/GroovyObject;Ljava/lang/Object;Ljava/lang/Object;Ljava/lang/Object;)Ljava/lang/Object;
      28: pop
      29: return

  public void visitParameter(org.codehaus.groovy.ast.Parameter);
    Code:
       0: aload_1
       1: new           #457                // class groovy/lang/Reference
       4: dup_x1
       5: swap
       6: invokespecial #459                // Method groovy/lang/Reference."<init>":(Ljava/lang/Object;)V
       9: astore_2
      10: invokestatic  #187                // Method $getCallSiteArray:()[Lorg/codehaus/groovy/runtime/callsite/CallSite;
      13: astore_3
      14: aload_3
      15: ldc_w         #460                // int 37
      18: aaload
      19: aload_0
      20: aload_2
      21: invokevirtual #464                // Method groovy/lang/Reference.get:()Ljava/lang/Object;
      24: checkcast     #466                // class org/codehaus/groovy/ast/Parameter
      27: ldc_w         #466                // class org/codehaus/groovy/ast/Parameter
      30: new           #90                 // class groovy/inspect/swingui/TreeNodeBuildingVisitor$_visitParameter_closure28
      33: dup
      34: aload_0
      35: aload_0
      36: aload_2
      37: invokespecial #469                // Method groovy/inspect/swingui/TreeNodeBuildingVisitor$_visitParameter_closure28."<init>":(Ljava/lang/Object;Ljava/lang/Object;Lgroovy/lang/Reference;)V
      40: invokeinterface #270,  5          // InterfaceMethod org/codehaus/groovy/runtime/callsite/CallSite.callCurrent:(Lgroovy/lang/GroovyObject;Ljava/lang/Object;Ljava/lang/Object;Ljava/lang/Object;)Ljava/lang/Object;
      45: pop
      46: return

  public void visitTupleExpression(org.codehaus.groovy.ast.expr.TupleExpression);
    Code:
       0: invokestatic  #187                // Method $getCallSiteArray:()[Lorg/codehaus/groovy/runtime/callsite/CallSite;
       3: astore_2
       4: aload_2
       5: ldc_w         #474                // int 38
       8: aaload
       9: aload_0
      10: aload_1
      11: ldc_w         #476                // class org/codehaus/groovy/ast/expr/TupleExpression
      14: new           #93                 // class groovy/inspect/swingui/TreeNodeBuildingVisitor$_visitTupleExpression_closure29
      17: dup
      18: aload_0
      19: aload_0
      20: invokespecial #477                // Method groovy/inspect/swingui/TreeNodeBuildingVisitor$_visitTupleExpression_closure29."<init>":(Ljava/lang/Object;Ljava/lang/Object;)V
      23: invokeinterface #270,  5          // InterfaceMethod org/codehaus/groovy/runtime/callsite/CallSite.callCurrent:(Lgroovy/lang/GroovyObject;Ljava/lang/Object;Ljava/lang/Object;Ljava/lang/Object;)Ljava/lang/Object;
      28: pop
      29: return

  public void visitListExpression(org.codehaus.groovy.ast.expr.ListExpression);
    Code:
       0: invokestatic  #187                // Method $getCallSiteArray:()[Lorg/codehaus/groovy/runtime/callsite/CallSite;
       3: astore_2
       4: aload_2
       5: ldc_w         #481                // int 39
       8: aaload
       9: aload_0
      10: aload_1
      11: ldc_w         #483                // class org/codehaus/groovy/ast/expr/ListExpression
      14: new           #96                 // class groovy/inspect/swingui/TreeNodeBuildingVisitor$_visitListExpression_closure30
      17: dup
      18: aload_0
      19: aload_0
      20: invokespecial #484                // Method groovy/inspect/swingui/TreeNodeBuildingVisitor$_visitListExpression_closure30."<init>":(Ljava/lang/Object;Ljava/lang/Object;)V
      23: invokeinterface #270,  5          // InterfaceMethod org/codehaus/groovy/runtime/callsite/CallSite.callCurrent:(Lgroovy/lang/GroovyObject;Ljava/lang/Object;Ljava/lang/Object;Ljava/lang/Object;)Ljava/lang/Object;
      28: pop
      29: return

  public void visitArrayExpression(org.codehaus.groovy.ast.expr.ArrayExpression);
    Code:
       0: invokestatic  #187                // Method $getCallSiteArray:()[Lorg/codehaus/groovy/runtime/callsite/CallSite;
       3: astore_2
       4: aload_2
       5: ldc_w         #488                // int 40
       8: aaload
       9: aload_0
      10: aload_1
      11: ldc_w         #490                // class org/codehaus/groovy/ast/expr/ArrayExpression
      14: new           #99                 // class groovy/inspect/swingui/TreeNodeBuildingVisitor$_visitArrayExpression_closure31
      17: dup
      18: aload_0
      19: aload_0
      20: invokespecial #491                // Method groovy/inspect/swingui/TreeNodeBuildingVisitor$_visitArrayExpression_closure31."<init>":(Ljava/lang/Object;Ljava/lang/Object;)V
      23: invokeinterface #270,  5          // InterfaceMethod org/codehaus/groovy/runtime/callsite/CallSite.callCurrent:(Lgroovy/lang/GroovyObject;Ljava/lang/Object;Ljava/lang/Object;Ljava/lang/Object;)Ljava/lang/Object;
      28: pop
      29: return

  public void visitMapExpression(org.codehaus.groovy.ast.expr.MapExpression);
    Code:
       0: invokestatic  #187                // Method $getCallSiteArray:()[Lorg/codehaus/groovy/runtime/callsite/CallSite;
       3: astore_2
       4: aload_2
       5: ldc_w         #495                // int 41
       8: aaload
       9: aload_0
      10: aload_1
      11: ldc_w         #497                // class org/codehaus/groovy/ast/expr/MapExpression
      14: new           #102                // class groovy/inspect/swingui/TreeNodeBuildingVisitor$_visitMapExpression_closure32
      17: dup
      18: aload_0
      19: aload_0
      20: invokespecial #498                // Method groovy/inspect/swingui/TreeNodeBuildingVisitor$_visitMapExpression_closure32."<init>":(Ljava/lang/Object;Ljava/lang/Object;)V
      23: invokeinterface #270,  5          // InterfaceMethod org/codehaus/groovy/runtime/callsite/CallSite.callCurrent:(Lgroovy/lang/GroovyObject;Ljava/lang/Object;Ljava/lang/Object;Ljava/lang/Object;)Ljava/lang/Object;
      28: pop
      29: return

  public void visitMapEntryExpression(org.codehaus.groovy.ast.expr.MapEntryExpression);
    Code:
       0: invokestatic  #187                // Method $getCallSiteArray:()[Lorg/codehaus/groovy/runtime/callsite/CallSite;
       3: astore_2
       4: aload_2
       5: ldc_w         #502                // int 42
       8: aaload
       9: aload_0
      10: aload_1
      11: ldc_w         #504                // class org/codehaus/groovy/ast/expr/MapEntryExpression
      14: new           #105                // class groovy/inspect/swingui/TreeNodeBuildingVisitor$_visitMapEntryExpression_closure33
      17: dup
      18: aload_0
      19: aload_0
      20: invokespecial #505                // Method groovy/inspect/swingui/TreeNodeBuildingVisitor$_visitMapEntryExpression_closure33."<init>":(Ljava/lang/Object;Ljava/lang/Object;)V
      23: invokeinterface #270,  5          // InterfaceMethod org/codehaus/groovy/runtime/callsite/CallSite.callCurrent:(Lgroovy/lang/GroovyObject;Ljava/lang/Object;Ljava/lang/Object;Ljava/lang/Object;)Ljava/lang/Object;
      28: pop
      29: return

  public void visitRangeExpression(org.codehaus.groovy.ast.expr.RangeExpression);
    Code:
       0: invokestatic  #187                // Method $getCallSiteArray:()[Lorg/codehaus/groovy/runtime/callsite/CallSite;
       3: astore_2
       4: aload_2
       5: ldc_w         #509                // int 43
       8: aaload
       9: aload_0
      10: aload_1
      11: ldc_w         #511                // class org/codehaus/groovy/ast/expr/RangeExpression
      14: new           #108                // class groovy/inspect/swingui/TreeNodeBuildingVisitor$_visitRangeExpression_closure34
      17: dup
      18: aload_0
      19: aload_0
      20: invokespecial #512                // Method groovy/inspect/swingui/TreeNodeBuildingVisitor$_visitRangeExpression_closure34."<init>":(Ljava/lang/Object;Ljava/lang/Object;)V
      23: invokeinterface #270,  5          // InterfaceMethod org/codehaus/groovy/runtime/callsite/CallSite.callCurrent:(Lgroovy/lang/GroovyObject;Ljava/lang/Object;Ljava/lang/Object;Ljava/lang/Object;)Ljava/lang/Object;
      28: pop
      29: return

  public void visitSpreadExpression(org.codehaus.groovy.ast.expr.SpreadExpression);
    Code:
       0: invokestatic  #187                // Method $getCallSiteArray:()[Lorg/codehaus/groovy/runtime/callsite/CallSite;
       3: astore_2
       4: aload_2
       5: ldc_w         #516                // int 44
       8: aaload
       9: aload_0
      10: aload_1
      11: ldc_w         #518                // class org/codehaus/groovy/ast/expr/SpreadExpression
      14: new           #111                // class groovy/inspect/swingui/TreeNodeBuildingVisitor$_visitSpreadExpression_closure35
      17: dup
      18: aload_0
      19: aload_0
      20: invokespecial #519                // Method groovy/inspect/swingui/TreeNodeBuildingVisitor$_visitSpreadExpression_closure35."<init>":(Ljava/lang/Object;Ljava/lang/Object;)V
      23: invokeinterface #270,  5          // InterfaceMethod org/codehaus/groovy/runtime/callsite/CallSite.callCurrent:(Lgroovy/lang/GroovyObject;Ljava/lang/Object;Ljava/lang/Object;Ljava/lang/Object;)Ljava/lang/Object;
      28: pop
      29: return

  public void visitSpreadMapExpression(org.codehaus.groovy.ast.expr.SpreadMapExpression);
    Code:
       0: invokestatic  #187                // Method $getCallSiteArray:()[Lorg/codehaus/groovy/runtime/callsite/CallSite;
       3: astore_2
       4: aload_2
       5: ldc_w         #523                // int 45
       8: aaload
       9: aload_0
      10: aload_1
      11: ldc_w         #525                // class org/codehaus/groovy/ast/expr/SpreadMapExpression
      14: new           #114                // class groovy/inspect/swingui/TreeNodeBuildingVisitor$_visitSpreadMapExpression_closure36
      17: dup
      18: aload_0
      19: aload_0
      20: invokespecial #526                // Method groovy/inspect/swingui/TreeNodeBuildingVisitor$_visitSpreadMapExpression_closure36."<init>":(Ljava/lang/Object;Ljava/lang/Object;)V
      23: invokeinterface #270,  5          // InterfaceMethod org/codehaus/groovy/runtime/callsite/CallSite.callCurrent:(Lgroovy/lang/GroovyObject;Ljava/lang/Object;Ljava/lang/Object;Ljava/lang/Object;)Ljava/lang/Object;
      28: pop
      29: return

  public void visitMethodPointerExpression(org.codehaus.groovy.ast.expr.MethodPointerExpression);
    Code:
       0: invokestatic  #187                // Method $getCallSiteArray:()[Lorg/codehaus/groovy/runtime/callsite/CallSite;
       3: astore_2
       4: aload_2
       5: ldc_w         #530                // int 46
       8: aaload
       9: aload_0
      10: aload_1
      11: ldc_w         #532                // class org/codehaus/groovy/ast/expr/MethodPointerExpression
      14: new           #117                // class groovy/inspect/swingui/TreeNodeBuildingVisitor$_visitMethodPointerExpression_closure37
      17: dup
      18: aload_0
      19: aload_0
      20: invokespecial #533                // Method groovy/inspect/swingui/TreeNodeBuildingVisitor$_visitMethodPointerExpression_closure37."<init>":(Ljava/lang/Object;Ljava/lang/Object;)V
      23: invokeinterface #270,  5          // InterfaceMethod org/codehaus/groovy/runtime/callsite/CallSite.callCurrent:(Lgroovy/lang/GroovyObject;Ljava/lang/Object;Ljava/lang/Object;Ljava/lang/Object;)Ljava/lang/Object;
      28: pop
      29: return

  public void visitUnaryMinusExpression(org.codehaus.groovy.ast.expr.UnaryMinusExpression);
    Code:
       0: invokestatic  #187                // Method $getCallSiteArray:()[Lorg/codehaus/groovy/runtime/callsite/CallSite;
       3: astore_2
       4: aload_2
       5: ldc_w         #537                // int 47
       8: aaload
       9: aload_0
      10: aload_1
      11: ldc_w         #539                // class org/codehaus/groovy/ast/expr/UnaryMinusExpression
      14: new           #120                // class groovy/inspect/swingui/TreeNodeBuildingVisitor$_visitUnaryMinusExpression_closure38
      17: dup
      18: aload_0
      19: aload_0
      20: invokespecial #540                // Method groovy/inspect/swingui/TreeNodeBuildingVisitor$_visitUnaryMinusExpression_closure38."<init>":(Ljava/lang/Object;Ljava/lang/Object;)V
      23: invokeinterface #270,  5          // InterfaceMethod org/codehaus/groovy/runtime/callsite/CallSite.callCurrent:(Lgroovy/lang/GroovyObject;Ljava/lang/Object;Ljava/lang/Object;Ljava/lang/Object;)Ljava/lang/Object;
      28: pop
      29: return

  public void visitUnaryPlusExpression(org.codehaus.groovy.ast.expr.UnaryPlusExpression);
    Code:
       0: invokestatic  #187                // Method $getCallSiteArray:()[Lorg/codehaus/groovy/runtime/callsite/CallSite;
       3: astore_2
       4: aload_2
       5: ldc_w         #544                // int 48
       8: aaload
       9: aload_0
      10: aload_1
      11: ldc_w         #546                // class org/codehaus/groovy/ast/expr/UnaryPlusExpression
      14: new           #123                // class groovy/inspect/swingui/TreeNodeBuildingVisitor$_visitUnaryPlusExpression_closure39
      17: dup
      18: aload_0
      19: aload_0
      20: invokespecial #547                // Method groovy/inspect/swingui/TreeNodeBuildingVisitor$_visitUnaryPlusExpression_closure39."<init>":(Ljava/lang/Object;Ljava/lang/Object;)V
      23: invokeinterface #270,  5          // InterfaceMethod org/codehaus/groovy/runtime/callsite/CallSite.callCurrent:(Lgroovy/lang/GroovyObject;Ljava/lang/Object;Ljava/lang/Object;Ljava/lang/Object;)Ljava/lang/Object;
      28: pop
      29: return

  public void visitBitwiseNegationExpression(org.codehaus.groovy.ast.expr.BitwiseNegationExpression);
    Code:
       0: invokestatic  #187                // Method $getCallSiteArray:()[Lorg/codehaus/groovy/runtime/callsite/CallSite;
       3: astore_2
       4: aload_2
       5: ldc_w         #551                // int 49
       8: aaload
       9: aload_0
      10: aload_1
      11: ldc_w         #553                // class org/codehaus/groovy/ast/expr/BitwiseNegationExpression
      14: new           #126                // class groovy/inspect/swingui/TreeNodeBuildingVisitor$_visitBitwiseNegationExpression_closure40
      17: dup
      18: aload_0
      19: aload_0
      20: invokespecial #554                // Method groovy/inspect/swingui/TreeNodeBuildingVisitor$_visitBitwiseNegationExpression_closure40."<init>":(Ljava/lang/Object;Ljava/lang/Object;)V
      23: invokeinterface #270,  5          // InterfaceMethod org/codehaus/groovy/runtime/callsite/CallSite.callCurrent:(Lgroovy/lang/GroovyObject;Ljava/lang/Object;Ljava/lang/Object;Ljava/lang/Object;)Ljava/lang/Object;
      28: pop
      29: return

  public void visitCastExpression(org.codehaus.groovy.ast.expr.CastExpression);
    Code:
       0: invokestatic  #187                // Method $getCallSiteArray:()[Lorg/codehaus/groovy/runtime/callsite/CallSite;
       3: astore_2
       4: aload_2
       5: ldc_w         #558                // int 50
       8: aaload
       9: aload_0
      10: aload_1
      11: ldc_w         #560                // class org/codehaus/groovy/ast/expr/CastExpression
      14: new           #129                // class groovy/inspect/swingui/TreeNodeBuildingVisitor$_visitCastExpression_closure41
      17: dup
      18: aload_0
      19: aload_0
      20: invokespecial #561                // Method groovy/inspect/swingui/TreeNodeBuildingVisitor$_visitCastExpression_closure41."<init>":(Ljava/lang/Object;Ljava/lang/Object;)V
      23: invokeinterface #270,  5          // InterfaceMethod org/codehaus/groovy/runtime/callsite/CallSite.callCurrent:(Lgroovy/lang/GroovyObject;Ljava/lang/Object;Ljava/lang/Object;Ljava/lang/Object;)Ljava/lang/Object;
      28: pop
      29: return

  public void visitConstantExpression(org.codehaus.groovy.ast.expr.ConstantExpression);
    Code:
       0: invokestatic  #187                // Method $getCallSiteArray:()[Lorg/codehaus/groovy/runtime/callsite/CallSite;
       3: astore_2
       4: aload_2
       5: ldc_w         #565                // int 51
       8: aaload
       9: aload_0
      10: aload_1
      11: ldc_w         #567                // class org/codehaus/groovy/ast/expr/ConstantExpression
      14: new           #132                // class groovy/inspect/swingui/TreeNodeBuildingVisitor$_visitConstantExpression_closure42
      17: dup
      18: aload_0
      19: aload_0
      20: invokespecial #568                // Method groovy/inspect/swingui/TreeNodeBuildingVisitor$_visitConstantExpression_closure42."<init>":(Ljava/lang/Object;Ljava/lang/Object;)V
      23: invokeinterface #270,  5          // InterfaceMethod org/codehaus/groovy/runtime/callsite/CallSite.callCurrent:(Lgroovy/lang/GroovyObject;Ljava/lang/Object;Ljava/lang/Object;Ljava/lang/Object;)Ljava/lang/Object;
      28: pop
      29: return

  public void visitClassExpression(org.codehaus.groovy.ast.expr.ClassExpression);
    Code:
       0: invokestatic  #187                // Method $getCallSiteArray:()[Lorg/codehaus/groovy/runtime/callsite/CallSite;
       3: astore_2
       4: aload_2
       5: ldc_w         #572                // int 52
       8: aaload
       9: aload_0
      10: aload_1
      11: ldc_w         #574                // class org/codehaus/groovy/ast/expr/ClassExpression
      14: new           #135                // class groovy/inspect/swingui/TreeNodeBuildingVisitor$_visitClassExpression_closure43
      17: dup
      18: aload_0
      19: aload_0
      20: invokespecial #575                // Method groovy/inspect/swingui/TreeNodeBuildingVisitor$_visitClassExpression_closure43."<init>":(Ljava/lang/Object;Ljava/lang/Object;)V
      23: invokeinterface #270,  5          // InterfaceMethod org/codehaus/groovy/runtime/callsite/CallSite.callCurrent:(Lgroovy/lang/GroovyObject;Ljava/lang/Object;Ljava/lang/Object;Ljava/lang/Object;)Ljava/lang/Object;
      28: pop
      29: return

  public void visitVariableExpression(org.codehaus.groovy.ast.expr.VariableExpression);
    Code:
       0: invokestatic  #187                // Method $getCallSiteArray:()[Lorg/codehaus/groovy/runtime/callsite/CallSite;
       3: astore_2
       4: aload_2
       5: ldc_w         #579                // int 53
       8: aaload
       9: aload_0
      10: aload_1
      11: ldc_w         #581                // class org/codehaus/groovy/ast/expr/VariableExpression
      14: new           #138                // class groovy/inspect/swingui/TreeNodeBuildingVisitor$_visitVariableExpression_closure44
      17: dup
      18: aload_0
      19: aload_0
      20: invokespecial #582                // Method groovy/inspect/swingui/TreeNodeBuildingVisitor$_visitVariableExpression_closure44."<init>":(Ljava/lang/Object;Ljava/lang/Object;)V
      23: invokeinterface #270,  5          // InterfaceMethod org/codehaus/groovy/runtime/callsite/CallSite.callCurrent:(Lgroovy/lang/GroovyObject;Ljava/lang/Object;Ljava/lang/Object;Ljava/lang/Object;)Ljava/lang/Object;
      28: pop
      29: return

  public void visitDeclarationExpression(org.codehaus.groovy.ast.expr.DeclarationExpression);
    Code:
       0: invokestatic  #187                // Method $getCallSiteArray:()[Lorg/codehaus/groovy/runtime/callsite/CallSite;
       3: astore_2
       4: aload_2
       5: ldc_w         #586                // int 54
       8: aaload
       9: aload_0
      10: aload_1
      11: ldc_w         #588                // class org/codehaus/groovy/ast/expr/DeclarationExpression
      14: new           #141                // class groovy/inspect/swingui/TreeNodeBuildingVisitor$_visitDeclarationExpression_closure45
      17: dup
      18: aload_0
      19: aload_0
      20: invokespecial #589                // Method groovy/inspect/swingui/TreeNodeBuildingVisitor$_visitDeclarationExpression_closure45."<init>":(Ljava/lang/Object;Ljava/lang/Object;)V
      23: invokeinterface #270,  5          // InterfaceMethod org/codehaus/groovy/runtime/callsite/CallSite.callCurrent:(Lgroovy/lang/GroovyObject;Ljava/lang/Object;Ljava/lang/Object;Ljava/lang/Object;)Ljava/lang/Object;
      28: pop
      29: return

  public void visitPropertyExpression(org.codehaus.groovy.ast.expr.PropertyExpression);
    Code:
       0: invokestatic  #187                // Method $getCallSiteArray:()[Lorg/codehaus/groovy/runtime/callsite/CallSite;
       3: astore_2
       4: aload_2
       5: ldc_w         #593                // int 55
       8: aaload
       9: aload_0
      10: aload_1
      11: ldc_w         #595                // class org/codehaus/groovy/ast/expr/PropertyExpression
      14: new           #144                // class groovy/inspect/swingui/TreeNodeBuildingVisitor$_visitPropertyExpression_closure46
      17: dup
      18: aload_0
      19: aload_0
      20: invokespecial #596                // Method groovy/inspect/swingui/TreeNodeBuildingVisitor$_visitPropertyExpression_closure46."<init>":(Ljava/lang/Object;Ljava/lang/Object;)V
      23: invokeinterface #270,  5          // InterfaceMethod org/codehaus/groovy/runtime/callsite/CallSite.callCurrent:(Lgroovy/lang/GroovyObject;Ljava/lang/Object;Ljava/lang/Object;Ljava/lang/Object;)Ljava/lang/Object;
      28: pop
      29: return

  public void visitAttributeExpression(org.codehaus.groovy.ast.expr.AttributeExpression);
    Code:
       0: invokestatic  #187                // Method $getCallSiteArray:()[Lorg/codehaus/groovy/runtime/callsite/CallSite;
       3: astore_2
       4: aload_2
       5: ldc_w         #600                // int 56
       8: aaload
       9: aload_0
      10: aload_1
      11: ldc_w         #602                // class org/codehaus/groovy/ast/expr/AttributeExpression
      14: new           #147                // class groovy/inspect/swingui/TreeNodeBuildingVisitor$_visitAttributeExpression_closure47
      17: dup
      18: aload_0
      19: aload_0
      20: invokespecial #603                // Method groovy/inspect/swingui/TreeNodeBuildingVisitor$_visitAttributeExpression_closure47."<init>":(Ljava/lang/Object;Ljava/lang/Object;)V
      23: invokeinterface #270,  5          // InterfaceMethod org/codehaus/groovy/runtime/callsite/CallSite.callCurrent:(Lgroovy/lang/GroovyObject;Ljava/lang/Object;Ljava/lang/Object;Ljava/lang/Object;)Ljava/lang/Object;
      28: pop
      29: return

  public void visitFieldExpression(org.codehaus.groovy.ast.expr.FieldExpression);
    Code:
       0: invokestatic  #187                // Method $getCallSiteArray:()[Lorg/codehaus/groovy/runtime/callsite/CallSite;
       3: astore_2
       4: aload_2
       5: ldc_w         #607                // int 57
       8: aaload
       9: aload_0
      10: aload_1
      11: ldc_w         #609                // class org/codehaus/groovy/ast/expr/FieldExpression
      14: new           #150                // class groovy/inspect/swingui/TreeNodeBuildingVisitor$_visitFieldExpression_closure48
      17: dup
      18: aload_0
      19: aload_0
      20: invokespecial #610                // Method groovy/inspect/swingui/TreeNodeBuildingVisitor$_visitFieldExpression_closure48."<init>":(Ljava/lang/Object;Ljava/lang/Object;)V
      23: invokeinterface #270,  5          // InterfaceMethod org/codehaus/groovy/runtime/callsite/CallSite.callCurrent:(Lgroovy/lang/GroovyObject;Ljava/lang/Object;Ljava/lang/Object;Ljava/lang/Object;)Ljava/lang/Object;
      28: pop
      29: return

  public void visitGStringExpression(org.codehaus.groovy.ast.expr.GStringExpression);
    Code:
       0: invokestatic  #187                // Method $getCallSiteArray:()[Lorg/codehaus/groovy/runtime/callsite/CallSite;
       3: astore_2
       4: aload_2
       5: ldc_w         #614                // int 58
       8: aaload
       9: aload_0
      10: aload_1
      11: ldc_w         #616                // class org/codehaus/groovy/ast/expr/GStringExpression
      14: new           #153                // class groovy/inspect/swingui/TreeNodeBuildingVisitor$_visitGStringExpression_closure49
      17: dup
      18: aload_0
      19: aload_0
      20: invokespecial #617                // Method groovy/inspect/swingui/TreeNodeBuildingVisitor$_visitGStringExpression_closure49."<init>":(Ljava/lang/Object;Ljava/lang/Object;)V
      23: invokeinterface #270,  5          // InterfaceMethod org/codehaus/groovy/runtime/callsite/CallSite.callCurrent:(Lgroovy/lang/GroovyObject;Ljava/lang/Object;Ljava/lang/Object;Ljava/lang/Object;)Ljava/lang/Object;
      28: pop
      29: return

  public void visitCatchStatement(org.codehaus.groovy.ast.stmt.CatchStatement);
    Code:
       0: invokestatic  #187                // Method $getCallSiteArray:()[Lorg/codehaus/groovy/runtime/callsite/CallSite;
       3: astore_2
       4: aload_2
       5: ldc_w         #621                // int 59
       8: aaload
       9: aload_0
      10: aload_1
      11: ldc_w         #623                // class org/codehaus/groovy/ast/stmt/CatchStatement
      14: new           #156                // class groovy/inspect/swingui/TreeNodeBuildingVisitor$_visitCatchStatement_closure50
      17: dup
      18: aload_0
      19: aload_0
      20: invokespecial #624                // Method groovy/inspect/swingui/TreeNodeBuildingVisitor$_visitCatchStatement_closure50."<init>":(Ljava/lang/Object;Ljava/lang/Object;)V
      23: invokeinterface #270,  5          // InterfaceMethod org/codehaus/groovy/runtime/callsite/CallSite.callCurrent:(Lgroovy/lang/GroovyObject;Ljava/lang/Object;Ljava/lang/Object;Ljava/lang/Object;)Ljava/lang/Object;
      28: pop
      29: return

  public void visitArgumentlistExpression(org.codehaus.groovy.ast.expr.ArgumentListExpression);
    Code:
       0: invokestatic  #187                // Method $getCallSiteArray:()[Lorg/codehaus/groovy/runtime/callsite/CallSite;
       3: astore_2
       4: aload_2
       5: ldc_w         #628                // int 60
       8: aaload
       9: aload_0
      10: aload_1
      11: ldc_w         #630                // class org/codehaus/groovy/ast/expr/ArgumentListExpression
      14: new           #159                // class groovy/inspect/swingui/TreeNodeBuildingVisitor$_visitArgumentlistExpression_closure51
      17: dup
      18: aload_0
      19: aload_0
      20: invokespecial #631                // Method groovy/inspect/swingui/TreeNodeBuildingVisitor$_visitArgumentlistExpression_closure51."<init>":(Ljava/lang/Object;Ljava/lang/Object;)V
      23: invokeinterface #270,  5          // InterfaceMethod org/codehaus/groovy/runtime/callsite/CallSite.callCurrent:(Lgroovy/lang/GroovyObject;Ljava/lang/Object;Ljava/lang/Object;Ljava/lang/Object;)Ljava/lang/Object;
      28: pop
      29: return

  public void visitClosureListExpression(org.codehaus.groovy.ast.expr.ClosureListExpression);
    Code:
       0: invokestatic  #187                // Method $getCallSiteArray:()[Lorg/codehaus/groovy/runtime/callsite/CallSite;
       3: astore_2
       4: aload_2
       5: ldc_w         #635                // int 61
       8: aaload
       9: aload_0
      10: aload_1
      11: ldc_w         #637                // class org/codehaus/groovy/ast/expr/ClosureListExpression
      14: new           #162                // class groovy/inspect/swingui/TreeNodeBuildingVisitor$_visitClosureListExpression_closure52
      17: dup
      18: aload_0
      19: aload_0
      20: invokespecial #638                // Method groovy/inspect/swingui/TreeNodeBuildingVisitor$_visitClosureListExpression_closure52."<init>":(Ljava/lang/Object;Ljava/lang/Object;)V
      23: invokeinterface #270,  5          // InterfaceMethod org/codehaus/groovy/runtime/callsite/CallSite.callCurrent:(Lgroovy/lang/GroovyObject;Ljava/lang/Object;Ljava/lang/Object;Ljava/lang/Object;)Ljava/lang/Object;
      28: pop
      29: return

  public void visitBytecodeExpression(org.codehaus.groovy.classgen.BytecodeExpression);
    Code:
       0: invokestatic  #187                // Method $getCallSiteArray:()[Lorg/codehaus/groovy/runtime/callsite/CallSite;
       3: astore_2
       4: aload_2
       5: ldc_w         #642                // int 62
       8: aaload
       9: aload_0
      10: aload_1
      11: ldc_w         #644                // class org/codehaus/groovy/classgen/BytecodeExpression
      14: new           #165                // class groovy/inspect/swingui/TreeNodeBuildingVisitor$_visitBytecodeExpression_closure53
      17: dup
      18: aload_0
      19: aload_0
      20: invokespecial #645                // Method groovy/inspect/swingui/TreeNodeBuildingVisitor$_visitBytecodeExpression_closure53."<init>":(Ljava/lang/Object;Ljava/lang/Object;)V
      23: invokeinterface #270,  5          // InterfaceMethod org/codehaus/groovy/runtime/callsite/CallSite.callCurrent:(Lgroovy/lang/GroovyObject;Ljava/lang/Object;Ljava/lang/Object;Ljava/lang/Object;)Ljava/lang/Object;
      28: pop
      29: return

  protected void visitListOfExpressions(java.util.List<? extends org.codehaus.groovy.ast.expr.Expression>);
    Code:
       0: invokestatic  #187                // Method $getCallSiteArray:()[Lorg/codehaus/groovy/runtime/callsite/CallSite;
       3: astore_2
       4: aload_2
       5: ldc_w         #649                // int 63
       8: aaload
       9: aload_1
      10: new           #168                // class groovy/inspect/swingui/TreeNodeBuildingVisitor$_visitListOfExpressions_closure54
      13: dup
      14: aload_0
      15: aload_0
      16: invokespecial #650                // Method groovy/inspect/swingui/TreeNodeBuildingVisitor$_visitListOfExpressions_closure54."<init>":(Ljava/lang/Object;Ljava/lang/Object;)V
      19: invokeinterface #239,  3          // InterfaceMethod org/codehaus/groovy/runtime/callsite/CallSite.call:(Ljava/lang/Object;Ljava/lang/Object;)Ljava/lang/Object;
      24: pop
      25: return

  protected groovy.lang.MetaClass $getStaticMetaClass();
    Code:
       0: aload_0
       1: invokevirtual #658                // Method java/lang/Object.getClass:()Ljava/lang/Class;
       4: ldc           #2                  // class groovy/inspect/swingui/TreeNodeBuildingVisitor
       6: if_acmpeq     14
       9: aload_0
      10: invokestatic  #662                // Method org/codehaus/groovy/runtime/ScriptBytecodeAdapter.initMetaClass:(Ljava/lang/Object;)Lgroovy/lang/MetaClass;
      13: areturn
      14: getstatic     #664                // Field $staticClassInfo:Lorg/codehaus/groovy/reflection/ClassInfo;
      17: astore_1
      18: aload_1
      19: ifnonnull     34
      22: aload_0
      23: invokevirtual #658                // Method java/lang/Object.getClass:()Ljava/lang/Class;
      26: invokestatic  #670                // Method org/codehaus/groovy/reflection/ClassInfo.getClassInfo:(Ljava/lang/Class;)Lorg/codehaus/groovy/reflection/ClassInfo;
      29: dup
      30: astore_1
      31: putstatic     #664                // Field $staticClassInfo:Lorg/codehaus/groovy/reflection/ClassInfo;
      34: aload_1
      35: invokevirtual #673                // Method org/codehaus/groovy/reflection/ClassInfo.getMetaClass:()Lgroovy/lang/MetaClass;
      38: areturn

  public groovy.lang.MetaClass getMetaClass();
    Code:
       0: aload_0
       1: getfield      #196                // Field metaClass:Lgroovy/lang/MetaClass;
       4: dup
       5: ifnull        9
       8: areturn
       9: pop
      10: aload_0
      11: dup
      12: invokevirtual #194                // Method $getStaticMetaClass:()Lgroovy/lang/MetaClass;
      15: putfield      #196                // Field metaClass:Lgroovy/lang/MetaClass;
      18: aload_0
      19: getfield      #196                // Field metaClass:Lgroovy/lang/MetaClass;
      22: areturn

  public void setMetaClass(groovy.lang.MetaClass);
    Code:
       0: aload_0
       1: aload_1
       2: putfield      #196                // Field metaClass:Lgroovy/lang/MetaClass;
       5: return

  public java.lang.Object invokeMethod(java.lang.String, java.lang.Object);
    Code:
       0: aload_0
       1: invokevirtual #678                // Method getMetaClass:()Lgroovy/lang/MetaClass;
       4: aload_0
       5: aload_1
       6: aload_2
       7: invokeinterface #683,  4          // InterfaceMethod groovy/lang/MetaClass.invokeMethod:(Ljava/lang/Object;Ljava/lang/String;Ljava/lang/Object;)Ljava/lang/Object;
      12: areturn

  public java.lang.Object getProperty(java.lang.String);
    Code:
       0: aload_0
       1: invokevirtual #678                // Method getMetaClass:()Lgroovy/lang/MetaClass;
       4: aload_0
       5: aload_1
       6: invokeinterface #688,  3          // InterfaceMethod groovy/lang/MetaClass.getProperty:(Ljava/lang/Object;Ljava/lang/String;)Ljava/lang/Object;
      11: areturn

  public void setProperty(java.lang.String, java.lang.Object);
    Code:
       0: aload_0
       1: invokevirtual #678                // Method getMetaClass:()Lgroovy/lang/MetaClass;
       4: aload_0
       5: aload_1
       6: aload_2
       7: invokeinterface #692,  4          // InterfaceMethod groovy/lang/MetaClass.setProperty:(Ljava/lang/Object;Ljava/lang/String;Ljava/lang/Object;)V
      12: return

  public java.lang.Object getCurrentNode();
    Code:
       0: aload_0
       1: getfield      #236                // Field currentNode:Ljava/lang/Object;
       4: areturn

  public void setCurrentNode(java.lang.Object);
    Code:
       0: aload_0
       1: aload_1
       2: putfield      #236                // Field currentNode:Ljava/lang/Object;
       5: return

  public void super$2$visitTernaryExpression(org.codehaus.groovy.ast.expr.TernaryExpression);
    Code:
       0: aload_0
       1: aload_1
       2: invokespecial #697                // Method org/codehaus/groovy/ast/CodeVisitorSupport.visitTernaryExpression:(Lorg/codehaus/groovy/ast/expr/TernaryExpression;)V
       5: return

  public void super$2$visitAttributeExpression(org.codehaus.groovy.ast.expr.AttributeExpression);
    Code:
       0: aload_0
       1: aload_1
       2: invokespecial #700                // Method org/codehaus/groovy/ast/CodeVisitorSupport.visitAttributeExpression:(Lorg/codehaus/groovy/ast/expr/AttributeExpression;)V
       5: return

  public void super$2$visitMapEntryExpression(org.codehaus.groovy.ast.expr.MapEntryExpression);
    Code:
       0: aload_0
       1: aload_1
       2: invokespecial #703                // Method org/codehaus/groovy/ast/CodeVisitorSupport.visitMapEntryExpression:(Lorg/codehaus/groovy/ast/expr/MapEntryExpression;)V
       5: return

  public void super$2$visitMethodPointerExpression(org.codehaus.groovy.ast.expr.MethodPointerExpression);
    Code:
       0: aload_0
       1: aload_1
       2: invokespecial #706                // Method org/codehaus/groovy/ast/CodeVisitorSupport.visitMethodPointerExpression:(Lorg/codehaus/groovy/ast/expr/MethodPointerExpression;)V
       5: return

  public void super$2$visitExpressionStatement(org.codehaus.groovy.ast.stmt.ExpressionStatement);
    Code:
       0: aload_0
       1: aload_1
       2: invokespecial #709                // Method org/codehaus/groovy/ast/CodeVisitorSupport.visitExpressionStatement:(Lorg/codehaus/groovy/ast/stmt/ExpressionStatement;)V
       5: return

  public void super$2$visitDeclarationExpression(org.codehaus.groovy.ast.expr.DeclarationExpression);
    Code:
       0: aload_0
       1: aload_1
       2: invokespecial #712                // Method org/codehaus/groovy/ast/CodeVisitorSupport.visitDeclarationExpression:(Lorg/codehaus/groovy/ast/expr/DeclarationExpression;)V
       5: return

  public void super$2$visitUnaryPlusExpression(org.codehaus.groovy.ast.expr.UnaryPlusExpression);
    Code:
       0: aload_0
       1: aload_1
       2: invokespecial #715                // Method org/codehaus/groovy/ast/CodeVisitorSupport.visitUnaryPlusExpression:(Lorg/codehaus/groovy/ast/expr/UnaryPlusExpression;)V
       5: return

  public void super$2$visitBitwiseNegationExpression(org.codehaus.groovy.ast.expr.BitwiseNegationExpression);
    Code:
       0: aload_0
       1: aload_1
       2: invokespecial #718                // Method org/codehaus/groovy/ast/CodeVisitorSupport.visitBitwiseNegationExpression:(Lorg/codehaus/groovy/ast/expr/BitwiseNegationExpression;)V
       5: return

  public void super$2$visitShortTernaryExpression(org.codehaus.groovy.ast.expr.ElvisOperatorExpression);
    Code:
       0: aload_0
       1: aload_1
       2: invokespecial #721                // Method org/codehaus/groovy/ast/CodeVisitorSupport.visitShortTernaryExpression:(Lorg/codehaus/groovy/ast/expr/ElvisOperatorExpression;)V
       5: return

  public void super$2$visitCastExpression(org.codehaus.groovy.ast.expr.CastExpression);
    Code:
       0: aload_0
       1: aload_1
       2: invokespecial #724                // Method org/codehaus/groovy/ast/CodeVisitorSupport.visitCastExpression:(Lorg/codehaus/groovy/ast/expr/CastExpression;)V
       5: return

  public void super$2$visitPrefixExpression(org.codehaus.groovy.ast.expr.PrefixExpression);
    Code:
       0: aload_0
       1: aload_1
       2: invokespecial #727                // Method org/codehaus/groovy/ast/CodeVisitorSupport.visitPrefixExpression:(Lorg/codehaus/groovy/ast/expr/PrefixExpression;)V
       5: return

  public void super$2$visitNotExpression(org.codehaus.groovy.ast.expr.NotExpression);
    Code:
       0: aload_0
       1: aload_1
       2: invokespecial #730                // Method org/codehaus/groovy/ast/CodeVisitorSupport.visitNotExpression:(Lorg/codehaus/groovy/ast/expr/NotExpression;)V
       5: return

  public void super$2$visitArrayExpression(org.codehaus.groovy.ast.expr.ArrayExpression);
    Code:
       0: aload_0
       1: aload_1
       2: invokespecial #733                // Method org/codehaus/groovy/ast/CodeVisitorSupport.visitArrayExpression:(Lorg/codehaus/groovy/ast/expr/ArrayExpression;)V
       5: return

  public void super$2$visitThrowStatement(org.codehaus.groovy.ast.stmt.ThrowStatement);
    Code:
       0: aload_0
       1: aload_1
       2: invokespecial #736                // Method org/codehaus/groovy/ast/CodeVisitorSupport.visitThrowStatement:(Lorg/codehaus/groovy/ast/stmt/ThrowStatement;)V
       5: return

  public void super$2$visitRangeExpression(org.codehaus.groovy.ast.expr.RangeExpression);
    Code:
       0: aload_0
       1: aload_1
       2: invokespecial #739                // Method org/codehaus/groovy/ast/CodeVisitorSupport.visitRangeExpression:(Lorg/codehaus/groovy/ast/expr/RangeExpression;)V
       5: return

  public void super$2$visitSpreadExpression(org.codehaus.groovy.ast.expr.SpreadExpression);
    Code:
       0: aload_0
       1: aload_1
       2: invokespecial #742                // Method org/codehaus/groovy/ast/CodeVisitorSupport.visitSpreadExpression:(Lorg/codehaus/groovy/ast/expr/SpreadExpression;)V
       5: return

  public void super$2$visitBreakStatement(org.codehaus.groovy.ast.stmt.BreakStatement);
    Code:
       0: aload_0
       1: aload_1
       2: invokespecial #745                // Method org/codehaus/groovy/ast/CodeVisitorSupport.visitBreakStatement:(Lorg/codehaus/groovy/ast/stmt/BreakStatement;)V
       5: return

  public void super$2$visitSpreadMapExpression(org.codehaus.groovy.ast.expr.SpreadMapExpression);
    Code:
       0: aload_0
       1: aload_1
       2: invokespecial #748                // Method org/codehaus/groovy/ast/CodeVisitorSupport.visitSpreadMapExpression:(Lorg/codehaus/groovy/ast/expr/SpreadMapExpression;)V
       5: return

  public void super$2$visitAssertStatement(org.codehaus.groovy.ast.stmt.AssertStatement);
    Code:
       0: aload_0
       1: aload_1
       2: invokespecial #751                // Method org/codehaus/groovy/ast/CodeVisitorSupport.visitAssertStatement:(Lorg/codehaus/groovy/ast/stmt/AssertStatement;)V
       5: return

  public void super$2$visitConstructorCallExpression(org.codehaus.groovy.ast.expr.ConstructorCallExpression);
    Code:
       0: aload_0
       1: aload_1
       2: invokespecial #754                // Method org/codehaus/groovy/ast/CodeVisitorSupport.visitConstructorCallExpression:(Lorg/codehaus/groovy/ast/expr/ConstructorCallExpression;)V
       5: return

  public void super$2$visitMapExpression(org.codehaus.groovy.ast.expr.MapExpression);
    Code:
       0: aload_0
       1: aload_1
       2: invokespecial #757                // Method org/codehaus/groovy/ast/CodeVisitorSupport.visitMapExpression:(Lorg/codehaus/groovy/ast/expr/MapExpression;)V
       5: return

  public void super$2$visitArgumentlistExpression(org.codehaus.groovy.ast.expr.ArgumentListExpression);
    Code:
       0: aload_0
       1: aload_1
       2: invokespecial #760                // Method org/codehaus/groovy/ast/CodeVisitorSupport.visitArgumentlistExpression:(Lorg/codehaus/groovy/ast/expr/ArgumentListExpression;)V
       5: return

  public void super$2$visitTupleExpression(org.codehaus.groovy.ast.expr.TupleExpression);
    Code:
       0: aload_0
       1: aload_1
       2: invokespecial #763                // Method org/codehaus/groovy/ast/CodeVisitorSupport.visitTupleExpression:(Lorg/codehaus/groovy/ast/expr/TupleExpression;)V
       5: return

  public void super$2$visitTryCatchFinally(org.codehaus.groovy.ast.stmt.TryCatchStatement);
    Code:
       0: aload_0
       1: aload_1
       2: invokespecial #766                // Method org/codehaus/groovy/ast/CodeVisitorSupport.visitTryCatchFinally:(Lorg/codehaus/groovy/ast/stmt/TryCatchStatement;)V
       5: return

  public void super$2$visitBooleanExpression(org.codehaus.groovy.ast.expr.BooleanExpression);
    Code:
       0: aload_0
       1: aload_1
       2: invokespecial #769                // Method org/codehaus/groovy/ast/CodeVisitorSupport.visitBooleanExpression:(Lorg/codehaus/groovy/ast/expr/BooleanExpression;)V
       5: return

  public void super$2$visitVariableExpression(org.codehaus.groovy.ast.expr.VariableExpression);
    Code:
       0: aload_0
       1: aload_1
       2: invokespecial #772                // Method org/codehaus/groovy/ast/CodeVisitorSupport.visitVariableExpression:(Lorg/codehaus/groovy/ast/expr/VariableExpression;)V
       5: return

  public void super$2$visitSynchronizedStatement(org.codehaus.groovy.ast.stmt.SynchronizedStatement);
    Code:
       0: aload_0
       1: aload_1
       2: invokespecial #775                // Method org/codehaus/groovy/ast/CodeVisitorSupport.visitSynchronizedStatement:(Lorg/codehaus/groovy/ast/stmt/SynchronizedStatement;)V
       5: return

  public void super$2$visitGStringExpression(org.codehaus.groovy.ast.expr.GStringExpression);
    Code:
       0: aload_0
       1: aload_1
       2: invokespecial #778                // Method org/codehaus/groovy/ast/CodeVisitorSupport.visitGStringExpression:(Lorg/codehaus/groovy/ast/expr/GStringExpression;)V
       5: return

  public void super$2$visitCatchStatement(org.codehaus.groovy.ast.stmt.CatchStatement);
    Code:
       0: aload_0
       1: aload_1
       2: invokespecial #781                // Method org/codehaus/groovy/ast/CodeVisitorSupport.visitCatchStatement:(Lorg/codehaus/groovy/ast/stmt/CatchStatement;)V
       5: return

  public void super$2$visitContinueStatement(org.codehaus.groovy.ast.stmt.ContinueStatement);
    Code:
       0: aload_0
       1: aload_1
       2: invokespecial #784                // Method org/codehaus/groovy/ast/CodeVisitorSupport.visitContinueStatement:(Lorg/codehaus/groovy/ast/stmt/ContinueStatement;)V
       5: return

  public void super$2$visitMethodCallExpression(org.codehaus.groovy.ast.expr.MethodCallExpression);
    Code:
       0: aload_0
       1: aload_1
       2: invokespecial #787                // Method org/codehaus/groovy/ast/CodeVisitorSupport.visitMethodCallExpression:(Lorg/codehaus/groovy/ast/expr/MethodCallExpression;)V
       5: return

  public void super$2$visitCaseStatement(org.codehaus.groovy.ast.stmt.CaseStatement);
    Code:
       0: aload_0
       1: aload_1
       2: invokespecial #790                // Method org/codehaus/groovy/ast/CodeVisitorSupport.visitCaseStatement:(Lorg/codehaus/groovy/ast/stmt/CaseStatement;)V
       5: return

  public void super$2$visitClosureExpression(org.codehaus.groovy.ast.expr.ClosureExpression);
    Code:
       0: aload_0
       1: aload_1
       2: invokespecial #793                // Method org/codehaus/groovy/ast/CodeVisitorSupport.visitClosureExpression:(Lorg/codehaus/groovy/ast/expr/ClosureExpression;)V
       5: return

  public void super$2$visitBlockStatement(org.codehaus.groovy.ast.stmt.BlockStatement);
    Code:
       0: aload_0
       1: aload_1
       2: invokespecial #796                // Method org/codehaus/groovy/ast/CodeVisitorSupport.visitBlockStatement:(Lorg/codehaus/groovy/ast/stmt/BlockStatement;)V
       5: return

  public void super$2$visitFieldExpression(org.codehaus.groovy.ast.expr.FieldExpression);
    Code:
       0: aload_0
       1: aload_1
       2: invokespecial #799                // Method org/codehaus/groovy/ast/CodeVisitorSupport.visitFieldExpression:(Lorg/codehaus/groovy/ast/expr/FieldExpression;)V
       5: return

  public void super$2$visitUnaryMinusExpression(org.codehaus.groovy.ast.expr.UnaryMinusExpression);
    Code:
       0: aload_0
       1: aload_1
       2: invokespecial #802                // Method org/codehaus/groovy/ast/CodeVisitorSupport.visitUnaryMinusExpression:(Lorg/codehaus/groovy/ast/expr/UnaryMinusExpression;)V
       5: return

  public void super$2$visitStaticMethodCallExpression(org.codehaus.groovy.ast.expr.StaticMethodCallExpression);
    Code:
       0: aload_0
       1: aload_1
       2: invokespecial #805                // Method org/codehaus/groovy/ast/CodeVisitorSupport.visitStaticMethodCallExpression:(Lorg/codehaus/groovy/ast/expr/StaticMethodCallExpression;)V
       5: return

  public void super$2$visitBinaryExpression(org.codehaus.groovy.ast.expr.BinaryExpression);
    Code:
       0: aload_0
       1: aload_1
       2: invokespecial #808                // Method org/codehaus/groovy/ast/CodeVisitorSupport.visitBinaryExpression:(Lorg/codehaus/groovy/ast/expr/BinaryExpression;)V
       5: return

  public void super$2$visitPostfixExpression(org.codehaus.groovy.ast.expr.PostfixExpression);
    Code:
       0: aload_0
       1: aload_1
       2: invokespecial #811                // Method org/codehaus/groovy/ast/CodeVisitorSupport.visitPostfixExpression:(Lorg/codehaus/groovy/ast/expr/PostfixExpression;)V
       5: return

  public void super$2$visitBytecodeExpression(org.codehaus.groovy.classgen.BytecodeExpression);
    Code:
       0: aload_0
       1: aload_1
       2: invokespecial #814                // Method org/codehaus/groovy/ast/CodeVisitorSupport.visitBytecodeExpression:(Lorg/codehaus/groovy/classgen/BytecodeExpression;)V
       5: return

  public void super$2$visitClosureListExpression(org.codehaus.groovy.ast.expr.ClosureListExpression);
    Code:
       0: aload_0
       1: aload_1
       2: invokespecial #817                // Method org/codehaus/groovy/ast/CodeVisitorSupport.visitClosureListExpression:(Lorg/codehaus/groovy/ast/expr/ClosureListExpression;)V
       5: return

  public void super$2$visitConstantExpression(org.codehaus.groovy.ast.expr.ConstantExpression);
    Code:
       0: aload_0
       1: aload_1
       2: invokespecial #820                // Method org/codehaus/groovy/ast/CodeVisitorSupport.visitConstantExpression:(Lorg/codehaus/groovy/ast/expr/ConstantExpression;)V
       5: return

  public void super$2$visitPropertyExpression(org.codehaus.groovy.ast.expr.PropertyExpression);
    Code:
       0: aload_0
       1: aload_1
       2: invokespecial #823                // Method org/codehaus/groovy/ast/CodeVisitorSupport.visitPropertyExpression:(Lorg/codehaus/groovy/ast/expr/PropertyExpression;)V
       5: return

  public void super$2$visitReturnStatement(org.codehaus.groovy.ast.stmt.ReturnStatement);
    Code:
       0: aload_0
       1: aload_1
       2: invokespecial #826                // Method org/codehaus/groovy/ast/CodeVisitorSupport.visitReturnStatement:(Lorg/codehaus/groovy/ast/stmt/ReturnStatement;)V
       5: return

  public void super$2$visitListExpression(org.codehaus.groovy.ast.expr.ListExpression);
    Code:
       0: aload_0
       1: aload_1
       2: invokespecial #829                // Method org/codehaus/groovy/ast/CodeVisitorSupport.visitListExpression:(Lorg/codehaus/groovy/ast/expr/ListExpression;)V
       5: return

  public void super$2$visitClassExpression(org.codehaus.groovy.ast.expr.ClassExpression);
    Code:
       0: aload_0
       1: aload_1
       2: invokespecial #832                // Method org/codehaus/groovy/ast/CodeVisitorSupport.visitClassExpression:(Lorg/codehaus/groovy/ast/expr/ClassExpression;)V
       5: return

  public void super$2$visitSwitch(org.codehaus.groovy.ast.stmt.SwitchStatement);
    Code:
       0: aload_0
       1: aload_1
       2: invokespecial #835                // Method org/codehaus/groovy/ast/CodeVisitorSupport.visitSwitch:(Lorg/codehaus/groovy/ast/stmt/SwitchStatement;)V
       5: return

  public void super$2$visitIfElse(org.codehaus.groovy.ast.stmt.IfStatement);
    Code:
       0: aload_0
       1: aload_1
       2: invokespecial #838                // Method org/codehaus/groovy/ast/CodeVisitorSupport.visitIfElse:(Lorg/codehaus/groovy/ast/stmt/IfStatement;)V
       5: return

  public void super$2$visitForLoop(org.codehaus.groovy.ast.stmt.ForStatement);
    Code:
       0: aload_0
       1: aload_1
       2: invokespecial #841                // Method org/codehaus/groovy/ast/CodeVisitorSupport.visitForLoop:(Lorg/codehaus/groovy/ast/stmt/ForStatement;)V
       5: return

  public void super$2$visitWhileLoop(org.codehaus.groovy.ast.stmt.WhileStatement);
    Code:
       0: aload_0
       1: aload_1
       2: invokespecial #844                // Method org/codehaus/groovy/ast/CodeVisitorSupport.visitWhileLoop:(Lorg/codehaus/groovy/ast/stmt/WhileStatement;)V
       5: return

  public void super$2$visitDoWhileLoop(org.codehaus.groovy.ast.stmt.DoWhileStatement);
    Code:
       0: aload_0
       1: aload_1
       2: invokespecial #847                // Method org/codehaus/groovy/ast/CodeVisitorSupport.visitDoWhileLoop:(Lorg/codehaus/groovy/ast/stmt/DoWhileStatement;)V
       5: return

  public void super$2$visitEmptyStatement(org.codehaus.groovy.ast.stmt.EmptyStatement);
    Code:
       0: aload_0
       1: aload_1
       2: invokespecial #850                // Method org/codehaus/groovy/ast/CodeVisitorSupport.visitEmptyStatement:(Lorg/codehaus/groovy/ast/stmt/EmptyStatement;)V
       5: return

  public void super$2$visitListOfExpressions(java.util.List);
    Code:
       0: aload_0
       1: aload_1
       2: invokespecial #853                // Method org/codehaus/groovy/ast/CodeVisitorSupport.visitListOfExpressions:(Ljava/util/List;)V
       5: return

  private static void $createCallSiteArray_1(java.lang.String[]);
    Code:
       0: aload_0
       1: ldc           #203                // int 0
       3: ldc_w         #857                // String <$constructor$>
       6: aastore
       7: aload_0
       8: ldc           #222                // int 1
      10: ldc_w         #859                // String getName
      13: aastore
      14: aload_0
      15: ldc           #227                // int 2
      17: ldc_w         #859                // String getName
      20: aastore
      21: aload_0
      22: ldc           #228                // int 3
      24: ldc_w         #860                // String getClass
      27: aastore
      28: aload_0
      29: ldc           #237                // int 4
      31: ldc_w         #862                // String make
      34: aastore
      35: aload_0
      36: ldc           #240                // int 5
      38: ldc_w         #863                // String call
      41: aastore
      42: aload_0
      43: ldc           #241                // int 6
      45: ldc_w         #862                // String make
      48: aastore
      49: aload_0
      50: ldc           #242                // int 7
      52: ldc_w         #865                // String add
      55: aastore
      56: aload_0
      57: ldc           #251                // int 8
      59: ldc_w         #863                // String call
      62: aastore
      63: aload_0
      64: ldc           #252                // int 9
      66: ldc_w         #863                // String call
      69: aastore
      70: aload_0
      71: ldc_w         #261                // int 10
      74: ldc_w         #866                // String addNode
      77: aastore
      78: aload_0
      79: ldc_w         #274                // int 11
      82: ldc_w         #866                // String addNode
      85: aastore
      86: aload_0
      87: ldc_w         #281                // int 12
      90: ldc_w         #866                // String addNode
      93: aastore
      94: aload_0
      95: ldc_w         #288                // int 13
      98: ldc_w         #866                // String addNode
     101: aastore
     102: aload_0
     103: ldc_w         #295                // int 14
     106: ldc_w         #866                // String addNode
     109: aastore
     110: aload_0
     111: ldc_w         #302                // int 15
     114: ldc_w         #866                // String addNode
     117: aastore
     118: aload_0
     119: ldc_w         #309                // int 16
     122: ldc_w         #866                // String addNode
     125: aastore
     126: aload_0
     127: ldc_w         #316                // int 17
     130: ldc_w         #866                // String addNode
     133: aastore
     134: aload_0
     135: ldc_w         #323                // int 18
     138: ldc_w         #866                // String addNode
     141: aastore
     142: aload_0
     143: ldc_w         #330                // int 19
     146: ldc_w         #866                // String addNode
     149: aastore
     150: aload_0
     151: ldc_w         #337                // int 20
     154: ldc_w         #866                // String addNode
     157: aastore
     158: aload_0
     159: ldc_w         #344                // int 21
     162: ldc_w         #866                // String addNode
     165: aastore
     166: aload_0
     167: ldc_w         #351                // int 22
     170: ldc_w         #866                // String addNode
     173: aastore
     174: aload_0
     175: ldc_w         #358                // int 23
     178: ldc_w         #866                // String addNode
     181: aastore
     182: aload_0
     183: ldc_w         #365                // int 24
     186: ldc_w         #866                // String addNode
     189: aastore
     190: aload_0
     191: ldc_w         #372                // int 25
     194: ldc_w         #866                // String addNode
     197: aastore
     198: aload_0
     199: ldc_w         #379                // int 26
     202: ldc_w         #866                // String addNode
     205: aastore
     206: aload_0
     207: ldc_w         #386                // int 27
     210: ldc_w         #866                // String addNode
     213: aastore
     214: aload_0
     215: ldc_w         #393                // int 28
     218: ldc_w         #866                // String addNode
     221: aastore
     222: aload_0
     223: ldc_w         #400                // int 29
     226: ldc_w         #866                // String addNode
     229: aastore
     230: aload_0
     231: ldc_w         #407                // int 30
     234: ldc_w         #866                // String addNode
     237: aastore
     238: aload_0
     239: ldc_w         #414                // int 31
     242: ldc_w         #866                // String addNode
     245: aastore
     246: aload_0
     247: ldc_w         #421                // int 32
     250: ldc_w         #866                // String addNode
     253: aastore
     254: aload_0
     255: ldc_w         #428                // int 33
     258: ldc_w         #866                // String addNode
     261: aastore
     262: aload_0
     263: ldc_w         #435                // int 34
     266: ldc_w         #866                // String addNode
     269: aastore
     270: aload_0
     271: ldc_w         #442                // int 35
     274: ldc_w         #866                // String addNode
     277: aastore
     278: aload_0
     279: ldc_w         #449                // int 36
     282: ldc_w         #866                // String addNode
     285: aastore
     286: aload_0
     287: ldc_w         #460                // int 37
     290: ldc_w         #866                // String addNode
     293: aastore
     294: aload_0
     295: ldc_w         #474                // int 38
     298: ldc_w         #866                // String addNode
     301: aastore
     302: aload_0
     303: ldc_w         #481                // int 39
     306: ldc_w         #866                // String addNode
     309: aastore
     310: aload_0
     311: ldc_w         #488                // int 40
     314: ldc_w         #866                // String addNode
     317: aastore
     318: aload_0
     319: ldc_w         #495                // int 41
     322: ldc_w         #866                // String addNode
     325: aastore
     326: aload_0
     327: ldc_w         #502                // int 42
     330: ldc_w         #866                // String addNode
     333: aastore
     334: aload_0
     335: ldc_w         #509                // int 43
     338: ldc_w         #866                // String addNode
     341: aastore
     342: aload_0
     343: ldc_w         #516                // int 44
     346: ldc_w         #866                // String addNode
     349: aastore
     350: aload_0
     351: ldc_w         #523                // int 45
     354: ldc_w         #866                // String addNode
     357: aastore
     358: aload_0
     359: ldc_w         #530                // int 46
     362: ldc_w         #866                // String addNode
     365: aastore
     366: aload_0
     367: ldc_w         #537                // int 47
     370: ldc_w         #866                // String addNode
     373: aastore
     374: aload_0
     375: ldc_w         #544                // int 48
     378: ldc_w         #866                // String addNode
     381: aastore
     382: aload_0
     383: ldc_w         #551                // int 49
     386: ldc_w         #866                // String addNode
     389: aastore
     390: aload_0
     391: ldc_w         #558                // int 50
     394: ldc_w         #866                // String addNode
     397: aastore
     398: aload_0
     399: ldc_w         #565                // int 51
     402: ldc_w         #866                // String addNode
     405: aastore
     406: aload_0
     407: ldc_w         #572                // int 52
     410: ldc_w         #866                // String addNode
     413: aastore
     414: aload_0
     415: ldc_w         #579                // int 53
     418: ldc_w         #866                // String addNode
     421: aastore
     422: aload_0
     423: ldc_w         #586                // int 54
     426: ldc_w         #866                // String addNode
     429: aastore
     430: aload_0
     431: ldc_w         #593                // int 55
     434: ldc_w         #866                // String addNode
     437: aastore
     438: aload_0
     439: ldc_w         #600                // int 56
     442: ldc_w         #866                // String addNode
     445: aastore
     446: aload_0
     447: ldc_w         #607                // int 57
     450: ldc_w         #866                // String addNode
     453: aastore
     454: aload_0
     455: ldc_w         #614                // int 58
     458: ldc_w         #866                // String addNode
     461: aastore
     462: aload_0
     463: ldc_w         #621                // int 59
     466: ldc_w         #866                // String addNode
     469: aastore
     470: aload_0
     471: ldc_w         #628                // int 60
     474: ldc_w         #866                // String addNode
     477: aastore
     478: aload_0
     479: ldc_w         #635                // int 61
     482: ldc_w         #866                // String addNode
     485: aastore
     486: aload_0
     487: ldc_w         #642                // int 62
     490: ldc_w         #866                // String addNode
     493: aastore
     494: aload_0
     495: ldc_w         #649                // int 63
     498: ldc_w         #868                // String each
     501: aastore
     502: return

  private static org.codehaus.groovy.runtime.callsite.CallSiteArray $createCallSiteArray();
    Code:
       0: ldc_w         #871                // int 64
       3: anewarray     #246                // class java/lang/String
       6: astore_0
       7: aload_0
       8: invokestatic  #873                // Method $createCallSiteArray_1:([Ljava/lang/String;)V
      11: new           #875                // class org/codehaus/groovy/runtime/callsite/CallSiteArray
      14: dup
      15: ldc           #2                  // class groovy/inspect/swingui/TreeNodeBuildingVisitor
      17: aload_0
      18: invokespecial #878                // Method org/codehaus/groovy/runtime/callsite/CallSiteArray."<init>":(Ljava/lang/Class;[Ljava/lang/String;)V
      21: areturn

  private static org.codehaus.groovy.runtime.callsite.CallSite[] $getCallSiteArray();
    Code:
       0: getstatic     #880                // Field $callSiteArray:Ljava/lang/ref/SoftReference;
       3: ifnull        20
       6: getstatic     #880                // Field $callSiteArray:Ljava/lang/ref/SoftReference;
       9: invokevirtual #883                // Method java/lang/ref/SoftReference.get:()Ljava/lang/Object;
      12: checkcast     #875                // class org/codehaus/groovy/runtime/callsite/CallSiteArray
      15: dup
      16: astore_0
      17: ifnonnull     35
      20: invokestatic  #885                // Method $createCallSiteArray:()Lorg/codehaus/groovy/runtime/callsite/CallSiteArray;
      23: astore_0
      24: new           #882                // class java/lang/ref/SoftReference
      27: dup
      28: aload_0
      29: invokespecial #886                // Method java/lang/ref/SoftReference."<init>":(Ljava/lang/Object;)V
      32: putstatic     #880                // Field $callSiteArray:Ljava/lang/ref/SoftReference;
      35: aload_0
      36: getfield      #890                // Field org/codehaus/groovy/runtime/callsite/CallSiteArray.array:[Lorg/codehaus/groovy/runtime/callsite/CallSite;
      39: areturn
}
