Compiled from "ServletLogChute.java"
public class org.apache.velocity.runtime.log.ServletLogChute implements org.apache.velocity.runtime.log.LogChute {
  public static final java.lang.String RUNTIME_LOG_LEVEL_KEY;

  private int enabled;

  protected javax.servlet.ServletContext servletContext;

  public static final java.lang.String PREFIX;

  static java.lang.Class class$javax$servlet$ServletContext;

  public org.apache.velocity.runtime.log.ServletLogChute();
    Code:
       0: aload_0
       1: invokespecial #6                  // Method java/lang/Object."<init>":()V
       4: aload_0
       5: iconst_m1
       6: putfield      #7                  // Field enabled:I
       9: aload_0
      10: aconst_null
      11: putfield      #8                  // Field servletContext:Ljavax/servlet/ServletContext;
      14: return

  public void init(org.apache.velocity.runtime.RuntimeServices) throws java.lang.Exception;
    Code:
       0: aload_1
       1: getstatic     #9                  // Field class$javax$servlet$ServletContext:Ljava/lang/Class;
       4: ifnonnull     19
       7: ldc           #10                 // String javax.servlet.ServletContext
       9: invokestatic  #11                 // Method class$:(Ljava/lang/String;)Ljava/lang/Class;
      12: dup
      13: putstatic     #9                  // Field class$javax$servlet$ServletContext:Ljava/lang/Class;
      16: goto          22
      19: getstatic     #9                  // Field class$javax$servlet$ServletContext:Ljava/lang/Class;
      22: invokevirtual #12                 // Method java/lang/Class.getName:()Ljava/lang/String;
      25: invokeinterface #13,  2           // InterfaceMethod org/apache/velocity/runtime/RuntimeServices.getApplicationAttribute:(Ljava/lang/Object;)Ljava/lang/Object;
      30: astore_2
      31: aload_2
      32: ifnonnull     45
      35: new           #14                 // class java/lang/UnsupportedOperationException
      38: dup
      39: ldc           #15                 // String Could not retrieve ServletContext from application attributes
      41: invokespecial #16                 // Method java/lang/UnsupportedOperationException."<init>":(Ljava/lang/String;)V
      44: athrow
      45: aload_0
      46: aload_2
      47: checkcast     #17                 // class javax/servlet/ServletContext
      50: putfield      #8                  // Field servletContext:Ljavax/servlet/ServletContext;
      53: aload_1
      54: ldc           #18                 // String runtime.log.logsystem.servlet.level
      56: invokeinterface #19,  2           // InterfaceMethod org/apache/velocity/runtime/RuntimeServices.getProperty:(Ljava/lang/String;)Ljava/lang/Object;
      61: checkcast     #20                 // class java/lang/String
      64: astore_3
      65: aload_3
      66: ifnull        78
      69: aload_0
      70: aload_0
      71: aload_3
      72: invokevirtual #21                 // Method toLevel:(Ljava/lang/String;)I
      75: invokevirtual #22                 // Method setEnabledLevel:(I)V
      78: return

  protected int toLevel(java.lang.String);
    Code:
       0: aload_1
       1: ldc           #23                 // String debug
       3: invokevirtual #24                 // Method java/lang/String.equalsIgnoreCase:(Ljava/lang/String;)Z
       6: ifeq          11
       9: iconst_0
      10: ireturn
      11: aload_1
      12: ldc           #25                 // String info
      14: invokevirtual #24                 // Method java/lang/String.equalsIgnoreCase:(Ljava/lang/String;)Z
      17: ifeq          22
      20: iconst_1
      21: ireturn
      22: aload_1
      23: ldc           #26                 // String warn
      25: invokevirtual #24                 // Method java/lang/String.equalsIgnoreCase:(Ljava/lang/String;)Z
      28: ifeq          33
      31: iconst_2
      32: ireturn
      33: aload_1
      34: ldc           #27                 // String error
      36: invokevirtual #24                 // Method java/lang/String.equalsIgnoreCase:(Ljava/lang/String;)Z
      39: ifeq          44
      42: iconst_3
      43: ireturn
      44: iconst_m1
      45: ireturn

  public void setEnabledLevel(int);
    Code:
       0: aload_0
       1: iload_1
       2: putfield      #7                  // Field enabled:I
       5: return

  public int getEnabledLevel();
    Code:
       0: aload_0
       1: getfield      #7                  // Field enabled:I
       4: ireturn

  public boolean isLevelEnabled(int);
    Code:
       0: iload_1
       1: aload_0
       2: getfield      #7                  // Field enabled:I
       5: if_icmplt     12
       8: iconst_1
       9: goto          13
      12: iconst_0
      13: ireturn

  public void log(int, java.lang.String);
    Code:
       0: aload_0
       1: iload_1
       2: invokevirtual #28                 // Method isLevelEnabled:(I)Z
       5: ifne          9
       8: return
       9: iload_1
      10: tableswitch   { // -1 to 3
                    -1: 137
                     0: 106
                     1: 75
                     2: 44
                     3: 168
               default: 199
          }
      44: aload_0
      45: getfield      #8                  // Field servletContext:Ljavax/servlet/ServletContext;
      48: new           #29                 // class java/lang/StringBuffer
      51: dup
      52: invokespecial #30                 // Method java/lang/StringBuffer."<init>":()V
      55: ldc           #31                 // String  Velocity   [warn]
      57: invokevirtual #32                 // Method java/lang/StringBuffer.append:(Ljava/lang/String;)Ljava/lang/StringBuffer;
      60: aload_2
      61: invokevirtual #32                 // Method java/lang/StringBuffer.append:(Ljava/lang/String;)Ljava/lang/StringBuffer;
      64: invokevirtual #33                 // Method java/lang/StringBuffer.toString:()Ljava/lang/String;
      67: invokeinterface #34,  2           // InterfaceMethod javax/servlet/ServletContext.log:(Ljava/lang/String;)V
      72: goto          227
      75: aload_0
      76: getfield      #8                  // Field servletContext:Ljavax/servlet/ServletContext;
      79: new           #29                 // class java/lang/StringBuffer
      82: dup
      83: invokespecial #30                 // Method java/lang/StringBuffer."<init>":()V
      86: ldc           #35                 // String  Velocity   [info]
      88: invokevirtual #32                 // Method java/lang/StringBuffer.append:(Ljava/lang/String;)Ljava/lang/StringBuffer;
      91: aload_2
      92: invokevirtual #32                 // Method java/lang/StringBuffer.append:(Ljava/lang/String;)Ljava/lang/StringBuffer;
      95: invokevirtual #33                 // Method java/lang/StringBuffer.toString:()Ljava/lang/String;
      98: invokeinterface #34,  2           // InterfaceMethod javax/servlet/ServletContext.log:(Ljava/lang/String;)V
     103: goto          227
     106: aload_0
     107: getfield      #8                  // Field servletContext:Ljavax/servlet/ServletContext;
     110: new           #29                 // class java/lang/StringBuffer
     113: dup
     114: invokespecial #30                 // Method java/lang/StringBuffer."<init>":()V
     117: ldc           #36                 // String  Velocity  [debug]
     119: invokevirtual #32                 // Method java/lang/StringBuffer.append:(Ljava/lang/String;)Ljava/lang/StringBuffer;
     122: aload_2
     123: invokevirtual #32                 // Method java/lang/StringBuffer.append:(Ljava/lang/String;)Ljava/lang/StringBuffer;
     126: invokevirtual #33                 // Method java/lang/StringBuffer.toString:()Ljava/lang/String;
     129: invokeinterface #34,  2           // InterfaceMethod javax/servlet/ServletContext.log:(Ljava/lang/String;)V
     134: goto          227
     137: aload_0
     138: getfield      #8                  // Field servletContext:Ljavax/servlet/ServletContext;
     141: new           #29                 // class java/lang/StringBuffer
     144: dup
     145: invokespecial #30                 // Method java/lang/StringBuffer."<init>":()V
     148: ldc           #37                 // String  Velocity  [trace]
     150: invokevirtual #32                 // Method java/lang/StringBuffer.append:(Ljava/lang/String;)Ljava/lang/StringBuffer;
     153: aload_2
     154: invokevirtual #32                 // Method java/lang/StringBuffer.append:(Ljava/lang/String;)Ljava/lang/StringBuffer;
     157: invokevirtual #33                 // Method java/lang/StringBuffer.toString:()Ljava/lang/String;
     160: invokeinterface #34,  2           // InterfaceMethod javax/servlet/ServletContext.log:(Ljava/lang/String;)V
     165: goto          227
     168: aload_0
     169: getfield      #8                  // Field servletContext:Ljavax/servlet/ServletContext;
     172: new           #29                 // class java/lang/StringBuffer
     175: dup
     176: invokespecial #30                 // Method java/lang/StringBuffer."<init>":()V
     179: ldc           #38                 // String  Velocity  [error]
     181: invokevirtual #32                 // Method java/lang/StringBuffer.append:(Ljava/lang/String;)Ljava/lang/StringBuffer;
     184: aload_2
     185: invokevirtual #32                 // Method java/lang/StringBuffer.append:(Ljava/lang/String;)Ljava/lang/StringBuffer;
     188: invokevirtual #33                 // Method java/lang/StringBuffer.toString:()Ljava/lang/String;
     191: invokeinterface #34,  2           // InterfaceMethod javax/servlet/ServletContext.log:(Ljava/lang/String;)V
     196: goto          227
     199: aload_0
     200: getfield      #8                  // Field servletContext:Ljavax/servlet/ServletContext;
     203: new           #29                 // class java/lang/StringBuffer
     206: dup
     207: invokespecial #30                 // Method java/lang/StringBuffer."<init>":()V
     210: ldc           #39                 // String  Velocity  :
     212: invokevirtual #32                 // Method java/lang/StringBuffer.append:(Ljava/lang/String;)Ljava/lang/StringBuffer;
     215: aload_2
     216: invokevirtual #32                 // Method java/lang/StringBuffer.append:(Ljava/lang/String;)Ljava/lang/StringBuffer;
     219: invokevirtual #33                 // Method java/lang/StringBuffer.toString:()Ljava/lang/String;
     222: invokeinterface #34,  2           // InterfaceMethod javax/servlet/ServletContext.log:(Ljava/lang/String;)V
     227: return

  public void log(int, java.lang.String, java.lang.Throwable);
    Code:
       0: aload_0
       1: iload_1
       2: invokevirtual #28                 // Method isLevelEnabled:(I)Z
       5: ifne          9
       8: return
       9: new           #29                 // class java/lang/StringBuffer
      12: dup
      13: invokespecial #30                 // Method java/lang/StringBuffer."<init>":()V
      16: aload_2
      17: invokevirtual #32                 // Method java/lang/StringBuffer.append:(Ljava/lang/String;)Ljava/lang/StringBuffer;
      20: ldc           #40                 // String  -
      22: invokevirtual #32                 // Method java/lang/StringBuffer.append:(Ljava/lang/String;)Ljava/lang/StringBuffer;
      25: aload_3
      26: invokevirtual #41                 // Method java/lang/Throwable.toString:()Ljava/lang/String;
      29: invokevirtual #32                 // Method java/lang/StringBuffer.append:(Ljava/lang/String;)Ljava/lang/StringBuffer;
      32: invokevirtual #33                 // Method java/lang/StringBuffer.toString:()Ljava/lang/String;
      35: astore_2
      36: iload_1
      37: iconst_3
      38: if_icmplt     91
      41: new           #42                 // class java/io/StringWriter
      44: dup
      45: invokespecial #43                 // Method java/io/StringWriter."<init>":()V
      48: astore        4
      50: aload_3
      51: new           #44                 // class java/io/PrintWriter
      54: dup
      55: aload         4
      57: invokespecial #45                 // Method java/io/PrintWriter."<init>":(Ljava/io/Writer;)V
      60: invokevirtual #46                 // Method java/lang/Throwable.printStackTrace:(Ljava/io/PrintWriter;)V
      63: new           #29                 // class java/lang/StringBuffer
      66: dup
      67: invokespecial #30                 // Method java/lang/StringBuffer."<init>":()V
      70: aload_2
      71: invokevirtual #32                 // Method java/lang/StringBuffer.append:(Ljava/lang/String;)Ljava/lang/StringBuffer;
      74: ldc           #47                 // String \n
      76: invokevirtual #32                 // Method java/lang/StringBuffer.append:(Ljava/lang/String;)Ljava/lang/StringBuffer;
      79: aload         4
      81: invokevirtual #48                 // Method java/io/StringWriter.toString:()Ljava/lang/String;
      84: invokevirtual #32                 // Method java/lang/StringBuffer.append:(Ljava/lang/String;)Ljava/lang/StringBuffer;
      87: invokevirtual #33                 // Method java/lang/StringBuffer.toString:()Ljava/lang/String;
      90: astore_2
      91: aload_0
      92: iload_1
      93: aload_2
      94: invokevirtual #49                 // Method log:(ILjava/lang/String;)V
      97: return

  static java.lang.Class class$(java.lang.String);
    Code:
       0: aload_0
       1: invokestatic  #1                  // Method java/lang/Class.forName:(Ljava/lang/String;)Ljava/lang/Class;
       4: areturn
       5: astore_1
       6: new           #3                  // class java/lang/NoClassDefFoundError
       9: dup
      10: invokespecial #4                  // Method java/lang/NoClassDefFoundError."<init>":()V
      13: aload_1
      14: invokevirtual #5                  // Method java/lang/NoClassDefFoundError.initCause:(Ljava/lang/Throwable;)Ljava/lang/Throwable;
      17: athrow
    Exception table:
       from    to  target type
           0     4     5   Class java/lang/ClassNotFoundException
}
