Compiled from "DFASerializer.java"
public class org.antlr.v4.runtime.dfa.DFASerializer {
  private final org.antlr.v4.runtime.dfa.DFA dfa;

  private final org.antlr.v4.runtime.Vocabulary vocabulary;

  public org.antlr.v4.runtime.dfa.DFASerializer(org.antlr.v4.runtime.dfa.DFA, java.lang.String[]);
    Code:
       0: aload_0
       1: aload_1
       2: aload_2
       3: invokestatic  #1                  // Method org/antlr/v4/runtime/VocabularyImpl.fromTokenNames:([Ljava/lang/String;)Lorg/antlr/v4/runtime/Vocabulary;
       6: invokespecial #2                  // Method "<init>":(Lorg/antlr/v4/runtime/dfa/DFA;Lorg/antlr/v4/runtime/Vocabulary;)V
       9: return

  public org.antlr.v4.runtime.dfa.DFASerializer(org.antlr.v4.runtime.dfa.DFA, org.antlr.v4.runtime.Vocabulary);
    Code:
       0: aload_0
       1: invokespecial #3                  // Method java/lang/Object."<init>":()V
       4: aload_0
       5: aload_1
       6: putfield      #4                  // Field dfa:Lorg/antlr/v4/runtime/dfa/DFA;
       9: aload_0
      10: aload_2
      11: putfield      #5                  // Field vocabulary:Lorg/antlr/v4/runtime/Vocabulary;
      14: return

  public java.lang.String toString();
    Code:
       0: aload_0
       1: getfield      #4                  // Field dfa:Lorg/antlr/v4/runtime/dfa/DFA;
       4: getfield      #6                  // Field org/antlr/v4/runtime/dfa/DFA.s0:Lorg/antlr/v4/runtime/dfa/DFAState;
       7: ifnonnull     12
      10: aconst_null
      11: areturn
      12: new           #7                  // class java/lang/StringBuilder
      15: dup
      16: invokespecial #8                  // Method java/lang/StringBuilder."<init>":()V
      19: astore_1
      20: aload_0
      21: getfield      #4                  // Field dfa:Lorg/antlr/v4/runtime/dfa/DFA;
      24: invokevirtual #9                  // Method org/antlr/v4/runtime/dfa/DFA.getStates:()Ljava/util/List;
      27: astore_2
      28: aload_2
      29: invokeinterface #10,  1           // InterfaceMethod java/util/List.iterator:()Ljava/util/Iterator;
      34: astore_3
      35: aload_3
      36: invokeinterface #11,  1           // InterfaceMethod java/util/Iterator.hasNext:()Z
      41: ifeq          168
      44: aload_3
      45: invokeinterface #12,  1           // InterfaceMethod java/util/Iterator.next:()Ljava/lang/Object;
      50: checkcast     #13                 // class org/antlr/v4/runtime/dfa/DFAState
      53: astore        4
      55: iconst_0
      56: istore        5
      58: aload         4
      60: getfield      #14                 // Field org/antlr/v4/runtime/dfa/DFAState.edges:[Lorg/antlr/v4/runtime/dfa/DFAState;
      63: ifnull        74
      66: aload         4
      68: getfield      #14                 // Field org/antlr/v4/runtime/dfa/DFAState.edges:[Lorg/antlr/v4/runtime/dfa/DFAState;
      71: arraylength
      72: istore        5
      74: iconst_0
      75: istore        6
      77: iload         6
      79: iload         5
      81: if_icmpge     165
      84: aload         4
      86: getfield      #14                 // Field org/antlr/v4/runtime/dfa/DFAState.edges:[Lorg/antlr/v4/runtime/dfa/DFAState;
      89: iload         6
      91: aaload
      92: astore        7
      94: aload         7
      96: ifnull        159
      99: aload         7
     101: getfield      #15                 // Field org/antlr/v4/runtime/dfa/DFAState.stateNumber:I
     104: ldc           #16                 // int 2147483647
     106: if_icmpeq     159
     109: aload_1
     110: aload_0
     111: aload         4
     113: invokevirtual #17                 // Method getStateString:(Lorg/antlr/v4/runtime/dfa/DFAState;)Ljava/lang/String;
     116: invokevirtual #18                 // Method java/lang/StringBuilder.append:(Ljava/lang/String;)Ljava/lang/StringBuilder;
     119: pop
     120: aload_0
     121: iload         6
     123: invokevirtual #19                 // Method getEdgeLabel:(I)Ljava/lang/String;
     126: astore        8
     128: aload_1
     129: ldc           #20                 // String -
     131: invokevirtual #18                 // Method java/lang/StringBuilder.append:(Ljava/lang/String;)Ljava/lang/StringBuilder;
     134: aload         8
     136: invokevirtual #18                 // Method java/lang/StringBuilder.append:(Ljava/lang/String;)Ljava/lang/StringBuilder;
     139: ldc           #21                 // String ->
     141: invokevirtual #18                 // Method java/lang/StringBuilder.append:(Ljava/lang/String;)Ljava/lang/StringBuilder;
     144: aload_0
     145: aload         7
     147: invokevirtual #17                 // Method getStateString:(Lorg/antlr/v4/runtime/dfa/DFAState;)Ljava/lang/String;
     150: invokevirtual #18                 // Method java/lang/StringBuilder.append:(Ljava/lang/String;)Ljava/lang/StringBuilder;
     153: bipush        10
     155: invokevirtual #22                 // Method java/lang/StringBuilder.append:(C)Ljava/lang/StringBuilder;
     158: pop
     159: iinc          6, 1
     162: goto          77
     165: goto          35
     168: aload_1
     169: invokevirtual #23                 // Method java/lang/StringBuilder.toString:()Ljava/lang/String;
     172: astore_3
     173: aload_3
     174: invokevirtual #24                 // Method java/lang/String.length:()I
     177: ifne          182
     180: aconst_null
     181: areturn
     182: aload_3
     183: areturn

  protected java.lang.String getEdgeLabel(int);
    Code:
       0: aload_0
       1: getfield      #5                  // Field vocabulary:Lorg/antlr/v4/runtime/Vocabulary;
       4: iload_1
       5: iconst_1
       6: isub
       7: invokeinterface #25,  2           // InterfaceMethod org/antlr/v4/runtime/Vocabulary.getDisplayName:(I)Ljava/lang/String;
      12: areturn

  protected java.lang.String getStateString(org.antlr.v4.runtime.dfa.DFAState);
    Code:
       0: aload_1
       1: getfield      #15                 // Field org/antlr/v4/runtime/dfa/DFAState.stateNumber:I
       4: istore_2
       5: new           #7                  // class java/lang/StringBuilder
       8: dup
       9: invokespecial #8                  // Method java/lang/StringBuilder."<init>":()V
      12: aload_1
      13: getfield      #26                 // Field org/antlr/v4/runtime/dfa/DFAState.isAcceptState:Z
      16: ifeq          24
      19: ldc           #27                 // String :
      21: goto          26
      24: ldc           #28                 // String
      26: invokevirtual #18                 // Method java/lang/StringBuilder.append:(Ljava/lang/String;)Ljava/lang/StringBuilder;
      29: ldc           #29                 // String s
      31: invokevirtual #18                 // Method java/lang/StringBuilder.append:(Ljava/lang/String;)Ljava/lang/StringBuilder;
      34: iload_2
      35: invokevirtual #30                 // Method java/lang/StringBuilder.append:(I)Ljava/lang/StringBuilder;
      38: aload_1
      39: getfield      #31                 // Field org/antlr/v4/runtime/dfa/DFAState.requiresFullContext:Z
      42: ifeq          50
      45: ldc           #32                 // String ^
      47: goto          52
      50: ldc           #28                 // String
      52: invokevirtual #18                 // Method java/lang/StringBuilder.append:(Ljava/lang/String;)Ljava/lang/StringBuilder;
      55: invokevirtual #23                 // Method java/lang/StringBuilder.toString:()Ljava/lang/String;
      58: astore_3
      59: aload_1
      60: getfield      #26                 // Field org/antlr/v4/runtime/dfa/DFAState.isAcceptState:Z
      63: ifeq          130
      66: aload_1
      67: getfield      #33                 // Field org/antlr/v4/runtime/dfa/DFAState.predicates:[Lorg/antlr/v4/runtime/dfa/DFAState$PredPrediction;
      70: ifnull        103
      73: new           #7                  // class java/lang/StringBuilder
      76: dup
      77: invokespecial #8                  // Method java/lang/StringBuilder."<init>":()V
      80: aload_3
      81: invokevirtual #18                 // Method java/lang/StringBuilder.append:(Ljava/lang/String;)Ljava/lang/StringBuilder;
      84: ldc           #34                 // String =>
      86: invokevirtual #18                 // Method java/lang/StringBuilder.append:(Ljava/lang/String;)Ljava/lang/StringBuilder;
      89: aload_1
      90: getfield      #33                 // Field org/antlr/v4/runtime/dfa/DFAState.predicates:[Lorg/antlr/v4/runtime/dfa/DFAState$PredPrediction;
      93: invokestatic  #35                 // Method java/util/Arrays.toString:([Ljava/lang/Object;)Ljava/lang/String;
      96: invokevirtual #18                 // Method java/lang/StringBuilder.append:(Ljava/lang/String;)Ljava/lang/StringBuilder;
      99: invokevirtual #23                 // Method java/lang/StringBuilder.toString:()Ljava/lang/String;
     102: areturn
     103: new           #7                  // class java/lang/StringBuilder
     106: dup
     107: invokespecial #8                  // Method java/lang/StringBuilder."<init>":()V
     110: aload_3
     111: invokevirtual #18                 // Method java/lang/StringBuilder.append:(Ljava/lang/String;)Ljava/lang/StringBuilder;
     114: ldc           #34                 // String =>
     116: invokevirtual #18                 // Method java/lang/StringBuilder.append:(Ljava/lang/String;)Ljava/lang/StringBuilder;
     119: aload_1
     120: getfield      #36                 // Field org/antlr/v4/runtime/dfa/DFAState.prediction:I
     123: invokevirtual #30                 // Method java/lang/StringBuilder.append:(I)Ljava/lang/StringBuilder;
     126: invokevirtual #23                 // Method java/lang/StringBuilder.toString:()Ljava/lang/String;
     129: areturn
     130: aload_3
     131: areturn
}
