Compiled from "DistributedPubSubMessages.java"
public final class akka.cluster.pubsub.protobuf.msg.DistributedPubSubMessages$Delta$Bucket$Builder extends akka.protobuf.GeneratedMessage$Builder<akka.cluster.pubsub.protobuf.msg.DistributedPubSubMessages$Delta$Bucket$Builder> implements akka.cluster.pubsub.protobuf.msg.DistributedPubSubMessages$Delta$BucketOrBuilder {
  private int bitField0_;

  private akka.cluster.pubsub.protobuf.msg.DistributedPubSubMessages$Address owner_;

  private akka.protobuf.SingleFieldBuilder<akka.cluster.pubsub.protobuf.msg.DistributedPubSubMessages$Address, akka.cluster.pubsub.protobuf.msg.DistributedPubSubMessages$Address$Builder, akka.cluster.pubsub.protobuf.msg.DistributedPubSubMessages$AddressOrBuilder> ownerBuilder_;

  private long version_;

  private java.util.List<akka.cluster.pubsub.protobuf.msg.DistributedPubSubMessages$Delta$Entry> content_;

  private akka.protobuf.RepeatedFieldBuilder<akka.cluster.pubsub.protobuf.msg.DistributedPubSubMessages$Delta$Entry, akka.cluster.pubsub.protobuf.msg.DistributedPubSubMessages$Delta$Entry$Builder, akka.cluster.pubsub.protobuf.msg.DistributedPubSubMessages$Delta$EntryOrBuilder> contentBuilder_;

  public static final akka.protobuf.Descriptors$Descriptor getDescriptor();
    Code:
       0: invokestatic  #3                  // Method akka/cluster/pubsub/protobuf/msg/DistributedPubSubMessages.access$3500:()Lakka/protobuf/Descriptors$Descriptor;
       3: areturn

  protected akka.protobuf.GeneratedMessage$FieldAccessorTable internalGetFieldAccessorTable();
    Code:
       0: invokestatic  #4                  // Method akka/cluster/pubsub/protobuf/msg/DistributedPubSubMessages.access$3600:()Lakka/protobuf/GeneratedMessage$FieldAccessorTable;
       3: ldc           #5                  // class akka/cluster/pubsub/protobuf/msg/DistributedPubSubMessages$Delta$Bucket
       5: ldc           #6                  // class akka/cluster/pubsub/protobuf/msg/DistributedPubSubMessages$Delta$Bucket$Builder
       7: invokevirtual #7                  // Method akka/protobuf/GeneratedMessage$FieldAccessorTable.ensureFieldAccessorsInitialized:(Ljava/lang/Class;Ljava/lang/Class;)Lakka/protobuf/GeneratedMessage$FieldAccessorTable;
      10: areturn

  private akka.cluster.pubsub.protobuf.msg.DistributedPubSubMessages$Delta$Bucket$Builder();
    Code:
       0: aload_0
       1: invokespecial #8                  // Method akka/protobuf/GeneratedMessage$Builder."<init>":()V
       4: aload_0
       5: invokestatic  #9                  // Method akka/cluster/pubsub/protobuf/msg/DistributedPubSubMessages$Address.getDefaultInstance:()Lakka/cluster/pubsub/protobuf/msg/DistributedPubSubMessages$Address;
       8: putfield      #10                 // Field owner_:Lakka/cluster/pubsub/protobuf/msg/DistributedPubSubMessages$Address;
      11: aload_0
      12: invokestatic  #11                 // Method java/util/Collections.emptyList:()Ljava/util/List;
      15: putfield      #12                 // Field content_:Ljava/util/List;
      18: aload_0
      19: invokespecial #13                 // Method maybeForceBuilderInitialization:()V
      22: return

  private akka.cluster.pubsub.protobuf.msg.DistributedPubSubMessages$Delta$Bucket$Builder(akka.protobuf.GeneratedMessage$BuilderParent);
    Code:
       0: aload_0
       1: aload_1
       2: invokespecial #14                 // Method akka/protobuf/GeneratedMessage$Builder."<init>":(Lakka/protobuf/GeneratedMessage$BuilderParent;)V
       5: aload_0
       6: invokestatic  #9                  // Method akka/cluster/pubsub/protobuf/msg/DistributedPubSubMessages$Address.getDefaultInstance:()Lakka/cluster/pubsub/protobuf/msg/DistributedPubSubMessages$Address;
       9: putfield      #10                 // Field owner_:Lakka/cluster/pubsub/protobuf/msg/DistributedPubSubMessages$Address;
      12: aload_0
      13: invokestatic  #11                 // Method java/util/Collections.emptyList:()Ljava/util/List;
      16: putfield      #12                 // Field content_:Ljava/util/List;
      19: aload_0
      20: invokespecial #13                 // Method maybeForceBuilderInitialization:()V
      23: return

  private void maybeForceBuilderInitialization();
    Code:
       0: invokestatic  #15                 // Method akka/cluster/pubsub/protobuf/msg/DistributedPubSubMessages$Delta$Bucket.access$4000:()Z
       3: ifeq          16
       6: aload_0
       7: invokespecial #16                 // Method getOwnerFieldBuilder:()Lakka/protobuf/SingleFieldBuilder;
      10: pop
      11: aload_0
      12: invokespecial #17                 // Method getContentFieldBuilder:()Lakka/protobuf/RepeatedFieldBuilder;
      15: pop
      16: return

  private static akka.cluster.pubsub.protobuf.msg.DistributedPubSubMessages$Delta$Bucket$Builder create();
    Code:
       0: new           #6                  // class akka/cluster/pubsub/protobuf/msg/DistributedPubSubMessages$Delta$Bucket$Builder
       3: dup
       4: invokespecial #18                 // Method "<init>":()V
       7: areturn

  public akka.cluster.pubsub.protobuf.msg.DistributedPubSubMessages$Delta$Bucket$Builder clear();
    Code:
       0: aload_0
       1: invokespecial #19                 // Method akka/protobuf/GeneratedMessage$Builder.clear:()Lakka/protobuf/GeneratedMessage$Builder;
       4: pop
       5: aload_0
       6: getfield      #20                 // Field ownerBuilder_:Lakka/protobuf/SingleFieldBuilder;
       9: ifnonnull     22
      12: aload_0
      13: invokestatic  #9                  // Method akka/cluster/pubsub/protobuf/msg/DistributedPubSubMessages$Address.getDefaultInstance:()Lakka/cluster/pubsub/protobuf/msg/DistributedPubSubMessages$Address;
      16: putfield      #10                 // Field owner_:Lakka/cluster/pubsub/protobuf/msg/DistributedPubSubMessages$Address;
      19: goto          30
      22: aload_0
      23: getfield      #20                 // Field ownerBuilder_:Lakka/protobuf/SingleFieldBuilder;
      26: invokevirtual #21                 // Method akka/protobuf/SingleFieldBuilder.clear:()Lakka/protobuf/SingleFieldBuilder;
      29: pop
      30: aload_0
      31: aload_0
      32: getfield      #22                 // Field bitField0_:I
      35: bipush        -2
      37: iand
      38: putfield      #22                 // Field bitField0_:I
      41: aload_0
      42: lconst_0
      43: putfield      #23                 // Field version_:J
      46: aload_0
      47: aload_0
      48: getfield      #22                 // Field bitField0_:I
      51: bipush        -3
      53: iand
      54: putfield      #22                 // Field bitField0_:I
      57: aload_0
      58: getfield      #24                 // Field contentBuilder_:Lakka/protobuf/RepeatedFieldBuilder;
      61: ifnonnull     85
      64: aload_0
      65: invokestatic  #11                 // Method java/util/Collections.emptyList:()Ljava/util/List;
      68: putfield      #12                 // Field content_:Ljava/util/List;
      71: aload_0
      72: aload_0
      73: getfield      #22                 // Field bitField0_:I
      76: bipush        -5
      78: iand
      79: putfield      #22                 // Field bitField0_:I
      82: goto          92
      85: aload_0
      86: getfield      #24                 // Field contentBuilder_:Lakka/protobuf/RepeatedFieldBuilder;
      89: invokevirtual #25                 // Method akka/protobuf/RepeatedFieldBuilder.clear:()V
      92: aload_0
      93: areturn

  public akka.cluster.pubsub.protobuf.msg.DistributedPubSubMessages$Delta$Bucket$Builder clone();
    Code:
       0: invokestatic  #2                  // Method create:()Lakka/cluster/pubsub/protobuf/msg/DistributedPubSubMessages$Delta$Bucket$Builder;
       3: aload_0
       4: invokevirtual #26                 // Method buildPartial:()Lakka/cluster/pubsub/protobuf/msg/DistributedPubSubMessages$Delta$Bucket;
       7: invokevirtual #27                 // Method mergeFrom:(Lakka/cluster/pubsub/protobuf/msg/DistributedPubSubMessages$Delta$Bucket;)Lakka/cluster/pubsub/protobuf/msg/DistributedPubSubMessages$Delta$Bucket$Builder;
      10: areturn

  public akka.protobuf.Descriptors$Descriptor getDescriptorForType();
    Code:
       0: invokestatic  #3                  // Method akka/cluster/pubsub/protobuf/msg/DistributedPubSubMessages.access$3500:()Lakka/protobuf/Descriptors$Descriptor;
       3: areturn

  public akka.cluster.pubsub.protobuf.msg.DistributedPubSubMessages$Delta$Bucket getDefaultInstanceForType();
    Code:
       0: invokestatic  #28                 // Method akka/cluster/pubsub/protobuf/msg/DistributedPubSubMessages$Delta$Bucket.getDefaultInstance:()Lakka/cluster/pubsub/protobuf/msg/DistributedPubSubMessages$Delta$Bucket;
       3: areturn

  public akka.cluster.pubsub.protobuf.msg.DistributedPubSubMessages$Delta$Bucket build();
    Code:
       0: aload_0
       1: invokevirtual #26                 // Method buildPartial:()Lakka/cluster/pubsub/protobuf/msg/DistributedPubSubMessages$Delta$Bucket;
       4: astore_1
       5: aload_1
       6: invokevirtual #29                 // Method akka/cluster/pubsub/protobuf/msg/DistributedPubSubMessages$Delta$Bucket.isInitialized:()Z
       9: ifne          17
      12: aload_1
      13: invokestatic  #30                 // Method newUninitializedMessageException:(Lakka/protobuf/Message;)Lakka/protobuf/UninitializedMessageException;
      16: athrow
      17: aload_1
      18: areturn

  public akka.cluster.pubsub.protobuf.msg.DistributedPubSubMessages$Delta$Bucket buildPartial();
    Code:
       0: new           #5                  // class akka/cluster/pubsub/protobuf/msg/DistributedPubSubMessages$Delta$Bucket
       3: dup
       4: aload_0
       5: aconst_null
       6: invokespecial #31                 // Method akka/cluster/pubsub/protobuf/msg/DistributedPubSubMessages$Delta$Bucket."<init>":(Lakka/protobuf/GeneratedMessage$Builder;Lakka/cluster/pubsub/protobuf/msg/DistributedPubSubMessages$1;)V
       9: astore_1
      10: aload_0
      11: getfield      #22                 // Field bitField0_:I
      14: istore_2
      15: iconst_0
      16: istore_3
      17: iload_2
      18: iconst_1
      19: iand
      20: iconst_1
      21: if_icmpne     28
      24: iload_3
      25: iconst_1
      26: ior
      27: istore_3
      28: aload_0
      29: getfield      #20                 // Field ownerBuilder_:Lakka/protobuf/SingleFieldBuilder;
      32: ifnonnull     47
      35: aload_1
      36: aload_0
      37: getfield      #10                 // Field owner_:Lakka/cluster/pubsub/protobuf/msg/DistributedPubSubMessages$Address;
      40: invokestatic  #32                 // Method akka/cluster/pubsub/protobuf/msg/DistributedPubSubMessages$Delta$Bucket.access$4202:(Lakka/cluster/pubsub/protobuf/msg/DistributedPubSubMessages$Delta$Bucket;Lakka/cluster/pubsub/protobuf/msg/DistributedPubSubMessages$Address;)Lakka/cluster/pubsub/protobuf/msg/DistributedPubSubMessages$Address;
      43: pop
      44: goto          62
      47: aload_1
      48: aload_0
      49: getfield      #20                 // Field ownerBuilder_:Lakka/protobuf/SingleFieldBuilder;
      52: invokevirtual #33                 // Method akka/protobuf/SingleFieldBuilder.build:()Lakka/protobuf/GeneratedMessage;
      55: checkcast     #34                 // class akka/cluster/pubsub/protobuf/msg/DistributedPubSubMessages$Address
      58: invokestatic  #32                 // Method akka/cluster/pubsub/protobuf/msg/DistributedPubSubMessages$Delta$Bucket.access$4202:(Lakka/cluster/pubsub/protobuf/msg/DistributedPubSubMessages$Delta$Bucket;Lakka/cluster/pubsub/protobuf/msg/DistributedPubSubMessages$Address;)Lakka/cluster/pubsub/protobuf/msg/DistributedPubSubMessages$Address;
      61: pop
      62: iload_2
      63: iconst_2
      64: iand
      65: iconst_2
      66: if_icmpne     73
      69: iload_3
      70: iconst_2
      71: ior
      72: istore_3
      73: aload_1
      74: aload_0
      75: getfield      #23                 // Field version_:J
      78: invokestatic  #35                 // Method akka/cluster/pubsub/protobuf/msg/DistributedPubSubMessages$Delta$Bucket.access$4302:(Lakka/cluster/pubsub/protobuf/msg/DistributedPubSubMessages$Delta$Bucket;J)J
      81: pop2
      82: aload_0
      83: getfield      #24                 // Field contentBuilder_:Lakka/protobuf/RepeatedFieldBuilder;
      86: ifnonnull     133
      89: aload_0
      90: getfield      #22                 // Field bitField0_:I
      93: iconst_4
      94: iand
      95: iconst_4
      96: if_icmpne     121
      99: aload_0
     100: aload_0
     101: getfield      #12                 // Field content_:Ljava/util/List;
     104: invokestatic  #36                 // Method java/util/Collections.unmodifiableList:(Ljava/util/List;)Ljava/util/List;
     107: putfield      #12                 // Field content_:Ljava/util/List;
     110: aload_0
     111: aload_0
     112: getfield      #22                 // Field bitField0_:I
     115: bipush        -5
     117: iand
     118: putfield      #22                 // Field bitField0_:I
     121: aload_1
     122: aload_0
     123: getfield      #12                 // Field content_:Ljava/util/List;
     126: invokestatic  #37                 // Method akka/cluster/pubsub/protobuf/msg/DistributedPubSubMessages$Delta$Bucket.access$4402:(Lakka/cluster/pubsub/protobuf/msg/DistributedPubSubMessages$Delta$Bucket;Ljava/util/List;)Ljava/util/List;
     129: pop
     130: goto          145
     133: aload_1
     134: aload_0
     135: getfield      #24                 // Field contentBuilder_:Lakka/protobuf/RepeatedFieldBuilder;
     138: invokevirtual #38                 // Method akka/protobuf/RepeatedFieldBuilder.build:()Ljava/util/List;
     141: invokestatic  #37                 // Method akka/cluster/pubsub/protobuf/msg/DistributedPubSubMessages$Delta$Bucket.access$4402:(Lakka/cluster/pubsub/protobuf/msg/DistributedPubSubMessages$Delta$Bucket;Ljava/util/List;)Ljava/util/List;
     144: pop
     145: aload_1
     146: iload_3
     147: invokestatic  #39                 // Method akka/cluster/pubsub/protobuf/msg/DistributedPubSubMessages$Delta$Bucket.access$4502:(Lakka/cluster/pubsub/protobuf/msg/DistributedPubSubMessages$Delta$Bucket;I)I
     150: pop
     151: aload_0
     152: invokevirtual #40                 // Method onBuilt:()V
     155: aload_1
     156: areturn

  public akka.cluster.pubsub.protobuf.msg.DistributedPubSubMessages$Delta$Bucket$Builder mergeFrom(akka.protobuf.Message);
    Code:
       0: aload_1
       1: instanceof    #5                  // class akka/cluster/pubsub/protobuf/msg/DistributedPubSubMessages$Delta$Bucket
       4: ifeq          16
       7: aload_0
       8: aload_1
       9: checkcast     #5                  // class akka/cluster/pubsub/protobuf/msg/DistributedPubSubMessages$Delta$Bucket
      12: invokevirtual #27                 // Method mergeFrom:(Lakka/cluster/pubsub/protobuf/msg/DistributedPubSubMessages$Delta$Bucket;)Lakka/cluster/pubsub/protobuf/msg/DistributedPubSubMessages$Delta$Bucket$Builder;
      15: areturn
      16: aload_0
      17: aload_1
      18: invokespecial #41                 // Method akka/protobuf/GeneratedMessage$Builder.mergeFrom:(Lakka/protobuf/Message;)Lakka/protobuf/AbstractMessage$Builder;
      21: pop
      22: aload_0
      23: areturn

  public akka.cluster.pubsub.protobuf.msg.DistributedPubSubMessages$Delta$Bucket$Builder mergeFrom(akka.cluster.pubsub.protobuf.msg.DistributedPubSubMessages$Delta$Bucket);
    Code:
       0: aload_1
       1: invokestatic  #28                 // Method akka/cluster/pubsub/protobuf/msg/DistributedPubSubMessages$Delta$Bucket.getDefaultInstance:()Lakka/cluster/pubsub/protobuf/msg/DistributedPubSubMessages$Delta$Bucket;
       4: if_acmpne     9
       7: aload_0
       8: areturn
       9: aload_1
      10: invokevirtual #42                 // Method akka/cluster/pubsub/protobuf/msg/DistributedPubSubMessages$Delta$Bucket.hasOwner:()Z
      13: ifeq          25
      16: aload_0
      17: aload_1
      18: invokevirtual #43                 // Method akka/cluster/pubsub/protobuf/msg/DistributedPubSubMessages$Delta$Bucket.getOwner:()Lakka/cluster/pubsub/protobuf/msg/DistributedPubSubMessages$Address;
      21: invokevirtual #44                 // Method mergeOwner:(Lakka/cluster/pubsub/protobuf/msg/DistributedPubSubMessages$Address;)Lakka/cluster/pubsub/protobuf/msg/DistributedPubSubMessages$Delta$Bucket$Builder;
      24: pop
      25: aload_1
      26: invokevirtual #45                 // Method akka/cluster/pubsub/protobuf/msg/DistributedPubSubMessages$Delta$Bucket.hasVersion:()Z
      29: ifeq          41
      32: aload_0
      33: aload_1
      34: invokevirtual #46                 // Method akka/cluster/pubsub/protobuf/msg/DistributedPubSubMessages$Delta$Bucket.getVersion:()J
      37: invokevirtual #47                 // Method setVersion:(J)Lakka/cluster/pubsub/protobuf/msg/DistributedPubSubMessages$Delta$Bucket$Builder;
      40: pop
      41: aload_0
      42: getfield      #24                 // Field contentBuilder_:Lakka/protobuf/RepeatedFieldBuilder;
      45: ifnonnull     119
      48: aload_1
      49: invokestatic  #48                 // Method akka/cluster/pubsub/protobuf/msg/DistributedPubSubMessages$Delta$Bucket.access$4400:(Lakka/cluster/pubsub/protobuf/msg/DistributedPubSubMessages$Delta$Bucket;)Ljava/util/List;
      52: invokeinterface #49,  1           // InterfaceMethod java/util/List.isEmpty:()Z
      57: ifne          205
      60: aload_0
      61: getfield      #12                 // Field content_:Ljava/util/List;
      64: invokeinterface #49,  1           // InterfaceMethod java/util/List.isEmpty:()Z
      69: ifeq          94
      72: aload_0
      73: aload_1
      74: invokestatic  #48                 // Method akka/cluster/pubsub/protobuf/msg/DistributedPubSubMessages$Delta$Bucket.access$4400:(Lakka/cluster/pubsub/protobuf/msg/DistributedPubSubMessages$Delta$Bucket;)Ljava/util/List;
      77: putfield      #12                 // Field content_:Ljava/util/List;
      80: aload_0
      81: aload_0
      82: getfield      #22                 // Field bitField0_:I
      85: bipush        -5
      87: iand
      88: putfield      #22                 // Field bitField0_:I
      91: goto          112
      94: aload_0
      95: invokespecial #50                 // Method ensureContentIsMutable:()V
      98: aload_0
      99: getfield      #12                 // Field content_:Ljava/util/List;
     102: aload_1
     103: invokestatic  #48                 // Method akka/cluster/pubsub/protobuf/msg/DistributedPubSubMessages$Delta$Bucket.access$4400:(Lakka/cluster/pubsub/protobuf/msg/DistributedPubSubMessages$Delta$Bucket;)Ljava/util/List;
     106: invokeinterface #51,  2           // InterfaceMethod java/util/List.addAll:(Ljava/util/Collection;)Z
     111: pop
     112: aload_0
     113: invokevirtual #52                 // Method onChanged:()V
     116: goto          205
     119: aload_1
     120: invokestatic  #48                 // Method akka/cluster/pubsub/protobuf/msg/DistributedPubSubMessages$Delta$Bucket.access$4400:(Lakka/cluster/pubsub/protobuf/msg/DistributedPubSubMessages$Delta$Bucket;)Ljava/util/List;
     123: invokeinterface #49,  1           // InterfaceMethod java/util/List.isEmpty:()Z
     128: ifne          205
     131: aload_0
     132: getfield      #24                 // Field contentBuilder_:Lakka/protobuf/RepeatedFieldBuilder;
     135: invokevirtual #53                 // Method akka/protobuf/RepeatedFieldBuilder.isEmpty:()Z
     138: ifeq          193
     141: aload_0
     142: getfield      #24                 // Field contentBuilder_:Lakka/protobuf/RepeatedFieldBuilder;
     145: invokevirtual #54                 // Method akka/protobuf/RepeatedFieldBuilder.dispose:()V
     148: aload_0
     149: aconst_null
     150: putfield      #24                 // Field contentBuilder_:Lakka/protobuf/RepeatedFieldBuilder;
     153: aload_0
     154: aload_1
     155: invokestatic  #48                 // Method akka/cluster/pubsub/protobuf/msg/DistributedPubSubMessages$Delta$Bucket.access$4400:(Lakka/cluster/pubsub/protobuf/msg/DistributedPubSubMessages$Delta$Bucket;)Ljava/util/List;
     158: putfield      #12                 // Field content_:Ljava/util/List;
     161: aload_0
     162: aload_0
     163: getfield      #22                 // Field bitField0_:I
     166: bipush        -5
     168: iand
     169: putfield      #22                 // Field bitField0_:I
     172: aload_0
     173: invokestatic  #55                 // Method akka/cluster/pubsub/protobuf/msg/DistributedPubSubMessages$Delta$Bucket.access$4600:()Z
     176: ifeq          186
     179: aload_0
     180: invokespecial #17                 // Method getContentFieldBuilder:()Lakka/protobuf/RepeatedFieldBuilder;
     183: goto          187
     186: aconst_null
     187: putfield      #24                 // Field contentBuilder_:Lakka/protobuf/RepeatedFieldBuilder;
     190: goto          205
     193: aload_0
     194: getfield      #24                 // Field contentBuilder_:Lakka/protobuf/RepeatedFieldBuilder;
     197: aload_1
     198: invokestatic  #48                 // Method akka/cluster/pubsub/protobuf/msg/DistributedPubSubMessages$Delta$Bucket.access$4400:(Lakka/cluster/pubsub/protobuf/msg/DistributedPubSubMessages$Delta$Bucket;)Ljava/util/List;
     201: invokevirtual #56                 // Method akka/protobuf/RepeatedFieldBuilder.addAllMessages:(Ljava/lang/Iterable;)Lakka/protobuf/RepeatedFieldBuilder;
     204: pop
     205: aload_0
     206: aload_1
     207: invokevirtual #57                 // Method akka/cluster/pubsub/protobuf/msg/DistributedPubSubMessages$Delta$Bucket.getUnknownFields:()Lakka/protobuf/UnknownFieldSet;
     210: invokevirtual #58                 // Method mergeUnknownFields:(Lakka/protobuf/UnknownFieldSet;)Lakka/protobuf/GeneratedMessage$Builder;
     213: pop
     214: aload_0
     215: areturn

  public final boolean isInitialized();
    Code:
       0: aload_0
       1: invokevirtual #59                 // Method hasOwner:()Z
       4: ifne          9
       7: iconst_0
       8: ireturn
       9: aload_0
      10: invokevirtual #60                 // Method hasVersion:()Z
      13: ifne          18
      16: iconst_0
      17: ireturn
      18: aload_0
      19: invokevirtual #61                 // Method getOwner:()Lakka/cluster/pubsub/protobuf/msg/DistributedPubSubMessages$Address;
      22: invokevirtual #62                 // Method akka/cluster/pubsub/protobuf/msg/DistributedPubSubMessages$Address.isInitialized:()Z
      25: ifne          30
      28: iconst_0
      29: ireturn
      30: iconst_0
      31: istore_1
      32: iload_1
      33: aload_0
      34: invokevirtual #63                 // Method getContentCount:()I
      37: if_icmpge     59
      40: aload_0
      41: iload_1
      42: invokevirtual #64                 // Method getContent:(I)Lakka/cluster/pubsub/protobuf/msg/DistributedPubSubMessages$Delta$Entry;
      45: invokevirtual #65                 // Method akka/cluster/pubsub/protobuf/msg/DistributedPubSubMessages$Delta$Entry.isInitialized:()Z
      48: ifne          53
      51: iconst_0
      52: ireturn
      53: iinc          1, 1
      56: goto          32
      59: iconst_1
      60: ireturn

  public akka.cluster.pubsub.protobuf.msg.DistributedPubSubMessages$Delta$Bucket$Builder mergeFrom(akka.protobuf.CodedInputStream, akka.protobuf.ExtensionRegistryLite) throws java.io.IOException;
    Code:
       0: aconst_null
       1: astore_3
       2: getstatic     #66                 // Field akka/cluster/pubsub/protobuf/msg/DistributedPubSubMessages$Delta$Bucket.PARSER:Lakka/protobuf/Parser;
       5: aload_1
       6: aload_2
       7: invokeinterface #67,  3           // InterfaceMethod akka/protobuf/Parser.parsePartialFrom:(Lakka/protobuf/CodedInputStream;Lakka/protobuf/ExtensionRegistryLite;)Ljava/lang/Object;
      12: checkcast     #5                  // class akka/cluster/pubsub/protobuf/msg/DistributedPubSubMessages$Delta$Bucket
      15: astore_3
      16: aload_3
      17: ifnull        58
      20: aload_0
      21: aload_3
      22: invokevirtual #27                 // Method mergeFrom:(Lakka/cluster/pubsub/protobuf/msg/DistributedPubSubMessages$Delta$Bucket;)Lakka/cluster/pubsub/protobuf/msg/DistributedPubSubMessages$Delta$Bucket$Builder;
      25: pop
      26: goto          58
      29: astore        4
      31: aload         4
      33: invokevirtual #69                 // Method akka/protobuf/InvalidProtocolBufferException.getUnfinishedMessage:()Lakka/protobuf/MessageLite;
      36: checkcast     #5                  // class akka/cluster/pubsub/protobuf/msg/DistributedPubSubMessages$Delta$Bucket
      39: astore_3
      40: aload         4
      42: athrow
      43: astore        5
      45: aload_3
      46: ifnull        55
      49: aload_0
      50: aload_3
      51: invokevirtual #27                 // Method mergeFrom:(Lakka/cluster/pubsub/protobuf/msg/DistributedPubSubMessages$Delta$Bucket;)Lakka/cluster/pubsub/protobuf/msg/DistributedPubSubMessages$Delta$Bucket$Builder;
      54: pop
      55: aload         5
      57: athrow
      58: aload_0
      59: areturn
    Exception table:
       from    to  target type
           2    16    29   Class akka/protobuf/InvalidProtocolBufferException
           2    16    43   any
          29    45    43   any

  public boolean hasOwner();
    Code:
       0: aload_0
       1: getfield      #22                 // Field bitField0_:I
       4: iconst_1
       5: iand
       6: iconst_1
       7: if_icmpne     14
      10: iconst_1
      11: goto          15
      14: iconst_0
      15: ireturn

  public akka.cluster.pubsub.protobuf.msg.DistributedPubSubMessages$Address getOwner();
    Code:
       0: aload_0
       1: getfield      #20                 // Field ownerBuilder_:Lakka/protobuf/SingleFieldBuilder;
       4: ifnonnull     12
       7: aload_0
       8: getfield      #10                 // Field owner_:Lakka/cluster/pubsub/protobuf/msg/DistributedPubSubMessages$Address;
      11: areturn
      12: aload_0
      13: getfield      #20                 // Field ownerBuilder_:Lakka/protobuf/SingleFieldBuilder;
      16: invokevirtual #70                 // Method akka/protobuf/SingleFieldBuilder.getMessage:()Lakka/protobuf/GeneratedMessage;
      19: checkcast     #34                 // class akka/cluster/pubsub/protobuf/msg/DistributedPubSubMessages$Address
      22: areturn

  public akka.cluster.pubsub.protobuf.msg.DistributedPubSubMessages$Delta$Bucket$Builder setOwner(akka.cluster.pubsub.protobuf.msg.DistributedPubSubMessages$Address);
    Code:
       0: aload_0
       1: getfield      #20                 // Field ownerBuilder_:Lakka/protobuf/SingleFieldBuilder;
       4: ifnonnull     31
       7: aload_1
       8: ifnonnull     19
      11: new           #71                 // class java/lang/NullPointerException
      14: dup
      15: invokespecial #72                 // Method java/lang/NullPointerException."<init>":()V
      18: athrow
      19: aload_0
      20: aload_1
      21: putfield      #10                 // Field owner_:Lakka/cluster/pubsub/protobuf/msg/DistributedPubSubMessages$Address;
      24: aload_0
      25: invokevirtual #52                 // Method onChanged:()V
      28: goto          40
      31: aload_0
      32: getfield      #20                 // Field ownerBuilder_:Lakka/protobuf/SingleFieldBuilder;
      35: aload_1
      36: invokevirtual #73                 // Method akka/protobuf/SingleFieldBuilder.setMessage:(Lakka/protobuf/GeneratedMessage;)Lakka/protobuf/SingleFieldBuilder;
      39: pop
      40: aload_0
      41: dup
      42: getfield      #22                 // Field bitField0_:I
      45: iconst_1
      46: ior
      47: putfield      #22                 // Field bitField0_:I
      50: aload_0
      51: areturn

  public akka.cluster.pubsub.protobuf.msg.DistributedPubSubMessages$Delta$Bucket$Builder setOwner(akka.cluster.pubsub.protobuf.msg.DistributedPubSubMessages$Address$Builder);
    Code:
       0: aload_0
       1: getfield      #20                 // Field ownerBuilder_:Lakka/protobuf/SingleFieldBuilder;
       4: ifnonnull     22
       7: aload_0
       8: aload_1
       9: invokevirtual #74                 // Method akka/cluster/pubsub/protobuf/msg/DistributedPubSubMessages$Address$Builder.build:()Lakka/cluster/pubsub/protobuf/msg/DistributedPubSubMessages$Address;
      12: putfield      #10                 // Field owner_:Lakka/cluster/pubsub/protobuf/msg/DistributedPubSubMessages$Address;
      15: aload_0
      16: invokevirtual #52                 // Method onChanged:()V
      19: goto          34
      22: aload_0
      23: getfield      #20                 // Field ownerBuilder_:Lakka/protobuf/SingleFieldBuilder;
      26: aload_1
      27: invokevirtual #74                 // Method akka/cluster/pubsub/protobuf/msg/DistributedPubSubMessages$Address$Builder.build:()Lakka/cluster/pubsub/protobuf/msg/DistributedPubSubMessages$Address;
      30: invokevirtual #73                 // Method akka/protobuf/SingleFieldBuilder.setMessage:(Lakka/protobuf/GeneratedMessage;)Lakka/protobuf/SingleFieldBuilder;
      33: pop
      34: aload_0
      35: dup
      36: getfield      #22                 // Field bitField0_:I
      39: iconst_1
      40: ior
      41: putfield      #22                 // Field bitField0_:I
      44: aload_0
      45: areturn

  public akka.cluster.pubsub.protobuf.msg.DistributedPubSubMessages$Delta$Bucket$Builder mergeOwner(akka.cluster.pubsub.protobuf.msg.DistributedPubSubMessages$Address);
    Code:
       0: aload_0
       1: getfield      #20                 // Field ownerBuilder_:Lakka/protobuf/SingleFieldBuilder;
       4: ifnonnull     60
       7: aload_0
       8: getfield      #22                 // Field bitField0_:I
      11: iconst_1
      12: iand
      13: iconst_1
      14: if_icmpne     48
      17: aload_0
      18: getfield      #10                 // Field owner_:Lakka/cluster/pubsub/protobuf/msg/DistributedPubSubMessages$Address;
      21: invokestatic  #9                  // Method akka/cluster/pubsub/protobuf/msg/DistributedPubSubMessages$Address.getDefaultInstance:()Lakka/cluster/pubsub/protobuf/msg/DistributedPubSubMessages$Address;
      24: if_acmpeq     48
      27: aload_0
      28: aload_0
      29: getfield      #10                 // Field owner_:Lakka/cluster/pubsub/protobuf/msg/DistributedPubSubMessages$Address;
      32: invokestatic  #75                 // Method akka/cluster/pubsub/protobuf/msg/DistributedPubSubMessages$Address.newBuilder:(Lakka/cluster/pubsub/protobuf/msg/DistributedPubSubMessages$Address;)Lakka/cluster/pubsub/protobuf/msg/DistributedPubSubMessages$Address$Builder;
      35: aload_1
      36: invokevirtual #76                 // Method akka/cluster/pubsub/protobuf/msg/DistributedPubSubMessages$Address$Builder.mergeFrom:(Lakka/cluster/pubsub/protobuf/msg/DistributedPubSubMessages$Address;)Lakka/cluster/pubsub/protobuf/msg/DistributedPubSubMessages$Address$Builder;
      39: invokevirtual #77                 // Method akka/cluster/pubsub/protobuf/msg/DistributedPubSubMessages$Address$Builder.buildPartial:()Lakka/cluster/pubsub/protobuf/msg/DistributedPubSubMessages$Address;
      42: putfield      #10                 // Field owner_:Lakka/cluster/pubsub/protobuf/msg/DistributedPubSubMessages$Address;
      45: goto          53
      48: aload_0
      49: aload_1
      50: putfield      #10                 // Field owner_:Lakka/cluster/pubsub/protobuf/msg/DistributedPubSubMessages$Address;
      53: aload_0
      54: invokevirtual #52                 // Method onChanged:()V
      57: goto          69
      60: aload_0
      61: getfield      #20                 // Field ownerBuilder_:Lakka/protobuf/SingleFieldBuilder;
      64: aload_1
      65: invokevirtual #78                 // Method akka/protobuf/SingleFieldBuilder.mergeFrom:(Lakka/protobuf/GeneratedMessage;)Lakka/protobuf/SingleFieldBuilder;
      68: pop
      69: aload_0
      70: dup
      71: getfield      #22                 // Field bitField0_:I
      74: iconst_1
      75: ior
      76: putfield      #22                 // Field bitField0_:I
      79: aload_0
      80: areturn

  public akka.cluster.pubsub.protobuf.msg.DistributedPubSubMessages$Delta$Bucket$Builder clearOwner();
    Code:
       0: aload_0
       1: getfield      #20                 // Field ownerBuilder_:Lakka/protobuf/SingleFieldBuilder;
       4: ifnonnull     21
       7: aload_0
       8: invokestatic  #9                  // Method akka/cluster/pubsub/protobuf/msg/DistributedPubSubMessages$Address.getDefaultInstance:()Lakka/cluster/pubsub/protobuf/msg/DistributedPubSubMessages$Address;
      11: putfield      #10                 // Field owner_:Lakka/cluster/pubsub/protobuf/msg/DistributedPubSubMessages$Address;
      14: aload_0
      15: invokevirtual #52                 // Method onChanged:()V
      18: goto          29
      21: aload_0
      22: getfield      #20                 // Field ownerBuilder_:Lakka/protobuf/SingleFieldBuilder;
      25: invokevirtual #21                 // Method akka/protobuf/SingleFieldBuilder.clear:()Lakka/protobuf/SingleFieldBuilder;
      28: pop
      29: aload_0
      30: aload_0
      31: getfield      #22                 // Field bitField0_:I
      34: bipush        -2
      36: iand
      37: putfield      #22                 // Field bitField0_:I
      40: aload_0
      41: areturn

  public akka.cluster.pubsub.protobuf.msg.DistributedPubSubMessages$Address$Builder getOwnerBuilder();
    Code:
       0: aload_0
       1: dup
       2: getfield      #22                 // Field bitField0_:I
       5: iconst_1
       6: ior
       7: putfield      #22                 // Field bitField0_:I
      10: aload_0
      11: invokevirtual #52                 // Method onChanged:()V
      14: aload_0
      15: invokespecial #16                 // Method getOwnerFieldBuilder:()Lakka/protobuf/SingleFieldBuilder;
      18: invokevirtual #79                 // Method akka/protobuf/SingleFieldBuilder.getBuilder:()Lakka/protobuf/GeneratedMessage$Builder;
      21: checkcast     #80                 // class akka/cluster/pubsub/protobuf/msg/DistributedPubSubMessages$Address$Builder
      24: areturn

  public akka.cluster.pubsub.protobuf.msg.DistributedPubSubMessages$AddressOrBuilder getOwnerOrBuilder();
    Code:
       0: aload_0
       1: getfield      #20                 // Field ownerBuilder_:Lakka/protobuf/SingleFieldBuilder;
       4: ifnull        18
       7: aload_0
       8: getfield      #20                 // Field ownerBuilder_:Lakka/protobuf/SingleFieldBuilder;
      11: invokevirtual #81                 // Method akka/protobuf/SingleFieldBuilder.getMessageOrBuilder:()Lakka/protobuf/MessageOrBuilder;
      14: checkcast     #82                 // class akka/cluster/pubsub/protobuf/msg/DistributedPubSubMessages$AddressOrBuilder
      17: areturn
      18: aload_0
      19: getfield      #10                 // Field owner_:Lakka/cluster/pubsub/protobuf/msg/DistributedPubSubMessages$Address;
      22: areturn

  private akka.protobuf.SingleFieldBuilder<akka.cluster.pubsub.protobuf.msg.DistributedPubSubMessages$Address, akka.cluster.pubsub.protobuf.msg.DistributedPubSubMessages$Address$Builder, akka.cluster.pubsub.protobuf.msg.DistributedPubSubMessages$AddressOrBuilder> getOwnerFieldBuilder();
    Code:
       0: aload_0
       1: getfield      #20                 // Field ownerBuilder_:Lakka/protobuf/SingleFieldBuilder;
       4: ifnonnull     35
       7: aload_0
       8: new           #83                 // class akka/protobuf/SingleFieldBuilder
      11: dup
      12: aload_0
      13: getfield      #10                 // Field owner_:Lakka/cluster/pubsub/protobuf/msg/DistributedPubSubMessages$Address;
      16: aload_0
      17: invokevirtual #84                 // Method getParentForChildren:()Lakka/protobuf/GeneratedMessage$BuilderParent;
      20: aload_0
      21: invokevirtual #85                 // Method isClean:()Z
      24: invokespecial #86                 // Method akka/protobuf/SingleFieldBuilder."<init>":(Lakka/protobuf/GeneratedMessage;Lakka/protobuf/GeneratedMessage$BuilderParent;Z)V
      27: putfield      #20                 // Field ownerBuilder_:Lakka/protobuf/SingleFieldBuilder;
      30: aload_0
      31: aconst_null
      32: putfield      #10                 // Field owner_:Lakka/cluster/pubsub/protobuf/msg/DistributedPubSubMessages$Address;
      35: aload_0
      36: getfield      #20                 // Field ownerBuilder_:Lakka/protobuf/SingleFieldBuilder;
      39: areturn

  public boolean hasVersion();
    Code:
       0: aload_0
       1: getfield      #22                 // Field bitField0_:I
       4: iconst_2
       5: iand
       6: iconst_2
       7: if_icmpne     14
      10: iconst_1
      11: goto          15
      14: iconst_0
      15: ireturn

  public long getVersion();
    Code:
       0: aload_0
       1: getfield      #23                 // Field version_:J
       4: lreturn

  public akka.cluster.pubsub.protobuf.msg.DistributedPubSubMessages$Delta$Bucket$Builder setVersion(long);
    Code:
       0: aload_0
       1: dup
       2: getfield      #22                 // Field bitField0_:I
       5: iconst_2
       6: ior
       7: putfield      #22                 // Field bitField0_:I
      10: aload_0
      11: lload_1
      12: putfield      #23                 // Field version_:J
      15: aload_0
      16: invokevirtual #52                 // Method onChanged:()V
      19: aload_0
      20: areturn

  public akka.cluster.pubsub.protobuf.msg.DistributedPubSubMessages$Delta$Bucket$Builder clearVersion();
    Code:
       0: aload_0
       1: aload_0
       2: getfield      #22                 // Field bitField0_:I
       5: bipush        -3
       7: iand
       8: putfield      #22                 // Field bitField0_:I
      11: aload_0
      12: lconst_0
      13: putfield      #23                 // Field version_:J
      16: aload_0
      17: invokevirtual #52                 // Method onChanged:()V
      20: aload_0
      21: areturn

  private void ensureContentIsMutable();
    Code:
       0: aload_0
       1: getfield      #22                 // Field bitField0_:I
       4: iconst_4
       5: iand
       6: iconst_4
       7: if_icmpeq     35
      10: aload_0
      11: new           #87                 // class java/util/ArrayList
      14: dup
      15: aload_0
      16: getfield      #12                 // Field content_:Ljava/util/List;
      19: invokespecial #88                 // Method java/util/ArrayList."<init>":(Ljava/util/Collection;)V
      22: putfield      #12                 // Field content_:Ljava/util/List;
      25: aload_0
      26: dup
      27: getfield      #22                 // Field bitField0_:I
      30: iconst_4
      31: ior
      32: putfield      #22                 // Field bitField0_:I
      35: return

  public java.util.List<akka.cluster.pubsub.protobuf.msg.DistributedPubSubMessages$Delta$Entry> getContentList();
    Code:
       0: aload_0
       1: getfield      #24                 // Field contentBuilder_:Lakka/protobuf/RepeatedFieldBuilder;
       4: ifnonnull     15
       7: aload_0
       8: getfield      #12                 // Field content_:Ljava/util/List;
      11: invokestatic  #36                 // Method java/util/Collections.unmodifiableList:(Ljava/util/List;)Ljava/util/List;
      14: areturn
      15: aload_0
      16: getfield      #24                 // Field contentBuilder_:Lakka/protobuf/RepeatedFieldBuilder;
      19: invokevirtual #89                 // Method akka/protobuf/RepeatedFieldBuilder.getMessageList:()Ljava/util/List;
      22: areturn

  public int getContentCount();
    Code:
       0: aload_0
       1: getfield      #24                 // Field contentBuilder_:Lakka/protobuf/RepeatedFieldBuilder;
       4: ifnonnull     17
       7: aload_0
       8: getfield      #12                 // Field content_:Ljava/util/List;
      11: invokeinterface #90,  1           // InterfaceMethod java/util/List.size:()I
      16: ireturn
      17: aload_0
      18: getfield      #24                 // Field contentBuilder_:Lakka/protobuf/RepeatedFieldBuilder;
      21: invokevirtual #91                 // Method akka/protobuf/RepeatedFieldBuilder.getCount:()I
      24: ireturn

  public akka.cluster.pubsub.protobuf.msg.DistributedPubSubMessages$Delta$Entry getContent(int);
    Code:
       0: aload_0
       1: getfield      #24                 // Field contentBuilder_:Lakka/protobuf/RepeatedFieldBuilder;
       4: ifnonnull     21
       7: aload_0
       8: getfield      #12                 // Field content_:Ljava/util/List;
      11: iload_1
      12: invokeinterface #92,  2           // InterfaceMethod java/util/List.get:(I)Ljava/lang/Object;
      17: checkcast     #93                 // class akka/cluster/pubsub/protobuf/msg/DistributedPubSubMessages$Delta$Entry
      20: areturn
      21: aload_0
      22: getfield      #24                 // Field contentBuilder_:Lakka/protobuf/RepeatedFieldBuilder;
      25: iload_1
      26: invokevirtual #94                 // Method akka/protobuf/RepeatedFieldBuilder.getMessage:(I)Lakka/protobuf/GeneratedMessage;
      29: checkcast     #93                 // class akka/cluster/pubsub/protobuf/msg/DistributedPubSubMessages$Delta$Entry
      32: areturn

  public akka.cluster.pubsub.protobuf.msg.DistributedPubSubMessages$Delta$Bucket$Builder setContent(int, akka.cluster.pubsub.protobuf.msg.DistributedPubSubMessages$Delta$Entry);
    Code:
       0: aload_0
       1: getfield      #24                 // Field contentBuilder_:Lakka/protobuf/RepeatedFieldBuilder;
       4: ifnonnull     42
       7: aload_2
       8: ifnonnull     19
      11: new           #71                 // class java/lang/NullPointerException
      14: dup
      15: invokespecial #72                 // Method java/lang/NullPointerException."<init>":()V
      18: athrow
      19: aload_0
      20: invokespecial #50                 // Method ensureContentIsMutable:()V
      23: aload_0
      24: getfield      #12                 // Field content_:Ljava/util/List;
      27: iload_1
      28: aload_2
      29: invokeinterface #95,  3           // InterfaceMethod java/util/List.set:(ILjava/lang/Object;)Ljava/lang/Object;
      34: pop
      35: aload_0
      36: invokevirtual #52                 // Method onChanged:()V
      39: goto          52
      42: aload_0
      43: getfield      #24                 // Field contentBuilder_:Lakka/protobuf/RepeatedFieldBuilder;
      46: iload_1
      47: aload_2
      48: invokevirtual #96                 // Method akka/protobuf/RepeatedFieldBuilder.setMessage:(ILakka/protobuf/GeneratedMessage;)Lakka/protobuf/RepeatedFieldBuilder;
      51: pop
      52: aload_0
      53: areturn

  public akka.cluster.pubsub.protobuf.msg.DistributedPubSubMessages$Delta$Bucket$Builder setContent(int, akka.cluster.pubsub.protobuf.msg.DistributedPubSubMessages$Delta$Entry$Builder);
    Code:
       0: aload_0
       1: getfield      #24                 // Field contentBuilder_:Lakka/protobuf/RepeatedFieldBuilder;
       4: ifnonnull     33
       7: aload_0
       8: invokespecial #50                 // Method ensureContentIsMutable:()V
      11: aload_0
      12: getfield      #12                 // Field content_:Ljava/util/List;
      15: iload_1
      16: aload_2
      17: invokevirtual #97                 // Method akka/cluster/pubsub/protobuf/msg/DistributedPubSubMessages$Delta$Entry$Builder.build:()Lakka/cluster/pubsub/protobuf/msg/DistributedPubSubMessages$Delta$Entry;
      20: invokeinterface #95,  3           // InterfaceMethod java/util/List.set:(ILjava/lang/Object;)Ljava/lang/Object;
      25: pop
      26: aload_0
      27: invokevirtual #52                 // Method onChanged:()V
      30: goto          46
      33: aload_0
      34: getfield      #24                 // Field contentBuilder_:Lakka/protobuf/RepeatedFieldBuilder;
      37: iload_1
      38: aload_2
      39: invokevirtual #97                 // Method akka/cluster/pubsub/protobuf/msg/DistributedPubSubMessages$Delta$Entry$Builder.build:()Lakka/cluster/pubsub/protobuf/msg/DistributedPubSubMessages$Delta$Entry;
      42: invokevirtual #96                 // Method akka/protobuf/RepeatedFieldBuilder.setMessage:(ILakka/protobuf/GeneratedMessage;)Lakka/protobuf/RepeatedFieldBuilder;
      45: pop
      46: aload_0
      47: areturn

  public akka.cluster.pubsub.protobuf.msg.DistributedPubSubMessages$Delta$Bucket$Builder addContent(akka.cluster.pubsub.protobuf.msg.DistributedPubSubMessages$Delta$Entry);
    Code:
       0: aload_0
       1: getfield      #24                 // Field contentBuilder_:Lakka/protobuf/RepeatedFieldBuilder;
       4: ifnonnull     41
       7: aload_1
       8: ifnonnull     19
      11: new           #71                 // class java/lang/NullPointerException
      14: dup
      15: invokespecial #72                 // Method java/lang/NullPointerException."<init>":()V
      18: athrow
      19: aload_0
      20: invokespecial #50                 // Method ensureContentIsMutable:()V
      23: aload_0
      24: getfield      #12                 // Field content_:Ljava/util/List;
      27: aload_1
      28: invokeinterface #98,  2           // InterfaceMethod java/util/List.add:(Ljava/lang/Object;)Z
      33: pop
      34: aload_0
      35: invokevirtual #52                 // Method onChanged:()V
      38: goto          50
      41: aload_0
      42: getfield      #24                 // Field contentBuilder_:Lakka/protobuf/RepeatedFieldBuilder;
      45: aload_1
      46: invokevirtual #99                 // Method akka/protobuf/RepeatedFieldBuilder.addMessage:(Lakka/protobuf/GeneratedMessage;)Lakka/protobuf/RepeatedFieldBuilder;
      49: pop
      50: aload_0
      51: areturn

  public akka.cluster.pubsub.protobuf.msg.DistributedPubSubMessages$Delta$Bucket$Builder addContent(int, akka.cluster.pubsub.protobuf.msg.DistributedPubSubMessages$Delta$Entry);
    Code:
       0: aload_0
       1: getfield      #24                 // Field contentBuilder_:Lakka/protobuf/RepeatedFieldBuilder;
       4: ifnonnull     41
       7: aload_2
       8: ifnonnull     19
      11: new           #71                 // class java/lang/NullPointerException
      14: dup
      15: invokespecial #72                 // Method java/lang/NullPointerException."<init>":()V
      18: athrow
      19: aload_0
      20: invokespecial #50                 // Method ensureContentIsMutable:()V
      23: aload_0
      24: getfield      #12                 // Field content_:Ljava/util/List;
      27: iload_1
      28: aload_2
      29: invokeinterface #100,  3          // InterfaceMethod java/util/List.add:(ILjava/lang/Object;)V
      34: aload_0
      35: invokevirtual #52                 // Method onChanged:()V
      38: goto          51
      41: aload_0
      42: getfield      #24                 // Field contentBuilder_:Lakka/protobuf/RepeatedFieldBuilder;
      45: iload_1
      46: aload_2
      47: invokevirtual #101                // Method akka/protobuf/RepeatedFieldBuilder.addMessage:(ILakka/protobuf/GeneratedMessage;)Lakka/protobuf/RepeatedFieldBuilder;
      50: pop
      51: aload_0
      52: areturn

  public akka.cluster.pubsub.protobuf.msg.DistributedPubSubMessages$Delta$Bucket$Builder addContent(akka.cluster.pubsub.protobuf.msg.DistributedPubSubMessages$Delta$Entry$Builder);
    Code:
       0: aload_0
       1: getfield      #24                 // Field contentBuilder_:Lakka/protobuf/RepeatedFieldBuilder;
       4: ifnonnull     32
       7: aload_0
       8: invokespecial #50                 // Method ensureContentIsMutable:()V
      11: aload_0
      12: getfield      #12                 // Field content_:Ljava/util/List;
      15: aload_1
      16: invokevirtual #97                 // Method akka/cluster/pubsub/protobuf/msg/DistributedPubSubMessages$Delta$Entry$Builder.build:()Lakka/cluster/pubsub/protobuf/msg/DistributedPubSubMessages$Delta$Entry;
      19: invokeinterface #98,  2           // InterfaceMethod java/util/List.add:(Ljava/lang/Object;)Z
      24: pop
      25: aload_0
      26: invokevirtual #52                 // Method onChanged:()V
      29: goto          44
      32: aload_0
      33: getfield      #24                 // Field contentBuilder_:Lakka/protobuf/RepeatedFieldBuilder;
      36: aload_1
      37: invokevirtual #97                 // Method akka/cluster/pubsub/protobuf/msg/DistributedPubSubMessages$Delta$Entry$Builder.build:()Lakka/cluster/pubsub/protobuf/msg/DistributedPubSubMessages$Delta$Entry;
      40: invokevirtual #99                 // Method akka/protobuf/RepeatedFieldBuilder.addMessage:(Lakka/protobuf/GeneratedMessage;)Lakka/protobuf/RepeatedFieldBuilder;
      43: pop
      44: aload_0
      45: areturn

  public akka.cluster.pubsub.protobuf.msg.DistributedPubSubMessages$Delta$Bucket$Builder addContent(int, akka.cluster.pubsub.protobuf.msg.DistributedPubSubMessages$Delta$Entry$Builder);
    Code:
       0: aload_0
       1: getfield      #24                 // Field contentBuilder_:Lakka/protobuf/RepeatedFieldBuilder;
       4: ifnonnull     32
       7: aload_0
       8: invokespecial #50                 // Method ensureContentIsMutable:()V
      11: aload_0
      12: getfield      #12                 // Field content_:Ljava/util/List;
      15: iload_1
      16: aload_2
      17: invokevirtual #97                 // Method akka/cluster/pubsub/protobuf/msg/DistributedPubSubMessages$Delta$Entry$Builder.build:()Lakka/cluster/pubsub/protobuf/msg/DistributedPubSubMessages$Delta$Entry;
      20: invokeinterface #100,  3          // InterfaceMethod java/util/List.add:(ILjava/lang/Object;)V
      25: aload_0
      26: invokevirtual #52                 // Method onChanged:()V
      29: goto          45
      32: aload_0
      33: getfield      #24                 // Field contentBuilder_:Lakka/protobuf/RepeatedFieldBuilder;
      36: iload_1
      37: aload_2
      38: invokevirtual #97                 // Method akka/cluster/pubsub/protobuf/msg/DistributedPubSubMessages$Delta$Entry$Builder.build:()Lakka/cluster/pubsub/protobuf/msg/DistributedPubSubMessages$Delta$Entry;
      41: invokevirtual #101                // Method akka/protobuf/RepeatedFieldBuilder.addMessage:(ILakka/protobuf/GeneratedMessage;)Lakka/protobuf/RepeatedFieldBuilder;
      44: pop
      45: aload_0
      46: areturn

  public akka.cluster.pubsub.protobuf.msg.DistributedPubSubMessages$Delta$Bucket$Builder addAllContent(java.lang.Iterable<? extends akka.cluster.pubsub.protobuf.msg.DistributedPubSubMessages$Delta$Entry>);
    Code:
       0: aload_0
       1: getfield      #24                 // Field contentBuilder_:Lakka/protobuf/RepeatedFieldBuilder;
       4: ifnonnull     26
       7: aload_0
       8: invokespecial #50                 // Method ensureContentIsMutable:()V
      11: aload_1
      12: aload_0
      13: getfield      #12                 // Field content_:Ljava/util/List;
      16: invokestatic  #102                // Method akka/protobuf/GeneratedMessage$Builder.addAll:(Ljava/lang/Iterable;Ljava/util/Collection;)V
      19: aload_0
      20: invokevirtual #52                 // Method onChanged:()V
      23: goto          35
      26: aload_0
      27: getfield      #24                 // Field contentBuilder_:Lakka/protobuf/RepeatedFieldBuilder;
      30: aload_1
      31: invokevirtual #56                 // Method akka/protobuf/RepeatedFieldBuilder.addAllMessages:(Ljava/lang/Iterable;)Lakka/protobuf/RepeatedFieldBuilder;
      34: pop
      35: aload_0
      36: areturn

  public akka.cluster.pubsub.protobuf.msg.DistributedPubSubMessages$Delta$Bucket$Builder clearContent();
    Code:
       0: aload_0
       1: getfield      #24                 // Field contentBuilder_:Lakka/protobuf/RepeatedFieldBuilder;
       4: ifnonnull     32
       7: aload_0
       8: invokestatic  #11                 // Method java/util/Collections.emptyList:()Ljava/util/List;
      11: putfield      #12                 // Field content_:Ljava/util/List;
      14: aload_0
      15: aload_0
      16: getfield      #22                 // Field bitField0_:I
      19: bipush        -5
      21: iand
      22: putfield      #22                 // Field bitField0_:I
      25: aload_0
      26: invokevirtual #52                 // Method onChanged:()V
      29: goto          39
      32: aload_0
      33: getfield      #24                 // Field contentBuilder_:Lakka/protobuf/RepeatedFieldBuilder;
      36: invokevirtual #25                 // Method akka/protobuf/RepeatedFieldBuilder.clear:()V
      39: aload_0
      40: areturn

  public akka.cluster.pubsub.protobuf.msg.DistributedPubSubMessages$Delta$Bucket$Builder removeContent(int);
    Code:
       0: aload_0
       1: getfield      #24                 // Field contentBuilder_:Lakka/protobuf/RepeatedFieldBuilder;
       4: ifnonnull     29
       7: aload_0
       8: invokespecial #50                 // Method ensureContentIsMutable:()V
      11: aload_0
      12: getfield      #12                 // Field content_:Ljava/util/List;
      15: iload_1
      16: invokeinterface #103,  2          // InterfaceMethod java/util/List.remove:(I)Ljava/lang/Object;
      21: pop
      22: aload_0
      23: invokevirtual #52                 // Method onChanged:()V
      26: goto          37
      29: aload_0
      30: getfield      #24                 // Field contentBuilder_:Lakka/protobuf/RepeatedFieldBuilder;
      33: iload_1
      34: invokevirtual #104                // Method akka/protobuf/RepeatedFieldBuilder.remove:(I)V
      37: aload_0
      38: areturn

  public akka.cluster.pubsub.protobuf.msg.DistributedPubSubMessages$Delta$Entry$Builder getContentBuilder(int);
    Code:
       0: aload_0
       1: invokespecial #17                 // Method getContentFieldBuilder:()Lakka/protobuf/RepeatedFieldBuilder;
       4: iload_1
       5: invokevirtual #105                // Method akka/protobuf/RepeatedFieldBuilder.getBuilder:(I)Lakka/protobuf/GeneratedMessage$Builder;
       8: checkcast     #106                // class akka/cluster/pubsub/protobuf/msg/DistributedPubSubMessages$Delta$Entry$Builder
      11: areturn

  public akka.cluster.pubsub.protobuf.msg.DistributedPubSubMessages$Delta$EntryOrBuilder getContentOrBuilder(int);
    Code:
       0: aload_0
       1: getfield      #24                 // Field contentBuilder_:Lakka/protobuf/RepeatedFieldBuilder;
       4: ifnonnull     21
       7: aload_0
       8: getfield      #12                 // Field content_:Ljava/util/List;
      11: iload_1
      12: invokeinterface #92,  2           // InterfaceMethod java/util/List.get:(I)Ljava/lang/Object;
      17: checkcast     #107                // class akka/cluster/pubsub/protobuf/msg/DistributedPubSubMessages$Delta$EntryOrBuilder
      20: areturn
      21: aload_0
      22: getfield      #24                 // Field contentBuilder_:Lakka/protobuf/RepeatedFieldBuilder;
      25: iload_1
      26: invokevirtual #108                // Method akka/protobuf/RepeatedFieldBuilder.getMessageOrBuilder:(I)Lakka/protobuf/MessageOrBuilder;
      29: checkcast     #107                // class akka/cluster/pubsub/protobuf/msg/DistributedPubSubMessages$Delta$EntryOrBuilder
      32: areturn

  public java.util.List<? extends akka.cluster.pubsub.protobuf.msg.DistributedPubSubMessages$Delta$EntryOrBuilder> getContentOrBuilderList();
    Code:
       0: aload_0
       1: getfield      #24                 // Field contentBuilder_:Lakka/protobuf/RepeatedFieldBuilder;
       4: ifnull        15
       7: aload_0
       8: getfield      #24                 // Field contentBuilder_:Lakka/protobuf/RepeatedFieldBuilder;
      11: invokevirtual #109                // Method akka/protobuf/RepeatedFieldBuilder.getMessageOrBuilderList:()Ljava/util/List;
      14: areturn
      15: aload_0
      16: getfield      #12                 // Field content_:Ljava/util/List;
      19: invokestatic  #36                 // Method java/util/Collections.unmodifiableList:(Ljava/util/List;)Ljava/util/List;
      22: areturn

  public akka.cluster.pubsub.protobuf.msg.DistributedPubSubMessages$Delta$Entry$Builder addContentBuilder();
    Code:
       0: aload_0
       1: invokespecial #17                 // Method getContentFieldBuilder:()Lakka/protobuf/RepeatedFieldBuilder;
       4: invokestatic  #110                // Method akka/cluster/pubsub/protobuf/msg/DistributedPubSubMessages$Delta$Entry.getDefaultInstance:()Lakka/cluster/pubsub/protobuf/msg/DistributedPubSubMessages$Delta$Entry;
       7: invokevirtual #111                // Method akka/protobuf/RepeatedFieldBuilder.addBuilder:(Lakka/protobuf/GeneratedMessage;)Lakka/protobuf/GeneratedMessage$Builder;
      10: checkcast     #106                // class akka/cluster/pubsub/protobuf/msg/DistributedPubSubMessages$Delta$Entry$Builder
      13: areturn

  public akka.cluster.pubsub.protobuf.msg.DistributedPubSubMessages$Delta$Entry$Builder addContentBuilder(int);
    Code:
       0: aload_0
       1: invokespecial #17                 // Method getContentFieldBuilder:()Lakka/protobuf/RepeatedFieldBuilder;
       4: iload_1
       5: invokestatic  #110                // Method akka/cluster/pubsub/protobuf/msg/DistributedPubSubMessages$Delta$Entry.getDefaultInstance:()Lakka/cluster/pubsub/protobuf/msg/DistributedPubSubMessages$Delta$Entry;
       8: invokevirtual #112                // Method akka/protobuf/RepeatedFieldBuilder.addBuilder:(ILakka/protobuf/GeneratedMessage;)Lakka/protobuf/GeneratedMessage$Builder;
      11: checkcast     #106                // class akka/cluster/pubsub/protobuf/msg/DistributedPubSubMessages$Delta$Entry$Builder
      14: areturn

  public java.util.List<akka.cluster.pubsub.protobuf.msg.DistributedPubSubMessages$Delta$Entry$Builder> getContentBuilderList();
    Code:
       0: aload_0
       1: invokespecial #17                 // Method getContentFieldBuilder:()Lakka/protobuf/RepeatedFieldBuilder;
       4: invokevirtual #113                // Method akka/protobuf/RepeatedFieldBuilder.getBuilderList:()Ljava/util/List;
       7: areturn

  private akka.protobuf.RepeatedFieldBuilder<akka.cluster.pubsub.protobuf.msg.DistributedPubSubMessages$Delta$Entry, akka.cluster.pubsub.protobuf.msg.DistributedPubSubMessages$Delta$Entry$Builder, akka.cluster.pubsub.protobuf.msg.DistributedPubSubMessages$Delta$EntryOrBuilder> getContentFieldBuilder();
    Code:
       0: aload_0
       1: getfield      #24                 // Field contentBuilder_:Lakka/protobuf/RepeatedFieldBuilder;
       4: ifnonnull     50
       7: aload_0
       8: new           #114                // class akka/protobuf/RepeatedFieldBuilder
      11: dup
      12: aload_0
      13: getfield      #12                 // Field content_:Ljava/util/List;
      16: aload_0
      17: getfield      #22                 // Field bitField0_:I
      20: iconst_4
      21: iand
      22: iconst_4
      23: if_icmpne     30
      26: iconst_1
      27: goto          31
      30: iconst_0
      31: aload_0
      32: invokevirtual #84                 // Method getParentForChildren:()Lakka/protobuf/GeneratedMessage$BuilderParent;
      35: aload_0
      36: invokevirtual #85                 // Method isClean:()Z
      39: invokespecial #115                // Method akka/protobuf/RepeatedFieldBuilder."<init>":(Ljava/util/List;ZLakka/protobuf/GeneratedMessage$BuilderParent;Z)V
      42: putfield      #24                 // Field contentBuilder_:Lakka/protobuf/RepeatedFieldBuilder;
      45: aload_0
      46: aconst_null
      47: putfield      #12                 // Field content_:Ljava/util/List;
      50: aload_0
      51: getfield      #24                 // Field contentBuilder_:Lakka/protobuf/RepeatedFieldBuilder;
      54: areturn

  public akka.protobuf.GeneratedMessage$Builder clear();
    Code:
       0: aload_0
       1: invokevirtual #116                // Method clear:()Lakka/cluster/pubsub/protobuf/msg/DistributedPubSubMessages$Delta$Bucket$Builder;
       4: areturn

  public akka.protobuf.GeneratedMessage$Builder clone();
    Code:
       0: aload_0
       1: invokevirtual #117                // Method clone:()Lakka/cluster/pubsub/protobuf/msg/DistributedPubSubMessages$Delta$Bucket$Builder;
       4: areturn

  public akka.protobuf.AbstractMessage$Builder mergeFrom(akka.protobuf.CodedInputStream, akka.protobuf.ExtensionRegistryLite) throws java.io.IOException;
    Code:
       0: aload_0
       1: aload_1
       2: aload_2
       3: invokevirtual #118                // Method mergeFrom:(Lakka/protobuf/CodedInputStream;Lakka/protobuf/ExtensionRegistryLite;)Lakka/cluster/pubsub/protobuf/msg/DistributedPubSubMessages$Delta$Bucket$Builder;
       6: areturn

  public akka.protobuf.AbstractMessage$Builder mergeFrom(akka.protobuf.Message);
    Code:
       0: aload_0
       1: aload_1
       2: invokevirtual #119                // Method mergeFrom:(Lakka/protobuf/Message;)Lakka/cluster/pubsub/protobuf/msg/DistributedPubSubMessages$Delta$Bucket$Builder;
       5: areturn

  public akka.protobuf.AbstractMessage$Builder clear();
    Code:
       0: aload_0
       1: invokevirtual #116                // Method clear:()Lakka/cluster/pubsub/protobuf/msg/DistributedPubSubMessages$Delta$Bucket$Builder;
       4: areturn

  public akka.protobuf.AbstractMessage$Builder clone();
    Code:
       0: aload_0
       1: invokevirtual #117                // Method clone:()Lakka/cluster/pubsub/protobuf/msg/DistributedPubSubMessages$Delta$Bucket$Builder;
       4: areturn

  public akka.protobuf.Message$Builder mergeFrom(akka.protobuf.CodedInputStream, akka.protobuf.ExtensionRegistryLite) throws java.io.IOException;
    Code:
       0: aload_0
       1: aload_1
       2: aload_2
       3: invokevirtual #118                // Method mergeFrom:(Lakka/protobuf/CodedInputStream;Lakka/protobuf/ExtensionRegistryLite;)Lakka/cluster/pubsub/protobuf/msg/DistributedPubSubMessages$Delta$Bucket$Builder;
       6: areturn

  public akka.protobuf.Message$Builder clone();
    Code:
       0: aload_0
       1: invokevirtual #117                // Method clone:()Lakka/cluster/pubsub/protobuf/msg/DistributedPubSubMessages$Delta$Bucket$Builder;
       4: areturn

  public akka.protobuf.Message buildPartial();
    Code:
       0: aload_0
       1: invokevirtual #26                 // Method buildPartial:()Lakka/cluster/pubsub/protobuf/msg/DistributedPubSubMessages$Delta$Bucket;
       4: areturn

  public akka.protobuf.Message build();
    Code:
       0: aload_0
       1: invokevirtual #120                // Method build:()Lakka/cluster/pubsub/protobuf/msg/DistributedPubSubMessages$Delta$Bucket;
       4: areturn

  public akka.protobuf.Message$Builder mergeFrom(akka.protobuf.Message);
    Code:
       0: aload_0
       1: aload_1
       2: invokevirtual #119                // Method mergeFrom:(Lakka/protobuf/Message;)Lakka/cluster/pubsub/protobuf/msg/DistributedPubSubMessages$Delta$Bucket$Builder;
       5: areturn

  public akka.protobuf.Message$Builder clear();
    Code:
       0: aload_0
       1: invokevirtual #116                // Method clear:()Lakka/cluster/pubsub/protobuf/msg/DistributedPubSubMessages$Delta$Bucket$Builder;
       4: areturn

  public akka.protobuf.MessageLite$Builder mergeFrom(akka.protobuf.CodedInputStream, akka.protobuf.ExtensionRegistryLite) throws java.io.IOException;
    Code:
       0: aload_0
       1: aload_1
       2: aload_2
       3: invokevirtual #118                // Method mergeFrom:(Lakka/protobuf/CodedInputStream;Lakka/protobuf/ExtensionRegistryLite;)Lakka/cluster/pubsub/protobuf/msg/DistributedPubSubMessages$Delta$Bucket$Builder;
       6: areturn

  public akka.protobuf.MessageLite$Builder clone();
    Code:
       0: aload_0
       1: invokevirtual #117                // Method clone:()Lakka/cluster/pubsub/protobuf/msg/DistributedPubSubMessages$Delta$Bucket$Builder;
       4: areturn

  public akka.protobuf.MessageLite buildPartial();
    Code:
       0: aload_0
       1: invokevirtual #26                 // Method buildPartial:()Lakka/cluster/pubsub/protobuf/msg/DistributedPubSubMessages$Delta$Bucket;
       4: areturn

  public akka.protobuf.MessageLite build();
    Code:
       0: aload_0
       1: invokevirtual #120                // Method build:()Lakka/cluster/pubsub/protobuf/msg/DistributedPubSubMessages$Delta$Bucket;
       4: areturn

  public akka.protobuf.MessageLite$Builder clear();
    Code:
       0: aload_0
       1: invokevirtual #116                // Method clear:()Lakka/cluster/pubsub/protobuf/msg/DistributedPubSubMessages$Delta$Bucket$Builder;
       4: areturn

  public akka.protobuf.MessageLite getDefaultInstanceForType();
    Code:
       0: aload_0
       1: invokevirtual #121                // Method getDefaultInstanceForType:()Lakka/cluster/pubsub/protobuf/msg/DistributedPubSubMessages$Delta$Bucket;
       4: areturn

  public akka.protobuf.Message getDefaultInstanceForType();
    Code:
       0: aload_0
       1: invokevirtual #121                // Method getDefaultInstanceForType:()Lakka/cluster/pubsub/protobuf/msg/DistributedPubSubMessages$Delta$Bucket;
       4: areturn

  public akka.protobuf.AbstractMessageLite$Builder mergeFrom(akka.protobuf.CodedInputStream, akka.protobuf.ExtensionRegistryLite) throws java.io.IOException;
    Code:
       0: aload_0
       1: aload_1
       2: aload_2
       3: invokevirtual #118                // Method mergeFrom:(Lakka/protobuf/CodedInputStream;Lakka/protobuf/ExtensionRegistryLite;)Lakka/cluster/pubsub/protobuf/msg/DistributedPubSubMessages$Delta$Bucket$Builder;
       6: areturn

  public akka.protobuf.AbstractMessageLite$Builder clone();
    Code:
       0: aload_0
       1: invokevirtual #117                // Method clone:()Lakka/cluster/pubsub/protobuf/msg/DistributedPubSubMessages$Delta$Bucket$Builder;
       4: areturn

  public java.lang.Object clone() throws java.lang.CloneNotSupportedException;
    Code:
       0: aload_0
       1: invokevirtual #117                // Method clone:()Lakka/cluster/pubsub/protobuf/msg/DistributedPubSubMessages$Delta$Bucket$Builder;
       4: areturn

  static akka.cluster.pubsub.protobuf.msg.DistributedPubSubMessages$Delta$Bucket$Builder access$3800();
    Code:
       0: invokestatic  #2                  // Method create:()Lakka/cluster/pubsub/protobuf/msg/DistributedPubSubMessages$Delta$Bucket$Builder;
       3: areturn

  akka.cluster.pubsub.protobuf.msg.DistributedPubSubMessages$Delta$Bucket$Builder(akka.protobuf.GeneratedMessage$BuilderParent, akka.cluster.pubsub.protobuf.msg.DistributedPubSubMessages$1);
    Code:
       0: aload_0
       1: aload_1
       2: invokespecial #1                  // Method "<init>":(Lakka/protobuf/GeneratedMessage$BuilderParent;)V
       5: return
}
