Compiled from "SpringWebFluxEngineContext.java"
final class org.thymeleaf.spring5.context.webflux.SpringWebFluxEngineContext$SessionAttributesMap extends org.thymeleaf.spring5.context.webflux.SpringWebFluxEngineContext$NoOpMapImpl {
  private final org.thymeleaf.spring5.context.webflux.SpringWebFluxEngineContext$WebExchangeAttributesVariablesMap attrVars;

  private org.springframework.web.server.WebSession session;

  org.thymeleaf.spring5.context.webflux.SpringWebFluxEngineContext$SessionAttributesMap(org.thymeleaf.spring5.context.webflux.SpringWebFluxEngineContext$WebExchangeAttributesVariablesMap);
    Code:
       0: aload_0
       1: invokespecial #1                  // Method org/thymeleaf/spring5/context/webflux/SpringWebFluxEngineContext$NoOpMapImpl."<init>":()V
       4: aload_0
       5: aconst_null
       6: putfield      #2                  // Field session:Lorg/springframework/web/server/WebSession;
       9: aload_0
      10: aload_1
      11: putfield      #3                  // Field attrVars:Lorg/thymeleaf/spring5/context/webflux/SpringWebFluxEngineContext$WebExchangeAttributesVariablesMap;
      14: return

  private org.springframework.web.server.WebSession getSession();
    Code:
       0: aload_0
       1: getfield      #2                  // Field session:Lorg/springframework/web/server/WebSession;
       4: ifnonnull     23
       7: aload_0
       8: aload_0
       9: getfield      #3                  // Field attrVars:Lorg/thymeleaf/spring5/context/webflux/SpringWebFluxEngineContext$WebExchangeAttributesVariablesMap;
      12: ldc           #5                  // String thymeleafWebSession
      14: invokevirtual #6                  // Method org/thymeleaf/spring5/context/webflux/SpringWebFluxEngineContext$WebExchangeAttributesVariablesMap.getVariable:(Ljava/lang/String;)Ljava/lang/Object;
      17: checkcast     #7                  // class org/springframework/web/server/WebSession
      20: putfield      #2                  // Field session:Lorg/springframework/web/server/WebSession;
      23: aload_0
      24: getfield      #2                  // Field session:Lorg/springframework/web/server/WebSession;
      27: areturn

  public int size();
    Code:
       0: aload_0
       1: invokespecial #8                  // Method getSession:()Lorg/springframework/web/server/WebSession;
       4: astore_1
       5: aload_1
       6: ifnonnull     11
       9: iconst_0
      10: ireturn
      11: aload_1
      12: invokeinterface #9,  1            // InterfaceMethod org/springframework/web/server/WebSession.getAttributes:()Ljava/util/Map;
      17: invokeinterface #10,  1           // InterfaceMethod java/util/Map.size:()I
      22: ireturn

  public boolean isEmpty();
    Code:
       0: aload_0
       1: invokespecial #8                  // Method getSession:()Lorg/springframework/web/server/WebSession;
       4: astore_1
       5: aload_1
       6: ifnonnull     11
       9: iconst_1
      10: ireturn
      11: aload_1
      12: invokeinterface #9,  1            // InterfaceMethod org/springframework/web/server/WebSession.getAttributes:()Ljava/util/Map;
      17: invokeinterface #11,  1           // InterfaceMethod java/util/Map.isEmpty:()Z
      22: ireturn

  public boolean containsKey(java.lang.Object);
    Code:
       0: iconst_1
       1: ireturn

  public boolean containsValue(java.lang.Object);
    Code:
       0: new           #12                 // class java/lang/UnsupportedOperationException
       3: dup
       4: ldc           #13                 // String Map does not support #containsValue()
       6: invokespecial #14                 // Method java/lang/UnsupportedOperationException."<init>":(Ljava/lang/String;)V
       9: athrow

  public java.lang.Object get(java.lang.Object);
    Code:
       0: aload_0
       1: invokespecial #8                  // Method getSession:()Lorg/springframework/web/server/WebSession;
       4: astore_2
       5: aload_2
       6: ifnonnull     11
       9: aconst_null
      10: areturn
      11: aload_2
      12: invokeinterface #9,  1            // InterfaceMethod org/springframework/web/server/WebSession.getAttributes:()Ljava/util/Map;
      17: aload_1
      18: ifnull        28
      21: aload_1
      22: invokevirtual #15                 // Method java/lang/Object.toString:()Ljava/lang/String;
      25: goto          29
      28: aconst_null
      29: invokeinterface #16,  2           // InterfaceMethod java/util/Map.get:(Ljava/lang/Object;)Ljava/lang/Object;
      34: invokestatic  #17                 // Method org/thymeleaf/spring5/context/webflux/SpringWebFluxEngineContext.resolveLazy:(Ljava/lang/Object;)Ljava/lang/Object;
      37: areturn

  public java.util.Set<java.lang.String> keySet();
    Code:
       0: aload_0
       1: invokespecial #8                  // Method getSession:()Lorg/springframework/web/server/WebSession;
       4: astore_1
       5: aload_1
       6: ifnonnull     13
       9: invokestatic  #18                 // Method java/util/Collections.emptySet:()Ljava/util/Set;
      12: areturn
      13: aload_1
      14: invokeinterface #9,  1            // InterfaceMethod org/springframework/web/server/WebSession.getAttributes:()Ljava/util/Map;
      19: invokeinterface #19,  1           // InterfaceMethod java/util/Map.keySet:()Ljava/util/Set;
      24: areturn

  public java.util.Collection<java.lang.Object> values();
    Code:
       0: aload_0
       1: invokespecial #8                  // Method getSession:()Lorg/springframework/web/server/WebSession;
       4: astore_1
       5: aload_1
       6: ifnonnull     13
       9: invokestatic  #20                 // Method java/util/Collections.emptyList:()Ljava/util/List;
      12: areturn
      13: aload_1
      14: invokeinterface #9,  1            // InterfaceMethod org/springframework/web/server/WebSession.getAttributes:()Ljava/util/Map;
      19: invokeinterface #21,  1           // InterfaceMethod java/util/Map.values:()Ljava/util/Collection;
      24: areturn

  public java.util.Set<java.util.Map$Entry<java.lang.String, java.lang.Object>> entrySet();
    Code:
       0: aload_0
       1: invokespecial #8                  // Method getSession:()Lorg/springframework/web/server/WebSession;
       4: astore_1
       5: aload_1
       6: ifnonnull     13
       9: invokestatic  #18                 // Method java/util/Collections.emptySet:()Ljava/util/Set;
      12: areturn
      13: aload_1
      14: invokeinterface #9,  1            // InterfaceMethod org/springframework/web/server/WebSession.getAttributes:()Ljava/util/Map;
      19: invokeinterface #22,  1           // InterfaceMethod java/util/Map.entrySet:()Ljava/util/Set;
      24: areturn
}
