Compiled from "Labrat2ProxyFacetImpl.java"
public class org.sonatype.nexus.plugins.labrat2.internal.proxy.Labrat2ProxyFacetImpl extends org.sonatype.nexus.repository.proxy.ProxyFacetSupport implements org.sonatype.nexus.plugins.labrat2.internal.proxy.Labrat2ProxyFacet {
  private org.sonatype.nexus.plugins.labrat2.internal.util.Labrat2PathUtils labrat2PathUtils;

  private org.sonatype.nexus.plugins.labrat2.internal.util.Labrat2DataAccess labrat2DataAccess;

  private static int[] $SWITCH_TABLE$org$sonatype$nexus$plugins$labrat2$internal$AssetKind;

  public org.sonatype.nexus.plugins.labrat2.internal.proxy.Labrat2ProxyFacetImpl(org.sonatype.nexus.plugins.labrat2.internal.util.Labrat2PathUtils, org.sonatype.nexus.plugins.labrat2.internal.util.Labrat2DataAccess);
    Code:
       0: aload_0
       1: invokespecial #18                 // Method org/sonatype/nexus/repository/proxy/ProxyFacetSupport."<init>":()V
       4: aload_0
       5: aload_1
       6: invokestatic  #21                 // Method com/google/common/base/Preconditions.checkNotNull:(Ljava/lang/Object;)Ljava/lang/Object;
       9: checkcast     #27                 // class org/sonatype/nexus/plugins/labrat2/internal/util/Labrat2PathUtils
      12: putfield      #29                 // Field labrat2PathUtils:Lorg/sonatype/nexus/plugins/labrat2/internal/util/Labrat2PathUtils;
      15: aload_0
      16: aload_2
      17: invokestatic  #21                 // Method com/google/common/base/Preconditions.checkNotNull:(Ljava/lang/Object;)Ljava/lang/Object;
      20: checkcast     #31                 // class org/sonatype/nexus/plugins/labrat2/internal/util/Labrat2DataAccess
      23: putfield      #33                 // Field labrat2DataAccess:Lorg/sonatype/nexus/plugins/labrat2/internal/util/Labrat2DataAccess;
      26: return

  protected void doValidate(org.sonatype.nexus.repository.config.Configuration) throws java.lang.Exception;
    Code:
       0: aload_0
       1: aload_1
       2: invokespecial #44                 // Method org/sonatype/nexus/repository/proxy/ProxyFacetSupport.doValidate:(Lorg/sonatype/nexus/repository/config/Configuration;)V
       5: return

  protected org.sonatype.nexus.repository.view.Content getCachedContent(org.sonatype.nexus.repository.view.Context);
    Code:
       0: aload_1
       1: invokevirtual #51                 // Method org/sonatype/nexus/repository/view/Context.getAttributes:()Lorg/sonatype/nexus/common/collect/AttributesMap;
       4: ldc           #57                 // class org/sonatype/nexus/plugins/labrat2/internal/AssetKind
       6: invokevirtual #59                 // Method org/sonatype/nexus/common/collect/AttributesMap.require:(Ljava/lang/Class;)Ljava/lang/Object;
       9: checkcast     #57                 // class org/sonatype/nexus/plugins/labrat2/internal/AssetKind
      12: astore_2
      13: aload_0
      14: getfield      #29                 // Field labrat2PathUtils:Lorg/sonatype/nexus/plugins/labrat2/internal/util/Labrat2PathUtils;
      17: aload_1
      18: invokevirtual #65                 // Method org/sonatype/nexus/plugins/labrat2/internal/util/Labrat2PathUtils.matcherState:(Lorg/sonatype/nexus/repository/view/Context;)Lorg/sonatype/nexus/repository/view/matchers/token/TokenMatcher$State;
      21: astore_3
      22: invokestatic  #69                 // Method $SWITCH_TABLE$org$sonatype$nexus$plugins$labrat2$internal$AssetKind:()[I
      25: aload_2
      26: invokevirtual #72                 // Method org/sonatype/nexus/plugins/labrat2/internal/AssetKind.ordinal:()I
      29: iaload
      30: tableswitch   { // 1 to 2
                     1: 52
                     2: 67
               default: 82
          }
      52: aload_0
      53: aload_0
      54: getfield      #29                 // Field labrat2PathUtils:Lorg/sonatype/nexus/plugins/labrat2/internal/util/Labrat2PathUtils;
      57: aload_3
      58: ldc           #76                 // String myPackageFilename.txt
      60: invokevirtual #78                 // Method org/sonatype/nexus/plugins/labrat2/internal/util/Labrat2PathUtils.buildAssetPath:(Lorg/sonatype/nexus/repository/view/matchers/token/TokenMatcher$State;Ljava/lang/String;)Ljava/lang/String;
      63: invokevirtual #82                 // Method getAsset:(Ljava/lang/String;)Lorg/sonatype/nexus/repository/view/Content;
      66: areturn
      67: aload_0
      68: aload_0
      69: getfield      #29                 // Field labrat2PathUtils:Lorg/sonatype/nexus/plugins/labrat2/internal/util/Labrat2PathUtils;
      72: aload_3
      73: ldc           #86                 // String myAssetFilename.fil
      75: invokevirtual #78                 // Method org/sonatype/nexus/plugins/labrat2/internal/util/Labrat2PathUtils.buildAssetPath:(Lorg/sonatype/nexus/repository/view/matchers/token/TokenMatcher$State;Ljava/lang/String;)Ljava/lang/String;
      78: invokevirtual #82                 // Method getAsset:(Ljava/lang/String;)Lorg/sonatype/nexus/repository/view/Content;
      81: areturn
      82: new           #88                 // class java/lang/IllegalStateException
      85: dup
      86: new           #90                 // class java/lang/StringBuilder
      89: dup
      90: ldc           #92                 // String Received an invalid AssetKind of type:
      92: invokespecial #94                 // Method java/lang/StringBuilder."<init>":(Ljava/lang/String;)V
      95: aload_2
      96: invokevirtual #97                 // Method org/sonatype/nexus/plugins/labrat2/internal/AssetKind.name:()Ljava/lang/String;
      99: invokevirtual #101                // Method java/lang/StringBuilder.append:(Ljava/lang/String;)Ljava/lang/StringBuilder;
     102: invokevirtual #105                // Method java/lang/StringBuilder.toString:()Ljava/lang/String;
     105: invokespecial #108                // Method java/lang/IllegalStateException."<init>":(Ljava/lang/String;)V
     108: athrow

  public org.sonatype.nexus.repository.view.Content getAsset(java.lang.String);
    Code:
       0: invokestatic  #118                // Method org/sonatype/nexus/transaction/UnitOfWork.currentTx:()Lorg/sonatype/nexus/transaction/Transaction;
       3: checkcast     #124                // class org/sonatype/nexus/repository/storage/StorageTx
       6: astore_2
       7: aload_0
       8: getfield      #33                 // Field labrat2DataAccess:Lorg/sonatype/nexus/plugins/labrat2/internal/util/Labrat2DataAccess;
      11: aload_2
      12: aload_2
      13: aload_0
      14: invokevirtual #126                // Method getRepository:()Lorg/sonatype/nexus/repository/Repository;
      17: invokeinterface #130,  2          // InterfaceMethod org/sonatype/nexus/repository/storage/StorageTx.findBucket:(Lorg/sonatype/nexus/repository/Repository;)Lorg/sonatype/nexus/repository/storage/Bucket;
      22: aload_1
      23: invokevirtual #134                // Method org/sonatype/nexus/plugins/labrat2/internal/util/Labrat2DataAccess.findAsset:(Lorg/sonatype/nexus/repository/storage/StorageTx;Lorg/sonatype/nexus/repository/storage/Bucket;Ljava/lang/String;)Lorg/sonatype/nexus/repository/storage/Asset;
      26: astore_3
      27: aload_3
      28: ifnonnull     33
      31: aconst_null
      32: areturn
      33: aload_0
      34: getfield      #33                 // Field labrat2DataAccess:Lorg/sonatype/nexus/plugins/labrat2/internal/util/Labrat2DataAccess;
      37: aload_3
      38: aload_2
      39: aload_3
      40: invokevirtual #138                // Method org/sonatype/nexus/repository/storage/Asset.requireBlobRef:()Lorg/sonatype/nexus/blobstore/api/BlobRef;
      43: invokeinterface #144,  2          // InterfaceMethod org/sonatype/nexus/repository/storage/StorageTx.requireBlob:(Lorg/sonatype/nexus/blobstore/api/BlobRef;)Lorg/sonatype/nexus/blobstore/api/Blob;
      48: invokevirtual #148                // Method org/sonatype/nexus/plugins/labrat2/internal/util/Labrat2DataAccess.toContent:(Lorg/sonatype/nexus/repository/storage/Asset;Lorg/sonatype/nexus/blobstore/api/Blob;)Lorg/sonatype/nexus/repository/view/Content;
      51: areturn

  protected org.sonatype.nexus.repository.view.Content store(org.sonatype.nexus.repository.view.Context, org.sonatype.nexus.repository.view.Content) throws java.io.IOException;
    Code:
       0: aload_1
       1: invokevirtual #51                 // Method org/sonatype/nexus/repository/view/Context.getAttributes:()Lorg/sonatype/nexus/common/collect/AttributesMap;
       4: ldc           #57                 // class org/sonatype/nexus/plugins/labrat2/internal/AssetKind
       6: invokevirtual #59                 // Method org/sonatype/nexus/common/collect/AttributesMap.require:(Ljava/lang/Class;)Ljava/lang/Object;
       9: checkcast     #57                 // class org/sonatype/nexus/plugins/labrat2/internal/AssetKind
      12: astore_3
      13: aload_0
      14: getfield      #29                 // Field labrat2PathUtils:Lorg/sonatype/nexus/plugins/labrat2/internal/util/Labrat2PathUtils;
      17: aload_1
      18: invokevirtual #65                 // Method org/sonatype/nexus/plugins/labrat2/internal/util/Labrat2PathUtils.matcherState:(Lorg/sonatype/nexus/repository/view/Context;)Lorg/sonatype/nexus/repository/view/matchers/token/TokenMatcher$State;
      21: astore        4
      23: invokestatic  #69                 // Method $SWITCH_TABLE$org$sonatype$nexus$plugins$labrat2$internal$AssetKind:()[I
      26: aload_3
      27: invokevirtual #72                 // Method org/sonatype/nexus/plugins/labrat2/internal/AssetKind.ordinal:()I
      30: iaload
      31: tableswitch   { // 1 to 2
                     1: 52
                     2: 70
               default: 88
          }
      52: aload_0
      53: aload_2
      54: aload_3
      55: aload_0
      56: getfield      #29                 // Field labrat2PathUtils:Lorg/sonatype/nexus/plugins/labrat2/internal/util/Labrat2PathUtils;
      59: aload         4
      61: ldc           #76                 // String myPackageFilename.txt
      63: invokevirtual #78                 // Method org/sonatype/nexus/plugins/labrat2/internal/util/Labrat2PathUtils.buildAssetPath:(Lorg/sonatype/nexus/repository/view/matchers/token/TokenMatcher$State;Ljava/lang/String;)Ljava/lang/String;
      66: invokespecial #162                // Method putMetadata:(Lorg/sonatype/nexus/repository/view/Content;Lorg/sonatype/nexus/plugins/labrat2/internal/AssetKind;Ljava/lang/String;)Lorg/sonatype/nexus/repository/view/Content;
      69: areturn
      70: aload_0
      71: aload_2
      72: aload_3
      73: aload_0
      74: getfield      #29                 // Field labrat2PathUtils:Lorg/sonatype/nexus/plugins/labrat2/internal/util/Labrat2PathUtils;
      77: aload         4
      79: ldc           #86                 // String myAssetFilename.fil
      81: invokevirtual #78                 // Method org/sonatype/nexus/plugins/labrat2/internal/util/Labrat2PathUtils.buildAssetPath:(Lorg/sonatype/nexus/repository/view/matchers/token/TokenMatcher$State;Ljava/lang/String;)Ljava/lang/String;
      84: invokespecial #166                // Method putLabrat2Package:(Lorg/sonatype/nexus/repository/view/Content;Lorg/sonatype/nexus/plugins/labrat2/internal/AssetKind;Ljava/lang/String;)Lorg/sonatype/nexus/repository/view/Content;
      87: areturn
      88: new           #88                 // class java/lang/IllegalStateException
      91: dup
      92: new           #90                 // class java/lang/StringBuilder
      95: dup
      96: ldc           #92                 // String Received an invalid AssetKind of type:
      98: invokespecial #94                 // Method java/lang/StringBuilder."<init>":(Ljava/lang/String;)V
     101: aload_3
     102: invokevirtual #97                 // Method org/sonatype/nexus/plugins/labrat2/internal/AssetKind.name:()Ljava/lang/String;
     105: invokevirtual #101                // Method java/lang/StringBuilder.append:(Ljava/lang/String;)Ljava/lang/StringBuilder;
     108: invokevirtual #105                // Method java/lang/StringBuilder.toString:()Ljava/lang/String;
     111: invokespecial #108                // Method java/lang/IllegalStateException."<init>":(Ljava/lang/String;)V
     114: athrow

  private org.sonatype.nexus.repository.view.Content putLabrat2Package(org.sonatype.nexus.repository.view.Content, org.sonatype.nexus.plugins.labrat2.internal.AssetKind, java.lang.String) throws java.io.IOException;
    Code:
       0: aload_0
       1: ldc           #171                // class org/sonatype/nexus/repository/storage/StorageFacet
       3: invokevirtual #173                // Method facet:(Ljava/lang/Class;)Lorg/sonatype/nexus/repository/Facet;
       6: checkcast     #171                // class org/sonatype/nexus/repository/storage/StorageFacet
       9: astore        4
      11: aconst_null
      12: astore        5
      14: aconst_null
      15: astore        6
      17: aload         4
      19: aload_1
      20: invokevirtual #177                // Method org/sonatype/nexus/repository/view/Content.openInputStream:()Ljava/io/InputStream;
      23: getstatic     #183                // Field org/sonatype/nexus/plugins/labrat2/internal/util/Labrat2DataAccess.HASH_ALGORITHMS:Ljava/util/List;
      26: invokeinterface #187,  3          // InterfaceMethod org/sonatype/nexus/repository/storage/StorageFacet.createTempBlob:(Ljava/io/InputStream;Ljava/lang/Iterable;)Lorg/sonatype/nexus/repository/storage/TempBlob;
      31: astore        7
      33: aload_0
      34: aload_3
      35: invokevirtual #191                // Method findOrCreateComponent:(Ljava/lang/String;)Lorg/sonatype/nexus/repository/storage/Component;
      38: astore        8
      40: aload_0
      41: aload         7
      43: aload_1
      44: aload_2
      45: aload_3
      46: aload         8
      48: invokevirtual #195                // Method findOrCreateAsset:(Lorg/sonatype/nexus/repository/storage/TempBlob;Lorg/sonatype/nexus/repository/view/Content;Lorg/sonatype/nexus/plugins/labrat2/internal/AssetKind;Ljava/lang/String;Lorg/sonatype/nexus/repository/storage/Component;)Lorg/sonatype/nexus/repository/view/Content;
      51: aload         7
      53: ifnull        61
      56: aload         7
      58: invokevirtual #199                // Method org/sonatype/nexus/repository/storage/TempBlob.close:()V
      61: areturn
      62: astore        5
      64: aload         7
      66: ifnull        74
      69: aload         7
      71: invokevirtual #199                // Method org/sonatype/nexus/repository/storage/TempBlob.close:()V
      74: aload         5
      76: athrow
      77: astore        6
      79: aload         5
      81: ifnonnull     91
      84: aload         6
      86: astore        5
      88: goto          105
      91: aload         5
      93: aload         6
      95: if_acmpeq     105
      98: aload         5
     100: aload         6
     102: invokevirtual #204                // Method java/lang/Throwable.addSuppressed:(Ljava/lang/Throwable;)V
     105: aload         5
     107: athrow
    Exception table:
       from    to  target type
          33    51    62   any
          17    61    77   any
          62    77    77   any

  protected org.sonatype.nexus.repository.storage.Component findOrCreateComponent(java.lang.String);
    Code:
       0: invokestatic  #118                // Method org/sonatype/nexus/transaction/UnitOfWork.currentTx:()Lorg/sonatype/nexus/transaction/Transaction;
       3: checkcast     #124                // class org/sonatype/nexus/repository/storage/StorageTx
       6: astore_2
       7: aload_2
       8: aload_0
       9: invokevirtual #126                // Method getRepository:()Lorg/sonatype/nexus/repository/Repository;
      12: invokeinterface #130,  2          // InterfaceMethod org/sonatype/nexus/repository/storage/StorageTx.findBucket:(Lorg/sonatype/nexus/repository/Repository;)Lorg/sonatype/nexus/repository/storage/Bucket;
      17: astore_3
      18: aload_0
      19: getfield      #33                 // Field labrat2DataAccess:Lorg/sonatype/nexus/plugins/labrat2/internal/util/Labrat2DataAccess;
      22: aload_2
      23: aload_0
      24: invokevirtual #126                // Method getRepository:()Lorg/sonatype/nexus/repository/Repository;
      27: aload_1
      28: invokevirtual #221                // Method org/sonatype/nexus/plugins/labrat2/internal/util/Labrat2DataAccess.findComponent:(Lorg/sonatype/nexus/repository/storage/StorageTx;Lorg/sonatype/nexus/repository/Repository;Ljava/lang/String;)Lorg/sonatype/nexus/repository/storage/Component;
      31: astore        4
      33: aload         4
      35: ifnonnull     65
      38: aload_2
      39: aload_3
      40: aload_0
      41: invokevirtual #126                // Method getRepository:()Lorg/sonatype/nexus/repository/Repository;
      44: invokeinterface #225,  1          // InterfaceMethod org/sonatype/nexus/repository/Repository.getFormat:()Lorg/sonatype/nexus/repository/Format;
      49: invokeinterface #231,  3          // InterfaceMethod org/sonatype/nexus/repository/storage/StorageTx.createComponent:(Lorg/sonatype/nexus/repository/storage/Bucket;Lorg/sonatype/nexus/repository/Format;)Lorg/sonatype/nexus/repository/storage/Component;
      54: aload_1
      55: invokeinterface #235,  2          // InterfaceMethod org/sonatype/nexus/repository/storage/Component.name:(Ljava/lang/String;)Ljava/lang/Object;
      60: checkcast     #218                // class org/sonatype/nexus/repository/storage/Component
      63: astore        4
      65: aload_2
      66: aload         4
      68: invokeinterface #238,  2          // InterfaceMethod org/sonatype/nexus/repository/storage/StorageTx.saveComponent:(Lorg/sonatype/nexus/repository/storage/Component;)V
      73: aload         4
      75: areturn

  private org.sonatype.nexus.repository.view.Content putMetadata(org.sonatype.nexus.repository.view.Content, org.sonatype.nexus.plugins.labrat2.internal.AssetKind, java.lang.String) throws java.io.IOException;
    Code:
       0: aload_0
       1: ldc           #171                // class org/sonatype/nexus/repository/storage/StorageFacet
       3: invokevirtual #173                // Method facet:(Ljava/lang/Class;)Lorg/sonatype/nexus/repository/Facet;
       6: checkcast     #171                // class org/sonatype/nexus/repository/storage/StorageFacet
       9: astore        4
      11: aconst_null
      12: astore        5
      14: aconst_null
      15: astore        6
      17: aload         4
      19: aload_1
      20: invokevirtual #177                // Method org/sonatype/nexus/repository/view/Content.openInputStream:()Ljava/io/InputStream;
      23: getstatic     #183                // Field org/sonatype/nexus/plugins/labrat2/internal/util/Labrat2DataAccess.HASH_ALGORITHMS:Ljava/util/List;
      26: invokeinterface #187,  3          // InterfaceMethod org/sonatype/nexus/repository/storage/StorageFacet.createTempBlob:(Ljava/io/InputStream;Ljava/lang/Iterable;)Lorg/sonatype/nexus/repository/storage/TempBlob;
      31: astore        7
      33: aload_0
      34: aload         7
      36: aload_1
      37: aload_2
      38: aload_3
      39: aconst_null
      40: invokevirtual #195                // Method findOrCreateAsset:(Lorg/sonatype/nexus/repository/storage/TempBlob;Lorg/sonatype/nexus/repository/view/Content;Lorg/sonatype/nexus/plugins/labrat2/internal/AssetKind;Ljava/lang/String;Lorg/sonatype/nexus/repository/storage/Component;)Lorg/sonatype/nexus/repository/view/Content;
      43: aload         7
      45: ifnull        53
      48: aload         7
      50: invokevirtual #199                // Method org/sonatype/nexus/repository/storage/TempBlob.close:()V
      53: areturn
      54: astore        5
      56: aload         7
      58: ifnull        66
      61: aload         7
      63: invokevirtual #199                // Method org/sonatype/nexus/repository/storage/TempBlob.close:()V
      66: aload         5
      68: athrow
      69: astore        6
      71: aload         5
      73: ifnonnull     83
      76: aload         6
      78: astore        5
      80: goto          97
      83: aload         5
      85: aload         6
      87: if_acmpeq     97
      90: aload         5
      92: aload         6
      94: invokevirtual #204                // Method java/lang/Throwable.addSuppressed:(Ljava/lang/Throwable;)V
      97: aload         5
      99: athrow
    Exception table:
       from    to  target type
          33    43    54   any
          17    53    69   any
          54    69    69   any

  protected org.sonatype.nexus.repository.view.Content findOrCreateAsset(org.sonatype.nexus.repository.storage.TempBlob, org.sonatype.nexus.repository.view.Content, org.sonatype.nexus.plugins.labrat2.internal.AssetKind, java.lang.String, org.sonatype.nexus.repository.storage.Component) throws java.io.IOException;
    Code:
       0: invokestatic  #118                // Method org/sonatype/nexus/transaction/UnitOfWork.currentTx:()Lorg/sonatype/nexus/transaction/Transaction;
       3: checkcast     #124                // class org/sonatype/nexus/repository/storage/StorageTx
       6: astore        6
       8: aload         6
      10: aload_0
      11: invokevirtual #126                // Method getRepository:()Lorg/sonatype/nexus/repository/Repository;
      14: invokeinterface #130,  2          // InterfaceMethod org/sonatype/nexus/repository/storage/StorageTx.findBucket:(Lorg/sonatype/nexus/repository/Repository;)Lorg/sonatype/nexus/repository/storage/Bucket;
      19: astore        7
      21: aload_0
      22: getfield      #33                 // Field labrat2DataAccess:Lorg/sonatype/nexus/plugins/labrat2/internal/util/Labrat2DataAccess;
      25: aload         6
      27: aload         7
      29: aload         4
      31: invokevirtual #134                // Method org/sonatype/nexus/plugins/labrat2/internal/util/Labrat2DataAccess.findAsset:(Lorg/sonatype/nexus/repository/storage/StorageTx;Lorg/sonatype/nexus/repository/storage/Bucket;Ljava/lang/String;)Lorg/sonatype/nexus/repository/storage/Asset;
      34: astore        8
      36: aload_3
      37: getstatic     #246                // Field org/sonatype/nexus/plugins/labrat2/internal/AssetKind.ARCHIVE:Lorg/sonatype/nexus/plugins/labrat2/internal/AssetKind;
      40: invokevirtual #249                // Method org/sonatype/nexus/plugins/labrat2/internal/AssetKind.equals:(Ljava/lang/Object;)Z
      43: ifeq          91
      46: aload         8
      48: ifnonnull     140
      51: aload         6
      53: aload         7
      55: aload         5
      57: invokeinterface #253,  3          // InterfaceMethod org/sonatype/nexus/repository/storage/StorageTx.createAsset:(Lorg/sonatype/nexus/repository/storage/Bucket;Lorg/sonatype/nexus/repository/storage/Component;)Lorg/sonatype/nexus/repository/storage/Asset;
      62: astore        8
      64: aload         8
      66: aload         4
      68: invokevirtual #257                // Method org/sonatype/nexus/repository/storage/Asset.name:(Ljava/lang/String;)Ljava/lang/Object;
      71: pop
      72: aload         8
      74: invokevirtual #258                // Method org/sonatype/nexus/repository/storage/Asset.formatAttributes:()Lorg/sonatype/nexus/common/collect/NestedAttributesMap;
      77: ldc_w         #262                // String asset_kind
      80: aload_3
      81: invokevirtual #97                 // Method org/sonatype/nexus/plugins/labrat2/internal/AssetKind.name:()Ljava/lang/String;
      84: invokevirtual #264                // Method org/sonatype/nexus/common/collect/NestedAttributesMap.set:(Ljava/lang/String;Ljava/lang/Object;)Ljava/lang/Object;
      87: pop
      88: goto          140
      91: aload         8
      93: ifnonnull     140
      96: aload         6
      98: aload         7
     100: aload_0
     101: invokevirtual #126                // Method getRepository:()Lorg/sonatype/nexus/repository/Repository;
     104: invokeinterface #225,  1          // InterfaceMethod org/sonatype/nexus/repository/Repository.getFormat:()Lorg/sonatype/nexus/repository/Format;
     109: invokeinterface #270,  3          // InterfaceMethod org/sonatype/nexus/repository/storage/StorageTx.createAsset:(Lorg/sonatype/nexus/repository/storage/Bucket;Lorg/sonatype/nexus/repository/Format;)Lorg/sonatype/nexus/repository/storage/Asset;
     114: astore        8
     116: aload         8
     118: aload         4
     120: invokevirtual #257                // Method org/sonatype/nexus/repository/storage/Asset.name:(Ljava/lang/String;)Ljava/lang/Object;
     123: pop
     124: aload         8
     126: invokevirtual #258                // Method org/sonatype/nexus/repository/storage/Asset.formatAttributes:()Lorg/sonatype/nexus/common/collect/NestedAttributesMap;
     129: ldc_w         #262                // String asset_kind
     132: aload_3
     133: invokevirtual #97                 // Method org/sonatype/nexus/plugins/labrat2/internal/AssetKind.name:()Ljava/lang/String;
     136: invokevirtual #264                // Method org/sonatype/nexus/common/collect/NestedAttributesMap.set:(Ljava/lang/String;Ljava/lang/Object;)Ljava/lang/Object;
     139: pop
     140: aload_0
     141: getfield      #33                 // Field labrat2DataAccess:Lorg/sonatype/nexus/plugins/labrat2/internal/util/Labrat2DataAccess;
     144: aload         6
     146: aload         8
     148: aload_1
     149: aload_2
     150: invokevirtual #273                // Method org/sonatype/nexus/plugins/labrat2/internal/util/Labrat2DataAccess.saveAsset:(Lorg/sonatype/nexus/repository/storage/StorageTx;Lorg/sonatype/nexus/repository/storage/Asset;Lcom/google/common/base/Supplier;Lorg/sonatype/nexus/repository/view/Payload;)Lorg/sonatype/nexus/repository/view/Content;
     153: areturn

  protected void indicateVerified(org.sonatype.nexus.repository.view.Context, org.sonatype.nexus.repository.view.Content, org.sonatype.nexus.repository.cache.CacheInfo) throws java.io.IOException;
    Code:
       0: aload_0
       1: aload_2
       2: aload_3
       3: invokevirtual #279                // Method setCacheInfo:(Lorg/sonatype/nexus/repository/view/Content;Lorg/sonatype/nexus/repository/cache/CacheInfo;)V
       6: return

  public void setCacheInfo(org.sonatype.nexus.repository.view.Content, org.sonatype.nexus.repository.cache.CacheInfo) throws java.io.IOException;
    Code:
       0: invokestatic  #118                // Method org/sonatype/nexus/transaction/UnitOfWork.currentTx:()Lorg/sonatype/nexus/transaction/Transaction;
       3: checkcast     #124                // class org/sonatype/nexus/repository/storage/StorageTx
       6: astore_3
       7: aload_3
       8: aload_3
       9: aload_0
      10: invokevirtual #126                // Method getRepository:()Lorg/sonatype/nexus/repository/Repository;
      13: invokeinterface #130,  2          // InterfaceMethod org/sonatype/nexus/repository/storage/StorageTx.findBucket:(Lorg/sonatype/nexus/repository/Repository;)Lorg/sonatype/nexus/repository/storage/Bucket;
      18: aload_1
      19: invokestatic  #286                // Method org/sonatype/nexus/repository/view/Content.findAsset:(Lorg/sonatype/nexus/repository/storage/StorageTx;Lorg/sonatype/nexus/repository/storage/Bucket;Lorg/sonatype/nexus/repository/view/Content;)Lorg/sonatype/nexus/repository/storage/Asset;
      22: astore        4
      24: aload         4
      26: ifnonnull     51
      29: aload_0
      30: getfield      #289                // Field log:Lorg/slf4j/Logger;
      33: ldc_w         #293                // String Attempting to set cache info for non-existent Labrat2 asset {}
      36: aload_1
      37: invokevirtual #295                // Method org/sonatype/nexus/repository/view/Content.getAttributes:()Lorg/sonatype/nexus/common/collect/AttributesMap;
      40: ldc           #139                // class org/sonatype/nexus/repository/storage/Asset
      42: invokevirtual #59                 // Method org/sonatype/nexus/common/collect/AttributesMap.require:(Ljava/lang/Class;)Ljava/lang/Object;
      45: invokeinterface #296,  3          // InterfaceMethod org/slf4j/Logger.debug:(Ljava/lang/String;Ljava/lang/Object;)V
      50: return
      51: aload_0
      52: getfield      #289                // Field log:Lorg/slf4j/Logger;
      55: ldc_w         #302                // String Updating cacheInfo of {} to {}
      58: aload         4
      60: aload_2
      61: invokeinterface #304,  4          // InterfaceMethod org/slf4j/Logger.debug:(Ljava/lang/String;Ljava/lang/Object;Ljava/lang/Object;)V
      66: aload         4
      68: aload_2
      69: invokestatic  #307                // Method org/sonatype/nexus/repository/cache/CacheInfo.applyToAsset:(Lorg/sonatype/nexus/repository/storage/Asset;Lorg/sonatype/nexus/repository/cache/CacheInfo;)V
      72: aload_3
      73: aload         4
      75: invokeinterface #313,  2          // InterfaceMethod org/sonatype/nexus/repository/storage/StorageTx.saveAsset:(Lorg/sonatype/nexus/repository/storage/Asset;)V
      80: return

  protected java.lang.String getUrl(org.sonatype.nexus.repository.view.Context);
    Code:
       0: aload_1
       1: invokevirtual #320                // Method org/sonatype/nexus/repository/view/Context.getRequest:()Lorg/sonatype/nexus/repository/view/Request;
       4: invokevirtual #324                // Method org/sonatype/nexus/repository/view/Request.getPath:()Ljava/lang/String;
       7: iconst_1
       8: invokevirtual #329                // Method java/lang/String.substring:(I)Ljava/lang/String;
      11: areturn

  static int[] $SWITCH_TABLE$org$sonatype$nexus$plugins$labrat2$internal$AssetKind();
    Code:
       0: getstatic     #333                // Field $SWITCH_TABLE$org$sonatype$nexus$plugins$labrat2$internal$AssetKind:[I
       3: dup
       4: ifnull        8
       7: areturn
       8: pop
       9: invokestatic  #335                // Method org/sonatype/nexus/plugins/labrat2/internal/AssetKind.values:()[Lorg/sonatype/nexus/plugins/labrat2/internal/AssetKind;
      12: arraylength
      13: newarray       int
      15: astore_0
      16: aload_0
      17: getstatic     #246                // Field org/sonatype/nexus/plugins/labrat2/internal/AssetKind.ARCHIVE:Lorg/sonatype/nexus/plugins/labrat2/internal/AssetKind;
      20: invokevirtual #72                 // Method org/sonatype/nexus/plugins/labrat2/internal/AssetKind.ordinal:()I
      23: iconst_2
      24: iastore
      25: goto          29
      28: pop
      29: aload_0
      30: getstatic     #339                // Field org/sonatype/nexus/plugins/labrat2/internal/AssetKind.PACKAGES:Lorg/sonatype/nexus/plugins/labrat2/internal/AssetKind;
      33: invokevirtual #72                 // Method org/sonatype/nexus/plugins/labrat2/internal/AssetKind.ordinal:()I
      36: iconst_1
      37: iastore
      38: goto          42
      41: pop
      42: aload_0
      43: dup
      44: putstatic     #333                // Field $SWITCH_TABLE$org$sonatype$nexus$plugins$labrat2$internal$AssetKind:[I
      47: areturn
    Exception table:
       from    to  target type
          16    25    28   Class java/lang/NoSuchFieldError
          29    38    41   Class java/lang/NoSuchFieldError
}
