Compiled from "ChunkedInput.java"
abstract class org.glassfish.jersey.client.ChunkedInput$AbstractBoundaryParser implements org.glassfish.jersey.client.ChunkParser {
  private org.glassfish.jersey.client.ChunkedInput$AbstractBoundaryParser();
    Code:
       0: aload_0
       1: invokespecial #2                  // Method java/lang/Object."<init>":()V
       4: return

  public byte[] readChunk(java.io.InputStream) throws java.io.IOException;
    Code:
       0: new           #3                  // class java/io/ByteArrayOutputStream
       3: dup
       4: invokespecial #4                  // Method java/io/ByteArrayOutputStream."<init>":()V
       7: astore_2
       8: aload_0
       9: invokevirtual #5                  // Method getDelimiterBufferSize:()I
      12: newarray       byte
      14: astore_3
      15: iconst_0
      16: istore        5
      18: aload_1
      19: invokevirtual #6                  // Method java/io/InputStream.read:()I
      22: dup
      23: istore        4
      25: iconst_m1
      26: if_icmpeq     178
      29: iload         4
      31: i2b
      32: istore        6
      34: aload_0
      35: iload         6
      37: iload         5
      39: aload_3
      40: invokevirtual #7                  // Method getDelimiter:(BI[B)[B
      43: astore        7
      45: aload         7
      47: ifnull        80
      50: iload         6
      52: aload         7
      54: iload         5
      56: baload
      57: if_icmpne     80
      60: aload_3
      61: iload         5
      63: iinc          5, 1
      66: iload         6
      68: bastore
      69: iload         5
      71: aload         7
      73: arraylength
      74: if_icmpne     175
      77: goto          178
      80: iload         5
      82: ifle          169
      85: aload_0
      86: iload         5
      88: iconst_1
      89: isub
      90: aload_3
      91: invokevirtual #8                  // Method getDelimiter:(I[B)[B
      94: astore        7
      96: aload_3
      97: iload         5
      99: iload         6
     101: bastore
     102: aload_3
     103: iconst_1
     104: iload         5
     106: aload         7
     108: invokestatic  #9                  // Method matchTail:([BII[B)I
     111: istore        8
     113: iload         8
     115: ifne          138
     118: aload_2
     119: aload_3
     120: iconst_0
     121: iload         5
     123: invokevirtual #10                 // Method java/io/ByteArrayOutputStream.write:([BII)V
     126: aload_2
     127: iload         6
     129: invokevirtual #11                 // Method java/io/ByteArrayOutputStream.write:(I)V
     132: iconst_0
     133: istore        5
     135: goto          166
     138: iload         8
     140: aload         7
     142: arraylength
     143: if_icmpne     149
     146: goto          178
     149: aload_2
     150: aload_3
     151: iconst_0
     152: iload         5
     154: iconst_1
     155: iadd
     156: iload         8
     158: isub
     159: invokevirtual #10                 // Method java/io/ByteArrayOutputStream.write:([BII)V
     162: iload         8
     164: istore        5
     166: goto          175
     169: aload_2
     170: iload         6
     172: invokevirtual #11                 // Method java/io/ByteArrayOutputStream.write:(I)V
     175: goto          18
     178: iload         4
     180: iconst_m1
     181: if_icmpeq     191
     184: aload_2
     185: invokevirtual #12                 // Method java/io/ByteArrayOutputStream.size:()I
     188: ifeq          15
     191: iload         5
     193: ifle          219
     196: iload         5
     198: aload_0
     199: iload         5
     201: iconst_1
     202: isub
     203: aload_3
     204: invokevirtual #8                  // Method getDelimiter:(I[B)[B
     207: arraylength
     208: if_icmpeq     219
     211: aload_2
     212: aload_3
     213: iconst_0
     214: iload         5
     216: invokevirtual #10                 // Method java/io/ByteArrayOutputStream.write:([BII)V
     219: aload_2
     220: invokevirtual #12                 // Method java/io/ByteArrayOutputStream.size:()I
     223: ifle          233
     226: aload_2
     227: invokevirtual #13                 // Method java/io/ByteArrayOutputStream.toByteArray:()[B
     230: goto          234
     233: aconst_null
     234: areturn

  abstract byte[] getDelimiter(byte, int, byte[]);

  abstract byte[] getDelimiter(int, byte[]);

  abstract int getDelimiterBufferSize();

  private static int matchTail(byte[], int, int, byte[]);
    Code:
       0: aload_3
       1: ifnonnull     6
       4: iconst_0
       5: ireturn
       6: iconst_0
       7: istore        4
       9: iload         4
      11: iload_2
      12: if_icmpge     65
      15: iload_2
      16: iload         4
      18: isub
      19: istore        5
      21: iconst_0
      22: istore        6
      24: iload         6
      26: iload         5
      28: if_icmpge     56
      31: aload_0
      32: iload_1
      33: iload         4
      35: iadd
      36: iload         6
      38: iadd
      39: baload
      40: aload_3
      41: iload         6
      43: baload
      44: if_icmpeq     50
      47: goto          59
      50: iinc          6, 1
      53: goto          24
      56: iload         5
      58: ireturn
      59: iinc          4, 1
      62: goto          9
      65: iconst_0
      66: ireturn

  org.glassfish.jersey.client.ChunkedInput$AbstractBoundaryParser(org.glassfish.jersey.client.ChunkedInput$1);
    Code:
       0: aload_0
       1: invokespecial #1                  // Method "<init>":()V
       4: return
}
