Compiled from "ClientConfig.java"
class org.glassfish.jersey.client.ClientConfig$State implements javax.ws.rs.core.Configurable<org.glassfish.jersey.client.ClientConfig$State>, org.glassfish.jersey.ExtendedConfig {
  private static final org.glassfish.jersey.client.ClientConfig$State$StateChangeStrategy IDENTITY;

  private static final org.glassfish.jersey.client.ClientConfig$State$StateChangeStrategy COPY_ON_CHANGE;

  private volatile org.glassfish.jersey.client.ClientConfig$State$StateChangeStrategy strategy;

  private final org.glassfish.jersey.model.internal.CommonConfig commonConfig;

  private final org.glassfish.jersey.client.JerseyClient client;

  private volatile org.glassfish.jersey.client.spi.ConnectorProvider connectorProvider;

  private volatile java.util.concurrent.ExecutorService executorService;

  private volatile java.util.concurrent.ScheduledExecutorService scheduledExecutorService;

  private final org.glassfish.jersey.internal.util.collection.LazyValue<org.glassfish.jersey.client.ClientRuntime> runtime;

  org.glassfish.jersey.client.ClientConfig$State(org.glassfish.jersey.client.JerseyClient);
    Code:
       0: aload_0
       1: invokespecial #2                  // Method java/lang/Object."<init>":()V
       4: aload_0
       5: aload_0
       6: invokedynamic #3,  0              // InvokeDynamic #0:get:(Lorg/glassfish/jersey/client/ClientConfig$State;)Lorg/glassfish/jersey/internal/util/collection/Value;
      11: invokestatic  #4                  // Method org/glassfish/jersey/internal/util/collection/Values.lazy:(Lorg/glassfish/jersey/internal/util/collection/Value;)Lorg/glassfish/jersey/internal/util/collection/LazyValue;
      14: putfield      #1                  // Field runtime:Lorg/glassfish/jersey/internal/util/collection/LazyValue;
      17: aload_0
      18: getstatic     #5                  // Field IDENTITY:Lorg/glassfish/jersey/client/ClientConfig$State$StateChangeStrategy;
      21: putfield      #6                  // Field strategy:Lorg/glassfish/jersey/client/ClientConfig$State$StateChangeStrategy;
      24: aload_0
      25: new           #7                  // class org/glassfish/jersey/model/internal/CommonConfig
      28: dup
      29: getstatic     #8                  // Field javax/ws/rs/RuntimeType.CLIENT:Ljavax/ws/rs/RuntimeType;
      32: getstatic     #9                  // Field org/glassfish/jersey/model/internal/ComponentBag.EXCLUDE_EMPTY:Ljava/util/function/Predicate;
      35: invokespecial #10                 // Method org/glassfish/jersey/model/internal/CommonConfig."<init>":(Ljavax/ws/rs/RuntimeType;Ljava/util/function/Predicate;)V
      38: putfield      #11                 // Field commonConfig:Lorg/glassfish/jersey/model/internal/CommonConfig;
      41: aload_0
      42: aload_1
      43: putfield      #12                 // Field client:Lorg/glassfish/jersey/client/JerseyClient;
      46: ldc           #13                 // class org/glassfish/jersey/client/spi/ConnectorProvider
      48: invokestatic  #14                 // Method org/glassfish/jersey/internal/ServiceFinder.find:(Ljava/lang/Class;)Lorg/glassfish/jersey/internal/ServiceFinder;
      51: invokevirtual #15                 // Method org/glassfish/jersey/internal/ServiceFinder.iterator:()Ljava/util/Iterator;
      54: astore_2
      55: aload_2
      56: invokeinterface #16,  1           // InterfaceMethod java/util/Iterator.hasNext:()Z
      61: ifeq          80
      64: aload_0
      65: aload_2
      66: invokeinterface #17,  1           // InterfaceMethod java/util/Iterator.next:()Ljava/lang/Object;
      71: checkcast     #13                 // class org/glassfish/jersey/client/spi/ConnectorProvider
      74: putfield      #18                 // Field connectorProvider:Lorg/glassfish/jersey/client/spi/ConnectorProvider;
      77: goto          91
      80: aload_0
      81: new           #19                 // class org/glassfish/jersey/client/HttpUrlConnectorProvider
      84: dup
      85: invokespecial #20                 // Method org/glassfish/jersey/client/HttpUrlConnectorProvider."<init>":()V
      88: putfield      #18                 // Field connectorProvider:Lorg/glassfish/jersey/client/spi/ConnectorProvider;
      91: return

  private org.glassfish.jersey.client.ClientConfig$State(org.glassfish.jersey.client.JerseyClient, org.glassfish.jersey.client.ClientConfig$State);
    Code:
       0: aload_0
       1: invokespecial #2                  // Method java/lang/Object."<init>":()V
       4: aload_0
       5: aload_0
       6: invokedynamic #3,  0              // InvokeDynamic #0:get:(Lorg/glassfish/jersey/client/ClientConfig$State;)Lorg/glassfish/jersey/internal/util/collection/Value;
      11: invokestatic  #4                  // Method org/glassfish/jersey/internal/util/collection/Values.lazy:(Lorg/glassfish/jersey/internal/util/collection/Value;)Lorg/glassfish/jersey/internal/util/collection/LazyValue;
      14: putfield      #1                  // Field runtime:Lorg/glassfish/jersey/internal/util/collection/LazyValue;
      17: aload_0
      18: getstatic     #5                  // Field IDENTITY:Lorg/glassfish/jersey/client/ClientConfig$State$StateChangeStrategy;
      21: putfield      #6                  // Field strategy:Lorg/glassfish/jersey/client/ClientConfig$State$StateChangeStrategy;
      24: aload_0
      25: aload_1
      26: putfield      #12                 // Field client:Lorg/glassfish/jersey/client/JerseyClient;
      29: aload_0
      30: new           #7                  // class org/glassfish/jersey/model/internal/CommonConfig
      33: dup
      34: aload_2
      35: getfield      #11                 // Field commonConfig:Lorg/glassfish/jersey/model/internal/CommonConfig;
      38: invokespecial #21                 // Method org/glassfish/jersey/model/internal/CommonConfig."<init>":(Lorg/glassfish/jersey/model/internal/CommonConfig;)V
      41: putfield      #11                 // Field commonConfig:Lorg/glassfish/jersey/model/internal/CommonConfig;
      44: aload_0
      45: aload_2
      46: getfield      #18                 // Field connectorProvider:Lorg/glassfish/jersey/client/spi/ConnectorProvider;
      49: putfield      #18                 // Field connectorProvider:Lorg/glassfish/jersey/client/spi/ConnectorProvider;
      52: aload_0
      53: aload_2
      54: getfield      #22                 // Field executorService:Ljava/util/concurrent/ExecutorService;
      57: putfield      #22                 // Field executorService:Ljava/util/concurrent/ExecutorService;
      60: aload_0
      61: aload_2
      62: getfield      #23                 // Field scheduledExecutorService:Ljava/util/concurrent/ScheduledExecutorService;
      65: putfield      #23                 // Field scheduledExecutorService:Ljava/util/concurrent/ScheduledExecutorService;
      68: return

  org.glassfish.jersey.client.ClientConfig$State copy();
    Code:
       0: new           #24                 // class org/glassfish/jersey/client/ClientConfig$State
       3: dup
       4: aload_0
       5: getfield      #12                 // Field client:Lorg/glassfish/jersey/client/JerseyClient;
       8: aload_0
       9: invokespecial #25                 // Method "<init>":(Lorg/glassfish/jersey/client/JerseyClient;Lorg/glassfish/jersey/client/ClientConfig$State;)V
      12: areturn

  org.glassfish.jersey.client.ClientConfig$State copy(org.glassfish.jersey.client.JerseyClient);
    Code:
       0: new           #24                 // class org/glassfish/jersey/client/ClientConfig$State
       3: dup
       4: aload_1
       5: aload_0
       6: invokespecial #25                 // Method "<init>":(Lorg/glassfish/jersey/client/JerseyClient;Lorg/glassfish/jersey/client/ClientConfig$State;)V
       9: areturn

  void markAsShared();
    Code:
       0: aload_0
       1: getstatic     #26                 // Field COPY_ON_CHANGE:Lorg/glassfish/jersey/client/ClientConfig$State$StateChangeStrategy;
       4: putfield      #6                  // Field strategy:Lorg/glassfish/jersey/client/ClientConfig$State$StateChangeStrategy;
       7: return

  org.glassfish.jersey.client.ClientConfig$State preInitialize();
    Code:
       0: aload_0
       1: getfield      #6                  // Field strategy:Lorg/glassfish/jersey/client/ClientConfig$State$StateChangeStrategy;
       4: aload_0
       5: invokeinterface #27,  2           // InterfaceMethod org/glassfish/jersey/client/ClientConfig$State$StateChangeStrategy.onChange:(Lorg/glassfish/jersey/client/ClientConfig$State;)Lorg/glassfish/jersey/client/ClientConfig$State;
      10: astore_1
      11: aload_1
      12: getstatic     #26                 // Field COPY_ON_CHANGE:Lorg/glassfish/jersey/client/ClientConfig$State$StateChangeStrategy;
      15: putfield      #6                  // Field strategy:Lorg/glassfish/jersey/client/ClientConfig$State$StateChangeStrategy;
      18: aload_1
      19: getfield      #1                  // Field runtime:Lorg/glassfish/jersey/internal/util/collection/LazyValue;
      22: invokeinterface #28,  1           // InterfaceMethod org/glassfish/jersey/internal/util/collection/LazyValue.get:()Ljava/lang/Object;
      27: checkcast     #29                 // class org/glassfish/jersey/client/ClientRuntime
      30: invokevirtual #30                 // Method org/glassfish/jersey/client/ClientRuntime.preInitialize:()V
      33: aload_1
      34: areturn

  public org.glassfish.jersey.client.ClientConfig$State property(java.lang.String, java.lang.Object);
    Code:
       0: aload_0
       1: getfield      #6                  // Field strategy:Lorg/glassfish/jersey/client/ClientConfig$State$StateChangeStrategy;
       4: aload_0
       5: invokeinterface #27,  2           // InterfaceMethod org/glassfish/jersey/client/ClientConfig$State$StateChangeStrategy.onChange:(Lorg/glassfish/jersey/client/ClientConfig$State;)Lorg/glassfish/jersey/client/ClientConfig$State;
      10: astore_3
      11: aload_3
      12: getfield      #11                 // Field commonConfig:Lorg/glassfish/jersey/model/internal/CommonConfig;
      15: aload_1
      16: aload_2
      17: invokevirtual #31                 // Method org/glassfish/jersey/model/internal/CommonConfig.property:(Ljava/lang/String;Ljava/lang/Object;)Lorg/glassfish/jersey/model/internal/CommonConfig;
      20: pop
      21: aload_3
      22: areturn

  public org.glassfish.jersey.client.ClientConfig$State loadFrom(javax.ws.rs.core.Configuration);
    Code:
       0: aload_0
       1: getfield      #6                  // Field strategy:Lorg/glassfish/jersey/client/ClientConfig$State$StateChangeStrategy;
       4: aload_0
       5: invokeinterface #27,  2           // InterfaceMethod org/glassfish/jersey/client/ClientConfig$State$StateChangeStrategy.onChange:(Lorg/glassfish/jersey/client/ClientConfig$State;)Lorg/glassfish/jersey/client/ClientConfig$State;
      10: astore_2
      11: aload_2
      12: getfield      #11                 // Field commonConfig:Lorg/glassfish/jersey/model/internal/CommonConfig;
      15: aload_1
      16: invokevirtual #32                 // Method org/glassfish/jersey/model/internal/CommonConfig.loadFrom:(Ljavax/ws/rs/core/Configuration;)Lorg/glassfish/jersey/model/internal/CommonConfig;
      19: pop
      20: aload_2
      21: areturn

  public org.glassfish.jersey.client.ClientConfig$State register(java.lang.Class<?>);
    Code:
       0: aload_0
       1: getfield      #6                  // Field strategy:Lorg/glassfish/jersey/client/ClientConfig$State$StateChangeStrategy;
       4: aload_0
       5: invokeinterface #27,  2           // InterfaceMethod org/glassfish/jersey/client/ClientConfig$State$StateChangeStrategy.onChange:(Lorg/glassfish/jersey/client/ClientConfig$State;)Lorg/glassfish/jersey/client/ClientConfig$State;
      10: astore_2
      11: aload_2
      12: getfield      #11                 // Field commonConfig:Lorg/glassfish/jersey/model/internal/CommonConfig;
      15: aload_1
      16: invokevirtual #33                 // Method org/glassfish/jersey/model/internal/CommonConfig.register:(Ljava/lang/Class;)Lorg/glassfish/jersey/model/internal/CommonConfig;
      19: pop
      20: aload_2
      21: areturn

  public org.glassfish.jersey.client.ClientConfig$State register(java.lang.Object);
    Code:
       0: aload_0
       1: getfield      #6                  // Field strategy:Lorg/glassfish/jersey/client/ClientConfig$State$StateChangeStrategy;
       4: aload_0
       5: invokeinterface #27,  2           // InterfaceMethod org/glassfish/jersey/client/ClientConfig$State$StateChangeStrategy.onChange:(Lorg/glassfish/jersey/client/ClientConfig$State;)Lorg/glassfish/jersey/client/ClientConfig$State;
      10: astore_2
      11: aload_2
      12: getfield      #11                 // Field commonConfig:Lorg/glassfish/jersey/model/internal/CommonConfig;
      15: aload_1
      16: invokevirtual #34                 // Method org/glassfish/jersey/model/internal/CommonConfig.register:(Ljava/lang/Object;)Lorg/glassfish/jersey/model/internal/CommonConfig;
      19: pop
      20: aload_2
      21: areturn

  public org.glassfish.jersey.client.ClientConfig$State register(java.lang.Class<?>, int);
    Code:
       0: aload_0
       1: getfield      #6                  // Field strategy:Lorg/glassfish/jersey/client/ClientConfig$State$StateChangeStrategy;
       4: aload_0
       5: invokeinterface #27,  2           // InterfaceMethod org/glassfish/jersey/client/ClientConfig$State$StateChangeStrategy.onChange:(Lorg/glassfish/jersey/client/ClientConfig$State;)Lorg/glassfish/jersey/client/ClientConfig$State;
      10: astore_3
      11: aload_3
      12: getfield      #11                 // Field commonConfig:Lorg/glassfish/jersey/model/internal/CommonConfig;
      15: aload_1
      16: iload_2
      17: invokevirtual #35                 // Method org/glassfish/jersey/model/internal/CommonConfig.register:(Ljava/lang/Class;I)Lorg/glassfish/jersey/model/internal/CommonConfig;
      20: pop
      21: aload_3
      22: areturn

  public org.glassfish.jersey.client.ClientConfig$State register(java.lang.Class<?>, java.lang.Class<?>...);
    Code:
       0: aload_0
       1: getfield      #6                  // Field strategy:Lorg/glassfish/jersey/client/ClientConfig$State$StateChangeStrategy;
       4: aload_0
       5: invokeinterface #27,  2           // InterfaceMethod org/glassfish/jersey/client/ClientConfig$State$StateChangeStrategy.onChange:(Lorg/glassfish/jersey/client/ClientConfig$State;)Lorg/glassfish/jersey/client/ClientConfig$State;
      10: astore_3
      11: aload_3
      12: getfield      #11                 // Field commonConfig:Lorg/glassfish/jersey/model/internal/CommonConfig;
      15: aload_1
      16: aload_2
      17: invokevirtual #36                 // Method org/glassfish/jersey/model/internal/CommonConfig.register:(Ljava/lang/Class;[Ljava/lang/Class;)Lorg/glassfish/jersey/model/internal/CommonConfig;
      20: pop
      21: aload_3
      22: areturn

  public org.glassfish.jersey.client.ClientConfig$State register(java.lang.Class<?>, java.util.Map<java.lang.Class<?>, java.lang.Integer>);
    Code:
       0: aload_0
       1: getfield      #6                  // Field strategy:Lorg/glassfish/jersey/client/ClientConfig$State$StateChangeStrategy;
       4: aload_0
       5: invokeinterface #27,  2           // InterfaceMethod org/glassfish/jersey/client/ClientConfig$State$StateChangeStrategy.onChange:(Lorg/glassfish/jersey/client/ClientConfig$State;)Lorg/glassfish/jersey/client/ClientConfig$State;
      10: astore_3
      11: aload_3
      12: getfield      #11                 // Field commonConfig:Lorg/glassfish/jersey/model/internal/CommonConfig;
      15: aload_1
      16: aload_2
      17: invokevirtual #37                 // Method org/glassfish/jersey/model/internal/CommonConfig.register:(Ljava/lang/Class;Ljava/util/Map;)Lorg/glassfish/jersey/model/internal/CommonConfig;
      20: pop
      21: aload_3
      22: areturn

  public org.glassfish.jersey.client.ClientConfig$State register(java.lang.Object, int);
    Code:
       0: aload_0
       1: getfield      #6                  // Field strategy:Lorg/glassfish/jersey/client/ClientConfig$State$StateChangeStrategy;
       4: aload_0
       5: invokeinterface #27,  2           // InterfaceMethod org/glassfish/jersey/client/ClientConfig$State$StateChangeStrategy.onChange:(Lorg/glassfish/jersey/client/ClientConfig$State;)Lorg/glassfish/jersey/client/ClientConfig$State;
      10: astore_3
      11: aload_3
      12: getfield      #11                 // Field commonConfig:Lorg/glassfish/jersey/model/internal/CommonConfig;
      15: aload_1
      16: iload_2
      17: invokevirtual #38                 // Method org/glassfish/jersey/model/internal/CommonConfig.register:(Ljava/lang/Object;I)Lorg/glassfish/jersey/model/internal/CommonConfig;
      20: pop
      21: aload_3
      22: areturn

  public org.glassfish.jersey.client.ClientConfig$State register(java.lang.Object, java.lang.Class<?>...);
    Code:
       0: aload_0
       1: getfield      #6                  // Field strategy:Lorg/glassfish/jersey/client/ClientConfig$State$StateChangeStrategy;
       4: aload_0
       5: invokeinterface #27,  2           // InterfaceMethod org/glassfish/jersey/client/ClientConfig$State$StateChangeStrategy.onChange:(Lorg/glassfish/jersey/client/ClientConfig$State;)Lorg/glassfish/jersey/client/ClientConfig$State;
      10: astore_3
      11: aload_3
      12: getfield      #11                 // Field commonConfig:Lorg/glassfish/jersey/model/internal/CommonConfig;
      15: aload_1
      16: aload_2
      17: invokevirtual #39                 // Method org/glassfish/jersey/model/internal/CommonConfig.register:(Ljava/lang/Object;[Ljava/lang/Class;)Lorg/glassfish/jersey/model/internal/CommonConfig;
      20: pop
      21: aload_3
      22: areturn

  public org.glassfish.jersey.client.ClientConfig$State register(java.lang.Object, java.util.Map<java.lang.Class<?>, java.lang.Integer>);
    Code:
       0: aload_0
       1: getfield      #6                  // Field strategy:Lorg/glassfish/jersey/client/ClientConfig$State$StateChangeStrategy;
       4: aload_0
       5: invokeinterface #27,  2           // InterfaceMethod org/glassfish/jersey/client/ClientConfig$State$StateChangeStrategy.onChange:(Lorg/glassfish/jersey/client/ClientConfig$State;)Lorg/glassfish/jersey/client/ClientConfig$State;
      10: astore_3
      11: aload_3
      12: getfield      #11                 // Field commonConfig:Lorg/glassfish/jersey/model/internal/CommonConfig;
      15: aload_1
      16: aload_2
      17: invokevirtual #40                 // Method org/glassfish/jersey/model/internal/CommonConfig.register:(Ljava/lang/Object;Ljava/util/Map;)Lorg/glassfish/jersey/model/internal/CommonConfig;
      20: pop
      21: aload_3
      22: areturn

  org.glassfish.jersey.client.ClientConfig$State connectorProvider(org.glassfish.jersey.client.spi.ConnectorProvider);
    Code:
       0: aload_1
       1: ifnonnull     15
       4: new           #41                 // class java/lang/NullPointerException
       7: dup
       8: invokestatic  #42                 // Method org/glassfish/jersey/client/internal/LocalizationMessages.NULL_CONNECTOR_PROVIDER:()Ljava/lang/String;
      11: invokespecial #43                 // Method java/lang/NullPointerException."<init>":(Ljava/lang/String;)V
      14: athrow
      15: aload_0
      16: getfield      #6                  // Field strategy:Lorg/glassfish/jersey/client/ClientConfig$State$StateChangeStrategy;
      19: aload_0
      20: invokeinterface #27,  2           // InterfaceMethod org/glassfish/jersey/client/ClientConfig$State$StateChangeStrategy.onChange:(Lorg/glassfish/jersey/client/ClientConfig$State;)Lorg/glassfish/jersey/client/ClientConfig$State;
      25: astore_2
      26: aload_2
      27: aload_1
      28: putfield      #18                 // Field connectorProvider:Lorg/glassfish/jersey/client/spi/ConnectorProvider;
      31: aload_2
      32: areturn

  org.glassfish.jersey.client.ClientConfig$State executorService(java.util.concurrent.ExecutorService);
    Code:
       0: aload_1
       1: ifnonnull     15
       4: new           #41                 // class java/lang/NullPointerException
       7: dup
       8: invokestatic  #44                 // Method org/glassfish/jersey/client/internal/LocalizationMessages.NULL_EXECUTOR_SERVICE:()Ljava/lang/String;
      11: invokespecial #43                 // Method java/lang/NullPointerException."<init>":(Ljava/lang/String;)V
      14: athrow
      15: aload_0
      16: getfield      #6                  // Field strategy:Lorg/glassfish/jersey/client/ClientConfig$State$StateChangeStrategy;
      19: aload_0
      20: invokeinterface #27,  2           // InterfaceMethod org/glassfish/jersey/client/ClientConfig$State$StateChangeStrategy.onChange:(Lorg/glassfish/jersey/client/ClientConfig$State;)Lorg/glassfish/jersey/client/ClientConfig$State;
      25: astore_2
      26: aload_2
      27: aload_1
      28: putfield      #22                 // Field executorService:Ljava/util/concurrent/ExecutorService;
      31: aload_2
      32: areturn

  org.glassfish.jersey.client.ClientConfig$State scheduledExecutorService(java.util.concurrent.ScheduledExecutorService);
    Code:
       0: aload_1
       1: ifnonnull     15
       4: new           #41                 // class java/lang/NullPointerException
       7: dup
       8: invokestatic  #45                 // Method org/glassfish/jersey/client/internal/LocalizationMessages.NULL_SCHEDULED_EXECUTOR_SERVICE:()Ljava/lang/String;
      11: invokespecial #43                 // Method java/lang/NullPointerException."<init>":(Ljava/lang/String;)V
      14: athrow
      15: aload_0
      16: getfield      #6                  // Field strategy:Lorg/glassfish/jersey/client/ClientConfig$State$StateChangeStrategy;
      19: aload_0
      20: invokeinterface #27,  2           // InterfaceMethod org/glassfish/jersey/client/ClientConfig$State$StateChangeStrategy.onChange:(Lorg/glassfish/jersey/client/ClientConfig$State;)Lorg/glassfish/jersey/client/ClientConfig$State;
      25: astore_2
      26: aload_2
      27: aload_1
      28: putfield      #23                 // Field scheduledExecutorService:Ljava/util/concurrent/ScheduledExecutorService;
      31: aload_2
      32: areturn

  org.glassfish.jersey.client.spi.Connector getConnector();
    Code:
       0: aload_0
       1: getfield      #1                  // Field runtime:Lorg/glassfish/jersey/internal/util/collection/LazyValue;
       4: invokeinterface #46,  1           // InterfaceMethod org/glassfish/jersey/internal/util/collection/LazyValue.isInitialized:()Z
       9: ifeq          30
      12: aload_0
      13: getfield      #1                  // Field runtime:Lorg/glassfish/jersey/internal/util/collection/LazyValue;
      16: invokeinterface #28,  1           // InterfaceMethod org/glassfish/jersey/internal/util/collection/LazyValue.get:()Ljava/lang/Object;
      21: checkcast     #29                 // class org/glassfish/jersey/client/ClientRuntime
      24: invokevirtual #47                 // Method org/glassfish/jersey/client/ClientRuntime.getConnector:()Lorg/glassfish/jersey/client/spi/Connector;
      27: goto          31
      30: aconst_null
      31: areturn

  org.glassfish.jersey.client.spi.ConnectorProvider getConnectorProvider();
    Code:
       0: aload_0
       1: getfield      #18                 // Field connectorProvider:Lorg/glassfish/jersey/client/spi/ConnectorProvider;
       4: areturn

  java.util.concurrent.ExecutorService getExecutorService();
    Code:
       0: aload_0
       1: getfield      #22                 // Field executorService:Ljava/util/concurrent/ExecutorService;
       4: areturn

  java.util.concurrent.ScheduledExecutorService getScheduledExecutorService();
    Code:
       0: aload_0
       1: getfield      #23                 // Field scheduledExecutorService:Ljava/util/concurrent/ScheduledExecutorService;
       4: areturn

  org.glassfish.jersey.client.JerseyClient getClient();
    Code:
       0: aload_0
       1: getfield      #12                 // Field client:Lorg/glassfish/jersey/client/JerseyClient;
       4: areturn

  public org.glassfish.jersey.client.ClientConfig$State getConfiguration();
    Code:
       0: aload_0
       1: areturn

  public javax.ws.rs.RuntimeType getRuntimeType();
    Code:
       0: aload_0
       1: getfield      #11                 // Field commonConfig:Lorg/glassfish/jersey/model/internal/CommonConfig;
       4: invokevirtual #48                 // Method org/glassfish/jersey/model/internal/CommonConfig.getConfiguration:()Lorg/glassfish/jersey/ExtendedConfig;
       7: invokeinterface #49,  1           // InterfaceMethod org/glassfish/jersey/ExtendedConfig.getRuntimeType:()Ljavax/ws/rs/RuntimeType;
      12: areturn

  public java.util.Map<java.lang.String, java.lang.Object> getProperties();
    Code:
       0: aload_0
       1: getfield      #11                 // Field commonConfig:Lorg/glassfish/jersey/model/internal/CommonConfig;
       4: invokevirtual #48                 // Method org/glassfish/jersey/model/internal/CommonConfig.getConfiguration:()Lorg/glassfish/jersey/ExtendedConfig;
       7: invokeinterface #50,  1           // InterfaceMethod org/glassfish/jersey/ExtendedConfig.getProperties:()Ljava/util/Map;
      12: areturn

  public java.lang.Object getProperty(java.lang.String);
    Code:
       0: aload_0
       1: getfield      #11                 // Field commonConfig:Lorg/glassfish/jersey/model/internal/CommonConfig;
       4: invokevirtual #48                 // Method org/glassfish/jersey/model/internal/CommonConfig.getConfiguration:()Lorg/glassfish/jersey/ExtendedConfig;
       7: aload_1
       8: invokeinterface #51,  2           // InterfaceMethod org/glassfish/jersey/ExtendedConfig.getProperty:(Ljava/lang/String;)Ljava/lang/Object;
      13: areturn

  public java.util.Collection<java.lang.String> getPropertyNames();
    Code:
       0: aload_0
       1: getfield      #11                 // Field commonConfig:Lorg/glassfish/jersey/model/internal/CommonConfig;
       4: invokevirtual #48                 // Method org/glassfish/jersey/model/internal/CommonConfig.getConfiguration:()Lorg/glassfish/jersey/ExtendedConfig;
       7: invokeinterface #52,  1           // InterfaceMethod org/glassfish/jersey/ExtendedConfig.getPropertyNames:()Ljava/util/Collection;
      12: areturn

  public boolean isProperty(java.lang.String);
    Code:
       0: aload_0
       1: getfield      #11                 // Field commonConfig:Lorg/glassfish/jersey/model/internal/CommonConfig;
       4: invokevirtual #48                 // Method org/glassfish/jersey/model/internal/CommonConfig.getConfiguration:()Lorg/glassfish/jersey/ExtendedConfig;
       7: aload_1
       8: invokeinterface #53,  2           // InterfaceMethod org/glassfish/jersey/ExtendedConfig.isProperty:(Ljava/lang/String;)Z
      13: ireturn

  public boolean isEnabled(javax.ws.rs.core.Feature);
    Code:
       0: aload_0
       1: getfield      #11                 // Field commonConfig:Lorg/glassfish/jersey/model/internal/CommonConfig;
       4: invokevirtual #48                 // Method org/glassfish/jersey/model/internal/CommonConfig.getConfiguration:()Lorg/glassfish/jersey/ExtendedConfig;
       7: aload_1
       8: invokeinterface #54,  2           // InterfaceMethod org/glassfish/jersey/ExtendedConfig.isEnabled:(Ljavax/ws/rs/core/Feature;)Z
      13: ireturn

  public boolean isEnabled(java.lang.Class<? extends javax.ws.rs.core.Feature>);
    Code:
       0: aload_0
       1: getfield      #11                 // Field commonConfig:Lorg/glassfish/jersey/model/internal/CommonConfig;
       4: invokevirtual #48                 // Method org/glassfish/jersey/model/internal/CommonConfig.getConfiguration:()Lorg/glassfish/jersey/ExtendedConfig;
       7: aload_1
       8: invokeinterface #55,  2           // InterfaceMethod org/glassfish/jersey/ExtendedConfig.isEnabled:(Ljava/lang/Class;)Z
      13: ireturn

  public boolean isRegistered(java.lang.Object);
    Code:
       0: aload_0
       1: getfield      #11                 // Field commonConfig:Lorg/glassfish/jersey/model/internal/CommonConfig;
       4: invokevirtual #48                 // Method org/glassfish/jersey/model/internal/CommonConfig.getConfiguration:()Lorg/glassfish/jersey/ExtendedConfig;
       7: aload_1
       8: invokeinterface #56,  2           // InterfaceMethod org/glassfish/jersey/ExtendedConfig.isRegistered:(Ljava/lang/Object;)Z
      13: ireturn

  public boolean isRegistered(java.lang.Class<?>);
    Code:
       0: aload_0
       1: getfield      #11                 // Field commonConfig:Lorg/glassfish/jersey/model/internal/CommonConfig;
       4: invokevirtual #48                 // Method org/glassfish/jersey/model/internal/CommonConfig.getConfiguration:()Lorg/glassfish/jersey/ExtendedConfig;
       7: aload_1
       8: invokeinterface #57,  2           // InterfaceMethod org/glassfish/jersey/ExtendedConfig.isRegistered:(Ljava/lang/Class;)Z
      13: ireturn

  public java.util.Map<java.lang.Class<?>, java.lang.Integer> getContracts(java.lang.Class<?>);
    Code:
       0: aload_0
       1: getfield      #11                 // Field commonConfig:Lorg/glassfish/jersey/model/internal/CommonConfig;
       4: invokevirtual #48                 // Method org/glassfish/jersey/model/internal/CommonConfig.getConfiguration:()Lorg/glassfish/jersey/ExtendedConfig;
       7: aload_1
       8: invokeinterface #58,  2           // InterfaceMethod org/glassfish/jersey/ExtendedConfig.getContracts:(Ljava/lang/Class;)Ljava/util/Map;
      13: areturn

  public java.util.Set<java.lang.Class<?>> getClasses();
    Code:
       0: aload_0
       1: getfield      #11                 // Field commonConfig:Lorg/glassfish/jersey/model/internal/CommonConfig;
       4: invokevirtual #48                 // Method org/glassfish/jersey/model/internal/CommonConfig.getConfiguration:()Lorg/glassfish/jersey/ExtendedConfig;
       7: invokeinterface #59,  1           // InterfaceMethod org/glassfish/jersey/ExtendedConfig.getClasses:()Ljava/util/Set;
      12: areturn

  public java.util.Set<java.lang.Object> getInstances();
    Code:
       0: aload_0
       1: getfield      #11                 // Field commonConfig:Lorg/glassfish/jersey/model/internal/CommonConfig;
       4: invokevirtual #48                 // Method org/glassfish/jersey/model/internal/CommonConfig.getConfiguration:()Lorg/glassfish/jersey/ExtendedConfig;
       7: invokeinterface #60,  1           // InterfaceMethod org/glassfish/jersey/ExtendedConfig.getInstances:()Ljava/util/Set;
      12: areturn

  public void configureAutoDiscoverableProviders(org.glassfish.jersey.internal.inject.InjectionManager, java.util.List<org.glassfish.jersey.internal.spi.AutoDiscoverable>);
    Code:
       0: aload_0
       1: getfield      #11                 // Field commonConfig:Lorg/glassfish/jersey/model/internal/CommonConfig;
       4: aload_1
       5: aload_2
       6: iconst_0
       7: invokevirtual #61                 // Method org/glassfish/jersey/model/internal/CommonConfig.configureAutoDiscoverableProviders:(Lorg/glassfish/jersey/internal/inject/InjectionManager;Ljava/util/Collection;Z)V
      10: return

  public void configureForcedAutoDiscoverableProviders(org.glassfish.jersey.internal.inject.InjectionManager);
    Code:
       0: aload_0
       1: getfield      #11                 // Field commonConfig:Lorg/glassfish/jersey/model/internal/CommonConfig;
       4: aload_1
       5: invokestatic  #62                 // Method java/util/Collections.emptyList:()Ljava/util/List;
       8: iconst_1
       9: invokevirtual #61                 // Method org/glassfish/jersey/model/internal/CommonConfig.configureAutoDiscoverableProviders:(Lorg/glassfish/jersey/internal/inject/InjectionManager;Ljava/util/Collection;Z)V
      12: return

  public void configureMetaProviders(org.glassfish.jersey.internal.inject.InjectionManager, org.glassfish.jersey.model.internal.ManagedObjectsFinalizer);
    Code:
       0: aload_0
       1: getfield      #11                 // Field commonConfig:Lorg/glassfish/jersey/model/internal/CommonConfig;
       4: aload_1
       5: aload_2
       6: invokevirtual #63                 // Method org/glassfish/jersey/model/internal/CommonConfig.configureMetaProviders:(Lorg/glassfish/jersey/internal/inject/InjectionManager;Lorg/glassfish/jersey/model/internal/ManagedObjectsFinalizer;)V
       9: return

  public org.glassfish.jersey.model.internal.ComponentBag getComponentBag();
    Code:
       0: aload_0
       1: getfield      #11                 // Field commonConfig:Lorg/glassfish/jersey/model/internal/CommonConfig;
       4: invokevirtual #64                 // Method org/glassfish/jersey/model/internal/CommonConfig.getComponentBag:()Lorg/glassfish/jersey/model/internal/ComponentBag;
       7: areturn

  private org.glassfish.jersey.client.ClientRuntime initRuntime();
    Code:
       0: aload_0
       1: invokevirtual #65                 // Method markAsShared:()V
       4: aload_0
       5: invokevirtual #66                 // Method copy:()Lorg/glassfish/jersey/client/ClientConfig$State;
       8: astore_1
       9: aload_1
      10: invokevirtual #65                 // Method markAsShared:()V
      13: invokestatic  #67                 // Method org/glassfish/jersey/internal/inject/Injections.createInjectionManager:()Lorg/glassfish/jersey/internal/inject/InjectionManager;
      16: astore_2
      17: aload_2
      18: new           #68                 // class org/glassfish/jersey/client/ClientBinder
      21: dup
      22: aload_1
      23: invokevirtual #69                 // Method getProperties:()Ljava/util/Map;
      26: invokespecial #70                 // Method org/glassfish/jersey/client/ClientBinder."<init>":(Ljava/util/Map;)V
      29: invokeinterface #71,  2           // InterfaceMethod org/glassfish/jersey/internal/inject/InjectionManager.register:(Lorg/glassfish/jersey/internal/inject/Binder;)V
      34: new           #72                 // class org/glassfish/jersey/client/ClientBootstrapBag
      37: dup
      38: invokespecial #73                 // Method org/glassfish/jersey/client/ClientBootstrapBag."<init>":()V
      41: astore_3
      42: aload_3
      43: new           #74                 // class org/glassfish/jersey/model/internal/ManagedObjectsFinalizer
      46: dup
      47: aload_2
      48: invokespecial #75                 // Method org/glassfish/jersey/model/internal/ManagedObjectsFinalizer."<init>":(Lorg/glassfish/jersey/internal/inject/InjectionManager;)V
      51: invokevirtual #76                 // Method org/glassfish/jersey/client/ClientBootstrapBag.setManagedObjectsFinalizer:(Lorg/glassfish/jersey/model/internal/ManagedObjectsFinalizer;)V
      54: new           #77                 // class org/glassfish/jersey/client/ClientMessageBodyFactory$MessageBodyWorkersConfigurator
      57: dup
      58: invokespecial #78                 // Method org/glassfish/jersey/client/ClientMessageBodyFactory$MessageBodyWorkersConfigurator."<init>":()V
      61: astore        4
      63: bipush        10
      65: anewarray     #79                 // class org/glassfish/jersey/internal/BootstrapConfigurator
      68: dup
      69: iconst_0
      70: new           #80                 // class org/glassfish/jersey/process/internal/RequestScope$RequestScopeConfigurator
      73: dup
      74: invokespecial #81                 // Method org/glassfish/jersey/process/internal/RequestScope$RequestScopeConfigurator."<init>":()V
      77: aastore
      78: dup
      79: iconst_1
      80: new           #82                 // class org/glassfish/jersey/internal/inject/ParamConverterConfigurator
      83: dup
      84: invokespecial #83                 // Method org/glassfish/jersey/internal/inject/ParamConverterConfigurator."<init>":()V
      87: aastore
      88: dup
      89: iconst_2
      90: new           #84                 // class org/glassfish/jersey/client/internal/inject/ParameterUpdaterConfigurator
      93: dup
      94: invokespecial #85                 // Method org/glassfish/jersey/client/internal/inject/ParameterUpdaterConfigurator."<init>":()V
      97: aastore
      98: dup
      99: iconst_3
     100: new           #86                 // class org/glassfish/jersey/client/ClientConfig$RuntimeConfigConfigurator
     103: dup
     104: aload_1
     105: aconst_null
     106: invokespecial #87                 // Method org/glassfish/jersey/client/ClientConfig$RuntimeConfigConfigurator."<init>":(Lorg/glassfish/jersey/client/ClientConfig$State;Lorg/glassfish/jersey/client/ClientConfig$1;)V
     109: aastore
     110: dup
     111: iconst_4
     112: new           #88                 // class org/glassfish/jersey/internal/ContextResolverFactory$ContextResolversConfigurator
     115: dup
     116: invokespecial #89                 // Method org/glassfish/jersey/internal/ContextResolverFactory$ContextResolversConfigurator."<init>":()V
     119: aastore
     120: dup
     121: iconst_5
     122: aload         4
     124: aastore
     125: dup
     126: bipush        6
     128: new           #90                 // class org/glassfish/jersey/internal/ExceptionMapperFactory$ExceptionMappersConfigurator
     131: dup
     132: invokespecial #91                 // Method org/glassfish/jersey/internal/ExceptionMapperFactory$ExceptionMappersConfigurator."<init>":()V
     135: aastore
     136: dup
     137: bipush        7
     139: new           #92                 // class org/glassfish/jersey/internal/JaxrsProviders$ProvidersConfigurator
     142: dup
     143: invokespecial #93                 // Method org/glassfish/jersey/internal/JaxrsProviders$ProvidersConfigurator."<init>":()V
     146: aastore
     147: dup
     148: bipush        8
     150: new           #94                 // class org/glassfish/jersey/internal/AutoDiscoverableConfigurator
     153: dup
     154: getstatic     #8                  // Field javax/ws/rs/RuntimeType.CLIENT:Ljavax/ws/rs/RuntimeType;
     157: invokespecial #95                 // Method org/glassfish/jersey/internal/AutoDiscoverableConfigurator."<init>":(Ljavax/ws/rs/RuntimeType;)V
     160: aastore
     161: dup
     162: bipush        9
     164: new           #96                 // class org/glassfish/jersey/client/ClientComponentConfigurator
     167: dup
     168: invokespecial #97                 // Method org/glassfish/jersey/client/ClientComponentConfigurator."<init>":()V
     171: aastore
     172: invokestatic  #98                 // Method java/util/Arrays.asList:([Ljava/lang/Object;)Ljava/util/List;
     175: astore        5
     177: aload         5
     179: aload_2
     180: aload_3
     181: invokedynamic #99,  0             // InvokeDynamic #1:accept:(Lorg/glassfish/jersey/internal/inject/InjectionManager;Lorg/glassfish/jersey/client/ClientBootstrapBag;)Ljava/util/function/Consumer;
     186: invokeinterface #100,  2          // InterfaceMethod java/util/List.forEach:(Ljava/util/function/Consumer;)V
     191: aload_1
     192: invokevirtual #69                 // Method getProperties:()Ljava/util/Map;
     195: getstatic     #8                  // Field javax/ws/rs/RuntimeType.CLIENT:Ljavax/ws/rs/RuntimeType;
     198: ldc           #102                // String jersey.config.disableAutoDiscovery
     200: getstatic     #103                // Field java/lang/Boolean.FALSE:Ljava/lang/Boolean;
     203: ldc           #104                // class java/lang/Boolean
     205: invokestatic  #105                // Method org/glassfish/jersey/CommonProperties.getValue:(Ljava/util/Map;Ljavax/ws/rs/RuntimeType;Ljava/lang/String;Ljava/lang/Object;Ljava/lang/Class;)Ljava/lang/Object;
     208: checkcast     #104                // class java/lang/Boolean
     211: invokevirtual #106                // Method java/lang/Boolean.booleanValue:()Z
     214: ifne          229
     217: aload_1
     218: aload_2
     219: aload_3
     220: invokevirtual #107                // Method org/glassfish/jersey/client/ClientBootstrapBag.getAutoDiscoverables:()Ljava/util/List;
     223: invokevirtual #108                // Method configureAutoDiscoverableProviders:(Lorg/glassfish/jersey/internal/inject/InjectionManager;Ljava/util/List;)V
     226: goto          234
     229: aload_1
     230: aload_2
     231: invokevirtual #109                // Method configureForcedAutoDiscoverableProviders:(Lorg/glassfish/jersey/internal/inject/InjectionManager;)V
     234: aload_1
     235: aload_2
     236: aload_3
     237: invokevirtual #110                // Method org/glassfish/jersey/client/ClientBootstrapBag.getManagedObjectsFinalizer:()Lorg/glassfish/jersey/model/internal/ManagedObjectsFinalizer;
     240: invokevirtual #111                // Method configureMetaProviders:(Lorg/glassfish/jersey/internal/inject/InjectionManager;Lorg/glassfish/jersey/model/internal/ManagedObjectsFinalizer;)V
     243: aload_3
     244: invokevirtual #112                // Method org/glassfish/jersey/client/ClientBootstrapBag.getComponentProviders:()Lorg/glassfish/jersey/internal/util/collection/LazyValue;
     247: invokeinterface #28,  1           // InterfaceMethod org/glassfish/jersey/internal/util/collection/LazyValue.get:()Ljava/lang/Object;
     252: checkcast     #113                // class java/util/Collection
     255: astore        6
     257: aload_1
     258: invokevirtual #114                // Method getComponentBag:()Lorg/glassfish/jersey/model/internal/ComponentBag;
     261: getstatic     #8                  // Field javax/ws/rs/RuntimeType.CLIENT:Ljavax/ws/rs/RuntimeType;
     264: aconst_null
     265: aload_2
     266: aload         6
     268: invokestatic  #115                // Method org/glassfish/jersey/internal/inject/ProviderBinder.bindProviders:(Lorg/glassfish/jersey/model/internal/ComponentBag;Ljavax/ws/rs/RuntimeType;Ljava/util/Set;Lorg/glassfish/jersey/internal/inject/InjectionManager;Ljava/util/Collection;)V
     271: new           #116                // class org/glassfish/jersey/client/ClientExecutorProvidersConfigurator
     274: dup
     275: aload_1
     276: invokevirtual #114                // Method getComponentBag:()Lorg/glassfish/jersey/model/internal/ComponentBag;
     279: aload_1
     280: getfield      #12                 // Field client:Lorg/glassfish/jersey/client/JerseyClient;
     283: aload_0
     284: getfield      #22                 // Field executorService:Ljava/util/concurrent/ExecutorService;
     287: aload_0
     288: getfield      #23                 // Field scheduledExecutorService:Ljava/util/concurrent/ScheduledExecutorService;
     291: invokespecial #117                // Method org/glassfish/jersey/client/ClientExecutorProvidersConfigurator."<init>":(Lorg/glassfish/jersey/model/internal/ComponentBag;Lorg/glassfish/jersey/client/JerseyClient;Ljava/util/concurrent/ExecutorService;Ljava/util/concurrent/ScheduledExecutorService;)V
     294: astore        7
     296: aload         7
     298: aload_2
     299: aload_3
     300: invokevirtual #118                // Method org/glassfish/jersey/client/ClientExecutorProvidersConfigurator.init:(Lorg/glassfish/jersey/internal/inject/InjectionManager;Lorg/glassfish/jersey/internal/BootstrapBag;)V
     303: aload_2
     304: invokeinterface #119,  1          // InterfaceMethod org/glassfish/jersey/internal/inject/InjectionManager.completeRegistration:()V
     309: aload         5
     311: aload_2
     312: aload_3
     313: invokedynamic #120,  0            // InvokeDynamic #2:accept:(Lorg/glassfish/jersey/internal/inject/InjectionManager;Lorg/glassfish/jersey/client/ClientBootstrapBag;)Ljava/util/function/Consumer;
     318: invokeinterface #100,  2          // InterfaceMethod java/util/List.forEach:(Ljava/util/function/Consumer;)V
     323: new           #121                // class org/glassfish/jersey/client/ClientConfig
     326: dup
     327: aload_1
     328: aconst_null
     329: invokespecial #122                // Method org/glassfish/jersey/client/ClientConfig."<init>":(Lorg/glassfish/jersey/client/ClientConfig$State;Lorg/glassfish/jersey/client/ClientConfig$1;)V
     332: astore        8
     334: aload_0
     335: getfield      #18                 // Field connectorProvider:Lorg/glassfish/jersey/client/spi/ConnectorProvider;
     338: aload_0
     339: getfield      #12                 // Field client:Lorg/glassfish/jersey/client/JerseyClient;
     342: aload         8
     344: invokeinterface #123,  3          // InterfaceMethod org/glassfish/jersey/client/spi/ConnectorProvider.getConnector:(Ljavax/ws/rs/client/Client;Ljavax/ws/rs/core/Configuration;)Lorg/glassfish/jersey/client/spi/Connector;
     349: astore        9
     351: new           #29                 // class org/glassfish/jersey/client/ClientRuntime
     354: dup
     355: aload         8
     357: aload         9
     359: aload_2
     360: aload_3
     361: invokespecial #124                // Method org/glassfish/jersey/client/ClientRuntime."<init>":(Lorg/glassfish/jersey/client/ClientConfig;Lorg/glassfish/jersey/client/spi/Connector;Lorg/glassfish/jersey/internal/inject/InjectionManager;Lorg/glassfish/jersey/internal/BootstrapBag;)V
     364: astore        10
     366: aload_0
     367: getfield      #12                 // Field client:Lorg/glassfish/jersey/client/JerseyClient;
     370: aload         10
     372: invokevirtual #125                // Method org/glassfish/jersey/client/JerseyClient.registerShutdownHook:(Lorg/glassfish/jersey/client/JerseyClient$ShutdownHook;)V
     375: aload         4
     377: aload         10
     379: invokevirtual #126                // Method org/glassfish/jersey/client/ClientMessageBodyFactory$MessageBodyWorkersConfigurator.setClientRuntime:(Lorg/glassfish/jersey/client/ClientRuntime;)V
     382: aload         10
     384: areturn

  public boolean equals(java.lang.Object);
    Code:
       0: aload_0
       1: aload_1
       2: if_acmpne     7
       5: iconst_1
       6: ireturn
       7: aload_1
       8: ifnull        22
      11: aload_0
      12: invokevirtual #127                // Method java/lang/Object.getClass:()Ljava/lang/Class;
      15: aload_1
      16: invokevirtual #127                // Method java/lang/Object.getClass:()Ljava/lang/Class;
      19: if_acmpeq     24
      22: iconst_0
      23: ireturn
      24: aload_1
      25: checkcast     #24                 // class org/glassfish/jersey/client/ClientConfig$State
      28: astore_2
      29: aload_0
      30: getfield      #12                 // Field client:Lorg/glassfish/jersey/client/JerseyClient;
      33: ifnull        53
      36: aload_0
      37: getfield      #12                 // Field client:Lorg/glassfish/jersey/client/JerseyClient;
      40: aload_2
      41: getfield      #12                 // Field client:Lorg/glassfish/jersey/client/JerseyClient;
      44: invokevirtual #128                // Method java/lang/Object.equals:(Ljava/lang/Object;)Z
      47: ifne          62
      50: goto          60
      53: aload_2
      54: getfield      #12                 // Field client:Lorg/glassfish/jersey/client/JerseyClient;
      57: ifnull        62
      60: iconst_0
      61: ireturn
      62: aload_0
      63: getfield      #11                 // Field commonConfig:Lorg/glassfish/jersey/model/internal/CommonConfig;
      66: aload_2
      67: getfield      #11                 // Field commonConfig:Lorg/glassfish/jersey/model/internal/CommonConfig;
      70: invokevirtual #129                // Method org/glassfish/jersey/model/internal/CommonConfig.equals:(Ljava/lang/Object;)Z
      73: ifne          78
      76: iconst_0
      77: ireturn
      78: aload_0
      79: getfield      #18                 // Field connectorProvider:Lorg/glassfish/jersey/client/spi/ConnectorProvider;
      82: ifnonnull     100
      85: aload_2
      86: getfield      #18                 // Field connectorProvider:Lorg/glassfish/jersey/client/spi/ConnectorProvider;
      89: ifnonnull     96
      92: iconst_1
      93: goto          111
      96: iconst_0
      97: goto          111
     100: aload_0
     101: getfield      #18                 // Field connectorProvider:Lorg/glassfish/jersey/client/spi/ConnectorProvider;
     104: aload_2
     105: getfield      #18                 // Field connectorProvider:Lorg/glassfish/jersey/client/spi/ConnectorProvider;
     108: invokevirtual #128                // Method java/lang/Object.equals:(Ljava/lang/Object;)Z
     111: ireturn

  public int hashCode();
    Code:
       0: aload_0
       1: getfield      #11                 // Field commonConfig:Lorg/glassfish/jersey/model/internal/CommonConfig;
       4: invokevirtual #130                // Method org/glassfish/jersey/model/internal/CommonConfig.hashCode:()I
       7: istore_1
       8: bipush        31
      10: iload_1
      11: imul
      12: aload_0
      13: getfield      #12                 // Field client:Lorg/glassfish/jersey/client/JerseyClient;
      16: ifnull        29
      19: aload_0
      20: getfield      #12                 // Field client:Lorg/glassfish/jersey/client/JerseyClient;
      23: invokevirtual #131                // Method java/lang/Object.hashCode:()I
      26: goto          30
      29: iconst_0
      30: iadd
      31: istore_1
      32: bipush        31
      34: iload_1
      35: imul
      36: aload_0
      37: getfield      #18                 // Field connectorProvider:Lorg/glassfish/jersey/client/spi/ConnectorProvider;
      40: ifnull        53
      43: aload_0
      44: getfield      #18                 // Field connectorProvider:Lorg/glassfish/jersey/client/spi/ConnectorProvider;
      47: invokevirtual #131                // Method java/lang/Object.hashCode:()I
      50: goto          54
      53: iconst_0
      54: iadd
      55: istore_1
      56: iload_1
      57: ireturn

  public javax.ws.rs.core.Configurable register(java.lang.Object, java.util.Map);
    Code:
       0: aload_0
       1: aload_1
       2: aload_2
       3: invokevirtual #132                // Method register:(Ljava/lang/Object;Ljava/util/Map;)Lorg/glassfish/jersey/client/ClientConfig$State;
       6: areturn

  public javax.ws.rs.core.Configurable register(java.lang.Object, java.lang.Class[]);
    Code:
       0: aload_0
       1: aload_1
       2: aload_2
       3: invokevirtual #133                // Method register:(Ljava/lang/Object;[Ljava/lang/Class;)Lorg/glassfish/jersey/client/ClientConfig$State;
       6: areturn

  public javax.ws.rs.core.Configurable register(java.lang.Object, int);
    Code:
       0: aload_0
       1: aload_1
       2: iload_2
       3: invokevirtual #134                // Method register:(Ljava/lang/Object;I)Lorg/glassfish/jersey/client/ClientConfig$State;
       6: areturn

  public javax.ws.rs.core.Configurable register(java.lang.Object);
    Code:
       0: aload_0
       1: aload_1
       2: invokevirtual #135                // Method register:(Ljava/lang/Object;)Lorg/glassfish/jersey/client/ClientConfig$State;
       5: areturn

  public javax.ws.rs.core.Configurable register(java.lang.Class, java.util.Map);
    Code:
       0: aload_0
       1: aload_1
       2: aload_2
       3: invokevirtual #136                // Method register:(Ljava/lang/Class;Ljava/util/Map;)Lorg/glassfish/jersey/client/ClientConfig$State;
       6: areturn

  public javax.ws.rs.core.Configurable register(java.lang.Class, java.lang.Class[]);
    Code:
       0: aload_0
       1: aload_1
       2: aload_2
       3: invokevirtual #137                // Method register:(Ljava/lang/Class;[Ljava/lang/Class;)Lorg/glassfish/jersey/client/ClientConfig$State;
       6: areturn

  public javax.ws.rs.core.Configurable register(java.lang.Class, int);
    Code:
       0: aload_0
       1: aload_1
       2: iload_2
       3: invokevirtual #138                // Method register:(Ljava/lang/Class;I)Lorg/glassfish/jersey/client/ClientConfig$State;
       6: areturn

  public javax.ws.rs.core.Configurable register(java.lang.Class);
    Code:
       0: aload_0
       1: aload_1
       2: invokevirtual #139                // Method register:(Ljava/lang/Class;)Lorg/glassfish/jersey/client/ClientConfig$State;
       5: areturn

  public javax.ws.rs.core.Configurable property(java.lang.String, java.lang.Object);
    Code:
       0: aload_0
       1: aload_1
       2: aload_2
       3: invokevirtual #140                // Method property:(Ljava/lang/String;Ljava/lang/Object;)Lorg/glassfish/jersey/client/ClientConfig$State;
       6: areturn

  public javax.ws.rs.core.Configuration getConfiguration();
    Code:
       0: aload_0
       1: invokevirtual #141                // Method getConfiguration:()Lorg/glassfish/jersey/client/ClientConfig$State;
       4: areturn

  private static void lambda$initRuntime$2(org.glassfish.jersey.internal.inject.InjectionManager, org.glassfish.jersey.client.ClientBootstrapBag, org.glassfish.jersey.internal.BootstrapConfigurator);
    Code:
       0: aload_2
       1: aload_0
       2: aload_1
       3: invokeinterface #142,  3          // InterfaceMethod org/glassfish/jersey/internal/BootstrapConfigurator.postInit:(Lorg/glassfish/jersey/internal/inject/InjectionManager;Lorg/glassfish/jersey/internal/BootstrapBag;)V
       8: return

  private static void lambda$initRuntime$1(org.glassfish.jersey.internal.inject.InjectionManager, org.glassfish.jersey.client.ClientBootstrapBag, org.glassfish.jersey.internal.BootstrapConfigurator);
    Code:
       0: aload_2
       1: aload_0
       2: aload_1
       3: invokeinterface #143,  3          // InterfaceMethod org/glassfish/jersey/internal/BootstrapConfigurator.init:(Lorg/glassfish/jersey/internal/inject/InjectionManager;Lorg/glassfish/jersey/internal/BootstrapBag;)V
       8: return

  private static org.glassfish.jersey.client.ClientConfig$State lambda$static$0(org.glassfish.jersey.client.ClientConfig$State);
    Code:
       0: aload_0
       1: areturn

  static org.glassfish.jersey.internal.util.collection.LazyValue access$200(org.glassfish.jersey.client.ClientConfig$State);
    Code:
       0: aload_0
       1: getfield      #1                  // Field runtime:Lorg/glassfish/jersey/internal/util/collection/LazyValue;
       4: areturn

  static {};
    Code:
       0: invokedynamic #144,  0            // InvokeDynamic #3:onChange:()Lorg/glassfish/jersey/client/ClientConfig$State$StateChangeStrategy;
       5: putstatic     #5                  // Field IDENTITY:Lorg/glassfish/jersey/client/ClientConfig$State$StateChangeStrategy;
       8: invokedynamic #145,  0            // InvokeDynamic #4:onChange:()Lorg/glassfish/jersey/client/ClientConfig$State$StateChangeStrategy;
      13: putstatic     #26                 // Field COPY_ON_CHANGE:Lorg/glassfish/jersey/client/ClientConfig$State$StateChangeStrategy;
      16: return
}
