Compiled from "SimpleInterceptorInvocation.java"
class org.jboss.weld.interceptor.reader.SimpleInterceptorInvocation$SimpleMethodInvocation implements org.jboss.weld.interceptor.proxy.InterceptorMethodInvocation {
  private final java.lang.reflect.Method method;

  final org.jboss.weld.interceptor.reader.SimpleInterceptorInvocation this$0;

  org.jboss.weld.interceptor.reader.SimpleInterceptorInvocation$SimpleMethodInvocation(org.jboss.weld.interceptor.reader.SimpleInterceptorInvocation, java.lang.reflect.Method);
    Code:
       0: aload_0
       1: aload_1
       2: putfield      #1                  // Field this$0:Lorg/jboss/weld/interceptor/reader/SimpleInterceptorInvocation;
       5: aload_0
       6: invokespecial #2                  // Method java/lang/Object."<init>":()V
       9: aload_0
      10: aload_2
      11: putfield      #3                  // Field method:Ljava/lang/reflect/Method;
      14: return

  public java.lang.Object invoke(javax.interceptor.InvocationContext) throws java.lang.Exception;
    Code:
       0: aload_1
       1: ifnull        27
       4: aload_0
       5: getfield      #3                  // Field method:Ljava/lang/reflect/Method;
       8: aload_0
       9: getfield      #1                  // Field this$0:Lorg/jboss/weld/interceptor/reader/SimpleInterceptorInvocation;
      12: invokestatic  #4                  // Method org/jboss/weld/interceptor/reader/SimpleInterceptorInvocation.access$000:(Lorg/jboss/weld/interceptor/reader/SimpleInterceptorInvocation;)Ljava/lang/Object;
      15: iconst_1
      16: anewarray     #5                  // class java/lang/Object
      19: dup
      20: iconst_0
      21: aload_1
      22: aastore
      23: invokevirtual #6                  // Method java/lang/reflect/Method.invoke:(Ljava/lang/Object;[Ljava/lang/Object;)Ljava/lang/Object;
      26: areturn
      27: aload_0
      28: getfield      #3                  // Field method:Ljava/lang/reflect/Method;
      31: aload_0
      32: getfield      #1                  // Field this$0:Lorg/jboss/weld/interceptor/reader/SimpleInterceptorInvocation;
      35: invokestatic  #4                  // Method org/jboss/weld/interceptor/reader/SimpleInterceptorInvocation.access$000:(Lorg/jboss/weld/interceptor/reader/SimpleInterceptorInvocation;)Ljava/lang/Object;
      38: iconst_0
      39: anewarray     #5                  // class java/lang/Object
      42: invokevirtual #6                  // Method java/lang/reflect/Method.invoke:(Ljava/lang/Object;[Ljava/lang/Object;)Ljava/lang/Object;
      45: areturn

  public boolean expectsInvocationContext();
    Code:
       0: aload_0
       1: getfield      #1                  // Field this$0:Lorg/jboss/weld/interceptor/reader/SimpleInterceptorInvocation;
       4: invokestatic  #7                  // Method org/jboss/weld/interceptor/reader/SimpleInterceptorInvocation.access$100:(Lorg/jboss/weld/interceptor/reader/SimpleInterceptorInvocation;)Z
       7: ifeq          23
      10: aload_0
      11: getfield      #1                  // Field this$0:Lorg/jboss/weld/interceptor/reader/SimpleInterceptorInvocation;
      14: invokestatic  #8                  // Method org/jboss/weld/interceptor/reader/SimpleInterceptorInvocation.access$200:(Lorg/jboss/weld/interceptor/reader/SimpleInterceptorInvocation;)Lorg/jboss/weld/interceptor/spi/model/InterceptionType;
      17: invokevirtual #9                  // Method org/jboss/weld/interceptor/spi/model/InterceptionType.isLifecycleCallback:()Z
      20: ifne          27
      23: iconst_1
      24: goto          28
      27: iconst_0
      28: ireturn

  public java.lang.String toString();
    Code:
       0: new           #10                 // class java/lang/StringBuilder
       3: dup
       4: invokespecial #11                 // Method java/lang/StringBuilder."<init>":()V
       7: ldc           #12                 // String SimpleMethodInvocation [method=
       9: invokevirtual #13                 // Method java/lang/StringBuilder.append:(Ljava/lang/String;)Ljava/lang/StringBuilder;
      12: aload_0
      13: getfield      #3                  // Field method:Ljava/lang/reflect/Method;
      16: invokevirtual #14                 // Method java/lang/StringBuilder.append:(Ljava/lang/Object;)Ljava/lang/StringBuilder;
      19: bipush        93
      21: invokevirtual #15                 // Method java/lang/StringBuilder.append:(C)Ljava/lang/StringBuilder;
      24: invokevirtual #16                 // Method java/lang/StringBuilder.toString:()Ljava/lang/String;
      27: areturn
}
