Compiled from "AbstractConnPool.java"
public abstract class org.apache.http.impl.conn.tsccm.AbstractConnPool {
  private final org.apache.commons.logging.Log log;

  protected final java.util.concurrent.locks.Lock poolLock;

  protected java.util.Set<org.apache.http.impl.conn.tsccm.BasicPoolEntry> leasedConnections;

  protected int numConnections;

  protected volatile boolean isShutDown;

  protected java.util.Set<org.apache.http.impl.conn.tsccm.BasicPoolEntryRef> issuedConnections;

  protected java.lang.ref.ReferenceQueue<java.lang.Object> refQueue;

  protected org.apache.http.impl.conn.IdleConnectionHandler idleConnHandler;

  protected org.apache.http.impl.conn.tsccm.AbstractConnPool();
    Code:
       0: aload_0
       1: invokespecial #1                  // Method java/lang/Object."<init>":()V
       4: aload_0
       5: aload_0
       6: invokevirtual #2                  // Method java/lang/Object.getClass:()Ljava/lang/Class;
       9: invokestatic  #3                  // Method org/apache/commons/logging/LogFactory.getLog:(Ljava/lang/Class;)Lorg/apache/commons/logging/Log;
      12: putfield      #4                  // Field log:Lorg/apache/commons/logging/Log;
      15: aload_0
      16: new           #5                  // class java/util/HashSet
      19: dup
      20: invokespecial #6                  // Method java/util/HashSet."<init>":()V
      23: putfield      #7                  // Field leasedConnections:Ljava/util/Set;
      26: aload_0
      27: new           #8                  // class org/apache/http/impl/conn/IdleConnectionHandler
      30: dup
      31: invokespecial #9                  // Method org/apache/http/impl/conn/IdleConnectionHandler."<init>":()V
      34: putfield      #10                 // Field idleConnHandler:Lorg/apache/http/impl/conn/IdleConnectionHandler;
      37: aload_0
      38: new           #11                 // class java/util/concurrent/locks/ReentrantLock
      41: dup
      42: invokespecial #12                 // Method java/util/concurrent/locks/ReentrantLock."<init>":()V
      45: putfield      #13                 // Field poolLock:Ljava/util/concurrent/locks/Lock;
      48: return

  public void enableConnectionGC() throws java.lang.IllegalStateException;
    Code:
       0: return

  public final org.apache.http.impl.conn.tsccm.BasicPoolEntry getEntry(org.apache.http.conn.routing.HttpRoute, java.lang.Object, long, java.util.concurrent.TimeUnit) throws org.apache.http.conn.ConnectionPoolTimeoutException, java.lang.InterruptedException;
    Code:
       0: aload_0
       1: aload_1
       2: aload_2
       3: invokevirtual #14                 // Method requestPoolEntry:(Lorg/apache/http/conn/routing/HttpRoute;Ljava/lang/Object;)Lorg/apache/http/impl/conn/tsccm/PoolEntryRequest;
       6: lload_3
       7: aload         5
       9: invokeinterface #15,  4           // InterfaceMethod org/apache/http/impl/conn/tsccm/PoolEntryRequest.getPoolEntry:(JLjava/util/concurrent/TimeUnit;)Lorg/apache/http/impl/conn/tsccm/BasicPoolEntry;
      14: areturn

  public abstract org.apache.http.impl.conn.tsccm.PoolEntryRequest requestPoolEntry(org.apache.http.conn.routing.HttpRoute, java.lang.Object);

  public abstract void freeEntry(org.apache.http.impl.conn.tsccm.BasicPoolEntry, boolean, long, java.util.concurrent.TimeUnit);

  public void handleReference(java.lang.ref.Reference<?>);
    Code:
       0: return

  protected abstract void handleLostEntry(org.apache.http.conn.routing.HttpRoute);

  public void closeIdleConnections(long, java.util.concurrent.TimeUnit);
    Code:
       0: aload_3
       1: ldc           #16                 // String Time unit
       3: invokestatic  #17                 // Method org/apache/http/util/Args.notNull:(Ljava/lang/Object;Ljava/lang/String;)Ljava/lang/Object;
       6: pop
       7: aload_0
       8: getfield      #13                 // Field poolLock:Ljava/util/concurrent/locks/Lock;
      11: invokeinterface #18,  1           // InterfaceMethod java/util/concurrent/locks/Lock.lock:()V
      16: aload_0
      17: getfield      #10                 // Field idleConnHandler:Lorg/apache/http/impl/conn/IdleConnectionHandler;
      20: aload_3
      21: lload_1
      22: invokevirtual #19                 // Method java/util/concurrent/TimeUnit.toMillis:(J)J
      25: invokevirtual #20                 // Method org/apache/http/impl/conn/IdleConnectionHandler.closeIdleConnections:(J)V
      28: aload_0
      29: getfield      #13                 // Field poolLock:Ljava/util/concurrent/locks/Lock;
      32: invokeinterface #21,  1           // InterfaceMethod java/util/concurrent/locks/Lock.unlock:()V
      37: goto          54
      40: astore        4
      42: aload_0
      43: getfield      #13                 // Field poolLock:Ljava/util/concurrent/locks/Lock;
      46: invokeinterface #21,  1           // InterfaceMethod java/util/concurrent/locks/Lock.unlock:()V
      51: aload         4
      53: athrow
      54: return
    Exception table:
       from    to  target type
          16    28    40   any
          40    42    40   any

  public void closeExpiredConnections();
    Code:
       0: aload_0
       1: getfield      #13                 // Field poolLock:Ljava/util/concurrent/locks/Lock;
       4: invokeinterface #18,  1           // InterfaceMethod java/util/concurrent/locks/Lock.lock:()V
       9: aload_0
      10: getfield      #10                 // Field idleConnHandler:Lorg/apache/http/impl/conn/IdleConnectionHandler;
      13: invokevirtual #22                 // Method org/apache/http/impl/conn/IdleConnectionHandler.closeExpiredConnections:()V
      16: aload_0
      17: getfield      #13                 // Field poolLock:Ljava/util/concurrent/locks/Lock;
      20: invokeinterface #21,  1           // InterfaceMethod java/util/concurrent/locks/Lock.unlock:()V
      25: goto          40
      28: astore_1
      29: aload_0
      30: getfield      #13                 // Field poolLock:Ljava/util/concurrent/locks/Lock;
      33: invokeinterface #21,  1           // InterfaceMethod java/util/concurrent/locks/Lock.unlock:()V
      38: aload_1
      39: athrow
      40: return
    Exception table:
       from    to  target type
           9    16    28   any
          28    29    28   any

  public abstract void deleteClosedConnections();

  public void shutdown();
    Code:
       0: aload_0
       1: getfield      #13                 // Field poolLock:Ljava/util/concurrent/locks/Lock;
       4: invokeinterface #18,  1           // InterfaceMethod java/util/concurrent/locks/Lock.lock:()V
       9: aload_0
      10: getfield      #23                 // Field isShutDown:Z
      13: ifeq          26
      16: aload_0
      17: getfield      #13                 // Field poolLock:Ljava/util/concurrent/locks/Lock;
      20: invokeinterface #21,  1           // InterfaceMethod java/util/concurrent/locks/Lock.unlock:()V
      25: return
      26: aload_0
      27: getfield      #7                  // Field leasedConnections:Ljava/util/Set;
      30: invokeinterface #24,  1           // InterfaceMethod java/util/Set.iterator:()Ljava/util/Iterator;
      35: astore_1
      36: aload_1
      37: invokeinterface #25,  1           // InterfaceMethod java/util/Iterator.hasNext:()Z
      42: ifeq          72
      45: aload_1
      46: invokeinterface #26,  1           // InterfaceMethod java/util/Iterator.next:()Ljava/lang/Object;
      51: checkcast     #27                 // class org/apache/http/impl/conn/tsccm/BasicPoolEntry
      54: astore_2
      55: aload_1
      56: invokeinterface #28,  1           // InterfaceMethod java/util/Iterator.remove:()V
      61: aload_0
      62: aload_2
      63: invokevirtual #29                 // Method org/apache/http/impl/conn/tsccm/BasicPoolEntry.getConnection:()Lorg/apache/http/conn/OperatedClientConnection;
      66: invokevirtual #30                 // Method closeConnection:(Lorg/apache/http/conn/OperatedClientConnection;)V
      69: goto          36
      72: aload_0
      73: getfield      #10                 // Field idleConnHandler:Lorg/apache/http/impl/conn/IdleConnectionHandler;
      76: invokevirtual #31                 // Method org/apache/http/impl/conn/IdleConnectionHandler.removeAll:()V
      79: aload_0
      80: iconst_1
      81: putfield      #23                 // Field isShutDown:Z
      84: aload_0
      85: getfield      #13                 // Field poolLock:Ljava/util/concurrent/locks/Lock;
      88: invokeinterface #21,  1           // InterfaceMethod java/util/concurrent/locks/Lock.unlock:()V
      93: goto          108
      96: astore_3
      97: aload_0
      98: getfield      #13                 // Field poolLock:Ljava/util/concurrent/locks/Lock;
     101: invokeinterface #21,  1           // InterfaceMethod java/util/concurrent/locks/Lock.unlock:()V
     106: aload_3
     107: athrow
     108: return
    Exception table:
       from    to  target type
           9    16    96   any
          26    84    96   any
          96    97    96   any

  protected void closeConnection(org.apache.http.conn.OperatedClientConnection);
    Code:
       0: aload_1
       1: ifnull        26
       4: aload_1
       5: invokeinterface #32,  1           // InterfaceMethod org/apache/http/conn/OperatedClientConnection.close:()V
      10: goto          26
      13: astore_2
      14: aload_0
      15: getfield      #4                  // Field log:Lorg/apache/commons/logging/Log;
      18: ldc           #34                 // String I/O error closing connection
      20: aload_2
      21: invokeinterface #35,  3           // InterfaceMethod org/apache/commons/logging/Log.debug:(Ljava/lang/Object;Ljava/lang/Throwable;)V
      26: return
    Exception table:
       from    to  target type
           4    10    13   Class java/io/IOException
}
