Compiled from "ObjectIdDictionary.java"
public class com.thoughtworks.xstream.core.util.ObjectIdDictionary {
  private final java.util.Map map;

  private final java.lang.ref.ReferenceQueue queue;

  public com.thoughtworks.xstream.core.util.ObjectIdDictionary();
    Code:
       0: aload_0
       1: invokespecial #2                  // Method java/lang/Object."<init>":()V
       4: aload_0
       5: new           #3                  // class java/util/HashMap
       8: dup
       9: invokespecial #4                  // Method java/util/HashMap."<init>":()V
      12: putfield      #5                  // Field map:Ljava/util/Map;
      15: aload_0
      16: new           #6                  // class java/lang/ref/ReferenceQueue
      19: dup
      20: invokespecial #7                  // Method java/lang/ref/ReferenceQueue."<init>":()V
      23: putfield      #1                  // Field queue:Ljava/lang/ref/ReferenceQueue;
      26: return

  public void associateId(java.lang.Object, java.lang.Object);
    Code:
       0: aload_0
       1: getfield      #5                  // Field map:Ljava/util/Map;
       4: new           #8                  // class com/thoughtworks/xstream/core/util/ObjectIdDictionary$WeakIdWrapper
       7: dup
       8: aload_0
       9: aload_1
      10: invokespecial #9                  // Method com/thoughtworks/xstream/core/util/ObjectIdDictionary$WeakIdWrapper."<init>":(Lcom/thoughtworks/xstream/core/util/ObjectIdDictionary;Ljava/lang/Object;)V
      13: aload_2
      14: invokeinterface #10,  3           // InterfaceMethod java/util/Map.put:(Ljava/lang/Object;Ljava/lang/Object;)Ljava/lang/Object;
      19: pop
      20: aload_0
      21: invokespecial #11                 // Method cleanup:()V
      24: return

  public java.lang.Object lookupId(java.lang.Object);
    Code:
       0: aload_0
       1: getfield      #5                  // Field map:Ljava/util/Map;
       4: new           #12                 // class com/thoughtworks/xstream/core/util/ObjectIdDictionary$IdWrapper
       7: dup
       8: aload_1
       9: invokespecial #13                 // Method com/thoughtworks/xstream/core/util/ObjectIdDictionary$IdWrapper."<init>":(Ljava/lang/Object;)V
      12: invokeinterface #14,  2           // InterfaceMethod java/util/Map.get:(Ljava/lang/Object;)Ljava/lang/Object;
      17: astore_2
      18: aload_2
      19: areturn

  public boolean containsId(java.lang.Object);
    Code:
       0: aload_0
       1: getfield      #5                  // Field map:Ljava/util/Map;
       4: new           #12                 // class com/thoughtworks/xstream/core/util/ObjectIdDictionary$IdWrapper
       7: dup
       8: aload_1
       9: invokespecial #13                 // Method com/thoughtworks/xstream/core/util/ObjectIdDictionary$IdWrapper."<init>":(Ljava/lang/Object;)V
      12: invokeinterface #15,  2           // InterfaceMethod java/util/Map.containsKey:(Ljava/lang/Object;)Z
      17: istore_2
      18: iload_2
      19: ireturn

  public void removeId(java.lang.Object);
    Code:
       0: aload_0
       1: getfield      #5                  // Field map:Ljava/util/Map;
       4: new           #12                 // class com/thoughtworks/xstream/core/util/ObjectIdDictionary$IdWrapper
       7: dup
       8: aload_1
       9: invokespecial #13                 // Method com/thoughtworks/xstream/core/util/ObjectIdDictionary$IdWrapper."<init>":(Ljava/lang/Object;)V
      12: invokeinterface #16,  2           // InterfaceMethod java/util/Map.remove:(Ljava/lang/Object;)Ljava/lang/Object;
      17: pop
      18: aload_0
      19: invokespecial #11                 // Method cleanup:()V
      22: return

  public int size();
    Code:
       0: aload_0
       1: invokespecial #11                 // Method cleanup:()V
       4: aload_0
       5: getfield      #5                  // Field map:Ljava/util/Map;
       8: invokeinterface #17,  1           // InterfaceMethod java/util/Map.size:()I
      13: ireturn

  private void cleanup();
    Code:
       0: aload_0
       1: getfield      #1                  // Field queue:Ljava/lang/ref/ReferenceQueue;
       4: invokevirtual #18                 // Method java/lang/ref/ReferenceQueue.poll:()Ljava/lang/ref/Reference;
       7: checkcast     #8                  // class com/thoughtworks/xstream/core/util/ObjectIdDictionary$WeakIdWrapper
      10: dup
      11: astore_1
      12: ifnull        29
      15: aload_0
      16: getfield      #5                  // Field map:Ljava/util/Map;
      19: aload_1
      20: invokeinterface #16,  2           // InterfaceMethod java/util/Map.remove:(Ljava/lang/Object;)Ljava/lang/Object;
      25: pop
      26: goto          0
      29: return

  static java.lang.ref.ReferenceQueue access$000(com.thoughtworks.xstream.core.util.ObjectIdDictionary);
    Code:
       0: aload_0
       1: getfield      #1                  // Field queue:Ljava/lang/ref/ReferenceQueue;
       4: areturn
}
