Compiled from "ObjectIdDictionary.java"
class com.thoughtworks.xstream.core.util.ObjectIdDictionary$IdWrapper implements com.thoughtworks.xstream.core.util.ObjectIdDictionary$Wrapper {
  private final java.lang.Object obj;

  private final int hashCode;

  public com.thoughtworks.xstream.core.util.ObjectIdDictionary$IdWrapper(java.lang.Object);
    Code:
       0: aload_0
       1: invokespecial #1                  // Method java/lang/Object."<init>":()V
       4: aload_0
       5: aload_1
       6: invokestatic  #2                  // Method java/lang/System.identityHashCode:(Ljava/lang/Object;)I
       9: putfield      #3                  // Field hashCode:I
      12: aload_0
      13: aload_1
      14: putfield      #4                  // Field obj:Ljava/lang/Object;
      17: return

  public int hashCode();
    Code:
       0: aload_0
       1: getfield      #3                  // Field hashCode:I
       4: ireturn

  public boolean equals(java.lang.Object);
    Code:
       0: aload_0
       1: getfield      #4                  // Field obj:Ljava/lang/Object;
       4: aload_1
       5: checkcast     #5                  // class com/thoughtworks/xstream/core/util/ObjectIdDictionary$Wrapper
       8: invokeinterface #6,  1            // InterfaceMethod com/thoughtworks/xstream/core/util/ObjectIdDictionary$Wrapper.get:()Ljava/lang/Object;
      13: if_acmpne     20
      16: iconst_1
      17: goto          21
      20: iconst_0
      21: ireturn

  public java.lang.String toString();
    Code:
       0: aload_0
       1: getfield      #4                  // Field obj:Ljava/lang/Object;
       4: invokevirtual #7                  // Method java/lang/Object.toString:()Ljava/lang/String;
       7: areturn

  public java.lang.Object get();
    Code:
       0: aload_0
       1: getfield      #4                  // Field obj:Ljava/lang/Object;
       4: areturn
}
