Compiled from "Primitives.java"
public final class com.thoughtworks.xstream.core.util.Primitives {
  private static final java.util.Map BOX;

  private static final java.util.Map UNBOX;

  private static final java.util.Map NAMED_PRIMITIVE;

  private static final java.util.Map REPRESENTING_CHAR;

  public com.thoughtworks.xstream.core.util.Primitives();
    Code:
       0: aload_0
       1: invokespecial #1                  // Method java/lang/Object."<init>":()V
       4: return

  public static java.lang.Class box(java.lang.Class);
    Code:
       0: getstatic     #2                  // Field BOX:Ljava/util/Map;
       3: aload_0
       4: invokeinterface #3,  2            // InterfaceMethod java/util/Map.get:(Ljava/lang/Object;)Ljava/lang/Object;
       9: checkcast     #4                  // class java/lang/Class
      12: areturn

  public static java.lang.Class unbox(java.lang.Class);
    Code:
       0: getstatic     #5                  // Field UNBOX:Ljava/util/Map;
       3: aload_0
       4: invokeinterface #3,  2            // InterfaceMethod java/util/Map.get:(Ljava/lang/Object;)Ljava/lang/Object;
       9: checkcast     #4                  // class java/lang/Class
      12: areturn

  public static boolean isBoxed(java.lang.Class);
    Code:
       0: getstatic     #5                  // Field UNBOX:Ljava/util/Map;
       3: aload_0
       4: invokeinterface #6,  2            // InterfaceMethod java/util/Map.containsKey:(Ljava/lang/Object;)Z
       9: ireturn

  public static java.lang.Class primitiveType(java.lang.String);
    Code:
       0: getstatic     #7                  // Field NAMED_PRIMITIVE:Ljava/util/Map;
       3: aload_0
       4: invokeinterface #3,  2            // InterfaceMethod java/util/Map.get:(Ljava/lang/Object;)Ljava/lang/Object;
       9: checkcast     #4                  // class java/lang/Class
      12: areturn

  public static char representingChar(java.lang.Class);
    Code:
       0: getstatic     #8                  // Field REPRESENTING_CHAR:Ljava/util/Map;
       3: aload_0
       4: invokeinterface #3,  2            // InterfaceMethod java/util/Map.get:(Ljava/lang/Object;)Ljava/lang/Object;
       9: checkcast     #9                  // class java/lang/Character
      12: astore_1
      13: aload_1
      14: ifnonnull     21
      17: iconst_0
      18: goto          25
      21: aload_1
      22: invokevirtual #10                 // Method java/lang/Character.charValue:()C
      25: ireturn

  static {};
    Code:
       0: new           #11                 // class java/util/HashMap
       3: dup
       4: invokespecial #12                 // Method java/util/HashMap."<init>":()V
       7: putstatic     #2                  // Field BOX:Ljava/util/Map;
      10: new           #11                 // class java/util/HashMap
      13: dup
      14: invokespecial #12                 // Method java/util/HashMap."<init>":()V
      17: putstatic     #5                  // Field UNBOX:Ljava/util/Map;
      20: new           #11                 // class java/util/HashMap
      23: dup
      24: invokespecial #12                 // Method java/util/HashMap."<init>":()V
      27: putstatic     #7                  // Field NAMED_PRIMITIVE:Ljava/util/Map;
      30: new           #11                 // class java/util/HashMap
      33: dup
      34: invokespecial #12                 // Method java/util/HashMap."<init>":()V
      37: putstatic     #8                  // Field REPRESENTING_CHAR:Ljava/util/Map;
      40: bipush        9
      42: anewarray     #13                 // class "[Ljava/lang/Class;"
      45: dup
      46: iconst_0
      47: iconst_2
      48: anewarray     #4                  // class java/lang/Class
      51: dup
      52: iconst_0
      53: getstatic     #14                 // Field java/lang/Byte.TYPE:Ljava/lang/Class;
      56: aastore
      57: dup
      58: iconst_1
      59: ldc_w         #15                 // class java/lang/Byte
      62: aastore
      63: aastore
      64: dup
      65: iconst_1
      66: iconst_2
      67: anewarray     #4                  // class java/lang/Class
      70: dup
      71: iconst_0
      72: getstatic     #16                 // Field java/lang/Character.TYPE:Ljava/lang/Class;
      75: aastore
      76: dup
      77: iconst_1
      78: ldc_w         #9                  // class java/lang/Character
      81: aastore
      82: aastore
      83: dup
      84: iconst_2
      85: iconst_2
      86: anewarray     #4                  // class java/lang/Class
      89: dup
      90: iconst_0
      91: getstatic     #17                 // Field java/lang/Short.TYPE:Ljava/lang/Class;
      94: aastore
      95: dup
      96: iconst_1
      97: ldc_w         #18                 // class java/lang/Short
     100: aastore
     101: aastore
     102: dup
     103: iconst_3
     104: iconst_2
     105: anewarray     #4                  // class java/lang/Class
     108: dup
     109: iconst_0
     110: getstatic     #19                 // Field java/lang/Integer.TYPE:Ljava/lang/Class;
     113: aastore
     114: dup
     115: iconst_1
     116: ldc_w         #20                 // class java/lang/Integer
     119: aastore
     120: aastore
     121: dup
     122: iconst_4
     123: iconst_2
     124: anewarray     #4                  // class java/lang/Class
     127: dup
     128: iconst_0
     129: getstatic     #21                 // Field java/lang/Long.TYPE:Ljava/lang/Class;
     132: aastore
     133: dup
     134: iconst_1
     135: ldc_w         #22                 // class java/lang/Long
     138: aastore
     139: aastore
     140: dup
     141: iconst_5
     142: iconst_2
     143: anewarray     #4                  // class java/lang/Class
     146: dup
     147: iconst_0
     148: getstatic     #23                 // Field java/lang/Float.TYPE:Ljava/lang/Class;
     151: aastore
     152: dup
     153: iconst_1
     154: ldc_w         #24                 // class java/lang/Float
     157: aastore
     158: aastore
     159: dup
     160: bipush        6
     162: iconst_2
     163: anewarray     #4                  // class java/lang/Class
     166: dup
     167: iconst_0
     168: getstatic     #25                 // Field java/lang/Double.TYPE:Ljava/lang/Class;
     171: aastore
     172: dup
     173: iconst_1
     174: ldc_w         #26                 // class java/lang/Double
     177: aastore
     178: aastore
     179: dup
     180: bipush        7
     182: iconst_2
     183: anewarray     #4                  // class java/lang/Class
     186: dup
     187: iconst_0
     188: getstatic     #27                 // Field java/lang/Boolean.TYPE:Ljava/lang/Class;
     191: aastore
     192: dup
     193: iconst_1
     194: ldc_w         #28                 // class java/lang/Boolean
     197: aastore
     198: aastore
     199: dup
     200: bipush        8
     202: iconst_2
     203: anewarray     #4                  // class java/lang/Class
     206: dup
     207: iconst_0
     208: getstatic     #29                 // Field java/lang/Void.TYPE:Ljava/lang/Class;
     211: aastore
     212: dup
     213: iconst_1
     214: ldc_w         #30                 // class java/lang/Void
     217: aastore
     218: aastore
     219: astore_0
     220: bipush        9
     222: anewarray     #9                  // class java/lang/Character
     225: dup
     226: iconst_0
     227: new           #9                  // class java/lang/Character
     230: dup
     231: bipush        66
     233: invokespecial #31                 // Method java/lang/Character."<init>":(C)V
     236: aastore
     237: dup
     238: iconst_1
     239: new           #9                  // class java/lang/Character
     242: dup
     243: bipush        67
     245: invokespecial #31                 // Method java/lang/Character."<init>":(C)V
     248: aastore
     249: dup
     250: iconst_2
     251: new           #9                  // class java/lang/Character
     254: dup
     255: bipush        83
     257: invokespecial #31                 // Method java/lang/Character."<init>":(C)V
     260: aastore
     261: dup
     262: iconst_3
     263: new           #9                  // class java/lang/Character
     266: dup
     267: bipush        73
     269: invokespecial #31                 // Method java/lang/Character."<init>":(C)V
     272: aastore
     273: dup
     274: iconst_4
     275: new           #9                  // class java/lang/Character
     278: dup
     279: bipush        74
     281: invokespecial #31                 // Method java/lang/Character."<init>":(C)V
     284: aastore
     285: dup
     286: iconst_5
     287: new           #9                  // class java/lang/Character
     290: dup
     291: bipush        70
     293: invokespecial #31                 // Method java/lang/Character."<init>":(C)V
     296: aastore
     297: dup
     298: bipush        6
     300: new           #9                  // class java/lang/Character
     303: dup
     304: bipush        68
     306: invokespecial #31                 // Method java/lang/Character."<init>":(C)V
     309: aastore
     310: dup
     311: bipush        7
     313: new           #9                  // class java/lang/Character
     316: dup
     317: bipush        90
     319: invokespecial #31                 // Method java/lang/Character."<init>":(C)V
     322: aastore
     323: dup
     324: bipush        8
     326: aconst_null
     327: aastore
     328: astore_1
     329: iconst_0
     330: istore_2
     331: iload_2
     332: aload_0
     333: arraylength
     334: if_icmpge     407
     337: aload_0
     338: iload_2
     339: aaload
     340: iconst_0
     341: aaload
     342: astore_3
     343: aload_0
     344: iload_2
     345: aaload
     346: iconst_1
     347: aaload
     348: astore        4
     350: getstatic     #2                  // Field BOX:Ljava/util/Map;
     353: aload_3
     354: aload         4
     356: invokeinterface #32,  3           // InterfaceMethod java/util/Map.put:(Ljava/lang/Object;Ljava/lang/Object;)Ljava/lang/Object;
     361: pop
     362: getstatic     #5                  // Field UNBOX:Ljava/util/Map;
     365: aload         4
     367: aload_3
     368: invokeinterface #32,  3           // InterfaceMethod java/util/Map.put:(Ljava/lang/Object;Ljava/lang/Object;)Ljava/lang/Object;
     373: pop
     374: getstatic     #7                  // Field NAMED_PRIMITIVE:Ljava/util/Map;
     377: aload_3
     378: invokevirtual #33                 // Method java/lang/Class.getName:()Ljava/lang/String;
     381: aload_3
     382: invokeinterface #32,  3           // InterfaceMethod java/util/Map.put:(Ljava/lang/Object;Ljava/lang/Object;)Ljava/lang/Object;
     387: pop
     388: getstatic     #8                  // Field REPRESENTING_CHAR:Ljava/util/Map;
     391: aload_3
     392: aload_1
     393: iload_2
     394: aaload
     395: invokeinterface #32,  3           // InterfaceMethod java/util/Map.put:(Ljava/lang/Object;Ljava/lang/Object;)Ljava/lang/Object;
     400: pop
     401: iinc          2, 1
     404: goto          331
     407: return
}
