Compiled from "MultiPartItem.scala"
public final class org.sisioh.trinity.domain.fileupload.MultiPartItem$$anonfun$fromRequest$1 extends scala.runtime.AbstractFunction1<org.jboss.netty.handler.codec.http.multipart.InterfaceHttpData, scala.Tuple2<java.lang.String, org.sisioh.trinity.domain.fileupload.MultiPartItem>> implements scala.Serializable {
  public static final long serialVersionUID;

  public final scala.Tuple2<java.lang.String, org.sisioh.trinity.domain.fileupload.MultiPartItem> apply(org.jboss.netty.handler.codec.http.multipart.InterfaceHttpData);
    Code:
       0: getstatic     #25                 // Field scala/Predef$ArrowAssoc$.MODULE$:Lscala/Predef$ArrowAssoc$;
       3: getstatic     #30                 // Field scala/Predef$.MODULE$:Lscala/Predef$;
       6: aload_1
       7: invokeinterface #36,  1           // InterfaceMethod org/jboss/netty/handler/codec/http/multipart/InterfaceHttpData.getName:()Ljava/lang/String;
      12: invokevirtual #40                 // Method scala/Predef$.any2ArrowAssoc:(Ljava/lang/Object;)Ljava/lang/Object;
      15: new           #42                 // class org/sisioh/trinity/domain/fileupload/MultiPartItem
      18: dup
      19: aload_1
      20: checkcast     #44                 // class org/jboss/netty/handler/codec/http/multipart/MixedFileUpload
      23: getstatic     #47                 // Field org/sisioh/trinity/domain/fileupload/MultiPartItem$.MODULE$:Lorg/sisioh/trinity/domain/fileupload/MultiPartItem$;
      26: invokevirtual #51                 // Method org/sisioh/trinity/domain/fileupload/MultiPartItem$.apply$default$2:()I
      29: invokespecial #55                 // Method org/sisioh/trinity/domain/fileupload/MultiPartItem."<init>":(Lorg/jboss/netty/handler/codec/http/multipart/MixedFileUpload;I)V
      32: invokevirtual #59                 // Method scala/Predef$ArrowAssoc$.$minus$greater$extension:(Ljava/lang/Object;Ljava/lang/Object;)Lscala/Tuple2;
      35: areturn

  public final java.lang.Object apply(java.lang.Object);
    Code:
       0: aload_0
       1: aload_1
       2: checkcast     #32                 // class org/jboss/netty/handler/codec/http/multipart/InterfaceHttpData
       5: invokevirtual #65                 // Method apply:(Lorg/jboss/netty/handler/codec/http/multipart/InterfaceHttpData;)Lscala/Tuple2;
       8: areturn

  public org.sisioh.trinity.domain.fileupload.MultiPartItem$$anonfun$fromRequest$1();
    Code:
       0: aload_0
       1: invokespecial #70                 // Method scala/runtime/AbstractFunction1."<init>":()V
       4: return
}
