Compiled from "ServerWebSocketContainer.java"
final class io.undertow.websockets.jsr.ServerWebSocketContainer$WebSocketHandshakeHolder {
  final java.util.List<io.undertow.websockets.core.protocol.Handshake> handshakes;

  final io.undertow.websockets.jsr.ConfiguredServerEndpoint endpoint;

  private io.undertow.websockets.jsr.ServerWebSocketContainer$WebSocketHandshakeHolder(java.util.List<io.undertow.websockets.core.protocol.Handshake>, io.undertow.websockets.jsr.ConfiguredServerEndpoint);
    Code:
       0: aload_0
       1: invokespecial #2                  // Method java/lang/Object."<init>":()V
       4: aload_0
       5: aload_1
       6: putfield      #3                  // Field handshakes:Ljava/util/List;
       9: aload_0
      10: aload_2
      11: putfield      #4                  // Field endpoint:Lio/undertow/websockets/jsr/ConfiguredServerEndpoint;
      14: return

  io.undertow.websockets.jsr.ServerWebSocketContainer$WebSocketHandshakeHolder(java.util.List, io.undertow.websockets.jsr.ConfiguredServerEndpoint, io.undertow.websockets.jsr.ServerWebSocketContainer$1);
    Code:
       0: aload_0
       1: aload_1
       2: aload_2
       3: invokespecial #1                  // Method "<init>":(Ljava/util/List;Lio/undertow/websockets/jsr/ConfiguredServerEndpoint;)V
       6: return
}
