Compiled from "PostfixExpressionTree.java"
public class com.google.javascript.jscomp.parsing.parser.trees.PostfixExpressionTree extends com.google.javascript.jscomp.parsing.parser.trees.ParseTree {
  public final com.google.javascript.jscomp.parsing.parser.trees.ParseTree operand;

  public final com.google.javascript.jscomp.parsing.parser.Token operator;

  public com.google.javascript.jscomp.parsing.parser.trees.PostfixExpressionTree(com.google.javascript.jscomp.parsing.parser.util.SourceRange, com.google.javascript.jscomp.parsing.parser.trees.ParseTree, com.google.javascript.jscomp.parsing.parser.Token);
    Code:
       0: aload_0
       1: getstatic     #1                  // Field com/google/javascript/jscomp/parsing/parser/trees/ParseTreeType.POSTFIX_EXPRESSION:Lcom/google/javascript/jscomp/parsing/parser/trees/ParseTreeType;
       4: aload_1
       5: invokespecial #2                  // Method com/google/javascript/jscomp/parsing/parser/trees/ParseTree."<init>":(Lcom/google/javascript/jscomp/parsing/parser/trees/ParseTreeType;Lcom/google/javascript/jscomp/parsing/parser/util/SourceRange;)V
       8: aload_0
       9: aload_2
      10: putfield      #3                  // Field operand:Lcom/google/javascript/jscomp/parsing/parser/trees/ParseTree;
      13: aload_0
      14: aload_3
      15: putfield      #4                  // Field operator:Lcom/google/javascript/jscomp/parsing/parser/Token;
      18: return
}
