Compiled from "BusWiringType.java"
public final class org.apache.cxf.configuration.spring.BusWiringType extends java.lang.Enum<org.apache.cxf.configuration.spring.BusWiringType> {
  public static final org.apache.cxf.configuration.spring.BusWiringType PROPERTY;

  public static final org.apache.cxf.configuration.spring.BusWiringType CONSTRUCTOR;

  private static final org.apache.cxf.configuration.spring.BusWiringType[] $VALUES;

  public static org.apache.cxf.configuration.spring.BusWiringType[] values();
    Code:
       0: getstatic     #1                  // Field $VALUES:[Lorg/apache/cxf/configuration/spring/BusWiringType;
       3: invokevirtual #2                  // Method "[Lorg/apache/cxf/configuration/spring/BusWiringType;".clone:()Ljava/lang/Object;
       6: checkcast     #3                  // class "[Lorg/apache/cxf/configuration/spring/BusWiringType;"
       9: areturn

  public static org.apache.cxf.configuration.spring.BusWiringType valueOf(java.lang.String);
    Code:
       0: ldc_w         #4                  // class org/apache/cxf/configuration/spring/BusWiringType
       3: aload_0
       4: invokestatic  #5                  // Method java/lang/Enum.valueOf:(Ljava/lang/Class;Ljava/lang/String;)Ljava/lang/Enum;
       7: checkcast     #4                  // class org/apache/cxf/configuration/spring/BusWiringType
      10: areturn

  private org.apache.cxf.configuration.spring.BusWiringType();
    Code:
       0: aload_0
       1: aload_1
       2: iload_2
       3: invokespecial #6                  // Method java/lang/Enum."<init>":(Ljava/lang/String;I)V
       6: return

  static {};
    Code:
       0: new           #4                  // class org/apache/cxf/configuration/spring/BusWiringType
       3: dup
       4: ldc           #7                  // String PROPERTY
       6: iconst_0
       7: invokespecial #8                  // Method "<init>":(Ljava/lang/String;I)V
      10: putstatic     #9                  // Field PROPERTY:Lorg/apache/cxf/configuration/spring/BusWiringType;
      13: new           #4                  // class org/apache/cxf/configuration/spring/BusWiringType
      16: dup
      17: ldc           #10                 // String CONSTRUCTOR
      19: iconst_1
      20: invokespecial #8                  // Method "<init>":(Ljava/lang/String;I)V
      23: putstatic     #11                 // Field CONSTRUCTOR:Lorg/apache/cxf/configuration/spring/BusWiringType;
      26: iconst_2
      27: anewarray     #4                  // class org/apache/cxf/configuration/spring/BusWiringType
      30: dup
      31: iconst_0
      32: getstatic     #9                  // Field PROPERTY:Lorg/apache/cxf/configuration/spring/BusWiringType;
      35: aastore
      36: dup
      37: iconst_1
      38: getstatic     #11                 // Field CONSTRUCTOR:Lorg/apache/cxf/configuration/spring/BusWiringType;
      41: aastore
      42: putstatic     #1                  // Field $VALUES:[Lorg/apache/cxf/configuration/spring/BusWiringType;
      45: return
}
