Compiled from "ConcurrentPool.java"
public final class com.mongodb.internal.connection.ConcurrentPool$Prune extends java.lang.Enum<com.mongodb.internal.connection.ConcurrentPool$Prune> {
  public static final com.mongodb.internal.connection.ConcurrentPool$Prune YES;

  public static final com.mongodb.internal.connection.ConcurrentPool$Prune NO;

  public static final com.mongodb.internal.connection.ConcurrentPool$Prune STOP;

  private static final com.mongodb.internal.connection.ConcurrentPool$Prune[] $VALUES;

  public static com.mongodb.internal.connection.ConcurrentPool$Prune[] values();
    Code:
       0: getstatic     #1                  // Field $VALUES:[Lcom/mongodb/internal/connection/ConcurrentPool$Prune;
       3: invokevirtual #2                  // Method "[Lcom/mongodb/internal/connection/ConcurrentPool$Prune;".clone:()Ljava/lang/Object;
       6: checkcast     #3                  // class "[Lcom/mongodb/internal/connection/ConcurrentPool$Prune;"
       9: areturn

  public static com.mongodb.internal.connection.ConcurrentPool$Prune valueOf(java.lang.String);
    Code:
       0: ldc           #4                  // class com/mongodb/internal/connection/ConcurrentPool$Prune
       2: aload_0
       3: invokestatic  #5                  // Method java/lang/Enum.valueOf:(Ljava/lang/Class;Ljava/lang/String;)Ljava/lang/Enum;
       6: checkcast     #4                  // class com/mongodb/internal/connection/ConcurrentPool$Prune
       9: areturn

  private com.mongodb.internal.connection.ConcurrentPool$Prune();
    Code:
       0: aload_0
       1: aload_1
       2: iload_2
       3: invokespecial #6                  // Method java/lang/Enum."<init>":(Ljava/lang/String;I)V
       6: return

  static {};
    Code:
       0: new           #4                  // class com/mongodb/internal/connection/ConcurrentPool$Prune
       3: dup
       4: ldc           #7                  // String YES
       6: iconst_0
       7: invokespecial #8                  // Method "<init>":(Ljava/lang/String;I)V
      10: putstatic     #9                  // Field YES:Lcom/mongodb/internal/connection/ConcurrentPool$Prune;
      13: new           #4                  // class com/mongodb/internal/connection/ConcurrentPool$Prune
      16: dup
      17: ldc           #10                 // String NO
      19: iconst_1
      20: invokespecial #8                  // Method "<init>":(Ljava/lang/String;I)V
      23: putstatic     #11                 // Field NO:Lcom/mongodb/internal/connection/ConcurrentPool$Prune;
      26: new           #4                  // class com/mongodb/internal/connection/ConcurrentPool$Prune
      29: dup
      30: ldc           #12                 // String STOP
      32: iconst_2
      33: invokespecial #8                  // Method "<init>":(Ljava/lang/String;I)V
      36: putstatic     #13                 // Field STOP:Lcom/mongodb/internal/connection/ConcurrentPool$Prune;
      39: iconst_3
      40: anewarray     #4                  // class com/mongodb/internal/connection/ConcurrentPool$Prune
      43: dup
      44: iconst_0
      45: getstatic     #9                  // Field YES:Lcom/mongodb/internal/connection/ConcurrentPool$Prune;
      48: aastore
      49: dup
      50: iconst_1
      51: getstatic     #11                 // Field NO:Lcom/mongodb/internal/connection/ConcurrentPool$Prune;
      54: aastore
      55: dup
      56: iconst_2
      57: getstatic     #13                 // Field STOP:Lcom/mongodb/internal/connection/ConcurrentPool$Prune;
      60: aastore
      61: putstatic     #1                  // Field $VALUES:[Lcom/mongodb/internal/connection/ConcurrentPool$Prune;
      64: return
}
