Compiled from "ForwardingELResolver.java"
public abstract class org.jboss.as.jsf.injection.weld.ForwardingELResolver extends javax.el.ELResolver {
  public org.jboss.as.jsf.injection.weld.ForwardingELResolver();
    Code:
       0: aload_0
       1: invokespecial #1                  // Method javax/el/ELResolver."<init>":()V
       4: return

  protected abstract javax.el.ELResolver delegate();

  public java.lang.Class<?> getCommonPropertyType(javax.el.ELContext, java.lang.Object);
    Code:
       0: aload_0
       1: invokevirtual #2                  // Method delegate:()Ljavax/el/ELResolver;
       4: aload_1
       5: aload_2
       6: invokevirtual #3                  // Method javax/el/ELResolver.getCommonPropertyType:(Ljavax/el/ELContext;Ljava/lang/Object;)Ljava/lang/Class;
       9: areturn

  public java.util.Iterator<java.beans.FeatureDescriptor> getFeatureDescriptors(javax.el.ELContext, java.lang.Object);
    Code:
       0: aload_0
       1: invokevirtual #2                  // Method delegate:()Ljavax/el/ELResolver;
       4: aload_1
       5: aload_2
       6: invokevirtual #4                  // Method javax/el/ELResolver.getFeatureDescriptors:(Ljavax/el/ELContext;Ljava/lang/Object;)Ljava/util/Iterator;
       9: areturn

  public java.lang.Class<?> getType(javax.el.ELContext, java.lang.Object, java.lang.Object);
    Code:
       0: aload_0
       1: invokevirtual #2                  // Method delegate:()Ljavax/el/ELResolver;
       4: aload_1
       5: aload_2
       6: aload_3
       7: invokevirtual #5                  // Method javax/el/ELResolver.getType:(Ljavax/el/ELContext;Ljava/lang/Object;Ljava/lang/Object;)Ljava/lang/Class;
      10: areturn

  public java.lang.Object getValue(javax.el.ELContext, java.lang.Object, java.lang.Object);
    Code:
       0: aload_0
       1: invokevirtual #2                  // Method delegate:()Ljavax/el/ELResolver;
       4: aload_1
       5: aload_2
       6: aload_3
       7: invokevirtual #6                  // Method javax/el/ELResolver.getValue:(Ljavax/el/ELContext;Ljava/lang/Object;Ljava/lang/Object;)Ljava/lang/Object;
      10: areturn

  public boolean isReadOnly(javax.el.ELContext, java.lang.Object, java.lang.Object);
    Code:
       0: aload_0
       1: invokevirtual #2                  // Method delegate:()Ljavax/el/ELResolver;
       4: aload_1
       5: aload_2
       6: aload_3
       7: invokevirtual #7                  // Method javax/el/ELResolver.isReadOnly:(Ljavax/el/ELContext;Ljava/lang/Object;Ljava/lang/Object;)Z
      10: ireturn

  public void setValue(javax.el.ELContext, java.lang.Object, java.lang.Object, java.lang.Object);
    Code:
       0: aload_0
       1: invokevirtual #2                  // Method delegate:()Ljavax/el/ELResolver;
       4: aload_1
       5: aload_2
       6: aload_3
       7: aload         4
       9: invokevirtual #8                  // Method javax/el/ELResolver.setValue:(Ljavax/el/ELContext;Ljava/lang/Object;Ljava/lang/Object;Ljava/lang/Object;)V
      12: return

  public boolean equals(java.lang.Object);
    Code:
       0: aload_0
       1: aload_1
       2: if_acmpeq     16
       5: aload_0
       6: invokevirtual #2                  // Method delegate:()Ljavax/el/ELResolver;
       9: aload_1
      10: invokevirtual #9                  // Method java/lang/Object.equals:(Ljava/lang/Object;)Z
      13: ifeq          20
      16: iconst_1
      17: goto          21
      20: iconst_0
      21: ireturn

  public int hashCode();
    Code:
       0: aload_0
       1: invokevirtual #2                  // Method delegate:()Ljavax/el/ELResolver;
       4: invokevirtual #10                 // Method java/lang/Object.hashCode:()I
       7: ireturn

  public java.lang.String toString();
    Code:
       0: aload_0
       1: invokevirtual #2                  // Method delegate:()Ljavax/el/ELResolver;
       4: invokevirtual #11                 // Method java/lang/Object.toString:()Ljava/lang/String;
       7: areturn
}
