Compiled from "DaemonExecutors.java"
public class com.cloudhopper.smpp.util.DaemonExecutors {
  public com.cloudhopper.smpp.util.DaemonExecutors();
    Code:
       0: aload_0
       1: invokespecial #1                  // Method java/lang/Object."<init>":()V
       4: return

  public static java.util.concurrent.ExecutorService newCachedDaemonThreadPool();
    Code:
       0: new           #2                  // class com/cloudhopper/smpp/util/DaemonExecutors$1
       3: dup
       4: invokespecial #3                  // Method com/cloudhopper/smpp/util/DaemonExecutors$1."<init>":()V
       7: invokestatic  #4                  // Method java/util/concurrent/Executors.newCachedThreadPool:(Ljava/util/concurrent/ThreadFactory;)Ljava/util/concurrent/ExecutorService;
      10: areturn
}
