Compiled from "MutableTriple.java"
public class org.apache.commons.lang3.tuple.MutableTriple<L, M, R> extends org.apache.commons.lang3.tuple.Triple<L, M, R> {
  public static final org.apache.commons.lang3.tuple.MutableTriple<?, ?, ?>[] EMPTY_ARRAY;

  private static final long serialVersionUID;

  public L left;

  public M middle;

  public R right;

  public static <L, M, R> org.apache.commons.lang3.tuple.MutableTriple<L, M, R>[] emptyArray();
    Code:
       0: getstatic     #1                  // Field EMPTY_ARRAY:[Lorg/apache/commons/lang3/tuple/MutableTriple;
       3: checkcast     #2                  // class "[Lorg/apache/commons/lang3/tuple/MutableTriple;"
       6: areturn

  public static <L, M, R> org.apache.commons.lang3.tuple.MutableTriple<L, M, R> of(L, M, R);
    Code:
       0: new           #3                  // class org/apache/commons/lang3/tuple/MutableTriple
       3: dup
       4: aload_0
       5: aload_1
       6: aload_2
       7: invokespecial #4                  // Method "<init>":(Ljava/lang/Object;Ljava/lang/Object;Ljava/lang/Object;)V
      10: areturn

  public org.apache.commons.lang3.tuple.MutableTriple();
    Code:
       0: aload_0
       1: invokespecial #5                  // Method org/apache/commons/lang3/tuple/Triple."<init>":()V
       4: return

  public org.apache.commons.lang3.tuple.MutableTriple(L, M, R);
    Code:
       0: aload_0
       1: invokespecial #5                  // Method org/apache/commons/lang3/tuple/Triple."<init>":()V
       4: aload_0
       5: aload_1
       6: putfield      #6                  // Field left:Ljava/lang/Object;
       9: aload_0
      10: aload_2
      11: putfield      #7                  // Field middle:Ljava/lang/Object;
      14: aload_0
      15: aload_3
      16: putfield      #8                  // Field right:Ljava/lang/Object;
      19: return

  public L getLeft();
    Code:
       0: aload_0
       1: getfield      #6                  // Field left:Ljava/lang/Object;
       4: areturn

  public M getMiddle();
    Code:
       0: aload_0
       1: getfield      #7                  // Field middle:Ljava/lang/Object;
       4: areturn

  public R getRight();
    Code:
       0: aload_0
       1: getfield      #8                  // Field right:Ljava/lang/Object;
       4: areturn

  public void setLeft(L);
    Code:
       0: aload_0
       1: aload_1
       2: putfield      #6                  // Field left:Ljava/lang/Object;
       5: return

  public void setMiddle(M);
    Code:
       0: aload_0
       1: aload_1
       2: putfield      #7                  // Field middle:Ljava/lang/Object;
       5: return

  public void setRight(R);
    Code:
       0: aload_0
       1: aload_1
       2: putfield      #8                  // Field right:Ljava/lang/Object;
       5: return

  static {};
    Code:
       0: iconst_0
       1: anewarray     #3                  // class org/apache/commons/lang3/tuple/MutableTriple
       4: putstatic     #1                  // Field EMPTY_ARRAY:[Lorg/apache/commons/lang3/tuple/MutableTriple;
       7: return
}
