Compiled from "AltsHandshakerStub.java"
class io.grpc.alts.internal.AltsHandshakerStub {
  private final io.grpc.stub.StreamObserver<io.grpc.alts.internal.HandshakerResp> reader;

  private io.grpc.stub.StreamObserver<io.grpc.alts.internal.HandshakerReq> writer;

  private final io.grpc.alts.internal.HandshakerServiceGrpc$HandshakerServiceStub serviceStub;

  private final java.util.concurrent.ArrayBlockingQueue<com.google.common.base.Optional<io.grpc.alts.internal.HandshakerResp>> responseQueue;

  private final java.util.concurrent.atomic.AtomicReference<java.lang.String> exceptionMessage;

  private static final long HANDSHAKE_RPC_DEADLINE_SECS;

  io.grpc.alts.internal.AltsHandshakerStub(io.grpc.alts.internal.HandshakerServiceGrpc$HandshakerServiceStub);
    Code:
       0: aload_0
       1: invokespecial #37                 // Method java/lang/Object."<init>":()V
       4: aload_0
       5: new           #9                  // class io/grpc/alts/internal/AltsHandshakerStub$Reader
       8: dup
       9: aload_0
      10: aconst_null
      11: invokespecial #40                 // Method io/grpc/alts/internal/AltsHandshakerStub$Reader."<init>":(Lio/grpc/alts/internal/AltsHandshakerStub;Lio/grpc/alts/internal/AltsHandshakerStub$1;)V
      14: putfield      #42                 // Field reader:Lio/grpc/stub/StreamObserver;
      17: aload_0
      18: new           #44                 // class java/util/concurrent/ArrayBlockingQueue
      21: dup
      22: iconst_1
      23: invokespecial #47                 // Method java/util/concurrent/ArrayBlockingQueue."<init>":(I)V
      26: putfield      #49                 // Field responseQueue:Ljava/util/concurrent/ArrayBlockingQueue;
      29: aload_0
      30: new           #51                 // class java/util/concurrent/atomic/AtomicReference
      33: dup
      34: invokespecial #52                 // Method java/util/concurrent/atomic/AtomicReference."<init>":()V
      37: putfield      #54                 // Field exceptionMessage:Ljava/util/concurrent/atomic/AtomicReference;
      40: aload_0
      41: aload_1
      42: putfield      #56                 // Field serviceStub:Lio/grpc/alts/internal/HandshakerServiceGrpc$HandshakerServiceStub;
      45: return

  io.grpc.alts.internal.AltsHandshakerStub();
    Code:
       0: aload_0
       1: invokespecial #37                 // Method java/lang/Object."<init>":()V
       4: aload_0
       5: new           #9                  // class io/grpc/alts/internal/AltsHandshakerStub$Reader
       8: dup
       9: aload_0
      10: aconst_null
      11: invokespecial #40                 // Method io/grpc/alts/internal/AltsHandshakerStub$Reader."<init>":(Lio/grpc/alts/internal/AltsHandshakerStub;Lio/grpc/alts/internal/AltsHandshakerStub$1;)V
      14: putfield      #42                 // Field reader:Lio/grpc/stub/StreamObserver;
      17: aload_0
      18: new           #44                 // class java/util/concurrent/ArrayBlockingQueue
      21: dup
      22: iconst_1
      23: invokespecial #47                 // Method java/util/concurrent/ArrayBlockingQueue."<init>":(I)V
      26: putfield      #49                 // Field responseQueue:Ljava/util/concurrent/ArrayBlockingQueue;
      29: aload_0
      30: new           #51                 // class java/util/concurrent/atomic/AtomicReference
      33: dup
      34: invokespecial #52                 // Method java/util/concurrent/atomic/AtomicReference."<init>":()V
      37: putfield      #54                 // Field exceptionMessage:Ljava/util/concurrent/atomic/AtomicReference;
      40: aload_0
      41: aconst_null
      42: putfield      #56                 // Field serviceStub:Lio/grpc/alts/internal/HandshakerServiceGrpc$HandshakerServiceStub;
      45: return

  io.grpc.alts.internal.AltsHandshakerStub(io.grpc.stub.StreamObserver<io.grpc.alts.internal.HandshakerReq>);
    Code:
       0: aload_0
       1: invokespecial #37                 // Method java/lang/Object."<init>":()V
       4: aload_0
       5: new           #9                  // class io/grpc/alts/internal/AltsHandshakerStub$Reader
       8: dup
       9: aload_0
      10: aconst_null
      11: invokespecial #40                 // Method io/grpc/alts/internal/AltsHandshakerStub$Reader."<init>":(Lio/grpc/alts/internal/AltsHandshakerStub;Lio/grpc/alts/internal/AltsHandshakerStub$1;)V
      14: putfield      #42                 // Field reader:Lio/grpc/stub/StreamObserver;
      17: aload_0
      18: new           #44                 // class java/util/concurrent/ArrayBlockingQueue
      21: dup
      22: iconst_1
      23: invokespecial #47                 // Method java/util/concurrent/ArrayBlockingQueue."<init>":(I)V
      26: putfield      #49                 // Field responseQueue:Ljava/util/concurrent/ArrayBlockingQueue;
      29: aload_0
      30: new           #51                 // class java/util/concurrent/atomic/AtomicReference
      33: dup
      34: invokespecial #52                 // Method java/util/concurrent/atomic/AtomicReference."<init>":()V
      37: putfield      #54                 // Field exceptionMessage:Ljava/util/concurrent/atomic/AtomicReference;
      40: aload_0
      41: aload_1
      42: putfield      #63                 // Field writer:Lio/grpc/stub/StreamObserver;
      45: aload_0
      46: aconst_null
      47: putfield      #56                 // Field serviceStub:Lio/grpc/alts/internal/HandshakerServiceGrpc$HandshakerServiceStub;
      50: return

  io.grpc.stub.StreamObserver<io.grpc.alts.internal.HandshakerResp> getReaderForTest();
    Code:
       0: aload_0
       1: getfield      #42                 // Field reader:Lio/grpc/stub/StreamObserver;
       4: areturn

  public io.grpc.alts.internal.HandshakerResp send(io.grpc.alts.internal.HandshakerReq) throws java.lang.InterruptedException, java.io.IOException;
    Code:
       0: aload_0
       1: invokespecial #75                 // Method createWriterIfNull:()V
       4: aload_0
       5: invokespecial #78                 // Method maybeThrowIoException:()V
       8: aload_0
       9: getfield      #49                 // Field responseQueue:Ljava/util/concurrent/ArrayBlockingQueue;
      12: invokevirtual #82                 // Method java/util/concurrent/ArrayBlockingQueue.isEmpty:()Z
      15: ifne          28
      18: new           #72                 // class java/io/IOException
      21: dup
      22: ldc           #84                 // String Received an unexpected response.
      24: invokespecial #87                 // Method java/io/IOException."<init>":(Ljava/lang/String;)V
      27: athrow
      28: aload_0
      29: getfield      #63                 // Field writer:Lio/grpc/stub/StreamObserver;
      32: aload_1
      33: invokeinterface #93,  2           // InterfaceMethod io/grpc/stub/StreamObserver.onNext:(Ljava/lang/Object;)V
      38: aload_0
      39: getfield      #49                 // Field responseQueue:Ljava/util/concurrent/ArrayBlockingQueue;
      42: invokevirtual #97                 // Method java/util/concurrent/ArrayBlockingQueue.take:()Ljava/lang/Object;
      45: checkcast     #99                 // class com/google/common/base/Optional
      48: astore_2
      49: aload_2
      50: invokevirtual #102                // Method com/google/common/base/Optional.isPresent:()Z
      53: ifne          60
      56: aload_0
      57: invokespecial #78                 // Method maybeThrowIoException:()V
      60: aload_2
      61: invokevirtual #105                // Method com/google/common/base/Optional.get:()Ljava/lang/Object;
      64: checkcast     #107                // class io/grpc/alts/internal/HandshakerResp
      67: areturn

  private void createWriterIfNull();
    Code:
       0: aload_0
       1: getfield      #63                 // Field writer:Lio/grpc/stub/StreamObserver;
       4: ifnonnull     34
       7: aload_0
       8: aload_0
       9: getfield      #56                 // Field serviceStub:Lio/grpc/alts/internal/HandshakerServiceGrpc$HandshakerServiceStub;
      12: ldc2_w        #31                 // long 20l
      15: getstatic     #118                // Field java/util/concurrent/TimeUnit.SECONDS:Ljava/util/concurrent/TimeUnit;
      18: invokevirtual #122                // Method io/grpc/alts/internal/HandshakerServiceGrpc$HandshakerServiceStub.withDeadlineAfter:(JLjava/util/concurrent/TimeUnit;)Lio/grpc/stub/AbstractStub;
      21: checkcast     #12                 // class io/grpc/alts/internal/HandshakerServiceGrpc$HandshakerServiceStub
      24: aload_0
      25: getfield      #42                 // Field reader:Lio/grpc/stub/StreamObserver;
      28: invokevirtual #126                // Method io/grpc/alts/internal/HandshakerServiceGrpc$HandshakerServiceStub.doHandshake:(Lio/grpc/stub/StreamObserver;)Lio/grpc/stub/StreamObserver;
      31: putfield      #63                 // Field writer:Lio/grpc/stub/StreamObserver;
      34: return

  private void maybeThrowIoException() throws java.io.IOException;
    Code:
       0: aload_0
       1: getfield      #54                 // Field exceptionMessage:Ljava/util/concurrent/atomic/AtomicReference;
       4: invokevirtual #127                // Method java/util/concurrent/atomic/AtomicReference.get:()Ljava/lang/Object;
       7: ifnull        28
      10: new           #72                 // class java/io/IOException
      13: dup
      14: aload_0
      15: getfield      #54                 // Field exceptionMessage:Ljava/util/concurrent/atomic/AtomicReference;
      18: invokevirtual #127                // Method java/util/concurrent/atomic/AtomicReference.get:()Ljava/lang/Object;
      21: checkcast     #129                // class java/lang/String
      24: invokespecial #87                 // Method java/io/IOException."<init>":(Ljava/lang/String;)V
      27: athrow
      28: return

  public void close();
    Code:
       0: aload_0
       1: getfield      #63                 // Field writer:Lio/grpc/stub/StreamObserver;
       4: ifnull        16
       7: aload_0
       8: getfield      #63                 // Field writer:Lio/grpc/stub/StreamObserver;
      11: invokeinterface #133,  1          // InterfaceMethod io/grpc/stub/StreamObserver.onCompleted:()V
      16: return

  static java.util.concurrent.ArrayBlockingQueue access$100(io.grpc.alts.internal.AltsHandshakerStub);
    Code:
       0: aload_0
       1: getfield      #49                 // Field responseQueue:Ljava/util/concurrent/ArrayBlockingQueue;
       4: areturn

  static java.util.concurrent.atomic.AtomicReference access$200(io.grpc.alts.internal.AltsHandshakerStub);
    Code:
       0: aload_0
       1: getfield      #54                 // Field exceptionMessage:Ljava/util/concurrent/atomic/AtomicReference;
       4: areturn
}
