Compiled from "Identity.java"
public final class io.grpc.alts.internal.Identity$IdentityOneofCase extends java.lang.Enum<io.grpc.alts.internal.Identity$IdentityOneofCase> implements com.google.protobuf.Internal$EnumLite, com.google.protobuf.AbstractMessageLite$InternalOneOfEnum {
  public static final io.grpc.alts.internal.Identity$IdentityOneofCase SERVICE_ACCOUNT;

  public static final io.grpc.alts.internal.Identity$IdentityOneofCase HOSTNAME;

  public static final io.grpc.alts.internal.Identity$IdentityOneofCase IDENTITYONEOF_NOT_SET;

  private final int value;

  private static final io.grpc.alts.internal.Identity$IdentityOneofCase[] $VALUES;

  public static io.grpc.alts.internal.Identity$IdentityOneofCase[] values();
    Code:
       0: getstatic     #31                 // Field $VALUES:[Lio/grpc/alts/internal/Identity$IdentityOneofCase;
       3: invokevirtual #36                 // Method "[Lio/grpc/alts/internal/Identity$IdentityOneofCase;".clone:()Ljava/lang/Object;
       6: checkcast     #32                 // class "[Lio/grpc/alts/internal/Identity$IdentityOneofCase;"
       9: areturn

  public static io.grpc.alts.internal.Identity$IdentityOneofCase valueOf(java.lang.String);
    Code:
       0: ldc           #2                  // class io/grpc/alts/internal/Identity$IdentityOneofCase
       2: aload_0
       3: invokestatic  #41                 // Method java/lang/Enum.valueOf:(Ljava/lang/Class;Ljava/lang/String;)Ljava/lang/Enum;
       6: checkcast     #2                  // class io/grpc/alts/internal/Identity$IdentityOneofCase
       9: areturn

  private io.grpc.alts.internal.Identity$IdentityOneofCase(int);
    Code:
       0: aload_0
       1: aload_1
       2: iload_2
       3: invokespecial #49                 // Method java/lang/Enum."<init>":(Ljava/lang/String;I)V
       6: aload_0
       7: iload_3
       8: putfield      #51                 // Field value:I
      11: return

  public static io.grpc.alts.internal.Identity$IdentityOneofCase valueOf(int);
    Code:
       0: iload_0
       1: invokestatic  #57                 // Method forNumber:(I)Lio/grpc/alts/internal/Identity$IdentityOneofCase;
       4: areturn

  public static io.grpc.alts.internal.Identity$IdentityOneofCase forNumber(int);
    Code:
       0: iload_0
       1: tableswitch   { // 0 to 2
                     0: 36
                     1: 28
                     2: 32
               default: 40
          }
      28: getstatic     #59                 // Field SERVICE_ACCOUNT:Lio/grpc/alts/internal/Identity$IdentityOneofCase;
      31: areturn
      32: getstatic     #61                 // Field HOSTNAME:Lio/grpc/alts/internal/Identity$IdentityOneofCase;
      35: areturn
      36: getstatic     #63                 // Field IDENTITYONEOF_NOT_SET:Lio/grpc/alts/internal/Identity$IdentityOneofCase;
      39: areturn
      40: aconst_null
      41: areturn

  public int getNumber();
    Code:
       0: aload_0
       1: getfield      #51                 // Field value:I
       4: ireturn

  static {};
    Code:
       0: new           #2                  // class io/grpc/alts/internal/Identity$IdentityOneofCase
       3: dup
       4: ldc           #68                 // String SERVICE_ACCOUNT
       6: iconst_0
       7: iconst_1
       8: invokespecial #70                 // Method "<init>":(Ljava/lang/String;II)V
      11: putstatic     #59                 // Field SERVICE_ACCOUNT:Lio/grpc/alts/internal/Identity$IdentityOneofCase;
      14: new           #2                  // class io/grpc/alts/internal/Identity$IdentityOneofCase
      17: dup
      18: ldc           #71                 // String HOSTNAME
      20: iconst_1
      21: iconst_2
      22: invokespecial #70                 // Method "<init>":(Ljava/lang/String;II)V
      25: putstatic     #61                 // Field HOSTNAME:Lio/grpc/alts/internal/Identity$IdentityOneofCase;
      28: new           #2                  // class io/grpc/alts/internal/Identity$IdentityOneofCase
      31: dup
      32: ldc           #72                 // String IDENTITYONEOF_NOT_SET
      34: iconst_2
      35: iconst_0
      36: invokespecial #70                 // Method "<init>":(Ljava/lang/String;II)V
      39: putstatic     #63                 // Field IDENTITYONEOF_NOT_SET:Lio/grpc/alts/internal/Identity$IdentityOneofCase;
      42: iconst_3
      43: anewarray     #2                  // class io/grpc/alts/internal/Identity$IdentityOneofCase
      46: dup
      47: iconst_0
      48: getstatic     #59                 // Field SERVICE_ACCOUNT:Lio/grpc/alts/internal/Identity$IdentityOneofCase;
      51: aastore
      52: dup
      53: iconst_1
      54: getstatic     #61                 // Field HOSTNAME:Lio/grpc/alts/internal/Identity$IdentityOneofCase;
      57: aastore
      58: dup
      59: iconst_2
      60: getstatic     #63                 // Field IDENTITYONEOF_NOT_SET:Lio/grpc/alts/internal/Identity$IdentityOneofCase;
      63: aastore
      64: putstatic     #31                 // Field $VALUES:[Lio/grpc/alts/internal/Identity$IdentityOneofCase;
      67: return
}
