Compiled from "AssemblerUtils.java"
public class org.apache.jena.sparql.core.assembler.AssemblerUtils {
  private static boolean initialized;

  private static org.apache.jena.rdf.model.Model modelExtras;

  public org.apache.jena.sparql.core.assembler.AssemblerUtils();
    Code:
       0: aload_0
       1: invokespecial #1                  // Method java/lang/Object."<init>":()V
       4: return

  public static org.apache.jena.shared.PrefixMapping readPrefixMapping(java.lang.String);
    Code:
       0: aload_0
       1: getstatic     #2                  // Field org/apache/jena/assembler/JA.PrefixMapping:Lorg/apache/jena/rdf/model/Resource;
       4: invokestatic  #3                  // Method build:(Ljava/lang/String;Lorg/apache/jena/rdf/model/Resource;)Ljava/lang/Object;
       7: checkcast     #4                  // class org/apache/jena/shared/PrefixMapping
      10: astore_1
      11: aload_1
      12: areturn

  public static void init();
    Code:
       0: getstatic     #5                  // Field initialized:Z
       3: ifeq          7
       6: return
       7: iconst_1
       8: putstatic     #5                  // Field initialized:Z
      11: invokestatic  #6                  // Method org/apache/jena/sparql/core/assembler/DatasetAssembler.getType:()Lorg/apache/jena/rdf/model/Resource;
      14: new           #7                  // class org/apache/jena/sparql/core/assembler/DatasetAssembler
      17: dup
      18: invokespecial #8                  // Method org/apache/jena/sparql/core/assembler/DatasetAssembler."<init>":()V
      21: invokestatic  #9                  // Method registerDataset:(Lorg/apache/jena/rdf/model/Resource;Lorg/apache/jena/assembler/Assembler;)V
      24: invokestatic  #10                 // Method org/apache/jena/sparql/core/assembler/InMemDatasetAssembler.getType:()Lorg/apache/jena/rdf/model/Resource;
      27: new           #11                 // class org/apache/jena/sparql/core/assembler/InMemDatasetAssembler
      30: dup
      31: invokespecial #12                 // Method org/apache/jena/sparql/core/assembler/InMemDatasetAssembler."<init>":()V
      34: invokestatic  #9                  // Method registerDataset:(Lorg/apache/jena/rdf/model/Resource;Lorg/apache/jena/assembler/Assembler;)V
      37: return

  public static void registerDataset(org.apache.jena.rdf.model.Resource, org.apache.jena.assembler.Assembler);
    Code:
       0: invokestatic  #13                 // Method org/apache/jena/assembler/ConstAssembler.general:()Lorg/apache/jena/assembler/assemblers/AssemblerGroup;
       3: aload_0
       4: aload_1
       5: invokestatic  #6                  // Method org/apache/jena/sparql/core/assembler/DatasetAssembler.getType:()Lorg/apache/jena/rdf/model/Resource;
       8: invokestatic  #14                 // Method register:(Lorg/apache/jena/assembler/assemblers/AssemblerGroup;Lorg/apache/jena/rdf/model/Resource;Lorg/apache/jena/assembler/Assembler;Lorg/apache/jena/rdf/model/Resource;)V
      11: return

  public static void registerModel(org.apache.jena.rdf.model.Resource, org.apache.jena.assembler.Assembler);
    Code:
       0: invokestatic  #13                 // Method org/apache/jena/assembler/ConstAssembler.general:()Lorg/apache/jena/assembler/assemblers/AssemblerGroup;
       3: aload_0
       4: aload_1
       5: getstatic     #15                 // Field org/apache/jena/assembler/JA.Model:Lorg/apache/jena/rdf/model/Resource;
       8: invokestatic  #14                 // Method register:(Lorg/apache/jena/assembler/assemblers/AssemblerGroup;Lorg/apache/jena/rdf/model/Resource;Lorg/apache/jena/assembler/Assembler;Lorg/apache/jena/rdf/model/Resource;)V
      11: return

  public static void register(org.apache.jena.assembler.assemblers.AssemblerGroup, org.apache.jena.rdf.model.Resource, org.apache.jena.assembler.Assembler, org.apache.jena.rdf.model.Resource);
    Code:
       0: aload_0
       1: aload_1
       2: aload_2
       3: invokestatic  #16                 // Method registerAssembler:(Lorg/apache/jena/assembler/assemblers/AssemblerGroup;Lorg/apache/jena/rdf/model/Resource;Lorg/apache/jena/assembler/Assembler;)V
       6: aload_3
       7: ifnull        34
      10: aload_3
      11: aload_1
      12: invokeinterface #17,  2           // InterfaceMethod org/apache/jena/rdf/model/Resource.equals:(Ljava/lang/Object;)Z
      17: ifne          34
      20: getstatic     #18                 // Field modelExtras:Lorg/apache/jena/rdf/model/Model;
      23: aload_1
      24: invokestatic  #19                 // Method org/apache/jena/vocabulary/RDFS$Init.subClassOf:()Lorg/apache/jena/rdf/model/Property;
      27: aload_3
      28: invokeinterface #20,  4           // InterfaceMethod org/apache/jena/rdf/model/Model.add:(Lorg/apache/jena/rdf/model/Resource;Lorg/apache/jena/rdf/model/Property;Lorg/apache/jena/rdf/model/RDFNode;)Lorg/apache/jena/rdf/model/Model;
      33: pop
      34: return

  public static void registerAssembler(org.apache.jena.assembler.assemblers.AssemblerGroup, org.apache.jena.rdf.model.Resource, org.apache.jena.assembler.Assembler);
    Code:
       0: aload_0
       1: ifnonnull     8
       4: invokestatic  #13                 // Method org/apache/jena/assembler/ConstAssembler.general:()Lorg/apache/jena/assembler/assemblers/AssemblerGroup;
       7: astore_0
       8: aload_0
       9: aload_1
      10: aload_2
      11: invokevirtual #21                 // Method org/apache/jena/assembler/assemblers/AssemblerGroup.implementWith:(Lorg/apache/jena/rdf/model/Resource;Lorg/apache/jena/assembler/Assembler;)Lorg/apache/jena/assembler/assemblers/AssemblerGroup;
      14: pop
      15: return

  public static org.apache.jena.rdf.model.Model readAssemblerFile(java.lang.String);
    Code:
       0: aconst_null
       1: astore_1
       2: aload_0
       3: invokestatic  #22                 // Method org/apache/jena/riot/RDFDataMgr.loadModel:(Ljava/lang/String;)Lorg/apache/jena/rdf/model/Model;
       6: astore_1
       7: goto          41
      10: astore_2
      11: new           #24                 // class org/apache/jena/sparql/ARQException
      14: dup
      15: new           #25                 // class java/lang/StringBuilder
      18: dup
      19: invokespecial #26                 // Method java/lang/StringBuilder."<init>":()V
      22: ldc           #27                 // String Failed reading assembler description:
      24: invokevirtual #28                 // Method java/lang/StringBuilder.append:(Ljava/lang/String;)Ljava/lang/StringBuilder;
      27: aload_2
      28: invokevirtual #29                 // Method java/lang/Exception.getMessage:()Ljava/lang/String;
      31: invokevirtual #28                 // Method java/lang/StringBuilder.append:(Ljava/lang/String;)Ljava/lang/StringBuilder;
      34: invokevirtual #30                 // Method java/lang/StringBuilder.toString:()Ljava/lang/String;
      37: invokespecial #31                 // Method org/apache/jena/sparql/ARQException."<init>":(Ljava/lang/String;)V
      40: athrow
      41: aload_1
      42: getstatic     #18                 // Field modelExtras:Lorg/apache/jena/rdf/model/Model;
      45: invokeinterface #32,  2           // InterfaceMethod org/apache/jena/rdf/model/Model.add:(Lorg/apache/jena/rdf/model/Model;)Lorg/apache/jena/rdf/model/Model;
      50: pop
      51: aload_1
      52: areturn
    Exception table:
       from    to  target type
           2     7    10   Class java/lang/Exception

  public static java.lang.Object build(java.lang.String, java.lang.String);
    Code:
       0: aload_1
       1: invokestatic  #33                 // Method org/apache/jena/rdf/model/ResourceFactory.createResource:(Ljava/lang/String;)Lorg/apache/jena/rdf/model/Resource;
       4: astore_2
       5: aload_0
       6: aload_2
       7: invokestatic  #3                  // Method build:(Ljava/lang/String;Lorg/apache/jena/rdf/model/Resource;)Ljava/lang/Object;
      10: areturn

  public static java.lang.Object build(java.lang.String, org.apache.jena.rdf.model.Resource);
    Code:
       0: aload_0
       1: ifnonnull     14
       4: new           #24                 // class org/apache/jena/sparql/ARQException
       7: dup
       8: ldc           #34                 // String No assembler file
      10: invokespecial #31                 // Method org/apache/jena/sparql/ARQException."<init>":(Ljava/lang/String;)V
      13: athrow
      14: aload_0
      15: invokestatic  #35                 // Method readAssemblerFile:(Ljava/lang/String;)Lorg/apache/jena/rdf/model/Model;
      18: astore_2
      19: aconst_null
      20: astore_3
      21: aload_2
      22: aload_1
      23: invokestatic  #36                 // Method org/apache/jena/sparql/util/graph/GraphUtils.findRootByType:(Lorg/apache/jena/rdf/model/Model;Lorg/apache/jena/rdf/model/Resource;)Lorg/apache/jena/rdf/model/Resource;
      26: astore_3
      27: aload_3
      28: ifnonnull     33
      31: aconst_null
      32: areturn
      33: goto          67
      36: astore        4
      38: new           #24                 // class org/apache/jena/sparql/ARQException
      41: dup
      42: new           #25                 // class java/lang/StringBuilder
      45: dup
      46: invokespecial #26                 // Method java/lang/StringBuilder."<init>":()V
      49: ldc           #38                 // String Multiple types for:
      51: invokevirtual #28                 // Method java/lang/StringBuilder.append:(Ljava/lang/String;)Ljava/lang/StringBuilder;
      54: getstatic     #39                 // Field org/apache/jena/sparql/core/assembler/DatasetAssemblerVocab.tDataset:Lorg/apache/jena/rdf/model/Resource;
      57: invokevirtual #40                 // Method java/lang/StringBuilder.append:(Ljava/lang/Object;)Ljava/lang/StringBuilder;
      60: invokevirtual #30                 // Method java/lang/StringBuilder.toString:()Ljava/lang/String;
      63: invokespecial #31                 // Method org/apache/jena/sparql/ARQException."<init>":(Ljava/lang/String;)V
      66: athrow
      67: getstatic     #41                 // Field org/apache/jena/assembler/Assembler.general:Lorg/apache/jena/assembler/assemblers/AssemblerGroup;
      70: aload_3
      71: invokevirtual #42                 // Method org/apache/jena/assembler/assemblers/AssemblerGroup.open:(Lorg/apache/jena/rdf/model/Resource;)Ljava/lang/Object;
      74: areturn
    Exception table:
       from    to  target type
          21    32    36   Class org/apache/jena/sparql/util/TypeNotUniqueException

  public static void setContext(org.apache.jena.rdf.model.Resource, org.apache.jena.sparql.util.Context);
    Code:
       0: new           #25                 // class java/lang/StringBuilder
       3: dup
       4: invokespecial #26                 // Method java/lang/StringBuilder."<init>":()V
       7: ldc           #43                 // String PREFIX ja: <
       9: invokevirtual #28                 // Method java/lang/StringBuilder.append:(Ljava/lang/String;)Ljava/lang/StringBuilder;
      12: invokestatic  #44                 // Method org/apache/jena/assembler/JA.getURI:()Ljava/lang/String;
      15: invokevirtual #28                 // Method java/lang/StringBuilder.append:(Ljava/lang/String;)Ljava/lang/StringBuilder;
      18: ldc           #45                 // String >\nSELECT * { ?x ja:context [ ja:cxtName ?name ; ja:cxtValue ?value ] }
      20: invokevirtual #28                 // Method java/lang/StringBuilder.append:(Ljava/lang/String;)Ljava/lang/StringBuilder;
      23: invokevirtual #30                 // Method java/lang/StringBuilder.toString:()Ljava/lang/String;
      26: astore_2
      27: new           #46                 // class org/apache/jena/query/QuerySolutionMap
      30: dup
      31: invokespecial #47                 // Method org/apache/jena/query/QuerySolutionMap."<init>":()V
      34: astore_3
      35: aload_3
      36: ldc           #48                 // String x
      38: aload_0
      39: invokevirtual #49                 // Method org/apache/jena/query/QuerySolutionMap.add:(Ljava/lang/String;Lorg/apache/jena/rdf/model/RDFNode;)V
      42: aload_2
      43: aload_0
      44: invokeinterface #50,  1           // InterfaceMethod org/apache/jena/rdf/model/Resource.getModel:()Lorg/apache/jena/rdf/model/Model;
      49: aload_3
      50: invokestatic  #51                 // Method org/apache/jena/query/QueryExecutionFactory.create:(Ljava/lang/String;Lorg/apache/jena/rdf/model/Model;Lorg/apache/jena/query/QuerySolution;)Lorg/apache/jena/query/QueryExecution;
      53: astore        4
      55: aload         4
      57: invokeinterface #52,  1           // InterfaceMethod org/apache/jena/query/QueryExecution.execSelect:()Lorg/apache/jena/query/ResultSet;
      62: astore        5
      64: aload         5
      66: invokeinterface #53,  1           // InterfaceMethod org/apache/jena/query/ResultSet.hasNext:()Z
      71: ifeq          159
      74: aload         5
      76: invokeinterface #54,  1           // InterfaceMethod org/apache/jena/query/ResultSet.next:()Lorg/apache/jena/query/QuerySolution;
      81: astore        6
      83: aload         6
      85: ldc           #55                 // String name
      87: invokeinterface #56,  2           // InterfaceMethod org/apache/jena/query/QuerySolution.getLiteral:(Ljava/lang/String;)Lorg/apache/jena/rdf/model/Literal;
      92: invokeinterface #57,  1           // InterfaceMethod org/apache/jena/rdf/model/Literal.getLexicalForm:()Ljava/lang/String;
      97: astore        7
      99: aload         6
     101: ldc           #58                 // String value
     103: invokeinterface #56,  2           // InterfaceMethod org/apache/jena/query/QuerySolution.getLiteral:(Ljava/lang/String;)Lorg/apache/jena/rdf/model/Literal;
     108: invokeinterface #57,  1           // InterfaceMethod org/apache/jena/rdf/model/Literal.getLexicalForm:()Ljava/lang/String;
     113: astore        8
     115: aload         7
     117: invokestatic  #59                 // Method org/apache/jena/sparql/util/MappingRegistry.mapPrefixName:(Ljava/lang/String;)Ljava/lang/String;
     120: astore        7
     122: aload         7
     124: invokestatic  #60                 // Method org/apache/jena/sparql/util/Symbol.create:(Ljava/lang/String;)Lorg/apache/jena/sparql/util/Symbol;
     127: astore        9
     129: ldc           #61                 // String undef
     131: aload         8
     133: invokevirtual #62                 // Method java/lang/String.equalsIgnoreCase:(Ljava/lang/String;)Z
     136: ifeq          148
     139: aload_1
     140: aload         9
     142: invokevirtual #63                 // Method org/apache/jena/sparql/util/Context.remove:(Lorg/apache/jena/sparql/util/Symbol;)V
     145: goto          156
     148: aload_1
     149: aload         9
     151: aload         8
     153: invokevirtual #64                 // Method org/apache/jena/sparql/util/Context.set:(Lorg/apache/jena/sparql/util/Symbol;Ljava/lang/Object;)V
     156: goto          64
     159: return

  static {};
    Code:
       0: iconst_0
       1: putstatic     #5                  // Field initialized:Z
       4: invokestatic  #65                 // Method org/apache/jena/system/JenaSystem.init:()V
       7: invokestatic  #66                 // Method org/apache/jena/rdf/model/ModelFactory.createDefaultModel:()Lorg/apache/jena/rdf/model/Model;
      10: putstatic     #18                 // Field modelExtras:Lorg/apache/jena/rdf/model/Model;
      13: return
}
