Compiled from "MethodMatchers.java"
class org.springframework.aop.support.MethodMatchers$ClassFilterAwareUnionMethodMatcher extends org.springframework.aop.support.MethodMatchers$UnionMethodMatcher {
  private final org.springframework.aop.ClassFilter cf1;

  private final org.springframework.aop.ClassFilter cf2;

  public org.springframework.aop.support.MethodMatchers$ClassFilterAwareUnionMethodMatcher(org.springframework.aop.MethodMatcher, org.springframework.aop.ClassFilter, org.springframework.aop.MethodMatcher, org.springframework.aop.ClassFilter);
    Code:
       0: aload_0
       1: aload_1
       2: aload_3
       3: invokespecial #1                  // Method org/springframework/aop/support/MethodMatchers$UnionMethodMatcher."<init>":(Lorg/springframework/aop/MethodMatcher;Lorg/springframework/aop/MethodMatcher;)V
       6: aload_0
       7: aload_2
       8: putfield      #2                  // Field cf1:Lorg/springframework/aop/ClassFilter;
      11: aload_0
      12: aload         4
      14: putfield      #3                  // Field cf2:Lorg/springframework/aop/ClassFilter;
      17: return

  protected boolean matchesClass1(java.lang.Class<?>);
    Code:
       0: aload_0
       1: getfield      #2                  // Field cf1:Lorg/springframework/aop/ClassFilter;
       4: aload_1
       5: invokeinterface #4,  2            // InterfaceMethod org/springframework/aop/ClassFilter.matches:(Ljava/lang/Class;)Z
      10: ireturn

  protected boolean matchesClass2(java.lang.Class<?>);
    Code:
       0: aload_0
       1: getfield      #3                  // Field cf2:Lorg/springframework/aop/ClassFilter;
       4: aload_1
       5: invokeinterface #4,  2            // InterfaceMethod org/springframework/aop/ClassFilter.matches:(Ljava/lang/Class;)Z
      10: ireturn

  public boolean equals(java.lang.Object);
    Code:
       0: aload_0
       1: aload_1
       2: if_acmpne     7
       5: iconst_1
       6: ireturn
       7: aload_0
       8: aload_1
       9: invokespecial #5                  // Method org/springframework/aop/support/MethodMatchers$UnionMethodMatcher.equals:(Ljava/lang/Object;)Z
      12: ifne          17
      15: iconst_0
      16: ireturn
      17: getstatic     #6                  // Field org/springframework/aop/ClassFilter.TRUE:Lorg/springframework/aop/ClassFilter;
      20: astore_2
      21: getstatic     #6                  // Field org/springframework/aop/ClassFilter.TRUE:Lorg/springframework/aop/ClassFilter;
      24: astore_3
      25: aload_1
      26: instanceof    #7                  // class org/springframework/aop/support/MethodMatchers$ClassFilterAwareUnionMethodMatcher
      29: ifeq          50
      32: aload_1
      33: checkcast     #7                  // class org/springframework/aop/support/MethodMatchers$ClassFilterAwareUnionMethodMatcher
      36: astore        4
      38: aload         4
      40: getfield      #2                  // Field cf1:Lorg/springframework/aop/ClassFilter;
      43: astore_2
      44: aload         4
      46: getfield      #3                  // Field cf2:Lorg/springframework/aop/ClassFilter;
      49: astore_3
      50: aload_0
      51: getfield      #2                  // Field cf1:Lorg/springframework/aop/ClassFilter;
      54: aload_2
      55: invokevirtual #8                  // Method java/lang/Object.equals:(Ljava/lang/Object;)Z
      58: ifeq          76
      61: aload_0
      62: getfield      #3                  // Field cf2:Lorg/springframework/aop/ClassFilter;
      65: aload_3
      66: invokevirtual #8                  // Method java/lang/Object.equals:(Ljava/lang/Object;)Z
      69: ifeq          76
      72: iconst_1
      73: goto          77
      76: iconst_0
      77: ireturn

  public int hashCode();
    Code:
       0: aload_0
       1: invokespecial #9                  // Method org/springframework/aop/support/MethodMatchers$UnionMethodMatcher.hashCode:()I
       4: ireturn

  public java.lang.String toString();
    Code:
       0: new           #10                 // class java/lang/StringBuilder
       3: dup
       4: invokespecial #11                 // Method java/lang/StringBuilder."<init>":()V
       7: aload_0
       8: invokevirtual #12                 // Method java/lang/Object.getClass:()Ljava/lang/Class;
      11: invokevirtual #13                 // Method java/lang/Class.getName:()Ljava/lang/String;
      14: invokevirtual #14                 // Method java/lang/StringBuilder.append:(Ljava/lang/String;)Ljava/lang/StringBuilder;
      17: ldc           #15                 // String :
      19: invokevirtual #14                 // Method java/lang/StringBuilder.append:(Ljava/lang/String;)Ljava/lang/StringBuilder;
      22: aload_0
      23: getfield      #2                  // Field cf1:Lorg/springframework/aop/ClassFilter;
      26: invokevirtual #16                 // Method java/lang/StringBuilder.append:(Ljava/lang/Object;)Ljava/lang/StringBuilder;
      29: ldc           #17                 // String ,
      31: invokevirtual #14                 // Method java/lang/StringBuilder.append:(Ljava/lang/String;)Ljava/lang/StringBuilder;
      34: aload_0
      35: getfield      #18                 // Field mm1:Lorg/springframework/aop/MethodMatcher;
      38: invokevirtual #16                 // Method java/lang/StringBuilder.append:(Ljava/lang/Object;)Ljava/lang/StringBuilder;
      41: ldc           #17                 // String ,
      43: invokevirtual #14                 // Method java/lang/StringBuilder.append:(Ljava/lang/String;)Ljava/lang/StringBuilder;
      46: aload_0
      47: getfield      #3                  // Field cf2:Lorg/springframework/aop/ClassFilter;
      50: invokevirtual #16                 // Method java/lang/StringBuilder.append:(Ljava/lang/Object;)Ljava/lang/StringBuilder;
      53: ldc           #17                 // String ,
      55: invokevirtual #14                 // Method java/lang/StringBuilder.append:(Ljava/lang/String;)Ljava/lang/StringBuilder;
      58: aload_0
      59: getfield      #19                 // Field mm2:Lorg/springframework/aop/MethodMatcher;
      62: invokevirtual #16                 // Method java/lang/StringBuilder.append:(Ljava/lang/Object;)Ljava/lang/StringBuilder;
      65: invokevirtual #20                 // Method java/lang/StringBuilder.toString:()Ljava/lang/String;
      68: areturn
}
