Compiled from "LDAPExtensionFeature.java"
public class net.nemerosa.ontrack.extension.ldap.LDAPExtensionFeature extends net.nemerosa.ontrack.extension.support.AbstractExtensionFeature {
  public static final java.lang.String LDAP_GROUP_MAPPING;

  public net.nemerosa.ontrack.extension.ldap.LDAPExtensionFeature();
    Code:
       0: aload_0
       1: ldc           #1                  // String ldap
       3: ldc           #2                  // String LDAP
       5: ldc           #3                  // String LDAP support for authentication and authorisations
       7: getstatic     #4                  // Field net/nemerosa/ontrack/model/extension/ExtensionFeatureOptions.DEFAULT:Lnet/nemerosa/ontrack/model/extension/ExtensionFeatureOptions;
      10: iconst_1
      11: invokevirtual #5                  // Method net/nemerosa/ontrack/model/extension/ExtensionFeatureOptions.withGui:(Z)Lnet/nemerosa/ontrack/model/extension/ExtensionFeatureOptions;
      14: invokespecial #6                  // Method net/nemerosa/ontrack/extension/support/AbstractExtensionFeature."<init>":(Ljava/lang/String;Ljava/lang/String;Ljava/lang/String;Lnet/nemerosa/ontrack/model/extension/ExtensionFeatureOptions;)V
      17: return
}
