Compiled from "JBossLogPrintWriter.java"
public final class org.jboss.as.connector.services.resourceadapters.deployment.JBossLogPrintWriter extends java.io.PrintWriter {
  private final java.lang.String deploymentName;

  private final org.jboss.logging.BasicLogger logger;

  private final org.jboss.logging.Logger$Level level;

  private java.lang.StringBuilder buffer;

  private java.util.Formatter formatter;

  public org.jboss.as.connector.services.resourceadapters.deployment.JBossLogPrintWriter(java.lang.String, org.jboss.logging.BasicLogger);
    Code:
       0: aload_0
       1: new           #1                  // class org/jboss/as/connector/services/resourceadapters/deployment/JBossLogPrintWriter$1
       4: dup
       5: invokespecial #2                  // Method org/jboss/as/connector/services/resourceadapters/deployment/JBossLogPrintWriter$1."<init>":()V
       8: invokespecial #3                  // Method java/io/PrintWriter."<init>":(Ljava/io/OutputStream;)V
      11: aload_0
      12: getstatic     #4                  // Field org/jboss/logging/Logger$Level.INFO:Lorg/jboss/logging/Logger$Level;
      15: putfield      #5                  // Field level:Lorg/jboss/logging/Logger$Level;
      18: aload_0
      19: new           #6                  // class java/lang/StringBuilder
      22: dup
      23: invokespecial #7                  // Method java/lang/StringBuilder."<init>":()V
      26: putfield      #8                  // Field buffer:Ljava/lang/StringBuilder;
      29: aload_0
      30: aload_1
      31: putfield      #9                  // Field deploymentName:Ljava/lang/String;
      34: aload_0
      35: aload_2
      36: putfield      #10                 // Field logger:Lorg/jboss/logging/BasicLogger;
      39: return

  public void write(int);
    Code:
       0: aload_0
       1: getfield      #11                 // Field lock:Ljava/lang/Object;
       4: dup
       5: astore_2
       6: monitorenter
       7: iload_1
       8: bipush        10
      10: if_icmpne     20
      13: aload_0
      14: invokespecial #12                 // Method outputLogger:()V
      17: goto          30
      20: aload_0
      21: getfield      #8                  // Field buffer:Ljava/lang/StringBuilder;
      24: iload_1
      25: i2c
      26: invokevirtual #13                 // Method java/lang/StringBuilder.append:(C)Ljava/lang/StringBuilder;
      29: pop
      30: aload_2
      31: monitorexit
      32: goto          40
      35: astore_3
      36: aload_2
      37: monitorexit
      38: aload_3
      39: athrow
      40: return
    Exception table:
       from    to  target type
           7    32    35   any
          35    38    35   any

  public void write(char[], int, int);
    Code:
       0: aload_0
       1: getfield      #11                 // Field lock:Ljava/lang/Object;
       4: dup
       5: astore        4
       7: monitorenter
       8: iconst_0
       9: istore        5
      11: iconst_0
      12: istore        6
      14: iload         6
      16: iload_3
      17: if_icmpge     69
      20: aload_1
      21: iload_2
      22: iload         6
      24: iadd
      25: caload
      26: istore        7
      28: iload         7
      30: bipush        10
      32: if_icmpne     63
      35: aload_0
      36: getfield      #8                  // Field buffer:Ljava/lang/StringBuilder;
      39: aload_1
      40: iload         5
      42: iload_2
      43: iadd
      44: iload         6
      46: iload         5
      48: isub
      49: invokevirtual #14                 // Method java/lang/StringBuilder.append:([CII)Ljava/lang/StringBuilder;
      52: pop
      53: aload_0
      54: invokespecial #12                 // Method outputLogger:()V
      57: iload         6
      59: iconst_1
      60: iadd
      61: istore        5
      63: iinc          6, 1
      66: goto          14
      69: aload_0
      70: getfield      #8                  // Field buffer:Ljava/lang/StringBuilder;
      73: aload_1
      74: iload         5
      76: iload_2
      77: iadd
      78: iload         6
      80: iload         5
      82: isub
      83: invokevirtual #14                 // Method java/lang/StringBuilder.append:([CII)Ljava/lang/StringBuilder;
      86: pop
      87: aload         4
      89: monitorexit
      90: goto          101
      93: astore        8
      95: aload         4
      97: monitorexit
      98: aload         8
     100: athrow
     101: return
    Exception table:
       from    to  target type
           8    90    93   any
          93    98    93   any

  public void write(char[]);
    Code:
       0: aload_0
       1: aload_1
       2: iconst_0
       3: aload_1
       4: arraylength
       5: invokevirtual #15                 // Method write:([CII)V
       8: return

  public void write(java.lang.String, int, int);
    Code:
       0: aload_0
       1: getfield      #11                 // Field lock:Ljava/lang/Object;
       4: dup
       5: astore        4
       7: monitorenter
       8: iconst_0
       9: istore        5
      11: iconst_0
      12: istore        6
      14: iload         6
      16: iload_3
      17: if_icmpge     73
      20: aload_1
      21: iload_2
      22: iload         6
      24: iadd
      25: invokevirtual #16                 // Method java/lang/String.charAt:(I)C
      28: istore        7
      30: iload         7
      32: bipush        10
      34: if_icmpne     67
      37: aload_0
      38: getfield      #8                  // Field buffer:Ljava/lang/StringBuilder;
      41: aload_1
      42: iload         5
      44: iload_2
      45: iadd
      46: iload_2
      47: iload         6
      49: iadd
      50: invokevirtual #17                 // Method java/lang/String.substring:(II)Ljava/lang/String;
      53: invokevirtual #18                 // Method java/lang/StringBuilder.append:(Ljava/lang/String;)Ljava/lang/StringBuilder;
      56: pop
      57: aload_0
      58: invokespecial #12                 // Method outputLogger:()V
      61: iload         6
      63: iconst_1
      64: iadd
      65: istore        5
      67: iinc          6, 1
      70: goto          14
      73: aload_0
      74: getfield      #8                  // Field buffer:Ljava/lang/StringBuilder;
      77: aload_1
      78: iload         5
      80: iload_2
      81: iadd
      82: iload_2
      83: iload         6
      85: iadd
      86: invokevirtual #17                 // Method java/lang/String.substring:(II)Ljava/lang/String;
      89: invokevirtual #18                 // Method java/lang/StringBuilder.append:(Ljava/lang/String;)Ljava/lang/StringBuilder;
      92: pop
      93: aload         4
      95: monitorexit
      96: goto          107
      99: astore        8
     101: aload         4
     103: monitorexit
     104: aload         8
     106: athrow
     107: return
    Exception table:
       from    to  target type
           8    96    99   any
          99   104    99   any

  public void write(java.lang.String);
    Code:
       0: aload_0
       1: aload_1
       2: iconst_0
       3: aload_1
       4: invokevirtual #19                 // Method java/lang/String.length:()I
       7: invokevirtual #20                 // Method write:(Ljava/lang/String;II)V
      10: return

  private void outputLogger();
    Code:
       0: aload_0
       1: getfield      #8                  // Field buffer:Ljava/lang/StringBuilder;
       4: invokevirtual #21                 // Method java/lang/StringBuilder.length:()I
       7: ifle          63
      10: aload_0
      11: getfield      #10                 // Field logger:Lorg/jboss/logging/BasicLogger;
      14: aload_0
      15: getfield      #5                  // Field level:Lorg/jboss/logging/Logger$Level;
      18: new           #6                  // class java/lang/StringBuilder
      21: dup
      22: invokespecial #7                  // Method java/lang/StringBuilder."<init>":()V
      25: aload_0
      26: getfield      #9                  // Field deploymentName:Ljava/lang/String;
      29: invokevirtual #18                 // Method java/lang/StringBuilder.append:(Ljava/lang/String;)Ljava/lang/StringBuilder;
      32: ldc           #22                 // String :
      34: invokevirtual #18                 // Method java/lang/StringBuilder.append:(Ljava/lang/String;)Ljava/lang/StringBuilder;
      37: aload_0
      38: getfield      #8                  // Field buffer:Ljava/lang/StringBuilder;
      41: invokevirtual #23                 // Method java/lang/StringBuilder.toString:()Ljava/lang/String;
      44: invokevirtual #18                 // Method java/lang/StringBuilder.append:(Ljava/lang/String;)Ljava/lang/StringBuilder;
      47: invokevirtual #23                 // Method java/lang/StringBuilder.toString:()Ljava/lang/String;
      50: invokeinterface #24,  3           // InterfaceMethod org/jboss/logging/BasicLogger.log:(Lorg/jboss/logging/Logger$Level;Ljava/lang/Object;)V
      55: aload_0
      56: getfield      #8                  // Field buffer:Ljava/lang/StringBuilder;
      59: iconst_0
      60: invokevirtual #25                 // Method java/lang/StringBuilder.setLength:(I)V
      63: return

  public void flush();
    Code:
       0: aload_0
       1: getfield      #11                 // Field lock:Ljava/lang/Object;
       4: dup
       5: astore_1
       6: monitorenter
       7: aload_0
       8: invokespecial #12                 // Method outputLogger:()V
      11: aload_1
      12: monitorexit
      13: goto          21
      16: astore_2
      17: aload_1
      18: monitorexit
      19: aload_2
      20: athrow
      21: return
    Exception table:
       from    to  target type
           7    13    16   any
          16    19    16   any

  public void close();
    Code:
       0: aload_0
       1: invokevirtual #26                 // Method flush:()V
       4: return

  public boolean checkError();
    Code:
       0: aload_0
       1: invokevirtual #26                 // Method flush:()V
       4: iconst_0
       5: ireturn

  protected void setError();
    Code:
       0: return

  protected void clearError();
    Code:
       0: return

  public void print(boolean);
    Code:
       0: aload_0
       1: iload_1
       2: invokestatic  #27                 // Method java/lang/String.valueOf:(Z)Ljava/lang/String;
       5: invokevirtual #28                 // Method write:(Ljava/lang/String;)V
       8: return

  public void print(char);
    Code:
       0: aload_0
       1: iload_1
       2: invokevirtual #29                 // Method write:(I)V
       5: return

  public void print(int);
    Code:
       0: aload_0
       1: iload_1
       2: invokestatic  #30                 // Method java/lang/String.valueOf:(I)Ljava/lang/String;
       5: invokevirtual #28                 // Method write:(Ljava/lang/String;)V
       8: return

  public void print(long);
    Code:
       0: aload_0
       1: lload_1
       2: invokestatic  #31                 // Method java/lang/String.valueOf:(J)Ljava/lang/String;
       5: invokevirtual #28                 // Method write:(Ljava/lang/String;)V
       8: return

  public void print(float);
    Code:
       0: aload_0
       1: fload_1
       2: invokestatic  #32                 // Method java/lang/String.valueOf:(F)Ljava/lang/String;
       5: invokevirtual #28                 // Method write:(Ljava/lang/String;)V
       8: return

  public void print(double);
    Code:
       0: aload_0
       1: dload_1
       2: invokestatic  #33                 // Method java/lang/String.valueOf:(D)Ljava/lang/String;
       5: invokevirtual #28                 // Method write:(Ljava/lang/String;)V
       8: return

  public void print(char[]);
    Code:
       0: aload_0
       1: aload_1
       2: invokevirtual #34                 // Method write:([C)V
       5: return

  public void print(java.lang.String);
    Code:
       0: aload_1
       1: ifnull        9
       4: aload_0
       5: aload_1
       6: invokevirtual #28                 // Method write:(Ljava/lang/String;)V
       9: return

  public void print(java.lang.Object);
    Code:
       0: aload_1
       1: ifnull        12
       4: aload_0
       5: aload_1
       6: invokestatic  #35                 // Method java/lang/String.valueOf:(Ljava/lang/Object;)Ljava/lang/String;
       9: invokevirtual #28                 // Method write:(Ljava/lang/String;)V
      12: return

  private void newLine();
    Code:
       0: aload_0
       1: invokespecial #12                 // Method outputLogger:()V
       4: return

  public void println();
    Code:
       0: aload_0
       1: invokespecial #36                 // Method newLine:()V
       4: return

  public void println(boolean);
    Code:
       0: aload_0
       1: getfield      #11                 // Field lock:Ljava/lang/Object;
       4: dup
       5: astore_2
       6: monitorenter
       7: aload_0
       8: iload_1
       9: invokevirtual #37                 // Method print:(Z)V
      12: aload_0
      13: invokevirtual #38                 // Method println:()V
      16: aload_2
      17: monitorexit
      18: goto          26
      21: astore_3
      22: aload_2
      23: monitorexit
      24: aload_3
      25: athrow
      26: return
    Exception table:
       from    to  target type
           7    18    21   any
          21    24    21   any

  public void println(char);
    Code:
       0: aload_0
       1: getfield      #11                 // Field lock:Ljava/lang/Object;
       4: dup
       5: astore_2
       6: monitorenter
       7: aload_0
       8: iload_1
       9: invokevirtual #39                 // Method print:(C)V
      12: aload_0
      13: invokevirtual #38                 // Method println:()V
      16: aload_2
      17: monitorexit
      18: goto          26
      21: astore_3
      22: aload_2
      23: monitorexit
      24: aload_3
      25: athrow
      26: return
    Exception table:
       from    to  target type
           7    18    21   any
          21    24    21   any

  public void println(int);
    Code:
       0: aload_0
       1: getfield      #11                 // Field lock:Ljava/lang/Object;
       4: dup
       5: astore_2
       6: monitorenter
       7: aload_0
       8: iload_1
       9: invokevirtual #40                 // Method print:(I)V
      12: aload_0
      13: invokevirtual #38                 // Method println:()V
      16: aload_2
      17: monitorexit
      18: goto          26
      21: astore_3
      22: aload_2
      23: monitorexit
      24: aload_3
      25: athrow
      26: return
    Exception table:
       from    to  target type
           7    18    21   any
          21    24    21   any

  public void println(long);
    Code:
       0: aload_0
       1: getfield      #11                 // Field lock:Ljava/lang/Object;
       4: dup
       5: astore_3
       6: monitorenter
       7: aload_0
       8: lload_1
       9: invokevirtual #41                 // Method print:(J)V
      12: aload_0
      13: invokevirtual #38                 // Method println:()V
      16: aload_3
      17: monitorexit
      18: goto          28
      21: astore        4
      23: aload_3
      24: monitorexit
      25: aload         4
      27: athrow
      28: return
    Exception table:
       from    to  target type
           7    18    21   any
          21    25    21   any

  public void println(float);
    Code:
       0: aload_0
       1: getfield      #11                 // Field lock:Ljava/lang/Object;
       4: dup
       5: astore_2
       6: monitorenter
       7: aload_0
       8: fload_1
       9: invokevirtual #42                 // Method print:(F)V
      12: aload_0
      13: invokevirtual #38                 // Method println:()V
      16: aload_2
      17: monitorexit
      18: goto          26
      21: astore_3
      22: aload_2
      23: monitorexit
      24: aload_3
      25: athrow
      26: return
    Exception table:
       from    to  target type
           7    18    21   any
          21    24    21   any

  public void println(double);
    Code:
       0: aload_0
       1: getfield      #11                 // Field lock:Ljava/lang/Object;
       4: dup
       5: astore_3
       6: monitorenter
       7: aload_0
       8: dload_1
       9: invokevirtual #43                 // Method print:(D)V
      12: aload_0
      13: invokevirtual #38                 // Method println:()V
      16: aload_3
      17: monitorexit
      18: goto          28
      21: astore        4
      23: aload_3
      24: monitorexit
      25: aload         4
      27: athrow
      28: return
    Exception table:
       from    to  target type
           7    18    21   any
          21    25    21   any

  public void println(char[]);
    Code:
       0: aload_0
       1: getfield      #11                 // Field lock:Ljava/lang/Object;
       4: dup
       5: astore_2
       6: monitorenter
       7: aload_0
       8: aload_1
       9: invokevirtual #44                 // Method print:([C)V
      12: aload_0
      13: invokevirtual #38                 // Method println:()V
      16: aload_2
      17: monitorexit
      18: goto          26
      21: astore_3
      22: aload_2
      23: monitorexit
      24: aload_3
      25: athrow
      26: return
    Exception table:
       from    to  target type
           7    18    21   any
          21    24    21   any

  public void println(java.lang.String);
    Code:
       0: aload_0
       1: getfield      #11                 // Field lock:Ljava/lang/Object;
       4: dup
       5: astore_2
       6: monitorenter
       7: aload_0
       8: aload_1
       9: invokevirtual #45                 // Method print:(Ljava/lang/String;)V
      12: aload_0
      13: invokevirtual #38                 // Method println:()V
      16: aload_2
      17: monitorexit
      18: goto          26
      21: astore_3
      22: aload_2
      23: monitorexit
      24: aload_3
      25: athrow
      26: return
    Exception table:
       from    to  target type
           7    18    21   any
          21    24    21   any

  public void println(java.lang.Object);
    Code:
       0: aload_1
       1: invokestatic  #35                 // Method java/lang/String.valueOf:(Ljava/lang/Object;)Ljava/lang/String;
       4: astore_2
       5: aload_0
       6: getfield      #11                 // Field lock:Ljava/lang/Object;
       9: dup
      10: astore_3
      11: monitorenter
      12: aload_0
      13: aload_2
      14: invokevirtual #45                 // Method print:(Ljava/lang/String;)V
      17: aload_0
      18: invokevirtual #38                 // Method println:()V
      21: aload_3
      22: monitorexit
      23: goto          33
      26: astore        4
      28: aload_3
      29: monitorexit
      30: aload         4
      32: athrow
      33: return
    Exception table:
       from    to  target type
          12    23    26   any
          26    30    26   any

  public org.jboss.as.connector.services.resourceadapters.deployment.JBossLogPrintWriter printf(java.lang.String, java.lang.Object...);
    Code:
       0: aload_0
       1: aload_1
       2: aload_2
       3: invokevirtual #46                 // Method format:(Ljava/lang/String;[Ljava/lang/Object;)Lorg/jboss/as/connector/services/resourceadapters/deployment/JBossLogPrintWriter;
       6: areturn

  public org.jboss.as.connector.services.resourceadapters.deployment.JBossLogPrintWriter printf(java.util.Locale, java.lang.String, java.lang.Object...);
    Code:
       0: aload_0
       1: aload_1
       2: aload_2
       3: aload_3
       4: invokevirtual #47                 // Method format:(Ljava/util/Locale;Ljava/lang/String;[Ljava/lang/Object;)Lorg/jboss/as/connector/services/resourceadapters/deployment/JBossLogPrintWriter;
       7: areturn

  public org.jboss.as.connector.services.resourceadapters.deployment.JBossLogPrintWriter format(java.lang.String, java.lang.Object...);
    Code:
       0: aload_0
       1: getfield      #11                 // Field lock:Ljava/lang/Object;
       4: dup
       5: astore_3
       6: monitorenter
       7: aload_0
       8: getfield      #48                 // Field formatter:Ljava/util/Formatter;
      11: ifnull        27
      14: aload_0
      15: getfield      #48                 // Field formatter:Ljava/util/Formatter;
      18: invokevirtual #49                 // Method java/util/Formatter.locale:()Ljava/util/Locale;
      21: invokestatic  #50                 // Method java/util/Locale.getDefault:()Ljava/util/Locale;
      24: if_acmpeq     39
      27: aload_0
      28: new           #51                 // class java/util/Formatter
      31: dup
      32: aload_0
      33: invokespecial #52                 // Method java/util/Formatter."<init>":(Ljava/lang/Appendable;)V
      36: putfield      #48                 // Field formatter:Ljava/util/Formatter;
      39: aload_0
      40: getfield      #48                 // Field formatter:Ljava/util/Formatter;
      43: invokestatic  #50                 // Method java/util/Locale.getDefault:()Ljava/util/Locale;
      46: aload_1
      47: aload_2
      48: invokevirtual #53                 // Method java/util/Formatter.format:(Ljava/util/Locale;Ljava/lang/String;[Ljava/lang/Object;)Ljava/util/Formatter;
      51: pop
      52: aload_3
      53: monitorexit
      54: goto          64
      57: astore        4
      59: aload_3
      60: monitorexit
      61: aload         4
      63: athrow
      64: aload_0
      65: areturn
    Exception table:
       from    to  target type
           7    54    57   any
          57    61    57   any

  public org.jboss.as.connector.services.resourceadapters.deployment.JBossLogPrintWriter format(java.util.Locale, java.lang.String, java.lang.Object...);
    Code:
       0: aload_0
       1: getfield      #11                 // Field lock:Ljava/lang/Object;
       4: dup
       5: astore        4
       7: monitorenter
       8: aload_0
       9: getfield      #48                 // Field formatter:Ljava/util/Formatter;
      12: ifnull        26
      15: aload_0
      16: getfield      #48                 // Field formatter:Ljava/util/Formatter;
      19: invokevirtual #49                 // Method java/util/Formatter.locale:()Ljava/util/Locale;
      22: aload_1
      23: if_acmpeq     39
      26: aload_0
      27: new           #51                 // class java/util/Formatter
      30: dup
      31: aload_0
      32: aload_1
      33: invokespecial #54                 // Method java/util/Formatter."<init>":(Ljava/lang/Appendable;Ljava/util/Locale;)V
      36: putfield      #48                 // Field formatter:Ljava/util/Formatter;
      39: aload_0
      40: getfield      #48                 // Field formatter:Ljava/util/Formatter;
      43: aload_1
      44: aload_2
      45: aload_3
      46: invokevirtual #53                 // Method java/util/Formatter.format:(Ljava/util/Locale;Ljava/lang/String;[Ljava/lang/Object;)Ljava/util/Formatter;
      49: pop
      50: aload         4
      52: monitorexit
      53: goto          64
      56: astore        5
      58: aload         4
      60: monitorexit
      61: aload         5
      63: athrow
      64: aload_0
      65: areturn
    Exception table:
       from    to  target type
           8    53    56   any
          56    61    56   any

  public org.jboss.as.connector.services.resourceadapters.deployment.JBossLogPrintWriter append(java.lang.CharSequence);
    Code:
       0: aload_1
       1: ifnull        14
       4: aload_0
       5: aload_1
       6: invokeinterface #55,  1           // InterfaceMethod java/lang/CharSequence.toString:()Ljava/lang/String;
      11: invokevirtual #28                 // Method write:(Ljava/lang/String;)V
      14: aload_0
      15: areturn

  public org.jboss.as.connector.services.resourceadapters.deployment.JBossLogPrintWriter append(java.lang.CharSequence, int, int);
    Code:
       0: aload_1
       1: ifnull        21
       4: aload_0
       5: aload_1
       6: iload_2
       7: iload_3
       8: invokeinterface #56,  3           // InterfaceMethod java/lang/CharSequence.subSequence:(II)Ljava/lang/CharSequence;
      13: invokeinterface #55,  1           // InterfaceMethod java/lang/CharSequence.toString:()Ljava/lang/String;
      18: invokevirtual #28                 // Method write:(Ljava/lang/String;)V
      21: aload_0
      22: areturn

  public org.jboss.as.connector.services.resourceadapters.deployment.JBossLogPrintWriter append(char);
    Code:
       0: aload_0
       1: iload_1
       2: invokevirtual #29                 // Method write:(I)V
       5: aload_0
       6: areturn

  public java.io.PrintWriter append(char);
    Code:
       0: aload_0
       1: iload_1
       2: invokevirtual #57                 // Method append:(C)Lorg/jboss/as/connector/services/resourceadapters/deployment/JBossLogPrintWriter;
       5: areturn

  public java.io.PrintWriter append(java.lang.CharSequence, int, int);
    Code:
       0: aload_0
       1: aload_1
       2: iload_2
       3: iload_3
       4: invokevirtual #58                 // Method append:(Ljava/lang/CharSequence;II)Lorg/jboss/as/connector/services/resourceadapters/deployment/JBossLogPrintWriter;
       7: areturn

  public java.io.PrintWriter append(java.lang.CharSequence);
    Code:
       0: aload_0
       1: aload_1
       2: invokevirtual #59                 // Method append:(Ljava/lang/CharSequence;)Lorg/jboss/as/connector/services/resourceadapters/deployment/JBossLogPrintWriter;
       5: areturn

  public java.io.PrintWriter format(java.util.Locale, java.lang.String, java.lang.Object[]);
    Code:
       0: aload_0
       1: aload_1
       2: aload_2
       3: aload_3
       4: invokevirtual #47                 // Method format:(Ljava/util/Locale;Ljava/lang/String;[Ljava/lang/Object;)Lorg/jboss/as/connector/services/resourceadapters/deployment/JBossLogPrintWriter;
       7: areturn

  public java.io.PrintWriter format(java.lang.String, java.lang.Object[]);
    Code:
       0: aload_0
       1: aload_1
       2: aload_2
       3: invokevirtual #46                 // Method format:(Ljava/lang/String;[Ljava/lang/Object;)Lorg/jboss/as/connector/services/resourceadapters/deployment/JBossLogPrintWriter;
       6: areturn

  public java.io.PrintWriter printf(java.util.Locale, java.lang.String, java.lang.Object[]);
    Code:
       0: aload_0
       1: aload_1
       2: aload_2
       3: aload_3
       4: invokevirtual #60                 // Method printf:(Ljava/util/Locale;Ljava/lang/String;[Ljava/lang/Object;)Lorg/jboss/as/connector/services/resourceadapters/deployment/JBossLogPrintWriter;
       7: areturn

  public java.io.PrintWriter printf(java.lang.String, java.lang.Object[]);
    Code:
       0: aload_0
       1: aload_1
       2: aload_2
       3: invokevirtual #61                 // Method printf:(Ljava/lang/String;[Ljava/lang/Object;)Lorg/jboss/as/connector/services/resourceadapters/deployment/JBossLogPrintWriter;
       6: areturn

  public java.io.Writer append(char) throws java.io.IOException;
    Code:
       0: aload_0
       1: iload_1
       2: invokevirtual #57                 // Method append:(C)Lorg/jboss/as/connector/services/resourceadapters/deployment/JBossLogPrintWriter;
       5: areturn

  public java.io.Writer append(java.lang.CharSequence, int, int) throws java.io.IOException;
    Code:
       0: aload_0
       1: aload_1
       2: iload_2
       3: iload_3
       4: invokevirtual #58                 // Method append:(Ljava/lang/CharSequence;II)Lorg/jboss/as/connector/services/resourceadapters/deployment/JBossLogPrintWriter;
       7: areturn

  public java.io.Writer append(java.lang.CharSequence) throws java.io.IOException;
    Code:
       0: aload_0
       1: aload_1
       2: invokevirtual #59                 // Method append:(Ljava/lang/CharSequence;)Lorg/jboss/as/connector/services/resourceadapters/deployment/JBossLogPrintWriter;
       5: areturn

  public java.lang.Appendable append(char) throws java.io.IOException;
    Code:
       0: aload_0
       1: iload_1
       2: invokevirtual #57                 // Method append:(C)Lorg/jboss/as/connector/services/resourceadapters/deployment/JBossLogPrintWriter;
       5: areturn

  public java.lang.Appendable append(java.lang.CharSequence, int, int) throws java.io.IOException;
    Code:
       0: aload_0
       1: aload_1
       2: iload_2
       3: iload_3
       4: invokevirtual #58                 // Method append:(Ljava/lang/CharSequence;II)Lorg/jboss/as/connector/services/resourceadapters/deployment/JBossLogPrintWriter;
       7: areturn

  public java.lang.Appendable append(java.lang.CharSequence) throws java.io.IOException;
    Code:
       0: aload_0
       1: aload_1
       2: invokevirtual #59                 // Method append:(Ljava/lang/CharSequence;)Lorg/jboss/as/connector/services/resourceadapters/deployment/JBossLogPrintWriter;
       5: areturn
}
