Compiled from "PoolingConnectionFactoryBean.java"
public class org.springframework.boot.jta.bitronix.PoolingConnectionFactoryBean$DirectXAConnectionFactory implements javax.jms.XAConnectionFactory {
  private final javax.jms.XAConnectionFactory connectionFactory;

  public org.springframework.boot.jta.bitronix.PoolingConnectionFactoryBean$DirectXAConnectionFactory();
    Code:
       0: aload_0
       1: invokespecial #1                  // Method java/lang/Object."<init>":()V
       4: aload_0
       5: invokestatic  #2                  // Method org/springframework/boot/jta/bitronix/PoolingConnectionFactoryBean.access$000:()Ljava/lang/ThreadLocal;
       8: invokevirtual #3                  // Method java/lang/ThreadLocal.get:()Ljava/lang/Object;
      11: checkcast     #4                  // class org/springframework/boot/jta/bitronix/PoolingConnectionFactoryBean
      14: invokestatic  #5                  // Method org/springframework/boot/jta/bitronix/PoolingConnectionFactoryBean.access$100:(Lorg/springframework/boot/jta/bitronix/PoolingConnectionFactoryBean;)Ljavax/jms/XAConnectionFactory;
      17: putfield      #6                  // Field connectionFactory:Ljavax/jms/XAConnectionFactory;
      20: return

  public javax.jms.XAConnection createXAConnection() throws javax.jms.JMSException;
    Code:
       0: aload_0
       1: getfield      #6                  // Field connectionFactory:Ljavax/jms/XAConnectionFactory;
       4: invokeinterface #7,  1            // InterfaceMethod javax/jms/XAConnectionFactory.createXAConnection:()Ljavax/jms/XAConnection;
       9: areturn

  public javax.jms.XAConnection createXAConnection(java.lang.String, java.lang.String) throws javax.jms.JMSException;
    Code:
       0: aload_0
       1: getfield      #6                  // Field connectionFactory:Ljavax/jms/XAConnectionFactory;
       4: aload_1
       5: aload_2
       6: invokeinterface #8,  3            // InterfaceMethod javax/jms/XAConnectionFactory.createXAConnection:(Ljava/lang/String;Ljava/lang/String;)Ljavax/jms/XAConnection;
      11: areturn

  public javax.jms.XAConnectionFactory getConnectionFactory();
    Code:
       0: aload_0
       1: getfield      #6                  // Field connectionFactory:Ljavax/jms/XAConnectionFactory;
       4: areturn
}
