Compiled from "CustomResourceDefinitionFluentImpl.java"
public class io.fabric8.kubernetes.api.model.apiextensions.CustomResourceDefinitionFluentImpl$SpecNestedImpl<N> extends io.fabric8.kubernetes.api.model.apiextensions.CustomResourceDefinitionSpecFluentImpl<io.fabric8.kubernetes.api.model.apiextensions.CustomResourceDefinitionFluent$SpecNested<N>> implements io.fabric8.kubernetes.api.model.apiextensions.CustomResourceDefinitionFluent$SpecNested<N>, io.fabric8.kubernetes.api.builder.Nested<N> {
  private final io.fabric8.kubernetes.api.model.apiextensions.CustomResourceDefinitionSpecBuilder builder;

  final io.fabric8.kubernetes.api.model.apiextensions.CustomResourceDefinitionFluentImpl this$0;

  io.fabric8.kubernetes.api.model.apiextensions.CustomResourceDefinitionFluentImpl$SpecNestedImpl(io.fabric8.kubernetes.api.model.apiextensions.CustomResourceDefinitionFluentImpl, io.fabric8.kubernetes.api.model.apiextensions.CustomResourceDefinitionSpec);
    Code:
       0: aload_0
       1: aload_1
       2: putfield      #1                  // Field this$0:Lio/fabric8/kubernetes/api/model/apiextensions/CustomResourceDefinitionFluentImpl;
       5: aload_0
       6: invokespecial #2                  // Method io/fabric8/kubernetes/api/model/apiextensions/CustomResourceDefinitionSpecFluentImpl."<init>":()V
       9: aload_0
      10: new           #3                  // class io/fabric8/kubernetes/api/model/apiextensions/CustomResourceDefinitionSpecBuilder
      13: dup
      14: aload_0
      15: aload_2
      16: invokespecial #4                  // Method io/fabric8/kubernetes/api/model/apiextensions/CustomResourceDefinitionSpecBuilder."<init>":(Lio/fabric8/kubernetes/api/model/apiextensions/CustomResourceDefinitionSpecFluent;Lio/fabric8/kubernetes/api/model/apiextensions/CustomResourceDefinitionSpec;)V
      19: putfield      #5                  // Field builder:Lio/fabric8/kubernetes/api/model/apiextensions/CustomResourceDefinitionSpecBuilder;
      22: return

  io.fabric8.kubernetes.api.model.apiextensions.CustomResourceDefinitionFluentImpl$SpecNestedImpl(io.fabric8.kubernetes.api.model.apiextensions.CustomResourceDefinitionFluentImpl);
    Code:
       0: aload_0
       1: aload_1
       2: putfield      #1                  // Field this$0:Lio/fabric8/kubernetes/api/model/apiextensions/CustomResourceDefinitionFluentImpl;
       5: aload_0
       6: invokespecial #2                  // Method io/fabric8/kubernetes/api/model/apiextensions/CustomResourceDefinitionSpecFluentImpl."<init>":()V
       9: aload_0
      10: new           #3                  // class io/fabric8/kubernetes/api/model/apiextensions/CustomResourceDefinitionSpecBuilder
      13: dup
      14: aload_0
      15: invokespecial #6                  // Method io/fabric8/kubernetes/api/model/apiextensions/CustomResourceDefinitionSpecBuilder."<init>":(Lio/fabric8/kubernetes/api/model/apiextensions/CustomResourceDefinitionSpecFluent;)V
      18: putfield      #5                  // Field builder:Lio/fabric8/kubernetes/api/model/apiextensions/CustomResourceDefinitionSpecBuilder;
      21: return

  public N and();
    Code:
       0: aload_0
       1: getfield      #1                  // Field this$0:Lio/fabric8/kubernetes/api/model/apiextensions/CustomResourceDefinitionFluentImpl;
       4: aload_0
       5: getfield      #5                  // Field builder:Lio/fabric8/kubernetes/api/model/apiextensions/CustomResourceDefinitionSpecBuilder;
       8: invokevirtual #7                  // Method io/fabric8/kubernetes/api/model/apiextensions/CustomResourceDefinitionSpecBuilder.build:()Lio/fabric8/kubernetes/api/model/apiextensions/CustomResourceDefinitionSpec;
      11: invokevirtual #8                  // Method io/fabric8/kubernetes/api/model/apiextensions/CustomResourceDefinitionFluentImpl.withSpec:(Lio/fabric8/kubernetes/api/model/apiextensions/CustomResourceDefinitionSpec;)Lio/fabric8/kubernetes/api/model/apiextensions/CustomResourceDefinitionFluent;
      14: areturn

  public N endSpec();
    Code:
       0: aload_0
       1: invokevirtual #9                  // Method and:()Ljava/lang/Object;
       4: areturn
}
