Compiled from "Watcher.scala"
public class fs2.io.Watcher$EventType$ {
  public static fs2.io.Watcher$EventType$ MODULE$;

  public static {};
    Code:
       0: new           #2                  // class fs2/io/Watcher$EventType$
       3: invokespecial #41                 // Method "<init>":()V
       6: return

  public java.nio.file.WatchEvent$Kind<?> toWatchEventKind(fs2.io.Watcher$EventType);
    Code:
       0: aload_1
       1: astore_3
       2: getstatic     #48                 // Field fs2/io/Watcher$EventType$Created$.MODULE$:Lfs2/io/Watcher$EventType$Created$;
       5: aload_3
       6: invokevirtual #52                 // Method java/lang/Object.equals:(Ljava/lang/Object;)Z
       9: ifeq          19
      12: getstatic     #58                 // Field java/nio/file/StandardWatchEventKinds.ENTRY_CREATE:Ljava/nio/file/WatchEvent$Kind;
      15: astore_2
      16: goto          120
      19: goto          22
      22: getstatic     #61                 // Field fs2/io/Watcher$EventType$Modified$.MODULE$:Lfs2/io/Watcher$EventType$Modified$;
      25: aload_3
      26: invokevirtual #52                 // Method java/lang/Object.equals:(Ljava/lang/Object;)Z
      29: ifeq          39
      32: getstatic     #64                 // Field java/nio/file/StandardWatchEventKinds.ENTRY_MODIFY:Ljava/nio/file/WatchEvent$Kind;
      35: astore_2
      36: goto          120
      39: goto          42
      42: getstatic     #67                 // Field fs2/io/Watcher$EventType$Deleted$.MODULE$:Lfs2/io/Watcher$EventType$Deleted$;
      45: aload_3
      46: invokevirtual #52                 // Method java/lang/Object.equals:(Ljava/lang/Object;)Z
      49: ifeq          59
      52: getstatic     #70                 // Field java/nio/file/StandardWatchEventKinds.ENTRY_DELETE:Ljava/nio/file/WatchEvent$Kind;
      55: astore_2
      56: goto          120
      59: goto          62
      62: getstatic     #73                 // Field fs2/io/Watcher$EventType$Overflow$.MODULE$:Lfs2/io/Watcher$EventType$Overflow$;
      65: aload_3
      66: invokevirtual #52                 // Method java/lang/Object.equals:(Ljava/lang/Object;)Z
      69: ifeq          79
      72: getstatic     #76                 // Field java/nio/file/StandardWatchEventKinds.OVERFLOW:Ljava/nio/file/WatchEvent$Kind;
      75: astore_2
      76: goto          120
      79: goto          82
      82: aload_3
      83: instanceof    #22                 // class fs2/io/Watcher$EventType$NonStandard
      86: ifeq          108
      89: aload_3
      90: checkcast     #22                 // class fs2/io/Watcher$EventType$NonStandard
      93: astore        4
      95: aload         4
      97: invokevirtual #80                 // Method fs2/io/Watcher$EventType$NonStandard.kind:()Ljava/nio/file/WatchEvent$Kind;
     100: astore        5
     102: aload         5
     104: astore_2
     105: goto          120
     108: goto          111
     111: new           #82                 // class scala/MatchError
     114: dup
     115: aload_3
     116: invokespecial #85                 // Method scala/MatchError."<init>":(Ljava/lang/Object;)V
     119: athrow
     120: aload_2
     121: areturn

  public fs2.io.Watcher$EventType$();
    Code:
       0: aload_0
       1: invokespecial #88                 // Method java/lang/Object."<init>":()V
       4: aload_0
       5: putstatic     #90                 // Field MODULE$:Lfs2/io/Watcher$EventType$;
       8: return
}
