Compiled from "RemoteTerminalServer.java"
public class apdu4j.remote.RemoteTerminalServer {
  private static org.slf4j.Logger logger;

  private static final java.lang.String BACKLOG;

  private static final java.lang.String HTTPPOOL;

  private static final java.lang.String SESSIONS;

  private static final java.lang.String THREADTIMEOUT;

  private static final java.lang.String BACKENDPOOL;

  private final java.util.concurrent.ConcurrentHashMap<java.util.UUID, apdu4j.remote.RemoteTerminalServer$Session> sessions;

  private final java.util.concurrent.ExecutorService e;

  private final java.lang.Class<? extends apdu4j.remote.RemoteTerminalThread> processor;

  private com.sun.net.httpserver.HttpServer server;

  public apdu4j.remote.RemoteTerminalServer(java.lang.Class<? extends apdu4j.remote.RemoteTerminalThread>);
    Code:
       0: aload_0
       1: invokespecial #6                  // Method java/lang/Object."<init>":()V
       4: aload_0
       5: ldc           #8                  // String apdu4j.remote.http.threadpool
       7: ldc           #9                  // String 200
       9: invokestatic  #10                 // Method java/lang/System.getProperty:(Ljava/lang/String;Ljava/lang/String;)Ljava/lang/String;
      12: invokestatic  #11                 // Method java/lang/Integer.valueOf:(Ljava/lang/String;)Ljava/lang/Integer;
      15: invokevirtual #12                 // Method java/lang/Integer.intValue:()I
      18: invokestatic  #13                 // Method java/util/concurrent/Executors.newFixedThreadPool:(I)Ljava/util/concurrent/ExecutorService;
      21: putfield      #2                  // Field e:Ljava/util/concurrent/ExecutorService;
      24: aload_0
      25: new           #14                 // class java/util/concurrent/ConcurrentHashMap
      28: dup
      29: ldc           #15                 // String apdu4j.remote.http.maxsessions
      31: ldc           #9                  // String 200
      33: invokestatic  #10                 // Method java/lang/System.getProperty:(Ljava/lang/String;Ljava/lang/String;)Ljava/lang/String;
      36: invokestatic  #11                 // Method java/lang/Integer.valueOf:(Ljava/lang/String;)Ljava/lang/Integer;
      39: invokevirtual #12                 // Method java/lang/Integer.intValue:()I
      42: invokespecial #16                 // Method java/util/concurrent/ConcurrentHashMap."<init>":(I)V
      45: putfield      #1                  // Field sessions:Ljava/util/concurrent/ConcurrentHashMap;
      48: aload_0
      49: aload_1
      50: putfield      #3                  // Field processor:Ljava/lang/Class;
      53: return

  public static void drop(com.sun.net.httpserver.HttpExchange) throws java.io.IOException;
    Code:
       0: aload_0
       1: invokestatic  #4                  // Method setStandardHeaders:(Lcom/sun/net/httpserver/HttpExchange;)V
       4: aload_0
       5: sipush        418
       8: lconst_0
       9: invokevirtual #17                 // Method com/sun/net/httpserver/HttpExchange.sendResponseHeaders:(IJ)V
      12: aload_0
      13: invokevirtual #18                 // Method com/sun/net/httpserver/HttpExchange.getResponseBody:()Ljava/io/OutputStream;
      16: astore_1
      17: aconst_null
      18: astore_2
      19: aload_1
      20: new           #19                 // class java/lang/StringBuilder
      23: dup
      24: invokespecial #20                 // Method java/lang/StringBuilder."<init>":()V
      27: ldc           #21                 // String apdu4j/
      29: invokevirtual #22                 // Method java/lang/StringBuilder.append:(Ljava/lang/String;)Ljava/lang/StringBuilder;
      32: invokestatic  #23                 // Method apdu4j/SCTool.getVersion:()Ljava/lang/String;
      35: invokevirtual #22                 // Method java/lang/StringBuilder.append:(Ljava/lang/String;)Ljava/lang/StringBuilder;
      38: invokevirtual #24                 // Method java/lang/StringBuilder.toString:()Ljava/lang/String;
      41: invokevirtual #25                 // Method java/lang/String.getBytes:()[B
      44: invokevirtual #26                 // Method java/io/OutputStream.write:([B)V
      47: aload_1
      48: ifnull        118
      51: aload_2
      52: ifnull        71
      55: aload_1
      56: invokevirtual #27                 // Method java/io/OutputStream.close:()V
      59: goto          118
      62: astore_3
      63: aload_2
      64: aload_3
      65: invokevirtual #29                 // Method java/lang/Throwable.addSuppressed:(Ljava/lang/Throwable;)V
      68: goto          118
      71: aload_1
      72: invokevirtual #27                 // Method java/io/OutputStream.close:()V
      75: goto          118
      78: astore_3
      79: aload_3
      80: astore_2
      81: aload_3
      82: athrow
      83: astore        4
      85: aload_1
      86: ifnull        115
      89: aload_2
      90: ifnull        111
      93: aload_1
      94: invokevirtual #27                 // Method java/io/OutputStream.close:()V
      97: goto          115
     100: astore        5
     102: aload_2
     103: aload         5
     105: invokevirtual #29                 // Method java/lang/Throwable.addSuppressed:(Ljava/lang/Throwable;)V
     108: goto          115
     111: aload_1
     112: invokevirtual #27                 // Method java/io/OutputStream.close:()V
     115: aload         4
     117: athrow
     118: return
    Exception table:
       from    to  target type
          55    59    62   Class java/lang/Throwable
          19    47    78   Class java/lang/Throwable
          19    47    83   any
          93    97   100   Class java/lang/Throwable
          78    85    83   any

  public void start(java.net.InetSocketAddress) throws java.io.IOException;
    Code:
       0: aload_0
       1: aload_1
       2: ldc           #30                 // String apdu4j.remote.http.backlog
       4: ldc           #31                 // String 10
       6: invokestatic  #10                 // Method java/lang/System.getProperty:(Ljava/lang/String;Ljava/lang/String;)Ljava/lang/String;
       9: invokestatic  #11                 // Method java/lang/Integer.valueOf:(Ljava/lang/String;)Ljava/lang/Integer;
      12: invokevirtual #12                 // Method java/lang/Integer.intValue:()I
      15: invokestatic  #32                 // Method com/sun/net/httpserver/HttpServer.create:(Ljava/net/InetSocketAddress;I)Lcom/sun/net/httpserver/HttpServer;
      18: putfield      #33                 // Field server:Lcom/sun/net/httpserver/HttpServer;
      21: aload_0
      22: getfield      #33                 // Field server:Lcom/sun/net/httpserver/HttpServer;
      25: ldc           #8                  // String apdu4j.remote.http.threadpool
      27: ldc           #31                 // String 10
      29: invokestatic  #10                 // Method java/lang/System.getProperty:(Ljava/lang/String;Ljava/lang/String;)Ljava/lang/String;
      32: invokestatic  #11                 // Method java/lang/Integer.valueOf:(Ljava/lang/String;)Ljava/lang/Integer;
      35: invokevirtual #12                 // Method java/lang/Integer.intValue:()I
      38: invokestatic  #34                 // Method java/util/concurrent/Executors.newWorkStealingPool:(I)Ljava/util/concurrent/ExecutorService;
      41: invokevirtual #35                 // Method com/sun/net/httpserver/HttpServer.setExecutor:(Ljava/util/concurrent/Executor;)V
      44: aload_0
      45: getfield      #33                 // Field server:Lcom/sun/net/httpserver/HttpServer;
      48: ldc           #36                 // String /
      50: new           #37                 // class apdu4j/remote/RemoteTerminalServer$MsgHandler
      53: dup
      54: aload_0
      55: aconst_null
      56: invokespecial #38                 // Method apdu4j/remote/RemoteTerminalServer$MsgHandler."<init>":(Lapdu4j/remote/RemoteTerminalServer;Lapdu4j/remote/RemoteTerminalServer$1;)V
      59: invokevirtual #39                 // Method com/sun/net/httpserver/HttpServer.createContext:(Ljava/lang/String;Lcom/sun/net/httpserver/HttpHandler;)Lcom/sun/net/httpserver/HttpContext;
      62: pop
      63: aload_0
      64: getfield      #33                 // Field server:Lcom/sun/net/httpserver/HttpServer;
      67: ldc           #40                 // String /status
      69: new           #41                 // class apdu4j/remote/RemoteTerminalServer$StatusHandler
      72: dup
      73: aload_0
      74: aconst_null
      75: invokespecial #42                 // Method apdu4j/remote/RemoteTerminalServer$StatusHandler."<init>":(Lapdu4j/remote/RemoteTerminalServer;Lapdu4j/remote/RemoteTerminalServer$1;)V
      78: invokevirtual #39                 // Method com/sun/net/httpserver/HttpServer.createContext:(Ljava/lang/String;Lcom/sun/net/httpserver/HttpHandler;)Lcom/sun/net/httpserver/HttpContext;
      81: pop
      82: getstatic     #5                  // Field logger:Lorg/slf4j/Logger;
      85: ldc           #43                 // String Server started on {}
      87: aload_0
      88: getfield      #33                 // Field server:Lcom/sun/net/httpserver/HttpServer;
      91: invokevirtual #44                 // Method com/sun/net/httpserver/HttpServer.getAddress:()Ljava/net/InetSocketAddress;
      94: invokeinterface #45,  3           // InterfaceMethod org/slf4j/Logger.info:(Ljava/lang/String;Ljava/lang/Object;)V
      99: aload_0
     100: getfield      #33                 // Field server:Lcom/sun/net/httpserver/HttpServer;
     103: invokevirtual #46                 // Method com/sun/net/httpserver/HttpServer.start:()V
     106: return

  public void stop(int);
    Code:
       0: aload_0
       1: getfield      #33                 // Field server:Lcom/sun/net/httpserver/HttpServer;
       4: iload_1
       5: invokevirtual #47                 // Method com/sun/net/httpserver/HttpServer.stop:(I)V
       8: return

  public void gc(long);
    Code:
       0: aload_0
       1: getfield      #1                  // Field sessions:Ljava/util/concurrent/ConcurrentHashMap;
       4: invokevirtual #48                 // Method java/util/concurrent/ConcurrentHashMap.values:()Ljava/util/Collection;
       7: invokeinterface #49,  1           // InterfaceMethod java/util/Collection.iterator:()Ljava/util/Iterator;
      12: astore_3
      13: aload_3
      14: invokeinterface #50,  1           // InterfaceMethod java/util/Iterator.hasNext:()Z
      19: ifeq          74
      22: aload_3
      23: invokeinterface #51,  1           // InterfaceMethod java/util/Iterator.next:()Ljava/lang/Object;
      28: checkcast     #52                 // class apdu4j/remote/RemoteTerminalServer$Session
      31: astore        4
      33: aload         4
      35: getfield      #53                 // Field apdu4j/remote/RemoteTerminalServer$Session.timestamp:J
      38: lload_1
      39: lcmp
      40: ifge          71
      43: getstatic     #5                  // Field logger:Lorg/slf4j/Logger;
      46: ldc           #54                 // String Pruning session: {}
      48: aload         4
      50: getfield      #55                 // Field apdu4j/remote/RemoteTerminalServer$Session.id:Ljava/util/UUID;
      53: invokeinterface #56,  3           // InterfaceMethod org/slf4j/Logger.debug:(Ljava/lang/String;Ljava/lang/Object;)V
      58: aload_0
      59: getfield      #1                  // Field sessions:Ljava/util/concurrent/ConcurrentHashMap;
      62: aload         4
      64: getfield      #55                 // Field apdu4j/remote/RemoteTerminalServer$Session.id:Ljava/util/UUID;
      67: invokevirtual #57                 // Method java/util/concurrent/ConcurrentHashMap.remove:(Ljava/lang/Object;)Ljava/lang/Object;
      70: pop
      71: goto          13
      74: return

  private static void setStandardHeaders(com.sun.net.httpserver.HttpExchange);
    Code:
       0: aload_0
       1: invokevirtual #58                 // Method com/sun/net/httpserver/HttpExchange.getResponseHeaders:()Lcom/sun/net/httpserver/Headers;
       4: astore_1
       5: aload_1
       6: ldc           #59                 // String Server
       8: new           #19                 // class java/lang/StringBuilder
      11: dup
      12: invokespecial #20                 // Method java/lang/StringBuilder."<init>":()V
      15: ldc           #21                 // String apdu4j/
      17: invokevirtual #22                 // Method java/lang/StringBuilder.append:(Ljava/lang/String;)Ljava/lang/StringBuilder;
      20: invokestatic  #23                 // Method apdu4j/SCTool.getVersion:()Ljava/lang/String;
      23: invokevirtual #22                 // Method java/lang/StringBuilder.append:(Ljava/lang/String;)Ljava/lang/StringBuilder;
      26: invokevirtual #24                 // Method java/lang/StringBuilder.toString:()Ljava/lang/String;
      29: invokevirtual #60                 // Method com/sun/net/httpserver/Headers.set:(Ljava/lang/String;Ljava/lang/String;)V
      32: return

  static org.slf4j.Logger access$200();
    Code:
       0: getstatic     #5                  // Field logger:Lorg/slf4j/Logger;
       3: areturn

  static void access$300(com.sun.net.httpserver.HttpExchange);
    Code:
       0: aload_0
       1: invokestatic  #4                  // Method setStandardHeaders:(Lcom/sun/net/httpserver/HttpExchange;)V
       4: return

  static java.lang.Class access$400(apdu4j.remote.RemoteTerminalServer);
    Code:
       0: aload_0
       1: getfield      #3                  // Field processor:Ljava/lang/Class;
       4: areturn

  static java.util.concurrent.ExecutorService access$500(apdu4j.remote.RemoteTerminalServer);
    Code:
       0: aload_0
       1: getfield      #2                  // Field e:Ljava/util/concurrent/ExecutorService;
       4: areturn

  static java.util.concurrent.ConcurrentHashMap access$600(apdu4j.remote.RemoteTerminalServer);
    Code:
       0: aload_0
       1: getfield      #1                  // Field sessions:Ljava/util/concurrent/ConcurrentHashMap;
       4: areturn

  static {};
    Code:
       0: ldc           #7                  // class apdu4j/remote/RemoteTerminalServer
       2: invokestatic  #61                 // Method org/slf4j/LoggerFactory.getLogger:(Ljava/lang/Class;)Lorg/slf4j/Logger;
       5: putstatic     #5                  // Field logger:Lorg/slf4j/Logger;
       8: return
}
