Compiled from "PluginContextImpl.java"
public class org.sonarsource.sonarlint.core.plugin.commons.sonarapi.PluginContextImpl$Builder {
  private org.sonarsource.sonarlint.plugin.api.SonarLintRuntime sonarRuntime;

  private org.sonar.api.config.Configuration bootConfiguration;

  public org.sonarsource.sonarlint.core.plugin.commons.sonarapi.PluginContextImpl$Builder();
    Code:
       0: aload_0
       1: invokespecial #21                 // Method java/lang/Object."<init>":()V
       4: return

  public org.sonarsource.sonarlint.core.plugin.commons.sonarapi.PluginContextImpl$Builder setSonarRuntime(org.sonarsource.sonarlint.plugin.api.SonarLintRuntime);
    Code:
       0: aload_0
       1: aload_1
       2: putfield      #27                 // Field sonarRuntime:Lorg/sonarsource/sonarlint/plugin/api/SonarLintRuntime;
       5: aload_0
       6: areturn

  public org.sonarsource.sonarlint.core.plugin.commons.sonarapi.PluginContextImpl$Builder setBootConfiguration(org.sonar.api.config.Configuration);
    Code:
       0: aload_0
       1: aload_1
       2: putfield      #32                 // Field bootConfiguration:Lorg/sonar/api/config/Configuration;
       5: aload_0
       6: areturn

  public org.sonar.api.Plugin$Context build();
    Code:
       0: aload_0
       1: getfield      #32                 // Field bootConfiguration:Lorg/sonar/api/config/Configuration;
       4: ldc           #37                 // String bootConfiguration is mandatory
       6: invokestatic  #43                 // Method java/util/Objects.requireNonNull:(Ljava/lang/Object;Ljava/lang/String;)Ljava/lang/Object;
       9: pop
      10: new           #7                  // class org/sonarsource/sonarlint/core/plugin/commons/sonarapi/PluginContextImpl
      13: dup
      14: aload_0
      15: invokespecial #46                 // Method org/sonarsource/sonarlint/core/plugin/commons/sonarapi/PluginContextImpl."<init>":(Lorg/sonarsource/sonarlint/core/plugin/commons/sonarapi/PluginContextImpl$Builder;)V
      18: areturn
}
