Compiled from "JMSFaultFactory.java"
public final class org.apache.cxf.binding.soap.jms.interceptor.JMSFaultFactory {
  static final java.util.logging.Logger LOG;

  private org.apache.cxf.binding.soap.jms.interceptor.JMSFaultFactory();
    Code:
       0: aload_0
       1: invokespecial #1                  // Method java/lang/Object."<init>":()V
       4: return

  public static org.apache.cxf.binding.soap.jms.interceptor.JMSFault createContentTypeMismatchFault(java.lang.String);
    Code:
       0: new           #2                  // class org/apache/cxf/common/i18n/Message
       3: dup
       4: ldc           #3                  // String CONTENTTYPE_MISMATCH
       6: getstatic     #4                  // Field LOG:Ljava/util/logging/Logger;
       9: iconst_1
      10: anewarray     #5                  // class java/lang/Object
      13: dup
      14: iconst_0
      15: aload_0
      16: aastore
      17: invokespecial #6                  // Method org/apache/cxf/common/i18n/Message."<init>":(Ljava/lang/String;Ljava/util/logging/Logger;[Ljava/lang/Object;)V
      20: invokevirtual #7                  // Method org/apache/cxf/common/i18n/Message.toString:()Ljava/lang/String;
      23: astore_1
      24: invokestatic  #8                  // Method org/apache/cxf/binding/soap/jms/interceptor/SoapJMSConstants.getContentTypeMismatchQName:()Ljavax/xml/namespace/QName;
      27: aload_1
      28: invokestatic  #9                  // Method createFault:(Ljavax/xml/namespace/QName;Ljava/lang/String;)Lorg/apache/cxf/binding/soap/jms/interceptor/JMSFault;
      31: areturn

  public static org.apache.cxf.binding.soap.jms.interceptor.JMSFault createContentEncodingNotSupported(java.lang.String);
    Code:
       0: new           #2                  // class org/apache/cxf/common/i18n/Message
       3: dup
       4: ldc           #10                 // String CONTENT_ENCODING_NOT_SUPPORTED
       6: getstatic     #4                  // Field LOG:Ljava/util/logging/Logger;
       9: iconst_1
      10: anewarray     #5                  // class java/lang/Object
      13: dup
      14: iconst_0
      15: aload_0
      16: aastore
      17: invokespecial #6                  // Method org/apache/cxf/common/i18n/Message."<init>":(Ljava/lang/String;Ljava/util/logging/Logger;[Ljava/lang/Object;)V
      20: invokevirtual #7                  // Method org/apache/cxf/common/i18n/Message.toString:()Ljava/lang/String;
      23: astore_1
      24: invokestatic  #8                  // Method org/apache/cxf/binding/soap/jms/interceptor/SoapJMSConstants.getContentTypeMismatchQName:()Ljavax/xml/namespace/QName;
      27: aload_1
      28: invokestatic  #9                  // Method createFault:(Ljavax/xml/namespace/QName;Ljava/lang/String;)Lorg/apache/cxf/binding/soap/jms/interceptor/JMSFault;
      31: areturn

  public static org.apache.cxf.binding.soap.jms.interceptor.JMSFault createMalformedRequestURIFault(java.lang.String);
    Code:
       0: new           #2                  // class org/apache/cxf/common/i18n/Message
       3: dup
       4: ldc           #11                 // String MALFORMED_REQUESTURI
       6: getstatic     #4                  // Field LOG:Ljava/util/logging/Logger;
       9: iconst_1
      10: anewarray     #5                  // class java/lang/Object
      13: dup
      14: iconst_0
      15: aload_0
      16: aastore
      17: invokespecial #6                  // Method org/apache/cxf/common/i18n/Message."<init>":(Ljava/lang/String;Ljava/util/logging/Logger;[Ljava/lang/Object;)V
      20: invokevirtual #7                  // Method org/apache/cxf/common/i18n/Message.toString:()Ljava/lang/String;
      23: astore_1
      24: invokestatic  #12                 // Method org/apache/cxf/binding/soap/jms/interceptor/SoapJMSConstants.getMalformedRequestURIQName:()Ljavax/xml/namespace/QName;
      27: aload_1
      28: invokestatic  #9                  // Method createFault:(Ljavax/xml/namespace/QName;Ljava/lang/String;)Lorg/apache/cxf/binding/soap/jms/interceptor/JMSFault;
      31: areturn

  public static org.apache.cxf.binding.soap.jms.interceptor.JMSFault createMismatchedSoapActionFault(java.lang.String);
    Code:
       0: new           #2                  // class org/apache/cxf/common/i18n/Message
       3: dup
       4: ldc           #13                 // String MISMATCHED_SOAPACTION
       6: getstatic     #4                  // Field LOG:Ljava/util/logging/Logger;
       9: iconst_1
      10: anewarray     #5                  // class java/lang/Object
      13: dup
      14: iconst_0
      15: aload_0
      16: aastore
      17: invokespecial #6                  // Method org/apache/cxf/common/i18n/Message."<init>":(Ljava/lang/String;Ljava/util/logging/Logger;[Ljava/lang/Object;)V
      20: invokevirtual #7                  // Method org/apache/cxf/common/i18n/Message.toString:()Ljava/lang/String;
      23: astore_1
      24: invokestatic  #14                 // Method org/apache/cxf/binding/soap/jms/interceptor/SoapJMSConstants.getMismatchedSoapActionQName:()Ljavax/xml/namespace/QName;
      27: aload_1
      28: invokestatic  #9                  // Method createFault:(Ljavax/xml/namespace/QName;Ljava/lang/String;)Lorg/apache/cxf/binding/soap/jms/interceptor/JMSFault;
      31: areturn

  public static org.apache.cxf.binding.soap.jms.interceptor.JMSFault createMissingContentTypeFault();
    Code:
       0: new           #2                  // class org/apache/cxf/common/i18n/Message
       3: dup
       4: ldc           #15                 // String MISSING_CONTENTTYPE
       6: getstatic     #4                  // Field LOG:Ljava/util/logging/Logger;
       9: iconst_0
      10: anewarray     #5                  // class java/lang/Object
      13: invokespecial #6                  // Method org/apache/cxf/common/i18n/Message."<init>":(Ljava/lang/String;Ljava/util/logging/Logger;[Ljava/lang/Object;)V
      16: invokevirtual #7                  // Method org/apache/cxf/common/i18n/Message.toString:()Ljava/lang/String;
      19: astore_0
      20: invokestatic  #16                 // Method org/apache/cxf/binding/soap/jms/interceptor/SoapJMSConstants.getMissingContentTypeQName:()Ljavax/xml/namespace/QName;
      23: aload_0
      24: invokestatic  #9                  // Method createFault:(Ljavax/xml/namespace/QName;Ljava/lang/String;)Lorg/apache/cxf/binding/soap/jms/interceptor/JMSFault;
      27: areturn

  public static org.apache.cxf.binding.soap.jms.interceptor.JMSFault createMissingSoapActionFault();
    Code:
       0: new           #2                  // class org/apache/cxf/common/i18n/Message
       3: dup
       4: ldc           #17                 // String MISSING_SOAPACTION
       6: getstatic     #4                  // Field LOG:Ljava/util/logging/Logger;
       9: iconst_0
      10: anewarray     #5                  // class java/lang/Object
      13: invokespecial #6                  // Method org/apache/cxf/common/i18n/Message."<init>":(Ljava/lang/String;Ljava/util/logging/Logger;[Ljava/lang/Object;)V
      16: invokevirtual #7                  // Method org/apache/cxf/common/i18n/Message.toString:()Ljava/lang/String;
      19: astore_0
      20: invokestatic  #18                 // Method org/apache/cxf/binding/soap/jms/interceptor/SoapJMSConstants.getMissingSoapActionQName:()Ljavax/xml/namespace/QName;
      23: aload_0
      24: invokestatic  #9                  // Method createFault:(Ljavax/xml/namespace/QName;Ljava/lang/String;)Lorg/apache/cxf/binding/soap/jms/interceptor/JMSFault;
      27: areturn

  public static org.apache.cxf.binding.soap.jms.interceptor.JMSFault createMissingRequestURIFault();
    Code:
       0: new           #2                  // class org/apache/cxf/common/i18n/Message
       3: dup
       4: ldc           #19                 // String MISSING_REQUESTURI
       6: getstatic     #4                  // Field LOG:Ljava/util/logging/Logger;
       9: iconst_0
      10: anewarray     #5                  // class java/lang/Object
      13: invokespecial #6                  // Method org/apache/cxf/common/i18n/Message."<init>":(Ljava/lang/String;Ljava/util/logging/Logger;[Ljava/lang/Object;)V
      16: invokevirtual #7                  // Method org/apache/cxf/common/i18n/Message.toString:()Ljava/lang/String;
      19: astore_0
      20: invokestatic  #20                 // Method org/apache/cxf/binding/soap/jms/interceptor/SoapJMSConstants.getMissingRequestURIQName:()Ljavax/xml/namespace/QName;
      23: aload_0
      24: invokestatic  #9                  // Method createFault:(Ljavax/xml/namespace/QName;Ljava/lang/String;)Lorg/apache/cxf/binding/soap/jms/interceptor/JMSFault;
      27: areturn

  public static org.apache.cxf.binding.soap.jms.interceptor.JMSFault createTargetServiceNotAllowedInRequestURIFault();
    Code:
       0: new           #2                  // class org/apache/cxf/common/i18n/Message
       3: dup
       4: ldc           #21                 // String TARGET_SERVICE_NOT_ALLOWED_IN_REQUESTURI
       6: getstatic     #4                  // Field LOG:Ljava/util/logging/Logger;
       9: iconst_0
      10: anewarray     #5                  // class java/lang/Object
      13: invokespecial #6                  // Method org/apache/cxf/common/i18n/Message."<init>":(Ljava/lang/String;Ljava/util/logging/Logger;[Ljava/lang/Object;)V
      16: invokevirtual #7                  // Method org/apache/cxf/common/i18n/Message.toString:()Ljava/lang/String;
      19: astore_0
      20: invokestatic  #22                 // Method org/apache/cxf/binding/soap/jms/interceptor/SoapJMSConstants.getTargetServiceNotAllowedInRequestURIQName:()Ljavax/xml/namespace/QName;
      23: aload_0
      24: invokestatic  #9                  // Method createFault:(Ljavax/xml/namespace/QName;Ljava/lang/String;)Lorg/apache/cxf/binding/soap/jms/interceptor/JMSFault;
      27: areturn

  public static org.apache.cxf.binding.soap.jms.interceptor.JMSFault createUnrecognizedBindingVerionFault(java.lang.String);
    Code:
       0: new           #2                  // class org/apache/cxf/common/i18n/Message
       3: dup
       4: ldc           #23                 // String UNRECOGNIZED_BINDINGVERSION
       6: getstatic     #4                  // Field LOG:Ljava/util/logging/Logger;
       9: iconst_1
      10: anewarray     #5                  // class java/lang/Object
      13: dup
      14: iconst_0
      15: aload_0
      16: aastore
      17: invokespecial #6                  // Method org/apache/cxf/common/i18n/Message."<init>":(Ljava/lang/String;Ljava/util/logging/Logger;[Ljava/lang/Object;)V
      20: invokevirtual #7                  // Method org/apache/cxf/common/i18n/Message.toString:()Ljava/lang/String;
      23: astore_1
      24: invokestatic  #24                 // Method org/apache/cxf/binding/soap/jms/interceptor/SoapJMSConstants.getUnrecognizedBindingVersionQName:()Ljavax/xml/namespace/QName;
      27: aload_1
      28: invokestatic  #9                  // Method createFault:(Ljavax/xml/namespace/QName;Ljava/lang/String;)Lorg/apache/cxf/binding/soap/jms/interceptor/JMSFault;
      31: areturn

  public static org.apache.cxf.binding.soap.jms.interceptor.JMSFault createUnsupportedJMSMessageFormatFault(java.lang.String);
    Code:
       0: new           #2                  // class org/apache/cxf/common/i18n/Message
       3: dup
       4: ldc           #25                 // String UNSUPPORTED_JMSMESSAGEFORMAT
       6: getstatic     #4                  // Field LOG:Ljava/util/logging/Logger;
       9: iconst_1
      10: anewarray     #5                  // class java/lang/Object
      13: dup
      14: iconst_0
      15: aload_0
      16: aastore
      17: invokespecial #6                  // Method org/apache/cxf/common/i18n/Message."<init>":(Ljava/lang/String;Ljava/util/logging/Logger;[Ljava/lang/Object;)V
      20: invokevirtual #7                  // Method org/apache/cxf/common/i18n/Message.toString:()Ljava/lang/String;
      23: astore_1
      24: invokestatic  #26                 // Method org/apache/cxf/binding/soap/jms/interceptor/SoapJMSConstants.getUnsupportedJMSMessageFormatQName:()Ljavax/xml/namespace/QName;
      27: aload_1
      28: invokestatic  #9                  // Method createFault:(Ljavax/xml/namespace/QName;Ljava/lang/String;)Lorg/apache/cxf/binding/soap/jms/interceptor/JMSFault;
      31: areturn

  private static org.apache.cxf.binding.soap.jms.interceptor.JMSFault createFault(javax.xml.namespace.QName, java.lang.String);
    Code:
       0: new           #27                 // class org/apache/cxf/binding/soap/jms/interceptor/JMSFaultType
       3: dup
       4: invokespecial #28                 // Method org/apache/cxf/binding/soap/jms/interceptor/JMSFaultType."<init>":()V
       7: astore_2
       8: aload_2
       9: aload_0
      10: invokevirtual #29                 // Method org/apache/cxf/binding/soap/jms/interceptor/JMSFaultType.setFaultCode:(Ljavax/xml/namespace/QName;)V
      13: new           #30                 // class org/apache/cxf/binding/soap/jms/interceptor/JMSFault
      16: dup
      17: aload_1
      18: invokespecial #31                 // Method org/apache/cxf/binding/soap/jms/interceptor/JMSFault."<init>":(Ljava/lang/String;)V
      21: astore_3
      22: aload_3
      23: aload_2
      24: invokevirtual #32                 // Method org/apache/cxf/binding/soap/jms/interceptor/JMSFault.setJmsFaultType:(Lorg/apache/cxf/binding/soap/jms/interceptor/JMSFaultType;)V
      27: aload_3
      28: iconst_1
      29: invokevirtual #33                 // Method org/apache/cxf/binding/soap/jms/interceptor/JMSFault.setSender:(Z)V
      32: aload_3
      33: areturn

  static {};
    Code:
       0: ldc_w         #34                 // class org/apache/cxf/binding/soap/jms/interceptor/JMSFaultFactory
       3: invokestatic  #35                 // Method org/apache/cxf/common/logging/LogUtils.getL7dLogger:(Ljava/lang/Class;)Ljava/util/logging/Logger;
       6: putstatic     #4                  // Field LOG:Ljava/util/logging/Logger;
       9: return
}
