Compiled from "JdbcTestUtils.java"
public class org.springframework.test.jdbc.JdbcTestUtils {
  private static final org.apache.commons.logging.Log logger;

  public org.springframework.test.jdbc.JdbcTestUtils();
    Code:
       0: aload_0
       1: invokespecial #1                  // Method java/lang/Object."<init>":()V
       4: return

  public static int countRowsInTable(org.springframework.jdbc.core.JdbcTemplate, java.lang.String);
    Code:
       0: aload_0
       1: new           #2                  // class java/lang/StringBuilder
       4: dup
       5: invokespecial #3                  // Method java/lang/StringBuilder."<init>":()V
       8: ldc           #4                  // String SELECT COUNT(0) FROM
      10: invokevirtual #5                  // Method java/lang/StringBuilder.append:(Ljava/lang/String;)Ljava/lang/StringBuilder;
      13: aload_1
      14: invokevirtual #5                  // Method java/lang/StringBuilder.append:(Ljava/lang/String;)Ljava/lang/StringBuilder;
      17: invokevirtual #6                  // Method java/lang/StringBuilder.toString:()Ljava/lang/String;
      20: ldc           #7                  // class java/lang/Integer
      22: invokevirtual #8                  // Method org/springframework/jdbc/core/JdbcTemplate.queryForObject:(Ljava/lang/String;Ljava/lang/Class;)Ljava/lang/Object;
      25: checkcast     #7                  // class java/lang/Integer
      28: invokevirtual #9                  // Method java/lang/Integer.intValue:()I
      31: ireturn

  public static int countRowsInTableWhere(org.springframework.jdbc.core.JdbcTemplate, java.lang.String, java.lang.String);
    Code:
       0: new           #2                  // class java/lang/StringBuilder
       3: dup
       4: invokespecial #3                  // Method java/lang/StringBuilder."<init>":()V
       7: ldc           #4                  // String SELECT COUNT(0) FROM
       9: invokevirtual #5                  // Method java/lang/StringBuilder.append:(Ljava/lang/String;)Ljava/lang/StringBuilder;
      12: aload_1
      13: invokevirtual #5                  // Method java/lang/StringBuilder.append:(Ljava/lang/String;)Ljava/lang/StringBuilder;
      16: invokevirtual #6                  // Method java/lang/StringBuilder.toString:()Ljava/lang/String;
      19: astore_3
      20: aload_2
      21: invokestatic  #10                 // Method org/springframework/util/StringUtils.hasText:(Ljava/lang/String;)Z
      24: ifeq          51
      27: new           #2                  // class java/lang/StringBuilder
      30: dup
      31: invokespecial #3                  // Method java/lang/StringBuilder."<init>":()V
      34: aload_3
      35: invokevirtual #5                  // Method java/lang/StringBuilder.append:(Ljava/lang/String;)Ljava/lang/StringBuilder;
      38: ldc           #11                 // String  WHERE
      40: invokevirtual #5                  // Method java/lang/StringBuilder.append:(Ljava/lang/String;)Ljava/lang/StringBuilder;
      43: aload_2
      44: invokevirtual #5                  // Method java/lang/StringBuilder.append:(Ljava/lang/String;)Ljava/lang/StringBuilder;
      47: invokevirtual #6                  // Method java/lang/StringBuilder.toString:()Ljava/lang/String;
      50: astore_3
      51: aload_0
      52: aload_3
      53: ldc           #7                  // class java/lang/Integer
      55: invokevirtual #8                  // Method org/springframework/jdbc/core/JdbcTemplate.queryForObject:(Ljava/lang/String;Ljava/lang/Class;)Ljava/lang/Object;
      58: checkcast     #7                  // class java/lang/Integer
      61: invokevirtual #9                  // Method java/lang/Integer.intValue:()I
      64: ireturn

  public static int deleteFromTables(org.springframework.jdbc.core.JdbcTemplate, java.lang.String...);
    Code:
       0: iconst_0
       1: istore_2
       2: aload_1
       3: astore_3
       4: aload_3
       5: arraylength
       6: istore        4
       8: iconst_0
       9: istore        5
      11: iload         5
      13: iload         4
      15: if_icmpge     110
      18: aload_3
      19: iload         5
      21: aaload
      22: astore        6
      24: aload_0
      25: new           #2                  // class java/lang/StringBuilder
      28: dup
      29: invokespecial #3                  // Method java/lang/StringBuilder."<init>":()V
      32: ldc           #12                 // String DELETE FROM
      34: invokevirtual #5                  // Method java/lang/StringBuilder.append:(Ljava/lang/String;)Ljava/lang/StringBuilder;
      37: aload         6
      39: invokevirtual #5                  // Method java/lang/StringBuilder.append:(Ljava/lang/String;)Ljava/lang/StringBuilder;
      42: invokevirtual #6                  // Method java/lang/StringBuilder.toString:()Ljava/lang/String;
      45: invokevirtual #13                 // Method org/springframework/jdbc/core/JdbcTemplate.update:(Ljava/lang/String;)I
      48: istore        7
      50: iload_2
      51: iload         7
      53: iadd
      54: istore_2
      55: getstatic     #14                 // Field logger:Lorg/apache/commons/logging/Log;
      58: invokeinterface #15,  1           // InterfaceMethod org/apache/commons/logging/Log.isInfoEnabled:()Z
      63: ifeq          104
      66: getstatic     #14                 // Field logger:Lorg/apache/commons/logging/Log;
      69: new           #2                  // class java/lang/StringBuilder
      72: dup
      73: invokespecial #3                  // Method java/lang/StringBuilder."<init>":()V
      76: ldc           #16                 // String Deleted
      78: invokevirtual #5                  // Method java/lang/StringBuilder.append:(Ljava/lang/String;)Ljava/lang/StringBuilder;
      81: iload         7
      83: invokevirtual #17                 // Method java/lang/StringBuilder.append:(I)Ljava/lang/StringBuilder;
      86: ldc           #18                 // String  rows from table
      88: invokevirtual #5                  // Method java/lang/StringBuilder.append:(Ljava/lang/String;)Ljava/lang/StringBuilder;
      91: aload         6
      93: invokevirtual #5                  // Method java/lang/StringBuilder.append:(Ljava/lang/String;)Ljava/lang/StringBuilder;
      96: invokevirtual #6                  // Method java/lang/StringBuilder.toString:()Ljava/lang/String;
      99: invokeinterface #19,  2           // InterfaceMethod org/apache/commons/logging/Log.info:(Ljava/lang/Object;)V
     104: iinc          5, 1
     107: goto          11
     110: iload_2
     111: ireturn

  public static int deleteFromTableWhere(org.springframework.jdbc.core.JdbcTemplate, java.lang.String, java.lang.String, java.lang.Object...);
    Code:
       0: new           #2                  // class java/lang/StringBuilder
       3: dup
       4: invokespecial #3                  // Method java/lang/StringBuilder."<init>":()V
       7: ldc           #12                 // String DELETE FROM
       9: invokevirtual #5                  // Method java/lang/StringBuilder.append:(Ljava/lang/String;)Ljava/lang/StringBuilder;
      12: aload_1
      13: invokevirtual #5                  // Method java/lang/StringBuilder.append:(Ljava/lang/String;)Ljava/lang/StringBuilder;
      16: invokevirtual #6                  // Method java/lang/StringBuilder.toString:()Ljava/lang/String;
      19: astore        4
      21: aload_2
      22: invokestatic  #10                 // Method org/springframework/util/StringUtils.hasText:(Ljava/lang/String;)Z
      25: ifeq          54
      28: new           #2                  // class java/lang/StringBuilder
      31: dup
      32: invokespecial #3                  // Method java/lang/StringBuilder."<init>":()V
      35: aload         4
      37: invokevirtual #5                  // Method java/lang/StringBuilder.append:(Ljava/lang/String;)Ljava/lang/StringBuilder;
      40: ldc           #11                 // String  WHERE
      42: invokevirtual #5                  // Method java/lang/StringBuilder.append:(Ljava/lang/String;)Ljava/lang/StringBuilder;
      45: aload_2
      46: invokevirtual #5                  // Method java/lang/StringBuilder.append:(Ljava/lang/String;)Ljava/lang/StringBuilder;
      49: invokevirtual #6                  // Method java/lang/StringBuilder.toString:()Ljava/lang/String;
      52: astore        4
      54: aload_3
      55: ifnull        73
      58: aload_3
      59: arraylength
      60: ifle          73
      63: aload_0
      64: aload         4
      66: aload_3
      67: invokevirtual #20                 // Method org/springframework/jdbc/core/JdbcTemplate.update:(Ljava/lang/String;[Ljava/lang/Object;)I
      70: goto          79
      73: aload_0
      74: aload         4
      76: invokevirtual #13                 // Method org/springframework/jdbc/core/JdbcTemplate.update:(Ljava/lang/String;)I
      79: istore        5
      81: getstatic     #14                 // Field logger:Lorg/apache/commons/logging/Log;
      84: invokeinterface #15,  1           // InterfaceMethod org/apache/commons/logging/Log.isInfoEnabled:()Z
      89: ifeq          129
      92: getstatic     #14                 // Field logger:Lorg/apache/commons/logging/Log;
      95: new           #2                  // class java/lang/StringBuilder
      98: dup
      99: invokespecial #3                  // Method java/lang/StringBuilder."<init>":()V
     102: ldc           #16                 // String Deleted
     104: invokevirtual #5                  // Method java/lang/StringBuilder.append:(Ljava/lang/String;)Ljava/lang/StringBuilder;
     107: iload         5
     109: invokevirtual #17                 // Method java/lang/StringBuilder.append:(I)Ljava/lang/StringBuilder;
     112: ldc           #18                 // String  rows from table
     114: invokevirtual #5                  // Method java/lang/StringBuilder.append:(Ljava/lang/String;)Ljava/lang/StringBuilder;
     117: aload_1
     118: invokevirtual #5                  // Method java/lang/StringBuilder.append:(Ljava/lang/String;)Ljava/lang/StringBuilder;
     121: invokevirtual #6                  // Method java/lang/StringBuilder.toString:()Ljava/lang/String;
     124: invokeinterface #19,  2           // InterfaceMethod org/apache/commons/logging/Log.info:(Ljava/lang/Object;)V
     129: iload         5
     131: ireturn

  public static void dropTables(org.springframework.jdbc.core.JdbcTemplate, java.lang.String...);
    Code:
       0: aload_1
       1: astore_2
       2: aload_2
       3: arraylength
       4: istore_3
       5: iconst_0
       6: istore        4
       8: iload         4
      10: iload_3
      11: if_icmpge     89
      14: aload_2
      15: iload         4
      17: aaload
      18: astore        5
      20: aload_0
      21: new           #2                  // class java/lang/StringBuilder
      24: dup
      25: invokespecial #3                  // Method java/lang/StringBuilder."<init>":()V
      28: ldc           #21                 // String DROP TABLE
      30: invokevirtual #5                  // Method java/lang/StringBuilder.append:(Ljava/lang/String;)Ljava/lang/StringBuilder;
      33: aload         5
      35: invokevirtual #5                  // Method java/lang/StringBuilder.append:(Ljava/lang/String;)Ljava/lang/StringBuilder;
      38: invokevirtual #6                  // Method java/lang/StringBuilder.toString:()Ljava/lang/String;
      41: invokevirtual #22                 // Method org/springframework/jdbc/core/JdbcTemplate.execute:(Ljava/lang/String;)V
      44: getstatic     #14                 // Field logger:Lorg/apache/commons/logging/Log;
      47: invokeinterface #15,  1           // InterfaceMethod org/apache/commons/logging/Log.isInfoEnabled:()Z
      52: ifeq          83
      55: getstatic     #14                 // Field logger:Lorg/apache/commons/logging/Log;
      58: new           #2                  // class java/lang/StringBuilder
      61: dup
      62: invokespecial #3                  // Method java/lang/StringBuilder."<init>":()V
      65: ldc           #23                 // String Dropped table
      67: invokevirtual #5                  // Method java/lang/StringBuilder.append:(Ljava/lang/String;)Ljava/lang/StringBuilder;
      70: aload         5
      72: invokevirtual #5                  // Method java/lang/StringBuilder.append:(Ljava/lang/String;)Ljava/lang/StringBuilder;
      75: invokevirtual #6                  // Method java/lang/StringBuilder.toString:()Ljava/lang/String;
      78: invokeinterface #19,  2           // InterfaceMethod org/apache/commons/logging/Log.info:(Ljava/lang/Object;)V
      83: iinc          4, 1
      86: goto          8
      89: return

  public static void executeSqlScript(org.springframework.jdbc.core.JdbcTemplate, org.springframework.core.io.ResourceLoader, java.lang.String, boolean) throws org.springframework.dao.DataAccessException;
    Code:
       0: aload_1
       1: aload_2
       2: invokeinterface #24,  2           // InterfaceMethod org/springframework/core/io/ResourceLoader.getResource:(Ljava/lang/String;)Lorg/springframework/core/io/Resource;
       7: astore        4
       9: aload_0
      10: aload         4
      12: iload_3
      13: invokestatic  #25                 // Method executeSqlScript:(Lorg/springframework/jdbc/core/JdbcTemplate;Lorg/springframework/core/io/Resource;Z)V
      16: return

  public static void executeSqlScript(org.springframework.jdbc.core.JdbcTemplate, org.springframework.core.io.Resource, boolean) throws org.springframework.dao.DataAccessException;
    Code:
       0: aload_0
       1: new           #26                 // class org/springframework/core/io/support/EncodedResource
       4: dup
       5: aload_1
       6: invokespecial #27                 // Method org/springframework/core/io/support/EncodedResource."<init>":(Lorg/springframework/core/io/Resource;)V
       9: iload_2
      10: invokestatic  #28                 // Method executeSqlScript:(Lorg/springframework/jdbc/core/JdbcTemplate;Lorg/springframework/core/io/support/EncodedResource;Z)V
      13: return

  public static void executeSqlScript(org.springframework.jdbc.core.JdbcTemplate, org.springframework.core.io.support.EncodedResource, boolean) throws org.springframework.dao.DataAccessException;
    Code:
       0: new           #29                 // class org/springframework/jdbc/datasource/init/ResourceDatabasePopulator
       3: dup
       4: iload_2
       5: iconst_0
       6: aload_1
       7: invokevirtual #30                 // Method org/springframework/core/io/support/EncodedResource.getEncoding:()Ljava/lang/String;
      10: iconst_1
      11: anewarray     #31                 // class org/springframework/core/io/Resource
      14: dup
      15: iconst_0
      16: aload_1
      17: invokevirtual #32                 // Method org/springframework/core/io/support/EncodedResource.getResource:()Lorg/springframework/core/io/Resource;
      20: aastore
      21: invokespecial #33                 // Method org/springframework/jdbc/datasource/init/ResourceDatabasePopulator."<init>":(ZZLjava/lang/String;[Lorg/springframework/core/io/Resource;)V
      24: aload_0
      25: invokevirtual #34                 // Method org/springframework/jdbc/core/JdbcTemplate.getDataSource:()Ljavax/sql/DataSource;
      28: invokevirtual #35                 // Method org/springframework/jdbc/datasource/init/ResourceDatabasePopulator.execute:(Ljavax/sql/DataSource;)V
      31: return

  public static java.lang.String readScript(java.io.LineNumberReader) throws java.io.IOException;
    Code:
       0: aload_0
       1: ldc           #37                 // String --
       3: invokestatic  #38                 // Method readScript:(Ljava/io/LineNumberReader;Ljava/lang/String;)Ljava/lang/String;
       6: areturn

  public static java.lang.String readScript(java.io.LineNumberReader, java.lang.String) throws java.io.IOException;
    Code:
       0: aload_0
       1: aload_1
       2: ldc           #39                 // String ;
       4: invokestatic  #40                 // Method org/springframework/jdbc/datasource/init/ScriptUtils.readScript:(Ljava/io/LineNumberReader;Ljava/lang/String;Ljava/lang/String;)Ljava/lang/String;
       7: areturn

  public static boolean containsSqlScriptDelimiters(java.lang.String, char);
    Code:
       0: aload_0
       1: iload_1
       2: invokestatic  #41                 // Method java/lang/String.valueOf:(C)Ljava/lang/String;
       5: invokestatic  #42                 // Method org/springframework/jdbc/datasource/init/ScriptUtils.containsSqlScriptDelimiters:(Ljava/lang/String;Ljava/lang/String;)Z
       8: ireturn

  public static void splitSqlScript(java.lang.String, char, java.util.List<java.lang.String>);
    Code:
       0: aload_0
       1: iload_1
       2: aload_2
       3: invokestatic  #43                 // Method org/springframework/jdbc/datasource/init/ScriptUtils.splitSqlScript:(Ljava/lang/String;CLjava/util/List;)V
       6: return

  static {};
    Code:
       0: ldc           #44                 // class org/springframework/test/jdbc/JdbcTestUtils
       2: invokestatic  #45                 // Method org/apache/commons/logging/LogFactory.getLog:(Ljava/lang/Class;)Lorg/apache/commons/logging/Log;
       5: putstatic     #14                 // Field logger:Lorg/apache/commons/logging/Log;
       8: return
}
