Compiled from "FadeSpec.scala"
public final class de.sciss.lucre.expr.graph.FadeSpec$ApplyOp<T extends de.sciss.lucre.Txn<T>> extends de.sciss.lucre.expr.graph.TernaryOp$Op<java.lang.Object, de.sciss.synth.Curve, java.lang.Object, de.sciss.proc.FadeSpec> implements java.io.Serializable {
  public static de.sciss.lucre.expr.graph.FadeSpec$ApplyOp fromProduct(scala.Product);
    Code:
       0: getstatic     #23                 // Field de/sciss/lucre/expr/graph/FadeSpec$ApplyOp$.MODULE$:Lde/sciss/lucre/expr/graph/FadeSpec$ApplyOp$;
       3: aload_0
       4: invokevirtual #25                 // Method de/sciss/lucre/expr/graph/FadeSpec$ApplyOp$.fromProduct:(Lscala/Product;)Lde/sciss/lucre/expr/graph/FadeSpec$ApplyOp;
       7: areturn

  public static <T extends de.sciss.lucre.Txn<T>> boolean unapply(de.sciss.lucre.expr.graph.FadeSpec$ApplyOp<T>);
    Code:
       0: getstatic     #23                 // Field de/sciss/lucre/expr/graph/FadeSpec$ApplyOp$.MODULE$:Lde/sciss/lucre/expr/graph/FadeSpec$ApplyOp$;
       3: aload_0
       4: invokevirtual #30                 // Method de/sciss/lucre/expr/graph/FadeSpec$ApplyOp$.unapply:(Lde/sciss/lucre/expr/graph/FadeSpec$ApplyOp;)Z
       7: ireturn

  public de.sciss.lucre.expr.graph.FadeSpec$ApplyOp();
    Code:
       0: aload_0
       1: invokespecial #34                 // Method de/sciss/lucre/expr/graph/TernaryOp$Op."<init>":()V
       4: return

  public int hashCode();
    Code:
       0: getstatic     #43                 // Field scala/runtime/ScalaRunTime$.MODULE$:Lscala/runtime/ScalaRunTime$;
       3: aload_0
       4: invokevirtual #47                 // Method scala/runtime/ScalaRunTime$._hashCode:(Lscala/Product;)I
       7: ireturn

  public boolean equals(java.lang.Object);
    Code:
       0: aload_0
       1: aload_1
       2: if_acmpeq     30
       5: aload_1
       6: astore_2
       7: aload_2
       8: instanceof    #2                  // class de/sciss/lucre/expr/graph/FadeSpec$ApplyOp
      11: ifeq          23
      14: aload_2
      15: checkcast     #2                  // class de/sciss/lucre/expr/graph/FadeSpec$ApplyOp
      18: astore_3
      19: iconst_1
      20: goto          27
      23: iconst_0
      24: goto          27
      27: ifeq          34
      30: iconst_1
      31: goto          35
      34: iconst_0
      35: ireturn

  public java.lang.String toString();
    Code:
       0: getstatic     #43                 // Field scala/runtime/ScalaRunTime$.MODULE$:Lscala/runtime/ScalaRunTime$;
       3: aload_0
       4: invokevirtual #59                 // Method scala/runtime/ScalaRunTime$._toString:(Lscala/Product;)Ljava/lang/String;
       7: areturn

  public boolean canEqual(java.lang.Object);
    Code:
       0: aload_1
       1: instanceof    #2                  // class de/sciss/lucre/expr/graph/FadeSpec$ApplyOp
       4: ireturn

  public int productArity();
    Code:
       0: iconst_0
       1: ireturn

  public java.lang.Object productElement(int);
    Code:
       0: iload_1
       1: istore_2
       2: new           #67                 // class java/lang/IndexOutOfBoundsException
       5: dup
       6: iload_1
       7: invokestatic  #73                 // Method scala/runtime/BoxesRunTime.boxToInteger:(I)Ljava/lang/Integer;
      10: invokevirtual #77                 // Method java/lang/Integer.toString:()Ljava/lang/String;
      13: invokespecial #80                 // Method java/lang/IndexOutOfBoundsException."<init>":(Ljava/lang/String;)V
      16: athrow
      17: athrow
      18: athrow

  public java.lang.String productElementName(int);
    Code:
       0: iload_1
       1: istore_2
       2: new           #67                 // class java/lang/IndexOutOfBoundsException
       5: dup
       6: iload_1
       7: invokestatic  #73                 // Method scala/runtime/BoxesRunTime.boxToInteger:(I)Ljava/lang/Integer;
      10: invokevirtual #77                 // Method java/lang/Integer.toString:()Ljava/lang/String;
      13: invokespecial #80                 // Method java/lang/IndexOutOfBoundsException."<init>":(Ljava/lang/String;)V
      16: athrow
      17: athrow
      18: athrow

  public java.lang.String productPrefix();
    Code:
       0: ldc           #88                 // String FadeSpec$ApplyOp
       2: areturn

  public de.sciss.proc.FadeSpec apply(long, de.sciss.synth.Curve, double);
    Code:
       0: getstatic     #98                 // Field de/sciss/proc/FadeSpec$.MODULE$:Lde/sciss/proc/FadeSpec$;
       3: lload_1
       4: aload_3
       5: dload         4
       7: d2f
       8: invokevirtual #101                // Method de/sciss/proc/FadeSpec$.apply:(JLde/sciss/synth/Curve;F)Lde/sciss/proc/FadeSpec;
      11: areturn

  public <T extends de.sciss.lucre.Txn<T>> de.sciss.lucre.expr.graph.FadeSpec$ApplyOp<T> copy();
    Code:
       0: new           #2                  // class de/sciss/lucre/expr/graph/FadeSpec$ApplyOp
       3: dup
       4: invokespecial #108                // Method "<init>":()V
       7: areturn

  public java.lang.Object apply(java.lang.Object, java.lang.Object, java.lang.Object);
    Code:
       0: aload_0
       1: aload_1
       2: invokestatic  #113                // Method scala/runtime/BoxesRunTime.unboxToLong:(Ljava/lang/Object;)J
       5: aload_2
       6: checkcast     #115                // class de/sciss/synth/Curve
       9: aload_3
      10: invokestatic  #119                // Method scala/runtime/BoxesRunTime.unboxToDouble:(Ljava/lang/Object;)D
      13: invokevirtual #121                // Method apply:(JLde/sciss/synth/Curve;D)Lde/sciss/proc/FadeSpec;
      16: areturn
}
