Compiled from "Grapheme.scala"
abstract class de.sciss.lucre.expr.graph.Grapheme$UnaryMappedGraphemeIExpr<T extends de.sciss.lucre.Txn<T>, A> extends de.sciss.lucre.expr.graph.impl.UnaryMappedObjIExpr<T, de.sciss.proc.Grapheme, de.sciss.lucre.expr.graph.Grapheme, A> {
  private final de.sciss.lucre.expr.Context<T> context;

  public de.sciss.lucre.expr.graph.Grapheme$UnaryMappedGraphemeIExpr(de.sciss.lucre.IExpr<T, de.sciss.lucre.expr.graph.Grapheme>, T, de.sciss.lucre.ITargets<T>, de.sciss.lucre.expr.Context<T>);
    Code:
       0: aload_0
       1: aload         4
       3: putfield      #25                 // Field context:Lde/sciss/lucre/expr/Context;
       6: aload_0
       7: aload_1
       8: aload_2
       9: aload_3
      10: invokespecial #28                 // Method de/sciss/lucre/expr/graph/impl/UnaryMappedObjIExpr."<init>":(Lde/sciss/lucre/IExpr;Lde/sciss/lucre/Txn;Lde/sciss/lucre/ITargets;)V
      13: return

  private de.sciss.lucre.ITargets<T> targets$accessor();
    Code:
       0: aload_0
       1: invokespecial #38                 // Method de/sciss/lucre/expr/graph/impl/UnaryMappedObjIExpr.targets:()Lde/sciss/lucre/ITargets;
       4: areturn

  public de.sciss.lucre.Disposable<T> observeObj(de.sciss.proc.Grapheme<T>, T);
    Code:
       0: aload_0
       1: getfield      #25                 // Field context:Lde/sciss/lucre/expr/Context;
       4: aload_1
       5: invokeinterface #49,  1           // InterfaceMethod de/sciss/proc/Grapheme.changed:()Lde/sciss/lucre/EventLike;
      10: aload_0
      11: invokedynamic #70,  0             // InvokeDynamic #0:apply:(Lde/sciss/lucre/expr/graph/Grapheme$UnaryMappedGraphemeIExpr;)Lscala/Function1;
      16: aload_2
      17: invokeinterface #76,  4           // InterfaceMethod de/sciss/lucre/expr/Context.reactTo:(Lde/sciss/lucre/EventLike;Lscala/Function1;Lde/sciss/lucre/Txn;)Lde/sciss/lucre/Disposable;
      22: areturn

  public de.sciss.lucre.Disposable observeObj(de.sciss.lucre.Obj, de.sciss.lucre.Txn);
    Code:
       0: aload_0
       1: aload_1
       2: checkcast     #45                 // class de/sciss/proc/Grapheme
       5: aload_2
       6: invokevirtual #80                 // Method observeObj:(Lde/sciss/proc/Grapheme;Lde/sciss/lucre/Txn;)Lde/sciss/lucre/Disposable;
       9: areturn

  private final void observeObj$$anonfun$2$$anonfun$1(de.sciss.lucre.Txn, de.sciss.lucre.BiPin$Update);
    Code:
       0: aload_0
       1: getstatic     #91                 // Field scala/Some$.MODULE$:Lscala/Some$;
       4: aload_2
       5: invokevirtual #95                 // Method de/sciss/lucre/BiPin$Update.pin:()Lde/sciss/lucre/BiPin;
       8: invokevirtual #98                 // Method scala/Some$.apply:(Ljava/lang/Object;)Lscala/Some;
      11: iconst_0
      12: aload_1
      13: invokevirtual #102                // Method mapValue:(Lscala/Option;ZLde/sciss/lucre/Txn;)Ljava/lang/Object;
      16: astore_3
      17: aload_0
      18: aload_3
      19: aload_1
      20: invokevirtual #106                // Method updateFromObj:(Ljava/lang/Object;Lde/sciss/lucre/Txn;)V
      23: return

  private final scala.Function1 observeObj$$anonfun$1(de.sciss.lucre.Txn);
    Code:
       0: aload_0
       1: aload_1
       2: invokedynamic #120,  0            // InvokeDynamic #1:applyVoid:(Lde/sciss/lucre/expr/graph/Grapheme$UnaryMappedGraphemeIExpr;Lde/sciss/lucre/Txn;)Lscala/runtime/function/JProcedure1;
       7: areturn

  private static java.lang.Object $deserializeLambda$(java.lang.invoke.SerializedLambda);
    Code:
       0: aload_0
       1: invokedynamic #132,  0            // InvokeDynamic #2:lambdaDeserialize:(Ljava/lang/invoke/SerializedLambda;)Ljava/lang/Object;
       6: areturn
}
