Compiled from "Runner.scala"
public interface de.sciss.lucre.expr.graph.Runner$Attr extends scala.Product {
  public static <A> de.sciss.lucre.expr.graph.Runner$Attr expr(A, scala.Function1<A, de.sciss.lucre.expr.graph.Ex<scala.Tuple2<java.lang.String, ?>>>);
    Code:
       0: getstatic     #25                 // Field de/sciss/lucre/expr/graph/Runner$Attr$.MODULE$:Lde/sciss/lucre/expr/graph/Runner$Attr$;
       3: aload_0
       4: aload_1
       5: invokevirtual #27                 // Method de/sciss/lucre/expr/graph/Runner$Attr$.expr:(Ljava/lang/Object;Lscala/Function1;)Lde/sciss/lucre/expr/graph/Runner$Attr;
       8: areturn

  public static <A, B> de.sciss.lucre.expr.graph.Runner$Attr flow(scala.Tuple2<A, B>, scala.Function1<A, de.sciss.lucre.expr.graph.Ex<java.lang.String>>, scala.Function1<B, de.sciss.lucre.expr.graph.Flow>);
    Code:
       0: getstatic     #25                 // Field de/sciss/lucre/expr/graph/Runner$Attr$.MODULE$:Lde/sciss/lucre/expr/graph/Runner$Attr$;
       3: aload_0
       4: aload_1
       5: aload_2
       6: invokevirtual #32                 // Method de/sciss/lucre/expr/graph/Runner$Attr$.flow:(Lscala/Tuple2;Lscala/Function1;Lscala/Function1;)Lde/sciss/lucre/expr/graph/Runner$Attr;
       9: areturn

  public static int ordinal(de.sciss.lucre.expr.graph.Runner$Attr);
    Code:
       0: getstatic     #25                 // Field de/sciss/lucre/expr/graph/Runner$Attr$.MODULE$:Lde/sciss/lucre/expr/graph/Runner$Attr$;
       3: aload_0
       4: invokevirtual #36                 // Method de/sciss/lucre/expr/graph/Runner$Attr$.ordinal:(Lde/sciss/lucre/expr/graph/Runner$Attr;)I
       7: ireturn

  public static de.sciss.lucre.expr.graph.Runner$Attr read(de.sciss.lucre.expr.ExElem$RefMapIn, java.lang.String, int, int);
    Code:
       0: getstatic     #25                 // Field de/sciss/lucre/expr/graph/Runner$Attr$.MODULE$:Lde/sciss/lucre/expr/graph/Runner$Attr$;
       3: aload_0
       4: aload_1
       5: iload_2
       6: iload_3
       7: invokevirtual #40                 // Method de/sciss/lucre/expr/graph/Runner$Attr$.read:(Lde/sciss/lucre/expr/ExElem$RefMapIn;Ljava/lang/String;II)Lde/sciss/lucre/expr/graph/Runner$Attr;
      10: areturn

  public abstract de.sciss.lucre.expr.graph.Ex<java.lang.String> key();

  public abstract <T extends de.sciss.lucre.Txn<T>> de.sciss.lucre.Form<T> expandValue(de.sciss.lucre.expr.Context<T>, T);
}
