Compiled from "Sys.scala"
final class de.sciss.lucre.expr.graph.Sys$ExpandedEnv<T extends de.sciss.lucre.Txn<T>> extends de.sciss.lucre.expr.graph.impl.MappedIExpr<T, java.lang.String, scala.Option<java.lang.String>> {
  public de.sciss.lucre.expr.graph.Sys$ExpandedEnv(de.sciss.lucre.IExpr<T, java.lang.String>, T, de.sciss.lucre.ITargets<T>);
    Code:
       0: aload_0
       1: aload_1
       2: aload_2
       3: aload_3
       4: invokespecial #18                 // Method de/sciss/lucre/expr/graph/impl/MappedIExpr."<init>":(Lde/sciss/lucre/IExpr;Lde/sciss/lucre/Exec;Lde/sciss/lucre/ITargets;)V
       7: return

  private de.sciss.lucre.ITargets<T> targets$accessor();
    Code:
       0: aload_0
       1: invokespecial #28                 // Method de/sciss/lucre/expr/graph/impl/MappedIExpr.targets:()Lde/sciss/lucre/ITargets;
       4: areturn

  public scala.Option<java.lang.String> mapValue(java.lang.String, T);
    Code:
       0: getstatic     #39                 // Field scala/sys/package$.MODULE$:Lscala/sys/package$;
       3: invokevirtual #43                 // Method scala/sys/package$.env:()Lscala/collection/immutable/Map;
       6: aload_1
       7: invokeinterface #49,  2           // InterfaceMethod scala/collection/immutable/Map.get:(Ljava/lang/Object;)Lscala/Option;
      12: areturn

  public java.lang.Object mapValue(java.lang.Object, de.sciss.lucre.Exec);
    Code:
       0: aload_0
       1: aload_1
       2: checkcast     #53                 // class java/lang/String
       5: aload_2
       6: checkcast     #55                 // class de/sciss/lucre/Txn
       9: invokevirtual #57                 // Method mapValue:(Ljava/lang/String;Lde/sciss/lucre/Txn;)Lscala/Option;
      12: areturn
}
