Compiled from "CallableProcessingInterceptor.java"
public interface org.springframework.web.context.request.async.CallableProcessingInterceptor {
  public static final java.lang.Object RESULT_NONE;

  public static final java.lang.Object RESPONSE_HANDLED;

  public default <T> void beforeConcurrentHandling(org.springframework.web.context.request.NativeWebRequest, java.util.concurrent.Callable<T>) throws java.lang.Exception;
    Code:
       0: return

  public default <T> void preProcess(org.springframework.web.context.request.NativeWebRequest, java.util.concurrent.Callable<T>) throws java.lang.Exception;
    Code:
       0: return

  public default <T> void postProcess(org.springframework.web.context.request.NativeWebRequest, java.util.concurrent.Callable<T>, java.lang.Object) throws java.lang.Exception;
    Code:
       0: return

  public default <T> java.lang.Object handleTimeout(org.springframework.web.context.request.NativeWebRequest, java.util.concurrent.Callable<T>) throws java.lang.Exception;
    Code:
       0: getstatic     #1                  // Field RESULT_NONE:Ljava/lang/Object;
       3: areturn

  public default <T> java.lang.Object handleError(org.springframework.web.context.request.NativeWebRequest, java.util.concurrent.Callable<T>, java.lang.Throwable) throws java.lang.Exception;
    Code:
       0: getstatic     #1                  // Field RESULT_NONE:Ljava/lang/Object;
       3: areturn

  public default <T> void afterCompletion(org.springframework.web.context.request.NativeWebRequest, java.util.concurrent.Callable<T>) throws java.lang.Exception;
    Code:
       0: return

  static {};
    Code:
       0: new           #2                  // class java/lang/Object
       3: dup
       4: invokespecial #3                  // Method java/lang/Object."<init>":()V
       7: putstatic     #1                  // Field RESULT_NONE:Ljava/lang/Object;
      10: new           #2                  // class java/lang/Object
      13: dup
      14: invokespecial #3                  // Method java/lang/Object."<init>":()V
      17: putstatic     #4                  // Field RESPONSE_HANDLED:Ljava/lang/Object;
      20: return
}
