Compiled from "AbstractAmazonCloudSearchDomain.java"
public class com.amazonaws.services.cloudsearchdomain.AbstractAmazonCloudSearchDomain implements com.amazonaws.services.cloudsearchdomain.AmazonCloudSearchDomain {
  protected com.amazonaws.services.cloudsearchdomain.AbstractAmazonCloudSearchDomain();
    Code:
       0: aload_0
       1: invokespecial #1                  // Method java/lang/Object."<init>":()V
       4: return

  public void setEndpoint(java.lang.String);
    Code:
       0: new           #2                  // class java/lang/UnsupportedOperationException
       3: dup
       4: invokespecial #3                  // Method java/lang/UnsupportedOperationException."<init>":()V
       7: athrow

  public void setRegion(com.amazonaws.regions.Region);
    Code:
       0: new           #2                  // class java/lang/UnsupportedOperationException
       3: dup
       4: invokespecial #3                  // Method java/lang/UnsupportedOperationException."<init>":()V
       7: athrow

  public com.amazonaws.services.cloudsearchdomain.model.SearchResult search(com.amazonaws.services.cloudsearchdomain.model.SearchRequest);
    Code:
       0: new           #2                  // class java/lang/UnsupportedOperationException
       3: dup
       4: invokespecial #3                  // Method java/lang/UnsupportedOperationException."<init>":()V
       7: athrow

  public com.amazonaws.services.cloudsearchdomain.model.SuggestResult suggest(com.amazonaws.services.cloudsearchdomain.model.SuggestRequest);
    Code:
       0: new           #2                  // class java/lang/UnsupportedOperationException
       3: dup
       4: invokespecial #3                  // Method java/lang/UnsupportedOperationException."<init>":()V
       7: athrow

  public com.amazonaws.services.cloudsearchdomain.model.UploadDocumentsResult uploadDocuments(com.amazonaws.services.cloudsearchdomain.model.UploadDocumentsRequest);
    Code:
       0: new           #2                  // class java/lang/UnsupportedOperationException
       3: dup
       4: invokespecial #3                  // Method java/lang/UnsupportedOperationException."<init>":()V
       7: athrow

  public void shutdown();
    Code:
       0: new           #2                  // class java/lang/UnsupportedOperationException
       3: dup
       4: invokespecial #3                  // Method java/lang/UnsupportedOperationException."<init>":()V
       7: athrow

  public com.amazonaws.ResponseMetadata getCachedResponseMetadata(com.amazonaws.AmazonWebServiceRequest);
    Code:
       0: new           #2                  // class java/lang/UnsupportedOperationException
       3: dup
       4: invokespecial #3                  // Method java/lang/UnsupportedOperationException."<init>":()V
       7: athrow
}
