Compiled from "MConfig.java"
final class com.mchange.v2.cfg.MConfig$PathsKey {
  java.lang.String[] paths;

  java.util.List delayedLogItems;

  public boolean equals(java.lang.Object);
    Code:
       0: aload_1
       1: instanceof    #1                  // class com/mchange/v2/cfg/MConfig$PathsKey
       4: ifeq          22
       7: aload_0
       8: getfield      #2                  // Field paths:[Ljava/lang/String;
      11: aload_1
      12: checkcast     #1                  // class com/mchange/v2/cfg/MConfig$PathsKey
      15: getfield      #2                  // Field paths:[Ljava/lang/String;
      18: invokestatic  #3                  // Method java/util/Arrays.equals:([Ljava/lang/Object;[Ljava/lang/Object;)Z
      21: ireturn
      22: iconst_0
      23: ireturn

  public int hashCode();
    Code:
       0: aload_0
       1: getfield      #2                  // Field paths:[Ljava/lang/String;
       4: invokestatic  #4                  // Method com/mchange/v1/util/ArrayUtils.hashArray:([Ljava/lang/Object;)I
       7: ireturn

  com.mchange.v2.cfg.MConfig$PathsKey(java.lang.String[], java.lang.String[]);
    Code:
       0: aload_0
       1: invokespecial #5                  // Method java/lang/Object."<init>":()V
       4: aload_0
       5: new           #6                  // class java/util/ArrayList
       8: dup
       9: invokespecial #7                  // Method java/util/ArrayList."<init>":()V
      12: putfield      #8                  // Field delayedLogItems:Ljava/util/List;
      15: aload_1
      16: aload_2
      17: aload_0
      18: getfield      #8                  // Field delayedLogItems:Ljava/util/List;
      21: invokestatic  #9                  // Method com/mchange/v2/cfg/ConfigUtils.vmCondensedPaths:([Ljava/lang/String;[Ljava/lang/String;Ljava/util/List;)Ljava/util/List;
      24: astore_3
      25: aload_0
      26: aload_3
      27: aload_3
      28: invokeinterface #10,  1           // InterfaceMethod java/util/List.size:()I
      33: anewarray     #11                 // class java/lang/String
      36: invokeinterface #12,  2           // InterfaceMethod java/util/List.toArray:([Ljava/lang/Object;)[Ljava/lang/Object;
      41: checkcast     #13                 // class "[Ljava/lang/String;"
      44: checkcast     #13                 // class "[Ljava/lang/String;"
      47: putfield      #2                  // Field paths:[Ljava/lang/String;
      50: return

  com.mchange.v2.cfg.MConfig$PathsKey(java.lang.String[]);
    Code:
       0: aload_0
       1: invokespecial #5                  // Method java/lang/Object."<init>":()V
       4: aload_0
       5: invokestatic  #14                 // Method java/util/Collections.emptyList:()Ljava/util/List;
       8: putfield      #8                  // Field delayedLogItems:Ljava/util/List;
      11: aload_0
      12: aload_1
      13: putfield      #2                  // Field paths:[Ljava/lang/String;
      16: return
}
