Compiled from "BasicGridBinder.java"
public abstract class org.hibernate.ogm.type.descriptor.BasicGridBinder<X> implements org.hibernate.ogm.type.descriptor.GridValueBinder<X> {
  private static final org.hibernate.ogm.util.impl.Log log;

  private final org.hibernate.type.descriptor.java.JavaTypeDescriptor<X> javaDescriptor;

  private final org.hibernate.ogm.type.descriptor.GridTypeDescriptor gridDescriptor;

  private static final org.hibernate.type.descriptor.WrapperOptions DEFAULT_OPTIONS;

  public org.hibernate.ogm.type.descriptor.BasicGridBinder(org.hibernate.type.descriptor.java.JavaTypeDescriptor<X>, org.hibernate.ogm.type.descriptor.GridTypeDescriptor);
    Code:
       0: aload_0
       1: invokespecial #1                  // Method java/lang/Object."<init>":()V
       4: aload_0
       5: aload_1
       6: putfield      #2                  // Field javaDescriptor:Lorg/hibernate/type/descriptor/java/JavaTypeDescriptor;
       9: aload_0
      10: aload_2
      11: putfield      #3                  // Field gridDescriptor:Lorg/hibernate/ogm/type/descriptor/GridTypeDescriptor;
      14: return

  public void bind(org.hibernate.ogm.datastore.spi.Tuple, X, java.lang.String[]);
    Code:
       0: aload_2
       1: ifnonnull     57
       4: aload_3
       5: astore        4
       7: aload         4
       9: arraylength
      10: istore        5
      12: iconst_0
      13: istore        6
      15: iload         6
      17: iload         5
      19: if_icmpge     54
      22: aload         4
      24: iload         6
      26: aaload
      27: astore        7
      29: getstatic     #4                  // Field log:Lorg/hibernate/ogm/util/impl/Log;
      32: ldc           #5                  // String binding [null] to parameter [%1$s]
      34: aload         7
      36: invokeinterface #6,  3            // InterfaceMethod org/hibernate/ogm/util/impl/Log.tracef:(Ljava/lang/String;Ljava/lang/Object;)V
      41: aload_1
      42: aload         7
      44: aconst_null
      45: invokevirtual #7                  // Method org/hibernate/ogm/datastore/spi/Tuple.put:(Ljava/lang/String;Ljava/lang/Object;)V
      48: iinc          6, 1
      51: goto          15
      54: goto          102
      57: getstatic     #4                  // Field log:Lorg/hibernate/ogm/util/impl/Log;
      60: invokeinterface #8,  1            // InterfaceMethod org/hibernate/ogm/util/impl/Log.isTraceEnabled:()Z
      65: ifeq          92
      68: getstatic     #4                  // Field log:Lorg/hibernate/ogm/util/impl/Log;
      71: ldc           #9                  // String binding [%1$s] to parameter(s) %2$s
      73: aload_0
      74: getfield      #2                  // Field javaDescriptor:Lorg/hibernate/type/descriptor/java/JavaTypeDescriptor;
      77: aload_2
      78: invokeinterface #10,  2           // InterfaceMethod org/hibernate/type/descriptor/java/JavaTypeDescriptor.extractLoggableRepresentation:(Ljava/lang/Object;)Ljava/lang/String;
      83: aload_3
      84: invokestatic  #11                 // Method java/util/Arrays.toString:([Ljava/lang/Object;)Ljava/lang/String;
      87: invokeinterface #12,  4           // InterfaceMethod org/hibernate/ogm/util/impl/Log.tracef:(Ljava/lang/String;Ljava/lang/Object;Ljava/lang/Object;)V
      92: aload_0
      93: aload_1
      94: aload_2
      95: aload_3
      96: getstatic     #13                 // Field DEFAULT_OPTIONS:Lorg/hibernate/type/descriptor/WrapperOptions;
      99: invokevirtual #14                 // Method doBind:(Lorg/hibernate/ogm/datastore/spi/Tuple;Ljava/lang/Object;[Ljava/lang/String;Lorg/hibernate/type/descriptor/WrapperOptions;)V
     102: return

  protected abstract void doBind(org.hibernate.ogm.datastore.spi.Tuple, X, java.lang.String[], org.hibernate.type.descriptor.WrapperOptions);

  static {};
    Code:
       0: invokestatic  #15                 // Method org/hibernate/ogm/util/impl/LoggerFactory.make:()Lorg/hibernate/ogm/util/impl/Log;
       3: putstatic     #4                  // Field log:Lorg/hibernate/ogm/util/impl/Log;
       6: new           #16                 // class org/hibernate/ogm/type/descriptor/BasicGridBinder$1
       9: dup
      10: invokespecial #17                 // Method org/hibernate/ogm/type/descriptor/BasicGridBinder$1."<init>":()V
      13: putstatic     #13                 // Field DEFAULT_OPTIONS:Lorg/hibernate/type/descriptor/WrapperOptions;
      16: return
}
