Compiled from "PGDataSourceFactory.java"
public class org.postgresql.osgi.PGDataSourceFactory implements org.osgi.service.jdbc.DataSourceFactory {
  public org.postgresql.osgi.PGDataSourceFactory();
    Code:
       0: aload_0
       1: invokespecial #1                  // Method java/lang/Object."<init>":()V
       4: return

  private void configureBaseDataSource(org.postgresql.ds.common.BaseDataSource, java.util.Properties) throws java.sql.SQLException;
    Code:
       0: aload_2
       1: ldc           #3                  // String url
       3: invokevirtual #4                  // Method java/util/Properties.containsKey:(Ljava/lang/Object;)Z
       6: ifeq          19
       9: aload_1
      10: aload_2
      11: ldc           #3                  // String url
      13: invokevirtual #5                  // Method java/util/Properties.getProperty:(Ljava/lang/String;)Ljava/lang/String;
      16: invokevirtual #6                  // Method org/postgresql/ds/common/BaseDataSource.setUrl:(Ljava/lang/String;)V
      19: aload_2
      20: ldc           #7                  // String serverName
      22: invokevirtual #4                  // Method java/util/Properties.containsKey:(Ljava/lang/Object;)Z
      25: ifeq          38
      28: aload_1
      29: aload_2
      30: ldc           #7                  // String serverName
      32: invokevirtual #5                  // Method java/util/Properties.getProperty:(Ljava/lang/String;)Ljava/lang/String;
      35: invokevirtual #8                  // Method org/postgresql/ds/common/BaseDataSource.setServerName:(Ljava/lang/String;)V
      38: aload_2
      39: ldc           #9                  // String portNumber
      41: invokevirtual #4                  // Method java/util/Properties.containsKey:(Ljava/lang/Object;)Z
      44: ifeq          60
      47: aload_1
      48: aload_2
      49: ldc           #9                  // String portNumber
      51: invokevirtual #5                  // Method java/util/Properties.getProperty:(Ljava/lang/String;)Ljava/lang/String;
      54: invokestatic  #10                 // Method java/lang/Integer.parseInt:(Ljava/lang/String;)I
      57: invokevirtual #11                 // Method org/postgresql/ds/common/BaseDataSource.setPortNumber:(I)V
      60: aload_2
      61: ldc           #12                 // String databaseName
      63: invokevirtual #4                  // Method java/util/Properties.containsKey:(Ljava/lang/Object;)Z
      66: ifeq          79
      69: aload_1
      70: aload_2
      71: ldc           #12                 // String databaseName
      73: invokevirtual #5                  // Method java/util/Properties.getProperty:(Ljava/lang/String;)Ljava/lang/String;
      76: invokevirtual #13                 // Method org/postgresql/ds/common/BaseDataSource.setDatabaseName:(Ljava/lang/String;)V
      79: aload_2
      80: ldc           #14                 // String user
      82: invokevirtual #4                  // Method java/util/Properties.containsKey:(Ljava/lang/Object;)Z
      85: ifeq          98
      88: aload_1
      89: aload_2
      90: ldc           #14                 // String user
      92: invokevirtual #5                  // Method java/util/Properties.getProperty:(Ljava/lang/String;)Ljava/lang/String;
      95: invokevirtual #15                 // Method org/postgresql/ds/common/BaseDataSource.setUser:(Ljava/lang/String;)V
      98: aload_2
      99: ldc           #16                 // String password
     101: invokevirtual #4                  // Method java/util/Properties.containsKey:(Ljava/lang/Object;)Z
     104: ifeq          117
     107: aload_1
     108: aload_2
     109: ldc           #16                 // String password
     111: invokevirtual #5                  // Method java/util/Properties.getProperty:(Ljava/lang/String;)Ljava/lang/String;
     114: invokevirtual #17                 // Method org/postgresql/ds/common/BaseDataSource.setPassword:(Ljava/lang/String;)V
     117: aload_2
     118: invokevirtual #18                 // Method java/util/Properties.entrySet:()Ljava/util/Set;
     121: invokeinterface #19,  1           // InterfaceMethod java/util/Set.iterator:()Ljava/util/Iterator;
     126: astore_3
     127: aload_3
     128: invokeinterface #20,  1           // InterfaceMethod java/util/Iterator.hasNext:()Z
     133: ifeq          174
     136: aload_3
     137: invokeinterface #21,  1           // InterfaceMethod java/util/Iterator.next:()Ljava/lang/Object;
     142: checkcast     #22                 // class java/util/Map$Entry
     145: astore        4
     147: aload_1
     148: aload         4
     150: invokeinterface #23,  1           // InterfaceMethod java/util/Map$Entry.getKey:()Ljava/lang/Object;
     155: checkcast     #24                 // class java/lang/String
     158: aload         4
     160: invokeinterface #25,  1           // InterfaceMethod java/util/Map$Entry.getValue:()Ljava/lang/Object;
     165: checkcast     #24                 // class java/lang/String
     168: invokevirtual #26                 // Method org/postgresql/ds/common/BaseDataSource.setProperty:(Ljava/lang/String;Ljava/lang/String;)V
     171: goto          127
     174: return

  public java.sql.Driver createDriver(java.util.Properties) throws java.sql.SQLException;
    Code:
       0: aload_1
       1: ifnull        31
       4: aload_1
       5: invokevirtual #27                 // Method java/util/Properties.isEmpty:()Z
       8: ifne          31
      11: new           #28                 // class org/postgresql/util/PSQLException
      14: dup
      15: ldc           #29                 // String Unsupported properties: {0}
      17: aload_1
      18: invokevirtual #30                 // Method java/util/Properties.stringPropertyNames:()Ljava/util/Set;
      21: invokestatic  #31                 // Method org/postgresql/util/GT.tr:(Ljava/lang/String;Ljava/lang/Object;)Ljava/lang/String;
      24: getstatic     #32                 // Field org/postgresql/util/PSQLState.INVALID_PARAMETER_VALUE:Lorg/postgresql/util/PSQLState;
      27: invokespecial #33                 // Method org/postgresql/util/PSQLException."<init>":(Ljava/lang/String;Lorg/postgresql/util/PSQLState;)V
      30: athrow
      31: new           #34                 // class org/postgresql/Driver
      34: dup
      35: invokespecial #35                 // Method org/postgresql/Driver."<init>":()V
      38: astore_2
      39: aload_2
      40: areturn

  private javax.sql.DataSource createPoolingDataSource(java.util.Properties) throws java.sql.SQLException;
    Code:
       0: new           #36                 // class org/postgresql/jdbc2/optional/PoolingDataSource
       3: dup
       4: invokespecial #37                 // Method org/postgresql/jdbc2/optional/PoolingDataSource."<init>":()V
       7: astore_2
       8: aload_1
       9: ldc           #38                 // String initialPoolSize
      11: invokevirtual #4                  // Method java/util/Properties.containsKey:(Ljava/lang/Object;)Z
      14: ifeq          30
      17: aload_2
      18: aload_1
      19: ldc           #38                 // String initialPoolSize
      21: invokevirtual #5                  // Method java/util/Properties.getProperty:(Ljava/lang/String;)Ljava/lang/String;
      24: invokestatic  #10                 // Method java/lang/Integer.parseInt:(Ljava/lang/String;)I
      27: invokevirtual #39                 // Method org/postgresql/jdbc2/optional/PoolingDataSource.setInitialConnections:(I)V
      30: aload_1
      31: ldc           #40                 // String maxPoolSize
      33: invokevirtual #4                  // Method java/util/Properties.containsKey:(Ljava/lang/Object;)Z
      36: ifeq          52
      39: aload_2
      40: aload_1
      41: ldc           #40                 // String maxPoolSize
      43: invokevirtual #5                  // Method java/util/Properties.getProperty:(Ljava/lang/String;)Ljava/lang/String;
      46: invokestatic  #10                 // Method java/lang/Integer.parseInt:(Ljava/lang/String;)I
      49: invokevirtual #41                 // Method org/postgresql/jdbc2/optional/PoolingDataSource.setMaxConnections:(I)V
      52: aload_1
      53: ldc           #42                 // String dataSourceName
      55: invokevirtual #4                  // Method java/util/Properties.containsKey:(Ljava/lang/Object;)Z
      58: ifeq          71
      61: aload_2
      62: aload_1
      63: ldc           #42                 // String dataSourceName
      65: invokevirtual #5                  // Method java/util/Properties.getProperty:(Ljava/lang/String;)Ljava/lang/String;
      68: invokevirtual #43                 // Method org/postgresql/jdbc2/optional/PoolingDataSource.setDataSourceName:(Ljava/lang/String;)V
      71: aload_0
      72: aload_2
      73: aload_1
      74: invokespecial #44                 // Method configureBaseDataSource:(Lorg/postgresql/ds/common/BaseDataSource;Ljava/util/Properties;)V
      77: aload_2
      78: areturn

  private javax.sql.DataSource createSimpleDataSource(java.util.Properties) throws java.sql.SQLException;
    Code:
       0: new           #45                 // class org/postgresql/jdbc2/optional/SimpleDataSource
       3: dup
       4: invokespecial #46                 // Method org/postgresql/jdbc2/optional/SimpleDataSource."<init>":()V
       7: astore_2
       8: aload_0
       9: aload_2
      10: aload_1
      11: invokespecial #44                 // Method configureBaseDataSource:(Lorg/postgresql/ds/common/BaseDataSource;Ljava/util/Properties;)V
      14: aload_2
      15: areturn

  public javax.sql.DataSource createDataSource(java.util.Properties) throws java.sql.SQLException;
    Code:
       0: new           #47                 // class org/postgresql/osgi/PGDataSourceFactory$SingleUseProperties
       3: dup
       4: aload_1
       5: invokespecial #48                 // Method org/postgresql/osgi/PGDataSourceFactory$SingleUseProperties."<init>":(Ljava/util/Properties;)V
       8: astore_1
       9: aload_1
      10: ldc           #38                 // String initialPoolSize
      12: invokevirtual #4                  // Method java/util/Properties.containsKey:(Ljava/lang/Object;)Z
      15: ifne          54
      18: aload_1
      19: ldc           #49                 // String minPoolSize
      21: invokevirtual #4                  // Method java/util/Properties.containsKey:(Ljava/lang/Object;)Z
      24: ifne          54
      27: aload_1
      28: ldc           #40                 // String maxPoolSize
      30: invokevirtual #4                  // Method java/util/Properties.containsKey:(Ljava/lang/Object;)Z
      33: ifne          54
      36: aload_1
      37: ldc           #50                 // String maxIdleTime
      39: invokevirtual #4                  // Method java/util/Properties.containsKey:(Ljava/lang/Object;)Z
      42: ifne          54
      45: aload_1
      46: ldc           #51                 // String maxStatements
      48: invokevirtual #4                  // Method java/util/Properties.containsKey:(Ljava/lang/Object;)Z
      51: ifeq          60
      54: aload_0
      55: aload_1
      56: invokespecial #52                 // Method createPoolingDataSource:(Ljava/util/Properties;)Ljavax/sql/DataSource;
      59: areturn
      60: aload_0
      61: aload_1
      62: invokespecial #53                 // Method createSimpleDataSource:(Ljava/util/Properties;)Ljavax/sql/DataSource;
      65: areturn

  public javax.sql.ConnectionPoolDataSource createConnectionPoolDataSource(java.util.Properties) throws java.sql.SQLException;
    Code:
       0: new           #47                 // class org/postgresql/osgi/PGDataSourceFactory$SingleUseProperties
       3: dup
       4: aload_1
       5: invokespecial #48                 // Method org/postgresql/osgi/PGDataSourceFactory$SingleUseProperties."<init>":(Ljava/util/Properties;)V
       8: astore_1
       9: new           #54                 // class org/postgresql/jdbc2/optional/ConnectionPool
      12: dup
      13: invokespecial #55                 // Method org/postgresql/jdbc2/optional/ConnectionPool."<init>":()V
      16: astore_2
      17: aload_0
      18: aload_2
      19: aload_1
      20: invokespecial #44                 // Method configureBaseDataSource:(Lorg/postgresql/ds/common/BaseDataSource;Ljava/util/Properties;)V
      23: aload_2
      24: areturn

  public javax.sql.XADataSource createXADataSource(java.util.Properties) throws java.sql.SQLException;
    Code:
       0: new           #47                 // class org/postgresql/osgi/PGDataSourceFactory$SingleUseProperties
       3: dup
       4: aload_1
       5: invokespecial #48                 // Method org/postgresql/osgi/PGDataSourceFactory$SingleUseProperties."<init>":(Ljava/util/Properties;)V
       8: astore_1
       9: new           #56                 // class org/postgresql/xa/PGXADataSource
      12: dup
      13: invokespecial #57                 // Method org/postgresql/xa/PGXADataSource."<init>":()V
      16: astore_2
      17: aload_0
      18: aload_2
      19: aload_1
      20: invokespecial #44                 // Method configureBaseDataSource:(Lorg/postgresql/ds/common/BaseDataSource;Ljava/util/Properties;)V
      23: aload_2
      24: areturn
}
