final class org.bouncycastle.operator.bc.BcDefaultDigestProvider$9 implements org.bouncycastle.operator.bc.BcDigestProvider {
  org.bouncycastle.operator.bc.BcDefaultDigestProvider$9();
    Code:
       0: aload_0
       1: invokespecial #21                 // Method java/lang/Object."<init>":()V
       4: return

  public org.bouncycastle.crypto.ExtendedDigest get(org.bouncycastle.asn1.x509.AlgorithmIdentifier);
    Code:
       0: new           #12                 // class org/bouncycastle/crypto/digests/SHA3Digest
       3: dup
       4: sipush        512
       7: invokespecial #22                 // Method org/bouncycastle/crypto/digests/SHA3Digest."<init>":(I)V
      10: areturn
}
