Compiled from "GrafanaAsyncClient.java"
public interface software.amazon.awssdk.services.grafana.GrafanaAsyncClient extends software.amazon.awssdk.core.SdkClient {
  public static final java.lang.String SERVICE_NAME;

  public static final java.lang.String SERVICE_METADATA_ID;

  public static software.amazon.awssdk.services.grafana.GrafanaAsyncClient create();
    Code:
       0: invokestatic  #1                  // InterfaceMethod builder:()Lsoftware/amazon/awssdk/services/grafana/GrafanaAsyncClientBuilder;
       3: invokeinterface #2,  1            // InterfaceMethod software/amazon/awssdk/services/grafana/GrafanaAsyncClientBuilder.build:()Ljava/lang/Object;
       8: checkcast     #3                  // class software/amazon/awssdk/services/grafana/GrafanaAsyncClient
      11: areturn

  public static software.amazon.awssdk.services.grafana.GrafanaAsyncClientBuilder builder();
    Code:
       0: new           #4                  // class software/amazon/awssdk/services/grafana/DefaultGrafanaAsyncClientBuilder
       3: dup
       4: invokespecial #5                  // Method software/amazon/awssdk/services/grafana/DefaultGrafanaAsyncClientBuilder."<init>":()V
       7: areturn

  public default java.util.concurrent.CompletableFuture<software.amazon.awssdk.services.grafana.model.AssociateLicenseResponse> associateLicense(software.amazon.awssdk.services.grafana.model.AssociateLicenseRequest);
    Code:
       0: new           #6                  // class java/lang/UnsupportedOperationException
       3: dup
       4: invokespecial #7                  // Method java/lang/UnsupportedOperationException."<init>":()V
       7: athrow

  public default java.util.concurrent.CompletableFuture<software.amazon.awssdk.services.grafana.model.AssociateLicenseResponse> associateLicense(java.util.function.Consumer<software.amazon.awssdk.services.grafana.model.AssociateLicenseRequest$Builder>);
    Code:
       0: aload_0
       1: invokestatic  #8                  // Method software/amazon/awssdk/services/grafana/model/AssociateLicenseRequest.builder:()Lsoftware/amazon/awssdk/services/grafana/model/AssociateLicenseRequest$Builder;
       4: aload_1
       5: invokeinterface #9,  2            // InterfaceMethod software/amazon/awssdk/services/grafana/model/AssociateLicenseRequest$Builder.applyMutation:(Ljava/util/function/Consumer;)Lsoftware/amazon/awssdk/utils/builder/SdkBuilder;
      10: checkcast     #10                 // class software/amazon/awssdk/services/grafana/model/AssociateLicenseRequest$Builder
      13: invokeinterface #11,  1           // InterfaceMethod software/amazon/awssdk/services/grafana/model/AssociateLicenseRequest$Builder.build:()Ljava/lang/Object;
      18: checkcast     #12                 // class software/amazon/awssdk/services/grafana/model/AssociateLicenseRequest
      21: invokeinterface #13,  2           // InterfaceMethod associateLicense:(Lsoftware/amazon/awssdk/services/grafana/model/AssociateLicenseRequest;)Ljava/util/concurrent/CompletableFuture;
      26: areturn

  public default java.util.concurrent.CompletableFuture<software.amazon.awssdk.services.grafana.model.CreateWorkspaceResponse> createWorkspace(software.amazon.awssdk.services.grafana.model.CreateWorkspaceRequest);
    Code:
       0: new           #6                  // class java/lang/UnsupportedOperationException
       3: dup
       4: invokespecial #7                  // Method java/lang/UnsupportedOperationException."<init>":()V
       7: athrow

  public default java.util.concurrent.CompletableFuture<software.amazon.awssdk.services.grafana.model.CreateWorkspaceResponse> createWorkspace(java.util.function.Consumer<software.amazon.awssdk.services.grafana.model.CreateWorkspaceRequest$Builder>);
    Code:
       0: aload_0
       1: invokestatic  #14                 // Method software/amazon/awssdk/services/grafana/model/CreateWorkspaceRequest.builder:()Lsoftware/amazon/awssdk/services/grafana/model/CreateWorkspaceRequest$Builder;
       4: aload_1
       5: invokeinterface #15,  2           // InterfaceMethod software/amazon/awssdk/services/grafana/model/CreateWorkspaceRequest$Builder.applyMutation:(Ljava/util/function/Consumer;)Lsoftware/amazon/awssdk/utils/builder/SdkBuilder;
      10: checkcast     #16                 // class software/amazon/awssdk/services/grafana/model/CreateWorkspaceRequest$Builder
      13: invokeinterface #17,  1           // InterfaceMethod software/amazon/awssdk/services/grafana/model/CreateWorkspaceRequest$Builder.build:()Ljava/lang/Object;
      18: checkcast     #18                 // class software/amazon/awssdk/services/grafana/model/CreateWorkspaceRequest
      21: invokeinterface #19,  2           // InterfaceMethod createWorkspace:(Lsoftware/amazon/awssdk/services/grafana/model/CreateWorkspaceRequest;)Ljava/util/concurrent/CompletableFuture;
      26: areturn

  public default java.util.concurrent.CompletableFuture<software.amazon.awssdk.services.grafana.model.CreateWorkspaceApiKeyResponse> createWorkspaceApiKey(software.amazon.awssdk.services.grafana.model.CreateWorkspaceApiKeyRequest);
    Code:
       0: new           #6                  // class java/lang/UnsupportedOperationException
       3: dup
       4: invokespecial #7                  // Method java/lang/UnsupportedOperationException."<init>":()V
       7: athrow

  public default java.util.concurrent.CompletableFuture<software.amazon.awssdk.services.grafana.model.CreateWorkspaceApiKeyResponse> createWorkspaceApiKey(java.util.function.Consumer<software.amazon.awssdk.services.grafana.model.CreateWorkspaceApiKeyRequest$Builder>);
    Code:
       0: aload_0
       1: invokestatic  #20                 // Method software/amazon/awssdk/services/grafana/model/CreateWorkspaceApiKeyRequest.builder:()Lsoftware/amazon/awssdk/services/grafana/model/CreateWorkspaceApiKeyRequest$Builder;
       4: aload_1
       5: invokeinterface #21,  2           // InterfaceMethod software/amazon/awssdk/services/grafana/model/CreateWorkspaceApiKeyRequest$Builder.applyMutation:(Ljava/util/function/Consumer;)Lsoftware/amazon/awssdk/utils/builder/SdkBuilder;
      10: checkcast     #22                 // class software/amazon/awssdk/services/grafana/model/CreateWorkspaceApiKeyRequest$Builder
      13: invokeinterface #23,  1           // InterfaceMethod software/amazon/awssdk/services/grafana/model/CreateWorkspaceApiKeyRequest$Builder.build:()Ljava/lang/Object;
      18: checkcast     #24                 // class software/amazon/awssdk/services/grafana/model/CreateWorkspaceApiKeyRequest
      21: invokeinterface #25,  2           // InterfaceMethod createWorkspaceApiKey:(Lsoftware/amazon/awssdk/services/grafana/model/CreateWorkspaceApiKeyRequest;)Ljava/util/concurrent/CompletableFuture;
      26: areturn

  public default java.util.concurrent.CompletableFuture<software.amazon.awssdk.services.grafana.model.DeleteWorkspaceResponse> deleteWorkspace(software.amazon.awssdk.services.grafana.model.DeleteWorkspaceRequest);
    Code:
       0: new           #6                  // class java/lang/UnsupportedOperationException
       3: dup
       4: invokespecial #7                  // Method java/lang/UnsupportedOperationException."<init>":()V
       7: athrow

  public default java.util.concurrent.CompletableFuture<software.amazon.awssdk.services.grafana.model.DeleteWorkspaceResponse> deleteWorkspace(java.util.function.Consumer<software.amazon.awssdk.services.grafana.model.DeleteWorkspaceRequest$Builder>);
    Code:
       0: aload_0
       1: invokestatic  #26                 // Method software/amazon/awssdk/services/grafana/model/DeleteWorkspaceRequest.builder:()Lsoftware/amazon/awssdk/services/grafana/model/DeleteWorkspaceRequest$Builder;
       4: aload_1
       5: invokeinterface #27,  2           // InterfaceMethod software/amazon/awssdk/services/grafana/model/DeleteWorkspaceRequest$Builder.applyMutation:(Ljava/util/function/Consumer;)Lsoftware/amazon/awssdk/utils/builder/SdkBuilder;
      10: checkcast     #28                 // class software/amazon/awssdk/services/grafana/model/DeleteWorkspaceRequest$Builder
      13: invokeinterface #29,  1           // InterfaceMethod software/amazon/awssdk/services/grafana/model/DeleteWorkspaceRequest$Builder.build:()Ljava/lang/Object;
      18: checkcast     #30                 // class software/amazon/awssdk/services/grafana/model/DeleteWorkspaceRequest
      21: invokeinterface #31,  2           // InterfaceMethod deleteWorkspace:(Lsoftware/amazon/awssdk/services/grafana/model/DeleteWorkspaceRequest;)Ljava/util/concurrent/CompletableFuture;
      26: areturn

  public default java.util.concurrent.CompletableFuture<software.amazon.awssdk.services.grafana.model.DeleteWorkspaceApiKeyResponse> deleteWorkspaceApiKey(software.amazon.awssdk.services.grafana.model.DeleteWorkspaceApiKeyRequest);
    Code:
       0: new           #6                  // class java/lang/UnsupportedOperationException
       3: dup
       4: invokespecial #7                  // Method java/lang/UnsupportedOperationException."<init>":()V
       7: athrow

  public default java.util.concurrent.CompletableFuture<software.amazon.awssdk.services.grafana.model.DeleteWorkspaceApiKeyResponse> deleteWorkspaceApiKey(java.util.function.Consumer<software.amazon.awssdk.services.grafana.model.DeleteWorkspaceApiKeyRequest$Builder>);
    Code:
       0: aload_0
       1: invokestatic  #32                 // Method software/amazon/awssdk/services/grafana/model/DeleteWorkspaceApiKeyRequest.builder:()Lsoftware/amazon/awssdk/services/grafana/model/DeleteWorkspaceApiKeyRequest$Builder;
       4: aload_1
       5: invokeinterface #33,  2           // InterfaceMethod software/amazon/awssdk/services/grafana/model/DeleteWorkspaceApiKeyRequest$Builder.applyMutation:(Ljava/util/function/Consumer;)Lsoftware/amazon/awssdk/utils/builder/SdkBuilder;
      10: checkcast     #34                 // class software/amazon/awssdk/services/grafana/model/DeleteWorkspaceApiKeyRequest$Builder
      13: invokeinterface #35,  1           // InterfaceMethod software/amazon/awssdk/services/grafana/model/DeleteWorkspaceApiKeyRequest$Builder.build:()Ljava/lang/Object;
      18: checkcast     #36                 // class software/amazon/awssdk/services/grafana/model/DeleteWorkspaceApiKeyRequest
      21: invokeinterface #37,  2           // InterfaceMethod deleteWorkspaceApiKey:(Lsoftware/amazon/awssdk/services/grafana/model/DeleteWorkspaceApiKeyRequest;)Ljava/util/concurrent/CompletableFuture;
      26: areturn

  public default java.util.concurrent.CompletableFuture<software.amazon.awssdk.services.grafana.model.DescribeWorkspaceResponse> describeWorkspace(software.amazon.awssdk.services.grafana.model.DescribeWorkspaceRequest);
    Code:
       0: new           #6                  // class java/lang/UnsupportedOperationException
       3: dup
       4: invokespecial #7                  // Method java/lang/UnsupportedOperationException."<init>":()V
       7: athrow

  public default java.util.concurrent.CompletableFuture<software.amazon.awssdk.services.grafana.model.DescribeWorkspaceResponse> describeWorkspace(java.util.function.Consumer<software.amazon.awssdk.services.grafana.model.DescribeWorkspaceRequest$Builder>);
    Code:
       0: aload_0
       1: invokestatic  #38                 // Method software/amazon/awssdk/services/grafana/model/DescribeWorkspaceRequest.builder:()Lsoftware/amazon/awssdk/services/grafana/model/DescribeWorkspaceRequest$Builder;
       4: aload_1
       5: invokeinterface #39,  2           // InterfaceMethod software/amazon/awssdk/services/grafana/model/DescribeWorkspaceRequest$Builder.applyMutation:(Ljava/util/function/Consumer;)Lsoftware/amazon/awssdk/utils/builder/SdkBuilder;
      10: checkcast     #40                 // class software/amazon/awssdk/services/grafana/model/DescribeWorkspaceRequest$Builder
      13: invokeinterface #41,  1           // InterfaceMethod software/amazon/awssdk/services/grafana/model/DescribeWorkspaceRequest$Builder.build:()Ljava/lang/Object;
      18: checkcast     #42                 // class software/amazon/awssdk/services/grafana/model/DescribeWorkspaceRequest
      21: invokeinterface #43,  2           // InterfaceMethod describeWorkspace:(Lsoftware/amazon/awssdk/services/grafana/model/DescribeWorkspaceRequest;)Ljava/util/concurrent/CompletableFuture;
      26: areturn

  public default java.util.concurrent.CompletableFuture<software.amazon.awssdk.services.grafana.model.DescribeWorkspaceAuthenticationResponse> describeWorkspaceAuthentication(software.amazon.awssdk.services.grafana.model.DescribeWorkspaceAuthenticationRequest);
    Code:
       0: new           #6                  // class java/lang/UnsupportedOperationException
       3: dup
       4: invokespecial #7                  // Method java/lang/UnsupportedOperationException."<init>":()V
       7: athrow

  public default java.util.concurrent.CompletableFuture<software.amazon.awssdk.services.grafana.model.DescribeWorkspaceAuthenticationResponse> describeWorkspaceAuthentication(java.util.function.Consumer<software.amazon.awssdk.services.grafana.model.DescribeWorkspaceAuthenticationRequest$Builder>);
    Code:
       0: aload_0
       1: invokestatic  #44                 // Method software/amazon/awssdk/services/grafana/model/DescribeWorkspaceAuthenticationRequest.builder:()Lsoftware/amazon/awssdk/services/grafana/model/DescribeWorkspaceAuthenticationRequest$Builder;
       4: aload_1
       5: invokeinterface #45,  2           // InterfaceMethod software/amazon/awssdk/services/grafana/model/DescribeWorkspaceAuthenticationRequest$Builder.applyMutation:(Ljava/util/function/Consumer;)Lsoftware/amazon/awssdk/utils/builder/SdkBuilder;
      10: checkcast     #46                 // class software/amazon/awssdk/services/grafana/model/DescribeWorkspaceAuthenticationRequest$Builder
      13: invokeinterface #47,  1           // InterfaceMethod software/amazon/awssdk/services/grafana/model/DescribeWorkspaceAuthenticationRequest$Builder.build:()Ljava/lang/Object;
      18: checkcast     #48                 // class software/amazon/awssdk/services/grafana/model/DescribeWorkspaceAuthenticationRequest
      21: invokeinterface #49,  2           // InterfaceMethod describeWorkspaceAuthentication:(Lsoftware/amazon/awssdk/services/grafana/model/DescribeWorkspaceAuthenticationRequest;)Ljava/util/concurrent/CompletableFuture;
      26: areturn

  public default java.util.concurrent.CompletableFuture<software.amazon.awssdk.services.grafana.model.DisassociateLicenseResponse> disassociateLicense(software.amazon.awssdk.services.grafana.model.DisassociateLicenseRequest);
    Code:
       0: new           #6                  // class java/lang/UnsupportedOperationException
       3: dup
       4: invokespecial #7                  // Method java/lang/UnsupportedOperationException."<init>":()V
       7: athrow

  public default java.util.concurrent.CompletableFuture<software.amazon.awssdk.services.grafana.model.DisassociateLicenseResponse> disassociateLicense(java.util.function.Consumer<software.amazon.awssdk.services.grafana.model.DisassociateLicenseRequest$Builder>);
    Code:
       0: aload_0
       1: invokestatic  #50                 // Method software/amazon/awssdk/services/grafana/model/DisassociateLicenseRequest.builder:()Lsoftware/amazon/awssdk/services/grafana/model/DisassociateLicenseRequest$Builder;
       4: aload_1
       5: invokeinterface #51,  2           // InterfaceMethod software/amazon/awssdk/services/grafana/model/DisassociateLicenseRequest$Builder.applyMutation:(Ljava/util/function/Consumer;)Lsoftware/amazon/awssdk/utils/builder/SdkBuilder;
      10: checkcast     #52                 // class software/amazon/awssdk/services/grafana/model/DisassociateLicenseRequest$Builder
      13: invokeinterface #53,  1           // InterfaceMethod software/amazon/awssdk/services/grafana/model/DisassociateLicenseRequest$Builder.build:()Ljava/lang/Object;
      18: checkcast     #54                 // class software/amazon/awssdk/services/grafana/model/DisassociateLicenseRequest
      21: invokeinterface #55,  2           // InterfaceMethod disassociateLicense:(Lsoftware/amazon/awssdk/services/grafana/model/DisassociateLicenseRequest;)Ljava/util/concurrent/CompletableFuture;
      26: areturn

  public default java.util.concurrent.CompletableFuture<software.amazon.awssdk.services.grafana.model.ListPermissionsResponse> listPermissions(software.amazon.awssdk.services.grafana.model.ListPermissionsRequest);
    Code:
       0: new           #6                  // class java/lang/UnsupportedOperationException
       3: dup
       4: invokespecial #7                  // Method java/lang/UnsupportedOperationException."<init>":()V
       7: athrow

  public default java.util.concurrent.CompletableFuture<software.amazon.awssdk.services.grafana.model.ListPermissionsResponse> listPermissions(java.util.function.Consumer<software.amazon.awssdk.services.grafana.model.ListPermissionsRequest$Builder>);
    Code:
       0: aload_0
       1: invokestatic  #56                 // Method software/amazon/awssdk/services/grafana/model/ListPermissionsRequest.builder:()Lsoftware/amazon/awssdk/services/grafana/model/ListPermissionsRequest$Builder;
       4: aload_1
       5: invokeinterface #57,  2           // InterfaceMethod software/amazon/awssdk/services/grafana/model/ListPermissionsRequest$Builder.applyMutation:(Ljava/util/function/Consumer;)Lsoftware/amazon/awssdk/utils/builder/SdkBuilder;
      10: checkcast     #58                 // class software/amazon/awssdk/services/grafana/model/ListPermissionsRequest$Builder
      13: invokeinterface #59,  1           // InterfaceMethod software/amazon/awssdk/services/grafana/model/ListPermissionsRequest$Builder.build:()Ljava/lang/Object;
      18: checkcast     #60                 // class software/amazon/awssdk/services/grafana/model/ListPermissionsRequest
      21: invokeinterface #61,  2           // InterfaceMethod listPermissions:(Lsoftware/amazon/awssdk/services/grafana/model/ListPermissionsRequest;)Ljava/util/concurrent/CompletableFuture;
      26: areturn

  public default software.amazon.awssdk.services.grafana.paginators.ListPermissionsPublisher listPermissionsPaginator(software.amazon.awssdk.services.grafana.model.ListPermissionsRequest);
    Code:
       0: new           #6                  // class java/lang/UnsupportedOperationException
       3: dup
       4: invokespecial #7                  // Method java/lang/UnsupportedOperationException."<init>":()V
       7: athrow

  public default software.amazon.awssdk.services.grafana.paginators.ListPermissionsPublisher listPermissionsPaginator(java.util.function.Consumer<software.amazon.awssdk.services.grafana.model.ListPermissionsRequest$Builder>);
    Code:
       0: aload_0
       1: invokestatic  #56                 // Method software/amazon/awssdk/services/grafana/model/ListPermissionsRequest.builder:()Lsoftware/amazon/awssdk/services/grafana/model/ListPermissionsRequest$Builder;
       4: aload_1
       5: invokeinterface #57,  2           // InterfaceMethod software/amazon/awssdk/services/grafana/model/ListPermissionsRequest$Builder.applyMutation:(Ljava/util/function/Consumer;)Lsoftware/amazon/awssdk/utils/builder/SdkBuilder;
      10: checkcast     #58                 // class software/amazon/awssdk/services/grafana/model/ListPermissionsRequest$Builder
      13: invokeinterface #59,  1           // InterfaceMethod software/amazon/awssdk/services/grafana/model/ListPermissionsRequest$Builder.build:()Ljava/lang/Object;
      18: checkcast     #60                 // class software/amazon/awssdk/services/grafana/model/ListPermissionsRequest
      21: invokeinterface #62,  2           // InterfaceMethod listPermissionsPaginator:(Lsoftware/amazon/awssdk/services/grafana/model/ListPermissionsRequest;)Lsoftware/amazon/awssdk/services/grafana/paginators/ListPermissionsPublisher;
      26: areturn

  public default java.util.concurrent.CompletableFuture<software.amazon.awssdk.services.grafana.model.ListTagsForResourceResponse> listTagsForResource(software.amazon.awssdk.services.grafana.model.ListTagsForResourceRequest);
    Code:
       0: new           #6                  // class java/lang/UnsupportedOperationException
       3: dup
       4: invokespecial #7                  // Method java/lang/UnsupportedOperationException."<init>":()V
       7: athrow

  public default java.util.concurrent.CompletableFuture<software.amazon.awssdk.services.grafana.model.ListTagsForResourceResponse> listTagsForResource(java.util.function.Consumer<software.amazon.awssdk.services.grafana.model.ListTagsForResourceRequest$Builder>);
    Code:
       0: aload_0
       1: invokestatic  #63                 // Method software/amazon/awssdk/services/grafana/model/ListTagsForResourceRequest.builder:()Lsoftware/amazon/awssdk/services/grafana/model/ListTagsForResourceRequest$Builder;
       4: aload_1
       5: invokeinterface #64,  2           // InterfaceMethod software/amazon/awssdk/services/grafana/model/ListTagsForResourceRequest$Builder.applyMutation:(Ljava/util/function/Consumer;)Lsoftware/amazon/awssdk/utils/builder/SdkBuilder;
      10: checkcast     #65                 // class software/amazon/awssdk/services/grafana/model/ListTagsForResourceRequest$Builder
      13: invokeinterface #66,  1           // InterfaceMethod software/amazon/awssdk/services/grafana/model/ListTagsForResourceRequest$Builder.build:()Ljava/lang/Object;
      18: checkcast     #67                 // class software/amazon/awssdk/services/grafana/model/ListTagsForResourceRequest
      21: invokeinterface #68,  2           // InterfaceMethod listTagsForResource:(Lsoftware/amazon/awssdk/services/grafana/model/ListTagsForResourceRequest;)Ljava/util/concurrent/CompletableFuture;
      26: areturn

  public default java.util.concurrent.CompletableFuture<software.amazon.awssdk.services.grafana.model.ListWorkspacesResponse> listWorkspaces(software.amazon.awssdk.services.grafana.model.ListWorkspacesRequest);
    Code:
       0: new           #6                  // class java/lang/UnsupportedOperationException
       3: dup
       4: invokespecial #7                  // Method java/lang/UnsupportedOperationException."<init>":()V
       7: athrow

  public default java.util.concurrent.CompletableFuture<software.amazon.awssdk.services.grafana.model.ListWorkspacesResponse> listWorkspaces(java.util.function.Consumer<software.amazon.awssdk.services.grafana.model.ListWorkspacesRequest$Builder>);
    Code:
       0: aload_0
       1: invokestatic  #69                 // Method software/amazon/awssdk/services/grafana/model/ListWorkspacesRequest.builder:()Lsoftware/amazon/awssdk/services/grafana/model/ListWorkspacesRequest$Builder;
       4: aload_1
       5: invokeinterface #70,  2           // InterfaceMethod software/amazon/awssdk/services/grafana/model/ListWorkspacesRequest$Builder.applyMutation:(Ljava/util/function/Consumer;)Lsoftware/amazon/awssdk/utils/builder/SdkBuilder;
      10: checkcast     #71                 // class software/amazon/awssdk/services/grafana/model/ListWorkspacesRequest$Builder
      13: invokeinterface #72,  1           // InterfaceMethod software/amazon/awssdk/services/grafana/model/ListWorkspacesRequest$Builder.build:()Ljava/lang/Object;
      18: checkcast     #73                 // class software/amazon/awssdk/services/grafana/model/ListWorkspacesRequest
      21: invokeinterface #74,  2           // InterfaceMethod listWorkspaces:(Lsoftware/amazon/awssdk/services/grafana/model/ListWorkspacesRequest;)Ljava/util/concurrent/CompletableFuture;
      26: areturn

  public default software.amazon.awssdk.services.grafana.paginators.ListWorkspacesPublisher listWorkspacesPaginator(software.amazon.awssdk.services.grafana.model.ListWorkspacesRequest);
    Code:
       0: new           #6                  // class java/lang/UnsupportedOperationException
       3: dup
       4: invokespecial #7                  // Method java/lang/UnsupportedOperationException."<init>":()V
       7: athrow

  public default software.amazon.awssdk.services.grafana.paginators.ListWorkspacesPublisher listWorkspacesPaginator(java.util.function.Consumer<software.amazon.awssdk.services.grafana.model.ListWorkspacesRequest$Builder>);
    Code:
       0: aload_0
       1: invokestatic  #69                 // Method software/amazon/awssdk/services/grafana/model/ListWorkspacesRequest.builder:()Lsoftware/amazon/awssdk/services/grafana/model/ListWorkspacesRequest$Builder;
       4: aload_1
       5: invokeinterface #70,  2           // InterfaceMethod software/amazon/awssdk/services/grafana/model/ListWorkspacesRequest$Builder.applyMutation:(Ljava/util/function/Consumer;)Lsoftware/amazon/awssdk/utils/builder/SdkBuilder;
      10: checkcast     #71                 // class software/amazon/awssdk/services/grafana/model/ListWorkspacesRequest$Builder
      13: invokeinterface #72,  1           // InterfaceMethod software/amazon/awssdk/services/grafana/model/ListWorkspacesRequest$Builder.build:()Ljava/lang/Object;
      18: checkcast     #73                 // class software/amazon/awssdk/services/grafana/model/ListWorkspacesRequest
      21: invokeinterface #75,  2           // InterfaceMethod listWorkspacesPaginator:(Lsoftware/amazon/awssdk/services/grafana/model/ListWorkspacesRequest;)Lsoftware/amazon/awssdk/services/grafana/paginators/ListWorkspacesPublisher;
      26: areturn

  public default java.util.concurrent.CompletableFuture<software.amazon.awssdk.services.grafana.model.TagResourceResponse> tagResource(software.amazon.awssdk.services.grafana.model.TagResourceRequest);
    Code:
       0: new           #6                  // class java/lang/UnsupportedOperationException
       3: dup
       4: invokespecial #7                  // Method java/lang/UnsupportedOperationException."<init>":()V
       7: athrow

  public default java.util.concurrent.CompletableFuture<software.amazon.awssdk.services.grafana.model.TagResourceResponse> tagResource(java.util.function.Consumer<software.amazon.awssdk.services.grafana.model.TagResourceRequest$Builder>);
    Code:
       0: aload_0
       1: invokestatic  #76                 // Method software/amazon/awssdk/services/grafana/model/TagResourceRequest.builder:()Lsoftware/amazon/awssdk/services/grafana/model/TagResourceRequest$Builder;
       4: aload_1
       5: invokeinterface #77,  2           // InterfaceMethod software/amazon/awssdk/services/grafana/model/TagResourceRequest$Builder.applyMutation:(Ljava/util/function/Consumer;)Lsoftware/amazon/awssdk/utils/builder/SdkBuilder;
      10: checkcast     #78                 // class software/amazon/awssdk/services/grafana/model/TagResourceRequest$Builder
      13: invokeinterface #79,  1           // InterfaceMethod software/amazon/awssdk/services/grafana/model/TagResourceRequest$Builder.build:()Ljava/lang/Object;
      18: checkcast     #80                 // class software/amazon/awssdk/services/grafana/model/TagResourceRequest
      21: invokeinterface #81,  2           // InterfaceMethod tagResource:(Lsoftware/amazon/awssdk/services/grafana/model/TagResourceRequest;)Ljava/util/concurrent/CompletableFuture;
      26: areturn

  public default java.util.concurrent.CompletableFuture<software.amazon.awssdk.services.grafana.model.UntagResourceResponse> untagResource(software.amazon.awssdk.services.grafana.model.UntagResourceRequest);
    Code:
       0: new           #6                  // class java/lang/UnsupportedOperationException
       3: dup
       4: invokespecial #7                  // Method java/lang/UnsupportedOperationException."<init>":()V
       7: athrow

  public default java.util.concurrent.CompletableFuture<software.amazon.awssdk.services.grafana.model.UntagResourceResponse> untagResource(java.util.function.Consumer<software.amazon.awssdk.services.grafana.model.UntagResourceRequest$Builder>);
    Code:
       0: aload_0
       1: invokestatic  #82                 // Method software/amazon/awssdk/services/grafana/model/UntagResourceRequest.builder:()Lsoftware/amazon/awssdk/services/grafana/model/UntagResourceRequest$Builder;
       4: aload_1
       5: invokeinterface #83,  2           // InterfaceMethod software/amazon/awssdk/services/grafana/model/UntagResourceRequest$Builder.applyMutation:(Ljava/util/function/Consumer;)Lsoftware/amazon/awssdk/utils/builder/SdkBuilder;
      10: checkcast     #84                 // class software/amazon/awssdk/services/grafana/model/UntagResourceRequest$Builder
      13: invokeinterface #85,  1           // InterfaceMethod software/amazon/awssdk/services/grafana/model/UntagResourceRequest$Builder.build:()Ljava/lang/Object;
      18: checkcast     #86                 // class software/amazon/awssdk/services/grafana/model/UntagResourceRequest
      21: invokeinterface #87,  2           // InterfaceMethod untagResource:(Lsoftware/amazon/awssdk/services/grafana/model/UntagResourceRequest;)Ljava/util/concurrent/CompletableFuture;
      26: areturn

  public default java.util.concurrent.CompletableFuture<software.amazon.awssdk.services.grafana.model.UpdatePermissionsResponse> updatePermissions(software.amazon.awssdk.services.grafana.model.UpdatePermissionsRequest);
    Code:
       0: new           #6                  // class java/lang/UnsupportedOperationException
       3: dup
       4: invokespecial #7                  // Method java/lang/UnsupportedOperationException."<init>":()V
       7: athrow

  public default java.util.concurrent.CompletableFuture<software.amazon.awssdk.services.grafana.model.UpdatePermissionsResponse> updatePermissions(java.util.function.Consumer<software.amazon.awssdk.services.grafana.model.UpdatePermissionsRequest$Builder>);
    Code:
       0: aload_0
       1: invokestatic  #88                 // Method software/amazon/awssdk/services/grafana/model/UpdatePermissionsRequest.builder:()Lsoftware/amazon/awssdk/services/grafana/model/UpdatePermissionsRequest$Builder;
       4: aload_1
       5: invokeinterface #89,  2           // InterfaceMethod software/amazon/awssdk/services/grafana/model/UpdatePermissionsRequest$Builder.applyMutation:(Ljava/util/function/Consumer;)Lsoftware/amazon/awssdk/utils/builder/SdkBuilder;
      10: checkcast     #90                 // class software/amazon/awssdk/services/grafana/model/UpdatePermissionsRequest$Builder
      13: invokeinterface #91,  1           // InterfaceMethod software/amazon/awssdk/services/grafana/model/UpdatePermissionsRequest$Builder.build:()Ljava/lang/Object;
      18: checkcast     #92                 // class software/amazon/awssdk/services/grafana/model/UpdatePermissionsRequest
      21: invokeinterface #93,  2           // InterfaceMethod updatePermissions:(Lsoftware/amazon/awssdk/services/grafana/model/UpdatePermissionsRequest;)Ljava/util/concurrent/CompletableFuture;
      26: areturn

  public default java.util.concurrent.CompletableFuture<software.amazon.awssdk.services.grafana.model.UpdateWorkspaceResponse> updateWorkspace(software.amazon.awssdk.services.grafana.model.UpdateWorkspaceRequest);
    Code:
       0: new           #6                  // class java/lang/UnsupportedOperationException
       3: dup
       4: invokespecial #7                  // Method java/lang/UnsupportedOperationException."<init>":()V
       7: athrow

  public default java.util.concurrent.CompletableFuture<software.amazon.awssdk.services.grafana.model.UpdateWorkspaceResponse> updateWorkspace(java.util.function.Consumer<software.amazon.awssdk.services.grafana.model.UpdateWorkspaceRequest$Builder>);
    Code:
       0: aload_0
       1: invokestatic  #94                 // Method software/amazon/awssdk/services/grafana/model/UpdateWorkspaceRequest.builder:()Lsoftware/amazon/awssdk/services/grafana/model/UpdateWorkspaceRequest$Builder;
       4: aload_1
       5: invokeinterface #95,  2           // InterfaceMethod software/amazon/awssdk/services/grafana/model/UpdateWorkspaceRequest$Builder.applyMutation:(Ljava/util/function/Consumer;)Lsoftware/amazon/awssdk/utils/builder/SdkBuilder;
      10: checkcast     #96                 // class software/amazon/awssdk/services/grafana/model/UpdateWorkspaceRequest$Builder
      13: invokeinterface #97,  1           // InterfaceMethod software/amazon/awssdk/services/grafana/model/UpdateWorkspaceRequest$Builder.build:()Ljava/lang/Object;
      18: checkcast     #98                 // class software/amazon/awssdk/services/grafana/model/UpdateWorkspaceRequest
      21: invokeinterface #99,  2           // InterfaceMethod updateWorkspace:(Lsoftware/amazon/awssdk/services/grafana/model/UpdateWorkspaceRequest;)Ljava/util/concurrent/CompletableFuture;
      26: areturn

  public default java.util.concurrent.CompletableFuture<software.amazon.awssdk.services.grafana.model.UpdateWorkspaceAuthenticationResponse> updateWorkspaceAuthentication(software.amazon.awssdk.services.grafana.model.UpdateWorkspaceAuthenticationRequest);
    Code:
       0: new           #6                  // class java/lang/UnsupportedOperationException
       3: dup
       4: invokespecial #7                  // Method java/lang/UnsupportedOperationException."<init>":()V
       7: athrow

  public default java.util.concurrent.CompletableFuture<software.amazon.awssdk.services.grafana.model.UpdateWorkspaceAuthenticationResponse> updateWorkspaceAuthentication(java.util.function.Consumer<software.amazon.awssdk.services.grafana.model.UpdateWorkspaceAuthenticationRequest$Builder>);
    Code:
       0: aload_0
       1: invokestatic  #100                // Method software/amazon/awssdk/services/grafana/model/UpdateWorkspaceAuthenticationRequest.builder:()Lsoftware/amazon/awssdk/services/grafana/model/UpdateWorkspaceAuthenticationRequest$Builder;
       4: aload_1
       5: invokeinterface #101,  2          // InterfaceMethod software/amazon/awssdk/services/grafana/model/UpdateWorkspaceAuthenticationRequest$Builder.applyMutation:(Ljava/util/function/Consumer;)Lsoftware/amazon/awssdk/utils/builder/SdkBuilder;
      10: checkcast     #102                // class software/amazon/awssdk/services/grafana/model/UpdateWorkspaceAuthenticationRequest$Builder
      13: invokeinterface #103,  1          // InterfaceMethod software/amazon/awssdk/services/grafana/model/UpdateWorkspaceAuthenticationRequest$Builder.build:()Ljava/lang/Object;
      18: checkcast     #104                // class software/amazon/awssdk/services/grafana/model/UpdateWorkspaceAuthenticationRequest
      21: invokeinterface #105,  2          // InterfaceMethod updateWorkspaceAuthentication:(Lsoftware/amazon/awssdk/services/grafana/model/UpdateWorkspaceAuthenticationRequest;)Ljava/util/concurrent/CompletableFuture;
      26: areturn
}
