Compiled from "SerializerUtilsTest.java"
public class io.druid.common.utils.SerializerUtilsTest {
  private io.druid.common.utils.SerializerUtils serializerUtils;

  private final float delta;

  private final java.lang.String[] strings;

  private final int[] ints;

  private final float[] floats;

  private final long[] longs;

  private final java.nio.charset.Charset UTF8;

  private byte[] stringsByte;

  private byte[] intsByte;

  private byte[] floatsByte;

  private byte[] longsByte;

  private java.io.ByteArrayOutputStream outStream;

  public io.druid.common.utils.SerializerUtilsTest();
    Code:
       0: aload_0
       1: invokespecial #1                  // Method java/lang/Object."<init>":()V
       4: aload_0
       5: fconst_0
       6: putfield      #2                  // Field delta:F
       9: aload_0
      10: iconst_3
      11: anewarray     #3                  // class java/lang/String
      14: dup
      15: iconst_0
      16: ldc           #4                  // String 1#
      18: aastore
      19: dup
      20: iconst_1
      21: ldc           #5                  // String 2
      23: aastore
      24: dup
      25: iconst_2
      26: ldc           #6                  // String 3
      28: aastore
      29: putfield      #7                  // Field strings:[Ljava/lang/String;
      32: aload_0
      33: iconst_3
      34: newarray       int
      36: dup
      37: iconst_0
      38: iconst_1
      39: iastore
      40: dup
      41: iconst_1
      42: iconst_2
      43: iastore
      44: dup
      45: iconst_2
      46: iconst_3
      47: iastore
      48: putfield      #8                  // Field ints:[I
      51: aload_0
      52: iconst_3
      53: newarray       float
      55: dup
      56: iconst_0
      57: ldc           #9                  // float 1.1f
      59: fastore
      60: dup
      61: iconst_1
      62: fconst_2
      63: fastore
      64: dup
      65: iconst_2
      66: ldc           #10                 // float 3.0f
      68: fastore
      69: putfield      #11                 // Field floats:[F
      72: aload_0
      73: iconst_3
      74: newarray       long
      76: dup
      77: iconst_0
      78: ldc2_w        #12                 // long 3l
      81: lastore
      82: dup
      83: iconst_1
      84: ldc2_w        #14                 // long 2l
      87: lastore
      88: dup
      89: iconst_2
      90: lconst_1
      91: lastore
      92: putfield      #16                 // Field longs:[J
      95: aload_0
      96: ldc           #17                 // String UTF-8
      98: invokestatic  #18                 // Method java/nio/charset/Charset.forName:(Ljava/lang/String;)Ljava/nio/charset/Charset;
     101: putfield      #19                 // Field UTF8:Ljava/nio/charset/Charset;
     104: return

  public void setUpByteArrays() throws java.io.IOException;
    Code:
       0: new           #20                 // class java/io/ByteArrayOutputStream
       3: dup
       4: invokespecial #21                 // Method java/io/ByteArrayOutputStream."<init>":()V
       7: astore_1
       8: new           #22                 // class java/io/DataOutputStream
      11: dup
      12: aload_1
      13: invokespecial #23                 // Method java/io/DataOutputStream."<init>":(Ljava/io/OutputStream;)V
      16: astore_2
      17: aload_2
      18: aload_0
      19: getfield      #7                  // Field strings:[Ljava/lang/String;
      22: arraylength
      23: invokevirtual #24                 // Method java/io/DataOutputStream.writeInt:(I)V
      26: iconst_0
      27: istore_3
      28: iload_3
      29: aload_0
      30: getfield      #7                  // Field strings:[Ljava/lang/String;
      33: arraylength
      34: if_icmpge     78
      37: aload_0
      38: getfield      #7                  // Field strings:[Ljava/lang/String;
      41: iload_3
      42: aaload
      43: aload_0
      44: getfield      #19                 // Field UTF8:Ljava/nio/charset/Charset;
      47: invokevirtual #25                 // Method java/lang/String.getBytes:(Ljava/nio/charset/Charset;)[B
      50: astore        4
      52: aload_2
      53: aload         4
      55: arraylength
      56: invokevirtual #24                 // Method java/io/DataOutputStream.writeInt:(I)V
      59: aload_2
      60: aload_0
      61: getfield      #7                  // Field strings:[Ljava/lang/String;
      64: iload_3
      65: aaload
      66: invokevirtual #26                 // Method java/lang/String.getBytes:()[B
      69: invokevirtual #27                 // Method java/io/DataOutputStream.write:([B)V
      72: iinc          3, 1
      75: goto          28
      78: aload_2
      79: invokevirtual #28                 // Method java/io/DataOutputStream.close:()V
      82: aload_0
      83: aload_1
      84: invokevirtual #29                 // Method java/io/ByteArrayOutputStream.toByteArray:()[B
      87: putfield      #30                 // Field stringsByte:[B
      90: aload_1
      91: invokevirtual #31                 // Method java/io/ByteArrayOutputStream.close:()V
      94: new           #20                 // class java/io/ByteArrayOutputStream
      97: dup
      98: invokespecial #21                 // Method java/io/ByteArrayOutputStream."<init>":()V
     101: astore_1
     102: new           #22                 // class java/io/DataOutputStream
     105: dup
     106: aload_1
     107: invokespecial #23                 // Method java/io/DataOutputStream."<init>":(Ljava/io/OutputStream;)V
     110: astore_2
     111: aload_2
     112: aload_0
     113: getfield      #8                  // Field ints:[I
     116: arraylength
     117: invokevirtual #24                 // Method java/io/DataOutputStream.writeInt:(I)V
     120: iconst_0
     121: istore_3
     122: iload_3
     123: aload_0
     124: getfield      #8                  // Field ints:[I
     127: arraylength
     128: if_icmpge     147
     131: aload_2
     132: aload_0
     133: getfield      #8                  // Field ints:[I
     136: iload_3
     137: iaload
     138: invokevirtual #24                 // Method java/io/DataOutputStream.writeInt:(I)V
     141: iinc          3, 1
     144: goto          122
     147: aload_2
     148: invokevirtual #28                 // Method java/io/DataOutputStream.close:()V
     151: aload_0
     152: aload_1
     153: invokevirtual #29                 // Method java/io/ByteArrayOutputStream.toByteArray:()[B
     156: putfield      #32                 // Field intsByte:[B
     159: aload_1
     160: invokevirtual #31                 // Method java/io/ByteArrayOutputStream.close:()V
     163: new           #20                 // class java/io/ByteArrayOutputStream
     166: dup
     167: invokespecial #21                 // Method java/io/ByteArrayOutputStream."<init>":()V
     170: astore_1
     171: new           #22                 // class java/io/DataOutputStream
     174: dup
     175: aload_1
     176: invokespecial #23                 // Method java/io/DataOutputStream."<init>":(Ljava/io/OutputStream;)V
     179: astore_2
     180: aload_2
     181: aload_0
     182: getfield      #11                 // Field floats:[F
     185: arraylength
     186: invokevirtual #24                 // Method java/io/DataOutputStream.writeInt:(I)V
     189: iconst_0
     190: istore_3
     191: iload_3
     192: aload_0
     193: getfield      #8                  // Field ints:[I
     196: arraylength
     197: if_icmpge     216
     200: aload_2
     201: aload_0
     202: getfield      #11                 // Field floats:[F
     205: iload_3
     206: faload
     207: invokevirtual #33                 // Method java/io/DataOutputStream.writeFloat:(F)V
     210: iinc          3, 1
     213: goto          191
     216: aload_2
     217: invokevirtual #28                 // Method java/io/DataOutputStream.close:()V
     220: aload_0
     221: aload_1
     222: invokevirtual #29                 // Method java/io/ByteArrayOutputStream.toByteArray:()[B
     225: putfield      #34                 // Field floatsByte:[B
     228: aload_1
     229: invokevirtual #31                 // Method java/io/ByteArrayOutputStream.close:()V
     232: new           #20                 // class java/io/ByteArrayOutputStream
     235: dup
     236: invokespecial #21                 // Method java/io/ByteArrayOutputStream."<init>":()V
     239: astore_1
     240: new           #22                 // class java/io/DataOutputStream
     243: dup
     244: aload_1
     245: invokespecial #23                 // Method java/io/DataOutputStream."<init>":(Ljava/io/OutputStream;)V
     248: astore_2
     249: aload_2
     250: aload_0
     251: getfield      #16                 // Field longs:[J
     254: arraylength
     255: invokevirtual #24                 // Method java/io/DataOutputStream.writeInt:(I)V
     258: iconst_0
     259: istore_3
     260: iload_3
     261: aload_0
     262: getfield      #16                 // Field longs:[J
     265: arraylength
     266: if_icmpge     285
     269: aload_2
     270: aload_0
     271: getfield      #16                 // Field longs:[J
     274: iload_3
     275: laload
     276: invokevirtual #35                 // Method java/io/DataOutputStream.writeLong:(J)V
     279: iinc          3, 1
     282: goto          260
     285: aload_2
     286: invokevirtual #28                 // Method java/io/DataOutputStream.close:()V
     289: aload_0
     290: aload_1
     291: invokevirtual #29                 // Method java/io/ByteArrayOutputStream.toByteArray:()[B
     294: putfield      #36                 // Field longsByte:[B
     297: aload_1
     298: invokevirtual #31                 // Method java/io/ByteArrayOutputStream.close:()V
     301: aload_0
     302: new           #37                 // class io/druid/common/utils/SerializerUtils
     305: dup
     306: invokespecial #38                 // Method io/druid/common/utils/SerializerUtils."<init>":()V
     309: putfield      #39                 // Field serializerUtils:Lio/druid/common/utils/SerializerUtils;
     312: aload_0
     313: new           #20                 // class java/io/ByteArrayOutputStream
     316: dup
     317: invokespecial #21                 // Method java/io/ByteArrayOutputStream."<init>":()V
     320: putfield      #40                 // Field outStream:Ljava/io/ByteArrayOutputStream;
     323: return

  public void testWriteInts() throws java.io.IOException;
    Code:
       0: aload_0
       1: getfield      #39                 // Field serializerUtils:Lio/druid/common/utils/SerializerUtils;
       4: aload_0
       5: getfield      #40                 // Field outStream:Ljava/io/ByteArrayOutputStream;
       8: aload_0
       9: getfield      #8                  // Field ints:[I
      12: invokevirtual #41                 // Method io/druid/common/utils/SerializerUtils.writeInts:(Ljava/io/OutputStream;[I)V
      15: aload_0
      16: getfield      #40                 // Field outStream:Ljava/io/ByteArrayOutputStream;
      19: invokevirtual #29                 // Method java/io/ByteArrayOutputStream.toByteArray:()[B
      22: astore_1
      23: aload_0
      24: getfield      #32                 // Field intsByte:[B
      27: aload_1
      28: invokestatic  #42                 // Method org/junit/Assert.assertArrayEquals:([B[B)V
      31: return

  public void testWriteIntList() throws java.io.IOException;
    Code:
       0: new           #43                 // class io/druid/collections/IntList
       3: dup
       4: invokespecial #44                 // Method io/druid/collections/IntList."<init>":()V
       7: astore_1
       8: iconst_0
       9: istore_2
      10: iload_2
      11: aload_0
      12: getfield      #8                  // Field ints:[I
      15: arraylength
      16: if_icmpge     35
      19: aload_1
      20: aload_0
      21: getfield      #8                  // Field ints:[I
      24: iload_2
      25: iaload
      26: invokevirtual #45                 // Method io/druid/collections/IntList.add:(I)V
      29: iinc          2, 1
      32: goto          10
      35: aload_0
      36: getfield      #39                 // Field serializerUtils:Lio/druid/common/utils/SerializerUtils;
      39: aload_0
      40: getfield      #40                 // Field outStream:Ljava/io/ByteArrayOutputStream;
      43: aload_1
      44: invokevirtual #46                 // Method io/druid/common/utils/SerializerUtils.writeInts:(Ljava/io/OutputStream;Lio/druid/collections/IntList;)V
      47: aload_0
      48: getfield      #40                 // Field outStream:Ljava/io/ByteArrayOutputStream;
      51: invokevirtual #29                 // Method java/io/ByteArrayOutputStream.toByteArray:()[B
      54: astore_2
      55: aload_0
      56: getfield      #32                 // Field intsByte:[B
      59: aload_2
      60: invokestatic  #42                 // Method org/junit/Assert.assertArrayEquals:([B[B)V
      63: return

  public void testWriteFloats() throws java.io.IOException;
    Code:
       0: aload_0
       1: getfield      #39                 // Field serializerUtils:Lio/druid/common/utils/SerializerUtils;
       4: aload_0
       5: getfield      #40                 // Field outStream:Ljava/io/ByteArrayOutputStream;
       8: aload_0
       9: getfield      #11                 // Field floats:[F
      12: invokevirtual #47                 // Method io/druid/common/utils/SerializerUtils.writeFloats:(Ljava/io/OutputStream;[F)V
      15: aload_0
      16: getfield      #40                 // Field outStream:Ljava/io/ByteArrayOutputStream;
      19: invokevirtual #29                 // Method java/io/ByteArrayOutputStream.toByteArray:()[B
      22: astore_1
      23: aload_0
      24: getfield      #34                 // Field floatsByte:[B
      27: aload_1
      28: invokestatic  #42                 // Method org/junit/Assert.assertArrayEquals:([B[B)V
      31: return

  public void testChannelWritefloat() throws java.io.IOException;
    Code:
       0: iconst_0
       1: istore_1
       2: aload_0
       3: getfield      #40                 // Field outStream:Ljava/io/ByteArrayOutputStream;
       6: invokestatic  #48                 // Method java/nio/channels/Channels.newChannel:(Ljava/io/OutputStream;)Ljava/nio/channels/WritableByteChannel;
       9: astore_2
      10: aload_0
      11: getfield      #39                 // Field serializerUtils:Lio/druid/common/utils/SerializerUtils;
      14: aload_2
      15: aload_0
      16: getfield      #11                 // Field floats:[F
      19: iconst_0
      20: faload
      21: invokevirtual #49                 // Method io/druid/common/utils/SerializerUtils.writeFloat:(Ljava/nio/channels/WritableByteChannel;F)V
      24: new           #50                 // class java/io/ByteArrayInputStream
      27: dup
      28: aload_0
      29: getfield      #40                 // Field outStream:Ljava/io/ByteArrayOutputStream;
      32: invokevirtual #29                 // Method java/io/ByteArrayOutputStream.toByteArray:()[B
      35: invokespecial #51                 // Method java/io/ByteArrayInputStream."<init>":([B)V
      38: astore_3
      39: aload_2
      40: ifnull        49
      43: aload_2
      44: invokeinterface #52,  1           // InterfaceMethod java/nio/channels/WritableByteChannel.close:()V
      49: aload_0
      50: getfield      #39                 // Field serializerUtils:Lio/druid/common/utils/SerializerUtils;
      53: aload_3
      54: invokevirtual #53                 // Method io/druid/common/utils/SerializerUtils.readFloat:(Ljava/io/InputStream;)F
      57: fstore        4
      59: aload_0
      60: getfield      #11                 // Field floats:[F
      63: iconst_0
      64: faload
      65: fstore        5
      67: fload         4
      69: fload         5
      71: fconst_0
      72: invokestatic  #54                 // Method org/junit/Assert.assertEquals:(FFF)V
      75: return

  public void testWriteLongs() throws java.io.IOException;
    Code:
       0: aload_0
       1: getfield      #39                 // Field serializerUtils:Lio/druid/common/utils/SerializerUtils;
       4: aload_0
       5: getfield      #40                 // Field outStream:Ljava/io/ByteArrayOutputStream;
       8: aload_0
       9: getfield      #16                 // Field longs:[J
      12: invokevirtual #55                 // Method io/druid/common/utils/SerializerUtils.writeLongs:(Ljava/io/OutputStream;[J)V
      15: aload_0
      16: getfield      #40                 // Field outStream:Ljava/io/ByteArrayOutputStream;
      19: invokevirtual #29                 // Method java/io/ByteArrayOutputStream.toByteArray:()[B
      22: astore_1
      23: aload_0
      24: getfield      #36                 // Field longsByte:[B
      27: aload_1
      28: invokestatic  #42                 // Method org/junit/Assert.assertArrayEquals:([B[B)V
      31: return

  public void testWriteStrings() throws java.io.IOException;
    Code:
       0: aload_0
       1: getfield      #39                 // Field serializerUtils:Lio/druid/common/utils/SerializerUtils;
       4: aload_0
       5: getfield      #40                 // Field outStream:Ljava/io/ByteArrayOutputStream;
       8: aload_0
       9: getfield      #7                  // Field strings:[Ljava/lang/String;
      12: invokevirtual #56                 // Method io/druid/common/utils/SerializerUtils.writeStrings:(Ljava/io/OutputStream;[Ljava/lang/String;)V
      15: aload_0
      16: getfield      #40                 // Field outStream:Ljava/io/ByteArrayOutputStream;
      19: invokevirtual #29                 // Method java/io/ByteArrayOutputStream.toByteArray:()[B
      22: astore_1
      23: aload_0
      24: getfield      #30                 // Field stringsByte:[B
      27: aload_1
      28: invokestatic  #42                 // Method org/junit/Assert.assertArrayEquals:([B[B)V
      31: return

  public void testChannelWritelong() throws java.io.IOException;
    Code:
       0: iconst_0
       1: istore_1
       2: aload_0
       3: getfield      #40                 // Field outStream:Ljava/io/ByteArrayOutputStream;
       6: invokestatic  #48                 // Method java/nio/channels/Channels.newChannel:(Ljava/io/OutputStream;)Ljava/nio/channels/WritableByteChannel;
       9: astore_2
      10: aload_0
      11: getfield      #39                 // Field serializerUtils:Lio/druid/common/utils/SerializerUtils;
      14: aload_2
      15: aload_0
      16: getfield      #16                 // Field longs:[J
      19: iconst_0
      20: laload
      21: invokevirtual #57                 // Method io/druid/common/utils/SerializerUtils.writeLong:(Ljava/nio/channels/WritableByteChannel;J)V
      24: new           #50                 // class java/io/ByteArrayInputStream
      27: dup
      28: aload_0
      29: getfield      #40                 // Field outStream:Ljava/io/ByteArrayOutputStream;
      32: invokevirtual #29                 // Method java/io/ByteArrayOutputStream.toByteArray:()[B
      35: invokespecial #51                 // Method java/io/ByteArrayInputStream."<init>":([B)V
      38: astore_3
      39: aload_2
      40: invokeinterface #52,  1           // InterfaceMethod java/nio/channels/WritableByteChannel.close:()V
      45: aload_3
      46: invokevirtual #58                 // Method java/io/ByteArrayInputStream.close:()V
      49: aload_0
      50: getfield      #39                 // Field serializerUtils:Lio/druid/common/utils/SerializerUtils;
      53: aload_3
      54: invokevirtual #59                 // Method io/druid/common/utils/SerializerUtils.readLong:(Ljava/io/InputStream;)J
      57: lstore        4
      59: aload_0
      60: getfield      #16                 // Field longs:[J
      63: iconst_0
      64: laload
      65: lstore        6
      67: lload         4
      69: lload         6
      71: invokestatic  #60                 // Method org/junit/Assert.assertEquals:(JJ)V
      74: return

  public void testReadInts() throws java.io.IOException;
    Code:
       0: new           #50                 // class java/io/ByteArrayInputStream
       3: dup
       4: aload_0
       5: getfield      #32                 // Field intsByte:[B
       8: invokespecial #51                 // Method java/io/ByteArrayInputStream."<init>":([B)V
      11: astore_1
      12: aload_0
      13: getfield      #39                 // Field serializerUtils:Lio/druid/common/utils/SerializerUtils;
      16: aload_1
      17: invokevirtual #61                 // Method io/druid/common/utils/SerializerUtils.readInts:(Ljava/io/InputStream;)[I
      20: astore_2
      21: aload_1
      22: invokevirtual #58                 // Method java/io/ByteArrayInputStream.close:()V
      25: aload_0
      26: getfield      #8                  // Field ints:[I
      29: aload_2
      30: invokestatic  #62                 // Method org/junit/Assert.assertArrayEquals:([I[I)V
      33: return

  public void testReadFloats() throws java.io.IOException;
    Code:
       0: new           #50                 // class java/io/ByteArrayInputStream
       3: dup
       4: aload_0
       5: getfield      #34                 // Field floatsByte:[B
       8: invokespecial #51                 // Method java/io/ByteArrayInputStream."<init>":([B)V
      11: astore_1
      12: aload_0
      13: getfield      #39                 // Field serializerUtils:Lio/druid/common/utils/SerializerUtils;
      16: aload_1
      17: invokevirtual #63                 // Method io/druid/common/utils/SerializerUtils.readFloats:(Ljava/io/InputStream;)[F
      20: astore_2
      21: aload_1
      22: invokevirtual #58                 // Method java/io/ByteArrayInputStream.close:()V
      25: aload_0
      26: getfield      #11                 // Field floats:[F
      29: aload_2
      30: fconst_0
      31: invokestatic  #64                 // Method org/junit/Assert.assertArrayEquals:([F[FF)V
      34: return

  public void testReadLongs() throws java.io.IOException;
    Code:
       0: new           #50                 // class java/io/ByteArrayInputStream
       3: dup
       4: aload_0
       5: getfield      #36                 // Field longsByte:[B
       8: invokespecial #51                 // Method java/io/ByteArrayInputStream."<init>":([B)V
      11: astore_1
      12: aload_0
      13: getfield      #39                 // Field serializerUtils:Lio/druid/common/utils/SerializerUtils;
      16: aload_1
      17: invokevirtual #65                 // Method io/druid/common/utils/SerializerUtils.readLongs:(Ljava/io/InputStream;)[J
      20: astore_2
      21: aload_1
      22: invokevirtual #58                 // Method java/io/ByteArrayInputStream.close:()V
      25: aload_0
      26: getfield      #16                 // Field longs:[J
      29: aload_2
      30: invokestatic  #66                 // Method org/junit/Assert.assertArrayEquals:([J[J)V
      33: return

  public void testReadStrings() throws java.io.IOException;
    Code:
       0: new           #50                 // class java/io/ByteArrayInputStream
       3: dup
       4: aload_0
       5: getfield      #30                 // Field stringsByte:[B
       8: invokespecial #51                 // Method java/io/ByteArrayInputStream."<init>":([B)V
      11: astore_1
      12: aload_0
      13: getfield      #39                 // Field serializerUtils:Lio/druid/common/utils/SerializerUtils;
      16: aload_1
      17: invokevirtual #67                 // Method io/druid/common/utils/SerializerUtils.readStrings:(Ljava/io/InputStream;)[Ljava/lang/String;
      20: astore_2
      21: aload_1
      22: invokevirtual #58                 // Method java/io/ByteArrayInputStream.close:()V
      25: aload_0
      26: getfield      #7                  // Field strings:[Ljava/lang/String;
      29: aload_2
      30: invokestatic  #68                 // Method org/junit/Assert.assertArrayEquals:([Ljava/lang/Object;[Ljava/lang/Object;)V
      33: return

  public void testChannelWriteString() throws java.io.IOException;
    Code:
       0: iconst_0
       1: istore_1
       2: aload_0
       3: getfield      #40                 // Field outStream:Ljava/io/ByteArrayOutputStream;
       6: invokestatic  #48                 // Method java/nio/channels/Channels.newChannel:(Ljava/io/OutputStream;)Ljava/nio/channels/WritableByteChannel;
       9: astore_2
      10: aload_0
      11: getfield      #39                 // Field serializerUtils:Lio/druid/common/utils/SerializerUtils;
      14: aload_2
      15: aload_0
      16: getfield      #7                  // Field strings:[Ljava/lang/String;
      19: iconst_0
      20: aaload
      21: invokevirtual #69                 // Method io/druid/common/utils/SerializerUtils.writeString:(Ljava/nio/channels/WritableByteChannel;Ljava/lang/String;)V
      24: new           #50                 // class java/io/ByteArrayInputStream
      27: dup
      28: aload_0
      29: getfield      #40                 // Field outStream:Ljava/io/ByteArrayOutputStream;
      32: invokevirtual #29                 // Method java/io/ByteArrayOutputStream.toByteArray:()[B
      35: invokespecial #51                 // Method java/io/ByteArrayInputStream."<init>":([B)V
      38: astore_3
      39: aload_2
      40: invokeinterface #52,  1           // InterfaceMethod java/nio/channels/WritableByteChannel.close:()V
      45: aload_3
      46: invokevirtual #58                 // Method java/io/ByteArrayInputStream.close:()V
      49: aload_0
      50: getfield      #39                 // Field serializerUtils:Lio/druid/common/utils/SerializerUtils;
      53: aload_3
      54: invokevirtual #70                 // Method io/druid/common/utils/SerializerUtils.readString:(Ljava/io/InputStream;)Ljava/lang/String;
      57: astore        4
      59: aload_0
      60: getfield      #7                  // Field strings:[Ljava/lang/String;
      63: iconst_0
      64: aaload
      65: astore        5
      67: aload         4
      69: aload         5
      71: invokestatic  #71                 // Method org/junit/Assert.assertEquals:(Ljava/lang/Object;Ljava/lang/Object;)V
      74: return

  public void testByteBufferReadStrings() throws java.io.IOException;
    Code:
       0: aload_0
       1: getfield      #30                 // Field stringsByte:[B
       4: arraylength
       5: invokestatic  #72                 // Method java/nio/ByteBuffer.allocate:(I)Ljava/nio/ByteBuffer;
       8: astore_1
       9: aload_1
      10: aload_0
      11: getfield      #30                 // Field stringsByte:[B
      14: invokevirtual #73                 // Method java/nio/ByteBuffer.put:([B)Ljava/nio/ByteBuffer;
      17: pop
      18: aload_1
      19: invokevirtual #74                 // Method java/nio/ByteBuffer.flip:()Ljava/nio/Buffer;
      22: pop
      23: aload_0
      24: getfield      #39                 // Field serializerUtils:Lio/druid/common/utils/SerializerUtils;
      27: aload_1
      28: invokevirtual #75                 // Method io/druid/common/utils/SerializerUtils.readStrings:(Ljava/nio/ByteBuffer;)[Ljava/lang/String;
      31: astore_2
      32: aload_0
      33: getfield      #7                  // Field strings:[Ljava/lang/String;
      36: aload_2
      37: invokestatic  #68                 // Method org/junit/Assert.assertArrayEquals:([Ljava/lang/Object;[Ljava/lang/Object;)V
      40: return

  public void tearDown() throws java.io.IOException;
    Code:
       0: aload_0
       1: aconst_null
       2: putfield      #39                 // Field serializerUtils:Lio/druid/common/utils/SerializerUtils;
       5: aload_0
       6: getfield      #40                 // Field outStream:Ljava/io/ByteArrayOutputStream;
       9: invokevirtual #31                 // Method java/io/ByteArrayOutputStream.close:()V
      12: return
}
