Compiled from "TransactionInterceptor.java"
class org.springframework.transaction.interceptor.TransactionInterceptor$1 implements org.springframework.transaction.interceptor.TransactionAspectSupport$InvocationCallback {
  final org.aopalliance.intercept.MethodInvocation val$invocation;

  final org.springframework.transaction.interceptor.TransactionInterceptor this$0;

  org.springframework.transaction.interceptor.TransactionInterceptor$1(org.springframework.transaction.interceptor.TransactionInterceptor, org.aopalliance.intercept.MethodInvocation);
    Code:
       0: aload_0
       1: aload_1
       2: putfield      #1                  // Field this$0:Lorg/springframework/transaction/interceptor/TransactionInterceptor;
       5: aload_0
       6: aload_2
       7: putfield      #2                  // Field val$invocation:Lorg/aopalliance/intercept/MethodInvocation;
      10: aload_0
      11: invokespecial #3                  // Method java/lang/Object."<init>":()V
      14: return

  public java.lang.Object proceedWithInvocation() throws java.lang.Throwable;
    Code:
       0: aload_0
       1: getfield      #2                  // Field val$invocation:Lorg/aopalliance/intercept/MethodInvocation;
       4: invokeinterface #4,  1            // InterfaceMethod org/aopalliance/intercept/MethodInvocation.proceed:()Ljava/lang/Object;
       9: areturn
}
