Compiled from "HpccOptions.java"
public class org.hpccsystems.spark.datasource.HpccOptions {
  public org.hpccsystems.ws.client.utils.Connection connectionInfo;

  public java.lang.String clusterName;

  public java.lang.String fileName;

  public java.lang.String projectList;

  public org.hpccsystems.dfs.client.CompressionAlgorithm compression;

  public java.lang.String filterString;

  public int expirySeconds;

  public int filePartLimit;

  public org.hpccsystems.spark.datasource.HpccOptions(java.util.TreeMap<java.lang.String, java.lang.String>) throws java.lang.Exception;
    Code:
       0: aload_0
       1: invokespecial #1                  // Method java/lang/Object."<init>":()V
       4: aload_0
       5: aconst_null
       6: putfield      #2                  // Field connectionInfo:Lorg/hpccsystems/ws/client/utils/Connection;
       9: aload_0
      10: aconst_null
      11: putfield      #3                  // Field clusterName:Ljava/lang/String;
      14: aload_0
      15: aconst_null
      16: putfield      #4                  // Field fileName:Ljava/lang/String;
      19: aload_0
      20: aconst_null
      21: putfield      #5                  // Field projectList:Ljava/lang/String;
      24: aload_0
      25: getstatic     #6                  // Field org/hpccsystems/dfs/client/CompressionAlgorithm.DEFAULT:Lorg/hpccsystems/dfs/client/CompressionAlgorithm;
      28: putfield      #7                  // Field compression:Lorg/hpccsystems/dfs/client/CompressionAlgorithm;
      31: aload_0
      32: aconst_null
      33: putfield      #8                  // Field filterString:Ljava/lang/String;
      36: aload_0
      37: bipush        120
      39: putfield      #9                  // Field expirySeconds:I
      42: aload_0
      43: iconst_m1
      44: putfield      #10                 // Field filePartLimit:I
      47: aconst_null
      48: astore_2
      49: aload_1
      50: ldc           #11                 // String host
      52: invokevirtual #12                 // Method java/util/TreeMap.containsKey:(Ljava/lang/Object;)Z
      55: ifeq          68
      58: aload_1
      59: ldc           #11                 // String host
      61: invokevirtual #13                 // Method java/util/TreeMap.get:(Ljava/lang/Object;)Ljava/lang/Object;
      64: checkcast     #14                 // class java/lang/String
      67: astore_2
      68: aconst_null
      69: astore_3
      70: aload_1
      71: ldc           #15                 // String username
      73: invokevirtual #12                 // Method java/util/TreeMap.containsKey:(Ljava/lang/Object;)Z
      76: ifeq          89
      79: aload_1
      80: ldc           #15                 // String username
      82: invokevirtual #13                 // Method java/util/TreeMap.get:(Ljava/lang/Object;)Ljava/lang/Object;
      85: checkcast     #14                 // class java/lang/String
      88: astore_3
      89: aconst_null
      90: astore        4
      92: aload_1
      93: ldc           #16                 // String password
      95: invokevirtual #12                 // Method java/util/TreeMap.containsKey:(Ljava/lang/Object;)Z
      98: ifeq          112
     101: aload_1
     102: ldc           #16                 // String password
     104: invokevirtual #13                 // Method java/util/TreeMap.get:(Ljava/lang/Object;)Ljava/lang/Object;
     107: checkcast     #14                 // class java/lang/String
     110: astore        4
     112: aload_0
     113: new           #17                 // class org/hpccsystems/ws/client/utils/Connection
     116: dup
     117: aload_2
     118: invokespecial #18                 // Method org/hpccsystems/ws/client/utils/Connection."<init>":(Ljava/lang/String;)V
     121: putfield      #2                  // Field connectionInfo:Lorg/hpccsystems/ws/client/utils/Connection;
     124: aload_0
     125: getfield      #2                  // Field connectionInfo:Lorg/hpccsystems/ws/client/utils/Connection;
     128: aload_3
     129: invokevirtual #19                 // Method org/hpccsystems/ws/client/utils/Connection.setUserName:(Ljava/lang/String;)V
     132: aload_0
     133: getfield      #2                  // Field connectionInfo:Lorg/hpccsystems/ws/client/utils/Connection;
     136: aload         4
     138: invokevirtual #20                 // Method org/hpccsystems/ws/client/utils/Connection.setPassword:(Ljava/lang/String;)V
     141: aload_1
     142: ldc           #21                 // String path
     144: invokevirtual #12                 // Method java/util/TreeMap.containsKey:(Ljava/lang/Object;)Z
     147: ifeq          163
     150: aload_0
     151: aload_1
     152: ldc           #21                 // String path
     154: invokevirtual #13                 // Method java/util/TreeMap.get:(Ljava/lang/Object;)Ljava/lang/Object;
     157: checkcast     #14                 // class java/lang/String
     160: putfield      #4                  // Field fileName:Ljava/lang/String;
     163: aload_1
     164: ldc           #22                 // String cluster
     166: invokevirtual #12                 // Method java/util/TreeMap.containsKey:(Ljava/lang/Object;)Z
     169: ifeq          185
     172: aload_0
     173: aload_1
     174: ldc           #22                 // String cluster
     176: invokevirtual #13                 // Method java/util/TreeMap.get:(Ljava/lang/Object;)Ljava/lang/Object;
     179: checkcast     #14                 // class java/lang/String
     182: putfield      #3                  // Field clusterName:Ljava/lang/String;
     185: aload_1
     186: ldc           #23                 // String fileaccesstimeout
     188: invokevirtual #12                 // Method java/util/TreeMap.containsKey:(Ljava/lang/Object;)Z
     191: ifeq          214
     194: aload_1
     195: ldc           #23                 // String fileaccesstimeout
     197: invokevirtual #13                 // Method java/util/TreeMap.get:(Ljava/lang/Object;)Ljava/lang/Object;
     200: checkcast     #14                 // class java/lang/String
     203: astore        5
     205: aload_0
     206: aload         5
     208: invokestatic  #24                 // Method java/lang/Integer.parseInt:(Ljava/lang/String;)I
     211: putfield      #9                  // Field expirySeconds:I
     214: aload_1
     215: ldc           #25                 // String limitperfilepart
     217: invokevirtual #12                 // Method java/util/TreeMap.containsKey:(Ljava/lang/Object;)Z
     220: ifeq          243
     223: aload_1
     224: ldc           #25                 // String limitperfilepart
     226: invokevirtual #13                 // Method java/util/TreeMap.get:(Ljava/lang/Object;)Ljava/lang/Object;
     229: checkcast     #14                 // class java/lang/String
     232: astore        5
     234: aload_0
     235: aload         5
     237: invokestatic  #24                 // Method java/lang/Integer.parseInt:(Ljava/lang/String;)I
     240: putfield      #10                 // Field filePartLimit:I
     243: aload_1
     244: ldc           #26                 // String projectlist
     246: invokevirtual #12                 // Method java/util/TreeMap.containsKey:(Ljava/lang/Object;)Z
     249: ifeq          265
     252: aload_0
     253: aload_1
     254: ldc           #26                 // String projectlist
     256: invokevirtual #13                 // Method java/util/TreeMap.get:(Ljava/lang/Object;)Ljava/lang/Object;
     259: checkcast     #14                 // class java/lang/String
     262: putfield      #5                  // Field projectList:Ljava/lang/String;
     265: aload_0
     266: getstatic     #6                  // Field org/hpccsystems/dfs/client/CompressionAlgorithm.DEFAULT:Lorg/hpccsystems/dfs/client/CompressionAlgorithm;
     269: putfield      #7                  // Field compression:Lorg/hpccsystems/dfs/client/CompressionAlgorithm;
     272: aload_1
     273: ldc           #27                 // String compression
     275: invokevirtual #12                 // Method java/util/TreeMap.containsKey:(Ljava/lang/Object;)Z
     278: ifeq          491
     281: aload_1
     282: ldc           #27                 // String compression
     284: invokevirtual #13                 // Method java/util/TreeMap.get:(Ljava/lang/Object;)Ljava/lang/Object;
     287: checkcast     #14                 // class java/lang/String
     290: astore        5
     292: aload         5
     294: invokevirtual #28                 // Method java/lang/String.toLowerCase:()Ljava/lang/String;
     297: astore        5
     299: aload         5
     301: astore        6
     303: iconst_m1
     304: istore        7
     306: aload         6
     308: invokevirtual #29                 // Method java/lang/String.hashCode:()I
     311: lookupswitch  { // 4
                101492: 384
                107622: 368
                107689: 400
               3387192: 352
               default: 413
          }
     352: aload         6
     354: ldc           #30                 // String none
     356: invokevirtual #31                 // Method java/lang/String.equals:(Ljava/lang/Object;)Z
     359: ifeq          413
     362: iconst_0
     363: istore        7
     365: goto          413
     368: aload         6
     370: ldc           #32                 // String lz4
     372: invokevirtual #31                 // Method java/lang/String.equals:(Ljava/lang/Object;)Z
     375: ifeq          413
     378: iconst_1
     379: istore        7
     381: goto          413
     384: aload         6
     386: ldc           #33                 // String flz
     388: invokevirtual #31                 // Method java/lang/String.equals:(Ljava/lang/Object;)Z
     391: ifeq          413
     394: iconst_2
     395: istore        7
     397: goto          413
     400: aload         6
     402: ldc           #34                 // String lzw
     404: invokevirtual #31                 // Method java/lang/String.equals:(Ljava/lang/Object;)Z
     407: ifeq          413
     410: iconst_3
     411: istore        7
     413: iload         7
     415: tableswitch   { // 0 to 3
                     0: 444
                     1: 454
                     2: 464
                     3: 474
               default: 484
          }
     444: aload_0
     445: getstatic     #35                 // Field org/hpccsystems/dfs/client/CompressionAlgorithm.NONE:Lorg/hpccsystems/dfs/client/CompressionAlgorithm;
     448: putfield      #7                  // Field compression:Lorg/hpccsystems/dfs/client/CompressionAlgorithm;
     451: goto          491
     454: aload_0
     455: getstatic     #36                 // Field org/hpccsystems/dfs/client/CompressionAlgorithm.LZ4:Lorg/hpccsystems/dfs/client/CompressionAlgorithm;
     458: putfield      #7                  // Field compression:Lorg/hpccsystems/dfs/client/CompressionAlgorithm;
     461: goto          491
     464: aload_0
     465: getstatic     #37                 // Field org/hpccsystems/dfs/client/CompressionAlgorithm.FLZ:Lorg/hpccsystems/dfs/client/CompressionAlgorithm;
     468: putfield      #7                  // Field compression:Lorg/hpccsystems/dfs/client/CompressionAlgorithm;
     471: goto          491
     474: aload_0
     475: getstatic     #38                 // Field org/hpccsystems/dfs/client/CompressionAlgorithm.LZW:Lorg/hpccsystems/dfs/client/CompressionAlgorithm;
     478: putfield      #7                  // Field compression:Lorg/hpccsystems/dfs/client/CompressionAlgorithm;
     481: goto          491
     484: aload_0
     485: getstatic     #6                  // Field org/hpccsystems/dfs/client/CompressionAlgorithm.DEFAULT:Lorg/hpccsystems/dfs/client/CompressionAlgorithm;
     488: putfield      #7                  // Field compression:Lorg/hpccsystems/dfs/client/CompressionAlgorithm;
     491: aload_1
     492: ldc           #39                 // String filter
     494: invokevirtual #12                 // Method java/util/TreeMap.containsKey:(Ljava/lang/Object;)Z
     497: ifeq          513
     500: aload_0
     501: aload_1
     502: ldc           #39                 // String filter
     504: invokevirtual #13                 // Method java/util/TreeMap.get:(Ljava/lang/Object;)Ljava/lang/Object;
     507: checkcast     #14                 // class java/lang/String
     510: putfield      #8                  // Field filterString:Ljava/lang/String;
     513: return

  public java.lang.String toString();
    Code:
       0: new           #40                 // class java/lang/StringBuilder
       3: dup
       4: invokespecial #41                 // Method java/lang/StringBuilder."<init>":()V
       7: ldc           #42                 // String [Connection: \'
       9: invokevirtual #43                 // Method java/lang/StringBuilder.append:(Ljava/lang/String;)Ljava/lang/StringBuilder;
      12: aload_0
      13: getfield      #2                  // Field connectionInfo:Lorg/hpccsystems/ws/client/utils/Connection;
      16: invokevirtual #44                 // Method java/lang/StringBuilder.append:(Ljava/lang/Object;)Ljava/lang/StringBuilder;
      19: ldc           #45                 // String \', clusterName: \'
      21: invokevirtual #43                 // Method java/lang/StringBuilder.append:(Ljava/lang/String;)Ljava/lang/StringBuilder;
      24: aload_0
      25: getfield      #3                  // Field clusterName:Ljava/lang/String;
      28: invokevirtual #43                 // Method java/lang/StringBuilder.append:(Ljava/lang/String;)Ljava/lang/StringBuilder;
      31: invokevirtual #46                 // Method java/lang/StringBuilder.toString:()Ljava/lang/String;
      34: astore_1
      35: new           #40                 // class java/lang/StringBuilder
      38: dup
      39: invokespecial #41                 // Method java/lang/StringBuilder."<init>":()V
      42: aload_1
      43: invokevirtual #43                 // Method java/lang/StringBuilder.append:(Ljava/lang/String;)Ljava/lang/StringBuilder;
      46: ldc           #47                 // String \', fileName: \'
      48: invokevirtual #43                 // Method java/lang/StringBuilder.append:(Ljava/lang/String;)Ljava/lang/StringBuilder;
      51: aload_0
      52: getfield      #4                  // Field fileName:Ljava/lang/String;
      55: invokevirtual #43                 // Method java/lang/StringBuilder.append:(Ljava/lang/String;)Ljava/lang/StringBuilder;
      58: ldc           #48                 // String \', projectList: \'
      60: invokevirtual #43                 // Method java/lang/StringBuilder.append:(Ljava/lang/String;)Ljava/lang/StringBuilder;
      63: aload_0
      64: getfield      #5                  // Field projectList:Ljava/lang/String;
      67: invokevirtual #43                 // Method java/lang/StringBuilder.append:(Ljava/lang/String;)Ljava/lang/StringBuilder;
      70: ldc           #49                 // String \', compression: \'
      72: invokevirtual #43                 // Method java/lang/StringBuilder.append:(Ljava/lang/String;)Ljava/lang/StringBuilder;
      75: aload_0
      76: getfield      #7                  // Field compression:Lorg/hpccsystems/dfs/client/CompressionAlgorithm;
      79: invokevirtual #44                 // Method java/lang/StringBuilder.append:(Ljava/lang/Object;)Ljava/lang/StringBuilder;
      82: ldc           #50                 // String \',
      84: invokevirtual #43                 // Method java/lang/StringBuilder.append:(Ljava/lang/String;)Ljava/lang/StringBuilder;
      87: invokevirtual #46                 // Method java/lang/StringBuilder.toString:()Ljava/lang/String;
      90: astore_1
      91: new           #40                 // class java/lang/StringBuilder
      94: dup
      95: invokespecial #41                 // Method java/lang/StringBuilder."<init>":()V
      98: aload_1
      99: invokevirtual #43                 // Method java/lang/StringBuilder.append:(Ljava/lang/String;)Ljava/lang/StringBuilder;
     102: ldc           #51                 // String filterString: \'
     104: invokevirtual #43                 // Method java/lang/StringBuilder.append:(Ljava/lang/String;)Ljava/lang/StringBuilder;
     107: aload_0
     108: getfield      #8                  // Field filterString:Ljava/lang/String;
     111: invokevirtual #43                 // Method java/lang/StringBuilder.append:(Ljava/lang/String;)Ljava/lang/StringBuilder;
     114: ldc           #52                 // String \', expirySeconds: \'
     116: invokevirtual #43                 // Method java/lang/StringBuilder.append:(Ljava/lang/String;)Ljava/lang/StringBuilder;
     119: aload_0
     120: getfield      #9                  // Field expirySeconds:I
     123: invokevirtual #53                 // Method java/lang/StringBuilder.append:(I)Ljava/lang/StringBuilder;
     126: ldc           #54                 // String \', filePartLimit: \'
     128: invokevirtual #43                 // Method java/lang/StringBuilder.append:(Ljava/lang/String;)Ljava/lang/StringBuilder;
     131: aload_0
     132: getfield      #10                 // Field filePartLimit:I
     135: invokevirtual #53                 // Method java/lang/StringBuilder.append:(I)Ljava/lang/StringBuilder;
     138: ldc           #55                 // String \']
     140: invokevirtual #43                 // Method java/lang/StringBuilder.append:(Ljava/lang/String;)Ljava/lang/StringBuilder;
     143: invokevirtual #46                 // Method java/lang/StringBuilder.toString:()Ljava/lang/String;
     146: astore_1
     147: aload_1
     148: areturn
}
