Compiled from "ClassLoaderUtil.java"
public final class net.sf.ehcache.util.ClassLoaderUtil {
  private net.sf.ehcache.util.ClassLoaderUtil();
    Code:
       0: aload_0
       1: invokespecial #1                  // Method java/lang/Object."<init>":()V
       4: return

  public static java.lang.ClassLoader getStandardClassLoader();
    Code:
       0: invokestatic  #2                  // Method java/lang/Thread.currentThread:()Ljava/lang/Thread;
       3: invokevirtual #3                  // Method java/lang/Thread.getContextClassLoader:()Ljava/lang/ClassLoader;
       6: areturn

  public static java.lang.ClassLoader getFallbackClassLoader();
    Code:
       0: ldc_w         #4                  // class net/sf/ehcache/util/ClassLoaderUtil
       3: invokevirtual #5                  // Method java/lang/Class.getClassLoader:()Ljava/lang/ClassLoader;
       6: areturn

  public static java.lang.Object createNewInstance(java.lang.String) throws net.sf.ehcache.CacheException;
    Code:
       0: aload_0
       1: iconst_0
       2: anewarray     #6                  // class java/lang/Class
       5: iconst_0
       6: anewarray     #7                  // class java/lang/Object
       9: invokestatic  #8                  // Method createNewInstance:(Ljava/lang/String;[Ljava/lang/Class;[Ljava/lang/Object;)Ljava/lang/Object;
      12: areturn

  public static java.lang.Object createNewInstance(java.lang.String, java.lang.Class[], java.lang.Object[]) throws net.sf.ehcache.CacheException;
    Code:
       0: aload_0
       1: invokestatic  #9                  // Method loadClass:(Ljava/lang/String;)Ljava/lang/Class;
       4: astore_3
       5: goto          52
       8: astore        5
      10: new           #11                 // class net/sf/ehcache/CacheException
      13: dup
      14: new           #12                 // class java/lang/StringBuilder
      17: dup
      18: invokespecial #13                 // Method java/lang/StringBuilder."<init>":()V
      21: ldc           #14                 // String Unable to load class
      23: invokevirtual #15                 // Method java/lang/StringBuilder.append:(Ljava/lang/String;)Ljava/lang/StringBuilder;
      26: aload_0
      27: invokevirtual #15                 // Method java/lang/StringBuilder.append:(Ljava/lang/String;)Ljava/lang/StringBuilder;
      30: ldc           #16                 // String . Initial cause was
      32: invokevirtual #15                 // Method java/lang/StringBuilder.append:(Ljava/lang/String;)Ljava/lang/StringBuilder;
      35: aload         5
      37: invokevirtual #17                 // Method java/lang/ClassNotFoundException.getMessage:()Ljava/lang/String;
      40: invokevirtual #15                 // Method java/lang/StringBuilder.append:(Ljava/lang/String;)Ljava/lang/StringBuilder;
      43: invokevirtual #18                 // Method java/lang/StringBuilder.toString:()Ljava/lang/String;
      46: aload         5
      48: invokespecial #19                 // Method net/sf/ehcache/CacheException."<init>":(Ljava/lang/String;Ljava/lang/Throwable;)V
      51: athrow
      52: aload_3
      53: aload_1
      54: invokevirtual #20                 // Method java/lang/Class.getConstructor:([Ljava/lang/Class;)Ljava/lang/reflect/Constructor;
      57: astore        5
      59: aload         5
      61: aload_2
      62: invokevirtual #21                 // Method java/lang/reflect/Constructor.newInstance:([Ljava/lang/Object;)Ljava/lang/Object;
      65: astore        4
      67: goto          340
      70: astore        5
      72: new           #11                 // class net/sf/ehcache/CacheException
      75: dup
      76: new           #12                 // class java/lang/StringBuilder
      79: dup
      80: invokespecial #13                 // Method java/lang/StringBuilder."<init>":()V
      83: ldc           #14                 // String Unable to load class
      85: invokevirtual #15                 // Method java/lang/StringBuilder.append:(Ljava/lang/String;)Ljava/lang/StringBuilder;
      88: aload_0
      89: invokevirtual #15                 // Method java/lang/StringBuilder.append:(Ljava/lang/String;)Ljava/lang/StringBuilder;
      92: ldc           #16                 // String . Initial cause was
      94: invokevirtual #15                 // Method java/lang/StringBuilder.append:(Ljava/lang/String;)Ljava/lang/StringBuilder;
      97: aload         5
      99: invokevirtual #23                 // Method java/lang/IllegalAccessException.getMessage:()Ljava/lang/String;
     102: invokevirtual #15                 // Method java/lang/StringBuilder.append:(Ljava/lang/String;)Ljava/lang/StringBuilder;
     105: invokevirtual #18                 // Method java/lang/StringBuilder.toString:()Ljava/lang/String;
     108: aload         5
     110: invokespecial #19                 // Method net/sf/ehcache/CacheException."<init>":(Ljava/lang/String;Ljava/lang/Throwable;)V
     113: athrow
     114: astore        5
     116: new           #11                 // class net/sf/ehcache/CacheException
     119: dup
     120: new           #12                 // class java/lang/StringBuilder
     123: dup
     124: invokespecial #13                 // Method java/lang/StringBuilder."<init>":()V
     127: ldc           #14                 // String Unable to load class
     129: invokevirtual #15                 // Method java/lang/StringBuilder.append:(Ljava/lang/String;)Ljava/lang/StringBuilder;
     132: aload_0
     133: invokevirtual #15                 // Method java/lang/StringBuilder.append:(Ljava/lang/String;)Ljava/lang/StringBuilder;
     136: ldc           #16                 // String . Initial cause was
     138: invokevirtual #15                 // Method java/lang/StringBuilder.append:(Ljava/lang/String;)Ljava/lang/StringBuilder;
     141: aload         5
     143: invokevirtual #25                 // Method java/lang/InstantiationException.getMessage:()Ljava/lang/String;
     146: invokevirtual #15                 // Method java/lang/StringBuilder.append:(Ljava/lang/String;)Ljava/lang/StringBuilder;
     149: invokevirtual #18                 // Method java/lang/StringBuilder.toString:()Ljava/lang/String;
     152: aload         5
     154: invokespecial #19                 // Method net/sf/ehcache/CacheException."<init>":(Ljava/lang/String;Ljava/lang/Throwable;)V
     157: athrow
     158: astore        5
     160: new           #11                 // class net/sf/ehcache/CacheException
     163: dup
     164: new           #12                 // class java/lang/StringBuilder
     167: dup
     168: invokespecial #13                 // Method java/lang/StringBuilder."<init>":()V
     171: ldc           #14                 // String Unable to load class
     173: invokevirtual #15                 // Method java/lang/StringBuilder.append:(Ljava/lang/String;)Ljava/lang/StringBuilder;
     176: aload_0
     177: invokevirtual #15                 // Method java/lang/StringBuilder.append:(Ljava/lang/String;)Ljava/lang/StringBuilder;
     180: ldc           #16                 // String . Initial cause was
     182: invokevirtual #15                 // Method java/lang/StringBuilder.append:(Ljava/lang/String;)Ljava/lang/StringBuilder;
     185: aload         5
     187: invokevirtual #27                 // Method java/lang/NoSuchMethodException.getMessage:()Ljava/lang/String;
     190: invokevirtual #15                 // Method java/lang/StringBuilder.append:(Ljava/lang/String;)Ljava/lang/StringBuilder;
     193: invokevirtual #18                 // Method java/lang/StringBuilder.toString:()Ljava/lang/String;
     196: aload         5
     198: invokespecial #19                 // Method net/sf/ehcache/CacheException."<init>":(Ljava/lang/String;Ljava/lang/Throwable;)V
     201: athrow
     202: astore        5
     204: new           #11                 // class net/sf/ehcache/CacheException
     207: dup
     208: new           #12                 // class java/lang/StringBuilder
     211: dup
     212: invokespecial #13                 // Method java/lang/StringBuilder."<init>":()V
     215: ldc           #14                 // String Unable to load class
     217: invokevirtual #15                 // Method java/lang/StringBuilder.append:(Ljava/lang/String;)Ljava/lang/StringBuilder;
     220: aload_0
     221: invokevirtual #15                 // Method java/lang/StringBuilder.append:(Ljava/lang/String;)Ljava/lang/StringBuilder;
     224: ldc           #16                 // String . Initial cause was
     226: invokevirtual #15                 // Method java/lang/StringBuilder.append:(Ljava/lang/String;)Ljava/lang/StringBuilder;
     229: aload         5
     231: invokevirtual #29                 // Method java/lang/SecurityException.getMessage:()Ljava/lang/String;
     234: invokevirtual #15                 // Method java/lang/StringBuilder.append:(Ljava/lang/String;)Ljava/lang/StringBuilder;
     237: invokevirtual #18                 // Method java/lang/StringBuilder.toString:()Ljava/lang/String;
     240: aload         5
     242: invokespecial #19                 // Method net/sf/ehcache/CacheException."<init>":(Ljava/lang/String;Ljava/lang/Throwable;)V
     245: athrow
     246: astore        5
     248: new           #11                 // class net/sf/ehcache/CacheException
     251: dup
     252: new           #12                 // class java/lang/StringBuilder
     255: dup
     256: invokespecial #13                 // Method java/lang/StringBuilder."<init>":()V
     259: ldc           #14                 // String Unable to load class
     261: invokevirtual #15                 // Method java/lang/StringBuilder.append:(Ljava/lang/String;)Ljava/lang/StringBuilder;
     264: aload_0
     265: invokevirtual #15                 // Method java/lang/StringBuilder.append:(Ljava/lang/String;)Ljava/lang/StringBuilder;
     268: ldc           #16                 // String . Initial cause was
     270: invokevirtual #15                 // Method java/lang/StringBuilder.append:(Ljava/lang/String;)Ljava/lang/StringBuilder;
     273: aload         5
     275: invokevirtual #31                 // Method java/lang/IllegalArgumentException.getMessage:()Ljava/lang/String;
     278: invokevirtual #15                 // Method java/lang/StringBuilder.append:(Ljava/lang/String;)Ljava/lang/StringBuilder;
     281: invokevirtual #18                 // Method java/lang/StringBuilder.toString:()Ljava/lang/String;
     284: aload         5
     286: invokespecial #19                 // Method net/sf/ehcache/CacheException."<init>":(Ljava/lang/String;Ljava/lang/Throwable;)V
     289: athrow
     290: astore        5
     292: new           #11                 // class net/sf/ehcache/CacheException
     295: dup
     296: new           #12                 // class java/lang/StringBuilder
     299: dup
     300: invokespecial #13                 // Method java/lang/StringBuilder."<init>":()V
     303: ldc           #14                 // String Unable to load class
     305: invokevirtual #15                 // Method java/lang/StringBuilder.append:(Ljava/lang/String;)Ljava/lang/StringBuilder;
     308: aload_0
     309: invokevirtual #15                 // Method java/lang/StringBuilder.append:(Ljava/lang/String;)Ljava/lang/StringBuilder;
     312: ldc           #16                 // String . Initial cause was
     314: invokevirtual #15                 // Method java/lang/StringBuilder.append:(Ljava/lang/String;)Ljava/lang/StringBuilder;
     317: aload         5
     319: invokevirtual #33                 // Method java/lang/reflect/InvocationTargetException.getCause:()Ljava/lang/Throwable;
     322: invokevirtual #34                 // Method java/lang/Throwable.getMessage:()Ljava/lang/String;
     325: invokevirtual #15                 // Method java/lang/StringBuilder.append:(Ljava/lang/String;)Ljava/lang/StringBuilder;
     328: invokevirtual #18                 // Method java/lang/StringBuilder.toString:()Ljava/lang/String;
     331: aload         5
     333: invokevirtual #33                 // Method java/lang/reflect/InvocationTargetException.getCause:()Ljava/lang/Throwable;
     336: invokespecial #19                 // Method net/sf/ehcache/CacheException."<init>":(Ljava/lang/String;Ljava/lang/Throwable;)V
     339: athrow
     340: aload         4
     342: areturn
    Exception table:
       from    to  target type
           0     5     8   Class java/lang/ClassNotFoundException
          52    67    70   Class java/lang/IllegalAccessException
          52    67   114   Class java/lang/InstantiationException
          52    67   158   Class java/lang/NoSuchMethodException
          52    67   202   Class java/lang/SecurityException
          52    67   246   Class java/lang/IllegalArgumentException
          52    67   290   Class java/lang/reflect/InvocationTargetException

  public static java.lang.Class loadClass(java.lang.String) throws java.lang.ClassNotFoundException;
    Code:
       0: aload_0
       1: iconst_1
       2: invokestatic  #35                 // Method getStandardClassLoader:()Ljava/lang/ClassLoader;
       5: invokestatic  #36                 // Method java/lang/Class.forName:(Ljava/lang/String;ZLjava/lang/ClassLoader;)Ljava/lang/Class;
       8: astore_1
       9: goto          22
      12: astore_2
      13: aload_0
      14: iconst_1
      15: invokestatic  #37                 // Method getFallbackClassLoader:()Ljava/lang/ClassLoader;
      18: invokestatic  #36                 // Method java/lang/Class.forName:(Ljava/lang/String;ZLjava/lang/ClassLoader;)Ljava/lang/Class;
      21: astore_1
      22: aload_1
      23: areturn
    Exception table:
       from    to  target type
           0     9    12   Class java/lang/ClassNotFoundException
}
