Compiled from "TimelineEntity.java"
public class org.apache.hadoop.yarn.api.records.timelineservice.TimelineEntity$Identifier {
  private java.lang.String type;

  private java.lang.String id;

  public org.apache.hadoop.yarn.api.records.timelineservice.TimelineEntity$Identifier(java.lang.String, java.lang.String);
    Code:
       0: aload_0
       1: invokespecial #3                  // Method java/lang/Object."<init>":()V
       4: aload_0
       5: aload_1
       6: putfield      #2                  // Field type:Ljava/lang/String;
       9: aload_0
      10: aload_2
      11: putfield      #1                  // Field id:Ljava/lang/String;
      14: return

  public org.apache.hadoop.yarn.api.records.timelineservice.TimelineEntity$Identifier();
    Code:
       0: aload_0
       1: invokespecial #3                  // Method java/lang/Object."<init>":()V
       4: return

  public java.lang.String getType();
    Code:
       0: aload_0
       1: getfield      #2                  // Field type:Ljava/lang/String;
       4: areturn

  public void setType(java.lang.String);
    Code:
       0: aload_0
       1: aload_1
       2: putfield      #2                  // Field type:Ljava/lang/String;
       5: return

  public java.lang.String getId();
    Code:
       0: aload_0
       1: getfield      #1                  // Field id:Ljava/lang/String;
       4: areturn

  public void setId(java.lang.String);
    Code:
       0: aload_0
       1: aload_1
       2: putfield      #1                  // Field id:Ljava/lang/String;
       5: return

  public java.lang.String toString();
    Code:
       0: new           #4                  // class java/lang/StringBuilder
       3: dup
       4: invokespecial #5                  // Method java/lang/StringBuilder."<init>":()V
       7: ldc           #6                  // String TimelineEntity[type=\'
       9: invokevirtual #7                  // Method java/lang/StringBuilder.append:(Ljava/lang/String;)Ljava/lang/StringBuilder;
      12: aload_0
      13: getfield      #2                  // Field type:Ljava/lang/String;
      16: invokevirtual #7                  // Method java/lang/StringBuilder.append:(Ljava/lang/String;)Ljava/lang/StringBuilder;
      19: bipush        39
      21: invokevirtual #8                  // Method java/lang/StringBuilder.append:(C)Ljava/lang/StringBuilder;
      24: ldc           #9                  // String , id=\'
      26: invokevirtual #7                  // Method java/lang/StringBuilder.append:(Ljava/lang/String;)Ljava/lang/StringBuilder;
      29: aload_0
      30: getfield      #1                  // Field id:Ljava/lang/String;
      33: invokevirtual #7                  // Method java/lang/StringBuilder.append:(Ljava/lang/String;)Ljava/lang/StringBuilder;
      36: bipush        39
      38: invokevirtual #8                  // Method java/lang/StringBuilder.append:(C)Ljava/lang/StringBuilder;
      41: ldc           #10                 // String ]
      43: invokevirtual #7                  // Method java/lang/StringBuilder.append:(Ljava/lang/String;)Ljava/lang/StringBuilder;
      46: invokevirtual #11                 // Method java/lang/StringBuilder.toString:()Ljava/lang/String;
      49: areturn

  public int hashCode();
    Code:
       0: bipush        31
       2: istore_1
       3: iconst_1
       4: istore_2
       5: bipush        31
       7: iload_2
       8: imul
       9: aload_0
      10: getfield      #1                  // Field id:Ljava/lang/String;
      13: ifnonnull     20
      16: iconst_0
      17: goto          27
      20: aload_0
      21: getfield      #1                  // Field id:Ljava/lang/String;
      24: invokevirtual #12                 // Method java/lang/String.hashCode:()I
      27: iadd
      28: istore_2
      29: bipush        31
      31: iload_2
      32: imul
      33: aload_0
      34: getfield      #2                  // Field type:Ljava/lang/String;
      37: ifnonnull     44
      40: iconst_0
      41: goto          51
      44: aload_0
      45: getfield      #2                  // Field type:Ljava/lang/String;
      48: invokevirtual #12                 // Method java/lang/String.hashCode:()I
      51: iadd
      52: istore_2
      53: iload_2
      54: ireturn

  public boolean equals(java.lang.Object);
    Code:
       0: aload_0
       1: aload_1
       2: if_acmpne     7
       5: iconst_1
       6: ireturn
       7: aload_1
       8: instanceof    #13                 // class org/apache/hadoop/yarn/api/records/timelineservice/TimelineEntity$Identifier
      11: ifne          16
      14: iconst_0
      15: ireturn
      16: aload_1
      17: checkcast     #13                 // class org/apache/hadoop/yarn/api/records/timelineservice/TimelineEntity$Identifier
      20: astore_2
      21: aload_0
      22: getfield      #1                  // Field id:Ljava/lang/String;
      25: ifnonnull     37
      28: aload_2
      29: invokevirtual #14                 // Method getId:()Ljava/lang/String;
      32: ifnull        53
      35: iconst_0
      36: ireturn
      37: aload_0
      38: getfield      #1                  // Field id:Ljava/lang/String;
      41: aload_2
      42: invokevirtual #14                 // Method getId:()Ljava/lang/String;
      45: invokevirtual #15                 // Method java/lang/String.equals:(Ljava/lang/Object;)Z
      48: ifne          53
      51: iconst_0
      52: ireturn
      53: aload_0
      54: getfield      #2                  // Field type:Ljava/lang/String;
      57: ifnonnull     69
      60: aload_2
      61: invokevirtual #16                 // Method getType:()Ljava/lang/String;
      64: ifnull        85
      67: iconst_0
      68: ireturn
      69: aload_0
      70: getfield      #2                  // Field type:Ljava/lang/String;
      73: aload_2
      74: invokevirtual #16                 // Method getType:()Ljava/lang/String;
      77: invokevirtual #15                 // Method java/lang/String.equals:(Ljava/lang/Object;)Z
      80: ifne          85
      83: iconst_0
      84: ireturn
      85: iconst_1
      86: ireturn

  static java.lang.String access$002(org.apache.hadoop.yarn.api.records.timelineservice.TimelineEntity$Identifier, java.lang.String);
    Code:
       0: aload_0
       1: aload_1
       2: dup_x1
       3: putfield      #2                  // Field type:Ljava/lang/String;
       6: areturn

  static java.lang.String access$000(org.apache.hadoop.yarn.api.records.timelineservice.TimelineEntity$Identifier);
    Code:
       0: aload_0
       1: getfield      #2                  // Field type:Ljava/lang/String;
       4: areturn

  static java.lang.String access$100(org.apache.hadoop.yarn.api.records.timelineservice.TimelineEntity$Identifier);
    Code:
       0: aload_0
       1: getfield      #1                  // Field id:Ljava/lang/String;
       4: areturn

  static java.lang.String access$102(org.apache.hadoop.yarn.api.records.timelineservice.TimelineEntity$Identifier, java.lang.String);
    Code:
       0: aload_0
       1: aload_1
       2: dup_x1
       3: putfield      #1                  // Field id:Ljava/lang/String;
       6: areturn
}
