Compiled from "TimelineMetricCalculator.java"
public final class org.apache.hadoop.yarn.api.records.timelineservice.TimelineMetricCalculator {
  private org.apache.hadoop.yarn.api.records.timelineservice.TimelineMetricCalculator();
    Code:
       0: aload_0
       1: invokespecial #1                  // Method java/lang/Object."<init>":()V
       4: return

  public static int compare(java.lang.Number, java.lang.Number);
    Code:
       0: aload_0
       1: ifnull        8
       4: aload_1
       5: ifnonnull     18
       8: new           #2                  // class org/apache/hadoop/yarn/exceptions/YarnRuntimeException
      11: dup
      12: ldc           #3                  // String Number to be compared shouldn\'t be null.
      14: invokespecial #4                  // Method org/apache/hadoop/yarn/exceptions/YarnRuntimeException."<init>":(Ljava/lang/String;)V
      17: athrow
      18: aload_0
      19: instanceof    #5                  // class java/lang/Integer
      22: ifne          32
      25: aload_0
      26: instanceof    #6                  // class java/lang/Long
      29: ifeq          64
      32: aload_0
      33: invokevirtual #7                  // Method java/lang/Number.longValue:()J
      36: aload_1
      37: invokevirtual #7                  // Method java/lang/Number.longValue:()J
      40: lcmp
      41: ifne          46
      44: iconst_0
      45: ireturn
      46: aload_0
      47: invokevirtual #7                  // Method java/lang/Number.longValue:()J
      50: aload_1
      51: invokevirtual #7                  // Method java/lang/Number.longValue:()J
      54: lcmp
      55: ifge          62
      58: iconst_m1
      59: goto          63
      62: iconst_1
      63: ireturn
      64: aload_0
      65: instanceof    #8                  // class java/lang/Float
      68: ifne          78
      71: aload_0
      72: instanceof    #9                  // class java/lang/Double
      75: ifeq          110
      78: aload_0
      79: invokevirtual #10                 // Method java/lang/Number.doubleValue:()D
      82: aload_1
      83: invokevirtual #10                 // Method java/lang/Number.doubleValue:()D
      86: dcmpl
      87: ifne          92
      90: iconst_0
      91: ireturn
      92: aload_0
      93: invokevirtual #10                 // Method java/lang/Number.doubleValue:()D
      96: aload_1
      97: invokevirtual #10                 // Method java/lang/Number.doubleValue:()D
     100: dcmpg
     101: ifge          108
     104: iconst_m1
     105: goto          109
     108: iconst_1
     109: ireturn
     110: new           #2                  // class org/apache/hadoop/yarn/exceptions/YarnRuntimeException
     113: dup
     114: new           #11                 // class java/lang/StringBuilder
     117: dup
     118: invokespecial #12                 // Method java/lang/StringBuilder."<init>":()V
     121: ldc           #13                 // String Unsupported types for number comparison:
     123: invokevirtual #14                 // Method java/lang/StringBuilder.append:(Ljava/lang/String;)Ljava/lang/StringBuilder;
     126: aload_0
     127: invokevirtual #15                 // Method java/lang/Object.getClass:()Ljava/lang/Class;
     130: invokevirtual #16                 // Method java/lang/Class.getName:()Ljava/lang/String;
     133: invokevirtual #14                 // Method java/lang/StringBuilder.append:(Ljava/lang/String;)Ljava/lang/StringBuilder;
     136: ldc           #17                 // String ,
     138: invokevirtual #14                 // Method java/lang/StringBuilder.append:(Ljava/lang/String;)Ljava/lang/StringBuilder;
     141: aload_1
     142: invokevirtual #15                 // Method java/lang/Object.getClass:()Ljava/lang/Class;
     145: invokevirtual #16                 // Method java/lang/Class.getName:()Ljava/lang/String;
     148: invokevirtual #14                 // Method java/lang/StringBuilder.append:(Ljava/lang/String;)Ljava/lang/StringBuilder;
     151: invokevirtual #18                 // Method java/lang/StringBuilder.toString:()Ljava/lang/String;
     154: invokespecial #4                  // Method org/apache/hadoop/yarn/exceptions/YarnRuntimeException."<init>":(Ljava/lang/String;)V
     157: athrow

  public static java.lang.Number sub(java.lang.Number, java.lang.Number);
    Code:
       0: aload_0
       1: ifnonnull     14
       4: new           #2                  // class org/apache/hadoop/yarn/exceptions/YarnRuntimeException
       7: dup
       8: ldc           #19                 // String Number to be subtracted shouldn\'t be null.
      10: invokespecial #4                  // Method org/apache/hadoop/yarn/exceptions/YarnRuntimeException."<init>":(Ljava/lang/String;)V
      13: athrow
      14: aload_1
      15: ifnonnull     20
      18: aload_0
      19: areturn
      20: aload_0
      21: instanceof    #5                  // class java/lang/Integer
      24: ifne          34
      27: aload_0
      28: instanceof    #6                  // class java/lang/Long
      31: ifeq          47
      34: aload_0
      35: invokevirtual #7                  // Method java/lang/Number.longValue:()J
      38: aload_1
      39: invokevirtual #7                  // Method java/lang/Number.longValue:()J
      42: lsub
      43: invokestatic  #20                 // Method java/lang/Long.valueOf:(J)Ljava/lang/Long;
      46: areturn
      47: aload_0
      48: instanceof    #8                  // class java/lang/Float
      51: ifne          61
      54: aload_0
      55: instanceof    #9                  // class java/lang/Double
      58: ifeq          74
      61: aload_0
      62: invokevirtual #10                 // Method java/lang/Number.doubleValue:()D
      65: aload_1
      66: invokevirtual #10                 // Method java/lang/Number.doubleValue:()D
      69: dsub
      70: invokestatic  #21                 // Method java/lang/Double.valueOf:(D)Ljava/lang/Double;
      73: areturn
      74: aconst_null
      75: areturn

  public static java.lang.Number sum(java.lang.Number, java.lang.Number);
    Code:
       0: aload_0
       1: ifnonnull     6
       4: aload_1
       5: areturn
       6: aload_1
       7: ifnonnull     12
      10: aload_0
      11: areturn
      12: aload_0
      13: instanceof    #5                  // class java/lang/Integer
      16: ifne          26
      19: aload_0
      20: instanceof    #6                  // class java/lang/Long
      23: ifeq          39
      26: aload_0
      27: invokevirtual #7                  // Method java/lang/Number.longValue:()J
      30: aload_1
      31: invokevirtual #7                  // Method java/lang/Number.longValue:()J
      34: ladd
      35: invokestatic  #20                 // Method java/lang/Long.valueOf:(J)Ljava/lang/Long;
      38: areturn
      39: aload_0
      40: instanceof    #8                  // class java/lang/Float
      43: ifne          53
      46: aload_0
      47: instanceof    #9                  // class java/lang/Double
      50: ifeq          66
      53: aload_0
      54: invokevirtual #10                 // Method java/lang/Number.doubleValue:()D
      57: aload_1
      58: invokevirtual #10                 // Method java/lang/Number.doubleValue:()D
      61: dadd
      62: invokestatic  #21                 // Method java/lang/Double.valueOf:(D)Ljava/lang/Double;
      65: areturn
      66: aconst_null
      67: areturn
}
