Compiled from "JsonCreatorCanonical.java"
class org.hl7.fhir.dstu3.formats.JsonCreatorCanonical$JsonCanStringValue extends org.hl7.fhir.dstu3.formats.JsonCreatorCanonical$JsonCanValue {
  private java.lang.String value;

  final org.hl7.fhir.dstu3.formats.JsonCreatorCanonical this$0;

  private org.hl7.fhir.dstu3.formats.JsonCreatorCanonical$JsonCanStringValue(org.hl7.fhir.dstu3.formats.JsonCreatorCanonical, java.lang.String, java.lang.String);
    Code:
       0: aload_0
       1: aload_1
       2: putfield      #3                  // Field this$0:Lorg/hl7/fhir/dstu3/formats/JsonCreatorCanonical;
       5: aload_0
       6: aload_1
       7: aload_2
       8: aconst_null
       9: invokespecial #4                  // Method org/hl7/fhir/dstu3/formats/JsonCreatorCanonical$JsonCanValue."<init>":(Lorg/hl7/fhir/dstu3/formats/JsonCreatorCanonical;Ljava/lang/String;Lorg/hl7/fhir/dstu3/formats/JsonCreatorCanonical$1;)V
      12: aload_0
      13: aload_3
      14: putfield      #1                  // Field value:Ljava/lang/String;
      17: return

  org.hl7.fhir.dstu3.formats.JsonCreatorCanonical$JsonCanStringValue(org.hl7.fhir.dstu3.formats.JsonCreatorCanonical, java.lang.String, java.lang.String, org.hl7.fhir.dstu3.formats.JsonCreatorCanonical$1);
    Code:
       0: aload_0
       1: aload_1
       2: aload_2
       3: aload_3
       4: invokespecial #2                  // Method "<init>":(Lorg/hl7/fhir/dstu3/formats/JsonCreatorCanonical;Ljava/lang/String;Ljava/lang/String;)V
       7: return

  static java.lang.String access$900(org.hl7.fhir.dstu3.formats.JsonCreatorCanonical$JsonCanStringValue);
    Code:
       0: aload_0
       1: getfield      #1                  // Field value:Ljava/lang/String;
       4: areturn
}
