Compiled from "IsSame.java"
public class org.hamcrest.core.IsSame<T> extends org.hamcrest.BaseMatcher<T> {
  private final T object;

  public org.hamcrest.core.IsSame(T);
    Code:
       0: aload_0
       1: invokespecial #1                  // Method org/hamcrest/BaseMatcher."<init>":()V
       4: aload_0
       5: aload_1
       6: putfield      #2                  // Field object:Ljava/lang/Object;
       9: return

  public boolean matches(java.lang.Object);
    Code:
       0: aload_1
       1: aload_0
       2: getfield      #2                  // Field object:Ljava/lang/Object;
       5: if_acmpne     12
       8: iconst_1
       9: goto          13
      12: iconst_0
      13: ireturn

  public void describeTo(org.hamcrest.Description);
    Code:
       0: aload_1
       1: ldc           #3                  // String sameInstance(
       3: invokeinterface #4,  2            // InterfaceMethod org/hamcrest/Description.appendText:(Ljava/lang/String;)Lorg/hamcrest/Description;
       8: aload_0
       9: getfield      #2                  // Field object:Ljava/lang/Object;
      12: invokeinterface #5,  2            // InterfaceMethod org/hamcrest/Description.appendValue:(Ljava/lang/Object;)Lorg/hamcrest/Description;
      17: ldc           #6                  // String )
      19: invokeinterface #4,  2            // InterfaceMethod org/hamcrest/Description.appendText:(Ljava/lang/String;)Lorg/hamcrest/Description;
      24: pop
      25: return

  public static <T> org.hamcrest.Matcher<T> sameInstance(T);
    Code:
       0: new           #7                  // class org/hamcrest/core/IsSame
       3: dup
       4: aload_0
       5: invokespecial #8                  // Method "<init>":(Ljava/lang/Object;)V
       8: areturn

  public static <T> org.hamcrest.Matcher<T> theInstance(T);
    Code:
       0: new           #7                  // class org/hamcrest/core/IsSame
       3: dup
       4: aload_0
       5: invokespecial #8                  // Method "<init>":(Ljava/lang/Object;)V
       8: areturn
}
