Compiled from "CloseableByteArrayOutputStream.java"
public class net.openhft.compiler.CloseableByteArrayOutputStream extends java.io.ByteArrayOutputStream {
  private final java.util.concurrent.CompletableFuture<?> closeFuture;

  public net.openhft.compiler.CloseableByteArrayOutputStream();
    Code:
       0: aload_0
       1: invokespecial #1                  // Method java/io/ByteArrayOutputStream."<init>":()V
       4: aload_0
       5: new           #2                  // class java/util/concurrent/CompletableFuture
       8: dup
       9: invokespecial #3                  // Method java/util/concurrent/CompletableFuture."<init>":()V
      12: putfield      #4                  // Field closeFuture:Ljava/util/concurrent/CompletableFuture;
      15: return

  public void close();
    Code:
       0: aload_0
       1: getfield      #4                  // Field closeFuture:Ljava/util/concurrent/CompletableFuture;
       4: aconst_null
       5: invokevirtual #5                  // Method java/util/concurrent/CompletableFuture.complete:(Ljava/lang/Object;)Z
       8: pop
       9: return

  public java.util.concurrent.CompletableFuture<?> closeFuture();
    Code:
       0: aload_0
       1: getfield      #4                  // Field closeFuture:Ljava/util/concurrent/CompletableFuture;
       4: areturn
}
