Compiled from "HTTPListenerConsumer.java"
public interface org.wildfly.swarm.config.undertow.server.HTTPListenerConsumer<T extends org.wildfly.swarm.config.undertow.server.HTTPListener<T>> {
  public abstract void accept(T);

  public default org.wildfly.swarm.config.undertow.server.HTTPListenerConsumer<T> andThen(org.wildfly.swarm.config.undertow.server.HTTPListenerConsumer<T>);
    Code:
       0: aload_0
       1: aload_1
       2: invokedynamic #1,  0              // InvokeDynamic #0:accept:(Lorg/wildfly/swarm/config/undertow/server/HTTPListenerConsumer;Lorg/wildfly/swarm/config/undertow/server/HTTPListenerConsumer;)Lorg/wildfly/swarm/config/undertow/server/HTTPListenerConsumer;
       7: areturn

  private void lambda$andThen$506(org.wildfly.swarm.config.undertow.server.HTTPListenerConsumer, org.wildfly.swarm.config.undertow.server.HTTPListener);
    Code:
       0: aload_0
       1: aload_2
       2: invokeinterface #2,  2            // InterfaceMethod accept:(Lorg/wildfly/swarm/config/undertow/server/HTTPListener;)V
       7: aload_1
       8: aload_2
       9: invokeinterface #2,  2            // InterfaceMethod accept:(Lorg/wildfly/swarm/config/undertow/server/HTTPListener;)V
      14: return
}
