Compiled from "FullTimeWindowedSerde.java"
class org.apache.kafka.streams.kstream.internals.FullTimeWindowedSerde<T> extends org.apache.kafka.common.serialization.Serdes$WrapperSerde<org.apache.kafka.streams.kstream.Windowed<T>> {
  org.apache.kafka.streams.kstream.internals.FullTimeWindowedSerde(org.apache.kafka.common.serialization.Serde<T>, long);
    Code:
       0: aload_0
       1: new           #1                  // class org/apache/kafka/streams/kstream/TimeWindowedSerializer
       4: dup
       5: aload_1
       6: invokeinterface #2,  1            // InterfaceMethod org/apache/kafka/common/serialization/Serde.serializer:()Lorg/apache/kafka/common/serialization/Serializer;
      11: invokespecial #3                  // Method org/apache/kafka/streams/kstream/TimeWindowedSerializer."<init>":(Lorg/apache/kafka/common/serialization/Serializer;)V
      14: new           #4                  // class org/apache/kafka/streams/kstream/TimeWindowedDeserializer
      17: dup
      18: aload_1
      19: invokeinterface #5,  1            // InterfaceMethod org/apache/kafka/common/serialization/Serde.deserializer:()Lorg/apache/kafka/common/serialization/Deserializer;
      24: lload_2
      25: invokespecial #6                  // Method org/apache/kafka/streams/kstream/TimeWindowedDeserializer."<init>":(Lorg/apache/kafka/common/serialization/Deserializer;J)V
      28: invokespecial #7                  // Method org/apache/kafka/common/serialization/Serdes$WrapperSerde."<init>":(Lorg/apache/kafka/common/serialization/Serializer;Lorg/apache/kafka/common/serialization/Deserializer;)V
      31: return
}
