Compiled from "KStreamBranch.java"
class org.apache.kafka.streams.kstream.internals.KStreamBranch$KStreamBranchProcessor extends org.apache.kafka.streams.processor.AbstractProcessor<K, V> {
  final org.apache.kafka.streams.kstream.internals.KStreamBranch this$0;

  private org.apache.kafka.streams.kstream.internals.KStreamBranch$KStreamBranchProcessor(org.apache.kafka.streams.kstream.internals.KStreamBranch);
    Code:
       0: aload_0
       1: aload_1
       2: putfield      #2                  // Field this$0:Lorg/apache/kafka/streams/kstream/internals/KStreamBranch;
       5: aload_0
       6: invokespecial #3                  // Method org/apache/kafka/streams/processor/AbstractProcessor."<init>":()V
       9: return

  public void process(K, V);
    Code:
       0: iconst_0
       1: istore_3
       2: iload_3
       3: aload_0
       4: getfield      #2                  // Field this$0:Lorg/apache/kafka/streams/kstream/internals/KStreamBranch;
       7: invokestatic  #4                  // Method org/apache/kafka/streams/kstream/internals/KStreamBranch.access$100:(Lorg/apache/kafka/streams/kstream/internals/KStreamBranch;)[Lorg/apache/kafka/streams/kstream/Predicate;
      10: arraylength
      11: if_icmpge     65
      14: aload_0
      15: getfield      #2                  // Field this$0:Lorg/apache/kafka/streams/kstream/internals/KStreamBranch;
      18: invokestatic  #4                  // Method org/apache/kafka/streams/kstream/internals/KStreamBranch.access$100:(Lorg/apache/kafka/streams/kstream/internals/KStreamBranch;)[Lorg/apache/kafka/streams/kstream/Predicate;
      21: iload_3
      22: aaload
      23: aload_1
      24: aload_2
      25: invokeinterface #5,  3            // InterfaceMethod org/apache/kafka/streams/kstream/Predicate.test:(Ljava/lang/Object;Ljava/lang/Object;)Z
      30: ifeq          59
      33: aload_0
      34: invokevirtual #6                  // Method context:()Lorg/apache/kafka/streams/processor/ProcessorContext;
      37: aload_1
      38: aload_2
      39: aload_0
      40: getfield      #2                  // Field this$0:Lorg/apache/kafka/streams/kstream/internals/KStreamBranch;
      43: invokestatic  #7                  // Method org/apache/kafka/streams/kstream/internals/KStreamBranch.access$200:(Lorg/apache/kafka/streams/kstream/internals/KStreamBranch;)[Ljava/lang/String;
      46: iload_3
      47: aaload
      48: invokestatic  #8                  // Method org/apache/kafka/streams/processor/To.child:(Ljava/lang/String;)Lorg/apache/kafka/streams/processor/To;
      51: invokeinterface #9,  4            // InterfaceMethod org/apache/kafka/streams/processor/ProcessorContext.forward:(Ljava/lang/Object;Ljava/lang/Object;Lorg/apache/kafka/streams/processor/To;)V
      56: goto          65
      59: iinc          3, 1
      62: goto          2
      65: return

  org.apache.kafka.streams.kstream.internals.KStreamBranch$KStreamBranchProcessor(org.apache.kafka.streams.kstream.internals.KStreamBranch, org.apache.kafka.streams.kstream.internals.KStreamBranch$1);
    Code:
       0: aload_0
       1: aload_1
       2: invokespecial #1                  // Method "<init>":(Lorg/apache/kafka/streams/kstream/internals/KStreamBranch;)V
       5: return
}
