Compiled from "KTableMaterializedValueGetterSupplier.java"
public class org.apache.kafka.streams.kstream.internals.KTableMaterializedValueGetterSupplier<K, V> implements org.apache.kafka.streams.kstream.internals.KTableValueGetterSupplier<K, V> {
  private final java.lang.String storeName;

  org.apache.kafka.streams.kstream.internals.KTableMaterializedValueGetterSupplier(java.lang.String);
    Code:
       0: aload_0
       1: invokespecial #2                  // Method java/lang/Object."<init>":()V
       4: aload_0
       5: aload_1
       6: putfield      #1                  // Field storeName:Ljava/lang/String;
       9: return

  public org.apache.kafka.streams.kstream.internals.KTableValueGetter<K, V> get();
    Code:
       0: new           #3                  // class org/apache/kafka/streams/kstream/internals/KTableMaterializedValueGetterSupplier$KTableMaterializedValueGetter
       3: dup
       4: aload_0
       5: aconst_null
       6: invokespecial #4                  // Method org/apache/kafka/streams/kstream/internals/KTableMaterializedValueGetterSupplier$KTableMaterializedValueGetter."<init>":(Lorg/apache/kafka/streams/kstream/internals/KTableMaterializedValueGetterSupplier;Lorg/apache/kafka/streams/kstream/internals/KTableMaterializedValueGetterSupplier$1;)V
       9: areturn

  public java.lang.String[] storeNames();
    Code:
       0: iconst_1
       1: anewarray     #5                  // class java/lang/String
       4: dup
       5: iconst_0
       6: aload_0
       7: getfield      #1                  // Field storeName:Ljava/lang/String;
      10: aastore
      11: areturn

  static java.lang.String access$100(org.apache.kafka.streams.kstream.internals.KTableMaterializedValueGetterSupplier);
    Code:
       0: aload_0
       1: getfield      #1                  // Field storeName:Ljava/lang/String;
       4: areturn
}
