Compiled from "PassThrough.java"
class org.apache.kafka.streams.kstream.internals.PassThrough<K, V> implements org.apache.kafka.streams.processor.ProcessorSupplier<K, V> {
  org.apache.kafka.streams.kstream.internals.PassThrough();
    Code:
       0: aload_0
       1: invokespecial #1                  // Method java/lang/Object."<init>":()V
       4: return

  public org.apache.kafka.streams.processor.Processor<K, V> get();
    Code:
       0: new           #2                  // class org/apache/kafka/streams/kstream/internals/PassThrough$PassThroughProcessor
       3: dup
       4: aconst_null
       5: invokespecial #3                  // Method org/apache/kafka/streams/kstream/internals/PassThrough$PassThroughProcessor."<init>":(Lorg/apache/kafka/streams/kstream/internals/PassThrough$1;)V
       8: areturn
}
