Compiled from "DevUtil.java"
class net.wasdev.wlp.common.plugins.util.DevUtil$2 extends java.lang.Thread {
  final java.util.concurrent.ThreadPoolExecutor val$executor;

  final net.wasdev.wlp.common.plugins.util.DevUtil this$0;

  net.wasdev.wlp.common.plugins.util.DevUtil$2(net.wasdev.wlp.common.plugins.util.DevUtil, java.util.concurrent.ThreadPoolExecutor);
    Code:
       0: aload_0
       1: aload_1
       2: putfield      #1                  // Field this$0:Lnet/wasdev/wlp/common/plugins/util/DevUtil;
       5: aload_0
       6: aload_2
       7: putfield      #2                  // Field val$executor:Ljava/util/concurrent/ThreadPoolExecutor;
      10: aload_0
      11: invokespecial #3                  // Method java/lang/Thread."<init>":()V
      14: return

  public void run();
    Code:
       0: aload_0
       1: getfield      #1                  // Field this$0:Lnet/wasdev/wlp/common/plugins/util/DevUtil;
       4: ldc           #4                  // String Inside Shutdown Hook, shutting down server
       6: invokevirtual #5                  // Method net/wasdev/wlp/common/plugins/util/DevUtil.debug:(Ljava/lang/String;)V
       9: aload_0
      10: getfield      #1                  // Field this$0:Lnet/wasdev/wlp/common/plugins/util/DevUtil;
      13: invokevirtual #6                  // Method net/wasdev/wlp/common/plugins/util/DevUtil.cleanUpTempConfig:()V
      16: aload_0
      17: getfield      #1                  // Field this$0:Lnet/wasdev/wlp/common/plugins/util/DevUtil;
      20: invokevirtual #7                  // Method net/wasdev/wlp/common/plugins/util/DevUtil.cleanUpServerEnv:()V
      23: aload_0
      24: getfield      #1                  // Field this$0:Lnet/wasdev/wlp/common/plugins/util/DevUtil;
      27: invokestatic  #8                  // Method net/wasdev/wlp/common/plugins/util/DevUtil.access$000:(Lnet/wasdev/wlp/common/plugins/util/DevUtil;)Lnet/wasdev/wlp/common/plugins/util/DevUtil$HotkeyReader;
      30: ifnull        43
      33: aload_0
      34: getfield      #1                  // Field this$0:Lnet/wasdev/wlp/common/plugins/util/DevUtil;
      37: invokestatic  #8                  // Method net/wasdev/wlp/common/plugins/util/DevUtil.access$000:(Lnet/wasdev/wlp/common/plugins/util/DevUtil;)Lnet/wasdev/wlp/common/plugins/util/DevUtil$HotkeyReader;
      40: invokevirtual #9                  // Method net/wasdev/wlp/common/plugins/util/DevUtil$HotkeyReader.shutdown:()V
      43: aload_0
      44: getfield      #2                  // Field val$executor:Ljava/util/concurrent/ThreadPoolExecutor;
      47: invokevirtual #10                 // Method java/util/concurrent/ThreadPoolExecutor.shutdown:()V
      50: aload_0
      51: getfield      #1                  // Field this$0:Lnet/wasdev/wlp/common/plugins/util/DevUtil;
      54: invokevirtual #11                 // Method net/wasdev/wlp/common/plugins/util/DevUtil.stopServer:()V
      57: return
}
