Compiled from "InstallFeatureUtil.java"
public abstract class net.wasdev.wlp.common.plugins.util.InstallFeatureUtil extends net.wasdev.wlp.common.plugins.util.ServerFeatureUtil {
  public static final java.lang.String OPEN_LIBERTY_GROUP_ID;

  public static final java.lang.String REPOSITORY_RESOLVER_ARTIFACT_ID;

  public static final java.lang.String INSTALL_MAP_ARTIFACT_ID;

  private final java.io.File installDirectory;

  private final java.io.File installJarFile;

  private final java.util.List<net.wasdev.wlp.common.plugins.util.InstallFeatureUtil$ProductProperties> propertiesList;

  private final java.lang.String to;

  private final java.util.Set<java.io.File> downloadedJsons;

  private static final java.lang.String INSTALL_MAP_PREFIX;

  private static final java.lang.String INSTALL_MAP_SUFFIX;

  private static final java.lang.String OPEN_LIBERTY_PRODUCT_ID;

  private static final int COPY_FILE_TIMEOUT_MILLIS;

  private java.lang.String openLibertyVersion;

  public net.wasdev.wlp.common.plugins.util.InstallFeatureUtil(java.io.File, java.lang.String, java.lang.String, java.util.Set<java.lang.String>) throws net.wasdev.wlp.common.plugins.util.PluginScenarioException, net.wasdev.wlp.common.plugins.util.PluginExecutionException;
    Code:
       0: aload_0
       1: invokespecial #2                  // Method net/wasdev/wlp/common/plugins/util/ServerFeatureUtil."<init>":()V
       4: aload_0
       5: aload_1
       6: putfield      #3                  // Field installDirectory:Ljava/io/File;
       9: aload_0
      10: aload_3
      11: putfield      #4                  // Field to:Ljava/lang/String;
      14: aload_0
      15: aload_0
      16: new           #5                  // class java/io/File
      19: dup
      20: aload_1
      21: ldc           #6                  // String lib/versions
      23: invokespecial #7                  // Method java/io/File."<init>":(Ljava/io/File;Ljava/lang/String;)V
      26: invokespecial #8                  // Method loadProperties:(Ljava/io/File;)Ljava/util/List;
      29: putfield      #9                  // Field propertiesList:Ljava/util/List;
      32: aload_0
      33: aload_0
      34: aload_1
      35: invokespecial #10                 // Method loadInstallJarFile:(Ljava/io/File;)Ljava/io/File;
      38: putfield      #1                  // Field installJarFile:Ljava/io/File;
      41: aload_0
      42: getfield      #1                  // Field installJarFile:Ljava/io/File;
      45: ifnonnull     58
      48: new           #11                 // class net/wasdev/wlp/common/plugins/util/PluginScenarioException
      51: dup
      52: ldc           #12                 // String Install map jar not found.
      54: invokespecial #13                 // Method net/wasdev/wlp/common/plugins/util/PluginScenarioException."<init>":(Ljava/lang/String;)V
      57: athrow
      58: aload_0
      59: aload_0
      60: invokespecial #14                 // Method downloadProductJsons:()Ljava/util/Set;
      63: putfield      #15                 // Field downloadedJsons:Ljava/util/Set;
      66: aload_0
      67: getfield      #15                 // Field downloadedJsons:Ljava/util/Set;
      70: invokeinterface #16,  1           // InterfaceMethod java/util/Set.isEmpty:()Z
      75: ifeq          88
      78: new           #11                 // class net/wasdev/wlp/common/plugins/util/PluginScenarioException
      81: dup
      82: ldc           #17                 // String Cannot find JSONs for to the installed runtime from the Maven repository.
      84: invokespecial #13                 // Method net/wasdev/wlp/common/plugins/util/PluginScenarioException."<init>":(Ljava/lang/String;)V
      87: athrow
      88: aload_0
      89: aload_2
      90: aload         4
      92: invokespecial #18                 // Method hasUnsupportedParameters:(Ljava/lang/String;Ljava/util/Set;)Z
      95: ifeq          108
      98: new           #11                 // class net/wasdev/wlp/common/plugins/util/PluginScenarioException
     101: dup
     102: ldc           #19                 // String Cannot install features from a Maven repository when using the \'to\' or \'from\' parameters or when specifying ESA files.
     104: invokespecial #13                 // Method net/wasdev/wlp/common/plugins/util/PluginScenarioException."<init>":(Ljava/lang/String;)V
     107: athrow
     108: return

  private java.io.File loadInstallJarFile(java.io.File);
    Code:
       0: aload_0
       1: getfield      #20                 // Field openLibertyVersion:Ljava/lang/String;
       4: ifnull        29
       7: aload_0
       8: ldc           #22                 // String io.openliberty.features
      10: ldc           #23                 // String install-map
      12: invokespecial #24                 // Method downloadOverrideJar:(Ljava/lang/String;Ljava/lang/String;)Ljava/io/File;
      15: astore_2
      16: aload_2
      17: ifnull        29
      20: aload_2
      21: invokevirtual #25                 // Method java/io/File.exists:()Z
      24: ifeq          29
      27: aload_2
      28: areturn
      29: new           #5                  // class java/io/File
      32: dup
      33: aload_1
      34: ldc           #26                 // String lib
      36: invokespecial #7                  // Method java/io/File."<init>":(Ljava/io/File;Ljava/lang/String;)V
      39: invokestatic  #27                 // Method getMapBasedInstallKernelJar:(Ljava/io/File;)Ljava/io/File;
      42: areturn

  public abstract void debug(java.lang.String);

  public abstract void debug(java.lang.String, java.lang.Throwable);

  public abstract void debug(java.lang.Throwable);

  public abstract void warn(java.lang.String);

  public abstract void info(java.lang.String);

  public abstract boolean isDebugEnabled();

  public abstract java.io.File downloadArtifact(java.lang.String, java.lang.String, java.lang.String, java.lang.String) throws net.wasdev.wlp.common.plugins.util.PluginExecutionException;

  public static java.util.Set<java.lang.String> combineToSet(java.util.Collection<java.lang.String>...);
    Code:
       0: new           #28                 // class java/util/HashSet
       3: dup
       4: invokespecial #29                 // Method java/util/HashSet."<init>":()V
       7: astore_1
       8: new           #28                 // class java/util/HashSet
      11: dup
      12: invokespecial #29                 // Method java/util/HashSet."<init>":()V
      15: astore_2
      16: aload_0
      17: astore_3
      18: aload_3
      19: arraylength
      20: istore        4
      22: iconst_0
      23: istore        5
      25: iload         5
      27: iload         4
      29: if_icmpge     118
      32: aload_3
      33: iload         5
      35: aaload
      36: astore        6
      38: aload         6
      40: ifnull        112
      43: aload         6
      45: invokeinterface #30,  1           // InterfaceMethod java/util/Collection.iterator:()Ljava/util/Iterator;
      50: astore        7
      52: aload         7
      54: invokeinterface #31,  1           // InterfaceMethod java/util/Iterator.hasNext:()Z
      59: ifeq          112
      62: aload         7
      64: invokeinterface #32,  1           // InterfaceMethod java/util/Iterator.next:()Ljava/lang/Object;
      69: checkcast     #33                 // class java/lang/String
      72: astore        8
      74: aload_2
      75: aload         8
      77: invokevirtual #34                 // Method java/lang/String.toLowerCase:()Ljava/lang/String;
      80: invokeinterface #35,  2           // InterfaceMethod java/util/Set.contains:(Ljava/lang/Object;)Z
      85: ifne          109
      88: aload_2
      89: aload         8
      91: invokevirtual #34                 // Method java/lang/String.toLowerCase:()Ljava/lang/String;
      94: invokeinterface #36,  2           // InterfaceMethod java/util/Set.add:(Ljava/lang/Object;)Z
      99: pop
     100: aload_1
     101: aload         8
     103: invokeinterface #36,  2           // InterfaceMethod java/util/Set.add:(Ljava/lang/Object;)Z
     108: pop
     109: goto          52
     112: iinc          5, 1
     115: goto          25
     118: aload_1
     119: areturn

  private java.util.Set<java.io.File> downloadProductJsons() throws net.wasdev.wlp.common.plugins.util.PluginExecutionException;
    Code:
       0: new           #28                 // class java/util/HashSet
       3: dup
       4: invokespecial #29                 // Method java/util/HashSet."<init>":()V
       7: astore_1
       8: aload_0
       9: getfield      #9                  // Field propertiesList:Ljava/util/List;
      12: invokeinterface #37,  1           // InterfaceMethod java/util/List.iterator:()Ljava/util/Iterator;
      17: astore_2
      18: aload_2
      19: invokeinterface #31,  1           // InterfaceMethod java/util/Iterator.hasNext:()Z
      24: ifeq          68
      27: aload_2
      28: invokeinterface #32,  1           // InterfaceMethod java/util/Iterator.next:()Ljava/lang/Object;
      33: checkcast     #38                 // class net/wasdev/wlp/common/plugins/util/InstallFeatureUtil$ProductProperties
      36: astore_3
      37: aload_0
      38: aload_3
      39: invokevirtual #39                 // Method net/wasdev/wlp/common/plugins/util/InstallFeatureUtil$ProductProperties.getId:()Ljava/lang/String;
      42: aload_3
      43: invokevirtual #40                 // Method net/wasdev/wlp/common/plugins/util/InstallFeatureUtil$ProductProperties.getVersion:()Ljava/lang/String;
      46: invokespecial #41                 // Method downloadJsons:(Ljava/lang/String;Ljava/lang/String;)Ljava/io/File;
      49: astore        4
      51: aload         4
      53: ifnull        65
      56: aload_1
      57: aload         4
      59: invokeinterface #36,  2           // InterfaceMethod java/util/Set.add:(Ljava/lang/Object;)Z
      64: pop
      65: goto          18
      68: aload_1
      69: areturn

  private java.io.File downloadJsons(java.lang.String, java.lang.String);
    Code:
       0: new           #42                 // class java/lang/StringBuilder
       3: dup
       4: invokespecial #43                 // Method java/lang/StringBuilder."<init>":()V
       7: aload_1
       8: invokevirtual #44                 // Method java/lang/StringBuilder.append:(Ljava/lang/String;)Ljava/lang/StringBuilder;
      11: ldc           #45                 // String .features
      13: invokevirtual #44                 // Method java/lang/StringBuilder.append:(Ljava/lang/String;)Ljava/lang/StringBuilder;
      16: invokevirtual #46                 // Method java/lang/StringBuilder.toString:()Ljava/lang/String;
      19: astore_3
      20: aload_0
      21: aload_3
      22: ldc           #47                 // String features
      24: ldc           #48                 // String json
      26: aload_2
      27: invokevirtual #49                 // Method downloadArtifact:(Ljava/lang/String;Ljava/lang/String;Ljava/lang/String;Ljava/lang/String;)Ljava/io/File;
      30: areturn
      31: astore        4
      33: aload_0
      34: new           #42                 // class java/lang/StringBuilder
      37: dup
      38: invokespecial #43                 // Method java/lang/StringBuilder."<init>":()V
      41: ldc           #51                 // String Cannot find json for productId
      43: invokevirtual #44                 // Method java/lang/StringBuilder.append:(Ljava/lang/String;)Ljava/lang/StringBuilder;
      46: aload_1
      47: invokevirtual #44                 // Method java/lang/StringBuilder.append:(Ljava/lang/String;)Ljava/lang/StringBuilder;
      50: ldc           #52                 // String , productVersion
      52: invokevirtual #44                 // Method java/lang/StringBuilder.append:(Ljava/lang/String;)Ljava/lang/StringBuilder;
      55: aload_2
      56: invokevirtual #44                 // Method java/lang/StringBuilder.append:(Ljava/lang/String;)Ljava/lang/StringBuilder;
      59: invokevirtual #46                 // Method java/lang/StringBuilder.toString:()Ljava/lang/String;
      62: aload         4
      64: invokevirtual #53                 // Method debug:(Ljava/lang/String;Ljava/lang/Throwable;)V
      67: aconst_null
      68: areturn
    Exception table:
       from    to  target type
          20    30    31   Class net/wasdev/wlp/common/plugins/util/PluginExecutionException

  private java.util.List<net.wasdev.wlp.common.plugins.util.InstallFeatureUtil$ProductProperties> loadProperties(java.io.File) throws net.wasdev.wlp.common.plugins.util.PluginExecutionException;
    Code:
       0: new           #54                 // class java/util/ArrayList
       3: dup
       4: invokespecial #55                 // Method java/util/ArrayList."<init>":()V
       7: astore_2
       8: aload_1
       9: new           #56                 // class net/wasdev/wlp/common/plugins/util/InstallFeatureUtil$1
      12: dup
      13: aload_0
      14: invokespecial #57                 // Method net/wasdev/wlp/common/plugins/util/InstallFeatureUtil$1."<init>":(Lnet/wasdev/wlp/common/plugins/util/InstallFeatureUtil;)V
      17: invokevirtual #58                 // Method java/io/File.listFiles:(Ljava/io/FilenameFilter;)[Ljava/io/File;
      20: astore_3
      21: aload_3
      22: ifnull        294
      25: aload_3
      26: astore        4
      28: aload         4
      30: arraylength
      31: istore        5
      33: iconst_0
      34: istore        6
      36: iload         6
      38: iload         5
      40: if_icmpge     294
      43: aload         4
      45: iload         6
      47: aaload
      48: astore        7
      50: new           #59                 // class java/util/Properties
      53: dup
      54: invokespecial #60                 // Method java/util/Properties."<init>":()V
      57: astore        8
      59: aconst_null
      60: astore        9
      62: new           #61                 // class java/io/FileInputStream
      65: dup
      66: aload         7
      68: invokespecial #62                 // Method java/io/FileInputStream."<init>":(Ljava/io/File;)V
      71: astore        9
      73: aload         8
      75: aload         9
      77: invokevirtual #63                 // Method java/util/Properties.load:(Ljava/io/InputStream;)V
      80: aload         8
      82: ldc           #64                 // String com.ibm.websphere.productId
      84: invokevirtual #65                 // Method java/util/Properties.getProperty:(Ljava/lang/String;)Ljava/lang/String;
      87: astore        10
      89: aload         8
      91: ldc           #66                 // String com.ibm.websphere.productVersion
      93: invokevirtual #65                 // Method java/util/Properties.getProperty:(Ljava/lang/String;)Ljava/lang/String;
      96: astore        11
      98: aload         10
     100: ifnonnull     139
     103: new           #50                 // class net/wasdev/wlp/common/plugins/util/PluginExecutionException
     106: dup
     107: new           #42                 // class java/lang/StringBuilder
     110: dup
     111: invokespecial #43                 // Method java/lang/StringBuilder."<init>":()V
     114: ldc           #67                 // String Cannot find the \"com.ibm.websphere.productId\" property in the file
     116: invokevirtual #44                 // Method java/lang/StringBuilder.append:(Ljava/lang/String;)Ljava/lang/StringBuilder;
     119: aload         7
     121: invokevirtual #68                 // Method java/io/File.getAbsolutePath:()Ljava/lang/String;
     124: invokevirtual #44                 // Method java/lang/StringBuilder.append:(Ljava/lang/String;)Ljava/lang/StringBuilder;
     127: ldc           #69                 // String . Ensure the file is valid properties file for the Liberty product or extension.
     129: invokevirtual #44                 // Method java/lang/StringBuilder.append:(Ljava/lang/String;)Ljava/lang/StringBuilder;
     132: invokevirtual #46                 // Method java/lang/StringBuilder.toString:()Ljava/lang/String;
     135: invokespecial #70                 // Method net/wasdev/wlp/common/plugins/util/PluginExecutionException."<init>":(Ljava/lang/String;)V
     138: athrow
     139: aload         11
     141: ifnonnull     180
     144: new           #50                 // class net/wasdev/wlp/common/plugins/util/PluginExecutionException
     147: dup
     148: new           #42                 // class java/lang/StringBuilder
     151: dup
     152: invokespecial #43                 // Method java/lang/StringBuilder."<init>":()V
     155: ldc           #71                 // String Cannot find the \"com.ibm.websphere.productVersion\" property in the file
     157: invokevirtual #44                 // Method java/lang/StringBuilder.append:(Ljava/lang/String;)Ljava/lang/StringBuilder;
     160: aload         7
     162: invokevirtual #68                 // Method java/io/File.getAbsolutePath:()Ljava/lang/String;
     165: invokevirtual #44                 // Method java/lang/StringBuilder.append:(Ljava/lang/String;)Ljava/lang/StringBuilder;
     168: ldc           #69                 // String . Ensure the file is valid properties file for the Liberty product or extension.
     170: invokevirtual #44                 // Method java/lang/StringBuilder.append:(Ljava/lang/String;)Ljava/lang/StringBuilder;
     173: invokevirtual #46                 // Method java/lang/StringBuilder.toString:()Ljava/lang/String;
     176: invokespecial #70                 // Method net/wasdev/wlp/common/plugins/util/PluginExecutionException."<init>":(Ljava/lang/String;)V
     179: athrow
     180: aload         10
     182: ldc           #72                 // String io.openliberty
     184: invokevirtual #73                 // Method java/lang/String.equals:(Ljava/lang/Object;)Z
     187: ifeq          196
     190: aload_0
     191: aload         11
     193: putfield      #20                 // Field openLibertyVersion:Ljava/lang/String;
     196: aload_2
     197: new           #38                 // class net/wasdev/wlp/common/plugins/util/InstallFeatureUtil$ProductProperties
     200: dup
     201: aload_0
     202: aload         10
     204: aload         11
     206: invokespecial #74                 // Method net/wasdev/wlp/common/plugins/util/InstallFeatureUtil$ProductProperties."<init>":(Lnet/wasdev/wlp/common/plugins/util/InstallFeatureUtil;Ljava/lang/String;Ljava/lang/String;)V
     209: invokeinterface #75,  2           // InterfaceMethod java/util/List.add:(Ljava/lang/Object;)Z
     214: pop
     215: aload         9
     217: ifnull        288
     220: aload         9
     222: invokevirtual #76                 // Method java/io/InputStream.close:()V
     225: goto          288
     228: astore        10
     230: goto          288
     233: astore        10
     235: new           #50                 // class net/wasdev/wlp/common/plugins/util/PluginExecutionException
     238: dup
     239: new           #42                 // class java/lang/StringBuilder
     242: dup
     243: invokespecial #43                 // Method java/lang/StringBuilder."<init>":()V
     246: ldc           #78                 // String Cannot read the product properties file
     248: invokevirtual #44                 // Method java/lang/StringBuilder.append:(Ljava/lang/String;)Ljava/lang/StringBuilder;
     251: aload         7
     253: invokevirtual #68                 // Method java/io/File.getAbsolutePath:()Ljava/lang/String;
     256: invokevirtual #44                 // Method java/lang/StringBuilder.append:(Ljava/lang/String;)Ljava/lang/StringBuilder;
     259: invokevirtual #46                 // Method java/lang/StringBuilder.toString:()Ljava/lang/String;
     262: aload         10
     264: invokespecial #79                 // Method net/wasdev/wlp/common/plugins/util/PluginExecutionException."<init>":(Ljava/lang/String;Ljava/lang/Throwable;)V
     267: athrow
     268: astore        12
     270: aload         9
     272: ifnull        285
     275: aload         9
     277: invokevirtual #76                 // Method java/io/InputStream.close:()V
     280: goto          285
     283: astore        13
     285: aload         12
     287: athrow
     288: iinc          6, 1
     291: goto          36
     294: aload_2
     295: invokeinterface #80,  1           // InterfaceMethod java/util/List.isEmpty:()Z
     300: ifeq          347
     303: new           #50                 // class net/wasdev/wlp/common/plugins/util/PluginExecutionException
     306: dup
     307: new           #42                 // class java/lang/StringBuilder
     310: dup
     311: invokespecial #43                 // Method java/lang/StringBuilder."<init>":()V
     314: ldc           #81                 // String Could not find any properties file in the
     316: invokevirtual #44                 // Method java/lang/StringBuilder.append:(Ljava/lang/String;)Ljava/lang/StringBuilder;
     319: aload_1
     320: invokevirtual #82                 // Method java/lang/StringBuilder.append:(Ljava/lang/Object;)Ljava/lang/StringBuilder;
     323: ldc           #83                 // String  directory. Ensure the directory
     325: invokevirtual #44                 // Method java/lang/StringBuilder.append:(Ljava/lang/String;)Ljava/lang/StringBuilder;
     328: aload_0
     329: getfield      #3                  // Field installDirectory:Ljava/io/File;
     332: invokevirtual #82                 // Method java/lang/StringBuilder.append:(Ljava/lang/Object;)Ljava/lang/StringBuilder;
     335: ldc           #84                 // String  contains a Liberty installation.
     337: invokevirtual #44                 // Method java/lang/StringBuilder.append:(Ljava/lang/String;)Ljava/lang/StringBuilder;
     340: invokevirtual #46                 // Method java/lang/StringBuilder.toString:()Ljava/lang/String;
     343: invokespecial #70                 // Method net/wasdev/wlp/common/plugins/util/PluginExecutionException."<init>":(Ljava/lang/String;)V
     346: athrow
     347: aload_2
     348: areturn
    Exception table:
       from    to  target type
         220   225   228   Class java/io/IOException
          62   215   233   Class java/io/IOException
          62   215   268   any
         275   280   283   Class java/io/IOException
         233   270   268   any

  private boolean hasUnsupportedParameters(java.lang.String, java.util.Set<java.lang.String>);
    Code:
       0: aload_1
       1: ifnull        8
       4: iconst_1
       5: goto          9
       8: iconst_0
       9: istore_3
      10: aload_2
      11: invokeinterface #16,  1           // InterfaceMethod java/util/Set.isEmpty:()Z
      16: ifne          23
      19: iconst_1
      20: goto          24
      23: iconst_0
      24: istore        4
      26: aload_0
      27: new           #42                 // class java/lang/StringBuilder
      30: dup
      31: invokespecial #43                 // Method java/lang/StringBuilder."<init>":()V
      34: ldc           #85                 // String hasFrom:
      36: invokevirtual #44                 // Method java/lang/StringBuilder.append:(Ljava/lang/String;)Ljava/lang/StringBuilder;
      39: iload_3
      40: invokevirtual #86                 // Method java/lang/StringBuilder.append:(Z)Ljava/lang/StringBuilder;
      43: invokevirtual #46                 // Method java/lang/StringBuilder.toString:()Ljava/lang/String;
      46: invokevirtual #87                 // Method debug:(Ljava/lang/String;)V
      49: aload_0
      50: new           #42                 // class java/lang/StringBuilder
      53: dup
      54: invokespecial #43                 // Method java/lang/StringBuilder."<init>":()V
      57: ldc           #88                 // String hasPluginListedEsas:
      59: invokevirtual #44                 // Method java/lang/StringBuilder.append:(Ljava/lang/String;)Ljava/lang/StringBuilder;
      62: iload         4
      64: invokevirtual #86                 // Method java/lang/StringBuilder.append:(Z)Ljava/lang/StringBuilder;
      67: invokevirtual #46                 // Method java/lang/StringBuilder.toString:()Ljava/lang/String;
      70: invokevirtual #87                 // Method debug:(Ljava/lang/String;)V
      73: iload_3
      74: ifne          82
      77: iload         4
      79: ifeq          86
      82: iconst_1
      83: goto          87
      86: iconst_0
      87: ireturn

  private java.io.File downloadEsaArtifact(java.lang.String) throws net.wasdev.wlp.common.plugins.util.PluginExecutionException;
    Code:
       0: aload_1
       1: ldc           #89                 // String :
       3: invokevirtual #90                 // Method java/lang/String.split:(Ljava/lang/String;)[Ljava/lang/String;
       6: astore_2
       7: aload_2
       8: iconst_0
       9: aaload
      10: astore_3
      11: aload_2
      12: iconst_1
      13: aaload
      14: astore        4
      16: aload_2
      17: iconst_2
      18: aaload
      19: astore        5
      21: aload_0
      22: aload_3
      23: aload         4
      25: ldc           #91                 // String esa
      27: aload         5
      29: invokevirtual #49                 // Method downloadArtifact:(Ljava/lang/String;Ljava/lang/String;Ljava/lang/String;Ljava/lang/String;)Ljava/io/File;
      32: areturn

  private java.util.List<java.io.File> downloadEsas(java.util.Collection<?>) throws net.wasdev.wlp.common.plugins.util.PluginExecutionException;
    Code:
       0: new           #54                 // class java/util/ArrayList
       3: dup
       4: invokespecial #55                 // Method java/util/ArrayList."<init>":()V
       7: astore_2
       8: aload_1
       9: invokeinterface #30,  1           // InterfaceMethod java/util/Collection.iterator:()Ljava/util/Iterator;
      14: astore_3
      15: aload_3
      16: invokeinterface #31,  1           // InterfaceMethod java/util/Iterator.hasNext:()Z
      21: ifeq          51
      24: aload_3
      25: invokeinterface #32,  1           // InterfaceMethod java/util/Iterator.next:()Ljava/lang/Object;
      30: astore        4
      32: aload_2
      33: aload_0
      34: aload         4
      36: checkcast     #33                 // class java/lang/String
      39: invokespecial #92                 // Method downloadEsaArtifact:(Ljava/lang/String;)Ljava/io/File;
      42: invokeinterface #75,  2           // InterfaceMethod java/util/List.add:(Ljava/lang/Object;)Z
      47: pop
      48: goto          15
      51: aload_2
      52: areturn

  public static java.util.Set<java.lang.String> getOpenLibertyFeatureSet(java.util.Set<java.io.File>) throws net.wasdev.wlp.common.plugins.util.PluginExecutionException;
    Code:
       0: new           #28                 // class java/util/HashSet
       3: dup
       4: invokespecial #29                 // Method java/util/HashSet."<init>":()V
       7: astore_1
       8: aload_0
       9: invokeinterface #93,  1           // InterfaceMethod java/util/Set.iterator:()Ljava/util/Iterator;
      14: astore_2
      15: aload_2
      16: invokeinterface #31,  1           // InterfaceMethod java/util/Iterator.hasNext:()Z
      21: ifeq          159
      24: aload_2
      25: invokeinterface #32,  1           // InterfaceMethod java/util/Iterator.next:()Ljava/lang/Object;
      30: checkcast     #5                  // class java/io/File
      33: astore_3
      34: aconst_null
      35: astore        4
      37: new           #94                 // class java/util/Scanner
      40: dup
      41: aload_3
      42: invokespecial #95                 // Method java/util/Scanner."<init>":(Ljava/io/File;)V
      45: astore        4
      47: aload         4
      49: ldc           #96                 // String io.openliberty.features:([^:]*):
      51: iconst_0
      52: invokevirtual #97                 // Method java/util/Scanner.findWithinHorizon:(Ljava/lang/String;I)Ljava/lang/String;
      55: ifnull        94
      58: aload         4
      60: invokevirtual #98                 // Method java/util/Scanner.match:()Ljava/util/regex/MatchResult;
      63: astore        5
      65: aload         5
      67: invokeinterface #99,  1           // InterfaceMethod java/util/regex/MatchResult.groupCount:()I
      72: iconst_1
      73: if_icmplt     91
      76: aload_1
      77: aload         5
      79: iconst_1
      80: invokeinterface #100,  2          // InterfaceMethod java/util/regex/MatchResult.group:(I)Ljava/lang/String;
      85: invokeinterface #36,  2           // InterfaceMethod java/util/Set.add:(Ljava/lang/Object;)Z
      90: pop
      91: goto          47
      94: aload         4
      96: ifnull        156
      99: aload         4
     101: invokevirtual #101                // Method java/util/Scanner.close:()V
     104: goto          156
     107: astore        5
     109: new           #50                 // class net/wasdev/wlp/common/plugins/util/PluginExecutionException
     112: dup
     113: new           #42                 // class java/lang/StringBuilder
     116: dup
     117: invokespecial #43                 // Method java/lang/StringBuilder."<init>":()V
     120: ldc           #103                // String The JSON file is not found at
     122: invokevirtual #44                 // Method java/lang/StringBuilder.append:(Ljava/lang/String;)Ljava/lang/StringBuilder;
     125: aload_3
     126: invokevirtual #68                 // Method java/io/File.getAbsolutePath:()Ljava/lang/String;
     129: invokevirtual #44                 // Method java/lang/StringBuilder.append:(Ljava/lang/String;)Ljava/lang/StringBuilder;
     132: invokevirtual #46                 // Method java/lang/StringBuilder.toString:()Ljava/lang/String;
     135: aload         5
     137: invokespecial #79                 // Method net/wasdev/wlp/common/plugins/util/PluginExecutionException."<init>":(Ljava/lang/String;Ljava/lang/Throwable;)V
     140: athrow
     141: astore        6
     143: aload         4
     145: ifnull        153
     148: aload         4
     150: invokevirtual #101                // Method java/util/Scanner.close:()V
     153: aload         6
     155: athrow
     156: goto          15
     159: aload_1
     160: areturn
    Exception table:
       from    to  target type
          37    94   107   Class java/io/FileNotFoundException
          37    94   141   any
         107   143   141   any

  private boolean isOnlyOpenLibertyFeatures(java.util.List<java.lang.String>) throws net.wasdev.wlp.common.plugins.util.PluginExecutionException;
    Code:
       0: aload_0
       1: getfield      #15                 // Field downloadedJsons:Ljava/util/Set;
       4: invokestatic  #104                // Method getOpenLibertyFeatureSet:(Ljava/util/Set;)Ljava/util/Set;
       7: aload_1
       8: invokestatic  #105                // Method containsIgnoreCase:(Ljava/util/Collection;Ljava/util/Collection;)Z
      11: istore_2
      12: aload_0
      13: new           #42                 // class java/lang/StringBuilder
      16: dup
      17: invokespecial #43                 // Method java/lang/StringBuilder."<init>":()V
      20: ldc           #106                // String Is installing only Open Liberty features?
      22: invokevirtual #44                 // Method java/lang/StringBuilder.append:(Ljava/lang/String;)Ljava/lang/StringBuilder;
      25: iload_2
      26: invokevirtual #86                 // Method java/lang/StringBuilder.append:(Z)Ljava/lang/StringBuilder;
      29: invokevirtual #46                 // Method java/lang/StringBuilder.toString:()Ljava/lang/String;
      32: invokevirtual #87                 // Method debug:(Ljava/lang/String;)V
      35: iload_2
      36: ireturn

  public static boolean containsIgnoreCase(java.util.Collection<java.lang.String>, java.util.Collection<java.lang.String>);
    Code:
       0: aload_0
       1: invokestatic  #107                // Method toLowerCase:(Ljava/util/Collection;)Ljava/util/Set;
       4: aload_1
       5: invokestatic  #107                // Method toLowerCase:(Ljava/util/Collection;)Ljava/util/Set;
       8: invokeinterface #108,  2          // InterfaceMethod java/util/Set.containsAll:(Ljava/util/Collection;)Z
      13: ireturn

  private static java.util.Set<java.lang.String> toLowerCase(java.util.Collection<java.lang.String>);
    Code:
       0: new           #28                 // class java/util/HashSet
       3: dup
       4: aload_0
       5: invokeinterface #109,  1          // InterfaceMethod java/util/Collection.size:()I
      10: invokespecial #110                // Method java/util/HashSet."<init>":(I)V
      13: astore_1
      14: aload_0
      15: invokeinterface #30,  1           // InterfaceMethod java/util/Collection.iterator:()Ljava/util/Iterator;
      20: astore_2
      21: aload_2
      22: invokeinterface #31,  1           // InterfaceMethod java/util/Iterator.hasNext:()Z
      27: ifeq          54
      30: aload_2
      31: invokeinterface #32,  1           // InterfaceMethod java/util/Iterator.next:()Ljava/lang/Object;
      36: checkcast     #33                 // class java/lang/String
      39: astore_3
      40: aload_1
      41: aload_3
      42: invokevirtual #34                 // Method java/lang/String.toLowerCase:()Ljava/lang/String;
      45: invokeinterface #36,  2           // InterfaceMethod java/util/Set.add:(Ljava/lang/Object;)Z
      50: pop
      51: goto          21
      54: aload_1
      55: areturn

  public void installFeatures(boolean, java.util.List<java.lang.String>) throws net.wasdev.wlp.common.plugins.util.PluginExecutionException;
    Code:
       0: new           #54                 // class java/util/ArrayList
       3: dup
       4: aload_0
       5: getfield      #15                 // Field downloadedJsons:Ljava/util/Set;
       8: invokespecial #111                // Method java/util/ArrayList."<init>":(Ljava/util/Collection;)V
      11: astore_3
      12: aload_0
      13: new           #42                 // class java/lang/StringBuilder
      16: dup
      17: invokespecial #43                 // Method java/lang/StringBuilder."<init>":()V
      20: ldc           #112                // String JSON repos:
      22: invokevirtual #44                 // Method java/lang/StringBuilder.append:(Ljava/lang/String;)Ljava/lang/StringBuilder;
      25: aload_3
      26: invokevirtual #82                 // Method java/lang/StringBuilder.append:(Ljava/lang/Object;)Ljava/lang/StringBuilder;
      29: invokevirtual #46                 // Method java/lang/StringBuilder.toString:()Ljava/lang/String;
      32: invokevirtual #87                 // Method debug:(Ljava/lang/String;)V
      35: aload_0
      36: new           #42                 // class java/lang/StringBuilder
      39: dup
      40: invokespecial #43                 // Method java/lang/StringBuilder."<init>":()V
      43: ldc           #113                // String Installing features:
      45: invokevirtual #44                 // Method java/lang/StringBuilder.append:(Ljava/lang/String;)Ljava/lang/StringBuilder;
      48: aload_2
      49: invokevirtual #82                 // Method java/lang/StringBuilder.append:(Ljava/lang/Object;)Ljava/lang/StringBuilder;
      52: invokevirtual #46                 // Method java/lang/StringBuilder.toString:()Ljava/lang/String;
      55: invokevirtual #114                // Method info:(Ljava/lang/String;)V
      58: aload_0
      59: aload_2
      60: invokespecial #115                // Method isOnlyOpenLibertyFeatures:(Ljava/util/List;)Z
      63: ifeq          70
      66: iconst_1
      67: goto          71
      70: iload_1
      71: istore        4
      73: aload_0
      74: aload_0
      75: getfield      #3                  // Field installDirectory:Ljava/io/File;
      78: invokespecial #116                // Method createMapBasedInstallKernelInstance:(Ljava/io/File;)Ljava/util/Map;
      81: astore        5
      83: aload         5
      85: ldc           #117                // String install.local.esa
      87: iconst_1
      88: invokestatic  #118                // Method java/lang/Boolean.valueOf:(Z)Ljava/lang/Boolean;
      91: invokeinterface #119,  3          // InterfaceMethod java/util/Map.put:(Ljava/lang/Object;Ljava/lang/Object;)Ljava/lang/Object;
      96: pop
      97: aload         5
      99: ldc           #120                // String single.json.file
     101: aload_3
     102: invokeinterface #119,  3          // InterfaceMethod java/util/Map.put:(Ljava/lang/Object;Ljava/lang/Object;)Ljava/lang/Object;
     107: pop
     108: aload         5
     110: ldc           #121                // String features.to.resolve
     112: aload_2
     113: invokeinterface #119,  3          // InterfaceMethod java/util/Map.put:(Ljava/lang/Object;Ljava/lang/Object;)Ljava/lang/Object;
     118: pop
     119: aload         5
     121: ldc           #122                // String license.accept
     123: iload         4
     125: invokestatic  #118                // Method java/lang/Boolean.valueOf:(Z)Ljava/lang/Boolean;
     128: invokeinterface #119,  3          // InterfaceMethod java/util/Map.put:(Ljava/lang/Object;Ljava/lang/Object;)Ljava/lang/Object;
     133: pop
     134: aload_0
     135: invokevirtual #123                // Method isDebugEnabled:()Z
     138: ifeq          154
     141: aload         5
     143: ldc           #124                // String debug
     145: getstatic     #125                // Field java/util/logging/Level.FINEST:Ljava/util/logging/Level;
     148: invokeinterface #119,  3          // InterfaceMethod java/util/Map.put:(Ljava/lang/Object;Ljava/lang/Object;)Ljava/lang/Object;
     153: pop
     154: aload         5
     156: ldc           #126                // String action.result
     158: invokeinterface #127,  2          // InterfaceMethod java/util/Map.get:(Ljava/lang/Object;)Ljava/lang/Object;
     163: checkcast     #128                // class java/util/Collection
     166: astore        6
     168: aload         6
     170: ifnonnull     228
     173: aload_0
     174: new           #42                 // class java/lang/StringBuilder
     177: dup
     178: invokespecial #43                 // Method java/lang/StringBuilder."<init>":()V
     181: ldc           #129                // String action.exception.stacktrace:
     183: invokevirtual #44                 // Method java/lang/StringBuilder.append:(Ljava/lang/String;)Ljava/lang/StringBuilder;
     186: aload         5
     188: ldc           #130                // String action.exception.stacktrace
     190: invokeinterface #127,  2          // InterfaceMethod java/util/Map.get:(Ljava/lang/Object;)Ljava/lang/Object;
     195: invokevirtual #82                 // Method java/lang/StringBuilder.append:(Ljava/lang/Object;)Ljava/lang/StringBuilder;
     198: invokevirtual #46                 // Method java/lang/StringBuilder.toString:()Ljava/lang/String;
     201: invokevirtual #87                 // Method debug:(Ljava/lang/String;)V
     204: aload         5
     206: ldc           #131                // String action.error.message
     208: invokeinterface #127,  2          // InterfaceMethod java/util/Map.get:(Ljava/lang/Object;)Ljava/lang/Object;
     213: checkcast     #33                 // class java/lang/String
     216: astore        7
     218: new           #50                 // class net/wasdev/wlp/common/plugins/util/PluginExecutionException
     221: dup
     222: aload         7
     224: invokespecial #70                 // Method net/wasdev/wlp/common/plugins/util/PluginExecutionException."<init>":(Ljava/lang/String;)V
     227: athrow
     228: aload         6
     230: invokeinterface #132,  1          // InterfaceMethod java/util/Collection.isEmpty:()Z
     235: ifeq          334
     238: aload_0
     239: new           #42                 // class java/lang/StringBuilder
     242: dup
     243: invokespecial #43                 // Method java/lang/StringBuilder."<init>":()V
     246: ldc           #129                // String action.exception.stacktrace:
     248: invokevirtual #44                 // Method java/lang/StringBuilder.append:(Ljava/lang/String;)Ljava/lang/StringBuilder;
     251: aload         5
     253: ldc           #130                // String action.exception.stacktrace
     255: invokeinterface #127,  2          // InterfaceMethod java/util/Map.get:(Ljava/lang/Object;)Ljava/lang/Object;
     260: invokevirtual #82                 // Method java/lang/StringBuilder.append:(Ljava/lang/Object;)Ljava/lang/StringBuilder;
     263: invokevirtual #46                 // Method java/lang/StringBuilder.toString:()Ljava/lang/String;
     266: invokevirtual #87                 // Method debug:(Ljava/lang/String;)V
     269: aload         5
     271: ldc           #131                // String action.error.message
     273: invokeinterface #127,  2          // InterfaceMethod java/util/Map.get:(Ljava/lang/Object;)Ljava/lang/Object;
     278: checkcast     #33                 // class java/lang/String
     281: astore        7
     283: aload         7
     285: ifnonnull     301
     288: aload_0
     289: ldc           #133                // String resolvedFeatures was empty but the install kernel did not issue any messages
     291: invokevirtual #87                 // Method debug:(Ljava/lang/String;)V
     294: aload_0
     295: ldc           #134                // String The features are already installed, so no action is needed.
     297: invokevirtual #114                // Method info:(Ljava/lang/String;)V
     300: return
     301: aload         7
     303: ldc           #135                // String CWWKF1250I
     305: invokevirtual #136                // Method java/lang/String.contains:(Ljava/lang/CharSequence;)Z
     308: ifeq          324
     311: aload_0
     312: aload         7
     314: invokevirtual #114                // Method info:(Ljava/lang/String;)V
     317: aload_0
     318: ldc           #134                // String The features are already installed, so no action is needed.
     320: invokevirtual #114                // Method info:(Ljava/lang/String;)V
     323: return
     324: new           #50                 // class net/wasdev/wlp/common/plugins/util/PluginExecutionException
     327: dup
     328: aload         7
     330: invokespecial #70                 // Method net/wasdev/wlp/common/plugins/util/PluginExecutionException."<init>":(Ljava/lang/String;)V
     333: athrow
     334: aload_0
     335: aload         6
     337: invokespecial #137                // Method downloadEsas:(Ljava/util/Collection;)Ljava/util/List;
     340: astore        7
     342: new           #42                 // class java/lang/StringBuilder
     345: dup
     346: invokespecial #43                 // Method java/lang/StringBuilder."<init>":()V
     349: astore        8
     351: new           #54                 // class java/util/ArrayList
     354: dup
     355: invokespecial #55                 // Method java/util/ArrayList."<init>":()V
     358: astore        9
     360: aload         7
     362: invokeinterface #30,  1           // InterfaceMethod java/util/Collection.iterator:()Ljava/util/Iterator;
     367: astore        10
     369: aload         10
     371: invokeinterface #31,  1           // InterfaceMethod java/util/Iterator.hasNext:()Z
     376: ifeq          642
     379: aload         10
     381: invokeinterface #32,  1           // InterfaceMethod java/util/Iterator.next:()Ljava/lang/Object;
     386: checkcast     #5                  // class java/io/File
     389: astore        11
     391: aload         5
     393: ldc           #122                // String license.accept
     395: iload         4
     397: invokestatic  #118                // Method java/lang/Boolean.valueOf:(Z)Ljava/lang/Boolean;
     400: invokeinterface #119,  3          // InterfaceMethod java/util/Map.put:(Ljava/lang/Object;Ljava/lang/Object;)Ljava/lang/Object;
     405: pop
     406: aload         5
     408: ldc           #138                // String action.install
     410: aload         11
     412: invokeinterface #119,  3          // InterfaceMethod java/util/Map.put:(Ljava/lang/Object;Ljava/lang/Object;)Ljava/lang/Object;
     417: pop
     418: aload_0
     419: getfield      #4                  // Field to:Ljava/lang/String;
     422: ifnull        465
     425: aload         5
     427: ldc           #139                // String to.extension
     429: aload_0
     430: getfield      #4                  // Field to:Ljava/lang/String;
     433: invokeinterface #119,  3          // InterfaceMethod java/util/Map.put:(Ljava/lang/Object;Ljava/lang/Object;)Ljava/lang/Object;
     438: pop
     439: aload_0
     440: new           #42                 // class java/lang/StringBuilder
     443: dup
     444: invokespecial #43                 // Method java/lang/StringBuilder."<init>":()V
     447: ldc           #140                // String Installing to extension:
     449: invokevirtual #44                 // Method java/lang/StringBuilder.append:(Ljava/lang/String;)Ljava/lang/StringBuilder;
     452: aload_0
     453: getfield      #4                  // Field to:Ljava/lang/String;
     456: invokevirtual #44                 // Method java/lang/StringBuilder.append:(Ljava/lang/String;)Ljava/lang/StringBuilder;
     459: invokevirtual #46                 // Method java/lang/StringBuilder.toString:()Ljava/lang/String;
     462: invokevirtual #87                 // Method debug:(Ljava/lang/String;)V
     465: aload         5
     467: ldc           #126                // String action.result
     469: invokeinterface #127,  2          // InterfaceMethod java/util/Map.get:(Ljava/lang/Object;)Ljava/lang/Object;
     474: checkcast     #141                // class java/lang/Integer
     477: astore        12
     479: aload_0
     480: new           #42                 // class java/lang/StringBuilder
     483: dup
     484: invokespecial #43                 // Method java/lang/StringBuilder."<init>":()V
     487: ldc           #142                // String action.result:
     489: invokevirtual #44                 // Method java/lang/StringBuilder.append:(Ljava/lang/String;)Ljava/lang/StringBuilder;
     492: aload         12
     494: invokevirtual #82                 // Method java/lang/StringBuilder.append:(Ljava/lang/Object;)Ljava/lang/StringBuilder;
     497: invokevirtual #46                 // Method java/lang/StringBuilder.toString:()Ljava/lang/String;
     500: invokevirtual #87                 // Method debug:(Ljava/lang/String;)V
     503: aload_0
     504: new           #42                 // class java/lang/StringBuilder
     507: dup
     508: invokespecial #43                 // Method java/lang/StringBuilder."<init>":()V
     511: ldc           #143                // String action.error.message:
     513: invokevirtual #44                 // Method java/lang/StringBuilder.append:(Ljava/lang/String;)Ljava/lang/StringBuilder;
     516: aload         5
     518: ldc           #131                // String action.error.message
     520: invokeinterface #127,  2          // InterfaceMethod java/util/Map.get:(Ljava/lang/Object;)Ljava/lang/Object;
     525: invokevirtual #82                 // Method java/lang/StringBuilder.append:(Ljava/lang/Object;)Ljava/lang/StringBuilder;
     528: invokevirtual #46                 // Method java/lang/StringBuilder.toString:()Ljava/lang/String;
     531: invokevirtual #87                 // Method debug:(Ljava/lang/String;)V
     534: aload         5
     536: ldc           #131                // String action.error.message
     538: invokeinterface #127,  2          // InterfaceMethod java/util/Map.get:(Ljava/lang/Object;)Ljava/lang/Object;
     543: ifnull        607
     546: aload_0
     547: new           #42                 // class java/lang/StringBuilder
     550: dup
     551: invokespecial #43                 // Method java/lang/StringBuilder."<init>":()V
     554: ldc           #129                // String action.exception.stacktrace:
     556: invokevirtual #44                 // Method java/lang/StringBuilder.append:(Ljava/lang/String;)Ljava/lang/StringBuilder;
     559: aload         5
     561: ldc           #130                // String action.exception.stacktrace
     563: invokeinterface #127,  2          // InterfaceMethod java/util/Map.get:(Ljava/lang/Object;)Ljava/lang/Object;
     568: invokevirtual #82                 // Method java/lang/StringBuilder.append:(Ljava/lang/Object;)Ljava/lang/StringBuilder;
     571: invokevirtual #46                 // Method java/lang/StringBuilder.toString:()Ljava/lang/String;
     574: invokevirtual #87                 // Method debug:(Ljava/lang/String;)V
     577: aload         5
     579: ldc           #131                // String action.error.message
     581: invokeinterface #127,  2          // InterfaceMethod java/util/Map.get:(Ljava/lang/Object;)Ljava/lang/Object;
     586: checkcast     #33                 // class java/lang/String
     589: astore        13
     591: aload_0
     592: aload         13
     594: invokevirtual #87                 // Method debug:(Ljava/lang/String;)V
     597: new           #50                 // class net/wasdev/wlp/common/plugins/util/PluginExecutionException
     600: dup
     601: aload         13
     603: invokespecial #70                 // Method net/wasdev/wlp/common/plugins/util/PluginExecutionException."<init>":(Ljava/lang/String;)V
     606: athrow
     607: aload         5
     609: ldc           #144                // String action.install.result
     611: invokeinterface #127,  2          // InterfaceMethod java/util/Map.get:(Ljava/lang/Object;)Ljava/lang/Object;
     616: ifnull        639
     619: aload         9
     621: aload         5
     623: ldc           #144                // String action.install.result
     625: invokeinterface #127,  2          // InterfaceMethod java/util/Map.get:(Ljava/lang/Object;)Ljava/lang/Object;
     630: checkcast     #128                // class java/util/Collection
     633: invokeinterface #145,  2          // InterfaceMethod java/util/Collection.addAll:(Ljava/util/Collection;)Z
     638: pop
     639: goto          369
     642: aload         9
     644: invokeinterface #30,  1           // InterfaceMethod java/util/Collection.iterator:()Ljava/util/Iterator;
     649: astore        10
     651: aload         10
     653: invokeinterface #31,  1           // InterfaceMethod java/util/Iterator.hasNext:()Z
     658: ifeq          689
     661: aload         10
     663: invokeinterface #32,  1           // InterfaceMethod java/util/Iterator.next:()Ljava/lang/Object;
     668: checkcast     #33                 // class java/lang/String
     671: astore        11
     673: aload         8
     675: aload         11
     677: invokevirtual #44                 // Method java/lang/StringBuilder.append:(Ljava/lang/String;)Ljava/lang/StringBuilder;
     680: ldc           #146                // String
     682: invokevirtual #44                 // Method java/lang/StringBuilder.append:(Ljava/lang/String;)Ljava/lang/StringBuilder;
     685: pop
     686: goto          651
     689: aload_0
     690: invokespecial #147                // Method productInfoValidate:()V
     693: aload_0
     694: new           #42                 // class java/lang/StringBuilder
     697: dup
     698: invokespecial #43                 // Method java/lang/StringBuilder."<init>":()V
     701: ldc           #148                // String The following features have been installed:
     703: invokevirtual #44                 // Method java/lang/StringBuilder.append:(Ljava/lang/String;)Ljava/lang/StringBuilder;
     706: aload         8
     708: invokevirtual #46                 // Method java/lang/StringBuilder.toString:()Ljava/lang/String;
     711: invokevirtual #44                 // Method java/lang/StringBuilder.append:(Ljava/lang/String;)Ljava/lang/StringBuilder;
     714: invokevirtual #46                 // Method java/lang/StringBuilder.toString:()Ljava/lang/String;
     717: invokevirtual #114                // Method info:(Ljava/lang/String;)V
     720: goto          760
     723: astore        5
     725: new           #50                 // class net/wasdev/wlp/common/plugins/util/PluginExecutionException
     728: dup
     729: new           #42                 // class java/lang/StringBuilder
     732: dup
     733: invokespecial #43                 // Method java/lang/StringBuilder."<init>":()V
     736: ldc           #150                // String Could not load the jar
     738: invokevirtual #44                 // Method java/lang/StringBuilder.append:(Ljava/lang/String;)Ljava/lang/StringBuilder;
     741: aload_0
     742: getfield      #1                  // Field installJarFile:Ljava/io/File;
     745: invokevirtual #68                 // Method java/io/File.getAbsolutePath:()Ljava/lang/String;
     748: invokevirtual #44                 // Method java/lang/StringBuilder.append:(Ljava/lang/String;)Ljava/lang/StringBuilder;
     751: invokevirtual #46                 // Method java/lang/StringBuilder.toString:()Ljava/lang/String;
     754: aload         5
     756: invokespecial #79                 // Method net/wasdev/wlp/common/plugins/util/PluginExecutionException."<init>":(Ljava/lang/String;Ljava/lang/Throwable;)V
     759: athrow
     760: return
    Exception table:
       from    to  target type
          73   300   723   Class java/security/PrivilegedActionException
         301   323   723   Class java/security/PrivilegedActionException
         324   720   723   Class java/security/PrivilegedActionException

  private java.util.Map<java.lang.String, java.lang.Object> createMapBasedInstallKernelInstance(java.io.File) throws java.security.PrivilegedActionException, net.wasdev.wlp.common.plugins.util.PluginExecutionException;
    Code:
       0: new           #151                // class net/wasdev/wlp/common/plugins/util/InstallFeatureUtil$2
       3: dup
       4: aload_0
       5: invokespecial #152                // Method net/wasdev/wlp/common/plugins/util/InstallFeatureUtil$2."<init>":(Lnet/wasdev/wlp/common/plugins/util/InstallFeatureUtil;)V
       8: invokestatic  #153                // Method java/security/AccessController.doPrivileged:(Ljava/security/PrivilegedExceptionAction;)Ljava/lang/Object;
      11: checkcast     #154                // class java/util/Map
      14: astore_2
      15: aload_2
      16: ifnonnull     49
      19: new           #50                 // class net/wasdev/wlp/common/plugins/util/PluginExecutionException
      22: dup
      23: new           #42                 // class java/lang/StringBuilder
      26: dup
      27: invokespecial #43                 // Method java/lang/StringBuilder."<init>":()V
      30: ldc           #155                // String Cannot run install jar file
      32: invokevirtual #44                 // Method java/lang/StringBuilder.append:(Ljava/lang/String;)Ljava/lang/StringBuilder;
      35: aload_0
      36: getfield      #1                  // Field installJarFile:Ljava/io/File;
      39: invokevirtual #82                 // Method java/lang/StringBuilder.append:(Ljava/lang/Object;)Ljava/lang/StringBuilder;
      42: invokevirtual #46                 // Method java/lang/StringBuilder.toString:()Ljava/lang/String;
      45: invokespecial #70                 // Method net/wasdev/wlp/common/plugins/util/PluginExecutionException."<init>":(Ljava/lang/String;)V
      48: athrow
      49: aload_0
      50: ldc           #22                 // String io.openliberty.features
      52: ldc           #156                // String repository-resolver
      54: invokevirtual #157                // Method getOverrideBundleDescriptor:(Ljava/lang/String;Ljava/lang/String;)Ljava/lang/String;
      57: astore_3
      58: aload_3
      59: ifnull        114
      62: new           #54                 // class java/util/ArrayList
      65: dup
      66: invokespecial #55                 // Method java/util/ArrayList."<init>":()V
      69: astore        4
      71: aload         4
      73: aload_3
      74: invokeinterface #75,  2           // InterfaceMethod java/util/List.add:(Ljava/lang/Object;)Z
      79: pop
      80: aload_0
      81: new           #42                 // class java/lang/StringBuilder
      84: dup
      85: invokespecial #43                 // Method java/lang/StringBuilder."<init>":()V
      88: ldc           #158                // String Overriding jar using:
      90: invokevirtual #44                 // Method java/lang/StringBuilder.append:(Ljava/lang/String;)Ljava/lang/StringBuilder;
      93: aload_3
      94: invokevirtual #44                 // Method java/lang/StringBuilder.append:(Ljava/lang/String;)Ljava/lang/StringBuilder;
      97: invokevirtual #46                 // Method java/lang/StringBuilder.toString:()Ljava/lang/String;
     100: invokevirtual #87                 // Method debug:(Ljava/lang/String;)V
     103: aload_2
     104: ldc           #159                // String override.jar.bundles
     106: aload         4
     108: invokeinterface #119,  3          // InterfaceMethod java/util/Map.put:(Ljava/lang/Object;Ljava/lang/Object;)Ljava/lang/Object;
     113: pop
     114: aload_2
     115: ldc           #160                // String runtime.install.dir
     117: aload_1
     118: invokeinterface #119,  3          // InterfaceMethod java/util/Map.put:(Ljava/lang/Object;Ljava/lang/Object;)Ljava/lang/Object;
     123: pop
     124: aload_2
     125: ldc           #161                // String install.map.jar.file
     127: aload_0
     128: getfield      #1                  // Field installJarFile:Ljava/io/File;
     131: invokeinterface #119,  3          // InterfaceMethod java/util/Map.put:(Ljava/lang/Object;Ljava/lang/Object;)Ljava/lang/Object;
     136: pop
     137: aload_0
     138: new           #42                 // class java/lang/StringBuilder
     141: dup
     142: invokespecial #43                 // Method java/lang/StringBuilder."<init>":()V
     145: ldc           #162                // String install.map.jar.file:
     147: invokevirtual #44                 // Method java/lang/StringBuilder.append:(Ljava/lang/String;)Ljava/lang/StringBuilder;
     150: aload_0
     151: getfield      #1                  // Field installJarFile:Ljava/io/File;
     154: invokevirtual #82                 // Method java/lang/StringBuilder.append:(Ljava/lang/Object;)Ljava/lang/StringBuilder;
     157: invokevirtual #46                 // Method java/lang/StringBuilder.toString:()Ljava/lang/String;
     160: invokevirtual #87                 // Method debug:(Ljava/lang/String;)V
     163: goto          252
     166: astore        4
     168: aload_0
     169: ldc           #164                // String This version of the install map does not support the key \"install.map.jar.file\"
     171: aload         4
     173: invokevirtual #53                 // Method debug:(Ljava/lang/String;Ljava/lang/Throwable;)V
     176: new           #42                 // class java/lang/StringBuilder
     179: dup
     180: invokespecial #43                 // Method java/lang/StringBuilder."<init>":()V
     183: aload_0
     184: getfield      #1                  // Field installJarFile:Ljava/io/File;
     187: invokevirtual #165                // Method java/io/File.getParentFile:()Ljava/io/File;
     190: invokevirtual #166                // Method java/io/File.getName:()Ljava/lang/String;
     193: invokevirtual #44                 // Method java/lang/StringBuilder.append:(Ljava/lang/String;)Ljava/lang/StringBuilder;
     196: getstatic     #167                // Field java/io/File.separator:Ljava/lang/String;
     199: invokevirtual #44                 // Method java/lang/StringBuilder.append:(Ljava/lang/String;)Ljava/lang/StringBuilder;
     202: aload_0
     203: getfield      #1                  // Field installJarFile:Ljava/io/File;
     206: invokevirtual #166                // Method java/io/File.getName:()Ljava/lang/String;
     209: invokevirtual #44                 // Method java/lang/StringBuilder.append:(Ljava/lang/String;)Ljava/lang/StringBuilder;
     212: invokevirtual #46                 // Method java/lang/StringBuilder.toString:()Ljava/lang/String;
     215: astore        5
     217: aload_2
     218: ldc           #168                // String install.map.jar
     220: aload         5
     222: invokeinterface #119,  3          // InterfaceMethod java/util/Map.put:(Ljava/lang/Object;Ljava/lang/Object;)Ljava/lang/Object;
     227: pop
     228: aload_0
     229: new           #42                 // class java/lang/StringBuilder
     232: dup
     233: invokespecial #43                 // Method java/lang/StringBuilder."<init>":()V
     236: ldc           #169                // String install.map.jar:
     238: invokevirtual #44                 // Method java/lang/StringBuilder.append:(Ljava/lang/String;)Ljava/lang/StringBuilder;
     241: aload         5
     243: invokevirtual #44                 // Method java/lang/StringBuilder.append:(Ljava/lang/String;)Ljava/lang/StringBuilder;
     246: invokevirtual #46                 // Method java/lang/StringBuilder.toString:()Ljava/lang/String;
     249: invokevirtual #87                 // Method debug:(Ljava/lang/String;)V
     252: aload_0
     253: new           #42                 // class java/lang/StringBuilder
     256: dup
     257: invokespecial #43                 // Method java/lang/StringBuilder."<init>":()V
     260: ldc           #170                // String install.kernel.init.code:
     262: invokevirtual #44                 // Method java/lang/StringBuilder.append:(Ljava/lang/String;)Ljava/lang/StringBuilder;
     265: aload_2
     266: ldc           #171                // String install.kernel.init.code
     268: invokeinterface #127,  2          // InterfaceMethod java/util/Map.get:(Ljava/lang/Object;)Ljava/lang/Object;
     273: invokevirtual #82                 // Method java/lang/StringBuilder.append:(Ljava/lang/Object;)Ljava/lang/StringBuilder;
     276: invokevirtual #46                 // Method java/lang/StringBuilder.toString:()Ljava/lang/String;
     279: invokevirtual #87                 // Method debug:(Ljava/lang/String;)V
     282: aload_0
     283: new           #42                 // class java/lang/StringBuilder
     286: dup
     287: invokespecial #43                 // Method java/lang/StringBuilder."<init>":()V
     290: ldc           #172                // String install.kernel.init.error.message:
     292: invokevirtual #44                 // Method java/lang/StringBuilder.append:(Ljava/lang/String;)Ljava/lang/StringBuilder;
     295: aload_2
     296: ldc           #173                // String install.kernel.init.error.message
     298: invokeinterface #127,  2          // InterfaceMethod java/util/Map.get:(Ljava/lang/Object;)Ljava/lang/Object;
     303: invokevirtual #82                 // Method java/lang/StringBuilder.append:(Ljava/lang/Object;)Ljava/lang/StringBuilder;
     306: invokevirtual #46                 // Method java/lang/StringBuilder.toString:()Ljava/lang/String;
     309: invokevirtual #87                 // Method debug:(Ljava/lang/String;)V
     312: new           #5                  // class java/io/File
     315: dup
     316: aload_1
     317: ldc           #174                // String usr/tmp
     319: invokespecial #7                  // Method java/io/File."<init>":(Ljava/io/File;Ljava/lang/String;)V
     322: astore        4
     324: aload_2
     325: ldc           #175                // String target.user.directory
     327: aload         4
     329: invokeinterface #119,  3          // InterfaceMethod java/util/Map.put:(Ljava/lang/Object;Ljava/lang/Object;)Ljava/lang/Object;
     334: pop
     335: aload_2
     336: areturn
    Exception table:
       from    to  target type
         124   163   166   Class java/lang/RuntimeException

  public java.lang.String getOverrideBundleDescriptor(java.lang.String, java.lang.String) throws net.wasdev.wlp.common.plugins.util.PluginExecutionException;
    Code:
       0: aload_0
       1: aload_1
       2: aload_2
       3: invokespecial #24                 // Method downloadOverrideJar:(Ljava/lang/String;Ljava/lang/String;)Ljava/io/File;
       6: astore_3
       7: aload_3
       8: ifnull        57
      11: aload_3
      12: invokevirtual #25                 // Method java/io/File.exists:()Z
      15: ifeq          57
      18: aload_3
      19: invokestatic  #176                // Method extractSymbolicName:(Ljava/io/File;)Ljava/lang/String;
      22: astore        4
      24: aload         4
      26: ifnull        57
      29: new           #42                 // class java/lang/StringBuilder
      32: dup
      33: invokespecial #43                 // Method java/lang/StringBuilder."<init>":()V
      36: aload_3
      37: invokevirtual #68                 // Method java/io/File.getAbsolutePath:()Ljava/lang/String;
      40: invokevirtual #44                 // Method java/lang/StringBuilder.append:(Ljava/lang/String;)Ljava/lang/StringBuilder;
      43: ldc           #177                // String ;
      45: invokevirtual #44                 // Method java/lang/StringBuilder.append:(Ljava/lang/String;)Ljava/lang/StringBuilder;
      48: aload         4
      50: invokevirtual #44                 // Method java/lang/StringBuilder.append:(Ljava/lang/String;)Ljava/lang/StringBuilder;
      53: invokevirtual #46                 // Method java/lang/StringBuilder.toString:()Ljava/lang/String;
      56: areturn
      57: aconst_null
      58: areturn

  private java.io.File downloadOverrideJar(java.lang.String, java.lang.String);
    Code:
       0: aload_0
       1: aload_1
       2: aload_2
       3: ldc           #178                // String jar
       5: ldc           #179                // String [%s)
       7: iconst_1
       8: anewarray     #180                // class java/lang/Object
      11: dup
      12: iconst_0
      13: new           #42                 // class java/lang/StringBuilder
      16: dup
      17: invokespecial #43                 // Method java/lang/StringBuilder."<init>":()V
      20: aload_0
      21: getfield      #20                 // Field openLibertyVersion:Ljava/lang/String;
      24: invokevirtual #44                 // Method java/lang/StringBuilder.append:(Ljava/lang/String;)Ljava/lang/StringBuilder;
      27: ldc           #181                // String ,
      29: invokevirtual #44                 // Method java/lang/StringBuilder.append:(Ljava/lang/String;)Ljava/lang/StringBuilder;
      32: aload_0
      33: getfield      #20                 // Field openLibertyVersion:Ljava/lang/String;
      36: invokestatic  #182                // Method getNextProductVersion:(Ljava/lang/String;)Ljava/lang/String;
      39: invokevirtual #44                 // Method java/lang/StringBuilder.append:(Ljava/lang/String;)Ljava/lang/StringBuilder;
      42: invokevirtual #46                 // Method java/lang/StringBuilder.toString:()Ljava/lang/String;
      45: aastore
      46: invokestatic  #183                // Method java/lang/String.format:(Ljava/lang/String;[Ljava/lang/Object;)Ljava/lang/String;
      49: invokevirtual #49                 // Method downloadArtifact:(Ljava/lang/String;Ljava/lang/String;Ljava/lang/String;Ljava/lang/String;)Ljava/io/File;
      52: areturn
      53: astore_3
      54: aload_0
      55: new           #42                 // class java/lang/StringBuilder
      58: dup
      59: invokespecial #43                 // Method java/lang/StringBuilder."<init>":()V
      62: ldc           #184                // String Could not find override bundle
      64: invokevirtual #44                 // Method java/lang/StringBuilder.append:(Ljava/lang/String;)Ljava/lang/StringBuilder;
      67: aload_1
      68: invokevirtual #44                 // Method java/lang/StringBuilder.append:(Ljava/lang/String;)Ljava/lang/StringBuilder;
      71: ldc           #89                 // String :
      73: invokevirtual #44                 // Method java/lang/StringBuilder.append:(Ljava/lang/String;)Ljava/lang/StringBuilder;
      76: aload_2
      77: invokevirtual #44                 // Method java/lang/StringBuilder.append:(Ljava/lang/String;)Ljava/lang/StringBuilder;
      80: ldc           #185                // String  for the current Open Liberty version
      82: invokevirtual #44                 // Method java/lang/StringBuilder.append:(Ljava/lang/String;)Ljava/lang/StringBuilder;
      85: aload_0
      86: getfield      #20                 // Field openLibertyVersion:Ljava/lang/String;
      89: invokevirtual #44                 // Method java/lang/StringBuilder.append:(Ljava/lang/String;)Ljava/lang/StringBuilder;
      92: invokevirtual #46                 // Method java/lang/StringBuilder.toString:()Ljava/lang/String;
      95: aload_3
      96: invokevirtual #53                 // Method debug:(Ljava/lang/String;Ljava/lang/Throwable;)V
      99: aconst_null
     100: areturn
    Exception table:
       from    to  target type
           0    52    53   Class net/wasdev/wlp/common/plugins/util/PluginExecutionException

  public static java.lang.String getNextProductVersion(java.lang.String) throws net.wasdev.wlp.common.plugins.util.PluginExecutionException;
    Code:
       0: aconst_null
       1: astore_1
       2: aload_0
       3: ldc           #186                // String .
       5: invokevirtual #187                // Method java/lang/String.lastIndexOf:(Ljava/lang/String;)I
       8: iconst_1
       9: iadd
      10: istore_2
      11: iload_2
      12: ifne          47
      15: new           #50                 // class net/wasdev/wlp/common/plugins/util/PluginExecutionException
      18: dup
      19: new           #42                 // class java/lang/StringBuilder
      22: dup
      23: invokespecial #43                 // Method java/lang/StringBuilder."<init>":()V
      26: ldc           #188                // String Product version
      28: invokevirtual #44                 // Method java/lang/StringBuilder.append:(Ljava/lang/String;)Ljava/lang/StringBuilder;
      31: aload_0
      32: invokevirtual #44                 // Method java/lang/StringBuilder.append:(Ljava/lang/String;)Ljava/lang/StringBuilder;
      35: ldc           #189                // String  is not in the expected format. It must have period separated version segments.
      37: invokevirtual #44                 // Method java/lang/StringBuilder.append:(Ljava/lang/String;)Ljava/lang/StringBuilder;
      40: invokevirtual #46                 // Method java/lang/StringBuilder.toString:()Ljava/lang/String;
      43: invokespecial #70                 // Method net/wasdev/wlp/common/plugins/util/PluginExecutionException."<init>":(Ljava/lang/String;)V
      46: athrow
      47: aload_0
      48: iload_2
      49: invokevirtual #190                // Method java/lang/String.substring:(I)Ljava/lang/String;
      52: astore_3
      53: aload_3
      54: invokestatic  #191                // Method java/lang/Integer.parseInt:(Ljava/lang/String;)I
      57: iconst_1
      58: iadd
      59: istore        4
      61: goto          100
      64: astore        5
      66: new           #50                 // class net/wasdev/wlp/common/plugins/util/PluginExecutionException
      69: dup
      70: new           #42                 // class java/lang/StringBuilder
      73: dup
      74: invokespecial #43                 // Method java/lang/StringBuilder."<init>":()V
      77: ldc           #188                // String Product version
      79: invokevirtual #44                 // Method java/lang/StringBuilder.append:(Ljava/lang/String;)Ljava/lang/StringBuilder;
      82: aload_0
      83: invokevirtual #44                 // Method java/lang/StringBuilder.append:(Ljava/lang/String;)Ljava/lang/StringBuilder;
      86: ldc           #193                // String  is not in the expected format. Its last segment is expected to be an integer.
      88: invokevirtual #44                 // Method java/lang/StringBuilder.append:(Ljava/lang/String;)Ljava/lang/StringBuilder;
      91: invokevirtual #46                 // Method java/lang/StringBuilder.toString:()Ljava/lang/String;
      94: aload         5
      96: invokespecial #79                 // Method net/wasdev/wlp/common/plugins/util/PluginExecutionException."<init>":(Ljava/lang/String;Ljava/lang/Throwable;)V
      99: athrow
     100: new           #42                 // class java/lang/StringBuilder
     103: dup
     104: invokespecial #43                 // Method java/lang/StringBuilder."<init>":()V
     107: aload_0
     108: iconst_0
     109: iload_2
     110: invokevirtual #194                // Method java/lang/String.substring:(II)Ljava/lang/String;
     113: invokevirtual #44                 // Method java/lang/StringBuilder.append:(Ljava/lang/String;)Ljava/lang/StringBuilder;
     116: iload         4
     118: invokevirtual #195                // Method java/lang/StringBuilder.append:(I)Ljava/lang/StringBuilder;
     121: invokevirtual #46                 // Method java/lang/StringBuilder.toString:()Ljava/lang/String;
     124: astore_1
     125: aload_1
     126: areturn
    Exception table:
       from    to  target type
          53    61    64   Class java/lang/NumberFormatException

  public static java.lang.String extractSymbolicName(java.io.File) throws net.wasdev.wlp.common.plugins.util.PluginExecutionException;
    Code:
       0: aconst_null
       1: astore_1
       2: new           #196                // class java/util/jar/JarFile
       5: dup
       6: aload_0
       7: invokespecial #197                // Method java/util/jar/JarFile."<init>":(Ljava/io/File;)V
      10: astore_1
      11: aload_1
      12: invokevirtual #198                // Method java/util/jar/JarFile.getManifest:()Ljava/util/jar/Manifest;
      15: invokevirtual #199                // Method java/util/jar/Manifest.getMainAttributes:()Ljava/util/jar/Attributes;
      18: ldc           #200                // String Bundle-SymbolicName
      20: invokevirtual #201                // Method java/util/jar/Attributes.getValue:(Ljava/lang/String;)Ljava/lang/String;
      23: astore_2
      24: aload_1
      25: ifnull        36
      28: aload_1
      29: invokevirtual #202                // Method java/util/jar/JarFile.close:()V
      32: goto          36
      35: astore_3
      36: aload_2
      37: areturn
      38: astore_2
      39: new           #50                 // class net/wasdev/wlp/common/plugins/util/PluginExecutionException
      42: dup
      43: new           #42                 // class java/lang/StringBuilder
      46: dup
      47: invokespecial #43                 // Method java/lang/StringBuilder."<init>":()V
      50: ldc           #150                // String Could not load the jar
      52: invokevirtual #44                 // Method java/lang/StringBuilder.append:(Ljava/lang/String;)Ljava/lang/StringBuilder;
      55: aload_0
      56: invokevirtual #68                 // Method java/io/File.getAbsolutePath:()Ljava/lang/String;
      59: invokevirtual #44                 // Method java/lang/StringBuilder.append:(Ljava/lang/String;)Ljava/lang/StringBuilder;
      62: invokevirtual #46                 // Method java/lang/StringBuilder.toString:()Ljava/lang/String;
      65: aload_2
      66: invokespecial #79                 // Method net/wasdev/wlp/common/plugins/util/PluginExecutionException."<init>":(Ljava/lang/String;Ljava/lang/Throwable;)V
      69: athrow
      70: astore        4
      72: aload_1
      73: ifnull        85
      76: aload_1
      77: invokevirtual #202                // Method java/util/jar/JarFile.close:()V
      80: goto          85
      83: astore        5
      85: aload         4
      87: athrow
    Exception table:
       from    to  target type
          28    32    35   Class java/io/IOException
           2    24    38   Class java/io/IOException
           2    24    70   any
          76    80    83   Class java/io/IOException
          38    72    70   any

  public static java.io.File getMapBasedInstallKernelJar(java.io.File);
    Code:
       0: aload_0
       1: new           #203                // class net/wasdev/wlp/common/plugins/util/InstallFeatureUtil$3
       4: dup
       5: invokespecial #204                // Method net/wasdev/wlp/common/plugins/util/InstallFeatureUtil$3."<init>":()V
       8: invokevirtual #58                 // Method java/io/File.listFiles:(Ljava/io/FilenameFilter;)[Ljava/io/File;
      11: astore_1
      12: aconst_null
      13: astore_2
      14: aload_1
      15: ifnull        58
      18: aload_1
      19: astore_3
      20: aload_3
      21: arraylength
      22: istore        4
      24: iconst_0
      25: istore        5
      27: iload         5
      29: iload         4
      31: if_icmpge     58
      34: aload_3
      35: iload         5
      37: aaload
      38: astore        6
      40: aload_2
      41: aload         6
      43: invokestatic  #205                // Method isReplacementJar:(Ljava/io/File;Ljava/io/File;)Z
      46: ifeq          52
      49: aload         6
      51: astore_2
      52: iinc          5, 1
      55: goto          27
      58: aload_2
      59: areturn

  private static boolean isReplacementJar(java.io.File, java.io.File);
    Code:
       0: aload_0
       1: ifnonnull     6
       4: iconst_1
       5: ireturn
       6: aload_1
       7: ifnonnull     12
      10: iconst_0
      11: ireturn
      12: aload_0
      13: invokevirtual #166                // Method java/io/File.getName:()Ljava/lang/String;
      16: invokestatic  #206                // Method extractVersion:(Ljava/lang/String;)Ljava/lang/String;
      19: astore_2
      20: aload_1
      21: invokevirtual #166                // Method java/io/File.getName:()Ljava/lang/String;
      24: invokestatic  #206                // Method extractVersion:(Ljava/lang/String;)Ljava/lang/String;
      27: astore_3
      28: aload_2
      29: aload_3
      30: invokestatic  #207                // Method compare:(Ljava/lang/String;Ljava/lang/String;)I
      33: ifge          40
      36: iconst_1
      37: goto          41
      40: iconst_0
      41: ireturn

  private static java.lang.String extractVersion(java.lang.String);
    Code:
       0: ldc           #208                // String com.ibm.ws.install.map
       2: invokevirtual #209                // Method java/lang/String.length:()I
       5: iconst_1
       6: iadd
       7: istore_1
       8: aload_0
       9: ldc           #210                // String .jar
      11: invokevirtual #187                // Method java/lang/String.lastIndexOf:(Ljava/lang/String;)I
      14: istore_2
      15: iload_1
      16: iload_2
      17: if_icmpge     27
      20: aload_0
      21: iload_1
      22: iload_2
      23: invokevirtual #194                // Method java/lang/String.substring:(II)Ljava/lang/String;
      26: areturn
      27: aconst_null
      28: areturn

  private static int compare(java.lang.String, java.lang.String);
    Code:
       0: aload_0
       1: ifnonnull     10
       4: aload_1
       5: ifnonnull     10
       8: iconst_0
       9: ireturn
      10: aload_0
      11: ifnonnull     20
      14: aload_1
      15: ifnull        20
      18: iconst_m1
      19: ireturn
      20: aload_0
      21: ifnull        30
      24: aload_1
      25: ifnonnull     30
      28: iconst_1
      29: ireturn
      30: aload_0
      31: ldc           #211                // String \\.
      33: invokevirtual #90                 // Method java/lang/String.split:(Ljava/lang/String;)[Ljava/lang/String;
      36: astore_2
      37: aload_1
      38: ldc           #211                // String \\.
      40: invokevirtual #90                 // Method java/lang/String.split:(Ljava/lang/String;)[Ljava/lang/String;
      43: astore_3
      44: iconst_0
      45: istore        4
      47: iload         4
      49: aload_2
      50: arraylength
      51: if_icmpge     120
      54: iload         4
      56: aload_3
      57: arraylength
      58: if_icmpge     120
      61: new           #141                // class java/lang/Integer
      64: dup
      65: aload_2
      66: iload         4
      68: aaload
      69: invokespecial #212                // Method java/lang/Integer."<init>":(Ljava/lang/String;)V
      72: new           #141                // class java/lang/Integer
      75: dup
      76: aload_3
      77: iload         4
      79: aaload
      80: invokespecial #212                // Method java/lang/Integer."<init>":(Ljava/lang/String;)V
      83: invokevirtual #213                // Method java/lang/Integer.compareTo:(Ljava/lang/Integer;)I
      86: istore        5
      88: goto          106
      91: astore        6
      93: aload_2
      94: iload         4
      96: aaload
      97: aload_3
      98: iload         4
     100: aaload
     101: invokevirtual #214                // Method java/lang/String.compareTo:(Ljava/lang/String;)I
     104: istore        5
     106: iload         5
     108: ifeq          114
     111: iload         5
     113: ireturn
     114: iinc          4, 1
     117: goto          47
     120: aload_2
     121: arraylength
     122: aload_3
     123: arraylength
     124: isub
     125: ireturn
    Exception table:
       from    to  target type
          61    88    91   Class java/lang/NumberFormatException

  private void productInfoValidate() throws net.wasdev.wlp.common.plugins.util.PluginExecutionException;
    Code:
       0: aload_0
       1: getfield      #3                  // Field installDirectory:Ljava/io/File;
       4: ldc           #215                // String validate
       6: invokestatic  #216                // Method productInfo:(Ljava/io/File;Ljava/lang/String;)Ljava/lang/String;
       9: astore_1
      10: aload_1
      11: ifnonnull     24
      14: new           #50                 // class net/wasdev/wlp/common/plugins/util/PluginExecutionException
      17: dup
      18: ldc           #217                // String Could not perform product validation. The productInfo command returned with no output
      20: invokespecial #70                 // Method net/wasdev/wlp/common/plugins/util/PluginExecutionException."<init>":(Ljava/lang/String;)V
      23: athrow
      24: aload_1
      25: ldc           #218                // String [ERROR]
      27: invokevirtual #136                // Method java/lang/String.contains:(Ljava/lang/CharSequence;)Z
      30: ifeq          42
      33: new           #50                 // class net/wasdev/wlp/common/plugins/util/PluginExecutionException
      36: dup
      37: aload_1
      38: invokespecial #70                 // Method net/wasdev/wlp/common/plugins/util/PluginExecutionException."<init>":(Ljava/lang/String;)V
      41: athrow
      42: aload_0
      43: ldc           #219                // String Product validation completed successfully.
      45: invokevirtual #114                // Method info:(Ljava/lang/String;)V
      48: return

  public static java.lang.String productInfo(java.io.File, java.lang.String) throws net.wasdev.wlp.common.plugins.util.PluginExecutionException;
    Code:
       0: aconst_null
       1: astore_2
       2: aconst_null
       3: astore_3
       4: aconst_null
       5: astore        4
       7: aconst_null
       8: astore        5
      10: invokestatic  #220                // Method net/wasdev/wlp/common/plugins/util/OSUtil.isWindows:()Z
      13: ifeq          44
      16: new           #42                 // class java/lang/StringBuilder
      19: dup
      20: invokespecial #43                 // Method java/lang/StringBuilder."<init>":()V
      23: aload_0
      24: invokevirtual #82                 // Method java/lang/StringBuilder.append:(Ljava/lang/Object;)Ljava/lang/StringBuilder;
      27: ldc           #221                // String \\bin\\productInfo.bat
      29: invokevirtual #44                 // Method java/lang/StringBuilder.append:(Ljava/lang/String;)Ljava/lang/StringBuilder;
      32: aload_1
      33: invokevirtual #44                 // Method java/lang/StringBuilder.append:(Ljava/lang/String;)Ljava/lang/StringBuilder;
      36: invokevirtual #46                 // Method java/lang/StringBuilder.toString:()Ljava/lang/String;
      39: astore        6
      41: goto          69
      44: new           #42                 // class java/lang/StringBuilder
      47: dup
      48: invokespecial #43                 // Method java/lang/StringBuilder."<init>":()V
      51: aload_0
      52: invokevirtual #82                 // Method java/lang/StringBuilder.append:(Ljava/lang/Object;)Ljava/lang/StringBuilder;
      55: ldc           #222                // String /bin/productInfo
      57: invokevirtual #44                 // Method java/lang/StringBuilder.append:(Ljava/lang/String;)Ljava/lang/StringBuilder;
      60: aload_1
      61: invokevirtual #44                 // Method java/lang/StringBuilder.append:(Ljava/lang/String;)Ljava/lang/StringBuilder;
      64: invokevirtual #46                 // Method java/lang/StringBuilder.toString:()Ljava/lang/String;
      67: astore        6
      69: invokestatic  #223                // Method java/lang/Runtime.getRuntime:()Ljava/lang/Runtime;
      72: aload         6
      74: invokevirtual #224                // Method java/lang/Runtime.exec:(Ljava/lang/String;)Ljava/lang/Process;
      77: astore_2
      78: new           #225                // class net/wasdev/wlp/common/plugins/util/InstallFeatureUtil$Worker
      81: dup
      82: aload_2
      83: aconst_null
      84: invokespecial #226                // Method net/wasdev/wlp/common/plugins/util/InstallFeatureUtil$Worker."<init>":(Ljava/lang/Process;Lnet/wasdev/wlp/common/plugins/util/InstallFeatureUtil$1;)V
      87: astore        5
      89: aload         5
      91: invokevirtual #227                // Method net/wasdev/wlp/common/plugins/util/InstallFeatureUtil$Worker.start:()V
      94: aload         5
      96: ldc2_w        #228                // long 300000l
      99: invokevirtual #230                // Method net/wasdev/wlp/common/plugins/util/InstallFeatureUtil$Worker.join:(J)V
     102: aload         5
     104: invokestatic  #231                // Method net/wasdev/wlp/common/plugins/util/InstallFeatureUtil$Worker.access$200:(Lnet/wasdev/wlp/common/plugins/util/InstallFeatureUtil$Worker;)Ljava/lang/Integer;
     107: ifnonnull     120
     110: new           #50                 // class net/wasdev/wlp/common/plugins/util/PluginExecutionException
     113: dup
     114: ldc           #232                // String productInfo command timed out
     116: invokespecial #70                 // Method net/wasdev/wlp/common/plugins/util/PluginExecutionException."<init>":(Ljava/lang/String;)V
     119: athrow
     120: aload_2
     121: invokevirtual #233                // Method java/lang/Process.exitValue:()I
     124: istore        7
     126: iload         7
     128: ifeq          159
     131: new           #50                 // class net/wasdev/wlp/common/plugins/util/PluginExecutionException
     134: dup
     135: new           #42                 // class java/lang/StringBuilder
     138: dup
     139: invokespecial #43                 // Method java/lang/StringBuilder."<init>":()V
     142: ldc           #234                // String productInfo exited with return code
     144: invokevirtual #44                 // Method java/lang/StringBuilder.append:(Ljava/lang/String;)Ljava/lang/StringBuilder;
     147: iload         7
     149: invokevirtual #195                // Method java/lang/StringBuilder.append:(I)Ljava/lang/StringBuilder;
     152: invokevirtual #46                 // Method java/lang/StringBuilder.toString:()Ljava/lang/String;
     155: invokespecial #70                 // Method net/wasdev/wlp/common/plugins/util/PluginExecutionException."<init>":(Ljava/lang/String;)V
     158: athrow
     159: aload_2
     160: invokevirtual #235                // Method java/lang/Process.getInputStream:()Ljava/io/InputStream;
     163: astore_3
     164: new           #94                 // class java/util/Scanner
     167: dup
     168: aload_3
     169: invokespecial #236                // Method java/util/Scanner."<init>":(Ljava/io/InputStream;)V
     172: astore        4
     174: aload         4
     176: ldc           #237                // String \\A
     178: invokevirtual #238                // Method java/util/Scanner.useDelimiter:(Ljava/lang/String;)Ljava/util/Scanner;
     181: pop
     182: aload         4
     184: invokevirtual #239                // Method java/util/Scanner.hasNext:()Z
     187: ifeq          231
     190: aload         4
     192: invokevirtual #240                // Method java/util/Scanner.next:()Ljava/lang/String;
     195: astore        8
     197: aload         4
     199: ifnull        207
     202: aload         4
     204: invokevirtual #101                // Method java/util/Scanner.close:()V
     207: aload_3
     208: ifnull        220
     211: aload_3
     212: invokevirtual #76                 // Method java/io/InputStream.close:()V
     215: goto          220
     218: astore        9
     220: aload_2
     221: ifnull        228
     224: aload_2
     225: invokevirtual #241                // Method java/lang/Process.destroy:()V
     228: aload         8
     230: areturn
     231: aconst_null
     232: astore        8
     234: aload         4
     236: ifnull        244
     239: aload         4
     241: invokevirtual #101                // Method java/util/Scanner.close:()V
     244: aload_3
     245: ifnull        257
     248: aload_3
     249: invokevirtual #76                 // Method java/io/InputStream.close:()V
     252: goto          257
     255: astore        9
     257: aload_2
     258: ifnull        265
     261: aload_2
     262: invokevirtual #241                // Method java/lang/Process.destroy:()V
     265: aload         8
     267: areturn
     268: astore        6
     270: new           #50                 // class net/wasdev/wlp/common/plugins/util/PluginExecutionException
     273: dup
     274: new           #42                 // class java/lang/StringBuilder
     277: dup
     278: invokespecial #43                 // Method java/lang/StringBuilder."<init>":()V
     281: ldc           #242                // String productInfo error:
     283: invokevirtual #44                 // Method java/lang/StringBuilder.append:(Ljava/lang/String;)Ljava/lang/StringBuilder;
     286: aload         6
     288: invokevirtual #82                 // Method java/lang/StringBuilder.append:(Ljava/lang/Object;)Ljava/lang/StringBuilder;
     291: invokevirtual #46                 // Method java/lang/StringBuilder.toString:()Ljava/lang/String;
     294: invokespecial #70                 // Method net/wasdev/wlp/common/plugins/util/PluginExecutionException."<init>":(Ljava/lang/String;)V
     297: athrow
     298: astore        6
     300: aload         5
     302: invokevirtual #244                // Method net/wasdev/wlp/common/plugins/util/InstallFeatureUtil$Worker.interrupt:()V
     305: invokestatic  #245                // Method java/lang/Thread.currentThread:()Ljava/lang/Thread;
     308: invokevirtual #246                // Method java/lang/Thread.interrupt:()V
     311: new           #50                 // class net/wasdev/wlp/common/plugins/util/PluginExecutionException
     314: dup
     315: new           #42                 // class java/lang/StringBuilder
     318: dup
     319: invokespecial #43                 // Method java/lang/StringBuilder."<init>":()V
     322: ldc           #242                // String productInfo error:
     324: invokevirtual #44                 // Method java/lang/StringBuilder.append:(Ljava/lang/String;)Ljava/lang/StringBuilder;
     327: aload         6
     329: invokevirtual #82                 // Method java/lang/StringBuilder.append:(Ljava/lang/Object;)Ljava/lang/StringBuilder;
     332: invokevirtual #46                 // Method java/lang/StringBuilder.toString:()Ljava/lang/String;
     335: invokespecial #70                 // Method net/wasdev/wlp/common/plugins/util/PluginExecutionException."<init>":(Ljava/lang/String;)V
     338: athrow
     339: astore        10
     341: aload         4
     343: ifnull        351
     346: aload         4
     348: invokevirtual #101                // Method java/util/Scanner.close:()V
     351: aload_3
     352: ifnull        364
     355: aload_3
     356: invokevirtual #76                 // Method java/io/InputStream.close:()V
     359: goto          364
     362: astore        11
     364: aload_2
     365: ifnull        372
     368: aload_2
     369: invokevirtual #241                // Method java/lang/Process.destroy:()V
     372: aload         10
     374: athrow
    Exception table:
       from    to  target type
         211   215   218   Class java/io/IOException
         248   252   255   Class java/io/IOException
          10   197   268   Class java/io/IOException
         231   234   268   Class java/io/IOException
          10   197   298   Class java/lang/InterruptedException
         231   234   298   Class java/lang/InterruptedException
          10   197   339   any
         231   234   339   any
         355   359   362   Class java/io/IOException
         268   341   339   any

  static java.io.File access$000(net.wasdev.wlp.common.plugins.util.InstallFeatureUtil);
    Code:
       0: aload_0
       1: getfield      #1                  // Field installJarFile:Ljava/io/File;
       4: areturn
}
