Compiled from "ServerProperties.java"
public class org.springframework.boot.autoconfigure.web.ServerProperties$Session {
  private java.lang.Integer timeout;

  private java.util.Set<javax.servlet.SessionTrackingMode> trackingModes;

  private boolean persistent;

  private java.io.File storeDir;

  private org.springframework.boot.autoconfigure.web.ServerProperties$Session$Cookie cookie;

  public org.springframework.boot.autoconfigure.web.ServerProperties$Session();
    Code:
       0: aload_0
       1: invokespecial #1                  // Method java/lang/Object."<init>":()V
       4: aload_0
       5: new           #2                  // class org/springframework/boot/autoconfigure/web/ServerProperties$Session$Cookie
       8: dup
       9: invokespecial #3                  // Method org/springframework/boot/autoconfigure/web/ServerProperties$Session$Cookie."<init>":()V
      12: putfield      #4                  // Field cookie:Lorg/springframework/boot/autoconfigure/web/ServerProperties$Session$Cookie;
      15: return

  public org.springframework.boot.autoconfigure.web.ServerProperties$Session$Cookie getCookie();
    Code:
       0: aload_0
       1: getfield      #4                  // Field cookie:Lorg/springframework/boot/autoconfigure/web/ServerProperties$Session$Cookie;
       4: areturn

  public java.lang.Integer getTimeout();
    Code:
       0: aload_0
       1: getfield      #5                  // Field timeout:Ljava/lang/Integer;
       4: areturn

  public void setTimeout(java.lang.Integer);
    Code:
       0: aload_0
       1: aload_1
       2: putfield      #5                  // Field timeout:Ljava/lang/Integer;
       5: return

  public java.util.Set<javax.servlet.SessionTrackingMode> getTrackingModes();
    Code:
       0: aload_0
       1: getfield      #6                  // Field trackingModes:Ljava/util/Set;
       4: areturn

  public void setTrackingModes(java.util.Set<javax.servlet.SessionTrackingMode>);
    Code:
       0: aload_0
       1: aload_1
       2: putfield      #6                  // Field trackingModes:Ljava/util/Set;
       5: return

  public boolean isPersistent();
    Code:
       0: aload_0
       1: getfield      #7                  // Field persistent:Z
       4: ireturn

  public void setPersistent(boolean);
    Code:
       0: aload_0
       1: iload_1
       2: putfield      #7                  // Field persistent:Z
       5: return

  public java.io.File getStoreDir();
    Code:
       0: aload_0
       1: getfield      #8                  // Field storeDir:Ljava/io/File;
       4: areturn

  public void setStoreDir(java.io.File);
    Code:
       0: aload_0
       1: aload_1
       2: putfield      #8                  // Field storeDir:Ljava/io/File;
       5: return
}
