Compiled from "OAuthError.kt"
public final class org.http4k.security.oauth.server.RfcError extends java.lang.Enum<org.http4k.security.oauth.server.RfcError> {
  public static final org.http4k.security.oauth.server.RfcError AccessDenied;

  public static final org.http4k.security.oauth.server.RfcError InvalidClient;

  public static final org.http4k.security.oauth.server.RfcError InvalidRequest;

  public static final org.http4k.security.oauth.server.RfcError InvalidRequestObject;

  public static final org.http4k.security.oauth.server.RfcError InvalidGrant;

  public static final org.http4k.security.oauth.server.RfcError InvalidScope;

  public static final org.http4k.security.oauth.server.RfcError UnsupportedGrantType;

  public static final org.http4k.security.oauth.server.RfcError UnsupportedResponseType;

  private static final org.http4k.security.oauth.server.RfcError[] $VALUES;

  private org.http4k.security.oauth.server.RfcError();
    Code:
       0: aload_0
       1: aload_1
       2: iload_2
       3: invokespecial #10                 // Method java/lang/Enum."<init>":(Ljava/lang/String;I)V
       6: return

  public final java.lang.String getRfcValue();
    Code:
       0: aload_0
       1: getstatic     #25                 // Field org/http4k/security/oauth/server/RfcError$WhenMappings.$EnumSwitchMapping$0:[I
       4: swap
       5: invokevirtual #29                 // Method ordinal:()I
       8: iaload
       9: tableswitch   { // 1 to 8
                     1: 56
                     2: 61
                     3: 66
                     4: 71
                     5: 76
                     6: 81
                     7: 86
                     8: 91
               default: 96
          }
      56: ldc           #31                 // String invalid_client
      58: goto          104
      61: ldc           #33                 // String invalid_grant
      63: goto          104
      66: ldc           #35                 // String invalid_scope
      68: goto          104
      71: ldc           #37                 // String unsupported_grant_type
      73: goto          104
      76: ldc           #39                 // String unsupported_response_type
      78: goto          104
      81: ldc           #41                 // String access_denied
      83: goto          104
      86: ldc           #43                 // String invalid_request
      88: goto          104
      91: ldc           #45                 // String invalid_request_object
      93: goto          104
      96: new           #47                 // class kotlin/NoWhenBranchMatchedException
      99: dup
     100: invokespecial #49                 // Method kotlin/NoWhenBranchMatchedException."<init>":()V
     103: athrow
     104: areturn

  public static org.http4k.security.oauth.server.RfcError[] values();
    Code:
       0: getstatic     #57                 // Field $VALUES:[Lorg/http4k/security/oauth/server/RfcError;
       3: invokevirtual #63                 // Method "[Ljava/lang/Object;".clone:()Ljava/lang/Object;
       6: checkcast     #64                 // class "[Lorg/http4k/security/oauth/server/RfcError;"
       9: areturn

  public static org.http4k.security.oauth.server.RfcError valueOf(java.lang.String);
    Code:
       0: ldc           #2                  // class org/http4k/security/oauth/server/RfcError
       2: aload_0
       3: invokestatic  #69                 // Method java/lang/Enum.valueOf:(Ljava/lang/Class;Ljava/lang/String;)Ljava/lang/Enum;
       6: checkcast     #2                  // class org/http4k/security/oauth/server/RfcError
       9: areturn

  private static final org.http4k.security.oauth.server.RfcError[] $values();
    Code:
       0: bipush        8
       2: anewarray     #2                  // class org/http4k/security/oauth/server/RfcError
       5: astore_0
       6: aload_0
       7: iconst_0
       8: getstatic     #74                 // Field AccessDenied:Lorg/http4k/security/oauth/server/RfcError;
      11: aastore
      12: aload_0
      13: iconst_1
      14: getstatic     #77                 // Field InvalidClient:Lorg/http4k/security/oauth/server/RfcError;
      17: aastore
      18: aload_0
      19: iconst_2
      20: getstatic     #80                 // Field InvalidRequest:Lorg/http4k/security/oauth/server/RfcError;
      23: aastore
      24: aload_0
      25: iconst_3
      26: getstatic     #83                 // Field InvalidRequestObject:Lorg/http4k/security/oauth/server/RfcError;
      29: aastore
      30: aload_0
      31: iconst_4
      32: getstatic     #86                 // Field InvalidGrant:Lorg/http4k/security/oauth/server/RfcError;
      35: aastore
      36: aload_0
      37: iconst_5
      38: getstatic     #89                 // Field InvalidScope:Lorg/http4k/security/oauth/server/RfcError;
      41: aastore
      42: aload_0
      43: bipush        6
      45: getstatic     #92                 // Field UnsupportedGrantType:Lorg/http4k/security/oauth/server/RfcError;
      48: aastore
      49: aload_0
      50: bipush        7
      52: getstatic     #95                 // Field UnsupportedResponseType:Lorg/http4k/security/oauth/server/RfcError;
      55: aastore
      56: aload_0
      57: areturn

  static {};
    Code:
       0: new           #2                  // class org/http4k/security/oauth/server/RfcError
       3: dup
       4: ldc           #97                 // String AccessDenied
       6: iconst_0
       7: invokespecial #98                 // Method "<init>":(Ljava/lang/String;I)V
      10: putstatic     #74                 // Field AccessDenied:Lorg/http4k/security/oauth/server/RfcError;
      13: new           #2                  // class org/http4k/security/oauth/server/RfcError
      16: dup
      17: ldc           #99                 // String InvalidClient
      19: iconst_1
      20: invokespecial #98                 // Method "<init>":(Ljava/lang/String;I)V
      23: putstatic     #77                 // Field InvalidClient:Lorg/http4k/security/oauth/server/RfcError;
      26: new           #2                  // class org/http4k/security/oauth/server/RfcError
      29: dup
      30: ldc           #100                // String InvalidRequest
      32: iconst_2
      33: invokespecial #98                 // Method "<init>":(Ljava/lang/String;I)V
      36: putstatic     #80                 // Field InvalidRequest:Lorg/http4k/security/oauth/server/RfcError;
      39: new           #2                  // class org/http4k/security/oauth/server/RfcError
      42: dup
      43: ldc           #101                // String InvalidRequestObject
      45: iconst_3
      46: invokespecial #98                 // Method "<init>":(Ljava/lang/String;I)V
      49: putstatic     #83                 // Field InvalidRequestObject:Lorg/http4k/security/oauth/server/RfcError;
      52: new           #2                  // class org/http4k/security/oauth/server/RfcError
      55: dup
      56: ldc           #102                // String InvalidGrant
      58: iconst_4
      59: invokespecial #98                 // Method "<init>":(Ljava/lang/String;I)V
      62: putstatic     #86                 // Field InvalidGrant:Lorg/http4k/security/oauth/server/RfcError;
      65: new           #2                  // class org/http4k/security/oauth/server/RfcError
      68: dup
      69: ldc           #103                // String InvalidScope
      71: iconst_5
      72: invokespecial #98                 // Method "<init>":(Ljava/lang/String;I)V
      75: putstatic     #89                 // Field InvalidScope:Lorg/http4k/security/oauth/server/RfcError;
      78: new           #2                  // class org/http4k/security/oauth/server/RfcError
      81: dup
      82: ldc           #104                // String UnsupportedGrantType
      84: bipush        6
      86: invokespecial #98                 // Method "<init>":(Ljava/lang/String;I)V
      89: putstatic     #92                 // Field UnsupportedGrantType:Lorg/http4k/security/oauth/server/RfcError;
      92: new           #2                  // class org/http4k/security/oauth/server/RfcError
      95: dup
      96: ldc           #105                // String UnsupportedResponseType
      98: bipush        7
     100: invokespecial #98                 // Method "<init>":(Ljava/lang/String;I)V
     103: putstatic     #95                 // Field UnsupportedResponseType:Lorg/http4k/security/oauth/server/RfcError;
     106: invokestatic  #107                // Method $values:()[Lorg/http4k/security/oauth/server/RfcError;
     109: putstatic     #57                 // Field $VALUES:[Lorg/http4k/security/oauth/server/RfcError;
     112: return
}
