Compiled from "PriorityClassBuilder.java"
public class io.dekorate.deps.kubernetes.api.model.scheduling.PriorityClassBuilder extends io.dekorate.deps.kubernetes.api.model.scheduling.PriorityClassFluentImpl<io.dekorate.deps.kubernetes.api.model.scheduling.PriorityClassBuilder> implements io.dekorate.deps.kubernetes.api.builder.VisitableBuilder<io.dekorate.deps.kubernetes.api.model.scheduling.PriorityClass, io.dekorate.deps.kubernetes.api.model.scheduling.PriorityClassBuilder> {
  io.dekorate.deps.kubernetes.api.model.scheduling.PriorityClassFluent<?> fluent;

  java.lang.Boolean validationEnabled;

  public io.dekorate.deps.kubernetes.api.model.scheduling.PriorityClassBuilder();
    Code:
       0: aload_0
       1: iconst_1
       2: invokestatic  #21                 // Method java/lang/Boolean.valueOf:(Z)Ljava/lang/Boolean;
       5: invokespecial #24                 // Method "<init>":(Ljava/lang/Boolean;)V
       8: return

  public io.dekorate.deps.kubernetes.api.model.scheduling.PriorityClassBuilder(java.lang.Boolean);
    Code:
       0: aload_0
       1: new           #28                 // class io/dekorate/deps/kubernetes/api/model/scheduling/PriorityClass
       4: dup
       5: invokespecial #30                 // Method io/dekorate/deps/kubernetes/api/model/scheduling/PriorityClass."<init>":()V
       8: aload_1
       9: invokespecial #33                 // Method "<init>":(Lio/dekorate/deps/kubernetes/api/model/scheduling/PriorityClass;Ljava/lang/Boolean;)V
      12: return

  public io.dekorate.deps.kubernetes.api.model.scheduling.PriorityClassBuilder(io.dekorate.deps.kubernetes.api.model.scheduling.PriorityClassFluent<?>);
    Code:
       0: aload_0
       1: aload_1
       2: iconst_1
       3: invokestatic  #21                 // Method java/lang/Boolean.valueOf:(Z)Ljava/lang/Boolean;
       6: invokespecial #38                 // Method "<init>":(Lio/dekorate/deps/kubernetes/api/model/scheduling/PriorityClassFluent;Ljava/lang/Boolean;)V
       9: return

  public io.dekorate.deps.kubernetes.api.model.scheduling.PriorityClassBuilder(io.dekorate.deps.kubernetes.api.model.scheduling.PriorityClassFluent<?>, java.lang.Boolean);
    Code:
       0: aload_0
       1: aload_1
       2: new           #28                 // class io/dekorate/deps/kubernetes/api/model/scheduling/PriorityClass
       5: dup
       6: invokespecial #30                 // Method io/dekorate/deps/kubernetes/api/model/scheduling/PriorityClass."<init>":()V
       9: aload_2
      10: invokespecial #42                 // Method "<init>":(Lio/dekorate/deps/kubernetes/api/model/scheduling/PriorityClassFluent;Lio/dekorate/deps/kubernetes/api/model/scheduling/PriorityClass;Ljava/lang/Boolean;)V
      13: return

  public io.dekorate.deps.kubernetes.api.model.scheduling.PriorityClassBuilder(io.dekorate.deps.kubernetes.api.model.scheduling.PriorityClassFluent<?>, io.dekorate.deps.kubernetes.api.model.scheduling.PriorityClass);
    Code:
       0: aload_0
       1: aload_1
       2: aload_2
       3: iconst_1
       4: invokestatic  #21                 // Method java/lang/Boolean.valueOf:(Z)Ljava/lang/Boolean;
       7: invokespecial #42                 // Method "<init>":(Lio/dekorate/deps/kubernetes/api/model/scheduling/PriorityClassFluent;Lio/dekorate/deps/kubernetes/api/model/scheduling/PriorityClass;Ljava/lang/Boolean;)V
      10: return

  public io.dekorate.deps.kubernetes.api.model.scheduling.PriorityClassBuilder(io.dekorate.deps.kubernetes.api.model.scheduling.PriorityClassFluent<?>, io.dekorate.deps.kubernetes.api.model.scheduling.PriorityClass, java.lang.Boolean);
    Code:
       0: aload_0
       1: invokespecial #48                 // Method io/dekorate/deps/kubernetes/api/model/scheduling/PriorityClassFluentImpl."<init>":()V
       4: aload_0
       5: aload_1
       6: putfield      #50                 // Field fluent:Lio/dekorate/deps/kubernetes/api/model/scheduling/PriorityClassFluent;
       9: aload_1
      10: aload_2
      11: invokevirtual #54                 // Method io/dekorate/deps/kubernetes/api/model/scheduling/PriorityClass.getApiVersion:()Ljava/lang/String;
      14: invokeinterface #60,  2           // InterfaceMethod io/dekorate/deps/kubernetes/api/model/scheduling/PriorityClassFluent.withApiVersion:(Ljava/lang/String;)Lio/dekorate/deps/kubernetes/api/model/scheduling/PriorityClassFluent;
      19: pop
      20: aload_1
      21: aload_2
      22: invokevirtual #63                 // Method io/dekorate/deps/kubernetes/api/model/scheduling/PriorityClass.getDescription:()Ljava/lang/String;
      25: invokeinterface #66,  2           // InterfaceMethod io/dekorate/deps/kubernetes/api/model/scheduling/PriorityClassFluent.withDescription:(Ljava/lang/String;)Lio/dekorate/deps/kubernetes/api/model/scheduling/PriorityClassFluent;
      30: pop
      31: aload_1
      32: aload_2
      33: invokevirtual #70                 // Method io/dekorate/deps/kubernetes/api/model/scheduling/PriorityClass.getGlobalDefault:()Ljava/lang/Boolean;
      36: invokeinterface #74,  2           // InterfaceMethod io/dekorate/deps/kubernetes/api/model/scheduling/PriorityClassFluent.withGlobalDefault:(Ljava/lang/Boolean;)Lio/dekorate/deps/kubernetes/api/model/scheduling/PriorityClassFluent;
      41: pop
      42: aload_1
      43: aload_2
      44: invokevirtual #77                 // Method io/dekorate/deps/kubernetes/api/model/scheduling/PriorityClass.getKind:()Ljava/lang/String;
      47: invokeinterface #80,  2           // InterfaceMethod io/dekorate/deps/kubernetes/api/model/scheduling/PriorityClassFluent.withKind:(Ljava/lang/String;)Lio/dekorate/deps/kubernetes/api/model/scheduling/PriorityClassFluent;
      52: pop
      53: aload_1
      54: aload_2
      55: invokevirtual #84                 // Method io/dekorate/deps/kubernetes/api/model/scheduling/PriorityClass.getMetadata:()Lio/dekorate/deps/kubernetes/api/model/ObjectMeta;
      58: invokeinterface #88,  2           // InterfaceMethod io/dekorate/deps/kubernetes/api/model/scheduling/PriorityClassFluent.withMetadata:(Lio/dekorate/deps/kubernetes/api/model/ObjectMeta;)Lio/dekorate/deps/kubernetes/api/model/scheduling/PriorityClassFluent;
      63: pop
      64: aload_1
      65: aload_2
      66: invokevirtual #91                 // Method io/dekorate/deps/kubernetes/api/model/scheduling/PriorityClass.getPreemptionPolicy:()Ljava/lang/String;
      69: invokeinterface #94,  2           // InterfaceMethod io/dekorate/deps/kubernetes/api/model/scheduling/PriorityClassFluent.withPreemptionPolicy:(Ljava/lang/String;)Lio/dekorate/deps/kubernetes/api/model/scheduling/PriorityClassFluent;
      74: pop
      75: aload_1
      76: aload_2
      77: invokevirtual #98                 // Method io/dekorate/deps/kubernetes/api/model/scheduling/PriorityClass.getValue:()Ljava/lang/Integer;
      80: invokeinterface #102,  2          // InterfaceMethod io/dekorate/deps/kubernetes/api/model/scheduling/PriorityClassFluent.withValue:(Ljava/lang/Integer;)Lio/dekorate/deps/kubernetes/api/model/scheduling/PriorityClassFluent;
      85: pop
      86: aload_0
      87: aload_3
      88: putfield      #104                // Field validationEnabled:Ljava/lang/Boolean;
      91: return

  public io.dekorate.deps.kubernetes.api.model.scheduling.PriorityClassBuilder(io.dekorate.deps.kubernetes.api.model.scheduling.PriorityClass);
    Code:
       0: aload_0
       1: aload_1
       2: iconst_1
       3: invokestatic  #21                 // Method java/lang/Boolean.valueOf:(Z)Ljava/lang/Boolean;
       6: invokespecial #33                 // Method "<init>":(Lio/dekorate/deps/kubernetes/api/model/scheduling/PriorityClass;Ljava/lang/Boolean;)V
       9: return

  public io.dekorate.deps.kubernetes.api.model.scheduling.PriorityClassBuilder(io.dekorate.deps.kubernetes.api.model.scheduling.PriorityClass, java.lang.Boolean);
    Code:
       0: aload_0
       1: invokespecial #48                 // Method io/dekorate/deps/kubernetes/api/model/scheduling/PriorityClassFluentImpl."<init>":()V
       4: aload_0
       5: aload_0
       6: putfield      #50                 // Field fluent:Lio/dekorate/deps/kubernetes/api/model/scheduling/PriorityClassFluent;
       9: aload_0
      10: aload_1
      11: invokevirtual #54                 // Method io/dekorate/deps/kubernetes/api/model/scheduling/PriorityClass.getApiVersion:()Ljava/lang/String;
      14: invokevirtual #106                // Method withApiVersion:(Ljava/lang/String;)Lio/dekorate/deps/kubernetes/api/model/scheduling/PriorityClassFluent;
      17: pop
      18: aload_0
      19: aload_1
      20: invokevirtual #63                 // Method io/dekorate/deps/kubernetes/api/model/scheduling/PriorityClass.getDescription:()Ljava/lang/String;
      23: invokevirtual #107                // Method withDescription:(Ljava/lang/String;)Lio/dekorate/deps/kubernetes/api/model/scheduling/PriorityClassFluent;
      26: pop
      27: aload_0
      28: aload_1
      29: invokevirtual #70                 // Method io/dekorate/deps/kubernetes/api/model/scheduling/PriorityClass.getGlobalDefault:()Ljava/lang/Boolean;
      32: invokevirtual #108                // Method withGlobalDefault:(Ljava/lang/Boolean;)Lio/dekorate/deps/kubernetes/api/model/scheduling/PriorityClassFluent;
      35: pop
      36: aload_0
      37: aload_1
      38: invokevirtual #77                 // Method io/dekorate/deps/kubernetes/api/model/scheduling/PriorityClass.getKind:()Ljava/lang/String;
      41: invokevirtual #109                // Method withKind:(Ljava/lang/String;)Lio/dekorate/deps/kubernetes/api/model/scheduling/PriorityClassFluent;
      44: pop
      45: aload_0
      46: aload_1
      47: invokevirtual #84                 // Method io/dekorate/deps/kubernetes/api/model/scheduling/PriorityClass.getMetadata:()Lio/dekorate/deps/kubernetes/api/model/ObjectMeta;
      50: invokevirtual #110                // Method withMetadata:(Lio/dekorate/deps/kubernetes/api/model/ObjectMeta;)Lio/dekorate/deps/kubernetes/api/model/scheduling/PriorityClassFluent;
      53: pop
      54: aload_0
      55: aload_1
      56: invokevirtual #91                 // Method io/dekorate/deps/kubernetes/api/model/scheduling/PriorityClass.getPreemptionPolicy:()Ljava/lang/String;
      59: invokevirtual #111                // Method withPreemptionPolicy:(Ljava/lang/String;)Lio/dekorate/deps/kubernetes/api/model/scheduling/PriorityClassFluent;
      62: pop
      63: aload_0
      64: aload_1
      65: invokevirtual #98                 // Method io/dekorate/deps/kubernetes/api/model/scheduling/PriorityClass.getValue:()Ljava/lang/Integer;
      68: invokevirtual #112                // Method withValue:(Ljava/lang/Integer;)Lio/dekorate/deps/kubernetes/api/model/scheduling/PriorityClassFluent;
      71: pop
      72: aload_0
      73: aload_2
      74: putfield      #104                // Field validationEnabled:Ljava/lang/Boolean;
      77: return

  public io.dekorate.deps.kubernetes.api.model.scheduling.PriorityClass build();
    Code:
       0: new           #28                 // class io/dekorate/deps/kubernetes/api/model/scheduling/PriorityClass
       3: dup
       4: aload_0
       5: getfield      #50                 // Field fluent:Lio/dekorate/deps/kubernetes/api/model/scheduling/PriorityClassFluent;
       8: invokeinterface #115,  1          // InterfaceMethod io/dekorate/deps/kubernetes/api/model/scheduling/PriorityClassFluent.getApiVersion:()Ljava/lang/String;
      13: aload_0
      14: getfield      #50                 // Field fluent:Lio/dekorate/deps/kubernetes/api/model/scheduling/PriorityClassFluent;
      17: invokeinterface #116,  1          // InterfaceMethod io/dekorate/deps/kubernetes/api/model/scheduling/PriorityClassFluent.getDescription:()Ljava/lang/String;
      22: aload_0
      23: getfield      #50                 // Field fluent:Lio/dekorate/deps/kubernetes/api/model/scheduling/PriorityClassFluent;
      26: invokeinterface #119,  1          // InterfaceMethod io/dekorate/deps/kubernetes/api/model/scheduling/PriorityClassFluent.isGlobalDefault:()Ljava/lang/Boolean;
      31: aload_0
      32: getfield      #50                 // Field fluent:Lio/dekorate/deps/kubernetes/api/model/scheduling/PriorityClassFluent;
      35: invokeinterface #120,  1          // InterfaceMethod io/dekorate/deps/kubernetes/api/model/scheduling/PriorityClassFluent.getKind:()Ljava/lang/String;
      40: aload_0
      41: getfield      #50                 // Field fluent:Lio/dekorate/deps/kubernetes/api/model/scheduling/PriorityClassFluent;
      44: invokeinterface #121,  1          // InterfaceMethod io/dekorate/deps/kubernetes/api/model/scheduling/PriorityClassFluent.getMetadata:()Lio/dekorate/deps/kubernetes/api/model/ObjectMeta;
      49: aload_0
      50: getfield      #50                 // Field fluent:Lio/dekorate/deps/kubernetes/api/model/scheduling/PriorityClassFluent;
      53: invokeinterface #122,  1          // InterfaceMethod io/dekorate/deps/kubernetes/api/model/scheduling/PriorityClassFluent.getPreemptionPolicy:()Ljava/lang/String;
      58: aload_0
      59: getfield      #50                 // Field fluent:Lio/dekorate/deps/kubernetes/api/model/scheduling/PriorityClassFluent;
      62: invokeinterface #123,  1          // InterfaceMethod io/dekorate/deps/kubernetes/api/model/scheduling/PriorityClassFluent.getValue:()Ljava/lang/Integer;
      67: invokespecial #126                // Method io/dekorate/deps/kubernetes/api/model/scheduling/PriorityClass."<init>":(Ljava/lang/String;Ljava/lang/String;Ljava/lang/Boolean;Ljava/lang/String;Lio/dekorate/deps/kubernetes/api/model/ObjectMeta;Ljava/lang/String;Ljava/lang/Integer;)V
      70: astore_1
      71: aload_1
      72: areturn

  public boolean equals(java.lang.Object);
    Code:
       0: aload_0
       1: aload_1
       2: if_acmpne     7
       5: iconst_1
       6: ireturn
       7: aload_1
       8: ifnull        22
      11: aload_0
      12: invokevirtual #135                // Method java/lang/Object.getClass:()Ljava/lang/Class;
      15: aload_1
      16: invokevirtual #135                // Method java/lang/Object.getClass:()Ljava/lang/Class;
      19: if_acmpeq     24
      22: iconst_0
      23: ireturn
      24: aload_0
      25: aload_1
      26: invokespecial #137                // Method io/dekorate/deps/kubernetes/api/model/scheduling/PriorityClassFluentImpl.equals:(Ljava/lang/Object;)Z
      29: ifne          34
      32: iconst_0
      33: ireturn
      34: aload_1
      35: checkcast     #2                  // class io/dekorate/deps/kubernetes/api/model/scheduling/PriorityClassBuilder
      38: astore_2
      39: aload_0
      40: getfield      #50                 // Field fluent:Lio/dekorate/deps/kubernetes/api/model/scheduling/PriorityClassFluent;
      43: ifnull        71
      46: aload_0
      47: getfield      #50                 // Field fluent:Lio/dekorate/deps/kubernetes/api/model/scheduling/PriorityClassFluent;
      50: aload_0
      51: if_acmpeq     71
      54: aload_0
      55: getfield      #50                 // Field fluent:Lio/dekorate/deps/kubernetes/api/model/scheduling/PriorityClassFluent;
      58: aload_2
      59: getfield      #50                 // Field fluent:Lio/dekorate/deps/kubernetes/api/model/scheduling/PriorityClassFluent;
      62: invokevirtual #138                // Method java/lang/Object.equals:(Ljava/lang/Object;)Z
      65: ifne          88
      68: goto          86
      71: aload_2
      72: getfield      #50                 // Field fluent:Lio/dekorate/deps/kubernetes/api/model/scheduling/PriorityClassFluent;
      75: ifnull        88
      78: aload_0
      79: getfield      #50                 // Field fluent:Lio/dekorate/deps/kubernetes/api/model/scheduling/PriorityClassFluent;
      82: aload_0
      83: if_acmpeq     88
      86: iconst_0
      87: ireturn
      88: aload_0
      89: getfield      #104                // Field validationEnabled:Ljava/lang/Boolean;
      92: ifnull        112
      95: aload_0
      96: getfield      #104                // Field validationEnabled:Ljava/lang/Boolean;
      99: aload_2
     100: getfield      #104                // Field validationEnabled:Ljava/lang/Boolean;
     103: invokevirtual #139                // Method java/lang/Boolean.equals:(Ljava/lang/Object;)Z
     106: ifne          121
     109: goto          119
     112: aload_2
     113: getfield      #104                // Field validationEnabled:Ljava/lang/Boolean;
     116: ifnull        121
     119: iconst_0
     120: ireturn
     121: iconst_1
     122: ireturn

  public java.lang.Object build();
    Code:
       0: aload_0
       1: invokevirtual #145                // Method build:()Lio/dekorate/deps/kubernetes/api/model/scheduling/PriorityClass;
       4: areturn
}
