Compiled from "CreateFlag.java"
public final class org.apache.hadoop.fs.CreateFlag extends java.lang.Enum<org.apache.hadoop.fs.CreateFlag> {
  public static final org.apache.hadoop.fs.CreateFlag CREATE;

  public static final org.apache.hadoop.fs.CreateFlag OVERWRITE;

  public static final org.apache.hadoop.fs.CreateFlag APPEND;

  public static final org.apache.hadoop.fs.CreateFlag SYNC_BLOCK;

  public static final org.apache.hadoop.fs.CreateFlag LAZY_PERSIST;

  public static final org.apache.hadoop.fs.CreateFlag NEW_BLOCK;

  public static final org.apache.hadoop.fs.CreateFlag NO_LOCAL_WRITE;

  public static final org.apache.hadoop.fs.CreateFlag SHOULD_REPLICATE;

  public static final org.apache.hadoop.fs.CreateFlag IGNORE_CLIENT_LOCALITY;

  private final short mode;

  private static final org.apache.hadoop.fs.CreateFlag[] $VALUES;

  public static org.apache.hadoop.fs.CreateFlag[] values();
    Code:
       0: getstatic     #1                  // Field $VALUES:[Lorg/apache/hadoop/fs/CreateFlag;
       3: invokevirtual #2                  // Method "[Lorg/apache/hadoop/fs/CreateFlag;".clone:()Ljava/lang/Object;
       6: checkcast     #3                  // class "[Lorg/apache/hadoop/fs/CreateFlag;"
       9: areturn

  public static org.apache.hadoop.fs.CreateFlag valueOf(java.lang.String);
    Code:
       0: ldc           #4                  // class org/apache/hadoop/fs/CreateFlag
       2: aload_0
       3: invokestatic  #5                  // Method java/lang/Enum.valueOf:(Ljava/lang/Class;Ljava/lang/String;)Ljava/lang/Enum;
       6: checkcast     #4                  // class org/apache/hadoop/fs/CreateFlag
       9: areturn

  private org.apache.hadoop.fs.CreateFlag(short);
    Code:
       0: aload_0
       1: aload_1
       2: iload_2
       3: invokespecial #6                  // Method java/lang/Enum."<init>":(Ljava/lang/String;I)V
       6: aload_0
       7: iload_3
       8: putfield      #7                  // Field mode:S
      11: return

  short getMode();
    Code:
       0: aload_0
       1: getfield      #7                  // Field mode:S
       4: ireturn

  public static void validate(java.util.EnumSet<org.apache.hadoop.fs.CreateFlag>);
    Code:
       0: aload_0
       1: ifnull        11
       4: aload_0
       5: invokevirtual #8                  // Method java/util/EnumSet.isEmpty:()Z
       8: ifeq          38
      11: new           #9                  // class org/apache/hadoop/HadoopIllegalArgumentException
      14: dup
      15: new           #10                 // class java/lang/StringBuilder
      18: dup
      19: invokespecial #11                 // Method java/lang/StringBuilder."<init>":()V
      22: aload_0
      23: invokevirtual #12                 // Method java/lang/StringBuilder.append:(Ljava/lang/Object;)Ljava/lang/StringBuilder;
      26: ldc           #13                 // String  does not specify any options
      28: invokevirtual #14                 // Method java/lang/StringBuilder.append:(Ljava/lang/String;)Ljava/lang/StringBuilder;
      31: invokevirtual #15                 // Method java/lang/StringBuilder.toString:()Ljava/lang/String;
      34: invokespecial #16                 // Method org/apache/hadoop/HadoopIllegalArgumentException."<init>":(Ljava/lang/String;)V
      37: athrow
      38: aload_0
      39: getstatic     #17                 // Field APPEND:Lorg/apache/hadoop/fs/CreateFlag;
      42: invokevirtual #18                 // Method java/util/EnumSet.contains:(Ljava/lang/Object;)Z
      45: istore_1
      46: aload_0
      47: getstatic     #19                 // Field OVERWRITE:Lorg/apache/hadoop/fs/CreateFlag;
      50: invokevirtual #18                 // Method java/util/EnumSet.contains:(Ljava/lang/Object;)Z
      53: istore_2
      54: iload_1
      55: ifeq          89
      58: iload_2
      59: ifeq          89
      62: new           #9                  // class org/apache/hadoop/HadoopIllegalArgumentException
      65: dup
      66: new           #10                 // class java/lang/StringBuilder
      69: dup
      70: invokespecial #11                 // Method java/lang/StringBuilder."<init>":()V
      73: aload_0
      74: invokevirtual #12                 // Method java/lang/StringBuilder.append:(Ljava/lang/Object;)Ljava/lang/StringBuilder;
      77: ldc           #20                 // String Both append and overwrite options cannot be enabled.
      79: invokevirtual #14                 // Method java/lang/StringBuilder.append:(Ljava/lang/String;)Ljava/lang/StringBuilder;
      82: invokevirtual #15                 // Method java/lang/StringBuilder.toString:()Ljava/lang/String;
      85: invokespecial #16                 // Method org/apache/hadoop/HadoopIllegalArgumentException."<init>":(Ljava/lang/String;)V
      88: athrow
      89: return

  public static void validate(java.lang.Object, boolean, java.util.EnumSet<org.apache.hadoop.fs.CreateFlag>) throws java.io.IOException;
    Code:
       0: aload_2
       1: invokestatic  #21                 // Method validate:(Ljava/util/EnumSet;)V
       4: aload_2
       5: getstatic     #17                 // Field APPEND:Lorg/apache/hadoop/fs/CreateFlag;
       8: invokevirtual #18                 // Method java/util/EnumSet.contains:(Ljava/lang/Object;)Z
      11: istore_3
      12: aload_2
      13: getstatic     #19                 // Field OVERWRITE:Lorg/apache/hadoop/fs/CreateFlag;
      16: invokevirtual #18                 // Method java/util/EnumSet.contains:(Ljava/lang/Object;)Z
      19: istore        4
      21: iload_1
      22: ifeq          73
      25: iload_3
      26: ifne          122
      29: iload         4
      31: ifne          122
      34: new           #22                 // class org/apache/hadoop/fs/FileAlreadyExistsException
      37: dup
      38: new           #10                 // class java/lang/StringBuilder
      41: dup
      42: invokespecial #11                 // Method java/lang/StringBuilder."<init>":()V
      45: ldc           #23                 // String File already exists:
      47: invokevirtual #14                 // Method java/lang/StringBuilder.append:(Ljava/lang/String;)Ljava/lang/StringBuilder;
      50: aload_0
      51: invokevirtual #24                 // Method java/lang/Object.toString:()Ljava/lang/String;
      54: invokevirtual #14                 // Method java/lang/StringBuilder.append:(Ljava/lang/String;)Ljava/lang/StringBuilder;
      57: ldc           #25                 // String . Append or overwrite option must be specified in
      59: invokevirtual #14                 // Method java/lang/StringBuilder.append:(Ljava/lang/String;)Ljava/lang/StringBuilder;
      62: aload_2
      63: invokevirtual #12                 // Method java/lang/StringBuilder.append:(Ljava/lang/Object;)Ljava/lang/StringBuilder;
      66: invokevirtual #15                 // Method java/lang/StringBuilder.toString:()Ljava/lang/String;
      69: invokespecial #26                 // Method org/apache/hadoop/fs/FileAlreadyExistsException."<init>":(Ljava/lang/String;)V
      72: athrow
      73: aload_2
      74: getstatic     #27                 // Field CREATE:Lorg/apache/hadoop/fs/CreateFlag;
      77: invokevirtual #18                 // Method java/util/EnumSet.contains:(Ljava/lang/Object;)Z
      80: ifne          122
      83: new           #28                 // class java/io/FileNotFoundException
      86: dup
      87: new           #10                 // class java/lang/StringBuilder
      90: dup
      91: invokespecial #11                 // Method java/lang/StringBuilder."<init>":()V
      94: ldc           #29                 // String Non existing file:
      96: invokevirtual #14                 // Method java/lang/StringBuilder.append:(Ljava/lang/String;)Ljava/lang/StringBuilder;
      99: aload_0
     100: invokevirtual #24                 // Method java/lang/Object.toString:()Ljava/lang/String;
     103: invokevirtual #14                 // Method java/lang/StringBuilder.append:(Ljava/lang/String;)Ljava/lang/StringBuilder;
     106: ldc           #30                 // String . Create option is not specified in
     108: invokevirtual #14                 // Method java/lang/StringBuilder.append:(Ljava/lang/String;)Ljava/lang/StringBuilder;
     111: aload_2
     112: invokevirtual #12                 // Method java/lang/StringBuilder.append:(Ljava/lang/Object;)Ljava/lang/StringBuilder;
     115: invokevirtual #15                 // Method java/lang/StringBuilder.toString:()Ljava/lang/String;
     118: invokespecial #31                 // Method java/io/FileNotFoundException."<init>":(Ljava/lang/String;)V
     121: athrow
     122: return

  public static void validateForAppend(java.util.EnumSet<org.apache.hadoop.fs.CreateFlag>);
    Code:
       0: aload_0
       1: invokestatic  #21                 // Method validate:(Ljava/util/EnumSet;)V
       4: aload_0
       5: getstatic     #17                 // Field APPEND:Lorg/apache/hadoop/fs/CreateFlag;
       8: invokevirtual #18                 // Method java/util/EnumSet.contains:(Ljava/lang/Object;)Z
      11: ifne          41
      14: new           #9                  // class org/apache/hadoop/HadoopIllegalArgumentException
      17: dup
      18: new           #10                 // class java/lang/StringBuilder
      21: dup
      22: invokespecial #11                 // Method java/lang/StringBuilder."<init>":()V
      25: aload_0
      26: invokevirtual #12                 // Method java/lang/StringBuilder.append:(Ljava/lang/Object;)Ljava/lang/StringBuilder;
      29: ldc           #32                 // String  does not contain APPEND
      31: invokevirtual #14                 // Method java/lang/StringBuilder.append:(Ljava/lang/String;)Ljava/lang/StringBuilder;
      34: invokevirtual #15                 // Method java/lang/StringBuilder.toString:()Ljava/lang/String;
      37: invokespecial #16                 // Method org/apache/hadoop/HadoopIllegalArgumentException."<init>":(Ljava/lang/String;)V
      40: athrow
      41: return

  static {};
    Code:
       0: new           #4                  // class org/apache/hadoop/fs/CreateFlag
       3: dup
       4: ldc           #33                 // String CREATE
       6: iconst_0
       7: iconst_1
       8: invokespecial #34                 // Method "<init>":(Ljava/lang/String;IS)V
      11: putstatic     #27                 // Field CREATE:Lorg/apache/hadoop/fs/CreateFlag;
      14: new           #4                  // class org/apache/hadoop/fs/CreateFlag
      17: dup
      18: ldc           #35                 // String OVERWRITE
      20: iconst_1
      21: iconst_2
      22: invokespecial #34                 // Method "<init>":(Ljava/lang/String;IS)V
      25: putstatic     #19                 // Field OVERWRITE:Lorg/apache/hadoop/fs/CreateFlag;
      28: new           #4                  // class org/apache/hadoop/fs/CreateFlag
      31: dup
      32: ldc           #36                 // String APPEND
      34: iconst_2
      35: iconst_4
      36: invokespecial #34                 // Method "<init>":(Ljava/lang/String;IS)V
      39: putstatic     #17                 // Field APPEND:Lorg/apache/hadoop/fs/CreateFlag;
      42: new           #4                  // class org/apache/hadoop/fs/CreateFlag
      45: dup
      46: ldc           #37                 // String SYNC_BLOCK
      48: iconst_3
      49: bipush        8
      51: invokespecial #34                 // Method "<init>":(Ljava/lang/String;IS)V
      54: putstatic     #38                 // Field SYNC_BLOCK:Lorg/apache/hadoop/fs/CreateFlag;
      57: new           #4                  // class org/apache/hadoop/fs/CreateFlag
      60: dup
      61: ldc           #39                 // String LAZY_PERSIST
      63: iconst_4
      64: bipush        16
      66: invokespecial #34                 // Method "<init>":(Ljava/lang/String;IS)V
      69: putstatic     #40                 // Field LAZY_PERSIST:Lorg/apache/hadoop/fs/CreateFlag;
      72: new           #4                  // class org/apache/hadoop/fs/CreateFlag
      75: dup
      76: ldc           #41                 // String NEW_BLOCK
      78: iconst_5
      79: bipush        32
      81: invokespecial #34                 // Method "<init>":(Ljava/lang/String;IS)V
      84: putstatic     #42                 // Field NEW_BLOCK:Lorg/apache/hadoop/fs/CreateFlag;
      87: new           #4                  // class org/apache/hadoop/fs/CreateFlag
      90: dup
      91: ldc           #43                 // String NO_LOCAL_WRITE
      93: bipush        6
      95: bipush        64
      97: invokespecial #34                 // Method "<init>":(Ljava/lang/String;IS)V
     100: putstatic     #44                 // Field NO_LOCAL_WRITE:Lorg/apache/hadoop/fs/CreateFlag;
     103: new           #4                  // class org/apache/hadoop/fs/CreateFlag
     106: dup
     107: ldc           #45                 // String SHOULD_REPLICATE
     109: bipush        7
     111: sipush        128
     114: invokespecial #34                 // Method "<init>":(Ljava/lang/String;IS)V
     117: putstatic     #46                 // Field SHOULD_REPLICATE:Lorg/apache/hadoop/fs/CreateFlag;
     120: new           #4                  // class org/apache/hadoop/fs/CreateFlag
     123: dup
     124: ldc           #47                 // String IGNORE_CLIENT_LOCALITY
     126: bipush        8
     128: sipush        256
     131: invokespecial #34                 // Method "<init>":(Ljava/lang/String;IS)V
     134: putstatic     #48                 // Field IGNORE_CLIENT_LOCALITY:Lorg/apache/hadoop/fs/CreateFlag;
     137: bipush        9
     139: anewarray     #4                  // class org/apache/hadoop/fs/CreateFlag
     142: dup
     143: iconst_0
     144: getstatic     #27                 // Field CREATE:Lorg/apache/hadoop/fs/CreateFlag;
     147: aastore
     148: dup
     149: iconst_1
     150: getstatic     #19                 // Field OVERWRITE:Lorg/apache/hadoop/fs/CreateFlag;
     153: aastore
     154: dup
     155: iconst_2
     156: getstatic     #17                 // Field APPEND:Lorg/apache/hadoop/fs/CreateFlag;
     159: aastore
     160: dup
     161: iconst_3
     162: getstatic     #38                 // Field SYNC_BLOCK:Lorg/apache/hadoop/fs/CreateFlag;
     165: aastore
     166: dup
     167: iconst_4
     168: getstatic     #40                 // Field LAZY_PERSIST:Lorg/apache/hadoop/fs/CreateFlag;
     171: aastore
     172: dup
     173: iconst_5
     174: getstatic     #42                 // Field NEW_BLOCK:Lorg/apache/hadoop/fs/CreateFlag;
     177: aastore
     178: dup
     179: bipush        6
     181: getstatic     #44                 // Field NO_LOCAL_WRITE:Lorg/apache/hadoop/fs/CreateFlag;
     184: aastore
     185: dup
     186: bipush        7
     188: getstatic     #46                 // Field SHOULD_REPLICATE:Lorg/apache/hadoop/fs/CreateFlag;
     191: aastore
     192: dup
     193: bipush        8
     195: getstatic     #48                 // Field IGNORE_CLIENT_LOCALITY:Lorg/apache/hadoop/fs/CreateFlag;
     198: aastore
     199: putstatic     #1                  // Field $VALUES:[Lorg/apache/hadoop/fs/CreateFlag;
     202: return
}
