Compiled from "FileContext.java"
class org.apache.hadoop.fs.FileContext$8 extends org.apache.hadoop.fs.FSLinkResolver<java.lang.Boolean> {
  final long val$newLength;

  final org.apache.hadoop.fs.FileContext this$0;

  org.apache.hadoop.fs.FileContext$8(org.apache.hadoop.fs.FileContext, long);
    Code:
       0: aload_0
       1: aload_1
       2: putfield      #1                  // Field this$0:Lorg/apache/hadoop/fs/FileContext;
       5: aload_0
       6: lload_2
       7: putfield      #2                  // Field val$newLength:J
      10: aload_0
      11: invokespecial #3                  // Method org/apache/hadoop/fs/FSLinkResolver."<init>":()V
      14: return

  public java.lang.Boolean next(org.apache.hadoop.fs.AbstractFileSystem, org.apache.hadoop.fs.Path) throws java.io.IOException, org.apache.hadoop.fs.UnresolvedLinkException;
    Code:
       0: aload_1
       1: aload_2
       2: aload_0
       3: getfield      #2                  // Field val$newLength:J
       6: invokevirtual #4                  // Method org/apache/hadoop/fs/AbstractFileSystem.truncate:(Lorg/apache/hadoop/fs/Path;J)Z
       9: invokestatic  #5                  // Method java/lang/Boolean.valueOf:(Z)Ljava/lang/Boolean;
      12: areturn

  public java.lang.Object next(org.apache.hadoop.fs.AbstractFileSystem, org.apache.hadoop.fs.Path) throws java.io.IOException, org.apache.hadoop.fs.UnresolvedLinkException;
    Code:
       0: aload_0
       1: aload_1
       2: aload_2
       3: invokevirtual #6                  // Method next:(Lorg/apache/hadoop/fs/AbstractFileSystem;Lorg/apache/hadoop/fs/Path;)Ljava/lang/Boolean;
       6: areturn
}
