Compiled from "GlobFilter.java"
public class org.apache.hadoop.fs.GlobFilter implements org.apache.hadoop.fs.PathFilter {
  private static final org.apache.hadoop.fs.PathFilter DEFAULT_FILTER;

  private org.apache.hadoop.fs.PathFilter userFilter;

  private org.apache.hadoop.fs.GlobPattern pattern;

  public org.apache.hadoop.fs.GlobFilter(java.lang.String) throws java.io.IOException;
    Code:
       0: aload_0
       1: invokespecial #1                  // Method java/lang/Object."<init>":()V
       4: aload_0
       5: getstatic     #2                  // Field DEFAULT_FILTER:Lorg/apache/hadoop/fs/PathFilter;
       8: putfield      #3                  // Field userFilter:Lorg/apache/hadoop/fs/PathFilter;
      11: aload_0
      12: aload_1
      13: getstatic     #2                  // Field DEFAULT_FILTER:Lorg/apache/hadoop/fs/PathFilter;
      16: invokevirtual #4                  // Method init:(Ljava/lang/String;Lorg/apache/hadoop/fs/PathFilter;)V
      19: return

  public org.apache.hadoop.fs.GlobFilter(java.lang.String, org.apache.hadoop.fs.PathFilter) throws java.io.IOException;
    Code:
       0: aload_0
       1: invokespecial #1                  // Method java/lang/Object."<init>":()V
       4: aload_0
       5: getstatic     #2                  // Field DEFAULT_FILTER:Lorg/apache/hadoop/fs/PathFilter;
       8: putfield      #3                  // Field userFilter:Lorg/apache/hadoop/fs/PathFilter;
      11: aload_0
      12: aload_1
      13: aload_2
      14: invokevirtual #4                  // Method init:(Ljava/lang/String;Lorg/apache/hadoop/fs/PathFilter;)V
      17: return

  void init(java.lang.String, org.apache.hadoop.fs.PathFilter) throws java.io.IOException;
    Code:
       0: aload_0
       1: aload_2
       2: putfield      #3                  // Field userFilter:Lorg/apache/hadoop/fs/PathFilter;
       5: aload_0
       6: new           #5                  // class org/apache/hadoop/fs/GlobPattern
       9: dup
      10: aload_1
      11: invokespecial #6                  // Method org/apache/hadoop/fs/GlobPattern."<init>":(Ljava/lang/String;)V
      14: putfield      #7                  // Field pattern:Lorg/apache/hadoop/fs/GlobPattern;
      17: goto          52
      20: astore_3
      21: new           #9                  // class java/io/IOException
      24: dup
      25: new           #10                 // class java/lang/StringBuilder
      28: dup
      29: invokespecial #11                 // Method java/lang/StringBuilder."<init>":()V
      32: ldc           #12                 // String Illegal file pattern:
      34: invokevirtual #13                 // Method java/lang/StringBuilder.append:(Ljava/lang/String;)Ljava/lang/StringBuilder;
      37: aload_3
      38: invokevirtual #14                 // Method com/google/re2j/PatternSyntaxException.getMessage:()Ljava/lang/String;
      41: invokevirtual #13                 // Method java/lang/StringBuilder.append:(Ljava/lang/String;)Ljava/lang/StringBuilder;
      44: invokevirtual #15                 // Method java/lang/StringBuilder.toString:()Ljava/lang/String;
      47: aload_3
      48: invokespecial #16                 // Method java/io/IOException."<init>":(Ljava/lang/String;Ljava/lang/Throwable;)V
      51: athrow
      52: return
    Exception table:
       from    to  target type
           0    17    20   Class com/google/re2j/PatternSyntaxException

  public boolean hasPattern();
    Code:
       0: aload_0
       1: getfield      #7                  // Field pattern:Lorg/apache/hadoop/fs/GlobPattern;
       4: invokevirtual #17                 // Method org/apache/hadoop/fs/GlobPattern.hasWildcard:()Z
       7: ireturn

  public boolean accept(org.apache.hadoop.fs.Path);
    Code:
       0: aload_0
       1: getfield      #7                  // Field pattern:Lorg/apache/hadoop/fs/GlobPattern;
       4: aload_1
       5: invokevirtual #18                 // Method org/apache/hadoop/fs/Path.getName:()Ljava/lang/String;
       8: invokevirtual #19                 // Method org/apache/hadoop/fs/GlobPattern.matches:(Ljava/lang/CharSequence;)Z
      11: ifeq          31
      14: aload_0
      15: getfield      #3                  // Field userFilter:Lorg/apache/hadoop/fs/PathFilter;
      18: aload_1
      19: invokeinterface #20,  2           // InterfaceMethod org/apache/hadoop/fs/PathFilter.accept:(Lorg/apache/hadoop/fs/Path;)Z
      24: ifeq          31
      27: iconst_1
      28: goto          32
      31: iconst_0
      32: ireturn

  static {};
    Code:
       0: new           #21                 // class org/apache/hadoop/fs/GlobFilter$1
       3: dup
       4: invokespecial #22                 // Method org/apache/hadoop/fs/GlobFilter$1."<init>":()V
       7: putstatic     #2                  // Field DEFAULT_FILTER:Lorg/apache/hadoop/fs/PathFilter;
      10: return
}
