Compiled from "Options.java"
public class org.apache.hadoop.fs.Options$CreateOpts$BytesPerChecksum extends org.apache.hadoop.fs.Options$CreateOpts {
  private final int bytesPerChecksum;

  protected org.apache.hadoop.fs.Options$CreateOpts$BytesPerChecksum(short);
    Code:
       0: aload_0
       1: aconst_null
       2: invokespecial #1                  // Method org/apache/hadoop/fs/Options$CreateOpts."<init>":(Lorg/apache/hadoop/fs/Options$1;)V
       5: iload_1
       6: ifgt          19
       9: new           #2                  // class java/lang/IllegalArgumentException
      12: dup
      13: ldc           #3                  // String Bytes per checksum must be greater than 0
      15: invokespecial #4                  // Method java/lang/IllegalArgumentException."<init>":(Ljava/lang/String;)V
      18: athrow
      19: aload_0
      20: iload_1
      21: putfield      #5                  // Field bytesPerChecksum:I
      24: return

  public int getValue();
    Code:
       0: aload_0
       1: getfield      #5                  // Field bytesPerChecksum:I
       4: ireturn
}
