Compiled from "S3ArnableField.java"
public final class software.amazon.awssdk.services.s3control.internal.S3ArnableField$Builder {
  private software.amazon.awssdk.arns.Arn arn;

  private software.amazon.awssdk.services.s3control.internal.S3ArnableField$Builder();
    Code:
       0: aload_0
       1: invokespecial #3                  // Method java/lang/Object."<init>":()V
       4: return

  public software.amazon.awssdk.services.s3control.internal.S3ArnableField$Builder arn(software.amazon.awssdk.arns.Arn);
    Code:
       0: aload_0
       1: aload_1
       2: putfield      #2                  // Field arn:Lsoftware/amazon/awssdk/arns/Arn;
       5: aload_0
       6: areturn

  public software.amazon.awssdk.services.s3control.internal.S3ArnableField build();
    Code:
       0: new           #4                  // class software/amazon/awssdk/services/s3control/internal/S3ArnableField
       3: dup
       4: aload_0
       5: aconst_null
       6: invokespecial #5                  // Method software/amazon/awssdk/services/s3control/internal/S3ArnableField."<init>":(Lsoftware/amazon/awssdk/services/s3control/internal/S3ArnableField$Builder;Lsoftware/amazon/awssdk/services/s3control/internal/S3ArnableField$1;)V
       9: areturn

  static software.amazon.awssdk.arns.Arn access$000(software.amazon.awssdk.services.s3control.internal.S3ArnableField$Builder);
    Code:
       0: aload_0
       1: getfield      #2                  // Field arn:Lsoftware/amazon/awssdk/arns/Arn;
       4: areturn

  software.amazon.awssdk.services.s3control.internal.S3ArnableField$Builder(software.amazon.awssdk.services.s3control.internal.S3ArnableField$1);
    Code:
       0: aload_0
       1: invokespecial #1                  // Method "<init>":()V
       4: return
}
