Compiled from "DateTimeFormatterBuilder.java"
class org.joda.time.format.DateTimeFormatterBuilder$TimeZoneName implements org.joda.time.format.DateTimePrinter,org.joda.time.format.DateTimeParser {
  static final int LONG_NAME;

  static final int SHORT_NAME;

  private final java.util.Map<java.lang.String, org.joda.time.DateTimeZone> iParseLookup;

  private final int iType;

  org.joda.time.format.DateTimeFormatterBuilder$TimeZoneName(int, java.util.Map<java.lang.String, org.joda.time.DateTimeZone>);
    Code:
       0: aload_0
       1: invokespecial #1                  // Method java/lang/Object."<init>":()V
       4: aload_0
       5: iload_1
       6: putfield      #2                  // Field iType:I
       9: aload_0
      10: aload_2
      11: putfield      #3                  // Field iParseLookup:Ljava/util/Map;
      14: return

  public int estimatePrintedLength();
    Code:
       0: aload_0
       1: getfield      #2                  // Field iType:I
       4: iconst_1
       5: if_icmpne     12
       8: iconst_4
       9: goto          14
      12: bipush        20
      14: ireturn

  public void printTo(java.lang.StringBuffer, long, org.joda.time.Chronology, int, org.joda.time.DateTimeZone, java.util.Locale);
    Code:
       0: aload_1
       1: aload_0
       2: lload_2
       3: iload         5
       5: i2l
       6: lsub
       7: aload         6
       9: aload         7
      11: invokespecial #4                  // Method print:(JLorg/joda/time/DateTimeZone;Ljava/util/Locale;)Ljava/lang/String;
      14: invokevirtual #5                  // Method java/lang/StringBuffer.append:(Ljava/lang/String;)Ljava/lang/StringBuffer;
      17: pop
      18: return

  public void printTo(java.io.Writer, long, org.joda.time.Chronology, int, org.joda.time.DateTimeZone, java.util.Locale) throws java.io.IOException;
    Code:
       0: aload_1
       1: aload_0
       2: lload_2
       3: iload         5
       5: i2l
       6: lsub
       7: aload         6
       9: aload         7
      11: invokespecial #4                  // Method print:(JLorg/joda/time/DateTimeZone;Ljava/util/Locale;)Ljava/lang/String;
      14: invokevirtual #6                  // Method java/io/Writer.write:(Ljava/lang/String;)V
      17: return

  private java.lang.String print(long, org.joda.time.DateTimeZone, java.util.Locale);
    Code:
       0: aload_3
       1: ifnonnull     7
       4: ldc           #7                  // String
       6: areturn
       7: aload_0
       8: getfield      #2                  // Field iType:I
      11: lookupswitch  { // 2
                     0: 36
                     1: 44
               default: 52
          }
      36: aload_3
      37: lload_1
      38: aload         4
      40: invokevirtual #8                  // Method org/joda/time/DateTimeZone.getName:(JLjava/util/Locale;)Ljava/lang/String;
      43: areturn
      44: aload_3
      45: lload_1
      46: aload         4
      48: invokevirtual #9                  // Method org/joda/time/DateTimeZone.getShortName:(JLjava/util/Locale;)Ljava/lang/String;
      51: areturn
      52: ldc           #7                  // String
      54: areturn

  public void printTo(java.lang.StringBuffer, org.joda.time.ReadablePartial, java.util.Locale);
    Code:
       0: return

  public void printTo(java.io.Writer, org.joda.time.ReadablePartial, java.util.Locale) throws java.io.IOException;
    Code:
       0: return

  public int estimateParsedLength();
    Code:
       0: aload_0
       1: getfield      #2                  // Field iType:I
       4: iconst_1
       5: if_icmpne     12
       8: iconst_4
       9: goto          14
      12: bipush        20
      14: ireturn

  public int parseInto(org.joda.time.format.DateTimeParserBucket, java.lang.String, int);
    Code:
       0: aload_0
       1: getfield      #3                  // Field iParseLookup:Ljava/util/Map;
       4: astore        4
       6: aload         4
       8: ifnull        16
      11: aload         4
      13: goto          19
      16: invokestatic  #10                 // Method org/joda/time/DateTimeUtils.getDefaultTimeZoneNames:()Ljava/util/Map;
      19: astore        4
      21: aload_2
      22: iload_3
      23: invokevirtual #11                 // Method java/lang/String.substring:(I)Ljava/lang/String;
      26: astore        5
      28: aconst_null
      29: astore        6
      31: aload         4
      33: invokeinterface #12,  1           // InterfaceMethod java/util/Map.keySet:()Ljava/util/Set;
      38: invokeinterface #13,  1           // InterfaceMethod java/util/Set.iterator:()Ljava/util/Iterator;
      43: astore        7
      45: aload         7
      47: invokeinterface #14,  1           // InterfaceMethod java/util/Iterator.hasNext:()Z
      52: ifeq          102
      55: aload         7
      57: invokeinterface #15,  1           // InterfaceMethod java/util/Iterator.next:()Ljava/lang/Object;
      62: checkcast     #16                 // class java/lang/String
      65: astore        8
      67: aload         5
      69: aload         8
      71: invokevirtual #17                 // Method java/lang/String.startsWith:(Ljava/lang/String;)Z
      74: ifeq          99
      77: aload         6
      79: ifnull        95
      82: aload         8
      84: invokevirtual #18                 // Method java/lang/String.length:()I
      87: aload         6
      89: invokevirtual #18                 // Method java/lang/String.length:()I
      92: if_icmple     99
      95: aload         8
      97: astore        6
      99: goto          45
     102: aload         6
     104: ifnull        131
     107: aload_1
     108: aload         4
     110: aload         6
     112: invokeinterface #19,  2           // InterfaceMethod java/util/Map.get:(Ljava/lang/Object;)Ljava/lang/Object;
     117: checkcast     #20                 // class org/joda/time/DateTimeZone
     120: invokevirtual #21                 // Method org/joda/time/format/DateTimeParserBucket.setZone:(Lorg/joda/time/DateTimeZone;)V
     123: iload_3
     124: aload         6
     126: invokevirtual #18                 // Method java/lang/String.length:()I
     129: iadd
     130: ireturn
     131: iload_3
     132: iconst_m1
     133: ixor
     134: ireturn
}
