Compiled from "Equivalence.java"
public final class org.sonar.api.internal.google.common.base.Equivalence$Wrapper<T> implements java.io.Serializable {
  private final org.sonar.api.internal.google.common.base.Equivalence<? super T> equivalence;

  private final T reference;

  private static final long serialVersionUID;

  private org.sonar.api.internal.google.common.base.Equivalence$Wrapper(org.sonar.api.internal.google.common.base.Equivalence<? super T>, T);
    Code:
       0: aload_0
       1: invokespecial #29                 // Method java/lang/Object."<init>":()V
       4: aload_0
       5: aload_1
       6: invokestatic  #35                 // Method org/sonar/api/internal/google/common/base/Preconditions.checkNotNull:(Ljava/lang/Object;)Ljava/lang/Object;
       9: checkcast     #10                 // class org/sonar/api/internal/google/common/base/Equivalence
      12: putfield      #37                 // Field equivalence:Lorg/sonar/api/internal/google/common/base/Equivalence;
      15: aload_0
      16: aload_2
      17: putfield      #39                 // Field reference:Ljava/lang/Object;
      20: return

  public T get();
    Code:
       0: aload_0
       1: getfield      #39                 // Field reference:Ljava/lang/Object;
       4: areturn

  public boolean equals(java.lang.Object);
    Code:
       0: aload_1
       1: aload_0
       2: if_acmpne     7
       5: iconst_1
       6: ireturn
       7: aload_1
       8: instanceof    #2                  // class org/sonar/api/internal/google/common/base/Equivalence$Wrapper
      11: ifeq          51
      14: aload_1
      15: checkcast     #2                  // class org/sonar/api/internal/google/common/base/Equivalence$Wrapper
      18: astore_2
      19: aload_0
      20: getfield      #37                 // Field equivalence:Lorg/sonar/api/internal/google/common/base/Equivalence;
      23: aload_2
      24: getfield      #37                 // Field equivalence:Lorg/sonar/api/internal/google/common/base/Equivalence;
      27: invokevirtual #48                 // Method java/lang/Object.equals:(Ljava/lang/Object;)Z
      30: ifeq          51
      33: aload_0
      34: getfield      #37                 // Field equivalence:Lorg/sonar/api/internal/google/common/base/Equivalence;
      37: astore_3
      38: aload_3
      39: aload_0
      40: getfield      #39                 // Field reference:Ljava/lang/Object;
      43: aload_2
      44: getfield      #39                 // Field reference:Ljava/lang/Object;
      47: invokevirtual #52                 // Method org/sonar/api/internal/google/common/base/Equivalence.equivalent:(Ljava/lang/Object;Ljava/lang/Object;)Z
      50: ireturn
      51: iconst_0
      52: ireturn

  public int hashCode();
    Code:
       0: aload_0
       1: getfield      #37                 // Field equivalence:Lorg/sonar/api/internal/google/common/base/Equivalence;
       4: aload_0
       5: getfield      #39                 // Field reference:Ljava/lang/Object;
       8: invokevirtual #62                 // Method org/sonar/api/internal/google/common/base/Equivalence.hash:(Ljava/lang/Object;)I
      11: ireturn

  public java.lang.String toString();
    Code:
       0: aload_0
       1: getfield      #37                 // Field equivalence:Lorg/sonar/api/internal/google/common/base/Equivalence;
       4: invokestatic  #70                 // Method java/lang/String.valueOf:(Ljava/lang/Object;)Ljava/lang/String;
       7: invokestatic  #70                 // Method java/lang/String.valueOf:(Ljava/lang/Object;)Ljava/lang/String;
      10: astore_1
      11: aload_0
      12: getfield      #39                 // Field reference:Ljava/lang/Object;
      15: invokestatic  #70                 // Method java/lang/String.valueOf:(Ljava/lang/Object;)Ljava/lang/String;
      18: invokestatic  #70                 // Method java/lang/String.valueOf:(Ljava/lang/Object;)Ljava/lang/String;
      21: astore_2
      22: new           #72                 // class java/lang/StringBuilder
      25: dup
      26: bipush        7
      28: aload_1
      29: invokevirtual #75                 // Method java/lang/String.length:()I
      32: iadd
      33: aload_2
      34: invokevirtual #75                 // Method java/lang/String.length:()I
      37: iadd
      38: invokespecial #78                 // Method java/lang/StringBuilder."<init>":(I)V
      41: aload_1
      42: invokevirtual #82                 // Method java/lang/StringBuilder.append:(Ljava/lang/String;)Ljava/lang/StringBuilder;
      45: ldc           #84                 // String .wrap(
      47: invokevirtual #82                 // Method java/lang/StringBuilder.append:(Ljava/lang/String;)Ljava/lang/StringBuilder;
      50: aload_2
      51: invokevirtual #82                 // Method java/lang/StringBuilder.append:(Ljava/lang/String;)Ljava/lang/StringBuilder;
      54: ldc           #86                 // String )
      56: invokevirtual #82                 // Method java/lang/StringBuilder.append:(Ljava/lang/String;)Ljava/lang/StringBuilder;
      59: invokevirtual #88                 // Method java/lang/StringBuilder.toString:()Ljava/lang/String;
      62: areturn

  org.sonar.api.internal.google.common.base.Equivalence$Wrapper(org.sonar.api.internal.google.common.base.Equivalence, java.lang.Object, org.sonar.api.internal.google.common.base.Equivalence$1);
    Code:
       0: aload_0
       1: aload_1
       2: aload_2
       3: invokespecial #91                 // Method "<init>":(Lorg/sonar/api/internal/google/common/base/Equivalence;Ljava/lang/Object;)V
       6: return
}
