Compiled from "PairwiseEquivalence.java"
final class org.sonar.api.internal.google.common.base.PairwiseEquivalence<T> extends org.sonar.api.internal.google.common.base.Equivalence<java.lang.Iterable<T>> implements java.io.Serializable {
  final org.sonar.api.internal.google.common.base.Equivalence<? super T> elementEquivalence;

  private static final long serialVersionUID;

  org.sonar.api.internal.google.common.base.PairwiseEquivalence(org.sonar.api.internal.google.common.base.Equivalence<? super T>);
    Code:
       0: aload_0
       1: invokespecial #23                 // Method org/sonar/api/internal/google/common/base/Equivalence."<init>":()V
       4: aload_0
       5: aload_1
       6: invokestatic  #29                 // Method org/sonar/api/internal/google/common/base/Preconditions.checkNotNull:(Ljava/lang/Object;)Ljava/lang/Object;
       9: checkcast     #5                  // class org/sonar/api/internal/google/common/base/Equivalence
      12: putfield      #31                 // Field elementEquivalence:Lorg/sonar/api/internal/google/common/base/Equivalence;
      15: return

  protected boolean doEquivalent(java.lang.Iterable<T>, java.lang.Iterable<T>);
    Code:
       0: aload_1
       1: invokeinterface #42,  1           // InterfaceMethod java/lang/Iterable.iterator:()Ljava/util/Iterator;
       6: astore_3
       7: aload_2
       8: invokeinterface #42,  1           // InterfaceMethod java/lang/Iterable.iterator:()Ljava/util/Iterator;
      13: astore        4
      15: aload_3
      16: invokeinterface #48,  1           // InterfaceMethod java/util/Iterator.hasNext:()Z
      21: ifeq          59
      24: aload         4
      26: invokeinterface #48,  1           // InterfaceMethod java/util/Iterator.hasNext:()Z
      31: ifeq          59
      34: aload_0
      35: getfield      #31                 // Field elementEquivalence:Lorg/sonar/api/internal/google/common/base/Equivalence;
      38: aload_3
      39: invokeinterface #52,  1           // InterfaceMethod java/util/Iterator.next:()Ljava/lang/Object;
      44: aload         4
      46: invokeinterface #52,  1           // InterfaceMethod java/util/Iterator.next:()Ljava/lang/Object;
      51: invokevirtual #56                 // Method org/sonar/api/internal/google/common/base/Equivalence.equivalent:(Ljava/lang/Object;Ljava/lang/Object;)Z
      54: ifne          15
      57: iconst_0
      58: ireturn
      59: aload_3
      60: invokeinterface #48,  1           // InterfaceMethod java/util/Iterator.hasNext:()Z
      65: ifne          82
      68: aload         4
      70: invokeinterface #48,  1           // InterfaceMethod java/util/Iterator.hasNext:()Z
      75: ifne          82
      78: iconst_1
      79: goto          83
      82: iconst_0
      83: ireturn

  protected int doHash(java.lang.Iterable<T>);
    Code:
       0: ldc           #67                 // int 78721
       2: istore_2
       3: aload_1
       4: invokeinterface #42,  1           // InterfaceMethod java/lang/Iterable.iterator:()Ljava/util/Iterator;
       9: astore_3
      10: aload_3
      11: invokeinterface #48,  1           // InterfaceMethod java/util/Iterator.hasNext:()Z
      16: ifeq          46
      19: aload_3
      20: invokeinterface #52,  1           // InterfaceMethod java/util/Iterator.next:()Ljava/lang/Object;
      25: astore        4
      27: iload_2
      28: sipush        24943
      31: imul
      32: aload_0
      33: getfield      #31                 // Field elementEquivalence:Lorg/sonar/api/internal/google/common/base/Equivalence;
      36: aload         4
      38: invokevirtual #71                 // Method org/sonar/api/internal/google/common/base/Equivalence.hash:(Ljava/lang/Object;)I
      41: iadd
      42: istore_2
      43: goto          10
      46: iload_2
      47: ireturn

  public boolean equals(java.lang.Object);
    Code:
       0: aload_1
       1: instanceof    #2                  // class org/sonar/api/internal/google/common/base/PairwiseEquivalence
       4: ifeq          24
       7: aload_1
       8: checkcast     #2                  // class org/sonar/api/internal/google/common/base/PairwiseEquivalence
      11: astore_2
      12: aload_0
      13: getfield      #31                 // Field elementEquivalence:Lorg/sonar/api/internal/google/common/base/Equivalence;
      16: aload_2
      17: getfield      #31                 // Field elementEquivalence:Lorg/sonar/api/internal/google/common/base/Equivalence;
      20: invokevirtual #84                 // Method java/lang/Object.equals:(Ljava/lang/Object;)Z
      23: ireturn
      24: iconst_0
      25: ireturn

  public int hashCode();
    Code:
       0: aload_0
       1: getfield      #31                 // Field elementEquivalence:Lorg/sonar/api/internal/google/common/base/Equivalence;
       4: invokevirtual #91                 // Method java/lang/Object.hashCode:()I
       7: ldc           #92                 // int 1185147655
       9: ixor
      10: ireturn

  public java.lang.String toString();
    Code:
       0: aload_0
       1: getfield      #31                 // Field elementEquivalence:Lorg/sonar/api/internal/google/common/base/Equivalence;
       4: invokestatic  #100                // Method java/lang/String.valueOf:(Ljava/lang/Object;)Ljava/lang/String;
       7: invokestatic  #100                // Method java/lang/String.valueOf:(Ljava/lang/Object;)Ljava/lang/String;
      10: astore_1
      11: new           #102                // class java/lang/StringBuilder
      14: dup
      15: bipush        11
      17: aload_1
      18: invokevirtual #105                // Method java/lang/String.length:()I
      21: iadd
      22: invokespecial #108                // Method java/lang/StringBuilder."<init>":(I)V
      25: aload_1
      26: invokevirtual #112                // Method java/lang/StringBuilder.append:(Ljava/lang/String;)Ljava/lang/StringBuilder;
      29: ldc           #114                // String .pairwise()
      31: invokevirtual #112                // Method java/lang/StringBuilder.append:(Ljava/lang/String;)Ljava/lang/StringBuilder;
      34: invokevirtual #116                // Method java/lang/StringBuilder.toString:()Ljava/lang/String;
      37: areturn

  protected int doHash(java.lang.Object);
    Code:
       0: aload_0
       1: aload_1
       2: checkcast     #38                 // class java/lang/Iterable
       5: invokevirtual #118                // Method doHash:(Ljava/lang/Iterable;)I
       8: ireturn

  protected boolean doEquivalent(java.lang.Object, java.lang.Object);
    Code:
       0: aload_0
       1: aload_1
       2: checkcast     #38                 // class java/lang/Iterable
       5: aload_2
       6: checkcast     #38                 // class java/lang/Iterable
       9: invokevirtual #121                // Method doEquivalent:(Ljava/lang/Iterable;Ljava/lang/Iterable;)Z
      12: ireturn
}
