Compiled from "Tester.java"
public class org.hl7.fhir.dstu3.elementmodel.Tester {
  private static com.google.gson.JsonParser parser;

  public org.hl7.fhir.dstu3.elementmodel.Tester();
    Code:
       0: aload_0
       1: invokespecial #1                  // Method java/lang/Object."<init>":()V
       4: return

  public static void main(java.lang.String[]) throws java.lang.Exception;
    Code:
       0: iconst_2
       1: anewarray     #2                  // class java/lang/String
       4: dup
       5: iconst_0
       6: ldc           #3                  // String C:\\work\\org.hl7.fhir\\build\\publish
       8: aastore
       9: dup
      10: iconst_1
      11: ldc           #4                  // String validation-min.xml.zip
      13: aastore
      14: invokestatic  #5                  // Method org/hl7/fhir/utilities/Utilities.path:([Ljava/lang/String;)Ljava/lang/String;
      17: invokestatic  #6                  // Method org/hl7/fhir/dstu3/context/SimpleWorkerContext.fromPack:(Ljava/lang/String;)Lorg/hl7/fhir/dstu3/context/SimpleWorkerContext;
      20: astore_1
      21: iconst_0
      22: istore_2
      23: iconst_0
      24: istore_3
      25: new           #7                  // class java/io/File
      28: dup
      29: ldc           #3                  // String C:\\work\\org.hl7.fhir\\build\\publish
      31: invokespecial #8                  // Method java/io/File."<init>":(Ljava/lang/String;)V
      34: invokevirtual #9                  // Method java/io/File.list:()[Ljava/lang/String;
      37: astore        4
      39: aload         4
      41: arraylength
      42: istore        5
      44: iconst_0
      45: istore        6
      47: iload         6
      49: iload         5
      51: if_icmpge     369
      54: aload         4
      56: iload         6
      58: aaload
      59: astore        7
      61: aload         7
      63: ldc           #10                 // String .xml
      65: invokevirtual #11                 // Method java/lang/String.endsWith:(Ljava/lang/String;)Z
      68: ifeq          363
      71: aload         7
      73: ldc           #12                 // String .canonical.xml
      75: invokevirtual #11                 // Method java/lang/String.endsWith:(Ljava/lang/String;)Z
      78: ifne          363
      81: aload         7
      83: ldc           #13                 // String profile
      85: invokevirtual #14                 // Method java/lang/String.contains:(Ljava/lang/CharSequence;)Z
      88: ifne          363
      91: aload         7
      93: ldc           #15                 // String questionnaire
      95: invokevirtual #14                 // Method java/lang/String.contains:(Ljava/lang/CharSequence;)Z
      98: ifne          363
     101: new           #7                  // class java/io/File
     104: dup
     105: new           #16                 // class java/lang/StringBuilder
     108: dup
     109: invokespecial #17                 // Method java/lang/StringBuilder."<init>":()V
     112: ldc           #18                 // String C:\\work\\org.hl7.fhir\\build\\publish\\
     114: invokevirtual #19                 // Method java/lang/StringBuilder.append:(Ljava/lang/String;)Ljava/lang/StringBuilder;
     117: aload         7
     119: ldc           #20                 // String .ttl
     121: invokestatic  #21                 // Method org/hl7/fhir/utilities/Utilities.changeFileExt:(Ljava/lang/String;Ljava/lang/String;)Ljava/lang/String;
     124: invokevirtual #19                 // Method java/lang/StringBuilder.append:(Ljava/lang/String;)Ljava/lang/StringBuilder;
     127: invokevirtual #22                 // Method java/lang/StringBuilder.toString:()Ljava/lang/String;
     130: invokespecial #8                  // Method java/io/File."<init>":(Ljava/lang/String;)V
     133: invokevirtual #23                 // Method java/io/File.exists:()Z
     136: ifeq          363
     139: getstatic     #24                 // Field java/lang/System.out:Ljava/io/PrintStream;
     142: new           #16                 // class java/lang/StringBuilder
     145: dup
     146: invokespecial #17                 // Method java/lang/StringBuilder."<init>":()V
     149: ldc           #25                 // String convert
     151: invokevirtual #19                 // Method java/lang/StringBuilder.append:(Ljava/lang/String;)Ljava/lang/StringBuilder;
     154: aload         7
     156: invokevirtual #19                 // Method java/lang/StringBuilder.append:(Ljava/lang/String;)Ljava/lang/StringBuilder;
     159: invokevirtual #22                 // Method java/lang/StringBuilder.toString:()Ljava/lang/String;
     162: invokevirtual #26                 // Method java/io/PrintStream.print:(Ljava/lang/String;)V
     165: aload_1
     166: new           #27                 // class java/io/FileInputStream
     169: dup
     170: new           #16                 // class java/lang/StringBuilder
     173: dup
     174: invokespecial #17                 // Method java/lang/StringBuilder."<init>":()V
     177: ldc           #18                 // String C:\\work\\org.hl7.fhir\\build\\publish\\
     179: invokevirtual #19                 // Method java/lang/StringBuilder.append:(Ljava/lang/String;)Ljava/lang/StringBuilder;
     182: aload         7
     184: invokevirtual #19                 // Method java/lang/StringBuilder.append:(Ljava/lang/String;)Ljava/lang/StringBuilder;
     187: invokevirtual #22                 // Method java/lang/StringBuilder.toString:()Ljava/lang/String;
     190: invokespecial #28                 // Method java/io/FileInputStream."<init>":(Ljava/lang/String;)V
     193: getstatic     #29                 // Field org/hl7/fhir/dstu3/elementmodel/Manager$FhirFormat.XML:Lorg/hl7/fhir/dstu3/elementmodel/Manager$FhirFormat;
     196: invokestatic  #30                 // Method org/hl7/fhir/dstu3/elementmodel/Manager.parse:(Lorg/hl7/fhir/dstu3/context/IWorkerContext;Ljava/io/InputStream;Lorg/hl7/fhir/dstu3/elementmodel/Manager$FhirFormat;)Lorg/hl7/fhir/dstu3/elementmodel/Element;
     199: astore        8
     201: aload_1
     202: aload         8
     204: new           #31                 // class java/io/FileOutputStream
     207: dup
     208: new           #16                 // class java/lang/StringBuilder
     211: dup
     212: invokespecial #17                 // Method java/lang/StringBuilder."<init>":()V
     215: ldc           #18                 // String C:\\work\\org.hl7.fhir\\build\\publish\\
     217: invokevirtual #19                 // Method java/lang/StringBuilder.append:(Ljava/lang/String;)Ljava/lang/StringBuilder;
     220: aload         7
     222: ldc           #32                 // String .mm.ttl
     224: invokestatic  #21                 // Method org/hl7/fhir/utilities/Utilities.changeFileExt:(Ljava/lang/String;Ljava/lang/String;)Ljava/lang/String;
     227: invokevirtual #19                 // Method java/lang/StringBuilder.append:(Ljava/lang/String;)Ljava/lang/StringBuilder;
     230: invokevirtual #22                 // Method java/lang/StringBuilder.toString:()Ljava/lang/String;
     233: invokespecial #33                 // Method java/io/FileOutputStream."<init>":(Ljava/lang/String;)V
     236: getstatic     #34                 // Field org/hl7/fhir/dstu3/elementmodel/Manager$FhirFormat.TURTLE:Lorg/hl7/fhir/dstu3/elementmodel/Manager$FhirFormat;
     239: getstatic     #35                 // Field org/hl7/fhir/dstu3/formats/IParser$OutputStyle.PRETTY:Lorg/hl7/fhir/dstu3/formats/IParser$OutputStyle;
     242: aconst_null
     243: invokestatic  #36                 // Method org/hl7/fhir/dstu3/elementmodel/Manager.compose:(Lorg/hl7/fhir/dstu3/context/IWorkerContext;Lorg/hl7/fhir/dstu3/elementmodel/Element;Ljava/io/OutputStream;Lorg/hl7/fhir/dstu3/elementmodel/Manager$FhirFormat;Lorg/hl7/fhir/dstu3/formats/IParser$OutputStyle;Ljava/lang/String;)V
     246: aload_1
     247: aload         8
     249: new           #31                 // class java/io/FileOutputStream
     252: dup
     253: ldc           #37                 // String C:\\temp\\resource.xml
     255: invokespecial #33                 // Method java/io/FileOutputStream."<init>":(Ljava/lang/String;)V
     258: getstatic     #29                 // Field org/hl7/fhir/dstu3/elementmodel/Manager$FhirFormat.XML:Lorg/hl7/fhir/dstu3/elementmodel/Manager$FhirFormat;
     261: getstatic     #35                 // Field org/hl7/fhir/dstu3/formats/IParser$OutputStyle.PRETTY:Lorg/hl7/fhir/dstu3/formats/IParser$OutputStyle;
     264: aconst_null
     265: invokestatic  #36                 // Method org/hl7/fhir/dstu3/elementmodel/Manager.compose:(Lorg/hl7/fhir/dstu3/context/IWorkerContext;Lorg/hl7/fhir/dstu3/elementmodel/Element;Ljava/io/OutputStream;Lorg/hl7/fhir/dstu3/elementmodel/Manager$FhirFormat;Lorg/hl7/fhir/dstu3/formats/IParser$OutputStyle;Ljava/lang/String;)V
     268: new           #16                 // class java/lang/StringBuilder
     271: dup
     272: invokespecial #17                 // Method java/lang/StringBuilder."<init>":()V
     275: ldc           #18                 // String C:\\work\\org.hl7.fhir\\build\\publish\\
     277: invokevirtual #19                 // Method java/lang/StringBuilder.append:(Ljava/lang/String;)Ljava/lang/StringBuilder;
     280: aload         7
     282: ldc           #32                 // String .mm.ttl
     284: invokestatic  #21                 // Method org/hl7/fhir/utilities/Utilities.changeFileExt:(Ljava/lang/String;Ljava/lang/String;)Ljava/lang/String;
     287: invokevirtual #19                 // Method java/lang/StringBuilder.append:(Ljava/lang/String;)Ljava/lang/StringBuilder;
     290: invokevirtual #22                 // Method java/lang/StringBuilder.toString:()Ljava/lang/String;
     293: invokestatic  #38                 // Method org/hl7/fhir/utilities/TextFile.fileToString:(Ljava/lang/String;)Ljava/lang/String;
     296: astore        9
     298: new           #16                 // class java/lang/StringBuilder
     301: dup
     302: invokespecial #17                 // Method java/lang/StringBuilder."<init>":()V
     305: ldc           #18                 // String C:\\work\\org.hl7.fhir\\build\\publish\\
     307: invokevirtual #19                 // Method java/lang/StringBuilder.append:(Ljava/lang/String;)Ljava/lang/StringBuilder;
     310: aload         7
     312: ldc           #20                 // String .ttl
     314: invokestatic  #21                 // Method org/hl7/fhir/utilities/Utilities.changeFileExt:(Ljava/lang/String;Ljava/lang/String;)Ljava/lang/String;
     317: invokevirtual #19                 // Method java/lang/StringBuilder.append:(Ljava/lang/String;)Ljava/lang/StringBuilder;
     320: invokevirtual #22                 // Method java/lang/StringBuilder.toString:()Ljava/lang/String;
     323: invokestatic  #38                 // Method org/hl7/fhir/utilities/TextFile.fileToString:(Ljava/lang/String;)Ljava/lang/String;
     326: astore        10
     328: iinc          2, 1
     331: aload         9
     333: aload         10
     335: invokevirtual #39                 // Method java/lang/String.equals:(Ljava/lang/Object;)Z
     338: ifeq          355
     341: getstatic     #24                 // Field java/lang/System.out:Ljava/io/PrintStream;
     344: ldc           #40                 // String .. ok
     346: invokevirtual #41                 // Method java/io/PrintStream.println:(Ljava/lang/String;)V
     349: iinc          3, 1
     352: goto          363
     355: getstatic     #24                 // Field java/lang/System.out:Ljava/io/PrintStream;
     358: ldc           #42                 // String .. fail
     360: invokevirtual #41                 // Method java/io/PrintStream.println:(Ljava/lang/String;)V
     363: iinc          6, 1
     366: goto          47
     369: getstatic     #24                 // Field java/lang/System.out:Ljava/io/PrintStream;
     372: new           #16                 // class java/lang/StringBuilder
     375: dup
     376: invokespecial #17                 // Method java/lang/StringBuilder."<init>":()V
     379: ldc           #43                 // String done -
     381: invokevirtual #19                 // Method java/lang/StringBuilder.append:(Ljava/lang/String;)Ljava/lang/StringBuilder;
     384: iload_2
     385: invokestatic  #44                 // Method java/lang/Integer.toString:(I)Ljava/lang/String;
     388: invokevirtual #19                 // Method java/lang/StringBuilder.append:(Ljava/lang/String;)Ljava/lang/StringBuilder;
     391: ldc           #45                 // String  files,
     393: invokevirtual #19                 // Method java/lang/StringBuilder.append:(Ljava/lang/String;)Ljava/lang/StringBuilder;
     396: iload_3
     397: invokestatic  #44                 // Method java/lang/Integer.toString:(I)Ljava/lang/String;
     400: invokevirtual #19                 // Method java/lang/StringBuilder.append:(Ljava/lang/String;)Ljava/lang/StringBuilder;
     403: ldc           #46                 // String  ok
     405: invokevirtual #19                 // Method java/lang/StringBuilder.append:(Ljava/lang/String;)Ljava/lang/StringBuilder;
     408: invokevirtual #22                 // Method java/lang/StringBuilder.toString:()Ljava/lang/String;
     411: invokevirtual #41                 // Method java/io/PrintStream.println:(Ljava/lang/String;)V
     414: return

  private static java.lang.String normalise(java.lang.String);
    Code:
       0: getstatic     #47                 // Field parser:Lcom/google/gson/JsonParser;
       3: aload_0
       4: invokevirtual #48                 // Method com/google/gson/JsonParser.parse:(Ljava/lang/String;)Lcom/google/gson/JsonElement;
       7: invokevirtual #49                 // Method com/google/gson/JsonElement.getAsJsonObject:()Lcom/google/gson/JsonObject;
      10: astore_1
      11: aload_1
      12: ldc           #50                 // String text
      14: invokevirtual #51                 // Method com/google/gson/JsonObject.get:(Ljava/lang/String;)Lcom/google/gson/JsonElement;
      17: astore_2
      18: aload_2
      19: ifnull        44
      22: aload_2
      23: checkcast     #52                 // class com/google/gson/JsonObject
      26: ldc           #53                 // String div
      28: invokevirtual #54                 // Method com/google/gson/JsonObject.has:(Ljava/lang/String;)Z
      31: ifeq          44
      34: aload_2
      35: checkcast     #52                 // class com/google/gson/JsonObject
      38: ldc           #53                 // String div
      40: invokevirtual #55                 // Method com/google/gson/JsonObject.remove:(Ljava/lang/String;)Lcom/google/gson/JsonElement;
      43: pop
      44: aload_1
      45: invokestatic  #56                 // Method removeComments:(Lcom/google/gson/JsonObject;)V
      48: aload_1
      49: invokevirtual #57                 // Method com/google/gson/JsonObject.toString:()Ljava/lang/String;
      52: areturn

  private static void removeComments(com.google.gson.JsonArray);
    Code:
       0: aload_0
       1: invokevirtual #58                 // Method com/google/gson/JsonArray.iterator:()Ljava/util/Iterator;
       4: astore_1
       5: aload_1
       6: invokeinterface #59,  1           // InterfaceMethod java/util/Iterator.hasNext:()Z
      11: ifeq          55
      14: aload_1
      15: invokeinterface #60,  1           // InterfaceMethod java/util/Iterator.next:()Ljava/lang/Object;
      20: checkcast     #61                 // class com/google/gson/JsonElement
      23: astore_2
      24: aload_2
      25: instanceof    #52                 // class com/google/gson/JsonObject
      28: ifeq          38
      31: aload_2
      32: checkcast     #52                 // class com/google/gson/JsonObject
      35: invokestatic  #56                 // Method removeComments:(Lcom/google/gson/JsonObject;)V
      38: aload_2
      39: instanceof    #62                 // class com/google/gson/JsonArray
      42: ifeq          52
      45: aload_2
      46: checkcast     #62                 // class com/google/gson/JsonArray
      49: invokestatic  #63                 // Method removeComments:(Lcom/google/gson/JsonArray;)V
      52: goto          5
      55: return

  private static void removeComments(com.google.gson.JsonObject);
    Code:
       0: aload_0
       1: ldc           #64                 // String fhir_comments
       3: invokevirtual #54                 // Method com/google/gson/JsonObject.has:(Ljava/lang/String;)Z
       6: ifeq          16
       9: aload_0
      10: ldc           #64                 // String fhir_comments
      12: invokevirtual #55                 // Method com/google/gson/JsonObject.remove:(Ljava/lang/String;)Lcom/google/gson/JsonElement;
      15: pop
      16: aload_0
      17: invokevirtual #65                 // Method com/google/gson/JsonObject.entrySet:()Ljava/util/Set;
      20: invokeinterface #66,  1           // InterfaceMethod java/util/Set.iterator:()Ljava/util/Iterator;
      25: astore_1
      26: aload_1
      27: invokeinterface #59,  1           // InterfaceMethod java/util/Iterator.hasNext:()Z
      32: ifeq          96
      35: aload_1
      36: invokeinterface #60,  1           // InterfaceMethod java/util/Iterator.next:()Ljava/lang/Object;
      41: checkcast     #67                 // class java/util/Map$Entry
      44: astore_2
      45: aload_2
      46: invokeinterface #68,  1           // InterfaceMethod java/util/Map$Entry.getValue:()Ljava/lang/Object;
      51: instanceof    #52                 // class com/google/gson/JsonObject
      54: ifeq          69
      57: aload_2
      58: invokeinterface #68,  1           // InterfaceMethod java/util/Map$Entry.getValue:()Ljava/lang/Object;
      63: checkcast     #52                 // class com/google/gson/JsonObject
      66: invokestatic  #56                 // Method removeComments:(Lcom/google/gson/JsonObject;)V
      69: aload_2
      70: invokeinterface #68,  1           // InterfaceMethod java/util/Map$Entry.getValue:()Ljava/lang/Object;
      75: instanceof    #62                 // class com/google/gson/JsonArray
      78: ifeq          93
      81: aload_2
      82: invokeinterface #68,  1           // InterfaceMethod java/util/Map$Entry.getValue:()Ljava/lang/Object;
      87: checkcast     #62                 // class com/google/gson/JsonArray
      90: invokestatic  #63                 // Method removeComments:(Lcom/google/gson/JsonArray;)V
      93: goto          26
      96: return

  static {};
    Code:
       0: new           #69                 // class com/google/gson/JsonParser
       3: dup
       4: invokespecial #70                 // Method com/google/gson/JsonParser."<init>":()V
       7: putstatic     #47                 // Field parser:Lcom/google/gson/JsonParser;
      10: return
}
