Compiled from "HotSwapper.java"
class javassist.util.HotSwapper$1 extends java.lang.Thread {
  final javassist.util.HotSwapper this$0;

  javassist.util.HotSwapper$1(javassist.util.HotSwapper);
    Code:
       0: aload_0
       1: aload_1
       2: putfield      #1                  // Field this$0:Ljavassist/util/HotSwapper;
       5: aload_0
       6: invokespecial #2                  // Method java/lang/Thread."<init>":()V
       9: return

  private void errorMsg(java.lang.Throwable);
    Code:
       0: getstatic     #3                  // Field java/lang/System.err:Ljava/io/PrintStream;
       3: ldc           #4                  // String Exception in thread \"HotSwap\"
       5: invokevirtual #5                  // Method java/io/PrintStream.print:(Ljava/lang/String;)V
       8: aload_1
       9: getstatic     #3                  // Field java/lang/System.err:Ljava/io/PrintStream;
      12: invokevirtual #6                  // Method java/lang/Throwable.printStackTrace:(Ljava/io/PrintStream;)V
      15: return

  public void run();
    Code:
       0: aconst_null
       1: astore_1
       2: aload_0
       3: getfield      #1                  // Field this$0:Ljavassist/util/HotSwapper;
       6: invokevirtual #7                  // Method javassist/util/HotSwapper.waitEvent:()Lcom/sun/jdi/event/EventSet;
       9: astore_1
      10: aload_1
      11: invokeinterface #8,  1            // InterfaceMethod com/sun/jdi/event/EventSet.eventIterator:()Lcom/sun/jdi/event/EventIterator;
      16: astore_2
      17: aload_2
      18: invokeinterface #9,  1            // InterfaceMethod com/sun/jdi/event/EventIterator.hasNext:()Z
      23: ifeq          53
      26: aload_2
      27: invokeinterface #10,  1           // InterfaceMethod com/sun/jdi/event/EventIterator.nextEvent:()Lcom/sun/jdi/event/Event;
      32: astore_3
      33: aload_3
      34: instanceof    #11                 // class com/sun/jdi/event/MethodEntryEvent
      37: ifeq          50
      40: aload_0
      41: getfield      #1                  // Field this$0:Ljavassist/util/HotSwapper;
      44: invokevirtual #12                 // Method javassist/util/HotSwapper.hotswap:()V
      47: goto          53
      50: goto          17
      53: goto          62
      56: astore_2
      57: aload_0
      58: aload_2
      59: invokespecial #14                 // Method errorMsg:(Ljava/lang/Throwable;)V
      62: aload_1
      63: ifnull        72
      66: aload_1
      67: invokeinterface #15,  1           // InterfaceMethod com/sun/jdi/event/EventSet.resume:()V
      72: goto          81
      75: astore_2
      76: aload_0
      77: aload_2
      78: invokespecial #14                 // Method errorMsg:(Ljava/lang/Throwable;)V
      81: return
    Exception table:
       from    to  target type
           2    53    56   Class java/lang/Throwable
          62    72    75   Class java/lang/Throwable
}
