Compiled from "DefaultTextPointer.java"
public class org.sonar.api.batch.fs.internal.DefaultTextPointer implements org.sonar.api.batch.fs.TextPointer {
  private final int line;

  private final int lineOffset;

  public org.sonar.api.batch.fs.internal.DefaultTextPointer(int, int);
    Code:
       0: aload_0
       1: invokespecial #15                 // Method java/lang/Object."<init>":()V
       4: aload_0
       5: iload_1
       6: putfield      #17                 // Field line:I
       9: aload_0
      10: iload_2
      11: putfield      #19                 // Field lineOffset:I
      14: return

  public int line();
    Code:
       0: aload_0
       1: getfield      #17                 // Field line:I
       4: ireturn

  public int lineOffset();
    Code:
       0: aload_0
       1: getfield      #19                 // Field lineOffset:I
       4: ireturn

  public java.lang.String toString();
    Code:
       0: new           #26                 // class java/lang/StringBuilder
       3: dup
       4: invokespecial #27                 // Method java/lang/StringBuilder."<init>":()V
       7: ldc           #29                 // String [line=
       9: invokevirtual #33                 // Method java/lang/StringBuilder.append:(Ljava/lang/String;)Ljava/lang/StringBuilder;
      12: aload_0
      13: getfield      #17                 // Field line:I
      16: invokevirtual #36                 // Method java/lang/StringBuilder.append:(I)Ljava/lang/StringBuilder;
      19: ldc           #38                 // String , lineOffset=
      21: invokevirtual #33                 // Method java/lang/StringBuilder.append:(Ljava/lang/String;)Ljava/lang/StringBuilder;
      24: aload_0
      25: getfield      #19                 // Field lineOffset:I
      28: invokevirtual #36                 // Method java/lang/StringBuilder.append:(I)Ljava/lang/StringBuilder;
      31: ldc           #40                 // String ]
      33: invokevirtual #33                 // Method java/lang/StringBuilder.append:(Ljava/lang/String;)Ljava/lang/StringBuilder;
      36: invokevirtual #42                 // Method java/lang/StringBuilder.toString:()Ljava/lang/String;
      39: areturn

  public boolean equals(java.lang.Object);
    Code:
       0: aload_1
       1: instanceof    #2                  // class org/sonar/api/batch/fs/internal/DefaultTextPointer
       4: ifne          9
       7: iconst_0
       8: ireturn
       9: aload_1
      10: checkcast     #2                  // class org/sonar/api/batch/fs/internal/DefaultTextPointer
      13: astore_2
      14: aload_2
      15: getfield      #17                 // Field line:I
      18: aload_0
      19: getfield      #17                 // Field line:I
      22: if_icmpne     40
      25: aload_2
      26: getfield      #19                 // Field lineOffset:I
      29: aload_0
      30: getfield      #19                 // Field lineOffset:I
      33: if_icmpne     40
      36: iconst_1
      37: goto          41
      40: iconst_0
      41: ireturn

  public int hashCode();
    Code:
       0: bipush        37
       2: aload_0
       3: getfield      #17                 // Field line:I
       6: imul
       7: aload_0
       8: getfield      #19                 // Field lineOffset:I
      11: iadd
      12: ireturn

  public int compareTo(org.sonar.api.batch.fs.TextPointer);
    Code:
       0: aload_0
       1: getfield      #17                 // Field line:I
       4: aload_1
       5: invokeinterface #52,  1           // InterfaceMethod org/sonar/api/batch/fs/TextPointer.line:()I
      10: if_icmpne     27
      13: aload_0
      14: getfield      #19                 // Field lineOffset:I
      17: aload_1
      18: invokeinterface #54,  1           // InterfaceMethod org/sonar/api/batch/fs/TextPointer.lineOffset:()I
      23: invokestatic  #60                 // Method java/lang/Integer.compare:(II)I
      26: ireturn
      27: aload_0
      28: getfield      #17                 // Field line:I
      31: aload_1
      32: invokeinterface #52,  1           // InterfaceMethod org/sonar/api/batch/fs/TextPointer.line:()I
      37: invokestatic  #60                 // Method java/lang/Integer.compare:(II)I
      40: ireturn

  public int compareTo(java.lang.Object);
    Code:
       0: aload_0
       1: aload_1
       2: checkcast     #6                  // class org/sonar/api/batch/fs/TextPointer
       5: invokevirtual #65                 // Method compareTo:(Lorg/sonar/api/batch/fs/TextPointer;)I
       8: ireturn
}
