Compiled from "FalsePredicate.java"
class org.sonar.api.batch.fs.internal.FalsePredicate extends org.sonar.api.batch.fs.internal.AbstractFilePredicate {
  static final org.sonar.api.batch.fs.FilePredicate FALSE;

  org.sonar.api.batch.fs.internal.FalsePredicate();
    Code:
       0: aload_0
       1: invokespecial #16                 // Method org/sonar/api/batch/fs/internal/AbstractFilePredicate."<init>":()V
       4: return

  public boolean apply(org.sonar.api.batch.fs.InputFile);
    Code:
       0: iconst_0
       1: ireturn

  public java.lang.Iterable<org.sonar.api.batch.fs.InputFile> filter(java.lang.Iterable<org.sonar.api.batch.fs.InputFile>);
    Code:
       0: invokestatic  #30                 // Method java/util/Collections.emptyList:()Ljava/util/List;
       3: areturn

  public java.lang.Iterable<org.sonar.api.batch.fs.InputFile> get(org.sonar.api.batch.fs.FileSystem$Index);
    Code:
       0: invokestatic  #30                 // Method java/util/Collections.emptyList:()Ljava/util/List;
       3: areturn

  static {};
    Code:
       0: new           #2                  // class org/sonar/api/batch/fs/internal/FalsePredicate
       3: dup
       4: invokespecial #39                 // Method "<init>":()V
       7: putstatic     #41                 // Field FALSE:Lorg/sonar/api/batch/fs/FilePredicate;
      10: return
}
