Compiled from "HttpSourceImpl.java"
public class io.mantisrx.runtime.source.http.impl.HttpSourceImpl$Builder<R, E, T> {
  public static final io.mantisrx.runtime.source.http.HttpServerProvider EMPTY_HTTP_SERVER_PROVIDER;

  private io.mantisrx.runtime.source.http.HttpRequestFactory<R> requestFactory;

  private io.mantisrx.runtime.source.http.HttpServerProvider serverProvider;

  private io.mantisrx.runtime.source.http.HttpClientFactory<R, E> httpClientFactory;

  private rx.Observer<io.mantisrx.runtime.source.http.impl.HttpSourceImpl$HttpSourceEvent> observer;

  private rx.functions.Func2<io.mantisrx.runtime.source.http.impl.ServerContext<mantis.io.reactivex.netty.protocol.http.client.HttpClientResponse<E>>, E, T> postProcessor;

  private io.mantisrx.runtime.source.http.ClientResumePolicy<R, E> clientResumePolicy;

  public io.mantisrx.runtime.source.http.impl.HttpSourceImpl$Builder(io.mantisrx.runtime.source.http.HttpClientFactory<R, E>, io.mantisrx.runtime.source.http.HttpRequestFactory<R>, rx.functions.Func2<io.mantisrx.runtime.source.http.impl.ServerContext<mantis.io.reactivex.netty.protocol.http.client.HttpClientResponse<E>>, E, T>);
    Code:
       0: aload_0
       1: invokespecial #1                  // Method java/lang/Object."<init>":()V
       4: aload_0
       5: aload_2
       6: putfield      #2                  // Field requestFactory:Lio/mantisrx/runtime/source/http/HttpRequestFactory;
       9: aload_0
      10: aload_1
      11: putfield      #3                  // Field httpClientFactory:Lio/mantisrx/runtime/source/http/HttpClientFactory;
      14: aload_0
      15: getstatic     #4                  // Field EMPTY_HTTP_SERVER_PROVIDER:Lio/mantisrx/runtime/source/http/HttpServerProvider;
      18: putfield      #5                  // Field serverProvider:Lio/mantisrx/runtime/source/http/HttpServerProvider;
      21: aload_0
      22: aload_3
      23: putfield      #6                  // Field postProcessor:Lrx/functions/Func2;
      26: aload_0
      27: new           #7                  // class io/mantisrx/runtime/source/http/impl/HttpSourceImpl$Builder$2
      30: dup
      31: aload_0
      32: invokespecial #8                  // Method io/mantisrx/runtime/source/http/impl/HttpSourceImpl$Builder$2."<init>":(Lio/mantisrx/runtime/source/http/impl/HttpSourceImpl$Builder;)V
      35: putfield      #9                  // Field clientResumePolicy:Lio/mantisrx/runtime/source/http/ClientResumePolicy;
      38: aload_0
      39: invokestatic  #10                 // Method rx/subjects/PublishSubject.create:()Lrx/subjects/PublishSubject;
      42: putfield      #11                 // Field observer:Lrx/Observer;
      45: return

  public io.mantisrx.runtime.source.http.impl.HttpSourceImpl$Builder(io.mantisrx.runtime.source.http.HttpClientFactory<R, E>, io.mantisrx.runtime.source.http.HttpRequestFactory<R>, rx.functions.Func2<io.mantisrx.runtime.source.http.impl.ServerContext<mantis.io.reactivex.netty.protocol.http.client.HttpClientResponse<E>>, E, T>, io.mantisrx.runtime.source.http.ClientResumePolicy<R, E>);
    Code:
       0: aload_0
       1: invokespecial #1                  // Method java/lang/Object."<init>":()V
       4: aload_0
       5: aload_2
       6: putfield      #2                  // Field requestFactory:Lio/mantisrx/runtime/source/http/HttpRequestFactory;
       9: aload_0
      10: aload_1
      11: putfield      #3                  // Field httpClientFactory:Lio/mantisrx/runtime/source/http/HttpClientFactory;
      14: aload_0
      15: getstatic     #4                  // Field EMPTY_HTTP_SERVER_PROVIDER:Lio/mantisrx/runtime/source/http/HttpServerProvider;
      18: putfield      #5                  // Field serverProvider:Lio/mantisrx/runtime/source/http/HttpServerProvider;
      21: aload_0
      22: aload_3
      23: putfield      #6                  // Field postProcessor:Lrx/functions/Func2;
      26: aload_0
      27: aload         4
      29: putfield      #9                  // Field clientResumePolicy:Lio/mantisrx/runtime/source/http/ClientResumePolicy;
      32: aload_0
      33: invokestatic  #10                 // Method rx/subjects/PublishSubject.create:()Lrx/subjects/PublishSubject;
      36: putfield      #11                 // Field observer:Lrx/Observer;
      39: return

  public io.mantisrx.runtime.source.http.impl.HttpSourceImpl$Builder<R, E, T> withServerProvider(io.mantisrx.runtime.source.http.HttpServerProvider);
    Code:
       0: aload_0
       1: aload_1
       2: putfield      #5                  // Field serverProvider:Lio/mantisrx/runtime/source/http/HttpServerProvider;
       5: aload_0
       6: areturn

  public io.mantisrx.runtime.source.http.impl.HttpSourceImpl$Builder<R, E, T> withActivityObserver(rx.Observer<io.mantisrx.runtime.source.http.impl.HttpSourceImpl$HttpSourceEvent>);
    Code:
       0: aload_0
       1: aload_1
       2: putfield      #11                 // Field observer:Lrx/Observer;
       5: aload_0
       6: areturn

  public io.mantisrx.runtime.source.http.impl.HttpSourceImpl$Builder<R, E, T> resumeWith(io.mantisrx.runtime.source.http.ClientResumePolicy<R, E>);
    Code:
       0: aload_0
       1: aload_1
       2: putfield      #9                  // Field clientResumePolicy:Lio/mantisrx/runtime/source/http/ClientResumePolicy;
       5: aload_0
       6: areturn

  public io.mantisrx.runtime.source.http.impl.HttpSourceImpl<R, E, T> build();
    Code:
       0: new           #12                 // class io/mantisrx/runtime/source/http/impl/HttpSourceImpl
       3: dup
       4: aload_0
       5: getfield      #2                  // Field requestFactory:Lio/mantisrx/runtime/source/http/HttpRequestFactory;
       8: aload_0
       9: getfield      #5                  // Field serverProvider:Lio/mantisrx/runtime/source/http/HttpServerProvider;
      12: aload_0
      13: getfield      #3                  // Field httpClientFactory:Lio/mantisrx/runtime/source/http/HttpClientFactory;
      16: aload_0
      17: getfield      #11                 // Field observer:Lrx/Observer;
      20: aload_0
      21: getfield      #6                  // Field postProcessor:Lrx/functions/Func2;
      24: aload_0
      25: getfield      #9                  // Field clientResumePolicy:Lio/mantisrx/runtime/source/http/ClientResumePolicy;
      28: invokespecial #13                 // Method io/mantisrx/runtime/source/http/impl/HttpSourceImpl."<init>":(Lio/mantisrx/runtime/source/http/HttpRequestFactory;Lio/mantisrx/runtime/source/http/HttpServerProvider;Lio/mantisrx/runtime/source/http/HttpClientFactory;Lrx/Observer;Lrx/functions/Func2;Lio/mantisrx/runtime/source/http/ClientResumePolicy;)V
      31: areturn

  static {};
    Code:
       0: new           #14                 // class io/mantisrx/runtime/source/http/impl/HttpSourceImpl$Builder$1
       3: dup
       4: invokespecial #15                 // Method io/mantisrx/runtime/source/http/impl/HttpSourceImpl$Builder$1."<init>":()V
       7: putstatic     #4                  // Field EMPTY_HTTP_SERVER_PROVIDER:Lio/mantisrx/runtime/source/http/HttpServerProvider;
      10: return
}
