Compiled from "FailOnTimeout.java"
public class org.junit.internal.runners.statements.FailOnTimeout$Builder {
  private boolean lookForStuckThread;

  private long timeout;

  private java.util.concurrent.TimeUnit unit;

  private org.junit.internal.runners.statements.FailOnTimeout$Builder();
    Code:
       0: aload_0
       1: invokespecial #5                  // Method java/lang/Object."<init>":()V
       4: aload_0
       5: iconst_0
       6: putfield      #1                  // Field lookForStuckThread:Z
       9: aload_0
      10: lconst_0
      11: putfield      #3                  // Field timeout:J
      14: aload_0
      15: getstatic     #6                  // Field java/util/concurrent/TimeUnit.SECONDS:Ljava/util/concurrent/TimeUnit;
      18: putfield      #2                  // Field unit:Ljava/util/concurrent/TimeUnit;
      21: return

  public org.junit.internal.runners.statements.FailOnTimeout$Builder withTimeout(long, java.util.concurrent.TimeUnit);
    Code:
       0: lload_1
       1: lconst_0
       2: lcmp
       3: ifge          16
       6: new           #7                  // class java/lang/IllegalArgumentException
       9: dup
      10: ldc           #8                  // String timeout must be non-negative
      12: invokespecial #9                  // Method java/lang/IllegalArgumentException."<init>":(Ljava/lang/String;)V
      15: athrow
      16: aload_3
      17: ifnonnull     30
      20: new           #10                 // class java/lang/NullPointerException
      23: dup
      24: ldc           #11                 // String TimeUnit cannot be null
      26: invokespecial #12                 // Method java/lang/NullPointerException."<init>":(Ljava/lang/String;)V
      29: athrow
      30: aload_0
      31: lload_1
      32: putfield      #3                  // Field timeout:J
      35: aload_0
      36: aload_3
      37: putfield      #2                  // Field unit:Ljava/util/concurrent/TimeUnit;
      40: aload_0
      41: areturn

  public org.junit.internal.runners.statements.FailOnTimeout$Builder withLookingForStuckThread(boolean);
    Code:
       0: aload_0
       1: iload_1
       2: putfield      #1                  // Field lookForStuckThread:Z
       5: aload_0
       6: areturn

  public org.junit.internal.runners.statements.FailOnTimeout build(org.junit.runners.model.Statement);
    Code:
       0: aload_1
       1: ifnonnull     14
       4: new           #10                 // class java/lang/NullPointerException
       7: dup
       8: ldc           #13                 // String statement cannot be null
      10: invokespecial #12                 // Method java/lang/NullPointerException."<init>":(Ljava/lang/String;)V
      13: athrow
      14: new           #14                 // class org/junit/internal/runners/statements/FailOnTimeout
      17: dup
      18: aload_0
      19: aload_1
      20: aconst_null
      21: invokespecial #15                 // Method org/junit/internal/runners/statements/FailOnTimeout."<init>":(Lorg/junit/internal/runners/statements/FailOnTimeout$Builder;Lorg/junit/runners/model/Statement;Lorg/junit/internal/runners/statements/FailOnTimeout$1;)V
      24: areturn

  org.junit.internal.runners.statements.FailOnTimeout$Builder(org.junit.internal.runners.statements.FailOnTimeout$1);
    Code:
       0: aload_0
       1: invokespecial #4                  // Method "<init>":()V
       4: return

  static long access$100(org.junit.internal.runners.statements.FailOnTimeout$Builder);
    Code:
       0: aload_0
       1: getfield      #3                  // Field timeout:J
       4: lreturn

  static java.util.concurrent.TimeUnit access$200(org.junit.internal.runners.statements.FailOnTimeout$Builder);
    Code:
       0: aload_0
       1: getfield      #2                  // Field unit:Ljava/util/concurrent/TimeUnit;
       4: areturn

  static boolean access$300(org.junit.internal.runners.statements.FailOnTimeout$Builder);
    Code:
       0: aload_0
       1: getfield      #1                  // Field lookForStuckThread:Z
       4: ireturn
}
