Compiled from "HtmlSerializer.java"
public abstract class org.htmlcleaner.HtmlSerializer extends org.htmlcleaner.Serializer {
  private static final java.util.Map<java.lang.Character, java.lang.String> RESERVED_XML_CHARS;

  private boolean isReservedXmlChar(char);
    Code:
       0: getstatic     #1                  // Field RESERVED_XML_CHARS:Ljava/util/Map;
       3: iload_1
       4: invokestatic  #2                  // Method java/lang/Character.valueOf:(C)Ljava/lang/Character;
       7: invokeinterface #3,  2            // InterfaceMethod java/util/Map.containsKey:(Ljava/lang/Object;)Z
      12: ireturn

  protected org.htmlcleaner.HtmlSerializer(org.htmlcleaner.CleanerProperties);
    Code:
       0: aload_0
       1: aload_1
       2: invokespecial #4                  // Method org/htmlcleaner/Serializer."<init>":(Lorg/htmlcleaner/CleanerProperties;)V
       5: return

  protected boolean isMinimizedTagSyntax(org.htmlcleaner.TagNode);
    Code:
       0: aload_0
       1: getfield      #5                  // Field props:Lorg/htmlcleaner/CleanerProperties;
       4: invokevirtual #6                  // Method org/htmlcleaner/CleanerProperties.getTagInfoProvider:()Lorg/htmlcleaner/ITagInfoProvider;
       7: aload_1
       8: invokevirtual #7                  // Method org/htmlcleaner/TagNode.getName:()Ljava/lang/String;
      11: invokeinterface #8,  2            // InterfaceMethod org/htmlcleaner/ITagInfoProvider.getTagInfo:(Ljava/lang/String;)Lorg/htmlcleaner/TagInfo;
      16: astore_2
      17: aload_2
      18: ifnull        39
      21: aload_1
      22: invokevirtual #9                  // Method org/htmlcleaner/TagNode.hasChildren:()Z
      25: ifne          39
      28: aload_2
      29: invokevirtual #10                 // Method org/htmlcleaner/TagInfo.isEmptyTag:()Z
      32: ifeq          39
      35: iconst_1
      36: goto          40
      39: iconst_0
      40: ireturn

  protected boolean dontEscape(org.htmlcleaner.TagNode);
    Code:
       0: aload_0
       1: aload_1
       2: invokevirtual #11                 // Method isScriptOrStyle:(Lorg/htmlcleaner/TagNode;)Z
       5: ireturn

  protected java.lang.String escapeText(java.lang.String);
    Code:
       0: aload_0
       1: getfield      #5                  // Field props:Lorg/htmlcleaner/CleanerProperties;
       4: invokevirtual #12                 // Method org/htmlcleaner/CleanerProperties.isRecognizeUnicodeChars:()Z
       7: istore_2
       8: aload_0
       9: getfield      #5                  // Field props:Lorg/htmlcleaner/CleanerProperties;
      12: invokevirtual #13                 // Method org/htmlcleaner/CleanerProperties.isTranslateSpecialEntities:()Z
      15: istore_3
      16: aload_1
      17: ifnull        773
      20: aload_1
      21: invokevirtual #14                 // Method java/lang/String.length:()I
      24: istore        4
      26: new           #15                 // class java/lang/StringBuilder
      29: dup
      30: iload         4
      32: invokespecial #16                 // Method java/lang/StringBuilder."<init>":(I)V
      35: astore        5
      37: iconst_0
      38: istore        6
      40: iload         6
      42: iload         4
      44: if_icmpge     767
      47: aload_1
      48: iload         6
      50: invokevirtual #17                 // Method java/lang/String.charAt:(I)C
      53: istore        7
      55: iload         7
      57: bipush        38
      59: if_icmpne     692
      62: iload         6
      64: iload         4
      66: iconst_2
      67: isub
      68: if_icmpge     388
      71: aload_1
      72: iload         6
      74: iconst_1
      75: iadd
      76: invokevirtual #17                 // Method java/lang/String.charAt:(I)C
      79: bipush        35
      81: if_icmpne     388
      84: aload_1
      85: iload         6
      87: iconst_2
      88: iadd
      89: invokevirtual #17                 // Method java/lang/String.charAt:(I)C
      92: invokestatic  #18                 // Method java/lang/Character.toLowerCase:(C)C
      95: bipush        120
      97: if_icmpne     104
     100: iconst_1
     101: goto          105
     104: iconst_0
     105: istore        8
     107: iload         6
     109: iload         8
     111: ifeq          118
     114: iconst_3
     115: goto          119
     118: iconst_2
     119: iadd
     120: istore        9
     122: iload         8
     124: ifeq          132
     127: bipush        16
     129: goto          134
     132: bipush        10
     134: istore        10
     136: ldc           #19                 // String
     138: astore        11
     140: iload         9
     142: iload         4
     144: if_icmpge     230
     147: aload_1
     148: iload         9
     150: invokevirtual #17                 // Method java/lang/String.charAt:(I)C
     153: istore        12
     155: iload         12
     157: bipush        59
     159: if_icmpne     165
     162: goto          230
     165: new           #15                 // class java/lang/StringBuilder
     168: dup
     169: invokespecial #20                 // Method java/lang/StringBuilder."<init>":()V
     172: aload         11
     174: invokevirtual #21                 // Method java/lang/StringBuilder.append:(Ljava/lang/String;)Ljava/lang/StringBuilder;
     177: iload         12
     179: invokevirtual #22                 // Method java/lang/StringBuilder.append:(C)Ljava/lang/StringBuilder;
     182: invokevirtual #23                 // Method java/lang/StringBuilder.toString:()Ljava/lang/String;
     185: iload         10
     187: invokestatic  #24                 // Method org/htmlcleaner/Utils.isValidInt:(Ljava/lang/String;I)Z
     190: ifeq          221
     193: new           #15                 // class java/lang/StringBuilder
     196: dup
     197: invokespecial #20                 // Method java/lang/StringBuilder."<init>":()V
     200: aload         11
     202: invokevirtual #21                 // Method java/lang/StringBuilder.append:(Ljava/lang/String;)Ljava/lang/StringBuilder;
     205: iload         12
     207: invokevirtual #22                 // Method java/lang/StringBuilder.append:(C)Ljava/lang/StringBuilder;
     210: invokevirtual #23                 // Method java/lang/StringBuilder.toString:()Ljava/lang/String;
     213: astore        11
     215: iinc          9, 1
     218: goto          227
     221: iinc          9, -1
     224: goto          230
     227: goto          140
     230: aload         11
     232: iload         10
     234: invokestatic  #24                 // Method org/htmlcleaner/Utils.isValidInt:(Ljava/lang/String;I)Z
     237: ifeq          362
     240: aload         11
     242: iload         10
     244: invokestatic  #25                 // Method java/lang/Integer.parseInt:(Ljava/lang/String;I)I
     247: i2c
     248: istore        12
     250: iload         12
     252: invokestatic  #26                 // Method org/htmlcleaner/Utils.isValidXmlChar:(C)Z
     255: ifne          265
     258: iload         9
     260: istore        6
     262: goto          359
     265: aload_0
     266: iload         12
     268: invokespecial #27                 // Method isReservedXmlChar:(C)Z
     271: ifne          324
     274: aload         5
     276: iload_2
     277: ifeq          288
     280: iload         12
     282: invokestatic  #28                 // Method java/lang/String.valueOf:(C)Ljava/lang/String;
     285: goto          313
     288: new           #15                 // class java/lang/StringBuilder
     291: dup
     292: invokespecial #20                 // Method java/lang/StringBuilder."<init>":()V
     295: ldc           #29                 // String &#
     297: invokevirtual #21                 // Method java/lang/StringBuilder.append:(Ljava/lang/String;)Ljava/lang/StringBuilder;
     300: aload         11
     302: invokevirtual #21                 // Method java/lang/StringBuilder.append:(Ljava/lang/String;)Ljava/lang/StringBuilder;
     305: ldc           #30                 // String ;
     307: invokevirtual #21                 // Method java/lang/StringBuilder.append:(Ljava/lang/String;)Ljava/lang/StringBuilder;
     310: invokevirtual #23                 // Method java/lang/StringBuilder.toString:()Ljava/lang/String;
     313: invokevirtual #21                 // Method java/lang/StringBuilder.append:(Ljava/lang/String;)Ljava/lang/StringBuilder;
     316: pop
     317: iload         9
     319: istore        6
     321: goto          359
     324: iload         9
     326: istore        6
     328: aload         5
     330: new           #15                 // class java/lang/StringBuilder
     333: dup
     334: invokespecial #20                 // Method java/lang/StringBuilder."<init>":()V
     337: ldc           #29                 // String &#
     339: invokevirtual #21                 // Method java/lang/StringBuilder.append:(Ljava/lang/String;)Ljava/lang/StringBuilder;
     342: aload         11
     344: invokevirtual #21                 // Method java/lang/StringBuilder.append:(Ljava/lang/String;)Ljava/lang/StringBuilder;
     347: ldc           #30                 // String ;
     349: invokevirtual #21                 // Method java/lang/StringBuilder.append:(Ljava/lang/String;)Ljava/lang/StringBuilder;
     352: invokevirtual #23                 // Method java/lang/StringBuilder.toString:()Ljava/lang/String;
     355: invokevirtual #21                 // Method java/lang/StringBuilder.append:(Ljava/lang/String;)Ljava/lang/StringBuilder;
     358: pop
     359: goto          385
     362: aload         5
     364: aload_0
     365: getfield      #5                  // Field props:Lorg/htmlcleaner/CleanerProperties;
     368: invokevirtual #31                 // Method org/htmlcleaner/CleanerProperties.isTransResCharsToNCR:()Z
     371: ifeq          379
     374: ldc           #32                 // String &#38;
     376: goto          381
     379: ldc           #33                 // String &
     381: invokevirtual #21                 // Method java/lang/StringBuilder.append:(Ljava/lang/String;)Ljava/lang/StringBuilder;
     384: pop
     385: goto          761
     388: aload_1
     389: iload         6
     391: iload         6
     393: getstatic     #34                 // Field org/htmlcleaner/SpecialEntities.INSTANCE:Lorg/htmlcleaner/SpecialEntities;
     396: invokevirtual #35                 // Method org/htmlcleaner/SpecialEntities.getMaxEntityLength:()I
     399: iconst_2
     400: iadd
     401: iload         4
     403: iload         6
     405: isub
     406: invokestatic  #36                 // Method java/lang/Math.min:(II)I
     409: iadd
     410: invokevirtual #37                 // Method java/lang/String.substring:(II)Ljava/lang/String;
     413: astore        8
     415: aload         8
     417: bipush        59
     419: invokevirtual #38                 // Method java/lang/String.indexOf:(I)I
     422: istore        9
     424: iload         9
     426: ifle          513
     429: aload         8
     431: iconst_1
     432: iload         9
     434: invokevirtual #37                 // Method java/lang/String.substring:(II)Ljava/lang/String;
     437: astore        10
     439: getstatic     #34                 // Field org/htmlcleaner/SpecialEntities.INSTANCE:Lorg/htmlcleaner/SpecialEntities;
     442: aload         10
     444: invokevirtual #39                 // Method org/htmlcleaner/SpecialEntities.getSpecialEntity:(Ljava/lang/String;)Lorg/htmlcleaner/SpecialEntity;
     447: astore        11
     449: aload         11
     451: ifnull        513
     454: iload_3
     455: ifeq          487
     458: aload         5
     460: iload_2
     461: ifeq          475
     464: aload         11
     466: invokevirtual #40                 // Method org/htmlcleaner/SpecialEntity.charValue:()C
     469: invokestatic  #2                  // Method java/lang/Character.valueOf:(C)Ljava/lang/Character;
     472: goto          480
     475: aload         11
     477: invokevirtual #41                 // Method org/htmlcleaner/SpecialEntity.getDecimalNCR:()Ljava/lang/String;
     480: invokevirtual #42                 // Method java/lang/StringBuilder.append:(Ljava/lang/Object;)Ljava/lang/StringBuilder;
     483: pop
     484: goto          498
     487: aload         5
     489: aload         11
     491: invokevirtual #43                 // Method org/htmlcleaner/SpecialEntity.getEscapedValue:()Ljava/lang/String;
     494: invokevirtual #21                 // Method java/lang/StringBuilder.append:(Ljava/lang/String;)Ljava/lang/StringBuilder;
     497: pop
     498: iload         6
     500: aload         10
     502: invokevirtual #14                 // Method java/lang/String.length:()I
     505: iconst_1
     506: iadd
     507: iadd
     508: istore        6
     510: goto          761
     513: aload_1
     514: iload         6
     516: invokevirtual #44                 // Method java/lang/String.substring:(I)Ljava/lang/String;
     519: astore        10
     521: iconst_0
     522: istore        11
     524: getstatic     #1                  // Field RESERVED_XML_CHARS:Ljava/util/Map;
     527: invokeinterface #45,  1           // InterfaceMethod java/util/Map.entrySet:()Ljava/util/Set;
     532: invokeinterface #46,  1           // InterfaceMethod java/util/Set.iterator:()Ljava/util/Iterator;
     537: astore        12
     539: aload         12
     541: invokeinterface #47,  1           // InterfaceMethod java/util/Iterator.hasNext:()Z
     546: ifeq          661
     549: aload         12
     551: invokeinterface #48,  1           // InterfaceMethod java/util/Iterator.next:()Ljava/lang/Object;
     556: checkcast     #49                 // class java/util/Map$Entry
     559: astore        13
     561: aload         13
     563: invokeinterface #50,  1           // InterfaceMethod java/util/Map$Entry.getValue:()Ljava/lang/Object;
     568: checkcast     #51                 // class java/lang/String
     571: astore        8
     573: aload         10
     575: aload         8
     577: invokevirtual #52                 // Method java/lang/String.startsWith:(Ljava/lang/String;)Z
     580: ifeq          658
     583: aload         5
     585: aload_0
     586: getfield      #5                  // Field props:Lorg/htmlcleaner/CleanerProperties;
     589: invokevirtual #31                 // Method org/htmlcleaner/CleanerProperties.isTransResCharsToNCR:()Z
     592: ifeq          634
     595: new           #15                 // class java/lang/StringBuilder
     598: dup
     599: invokespecial #20                 // Method java/lang/StringBuilder."<init>":()V
     602: ldc           #29                 // String &#
     604: invokevirtual #21                 // Method java/lang/StringBuilder.append:(Ljava/lang/String;)Ljava/lang/StringBuilder;
     607: aload         13
     609: invokeinterface #53,  1           // InterfaceMethod java/util/Map$Entry.getKey:()Ljava/lang/Object;
     614: checkcast     #54                 // class java/lang/Character
     617: invokevirtual #55                 // Method java/lang/Character.charValue:()C
     620: invokevirtual #56                 // Method java/lang/StringBuilder.append:(I)Ljava/lang/StringBuilder;
     623: ldc           #30                 // String ;
     625: invokevirtual #21                 // Method java/lang/StringBuilder.append:(Ljava/lang/String;)Ljava/lang/StringBuilder;
     628: invokevirtual #23                 // Method java/lang/StringBuilder.toString:()Ljava/lang/String;
     631: goto          636
     634: aload         8
     636: invokevirtual #21                 // Method java/lang/StringBuilder.append:(Ljava/lang/String;)Ljava/lang/StringBuilder;
     639: pop
     640: iload         6
     642: aload         8
     644: invokevirtual #14                 // Method java/lang/String.length:()I
     647: iconst_1
     648: isub
     649: iadd
     650: istore        6
     652: iconst_1
     653: istore        11
     655: goto          661
     658: goto          539
     661: iload         11
     663: ifne          689
     666: aload         5
     668: aload_0
     669: getfield      #5                  // Field props:Lorg/htmlcleaner/CleanerProperties;
     672: invokevirtual #31                 // Method org/htmlcleaner/CleanerProperties.isTransResCharsToNCR:()Z
     675: ifeq          683
     678: ldc           #32                 // String &#38;
     680: goto          685
     683: ldc           #33                 // String &
     685: invokevirtual #21                 // Method java/lang/StringBuilder.append:(Ljava/lang/String;)Ljava/lang/StringBuilder;
     688: pop
     689: goto          761
     692: aload_0
     693: iload         7
     695: invokespecial #27                 // Method isReservedXmlChar:(C)Z
     698: ifeq          753
     701: aload         5
     703: aload_0
     704: getfield      #5                  // Field props:Lorg/htmlcleaner/CleanerProperties;
     707: invokevirtual #31                 // Method org/htmlcleaner/CleanerProperties.isTransResCharsToNCR:()Z
     710: ifeq          741
     713: new           #15                 // class java/lang/StringBuilder
     716: dup
     717: invokespecial #20                 // Method java/lang/StringBuilder."<init>":()V
     720: ldc           #29                 // String &#
     722: invokevirtual #21                 // Method java/lang/StringBuilder.append:(Ljava/lang/String;)Ljava/lang/StringBuilder;
     725: iload         7
     727: invokevirtual #56                 // Method java/lang/StringBuilder.append:(I)Ljava/lang/StringBuilder;
     730: ldc           #30                 // String ;
     732: invokevirtual #21                 // Method java/lang/StringBuilder.append:(Ljava/lang/String;)Ljava/lang/StringBuilder;
     735: invokevirtual #23                 // Method java/lang/StringBuilder.toString:()Ljava/lang/String;
     738: goto          746
     741: iload         7
     743: invokestatic  #2                  // Method java/lang/Character.valueOf:(C)Ljava/lang/Character;
     746: invokevirtual #42                 // Method java/lang/StringBuilder.append:(Ljava/lang/Object;)Ljava/lang/StringBuilder;
     749: pop
     750: goto          761
     753: aload         5
     755: iload         7
     757: invokevirtual #22                 // Method java/lang/StringBuilder.append:(C)Ljava/lang/StringBuilder;
     760: pop
     761: iinc          6, 1
     764: goto          40
     767: aload         5
     769: invokevirtual #23                 // Method java/lang/StringBuilder.toString:()Ljava/lang/String;
     772: areturn
     773: aconst_null
     774: areturn

  protected void serializeOpenTag(org.htmlcleaner.TagNode, java.io.Writer, boolean) throws java.io.IOException;
    Code:
       0: aload_1
       1: invokevirtual #7                  // Method org/htmlcleaner/TagNode.getName:()Ljava/lang/String;
       4: astore        4
       6: aload         4
       8: invokestatic  #57                 // Method org/htmlcleaner/Utils.isEmptyString:(Ljava/lang/Object;)Z
      11: ifeq          15
      14: return
      15: aload_0
      16: getfield      #5                  // Field props:Lorg/htmlcleaner/CleanerProperties;
      19: invokevirtual #58                 // Method org/htmlcleaner/CleanerProperties.isNamespacesAware:()Z
      22: istore        5
      24: iload         5
      26: ifne          44
      29: aload         4
      31: invokestatic  #59                 // Method org/htmlcleaner/Utils.getXmlNSPrefix:(Ljava/lang/String;)Ljava/lang/String;
      34: ifnull        44
      37: aload         4
      39: invokestatic  #60                 // Method org/htmlcleaner/Utils.getXmlName:(Ljava/lang/String;)Ljava/lang/String;
      42: astore        4
      44: aload_2
      45: new           #15                 // class java/lang/StringBuilder
      48: dup
      49: invokespecial #20                 // Method java/lang/StringBuilder."<init>":()V
      52: ldc           #61                 // String <
      54: invokevirtual #21                 // Method java/lang/StringBuilder.append:(Ljava/lang/String;)Ljava/lang/StringBuilder;
      57: aload         4
      59: invokevirtual #21                 // Method java/lang/StringBuilder.append:(Ljava/lang/String;)Ljava/lang/StringBuilder;
      62: invokevirtual #23                 // Method java/lang/StringBuilder.toString:()Ljava/lang/String;
      65: invokevirtual #62                 // Method java/io/Writer.write:(Ljava/lang/String;)V
      68: aload_1
      69: invokevirtual #63                 // Method org/htmlcleaner/TagNode.getAttributes:()Ljava/util/Map;
      72: invokeinterface #45,  1           // InterfaceMethod java/util/Map.entrySet:()Ljava/util/Set;
      77: invokeinterface #46,  1           // InterfaceMethod java/util/Set.iterator:()Ljava/util/Iterator;
      82: astore        6
      84: aload         6
      86: invokeinterface #47,  1           // InterfaceMethod java/util/Iterator.hasNext:()Z
      91: ifeq          192
      94: aload         6
      96: invokeinterface #48,  1           // InterfaceMethod java/util/Iterator.next:()Ljava/lang/Object;
     101: checkcast     #49                 // class java/util/Map$Entry
     104: astore        7
     106: aload         7
     108: invokeinterface #53,  1           // InterfaceMethod java/util/Map$Entry.getKey:()Ljava/lang/Object;
     113: checkcast     #51                 // class java/lang/String
     116: astore        8
     118: iload         5
     120: ifne          138
     123: aload         8
     125: invokestatic  #59                 // Method org/htmlcleaner/Utils.getXmlNSPrefix:(Ljava/lang/String;)Ljava/lang/String;
     128: ifnull        138
     131: aload         8
     133: invokestatic  #60                 // Method org/htmlcleaner/Utils.getXmlName:(Ljava/lang/String;)Ljava/lang/String;
     136: astore        8
     138: aload_2
     139: new           #15                 // class java/lang/StringBuilder
     142: dup
     143: invokespecial #20                 // Method java/lang/StringBuilder."<init>":()V
     146: ldc           #64                 // String
     148: invokevirtual #21                 // Method java/lang/StringBuilder.append:(Ljava/lang/String;)Ljava/lang/StringBuilder;
     151: aload         8
     153: invokevirtual #21                 // Method java/lang/StringBuilder.append:(Ljava/lang/String;)Ljava/lang/StringBuilder;
     156: ldc           #65                 // String =\"
     158: invokevirtual #21                 // Method java/lang/StringBuilder.append:(Ljava/lang/String;)Ljava/lang/StringBuilder;
     161: aload_0
     162: aload         7
     164: invokeinterface #50,  1           // InterfaceMethod java/util/Map$Entry.getValue:()Ljava/lang/Object;
     169: checkcast     #51                 // class java/lang/String
     172: invokevirtual #66                 // Method escapeText:(Ljava/lang/String;)Ljava/lang/String;
     175: invokevirtual #21                 // Method java/lang/StringBuilder.append:(Ljava/lang/String;)Ljava/lang/StringBuilder;
     178: ldc           #67                 // String \"
     180: invokevirtual #21                 // Method java/lang/StringBuilder.append:(Ljava/lang/String;)Ljava/lang/StringBuilder;
     183: invokevirtual #23                 // Method java/lang/StringBuilder.toString:()Ljava/lang/String;
     186: invokevirtual #62                 // Method java/io/Writer.write:(Ljava/lang/String;)V
     189: goto          84
     192: iload         5
     194: ifeq          349
     197: aload_1
     198: invokevirtual #68                 // Method org/htmlcleaner/TagNode.getNamespaceDeclarations:()Ljava/util/Map;
     201: astore        6
     203: aload         6
     205: ifnull        349
     208: aload         6
     210: invokeinterface #45,  1           // InterfaceMethod java/util/Map.entrySet:()Ljava/util/Set;
     215: invokeinterface #46,  1           // InterfaceMethod java/util/Set.iterator:()Ljava/util/Iterator;
     220: astore        7
     222: aload         7
     224: invokeinterface #47,  1           // InterfaceMethod java/util/Iterator.hasNext:()Z
     229: ifeq          349
     232: aload         7
     234: invokeinterface #48,  1           // InterfaceMethod java/util/Iterator.next:()Ljava/lang/Object;
     239: checkcast     #49                 // class java/util/Map$Entry
     242: astore        8
     244: aload         8
     246: invokeinterface #53,  1           // InterfaceMethod java/util/Map$Entry.getKey:()Ljava/lang/Object;
     251: checkcast     #51                 // class java/lang/String
     254: astore        9
     256: ldc           #69                 // String xmlns
     258: astore        10
     260: aload         9
     262: invokevirtual #14                 // Method java/lang/String.length:()I
     265: ifle          295
     268: new           #15                 // class java/lang/StringBuilder
     271: dup
     272: invokespecial #20                 // Method java/lang/StringBuilder."<init>":()V
     275: aload         10
     277: invokevirtual #21                 // Method java/lang/StringBuilder.append:(Ljava/lang/String;)Ljava/lang/StringBuilder;
     280: ldc           #70                 // String :
     282: invokevirtual #21                 // Method java/lang/StringBuilder.append:(Ljava/lang/String;)Ljava/lang/StringBuilder;
     285: aload         9
     287: invokevirtual #21                 // Method java/lang/StringBuilder.append:(Ljava/lang/String;)Ljava/lang/StringBuilder;
     290: invokevirtual #23                 // Method java/lang/StringBuilder.toString:()Ljava/lang/String;
     293: astore        10
     295: aload_2
     296: new           #15                 // class java/lang/StringBuilder
     299: dup
     300: invokespecial #20                 // Method java/lang/StringBuilder."<init>":()V
     303: ldc           #64                 // String
     305: invokevirtual #21                 // Method java/lang/StringBuilder.append:(Ljava/lang/String;)Ljava/lang/StringBuilder;
     308: aload         10
     310: invokevirtual #21                 // Method java/lang/StringBuilder.append:(Ljava/lang/String;)Ljava/lang/StringBuilder;
     313: ldc           #65                 // String =\"
     315: invokevirtual #21                 // Method java/lang/StringBuilder.append:(Ljava/lang/String;)Ljava/lang/StringBuilder;
     318: aload_0
     319: aload         8
     321: invokeinterface #50,  1           // InterfaceMethod java/util/Map$Entry.getValue:()Ljava/lang/Object;
     326: checkcast     #51                 // class java/lang/String
     329: invokevirtual #66                 // Method escapeText:(Ljava/lang/String;)Ljava/lang/String;
     332: invokevirtual #21                 // Method java/lang/StringBuilder.append:(Ljava/lang/String;)Ljava/lang/StringBuilder;
     335: ldc           #67                 // String \"
     337: invokevirtual #21                 // Method java/lang/StringBuilder.append:(Ljava/lang/String;)Ljava/lang/StringBuilder;
     340: invokevirtual #23                 // Method java/lang/StringBuilder.toString:()Ljava/lang/String;
     343: invokevirtual #62                 // Method java/io/Writer.write:(Ljava/lang/String;)V
     346: goto          222
     349: aload_0
     350: aload_1
     351: invokevirtual #71                 // Method isMinimizedTagSyntax:(Lorg/htmlcleaner/TagNode;)Z
     354: ifeq          376
     357: aload_2
     358: ldc           #72                 // String  />
     360: invokevirtual #62                 // Method java/io/Writer.write:(Ljava/lang/String;)V
     363: iload_3
     364: ifeq          382
     367: aload_2
     368: ldc           #73                 // String \n
     370: invokevirtual #62                 // Method java/io/Writer.write:(Ljava/lang/String;)V
     373: goto          382
     376: aload_2
     377: ldc           #74                 // String >
     379: invokevirtual #62                 // Method java/io/Writer.write:(Ljava/lang/String;)V
     382: return

  protected void serializeEndTag(org.htmlcleaner.TagNode, java.io.Writer, boolean) throws java.io.IOException;
    Code:
       0: aload_1
       1: invokevirtual #7                  // Method org/htmlcleaner/TagNode.getName:()Ljava/lang/String;
       4: astore        4
       6: aload         4
       8: invokestatic  #57                 // Method org/htmlcleaner/Utils.isEmptyString:(Ljava/lang/Object;)Z
      11: ifeq          15
      14: return
      15: aload         4
      17: invokestatic  #59                 // Method org/htmlcleaner/Utils.getXmlNSPrefix:(Ljava/lang/String;)Ljava/lang/String;
      20: ifnull        40
      23: aload_0
      24: getfield      #5                  // Field props:Lorg/htmlcleaner/CleanerProperties;
      27: invokevirtual #58                 // Method org/htmlcleaner/CleanerProperties.isNamespacesAware:()Z
      30: ifne          40
      33: aload         4
      35: invokestatic  #60                 // Method org/htmlcleaner/Utils.getXmlName:(Ljava/lang/String;)Ljava/lang/String;
      38: astore        4
      40: aload_2
      41: new           #15                 // class java/lang/StringBuilder
      44: dup
      45: invokespecial #20                 // Method java/lang/StringBuilder."<init>":()V
      48: ldc           #75                 // String </
      50: invokevirtual #21                 // Method java/lang/StringBuilder.append:(Ljava/lang/String;)Ljava/lang/StringBuilder;
      53: aload         4
      55: invokevirtual #21                 // Method java/lang/StringBuilder.append:(Ljava/lang/String;)Ljava/lang/StringBuilder;
      58: ldc           #74                 // String >
      60: invokevirtual #21                 // Method java/lang/StringBuilder.append:(Ljava/lang/String;)Ljava/lang/StringBuilder;
      63: invokevirtual #23                 // Method java/lang/StringBuilder.toString:()Ljava/lang/String;
      66: invokevirtual #62                 // Method java/io/Writer.write:(Ljava/lang/String;)V
      69: iload_3
      70: ifeq          79
      73: aload_2
      74: ldc           #73                 // String \n
      76: invokevirtual #62                 // Method java/io/Writer.write:(Ljava/lang/String;)V
      79: return

  static {};
    Code:
       0: new           #76                 // class java/util/HashMap
       3: dup
       4: invokespecial #77                 // Method java/util/HashMap."<init>":()V
       7: putstatic     #1                  // Field RESERVED_XML_CHARS:Ljava/util/Map;
      10: getstatic     #1                  // Field RESERVED_XML_CHARS:Ljava/util/Map;
      13: bipush        38
      15: invokestatic  #2                  // Method java/lang/Character.valueOf:(C)Ljava/lang/Character;
      18: ldc           #78                 // String &amp;
      20: invokeinterface #79,  3           // InterfaceMethod java/util/Map.put:(Ljava/lang/Object;Ljava/lang/Object;)Ljava/lang/Object;
      25: pop
      26: getstatic     #1                  // Field RESERVED_XML_CHARS:Ljava/util/Map;
      29: bipush        60
      31: invokestatic  #2                  // Method java/lang/Character.valueOf:(C)Ljava/lang/Character;
      34: ldc           #80                 // String &lt;
      36: invokeinterface #79,  3           // InterfaceMethod java/util/Map.put:(Ljava/lang/Object;Ljava/lang/Object;)Ljava/lang/Object;
      41: pop
      42: getstatic     #1                  // Field RESERVED_XML_CHARS:Ljava/util/Map;
      45: bipush        62
      47: invokestatic  #2                  // Method java/lang/Character.valueOf:(C)Ljava/lang/Character;
      50: ldc           #81                 // String &gt;
      52: invokeinterface #79,  3           // InterfaceMethod java/util/Map.put:(Ljava/lang/Object;Ljava/lang/Object;)Ljava/lang/Object;
      57: pop
      58: getstatic     #1                  // Field RESERVED_XML_CHARS:Ljava/util/Map;
      61: bipush        34
      63: invokestatic  #2                  // Method java/lang/Character.valueOf:(C)Ljava/lang/Character;
      66: ldc           #82                 // String &quot;
      68: invokeinterface #79,  3           // InterfaceMethod java/util/Map.put:(Ljava/lang/Object;Ljava/lang/Object;)Ljava/lang/Object;
      73: pop
      74: getstatic     #1                  // Field RESERVED_XML_CHARS:Ljava/util/Map;
      77: bipush        39
      79: invokestatic  #2                  // Method java/lang/Character.valueOf:(C)Ljava/lang/Character;
      82: ldc           #83                 // String &apos;
      84: invokeinterface #79,  3           // InterfaceMethod java/util/Map.put:(Ljava/lang/Object;Ljava/lang/Object;)Ljava/lang/Object;
      89: pop
      90: return
}
