Compiled from "XPather.java"
public class org.htmlcleaner.XPather {
  private java.lang.String[] tokenArray;

  public org.htmlcleaner.XPather(java.lang.String);
    Code:
       0: aload_0
       1: invokespecial #1                  // Method java/lang/Object."<init>":()V
       4: new           #2                  // class java/util/StringTokenizer
       7: dup
       8: aload_1
       9: ldc           #3                  // String /()[]\"\'=<>
      11: iconst_1
      12: invokespecial #4                  // Method java/util/StringTokenizer."<init>":(Ljava/lang/String;Ljava/lang/String;Z)V
      15: astore_2
      16: aload_2
      17: invokevirtual #5                  // Method java/util/StringTokenizer.countTokens:()I
      20: istore_3
      21: aload_0
      22: iload_3
      23: anewarray     #6                  // class java/lang/String
      26: putfield      #7                  // Field tokenArray:[Ljava/lang/String;
      29: iconst_0
      30: istore        4
      32: aload_2
      33: invokevirtual #8                  // Method java/util/StringTokenizer.hasMoreTokens:()Z
      36: ifeq          56
      39: aload_0
      40: getfield      #7                  // Field tokenArray:[Ljava/lang/String;
      43: iload         4
      45: iinc          4, 1
      48: aload_2
      49: invokevirtual #9                  // Method java/util/StringTokenizer.nextToken:()Ljava/lang/String;
      52: aastore
      53: goto          32
      56: return

  public java.lang.Object[] evaluateAgainstNode(org.htmlcleaner.TagNode) throws org.htmlcleaner.XPatherException;
    Code:
       0: aload_1
       1: ifnonnull     14
       4: new           #10                 // class org/htmlcleaner/XPatherException
       7: dup
       8: ldc           #11                 // String Cannot evaluate XPath expression against null value!
      10: invokespecial #12                 // Method org/htmlcleaner/XPatherException."<init>":(Ljava/lang/String;)V
      13: athrow
      14: aload_0
      15: aload_0
      16: aload_1
      17: invokespecial #13                 // Method singleton:(Ljava/lang/Object;)Ljava/util/Collection;
      20: iconst_0
      21: aload_0
      22: getfield      #7                  // Field tokenArray:[Ljava/lang/String;
      25: arraylength
      26: iconst_1
      27: isub
      28: iconst_0
      29: iconst_1
      30: iconst_0
      31: iconst_0
      32: aconst_null
      33: invokespecial #14                 // Method evaluateAgainst:(Ljava/util/Collection;IIZIIZLjava/util/Collection;)Ljava/util/Collection;
      36: astore_2
      37: aload_2
      38: invokeinterface #15,  1           // InterfaceMethod java/util/Collection.size:()I
      43: anewarray     #16                 // class java/lang/Object
      46: astore_3
      47: aload_2
      48: invokeinterface #17,  1           // InterfaceMethod java/util/Collection.iterator:()Ljava/util/Iterator;
      53: astore        4
      55: iconst_0
      56: istore        5
      58: aload         4
      60: invokeinterface #18,  1           // InterfaceMethod java/util/Iterator.hasNext:()Z
      65: ifeq          85
      68: aload_3
      69: iload         5
      71: iinc          5, 1
      74: aload         4
      76: invokeinterface #19,  1           // InterfaceMethod java/util/Iterator.next:()Ljava/lang/Object;
      81: aastore
      82: goto          58
      85: aload_3
      86: areturn

  private void throwStandardException() throws org.htmlcleaner.XPatherException;
    Code:
       0: new           #10                 // class org/htmlcleaner/XPatherException
       3: dup
       4: invokespecial #20                 // Method org/htmlcleaner/XPatherException."<init>":()V
       7: athrow

  private java.util.Collection evaluateAgainst(java.util.Collection, int, int, boolean, int, int, boolean, java.util.Collection) throws org.htmlcleaner.XPatherException;
    Code:
       0: iload_2
       1: iflt          720
       4: iload_3
       5: aload_0
       6: getfield      #7                  // Field tokenArray:[Ljava/lang/String;
       9: arraylength
      10: if_icmpge     720
      13: iload_2
      14: iload_3
      15: if_icmpgt     720
      18: ldc           #21                 // String
      20: aload_0
      21: getfield      #7                  // Field tokenArray:[Ljava/lang/String;
      24: iload_2
      25: aaload
      26: invokevirtual #22                 // Method java/lang/String.trim:()Ljava/lang/String;
      29: invokevirtual #23                 // Method java/lang/String.equals:(Ljava/lang/Object;)Z
      32: ifeq          55
      35: aload_0
      36: aload_1
      37: iload_2
      38: iconst_1
      39: iadd
      40: iload_3
      41: iload         4
      43: iload         5
      45: iload         6
      47: iload         7
      49: aload         8
      51: invokespecial #14                 // Method evaluateAgainst:(Ljava/util/Collection;IIZIIZLjava/util/Collection;)Ljava/util/Collection;
      54: areturn
      55: aload_0
      56: ldc           #24                 // String (
      58: iload_2
      59: invokespecial #25                 // Method isToken:(Ljava/lang/String;I)Z
      62: ifeq          129
      65: aload_0
      66: iload_2
      67: iload_3
      68: invokespecial #26                 // Method findClosingIndex:(II)I
      71: istore        9
      73: iload         9
      75: ifle          122
      78: aload_0
      79: aload_1
      80: iload_2
      81: iconst_1
      82: iadd
      83: iload         9
      85: iconst_1
      86: isub
      87: iconst_0
      88: iload         5
      90: iload         6
      92: iload         7
      94: aload         8
      96: invokespecial #14                 // Method evaluateAgainst:(Ljava/util/Collection;IIZIIZLjava/util/Collection;)Ljava/util/Collection;
      99: astore        10
     101: aload_0
     102: aload         10
     104: iload         9
     106: iconst_1
     107: iadd
     108: iload_3
     109: iconst_0
     110: iload         5
     112: iload         6
     114: iload         7
     116: aload         8
     118: invokespecial #14                 // Method evaluateAgainst:(Ljava/util/Collection;IIZIIZLjava/util/Collection;)Ljava/util/Collection;
     121: areturn
     122: aload_0
     123: invokespecial #27                 // Method throwStandardException:()V
     126: goto          722
     129: aload_0
     130: ldc           #28                 // String [
     132: iload_2
     133: invokespecial #25                 // Method isToken:(Ljava/lang/String;I)Z
     136: ifeq          198
     139: aload_0
     140: iload_2
     141: iload_3
     142: invokespecial #26                 // Method findClosingIndex:(II)I
     145: istore        9
     147: iload         9
     149: ifle          191
     152: aload_1
     153: ifnull        191
     156: aload_0
     157: aload_1
     158: iload_2
     159: iconst_1
     160: iadd
     161: iload         9
     163: iconst_1
     164: isub
     165: invokespecial #29                 // Method filterByCondition:(Ljava/util/Collection;II)Ljava/util/Collection;
     168: astore        10
     170: aload_0
     171: aload         10
     173: iload         9
     175: iconst_1
     176: iadd
     177: iload_3
     178: iconst_0
     179: iload         5
     181: iload         6
     183: iload         7
     185: aload         8
     187: invokespecial #14                 // Method evaluateAgainst:(Ljava/util/Collection;IIZIIZLjava/util/Collection;)Ljava/util/Collection;
     190: areturn
     191: aload_0
     192: invokespecial #27                 // Method throwStandardException:()V
     195: goto          722
     198: aload_0
     199: ldc           #30                 // String \"
     201: iload_2
     202: invokespecial #25                 // Method isToken:(Ljava/lang/String;I)Z
     205: ifne          218
     208: aload_0
     209: ldc           #31                 // String \'
     211: iload_2
     212: invokespecial #25                 // Method isToken:(Ljava/lang/String;I)Z
     215: ifeq          277
     218: aload_0
     219: iload_2
     220: iload_3
     221: invokespecial #26                 // Method findClosingIndex:(II)I
     224: istore        9
     226: iload         9
     228: iload_2
     229: if_icmple     270
     232: aload_0
     233: aload_0
     234: iload_2
     235: iconst_1
     236: iadd
     237: iload         9
     239: iconst_1
     240: isub
     241: invokespecial #32                 // Method flatten:(II)Ljava/lang/String;
     244: invokespecial #13                 // Method singleton:(Ljava/lang/Object;)Ljava/util/Collection;
     247: astore        10
     249: aload_0
     250: aload         10
     252: iload         9
     254: iconst_1
     255: iadd
     256: iload_3
     257: iconst_0
     258: iload         5
     260: iload         6
     262: iload         7
     264: aload         8
     266: invokespecial #14                 // Method evaluateAgainst:(Ljava/util/Collection;IIZIIZLjava/util/Collection;)Ljava/util/Collection;
     269: areturn
     270: aload_0
     271: invokespecial #27                 // Method throwStandardException:()V
     274: goto          722
     277: aload_0
     278: ldc           #33                 // String =
     280: iload_2
     281: invokespecial #25                 // Method isToken:(Ljava/lang/String;I)Z
     284: ifne          307
     287: aload_0
     288: ldc           #34                 // String <
     290: iload_2
     291: invokespecial #25                 // Method isToken:(Ljava/lang/String;I)Z
     294: ifne          307
     297: aload_0
     298: ldc           #35                 // String >
     300: iload_2
     301: invokespecial #25                 // Method isToken:(Ljava/lang/String;I)Z
     304: ifeq          457
     307: iload         7
     309: ifeq          457
     312: aload_0
     313: ldc           #33                 // String =
     315: iload_2
     316: iconst_1
     317: iadd
     318: invokespecial #25                 // Method isToken:(Ljava/lang/String;I)Z
     321: ifeq          407
     324: aload_0
     325: ldc           #34                 // String <
     327: iload_2
     328: invokespecial #25                 // Method isToken:(Ljava/lang/String;I)Z
     331: ifne          344
     334: aload_0
     335: ldc           #35                 // String >
     337: iload_2
     338: invokespecial #25                 // Method isToken:(Ljava/lang/String;I)Z
     341: ifeq          407
     344: aload_0
     345: aload         8
     347: iload_2
     348: iconst_2
     349: iadd
     350: iload_3
     351: iconst_0
     352: iload         5
     354: iload         6
     356: iload         7
     358: aload         8
     360: invokespecial #14                 // Method evaluateAgainst:(Ljava/util/Collection;IIZIIZLjava/util/Collection;)Ljava/util/Collection;
     363: astore        10
     365: aload_0
     366: aload_1
     367: aload         10
     369: new           #36                 // class java/lang/StringBuilder
     372: dup
     373: invokespecial #37                 // Method java/lang/StringBuilder."<init>":()V
     376: aload_0
     377: getfield      #7                  // Field tokenArray:[Ljava/lang/String;
     380: iload_2
     381: aaload
     382: invokevirtual #38                 // Method java/lang/StringBuilder.append:(Ljava/lang/String;)Ljava/lang/StringBuilder;
     385: aload_0
     386: getfield      #7                  // Field tokenArray:[Ljava/lang/String;
     389: iload_2
     390: iconst_1
     391: iadd
     392: aaload
     393: invokevirtual #38                 // Method java/lang/StringBuilder.append:(Ljava/lang/String;)Ljava/lang/StringBuilder;
     396: invokevirtual #39                 // Method java/lang/StringBuilder.toString:()Ljava/lang/String;
     399: invokespecial #40                 // Method evaluateLogic:(Ljava/util/Collection;Ljava/util/Collection;Ljava/lang/String;)Z
     402: istore        9
     404: goto          443
     407: aload_0
     408: aload         8
     410: iload_2
     411: iconst_1
     412: iadd
     413: iload_3
     414: iconst_0
     415: iload         5
     417: iload         6
     419: iload         7
     421: aload         8
     423: invokespecial #14                 // Method evaluateAgainst:(Ljava/util/Collection;IIZIIZLjava/util/Collection;)Ljava/util/Collection;
     426: astore        10
     428: aload_0
     429: aload_1
     430: aload         10
     432: aload_0
     433: getfield      #7                  // Field tokenArray:[Ljava/lang/String;
     436: iload_2
     437: aaload
     438: invokespecial #40                 // Method evaluateLogic:(Ljava/util/Collection;Ljava/util/Collection;Ljava/lang/String;)Z
     441: istore        9
     443: aload_0
     444: new           #41                 // class java/lang/Boolean
     447: dup
     448: iload         9
     450: invokespecial #42                 // Method java/lang/Boolean."<init>":(Z)V
     453: invokespecial #13                 // Method singleton:(Ljava/lang/Object;)Ljava/util/Collection;
     456: areturn
     457: aload_0
     458: ldc           #43                 // String /
     460: iload_2
     461: invokespecial #25                 // Method isToken:(Ljava/lang/String;I)Z
     464: ifeq          558
     467: aload_0
     468: ldc           #43                 // String /
     470: iload_2
     471: iconst_1
     472: iadd
     473: invokespecial #25                 // Method isToken:(Ljava/lang/String;I)Z
     476: istore        9
     478: iload         9
     480: ifeq          486
     483: iinc          2, 1
     486: iload_2
     487: iload_3
     488: if_icmpge     551
     491: aload_0
     492: iload_2
     493: iload_3
     494: invokespecial #26                 // Method findClosingIndex:(II)I
     497: iconst_1
     498: isub
     499: istore        10
     501: iload         10
     503: iload_2
     504: if_icmpgt     510
     507: iload_3
     508: istore        10
     510: aload_0
     511: aload_1
     512: iload_2
     513: iconst_1
     514: iadd
     515: iload         10
     517: iload         9
     519: iconst_1
     520: iload         6
     522: iload         7
     524: aload         8
     526: invokespecial #14                 // Method evaluateAgainst:(Ljava/util/Collection;IIZIIZLjava/util/Collection;)Ljava/util/Collection;
     529: astore        11
     531: aload_0
     532: aload         11
     534: iload         10
     536: iconst_1
     537: iadd
     538: iload_3
     539: iconst_0
     540: iconst_1
     541: iload         6
     543: iload         7
     545: aload         8
     547: invokespecial #14                 // Method evaluateAgainst:(Ljava/util/Collection;IIZIIZLjava/util/Collection;)Ljava/util/Collection;
     550: areturn
     551: aload_0
     552: invokespecial #27                 // Method throwStandardException:()V
     555: goto          722
     558: aload_0
     559: iload_2
     560: iload_3
     561: invokespecial #44                 // Method isFunctionCall:(II)Z
     564: ifeq          612
     567: aload_0
     568: iload_2
     569: iconst_1
     570: iadd
     571: iload_3
     572: invokespecial #26                 // Method findClosingIndex:(II)I
     575: istore        9
     577: aload_0
     578: aload_1
     579: iload_2
     580: iload_3
     581: iload         5
     583: iload         6
     585: iload         7
     587: invokespecial #45                 // Method evaluateFunction:(Ljava/util/Collection;IIIIZ)Ljava/util/Collection;
     590: astore        10
     592: aload_0
     593: aload         10
     595: iload         9
     597: iconst_1
     598: iadd
     599: iload_3
     600: iconst_0
     601: iconst_1
     602: iload         6
     604: iload         7
     606: aload         8
     608: invokespecial #14                 // Method evaluateAgainst:(Ljava/util/Collection;IIZIIZLjava/util/Collection;)Ljava/util/Collection;
     611: areturn
     612: aload_0
     613: aload_0
     614: getfield      #7                  // Field tokenArray:[Ljava/lang/String;
     617: iload_2
     618: aaload
     619: invokespecial #46                 // Method isValidInteger:(Ljava/lang/String;)Z
     622: ifeq          660
     625: aload_0
     626: aload_0
     627: getfield      #7                  // Field tokenArray:[Ljava/lang/String;
     630: iload_2
     631: aaload
     632: invokestatic  #47                 // Method java/lang/Integer.valueOf:(Ljava/lang/String;)Ljava/lang/Integer;
     635: invokespecial #13                 // Method singleton:(Ljava/lang/Object;)Ljava/util/Collection;
     638: astore        9
     640: aload_0
     641: aload         9
     643: iload_2
     644: iconst_1
     645: iadd
     646: iload_3
     647: iconst_0
     648: iload         5
     650: iload         6
     652: iload         7
     654: aload         8
     656: invokespecial #14                 // Method evaluateAgainst:(Ljava/util/Collection;IIZIIZLjava/util/Collection;)Ljava/util/Collection;
     659: areturn
     660: aload_0
     661: aload_0
     662: getfield      #7                  // Field tokenArray:[Ljava/lang/String;
     665: iload_2
     666: aaload
     667: invokespecial #48                 // Method isValidDouble:(Ljava/lang/String;)Z
     670: ifeq          708
     673: aload_0
     674: aload_0
     675: getfield      #7                  // Field tokenArray:[Ljava/lang/String;
     678: iload_2
     679: aaload
     680: invokestatic  #49                 // Method java/lang/Double.valueOf:(Ljava/lang/String;)Ljava/lang/Double;
     683: invokespecial #13                 // Method singleton:(Ljava/lang/Object;)Ljava/util/Collection;
     686: astore        9
     688: aload_0
     689: aload         9
     691: iload_2
     692: iconst_1
     693: iadd
     694: iload_3
     695: iconst_0
     696: iload         5
     698: iload         6
     700: iload         7
     702: aload         8
     704: invokespecial #14                 // Method evaluateAgainst:(Ljava/util/Collection;IIZIIZLjava/util/Collection;)Ljava/util/Collection;
     707: areturn
     708: aload_0
     709: aload_1
     710: iload_2
     711: iload_3
     712: iload         4
     714: iload         7
     716: invokespecial #50                 // Method getElementsByName:(Ljava/util/Collection;IIZZ)Ljava/util/Collection;
     719: areturn
     720: aload_1
     721: areturn
     722: new           #10                 // class org/htmlcleaner/XPatherException
     725: dup
     726: invokespecial #20                 // Method org/htmlcleaner/XPatherException."<init>":()V
     729: athrow

  private java.lang.String flatten(int, int);
    Code:
       0: iload_1
       1: iload_2
       2: if_icmpgt     45
       5: new           #51                 // class java/lang/StringBuffer
       8: dup
       9: invokespecial #52                 // Method java/lang/StringBuffer."<init>":()V
      12: astore_3
      13: iload_1
      14: istore        4
      16: iload         4
      18: iload_2
      19: if_icmpgt     40
      22: aload_3
      23: aload_0
      24: getfield      #7                  // Field tokenArray:[Ljava/lang/String;
      27: iload         4
      29: aaload
      30: invokevirtual #53                 // Method java/lang/StringBuffer.append:(Ljava/lang/String;)Ljava/lang/StringBuffer;
      33: pop
      34: iinc          4, 1
      37: goto          16
      40: aload_3
      41: invokevirtual #54                 // Method java/lang/StringBuffer.toString:()Ljava/lang/String;
      44: areturn
      45: ldc           #21                 // String
      47: areturn

  private boolean isValidInteger(java.lang.String);
    Code:
       0: aload_1
       1: invokestatic  #55                 // Method java/lang/Integer.parseInt:(Ljava/lang/String;)I
       4: pop
       5: iconst_1
       6: ireturn
       7: astore_2
       8: iconst_0
       9: ireturn
    Exception table:
       from    to  target type
           0     6     7   Class java/lang/NumberFormatException

  private boolean isValidDouble(java.lang.String);
    Code:
       0: aload_1
       1: invokestatic  #57                 // Method java/lang/Double.parseDouble:(Ljava/lang/String;)D
       4: pop2
       5: iconst_1
       6: ireturn
       7: astore_2
       8: iconst_0
       9: ireturn
    Exception table:
       from    to  target type
           0     6     7   Class java/lang/NumberFormatException

  private boolean isIdentifier(java.lang.String);
    Code:
       0: aload_1
       1: ifnonnull     6
       4: iconst_0
       5: ireturn
       6: aload_1
       7: invokevirtual #22                 // Method java/lang/String.trim:()Ljava/lang/String;
      10: astore_1
      11: aload_1
      12: invokevirtual #58                 // Method java/lang/String.length:()I
      15: ifle          74
      18: aload_1
      19: iconst_0
      20: invokevirtual #59                 // Method java/lang/String.charAt:(I)C
      23: invokestatic  #60                 // Method java/lang/Character.isLetter:(C)Z
      26: ifne          31
      29: iconst_0
      30: ireturn
      31: iconst_1
      32: istore_2
      33: iload_2
      34: aload_1
      35: invokevirtual #58                 // Method java/lang/String.length:()I
      38: if_icmpge     74
      41: aload_1
      42: iload_2
      43: invokevirtual #59                 // Method java/lang/String.charAt:(I)C
      46: istore_3
      47: iload_3
      48: bipush        95
      50: if_icmpeq     68
      53: iload_3
      54: bipush        45
      56: if_icmpeq     68
      59: iload_3
      60: invokestatic  #61                 // Method java/lang/Character.isLetterOrDigit:(C)Z
      63: ifne          68
      66: iconst_0
      67: ireturn
      68: iinc          2, 1
      71: goto          33
      74: iconst_0
      75: ireturn

  private boolean isFunctionCall(int, int);
    Code:
       0: aload_0
       1: aload_0
       2: getfield      #7                  // Field tokenArray:[Ljava/lang/String;
       5: iload_1
       6: aaload
       7: invokespecial #62                 // Method isIdentifier:(Ljava/lang/String;)Z
      10: ifne          27
      13: aload_0
      14: ldc           #24                 // String (
      16: iload_1
      17: iconst_1
      18: iadd
      19: invokespecial #25                 // Method isToken:(Ljava/lang/String;I)Z
      22: ifne          27
      25: iconst_0
      26: ireturn
      27: aload_0
      28: iload_1
      29: iconst_1
      30: iadd
      31: iload_2
      32: invokespecial #26                 // Method findClosingIndex:(II)I
      35: iload_1
      36: iconst_1
      37: iadd
      38: if_icmple     45
      41: iconst_1
      42: goto          46
      45: iconst_0
      46: ireturn

  private java.util.Collection evaluateFunction(java.util.Collection, int, int, int, int, boolean) throws org.htmlcleaner.XPatherException;
    Code:
       0: aload_0
       1: getfield      #7                  // Field tokenArray:[Ljava/lang/String;
       4: iload_2
       5: aaload
       6: invokevirtual #22                 // Method java/lang/String.trim:()Ljava/lang/String;
       9: astore        7
      11: new           #63                 // class java/util/ArrayList
      14: dup
      15: invokespecial #64                 // Method java/util/ArrayList."<init>":()V
      18: astore        8
      20: aload_1
      21: invokeinterface #15,  1           // InterfaceMethod java/util/Collection.size:()I
      26: istore        9
      28: aload_1
      29: invokeinterface #17,  1           // InterfaceMethod java/util/Collection.iterator:()Ljava/util/Iterator;
      34: astore        10
      36: iconst_0
      37: istore        11
      39: aload         10
      41: invokeinterface #18,  1           // InterfaceMethod java/util/Iterator.hasNext:()Z
      46: ifeq          379
      49: aload         10
      51: invokeinterface #19,  1           // InterfaceMethod java/util/Iterator.next:()Ljava/lang/Object;
      56: astore        12
      58: iinc          11, 1
      61: ldc           #65                 // String last
      63: aload         7
      65: invokevirtual #23                 // Method java/lang/String.equals:(Ljava/lang/Object;)Z
      68: ifeq          95
      71: aload         8
      73: iload         6
      75: ifeq          83
      78: iload         5
      80: goto          85
      83: iload         9
      85: invokestatic  #66                 // Method java/lang/Integer.valueOf:(I)Ljava/lang/Integer;
      88: invokevirtual #67                 // Method java/util/ArrayList.add:(Ljava/lang/Object;)Z
      91: pop
      92: goto          376
      95: ldc           #68                 // String position
      97: aload         7
      99: invokevirtual #23                 // Method java/lang/String.equals:(Ljava/lang/Object;)Z
     102: ifeq          129
     105: aload         8
     107: iload         6
     109: ifeq          117
     112: iload         4
     114: goto          119
     117: iload         11
     119: invokestatic  #66                 // Method java/lang/Integer.valueOf:(I)Ljava/lang/Integer;
     122: invokevirtual #67                 // Method java/util/ArrayList.add:(Ljava/lang/Object;)Z
     125: pop
     126: goto          376
     129: ldc           #69                 // String text
     131: aload         7
     133: invokevirtual #23                 // Method java/lang/String.equals:(Ljava/lang/Object;)Z
     136: ifeq          186
     139: aload         12
     141: instanceof    #70                 // class org/htmlcleaner/TagNode
     144: ifeq          164
     147: aload         8
     149: aload         12
     151: checkcast     #70                 // class org/htmlcleaner/TagNode
     154: invokevirtual #71                 // Method org/htmlcleaner/TagNode.getText:()Ljava/lang/CharSequence;
     157: invokevirtual #67                 // Method java/util/ArrayList.add:(Ljava/lang/Object;)Z
     160: pop
     161: goto          376
     164: aload         12
     166: instanceof    #6                  // class java/lang/String
     169: ifeq          376
     172: aload         8
     174: aload         12
     176: invokevirtual #72                 // Method java/lang/Object.toString:()Ljava/lang/String;
     179: invokevirtual #67                 // Method java/util/ArrayList.add:(Ljava/lang/Object;)Z
     182: pop
     183: goto          376
     186: ldc           #73                 // String count
     188: aload         7
     190: invokevirtual #23                 // Method java/lang/String.equals:(Ljava/lang/Object;)Z
     193: ifeq          235
     196: aload_0
     197: aload_1
     198: iload_2
     199: iconst_2
     200: iadd
     201: iload_3
     202: iconst_1
     203: isub
     204: iconst_0
     205: iload         4
     207: iconst_0
     208: iload         6
     210: aconst_null
     211: invokespecial #14                 // Method evaluateAgainst:(Ljava/util/Collection;IIZIIZLjava/util/Collection;)Ljava/util/Collection;
     214: astore        13
     216: aload         8
     218: aload         13
     220: invokeinterface #15,  1           // InterfaceMethod java/util/Collection.size:()I
     225: invokestatic  #66                 // Method java/lang/Integer.valueOf:(I)Ljava/lang/Integer;
     228: invokevirtual #67                 // Method java/util/ArrayList.add:(Ljava/lang/Object;)Z
     231: pop
     232: goto          376
     235: ldc           #74                 // String data
     237: aload         7
     239: invokevirtual #23                 // Method java/lang/String.equals:(Ljava/lang/Object;)Z
     242: ifeq          343
     245: aload_0
     246: aload_1
     247: iload_2
     248: iconst_2
     249: iadd
     250: iload_3
     251: iconst_1
     252: isub
     253: iconst_0
     254: iload         4
     256: iconst_0
     257: iload         6
     259: aconst_null
     260: invokespecial #14                 // Method evaluateAgainst:(Ljava/util/Collection;IIZIIZLjava/util/Collection;)Ljava/util/Collection;
     263: astore        13
     265: aload         13
     267: invokeinterface #17,  1           // InterfaceMethod java/util/Collection.iterator:()Ljava/util/Iterator;
     272: astore        14
     274: aload         14
     276: invokeinterface #18,  1           // InterfaceMethod java/util/Iterator.hasNext:()Z
     281: ifeq          340
     284: aload         14
     286: invokeinterface #19,  1           // InterfaceMethod java/util/Iterator.next:()Ljava/lang/Object;
     291: astore        15
     293: aload         15
     295: instanceof    #70                 // class org/htmlcleaner/TagNode
     298: ifeq          318
     301: aload         8
     303: aload         15
     305: checkcast     #70                 // class org/htmlcleaner/TagNode
     308: invokevirtual #71                 // Method org/htmlcleaner/TagNode.getText:()Ljava/lang/CharSequence;
     311: invokevirtual #67                 // Method java/util/ArrayList.add:(Ljava/lang/Object;)Z
     314: pop
     315: goto          337
     318: aload         15
     320: instanceof    #6                  // class java/lang/String
     323: ifeq          337
     326: aload         8
     328: aload         15
     330: invokevirtual #72                 // Method java/lang/Object.toString:()Ljava/lang/String;
     333: invokevirtual #67                 // Method java/util/ArrayList.add:(Ljava/lang/Object;)Z
     336: pop
     337: goto          274
     340: goto          376
     343: new           #10                 // class org/htmlcleaner/XPatherException
     346: dup
     347: new           #36                 // class java/lang/StringBuilder
     350: dup
     351: invokespecial #37                 // Method java/lang/StringBuilder."<init>":()V
     354: ldc           #75                 // String Unknown function
     356: invokevirtual #38                 // Method java/lang/StringBuilder.append:(Ljava/lang/String;)Ljava/lang/StringBuilder;
     359: aload         7
     361: invokevirtual #38                 // Method java/lang/StringBuilder.append:(Ljava/lang/String;)Ljava/lang/StringBuilder;
     364: ldc           #76                 // String !
     366: invokevirtual #38                 // Method java/lang/StringBuilder.append:(Ljava/lang/String;)Ljava/lang/StringBuilder;
     369: invokevirtual #39                 // Method java/lang/StringBuilder.toString:()Ljava/lang/String;
     372: invokespecial #12                 // Method org/htmlcleaner/XPatherException."<init>":(Ljava/lang/String;)V
     375: athrow
     376: goto          39
     379: aload         8
     381: areturn

  private java.util.Collection filterByCondition(java.util.Collection, int, int) throws org.htmlcleaner.XPatherException;
    Code:
       0: new           #63                 // class java/util/ArrayList
       3: dup
       4: invokespecial #64                 // Method java/util/ArrayList."<init>":()V
       7: astore        4
       9: aload_1
      10: invokeinterface #17,  1           // InterfaceMethod java/util/Collection.iterator:()Ljava/util/Iterator;
      15: astore        5
      17: iconst_0
      18: istore        6
      20: aload_1
      21: invokeinterface #15,  1           // InterfaceMethod java/util/Collection.size:()I
      26: istore        7
      28: aload         5
      30: invokeinterface #18,  1           // InterfaceMethod java/util/Iterator.hasNext:()Z
      35: ifeq          173
      38: aload         5
      40: invokeinterface #19,  1           // InterfaceMethod java/util/Iterator.next:()Ljava/lang/Object;
      45: astore        8
      47: iinc          6, 1
      50: new           #63                 // class java/util/ArrayList
      53: dup
      54: aload_0
      55: aload_0
      56: aload         8
      58: invokespecial #13                 // Method singleton:(Ljava/lang/Object;)Ljava/util/Collection;
      61: iload_2
      62: iload_3
      63: iconst_0
      64: iload         6
      66: iload         7
      68: iconst_1
      69: aload_0
      70: aload         8
      72: invokespecial #13                 // Method singleton:(Ljava/lang/Object;)Ljava/util/Collection;
      75: invokespecial #14                 // Method evaluateAgainst:(Ljava/util/Collection;IIZIIZLjava/util/Collection;)Ljava/util/Collection;
      78: invokespecial #77                 // Method java/util/ArrayList."<init>":(Ljava/util/Collection;)V
      81: astore        9
      83: aload         9
      85: invokevirtual #78                 // Method java/util/ArrayList.size:()I
      88: iconst_1
      89: if_icmplt     170
      92: aload         9
      94: iconst_0
      95: invokevirtual #79                 // Method java/util/ArrayList.get:(I)Ljava/lang/Object;
      98: astore        10
     100: aload         10
     102: instanceof    #41                 // class java/lang/Boolean
     105: ifeq          130
     108: aload         10
     110: checkcast     #41                 // class java/lang/Boolean
     113: invokevirtual #80                 // Method java/lang/Boolean.booleanValue:()Z
     116: ifeq          170
     119: aload         4
     121: aload         8
     123: invokevirtual #67                 // Method java/util/ArrayList.add:(Ljava/lang/Object;)Z
     126: pop
     127: goto          170
     130: aload         10
     132: instanceof    #81                 // class java/lang/Integer
     135: ifeq          162
     138: aload         10
     140: checkcast     #81                 // class java/lang/Integer
     143: invokevirtual #82                 // Method java/lang/Integer.intValue:()I
     146: iload         6
     148: if_icmpne     170
     151: aload         4
     153: aload         8
     155: invokevirtual #67                 // Method java/util/ArrayList.add:(Ljava/lang/Object;)Z
     158: pop
     159: goto          170
     162: aload         4
     164: aload         8
     166: invokevirtual #67                 // Method java/util/ArrayList.add:(Ljava/lang/Object;)Z
     169: pop
     170: goto          28
     173: aload         4
     175: areturn

  private boolean isToken(java.lang.String, int);
    Code:
       0: aload_0
       1: getfield      #7                  // Field tokenArray:[Ljava/lang/String;
       4: arraylength
       5: istore_3
       6: iload_2
       7: iflt          38
      10: iload_2
      11: iload_3
      12: if_icmpge     38
      15: aload_0
      16: getfield      #7                  // Field tokenArray:[Ljava/lang/String;
      19: iload_2
      20: aaload
      21: invokevirtual #22                 // Method java/lang/String.trim:()Ljava/lang/String;
      24: aload_1
      25: invokevirtual #22                 // Method java/lang/String.trim:()Ljava/lang/String;
      28: invokevirtual #23                 // Method java/lang/String.equals:(Ljava/lang/Object;)Z
      31: ifeq          38
      34: iconst_1
      35: goto          39
      38: iconst_0
      39: ireturn

  private int findClosingIndex(int, int);
    Code:
       0: iload_1
       1: iload_2
       2: if_icmpge     454
       5: aload_0
       6: getfield      #7                  // Field tokenArray:[Ljava/lang/String;
       9: iload_1
      10: aaload
      11: astore_3
      12: ldc           #30                 // String \"
      14: aload_3
      15: invokevirtual #23                 // Method java/lang/String.equals:(Ljava/lang/Object;)Z
      18: ifeq          59
      21: iload_1
      22: iconst_1
      23: iadd
      24: istore        4
      26: iload         4
      28: iload_2
      29: if_icmpgt     56
      32: ldc           #30                 // String \"
      34: aload_0
      35: getfield      #7                  // Field tokenArray:[Ljava/lang/String;
      38: iload         4
      40: aaload
      41: invokevirtual #23                 // Method java/lang/String.equals:(Ljava/lang/Object;)Z
      44: ifeq          50
      47: iload         4
      49: ireturn
      50: iinc          4, 1
      53: goto          26
      56: goto          454
      59: ldc           #31                 // String \'
      61: aload_3
      62: invokevirtual #23                 // Method java/lang/String.equals:(Ljava/lang/Object;)Z
      65: ifeq          106
      68: iload_1
      69: iconst_1
      70: iadd
      71: istore        4
      73: iload         4
      75: iload_2
      76: if_icmpgt     103
      79: ldc           #31                 // String \'
      81: aload_0
      82: getfield      #7                  // Field tokenArray:[Ljava/lang/String;
      85: iload         4
      87: aaload
      88: invokevirtual #23                 // Method java/lang/String.equals:(Ljava/lang/Object;)Z
      91: ifeq          97
      94: iload         4
      96: ireturn
      97: iinc          4, 1
     100: goto          73
     103: goto          454
     106: ldc           #24                 // String (
     108: aload_3
     109: invokevirtual #23                 // Method java/lang/String.equals:(Ljava/lang/Object;)Z
     112: ifne          133
     115: ldc           #28                 // String [
     117: aload_3
     118: invokevirtual #23                 // Method java/lang/String.equals:(Ljava/lang/Object;)Z
     121: ifne          133
     124: ldc           #43                 // String /
     126: aload_3
     127: invokevirtual #23                 // Method java/lang/String.equals:(Ljava/lang/Object;)Z
     130: ifeq          454
     133: iconst_1
     134: istore        4
     136: iconst_1
     137: istore        5
     139: ldc           #24                 // String (
     141: aload_3
     142: invokevirtual #23                 // Method java/lang/String.equals:(Ljava/lang/Object;)Z
     145: ifeq          152
     148: iconst_1
     149: goto          153
     152: iconst_0
     153: istore        6
     155: ldc           #28                 // String [
     157: aload_3
     158: invokevirtual #23                 // Method java/lang/String.equals:(Ljava/lang/Object;)Z
     161: ifeq          168
     164: iconst_1
     165: goto          169
     168: iconst_0
     169: istore        7
     171: ldc           #43                 // String /
     173: aload_3
     174: invokevirtual #23                 // Method java/lang/String.equals:(Ljava/lang/Object;)Z
     177: ifeq          184
     180: iconst_1
     181: goto          185
     184: iconst_0
     185: istore        8
     187: iload_1
     188: iconst_1
     189: iadd
     190: istore        9
     192: iload         9
     194: iload_2
     195: if_icmpgt     454
     198: ldc           #30                 // String \"
     200: aload_0
     201: getfield      #7                  // Field tokenArray:[Ljava/lang/String;
     204: iload         9
     206: aaload
     207: invokevirtual #23                 // Method java/lang/String.equals:(Ljava/lang/Object;)Z
     210: ifeq          228
     213: iload         4
     215: ifne          222
     218: iconst_1
     219: goto          223
     222: iconst_0
     223: istore        4
     225: goto          420
     228: ldc           #31                 // String \'
     230: aload_0
     231: getfield      #7                  // Field tokenArray:[Ljava/lang/String;
     234: iload         9
     236: aaload
     237: invokevirtual #23                 // Method java/lang/String.equals:(Ljava/lang/Object;)Z
     240: ifeq          258
     243: iload         5
     245: ifne          252
     248: iconst_1
     249: goto          253
     252: iconst_0
     253: istore        5
     255: goto          420
     258: ldc           #24                 // String (
     260: aload_0
     261: getfield      #7                  // Field tokenArray:[Ljava/lang/String;
     264: iload         9
     266: aaload
     267: invokevirtual #23                 // Method java/lang/String.equals:(Ljava/lang/Object;)Z
     270: ifeq          289
     273: iload         4
     275: ifeq          289
     278: iload         5
     280: ifeq          289
     283: iinc          6, 1
     286: goto          420
     289: ldc           #83                 // String )
     291: aload_0
     292: getfield      #7                  // Field tokenArray:[Ljava/lang/String;
     295: iload         9
     297: aaload
     298: invokevirtual #23                 // Method java/lang/String.equals:(Ljava/lang/Object;)Z
     301: ifeq          320
     304: iload         4
     306: ifeq          320
     309: iload         5
     311: ifeq          320
     314: iinc          6, -1
     317: goto          420
     320: ldc           #28                 // String [
     322: aload_0
     323: getfield      #7                  // Field tokenArray:[Ljava/lang/String;
     326: iload         9
     328: aaload
     329: invokevirtual #23                 // Method java/lang/String.equals:(Ljava/lang/Object;)Z
     332: ifeq          351
     335: iload         4
     337: ifeq          351
     340: iload         5
     342: ifeq          351
     345: iinc          7, 1
     348: goto          420
     351: ldc           #84                 // String ]
     353: aload_0
     354: getfield      #7                  // Field tokenArray:[Ljava/lang/String;
     357: iload         9
     359: aaload
     360: invokevirtual #23                 // Method java/lang/String.equals:(Ljava/lang/Object;)Z
     363: ifeq          382
     366: iload         4
     368: ifeq          382
     371: iload         5
     373: ifeq          382
     376: iinc          7, -1
     379: goto          420
     382: ldc           #43                 // String /
     384: aload_0
     385: getfield      #7                  // Field tokenArray:[Ljava/lang/String;
     388: iload         9
     390: aaload
     391: invokevirtual #23                 // Method java/lang/String.equals:(Ljava/lang/Object;)Z
     394: ifeq          420
     397: iload         4
     399: ifeq          420
     402: iload         5
     404: ifeq          420
     407: iload         6
     409: ifne          420
     412: iload         7
     414: ifne          420
     417: iinc          8, -1
     420: iload         4
     422: ifeq          448
     425: iload         5
     427: ifeq          448
     430: iload         6
     432: ifne          448
     435: iload         7
     437: ifne          448
     440: iload         8
     442: ifne          448
     445: iload         9
     447: ireturn
     448: iinc          9, 1
     451: goto          192
     454: iconst_m1
     455: ireturn

  private boolean isAtt(java.lang.String);
    Code:
       0: aload_1
       1: ifnull        25
       4: aload_1
       5: invokevirtual #58                 // Method java/lang/String.length:()I
       8: iconst_1
       9: if_icmple     25
      12: aload_1
      13: ldc           #85                 // String @
      15: invokevirtual #86                 // Method java/lang/String.startsWith:(Ljava/lang/String;)Z
      18: ifeq          25
      21: iconst_1
      22: goto          26
      25: iconst_0
      26: ireturn

  private java.util.Collection singleton(java.lang.Object);
    Code:
       0: new           #63                 // class java/util/ArrayList
       3: dup
       4: invokespecial #64                 // Method java/util/ArrayList."<init>":()V
       7: astore_2
       8: aload_2
       9: aload_1
      10: invokevirtual #67                 // Method java/util/ArrayList.add:(Ljava/lang/Object;)Z
      13: pop
      14: aload_2
      15: areturn

  private java.util.Collection getElementsByName(java.util.Collection, int, int, boolean, boolean) throws org.htmlcleaner.XPatherException;
    Code:
       0: aload_0
       1: getfield      #7                  // Field tokenArray:[Ljava/lang/String;
       4: iload_2
       5: aaload
       6: invokevirtual #22                 // Method java/lang/String.trim:()Ljava/lang/String;
       9: astore        6
      11: aload_0
      12: aload         6
      14: invokespecial #87                 // Method isAtt:(Ljava/lang/String;)Z
      17: ifeq          259
      20: aload         6
      22: iconst_1
      23: invokevirtual #88                 // Method java/lang/String.substring:(I)Ljava/lang/String;
      26: astore        6
      28: new           #63                 // class java/util/ArrayList
      31: dup
      32: invokespecial #64                 // Method java/util/ArrayList."<init>":()V
      35: astore        7
      37: iload         4
      39: ifeq          113
      42: new           #89                 // class java/util/LinkedHashSet
      45: dup
      46: invokespecial #90                 // Method java/util/LinkedHashSet."<init>":()V
      49: astore        8
      51: aload_1
      52: invokeinterface #17,  1           // InterfaceMethod java/util/Collection.iterator:()Ljava/util/Iterator;
      57: astore        9
      59: aload         9
      61: invokeinterface #18,  1           // InterfaceMethod java/util/Iterator.hasNext:()Z
      66: ifeq          110
      69: aload         9
      71: invokeinterface #19,  1           // InterfaceMethod java/util/Iterator.next:()Ljava/lang/Object;
      76: astore        10
      78: aload         10
      80: instanceof    #70                 // class org/htmlcleaner/TagNode
      83: ifeq          107
      86: aload         10
      88: checkcast     #70                 // class org/htmlcleaner/TagNode
      91: astore        11
      93: aload         8
      95: aload         11
      97: iconst_1
      98: invokevirtual #91                 // Method org/htmlcleaner/TagNode.getAllElementsList:(Z)Ljava/util/List;
     101: invokeinterface #92,  2           // InterfaceMethod java/util/Collection.addAll:(Ljava/util/Collection;)Z
     106: pop
     107: goto          59
     110: goto          116
     113: aload_1
     114: astore        8
     116: aload         8
     118: invokeinterface #17,  1           // InterfaceMethod java/util/Collection.iterator:()Ljava/util/Iterator;
     123: astore        9
     125: aload         9
     127: invokeinterface #18,  1           // InterfaceMethod java/util/Iterator.hasNext:()Z
     132: ifeq          256
     135: aload         9
     137: invokeinterface #19,  1           // InterfaceMethod java/util/Iterator.next:()Ljava/lang/Object;
     142: astore        10
     144: aload         10
     146: instanceof    #70                 // class org/htmlcleaner/TagNode
     149: ifeq          249
     152: aload         10
     154: checkcast     #70                 // class org/htmlcleaner/TagNode
     157: astore        11
     159: ldc           #93                 // String *
     161: aload         6
     163: invokevirtual #23                 // Method java/lang/String.equals:(Ljava/lang/Object;)Z
     166: ifeq          204
     169: aload         7
     171: aload_0
     172: aload         11
     174: invokevirtual #94                 // Method org/htmlcleaner/TagNode.getAttributes:()Ljava/util/Map;
     177: invokeinterface #95,  1           // InterfaceMethod java/util/Map.values:()Ljava/util/Collection;
     182: iload_2
     183: iconst_1
     184: iadd
     185: iload_3
     186: iconst_0
     187: iconst_1
     188: iconst_1
     189: iload         5
     191: aconst_null
     192: invokespecial #14                 // Method evaluateAgainst:(Ljava/util/Collection;IIZIIZLjava/util/Collection;)Ljava/util/Collection;
     195: invokeinterface #92,  2           // InterfaceMethod java/util/Collection.addAll:(Ljava/util/Collection;)Z
     200: pop
     201: goto          246
     204: aload         11
     206: aload         6
     208: invokevirtual #96                 // Method org/htmlcleaner/TagNode.getAttributeByName:(Ljava/lang/String;)Ljava/lang/String;
     211: astore        12
     213: aload         12
     215: ifnull        246
     218: aload         7
     220: aload_0
     221: aload_0
     222: aload         12
     224: invokespecial #13                 // Method singleton:(Ljava/lang/Object;)Ljava/util/Collection;
     227: iload_2
     228: iconst_1
     229: iadd
     230: iload_3
     231: iconst_0
     232: iconst_1
     233: iconst_1
     234: iload         5
     236: aconst_null
     237: invokespecial #14                 // Method evaluateAgainst:(Ljava/util/Collection;IIZIIZLjava/util/Collection;)Ljava/util/Collection;
     240: invokeinterface #92,  2           // InterfaceMethod java/util/Collection.addAll:(Ljava/util/Collection;)Z
     245: pop
     246: goto          253
     249: aload_0
     250: invokespecial #27                 // Method throwStandardException:()V
     253: goto          125
     256: aload         7
     258: areturn
     259: new           #89                 // class java/util/LinkedHashSet
     262: dup
     263: invokespecial #90                 // Method java/util/LinkedHashSet."<init>":()V
     266: astore        7
     268: aload_1
     269: invokeinterface #17,  1           // InterfaceMethod java/util/Collection.iterator:()Ljava/util/Iterator;
     274: astore        8
     276: iconst_0
     277: istore        9
     279: aload         8
     281: invokeinterface #18,  1           // InterfaceMethod java/util/Iterator.hasNext:()Z
     286: ifeq          613
     289: aload         8
     291: invokeinterface #19,  1           // InterfaceMethod java/util/Iterator.next:()Ljava/lang/Object;
     296: astore        10
     298: aload         10
     300: instanceof    #70                 // class org/htmlcleaner/TagNode
     303: ifeq          606
     306: aload         10
     308: checkcast     #70                 // class org/htmlcleaner/TagNode
     311: astore        11
     313: iinc          9, 1
     316: ldc           #97                 // String .
     318: aload         6
     320: invokevirtual #23                 // Method java/lang/String.equals:(Ljava/lang/Object;)Z
     323: istore        12
     325: ldc           #98                 // String ..
     327: aload         6
     329: invokevirtual #23                 // Method java/lang/String.equals:(Ljava/lang/Object;)Z
     332: istore        13
     334: ldc           #93                 // String *
     336: aload         6
     338: invokevirtual #23                 // Method java/lang/String.equals:(Ljava/lang/Object;)Z
     341: istore        14
     343: iload         12
     345: ifeq          359
     348: aload_0
     349: aload         11
     351: invokespecial #13                 // Method singleton:(Ljava/lang/Object;)Ljava/util/Collection;
     354: astore        15
     356: goto          420
     359: iload         13
     361: ifeq          397
     364: aload         11
     366: invokevirtual #99                 // Method org/htmlcleaner/TagNode.getParent:()Lorg/htmlcleaner/TagNode;
     369: astore        16
     371: aload         16
     373: ifnull        385
     376: aload_0
     377: aload         16
     379: invokespecial #13                 // Method singleton:(Ljava/lang/Object;)Ljava/util/Collection;
     382: goto          392
     385: new           #63                 // class java/util/ArrayList
     388: dup
     389: invokespecial #64                 // Method java/util/ArrayList."<init>":()V
     392: astore        15
     394: goto          420
     397: iload         14
     399: ifeq          410
     402: aload         11
     404: invokevirtual #100                // Method org/htmlcleaner/TagNode.getChildTagList:()Ljava/util/List;
     407: goto          418
     410: aload         11
     412: aload         6
     414: iconst_0
     415: invokevirtual #101                // Method org/htmlcleaner/TagNode.getElementListByName:(Ljava/lang/String;Z)Ljava/util/List;
     418: astore        15
     420: new           #89                 // class java/util/LinkedHashSet
     423: dup
     424: aload         15
     426: invokespecial #102                // Method java/util/LinkedHashSet."<init>":(Ljava/util/Collection;)V
     429: astore        16
     431: aload_0
     432: aload         16
     434: iload_2
     435: iconst_1
     436: iadd
     437: iload_3
     438: iconst_0
     439: iload         9
     441: aload         16
     443: invokevirtual #103                // Method java/util/LinkedHashSet.size:()I
     446: iload         5
     448: aconst_null
     449: invokespecial #14                 // Method evaluateAgainst:(Ljava/util/Collection;IIZIIZLjava/util/Collection;)Ljava/util/Collection;
     452: astore        17
     454: iload         4
     456: ifeq          593
     459: aload         11
     461: invokevirtual #100                // Method org/htmlcleaner/TagNode.getChildTagList:()Ljava/util/List;
     464: astore        18
     466: iload         12
     468: ifne          481
     471: iload         13
     473: ifne          481
     476: iload         14
     478: ifeq          491
     481: aload         7
     483: aload         17
     485: invokeinterface #92,  2           // InterfaceMethod java/util/Collection.addAll:(Ljava/util/Collection;)Z
     490: pop
     491: aload         18
     493: invokeinterface #104,  1          // InterfaceMethod java/util/List.iterator:()Ljava/util/Iterator;
     498: astore        19
     500: aload         19
     502: invokeinterface #18,  1           // InterfaceMethod java/util/Iterator.hasNext:()Z
     507: ifeq          590
     510: aload         19
     512: invokeinterface #19,  1           // InterfaceMethod java/util/Iterator.next:()Ljava/lang/Object;
     517: checkcast     #70                 // class org/htmlcleaner/TagNode
     520: astore        20
     522: aload_0
     523: aload_0
     524: aload         20
     526: invokespecial #13                 // Method singleton:(Ljava/lang/Object;)Ljava/util/Collection;
     529: iload_2
     530: iload_3
     531: iload         4
     533: iload         5
     535: invokespecial #50                 // Method getElementsByName:(Ljava/util/Collection;IIZZ)Ljava/util/Collection;
     538: astore        21
     540: iload         12
     542: ifne          577
     545: iload         13
     547: ifne          577
     550: iload         14
     552: ifne          577
     555: aload         17
     557: aload         20
     559: invokeinterface #105,  2          // InterfaceMethod java/util/Collection.contains:(Ljava/lang/Object;)Z
     564: ifeq          577
     567: aload         7
     569: aload         20
     571: invokeinterface #106,  2          // InterfaceMethod java/util/Collection.add:(Ljava/lang/Object;)Z
     576: pop
     577: aload         7
     579: aload         21
     581: invokeinterface #92,  2           // InterfaceMethod java/util/Collection.addAll:(Ljava/util/Collection;)Z
     586: pop
     587: goto          500
     590: goto          603
     593: aload         7
     595: aload         17
     597: invokeinterface #92,  2           // InterfaceMethod java/util/Collection.addAll:(Ljava/util/Collection;)Z
     602: pop
     603: goto          610
     606: aload_0
     607: invokespecial #27                 // Method throwStandardException:()V
     610: goto          279
     613: aload         7
     615: areturn

  private boolean evaluateLogic(java.util.Collection, java.util.Collection, java.lang.String);
    Code:
       0: aload_1
       1: ifnull        26
       4: aload_1
       5: invokeinterface #15,  1           // InterfaceMethod java/util/Collection.size:()I
      10: ifeq          26
      13: aload_2
      14: ifnull        26
      17: aload_2
      18: invokeinterface #15,  1           // InterfaceMethod java/util/Collection.size:()I
      23: ifne          28
      26: iconst_0
      27: ireturn
      28: aload_1
      29: invokeinterface #17,  1           // InterfaceMethod java/util/Collection.iterator:()Ljava/util/Iterator;
      34: invokeinterface #19,  1           // InterfaceMethod java/util/Iterator.next:()Ljava/lang/Object;
      39: astore        4
      41: aload_2
      42: invokeinterface #17,  1           // InterfaceMethod java/util/Collection.iterator:()Ljava/util/Iterator;
      47: invokeinterface #19,  1           // InterfaceMethod java/util/Iterator.next:()Ljava/lang/Object;
      52: astore        5
      54: aload         4
      56: instanceof    #107                // class java/lang/Number
      59: ifeq          208
      62: aload         5
      64: instanceof    #107                // class java/lang/Number
      67: ifeq          208
      70: aload         4
      72: checkcast     #107                // class java/lang/Number
      75: invokevirtual #108                // Method java/lang/Number.doubleValue:()D
      78: dstore        6
      80: aload         5
      82: checkcast     #107                // class java/lang/Number
      85: invokevirtual #108                // Method java/lang/Number.doubleValue:()D
      88: dstore        8
      90: ldc           #33                 // String =
      92: aload_3
      93: invokevirtual #23                 // Method java/lang/String.equals:(Ljava/lang/Object;)Z
      96: ifeq          113
      99: dload         6
     101: dload         8
     103: dcmpl
     104: ifne          111
     107: iconst_1
     108: goto          112
     111: iconst_0
     112: ireturn
     113: ldc           #34                 // String <
     115: aload_3
     116: invokevirtual #23                 // Method java/lang/String.equals:(Ljava/lang/Object;)Z
     119: ifeq          136
     122: dload         6
     124: dload         8
     126: dcmpg
     127: ifge          134
     130: iconst_1
     131: goto          135
     134: iconst_0
     135: ireturn
     136: ldc           #35                 // String >
     138: aload_3
     139: invokevirtual #23                 // Method java/lang/String.equals:(Ljava/lang/Object;)Z
     142: ifeq          159
     145: dload         6
     147: dload         8
     149: dcmpl
     150: ifle          157
     153: iconst_1
     154: goto          158
     157: iconst_0
     158: ireturn
     159: ldc           #109                // String <=
     161: aload_3
     162: invokevirtual #23                 // Method java/lang/String.equals:(Ljava/lang/Object;)Z
     165: ifeq          182
     168: dload         6
     170: dload         8
     172: dcmpg
     173: ifgt          180
     176: iconst_1
     177: goto          181
     180: iconst_0
     181: ireturn
     182: ldc           #110                // String >=
     184: aload_3
     185: invokevirtual #23                 // Method java/lang/String.equals:(Ljava/lang/Object;)Z
     188: ifeq          205
     191: dload         6
     193: dload         8
     195: dcmpl
     196: iflt          203
     199: iconst_1
     200: goto          204
     203: iconst_0
     204: ireturn
     205: goto          333
     208: aload_0
     209: aload         4
     211: invokespecial #111                // Method toText:(Ljava/lang/Object;)Ljava/lang/String;
     214: astore        6
     216: aload_0
     217: aload         5
     219: invokespecial #111                // Method toText:(Ljava/lang/Object;)Ljava/lang/String;
     222: astore        7
     224: aload         6
     226: aload         7
     228: invokevirtual #112                // Method java/lang/String.compareTo:(Ljava/lang/String;)I
     231: istore        8
     233: ldc           #33                 // String =
     235: aload_3
     236: invokevirtual #23                 // Method java/lang/String.equals:(Ljava/lang/Object;)Z
     239: ifeq          253
     242: iload         8
     244: ifne          251
     247: iconst_1
     248: goto          252
     251: iconst_0
     252: ireturn
     253: ldc           #34                 // String <
     255: aload_3
     256: invokevirtual #23                 // Method java/lang/String.equals:(Ljava/lang/Object;)Z
     259: ifeq          273
     262: iload         8
     264: ifge          271
     267: iconst_1
     268: goto          272
     271: iconst_0
     272: ireturn
     273: ldc           #35                 // String >
     275: aload_3
     276: invokevirtual #23                 // Method java/lang/String.equals:(Ljava/lang/Object;)Z
     279: ifeq          293
     282: iload         8
     284: ifle          291
     287: iconst_1
     288: goto          292
     291: iconst_0
     292: ireturn
     293: ldc           #109                // String <=
     295: aload_3
     296: invokevirtual #23                 // Method java/lang/String.equals:(Ljava/lang/Object;)Z
     299: ifeq          313
     302: iload         8
     304: ifgt          311
     307: iconst_1
     308: goto          312
     311: iconst_0
     312: ireturn
     313: ldc           #110                // String >=
     315: aload_3
     316: invokevirtual #23                 // Method java/lang/String.equals:(Ljava/lang/Object;)Z
     319: ifeq          333
     322: iload         8
     324: iflt          331
     327: iconst_1
     328: goto          332
     331: iconst_0
     332: ireturn
     333: iconst_0
     334: ireturn

  private java.lang.String toText(java.lang.Object);
    Code:
       0: aload_1
       1: ifnonnull     7
       4: ldc           #21                 // String
       6: areturn
       7: aload_1
       8: instanceof    #70                 // class org/htmlcleaner/TagNode
      11: ifeq          25
      14: aload_1
      15: checkcast     #70                 // class org/htmlcleaner/TagNode
      18: invokevirtual #71                 // Method org/htmlcleaner/TagNode.getText:()Ljava/lang/CharSequence;
      21: invokevirtual #72                 // Method java/lang/Object.toString:()Ljava/lang/String;
      24: areturn
      25: aload_1
      26: invokevirtual #72                 // Method java/lang/Object.toString:()Ljava/lang/String;
      29: areturn
}
