Compiled from "DefaultInternalAdminClient.java"
public class org.apache.kerby.kerberos.kerb.admin.kadmin.remote.impl.DefaultInternalAdminClient extends org.apache.kerby.kerberos.kerb.admin.kadmin.remote.impl.AbstractInternalAdminClient {
  private org.apache.kerby.kerberos.kerb.admin.kadmin.remote.impl.DefaultAdminHandler adminHandler;

  private org.apache.kerby.kerberos.kerb.transport.KrbTransport transport;

  public org.apache.kerby.kerberos.kerb.admin.kadmin.remote.impl.DefaultInternalAdminClient(org.apache.kerby.kerberos.kerb.admin.kadmin.remote.AdminSetting);
    Code:
       0: aload_0
       1: aload_1
       2: invokespecial #1                  // Method org/apache/kerby/kerberos/kerb/admin/kadmin/remote/impl/AbstractInternalAdminClient."<init>":(Lorg/apache/kerby/kerberos/kerb/admin/kadmin/remote/AdminSetting;)V
       5: return

  public org.apache.kerby.kerberos.kerb.admin.kadmin.remote.AdminHandler getAdminHanlder();
    Code:
       0: aload_0
       1: getfield      #2                  // Field adminHandler:Lorg/apache/kerby/kerberos/kerb/admin/kadmin/remote/impl/DefaultAdminHandler;
       4: areturn

  public org.apache.kerby.kerberos.kerb.transport.KrbTransport getTransport();
    Code:
       0: aload_0
       1: getfield      #3                  // Field transport:Lorg/apache/kerby/kerberos/kerb/transport/KrbTransport;
       4: areturn

  public void init() throws org.apache.kerby.kerberos.kerb.KrbException;
    Code:
       0: aload_0
       1: invokespecial #4                  // Method org/apache/kerby/kerberos/kerb/admin/kadmin/remote/impl/AbstractInternalAdminClient.init:()V
       4: aload_0
       5: new           #5                  // class org/apache/kerby/kerberos/kerb/admin/kadmin/remote/impl/DefaultAdminHandler
       8: dup
       9: invokespecial #6                  // Method org/apache/kerby/kerberos/kerb/admin/kadmin/remote/impl/DefaultAdminHandler."<init>":()V
      12: putfield      #2                  // Field adminHandler:Lorg/apache/kerby/kerberos/kerb/admin/kadmin/remote/impl/DefaultAdminHandler;
      15: aload_0
      16: getfield      #2                  // Field adminHandler:Lorg/apache/kerby/kerberos/kerb/admin/kadmin/remote/impl/DefaultAdminHandler;
      19: aload_0
      20: invokevirtual #7                  // Method getContext:()Lorg/apache/kerby/kerberos/kerb/admin/kadmin/remote/AdminContext;
      23: invokevirtual #8                  // Method org/apache/kerby/kerberos/kerb/admin/kadmin/remote/impl/DefaultAdminHandler.init:(Lorg/apache/kerby/kerberos/kerb/admin/kadmin/remote/AdminContext;)V
      26: aload_0
      27: invokevirtual #9                  // Method getSetting:()Lorg/apache/kerby/kerberos/kerb/admin/kadmin/remote/AdminSetting;
      30: invokestatic  #10                 // Method org/apache/kerby/kerberos/kerb/admin/kadmin/remote/AdminUtil.getTransportPair:(Lorg/apache/kerby/kerberos/kerb/admin/kadmin/remote/AdminSetting;)Lorg/apache/kerby/kerberos/kerb/transport/TransportPair;
      33: astore_1
      34: new           #11                 // class org/apache/kerby/kerberos/kerb/transport/KrbNetwork
      37: dup
      38: invokespecial #12                 // Method org/apache/kerby/kerberos/kerb/transport/KrbNetwork."<init>":()V
      41: astore_2
      42: aload_2
      43: aload_0
      44: invokevirtual #9                  // Method getSetting:()Lorg/apache/kerby/kerberos/kerb/admin/kadmin/remote/AdminSetting;
      47: invokevirtual #13                 // Method org/apache/kerby/kerberos/kerb/admin/kadmin/remote/AdminSetting.getTimeout:()I
      50: invokevirtual #14                 // Method org/apache/kerby/kerberos/kerb/transport/KrbNetwork.setSocketTimeout:(I)V
      53: aload_0
      54: aload_2
      55: aload_1
      56: invokevirtual #15                 // Method org/apache/kerby/kerberos/kerb/transport/KrbNetwork.connect:(Lorg/apache/kerby/kerberos/kerb/transport/TransportPair;)Lorg/apache/kerby/kerberos/kerb/transport/KrbTransport;
      59: putfield      #3                  // Field transport:Lorg/apache/kerby/kerberos/kerb/transport/KrbTransport;
      62: goto          77
      65: astore_3
      66: new           #17                 // class org/apache/kerby/kerberos/kerb/KrbException
      69: dup
      70: ldc           #18                 // String Failed to create transport
      72: aload_3
      73: invokespecial #19                 // Method org/apache/kerby/kerberos/kerb/KrbException."<init>":(Ljava/lang/String;Ljava/lang/Throwable;)V
      76: athrow
      77: return
    Exception table:
       from    to  target type
          53    62    65   Class java/io/IOException
}
