Compiled from "DefaultAsyncWaitStrategyFactory.java"
class org.apache.logging.log4j.core.async.DefaultAsyncWaitStrategyFactory implements org.apache.logging.log4j.core.async.AsyncWaitStrategyFactory {
  static final java.lang.String DEFAULT_WAIT_STRATEGY_CLASSNAME;

  private static final org.apache.logging.log4j.Logger LOGGER;

  private final java.lang.String propertyName;

  public org.apache.logging.log4j.core.async.DefaultAsyncWaitStrategyFactory(java.lang.String);
    Code:
       0: aload_0
       1: invokespecial #1                  // Method java/lang/Object."<init>":()V
       4: aload_0
       5: aload_1
       6: putfield      #2                  // Field propertyName:Ljava/lang/String;
       9: return

  public com.lmax.disruptor.WaitStrategy createWaitStrategy();
    Code:
       0: invokestatic  #3                  // Method org/apache/logging/log4j/util/PropertiesUtil.getProperties:()Lorg/apache/logging/log4j/util/PropertiesUtil;
       3: aload_0
       4: getfield      #2                  // Field propertyName:Ljava/lang/String;
       7: ldc           #4                  // String TIMEOUT
       9: invokevirtual #5                  // Method org/apache/logging/log4j/util/PropertiesUtil.getStringProperty:(Ljava/lang/String;Ljava/lang/String;)Ljava/lang/String;
      12: astore_1
      13: getstatic     #6                  // Field LOGGER:Lorg/apache/logging/log4j/Logger;
      16: ldc           #7                  // String DefaultAsyncWaitStrategyFactory property {}={}
      18: aload_0
      19: getfield      #2                  // Field propertyName:Ljava/lang/String;
      22: aload_1
      23: invokeinterface #8,  4            // InterfaceMethod org/apache/logging/log4j/Logger.trace:(Ljava/lang/String;Ljava/lang/Object;Ljava/lang/Object;)V
      28: aload_1
      29: invokestatic  #9                  // Method org/apache/logging/log4j/util/Strings.toRootUpperCase:(Ljava/lang/String;)Ljava/lang/String;
      32: astore_2
      33: aload_2
      34: astore_3
      35: iconst_m1
      36: istore        4
      38: aload_3
      39: invokevirtual #10                 // Method java/lang/String.hashCode:()I
      42: lookupswitch  { // 5
            -595928767: 152
            -349268549: 137
              63294573: 122
              78984887: 92
              84436845: 107
               default: 164
          }
      92: aload_3
      93: ldc           #11                 // String SLEEP
      95: invokevirtual #12                 // Method java/lang/String.equals:(Ljava/lang/Object;)Z
      98: ifeq          164
     101: iconst_0
     102: istore        4
     104: goto          164
     107: aload_3
     108: ldc           #13                 // String YIELD
     110: invokevirtual #12                 // Method java/lang/String.equals:(Ljava/lang/Object;)Z
     113: ifeq          164
     116: iconst_1
     117: istore        4
     119: goto          164
     122: aload_3
     123: ldc           #14                 // String BLOCK
     125: invokevirtual #12                 // Method java/lang/String.equals:(Ljava/lang/Object;)Z
     128: ifeq          164
     131: iconst_2
     132: istore        4
     134: goto          164
     137: aload_3
     138: ldc           #15                 // String BUSYSPIN
     140: invokevirtual #12                 // Method java/lang/String.equals:(Ljava/lang/Object;)Z
     143: ifeq          164
     146: iconst_3
     147: istore        4
     149: goto          164
     152: aload_3
     153: ldc           #4                  // String TIMEOUT
     155: invokevirtual #12                 // Method java/lang/String.equals:(Ljava/lang/Object;)Z
     158: ifeq          164
     161: iconst_4
     162: istore        4
     164: iload         4
     166: tableswitch   { // 0 to 4
                     0: 200
                     1: 270
                     2: 288
                     3: 306
                     4: 324
               default: 332
          }
     200: aload_0
     201: getfield      #2                  // Field propertyName:Ljava/lang/String;
     204: ldc           #16                 // String SleepTimeNs
     206: ldc2_w        #17                 // long 100l
     209: invokestatic  #19                 // Method parseAdditionalLongProperty:(Ljava/lang/String;Ljava/lang/String;J)J
     212: lstore        5
     214: aload_0
     215: getfield      #2                  // Field propertyName:Ljava/lang/String;
     218: ldc           #20                 // String Retries
     220: invokestatic  #21                 // Method getFullPropertyKey:(Ljava/lang/String;Ljava/lang/String;)Ljava/lang/String;
     223: astore        7
     225: invokestatic  #3                  // Method org/apache/logging/log4j/util/PropertiesUtil.getProperties:()Lorg/apache/logging/log4j/util/PropertiesUtil;
     228: aload         7
     230: sipush        200
     233: invokevirtual #22                 // Method org/apache/logging/log4j/util/PropertiesUtil.getIntegerProperty:(Ljava/lang/String;I)I
     236: istore        8
     238: getstatic     #6                  // Field LOGGER:Lorg/apache/logging/log4j/Logger;
     241: ldc           #23                 // String DefaultAsyncWaitStrategyFactory creating SleepingWaitStrategy(retries={}, sleepTimeNs={})
     243: iload         8
     245: invokestatic  #24                 // Method java/lang/Integer.valueOf:(I)Ljava/lang/Integer;
     248: lload         5
     250: invokestatic  #25                 // Method java/lang/Long.valueOf:(J)Ljava/lang/Long;
     253: invokeinterface #8,  4            // InterfaceMethod org/apache/logging/log4j/Logger.trace:(Ljava/lang/String;Ljava/lang/Object;Ljava/lang/Object;)V
     258: new           #26                 // class com/lmax/disruptor/SleepingWaitStrategy
     261: dup
     262: iload         8
     264: lload         5
     266: invokespecial #27                 // Method com/lmax/disruptor/SleepingWaitStrategy."<init>":(IJ)V
     269: areturn
     270: getstatic     #6                  // Field LOGGER:Lorg/apache/logging/log4j/Logger;
     273: ldc           #28                 // String DefaultAsyncWaitStrategyFactory creating YieldingWaitStrategy
     275: invokeinterface #29,  2           // InterfaceMethod org/apache/logging/log4j/Logger.trace:(Ljava/lang/String;)V
     280: new           #30                 // class com/lmax/disruptor/YieldingWaitStrategy
     283: dup
     284: invokespecial #31                 // Method com/lmax/disruptor/YieldingWaitStrategy."<init>":()V
     287: areturn
     288: getstatic     #6                  // Field LOGGER:Lorg/apache/logging/log4j/Logger;
     291: ldc           #32                 // String DefaultAsyncWaitStrategyFactory creating BlockingWaitStrategy
     293: invokeinterface #29,  2           // InterfaceMethod org/apache/logging/log4j/Logger.trace:(Ljava/lang/String;)V
     298: new           #33                 // class com/lmax/disruptor/BlockingWaitStrategy
     301: dup
     302: invokespecial #34                 // Method com/lmax/disruptor/BlockingWaitStrategy."<init>":()V
     305: areturn
     306: getstatic     #6                  // Field LOGGER:Lorg/apache/logging/log4j/Logger;
     309: ldc           #35                 // String DefaultAsyncWaitStrategyFactory creating BusySpinWaitStrategy
     311: invokeinterface #29,  2           // InterfaceMethod org/apache/logging/log4j/Logger.trace:(Ljava/lang/String;)V
     316: new           #36                 // class com/lmax/disruptor/BusySpinWaitStrategy
     319: dup
     320: invokespecial #37                 // Method com/lmax/disruptor/BusySpinWaitStrategy."<init>":()V
     323: areturn
     324: aload_0
     325: getfield      #2                  // Field propertyName:Ljava/lang/String;
     328: invokestatic  #38                 // Method createDefaultWaitStrategy:(Ljava/lang/String;)Lcom/lmax/disruptor/WaitStrategy;
     331: areturn
     332: aload_0
     333: getfield      #2                  // Field propertyName:Ljava/lang/String;
     336: invokestatic  #38                 // Method createDefaultWaitStrategy:(Ljava/lang/String;)Lcom/lmax/disruptor/WaitStrategy;
     339: areturn

  static com.lmax.disruptor.WaitStrategy createDefaultWaitStrategy(java.lang.String);
    Code:
       0: aload_0
       1: ldc           #39                 // String Timeout
       3: ldc2_w        #40                 // long 10l
       6: invokestatic  #19                 // Method parseAdditionalLongProperty:(Ljava/lang/String;Ljava/lang/String;J)J
       9: lstore_1
      10: getstatic     #6                  // Field LOGGER:Lorg/apache/logging/log4j/Logger;
      13: ldc           #42                 // String DefaultAsyncWaitStrategyFactory creating TimeoutBlockingWaitStrategy(timeout={}, unit=MILLIS)
      15: lload_1
      16: invokestatic  #25                 // Method java/lang/Long.valueOf:(J)Ljava/lang/Long;
      19: invokeinterface #43,  3           // InterfaceMethod org/apache/logging/log4j/Logger.trace:(Ljava/lang/String;Ljava/lang/Object;)V
      24: new           #44                 // class org/apache/logging/log4j/core/async/TimeoutBlockingWaitStrategy
      27: dup
      28: lload_1
      29: getstatic     #45                 // Field java/util/concurrent/TimeUnit.MILLISECONDS:Ljava/util/concurrent/TimeUnit;
      32: invokespecial #46                 // Method org/apache/logging/log4j/core/async/TimeoutBlockingWaitStrategy."<init>":(JLjava/util/concurrent/TimeUnit;)V
      35: areturn

  private static java.lang.String getFullPropertyKey(java.lang.String, java.lang.String);
    Code:
       0: aload_0
       1: ldc           #47                 // String AsyncLogger.
       3: invokevirtual #48                 // Method java/lang/String.startsWith:(Ljava/lang/String;)Z
       6: ifeq          29
       9: new           #49                 // class java/lang/StringBuilder
      12: dup
      13: invokespecial #50                 // Method java/lang/StringBuilder."<init>":()V
      16: ldc           #47                 // String AsyncLogger.
      18: invokevirtual #51                 // Method java/lang/StringBuilder.append:(Ljava/lang/String;)Ljava/lang/StringBuilder;
      21: aload_1
      22: invokevirtual #51                 // Method java/lang/StringBuilder.append:(Ljava/lang/String;)Ljava/lang/StringBuilder;
      25: invokevirtual #52                 // Method java/lang/StringBuilder.toString:()Ljava/lang/String;
      28: areturn
      29: aload_0
      30: ldc           #53                 // String AsyncLoggerConfig.
      32: invokevirtual #48                 // Method java/lang/String.startsWith:(Ljava/lang/String;)Z
      35: ifeq          58
      38: new           #49                 // class java/lang/StringBuilder
      41: dup
      42: invokespecial #50                 // Method java/lang/StringBuilder."<init>":()V
      45: ldc           #53                 // String AsyncLoggerConfig.
      47: invokevirtual #51                 // Method java/lang/StringBuilder.append:(Ljava/lang/String;)Ljava/lang/StringBuilder;
      50: aload_1
      51: invokevirtual #51                 // Method java/lang/StringBuilder.append:(Ljava/lang/String;)Ljava/lang/StringBuilder;
      54: invokevirtual #52                 // Method java/lang/StringBuilder.toString:()Ljava/lang/String;
      57: areturn
      58: new           #49                 // class java/lang/StringBuilder
      61: dup
      62: invokespecial #50                 // Method java/lang/StringBuilder."<init>":()V
      65: aload_0
      66: invokevirtual #51                 // Method java/lang/StringBuilder.append:(Ljava/lang/String;)Ljava/lang/StringBuilder;
      69: aload_1
      70: invokevirtual #51                 // Method java/lang/StringBuilder.append:(Ljava/lang/String;)Ljava/lang/StringBuilder;
      73: invokevirtual #52                 // Method java/lang/StringBuilder.toString:()Ljava/lang/String;
      76: areturn

  private static long parseAdditionalLongProperty(java.lang.String, java.lang.String, long);
    Code:
       0: aload_0
       1: aload_1
       2: invokestatic  #21                 // Method getFullPropertyKey:(Ljava/lang/String;Ljava/lang/String;)Ljava/lang/String;
       5: astore        4
       7: invokestatic  #3                  // Method org/apache/logging/log4j/util/PropertiesUtil.getProperties:()Lorg/apache/logging/log4j/util/PropertiesUtil;
      10: aload         4
      12: lload_2
      13: invokevirtual #54                 // Method org/apache/logging/log4j/util/PropertiesUtil.getLongProperty:(Ljava/lang/String;J)J
      16: lreturn

  static {};
    Code:
       0: ldc           #44                 // class org/apache/logging/log4j/core/async/TimeoutBlockingWaitStrategy
       2: invokevirtual #55                 // Method java/lang/Class.getName:()Ljava/lang/String;
       5: putstatic     #56                 // Field DEFAULT_WAIT_STRATEGY_CLASSNAME:Ljava/lang/String;
       8: invokestatic  #57                 // Method org/apache/logging/log4j/status/StatusLogger.getLogger:()Lorg/apache/logging/log4j/status/StatusLogger;
      11: putstatic     #6                  // Field LOGGER:Lorg/apache/logging/log4j/Logger;
      14: return
}
