Compiled from "RingBufferLogEventTranslator.java"
public class org.apache.logging.log4j.core.async.RingBufferLogEventTranslator implements com.lmax.disruptor.EventTranslator<org.apache.logging.log4j.core.async.RingBufferLogEvent> {
  private static final org.apache.logging.log4j.core.ContextDataInjector INJECTOR;

  private org.apache.logging.log4j.core.async.AsyncLogger asyncLogger;

  java.lang.String loggerName;

  protected org.apache.logging.log4j.Marker marker;

  protected java.lang.String fqcn;

  protected org.apache.logging.log4j.Level level;

  protected org.apache.logging.log4j.message.Message message;

  protected java.lang.Throwable thrown;

  private org.apache.logging.log4j.ThreadContext$ContextStack contextStack;

  private long threadId;

  private java.lang.String threadName;

  private int threadPriority;

  private java.lang.StackTraceElement location;

  private org.apache.logging.log4j.core.util.Clock clock;

  private org.apache.logging.log4j.core.util.NanoClock nanoClock;

  public org.apache.logging.log4j.core.async.RingBufferLogEventTranslator();
    Code:
       0: aload_0
       1: invokespecial #1                  // Method java/lang/Object."<init>":()V
       4: aload_0
       5: invokestatic  #2                  // Method java/lang/Thread.currentThread:()Ljava/lang/Thread;
       8: invokevirtual #3                  // Method java/lang/Thread.getId:()J
      11: putfield      #4                  // Field threadId:J
      14: aload_0
      15: invokestatic  #2                  // Method java/lang/Thread.currentThread:()Ljava/lang/Thread;
      18: invokevirtual #5                  // Method java/lang/Thread.getName:()Ljava/lang/String;
      21: putfield      #6                  // Field threadName:Ljava/lang/String;
      24: aload_0
      25: invokestatic  #2                  // Method java/lang/Thread.currentThread:()Ljava/lang/Thread;
      28: invokevirtual #7                  // Method java/lang/Thread.getPriority:()I
      31: putfield      #8                  // Field threadPriority:I
      34: return

  public void translateTo(org.apache.logging.log4j.core.async.RingBufferLogEvent, long);
    Code:
       0: aload_1
       1: aload_0
       2: getfield      #9                  // Field asyncLogger:Lorg/apache/logging/log4j/core/async/AsyncLogger;
       5: aload_0
       6: getfield      #10                 // Field loggerName:Ljava/lang/String;
       9: aload_0
      10: getfield      #11                 // Field marker:Lorg/apache/logging/log4j/Marker;
      13: aload_0
      14: getfield      #12                 // Field fqcn:Ljava/lang/String;
      17: aload_0
      18: getfield      #13                 // Field level:Lorg/apache/logging/log4j/Level;
      21: aload_0
      22: getfield      #14                 // Field message:Lorg/apache/logging/log4j/message/Message;
      25: aload_0
      26: getfield      #15                 // Field thrown:Ljava/lang/Throwable;
      29: getstatic     #16                 // Field INJECTOR:Lorg/apache/logging/log4j/core/ContextDataInjector;
      32: aconst_null
      33: aload_1
      34: invokevirtual #17                 // Method org/apache/logging/log4j/core/async/RingBufferLogEvent.getContextData:()Lorg/apache/logging/log4j/util/ReadOnlyStringMap;
      37: checkcast     #18                 // class org/apache/logging/log4j/util/StringMap
      40: invokeinterface #19,  3           // InterfaceMethod org/apache/logging/log4j/core/ContextDataInjector.injectContextData:(Ljava/util/List;Lorg/apache/logging/log4j/util/StringMap;)Lorg/apache/logging/log4j/util/StringMap;
      45: aload_0
      46: getfield      #20                 // Field contextStack:Lorg/apache/logging/log4j/ThreadContext$ContextStack;
      49: aload_0
      50: getfield      #4                  // Field threadId:J
      53: aload_0
      54: getfield      #6                  // Field threadName:Ljava/lang/String;
      57: aload_0
      58: getfield      #8                  // Field threadPriority:I
      61: aload_0
      62: getfield      #21                 // Field location:Ljava/lang/StackTraceElement;
      65: aload_0
      66: getfield      #22                 // Field clock:Lorg/apache/logging/log4j/core/util/Clock;
      69: aload_0
      70: getfield      #23                 // Field nanoClock:Lorg/apache/logging/log4j/core/util/NanoClock;
      73: invokevirtual #24                 // Method org/apache/logging/log4j/core/async/RingBufferLogEvent.setValues:(Lorg/apache/logging/log4j/core/async/AsyncLogger;Ljava/lang/String;Lorg/apache/logging/log4j/Marker;Ljava/lang/String;Lorg/apache/logging/log4j/Level;Lorg/apache/logging/log4j/message/Message;Ljava/lang/Throwable;Lorg/apache/logging/log4j/util/StringMap;Lorg/apache/logging/log4j/ThreadContext$ContextStack;JLjava/lang/String;ILjava/lang/StackTraceElement;Lorg/apache/logging/log4j/core/util/Clock;Lorg/apache/logging/log4j/core/util/NanoClock;)V
      76: aload_0
      77: invokevirtual #25                 // Method clear:()V
      80: goto          92
      83: astore        4
      85: aload_0
      86: invokevirtual #25                 // Method clear:()V
      89: aload         4
      91: athrow
      92: return
    Exception table:
       from    to  target type
           0    76    83   any
          83    85    83   any

  void clear();
    Code:
       0: aload_0
       1: aconst_null
       2: aconst_null
       3: aconst_null
       4: aconst_null
       5: aconst_null
       6: aconst_null
       7: aconst_null
       8: aconst_null
       9: aconst_null
      10: aconst_null
      11: aconst_null
      12: invokevirtual #26                 // Method setBasicValues:(Lorg/apache/logging/log4j/core/async/AsyncLogger;Ljava/lang/String;Lorg/apache/logging/log4j/Marker;Ljava/lang/String;Lorg/apache/logging/log4j/Level;Lorg/apache/logging/log4j/message/Message;Ljava/lang/Throwable;Lorg/apache/logging/log4j/ThreadContext$ContextStack;Ljava/lang/StackTraceElement;Lorg/apache/logging/log4j/core/util/Clock;Lorg/apache/logging/log4j/core/util/NanoClock;)V
      15: return

  public void setBasicValues(org.apache.logging.log4j.core.async.AsyncLogger, java.lang.String, org.apache.logging.log4j.Marker, java.lang.String, org.apache.logging.log4j.Level, org.apache.logging.log4j.message.Message, java.lang.Throwable, org.apache.logging.log4j.ThreadContext$ContextStack, java.lang.StackTraceElement, org.apache.logging.log4j.core.util.Clock, org.apache.logging.log4j.core.util.NanoClock);
    Code:
       0: aload_0
       1: aload_1
       2: putfield      #9                  // Field asyncLogger:Lorg/apache/logging/log4j/core/async/AsyncLogger;
       5: aload_0
       6: aload_2
       7: putfield      #10                 // Field loggerName:Ljava/lang/String;
      10: aload_0
      11: aload_3
      12: putfield      #11                 // Field marker:Lorg/apache/logging/log4j/Marker;
      15: aload_0
      16: aload         4
      18: putfield      #12                 // Field fqcn:Ljava/lang/String;
      21: aload_0
      22: aload         5
      24: putfield      #13                 // Field level:Lorg/apache/logging/log4j/Level;
      27: aload_0
      28: aload         6
      30: putfield      #14                 // Field message:Lorg/apache/logging/log4j/message/Message;
      33: aload_0
      34: aload         7
      36: putfield      #15                 // Field thrown:Ljava/lang/Throwable;
      39: aload_0
      40: aload         8
      42: putfield      #20                 // Field contextStack:Lorg/apache/logging/log4j/ThreadContext$ContextStack;
      45: aload_0
      46: aload         9
      48: putfield      #21                 // Field location:Ljava/lang/StackTraceElement;
      51: aload_0
      52: aload         10
      54: putfield      #22                 // Field clock:Lorg/apache/logging/log4j/core/util/Clock;
      57: aload_0
      58: aload         11
      60: putfield      #23                 // Field nanoClock:Lorg/apache/logging/log4j/core/util/NanoClock;
      63: return

  public void updateThreadValues();
    Code:
       0: invokestatic  #2                  // Method java/lang/Thread.currentThread:()Ljava/lang/Thread;
       3: astore_1
       4: aload_0
       5: aload_1
       6: invokevirtual #3                  // Method java/lang/Thread.getId:()J
       9: putfield      #4                  // Field threadId:J
      12: aload_0
      13: aload_1
      14: invokevirtual #5                  // Method java/lang/Thread.getName:()Ljava/lang/String;
      17: putfield      #6                  // Field threadName:Ljava/lang/String;
      20: aload_0
      21: aload_1
      22: invokevirtual #7                  // Method java/lang/Thread.getPriority:()I
      25: putfield      #8                  // Field threadPriority:I
      28: return

  public void translateTo(java.lang.Object, long);
    Code:
       0: aload_0
       1: aload_1
       2: checkcast     #27                 // class org/apache/logging/log4j/core/async/RingBufferLogEvent
       5: lload_2
       6: invokevirtual #28                 // Method translateTo:(Lorg/apache/logging/log4j/core/async/RingBufferLogEvent;J)V
       9: return

  static {};
    Code:
       0: invokestatic  #29                 // Method org/apache/logging/log4j/core/impl/ContextDataInjectorFactory.createInjector:()Lorg/apache/logging/log4j/core/ContextDataInjector;
       3: putstatic     #16                 // Field INJECTOR:Lorg/apache/logging/log4j/core/ContextDataInjector;
       6: return
}
