Compiled from "WUFileType.java"
public final class org.hpccsystems.ws.client.wrappers.WUFileType extends java.lang.Enum<org.hpccsystems.ws.client.wrappers.WUFileType> {
  public static final org.hpccsystems.ws.client.wrappers.WUFileType CPP;

  public static final org.hpccsystems.ws.client.wrappers.WUFileType ThorLog;

  public static final org.hpccsystems.ws.client.wrappers.WUFileType ThorSlaveLog;

  public static final org.hpccsystems.ws.client.wrappers.WUFileType EclAgentLog;

  public static final org.hpccsystems.ws.client.wrappers.WUFileType XML;

  public static final org.hpccsystems.ws.client.wrappers.WUFileType RES;

  public static final org.hpccsystems.ws.client.wrappers.WUFileType DDL;

  public static final org.hpccsystems.ws.client.wrappers.WUFileType WUECL;

  public static final org.hpccsystems.ws.client.wrappers.WUFileType ArchiveQuery;

  private static final org.hpccsystems.ws.client.wrappers.WUFileType[] $VALUES;

  public static org.hpccsystems.ws.client.wrappers.WUFileType[] values();
    Code:
       0: getstatic     #1                  // Field $VALUES:[Lorg/hpccsystems/ws/client/wrappers/WUFileType;
       3: invokevirtual #2                  // Method "[Lorg/hpccsystems/ws/client/wrappers/WUFileType;".clone:()Ljava/lang/Object;
       6: checkcast     #3                  // class "[Lorg/hpccsystems/ws/client/wrappers/WUFileType;"
       9: areturn

  public static org.hpccsystems.ws.client.wrappers.WUFileType valueOf(java.lang.String);
    Code:
       0: ldc           #4                  // class org/hpccsystems/ws/client/wrappers/WUFileType
       2: aload_0
       3: invokestatic  #5                  // Method java/lang/Enum.valueOf:(Ljava/lang/Class;Ljava/lang/String;)Ljava/lang/Enum;
       6: checkcast     #4                  // class org/hpccsystems/ws/client/wrappers/WUFileType
       9: areturn

  private org.hpccsystems.ws.client.wrappers.WUFileType();
    Code:
       0: aload_0
       1: aload_1
       2: iload_2
       3: invokespecial #6                  // Method java/lang/Enum."<init>":(Ljava/lang/String;I)V
       6: return

  static {};
    Code:
       0: new           #4                  // class org/hpccsystems/ws/client/wrappers/WUFileType
       3: dup
       4: ldc           #7                  // String CPP
       6: iconst_0
       7: invokespecial #8                  // Method "<init>":(Ljava/lang/String;I)V
      10: putstatic     #9                  // Field CPP:Lorg/hpccsystems/ws/client/wrappers/WUFileType;
      13: new           #4                  // class org/hpccsystems/ws/client/wrappers/WUFileType
      16: dup
      17: ldc           #10                 // String ThorLog
      19: iconst_1
      20: invokespecial #8                  // Method "<init>":(Ljava/lang/String;I)V
      23: putstatic     #11                 // Field ThorLog:Lorg/hpccsystems/ws/client/wrappers/WUFileType;
      26: new           #4                  // class org/hpccsystems/ws/client/wrappers/WUFileType
      29: dup
      30: ldc           #12                 // String ThorSlaveLog
      32: iconst_2
      33: invokespecial #8                  // Method "<init>":(Ljava/lang/String;I)V
      36: putstatic     #13                 // Field ThorSlaveLog:Lorg/hpccsystems/ws/client/wrappers/WUFileType;
      39: new           #4                  // class org/hpccsystems/ws/client/wrappers/WUFileType
      42: dup
      43: ldc           #14                 // String EclAgentLog
      45: iconst_3
      46: invokespecial #8                  // Method "<init>":(Ljava/lang/String;I)V
      49: putstatic     #15                 // Field EclAgentLog:Lorg/hpccsystems/ws/client/wrappers/WUFileType;
      52: new           #4                  // class org/hpccsystems/ws/client/wrappers/WUFileType
      55: dup
      56: ldc           #16                 // String XML
      58: iconst_4
      59: invokespecial #8                  // Method "<init>":(Ljava/lang/String;I)V
      62: putstatic     #17                 // Field XML:Lorg/hpccsystems/ws/client/wrappers/WUFileType;
      65: new           #4                  // class org/hpccsystems/ws/client/wrappers/WUFileType
      68: dup
      69: ldc           #18                 // String RES
      71: iconst_5
      72: invokespecial #8                  // Method "<init>":(Ljava/lang/String;I)V
      75: putstatic     #19                 // Field RES:Lorg/hpccsystems/ws/client/wrappers/WUFileType;
      78: new           #4                  // class org/hpccsystems/ws/client/wrappers/WUFileType
      81: dup
      82: ldc           #20                 // String DDL
      84: bipush        6
      86: invokespecial #8                  // Method "<init>":(Ljava/lang/String;I)V
      89: putstatic     #21                 // Field DDL:Lorg/hpccsystems/ws/client/wrappers/WUFileType;
      92: new           #4                  // class org/hpccsystems/ws/client/wrappers/WUFileType
      95: dup
      96: ldc           #22                 // String WUECL
      98: bipush        7
     100: invokespecial #8                  // Method "<init>":(Ljava/lang/String;I)V
     103: putstatic     #23                 // Field WUECL:Lorg/hpccsystems/ws/client/wrappers/WUFileType;
     106: new           #4                  // class org/hpccsystems/ws/client/wrappers/WUFileType
     109: dup
     110: ldc           #24                 // String ArchiveQuery
     112: bipush        8
     114: invokespecial #8                  // Method "<init>":(Ljava/lang/String;I)V
     117: putstatic     #25                 // Field ArchiveQuery:Lorg/hpccsystems/ws/client/wrappers/WUFileType;
     120: bipush        9
     122: anewarray     #4                  // class org/hpccsystems/ws/client/wrappers/WUFileType
     125: dup
     126: iconst_0
     127: getstatic     #9                  // Field CPP:Lorg/hpccsystems/ws/client/wrappers/WUFileType;
     130: aastore
     131: dup
     132: iconst_1
     133: getstatic     #11                 // Field ThorLog:Lorg/hpccsystems/ws/client/wrappers/WUFileType;
     136: aastore
     137: dup
     138: iconst_2
     139: getstatic     #13                 // Field ThorSlaveLog:Lorg/hpccsystems/ws/client/wrappers/WUFileType;
     142: aastore
     143: dup
     144: iconst_3
     145: getstatic     #15                 // Field EclAgentLog:Lorg/hpccsystems/ws/client/wrappers/WUFileType;
     148: aastore
     149: dup
     150: iconst_4
     151: getstatic     #17                 // Field XML:Lorg/hpccsystems/ws/client/wrappers/WUFileType;
     154: aastore
     155: dup
     156: iconst_5
     157: getstatic     #19                 // Field RES:Lorg/hpccsystems/ws/client/wrappers/WUFileType;
     160: aastore
     161: dup
     162: bipush        6
     164: getstatic     #21                 // Field DDL:Lorg/hpccsystems/ws/client/wrappers/WUFileType;
     167: aastore
     168: dup
     169: bipush        7
     171: getstatic     #23                 // Field WUECL:Lorg/hpccsystems/ws/client/wrappers/WUFileType;
     174: aastore
     175: dup
     176: bipush        8
     178: getstatic     #25                 // Field ArchiveQuery:Lorg/hpccsystems/ws/client/wrappers/WUFileType;
     181: aastore
     182: putstatic     #1                  // Field $VALUES:[Lorg/hpccsystems/ws/client/wrappers/WUFileType;
     185: return
}
