Compiled from "LimitedResultSetWrapper.java"
public class info.archinnov.achilles.internals.types.LimitedResultSetWrapper implements com.datastax.driver.core.ResultSet {
  private final com.datastax.driver.core.ResultSet delegate;

  public info.archinnov.achilles.internals.types.LimitedResultSetWrapper(com.datastax.driver.core.ResultSet);
    Code:
       0: aload_0
       1: invokespecial #1                  // Method java/lang/Object."<init>":()V
       4: aload_0
       5: aload_1
       6: putfield      #2                  // Field delegate:Lcom/datastax/driver/core/ResultSet;
       9: return

  public com.datastax.driver.core.ColumnDefinitions getColumnDefinitions();
    Code:
       0: aload_0
       1: getfield      #2                  // Field delegate:Lcom/datastax/driver/core/ResultSet;
       4: invokeinterface #3,  1            // InterfaceMethod com/datastax/driver/core/ResultSet.getColumnDefinitions:()Lcom/datastax/driver/core/ColumnDefinitions;
       9: areturn

  public boolean isExhausted();
    Code:
       0: aload_0
       1: getfield      #2                  // Field delegate:Lcom/datastax/driver/core/ResultSet;
       4: invokeinterface #4,  1            // InterfaceMethod com/datastax/driver/core/ResultSet.isExhausted:()Z
       9: ireturn

  public com.datastax.driver.core.Row one();
    Code:
       0: new           #5                  // class java/lang/UnsupportedOperationException
       3: dup
       4: ldc           #6                  // String You are not allowed to consume the ResultSet at this stage
       6: invokespecial #7                  // Method java/lang/UnsupportedOperationException."<init>":(Ljava/lang/String;)V
       9: athrow

  public java.util.List<com.datastax.driver.core.Row> all();
    Code:
       0: new           #5                  // class java/lang/UnsupportedOperationException
       3: dup
       4: ldc           #6                  // String You are not allowed to consume the ResultSet at this stage
       6: invokespecial #7                  // Method java/lang/UnsupportedOperationException."<init>":(Ljava/lang/String;)V
       9: athrow

  public java.util.Iterator<com.datastax.driver.core.Row> iterator();
    Code:
       0: new           #5                  // class java/lang/UnsupportedOperationException
       3: dup
       4: ldc           #6                  // String You are not allowed to consume the ResultSet at this stage
       6: invokespecial #7                  // Method java/lang/UnsupportedOperationException."<init>":(Ljava/lang/String;)V
       9: athrow

  public int getAvailableWithoutFetching();
    Code:
       0: aload_0
       1: getfield      #2                  // Field delegate:Lcom/datastax/driver/core/ResultSet;
       4: invokeinterface #8,  1            // InterfaceMethod com/datastax/driver/core/ResultSet.getAvailableWithoutFetching:()I
       9: ireturn

  public boolean isFullyFetched();
    Code:
       0: aload_0
       1: getfield      #2                  // Field delegate:Lcom/datastax/driver/core/ResultSet;
       4: invokeinterface #9,  1            // InterfaceMethod com/datastax/driver/core/ResultSet.isFullyFetched:()Z
       9: ireturn

  public com.google.common.util.concurrent.ListenableFuture<com.datastax.driver.core.ResultSet> fetchMoreResults();
    Code:
       0: new           #5                  // class java/lang/UnsupportedOperationException
       3: dup
       4: ldc           #6                  // String You are not allowed to consume the ResultSet at this stage
       6: invokespecial #7                  // Method java/lang/UnsupportedOperationException."<init>":(Ljava/lang/String;)V
       9: athrow

  public com.datastax.driver.core.ExecutionInfo getExecutionInfo();
    Code:
       0: aload_0
       1: getfield      #2                  // Field delegate:Lcom/datastax/driver/core/ResultSet;
       4: invokeinterface #10,  1           // InterfaceMethod com/datastax/driver/core/ResultSet.getExecutionInfo:()Lcom/datastax/driver/core/ExecutionInfo;
       9: areturn

  public java.util.List<com.datastax.driver.core.ExecutionInfo> getAllExecutionInfo();
    Code:
       0: aload_0
       1: getfield      #2                  // Field delegate:Lcom/datastax/driver/core/ResultSet;
       4: invokeinterface #11,  1           // InterfaceMethod com/datastax/driver/core/ResultSet.getAllExecutionInfo:()Ljava/util/List;
       9: areturn

  public boolean wasApplied();
    Code:
       0: aload_0
       1: getfield      #2                  // Field delegate:Lcom/datastax/driver/core/ResultSet;
       4: invokeinterface #12,  1           // InterfaceMethod com/datastax/driver/core/ResultSet.wasApplied:()Z
       9: ireturn

  public java.lang.Object one();
    Code:
       0: aload_0
       1: invokevirtual #13                 // Method one:()Lcom/datastax/driver/core/Row;
       4: areturn
}
