Compiled from "OverridingOptional.java"
public class info.archinnov.achilles.internals.types.OverridingOptional<T> {
  private final java.util.List<java.util.Optional<T>> options;

  private T defaultValue;

  private info.archinnov.achilles.internals.types.OverridingOptional(java.util.Optional<T>);
    Code:
       0: aload_0
       1: invokespecial #3                  // Method java/lang/Object."<init>":()V
       4: aload_0
       5: new           #4                  // class java/util/ArrayList
       8: dup
       9: invokespecial #5                  // Method java/util/ArrayList."<init>":()V
      12: putfield      #2                  // Field options:Ljava/util/List;
      15: aload_0
      16: getfield      #2                  // Field options:Ljava/util/List;
      19: aload_1
      20: invokeinterface #6,  2            // InterfaceMethod java/util/List.add:(Ljava/lang/Object;)Z
      25: pop
      26: return

  public static <T> info.archinnov.achilles.internals.types.OverridingOptional<T> from(java.util.Optional<T>);
    Code:
       0: new           #7                  // class info/archinnov/achilles/internals/types/OverridingOptional
       3: dup
       4: aload_0
       5: invokespecial #8                  // Method "<init>":(Ljava/util/Optional;)V
       8: areturn

  public static <T> info.archinnov.achilles.internals.types.OverridingOptional<T> from(T);
    Code:
       0: new           #7                  // class info/archinnov/achilles/internals/types/OverridingOptional
       3: dup
       4: aload_0
       5: invokestatic  #9                  // Method java/util/Optional.ofNullable:(Ljava/lang/Object;)Ljava/util/Optional;
       8: invokespecial #8                  // Method "<init>":(Ljava/util/Optional;)V
      11: areturn

  public info.archinnov.achilles.internals.types.OverridingOptional<T> andThen(java.util.Optional<T>);
    Code:
       0: aload_0
       1: getfield      #2                  // Field options:Ljava/util/List;
       4: aload_1
       5: invokeinterface #6,  2            // InterfaceMethod java/util/List.add:(Ljava/lang/Object;)Z
      10: pop
      11: aload_0
      12: areturn

  public info.archinnov.achilles.internals.types.OverridingOptional<T> andThen(T);
    Code:
       0: aload_0
       1: getfield      #2                  // Field options:Ljava/util/List;
       4: aload_1
       5: invokestatic  #9                  // Method java/util/Optional.ofNullable:(Ljava/lang/Object;)Ljava/util/Optional;
       8: invokeinterface #6,  2            // InterfaceMethod java/util/List.add:(Ljava/lang/Object;)Z
      13: pop
      14: aload_0
      15: areturn

  public java.util.Optional<T> getOptional();
    Code:
       0: aload_0
       1: getfield      #2                  // Field options:Ljava/util/List;
       4: invokeinterface #10,  1           // InterfaceMethod java/util/List.stream:()Ljava/util/stream/Stream;
       9: invokedynamic #11,  0             // InvokeDynamic #0:test:()Ljava/util/function/Predicate;
      14: invokeinterface #12,  2           // InterfaceMethod java/util/stream/Stream.filter:(Ljava/util/function/Predicate;)Ljava/util/stream/Stream;
      19: invokedynamic #13,  0             // InvokeDynamic #1:apply:()Ljava/util/function/Function;
      24: invokeinterface #14,  2           // InterfaceMethod java/util/stream/Stream.map:(Ljava/util/function/Function;)Ljava/util/stream/Stream;
      29: invokeinterface #15,  1           // InterfaceMethod java/util/stream/Stream.findFirst:()Ljava/util/Optional;
      34: areturn

  public info.archinnov.achilles.internals.types.OverridingOptional<T>.OverridingOptionalFinal defaultValue(T);
    Code:
       0: aload_0
       1: aload_1
       2: putfield      #1                  // Field defaultValue:Ljava/lang/Object;
       5: new           #16                 // class info/archinnov/achilles/internals/types/OverridingOptional$OverridingOptionalFinal
       8: dup
       9: aload_0
      10: aconst_null
      11: invokespecial #17                 // Method info/archinnov/achilles/internals/types/OverridingOptional$OverridingOptionalFinal."<init>":(Linfo/archinnov/achilles/internals/types/OverridingOptional;Linfo/archinnov/achilles/internals/types/OverridingOptional$1;)V
      14: areturn

  static java.util.List access$100(info.archinnov.achilles.internals.types.OverridingOptional);
    Code:
       0: aload_0
       1: getfield      #2                  // Field options:Ljava/util/List;
       4: areturn

  static java.lang.Object access$200(info.archinnov.achilles.internals.types.OverridingOptional);
    Code:
       0: aload_0
       1: getfield      #1                  // Field defaultValue:Ljava/lang/Object;
       4: areturn
}
