Compiled from "OverridingOptional.java"
public class info.archinnov.achilles.internals.types.OverridingOptional$OverridingOptionalFinal {
  final info.archinnov.achilles.internals.types.OverridingOptional this$0;

  private info.archinnov.achilles.internals.types.OverridingOptional$OverridingOptionalFinal(info.archinnov.achilles.internals.types.OverridingOptional);
    Code:
       0: aload_0
       1: aload_1
       2: putfield      #2                  // Field this$0:Linfo/archinnov/achilles/internals/types/OverridingOptional;
       5: aload_0
       6: invokespecial #3                  // Method java/lang/Object."<init>":()V
       9: return

  public T get();
    Code:
       0: aload_0
       1: getfield      #2                  // Field this$0:Linfo/archinnov/achilles/internals/types/OverridingOptional;
       4: invokestatic  #4                  // Method info/archinnov/achilles/internals/types/OverridingOptional.access$100:(Linfo/archinnov/achilles/internals/types/OverridingOptional;)Ljava/util/List;
       7: invokeinterface #5,  1            // InterfaceMethod java/util/List.stream:()Ljava/util/stream/Stream;
      12: invokedynamic #6,  0              // InvokeDynamic #0:test:()Ljava/util/function/Predicate;
      17: invokeinterface #7,  2            // InterfaceMethod java/util/stream/Stream.filter:(Ljava/util/function/Predicate;)Ljava/util/stream/Stream;
      22: invokedynamic #8,  0              // InvokeDynamic #1:apply:()Ljava/util/function/Function;
      27: invokeinterface #9,  2            // InterfaceMethod java/util/stream/Stream.map:(Ljava/util/function/Function;)Ljava/util/stream/Stream;
      32: invokeinterface #10,  1           // InterfaceMethod java/util/stream/Stream.findFirst:()Ljava/util/Optional;
      37: astore_1
      38: aload_1
      39: aload_0
      40: getfield      #2                  // Field this$0:Linfo/archinnov/achilles/internals/types/OverridingOptional;
      43: invokestatic  #11                 // Method info/archinnov/achilles/internals/types/OverridingOptional.access$200:(Linfo/archinnov/achilles/internals/types/OverridingOptional;)Ljava/lang/Object;
      46: invokevirtual #12                 // Method java/util/Optional.orElse:(Ljava/lang/Object;)Ljava/lang/Object;
      49: areturn

  info.archinnov.achilles.internals.types.OverridingOptional$OverridingOptionalFinal(info.archinnov.achilles.internals.types.OverridingOptional, info.archinnov.achilles.internals.types.OverridingOptional$1);
    Code:
       0: aload_0
       1: aload_1
       2: invokespecial #1                  // Method "<init>":(Linfo/archinnov/achilles/internals/types/OverridingOptional;)V
       5: return
}
