Compiled from "Compression.java"
public final class org.apache.hadoop.io.file.tfile.Compression {
  static final org.slf4j.Logger LOG;

  private org.apache.hadoop.io.file.tfile.Compression();
    Code:
       0: aload_0
       1: invokespecial #1                  // Method java/lang/Object."<init>":()V
       4: return

  public static org.apache.hadoop.io.file.tfile.Compression$Algorithm getCompressionAlgorithmByName(java.lang.String);
    Code:
       0: ldc           #2                  // class org/apache/hadoop/io/file/tfile/Compression$Algorithm
       2: invokevirtual #3                  // Method java/lang/Class.getEnumConstants:()[Ljava/lang/Object;
       5: checkcast     #4                  // class "[Lorg/apache/hadoop/io/file/tfile/Compression$Algorithm;"
       8: astore_1
       9: aload_1
      10: astore_2
      11: aload_2
      12: arraylength
      13: istore_3
      14: iconst_0
      15: istore        4
      17: iload         4
      19: iload_3
      20: if_icmpge     50
      23: aload_2
      24: iload         4
      26: aaload
      27: astore        5
      29: aload         5
      31: invokevirtual #5                  // Method org/apache/hadoop/io/file/tfile/Compression$Algorithm.getName:()Ljava/lang/String;
      34: aload_0
      35: invokevirtual #6                  // Method java/lang/String.equals:(Ljava/lang/Object;)Z
      38: ifeq          44
      41: aload         5
      43: areturn
      44: iinc          4, 1
      47: goto          17
      50: new           #7                  // class java/lang/IllegalArgumentException
      53: dup
      54: new           #8                  // class java/lang/StringBuilder
      57: dup
      58: invokespecial #9                  // Method java/lang/StringBuilder."<init>":()V
      61: ldc           #10                 // String Unsupported compression algorithm name:
      63: invokevirtual #11                 // Method java/lang/StringBuilder.append:(Ljava/lang/String;)Ljava/lang/StringBuilder;
      66: aload_0
      67: invokevirtual #11                 // Method java/lang/StringBuilder.append:(Ljava/lang/String;)Ljava/lang/StringBuilder;
      70: invokevirtual #12                 // Method java/lang/StringBuilder.toString:()Ljava/lang/String;
      73: invokespecial #13                 // Method java/lang/IllegalArgumentException."<init>":(Ljava/lang/String;)V
      76: athrow

  static java.lang.String[] getSupportedAlgorithms();
    Code:
       0: ldc           #2                  // class org/apache/hadoop/io/file/tfile/Compression$Algorithm
       2: invokevirtual #3                  // Method java/lang/Class.getEnumConstants:()[Ljava/lang/Object;
       5: checkcast     #4                  // class "[Lorg/apache/hadoop/io/file/tfile/Compression$Algorithm;"
       8: astore_0
       9: new           #14                 // class java/util/ArrayList
      12: dup
      13: invokespecial #15                 // Method java/util/ArrayList."<init>":()V
      16: astore_1
      17: aload_0
      18: astore_2
      19: aload_2
      20: arraylength
      21: istore_3
      22: iconst_0
      23: istore        4
      25: iload         4
      27: iload_3
      28: if_icmpge     61
      31: aload_2
      32: iload         4
      34: aaload
      35: astore        5
      37: aload         5
      39: invokevirtual #16                 // Method org/apache/hadoop/io/file/tfile/Compression$Algorithm.isSupported:()Z
      42: ifeq          55
      45: aload_1
      46: aload         5
      48: invokevirtual #5                  // Method org/apache/hadoop/io/file/tfile/Compression$Algorithm.getName:()Ljava/lang/String;
      51: invokevirtual #17                 // Method java/util/ArrayList.add:(Ljava/lang/Object;)Z
      54: pop
      55: iinc          4, 1
      58: goto          25
      61: aload_1
      62: aload_1
      63: invokevirtual #18                 // Method java/util/ArrayList.size:()I
      66: anewarray     #19                 // class java/lang/String
      69: invokevirtual #20                 // Method java/util/ArrayList.toArray:([Ljava/lang/Object;)[Ljava/lang/Object;
      72: checkcast     #21                 // class "[Ljava/lang/String;"
      75: areturn

  static {};
    Code:
       0: ldc           #22                 // class org/apache/hadoop/io/file/tfile/Compression
       2: invokestatic  #23                 // Method org/slf4j/LoggerFactory.getLogger:(Ljava/lang/Class;)Lorg/slf4j/Logger;
       5: putstatic     #24                 // Field LOG:Lorg/slf4j/Logger;
       8: return
}
