Compiled from "FunctionsImpl.java"
class org.apache.pulsar.client.admin.internal.FunctionsImpl$8 implements org.asynchttpclient.AsyncHandler<org.asynchttpclient.HttpResponseStatus> {
  private org.asynchttpclient.HttpResponseStatus status;

  final java.nio.channels.FileChannel val$os;

  final org.apache.pulsar.client.admin.internal.FunctionsImpl this$0;

  org.apache.pulsar.client.admin.internal.FunctionsImpl$8(org.apache.pulsar.client.admin.internal.FunctionsImpl, java.nio.channels.FileChannel);
    Code:
       0: aload_0
       1: aload_1
       2: putfield      #1                  // Field this$0:Lorg/apache/pulsar/client/admin/internal/FunctionsImpl;
       5: aload_0
       6: aload_2
       7: putfield      #2                  // Field val$os:Ljava/nio/channels/FileChannel;
      10: aload_0
      11: invokespecial #3                  // Method java/lang/Object."<init>":()V
      14: return

  public org.asynchttpclient.AsyncHandler$State onStatusReceived(org.asynchttpclient.HttpResponseStatus) throws java.lang.Exception;
    Code:
       0: aload_0
       1: aload_1
       2: putfield      #4                  // Field status:Lorg/asynchttpclient/HttpResponseStatus;
       5: aload_0
       6: getfield      #4                  // Field status:Lorg/asynchttpclient/HttpResponseStatus;
       9: invokevirtual #5                  // Method org/asynchttpclient/HttpResponseStatus.getStatusCode:()I
      12: getstatic     #6                  // Field javax/ws/rs/core/Response$Status.OK:Ljavax/ws/rs/core/Response$Status;
      15: invokevirtual #7                  // Method javax/ws/rs/core/Response$Status.getStatusCode:()I
      18: if_icmpeq     25
      21: getstatic     #8                  // Field org/asynchttpclient/AsyncHandler$State.ABORT:Lorg/asynchttpclient/AsyncHandler$State;
      24: areturn
      25: getstatic     #9                  // Field org/asynchttpclient/AsyncHandler$State.CONTINUE:Lorg/asynchttpclient/AsyncHandler$State;
      28: areturn

  public org.asynchttpclient.AsyncHandler$State onHeadersReceived(io.netty.handler.codec.http.HttpHeaders) throws java.lang.Exception;
    Code:
       0: getstatic     #9                  // Field org/asynchttpclient/AsyncHandler$State.CONTINUE:Lorg/asynchttpclient/AsyncHandler$State;
       3: areturn

  public org.asynchttpclient.AsyncHandler$State onBodyPartReceived(org.asynchttpclient.HttpResponseBodyPart) throws java.lang.Exception;
    Code:
       0: aload_0
       1: getfield      #2                  // Field val$os:Ljava/nio/channels/FileChannel;
       4: aload_1
       5: invokevirtual #10                 // Method org/asynchttpclient/HttpResponseBodyPart.getBodyByteBuffer:()Ljava/nio/ByteBuffer;
       8: invokevirtual #11                 // Method java/nio/channels/FileChannel.write:(Ljava/nio/ByteBuffer;)I
      11: pop
      12: getstatic     #9                  // Field org/asynchttpclient/AsyncHandler$State.CONTINUE:Lorg/asynchttpclient/AsyncHandler$State;
      15: areturn

  public org.asynchttpclient.HttpResponseStatus onCompleted() throws java.lang.Exception;
    Code:
       0: aload_0
       1: getfield      #4                  // Field status:Lorg/asynchttpclient/HttpResponseStatus;
       4: areturn

  public void onThrowable(java.lang.Throwable);
    Code:
       0: return

  public java.lang.Object onCompleted() throws java.lang.Exception;
    Code:
       0: aload_0
       1: invokevirtual #12                 // Method onCompleted:()Lorg/asynchttpclient/HttpResponseStatus;
       4: areturn
}
