Compiled from "MissingImportHandlerUI.java"
public class org.protege.editor.owl.ui.ontology.imports.missing.MissingImportHandlerUI implements org.protege.editor.owl.model.MissingImportHandler {
  private final org.slf4j.Logger logger;

  private final org.protege.editor.owl.OWLEditorKit owlEditorKit;

  public org.protege.editor.owl.ui.ontology.imports.missing.MissingImportHandlerUI(org.protege.editor.owl.OWLEditorKit);
    Code:
       0: aload_0
       1: invokespecial #1                  // Method java/lang/Object."<init>":()V
       4: aload_0
       5: ldc           #2                  // class org/protege/editor/owl/ui/ontology/imports/missing/MissingImportHandlerUI
       7: invokestatic  #3                  // Method org/slf4j/LoggerFactory.getLogger:(Ljava/lang/Class;)Lorg/slf4j/Logger;
      10: putfield      #4                  // Field logger:Lorg/slf4j/Logger;
      13: aload_0
      14: aload_1
      15: putfield      #5                  // Field owlEditorKit:Lorg/protege/editor/owl/OWLEditorKit;
      18: return

  public org.semanticweb.owlapi.model.IRI getDocumentIRI(org.semanticweb.owlapi.model.IRI);
    Code:
       0: new           #6                  // class java/util/concurrent/FutureTask
       3: dup
       4: aload_0
       5: aload_1
       6: invokedynamic #7,  0              // InvokeDynamic #0:call:(Lorg/protege/editor/owl/ui/ontology/imports/missing/MissingImportHandlerUI;Lorg/semanticweb/owlapi/model/IRI;)Ljava/util/concurrent/Callable;
      11: invokespecial #8                  // Method java/util/concurrent/FutureTask."<init>":(Ljava/util/concurrent/Callable;)V
      14: astore_2
      15: aload_2
      16: invokestatic  #9                  // Method javax/swing/SwingUtilities.invokeLater:(Ljava/lang/Runnable;)V
      19: aload_2
      20: invokevirtual #10                 // Method java/util/concurrent/FutureTask.get:()Ljava/lang/Object;
      23: checkcast     #11                 // class org/semanticweb/owlapi/model/IRI
      26: areturn
      27: astore_3
      28: aload_0
      29: getfield      #4                  // Field logger:Lorg/slf4j/Logger;
      32: ldc           #13                 // String Resolve import task interrupted
      34: invokeinterface #14,  2           // InterfaceMethod org/slf4j/Logger.debug:(Ljava/lang/String;)V
      39: aconst_null
      40: areturn
      41: astore_3
      42: aload_0
      43: getfield      #4                  // Field logger:Lorg/slf4j/Logger;
      46: ldc           #16                 // String An exception was thrown whilst the user was resolving a missing import: {}
      48: aload_3
      49: invokevirtual #17                 // Method java/util/concurrent/ExecutionException.getCause:()Ljava/lang/Throwable;
      52: invokevirtual #18                 // Method java/lang/Throwable.getMessage:()Ljava/lang/String;
      55: invokeinterface #19,  3           // InterfaceMethod org/slf4j/Logger.error:(Ljava/lang/String;Ljava/lang/Object;)V
      60: aconst_null
      61: areturn
    Exception table:
       from    to  target type
          19    26    27   Class java/lang/InterruptedException
          19    26    41   Class java/util/concurrent/ExecutionException

  private void updateActiveCatalog(org.semanticweb.owlapi.model.IRI, java.io.File);
    Code:
       0: aload_0
       1: getfield      #5                  // Field owlEditorKit:Lorg/protege/editor/owl/OWLEditorKit;
       4: invokevirtual #20                 // Method org/protege/editor/owl/OWLEditorKit.getOWLModelManager:()Lorg/protege/editor/owl/model/OWLModelManager;
       7: invokeinterface #21,  1           // InterfaceMethod org/protege/editor/owl/model/OWLModelManager.getOntologyCatalogManager:()Lorg/protege/editor/owl/model/library/OntologyCatalogManager;
      12: astore_3
      13: aload_3
      14: invokevirtual #22                 // Method org/protege/editor/owl/model/library/OntologyCatalogManager.getCurrentCatalog:()Ljava/util/Optional;
      17: aload_0
      18: aload_2
      19: aload_1
      20: invokedynamic #23,  0             // InvokeDynamic #1:accept:(Lorg/protege/editor/owl/ui/ontology/imports/missing/MissingImportHandlerUI;Ljava/io/File;Lorg/semanticweb/owlapi/model/IRI;)Ljava/util/function/Consumer;
      25: invokevirtual #24                 // Method java/util/Optional.ifPresent:(Ljava/util/function/Consumer;)V
      28: return

  private void lambda$updateActiveCatalog$1(java.io.File, org.semanticweb.owlapi.model.IRI, org.protege.xmlcatalog.XMLCatalog);
    Code:
       0: aload_1
       1: invokevirtual #25                 // Method java/io/File.toURI:()Ljava/net/URI;
       4: aload_3
       5: invokestatic  #26                 // Method org/protege/xmlcatalog/CatalogUtilities.relativize:(Ljava/net/URI;Lorg/protege/xmlcatalog/XmlBaseContext;)Ljava/net/URI;
       8: astore        4
      10: aload_3
      11: iconst_0
      12: new           #27                 // class org/protege/xmlcatalog/entry/UriEntry
      15: dup
      16: ldc           #28                 // String User Entered Import Resolution
      18: aload_3
      19: aload_2
      20: invokevirtual #29                 // Method org/semanticweb/owlapi/model/IRI.toString:()Ljava/lang/String;
      23: aload         4
      25: aconst_null
      26: invokespecial #30                 // Method org/protege/xmlcatalog/entry/UriEntry."<init>":(Ljava/lang/String;Lorg/protege/xmlcatalog/XmlBaseContext;Ljava/lang/String;Ljava/net/URI;Ljava/net/URI;)V
      29: invokevirtual #31                 // Method org/protege/xmlcatalog/XMLCatalog.addEntry:(ILorg/protege/xmlcatalog/entry/Entry;)V
      32: new           #32                 // class java/io/File
      35: dup
      36: aload_3
      37: invokevirtual #33                 // Method org/protege/xmlcatalog/XMLCatalog.getXmlBaseContext:()Lorg/protege/xmlcatalog/XmlBaseContext;
      40: invokeinterface #34,  1           // InterfaceMethod org/protege/xmlcatalog/XmlBaseContext.getXmlBase:()Ljava/net/URI;
      45: invokespecial #35                 // Method java/io/File."<init>":(Ljava/net/URI;)V
      48: astore        5
      50: aload_3
      51: aload         5
      53: invokestatic  #36                 // Method org/protege/xmlcatalog/CatalogUtilities.save:(Lorg/protege/xmlcatalog/XMLCatalog;Ljava/io/File;)V
      56: goto          74
      59: astore        6
      61: aload_0
      62: getfield      #4                  // Field logger:Lorg/slf4j/Logger;
      65: ldc           #38                 // String Could not save user supplied import redirection to catalog.
      67: aload         6
      69: invokeinterface #39,  3           // InterfaceMethod org/slf4j/Logger.error:(Ljava/lang/String;Ljava/lang/Throwable;)V
      74: return
    Exception table:
       from    to  target type
          50    56    59   Class java/io/IOException

  private org.semanticweb.owlapi.model.IRI lambda$getDocumentIRI$0(org.semanticweb.owlapi.model.IRI) throws java.lang.Exception;
    Code:
       0: aconst_null
       1: new           #40                 // class java/lang/StringBuilder
       4: dup
       5: invokespecial #41                 // Method java/lang/StringBuilder."<init>":()V
       8: ldc           #42                 // String <html><body>The system couldn\'t locate the ontology<br><br><b>
      10: invokevirtual #43                 // Method java/lang/StringBuilder.append:(Ljava/lang/String;)Ljava/lang/StringBuilder;
      13: aload_1
      14: invokevirtual #29                 // Method org/semanticweb/owlapi/model/IRI.toString:()Ljava/lang/String;
      17: invokevirtual #43                 // Method java/lang/StringBuilder.append:(Ljava/lang/String;)Ljava/lang/StringBuilder;
      20: ldc           #44                 // String </b><br><br>Would you like to attempt to resolve the missing import?</body></html>
      22: invokevirtual #43                 // Method java/lang/StringBuilder.append:(Ljava/lang/String;)Ljava/lang/StringBuilder;
      25: invokevirtual #45                 // Method java/lang/StringBuilder.toString:()Ljava/lang/String;
      28: ldc           #46                 // String Resolve missing import?
      30: iconst_0
      31: iconst_2
      32: invokestatic  #48                 // Method javax/swing/JOptionPane.showConfirmDialog:(Ljava/awt/Component;Ljava/lang/Object;Ljava/lang/String;II)I
      35: istore_2
      36: iload_2
      37: ifeq          42
      40: aconst_null
      41: areturn
      42: new           #49                 // class org/protege/editor/owl/ui/UIHelper
      45: dup
      46: aload_0
      47: getfield      #5                  // Field owlEditorKit:Lorg/protege/editor/owl/OWLEditorKit;
      50: invokespecial #50                 // Method org/protege/editor/owl/ui/UIHelper."<init>":(Lorg/protege/editor/owl/OWLEditorKit;)V
      53: astore_3
      54: aload_3
      55: ldc           #51                 // String Please select an ontology file
      57: invokevirtual #52                 // Method org/protege/editor/owl/ui/UIHelper.chooseOWLFile:(Ljava/lang/String;)Ljava/io/File;
      60: astore        4
      62: aload         4
      64: ifnonnull     69
      67: aload_1
      68: areturn
      69: aload_0
      70: aload_1
      71: aload         4
      73: invokespecial #53                 // Method updateActiveCatalog:(Lorg/semanticweb/owlapi/model/IRI;Ljava/io/File;)V
      76: aload         4
      78: invokestatic  #54                 // Method org/semanticweb/owlapi/model/IRI.create:(Ljava/io/File;)Lorg/semanticweb/owlapi/model/IRI;
      81: areturn
}
