Compiled from "BalancingDispatcher.scala"
public class akka.dispatch.BalancingDispatcher extends akka.dispatch.Dispatcher {
  private final boolean attemptTeamWork;

  private final java.util.concurrent.ConcurrentSkipListSet<akka.actor.ActorCell> team;

  private final akka.dispatch.MessageQueue messageQueue;

  public java.util.concurrent.ConcurrentSkipListSet<akka.actor.ActorCell> team();
    Code:
       0: aload_0
       1: getfield      #18                 // Field team:Ljava/util/concurrent/ConcurrentSkipListSet;
       4: areturn

  public akka.dispatch.MessageQueue messageQueue();
    Code:
       0: aload_0
       1: getfield      #23                 // Field messageQueue:Lakka/dispatch/MessageQueue;
       4: areturn

  public akka.dispatch.Mailbox createMailbox(akka.actor.Cell, akka.dispatch.MailboxType);
    Code:
       0: new           #27                 // class akka/dispatch/BalancingDispatcher$SharingMailbox
       3: dup
       4: aload_0
       5: aload_1
       6: invokeinterface #33,  1           // InterfaceMethod akka/actor/Cell.systemImpl:()Lakka/actor/ActorSystemImpl;
      11: aload_0
      12: invokevirtual #35                 // Method messageQueue:()Lakka/dispatch/MessageQueue;
      15: invokespecial #39                 // Method akka/dispatch/BalancingDispatcher$SharingMailbox."<init>":(Lakka/dispatch/BalancingDispatcher;Lakka/actor/ActorSystemImpl;Lakka/dispatch/MessageQueue;)V
      18: areturn

  public void register(akka.actor.ActorCell);
    Code:
       0: aload_0
       1: aload_1
       2: invokespecial #49                 // Method akka/dispatch/MessageDispatcher.register:(Lakka/actor/ActorCell;)V
       5: aload_0
       6: invokevirtual #51                 // Method team:()Ljava/util/concurrent/ConcurrentSkipListSet;
       9: aload_1
      10: invokevirtual #57                 // Method java/util/concurrent/ConcurrentSkipListSet.add:(Ljava/lang/Object;)Z
      13: pop
      14: return

  public void unregister(akka.actor.ActorCell);
    Code:
       0: aload_0
       1: invokevirtual #51                 // Method team:()Ljava/util/concurrent/ConcurrentSkipListSet;
       4: aload_1
       5: invokevirtual #62                 // Method java/util/concurrent/ConcurrentSkipListSet.remove:(Ljava/lang/Object;)Z
       8: pop
       9: aload_0
      10: aload_1
      11: invokespecial #64                 // Method akka/dispatch/MessageDispatcher.unregister:(Lakka/actor/ActorCell;)V
      14: aload_0
      15: invokevirtual #68                 // Method teamWork:()V
      18: return

  public void dispatch(akka.actor.ActorCell, akka.dispatch.Envelope);
    Code:
       0: aload_0
       1: invokevirtual #35                 // Method messageQueue:()Lakka/dispatch/MessageQueue;
       4: aload_1
       5: invokevirtual #76                 // Method akka/actor/ActorCell.self:()Lakka/actor/InternalActorRef;
       8: aload_2
       9: invokeinterface #82,  3           // InterfaceMethod akka/dispatch/MessageQueue.enqueue:(Lakka/actor/ActorRef;Lakka/dispatch/Envelope;)V
      14: aload_0
      15: aload_1
      16: invokevirtual #86                 // Method akka/actor/ActorCell.mailbox:()Lakka/dispatch/Mailbox;
      19: iconst_0
      20: iconst_0
      21: invokevirtual #90                 // Method registerForExecution:(Lakka/dispatch/Mailbox;ZZ)Z
      24: ifne          31
      27: aload_0
      28: invokevirtual #68                 // Method teamWork:()V
      31: return

  public void teamWork();
    Code:
       0: aload_0
       1: getfield      #95                 // Field attemptTeamWork:Z
       4: ifeq          15
       7: aload_0
       8: aload_0
       9: invokespecial #99                 // Method scheduleOne$default$1$1:()Ljava/util/Iterator;
      12: invokespecial #103                // Method scheduleOne$1:(Ljava/util/Iterator;)V
      15: return

  private final void scheduleOne$1(java.util.Iterator);
    Code:
       0: aload_0
       1: invokevirtual #35                 // Method messageQueue:()Lakka/dispatch/MessageQueue;
       4: invokeinterface #107,  1          // InterfaceMethod akka/dispatch/MessageQueue.hasMessages:()Z
       9: ifeq          101
      12: aload_1
      13: invokeinterface #112,  1          // InterfaceMethod java/util/Iterator.hasNext:()Z
      18: ifeq          101
      21: aload_0
      22: invokevirtual #116                // Method executorService:()Lakka/dispatch/ExecutorServiceDelegate;
      25: invokeinterface #122,  1          // InterfaceMethod akka/dispatch/ExecutorServiceDelegate.executor:()Ljava/util/concurrent/ExecutorService;
      30: astore_3
      31: aload_3
      32: instanceof    #124                // class akka/dispatch/LoadMetrics
      35: ifeq          65
      38: aload_3
      39: astore        4
      41: aload         4
      43: checkcast     #124                // class akka/dispatch/LoadMetrics
      46: invokeinterface #127,  1          // InterfaceMethod akka/dispatch/LoadMetrics.atFullThrottle:()Z
      51: iconst_0
      52: if_icmpne     59
      55: iconst_1
      56: goto          60
      59: iconst_0
      60: istore        5
      62: goto          68
      65: iconst_1
      66: istore        5
      68: iload         5
      70: ifeq          101
      73: aload_0
      74: aload_1
      75: invokeinterface #131,  1          // InterfaceMethod java/util/Iterator.next:()Ljava/lang/Object;
      80: checkcast     #133                // class akka/actor/dungeon/Dispatch
      83: invokeinterface #134,  1          // InterfaceMethod akka/actor/dungeon/Dispatch.mailbox:()Lakka/dispatch/Mailbox;
      88: iconst_0
      89: iconst_0
      90: invokevirtual #90                 // Method registerForExecution:(Lakka/dispatch/Mailbox;ZZ)Z
      93: ifne          101
      96: aload_1
      97: astore_1
      98: goto          0
     101: getstatic     #140                // Field scala/runtime/BoxedUnit.UNIT:Lscala/runtime/BoxedUnit;
     104: pop
     105: return

  private final java.util.Iterator scheduleOne$default$1$1();
    Code:
       0: aload_0
       1: invokevirtual #51                 // Method team:()Ljava/util/concurrent/ConcurrentSkipListSet;
       4: invokevirtual #147                // Method java/util/concurrent/ConcurrentSkipListSet.iterator:()Ljava/util/Iterator;
       7: areturn

  public akka.dispatch.BalancingDispatcher(akka.dispatch.MessageDispatcherConfigurator, java.lang.String, int, scala.concurrent.duration.Duration, akka.dispatch.MailboxType, akka.dispatch.ExecutorServiceFactoryProvider, scala.concurrent.duration.FiniteDuration, boolean);
    Code:
       0: aload_0
       1: iload         8
       3: putfield      #95                 // Field attemptTeamWork:Z
       6: aload_0
       7: aload_1
       8: aload_2
       9: iload_3
      10: aload         4
      12: aload         6
      14: aload         7
      16: invokespecial #151                // Method akka/dispatch/Dispatcher."<init>":(Lakka/dispatch/MessageDispatcherConfigurator;Ljava/lang/String;ILscala/concurrent/duration/Duration;Lakka/dispatch/ExecutorServiceFactoryProvider;Lscala/concurrent/duration/FiniteDuration;)V
      19: aload_0
      20: new           #53                 // class java/util/concurrent/ConcurrentSkipListSet
      23: dup
      24: getstatic     #157                // Field akka/util/Helpers$.MODULE$:Lakka/util/Helpers$;
      27: new           #159                // class akka/dispatch/BalancingDispatcher$$anon$1
      30: dup
      31: aload_0
      32: invokespecial #162                // Method akka/dispatch/BalancingDispatcher$$anon$1."<init>":(Lakka/dispatch/BalancingDispatcher;)V
      35: invokevirtual #166                // Method akka/util/Helpers$.identityHashComparator:(Ljava/util/Comparator;)Ljava/util/Comparator;
      38: invokespecial #169                // Method java/util/concurrent/ConcurrentSkipListSet."<init>":(Ljava/util/Comparator;)V
      41: putfield      #18                 // Field team:Ljava/util/concurrent/ConcurrentSkipListSet;
      44: aload_0
      45: aload         5
      47: getstatic     #174                // Field scala/None$.MODULE$:Lscala/None$;
      50: getstatic     #174                // Field scala/None$.MODULE$:Lscala/None$;
      53: invokeinterface #180,  3          // InterfaceMethod akka/dispatch/MailboxType.create:(Lscala/Option;Lscala/Option;)Lakka/dispatch/MessageQueue;
      58: putfield      #23                 // Field messageQueue:Lakka/dispatch/MessageQueue;
      61: return
}
