Compiled from "Dispatcher.scala"
public final class akka.dispatch.Dispatcher$$anon$1 extends akka.dispatch.Mailbox implements akka.dispatch.DefaultSystemMessageQueue {
  public final void systemEnqueue(akka.actor.ActorRef, akka.dispatch.sysmsg.SystemMessage);
    Code:
       0: aload_0
       1: aload_1
       2: aload_2
       3: invokestatic  #19                 // Method akka/dispatch/DefaultSystemMessageQueue$class.systemEnqueue:(Lakka/dispatch/Mailbox;Lakka/actor/ActorRef;Lakka/dispatch/sysmsg/SystemMessage;)V
       6: return

  public final akka.dispatch.sysmsg.SystemMessage systemDrain(akka.dispatch.sysmsg.SystemMessage);
    Code:
       0: aload_0
       1: aload_1
       2: invokestatic  #30                 // Method akka/dispatch/DefaultSystemMessageQueue$class.systemDrain:(Lakka/dispatch/Mailbox;Lakka/dispatch/sysmsg/SystemMessage;)Lakka/dispatch/sysmsg/SystemMessage;
       5: areturn

  public boolean hasSystemMessages();
    Code:
       0: aload_0
       1: invokestatic  #36                 // Method akka/dispatch/DefaultSystemMessageQueue$class.hasSystemMessages:(Lakka/dispatch/Mailbox;)Z
       4: ireturn

  public akka.dispatch.Dispatcher$$anon$1(akka.dispatch.Dispatcher, akka.actor.Cell, akka.dispatch.MailboxType);
    Code:
       0: aload_0
       1: aload_3
       2: new           #40                 // class scala/Some
       5: dup
       6: aload_2
       7: invokeinterface #46,  1           // InterfaceMethod akka/actor/Cell.self:()Lakka/actor/ActorRef;
      12: invokespecial #49                 // Method scala/Some."<init>":(Ljava/lang/Object;)V
      15: new           #40                 // class scala/Some
      18: dup
      19: aload_2
      20: invokeinterface #53,  1           // InterfaceMethod akka/actor/Cell.system:()Lakka/actor/ActorSystem;
      25: invokespecial #49                 // Method scala/Some."<init>":(Ljava/lang/Object;)V
      28: invokeinterface #59,  3           // InterfaceMethod akka/dispatch/MailboxType.create:(Lscala/Option;Lscala/Option;)Lakka/dispatch/MessageQueue;
      33: invokespecial #62                 // Method akka/dispatch/Mailbox."<init>":(Lakka/dispatch/MessageQueue;)V
      36: aload_0
      37: invokestatic  #66                 // Method akka/dispatch/DefaultSystemMessageQueue$class.$init$:(Lakka/dispatch/Mailbox;)V
      40: return
}
