Compiled from "Future.scala"
public final class akka.dispatch.ExecutionContexts {
  public static scala.concurrent.ExecutionContextExecutor global();
    Code:
       0: getstatic     #16                 // Field akka/dispatch/ExecutionContexts$.MODULE$:Lakka/dispatch/ExecutionContexts$;
       3: invokevirtual #18                 // Method akka/dispatch/ExecutionContexts$.global:()Lscala/concurrent/ExecutionContextExecutor;
       6: areturn

  public static scala.concurrent.ExecutionContextExecutorService fromExecutorService(java.util.concurrent.ExecutorService, akka.japi.Procedure<java.lang.Throwable>);
    Code:
       0: getstatic     #16                 // Field akka/dispatch/ExecutionContexts$.MODULE$:Lakka/dispatch/ExecutionContexts$;
       3: aload_0
       4: aload_1
       5: invokevirtual #22                 // Method akka/dispatch/ExecutionContexts$.fromExecutorService:(Ljava/util/concurrent/ExecutorService;Lakka/japi/Procedure;)Lscala/concurrent/ExecutionContextExecutorService;
       8: areturn

  public static scala.concurrent.ExecutionContextExecutorService fromExecutorService(java.util.concurrent.ExecutorService);
    Code:
       0: getstatic     #16                 // Field akka/dispatch/ExecutionContexts$.MODULE$:Lakka/dispatch/ExecutionContexts$;
       3: aload_0
       4: invokevirtual #25                 // Method akka/dispatch/ExecutionContexts$.fromExecutorService:(Ljava/util/concurrent/ExecutorService;)Lscala/concurrent/ExecutionContextExecutorService;
       7: areturn

  public static scala.concurrent.ExecutionContextExecutor fromExecutor(java.util.concurrent.Executor, akka.japi.Procedure<java.lang.Throwable>);
    Code:
       0: getstatic     #16                 // Field akka/dispatch/ExecutionContexts$.MODULE$:Lakka/dispatch/ExecutionContexts$;
       3: aload_0
       4: aload_1
       5: invokevirtual #29                 // Method akka/dispatch/ExecutionContexts$.fromExecutor:(Ljava/util/concurrent/Executor;Lakka/japi/Procedure;)Lscala/concurrent/ExecutionContextExecutor;
       8: areturn

  public static scala.concurrent.ExecutionContextExecutor fromExecutor(java.util.concurrent.Executor);
    Code:
       0: getstatic     #16                 // Field akka/dispatch/ExecutionContexts$.MODULE$:Lakka/dispatch/ExecutionContexts$;
       3: aload_0
       4: invokevirtual #32                 // Method akka/dispatch/ExecutionContexts$.fromExecutor:(Ljava/util/concurrent/Executor;)Lscala/concurrent/ExecutionContextExecutor;
       7: areturn
}
