Compiled from "Future.scala"
public final class akka.dispatch.Futures$$anonfun$fold$1 extends scala.runtime.AbstractFunction2<R, T, R> implements scala.Serializable {
  public static final long serialVersionUID;

  private final akka.japi.Function2 fun$1;

  public final R apply(R, T);
    Code:
       0: aload_0
       1: getfield      #23                 // Field fun$1:Lakka/japi/Function2;
       4: aload_1
       5: aload_2
       6: invokeinterface #27,  3           // InterfaceMethod akka/japi/Function2.apply:(Ljava/lang/Object;Ljava/lang/Object;)Ljava/lang/Object;
      11: areturn

  public akka.dispatch.Futures$$anonfun$fold$1(akka.japi.Function2);
    Code:
       0: aload_0
       1: aload_1
       2: putfield      #23                 // Field fun$1:Lakka/japi/Function2;
       5: aload_0
       6: invokespecial #37                 // Method scala/runtime/AbstractFunction2."<init>":()V
       9: return
}
