Compiled from "Mailbox.scala"
public final class akka.dispatch.SingleConsumerOnlyUnboundedMailbox$ extends scala.runtime.AbstractFunction0<akka.dispatch.SingleConsumerOnlyUnboundedMailbox> implements scala.Serializable {
  public static final akka.dispatch.SingleConsumerOnlyUnboundedMailbox$ MODULE$;

  public static {};
    Code:
       0: new           #2                  // class akka/dispatch/SingleConsumerOnlyUnboundedMailbox$
       3: invokespecial #15                 // Method "<init>":()V
       6: return

  public final java.lang.String toString();
    Code:
       0: ldc           #19                 // String SingleConsumerOnlyUnboundedMailbox
       2: areturn

  public akka.dispatch.SingleConsumerOnlyUnboundedMailbox apply();
    Code:
       0: new           #24                 // class akka/dispatch/SingleConsumerOnlyUnboundedMailbox
       3: dup
       4: invokespecial #25                 // Method akka/dispatch/SingleConsumerOnlyUnboundedMailbox."<init>":()V
       7: areturn

  public boolean unapply(akka.dispatch.SingleConsumerOnlyUnboundedMailbox);
    Code:
       0: aload_1
       1: ifnonnull     8
       4: iconst_0
       5: goto          9
       8: iconst_1
       9: ireturn

  private java.lang.Object readResolve();
    Code:
       0: getstatic     #33                 // Field MODULE$:Lakka/dispatch/SingleConsumerOnlyUnboundedMailbox$;
       3: areturn

  public java.lang.Object apply();
    Code:
       0: aload_0
       1: invokevirtual #35                 // Method apply:()Lakka/dispatch/SingleConsumerOnlyUnboundedMailbox;
       4: areturn

  private akka.dispatch.SingleConsumerOnlyUnboundedMailbox$();
    Code:
       0: aload_0
       1: invokespecial #36                 // Method scala/runtime/AbstractFunction0."<init>":()V
       4: aload_0
       5: putstatic     #33                 // Field MODULE$:Lakka/dispatch/SingleConsumerOnlyUnboundedMailbox$;
       8: return
}
