Compiled from "Mailbox.scala"
public class akka.dispatch.UnboundedControlAwareMailbox$MessageQueue implements akka.dispatch.UnboundedControlAwareMessageQueueSemantics,java.io.Serializable {
  private final java.util.Queue<akka.dispatch.Envelope> controlQueue;

  private final java.util.Queue<akka.dispatch.Envelope> queue;

  public void enqueue(akka.actor.ActorRef, akka.dispatch.Envelope);
    Code:
       0: aload_0
       1: aload_1
       2: aload_2
       3: invokestatic  #20                 // Method akka/dispatch/ControlAwareMessageQueueSemantics$class.enqueue:(Lakka/dispatch/ControlAwareMessageQueueSemantics;Lakka/actor/ActorRef;Lakka/dispatch/Envelope;)V
       6: return

  public akka.dispatch.Envelope dequeue();
    Code:
       0: aload_0
       1: invokestatic  #31                 // Method akka/dispatch/ControlAwareMessageQueueSemantics$class.dequeue:(Lakka/dispatch/ControlAwareMessageQueueSemantics;)Lakka/dispatch/Envelope;
       4: areturn

  public int numberOfMessages();
    Code:
       0: aload_0
       1: invokestatic  #36                 // Method akka/dispatch/ControlAwareMessageQueueSemantics$class.numberOfMessages:(Lakka/dispatch/ControlAwareMessageQueueSemantics;)I
       4: ireturn

  public boolean hasMessages();
    Code:
       0: aload_0
       1: invokestatic  #41                 // Method akka/dispatch/ControlAwareMessageQueueSemantics$class.hasMessages:(Lakka/dispatch/ControlAwareMessageQueueSemantics;)Z
       4: ireturn

  public void cleanUp(akka.actor.ActorRef, akka.dispatch.MessageQueue);
    Code:
       0: aload_0
       1: aload_1
       2: aload_2
       3: invokestatic  #48                 // Method akka/dispatch/QueueBasedMessageQueue$class.cleanUp:(Lakka/dispatch/QueueBasedMessageQueue;Lakka/actor/ActorRef;Lakka/dispatch/MessageQueue;)V
       6: return

  public java.util.Queue<akka.dispatch.Envelope> controlQueue();
    Code:
       0: aload_0
       1: getfield      #54                 // Field controlQueue:Ljava/util/Queue;
       4: areturn

  public java.util.Queue<akka.dispatch.Envelope> queue();
    Code:
       0: aload_0
       1: getfield      #56                 // Field queue:Ljava/util/Queue;
       4: areturn

  public akka.dispatch.UnboundedControlAwareMailbox$MessageQueue();
    Code:
       0: aload_0
       1: invokespecial #60                 // Method java/lang/Object."<init>":()V
       4: aload_0
       5: invokestatic  #64                 // Method akka/dispatch/QueueBasedMessageQueue$class.$init$:(Lakka/dispatch/QueueBasedMessageQueue;)V
       8: aload_0
       9: invokestatic  #67                 // Method akka/dispatch/ControlAwareMessageQueueSemantics$class.$init$:(Lakka/dispatch/ControlAwareMessageQueueSemantics;)V
      12: aload_0
      13: new           #69                 // class java/util/concurrent/ConcurrentLinkedQueue
      16: dup
      17: invokespecial #70                 // Method java/util/concurrent/ConcurrentLinkedQueue."<init>":()V
      20: putfield      #54                 // Field controlQueue:Ljava/util/Queue;
      23: aload_0
      24: new           #69                 // class java/util/concurrent/ConcurrentLinkedQueue
      27: dup
      28: invokespecial #70                 // Method java/util/concurrent/ConcurrentLinkedQueue."<init>":()V
      31: putfield      #56                 // Field queue:Ljava/util/Queue;
      34: return
}
