Compiled from "Field.java"
public class org.apache.kafka.connect.data.Field {
  private final java.lang.String name;

  private final int index;

  private final org.apache.kafka.connect.data.Schema schema;

  public org.apache.kafka.connect.data.Field(java.lang.String, int, org.apache.kafka.connect.data.Schema);
    Code:
       0: aload_0
       1: invokespecial #1                  // Method java/lang/Object."<init>":()V
       4: aload_0
       5: aload_1
       6: putfield      #2                  // Field name:Ljava/lang/String;
       9: aload_0
      10: iload_2
      11: putfield      #3                  // Field index:I
      14: aload_0
      15: aload_3
      16: putfield      #4                  // Field schema:Lorg/apache/kafka/connect/data/Schema;
      19: return

  public java.lang.String name();
    Code:
       0: aload_0
       1: getfield      #2                  // Field name:Ljava/lang/String;
       4: areturn

  public int index();
    Code:
       0: aload_0
       1: getfield      #3                  // Field index:I
       4: ireturn

  public org.apache.kafka.connect.data.Schema schema();
    Code:
       0: aload_0
       1: getfield      #4                  // Field schema:Lorg/apache/kafka/connect/data/Schema;
       4: areturn

  public boolean equals(java.lang.Object);
    Code:
       0: aload_0
       1: aload_1
       2: if_acmpne     7
       5: iconst_1
       6: ireturn
       7: aload_1
       8: ifnull        22
      11: aload_0
      12: invokevirtual #5                  // Method java/lang/Object.getClass:()Ljava/lang/Class;
      15: aload_1
      16: invokevirtual #5                  // Method java/lang/Object.getClass:()Ljava/lang/Class;
      19: if_acmpeq     24
      22: iconst_0
      23: ireturn
      24: aload_1
      25: checkcast     #6                  // class org/apache/kafka/connect/data/Field
      28: astore_2
      29: aload_0
      30: getfield      #3                  // Field index:I
      33: invokestatic  #7                  // Method java/lang/Integer.valueOf:(I)Ljava/lang/Integer;
      36: aload_2
      37: getfield      #3                  // Field index:I
      40: invokestatic  #7                  // Method java/lang/Integer.valueOf:(I)Ljava/lang/Integer;
      43: invokestatic  #8                  // Method java/util/Objects.equals:(Ljava/lang/Object;Ljava/lang/Object;)Z
      46: ifeq          81
      49: aload_0
      50: getfield      #2                  // Field name:Ljava/lang/String;
      53: aload_2
      54: getfield      #2                  // Field name:Ljava/lang/String;
      57: invokestatic  #8                  // Method java/util/Objects.equals:(Ljava/lang/Object;Ljava/lang/Object;)Z
      60: ifeq          81
      63: aload_0
      64: getfield      #4                  // Field schema:Lorg/apache/kafka/connect/data/Schema;
      67: aload_2
      68: getfield      #4                  // Field schema:Lorg/apache/kafka/connect/data/Schema;
      71: invokestatic  #8                  // Method java/util/Objects.equals:(Ljava/lang/Object;Ljava/lang/Object;)Z
      74: ifeq          81
      77: iconst_1
      78: goto          82
      81: iconst_0
      82: ireturn

  public int hashCode();
    Code:
       0: iconst_3
       1: anewarray     #9                  // class java/lang/Object
       4: dup
       5: iconst_0
       6: aload_0
       7: getfield      #2                  // Field name:Ljava/lang/String;
      10: aastore
      11: dup
      12: iconst_1
      13: aload_0
      14: getfield      #3                  // Field index:I
      17: invokestatic  #7                  // Method java/lang/Integer.valueOf:(I)Ljava/lang/Integer;
      20: aastore
      21: dup
      22: iconst_2
      23: aload_0
      24: getfield      #4                  // Field schema:Lorg/apache/kafka/connect/data/Schema;
      27: aastore
      28: invokestatic  #10                 // Method java/util/Objects.hash:([Ljava/lang/Object;)I
      31: ireturn

  public java.lang.String toString();
    Code:
       0: new           #11                 // class java/lang/StringBuilder
       3: dup
       4: invokespecial #12                 // Method java/lang/StringBuilder."<init>":()V
       7: ldc           #13                 // String Field{name=
       9: invokevirtual #14                 // Method java/lang/StringBuilder.append:(Ljava/lang/String;)Ljava/lang/StringBuilder;
      12: aload_0
      13: getfield      #2                  // Field name:Ljava/lang/String;
      16: invokevirtual #14                 // Method java/lang/StringBuilder.append:(Ljava/lang/String;)Ljava/lang/StringBuilder;
      19: ldc           #15                 // String , index=
      21: invokevirtual #14                 // Method java/lang/StringBuilder.append:(Ljava/lang/String;)Ljava/lang/StringBuilder;
      24: aload_0
      25: getfield      #3                  // Field index:I
      28: invokevirtual #16                 // Method java/lang/StringBuilder.append:(I)Ljava/lang/StringBuilder;
      31: ldc           #17                 // String , schema=
      33: invokevirtual #14                 // Method java/lang/StringBuilder.append:(Ljava/lang/String;)Ljava/lang/StringBuilder;
      36: aload_0
      37: getfield      #4                  // Field schema:Lorg/apache/kafka/connect/data/Schema;
      40: invokevirtual #18                 // Method java/lang/StringBuilder.append:(Ljava/lang/Object;)Ljava/lang/StringBuilder;
      43: ldc           #19                 // String }
      45: invokevirtual #14                 // Method java/lang/StringBuilder.append:(Ljava/lang/String;)Ljava/lang/StringBuilder;
      48: invokevirtual #20                 // Method java/lang/StringBuilder.toString:()Ljava/lang/String;
      51: areturn
}
