Compiled from "Schema.java"
class org.apache.kafka.connect.data.Schema$1 {
  static final int[] $SwitchMap$org$apache$kafka$connect$data$Schema$Type;

  static {};
    Code:
       0: invokestatic  #1                  // Method org/apache/kafka/connect/data/Schema$Type.values:()[Lorg/apache/kafka/connect/data/Schema$Type;
       3: arraylength
       4: newarray       int
       6: putstatic     #2                  // Field $SwitchMap$org$apache$kafka$connect$data$Schema$Type:[I
       9: getstatic     #2                  // Field $SwitchMap$org$apache$kafka$connect$data$Schema$Type:[I
      12: getstatic     #3                  // Field org/apache/kafka/connect/data/Schema$Type.INT8:Lorg/apache/kafka/connect/data/Schema$Type;
      15: invokevirtual #4                  // Method org/apache/kafka/connect/data/Schema$Type.ordinal:()I
      18: iconst_1
      19: iastore
      20: goto          24
      23: astore_0
      24: getstatic     #2                  // Field $SwitchMap$org$apache$kafka$connect$data$Schema$Type:[I
      27: getstatic     #6                  // Field org/apache/kafka/connect/data/Schema$Type.INT16:Lorg/apache/kafka/connect/data/Schema$Type;
      30: invokevirtual #4                  // Method org/apache/kafka/connect/data/Schema$Type.ordinal:()I
      33: iconst_2
      34: iastore
      35: goto          39
      38: astore_0
      39: getstatic     #2                  // Field $SwitchMap$org$apache$kafka$connect$data$Schema$Type:[I
      42: getstatic     #7                  // Field org/apache/kafka/connect/data/Schema$Type.INT32:Lorg/apache/kafka/connect/data/Schema$Type;
      45: invokevirtual #4                  // Method org/apache/kafka/connect/data/Schema$Type.ordinal:()I
      48: iconst_3
      49: iastore
      50: goto          54
      53: astore_0
      54: getstatic     #2                  // Field $SwitchMap$org$apache$kafka$connect$data$Schema$Type:[I
      57: getstatic     #8                  // Field org/apache/kafka/connect/data/Schema$Type.INT64:Lorg/apache/kafka/connect/data/Schema$Type;
      60: invokevirtual #4                  // Method org/apache/kafka/connect/data/Schema$Type.ordinal:()I
      63: iconst_4
      64: iastore
      65: goto          69
      68: astore_0
      69: getstatic     #2                  // Field $SwitchMap$org$apache$kafka$connect$data$Schema$Type:[I
      72: getstatic     #9                  // Field org/apache/kafka/connect/data/Schema$Type.FLOAT32:Lorg/apache/kafka/connect/data/Schema$Type;
      75: invokevirtual #4                  // Method org/apache/kafka/connect/data/Schema$Type.ordinal:()I
      78: iconst_5
      79: iastore
      80: goto          84
      83: astore_0
      84: getstatic     #2                  // Field $SwitchMap$org$apache$kafka$connect$data$Schema$Type:[I
      87: getstatic     #10                 // Field org/apache/kafka/connect/data/Schema$Type.FLOAT64:Lorg/apache/kafka/connect/data/Schema$Type;
      90: invokevirtual #4                  // Method org/apache/kafka/connect/data/Schema$Type.ordinal:()I
      93: bipush        6
      95: iastore
      96: goto          100
      99: astore_0
     100: getstatic     #2                  // Field $SwitchMap$org$apache$kafka$connect$data$Schema$Type:[I
     103: getstatic     #11                 // Field org/apache/kafka/connect/data/Schema$Type.BOOLEAN:Lorg/apache/kafka/connect/data/Schema$Type;
     106: invokevirtual #4                  // Method org/apache/kafka/connect/data/Schema$Type.ordinal:()I
     109: bipush        7
     111: iastore
     112: goto          116
     115: astore_0
     116: getstatic     #2                  // Field $SwitchMap$org$apache$kafka$connect$data$Schema$Type:[I
     119: getstatic     #12                 // Field org/apache/kafka/connect/data/Schema$Type.STRING:Lorg/apache/kafka/connect/data/Schema$Type;
     122: invokevirtual #4                  // Method org/apache/kafka/connect/data/Schema$Type.ordinal:()I
     125: bipush        8
     127: iastore
     128: goto          132
     131: astore_0
     132: getstatic     #2                  // Field $SwitchMap$org$apache$kafka$connect$data$Schema$Type:[I
     135: getstatic     #13                 // Field org/apache/kafka/connect/data/Schema$Type.BYTES:Lorg/apache/kafka/connect/data/Schema$Type;
     138: invokevirtual #4                  // Method org/apache/kafka/connect/data/Schema$Type.ordinal:()I
     141: bipush        9
     143: iastore
     144: goto          148
     147: astore_0
     148: return
    Exception table:
       from    to  target type
           9    20    23   Class java/lang/NoSuchFieldError
          24    35    38   Class java/lang/NoSuchFieldError
          39    50    53   Class java/lang/NoSuchFieldError
          54    65    68   Class java/lang/NoSuchFieldError
          69    80    83   Class java/lang/NoSuchFieldError
          84    96    99   Class java/lang/NoSuchFieldError
         100   112   115   Class java/lang/NoSuchFieldError
         116   128   131   Class java/lang/NoSuchFieldError
         132   144   147   Class java/lang/NoSuchFieldError
}
