Compiled from "Values.java"
public class org.apache.kafka.connect.data.Values {
  private static final org.slf4j.Logger LOG;

  private static final java.util.TimeZone UTC;

  private static final org.apache.kafka.connect.data.SchemaAndValue NULL_SCHEMA_AND_VALUE;

  private static final org.apache.kafka.connect.data.SchemaAndValue TRUE_SCHEMA_AND_VALUE;

  private static final org.apache.kafka.connect.data.SchemaAndValue FALSE_SCHEMA_AND_VALUE;

  private static final org.apache.kafka.connect.data.Schema ARRAY_SELECTOR_SCHEMA;

  private static final org.apache.kafka.connect.data.Schema MAP_SELECTOR_SCHEMA;

  private static final org.apache.kafka.connect.data.Schema STRUCT_SELECTOR_SCHEMA;

  private static final java.lang.String TRUE_LITERAL;

  private static final java.lang.String FALSE_LITERAL;

  private static final long MILLIS_PER_DAY;

  private static final java.lang.String NULL_VALUE;

  static final java.lang.String ISO_8601_DATE_FORMAT_PATTERN;

  static final java.lang.String ISO_8601_TIME_FORMAT_PATTERN;

  static final java.lang.String ISO_8601_TIMESTAMP_FORMAT_PATTERN;

  private static final java.util.Set<java.lang.String> TEMPORAL_LOGICAL_TYPE_NAMES;

  private static final java.lang.String QUOTE_DELIMITER;

  private static final java.lang.String COMMA_DELIMITER;

  private static final java.lang.String ENTRY_DELIMITER;

  private static final java.lang.String ARRAY_BEGIN_DELIMITER;

  private static final java.lang.String ARRAY_END_DELIMITER;

  private static final java.lang.String MAP_BEGIN_DELIMITER;

  private static final java.lang.String MAP_END_DELIMITER;

  private static final int ISO_8601_DATE_LENGTH;

  private static final int ISO_8601_TIME_LENGTH;

  private static final int ISO_8601_TIMESTAMP_LENGTH;

  private static final java.util.regex.Pattern TWO_BACKSLASHES;

  private static final java.util.regex.Pattern DOUBLEQOUTE;

  public org.apache.kafka.connect.data.Values();
    Code:
       0: aload_0
       1: invokespecial #2                  // Method java/lang/Object."<init>":()V
       4: return

  public static java.lang.Boolean convertToBoolean(org.apache.kafka.connect.data.Schema, java.lang.Object) throws org.apache.kafka.connect.errors.DataException;
    Code:
       0: getstatic     #3                  // Field org/apache/kafka/connect/data/Schema.OPTIONAL_BOOLEAN_SCHEMA:Lorg/apache/kafka/connect/data/Schema;
       3: aload_0
       4: aload_1
       5: invokestatic  #4                  // Method convertTo:(Lorg/apache/kafka/connect/data/Schema;Lorg/apache/kafka/connect/data/Schema;Ljava/lang/Object;)Ljava/lang/Object;
       8: checkcast     #5                  // class java/lang/Boolean
      11: areturn

  public static java.lang.Byte convertToByte(org.apache.kafka.connect.data.Schema, java.lang.Object) throws org.apache.kafka.connect.errors.DataException;
    Code:
       0: getstatic     #6                  // Field org/apache/kafka/connect/data/Schema.OPTIONAL_INT8_SCHEMA:Lorg/apache/kafka/connect/data/Schema;
       3: aload_0
       4: aload_1
       5: invokestatic  #4                  // Method convertTo:(Lorg/apache/kafka/connect/data/Schema;Lorg/apache/kafka/connect/data/Schema;Ljava/lang/Object;)Ljava/lang/Object;
       8: checkcast     #7                  // class java/lang/Byte
      11: areturn

  public static java.lang.Short convertToShort(org.apache.kafka.connect.data.Schema, java.lang.Object) throws org.apache.kafka.connect.errors.DataException;
    Code:
       0: getstatic     #8                  // Field org/apache/kafka/connect/data/Schema.OPTIONAL_INT16_SCHEMA:Lorg/apache/kafka/connect/data/Schema;
       3: aload_0
       4: aload_1
       5: invokestatic  #4                  // Method convertTo:(Lorg/apache/kafka/connect/data/Schema;Lorg/apache/kafka/connect/data/Schema;Ljava/lang/Object;)Ljava/lang/Object;
       8: checkcast     #9                  // class java/lang/Short
      11: areturn

  public static java.lang.Integer convertToInteger(org.apache.kafka.connect.data.Schema, java.lang.Object) throws org.apache.kafka.connect.errors.DataException;
    Code:
       0: getstatic     #10                 // Field org/apache/kafka/connect/data/Schema.OPTIONAL_INT32_SCHEMA:Lorg/apache/kafka/connect/data/Schema;
       3: aload_0
       4: aload_1
       5: invokestatic  #4                  // Method convertTo:(Lorg/apache/kafka/connect/data/Schema;Lorg/apache/kafka/connect/data/Schema;Ljava/lang/Object;)Ljava/lang/Object;
       8: checkcast     #11                 // class java/lang/Integer
      11: areturn

  public static java.lang.Long convertToLong(org.apache.kafka.connect.data.Schema, java.lang.Object) throws org.apache.kafka.connect.errors.DataException;
    Code:
       0: getstatic     #12                 // Field org/apache/kafka/connect/data/Schema.OPTIONAL_INT64_SCHEMA:Lorg/apache/kafka/connect/data/Schema;
       3: aload_0
       4: aload_1
       5: invokestatic  #4                  // Method convertTo:(Lorg/apache/kafka/connect/data/Schema;Lorg/apache/kafka/connect/data/Schema;Ljava/lang/Object;)Ljava/lang/Object;
       8: checkcast     #13                 // class java/lang/Long
      11: areturn

  public static java.lang.Float convertToFloat(org.apache.kafka.connect.data.Schema, java.lang.Object) throws org.apache.kafka.connect.errors.DataException;
    Code:
       0: getstatic     #14                 // Field org/apache/kafka/connect/data/Schema.OPTIONAL_FLOAT32_SCHEMA:Lorg/apache/kafka/connect/data/Schema;
       3: aload_0
       4: aload_1
       5: invokestatic  #4                  // Method convertTo:(Lorg/apache/kafka/connect/data/Schema;Lorg/apache/kafka/connect/data/Schema;Ljava/lang/Object;)Ljava/lang/Object;
       8: checkcast     #15                 // class java/lang/Float
      11: areturn

  public static java.lang.Double convertToDouble(org.apache.kafka.connect.data.Schema, java.lang.Object) throws org.apache.kafka.connect.errors.DataException;
    Code:
       0: getstatic     #16                 // Field org/apache/kafka/connect/data/Schema.OPTIONAL_FLOAT64_SCHEMA:Lorg/apache/kafka/connect/data/Schema;
       3: aload_0
       4: aload_1
       5: invokestatic  #4                  // Method convertTo:(Lorg/apache/kafka/connect/data/Schema;Lorg/apache/kafka/connect/data/Schema;Ljava/lang/Object;)Ljava/lang/Object;
       8: checkcast     #17                 // class java/lang/Double
      11: areturn

  public static java.lang.String convertToString(org.apache.kafka.connect.data.Schema, java.lang.Object);
    Code:
       0: getstatic     #18                 // Field org/apache/kafka/connect/data/Schema.OPTIONAL_STRING_SCHEMA:Lorg/apache/kafka/connect/data/Schema;
       3: aload_0
       4: aload_1
       5: invokestatic  #4                  // Method convertTo:(Lorg/apache/kafka/connect/data/Schema;Lorg/apache/kafka/connect/data/Schema;Ljava/lang/Object;)Ljava/lang/Object;
       8: checkcast     #19                 // class java/lang/String
      11: areturn

  public static java.util.List<?> convertToList(org.apache.kafka.connect.data.Schema, java.lang.Object);
    Code:
       0: getstatic     #20                 // Field ARRAY_SELECTOR_SCHEMA:Lorg/apache/kafka/connect/data/Schema;
       3: aload_0
       4: aload_1
       5: invokestatic  #4                  // Method convertTo:(Lorg/apache/kafka/connect/data/Schema;Lorg/apache/kafka/connect/data/Schema;Ljava/lang/Object;)Ljava/lang/Object;
       8: checkcast     #21                 // class java/util/List
      11: areturn

  public static java.util.Map<?, ?> convertToMap(org.apache.kafka.connect.data.Schema, java.lang.Object);
    Code:
       0: getstatic     #22                 // Field MAP_SELECTOR_SCHEMA:Lorg/apache/kafka/connect/data/Schema;
       3: aload_0
       4: aload_1
       5: invokestatic  #4                  // Method convertTo:(Lorg/apache/kafka/connect/data/Schema;Lorg/apache/kafka/connect/data/Schema;Ljava/lang/Object;)Ljava/lang/Object;
       8: checkcast     #23                 // class java/util/Map
      11: areturn

  public static org.apache.kafka.connect.data.Struct convertToStruct(org.apache.kafka.connect.data.Schema, java.lang.Object);
    Code:
       0: getstatic     #24                 // Field STRUCT_SELECTOR_SCHEMA:Lorg/apache/kafka/connect/data/Schema;
       3: aload_0
       4: aload_1
       5: invokestatic  #4                  // Method convertTo:(Lorg/apache/kafka/connect/data/Schema;Lorg/apache/kafka/connect/data/Schema;Ljava/lang/Object;)Ljava/lang/Object;
       8: checkcast     #25                 // class org/apache/kafka/connect/data/Struct
      11: areturn

  public static java.util.Date convertToTime(org.apache.kafka.connect.data.Schema, java.lang.Object);
    Code:
       0: getstatic     #26                 // Field org/apache/kafka/connect/data/Time.SCHEMA:Lorg/apache/kafka/connect/data/Schema;
       3: aload_0
       4: aload_1
       5: invokestatic  #4                  // Method convertTo:(Lorg/apache/kafka/connect/data/Schema;Lorg/apache/kafka/connect/data/Schema;Ljava/lang/Object;)Ljava/lang/Object;
       8: checkcast     #27                 // class java/util/Date
      11: areturn

  public static java.util.Date convertToDate(org.apache.kafka.connect.data.Schema, java.lang.Object);
    Code:
       0: getstatic     #28                 // Field org/apache/kafka/connect/data/Date.SCHEMA:Lorg/apache/kafka/connect/data/Schema;
       3: aload_0
       4: aload_1
       5: invokestatic  #4                  // Method convertTo:(Lorg/apache/kafka/connect/data/Schema;Lorg/apache/kafka/connect/data/Schema;Ljava/lang/Object;)Ljava/lang/Object;
       8: checkcast     #27                 // class java/util/Date
      11: areturn

  public static java.util.Date convertToTimestamp(org.apache.kafka.connect.data.Schema, java.lang.Object);
    Code:
       0: getstatic     #29                 // Field org/apache/kafka/connect/data/Timestamp.SCHEMA:Lorg/apache/kafka/connect/data/Schema;
       3: aload_0
       4: aload_1
       5: invokestatic  #4                  // Method convertTo:(Lorg/apache/kafka/connect/data/Schema;Lorg/apache/kafka/connect/data/Schema;Ljava/lang/Object;)Ljava/lang/Object;
       8: checkcast     #27                 // class java/util/Date
      11: areturn

  public static java.math.BigDecimal convertToDecimal(org.apache.kafka.connect.data.Schema, java.lang.Object, int);
    Code:
       0: iload_2
       1: invokestatic  #30                 // Method org/apache/kafka/connect/data/Decimal.schema:(I)Lorg/apache/kafka/connect/data/Schema;
       4: aload_0
       5: aload_1
       6: invokestatic  #4                  // Method convertTo:(Lorg/apache/kafka/connect/data/Schema;Lorg/apache/kafka/connect/data/Schema;Ljava/lang/Object;)Ljava/lang/Object;
       9: checkcast     #31                 // class java/math/BigDecimal
      12: areturn

  public static org.apache.kafka.connect.data.Schema inferSchema(java.lang.Object);
    Code:
       0: aload_0
       1: instanceof    #19                 // class java/lang/String
       4: ifeq          11
       7: getstatic     #32                 // Field org/apache/kafka/connect/data/Schema.STRING_SCHEMA:Lorg/apache/kafka/connect/data/Schema;
      10: areturn
      11: aload_0
      12: instanceof    #5                  // class java/lang/Boolean
      15: ifeq          22
      18: getstatic     #33                 // Field org/apache/kafka/connect/data/Schema.BOOLEAN_SCHEMA:Lorg/apache/kafka/connect/data/Schema;
      21: areturn
      22: aload_0
      23: instanceof    #7                  // class java/lang/Byte
      26: ifeq          33
      29: getstatic     #34                 // Field org/apache/kafka/connect/data/Schema.INT8_SCHEMA:Lorg/apache/kafka/connect/data/Schema;
      32: areturn
      33: aload_0
      34: instanceof    #9                  // class java/lang/Short
      37: ifeq          44
      40: getstatic     #35                 // Field org/apache/kafka/connect/data/Schema.INT16_SCHEMA:Lorg/apache/kafka/connect/data/Schema;
      43: areturn
      44: aload_0
      45: instanceof    #11                 // class java/lang/Integer
      48: ifeq          55
      51: getstatic     #36                 // Field org/apache/kafka/connect/data/Schema.INT32_SCHEMA:Lorg/apache/kafka/connect/data/Schema;
      54: areturn
      55: aload_0
      56: instanceof    #13                 // class java/lang/Long
      59: ifeq          66
      62: getstatic     #37                 // Field org/apache/kafka/connect/data/Schema.INT64_SCHEMA:Lorg/apache/kafka/connect/data/Schema;
      65: areturn
      66: aload_0
      67: instanceof    #15                 // class java/lang/Float
      70: ifeq          77
      73: getstatic     #38                 // Field org/apache/kafka/connect/data/Schema.FLOAT32_SCHEMA:Lorg/apache/kafka/connect/data/Schema;
      76: areturn
      77: aload_0
      78: instanceof    #17                 // class java/lang/Double
      81: ifeq          88
      84: getstatic     #39                 // Field org/apache/kafka/connect/data/Schema.FLOAT64_SCHEMA:Lorg/apache/kafka/connect/data/Schema;
      87: areturn
      88: aload_0
      89: instanceof    #40                 // class "[B"
      92: ifne          102
      95: aload_0
      96: instanceof    #41                 // class java/nio/ByteBuffer
      99: ifeq          106
     102: getstatic     #42                 // Field org/apache/kafka/connect/data/Schema.BYTES_SCHEMA:Lorg/apache/kafka/connect/data/Schema;
     105: areturn
     106: aload_0
     107: instanceof    #21                 // class java/util/List
     110: ifeq          186
     113: aload_0
     114: checkcast     #21                 // class java/util/List
     117: astore_1
     118: aload_1
     119: invokeinterface #43,  1           // InterfaceMethod java/util/List.isEmpty:()Z
     124: ifeq          129
     127: aconst_null
     128: areturn
     129: new           #44                 // class org/apache/kafka/connect/data/Values$SchemaDetector
     132: dup
     133: invokespecial #45                 // Method org/apache/kafka/connect/data/Values$SchemaDetector."<init>":()V
     136: astore_2
     137: aload_1
     138: invokeinterface #46,  1           // InterfaceMethod java/util/List.iterator:()Ljava/util/Iterator;
     143: astore_3
     144: aload_3
     145: invokeinterface #47,  1           // InterfaceMethod java/util/Iterator.hasNext:()Z
     150: ifeq          175
     153: aload_3
     154: invokeinterface #48,  1           // InterfaceMethod java/util/Iterator.next:()Ljava/lang/Object;
     159: astore        4
     161: aload_2
     162: aload         4
     164: invokevirtual #49                 // Method org/apache/kafka/connect/data/Values$SchemaDetector.canDetect:(Ljava/lang/Object;)Z
     167: ifne          172
     170: aconst_null
     171: areturn
     172: goto          144
     175: aload_2
     176: invokevirtual #50                 // Method org/apache/kafka/connect/data/Values$SchemaDetector.schema:()Lorg/apache/kafka/connect/data/Schema;
     179: invokestatic  #51                 // Method org/apache/kafka/connect/data/SchemaBuilder.array:(Lorg/apache/kafka/connect/data/Schema;)Lorg/apache/kafka/connect/data/SchemaBuilder;
     182: invokevirtual #52                 // Method org/apache/kafka/connect/data/SchemaBuilder.build:()Lorg/apache/kafka/connect/data/Schema;
     185: areturn
     186: aload_0
     187: instanceof    #23                 // class java/util/Map
     190: ifeq          308
     193: aload_0
     194: checkcast     #23                 // class java/util/Map
     197: astore_1
     198: aload_1
     199: invokeinterface #53,  1           // InterfaceMethod java/util/Map.isEmpty:()Z
     204: ifeq          209
     207: aconst_null
     208: areturn
     209: new           #44                 // class org/apache/kafka/connect/data/Values$SchemaDetector
     212: dup
     213: invokespecial #45                 // Method org/apache/kafka/connect/data/Values$SchemaDetector."<init>":()V
     216: astore_2
     217: new           #44                 // class org/apache/kafka/connect/data/Values$SchemaDetector
     220: dup
     221: invokespecial #45                 // Method org/apache/kafka/connect/data/Values$SchemaDetector."<init>":()V
     224: astore_3
     225: aload_1
     226: invokeinterface #54,  1           // InterfaceMethod java/util/Map.entrySet:()Ljava/util/Set;
     231: invokeinterface #55,  1           // InterfaceMethod java/util/Set.iterator:()Ljava/util/Iterator;
     236: astore        4
     238: aload         4
     240: invokeinterface #47,  1           // InterfaceMethod java/util/Iterator.hasNext:()Z
     245: ifeq          293
     248: aload         4
     250: invokeinterface #48,  1           // InterfaceMethod java/util/Iterator.next:()Ljava/lang/Object;
     255: checkcast     #56                 // class java/util/Map$Entry
     258: astore        5
     260: aload_2
     261: aload         5
     263: invokeinterface #57,  1           // InterfaceMethod java/util/Map$Entry.getKey:()Ljava/lang/Object;
     268: invokevirtual #49                 // Method org/apache/kafka/connect/data/Values$SchemaDetector.canDetect:(Ljava/lang/Object;)Z
     271: ifeq          288
     274: aload_3
     275: aload         5
     277: invokeinterface #58,  1           // InterfaceMethod java/util/Map$Entry.getValue:()Ljava/lang/Object;
     282: invokevirtual #49                 // Method org/apache/kafka/connect/data/Values$SchemaDetector.canDetect:(Ljava/lang/Object;)Z
     285: ifne          290
     288: aconst_null
     289: areturn
     290: goto          238
     293: aload_2
     294: invokevirtual #50                 // Method org/apache/kafka/connect/data/Values$SchemaDetector.schema:()Lorg/apache/kafka/connect/data/Schema;
     297: aload_3
     298: invokevirtual #50                 // Method org/apache/kafka/connect/data/Values$SchemaDetector.schema:()Lorg/apache/kafka/connect/data/Schema;
     301: invokestatic  #59                 // Method org/apache/kafka/connect/data/SchemaBuilder.map:(Lorg/apache/kafka/connect/data/Schema;Lorg/apache/kafka/connect/data/Schema;)Lorg/apache/kafka/connect/data/SchemaBuilder;
     304: invokevirtual #52                 // Method org/apache/kafka/connect/data/SchemaBuilder.build:()Lorg/apache/kafka/connect/data/Schema;
     307: areturn
     308: aload_0
     309: instanceof    #25                 // class org/apache/kafka/connect/data/Struct
     312: ifeq          323
     315: aload_0
     316: checkcast     #25                 // class org/apache/kafka/connect/data/Struct
     319: invokevirtual #60                 // Method org/apache/kafka/connect/data/Struct.schema:()Lorg/apache/kafka/connect/data/Schema;
     322: areturn
     323: aconst_null
     324: areturn

  public static org.apache.kafka.connect.data.SchemaAndValue parseString(java.lang.String);
    Code:
       0: aload_0
       1: ifnonnull     8
       4: getstatic     #61                 // Field NULL_SCHEMA_AND_VALUE:Lorg/apache/kafka/connect/data/SchemaAndValue;
       7: areturn
       8: aload_0
       9: invokevirtual #62                 // Method java/lang/String.isEmpty:()Z
      12: ifeq          27
      15: new           #63                 // class org/apache/kafka/connect/data/SchemaAndValue
      18: dup
      19: getstatic     #32                 // Field org/apache/kafka/connect/data/Schema.STRING_SCHEMA:Lorg/apache/kafka/connect/data/Schema;
      22: aload_0
      23: invokespecial #64                 // Method org/apache/kafka/connect/data/SchemaAndValue."<init>":(Lorg/apache/kafka/connect/data/Schema;Ljava/lang/Object;)V
      26: areturn
      27: new           #65                 // class org/apache/kafka/connect/data/Values$Parser
      30: dup
      31: aload_0
      32: invokespecial #66                 // Method org/apache/kafka/connect/data/Values$Parser."<init>":(Ljava/lang/String;)V
      35: astore_1
      36: aload_1
      37: iconst_0
      38: invokestatic  #67                 // Method parse:(Lorg/apache/kafka/connect/data/Values$Parser;Z)Lorg/apache/kafka/connect/data/SchemaAndValue;
      41: areturn

  protected static java.lang.Object convertTo(org.apache.kafka.connect.data.Schema, org.apache.kafka.connect.data.Schema, java.lang.Object) throws org.apache.kafka.connect.errors.DataException;
    Code:
       0: aload_2
       1: ifnonnull     25
       4: aload_0
       5: invokeinterface #68,  1           // InterfaceMethod org/apache/kafka/connect/data/Schema.isOptional:()Z
      10: ifeq          15
      13: aconst_null
      14: areturn
      15: new           #69                 // class org/apache/kafka/connect/errors/DataException
      18: dup
      19: ldc           #70                 // String Unable to convert a null value to a schema that requires a value
      21: invokespecial #71                 // Method org/apache/kafka/connect/errors/DataException."<init>":(Ljava/lang/String;)V
      24: athrow
      25: getstatic     #72                 // Field org/apache/kafka/connect/data/Values$1.$SwitchMap$org$apache$kafka$connect$data$Schema$Type:[I
      28: aload_0
      29: invokeinterface #73,  1           // InterfaceMethod org/apache/kafka/connect/data/Schema.type:()Lorg/apache/kafka/connect/data/Schema$Type;
      34: invokevirtual #74                 // Method org/apache/kafka/connect/data/Schema$Type.ordinal:()I
      37: iaload
      38: tableswitch   { // 1 to 12
                     1: 100
                     2: 242
                     3: 261
                     4: 324
                     5: 345
                     6: 366
                     7: 658
                     8: 830
                     9: 850
                    10: 869
                    11: 900
                    12: 931
               default: 947
          }
     100: ldc           #76                 // String org.apache.kafka.connect.data.Decimal
     102: aload_0
     103: invokeinterface #77,  1           // InterfaceMethod org/apache/kafka/connect/data/Schema.name:()Ljava/lang/String;
     108: invokevirtual #78                 // Method java/lang/String.equals:(Ljava/lang/Object;)Z
     111: ifeq          202
     114: aload_2
     115: instanceof    #41                 // class java/nio/ByteBuffer
     118: ifeq          129
     121: aload_2
     122: checkcast     #41                 // class java/nio/ByteBuffer
     125: invokestatic  #79                 // Method org/apache/kafka/common/utils/Utils.toArray:(Ljava/nio/ByteBuffer;)[B
     128: astore_2
     129: aload_2
     130: instanceof    #40                 // class "[B"
     133: ifeq          148
     136: aload_0
     137: aload_2
     138: checkcast     #40                 // class "[B"
     141: checkcast     #40                 // class "[B"
     144: invokestatic  #80                 // Method org/apache/kafka/connect/data/Decimal.toLogical:(Lorg/apache/kafka/connect/data/Schema;[B)Ljava/math/BigDecimal;
     147: areturn
     148: aload_2
     149: instanceof    #31                 // class java/math/BigDecimal
     152: ifeq          157
     155: aload_2
     156: areturn
     157: aload_2
     158: instanceof    #81                 // class java/lang/Number
     161: ifeq          177
     164: aload_2
     165: checkcast     #81                 // class java/lang/Number
     168: invokevirtual #82                 // Method java/lang/Number.doubleValue:()D
     171: dstore_3
     172: dload_3
     173: invokestatic  #83                 // Method java/math/BigDecimal.valueOf:(D)Ljava/math/BigDecimal;
     176: areturn
     177: aload_2
     178: instanceof    #19                 // class java/lang/String
     181: ifeq          202
     184: new           #31                 // class java/math/BigDecimal
     187: dup
     188: aload_2
     189: invokevirtual #84                 // Method java/lang/Object.toString:()Ljava/lang/String;
     192: invokespecial #85                 // Method java/math/BigDecimal."<init>":(Ljava/lang/String;)V
     195: invokevirtual #86                 // Method java/math/BigDecimal.doubleValue:()D
     198: invokestatic  #87                 // Method java/lang/Double.valueOf:(D)Ljava/lang/Double;
     201: areturn
     202: aload_2
     203: instanceof    #41                 // class java/nio/ByteBuffer
     206: ifeq          217
     209: aload_2
     210: checkcast     #41                 // class java/nio/ByteBuffer
     213: invokestatic  #79                 // Method org/apache/kafka/common/utils/Utils.toArray:(Ljava/nio/ByteBuffer;)[B
     216: areturn
     217: aload_2
     218: instanceof    #40                 // class "[B"
     221: ifeq          226
     224: aload_2
     225: areturn
     226: aload_2
     227: instanceof    #31                 // class java/math/BigDecimal
     230: ifeq          947
     233: aload_0
     234: aload_2
     235: checkcast     #31                 // class java/math/BigDecimal
     238: invokestatic  #88                 // Method org/apache/kafka/connect/data/Decimal.fromLogical:(Lorg/apache/kafka/connect/data/Schema;Ljava/math/BigDecimal;)[B
     241: areturn
     242: new           #89                 // class java/lang/StringBuilder
     245: dup
     246: invokespecial #90                 // Method java/lang/StringBuilder."<init>":()V
     249: astore_3
     250: aload_3
     251: aload_2
     252: iconst_0
     253: invokestatic  #91                 // Method append:(Ljava/lang/StringBuilder;Ljava/lang/Object;Z)V
     256: aload_3
     257: invokevirtual #92                 // Method java/lang/StringBuilder.toString:()Ljava/lang/String;
     260: areturn
     261: aload_2
     262: instanceof    #5                  // class java/lang/Boolean
     265: ifeq          270
     268: aload_2
     269: areturn
     270: aload_2
     271: instanceof    #19                 // class java/lang/String
     274: ifeq          303
     277: aload_2
     278: invokevirtual #84                 // Method java/lang/Object.toString:()Ljava/lang/String;
     281: invokestatic  #93                 // Method parseString:(Ljava/lang/String;)Lorg/apache/kafka/connect/data/SchemaAndValue;
     284: astore        4
     286: aload         4
     288: invokevirtual #94                 // Method org/apache/kafka/connect/data/SchemaAndValue.value:()Ljava/lang/Object;
     291: instanceof    #5                  // class java/lang/Boolean
     294: ifeq          303
     297: aload         4
     299: invokevirtual #94                 // Method org/apache/kafka/connect/data/SchemaAndValue.value:()Ljava/lang/Object;
     302: areturn
     303: aload_2
     304: aload_1
     305: aconst_null
     306: invokestatic  #95                 // Method asLong:(Ljava/lang/Object;Lorg/apache/kafka/connect/data/Schema;Ljava/lang/Throwable;)J
     309: lconst_0
     310: lcmp
     311: ifne          320
     314: getstatic     #96                 // Field java/lang/Boolean.FALSE:Ljava/lang/Boolean;
     317: goto          323
     320: getstatic     #97                 // Field java/lang/Boolean.TRUE:Ljava/lang/Boolean;
     323: areturn
     324: aload_2
     325: instanceof    #7                  // class java/lang/Byte
     328: ifeq          333
     331: aload_2
     332: areturn
     333: aload_2
     334: aload_1
     335: aconst_null
     336: invokestatic  #95                 // Method asLong:(Ljava/lang/Object;Lorg/apache/kafka/connect/data/Schema;Ljava/lang/Throwable;)J
     339: l2i
     340: i2b
     341: invokestatic  #98                 // Method java/lang/Byte.valueOf:(B)Ljava/lang/Byte;
     344: areturn
     345: aload_2
     346: instanceof    #9                  // class java/lang/Short
     349: ifeq          354
     352: aload_2
     353: areturn
     354: aload_2
     355: aload_1
     356: aconst_null
     357: invokestatic  #95                 // Method asLong:(Ljava/lang/Object;Lorg/apache/kafka/connect/data/Schema;Ljava/lang/Throwable;)J
     360: l2i
     361: i2s
     362: invokestatic  #99                 // Method java/lang/Short.valueOf:(S)Ljava/lang/Short;
     365: areturn
     366: ldc           #101                // String org.apache.kafka.connect.data.Date
     368: aload_0
     369: invokeinterface #77,  1           // InterfaceMethod org/apache/kafka/connect/data/Schema.name:()Ljava/lang/String;
     374: invokevirtual #78                 // Method java/lang/String.equals:(Ljava/lang/Object;)Z
     377: ifeq          489
     380: aload_2
     381: instanceof    #19                 // class java/lang/String
     384: ifeq          402
     387: aload_2
     388: invokevirtual #84                 // Method java/lang/Object.toString:()Ljava/lang/String;
     391: invokestatic  #93                 // Method parseString:(Ljava/lang/String;)Lorg/apache/kafka/connect/data/SchemaAndValue;
     394: astore        4
     396: aload         4
     398: invokevirtual #94                 // Method org/apache/kafka/connect/data/SchemaAndValue.value:()Ljava/lang/Object;
     401: astore_2
     402: aload_2
     403: instanceof    #27                 // class java/util/Date
     406: ifeq          473
     409: aload_1
     410: ifnull        471
     413: aload_1
     414: invokeinterface #77,  1           // InterfaceMethod org/apache/kafka/connect/data/Schema.name:()Ljava/lang/String;
     419: astore        4
     421: ldc           #101                // String org.apache.kafka.connect.data.Date
     423: aload         4
     425: invokevirtual #78                 // Method java/lang/String.equals:(Ljava/lang/Object;)Z
     428: ifeq          433
     431: aload_2
     432: areturn
     433: ldc           #103                // String org.apache.kafka.connect.data.Timestamp
     435: aload         4
     437: invokevirtual #78                 // Method java/lang/String.equals:(Ljava/lang/Object;)Z
     440: ifeq          468
     443: aload_2
     444: checkcast     #27                 // class java/util/Date
     447: invokevirtual #104                // Method java/util/Date.getTime:()J
     450: lstore        5
     452: lload         5
     454: ldc2_w        #105                // long 86400000l
     457: ldiv
     458: l2i
     459: istore        7
     461: aload_0
     462: iload         7
     464: invokestatic  #107                // Method org/apache/kafka/connect/data/Date.toLogical:(Lorg/apache/kafka/connect/data/Schema;I)Ljava/util/Date;
     467: areturn
     468: goto          473
     471: aload_2
     472: areturn
     473: aload_2
     474: aload_1
     475: aconst_null
     476: invokestatic  #95                 // Method asLong:(Ljava/lang/Object;Lorg/apache/kafka/connect/data/Schema;Ljava/lang/Throwable;)J
     479: lstore        4
     481: aload_0
     482: lload         4
     484: l2i
     485: invokestatic  #107                // Method org/apache/kafka/connect/data/Date.toLogical:(Lorg/apache/kafka/connect/data/Schema;I)Ljava/util/Date;
     488: areturn
     489: ldc           #109                // String org.apache.kafka.connect.data.Time
     491: aload_0
     492: invokeinterface #77,  1           // InterfaceMethod org/apache/kafka/connect/data/Schema.name:()Ljava/lang/String;
     497: invokevirtual #78                 // Method java/lang/String.equals:(Ljava/lang/Object;)Z
     500: ifeq          638
     503: aload_2
     504: instanceof    #19                 // class java/lang/String
     507: ifeq          525
     510: aload_2
     511: invokevirtual #84                 // Method java/lang/Object.toString:()Ljava/lang/String;
     514: invokestatic  #93                 // Method parseString:(Ljava/lang/String;)Lorg/apache/kafka/connect/data/SchemaAndValue;
     517: astore        4
     519: aload         4
     521: invokevirtual #94                 // Method org/apache/kafka/connect/data/SchemaAndValue.value:()Ljava/lang/Object;
     524: astore_2
     525: aload_2
     526: instanceof    #27                 // class java/util/Date
     529: ifeq          622
     532: aload_1
     533: ifnull        620
     536: aload_1
     537: invokeinterface #77,  1           // InterfaceMethod org/apache/kafka/connect/data/Schema.name:()Ljava/lang/String;
     542: astore        4
     544: ldc           #109                // String org.apache.kafka.connect.data.Time
     546: aload         4
     548: invokevirtual #78                 // Method java/lang/String.equals:(Ljava/lang/Object;)Z
     551: ifeq          556
     554: aload_2
     555: areturn
     556: ldc           #103                // String org.apache.kafka.connect.data.Timestamp
     558: aload         4
     560: invokevirtual #78                 // Method java/lang/String.equals:(Ljava/lang/Object;)Z
     563: ifeq          617
     566: getstatic     #110                // Field UTC:Ljava/util/TimeZone;
     569: invokestatic  #111                // Method java/util/Calendar.getInstance:(Ljava/util/TimeZone;)Ljava/util/Calendar;
     572: astore        5
     574: aload         5
     576: aload_2
     577: checkcast     #27                 // class java/util/Date
     580: invokevirtual #112                // Method java/util/Calendar.setTime:(Ljava/util/Date;)V
     583: aload         5
     585: iconst_1
     586: sipush        1970
     589: invokevirtual #114                // Method java/util/Calendar.set:(II)V
     592: aload         5
     594: iconst_2
     595: iconst_0
     596: invokevirtual #114                // Method java/util/Calendar.set:(II)V
     599: aload         5
     601: iconst_5
     602: iconst_1
     603: invokevirtual #114                // Method java/util/Calendar.set:(II)V
     606: aload_0
     607: aload         5
     609: invokevirtual #115                // Method java/util/Calendar.getTimeInMillis:()J
     612: l2i
     613: invokestatic  #116                // Method org/apache/kafka/connect/data/Time.toLogical:(Lorg/apache/kafka/connect/data/Schema;I)Ljava/util/Date;
     616: areturn
     617: goto          622
     620: aload_2
     621: areturn
     622: aload_2
     623: aload_1
     624: aconst_null
     625: invokestatic  #95                 // Method asLong:(Ljava/lang/Object;Lorg/apache/kafka/connect/data/Schema;Ljava/lang/Throwable;)J
     628: lstore        4
     630: aload_0
     631: lload         4
     633: l2i
     634: invokestatic  #116                // Method org/apache/kafka/connect/data/Time.toLogical:(Lorg/apache/kafka/connect/data/Schema;I)Ljava/util/Date;
     637: areturn
     638: aload_2
     639: instanceof    #11                 // class java/lang/Integer
     642: ifeq          647
     645: aload_2
     646: areturn
     647: aload_2
     648: aload_1
     649: aconst_null
     650: invokestatic  #95                 // Method asLong:(Ljava/lang/Object;Lorg/apache/kafka/connect/data/Schema;Ljava/lang/Throwable;)J
     653: l2i
     654: invokestatic  #117                // Method java/lang/Integer.valueOf:(I)Ljava/lang/Integer;
     657: areturn
     658: ldc           #103                // String org.apache.kafka.connect.data.Timestamp
     660: aload_0
     661: invokeinterface #77,  1           // InterfaceMethod org/apache/kafka/connect/data/Schema.name:()Ljava/lang/String;
     666: invokevirtual #78                 // Method java/lang/String.equals:(Ljava/lang/Object;)Z
     669: ifeq          811
     672: aload_2
     673: instanceof    #19                 // class java/lang/String
     676: ifeq          694
     679: aload_2
     680: invokevirtual #84                 // Method java/lang/Object.toString:()Ljava/lang/String;
     683: invokestatic  #93                 // Method parseString:(Ljava/lang/String;)Lorg/apache/kafka/connect/data/SchemaAndValue;
     686: astore        4
     688: aload         4
     690: invokevirtual #94                 // Method org/apache/kafka/connect/data/SchemaAndValue.value:()Ljava/lang/Object;
     693: astore_2
     694: aload_2
     695: instanceof    #27                 // class java/util/Date
     698: ifeq          796
     701: aload_2
     702: checkcast     #27                 // class java/util/Date
     705: astore        4
     707: aload_1
     708: ifnull        794
     711: aload_1
     712: invokeinterface #77,  1           // InterfaceMethod org/apache/kafka/connect/data/Schema.name:()Ljava/lang/String;
     717: astore        5
     719: ldc           #101                // String org.apache.kafka.connect.data.Date
     721: aload         5
     723: invokevirtual #78                 // Method java/lang/String.equals:(Ljava/lang/Object;)Z
     726: ifeq          753
     729: aload_1
     730: aload         4
     732: invokestatic  #118                // Method org/apache/kafka/connect/data/Date.fromLogical:(Lorg/apache/kafka/connect/data/Schema;Ljava/util/Date;)I
     735: istore        6
     737: iload         6
     739: i2l
     740: ldc2_w        #105                // long 86400000l
     743: lmul
     744: lstore        7
     746: aload_0
     747: lload         7
     749: invokestatic  #119                // Method org/apache/kafka/connect/data/Timestamp.toLogical:(Lorg/apache/kafka/connect/data/Schema;J)Ljava/util/Date;
     752: areturn
     753: ldc           #109                // String org.apache.kafka.connect.data.Time
     755: aload         5
     757: invokevirtual #78                 // Method java/lang/String.equals:(Ljava/lang/Object;)Z
     760: ifeq          779
     763: aload_1
     764: aload         4
     766: invokestatic  #120                // Method org/apache/kafka/connect/data/Time.fromLogical:(Lorg/apache/kafka/connect/data/Schema;Ljava/util/Date;)I
     769: i2l
     770: lstore        6
     772: aload_0
     773: lload         6
     775: invokestatic  #119                // Method org/apache/kafka/connect/data/Timestamp.toLogical:(Lorg/apache/kafka/connect/data/Schema;J)Ljava/util/Date;
     778: areturn
     779: ldc           #103                // String org.apache.kafka.connect.data.Timestamp
     781: aload         5
     783: invokevirtual #78                 // Method java/lang/String.equals:(Ljava/lang/Object;)Z
     786: ifeq          791
     789: aload_2
     790: areturn
     791: goto          796
     794: aload_2
     795: areturn
     796: aload_2
     797: aload_1
     798: aconst_null
     799: invokestatic  #95                 // Method asLong:(Ljava/lang/Object;Lorg/apache/kafka/connect/data/Schema;Ljava/lang/Throwable;)J
     802: lstore        4
     804: aload_0
     805: lload         4
     807: invokestatic  #119                // Method org/apache/kafka/connect/data/Timestamp.toLogical:(Lorg/apache/kafka/connect/data/Schema;J)Ljava/util/Date;
     810: areturn
     811: aload_2
     812: instanceof    #13                 // class java/lang/Long
     815: ifeq          820
     818: aload_2
     819: areturn
     820: aload_2
     821: aload_1
     822: aconst_null
     823: invokestatic  #95                 // Method asLong:(Ljava/lang/Object;Lorg/apache/kafka/connect/data/Schema;Ljava/lang/Throwable;)J
     826: invokestatic  #121                // Method java/lang/Long.valueOf:(J)Ljava/lang/Long;
     829: areturn
     830: aload_2
     831: instanceof    #15                 // class java/lang/Float
     834: ifeq          839
     837: aload_2
     838: areturn
     839: aload_2
     840: aload_1
     841: aconst_null
     842: invokestatic  #122                // Method asDouble:(Ljava/lang/Object;Lorg/apache/kafka/connect/data/Schema;Ljava/lang/Throwable;)D
     845: d2f
     846: invokestatic  #123                // Method java/lang/Float.valueOf:(F)Ljava/lang/Float;
     849: areturn
     850: aload_2
     851: instanceof    #17                 // class java/lang/Double
     854: ifeq          859
     857: aload_2
     858: areturn
     859: aload_2
     860: aload_1
     861: aconst_null
     862: invokestatic  #122                // Method asDouble:(Ljava/lang/Object;Lorg/apache/kafka/connect/data/Schema;Ljava/lang/Throwable;)D
     865: invokestatic  #87                 // Method java/lang/Double.valueOf:(D)Ljava/lang/Double;
     868: areturn
     869: aload_2
     870: instanceof    #19                 // class java/lang/String
     873: ifeq          891
     876: aload_2
     877: invokevirtual #84                 // Method java/lang/Object.toString:()Ljava/lang/String;
     880: invokestatic  #93                 // Method parseString:(Ljava/lang/String;)Lorg/apache/kafka/connect/data/SchemaAndValue;
     883: astore        4
     885: aload         4
     887: invokevirtual #94                 // Method org/apache/kafka/connect/data/SchemaAndValue.value:()Ljava/lang/Object;
     890: astore_2
     891: aload_2
     892: instanceof    #21                 // class java/util/List
     895: ifeq          947
     898: aload_2
     899: areturn
     900: aload_2
     901: instanceof    #19                 // class java/lang/String
     904: ifeq          922
     907: aload_2
     908: invokevirtual #84                 // Method java/lang/Object.toString:()Ljava/lang/String;
     911: invokestatic  #93                 // Method parseString:(Ljava/lang/String;)Lorg/apache/kafka/connect/data/SchemaAndValue;
     914: astore        4
     916: aload         4
     918: invokevirtual #94                 // Method org/apache/kafka/connect/data/SchemaAndValue.value:()Ljava/lang/Object;
     921: astore_2
     922: aload_2
     923: instanceof    #23                 // class java/util/Map
     926: ifeq          947
     929: aload_2
     930: areturn
     931: aload_2
     932: instanceof    #25                 // class org/apache/kafka/connect/data/Struct
     935: ifeq          947
     938: aload_2
     939: checkcast     #25                 // class org/apache/kafka/connect/data/Struct
     942: astore        4
     944: aload         4
     946: areturn
     947: new           #69                 // class org/apache/kafka/connect/errors/DataException
     950: dup
     951: new           #89                 // class java/lang/StringBuilder
     954: dup
     955: invokespecial #90                 // Method java/lang/StringBuilder."<init>":()V
     958: ldc           #124                // String Unable to convert
     960: invokevirtual #125                // Method java/lang/StringBuilder.append:(Ljava/lang/String;)Ljava/lang/StringBuilder;
     963: aload_2
     964: invokevirtual #126                // Method java/lang/StringBuilder.append:(Ljava/lang/Object;)Ljava/lang/StringBuilder;
     967: ldc           #127                // String  (
     969: invokevirtual #125                // Method java/lang/StringBuilder.append:(Ljava/lang/String;)Ljava/lang/StringBuilder;
     972: aload_2
     973: invokevirtual #128                // Method java/lang/Object.getClass:()Ljava/lang/Class;
     976: invokevirtual #126                // Method java/lang/StringBuilder.append:(Ljava/lang/Object;)Ljava/lang/StringBuilder;
     979: ldc           #129                // String ) to
     981: invokevirtual #125                // Method java/lang/StringBuilder.append:(Ljava/lang/String;)Ljava/lang/StringBuilder;
     984: aload_0
     985: invokevirtual #126                // Method java/lang/StringBuilder.append:(Ljava/lang/Object;)Ljava/lang/StringBuilder;
     988: invokevirtual #92                 // Method java/lang/StringBuilder.toString:()Ljava/lang/String;
     991: invokespecial #71                 // Method org/apache/kafka/connect/errors/DataException."<init>":(Ljava/lang/String;)V
     994: athrow

  protected static long asLong(java.lang.Object, org.apache.kafka.connect.data.Schema, java.lang.Throwable);
    Code:
       0: aload_0
       1: instanceof    #81                 // class java/lang/Number
       4: ifeq          17
       7: aload_0
       8: checkcast     #81                 // class java/lang/Number
      11: astore_3
      12: aload_3
      13: invokevirtual #130                // Method java/lang/Number.longValue:()J
      16: lreturn
      17: aload_0
      18: instanceof    #19                 // class java/lang/String
      21: ifeq          39
      24: new           #31                 // class java/math/BigDecimal
      27: dup
      28: aload_0
      29: invokevirtual #84                 // Method java/lang/Object.toString:()Ljava/lang/String;
      32: invokespecial #85                 // Method java/math/BigDecimal."<init>":(Ljava/lang/String;)V
      35: invokevirtual #131                // Method java/math/BigDecimal.longValue:()J
      38: lreturn
      39: goto          45
      42: astore_3
      43: aload_3
      44: astore_2
      45: aload_1
      46: ifnull        168
      49: aload_1
      50: invokeinterface #77,  1           // InterfaceMethod org/apache/kafka/connect/data/Schema.name:()Ljava/lang/String;
      55: astore_3
      56: aload_0
      57: instanceof    #27                 // class java/util/Date
      60: ifeq          119
      63: ldc           #101                // String org.apache.kafka.connect.data.Date
      65: aload_3
      66: invokevirtual #78                 // Method java/lang/String.equals:(Ljava/lang/Object;)Z
      69: ifeq          82
      72: aload_1
      73: aload_0
      74: checkcast     #27                 // class java/util/Date
      77: invokestatic  #118                // Method org/apache/kafka/connect/data/Date.fromLogical:(Lorg/apache/kafka/connect/data/Schema;Ljava/util/Date;)I
      80: i2l
      81: lreturn
      82: ldc           #109                // String org.apache.kafka.connect.data.Time
      84: aload_3
      85: invokevirtual #78                 // Method java/lang/String.equals:(Ljava/lang/Object;)Z
      88: ifeq          101
      91: aload_1
      92: aload_0
      93: checkcast     #27                 // class java/util/Date
      96: invokestatic  #120                // Method org/apache/kafka/connect/data/Time.fromLogical:(Lorg/apache/kafka/connect/data/Schema;Ljava/util/Date;)I
      99: i2l
     100: lreturn
     101: ldc           #103                // String org.apache.kafka.connect.data.Timestamp
     103: aload_3
     104: invokevirtual #78                 // Method java/lang/String.equals:(Ljava/lang/Object;)Z
     107: ifeq          119
     110: aload_1
     111: aload_0
     112: checkcast     #27                 // class java/util/Date
     115: invokestatic  #133                // Method org/apache/kafka/connect/data/Timestamp.fromLogical:(Lorg/apache/kafka/connect/data/Schema;Ljava/util/Date;)J
     118: lreturn
     119: new           #69                 // class org/apache/kafka/connect/errors/DataException
     122: dup
     123: new           #89                 // class java/lang/StringBuilder
     126: dup
     127: invokespecial #90                 // Method java/lang/StringBuilder."<init>":()V
     130: ldc           #124                // String Unable to convert
     132: invokevirtual #125                // Method java/lang/StringBuilder.append:(Ljava/lang/String;)Ljava/lang/StringBuilder;
     135: aload_0
     136: invokevirtual #126                // Method java/lang/StringBuilder.append:(Ljava/lang/Object;)Ljava/lang/StringBuilder;
     139: ldc           #127                // String  (
     141: invokevirtual #125                // Method java/lang/StringBuilder.append:(Ljava/lang/String;)Ljava/lang/StringBuilder;
     144: aload_0
     145: invokevirtual #128                // Method java/lang/Object.getClass:()Ljava/lang/Class;
     148: invokevirtual #126                // Method java/lang/StringBuilder.append:(Ljava/lang/Object;)Ljava/lang/StringBuilder;
     151: ldc           #129                // String ) to
     153: invokevirtual #125                // Method java/lang/StringBuilder.append:(Ljava/lang/String;)Ljava/lang/StringBuilder;
     156: aload_1
     157: invokevirtual #126                // Method java/lang/StringBuilder.append:(Ljava/lang/Object;)Ljava/lang/StringBuilder;
     160: invokevirtual #92                 // Method java/lang/StringBuilder.toString:()Ljava/lang/String;
     163: aload_2
     164: invokespecial #134                // Method org/apache/kafka/connect/errors/DataException."<init>":(Ljava/lang/String;Ljava/lang/Throwable;)V
     167: athrow
     168: new           #69                 // class org/apache/kafka/connect/errors/DataException
     171: dup
     172: new           #89                 // class java/lang/StringBuilder
     175: dup
     176: invokespecial #90                 // Method java/lang/StringBuilder."<init>":()V
     179: ldc           #124                // String Unable to convert
     181: invokevirtual #125                // Method java/lang/StringBuilder.append:(Ljava/lang/String;)Ljava/lang/StringBuilder;
     184: aload_0
     185: invokevirtual #126                // Method java/lang/StringBuilder.append:(Ljava/lang/Object;)Ljava/lang/StringBuilder;
     188: ldc           #127                // String  (
     190: invokevirtual #125                // Method java/lang/StringBuilder.append:(Ljava/lang/String;)Ljava/lang/StringBuilder;
     193: aload_0
     194: invokevirtual #128                // Method java/lang/Object.getClass:()Ljava/lang/Class;
     197: invokevirtual #126                // Method java/lang/StringBuilder.append:(Ljava/lang/Object;)Ljava/lang/StringBuilder;
     200: ldc           #135                // String ) to a number
     202: invokevirtual #125                // Method java/lang/StringBuilder.append:(Ljava/lang/String;)Ljava/lang/StringBuilder;
     205: invokevirtual #92                 // Method java/lang/StringBuilder.toString:()Ljava/lang/String;
     208: aload_2
     209: invokespecial #134                // Method org/apache/kafka/connect/errors/DataException."<init>":(Ljava/lang/String;Ljava/lang/Throwable;)V
     212: athrow
    Exception table:
       from    to  target type
           0    16    42   Class java/lang/NumberFormatException
          17    38    42   Class java/lang/NumberFormatException

  protected static double asDouble(java.lang.Object, org.apache.kafka.connect.data.Schema, java.lang.Throwable);
    Code:
       0: aload_0
       1: instanceof    #81                 // class java/lang/Number
       4: ifeq          17
       7: aload_0
       8: checkcast     #81                 // class java/lang/Number
      11: astore_3
      12: aload_3
      13: invokevirtual #82                 // Method java/lang/Number.doubleValue:()D
      16: dreturn
      17: aload_0
      18: instanceof    #19                 // class java/lang/String
      21: ifeq          39
      24: new           #31                 // class java/math/BigDecimal
      27: dup
      28: aload_0
      29: invokevirtual #84                 // Method java/lang/Object.toString:()Ljava/lang/String;
      32: invokespecial #85                 // Method java/math/BigDecimal."<init>":(Ljava/lang/String;)V
      35: invokevirtual #86                 // Method java/math/BigDecimal.doubleValue:()D
      38: dreturn
      39: goto          45
      42: astore_3
      43: aload_3
      44: astore_2
      45: aload_0
      46: aload_1
      47: aload_2
      48: invokestatic  #95                 // Method asLong:(Ljava/lang/Object;Lorg/apache/kafka/connect/data/Schema;Ljava/lang/Throwable;)J
      51: l2d
      52: dreturn
    Exception table:
       from    to  target type
           0    16    42   Class java/lang/NumberFormatException
          17    38    42   Class java/lang/NumberFormatException

  protected static void append(java.lang.StringBuilder, java.lang.Object, boolean);
    Code:
       0: aload_1
       1: ifnonnull     14
       4: aload_0
       5: ldc           #136                // String null
       7: invokevirtual #125                // Method java/lang/StringBuilder.append:(Ljava/lang/String;)Ljava/lang/StringBuilder;
      10: pop
      11: goto          494
      14: aload_1
      15: instanceof    #81                 // class java/lang/Number
      18: ifeq          30
      21: aload_0
      22: aload_1
      23: invokevirtual #126                // Method java/lang/StringBuilder.append:(Ljava/lang/Object;)Ljava/lang/StringBuilder;
      26: pop
      27: goto          494
      30: aload_1
      31: instanceof    #5                  // class java/lang/Boolean
      34: ifeq          46
      37: aload_0
      38: aload_1
      39: invokevirtual #126                // Method java/lang/StringBuilder.append:(Ljava/lang/Object;)Ljava/lang/StringBuilder;
      42: pop
      43: goto          494
      46: aload_1
      47: instanceof    #19                 // class java/lang/String
      50: ifeq          93
      53: iload_2
      54: ifeq          84
      57: aload_1
      58: checkcast     #19                 // class java/lang/String
      61: invokestatic  #137                // Method escape:(Ljava/lang/String;)Ljava/lang/String;
      64: astore_3
      65: aload_0
      66: bipush        34
      68: invokevirtual #138                // Method java/lang/StringBuilder.append:(C)Ljava/lang/StringBuilder;
      71: aload_3
      72: invokevirtual #125                // Method java/lang/StringBuilder.append:(Ljava/lang/String;)Ljava/lang/StringBuilder;
      75: bipush        34
      77: invokevirtual #138                // Method java/lang/StringBuilder.append:(C)Ljava/lang/StringBuilder;
      80: pop
      81: goto          494
      84: aload_0
      85: aload_1
      86: invokevirtual #126                // Method java/lang/StringBuilder.append:(Ljava/lang/Object;)Ljava/lang/StringBuilder;
      89: pop
      90: goto          494
      93: aload_1
      94: instanceof    #40                 // class "[B"
      97: ifeq          146
     100: invokestatic  #139                // Method java/util/Base64.getEncoder:()Ljava/util/Base64$Encoder;
     103: aload_1
     104: checkcast     #40                 // class "[B"
     107: checkcast     #40                 // class "[B"
     110: invokevirtual #140                // Method java/util/Base64$Encoder.encodeToString:([B)Ljava/lang/String;
     113: astore_1
     114: iload_2
     115: ifeq          137
     118: aload_0
     119: bipush        34
     121: invokevirtual #138                // Method java/lang/StringBuilder.append:(C)Ljava/lang/StringBuilder;
     124: aload_1
     125: invokevirtual #126                // Method java/lang/StringBuilder.append:(Ljava/lang/Object;)Ljava/lang/StringBuilder;
     128: bipush        34
     130: invokevirtual #138                // Method java/lang/StringBuilder.append:(C)Ljava/lang/StringBuilder;
     133: pop
     134: goto          494
     137: aload_0
     138: aload_1
     139: invokevirtual #126                // Method java/lang/StringBuilder.append:(Ljava/lang/Object;)Ljava/lang/StringBuilder;
     142: pop
     143: goto          494
     146: aload_1
     147: instanceof    #41                 // class java/nio/ByteBuffer
     150: ifeq          170
     153: aload_1
     154: checkcast     #41                 // class java/nio/ByteBuffer
     157: invokestatic  #141                // Method org/apache/kafka/common/utils/Utils.readBytes:(Ljava/nio/ByteBuffer;)[B
     160: astore_3
     161: aload_0
     162: aload_3
     163: iload_2
     164: invokestatic  #91                 // Method append:(Ljava/lang/StringBuilder;Ljava/lang/Object;Z)V
     167: goto          494
     170: aload_1
     171: instanceof    #21                 // class java/util/List
     174: ifeq          209
     177: aload_1
     178: checkcast     #21                 // class java/util/List
     181: astore_3
     182: aload_0
     183: bipush        91
     185: invokevirtual #138                // Method java/lang/StringBuilder.append:(C)Ljava/lang/StringBuilder;
     188: pop
     189: aload_0
     190: aload_3
     191: invokeinterface #46,  1           // InterfaceMethod java/util/List.iterator:()Ljava/util/Iterator;
     196: invokestatic  #142                // Method appendIterable:(Ljava/lang/StringBuilder;Ljava/util/Iterator;)V
     199: aload_0
     200: bipush        93
     202: invokevirtual #138                // Method java/lang/StringBuilder.append:(C)Ljava/lang/StringBuilder;
     205: pop
     206: goto          494
     209: aload_1
     210: instanceof    #23                 // class java/util/Map
     213: ifeq          253
     216: aload_1
     217: checkcast     #23                 // class java/util/Map
     220: astore_3
     221: aload_0
     222: bipush        123
     224: invokevirtual #138                // Method java/lang/StringBuilder.append:(C)Ljava/lang/StringBuilder;
     227: pop
     228: aload_0
     229: aload_3
     230: invokeinterface #54,  1           // InterfaceMethod java/util/Map.entrySet:()Ljava/util/Set;
     235: invokeinterface #55,  1           // InterfaceMethod java/util/Set.iterator:()Ljava/util/Iterator;
     240: invokestatic  #142                // Method appendIterable:(Ljava/lang/StringBuilder;Ljava/util/Iterator;)V
     243: aload_0
     244: bipush        125
     246: invokevirtual #138                // Method java/lang/StringBuilder.append:(C)Ljava/lang/StringBuilder;
     249: pop
     250: goto          494
     253: aload_1
     254: instanceof    #25                 // class org/apache/kafka/connect/data/Struct
     257: ifeq          376
     260: aload_1
     261: checkcast     #25                 // class org/apache/kafka/connect/data/Struct
     264: astore_3
     265: aload_3
     266: invokevirtual #60                 // Method org/apache/kafka/connect/data/Struct.schema:()Lorg/apache/kafka/connect/data/Schema;
     269: astore        4
     271: iconst_1
     272: istore        5
     274: aload_0
     275: bipush        123
     277: invokevirtual #138                // Method java/lang/StringBuilder.append:(C)Ljava/lang/StringBuilder;
     280: pop
     281: aload         4
     283: invokeinterface #143,  1          // InterfaceMethod org/apache/kafka/connect/data/Schema.fields:()Ljava/util/List;
     288: invokeinterface #46,  1           // InterfaceMethod java/util/List.iterator:()Ljava/util/Iterator;
     293: astore        6
     295: aload         6
     297: invokeinterface #47,  1           // InterfaceMethod java/util/Iterator.hasNext:()Z
     302: ifeq          366
     305: aload         6
     307: invokeinterface #48,  1           // InterfaceMethod java/util/Iterator.next:()Ljava/lang/Object;
     312: checkcast     #144                // class org/apache/kafka/connect/data/Field
     315: astore        7
     317: iload         5
     319: ifeq          328
     322: iconst_0
     323: istore        5
     325: goto          335
     328: aload_0
     329: bipush        44
     331: invokevirtual #138                // Method java/lang/StringBuilder.append:(C)Ljava/lang/StringBuilder;
     334: pop
     335: aload_0
     336: aload         7
     338: invokevirtual #145                // Method org/apache/kafka/connect/data/Field.name:()Ljava/lang/String;
     341: iconst_1
     342: invokestatic  #91                 // Method append:(Ljava/lang/StringBuilder;Ljava/lang/Object;Z)V
     345: aload_0
     346: bipush        58
     348: invokevirtual #138                // Method java/lang/StringBuilder.append:(C)Ljava/lang/StringBuilder;
     351: pop
     352: aload_0
     353: aload_3
     354: aload         7
     356: invokevirtual #146                // Method org/apache/kafka/connect/data/Struct.get:(Lorg/apache/kafka/connect/data/Field;)Ljava/lang/Object;
     359: iconst_1
     360: invokestatic  #91                 // Method append:(Ljava/lang/StringBuilder;Ljava/lang/Object;Z)V
     363: goto          295
     366: aload_0
     367: bipush        125
     369: invokevirtual #138                // Method java/lang/StringBuilder.append:(C)Ljava/lang/StringBuilder;
     372: pop
     373: goto          494
     376: aload_1
     377: instanceof    #56                 // class java/util/Map$Entry
     380: ifeq          420
     383: aload_1
     384: checkcast     #56                 // class java/util/Map$Entry
     387: astore_3
     388: aload_0
     389: aload_3
     390: invokeinterface #57,  1           // InterfaceMethod java/util/Map$Entry.getKey:()Ljava/lang/Object;
     395: iconst_1
     396: invokestatic  #91                 // Method append:(Ljava/lang/StringBuilder;Ljava/lang/Object;Z)V
     399: aload_0
     400: bipush        58
     402: invokevirtual #138                // Method java/lang/StringBuilder.append:(C)Ljava/lang/StringBuilder;
     405: pop
     406: aload_0
     407: aload_3
     408: invokeinterface #58,  1           // InterfaceMethod java/util/Map$Entry.getValue:()Ljava/lang/Object;
     413: iconst_1
     414: invokestatic  #91                 // Method append:(Ljava/lang/StringBuilder;Ljava/lang/Object;Z)V
     417: goto          494
     420: aload_1
     421: instanceof    #27                 // class java/util/Date
     424: ifeq          452
     427: aload_1
     428: checkcast     #27                 // class java/util/Date
     431: astore_3
     432: aload_3
     433: invokestatic  #147                // Method dateFormatFor:(Ljava/util/Date;)Ljava/text/DateFormat;
     436: aload_3
     437: invokevirtual #148                // Method java/text/DateFormat.format:(Ljava/util/Date;)Ljava/lang/String;
     440: astore        4
     442: aload_0
     443: aload         4
     445: invokevirtual #125                // Method java/lang/StringBuilder.append:(Ljava/lang/String;)Ljava/lang/StringBuilder;
     448: pop
     449: goto          494
     452: new           #69                 // class org/apache/kafka/connect/errors/DataException
     455: dup
     456: new           #89                 // class java/lang/StringBuilder
     459: dup
     460: invokespecial #90                 // Method java/lang/StringBuilder."<init>":()V
     463: ldc           #149                // String Failed to serialize unexpected value type
     465: invokevirtual #125                // Method java/lang/StringBuilder.append:(Ljava/lang/String;)Ljava/lang/StringBuilder;
     468: aload_1
     469: invokevirtual #128                // Method java/lang/Object.getClass:()Ljava/lang/Class;
     472: invokevirtual #150                // Method java/lang/Class.getName:()Ljava/lang/String;
     475: invokevirtual #125                // Method java/lang/StringBuilder.append:(Ljava/lang/String;)Ljava/lang/StringBuilder;
     478: ldc           #151                // String :
     480: invokevirtual #125                // Method java/lang/StringBuilder.append:(Ljava/lang/String;)Ljava/lang/StringBuilder;
     483: aload_1
     484: invokevirtual #126                // Method java/lang/StringBuilder.append:(Ljava/lang/Object;)Ljava/lang/StringBuilder;
     487: invokevirtual #92                 // Method java/lang/StringBuilder.toString:()Ljava/lang/String;
     490: invokespecial #71                 // Method org/apache/kafka/connect/errors/DataException."<init>":(Ljava/lang/String;)V
     493: athrow
     494: return

  protected static void appendIterable(java.lang.StringBuilder, java.util.Iterator<?>);
    Code:
       0: aload_1
       1: invokeinterface #47,  1           // InterfaceMethod java/util/Iterator.hasNext:()Z
       6: ifeq          50
       9: aload_0
      10: aload_1
      11: invokeinterface #48,  1           // InterfaceMethod java/util/Iterator.next:()Ljava/lang/Object;
      16: iconst_1
      17: invokestatic  #91                 // Method append:(Ljava/lang/StringBuilder;Ljava/lang/Object;Z)V
      20: aload_1
      21: invokeinterface #47,  1           // InterfaceMethod java/util/Iterator.hasNext:()Z
      26: ifeq          50
      29: aload_0
      30: bipush        44
      32: invokevirtual #138                // Method java/lang/StringBuilder.append:(C)Ljava/lang/StringBuilder;
      35: pop
      36: aload_0
      37: aload_1
      38: invokeinterface #48,  1           // InterfaceMethod java/util/Iterator.next:()Ljava/lang/Object;
      43: iconst_1
      44: invokestatic  #91                 // Method append:(Ljava/lang/StringBuilder;Ljava/lang/Object;Z)V
      47: goto          20
      50: return

  protected static java.lang.String escape(java.lang.String);
    Code:
       0: getstatic     #152                // Field TWO_BACKSLASHES:Ljava/util/regex/Pattern;
       3: aload_0
       4: invokevirtual #153                // Method java/util/regex/Pattern.matcher:(Ljava/lang/CharSequence;)Ljava/util/regex/Matcher;
       7: ldc           #154                // String \\\\\\\\
       9: invokevirtual #155                // Method java/util/regex/Matcher.replaceAll:(Ljava/lang/String;)Ljava/lang/String;
      12: astore_1
      13: getstatic     #156                // Field DOUBLEQOUTE:Ljava/util/regex/Pattern;
      16: aload_1
      17: invokevirtual #153                // Method java/util/regex/Pattern.matcher:(Ljava/lang/CharSequence;)Ljava/util/regex/Matcher;
      20: ldc           #157                // String \\\\\"
      22: invokevirtual #155                // Method java/util/regex/Matcher.replaceAll:(Ljava/lang/String;)Ljava/lang/String;
      25: areturn

  public static java.text.DateFormat dateFormatFor(java.util.Date);
    Code:
       0: aload_0
       1: invokevirtual #104                // Method java/util/Date.getTime:()J
       4: ldc2_w        #105                // long 86400000l
       7: lcmp
       8: ifge          21
      11: new           #158                // class java/text/SimpleDateFormat
      14: dup
      15: ldc           #159                // String HH:mm:ss.SSS\'Z\'
      17: invokespecial #160                // Method java/text/SimpleDateFormat."<init>":(Ljava/lang/String;)V
      20: areturn
      21: aload_0
      22: invokevirtual #104                // Method java/util/Date.getTime:()J
      25: ldc2_w        #105                // long 86400000l
      28: lrem
      29: lconst_0
      30: lcmp
      31: ifne          44
      34: new           #158                // class java/text/SimpleDateFormat
      37: dup
      38: ldc           #161                // String yyyy-MM-dd
      40: invokespecial #160                // Method java/text/SimpleDateFormat."<init>":(Ljava/lang/String;)V
      43: areturn
      44: new           #158                // class java/text/SimpleDateFormat
      47: dup
      48: ldc           #162                // String yyyy-MM-dd\'T\'HH:mm:ss.SSS\'Z\'
      50: invokespecial #160                // Method java/text/SimpleDateFormat."<init>":(Ljava/lang/String;)V
      53: areturn

  protected static boolean canParseSingleTokenLiteral(org.apache.kafka.connect.data.Values$Parser, boolean, java.lang.String);
    Code:
       0: aload_0
       1: invokevirtual #163                // Method org/apache/kafka/connect/data/Values$Parser.mark:()I
       4: istore_3
       5: aload_0
       6: aload_2
       7: invokevirtual #164                // Method org/apache/kafka/connect/data/Values$Parser.canConsume:(Ljava/lang/String;)Z
      10: ifeq          26
      13: iload_1
      14: ifne          24
      17: aload_0
      18: invokevirtual #165                // Method org/apache/kafka/connect/data/Values$Parser.hasNext:()Z
      21: ifne          26
      24: iconst_1
      25: ireturn
      26: aload_0
      27: iload_3
      28: invokevirtual #166                // Method org/apache/kafka/connect/data/Values$Parser.rewindTo:(I)V
      31: iconst_0
      32: ireturn

  protected static org.apache.kafka.connect.data.SchemaAndValue parse(org.apache.kafka.connect.data.Values$Parser, boolean) throws java.util.NoSuchElementException;
    Code:
       0: aload_0
       1: invokevirtual #165                // Method org/apache/kafka/connect/data/Values$Parser.hasNext:()Z
       4: ifne          9
       7: aconst_null
       8: areturn
       9: iload_1
      10: ifeq          113
      13: aload_0
      14: ldc           #167                // String \"
      16: invokevirtual #164                // Method org/apache/kafka/connect/data/Values$Parser.canConsume:(Ljava/lang/String;)Z
      19: ifeq          113
      22: new           #89                 // class java/lang/StringBuilder
      25: dup
      26: invokespecial #90                 // Method java/lang/StringBuilder."<init>":()V
      29: astore_2
      30: aload_0
      31: invokevirtual #165                // Method org/apache/kafka/connect/data/Values$Parser.hasNext:()Z
      34: ifeq          61
      37: aload_0
      38: ldc           #167                // String \"
      40: invokevirtual #164                // Method org/apache/kafka/connect/data/Values$Parser.canConsume:(Ljava/lang/String;)Z
      43: ifeq          49
      46: goto          61
      49: aload_2
      50: aload_0
      51: invokevirtual #168                // Method org/apache/kafka/connect/data/Values$Parser.next:()Ljava/lang/String;
      54: invokevirtual #125                // Method java/lang/StringBuilder.append:(Ljava/lang/String;)Ljava/lang/StringBuilder;
      57: pop
      58: goto          30
      61: aload_2
      62: invokevirtual #92                 // Method java/lang/StringBuilder.toString:()Ljava/lang/String;
      65: astore_3
      66: aload_3
      67: invokestatic  #93                 // Method parseString:(Ljava/lang/String;)Lorg/apache/kafka/connect/data/SchemaAndValue;
      70: astore        4
      72: aload         4
      74: ifnull        101
      77: getstatic     #169                // Field TEMPORAL_LOGICAL_TYPE_NAMES:Ljava/util/Set;
      80: aload         4
      82: invokevirtual #170                // Method org/apache/kafka/connect/data/SchemaAndValue.schema:()Lorg/apache/kafka/connect/data/Schema;
      85: invokeinterface #77,  1           // InterfaceMethod org/apache/kafka/connect/data/Schema.name:()Ljava/lang/String;
      90: invokeinterface #171,  2          // InterfaceMethod java/util/Set.contains:(Ljava/lang/Object;)Z
      95: ifeq          101
      98: aload         4
     100: areturn
     101: new           #63                 // class org/apache/kafka/connect/data/SchemaAndValue
     104: dup
     105: getstatic     #32                 // Field org/apache/kafka/connect/data/Schema.STRING_SCHEMA:Lorg/apache/kafka/connect/data/Schema;
     108: aload_3
     109: invokespecial #64                 // Method org/apache/kafka/connect/data/SchemaAndValue."<init>":(Lorg/apache/kafka/connect/data/Schema;Ljava/lang/Object;)V
     112: areturn
     113: aload_0
     114: iload_1
     115: ldc           #136                // String null
     117: invokestatic  #172                // Method canParseSingleTokenLiteral:(Lorg/apache/kafka/connect/data/Values$Parser;ZLjava/lang/String;)Z
     120: ifeq          125
     123: aconst_null
     124: areturn
     125: aload_0
     126: iload_1
     127: getstatic     #173                // Field TRUE_LITERAL:Ljava/lang/String;
     130: invokestatic  #172                // Method canParseSingleTokenLiteral:(Lorg/apache/kafka/connect/data/Values$Parser;ZLjava/lang/String;)Z
     133: ifeq          140
     136: getstatic     #174                // Field TRUE_SCHEMA_AND_VALUE:Lorg/apache/kafka/connect/data/SchemaAndValue;
     139: areturn
     140: aload_0
     141: iload_1
     142: getstatic     #175                // Field FALSE_LITERAL:Ljava/lang/String;
     145: invokestatic  #172                // Method canParseSingleTokenLiteral:(Lorg/apache/kafka/connect/data/Values$Parser;ZLjava/lang/String;)Z
     148: ifeq          155
     151: getstatic     #176                // Field FALSE_SCHEMA_AND_VALUE:Lorg/apache/kafka/connect/data/SchemaAndValue;
     154: areturn
     155: aload_0
     156: invokevirtual #163                // Method org/apache/kafka/connect/data/Values$Parser.mark:()I
     159: istore_2
     160: aload_0
     161: ldc           #177                // String [
     163: invokevirtual #164                // Method org/apache/kafka/connect/data/Values$Parser.canConsume:(Ljava/lang/String;)Z
     166: ifeq          434
     169: new           #178                // class java/util/ArrayList
     172: dup
     173: invokespecial #179                // Method java/util/ArrayList."<init>":()V
     176: astore_3
     177: aconst_null
     178: astore        4
     180: aload_0
     181: invokevirtual #165                // Method org/apache/kafka/connect/data/Values$Parser.hasNext:()Z
     184: ifeq          362
     187: aload_0
     188: ldc           #180                // String ]
     190: invokevirtual #164                // Method org/apache/kafka/connect/data/Values$Parser.canConsume:(Ljava/lang/String;)Z
     193: ifeq          240
     196: aload         4
     198: ifnull        221
     201: aload         4
     203: invokestatic  #51                 // Method org/apache/kafka/connect/data/SchemaBuilder.array:(Lorg/apache/kafka/connect/data/Schema;)Lorg/apache/kafka/connect/data/SchemaBuilder;
     206: invokevirtual #181                // Method org/apache/kafka/connect/data/SchemaBuilder.schema:()Lorg/apache/kafka/connect/data/Schema;
     209: astore        5
     211: aload         5
     213: aload_3
     214: invokestatic  #182                // Method alignListEntriesWithSchema:(Lorg/apache/kafka/connect/data/Schema;Ljava/util/List;)Ljava/util/List;
     217: astore_3
     218: goto          229
     221: invokestatic  #183                // Method org/apache/kafka/connect/data/SchemaBuilder.arrayOfNull:()Lorg/apache/kafka/connect/data/SchemaBuilder;
     224: invokevirtual #52                 // Method org/apache/kafka/connect/data/SchemaBuilder.build:()Lorg/apache/kafka/connect/data/Schema;
     227: astore        5
     229: new           #63                 // class org/apache/kafka/connect/data/SchemaAndValue
     232: dup
     233: aload         5
     235: aload_3
     236: invokespecial #64                 // Method org/apache/kafka/connect/data/SchemaAndValue."<init>":(Lorg/apache/kafka/connect/data/Schema;Ljava/lang/Object;)V
     239: areturn
     240: aload_0
     241: ldc           #184                // String ,
     243: invokevirtual #164                // Method org/apache/kafka/connect/data/Values$Parser.canConsume:(Ljava/lang/String;)Z
     246: ifeq          279
     249: new           #69                 // class org/apache/kafka/connect/errors/DataException
     252: dup
     253: new           #89                 // class java/lang/StringBuilder
     256: dup
     257: invokespecial #90                 // Method java/lang/StringBuilder."<init>":()V
     260: ldc           #185                // String Unable to parse an empty array element:
     262: invokevirtual #125                // Method java/lang/StringBuilder.append:(Ljava/lang/String;)Ljava/lang/StringBuilder;
     265: aload_0
     266: invokevirtual #186                // Method org/apache/kafka/connect/data/Values$Parser.original:()Ljava/lang/String;
     269: invokevirtual #125                // Method java/lang/StringBuilder.append:(Ljava/lang/String;)Ljava/lang/StringBuilder;
     272: invokevirtual #92                 // Method java/lang/StringBuilder.toString:()Ljava/lang/String;
     275: invokespecial #71                 // Method org/apache/kafka/connect/errors/DataException."<init>":(Ljava/lang/String;)V
     278: athrow
     279: aload_0
     280: iconst_1
     281: invokestatic  #67                 // Method parse:(Lorg/apache/kafka/connect/data/Values$Parser;Z)Lorg/apache/kafka/connect/data/SchemaAndValue;
     284: astore        5
     286: aload         4
     288: aload         5
     290: invokestatic  #187                // Method commonSchemaFor:(Lorg/apache/kafka/connect/data/Schema;Lorg/apache/kafka/connect/data/SchemaAndValue;)Lorg/apache/kafka/connect/data/Schema;
     293: astore        4
     295: aload_3
     296: aload         5
     298: ifnull        309
     301: aload         5
     303: invokevirtual #94                 // Method org/apache/kafka/connect/data/SchemaAndValue.value:()Ljava/lang/Object;
     306: goto          310
     309: aconst_null
     310: invokeinterface #188,  2          // InterfaceMethod java/util/List.add:(Ljava/lang/Object;)Z
     315: pop
     316: aload_0
     317: invokevirtual #163                // Method org/apache/kafka/connect/data/Values$Parser.mark:()I
     320: istore        6
     322: aload_0
     323: ldc           #180                // String ]
     325: invokevirtual #164                // Method org/apache/kafka/connect/data/Values$Parser.canConsume:(Ljava/lang/String;)Z
     328: ifeq          340
     331: aload_0
     332: iload         6
     334: invokevirtual #166                // Method org/apache/kafka/connect/data/Values$Parser.rewindTo:(I)V
     337: goto          359
     340: aload_0
     341: ldc           #184                // String ,
     343: invokevirtual #164                // Method org/apache/kafka/connect/data/Values$Parser.canConsume:(Ljava/lang/String;)Z
     346: ifne          359
     349: new           #69                 // class org/apache/kafka/connect/errors/DataException
     352: dup
     353: ldc           #189                // String Array elements missing \',\' delimiter
     355: invokespecial #71                 // Method org/apache/kafka/connect/errors/DataException."<init>":(Ljava/lang/String;)V
     358: athrow
     359: goto          180
     362: ldc           #184                // String ,
     364: aload_0
     365: invokevirtual #190                // Method org/apache/kafka/connect/data/Values$Parser.previous:()Ljava/lang/String;
     368: invokevirtual #78                 // Method java/lang/String.equals:(Ljava/lang/Object;)Z
     371: ifeq          404
     374: new           #69                 // class org/apache/kafka/connect/errors/DataException
     377: dup
     378: new           #89                 // class java/lang/StringBuilder
     381: dup
     382: invokespecial #90                 // Method java/lang/StringBuilder."<init>":()V
     385: ldc           #191                // String Array is missing element after \',\':
     387: invokevirtual #125                // Method java/lang/StringBuilder.append:(Ljava/lang/String;)Ljava/lang/StringBuilder;
     390: aload_0
     391: invokevirtual #186                // Method org/apache/kafka/connect/data/Values$Parser.original:()Ljava/lang/String;
     394: invokevirtual #125                // Method java/lang/StringBuilder.append:(Ljava/lang/String;)Ljava/lang/StringBuilder;
     397: invokevirtual #92                 // Method java/lang/StringBuilder.toString:()Ljava/lang/String;
     400: invokespecial #71                 // Method org/apache/kafka/connect/errors/DataException."<init>":(Ljava/lang/String;)V
     403: athrow
     404: new           #69                 // class org/apache/kafka/connect/errors/DataException
     407: dup
     408: new           #89                 // class java/lang/StringBuilder
     411: dup
     412: invokespecial #90                 // Method java/lang/StringBuilder."<init>":()V
     415: ldc           #192                // String Array is missing terminating \']\':
     417: invokevirtual #125                // Method java/lang/StringBuilder.append:(Ljava/lang/String;)Ljava/lang/StringBuilder;
     420: aload_0
     421: invokevirtual #186                // Method org/apache/kafka/connect/data/Values$Parser.original:()Ljava/lang/String;
     424: invokevirtual #125                // Method java/lang/StringBuilder.append:(Ljava/lang/String;)Ljava/lang/StringBuilder;
     427: invokevirtual #92                 // Method java/lang/StringBuilder.toString:()Ljava/lang/String;
     430: invokespecial #71                 // Method org/apache/kafka/connect/errors/DataException."<init>":(Ljava/lang/String;)V
     433: athrow
     434: aload_0
     435: ldc           #193                // String {
     437: invokevirtual #164                // Method org/apache/kafka/connect/data/Values$Parser.canConsume:(Ljava/lang/String;)Z
     440: ifeq          823
     443: new           #194                // class java/util/LinkedHashMap
     446: dup
     447: invokespecial #195                // Method java/util/LinkedHashMap."<init>":()V
     450: astore_3
     451: aconst_null
     452: astore        4
     454: aconst_null
     455: astore        5
     457: aload_0
     458: invokevirtual #165                // Method org/apache/kafka/connect/data/Values$Parser.hasNext:()Z
     461: ifeq          751
     464: aload_0
     465: ldc           #196                // String }
     467: invokevirtual #164                // Method org/apache/kafka/connect/data/Values$Parser.canConsume:(Ljava/lang/String;)Z
     470: ifeq          546
     473: aload         4
     475: ifnull        505
     478: aload         5
     480: ifnull        505
     483: aload         4
     485: aload         5
     487: invokestatic  #59                 // Method org/apache/kafka/connect/data/SchemaBuilder.map:(Lorg/apache/kafka/connect/data/Schema;Lorg/apache/kafka/connect/data/Schema;)Lorg/apache/kafka/connect/data/SchemaBuilder;
     490: invokevirtual #52                 // Method org/apache/kafka/connect/data/SchemaBuilder.build:()Lorg/apache/kafka/connect/data/Schema;
     493: astore        6
     495: aload         6
     497: aload_3
     498: invokestatic  #197                // Method alignMapKeysAndValuesWithSchema:(Lorg/apache/kafka/connect/data/Schema;Ljava/util/Map;)Ljava/util/Map;
     501: astore_3
     502: goto          535
     505: aload         4
     507: ifnull        527
     510: aload         4
     512: invokestatic  #198                // Method org/apache/kafka/connect/data/SchemaBuilder.mapWithNullValues:(Lorg/apache/kafka/connect/data/Schema;)Lorg/apache/kafka/connect/data/SchemaBuilder;
     515: astore        6
     517: aload         6
     519: aload_3
     520: invokestatic  #199                // Method alignMapKeysWithSchema:(Lorg/apache/kafka/connect/data/Schema;Ljava/util/Map;)Ljava/util/Map;
     523: astore_3
     524: goto          535
     527: invokestatic  #200                // Method org/apache/kafka/connect/data/SchemaBuilder.mapOfNull:()Lorg/apache/kafka/connect/data/SchemaBuilder;
     530: invokevirtual #52                 // Method org/apache/kafka/connect/data/SchemaBuilder.build:()Lorg/apache/kafka/connect/data/Schema;
     533: astore        6
     535: new           #63                 // class org/apache/kafka/connect/data/SchemaAndValue
     538: dup
     539: aload         6
     541: aload_3
     542: invokespecial #64                 // Method org/apache/kafka/connect/data/SchemaAndValue."<init>":(Lorg/apache/kafka/connect/data/Schema;Ljava/lang/Object;)V
     545: areturn
     546: aload_0
     547: ldc           #184                // String ,
     549: invokevirtual #164                // Method org/apache/kafka/connect/data/Values$Parser.canConsume:(Ljava/lang/String;)Z
     552: ifeq          585
     555: new           #69                 // class org/apache/kafka/connect/errors/DataException
     558: dup
     559: new           #89                 // class java/lang/StringBuilder
     562: dup
     563: invokespecial #90                 // Method java/lang/StringBuilder."<init>":()V
     566: ldc           #201                // String Unable to parse a map entry with no key or value:
     568: invokevirtual #125                // Method java/lang/StringBuilder.append:(Ljava/lang/String;)Ljava/lang/StringBuilder;
     571: aload_0
     572: invokevirtual #186                // Method org/apache/kafka/connect/data/Values$Parser.original:()Ljava/lang/String;
     575: invokevirtual #125                // Method java/lang/StringBuilder.append:(Ljava/lang/String;)Ljava/lang/StringBuilder;
     578: invokevirtual #92                 // Method java/lang/StringBuilder.toString:()Ljava/lang/String;
     581: invokespecial #71                 // Method org/apache/kafka/connect/errors/DataException."<init>":(Ljava/lang/String;)V
     584: athrow
     585: aload_0
     586: iconst_1
     587: invokestatic  #67                 // Method parse:(Lorg/apache/kafka/connect/data/Values$Parser;Z)Lorg/apache/kafka/connect/data/SchemaAndValue;
     590: astore        6
     592: aload         6
     594: ifnull        605
     597: aload         6
     599: invokevirtual #94                 // Method org/apache/kafka/connect/data/SchemaAndValue.value:()Ljava/lang/Object;
     602: ifnonnull     635
     605: new           #69                 // class org/apache/kafka/connect/errors/DataException
     608: dup
     609: new           #89                 // class java/lang/StringBuilder
     612: dup
     613: invokespecial #90                 // Method java/lang/StringBuilder."<init>":()V
     616: ldc           #202                // String Map entry may not have a null key:
     618: invokevirtual #125                // Method java/lang/StringBuilder.append:(Ljava/lang/String;)Ljava/lang/StringBuilder;
     621: aload_0
     622: invokevirtual #186                // Method org/apache/kafka/connect/data/Values$Parser.original:()Ljava/lang/String;
     625: invokevirtual #125                // Method java/lang/StringBuilder.append:(Ljava/lang/String;)Ljava/lang/StringBuilder;
     628: invokevirtual #92                 // Method java/lang/StringBuilder.toString:()Ljava/lang/String;
     631: invokespecial #71                 // Method org/apache/kafka/connect/errors/DataException."<init>":(Ljava/lang/String;)V
     634: athrow
     635: aload_0
     636: ldc           #203                // String :
     638: invokevirtual #164                // Method org/apache/kafka/connect/data/Values$Parser.canConsume:(Ljava/lang/String;)Z
     641: ifne          686
     644: new           #69                 // class org/apache/kafka/connect/errors/DataException
     647: dup
     648: new           #89                 // class java/lang/StringBuilder
     651: dup
     652: invokespecial #90                 // Method java/lang/StringBuilder."<init>":()V
     655: ldc           #204                // String Map entry is missing \':\' at
     657: invokevirtual #125                // Method java/lang/StringBuilder.append:(Ljava/lang/String;)Ljava/lang/StringBuilder;
     660: aload_0
     661: invokevirtual #205                // Method org/apache/kafka/connect/data/Values$Parser.position:()I
     664: invokevirtual #206                // Method java/lang/StringBuilder.append:(I)Ljava/lang/StringBuilder;
     667: ldc           #207                // String  in
     669: invokevirtual #125                // Method java/lang/StringBuilder.append:(Ljava/lang/String;)Ljava/lang/StringBuilder;
     672: aload_0
     673: invokevirtual #186                // Method org/apache/kafka/connect/data/Values$Parser.original:()Ljava/lang/String;
     676: invokevirtual #125                // Method java/lang/StringBuilder.append:(Ljava/lang/String;)Ljava/lang/StringBuilder;
     679: invokevirtual #92                 // Method java/lang/StringBuilder.toString:()Ljava/lang/String;
     682: invokespecial #71                 // Method org/apache/kafka/connect/errors/DataException."<init>":(Ljava/lang/String;)V
     685: athrow
     686: aload_0
     687: iconst_1
     688: invokestatic  #67                 // Method parse:(Lorg/apache/kafka/connect/data/Values$Parser;Z)Lorg/apache/kafka/connect/data/SchemaAndValue;
     691: astore        7
     693: aload         7
     695: ifnull        706
     698: aload         7
     700: invokevirtual #94                 // Method org/apache/kafka/connect/data/SchemaAndValue.value:()Ljava/lang/Object;
     703: goto          707
     706: aconst_null
     707: astore        8
     709: aload_3
     710: aload         6
     712: invokevirtual #94                 // Method org/apache/kafka/connect/data/SchemaAndValue.value:()Ljava/lang/Object;
     715: aload         8
     717: invokeinterface #208,  3          // InterfaceMethod java/util/Map.put:(Ljava/lang/Object;Ljava/lang/Object;)Ljava/lang/Object;
     722: pop
     723: aload_0
     724: ldc           #184                // String ,
     726: invokevirtual #164                // Method org/apache/kafka/connect/data/Values$Parser.canConsume:(Ljava/lang/String;)Z
     729: pop
     730: aload         4
     732: aload         6
     734: invokestatic  #187                // Method commonSchemaFor:(Lorg/apache/kafka/connect/data/Schema;Lorg/apache/kafka/connect/data/SchemaAndValue;)Lorg/apache/kafka/connect/data/Schema;
     737: astore        4
     739: aload         5
     741: aload         7
     743: invokestatic  #187                // Method commonSchemaFor:(Lorg/apache/kafka/connect/data/Schema;Lorg/apache/kafka/connect/data/SchemaAndValue;)Lorg/apache/kafka/connect/data/Schema;
     746: astore        5
     748: goto          457
     751: ldc           #184                // String ,
     753: aload_0
     754: invokevirtual #190                // Method org/apache/kafka/connect/data/Values$Parser.previous:()Ljava/lang/String;
     757: invokevirtual #78                 // Method java/lang/String.equals:(Ljava/lang/Object;)Z
     760: ifeq          793
     763: new           #69                 // class org/apache/kafka/connect/errors/DataException
     766: dup
     767: new           #89                 // class java/lang/StringBuilder
     770: dup
     771: invokespecial #90                 // Method java/lang/StringBuilder."<init>":()V
     774: ldc           #209                // String Map is missing element after \',\':
     776: invokevirtual #125                // Method java/lang/StringBuilder.append:(Ljava/lang/String;)Ljava/lang/StringBuilder;
     779: aload_0
     780: invokevirtual #186                // Method org/apache/kafka/connect/data/Values$Parser.original:()Ljava/lang/String;
     783: invokevirtual #125                // Method java/lang/StringBuilder.append:(Ljava/lang/String;)Ljava/lang/StringBuilder;
     786: invokevirtual #92                 // Method java/lang/StringBuilder.toString:()Ljava/lang/String;
     789: invokespecial #71                 // Method org/apache/kafka/connect/errors/DataException."<init>":(Ljava/lang/String;)V
     792: athrow
     793: new           #69                 // class org/apache/kafka/connect/errors/DataException
     796: dup
     797: new           #89                 // class java/lang/StringBuilder
     800: dup
     801: invokespecial #90                 // Method java/lang/StringBuilder."<init>":()V
     804: ldc           #210                // String Map is missing terminating \'}\':
     806: invokevirtual #125                // Method java/lang/StringBuilder.append:(Ljava/lang/String;)Ljava/lang/StringBuilder;
     809: aload_0
     810: invokevirtual #186                // Method org/apache/kafka/connect/data/Values$Parser.original:()Ljava/lang/String;
     813: invokevirtual #125                // Method java/lang/StringBuilder.append:(Ljava/lang/String;)Ljava/lang/StringBuilder;
     816: invokevirtual #92                 // Method java/lang/StringBuilder.toString:()Ljava/lang/String;
     819: invokespecial #71                 // Method org/apache/kafka/connect/errors/DataException."<init>":(Ljava/lang/String;)V
     822: athrow
     823: goto          843
     826: astore_3
     827: getstatic     #211                // Field LOG:Lorg/slf4j/Logger;
     830: ldc           #212                // String Unable to parse the value as a map or an array; reverting to string
     832: aload_3
     833: invokeinterface #213,  3          // InterfaceMethod org/slf4j/Logger.trace:(Ljava/lang/String;Ljava/lang/Throwable;)V
     838: aload_0
     839: iload_2
     840: invokevirtual #166                // Method org/apache/kafka/connect/data/Values$Parser.rewindTo:(I)V
     843: aload_0
     844: invokevirtual #168                // Method org/apache/kafka/connect/data/Values$Parser.next:()Ljava/lang/String;
     847: astore_3
     848: aload_3
     849: invokevirtual #214                // Method java/lang/String.trim:()Ljava/lang/String;
     852: invokevirtual #62                 // Method java/lang/String.isEmpty:()Z
     855: ifeq          870
     858: new           #63                 // class org/apache/kafka/connect/data/SchemaAndValue
     861: dup
     862: getstatic     #32                 // Field org/apache/kafka/connect/data/Schema.STRING_SCHEMA:Lorg/apache/kafka/connect/data/Schema;
     865: aload_3
     866: invokespecial #64                 // Method org/apache/kafka/connect/data/SchemaAndValue."<init>":(Lorg/apache/kafka/connect/data/Schema;Ljava/lang/Object;)V
     869: areturn
     870: aload_3
     871: invokevirtual #214                // Method java/lang/String.trim:()Ljava/lang/String;
     874: astore_3
     875: aload_3
     876: iconst_0
     877: invokevirtual #215                // Method java/lang/String.charAt:(I)C
     880: istore        4
     882: iload         4
     884: invokestatic  #216                // Method java/lang/Character.isDigit:(C)Z
     887: istore        5
     889: iload         5
     891: ifeq          968
     894: aload_0
     895: invokevirtual #163                // Method org/apache/kafka/connect/data/Values$Parser.mark:()I
     898: istore        6
     900: aload_0
     901: iconst_4
     902: invokevirtual #217                // Method org/apache/kafka/connect/data/Values$Parser.next:(I)Ljava/lang/String;
     905: astore        7
     907: aload         7
     909: ifnull        948
     912: new           #89                 // class java/lang/StringBuilder
     915: dup
     916: invokespecial #90                 // Method java/lang/StringBuilder."<init>":()V
     919: aload_3
     920: invokevirtual #125                // Method java/lang/StringBuilder.append:(Ljava/lang/String;)Ljava/lang/StringBuilder;
     923: aload         7
     925: invokevirtual #125                // Method java/lang/StringBuilder.append:(Ljava/lang/String;)Ljava/lang/StringBuilder;
     928: invokevirtual #92                 // Method java/lang/StringBuilder.toString:()Ljava/lang/String;
     931: astore        8
     933: aload         8
     935: invokestatic  #218                // Method parseAsTemporal:(Ljava/lang/String;)Lorg/apache/kafka/connect/data/SchemaAndValue;
     938: astore        9
     940: aload         9
     942: ifnull        948
     945: aload         9
     947: areturn
     948: aload_0
     949: iload         6
     951: invokevirtual #166                // Method org/apache/kafka/connect/data/Values$Parser.rewindTo:(I)V
     954: aload_3
     955: invokestatic  #218                // Method parseAsTemporal:(Ljava/lang/String;)Lorg/apache/kafka/connect/data/SchemaAndValue;
     958: astore        8
     960: aload         8
     962: ifnull        968
     965: aload         8
     967: areturn
     968: iload         5
     970: ifne          987
     973: iload         4
     975: bipush        43
     977: if_icmpeq     987
     980: iload         4
     982: bipush        45
     984: if_icmpne     1146
     987: new           #31                 // class java/math/BigDecimal
     990: dup
     991: aload_3
     992: invokespecial #85                 // Method java/math/BigDecimal."<init>":(Ljava/lang/String;)V
     995: astore        6
     997: new           #63                 // class org/apache/kafka/connect/data/SchemaAndValue
    1000: dup
    1001: getstatic     #34                 // Field org/apache/kafka/connect/data/Schema.INT8_SCHEMA:Lorg/apache/kafka/connect/data/Schema;
    1004: aload         6
    1006: invokevirtual #219                // Method java/math/BigDecimal.byteValueExact:()B
    1009: invokestatic  #98                 // Method java/lang/Byte.valueOf:(B)Ljava/lang/Byte;
    1012: invokespecial #64                 // Method org/apache/kafka/connect/data/SchemaAndValue."<init>":(Lorg/apache/kafka/connect/data/Schema;Ljava/lang/Object;)V
    1015: areturn
    1016: astore        7
    1018: new           #63                 // class org/apache/kafka/connect/data/SchemaAndValue
    1021: dup
    1022: getstatic     #35                 // Field org/apache/kafka/connect/data/Schema.INT16_SCHEMA:Lorg/apache/kafka/connect/data/Schema;
    1025: aload         6
    1027: invokevirtual #221                // Method java/math/BigDecimal.shortValueExact:()S
    1030: invokestatic  #99                 // Method java/lang/Short.valueOf:(S)Ljava/lang/Short;
    1033: invokespecial #64                 // Method org/apache/kafka/connect/data/SchemaAndValue."<init>":(Lorg/apache/kafka/connect/data/Schema;Ljava/lang/Object;)V
    1036: areturn
    1037: astore        7
    1039: new           #63                 // class org/apache/kafka/connect/data/SchemaAndValue
    1042: dup
    1043: getstatic     #36                 // Field org/apache/kafka/connect/data/Schema.INT32_SCHEMA:Lorg/apache/kafka/connect/data/Schema;
    1046: aload         6
    1048: invokevirtual #222                // Method java/math/BigDecimal.intValueExact:()I
    1051: invokestatic  #117                // Method java/lang/Integer.valueOf:(I)Ljava/lang/Integer;
    1054: invokespecial #64                 // Method org/apache/kafka/connect/data/SchemaAndValue."<init>":(Lorg/apache/kafka/connect/data/Schema;Ljava/lang/Object;)V
    1057: areturn
    1058: astore        7
    1060: new           #63                 // class org/apache/kafka/connect/data/SchemaAndValue
    1063: dup
    1064: getstatic     #37                 // Field org/apache/kafka/connect/data/Schema.INT64_SCHEMA:Lorg/apache/kafka/connect/data/Schema;
    1067: aload         6
    1069: invokevirtual #223                // Method java/math/BigDecimal.longValueExact:()J
    1072: invokestatic  #121                // Method java/lang/Long.valueOf:(J)Ljava/lang/Long;
    1075: invokespecial #64                 // Method org/apache/kafka/connect/data/SchemaAndValue."<init>":(Lorg/apache/kafka/connect/data/Schema;Ljava/lang/Object;)V
    1078: areturn
    1079: astore        7
    1081: aload         6
    1083: invokevirtual #86                 // Method java/math/BigDecimal.doubleValue:()D
    1086: dstore        7
    1088: dload         7
    1090: ldc2_w        #224                // double -Infinityd
    1093: dcmpl
    1094: ifeq          1122
    1097: dload         7
    1099: ldc2_w        #226                // double Infinityd
    1102: dcmpl
    1103: ifeq          1122
    1106: new           #63                 // class org/apache/kafka/connect/data/SchemaAndValue
    1109: dup
    1110: getstatic     #39                 // Field org/apache/kafka/connect/data/Schema.FLOAT64_SCHEMA:Lorg/apache/kafka/connect/data/Schema;
    1113: dload         7
    1115: invokestatic  #87                 // Method java/lang/Double.valueOf:(D)Ljava/lang/Double;
    1118: invokespecial #64                 // Method org/apache/kafka/connect/data/SchemaAndValue."<init>":(Lorg/apache/kafka/connect/data/Schema;Ljava/lang/Object;)V
    1121: areturn
    1122: aload         6
    1124: invokevirtual #228                // Method java/math/BigDecimal.scale:()I
    1127: invokestatic  #30                 // Method org/apache/kafka/connect/data/Decimal.schema:(I)Lorg/apache/kafka/connect/data/Schema;
    1130: astore        9
    1132: new           #63                 // class org/apache/kafka/connect/data/SchemaAndValue
    1135: dup
    1136: aload         9
    1138: aload         6
    1140: invokespecial #64                 // Method org/apache/kafka/connect/data/SchemaAndValue."<init>":(Lorg/apache/kafka/connect/data/Schema;Ljava/lang/Object;)V
    1143: areturn
    1144: astore        6
    1146: iload_1
    1147: ifeq          1160
    1150: new           #69                 // class org/apache/kafka/connect/errors/DataException
    1153: dup
    1154: ldc           #229                // String Failed to parse embedded value
    1156: invokespecial #71                 // Method org/apache/kafka/connect/errors/DataException."<init>":(Ljava/lang/String;)V
    1159: athrow
    1160: new           #63                 // class org/apache/kafka/connect/data/SchemaAndValue
    1163: dup
    1164: getstatic     #32                 // Field org/apache/kafka/connect/data/Schema.STRING_SCHEMA:Lorg/apache/kafka/connect/data/Schema;
    1167: aload_0
    1168: invokevirtual #186                // Method org/apache/kafka/connect/data/Values$Parser.original:()Ljava/lang/String;
    1171: invokespecial #64                 // Method org/apache/kafka/connect/data/SchemaAndValue."<init>":(Lorg/apache/kafka/connect/data/Schema;Ljava/lang/Object;)V
    1174: areturn
    Exception table:
       from    to  target type
         160   239   826   Class org/apache/kafka/connect/errors/DataException
         240   545   826   Class org/apache/kafka/connect/errors/DataException
         546   823   826   Class org/apache/kafka/connect/errors/DataException
         997  1015  1016   Class java/lang/ArithmeticException
        1018  1036  1037   Class java/lang/ArithmeticException
        1039  1057  1058   Class java/lang/ArithmeticException
        1060  1078  1079   Class java/lang/ArithmeticException
         987  1015  1144   Class java/lang/NumberFormatException
        1016  1036  1144   Class java/lang/NumberFormatException
        1037  1057  1144   Class java/lang/NumberFormatException
        1058  1078  1144   Class java/lang/NumberFormatException
        1079  1121  1144   Class java/lang/NumberFormatException
        1122  1143  1144   Class java/lang/NumberFormatException

  private static org.apache.kafka.connect.data.SchemaAndValue parseAsTemporal(java.lang.String);
    Code:
       0: aload_0
       1: ifnonnull     6
       4: aconst_null
       5: areturn
       6: aload_0
       7: ldc           #230                // String \\:
       9: ldc           #203                // String :
      11: invokevirtual #231                // Method java/lang/String.replace:(Ljava/lang/CharSequence;Ljava/lang/CharSequence;)Ljava/lang/String;
      14: astore_0
      15: aload_0
      16: invokevirtual #232                // Method java/lang/String.length:()I
      19: istore_1
      20: iload_1
      21: getstatic     #233                // Field ISO_8601_TIME_LENGTH:I
      24: if_icmpne     55
      27: new           #63                 // class org/apache/kafka/connect/data/SchemaAndValue
      30: dup
      31: getstatic     #26                 // Field org/apache/kafka/connect/data/Time.SCHEMA:Lorg/apache/kafka/connect/data/Schema;
      34: new           #158                // class java/text/SimpleDateFormat
      37: dup
      38: ldc           #159                // String HH:mm:ss.SSS\'Z\'
      40: invokespecial #160                // Method java/text/SimpleDateFormat."<init>":(Ljava/lang/String;)V
      43: aload_0
      44: invokevirtual #234                // Method java/text/SimpleDateFormat.parse:(Ljava/lang/String;)Ljava/util/Date;
      47: invokespecial #64                 // Method org/apache/kafka/connect/data/SchemaAndValue."<init>":(Lorg/apache/kafka/connect/data/Schema;Ljava/lang/Object;)V
      50: areturn
      51: astore_2
      52: goto          122
      55: iload_1
      56: getstatic     #236                // Field ISO_8601_TIMESTAMP_LENGTH:I
      59: if_icmpne     90
      62: new           #63                 // class org/apache/kafka/connect/data/SchemaAndValue
      65: dup
      66: getstatic     #29                 // Field org/apache/kafka/connect/data/Timestamp.SCHEMA:Lorg/apache/kafka/connect/data/Schema;
      69: new           #158                // class java/text/SimpleDateFormat
      72: dup
      73: ldc           #162                // String yyyy-MM-dd\'T\'HH:mm:ss.SSS\'Z\'
      75: invokespecial #160                // Method java/text/SimpleDateFormat."<init>":(Ljava/lang/String;)V
      78: aload_0
      79: invokevirtual #234                // Method java/text/SimpleDateFormat.parse:(Ljava/lang/String;)Ljava/util/Date;
      82: invokespecial #64                 // Method org/apache/kafka/connect/data/SchemaAndValue."<init>":(Lorg/apache/kafka/connect/data/Schema;Ljava/lang/Object;)V
      85: areturn
      86: astore_2
      87: goto          122
      90: iload_1
      91: getstatic     #237                // Field ISO_8601_DATE_LENGTH:I
      94: if_icmpne     122
      97: new           #63                 // class org/apache/kafka/connect/data/SchemaAndValue
     100: dup
     101: getstatic     #28                 // Field org/apache/kafka/connect/data/Date.SCHEMA:Lorg/apache/kafka/connect/data/Schema;
     104: new           #158                // class java/text/SimpleDateFormat
     107: dup
     108: ldc           #161                // String yyyy-MM-dd
     110: invokespecial #160                // Method java/text/SimpleDateFormat."<init>":(Ljava/lang/String;)V
     113: aload_0
     114: invokevirtual #234                // Method java/text/SimpleDateFormat.parse:(Ljava/lang/String;)Ljava/util/Date;
     117: invokespecial #64                 // Method org/apache/kafka/connect/data/SchemaAndValue."<init>":(Lorg/apache/kafka/connect/data/Schema;Ljava/lang/Object;)V
     120: areturn
     121: astore_2
     122: aconst_null
     123: areturn
    Exception table:
       from    to  target type
          27    50    51   Class java/text/ParseException
          62    85    86   Class java/text/ParseException
          97   120   121   Class java/text/ParseException

  protected static org.apache.kafka.connect.data.Schema commonSchemaFor(org.apache.kafka.connect.data.Schema, org.apache.kafka.connect.data.SchemaAndValue);
    Code:
       0: aload_1
       1: ifnonnull     6
       4: aload_0
       5: areturn
       6: aload_0
       7: ifnonnull     15
      10: aload_1
      11: invokevirtual #170                // Method org/apache/kafka/connect/data/SchemaAndValue.schema:()Lorg/apache/kafka/connect/data/Schema;
      14: areturn
      15: aload_1
      16: invokevirtual #170                // Method org/apache/kafka/connect/data/SchemaAndValue.schema:()Lorg/apache/kafka/connect/data/Schema;
      19: astore_2
      20: aload_0
      21: invokeinterface #73,  1           // InterfaceMethod org/apache/kafka/connect/data/Schema.type:()Lorg/apache/kafka/connect/data/Schema$Type;
      26: astore_3
      27: aload_2
      28: invokeinterface #73,  1           // InterfaceMethod org/apache/kafka/connect/data/Schema.type:()Lorg/apache/kafka/connect/data/Schema$Type;
      33: astore        4
      35: aload_3
      36: aload         4
      38: if_acmpeq     354
      41: getstatic     #72                 // Field org/apache/kafka/connect/data/Values$1.$SwitchMap$org$apache$kafka$connect$data$Schema$Type:[I
      44: aload_0
      45: invokeinterface #73,  1           // InterfaceMethod org/apache/kafka/connect/data/Schema.type:()Lorg/apache/kafka/connect/data/Schema$Type;
      50: invokevirtual #74                 // Method org/apache/kafka/connect/data/Schema$Type.ordinal:()I
      53: iaload
      54: tableswitch   { // 4 to 9
                     4: 92
                     5: 134
                     6: 178
                     7: 222
                     8: 266
                     9: 310
               default: 352
          }
      92: aload         4
      94: getstatic     #238                // Field org/apache/kafka/connect/data/Schema$Type.INT16:Lorg/apache/kafka/connect/data/Schema$Type;
      97: if_acmpeq     132
     100: aload         4
     102: getstatic     #239                // Field org/apache/kafka/connect/data/Schema$Type.INT32:Lorg/apache/kafka/connect/data/Schema$Type;
     105: if_acmpeq     132
     108: aload         4
     110: getstatic     #240                // Field org/apache/kafka/connect/data/Schema$Type.INT64:Lorg/apache/kafka/connect/data/Schema$Type;
     113: if_acmpeq     132
     116: aload         4
     118: getstatic     #241                // Field org/apache/kafka/connect/data/Schema$Type.FLOAT32:Lorg/apache/kafka/connect/data/Schema$Type;
     121: if_acmpeq     132
     124: aload         4
     126: getstatic     #242                // Field org/apache/kafka/connect/data/Schema$Type.FLOAT64:Lorg/apache/kafka/connect/data/Schema$Type;
     129: if_acmpne     352
     132: aload_2
     133: areturn
     134: aload         4
     136: getstatic     #243                // Field org/apache/kafka/connect/data/Schema$Type.INT8:Lorg/apache/kafka/connect/data/Schema$Type;
     139: if_acmpne     144
     142: aload_0
     143: areturn
     144: aload         4
     146: getstatic     #239                // Field org/apache/kafka/connect/data/Schema$Type.INT32:Lorg/apache/kafka/connect/data/Schema$Type;
     149: if_acmpeq     176
     152: aload         4
     154: getstatic     #240                // Field org/apache/kafka/connect/data/Schema$Type.INT64:Lorg/apache/kafka/connect/data/Schema$Type;
     157: if_acmpeq     176
     160: aload         4
     162: getstatic     #241                // Field org/apache/kafka/connect/data/Schema$Type.FLOAT32:Lorg/apache/kafka/connect/data/Schema$Type;
     165: if_acmpeq     176
     168: aload         4
     170: getstatic     #242                // Field org/apache/kafka/connect/data/Schema$Type.FLOAT64:Lorg/apache/kafka/connect/data/Schema$Type;
     173: if_acmpne     352
     176: aload_2
     177: areturn
     178: aload         4
     180: getstatic     #243                // Field org/apache/kafka/connect/data/Schema$Type.INT8:Lorg/apache/kafka/connect/data/Schema$Type;
     183: if_acmpeq     194
     186: aload         4
     188: getstatic     #238                // Field org/apache/kafka/connect/data/Schema$Type.INT16:Lorg/apache/kafka/connect/data/Schema$Type;
     191: if_acmpne     196
     194: aload_0
     195: areturn
     196: aload         4
     198: getstatic     #240                // Field org/apache/kafka/connect/data/Schema$Type.INT64:Lorg/apache/kafka/connect/data/Schema$Type;
     201: if_acmpeq     220
     204: aload         4
     206: getstatic     #241                // Field org/apache/kafka/connect/data/Schema$Type.FLOAT32:Lorg/apache/kafka/connect/data/Schema$Type;
     209: if_acmpeq     220
     212: aload         4
     214: getstatic     #242                // Field org/apache/kafka/connect/data/Schema$Type.FLOAT64:Lorg/apache/kafka/connect/data/Schema$Type;
     217: if_acmpne     352
     220: aload_2
     221: areturn
     222: aload         4
     224: getstatic     #243                // Field org/apache/kafka/connect/data/Schema$Type.INT8:Lorg/apache/kafka/connect/data/Schema$Type;
     227: if_acmpeq     246
     230: aload         4
     232: getstatic     #238                // Field org/apache/kafka/connect/data/Schema$Type.INT16:Lorg/apache/kafka/connect/data/Schema$Type;
     235: if_acmpeq     246
     238: aload         4
     240: getstatic     #239                // Field org/apache/kafka/connect/data/Schema$Type.INT32:Lorg/apache/kafka/connect/data/Schema$Type;
     243: if_acmpne     248
     246: aload_0
     247: areturn
     248: aload         4
     250: getstatic     #241                // Field org/apache/kafka/connect/data/Schema$Type.FLOAT32:Lorg/apache/kafka/connect/data/Schema$Type;
     253: if_acmpeq     264
     256: aload         4
     258: getstatic     #242                // Field org/apache/kafka/connect/data/Schema$Type.FLOAT64:Lorg/apache/kafka/connect/data/Schema$Type;
     261: if_acmpne     352
     264: aload_2
     265: areturn
     266: aload         4
     268: getstatic     #243                // Field org/apache/kafka/connect/data/Schema$Type.INT8:Lorg/apache/kafka/connect/data/Schema$Type;
     271: if_acmpeq     298
     274: aload         4
     276: getstatic     #238                // Field org/apache/kafka/connect/data/Schema$Type.INT16:Lorg/apache/kafka/connect/data/Schema$Type;
     279: if_acmpeq     298
     282: aload         4
     284: getstatic     #239                // Field org/apache/kafka/connect/data/Schema$Type.INT32:Lorg/apache/kafka/connect/data/Schema$Type;
     287: if_acmpeq     298
     290: aload         4
     292: getstatic     #240                // Field org/apache/kafka/connect/data/Schema$Type.INT64:Lorg/apache/kafka/connect/data/Schema$Type;
     295: if_acmpne     300
     298: aload_0
     299: areturn
     300: aload         4
     302: getstatic     #242                // Field org/apache/kafka/connect/data/Schema$Type.FLOAT64:Lorg/apache/kafka/connect/data/Schema$Type;
     305: if_acmpne     352
     308: aload_2
     309: areturn
     310: aload         4
     312: getstatic     #243                // Field org/apache/kafka/connect/data/Schema$Type.INT8:Lorg/apache/kafka/connect/data/Schema$Type;
     315: if_acmpeq     350
     318: aload         4
     320: getstatic     #238                // Field org/apache/kafka/connect/data/Schema$Type.INT16:Lorg/apache/kafka/connect/data/Schema$Type;
     323: if_acmpeq     350
     326: aload         4
     328: getstatic     #239                // Field org/apache/kafka/connect/data/Schema$Type.INT32:Lorg/apache/kafka/connect/data/Schema$Type;
     331: if_acmpeq     350
     334: aload         4
     336: getstatic     #240                // Field org/apache/kafka/connect/data/Schema$Type.INT64:Lorg/apache/kafka/connect/data/Schema$Type;
     339: if_acmpeq     350
     342: aload         4
     344: getstatic     #241                // Field org/apache/kafka/connect/data/Schema$Type.FLOAT32:Lorg/apache/kafka/connect/data/Schema$Type;
     347: if_acmpne     352
     350: aload_0
     351: areturn
     352: aconst_null
     353: areturn
     354: aload_0
     355: invokeinterface #68,  1           // InterfaceMethod org/apache/kafka/connect/data/Schema.isOptional:()Z
     360: aload_2
     361: invokeinterface #68,  1           // InterfaceMethod org/apache/kafka/connect/data/Schema.isOptional:()Z
     366: if_icmpne     384
     369: aload_0
     370: invokeinterface #68,  1           // InterfaceMethod org/apache/kafka/connect/data/Schema.isOptional:()Z
     375: ifeq          382
     378: aload_0
     379: goto          383
     382: aload_2
     383: areturn
     384: aload_0
     385: aload_2
     386: invokevirtual #244                // Method java/lang/Object.equals:(Ljava/lang/Object;)Z
     389: ifne          394
     392: aconst_null
     393: areturn
     394: aload_0
     395: areturn

  protected static java.util.List<java.lang.Object> alignListEntriesWithSchema(org.apache.kafka.connect.data.Schema, java.util.List<java.lang.Object>);
    Code:
       0: aload_0
       1: invokeinterface #245,  1          // InterfaceMethod org/apache/kafka/connect/data/Schema.valueSchema:()Lorg/apache/kafka/connect/data/Schema;
       6: astore_2
       7: new           #178                // class java/util/ArrayList
      10: dup
      11: invokespecial #179                // Method java/util/ArrayList."<init>":()V
      14: astore_3
      15: aload_1
      16: invokeinterface #46,  1           // InterfaceMethod java/util/List.iterator:()Ljava/util/Iterator;
      21: astore        4
      23: aload         4
      25: invokeinterface #47,  1           // InterfaceMethod java/util/Iterator.hasNext:()Z
      30: ifeq          63
      33: aload         4
      35: invokeinterface #48,  1           // InterfaceMethod java/util/Iterator.next:()Ljava/lang/Object;
      40: astore        5
      42: aload_2
      43: aconst_null
      44: aload         5
      46: invokestatic  #4                  // Method convertTo:(Lorg/apache/kafka/connect/data/Schema;Lorg/apache/kafka/connect/data/Schema;Ljava/lang/Object;)Ljava/lang/Object;
      49: astore        6
      51: aload_3
      52: aload         6
      54: invokeinterface #188,  2          // InterfaceMethod java/util/List.add:(Ljava/lang/Object;)Z
      59: pop
      60: goto          23
      63: aload_3
      64: areturn

  protected static java.util.Map<java.lang.Object, java.lang.Object> alignMapKeysAndValuesWithSchema(org.apache.kafka.connect.data.Schema, java.util.Map<java.lang.Object, java.lang.Object>);
    Code:
       0: aload_0
       1: invokeinterface #246,  1          // InterfaceMethod org/apache/kafka/connect/data/Schema.keySchema:()Lorg/apache/kafka/connect/data/Schema;
       6: astore_2
       7: aload_0
       8: invokeinterface #245,  1          // InterfaceMethod org/apache/kafka/connect/data/Schema.valueSchema:()Lorg/apache/kafka/connect/data/Schema;
      13: astore_3
      14: new           #194                // class java/util/LinkedHashMap
      17: dup
      18: invokespecial #195                // Method java/util/LinkedHashMap."<init>":()V
      21: astore        4
      23: aload_1
      24: invokeinterface #54,  1           // InterfaceMethod java/util/Map.entrySet:()Ljava/util/Set;
      29: invokeinterface #55,  1           // InterfaceMethod java/util/Set.iterator:()Ljava/util/Iterator;
      34: astore        5
      36: aload         5
      38: invokeinterface #47,  1           // InterfaceMethod java/util/Iterator.hasNext:()Z
      43: ifeq          101
      46: aload         5
      48: invokeinterface #48,  1           // InterfaceMethod java/util/Iterator.next:()Ljava/lang/Object;
      53: checkcast     #56                 // class java/util/Map$Entry
      56: astore        6
      58: aload_2
      59: aconst_null
      60: aload         6
      62: invokeinterface #57,  1           // InterfaceMethod java/util/Map$Entry.getKey:()Ljava/lang/Object;
      67: invokestatic  #4                  // Method convertTo:(Lorg/apache/kafka/connect/data/Schema;Lorg/apache/kafka/connect/data/Schema;Ljava/lang/Object;)Ljava/lang/Object;
      70: astore        7
      72: aload_3
      73: aconst_null
      74: aload         6
      76: invokeinterface #58,  1           // InterfaceMethod java/util/Map$Entry.getValue:()Ljava/lang/Object;
      81: invokestatic  #4                  // Method convertTo:(Lorg/apache/kafka/connect/data/Schema;Lorg/apache/kafka/connect/data/Schema;Ljava/lang/Object;)Ljava/lang/Object;
      84: astore        8
      86: aload         4
      88: aload         7
      90: aload         8
      92: invokeinterface #208,  3          // InterfaceMethod java/util/Map.put:(Ljava/lang/Object;Ljava/lang/Object;)Ljava/lang/Object;
      97: pop
      98: goto          36
     101: aload         4
     103: areturn

  protected static java.util.Map<java.lang.Object, java.lang.Object> alignMapKeysWithSchema(org.apache.kafka.connect.data.Schema, java.util.Map<java.lang.Object, java.lang.Object>);
    Code:
       0: aload_0
       1: invokeinterface #246,  1          // InterfaceMethod org/apache/kafka/connect/data/Schema.keySchema:()Lorg/apache/kafka/connect/data/Schema;
       6: astore_2
       7: new           #194                // class java/util/LinkedHashMap
      10: dup
      11: invokespecial #195                // Method java/util/LinkedHashMap."<init>":()V
      14: astore_3
      15: aload_1
      16: invokeinterface #54,  1           // InterfaceMethod java/util/Map.entrySet:()Ljava/util/Set;
      21: invokeinterface #55,  1           // InterfaceMethod java/util/Set.iterator:()Ljava/util/Iterator;
      26: astore        4
      28: aload         4
      30: invokeinterface #47,  1           // InterfaceMethod java/util/Iterator.hasNext:()Z
      35: ifeq          83
      38: aload         4
      40: invokeinterface #48,  1           // InterfaceMethod java/util/Iterator.next:()Ljava/lang/Object;
      45: checkcast     #56                 // class java/util/Map$Entry
      48: astore        5
      50: aload_2
      51: aconst_null
      52: aload         5
      54: invokeinterface #57,  1           // InterfaceMethod java/util/Map$Entry.getKey:()Ljava/lang/Object;
      59: invokestatic  #4                  // Method convertTo:(Lorg/apache/kafka/connect/data/Schema;Lorg/apache/kafka/connect/data/Schema;Ljava/lang/Object;)Ljava/lang/Object;
      62: astore        6
      64: aload_3
      65: aload         6
      67: aload         5
      69: invokeinterface #58,  1           // InterfaceMethod java/util/Map$Entry.getValue:()Ljava/lang/Object;
      74: invokeinterface #208,  3          // InterfaceMethod java/util/Map.put:(Ljava/lang/Object;Ljava/lang/Object;)Ljava/lang/Object;
      79: pop
      80: goto          28
      83: aload_3
      84: areturn

  static {};
    Code:
       0: ldc           #1                  // class org/apache/kafka/connect/data/Values
       2: invokestatic  #247                // Method org/slf4j/LoggerFactory.getLogger:(Ljava/lang/Class;)Lorg/slf4j/Logger;
       5: putstatic     #211                // Field LOG:Lorg/slf4j/Logger;
       8: ldc           #248                // String UTC
      10: invokestatic  #249                // Method java/util/TimeZone.getTimeZone:(Ljava/lang/String;)Ljava/util/TimeZone;
      13: putstatic     #110                // Field UTC:Ljava/util/TimeZone;
      16: new           #63                 // class org/apache/kafka/connect/data/SchemaAndValue
      19: dup
      20: aconst_null
      21: aconst_null
      22: invokespecial #64                 // Method org/apache/kafka/connect/data/SchemaAndValue."<init>":(Lorg/apache/kafka/connect/data/Schema;Ljava/lang/Object;)V
      25: putstatic     #61                 // Field NULL_SCHEMA_AND_VALUE:Lorg/apache/kafka/connect/data/SchemaAndValue;
      28: new           #63                 // class org/apache/kafka/connect/data/SchemaAndValue
      31: dup
      32: getstatic     #33                 // Field org/apache/kafka/connect/data/Schema.BOOLEAN_SCHEMA:Lorg/apache/kafka/connect/data/Schema;
      35: getstatic     #97                 // Field java/lang/Boolean.TRUE:Ljava/lang/Boolean;
      38: invokespecial #64                 // Method org/apache/kafka/connect/data/SchemaAndValue."<init>":(Lorg/apache/kafka/connect/data/Schema;Ljava/lang/Object;)V
      41: putstatic     #174                // Field TRUE_SCHEMA_AND_VALUE:Lorg/apache/kafka/connect/data/SchemaAndValue;
      44: new           #63                 // class org/apache/kafka/connect/data/SchemaAndValue
      47: dup
      48: getstatic     #33                 // Field org/apache/kafka/connect/data/Schema.BOOLEAN_SCHEMA:Lorg/apache/kafka/connect/data/Schema;
      51: getstatic     #96                 // Field java/lang/Boolean.FALSE:Ljava/lang/Boolean;
      54: invokespecial #64                 // Method org/apache/kafka/connect/data/SchemaAndValue."<init>":(Lorg/apache/kafka/connect/data/Schema;Ljava/lang/Object;)V
      57: putstatic     #176                // Field FALSE_SCHEMA_AND_VALUE:Lorg/apache/kafka/connect/data/SchemaAndValue;
      60: getstatic     #32                 // Field org/apache/kafka/connect/data/Schema.STRING_SCHEMA:Lorg/apache/kafka/connect/data/Schema;
      63: invokestatic  #51                 // Method org/apache/kafka/connect/data/SchemaBuilder.array:(Lorg/apache/kafka/connect/data/Schema;)Lorg/apache/kafka/connect/data/SchemaBuilder;
      66: invokevirtual #52                 // Method org/apache/kafka/connect/data/SchemaBuilder.build:()Lorg/apache/kafka/connect/data/Schema;
      69: putstatic     #20                 // Field ARRAY_SELECTOR_SCHEMA:Lorg/apache/kafka/connect/data/Schema;
      72: getstatic     #32                 // Field org/apache/kafka/connect/data/Schema.STRING_SCHEMA:Lorg/apache/kafka/connect/data/Schema;
      75: getstatic     #32                 // Field org/apache/kafka/connect/data/Schema.STRING_SCHEMA:Lorg/apache/kafka/connect/data/Schema;
      78: invokestatic  #59                 // Method org/apache/kafka/connect/data/SchemaBuilder.map:(Lorg/apache/kafka/connect/data/Schema;Lorg/apache/kafka/connect/data/Schema;)Lorg/apache/kafka/connect/data/SchemaBuilder;
      81: invokevirtual #52                 // Method org/apache/kafka/connect/data/SchemaBuilder.build:()Lorg/apache/kafka/connect/data/Schema;
      84: putstatic     #22                 // Field MAP_SELECTOR_SCHEMA:Lorg/apache/kafka/connect/data/Schema;
      87: invokestatic  #250                // Method org/apache/kafka/connect/data/SchemaBuilder.struct:()Lorg/apache/kafka/connect/data/SchemaBuilder;
      90: invokevirtual #52                 // Method org/apache/kafka/connect/data/SchemaBuilder.build:()Lorg/apache/kafka/connect/data/Schema;
      93: putstatic     #24                 // Field STRUCT_SELECTOR_SCHEMA:Lorg/apache/kafka/connect/data/Schema;
      96: getstatic     #97                 // Field java/lang/Boolean.TRUE:Ljava/lang/Boolean;
      99: invokevirtual #251                // Method java/lang/Boolean.toString:()Ljava/lang/String;
     102: putstatic     #173                // Field TRUE_LITERAL:Ljava/lang/String;
     105: getstatic     #96                 // Field java/lang/Boolean.FALSE:Ljava/lang/Boolean;
     108: invokevirtual #251                // Method java/lang/Boolean.toString:()Ljava/lang/String;
     111: putstatic     #175                // Field FALSE_LITERAL:Ljava/lang/String;
     114: new           #252                // class java/util/HashSet
     117: dup
     118: iconst_3
     119: anewarray     #19                 // class java/lang/String
     122: dup
     123: iconst_0
     124: ldc           #109                // String org.apache.kafka.connect.data.Time
     126: aastore
     127: dup
     128: iconst_1
     129: ldc           #103                // String org.apache.kafka.connect.data.Timestamp
     131: aastore
     132: dup
     133: iconst_2
     134: ldc           #101                // String org.apache.kafka.connect.data.Date
     136: aastore
     137: invokestatic  #253                // Method java/util/Arrays.asList:([Ljava/lang/Object;)Ljava/util/List;
     140: invokespecial #254                // Method java/util/HashSet."<init>":(Ljava/util/Collection;)V
     143: invokestatic  #255                // Method java/util/Collections.unmodifiableSet:(Ljava/util/Set;)Ljava/util/Set;
     146: putstatic     #169                // Field TEMPORAL_LOGICAL_TYPE_NAMES:Ljava/util/Set;
     149: ldc           #161                // String yyyy-MM-dd
     151: invokevirtual #232                // Method java/lang/String.length:()I
     154: putstatic     #237                // Field ISO_8601_DATE_LENGTH:I
     157: ldc           #159                // String HH:mm:ss.SSS\'Z\'
     159: invokevirtual #232                // Method java/lang/String.length:()I
     162: iconst_2
     163: isub
     164: putstatic     #233                // Field ISO_8601_TIME_LENGTH:I
     167: ldc           #162                // String yyyy-MM-dd\'T\'HH:mm:ss.SSS\'Z\'
     169: invokevirtual #232                // Method java/lang/String.length:()I
     172: iconst_4
     173: isub
     174: putstatic     #236                // Field ISO_8601_TIMESTAMP_LENGTH:I
     177: ldc_w         #256                // String \\\\
     180: invokestatic  #257                // Method java/util/regex/Pattern.compile:(Ljava/lang/String;)Ljava/util/regex/Pattern;
     183: putstatic     #152                // Field TWO_BACKSLASHES:Ljava/util/regex/Pattern;
     186: ldc           #167                // String \"
     188: invokestatic  #257                // Method java/util/regex/Pattern.compile:(Ljava/lang/String;)Ljava/util/regex/Pattern;
     191: putstatic     #156                // Field DOUBLEQOUTE:Ljava/util/regex/Pattern;
     194: return
}
