Compiled from "Options.java"
public final class io.dekorate.deps.okio.Options extends java.util.AbstractList<io.dekorate.deps.okio.ByteString> implements java.util.RandomAccess {
  final io.dekorate.deps.okio.ByteString[] byteStrings;

  final int[] trie;

  private io.dekorate.deps.okio.Options(io.dekorate.deps.okio.ByteString[], int[]);
    Code:
       0: aload_0
       1: invokespecial #17                 // Method java/util/AbstractList."<init>":()V
       4: aload_0
       5: aload_1
       6: putfield      #19                 // Field byteStrings:[Lio/dekorate/deps/okio/ByteString;
       9: aload_0
      10: aload_2
      11: putfield      #21                 // Field trie:[I
      14: return

  public static io.dekorate.deps.okio.Options of(io.dekorate.deps.okio.ByteString...);
    Code:
       0: aload_0
       1: arraylength
       2: ifne          28
       5: new           #2                  // class io/dekorate/deps/okio/Options
       8: dup
       9: iconst_0
      10: anewarray     #27                 // class io/dekorate/deps/okio/ByteString
      13: iconst_2
      14: newarray       int
      16: dup
      17: iconst_0
      18: iconst_0
      19: iastore
      20: dup
      21: iconst_1
      22: iconst_m1
      23: iastore
      24: invokespecial #29                 // Method "<init>":([Lio/dekorate/deps/okio/ByteString;[I)V
      27: areturn
      28: new           #31                 // class java/util/ArrayList
      31: dup
      32: aload_0
      33: invokestatic  #37                 // Method java/util/Arrays.asList:([Ljava/lang/Object;)Ljava/util/List;
      36: invokespecial #40                 // Method java/util/ArrayList."<init>":(Ljava/util/Collection;)V
      39: astore_1
      40: aload_1
      41: invokestatic  #46                 // Method java/util/Collections.sort:(Ljava/util/List;)V
      44: new           #31                 // class java/util/ArrayList
      47: dup
      48: invokespecial #47                 // Method java/util/ArrayList."<init>":()V
      51: astore_2
      52: iconst_0
      53: istore_3
      54: iload_3
      55: aload_1
      56: invokeinterface #53,  1           // InterfaceMethod java/util/List.size:()I
      61: if_icmpge     81
      64: aload_2
      65: iconst_m1
      66: invokestatic  #59                 // Method java/lang/Integer.valueOf:(I)Ljava/lang/Integer;
      69: invokeinterface #63,  2           // InterfaceMethod java/util/List.add:(Ljava/lang/Object;)Z
      74: pop
      75: iinc          3, 1
      78: goto          54
      81: iconst_0
      82: istore_3
      83: iload_3
      84: aload_1
      85: invokeinterface #53,  1           // InterfaceMethod java/util/List.size:()I
      90: if_icmpge     121
      93: aload_1
      94: aload_0
      95: iload_3
      96: aaload
      97: invokestatic  #67                 // Method java/util/Collections.binarySearch:(Ljava/util/List;Ljava/lang/Object;)I
     100: istore        4
     102: aload_2
     103: iload         4
     105: iload_3
     106: invokestatic  #59                 // Method java/lang/Integer.valueOf:(I)Ljava/lang/Integer;
     109: invokeinterface #71,  3           // InterfaceMethod java/util/List.set:(ILjava/lang/Object;)Ljava/lang/Object;
     114: pop
     115: iinc          3, 1
     118: goto          83
     121: aload_1
     122: iconst_0
     123: invokeinterface #75,  2           // InterfaceMethod java/util/List.get:(I)Ljava/lang/Object;
     128: checkcast     #27                 // class io/dekorate/deps/okio/ByteString
     131: invokevirtual #76                 // Method io/dekorate/deps/okio/ByteString.size:()I
     134: ifne          147
     137: new           #78                 // class java/lang/IllegalArgumentException
     140: dup
     141: ldc           #80                 // String the empty byte string is not a supported option
     143: invokespecial #83                 // Method java/lang/IllegalArgumentException."<init>":(Ljava/lang/String;)V
     146: athrow
     147: iconst_0
     148: istore_3
     149: iload_3
     150: aload_1
     151: invokeinterface #53,  1           // InterfaceMethod java/util/List.size:()I
     156: if_icmpge     317
     159: aload_1
     160: iload_3
     161: invokeinterface #75,  2           // InterfaceMethod java/util/List.get:(I)Ljava/lang/Object;
     166: checkcast     #27                 // class io/dekorate/deps/okio/ByteString
     169: astore        4
     171: iload_3
     172: iconst_1
     173: iadd
     174: istore        5
     176: iload         5
     178: aload_1
     179: invokeinterface #53,  1           // InterfaceMethod java/util/List.size:()I
     184: if_icmpge     311
     187: aload_1
     188: iload         5
     190: invokeinterface #75,  2           // InterfaceMethod java/util/List.get:(I)Ljava/lang/Object;
     195: checkcast     #27                 // class io/dekorate/deps/okio/ByteString
     198: astore        6
     200: aload         6
     202: aload         4
     204: invokevirtual #87                 // Method io/dekorate/deps/okio/ByteString.startsWith:(Lio/dekorate/deps/okio/ByteString;)Z
     207: ifne          213
     210: goto          311
     213: aload         6
     215: invokevirtual #76                 // Method io/dekorate/deps/okio/ByteString.size:()I
     218: aload         4
     220: invokevirtual #76                 // Method io/dekorate/deps/okio/ByteString.size:()I
     223: if_icmpne     254
     226: new           #78                 // class java/lang/IllegalArgumentException
     229: dup
     230: new           #89                 // class java/lang/StringBuilder
     233: dup
     234: invokespecial #90                 // Method java/lang/StringBuilder."<init>":()V
     237: ldc           #92                 // String duplicate option:
     239: invokevirtual #96                 // Method java/lang/StringBuilder.append:(Ljava/lang/String;)Ljava/lang/StringBuilder;
     242: aload         6
     244: invokevirtual #99                 // Method java/lang/StringBuilder.append:(Ljava/lang/Object;)Ljava/lang/StringBuilder;
     247: invokevirtual #103                // Method java/lang/StringBuilder.toString:()Ljava/lang/String;
     250: invokespecial #83                 // Method java/lang/IllegalArgumentException."<init>":(Ljava/lang/String;)V
     253: athrow
     254: aload_2
     255: iload         5
     257: invokeinterface #75,  2           // InterfaceMethod java/util/List.get:(I)Ljava/lang/Object;
     262: checkcast     #55                 // class java/lang/Integer
     265: invokevirtual #106                // Method java/lang/Integer.intValue:()I
     268: aload_2
     269: iload_3
     270: invokeinterface #75,  2           // InterfaceMethod java/util/List.get:(I)Ljava/lang/Object;
     275: checkcast     #55                 // class java/lang/Integer
     278: invokevirtual #106                // Method java/lang/Integer.intValue:()I
     281: if_icmple     305
     284: aload_1
     285: iload         5
     287: invokeinterface #109,  2          // InterfaceMethod java/util/List.remove:(I)Ljava/lang/Object;
     292: pop
     293: aload_2
     294: iload         5
     296: invokeinterface #109,  2          // InterfaceMethod java/util/List.remove:(I)Ljava/lang/Object;
     301: pop
     302: goto          308
     305: iinc          5, 1
     308: goto          176
     311: iinc          3, 1
     314: goto          149
     317: new           #111                // class io/dekorate/deps/okio/Buffer
     320: dup
     321: invokespecial #112                // Method io/dekorate/deps/okio/Buffer."<init>":()V
     324: astore_3
     325: lconst_0
     326: aload_3
     327: iconst_0
     328: aload_1
     329: iconst_0
     330: aload_1
     331: invokeinterface #53,  1           // InterfaceMethod java/util/List.size:()I
     336: aload_2
     337: invokestatic  #116                // Method buildTrieRecursive:(JLio/dekorate/deps/okio/Buffer;ILjava/util/List;IILjava/util/List;)V
     340: aload_3
     341: invokestatic  #120                // Method intCount:(Lio/dekorate/deps/okio/Buffer;)I
     344: newarray       int
     346: astore        4
     348: iconst_0
     349: istore        5
     351: iload         5
     353: aload         4
     355: arraylength
     356: if_icmpge     374
     359: aload         4
     361: iload         5
     363: aload_3
     364: invokevirtual #124                // Method io/dekorate/deps/okio/Buffer.readInt:()I
     367: iastore
     368: iinc          5, 1
     371: goto          351
     374: aload_3
     375: invokevirtual #128                // Method io/dekorate/deps/okio/Buffer.exhausted:()Z
     378: ifne          389
     381: new           #130                // class java/lang/AssertionError
     384: dup
     385: invokespecial #131                // Method java/lang/AssertionError."<init>":()V
     388: athrow
     389: new           #2                  // class io/dekorate/deps/okio/Options
     392: dup
     393: aload_0
     394: invokevirtual #136                // Method "[Lio/dekorate/deps/okio/ByteString;".clone:()Ljava/lang/Object;
     397: checkcast     #132                // class "[Lio/dekorate/deps/okio/ByteString;"
     400: aload         4
     402: invokespecial #29                 // Method "<init>":([Lio/dekorate/deps/okio/ByteString;[I)V
     405: areturn

  private static void buildTrieRecursive(long, io.dekorate.deps.okio.Buffer, int, java.util.List<io.dekorate.deps.okio.ByteString>, int, int, java.util.List<java.lang.Integer>);
    Code:
       0: iload         5
       2: iload         6
       4: if_icmplt     15
       7: new           #130                // class java/lang/AssertionError
      10: dup
      11: invokespecial #131                // Method java/lang/AssertionError."<init>":()V
      14: athrow
      15: iload         5
      17: istore        8
      19: iload         8
      21: iload         6
      23: if_icmpge     59
      26: aload         4
      28: iload         8
      30: invokeinterface #75,  2           // InterfaceMethod java/util/List.get:(I)Ljava/lang/Object;
      35: checkcast     #27                 // class io/dekorate/deps/okio/ByteString
      38: invokevirtual #76                 // Method io/dekorate/deps/okio/ByteString.size:()I
      41: iload_3
      42: if_icmpge     53
      45: new           #130                // class java/lang/AssertionError
      48: dup
      49: invokespecial #131                // Method java/lang/AssertionError."<init>":()V
      52: athrow
      53: iinc          8, 1
      56: goto          19
      59: aload         4
      61: iload         5
      63: invokeinterface #75,  2           // InterfaceMethod java/util/List.get:(I)Ljava/lang/Object;
      68: checkcast     #27                 // class io/dekorate/deps/okio/ByteString
      71: astore        8
      73: aload         4
      75: iload         6
      77: iconst_1
      78: isub
      79: invokeinterface #75,  2           // InterfaceMethod java/util/List.get:(I)Ljava/lang/Object;
      84: checkcast     #27                 // class io/dekorate/deps/okio/ByteString
      87: astore        9
      89: iconst_m1
      90: istore        10
      92: iload_3
      93: aload         8
      95: invokevirtual #76                 // Method io/dekorate/deps/okio/ByteString.size:()I
      98: if_icmpne     135
     101: aload         7
     103: iload         5
     105: invokeinterface #75,  2           // InterfaceMethod java/util/List.get:(I)Ljava/lang/Object;
     110: checkcast     #55                 // class java/lang/Integer
     113: invokevirtual #106                // Method java/lang/Integer.intValue:()I
     116: istore        10
     118: iinc          5, 1
     121: aload         4
     123: iload         5
     125: invokeinterface #75,  2           // InterfaceMethod java/util/List.get:(I)Ljava/lang/Object;
     130: checkcast     #27                 // class io/dekorate/deps/okio/ByteString
     133: astore        8
     135: aload         8
     137: iload_3
     138: invokevirtual #156                // Method io/dekorate/deps/okio/ByteString.getByte:(I)B
     141: aload         9
     143: iload_3
     144: invokevirtual #156                // Method io/dekorate/deps/okio/ByteString.getByte:(I)B
     147: if_icmpeq     521
     150: iconst_1
     151: istore        11
     153: iload         5
     155: iconst_1
     156: iadd
     157: istore        12
     159: iload         12
     161: iload         6
     163: if_icmpge     212
     166: aload         4
     168: iload         12
     170: iconst_1
     171: isub
     172: invokeinterface #75,  2           // InterfaceMethod java/util/List.get:(I)Ljava/lang/Object;
     177: checkcast     #27                 // class io/dekorate/deps/okio/ByteString
     180: iload_3
     181: invokevirtual #156                // Method io/dekorate/deps/okio/ByteString.getByte:(I)B
     184: aload         4
     186: iload         12
     188: invokeinterface #75,  2           // InterfaceMethod java/util/List.get:(I)Ljava/lang/Object;
     193: checkcast     #27                 // class io/dekorate/deps/okio/ByteString
     196: iload_3
     197: invokevirtual #156                // Method io/dekorate/deps/okio/ByteString.getByte:(I)B
     200: if_icmpeq     206
     203: iinc          11, 1
     206: iinc          12, 1
     209: goto          159
     212: lload_0
     213: aload_2
     214: invokestatic  #120                // Method intCount:(Lio/dekorate/deps/okio/Buffer;)I
     217: i2l
     218: ladd
     219: ldc2_w        #157                // long 2l
     222: ladd
     223: iload         11
     225: iconst_2
     226: imul
     227: i2l
     228: ladd
     229: lstore        12
     231: aload_2
     232: iload         11
     234: invokevirtual #162                // Method io/dekorate/deps/okio/Buffer.writeInt:(I)Lio/dekorate/deps/okio/Buffer;
     237: pop
     238: aload_2
     239: iload         10
     241: invokevirtual #162                // Method io/dekorate/deps/okio/Buffer.writeInt:(I)Lio/dekorate/deps/okio/Buffer;
     244: pop
     245: iload         5
     247: istore        14
     249: iload         14
     251: iload         6
     253: if_icmpge     321
     256: aload         4
     258: iload         14
     260: invokeinterface #75,  2           // InterfaceMethod java/util/List.get:(I)Ljava/lang/Object;
     265: checkcast     #27                 // class io/dekorate/deps/okio/ByteString
     268: iload_3
     269: invokevirtual #156                // Method io/dekorate/deps/okio/ByteString.getByte:(I)B
     272: istore        15
     274: iload         14
     276: iload         5
     278: if_icmpeq     304
     281: iload         15
     283: aload         4
     285: iload         14
     287: iconst_1
     288: isub
     289: invokeinterface #75,  2           // InterfaceMethod java/util/List.get:(I)Ljava/lang/Object;
     294: checkcast     #27                 // class io/dekorate/deps/okio/ByteString
     297: iload_3
     298: invokevirtual #156                // Method io/dekorate/deps/okio/ByteString.getByte:(I)B
     301: if_icmpeq     315
     304: aload_2
     305: iload         15
     307: sipush        255
     310: iand
     311: invokevirtual #162                // Method io/dekorate/deps/okio/Buffer.writeInt:(I)Lio/dekorate/deps/okio/Buffer;
     314: pop
     315: iinc          14, 1
     318: goto          249
     321: new           #111                // class io/dekorate/deps/okio/Buffer
     324: dup
     325: invokespecial #112                // Method io/dekorate/deps/okio/Buffer."<init>":()V
     328: astore        14
     330: iload         5
     332: istore        15
     334: iload         15
     336: iload         6
     338: if_icmpge     507
     341: aload         4
     343: iload         15
     345: invokeinterface #75,  2           // InterfaceMethod java/util/List.get:(I)Ljava/lang/Object;
     350: checkcast     #27                 // class io/dekorate/deps/okio/ByteString
     353: iload_3
     354: invokevirtual #156                // Method io/dekorate/deps/okio/ByteString.getByte:(I)B
     357: istore        16
     359: iload         6
     361: istore        17
     363: iload         15
     365: iconst_1
     366: iadd
     367: istore        18
     369: iload         18
     371: iload         6
     373: if_icmpge     410
     376: iload         16
     378: aload         4
     380: iload         18
     382: invokeinterface #75,  2           // InterfaceMethod java/util/List.get:(I)Ljava/lang/Object;
     387: checkcast     #27                 // class io/dekorate/deps/okio/ByteString
     390: iload_3
     391: invokevirtual #156                // Method io/dekorate/deps/okio/ByteString.getByte:(I)B
     394: if_icmpeq     404
     397: iload         18
     399: istore        17
     401: goto          410
     404: iinc          18, 1
     407: goto          369
     410: iload         15
     412: iconst_1
     413: iadd
     414: iload         17
     416: if_icmpne     463
     419: iload_3
     420: iconst_1
     421: iadd
     422: aload         4
     424: iload         15
     426: invokeinterface #75,  2           // InterfaceMethod java/util/List.get:(I)Ljava/lang/Object;
     431: checkcast     #27                 // class io/dekorate/deps/okio/ByteString
     434: invokevirtual #76                 // Method io/dekorate/deps/okio/ByteString.size:()I
     437: if_icmpne     463
     440: aload_2
     441: aload         7
     443: iload         15
     445: invokeinterface #75,  2           // InterfaceMethod java/util/List.get:(I)Ljava/lang/Object;
     450: checkcast     #55                 // class java/lang/Integer
     453: invokevirtual #106                // Method java/lang/Integer.intValue:()I
     456: invokevirtual #162                // Method io/dekorate/deps/okio/Buffer.writeInt:(I)Lio/dekorate/deps/okio/Buffer;
     459: pop
     460: goto          500
     463: aload_2
     464: ldc2_w        #163                // long -1l
     467: lload         12
     469: aload         14
     471: invokestatic  #120                // Method intCount:(Lio/dekorate/deps/okio/Buffer;)I
     474: i2l
     475: ladd
     476: lmul
     477: l2i
     478: invokevirtual #162                // Method io/dekorate/deps/okio/Buffer.writeInt:(I)Lio/dekorate/deps/okio/Buffer;
     481: pop
     482: lload         12
     484: aload         14
     486: iload_3
     487: iconst_1
     488: iadd
     489: aload         4
     491: iload         15
     493: iload         17
     495: aload         7
     497: invokestatic  #116                // Method buildTrieRecursive:(JLio/dekorate/deps/okio/Buffer;ILjava/util/List;IILjava/util/List;)V
     500: iload         17
     502: istore        15
     504: goto          334
     507: aload_2
     508: aload         14
     510: aload         14
     512: invokevirtual #167                // Method io/dekorate/deps/okio/Buffer.size:()J
     515: invokevirtual #171                // Method io/dekorate/deps/okio/Buffer.write:(Lio/dekorate/deps/okio/Buffer;J)V
     518: goto          763
     521: iconst_0
     522: istore        11
     524: iload_3
     525: istore        12
     527: aload         8
     529: invokevirtual #76                 // Method io/dekorate/deps/okio/ByteString.size:()I
     532: aload         9
     534: invokevirtual #76                 // Method io/dekorate/deps/okio/ByteString.size:()I
     537: invokestatic  #177                // Method java/lang/Math.min:(II)I
     540: istore        13
     542: iload         12
     544: iload         13
     546: if_icmpge     575
     549: aload         8
     551: iload         12
     553: invokevirtual #156                // Method io/dekorate/deps/okio/ByteString.getByte:(I)B
     556: aload         9
     558: iload         12
     560: invokevirtual #156                // Method io/dekorate/deps/okio/ByteString.getByte:(I)B
     563: if_icmpne     575
     566: iinc          11, 1
     569: iinc          12, 1
     572: goto          542
     575: lload_0
     576: aload_2
     577: invokestatic  #120                // Method intCount:(Lio/dekorate/deps/okio/Buffer;)I
     580: i2l
     581: ladd
     582: ldc2_w        #157                // long 2l
     585: ladd
     586: iload         11
     588: i2l
     589: ladd
     590: lconst_1
     591: ladd
     592: lstore        12
     594: aload_2
     595: iload         11
     597: ineg
     598: invokevirtual #162                // Method io/dekorate/deps/okio/Buffer.writeInt:(I)Lio/dekorate/deps/okio/Buffer;
     601: pop
     602: aload_2
     603: iload         10
     605: invokevirtual #162                // Method io/dekorate/deps/okio/Buffer.writeInt:(I)Lio/dekorate/deps/okio/Buffer;
     608: pop
     609: iload_3
     610: istore        14
     612: iload         14
     614: iload_3
     615: iload         11
     617: iadd
     618: if_icmpge     643
     621: aload_2
     622: aload         8
     624: iload         14
     626: invokevirtual #156                // Method io/dekorate/deps/okio/ByteString.getByte:(I)B
     629: sipush        255
     632: iand
     633: invokevirtual #162                // Method io/dekorate/deps/okio/Buffer.writeInt:(I)Lio/dekorate/deps/okio/Buffer;
     636: pop
     637: iinc          14, 1
     640: goto          612
     643: iload         5
     645: iconst_1
     646: iadd
     647: iload         6
     649: if_icmpne     705
     652: iload_3
     653: iload         11
     655: iadd
     656: aload         4
     658: iload         5
     660: invokeinterface #75,  2           // InterfaceMethod java/util/List.get:(I)Ljava/lang/Object;
     665: checkcast     #27                 // class io/dekorate/deps/okio/ByteString
     668: invokevirtual #76                 // Method io/dekorate/deps/okio/ByteString.size:()I
     671: if_icmpeq     682
     674: new           #130                // class java/lang/AssertionError
     677: dup
     678: invokespecial #131                // Method java/lang/AssertionError."<init>":()V
     681: athrow
     682: aload_2
     683: aload         7
     685: iload         5
     687: invokeinterface #75,  2           // InterfaceMethod java/util/List.get:(I)Ljava/lang/Object;
     692: checkcast     #55                 // class java/lang/Integer
     695: invokevirtual #106                // Method java/lang/Integer.intValue:()I
     698: invokevirtual #162                // Method io/dekorate/deps/okio/Buffer.writeInt:(I)Lio/dekorate/deps/okio/Buffer;
     701: pop
     702: goto          763
     705: new           #111                // class io/dekorate/deps/okio/Buffer
     708: dup
     709: invokespecial #112                // Method io/dekorate/deps/okio/Buffer."<init>":()V
     712: astore        14
     714: aload_2
     715: ldc2_w        #163                // long -1l
     718: lload         12
     720: aload         14
     722: invokestatic  #120                // Method intCount:(Lio/dekorate/deps/okio/Buffer;)I
     725: i2l
     726: ladd
     727: lmul
     728: l2i
     729: invokevirtual #162                // Method io/dekorate/deps/okio/Buffer.writeInt:(I)Lio/dekorate/deps/okio/Buffer;
     732: pop
     733: lload         12
     735: aload         14
     737: iload_3
     738: iload         11
     740: iadd
     741: aload         4
     743: iload         5
     745: iload         6
     747: aload         7
     749: invokestatic  #116                // Method buildTrieRecursive:(JLio/dekorate/deps/okio/Buffer;ILjava/util/List;IILjava/util/List;)V
     752: aload_2
     753: aload         14
     755: aload         14
     757: invokevirtual #167                // Method io/dekorate/deps/okio/Buffer.size:()J
     760: invokevirtual #171                // Method io/dekorate/deps/okio/Buffer.write:(Lio/dekorate/deps/okio/Buffer;J)V
     763: return

  public io.dekorate.deps.okio.ByteString get(int);
    Code:
       0: aload_0
       1: getfield      #19                 // Field byteStrings:[Lio/dekorate/deps/okio/ByteString;
       4: iload_1
       5: aaload
       6: areturn

  public final int size();
    Code:
       0: aload_0
       1: getfield      #19                 // Field byteStrings:[Lio/dekorate/deps/okio/ByteString;
       4: arraylength
       5: ireturn

  private static int intCount(io.dekorate.deps.okio.Buffer);
    Code:
       0: aload_0
       1: invokevirtual #167                // Method io/dekorate/deps/okio/Buffer.size:()J
       4: ldc2_w        #197                // long 4l
       7: ldiv
       8: l2i
       9: ireturn

  public java.lang.Object get(int);
    Code:
       0: aload_0
       1: iload_1
       2: invokevirtual #200                // Method get:(I)Lio/dekorate/deps/okio/ByteString;
       5: areturn
}
