Compiled from "DefaultWebFluxTagsProvider.java"
public class org.springframework.boot.actuate.metrics.web.reactive.server.DefaultWebFluxTagsProvider implements org.springframework.boot.actuate.metrics.web.reactive.server.WebFluxTagsProvider {
  public org.springframework.boot.actuate.metrics.web.reactive.server.DefaultWebFluxTagsProvider();
    Code:
       0: aload_0
       1: invokespecial #1                  // Method java/lang/Object."<init>":()V
       4: return

  public java.lang.Iterable<io.micrometer.core.instrument.Tag> httpRequestTags(org.springframework.web.server.ServerWebExchange, java.lang.Throwable);
    Code:
       0: iconst_5
       1: anewarray     #2                  // class io/micrometer/core/instrument/Tag
       4: dup
       5: iconst_0
       6: aload_1
       7: invokestatic  #3                  // Method org/springframework/boot/actuate/metrics/web/reactive/server/WebFluxTags.method:(Lorg/springframework/web/server/ServerWebExchange;)Lio/micrometer/core/instrument/Tag;
      10: aastore
      11: dup
      12: iconst_1
      13: aload_1
      14: invokestatic  #4                  // Method org/springframework/boot/actuate/metrics/web/reactive/server/WebFluxTags.uri:(Lorg/springframework/web/server/ServerWebExchange;)Lio/micrometer/core/instrument/Tag;
      17: aastore
      18: dup
      19: iconst_2
      20: aload_2
      21: invokestatic  #5                  // Method org/springframework/boot/actuate/metrics/web/reactive/server/WebFluxTags.exception:(Ljava/lang/Throwable;)Lio/micrometer/core/instrument/Tag;
      24: aastore
      25: dup
      26: iconst_3
      27: aload_1
      28: invokestatic  #6                  // Method org/springframework/boot/actuate/metrics/web/reactive/server/WebFluxTags.status:(Lorg/springframework/web/server/ServerWebExchange;)Lio/micrometer/core/instrument/Tag;
      31: aastore
      32: dup
      33: iconst_4
      34: aload_1
      35: invokestatic  #7                  // Method org/springframework/boot/actuate/metrics/web/reactive/server/WebFluxTags.outcome:(Lorg/springframework/web/server/ServerWebExchange;)Lio/micrometer/core/instrument/Tag;
      38: aastore
      39: invokestatic  #8                  // Method java/util/Arrays.asList:([Ljava/lang/Object;)Ljava/util/List;
      42: areturn
}
