Compiled from "WeldRuntime.java"
public class org.jboss.weld.bootstrap.WeldRuntime {
  private org.jboss.weld.manager.BeanManagerImpl deploymentManager;

  private java.util.concurrent.ConcurrentMap<org.jboss.weld.bootstrap.spi.BeanDeploymentArchive, org.jboss.weld.manager.BeanManagerImpl> bdaToBeanManagerMap;

  private java.lang.String contextId;

  public org.jboss.weld.bootstrap.WeldRuntime(java.lang.String, org.jboss.weld.manager.BeanManagerImpl, java.util.concurrent.ConcurrentMap<org.jboss.weld.bootstrap.spi.BeanDeploymentArchive, org.jboss.weld.manager.BeanManagerImpl>);
    Code:
       0: aload_0
       1: invokespecial #1                  // Method java/lang/Object."<init>":()V
       4: aload_0
       5: aload_1
       6: putfield      #2                  // Field contextId:Ljava/lang/String;
       9: aload_0
      10: aload_2
      11: putfield      #3                  // Field deploymentManager:Lorg/jboss/weld/manager/BeanManagerImpl;
      14: aload_0
      15: aload_3
      16: putfield      #4                  // Field bdaToBeanManagerMap:Ljava/util/concurrent/ConcurrentMap;
      19: return

  public org.jboss.weld.manager.BeanManagerImpl getManager(org.jboss.weld.bootstrap.spi.BeanDeploymentArchive);
    Code:
       0: aload_0
       1: getfield      #4                  // Field bdaToBeanManagerMap:Ljava/util/concurrent/ConcurrentMap;
       4: aload_1
       5: invokeinterface #5,  2            // InterfaceMethod java/util/concurrent/ConcurrentMap.get:(Ljava/lang/Object;)Ljava/lang/Object;
      10: checkcast     #6                  // class org/jboss/weld/manager/BeanManagerImpl
      13: astore_2
      14: aload_2
      15: ifnonnull     22
      18: aconst_null
      19: goto          26
      22: aload_2
      23: invokevirtual #7                  // Method org/jboss/weld/manager/BeanManagerImpl.getCurrent:()Lorg/jboss/weld/manager/BeanManagerImpl;
      26: areturn

  public void shutdown();
    Code:
       0: aload_0
       1: getfield      #3                  // Field deploymentManager:Lorg/jboss/weld/manager/BeanManagerImpl;
       4: invokevirtual #8                  // Method org/jboss/weld/manager/BeanManagerImpl.instance:()Ljavax/enterprise/inject/Instance;
       7: ldc           #9                  // class org/jboss/weld/context/ApplicationContext
       9: iconst_0
      10: anewarray     #10                 // class java/lang/annotation/Annotation
      13: invokeinterface #11,  3           // InterfaceMethod javax/enterprise/inject/Instance.select:(Ljava/lang/Class;[Ljava/lang/annotation/Annotation;)Ljavax/enterprise/inject/Instance;
      18: invokeinterface #12,  1           // InterfaceMethod javax/enterprise/inject/Instance.get:()Ljava/lang/Object;
      23: checkcast     #9                  // class org/jboss/weld/context/ApplicationContext
      26: invokeinterface #13,  1           // InterfaceMethod org/jboss/weld/context/ApplicationContext.invalidate:()V
      31: aload_0
      32: getfield      #3                  // Field deploymentManager:Lorg/jboss/weld/manager/BeanManagerImpl;
      35: invokevirtual #8                  // Method org/jboss/weld/manager/BeanManagerImpl.instance:()Ljavax/enterprise/inject/Instance;
      38: ldc           #14                 // class org/jboss/weld/context/SingletonContext
      40: iconst_0
      41: anewarray     #10                 // class java/lang/annotation/Annotation
      44: invokeinterface #11,  3           // InterfaceMethod javax/enterprise/inject/Instance.select:(Ljava/lang/Class;[Ljava/lang/annotation/Annotation;)Ljavax/enterprise/inject/Instance;
      49: invokeinterface #12,  1           // InterfaceMethod javax/enterprise/inject/Instance.get:()Ljava/lang/Object;
      54: checkcast     #14                 // class org/jboss/weld/context/SingletonContext
      57: invokeinterface #15,  1           // InterfaceMethod org/jboss/weld/context/SingletonContext.invalidate:()V
      62: aload_0
      63: getfield      #3                  // Field deploymentManager:Lorg/jboss/weld/manager/BeanManagerImpl;
      66: invokevirtual #16                 // Method org/jboss/weld/manager/BeanManagerImpl.getServices:()Lorg/jboss/weld/bootstrap/api/ServiceRegistry;
      69: ldc           #17                 // class org/jboss/weld/bootstrap/BeanDeploymentModules
      71: invokeinterface #18,  2           // InterfaceMethod org/jboss/weld/bootstrap/api/ServiceRegistry.get:(Ljava/lang/Class;)Lorg/jboss/weld/bootstrap/api/Service;
      76: checkcast     #17                 // class org/jboss/weld/bootstrap/BeanDeploymentModules
      79: invokevirtual #19                 // Method org/jboss/weld/bootstrap/BeanDeploymentModules.iterator:()Ljava/util/Iterator;
      82: astore_1
      83: aload_1
      84: invokeinterface #20,  1           // InterfaceMethod java/util/Iterator.hasNext:()Z
      89: ifeq          131
      92: aload_1
      93: invokeinterface #21,  1           // InterfaceMethod java/util/Iterator.next:()Ljava/lang/Object;
      98: checkcast     #22                 // class org/jboss/weld/bootstrap/BeanDeploymentModule
     101: astore_2
     102: aload_2
     103: invokevirtual #23                 // Method org/jboss/weld/bootstrap/BeanDeploymentModule.isWebModule:()Z
     106: ifne          128
     109: aload_2
     110: ldc           #24                 // class java/lang/Object
     112: getstatic     #25                 // Field org/jboss/weld/event/ContextEvent.APPLICATION_DESTROYED:Lorg/jboss/weld/event/ContextEvent;
     115: iconst_1
     116: anewarray     #10                 // class java/lang/annotation/Annotation
     119: dup
     120: iconst_0
     121: getstatic     #26                 // Field org/jboss/weld/literal/DestroyedLiteral.APPLICATION:Lorg/jboss/weld/literal/DestroyedLiteral;
     124: aastore
     125: invokevirtual #27                 // Method org/jboss/weld/bootstrap/BeanDeploymentModule.fireEvent:(Ljava/lang/reflect/Type;Ljava/lang/Object;[Ljava/lang/annotation/Annotation;)V
     128: goto          83
     131: goto          135
     134: astore_1
     135: aload_0
     136: getfield      #3                  // Field deploymentManager:Lorg/jboss/weld/manager/BeanManagerImpl;
     139: invokestatic  #29                 // Method org/jboss/weld/bootstrap/events/BeforeShutdownImpl.fire:(Lorg/jboss/weld/manager/BeanManagerImpl;)V
     142: aload_0
     143: getfield      #2                  // Field contextId:Ljava/lang/String;
     146: invokestatic  #30                 // Method org/jboss/weld/Container.instance:(Ljava/lang/String;)Lorg/jboss/weld/Container;
     149: astore_1
     150: aload_1
     151: getstatic     #31                 // Field org/jboss/weld/ContainerState.SHUTDOWN:Lorg/jboss/weld/ContainerState;
     154: invokevirtual #32                 // Method org/jboss/weld/Container.setState:(Lorg/jboss/weld/ContainerState;)V
     157: aload_1
     158: invokevirtual #33                 // Method org/jboss/weld/Container.cleanup:()V
     161: goto          189
     164: astore_3
     165: aload_0
     166: getfield      #2                  // Field contextId:Ljava/lang/String;
     169: invokestatic  #30                 // Method org/jboss/weld/Container.instance:(Ljava/lang/String;)Lorg/jboss/weld/Container;
     172: astore        4
     174: aload         4
     176: getstatic     #31                 // Field org/jboss/weld/ContainerState.SHUTDOWN:Lorg/jboss/weld/ContainerState;
     179: invokevirtual #32                 // Method org/jboss/weld/Container.setState:(Lorg/jboss/weld/ContainerState;)V
     182: aload         4
     184: invokevirtual #33                 // Method org/jboss/weld/Container.cleanup:()V
     187: aload_3
     188: athrow
     189: goto          336
     192: astore        5
     194: aload_0
     195: getfield      #3                  // Field deploymentManager:Lorg/jboss/weld/manager/BeanManagerImpl;
     198: invokevirtual #16                 // Method org/jboss/weld/manager/BeanManagerImpl.getServices:()Lorg/jboss/weld/bootstrap/api/ServiceRegistry;
     201: ldc           #17                 // class org/jboss/weld/bootstrap/BeanDeploymentModules
     203: invokeinterface #18,  2           // InterfaceMethod org/jboss/weld/bootstrap/api/ServiceRegistry.get:(Ljava/lang/Class;)Lorg/jboss/weld/bootstrap/api/Service;
     208: checkcast     #17                 // class org/jboss/weld/bootstrap/BeanDeploymentModules
     211: invokevirtual #19                 // Method org/jboss/weld/bootstrap/BeanDeploymentModules.iterator:()Ljava/util/Iterator;
     214: astore        6
     216: aload         6
     218: invokeinterface #20,  1           // InterfaceMethod java/util/Iterator.hasNext:()Z
     223: ifeq          269
     226: aload         6
     228: invokeinterface #21,  1           // InterfaceMethod java/util/Iterator.next:()Ljava/lang/Object;
     233: checkcast     #22                 // class org/jboss/weld/bootstrap/BeanDeploymentModule
     236: astore        7
     238: aload         7
     240: invokevirtual #23                 // Method org/jboss/weld/bootstrap/BeanDeploymentModule.isWebModule:()Z
     243: ifne          266
     246: aload         7
     248: ldc           #24                 // class java/lang/Object
     250: getstatic     #25                 // Field org/jboss/weld/event/ContextEvent.APPLICATION_DESTROYED:Lorg/jboss/weld/event/ContextEvent;
     253: iconst_1
     254: anewarray     #10                 // class java/lang/annotation/Annotation
     257: dup
     258: iconst_0
     259: getstatic     #26                 // Field org/jboss/weld/literal/DestroyedLiteral.APPLICATION:Lorg/jboss/weld/literal/DestroyedLiteral;
     262: aastore
     263: invokevirtual #27                 // Method org/jboss/weld/bootstrap/BeanDeploymentModule.fireEvent:(Ljava/lang/reflect/Type;Ljava/lang/Object;[Ljava/lang/annotation/Annotation;)V
     266: goto          216
     269: goto          274
     272: astore        6
     274: aload_0
     275: getfield      #3                  // Field deploymentManager:Lorg/jboss/weld/manager/BeanManagerImpl;
     278: invokestatic  #29                 // Method org/jboss/weld/bootstrap/events/BeforeShutdownImpl.fire:(Lorg/jboss/weld/manager/BeanManagerImpl;)V
     281: aload_0
     282: getfield      #2                  // Field contextId:Ljava/lang/String;
     285: invokestatic  #30                 // Method org/jboss/weld/Container.instance:(Ljava/lang/String;)Lorg/jboss/weld/Container;
     288: astore        6
     290: aload         6
     292: getstatic     #31                 // Field org/jboss/weld/ContainerState.SHUTDOWN:Lorg/jboss/weld/ContainerState;
     295: invokevirtual #32                 // Method org/jboss/weld/Container.setState:(Lorg/jboss/weld/ContainerState;)V
     298: aload         6
     300: invokevirtual #33                 // Method org/jboss/weld/Container.cleanup:()V
     303: goto          333
     306: astore        8
     308: aload_0
     309: getfield      #2                  // Field contextId:Ljava/lang/String;
     312: invokestatic  #30                 // Method org/jboss/weld/Container.instance:(Ljava/lang/String;)Lorg/jboss/weld/Container;
     315: astore        9
     317: aload         9
     319: getstatic     #31                 // Field org/jboss/weld/ContainerState.SHUTDOWN:Lorg/jboss/weld/ContainerState;
     322: invokevirtual #32                 // Method org/jboss/weld/Container.setState:(Lorg/jboss/weld/ContainerState;)V
     325: aload         9
     327: invokevirtual #33                 // Method org/jboss/weld/Container.cleanup:()V
     330: aload         8
     332: athrow
     333: aload         5
     335: athrow
     336: return
    Exception table:
       from    to  target type
          62   131   134   Class java/lang/Exception
         135   142   164   any
           0    62   192   any
         194   269   272   Class java/lang/Exception
         274   281   306   any
         306   308   306   any
         192   194   192   any
}
