Compiled from "RouterMetrics.java"
public class org.springframework.integration.support.management.RouterMetrics extends org.springframework.integration.support.management.LifecycleMessageHandlerMetrics implements org.springframework.integration.support.management.MappingMessageRouterManagement {
  private final org.springframework.integration.support.management.MappingMessageRouterManagement router;

  public org.springframework.integration.support.management.RouterMetrics(org.springframework.context.Lifecycle, org.springframework.integration.support.management.MappingMessageRouterManagement);
    Code:
       0: aload_0
       1: aload_1
       2: aload_2
       3: checkcast     #1                  // class org/springframework/integration/support/management/MessageHandlerMetrics
       6: invokespecial #2                  // Method org/springframework/integration/support/management/LifecycleMessageHandlerMetrics."<init>":(Lorg/springframework/context/Lifecycle;Lorg/springframework/integration/support/management/MessageHandlerMetrics;)V
       9: aload_0
      10: aload_2
      11: putfield      #3                  // Field router:Lorg/springframework/integration/support/management/MappingMessageRouterManagement;
      14: return

  public void setChannelMapping(java.lang.String, java.lang.String);
    Code:
       0: aload_0
       1: getfield      #3                  // Field router:Lorg/springframework/integration/support/management/MappingMessageRouterManagement;
       4: aload_1
       5: aload_2
       6: invokeinterface #4,  3            // InterfaceMethod org/springframework/integration/support/management/MappingMessageRouterManagement.setChannelMapping:(Ljava/lang/String;Ljava/lang/String;)V
      11: return

  public void removeChannelMapping(java.lang.String);
    Code:
       0: aload_0
       1: getfield      #3                  // Field router:Lorg/springframework/integration/support/management/MappingMessageRouterManagement;
       4: aload_1
       5: invokeinterface #5,  2            // InterfaceMethod org/springframework/integration/support/management/MappingMessageRouterManagement.removeChannelMapping:(Ljava/lang/String;)V
      10: return

  public void replaceChannelMappings(java.util.Properties);
    Code:
       0: aload_0
       1: getfield      #3                  // Field router:Lorg/springframework/integration/support/management/MappingMessageRouterManagement;
       4: aload_1
       5: invokeinterface #6,  2            // InterfaceMethod org/springframework/integration/support/management/MappingMessageRouterManagement.replaceChannelMappings:(Ljava/util/Properties;)V
      10: return

  public java.util.Map<java.lang.String, java.lang.String> getChannelMappings();
    Code:
       0: aload_0
       1: getfield      #3                  // Field router:Lorg/springframework/integration/support/management/MappingMessageRouterManagement;
       4: invokeinterface #7,  1            // InterfaceMethod org/springframework/integration/support/management/MappingMessageRouterManagement.getChannelMappings:()Ljava/util/Map;
       9: areturn

  public void setChannelMappings(java.util.Map<java.lang.String, java.lang.String>);
    Code:
       0: aload_0
       1: getfield      #3                  // Field router:Lorg/springframework/integration/support/management/MappingMessageRouterManagement;
       4: aload_1
       5: invokeinterface #8,  2            // InterfaceMethod org/springframework/integration/support/management/MappingMessageRouterManagement.setChannelMappings:(Ljava/util/Map;)V
      10: return

  public java.util.Collection<java.lang.String> getDynamicChannelNames();
    Code:
       0: aload_0
       1: getfield      #3                  // Field router:Lorg/springframework/integration/support/management/MappingMessageRouterManagement;
       4: invokeinterface #9,  1            // InterfaceMethod org/springframework/integration/support/management/MappingMessageRouterManagement.getDynamicChannelNames:()Ljava/util/Collection;
       9: areturn
}
