Compiled from "BOMStripperInputStream.java"
public class net.jangaroo.utils.BOMStripperInputStream extends java.io.PushbackInputStream {
  private static final int[][] BOMS;

  private static int testForBOM(int[], int[]);
    Code:
       0: iconst_0
       1: istore_2
       2: iload_2
       3: aload_0
       4: arraylength
       5: if_icmpge     25
       8: aload_0
       9: iload_2
      10: iaload
      11: aload_1
      12: iload_2
      13: iaload
      14: if_icmpeq     19
      17: iconst_0
      18: ireturn
      19: iinc          2, 1
      22: goto          2
      25: aload_0
      26: arraylength
      27: ireturn

  public net.jangaroo.utils.BOMStripperInputStream(java.io.InputStream) throws java.io.IOException;
    Code:
       0: aload_0
       1: aload_1
       2: iconst_4
       3: invokespecial #1                  // Method java/io/PushbackInputStream."<init>":(Ljava/io/InputStream;I)V
       6: iconst_4
       7: newarray       int
       9: dup
      10: iconst_0
      11: aload_0
      12: invokevirtual #2                  // Method read:()I
      15: iastore
      16: dup
      17: iconst_1
      18: aload_0
      19: invokevirtual #2                  // Method read:()I
      22: iastore
      23: dup
      24: iconst_2
      25: aload_0
      26: invokevirtual #2                  // Method read:()I
      29: iastore
      30: dup
      31: iconst_3
      32: aload_0
      33: invokevirtual #2                  // Method read:()I
      36: iastore
      37: astore_2
      38: iconst_0
      39: istore_3
      40: getstatic     #3                  // Field BOMS:[[I
      43: astore        4
      45: aload         4
      47: arraylength
      48: istore        5
      50: iconst_0
      51: istore        6
      53: iload         6
      55: iload         5
      57: if_icmpge     87
      60: aload         4
      62: iload         6
      64: aaload
      65: astore        7
      67: aload         7
      69: aload_2
      70: invokestatic  #4                  // Method testForBOM:([I[I)I
      73: istore_3
      74: iload_3
      75: ifeq          81
      78: goto          87
      81: iinc          6, 1
      84: goto          53
      87: aload_2
      88: arraylength
      89: iconst_1
      90: isub
      91: istore        4
      93: iload         4
      95: iload_3
      96: if_icmplt     121
      99: aload_2
     100: iload         4
     102: iaload
     103: iconst_m1
     104: if_icmpeq     115
     107: aload_0
     108: aload_2
     109: iload         4
     111: iaload
     112: invokevirtual #5                  // Method unread:(I)V
     115: iinc          4, -1
     118: goto          93
     121: return

  static {};
    Code:
       0: bipush        12
       2: anewarray     #6                  // class "[I"
       5: dup
       6: iconst_0
       7: iconst_4
       8: newarray       int
      10: dup
      11: iconst_0
      12: iconst_0
      13: iastore
      14: dup
      15: iconst_1
      16: iconst_0
      17: iastore
      18: dup
      19: iconst_2
      20: sipush        254
      23: iastore
      24: dup
      25: iconst_3
      26: sipush        255
      29: iastore
      30: aastore
      31: dup
      32: iconst_1
      33: iconst_4
      34: newarray       int
      36: dup
      37: iconst_0
      38: sipush        255
      41: iastore
      42: dup
      43: iconst_1
      44: sipush        254
      47: iastore
      48: dup
      49: iconst_2
      50: iconst_0
      51: iastore
      52: dup
      53: iconst_3
      54: iconst_0
      55: iastore
      56: aastore
      57: dup
      58: iconst_2
      59: iconst_4
      60: newarray       int
      62: dup
      63: iconst_0
      64: bipush        43
      66: iastore
      67: dup
      68: iconst_1
      69: bipush        47
      71: iastore
      72: dup
      73: iconst_2
      74: bipush        118
      76: iastore
      77: dup
      78: iconst_3
      79: bipush        56
      81: iastore
      82: aastore
      83: dup
      84: iconst_3
      85: iconst_4
      86: newarray       int
      88: dup
      89: iconst_0
      90: bipush        43
      92: iastore
      93: dup
      94: iconst_1
      95: bipush        47
      97: iastore
      98: dup
      99: iconst_2
     100: bipush        118
     102: iastore
     103: dup
     104: iconst_3
     105: bipush        57
     107: iastore
     108: aastore
     109: dup
     110: iconst_4
     111: iconst_4
     112: newarray       int
     114: dup
     115: iconst_0
     116: bipush        43
     118: iastore
     119: dup
     120: iconst_1
     121: bipush        47
     123: iastore
     124: dup
     125: iconst_2
     126: bipush        118
     128: iastore
     129: dup
     130: iconst_3
     131: bipush        43
     133: iastore
     134: aastore
     135: dup
     136: iconst_5
     137: iconst_4
     138: newarray       int
     140: dup
     141: iconst_0
     142: bipush        43
     144: iastore
     145: dup
     146: iconst_1
     147: bipush        47
     149: iastore
     150: dup
     151: iconst_2
     152: bipush        118
     154: iastore
     155: dup
     156: iconst_3
     157: bipush        47
     159: iastore
     160: aastore
     161: dup
     162: bipush        6
     164: iconst_4
     165: newarray       int
     167: dup
     168: iconst_0
     169: sipush        221
     172: iastore
     173: dup
     174: iconst_1
     175: bipush        115
     177: iastore
     178: dup
     179: iconst_2
     180: bipush        102
     182: iastore
     183: dup
     184: iconst_3
     185: bipush        115
     187: iastore
     188: aastore
     189: dup
     190: bipush        7
     192: iconst_3
     193: newarray       int
     195: dup
     196: iconst_0
     197: sipush        239
     200: iastore
     201: dup
     202: iconst_1
     203: sipush        187
     206: iastore
     207: dup
     208: iconst_2
     209: sipush        191
     212: iastore
     213: aastore
     214: dup
     215: bipush        8
     217: iconst_3
     218: newarray       int
     220: dup
     221: iconst_0
     222: bipush        14
     224: iastore
     225: dup
     226: iconst_1
     227: sipush        254
     230: iastore
     231: dup
     232: iconst_2
     233: sipush        255
     236: iastore
     237: aastore
     238: dup
     239: bipush        9
     241: iconst_3
     242: newarray       int
     244: dup
     245: iconst_0
     246: sipush        251
     249: iastore
     250: dup
     251: iconst_1
     252: sipush        238
     255: iastore
     256: dup
     257: iconst_2
     258: bipush        40
     260: iastore
     261: aastore
     262: dup
     263: bipush        10
     265: iconst_2
     266: newarray       int
     268: dup
     269: iconst_0
     270: sipush        254
     273: iastore
     274: dup
     275: iconst_1
     276: sipush        255
     279: iastore
     280: aastore
     281: dup
     282: bipush        11
     284: iconst_2
     285: newarray       int
     287: dup
     288: iconst_0
     289: sipush        255
     292: iastore
     293: dup
     294: iconst_1
     295: sipush        254
     298: iastore
     299: aastore
     300: putstatic     #3                  // Field BOMS:[[I
     303: return
}
