Compiled from "Projections.java"
public final class org.hibernate.criterion.Projections {
  public static org.hibernate.criterion.PropertyProjection property(java.lang.String);
    Code:
       0: new           #1                  // class org/hibernate/criterion/PropertyProjection
       3: dup
       4: aload_0
       5: invokespecial #2                  // Method org/hibernate/criterion/PropertyProjection."<init>":(Ljava/lang/String;)V
       8: areturn

  public static org.hibernate.criterion.PropertyProjection groupProperty(java.lang.String);
    Code:
       0: new           #1                  // class org/hibernate/criterion/PropertyProjection
       3: dup
       4: aload_0
       5: iconst_1
       6: invokespecial #3                  // Method org/hibernate/criterion/PropertyProjection."<init>":(Ljava/lang/String;Z)V
       9: areturn

  public static org.hibernate.criterion.IdentifierProjection id();
    Code:
       0: new           #4                  // class org/hibernate/criterion/IdentifierProjection
       3: dup
       4: invokespecial #5                  // Method org/hibernate/criterion/IdentifierProjection."<init>":()V
       7: areturn

  public static org.hibernate.criterion.Projection distinct(org.hibernate.criterion.Projection);
    Code:
       0: new           #6                  // class org/hibernate/criterion/Distinct
       3: dup
       4: aload_0
       5: invokespecial #7                  // Method org/hibernate/criterion/Distinct."<init>":(Lorg/hibernate/criterion/Projection;)V
       8: areturn

  public static org.hibernate.criterion.ProjectionList projectionList();
    Code:
       0: new           #8                  // class org/hibernate/criterion/ProjectionList
       3: dup
       4: invokespecial #9                  // Method org/hibernate/criterion/ProjectionList."<init>":()V
       7: areturn

  public static org.hibernate.criterion.Projection rowCount();
    Code:
       0: new           #10                 // class org/hibernate/criterion/RowCountProjection
       3: dup
       4: invokespecial #11                 // Method org/hibernate/criterion/RowCountProjection."<init>":()V
       7: areturn

  public static org.hibernate.criterion.CountProjection count(java.lang.String);
    Code:
       0: new           #12                 // class org/hibernate/criterion/CountProjection
       3: dup
       4: aload_0
       5: invokespecial #13                 // Method org/hibernate/criterion/CountProjection."<init>":(Ljava/lang/String;)V
       8: areturn

  public static org.hibernate.criterion.CountProjection countDistinct(java.lang.String);
    Code:
       0: new           #12                 // class org/hibernate/criterion/CountProjection
       3: dup
       4: aload_0
       5: invokespecial #13                 // Method org/hibernate/criterion/CountProjection."<init>":(Ljava/lang/String;)V
       8: invokevirtual #14                 // Method org/hibernate/criterion/CountProjection.setDistinct:()Lorg/hibernate/criterion/CountProjection;
      11: areturn

  public static org.hibernate.criterion.AggregateProjection max(java.lang.String);
    Code:
       0: new           #15                 // class org/hibernate/criterion/AggregateProjection
       3: dup
       4: ldc           #16                 // String max
       6: aload_0
       7: invokespecial #17                 // Method org/hibernate/criterion/AggregateProjection."<init>":(Ljava/lang/String;Ljava/lang/String;)V
      10: areturn

  public static org.hibernate.criterion.AggregateProjection min(java.lang.String);
    Code:
       0: new           #15                 // class org/hibernate/criterion/AggregateProjection
       3: dup
       4: ldc           #18                 // String min
       6: aload_0
       7: invokespecial #17                 // Method org/hibernate/criterion/AggregateProjection."<init>":(Ljava/lang/String;Ljava/lang/String;)V
      10: areturn

  public static org.hibernate.criterion.AggregateProjection avg(java.lang.String);
    Code:
       0: new           #19                 // class org/hibernate/criterion/AvgProjection
       3: dup
       4: aload_0
       5: invokespecial #20                 // Method org/hibernate/criterion/AvgProjection."<init>":(Ljava/lang/String;)V
       8: areturn

  public static org.hibernate.criterion.AggregateProjection sum(java.lang.String);
    Code:
       0: new           #15                 // class org/hibernate/criterion/AggregateProjection
       3: dup
       4: ldc           #21                 // String sum
       6: aload_0
       7: invokespecial #17                 // Method org/hibernate/criterion/AggregateProjection."<init>":(Ljava/lang/String;Ljava/lang/String;)V
      10: areturn

  public static org.hibernate.criterion.Projection alias(org.hibernate.criterion.Projection, java.lang.String);
    Code:
       0: new           #22                 // class org/hibernate/criterion/AliasedProjection
       3: dup
       4: aload_0
       5: aload_1
       6: invokespecial #23                 // Method org/hibernate/criterion/AliasedProjection."<init>":(Lorg/hibernate/criterion/Projection;Ljava/lang/String;)V
       9: areturn

  public static org.hibernate.criterion.Projection sqlProjection(java.lang.String, java.lang.String[], org.hibernate.type.Type[]);
    Code:
       0: new           #24                 // class org/hibernate/criterion/SQLProjection
       3: dup
       4: aload_0
       5: aload_1
       6: aload_2
       7: invokespecial #25                 // Method org/hibernate/criterion/SQLProjection."<init>":(Ljava/lang/String;[Ljava/lang/String;[Lorg/hibernate/type/Type;)V
      10: areturn

  public static org.hibernate.criterion.Projection sqlGroupProjection(java.lang.String, java.lang.String, java.lang.String[], org.hibernate.type.Type[]);
    Code:
       0: new           #24                 // class org/hibernate/criterion/SQLProjection
       3: dup
       4: aload_0
       5: aload_1
       6: aload_2
       7: aload_3
       8: invokespecial #26                 // Method org/hibernate/criterion/SQLProjection."<init>":(Ljava/lang/String;Ljava/lang/String;[Ljava/lang/String;[Lorg/hibernate/type/Type;)V
      11: areturn

  private org.hibernate.criterion.Projections();
    Code:
       0: aload_0
       1: invokespecial #27                 // Method java/lang/Object."<init>":()V
       4: return
}
