Compiled from "JmsManager.java"
class org.apache.logging.log4j.core.appender.mom.JmsManager$Reconnector extends org.apache.logging.log4j.core.util.Log4jThread {
  private final java.util.concurrent.CountDownLatch latch;

  private volatile boolean shutdown;

  private final java.lang.Object owner;

  final org.apache.logging.log4j.core.appender.mom.JmsManager this$0;

  private org.apache.logging.log4j.core.appender.mom.JmsManager$Reconnector(org.apache.logging.log4j.core.appender.mom.JmsManager, java.lang.Object);
    Code:
       0: aload_0
       1: aload_1
       2: putfield      #2                  // Field this$0:Lorg/apache/logging/log4j/core/appender/mom/JmsManager;
       5: aload_0
       6: ldc           #3                  // String JmsManager-Reconnector
       8: invokespecial #4                  // Method org/apache/logging/log4j/core/util/Log4jThread."<init>":(Ljava/lang/String;)V
      11: aload_0
      12: new           #5                  // class java/util/concurrent/CountDownLatch
      15: dup
      16: iconst_1
      17: invokespecial #6                  // Method java/util/concurrent/CountDownLatch."<init>":(I)V
      20: putfield      #7                  // Field latch:Ljava/util/concurrent/CountDownLatch;
      23: aload_0
      24: aload_2
      25: putfield      #8                  // Field owner:Ljava/lang/Object;
      28: return

  public void latch();
    Code:
       0: aload_0
       1: getfield      #7                  // Field latch:Ljava/util/concurrent/CountDownLatch;
       4: invokevirtual #9                  // Method java/util/concurrent/CountDownLatch.await:()V
       7: goto          11
      10: astore_1
      11: return
    Exception table:
       from    to  target type
           0     7    10   Class java/lang/InterruptedException

  void reconnect() throws javax.naming.NamingException, javax.jms.JMSException;
    Code:
       0: aload_0
       1: getfield      #2                  // Field this$0:Lorg/apache/logging/log4j/core/appender/mom/JmsManager;
       4: invokevirtual #11                 // Method org/apache/logging/log4j/core/appender/mom/JmsManager.getJndiManager:()Lorg/apache/logging/log4j/core/net/JndiManager;
       7: astore_1
       8: aload_0
       9: getfield      #2                  // Field this$0:Lorg/apache/logging/log4j/core/appender/mom/JmsManager;
      12: aload_1
      13: invokestatic  #12                 // Method org/apache/logging/log4j/core/appender/mom/JmsManager.access$300:(Lorg/apache/logging/log4j/core/appender/mom/JmsManager;Lorg/apache/logging/log4j/core/net/JndiManager;)Ljavax/jms/Connection;
      16: astore_2
      17: aload_0
      18: getfield      #2                  // Field this$0:Lorg/apache/logging/log4j/core/appender/mom/JmsManager;
      21: aload_2
      22: invokestatic  #13                 // Method org/apache/logging/log4j/core/appender/mom/JmsManager.access$400:(Lorg/apache/logging/log4j/core/appender/mom/JmsManager;Ljavax/jms/Connection;)Ljavax/jms/Session;
      25: astore_3
      26: aload_0
      27: getfield      #2                  // Field this$0:Lorg/apache/logging/log4j/core/appender/mom/JmsManager;
      30: aload_1
      31: invokestatic  #14                 // Method org/apache/logging/log4j/core/appender/mom/JmsManager.access$500:(Lorg/apache/logging/log4j/core/appender/mom/JmsManager;Lorg/apache/logging/log4j/core/net/JndiManager;)Ljavax/jms/Destination;
      34: astore        4
      36: aload_0
      37: getfield      #2                  // Field this$0:Lorg/apache/logging/log4j/core/appender/mom/JmsManager;
      40: aload_3
      41: aload         4
      43: invokevirtual #15                 // Method org/apache/logging/log4j/core/appender/mom/JmsManager.createMessageProducer:(Ljavax/jms/Session;Ljavax/jms/Destination;)Ljavax/jms/MessageProducer;
      46: astore        5
      48: aload_2
      49: invokeinterface #16,  1           // InterfaceMethod javax/jms/Connection.start:()V
      54: aload_0
      55: getfield      #8                  // Field owner:Ljava/lang/Object;
      58: dup
      59: astore        6
      61: monitorenter
      62: aload_0
      63: getfield      #2                  // Field this$0:Lorg/apache/logging/log4j/core/appender/mom/JmsManager;
      66: aload_1
      67: invokestatic  #17                 // Method org/apache/logging/log4j/core/appender/mom/JmsManager.access$602:(Lorg/apache/logging/log4j/core/appender/mom/JmsManager;Lorg/apache/logging/log4j/core/net/JndiManager;)Lorg/apache/logging/log4j/core/net/JndiManager;
      70: pop
      71: aload_0
      72: getfield      #2                  // Field this$0:Lorg/apache/logging/log4j/core/appender/mom/JmsManager;
      75: aload_2
      76: invokestatic  #18                 // Method org/apache/logging/log4j/core/appender/mom/JmsManager.access$702:(Lorg/apache/logging/log4j/core/appender/mom/JmsManager;Ljavax/jms/Connection;)Ljavax/jms/Connection;
      79: pop
      80: aload_0
      81: getfield      #2                  // Field this$0:Lorg/apache/logging/log4j/core/appender/mom/JmsManager;
      84: aload_3
      85: invokestatic  #19                 // Method org/apache/logging/log4j/core/appender/mom/JmsManager.access$802:(Lorg/apache/logging/log4j/core/appender/mom/JmsManager;Ljavax/jms/Session;)Ljavax/jms/Session;
      88: pop
      89: aload_0
      90: getfield      #2                  // Field this$0:Lorg/apache/logging/log4j/core/appender/mom/JmsManager;
      93: aload         4
      95: invokestatic  #20                 // Method org/apache/logging/log4j/core/appender/mom/JmsManager.access$902:(Lorg/apache/logging/log4j/core/appender/mom/JmsManager;Ljavax/jms/Destination;)Ljavax/jms/Destination;
      98: pop
      99: aload_0
     100: getfield      #2                  // Field this$0:Lorg/apache/logging/log4j/core/appender/mom/JmsManager;
     103: aload         5
     105: invokestatic  #21                 // Method org/apache/logging/log4j/core/appender/mom/JmsManager.access$1002:(Lorg/apache/logging/log4j/core/appender/mom/JmsManager;Ljavax/jms/MessageProducer;)Ljavax/jms/MessageProducer;
     108: pop
     109: aload_0
     110: getfield      #2                  // Field this$0:Lorg/apache/logging/log4j/core/appender/mom/JmsManager;
     113: aconst_null
     114: invokestatic  #22                 // Method org/apache/logging/log4j/core/appender/mom/JmsManager.access$1102:(Lorg/apache/logging/log4j/core/appender/mom/JmsManager;Lorg/apache/logging/log4j/core/appender/mom/JmsManager$Reconnector;)Lorg/apache/logging/log4j/core/appender/mom/JmsManager$Reconnector;
     117: pop
     118: aload_0
     119: iconst_1
     120: putfield      #23                 // Field shutdown:Z
     123: aload         6
     125: monitorexit
     126: goto          137
     129: astore        7
     131: aload         6
     133: monitorexit
     134: aload         7
     136: athrow
     137: invokestatic  #24                 // Method org/apache/logging/log4j/core/appender/mom/JmsManager.access$1300:()Lorg/apache/logging/log4j/status/StatusLogger;
     140: ldc           #25                 // String Connection reestablished to {}
     142: aload_0
     143: getfield      #2                  // Field this$0:Lorg/apache/logging/log4j/core/appender/mom/JmsManager;
     146: invokestatic  #26                 // Method org/apache/logging/log4j/core/appender/mom/JmsManager.access$1200:(Lorg/apache/logging/log4j/core/appender/mom/JmsManager;)Lorg/apache/logging/log4j/core/appender/mom/JmsManager$JmsManagerConfiguration;
     149: invokevirtual #27                 // Method org/apache/logging/log4j/status/StatusLogger.debug:(Ljava/lang/String;Ljava/lang/Object;)V
     152: return
    Exception table:
       from    to  target type
          62   126   129   any
         129   134   129   any

  public void run();
    Code:
       0: aload_0
       1: getfield      #23                 // Field shutdown:Z
       4: ifne          78
       7: aload_0
       8: getfield      #2                  // Field this$0:Lorg/apache/logging/log4j/core/appender/mom/JmsManager;
      11: invokestatic  #26                 // Method org/apache/logging/log4j/core/appender/mom/JmsManager.access$1200:(Lorg/apache/logging/log4j/core/appender/mom/JmsManager;)Lorg/apache/logging/log4j/core/appender/mom/JmsManager$JmsManagerConfiguration;
      14: invokevirtual #28                 // Method org/apache/logging/log4j/core/appender/mom/JmsManager$JmsManagerConfiguration.getReconnectIntervalMillis:()J
      17: invokestatic  #29                 // Method sleep:(J)V
      20: aload_0
      21: invokevirtual #30                 // Method reconnect:()V
      24: aload_0
      25: getfield      #7                  // Field latch:Ljava/util/concurrent/CountDownLatch;
      28: invokevirtual #31                 // Method java/util/concurrent/CountDownLatch.countDown:()V
      31: goto          75
      34: astore_1
      35: invokestatic  #34                 // Method org/apache/logging/log4j/core/appender/mom/JmsManager.access$1400:()Lorg/apache/logging/log4j/status/StatusLogger;
      38: ldc           #35                 // String Cannot reestablish JMS connection to {}: {}
      40: aload_0
      41: getfield      #2                  // Field this$0:Lorg/apache/logging/log4j/core/appender/mom/JmsManager;
      44: invokestatic  #26                 // Method org/apache/logging/log4j/core/appender/mom/JmsManager.access$1200:(Lorg/apache/logging/log4j/core/appender/mom/JmsManager;)Lorg/apache/logging/log4j/core/appender/mom/JmsManager$JmsManagerConfiguration;
      47: aload_1
      48: invokevirtual #36                 // Method java/lang/Exception.getLocalizedMessage:()Ljava/lang/String;
      51: aload_1
      52: invokevirtual #37                 // Method org/apache/logging/log4j/status/StatusLogger.debug:(Ljava/lang/String;Ljava/lang/Object;Ljava/lang/Object;Ljava/lang/Object;)V
      55: aload_0
      56: getfield      #7                  // Field latch:Ljava/util/concurrent/CountDownLatch;
      59: invokevirtual #31                 // Method java/util/concurrent/CountDownLatch.countDown:()V
      62: goto          75
      65: astore_2
      66: aload_0
      67: getfield      #7                  // Field latch:Ljava/util/concurrent/CountDownLatch;
      70: invokevirtual #31                 // Method java/util/concurrent/CountDownLatch.countDown:()V
      73: aload_2
      74: athrow
      75: goto          0
      78: return
    Exception table:
       from    to  target type
           7    24    34   Class java/lang/InterruptedException
           7    24    34   Class javax/jms/JMSException
           7    24    34   Class javax/naming/NamingException
           7    24    65   any
          34    55    65   any

  public void shutdown();
    Code:
       0: aload_0
       1: iconst_1
       2: putfield      #23                 // Field shutdown:Z
       5: return

  org.apache.logging.log4j.core.appender.mom.JmsManager$Reconnector(org.apache.logging.log4j.core.appender.mom.JmsManager, java.lang.Object, org.apache.logging.log4j.core.appender.mom.JmsManager$1);
    Code:
       0: aload_0
       1: aload_1
       2: aload_2
       3: invokespecial #1                  // Method "<init>":(Lorg/apache/logging/log4j/core/appender/mom/JmsManager;Ljava/lang/Object;)V
       6: return
}
