Compiled from "PipelineRuleParser.java"
class org.graylog.plugins.pipelineprocessor.parser.PipelineRuleParser$PipelineAstBuilder extends org.graylog.plugins.pipelineprocessor.parser.RuleLangBaseListener {
  private final org.graylog.plugins.pipelineprocessor.parser.PipelineRuleParser$ParseContext parseContext;

  public org.graylog.plugins.pipelineprocessor.parser.PipelineRuleParser$PipelineAstBuilder(org.graylog.plugins.pipelineprocessor.parser.PipelineRuleParser$ParseContext);
    Code:
       0: aload_0
       1: invokespecial #1                  // Method org/graylog/plugins/pipelineprocessor/parser/RuleLangBaseListener."<init>":()V
       4: aload_0
       5: aload_1
       6: putfield      #2                  // Field parseContext:Lorg/graylog/plugins/pipelineprocessor/parser/PipelineRuleParser$ParseContext;
       9: return

  public void exitPipelineDeclaration(org.graylog.plugins.pipelineprocessor.parser.RuleLangParser$PipelineDeclarationContext);
    Code:
       0: invokestatic  #3                  // Method org/graylog/plugins/pipelineprocessor/ast/Pipeline.builder:()Lorg/graylog/plugins/pipelineprocessor/ast/Pipeline$Builder;
       3: astore_2
       4: aload_2
       5: aload_1
       6: getfield      #4                  // Field org/graylog/plugins/pipelineprocessor/parser/RuleLangParser$PipelineDeclarationContext.name:Lorg/antlr/v4/runtime/Token;
       9: invokeinterface #5,  1            // InterfaceMethod org/antlr/v4/runtime/Token.getText:()Ljava/lang/String;
      14: bipush        34
      16: invokestatic  #6                  // Method org/graylog/plugins/pipelineprocessor/parser/PipelineRuleParser.unquote:(Ljava/lang/String;C)Ljava/lang/String;
      19: invokevirtual #7                  // Method org/graylog/plugins/pipelineprocessor/ast/Pipeline$Builder.name:(Ljava/lang/String;)Lorg/graylog/plugins/pipelineprocessor/ast/Pipeline$Builder;
      22: pop
      23: invokedynamic #8,  0              // InvokeDynamic #0:applyAsInt:()Ljava/util/function/ToIntFunction;
      28: invokestatic  #9                  // InterfaceMethod java/util/Comparator.comparingInt:(Ljava/util/function/ToIntFunction;)Ljava/util/Comparator;
      31: invokestatic  #10                 // Method com/google/common/collect/ImmutableSortedSet.orderedBy:(Ljava/util/Comparator;)Lcom/google/common/collect/ImmutableSortedSet$Builder;
      34: astore_3
      35: aload_1
      36: invokevirtual #11                 // Method org/graylog/plugins/pipelineprocessor/parser/RuleLangParser$PipelineDeclarationContext.stageDeclaration:()Ljava/util/List;
      39: invokeinterface #12,  1           // InterfaceMethod java/util/List.iterator:()Ljava/util/Iterator;
      44: astore        4
      46: aload         4
      48: invokeinterface #13,  1           // InterfaceMethod java/util/Iterator.hasNext:()Z
      53: ifeq          248
      56: aload         4
      58: invokeinterface #14,  1           // InterfaceMethod java/util/Iterator.next:()Ljava/lang/Object;
      63: checkcast     #15                 // class org/graylog/plugins/pipelineprocessor/parser/RuleLangParser$StageDeclarationContext
      66: astore        5
      68: invokestatic  #16                 // Method org/graylog/plugins/pipelineprocessor/ast/Stage.builder:()Lorg/graylog/plugins/pipelineprocessor/ast/Stage$Builder;
      71: astore        6
      73: aload         5
      75: getfield      #17                 // Field org/graylog/plugins/pipelineprocessor/parser/RuleLangParser$StageDeclarationContext.stage:Lorg/antlr/v4/runtime/Token;
      78: astore        7
      80: aload         7
      82: ifnonnull     106
      85: aload_0
      86: getfield      #2                  // Field parseContext:Lorg/graylog/plugins/pipelineprocessor/parser/PipelineRuleParser$ParseContext;
      89: new           #18                 // class org/graylog/plugins/pipelineprocessor/parser/errors/SyntaxError
      92: dup
      93: aconst_null
      94: iconst_0
      95: iconst_0
      96: ldc           #19                 // String
      98: aconst_null
      99: invokespecial #20                 // Method org/graylog/plugins/pipelineprocessor/parser/errors/SyntaxError."<init>":(Ljava/lang/Object;IILjava/lang/String;Lorg/antlr/v4/runtime/RecognitionException;)V
     102: invokevirtual #21                 // Method org/graylog/plugins/pipelineprocessor/parser/PipelineRuleParser$ParseContext.addError:(Lorg/graylog/plugins/pipelineprocessor/parser/errors/ParseError;)V
     105: return
     106: aload         7
     108: invokeinterface #5,  1            // InterfaceMethod org/antlr/v4/runtime/Token.getText:()Ljava/lang/String;
     113: invokestatic  #22                 // Method java/lang/Integer.parseInt:(Ljava/lang/String;)I
     116: istore        8
     118: aload         6
     120: iload         8
     122: invokevirtual #23                 // Method org/graylog/plugins/pipelineprocessor/ast/Stage$Builder.stage:(I)Lorg/graylog/plugins/pipelineprocessor/ast/Stage$Builder;
     125: pop
     126: aload         5
     128: getfield      #24                 // Field org/graylog/plugins/pipelineprocessor/parser/RuleLangParser$StageDeclarationContext.modifier:Lorg/antlr/v4/runtime/Token;
     131: astore        9
     133: aload         9
     135: ifnonnull     171
     138: aload_0
     139: getfield      #2                  // Field parseContext:Lorg/graylog/plugins/pipelineprocessor/parser/PipelineRuleParser$ParseContext;
     142: new           #18                 // class org/graylog/plugins/pipelineprocessor/parser/errors/SyntaxError
     145: dup
     146: aconst_null
     147: aload         7
     149: invokeinterface #25,  1           // InterfaceMethod org/antlr/v4/runtime/Token.getLine:()I
     154: aload         7
     156: invokeinterface #26,  1           // InterfaceMethod org/antlr/v4/runtime/Token.getCharPositionInLine:()I
     161: ldc           #19                 // String
     163: aconst_null
     164: invokespecial #20                 // Method org/graylog/plugins/pipelineprocessor/parser/errors/SyntaxError."<init>":(Ljava/lang/Object;IILjava/lang/String;Lorg/antlr/v4/runtime/RecognitionException;)V
     167: invokevirtual #21                 // Method org/graylog/plugins/pipelineprocessor/parser/PipelineRuleParser$ParseContext.addError:(Lorg/graylog/plugins/pipelineprocessor/parser/errors/ParseError;)V
     170: return
     171: aload         9
     173: invokeinterface #5,  1            // InterfaceMethod org/antlr/v4/runtime/Token.getText:()Ljava/lang/String;
     178: ldc           #27                 // String all
     180: invokevirtual #28                 // Method java/lang/String.equalsIgnoreCase:(Ljava/lang/String;)Z
     183: istore        10
     185: aload         6
     187: iload         10
     189: invokevirtual #29                 // Method org/graylog/plugins/pipelineprocessor/ast/Stage$Builder.matchAll:(Z)Lorg/graylog/plugins/pipelineprocessor/ast/Stage$Builder;
     192: pop
     193: aload         5
     195: invokevirtual #30                 // Method org/graylog/plugins/pipelineprocessor/parser/RuleLangParser$StageDeclarationContext.ruleRef:()Ljava/util/List;
     198: invokeinterface #31,  1           // InterfaceMethod java/util/List.stream:()Ljava/util/stream/Stream;
     203: aload_0
     204: invokedynamic #32,  0             // InvokeDynamic #1:apply:(Lorg/graylog/plugins/pipelineprocessor/parser/PipelineRuleParser$PipelineAstBuilder;)Ljava/util/function/Function;
     209: invokeinterface #33,  2           // InterfaceMethod java/util/stream/Stream.map:(Ljava/util/function/Function;)Ljava/util/stream/Stream;
     214: invokestatic  #34                 // Method java/util/stream/Collectors.toList:()Ljava/util/stream/Collector;
     217: invokeinterface #35,  2           // InterfaceMethod java/util/stream/Stream.collect:(Ljava/util/stream/Collector;)Ljava/lang/Object;
     222: checkcast     #36                 // class java/util/List
     225: astore        11
     227: aload         6
     229: aload         11
     231: invokevirtual #37                 // Method org/graylog/plugins/pipelineprocessor/ast/Stage$Builder.ruleReferences:(Ljava/util/List;)Lorg/graylog/plugins/pipelineprocessor/ast/Stage$Builder;
     234: pop
     235: aload_3
     236: aload         6
     238: invokevirtual #38                 // Method org/graylog/plugins/pipelineprocessor/ast/Stage$Builder.build:()Lorg/graylog/plugins/pipelineprocessor/ast/Stage;
     241: invokevirtual #39                 // Method com/google/common/collect/ImmutableSortedSet$Builder.add:(Ljava/lang/Object;)Lcom/google/common/collect/ImmutableSortedSet$Builder;
     244: pop
     245: goto          46
     248: aload_2
     249: aload_3
     250: invokevirtual #40                 // Method com/google/common/collect/ImmutableSortedSet$Builder.build:()Lcom/google/common/collect/ImmutableSortedSet;
     253: invokevirtual #41                 // Method org/graylog/plugins/pipelineprocessor/ast/Pipeline$Builder.stages:(Ljava/util/SortedSet;)Lorg/graylog/plugins/pipelineprocessor/ast/Pipeline$Builder;
     256: pop
     257: aload_0
     258: getfield      #2                  // Field parseContext:Lorg/graylog/plugins/pipelineprocessor/parser/PipelineRuleParser$ParseContext;
     261: getfield      #42                 // Field org/graylog/plugins/pipelineprocessor/parser/PipelineRuleParser$ParseContext.pipelines:Ljava/util/List;
     264: aload_2
     265: invokevirtual #43                 // Method org/graylog/plugins/pipelineprocessor/ast/Pipeline$Builder.build:()Lorg/graylog/plugins/pipelineprocessor/ast/Pipeline;
     268: invokeinterface #44,  2           // InterfaceMethod java/util/List.add:(Ljava/lang/Object;)Z
     273: pop
     274: return

  public void exitInteger(org.graylog.plugins.pipelineprocessor.parser.RuleLangParser$IntegerContext);
    Code:
       0: new           #45                 // class org/graylog/plugins/pipelineprocessor/ast/expressions/LongExpression
       3: dup
       4: aload_1
       5: invokevirtual #46                 // Method org/graylog/plugins/pipelineprocessor/parser/RuleLangParser$IntegerContext.getStart:()Lorg/antlr/v4/runtime/Token;
       8: aload_1
       9: invokevirtual #47                 // Method org/graylog/plugins/pipelineprocessor/parser/RuleLangParser$IntegerContext.getText:()Ljava/lang/String;
      12: invokestatic  #48                 // Method java/lang/Long.parseLong:(Ljava/lang/String;)J
      15: invokespecial #49                 // Method org/graylog/plugins/pipelineprocessor/ast/expressions/LongExpression."<init>":(Lorg/antlr/v4/runtime/Token;J)V
      18: astore_2
      19: invokestatic  #50                 // Method org/graylog/plugins/pipelineprocessor/parser/PipelineRuleParser.access$000:()Lorg/slf4j/Logger;
      22: ldc           #51                 // String INT: ctx {} => {}
      24: aload_1
      25: aload_2
      26: invokeinterface #52,  4           // InterfaceMethod org/slf4j/Logger.trace:(Ljava/lang/String;Ljava/lang/Object;Ljava/lang/Object;)V
      31: aload_0
      32: getfield      #2                  // Field parseContext:Lorg/graylog/plugins/pipelineprocessor/parser/PipelineRuleParser$ParseContext;
      35: invokestatic  #53                 // Method org/graylog/plugins/pipelineprocessor/parser/PipelineRuleParser$ParseContext.access$200:(Lorg/graylog/plugins/pipelineprocessor/parser/PipelineRuleParser$ParseContext;)Lorg/antlr/v4/runtime/tree/ParseTreeProperty;
      38: aload_1
      39: aload_2
      40: invokevirtual #54                 // Method org/antlr/v4/runtime/tree/ParseTreeProperty.put:(Lorg/antlr/v4/runtime/tree/ParseTree;Ljava/lang/Object;)V
      43: return

  public void exitString(org.graylog.plugins.pipelineprocessor.parser.RuleLangParser$StringContext);
    Code:
       0: aload_1
       1: invokevirtual #55                 // Method org/graylog/plugins/pipelineprocessor/parser/RuleLangParser$StringContext.getText:()Ljava/lang/String;
       4: bipush        34
       6: invokestatic  #6                  // Method org/graylog/plugins/pipelineprocessor/parser/PipelineRuleParser.unquote:(Ljava/lang/String;C)Ljava/lang/String;
       9: invokestatic  #56                 // Method org/graylog/plugins/pipelineprocessor/parser/PipelineRuleParser.unescape:(Ljava/lang/String;)Ljava/lang/String;
      12: astore_2
      13: new           #57                 // class org/graylog/plugins/pipelineprocessor/ast/expressions/StringExpression
      16: dup
      17: aload_1
      18: invokevirtual #58                 // Method org/graylog/plugins/pipelineprocessor/parser/RuleLangParser$StringContext.getStart:()Lorg/antlr/v4/runtime/Token;
      21: aload_2
      22: invokespecial #59                 // Method org/graylog/plugins/pipelineprocessor/ast/expressions/StringExpression."<init>":(Lorg/antlr/v4/runtime/Token;Ljava/lang/String;)V
      25: astore_3
      26: invokestatic  #50                 // Method org/graylog/plugins/pipelineprocessor/parser/PipelineRuleParser.access$000:()Lorg/slf4j/Logger;
      29: ldc           #60                 // String STRING: ctx {} => {}
      31: aload_1
      32: aload_3
      33: invokeinterface #52,  4           // InterfaceMethod org/slf4j/Logger.trace:(Ljava/lang/String;Ljava/lang/Object;Ljava/lang/Object;)V
      38: aload_0
      39: getfield      #2                  // Field parseContext:Lorg/graylog/plugins/pipelineprocessor/parser/PipelineRuleParser$ParseContext;
      42: invokestatic  #53                 // Method org/graylog/plugins/pipelineprocessor/parser/PipelineRuleParser$ParseContext.access$200:(Lorg/graylog/plugins/pipelineprocessor/parser/PipelineRuleParser$ParseContext;)Lorg/antlr/v4/runtime/tree/ParseTreeProperty;
      45: aload_1
      46: aload_3
      47: invokevirtual #54                 // Method org/antlr/v4/runtime/tree/ParseTreeProperty.put:(Lorg/antlr/v4/runtime/tree/ParseTree;Ljava/lang/Object;)V
      50: return

  private java.lang.String lambda$exitPipelineDeclaration$0(org.graylog.plugins.pipelineprocessor.parser.RuleLangParser$RuleRefContext);
    Code:
       0: aload_1
       1: getfield      #61                 // Field org/graylog/plugins/pipelineprocessor/parser/RuleLangParser$RuleRefContext.name:Lorg/antlr/v4/runtime/Token;
       4: astore_2
       5: aload_2
       6: ifnonnull     52
       9: aload_1
      10: invokevirtual #62                 // Method org/graylog/plugins/pipelineprocessor/parser/RuleLangParser$RuleRefContext.Rule:()Lorg/antlr/v4/runtime/tree/TerminalNode;
      13: invokeinterface #63,  1           // InterfaceMethod org/antlr/v4/runtime/tree/TerminalNode.getSymbol:()Lorg/antlr/v4/runtime/Token;
      18: astore_3
      19: aload_0
      20: getfield      #2                  // Field parseContext:Lorg/graylog/plugins/pipelineprocessor/parser/PipelineRuleParser$ParseContext;
      23: new           #18                 // class org/graylog/plugins/pipelineprocessor/parser/errors/SyntaxError
      26: dup
      27: aload_3
      28: aload_3
      29: invokeinterface #25,  1           // InterfaceMethod org/antlr/v4/runtime/Token.getLine:()I
      34: aload_3
      35: invokeinterface #26,  1           // InterfaceMethod org/antlr/v4/runtime/Token.getCharPositionInLine:()I
      40: ldc           #64                 // String invalid rule reference
      42: aconst_null
      43: invokespecial #20                 // Method org/graylog/plugins/pipelineprocessor/parser/errors/SyntaxError."<init>":(Ljava/lang/Object;IILjava/lang/String;Lorg/antlr/v4/runtime/RecognitionException;)V
      46: invokevirtual #21                 // Method org/graylog/plugins/pipelineprocessor/parser/PipelineRuleParser$ParseContext.addError:(Lorg/graylog/plugins/pipelineprocessor/parser/errors/ParseError;)V
      49: ldc           #65                 // String __illegal_reference
      51: areturn
      52: aload_2
      53: invokeinterface #5,  1            // InterfaceMethod org/antlr/v4/runtime/Token.getText:()Ljava/lang/String;
      58: bipush        34
      60: invokestatic  #6                  // Method org/graylog/plugins/pipelineprocessor/parser/PipelineRuleParser.unquote:(Ljava/lang/String;C)Ljava/lang/String;
      63: areturn
}
