Compiled from "RuleLangParser.java"
public class org.graylog.plugins.pipelineprocessor.parser.RuleLangParser$SignedExpressionContext extends org.graylog.plugins.pipelineprocessor.parser.RuleLangParser$ExpressionContext {
  public org.antlr.v4.runtime.Token sign;

  public org.graylog.plugins.pipelineprocessor.parser.RuleLangParser$ExpressionContext expr;

  public org.graylog.plugins.pipelineprocessor.parser.RuleLangParser$ExpressionContext expression();
    Code:
       0: aload_0
       1: ldc           #1                  // class org/graylog/plugins/pipelineprocessor/parser/RuleLangParser$ExpressionContext
       3: iconst_0
       4: invokevirtual #2                  // Method getRuleContext:(Ljava/lang/Class;I)Lorg/antlr/v4/runtime/ParserRuleContext;
       7: checkcast     #1                  // class org/graylog/plugins/pipelineprocessor/parser/RuleLangParser$ExpressionContext
      10: areturn

  public org.graylog.plugins.pipelineprocessor.parser.RuleLangParser$SignedExpressionContext(org.graylog.plugins.pipelineprocessor.parser.RuleLangParser$ExpressionContext);
    Code:
       0: aload_0
       1: invokespecial #3                  // Method org/graylog/plugins/pipelineprocessor/parser/RuleLangParser$ExpressionContext."<init>":()V
       4: aload_0
       5: aload_1
       6: invokevirtual #4                  // Method copyFrom:(Lorg/graylog/plugins/pipelineprocessor/parser/RuleLangParser$ExpressionContext;)V
       9: return

  public void enterRule(org.antlr.v4.runtime.tree.ParseTreeListener);
    Code:
       0: aload_1
       1: instanceof    #5                  // class org/graylog/plugins/pipelineprocessor/parser/RuleLangListener
       4: ifeq          17
       7: aload_1
       8: checkcast     #5                  // class org/graylog/plugins/pipelineprocessor/parser/RuleLangListener
      11: aload_0
      12: invokeinterface #6,  2            // InterfaceMethod org/graylog/plugins/pipelineprocessor/parser/RuleLangListener.enterSignedExpression:(Lorg/graylog/plugins/pipelineprocessor/parser/RuleLangParser$SignedExpressionContext;)V
      17: return

  public void exitRule(org.antlr.v4.runtime.tree.ParseTreeListener);
    Code:
       0: aload_1
       1: instanceof    #5                  // class org/graylog/plugins/pipelineprocessor/parser/RuleLangListener
       4: ifeq          17
       7: aload_1
       8: checkcast     #5                  // class org/graylog/plugins/pipelineprocessor/parser/RuleLangListener
      11: aload_0
      12: invokeinterface #7,  2            // InterfaceMethod org/graylog/plugins/pipelineprocessor/parser/RuleLangListener.exitSignedExpression:(Lorg/graylog/plugins/pipelineprocessor/parser/RuleLangParser$SignedExpressionContext;)V
      17: return
}
