Compiled from "ClazzAs.java"
class io.sundr.builder.internal.functions.ClazzAs$2$1 implements io.sundr.Provider<java.util.List<io.sundr.codegen.model.Statement>> {
  final io.sundr.codegen.model.TypeDef val$fluentImplType;

  final java.util.List val$properties;

  final io.sundr.builder.internal.functions.ClazzAs$2 this$0;

  io.sundr.builder.internal.functions.ClazzAs$2$1(io.sundr.builder.internal.functions.ClazzAs$2, io.sundr.codegen.model.TypeDef, java.util.List);
    Code:
       0: aload_0
       1: aload_1
       2: putfield      #1                  // Field this$0:Lio/sundr/builder/internal/functions/ClazzAs$2;
       5: aload_0
       6: aload_2
       7: putfield      #2                  // Field val$fluentImplType:Lio/sundr/codegen/model/TypeDef;
      10: aload_0
      11: aload_3
      12: putfield      #3                  // Field val$properties:Ljava/util/List;
      15: aload_0
      16: invokespecial #4                  // Method java/lang/Object."<init>":()V
      19: return

  public java.util.List<io.sundr.codegen.model.Statement> get();
    Code:
       0: aload_0
       1: getfield      #2                  // Field val$fluentImplType:Lio/sundr/codegen/model/TypeDef;
       4: aload_0
       5: getfield      #3                  // Field val$properties:Ljava/util/List;
       8: invokestatic  #5                  // Method io/sundr/builder/internal/functions/ClazzAs.access$200:(Lio/sundr/codegen/model/TypeDef;Ljava/util/Collection;)Ljava/util/List;
      11: areturn

  public java.lang.Object get();
    Code:
       0: aload_0
       1: invokevirtual #6                  // Method get:()Ljava/util/List;
       4: areturn
}
