Compiled from "ToMethod.java"
final class io.sundr.builder.internal.functions.ToMethod$2 implements io.sundr.Function<io.sundr.codegen.model.Property, java.util.List<io.sundr.codegen.model.Method>> {
  io.sundr.builder.internal.functions.ToMethod$2();
    Code:
       0: aload_0
       1: invokespecial #1                  // Method java/lang/Object."<init>":()V
       4: return

  public java.util.List<io.sundr.codegen.model.Method> apply(io.sundr.codegen.model.Property);
    Code:
       0: new           #2                  // class java/util/ArrayList
       3: dup
       4: invokespecial #3                  // Method java/util/ArrayList."<init>":()V
       7: astore_2
       8: getstatic     #4                  // Field io/sundr/builder/internal/functions/TypeAs.UNWRAP_COLLECTION_OF:Lio/sundr/Function;
      11: aload_1
      12: invokevirtual #5                  // Method io/sundr/codegen/model/Property.getTypeRef:()Lio/sundr/codegen/model/TypeRef;
      15: invokeinterface #6,  2            // InterfaceMethod io/sundr/Function.apply:(Ljava/lang/Object;)Ljava/lang/Object;
      20: checkcast     #7                  // class io/sundr/codegen/model/TypeRef
      23: astore_3
      24: getstatic     #8                  // Field io/sundr/builder/internal/functions/TypeAs.VISITABLE_BUILDER:Lio/sundr/Function;
      27: aload_3
      28: invokeinterface #6,  2            // InterfaceMethod io/sundr/Function.apply:(Ljava/lang/Object;)Ljava/lang/Object;
      33: checkcast     #7                  // class io/sundr/codegen/model/TypeRef
      36: astore        4
      38: new           #9                  // class io/sundr/codegen/model/PropertyBuilder
      41: dup
      42: aload_1
      43: invokespecial #10                 // Method io/sundr/codegen/model/PropertyBuilder."<init>":(Lio/sundr/codegen/model/Property;)V
      46: ldc           #11                 // String builder
      48: invokevirtual #12                 // Method io/sundr/codegen/model/PropertyBuilder.withName:(Ljava/lang/String;)Lio/sundr/codegen/model/PropertyFluent;
      51: checkcast     #9                  // class io/sundr/codegen/model/PropertyBuilder
      54: aload         4
      56: invokevirtual #13                 // Method io/sundr/codegen/model/PropertyBuilder.withTypeRef:(Lio/sundr/codegen/model/TypeRef;)Lio/sundr/codegen/model/PropertyFluent;
      59: checkcast     #9                  // class io/sundr/codegen/model/PropertyBuilder
      62: invokevirtual #14                 // Method io/sundr/codegen/model/PropertyBuilder.build:()Lio/sundr/codegen/model/EditableProperty;
      65: astore        5
      67: aload_1
      68: getstatic     #15                 // Field io/sundr/builder/Constants.ORIGIN_TYPEDEF:Lio/sundr/codegen/model/AttributeKey;
      71: invokevirtual #16                 // Method io/sundr/codegen/model/Property.getAttribute:(Lio/sundr/codegen/model/AttributeKey;)Ljava/lang/Object;
      74: checkcast     #17                 // class io/sundr/codegen/model/TypeDef
      77: astore        6
      79: aload_1
      80: getstatic     #18                 // Field io/sundr/builder/Constants.GENERIC_TYPE_REF:Lio/sundr/codegen/model/AttributeKey;
      83: invokevirtual #19                 // Method io/sundr/codegen/model/Property.hasAttribute:(Lio/sundr/codegen/model/AttributeKey;)Z
      86: ifeq          102
      89: aload_1
      90: getstatic     #18                 // Field io/sundr/builder/Constants.GENERIC_TYPE_REF:Lio/sundr/codegen/model/AttributeKey;
      93: invokevirtual #16                 // Method io/sundr/codegen/model/Property.getAttribute:(Lio/sundr/codegen/model/AttributeKey;)Ljava/lang/Object;
      96: checkcast     #7                  // class io/sundr/codegen/model/TypeRef
      99: goto          105
     102: getstatic     #20                 // Field io/sundr/codegen/Constants.T_REF:Lio/sundr/codegen/model/TypeParamRef;
     105: astore        7
     107: getstatic     #21                 // Field io/sundr/builder/internal/functions/TypeAs.BOXED_OF:Lio/sundr/Function;
     110: iconst_1
     111: anewarray     #22                 // class io/sundr/Function
     114: dup
     115: iconst_0
     116: getstatic     #4                  // Field io/sundr/builder/internal/functions/TypeAs.UNWRAP_COLLECTION_OF:Lio/sundr/Function;
     119: aastore
     120: invokestatic  #23                 // Method io/sundr/builder/internal/functions/TypeAs.combine:([Lio/sundr/Function;)Lio/sundr/Function;
     123: aload_1
     124: invokevirtual #5                  // Method io/sundr/codegen/model/Property.getTypeRef:()Lio/sundr/codegen/model/TypeRef;
     127: invokeinterface #6,  2            // InterfaceMethod io/sundr/Function.apply:(Ljava/lang/Object;)Ljava/lang/Object;
     132: invokeinterface #6,  2            // InterfaceMethod io/sundr/Function.apply:(Ljava/lang/Object;)Ljava/lang/Object;
     137: checkcast     #7                  // class io/sundr/codegen/model/TypeRef
     140: astore        8
     142: new           #2                  // class java/util/ArrayList
     145: dup
     146: invokespecial #3                  // Method java/util/ArrayList."<init>":()V
     149: astore        9
     151: new           #9                  // class io/sundr/codegen/model/PropertyBuilder
     154: dup
     155: aload_1
     156: invokespecial #10                 // Method io/sundr/codegen/model/PropertyBuilder."<init>":(Lio/sundr/codegen/model/Property;)V
     159: ldc           #24                 // String items
     161: invokevirtual #12                 // Method io/sundr/codegen/model/PropertyBuilder.withName:(Ljava/lang/String;)Lio/sundr/codegen/model/PropertyFluent;
     164: checkcast     #9                  // class io/sundr/codegen/model/PropertyBuilder
     167: aload         8
     169: iconst_1
     170: invokevirtual #25                 // Method io/sundr/codegen/model/TypeRef.withDimensions:(I)Lio/sundr/codegen/model/TypeRef;
     173: invokevirtual #13                 // Method io/sundr/codegen/model/PropertyBuilder.withTypeRef:(Lio/sundr/codegen/model/TypeRef;)Lio/sundr/codegen/model/PropertyFluent;
     176: checkcast     #9                  // class io/sundr/codegen/model/PropertyBuilder
     179: invokevirtual #14                 // Method io/sundr/codegen/model/PropertyBuilder.build:()Lio/sundr/codegen/model/EditableProperty;
     182: astore        10
     184: new           #9                  // class io/sundr/codegen/model/PropertyBuilder
     187: dup
     188: aload_1
     189: invokespecial #10                 // Method io/sundr/codegen/model/PropertyBuilder."<init>":(Lio/sundr/codegen/model/Property;)V
     192: ldc           #26                 // String item
     194: invokevirtual #12                 // Method io/sundr/codegen/model/PropertyBuilder.withName:(Ljava/lang/String;)Lio/sundr/codegen/model/PropertyFluent;
     197: checkcast     #9                  // class io/sundr/codegen/model/PropertyBuilder
     200: aload         8
     202: invokevirtual #13                 // Method io/sundr/codegen/model/PropertyBuilder.withTypeRef:(Lio/sundr/codegen/model/TypeRef;)Lio/sundr/codegen/model/PropertyFluent;
     205: checkcast     #9                  // class io/sundr/codegen/model/PropertyBuilder
     208: invokevirtual #14                 // Method io/sundr/codegen/model/PropertyBuilder.build:()Lio/sundr/codegen/model/EditableProperty;
     211: astore        11
     213: new           #2                  // class java/util/ArrayList
     216: dup
     217: invokespecial #3                  // Method java/util/ArrayList."<init>":()V
     220: astore        12
     222: new           #27                 // class java/lang/StringBuilder
     225: dup
     226: invokespecial #28                 // Method java/lang/StringBuilder."<init>":()V
     229: ldc           #29                 // String addTo
     231: invokevirtual #30                 // Method java/lang/StringBuilder.append:(Ljava/lang/String;)Ljava/lang/StringBuilder;
     234: aload_1
     235: invokevirtual #31                 // Method io/sundr/codegen/model/Property.getNameCapitalized:()Ljava/lang/String;
     238: invokevirtual #30                 // Method java/lang/StringBuilder.append:(Ljava/lang/String;)Ljava/lang/StringBuilder;
     241: invokevirtual #32                 // Method java/lang/StringBuilder.toString:()Ljava/lang/String;
     244: astore        13
     246: new           #27                 // class java/lang/StringBuilder
     249: dup
     250: invokespecial #28                 // Method java/lang/StringBuilder."<init>":()V
     253: ldc           #33                 // String setTo
     255: invokevirtual #30                 // Method java/lang/StringBuilder.append:(Ljava/lang/String;)Ljava/lang/StringBuilder;
     258: aload_1
     259: invokevirtual #31                 // Method io/sundr/codegen/model/Property.getNameCapitalized:()Ljava/lang/String;
     262: invokevirtual #30                 // Method java/lang/StringBuilder.append:(Ljava/lang/String;)Ljava/lang/StringBuilder;
     265: invokevirtual #32                 // Method java/lang/StringBuilder.toString:()Ljava/lang/String;
     268: astore        14
     270: new           #27                 // class java/lang/StringBuilder
     273: dup
     274: invokespecial #28                 // Method java/lang/StringBuilder."<init>":()V
     277: ldc           #34                 // String addAllTo
     279: invokevirtual #30                 // Method java/lang/StringBuilder.append:(Ljava/lang/String;)Ljava/lang/StringBuilder;
     282: aload_3
     283: aload         6
     285: invokestatic  #35                 // Method io/sundr/builder/internal/utils/BuilderUtils.fullyQualifiedNameDiff:(Lio/sundr/codegen/model/TypeRef;Lio/sundr/codegen/model/TypeDef;)Ljava/lang/String;
     288: invokevirtual #30                 // Method java/lang/StringBuilder.append:(Ljava/lang/String;)Ljava/lang/StringBuilder;
     291: aload_1
     292: invokevirtual #31                 // Method io/sundr/codegen/model/Property.getNameCapitalized:()Ljava/lang/String;
     295: invokevirtual #30                 // Method java/lang/StringBuilder.append:(Ljava/lang/String;)Ljava/lang/StringBuilder;
     298: invokevirtual #32                 // Method java/lang/StringBuilder.toString:()Ljava/lang/String;
     301: astore        15
     303: getstatic     #36                 // Field io/sundr/builder/internal/functions/Descendants.PROPERTY_BUILDABLE_DESCENDANTS:Lio/sundr/Function;
     306: aload_1
     307: invokeinterface #6,  2            // InterfaceMethod io/sundr/Function.apply:(Ljava/lang/Object;)Ljava/lang/Object;
     312: checkcast     #37                 // class java/util/Set
     315: astore        16
     317: aload_1
     318: invokevirtual #38                 // Method io/sundr/codegen/model/Property.getName:()Ljava/lang/String;
     321: astore        17
     323: aload_1
     324: getstatic     #39                 // Field io/sundr/builder/Constants.DESCENDANT_OF:Lio/sundr/codegen/model/AttributeKey;
     327: invokevirtual #19                 // Method io/sundr/codegen/model/Property.hasAttribute:(Lio/sundr/codegen/model/AttributeKey;)Z
     330: ifeq          357
     333: aload_1
     334: getstatic     #39                 // Field io/sundr/builder/Constants.DESCENDANT_OF:Lio/sundr/codegen/model/AttributeKey;
     337: invokevirtual #16                 // Method io/sundr/codegen/model/Property.getAttribute:(Lio/sundr/codegen/model/AttributeKey;)Ljava/lang/Object;
     340: checkcast     #40                 // class io/sundr/codegen/model/Property
     343: astore        18
     345: aload         18
     347: ifnull        357
     350: aload         18
     352: invokevirtual #38                 // Method io/sundr/codegen/model/Property.getName:()Ljava/lang/String;
     355: astore        17
     357: new           #41                 // class io/sundr/codegen/model/MethodBuilder
     360: dup
     361: invokespecial #42                 // Method io/sundr/codegen/model/MethodBuilder."<init>":()V
     364: iconst_1
     365: anewarray     #43                 // class javax/lang/model/element/Modifier
     368: dup
     369: iconst_0
     370: getstatic     #44                 // Field javax/lang/model/element/Modifier.PUBLIC:Ljavax/lang/model/element/Modifier;
     373: aastore
     374: invokestatic  #45                 // Method io/sundr/codegen/utils/TypeUtils.modifiersToInt:([Ljavax/lang/model/element/Modifier;)I
     377: invokevirtual #46                 // Method io/sundr/codegen/model/MethodBuilder.withModifiers:(I)Lio/sundr/codegen/model/ModifierSupportFluent;
     380: checkcast     #41                 // class io/sundr/codegen/model/MethodBuilder
     383: aload         12
     385: invokevirtual #47                 // Method io/sundr/codegen/model/MethodBuilder.withParameters:(Ljava/util/List;)Lio/sundr/codegen/model/MethodFluent;
     388: checkcast     #41                 // class io/sundr/codegen/model/MethodBuilder
     391: aload         13
     393: invokevirtual #48                 // Method io/sundr/codegen/model/MethodBuilder.withName:(Ljava/lang/String;)Lio/sundr/codegen/model/MethodFluent;
     396: checkcast     #41                 // class io/sundr/codegen/model/MethodBuilder
     399: aload         7
     401: invokevirtual #49                 // Method io/sundr/codegen/model/MethodBuilder.withReturnType:(Lio/sundr/codegen/model/TypeRef;)Lio/sundr/codegen/model/MethodFluent;
     404: checkcast     #41                 // class io/sundr/codegen/model/MethodBuilder
     407: iconst_1
     408: anewarray     #40                 // class io/sundr/codegen/model/Property
     411: dup
     412: iconst_0
     413: getstatic     #50                 // Field io/sundr/builder/Constants.INDEX:Lio/sundr/codegen/model/Property;
     416: aastore
     417: invokevirtual #51                 // Method io/sundr/codegen/model/MethodBuilder.addToArguments:([Lio/sundr/codegen/model/Property;)Lio/sundr/codegen/model/MethodFluent;
     420: checkcast     #41                 // class io/sundr/codegen/model/MethodBuilder
     423: iconst_1
     424: anewarray     #40                 // class io/sundr/codegen/model/Property
     427: dup
     428: iconst_0
     429: aload         11
     431: aastore
     432: invokevirtual #51                 // Method io/sundr/codegen/model/MethodBuilder.addToArguments:([Lio/sundr/codegen/model/Property;)Lio/sundr/codegen/model/MethodFluent;
     435: checkcast     #41                 // class io/sundr/codegen/model/MethodBuilder
     438: invokevirtual #52                 // Method io/sundr/codegen/model/MethodBuilder.withNewBlock:()Lio/sundr/codegen/model/MethodFluent$BlockNested;
     441: iconst_3
     442: anewarray     #53                 // class io/sundr/codegen/model/Statement
     445: dup
     446: iconst_0
     447: new           #54                 // class io/sundr/codegen/model/StringStatement
     450: dup
     451: new           #27                 // class java/lang/StringBuilder
     454: dup
     455: invokespecial #28                 // Method java/lang/StringBuilder."<init>":()V
     458: ldc           #55                 // String if (this.
     460: invokevirtual #30                 // Method java/lang/StringBuilder.append:(Ljava/lang/String;)Ljava/lang/StringBuilder;
     463: aload         17
     465: invokevirtual #30                 // Method java/lang/StringBuilder.append:(Ljava/lang/String;)Ljava/lang/StringBuilder;
     468: ldc           #56                 // String  == null) {this.
     470: invokevirtual #30                 // Method java/lang/StringBuilder.append:(Ljava/lang/String;)Ljava/lang/StringBuilder;
     473: aload         17
     475: invokevirtual #30                 // Method java/lang/StringBuilder.append:(Ljava/lang/String;)Ljava/lang/StringBuilder;
     478: ldc           #57                 // String  =
     480: invokevirtual #30                 // Method java/lang/StringBuilder.append:(Ljava/lang/String;)Ljava/lang/StringBuilder;
     483: aload_1
     484: getstatic     #58                 // Field io/sundr/codegen/model/Attributeable.LAZY_INIT:Lio/sundr/codegen/model/AttributeKey;
     487: invokevirtual #16                 // Method io/sundr/codegen/model/Property.getAttribute:(Lio/sundr/codegen/model/AttributeKey;)Ljava/lang/Object;
     490: checkcast     #59                 // class java/lang/String
     493: invokevirtual #30                 // Method java/lang/StringBuilder.append:(Ljava/lang/String;)Ljava/lang/StringBuilder;
     496: ldc           #60                 // String ;}
     498: invokevirtual #30                 // Method java/lang/StringBuilder.append:(Ljava/lang/String;)Ljava/lang/StringBuilder;
     501: invokevirtual #32                 // Method java/lang/StringBuilder.toString:()Ljava/lang/String;
     504: invokespecial #61                 // Method io/sundr/codegen/model/StringStatement."<init>":(Ljava/lang/String;)V
     507: aastore
     508: dup
     509: iconst_1
     510: new           #54                 // class io/sundr/codegen/model/StringStatement
     513: dup
     514: new           #27                 // class java/lang/StringBuilder
     517: dup
     518: invokespecial #28                 // Method java/lang/StringBuilder."<init>":()V
     521: ldc           #62                 // String this.
     523: invokevirtual #30                 // Method java/lang/StringBuilder.append:(Ljava/lang/String;)Ljava/lang/StringBuilder;
     526: aload         17
     528: invokevirtual #30                 // Method java/lang/StringBuilder.append:(Ljava/lang/String;)Ljava/lang/StringBuilder;
     531: ldc           #63                 // String .add(index, item);
     533: invokevirtual #30                 // Method java/lang/StringBuilder.append:(Ljava/lang/String;)Ljava/lang/StringBuilder;
     536: invokevirtual #32                 // Method java/lang/StringBuilder.toString:()Ljava/lang/String;
     539: invokespecial #61                 // Method io/sundr/codegen/model/StringStatement."<init>":(Ljava/lang/String;)V
     542: aastore
     543: dup
     544: iconst_2
     545: new           #54                 // class io/sundr/codegen/model/StringStatement
     548: dup
     549: new           #27                 // class java/lang/StringBuilder
     552: dup
     553: invokespecial #28                 // Method java/lang/StringBuilder."<init>":()V
     556: ldc           #64                 // String return (
     558: invokevirtual #30                 // Method java/lang/StringBuilder.append:(Ljava/lang/String;)Ljava/lang/StringBuilder;
     561: aload         7
     563: invokevirtual #65                 // Method java/lang/StringBuilder.append:(Ljava/lang/Object;)Ljava/lang/StringBuilder;
     566: ldc           #66                 // String )this;
     568: invokevirtual #30                 // Method java/lang/StringBuilder.append:(Ljava/lang/String;)Ljava/lang/StringBuilder;
     571: invokevirtual #32                 // Method java/lang/StringBuilder.toString:()Ljava/lang/String;
     574: invokespecial #61                 // Method io/sundr/codegen/model/StringStatement."<init>":(Ljava/lang/String;)V
     577: aastore
     578: invokeinterface #67,  2           // InterfaceMethod io/sundr/codegen/model/MethodFluent$BlockNested.withStatements:([Lio/sundr/codegen/model/Statement;)Lio/sundr/codegen/model/BlockFluent;
     583: checkcast     #68                 // class io/sundr/codegen/model/MethodFluent$BlockNested
     586: invokeinterface #69,  1           // InterfaceMethod io/sundr/codegen/model/MethodFluent$BlockNested.endBlock:()Ljava/lang/Object;
     591: checkcast     #41                 // class io/sundr/codegen/model/MethodBuilder
     594: getstatic     #70                 // Field io/sundr/codegen/model/Attributeable.ALSO_IMPORT:Lio/sundr/codegen/model/AttributeKey;
     597: aload         9
     599: invokevirtual #71                 // Method io/sundr/codegen/model/MethodBuilder.addToAttributes:(Lio/sundr/codegen/model/AttributeKey;Ljava/lang/Object;)Lio/sundr/codegen/model/AttributeSupportFluent;
     602: checkcast     #41                 // class io/sundr/codegen/model/MethodBuilder
     605: invokevirtual #72                 // Method io/sundr/codegen/model/MethodBuilder.build:()Lio/sundr/codegen/model/EditableMethod;
     608: astore        18
     610: new           #41                 // class io/sundr/codegen/model/MethodBuilder
     613: dup
     614: invokespecial #42                 // Method io/sundr/codegen/model/MethodBuilder."<init>":()V
     617: iconst_1
     618: anewarray     #43                 // class javax/lang/model/element/Modifier
     621: dup
     622: iconst_0
     623: getstatic     #44                 // Field javax/lang/model/element/Modifier.PUBLIC:Ljavax/lang/model/element/Modifier;
     626: aastore
     627: invokestatic  #45                 // Method io/sundr/codegen/utils/TypeUtils.modifiersToInt:([Ljavax/lang/model/element/Modifier;)I
     630: invokevirtual #46                 // Method io/sundr/codegen/model/MethodBuilder.withModifiers:(I)Lio/sundr/codegen/model/ModifierSupportFluent;
     633: checkcast     #41                 // class io/sundr/codegen/model/MethodBuilder
     636: aload         12
     638: invokevirtual #47                 // Method io/sundr/codegen/model/MethodBuilder.withParameters:(Ljava/util/List;)Lio/sundr/codegen/model/MethodFluent;
     641: checkcast     #41                 // class io/sundr/codegen/model/MethodBuilder
     644: aload         14
     646: invokevirtual #48                 // Method io/sundr/codegen/model/MethodBuilder.withName:(Ljava/lang/String;)Lio/sundr/codegen/model/MethodFluent;
     649: checkcast     #41                 // class io/sundr/codegen/model/MethodBuilder
     652: aload         7
     654: invokevirtual #49                 // Method io/sundr/codegen/model/MethodBuilder.withReturnType:(Lio/sundr/codegen/model/TypeRef;)Lio/sundr/codegen/model/MethodFluent;
     657: checkcast     #41                 // class io/sundr/codegen/model/MethodBuilder
     660: iconst_1
     661: anewarray     #40                 // class io/sundr/codegen/model/Property
     664: dup
     665: iconst_0
     666: getstatic     #50                 // Field io/sundr/builder/Constants.INDEX:Lio/sundr/codegen/model/Property;
     669: aastore
     670: invokevirtual #51                 // Method io/sundr/codegen/model/MethodBuilder.addToArguments:([Lio/sundr/codegen/model/Property;)Lio/sundr/codegen/model/MethodFluent;
     673: checkcast     #41                 // class io/sundr/codegen/model/MethodBuilder
     676: iconst_1
     677: anewarray     #40                 // class io/sundr/codegen/model/Property
     680: dup
     681: iconst_0
     682: aload         11
     684: aastore
     685: invokevirtual #51                 // Method io/sundr/codegen/model/MethodBuilder.addToArguments:([Lio/sundr/codegen/model/Property;)Lio/sundr/codegen/model/MethodFluent;
     688: checkcast     #41                 // class io/sundr/codegen/model/MethodBuilder
     691: invokevirtual #52                 // Method io/sundr/codegen/model/MethodBuilder.withNewBlock:()Lio/sundr/codegen/model/MethodFluent$BlockNested;
     694: iconst_2
     695: anewarray     #53                 // class io/sundr/codegen/model/Statement
     698: dup
     699: iconst_0
     700: new           #54                 // class io/sundr/codegen/model/StringStatement
     703: dup
     704: new           #27                 // class java/lang/StringBuilder
     707: dup
     708: invokespecial #28                 // Method java/lang/StringBuilder."<init>":()V
     711: ldc           #55                 // String if (this.
     713: invokevirtual #30                 // Method java/lang/StringBuilder.append:(Ljava/lang/String;)Ljava/lang/StringBuilder;
     716: aload         17
     718: invokevirtual #30                 // Method java/lang/StringBuilder.append:(Ljava/lang/String;)Ljava/lang/StringBuilder;
     721: ldc           #56                 // String  == null) {this.
     723: invokevirtual #30                 // Method java/lang/StringBuilder.append:(Ljava/lang/String;)Ljava/lang/StringBuilder;
     726: aload         17
     728: invokevirtual #30                 // Method java/lang/StringBuilder.append:(Ljava/lang/String;)Ljava/lang/StringBuilder;
     731: ldc           #57                 // String  =
     733: invokevirtual #30                 // Method java/lang/StringBuilder.append:(Ljava/lang/String;)Ljava/lang/StringBuilder;
     736: aload_1
     737: getstatic     #58                 // Field io/sundr/codegen/model/Attributeable.LAZY_INIT:Lio/sundr/codegen/model/AttributeKey;
     740: invokevirtual #16                 // Method io/sundr/codegen/model/Property.getAttribute:(Lio/sundr/codegen/model/AttributeKey;)Ljava/lang/Object;
     743: checkcast     #59                 // class java/lang/String
     746: invokevirtual #30                 // Method java/lang/StringBuilder.append:(Ljava/lang/String;)Ljava/lang/StringBuilder;
     749: ldc           #60                 // String ;}
     751: invokevirtual #30                 // Method java/lang/StringBuilder.append:(Ljava/lang/String;)Ljava/lang/StringBuilder;
     754: invokevirtual #32                 // Method java/lang/StringBuilder.toString:()Ljava/lang/String;
     757: invokespecial #61                 // Method io/sundr/codegen/model/StringStatement."<init>":(Ljava/lang/String;)V
     760: aastore
     761: dup
     762: iconst_1
     763: new           #54                 // class io/sundr/codegen/model/StringStatement
     766: dup
     767: new           #27                 // class java/lang/StringBuilder
     770: dup
     771: invokespecial #28                 // Method java/lang/StringBuilder."<init>":()V
     774: ldc           #62                 // String this.
     776: invokevirtual #30                 // Method java/lang/StringBuilder.append:(Ljava/lang/String;)Ljava/lang/StringBuilder;
     779: aload         17
     781: invokevirtual #30                 // Method java/lang/StringBuilder.append:(Ljava/lang/String;)Ljava/lang/StringBuilder;
     784: ldc           #73                 // String .set(index, item); return (
     786: invokevirtual #30                 // Method java/lang/StringBuilder.append:(Ljava/lang/String;)Ljava/lang/StringBuilder;
     789: aload         7
     791: invokevirtual #65                 // Method java/lang/StringBuilder.append:(Ljava/lang/Object;)Ljava/lang/StringBuilder;
     794: ldc           #66                 // String )this;
     796: invokevirtual #30                 // Method java/lang/StringBuilder.append:(Ljava/lang/String;)Ljava/lang/StringBuilder;
     799: invokevirtual #32                 // Method java/lang/StringBuilder.toString:()Ljava/lang/String;
     802: invokespecial #61                 // Method io/sundr/codegen/model/StringStatement."<init>":(Ljava/lang/String;)V
     805: aastore
     806: invokeinterface #67,  2           // InterfaceMethod io/sundr/codegen/model/MethodFluent$BlockNested.withStatements:([Lio/sundr/codegen/model/Statement;)Lio/sundr/codegen/model/BlockFluent;
     811: checkcast     #68                 // class io/sundr/codegen/model/MethodFluent$BlockNested
     814: invokeinterface #69,  1           // InterfaceMethod io/sundr/codegen/model/MethodFluent$BlockNested.endBlock:()Ljava/lang/Object;
     819: checkcast     #41                 // class io/sundr/codegen/model/MethodBuilder
     822: getstatic     #70                 // Field io/sundr/codegen/model/Attributeable.ALSO_IMPORT:Lio/sundr/codegen/model/AttributeKey;
     825: aload         9
     827: invokevirtual #71                 // Method io/sundr/codegen/model/MethodBuilder.addToAttributes:(Lio/sundr/codegen/model/AttributeKey;Ljava/lang/Object;)Lio/sundr/codegen/model/AttributeSupportFluent;
     830: checkcast     #41                 // class io/sundr/codegen/model/MethodBuilder
     833: invokevirtual #72                 // Method io/sundr/codegen/model/MethodBuilder.build:()Lio/sundr/codegen/model/EditableMethod;
     836: astore        19
     838: new           #2                  // class java/util/ArrayList
     841: dup
     842: invokespecial #3                  // Method java/util/ArrayList."<init>":()V
     845: astore        20
     847: new           #2                  // class java/util/ArrayList
     850: dup
     851: invokespecial #3                  // Method java/util/ArrayList."<init>":()V
     854: astore        21
     856: new           #2                  // class java/util/ArrayList
     859: dup
     860: invokespecial #3                  // Method java/util/ArrayList."<init>":()V
     863: astore        22
     865: aload         8
     867: invokestatic  #74                 // Method io/sundr/builder/internal/utils/BuilderUtils.isBuildable:(Lio/sundr/codegen/model/TypeRef;)Z
     870: ifeq          1612
     873: aload         8
     875: invokestatic  #75                 // Method io/sundr/codegen/utils/TypeUtils.isAbstract:(Lio/sundr/codegen/model/TypeRef;)Z
     878: ifne          1612
     881: aload         8
     883: checkcast     #76                 // class io/sundr/codegen/model/ClassRef
     886: astore        23
     888: aload         23
     890: invokevirtual #77                 // Method io/sundr/codegen/model/ClassRef.getName:()Ljava/lang/String;
     893: astore        24
     895: aload         12
     897: aload         23
     899: invokevirtual #78                 // Method io/sundr/codegen/model/ClassRef.getDefinition:()Lio/sundr/codegen/model/TypeDef;
     902: invokevirtual #79                 // Method io/sundr/codegen/model/TypeDef.getParameters:()Ljava/util/List;
     905: invokeinterface #80,  2           // InterfaceMethod java/util/List.addAll:(Ljava/util/Collection;)Z
     910: pop
     911: new           #27                 // class java/lang/StringBuilder
     914: dup
     915: invokespecial #28                 // Method java/lang/StringBuilder."<init>":()V
     918: aload         24
     920: invokevirtual #30                 // Method java/lang/StringBuilder.append:(Ljava/lang/String;)Ljava/lang/StringBuilder;
     923: ldc           #81                 // String Builder
     925: invokevirtual #30                 // Method java/lang/StringBuilder.append:(Ljava/lang/String;)Ljava/lang/StringBuilder;
     928: invokevirtual #32                 // Method java/lang/StringBuilder.toString:()Ljava/lang/String;
     931: astore        25
     933: aload         9
     935: getstatic     #82                 // Field io/sundr/builder/internal/functions/TypeAs.BUILDER:Lio/sundr/Function;
     938: aload         23
     940: invokevirtual #78                 // Method io/sundr/codegen/model/ClassRef.getDefinition:()Lio/sundr/codegen/model/TypeDef;
     943: invokeinterface #6,  2            // InterfaceMethod io/sundr/Function.apply:(Ljava/lang/Object;)Ljava/lang/Object;
     948: checkcast     #17                 // class io/sundr/codegen/model/TypeDef
     951: invokevirtual #83                 // Method io/sundr/codegen/model/TypeDef.toInternalReference:()Lio/sundr/codegen/model/ClassRef;
     954: invokeinterface #84,  2           // InterfaceMethod java/util/List.add:(Ljava/lang/Object;)Z
     959: pop
     960: aload         20
     962: new           #54                 // class io/sundr/codegen/model/StringStatement
     965: dup
     966: new           #27                 // class java/lang/StringBuilder
     969: dup
     970: invokespecial #28                 // Method java/lang/StringBuilder."<init>":()V
     973: ldc           #55                 // String if (this.
     975: invokevirtual #30                 // Method java/lang/StringBuilder.append:(Ljava/lang/String;)Ljava/lang/StringBuilder;
     978: aload         17
     980: invokevirtual #30                 // Method java/lang/StringBuilder.append:(Ljava/lang/String;)Ljava/lang/StringBuilder;
     983: ldc           #56                 // String  == null) {this.
     985: invokevirtual #30                 // Method java/lang/StringBuilder.append:(Ljava/lang/String;)Ljava/lang/StringBuilder;
     988: aload         17
     990: invokevirtual #30                 // Method java/lang/StringBuilder.append:(Ljava/lang/String;)Ljava/lang/StringBuilder;
     993: ldc           #57                 // String  =
     995: invokevirtual #30                 // Method java/lang/StringBuilder.append:(Ljava/lang/String;)Ljava/lang/StringBuilder;
     998: aload_1
     999: getstatic     #58                 // Field io/sundr/codegen/model/Attributeable.LAZY_INIT:Lio/sundr/codegen/model/AttributeKey;
    1002: invokevirtual #16                 // Method io/sundr/codegen/model/Property.getAttribute:(Lio/sundr/codegen/model/AttributeKey;)Ljava/lang/Object;
    1005: checkcast     #59                 // class java/lang/String
    1008: invokevirtual #30                 // Method java/lang/StringBuilder.append:(Ljava/lang/String;)Ljava/lang/StringBuilder;
    1011: ldc           #60                 // String ;}
    1013: invokevirtual #30                 // Method java/lang/StringBuilder.append:(Ljava/lang/String;)Ljava/lang/StringBuilder;
    1016: invokevirtual #32                 // Method java/lang/StringBuilder.toString:()Ljava/lang/String;
    1019: invokespecial #61                 // Method io/sundr/codegen/model/StringStatement."<init>":(Ljava/lang/String;)V
    1022: invokeinterface #84,  2           // InterfaceMethod java/util/List.add:(Ljava/lang/Object;)Z
    1027: pop
    1028: aload         20
    1030: new           #54                 // class io/sundr/codegen/model/StringStatement
    1033: dup
    1034: new           #27                 // class java/lang/StringBuilder
    1037: dup
    1038: invokespecial #28                 // Method java/lang/StringBuilder."<init>":()V
    1041: ldc           #85                 // String for (
    1043: invokevirtual #30                 // Method java/lang/StringBuilder.append:(Ljava/lang/String;)Ljava/lang/StringBuilder;
    1046: aload         24
    1048: invokevirtual #30                 // Method java/lang/StringBuilder.append:(Ljava/lang/String;)Ljava/lang/StringBuilder;
    1051: ldc           #86                 // String  item : items) {
    1053: invokevirtual #30                 // Method java/lang/StringBuilder.append:(Ljava/lang/String;)Ljava/lang/StringBuilder;
    1056: aload         25
    1058: invokevirtual #30                 // Method java/lang/StringBuilder.append:(Ljava/lang/String;)Ljava/lang/StringBuilder;
    1061: ldc           #87                 // String  builder = new
    1063: invokevirtual #30                 // Method java/lang/StringBuilder.append:(Ljava/lang/String;)Ljava/lang/StringBuilder;
    1066: aload         25
    1068: invokevirtual #30                 // Method java/lang/StringBuilder.append:(Ljava/lang/String;)Ljava/lang/StringBuilder;
    1071: ldc           #88                 // String (item);_visitables.get(\"
    1073: invokevirtual #30                 // Method java/lang/StringBuilder.append:(Ljava/lang/String;)Ljava/lang/StringBuilder;
    1076: aload         17
    1078: invokevirtual #30                 // Method java/lang/StringBuilder.append:(Ljava/lang/String;)Ljava/lang/StringBuilder;
    1081: ldc           #89                 // String \").add(builder);this.
    1083: invokevirtual #30                 // Method java/lang/StringBuilder.append:(Ljava/lang/String;)Ljava/lang/StringBuilder;
    1086: aload         17
    1088: invokevirtual #30                 // Method java/lang/StringBuilder.append:(Ljava/lang/String;)Ljava/lang/StringBuilder;
    1091: ldc           #90                 // String .add(builder);} return (
    1093: invokevirtual #30                 // Method java/lang/StringBuilder.append:(Ljava/lang/String;)Ljava/lang/StringBuilder;
    1096: aload         7
    1098: invokevirtual #65                 // Method java/lang/StringBuilder.append:(Ljava/lang/Object;)Ljava/lang/StringBuilder;
    1101: ldc           #66                 // String )this;
    1103: invokevirtual #30                 // Method java/lang/StringBuilder.append:(Ljava/lang/String;)Ljava/lang/StringBuilder;
    1106: invokevirtual #32                 // Method java/lang/StringBuilder.toString:()Ljava/lang/String;
    1109: invokespecial #61                 // Method io/sundr/codegen/model/StringStatement."<init>":(Ljava/lang/String;)V
    1112: invokeinterface #84,  2           // InterfaceMethod java/util/List.add:(Ljava/lang/Object;)Z
    1117: pop
    1118: new           #41                 // class io/sundr/codegen/model/MethodBuilder
    1121: dup
    1122: aload         18
    1124: invokespecial #91                 // Method io/sundr/codegen/model/MethodBuilder."<init>":(Lio/sundr/codegen/model/Method;)V
    1127: aload         12
    1129: invokevirtual #47                 // Method io/sundr/codegen/model/MethodBuilder.withParameters:(Ljava/util/List;)Lio/sundr/codegen/model/MethodFluent;
    1132: checkcast     #41                 // class io/sundr/codegen/model/MethodBuilder
    1135: invokevirtual #92                 // Method io/sundr/codegen/model/MethodBuilder.editBlock:()Lio/sundr/codegen/model/MethodFluent$BlockNested;
    1138: iconst_2
    1139: anewarray     #53                 // class io/sundr/codegen/model/Statement
    1142: dup
    1143: iconst_0
    1144: new           #54                 // class io/sundr/codegen/model/StringStatement
    1147: dup
    1148: new           #27                 // class java/lang/StringBuilder
    1151: dup
    1152: invokespecial #28                 // Method java/lang/StringBuilder."<init>":()V
    1155: ldc           #55                 // String if (this.
    1157: invokevirtual #30                 // Method java/lang/StringBuilder.append:(Ljava/lang/String;)Ljava/lang/StringBuilder;
    1160: aload         17
    1162: invokevirtual #30                 // Method java/lang/StringBuilder.append:(Ljava/lang/String;)Ljava/lang/StringBuilder;
    1165: ldc           #56                 // String  == null) {this.
    1167: invokevirtual #30                 // Method java/lang/StringBuilder.append:(Ljava/lang/String;)Ljava/lang/StringBuilder;
    1170: aload         17
    1172: invokevirtual #30                 // Method java/lang/StringBuilder.append:(Ljava/lang/String;)Ljava/lang/StringBuilder;
    1175: ldc           #57                 // String  =
    1177: invokevirtual #30                 // Method java/lang/StringBuilder.append:(Ljava/lang/String;)Ljava/lang/StringBuilder;
    1180: aload_1
    1181: getstatic     #58                 // Field io/sundr/codegen/model/Attributeable.LAZY_INIT:Lio/sundr/codegen/model/AttributeKey;
    1184: invokevirtual #16                 // Method io/sundr/codegen/model/Property.getAttribute:(Lio/sundr/codegen/model/AttributeKey;)Ljava/lang/Object;
    1187: checkcast     #59                 // class java/lang/String
    1190: invokevirtual #30                 // Method java/lang/StringBuilder.append:(Ljava/lang/String;)Ljava/lang/StringBuilder;
    1193: ldc           #60                 // String ;}
    1195: invokevirtual #30                 // Method java/lang/StringBuilder.append:(Ljava/lang/String;)Ljava/lang/StringBuilder;
    1198: invokevirtual #32                 // Method java/lang/StringBuilder.toString:()Ljava/lang/String;
    1201: invokespecial #61                 // Method io/sundr/codegen/model/StringStatement."<init>":(Ljava/lang/String;)V
    1204: aastore
    1205: dup
    1206: iconst_1
    1207: new           #54                 // class io/sundr/codegen/model/StringStatement
    1210: dup
    1211: new           #27                 // class java/lang/StringBuilder
    1214: dup
    1215: invokespecial #28                 // Method java/lang/StringBuilder."<init>":()V
    1218: aload         25
    1220: invokevirtual #30                 // Method java/lang/StringBuilder.append:(Ljava/lang/String;)Ljava/lang/StringBuilder;
    1223: ldc           #87                 // String  builder = new
    1225: invokevirtual #30                 // Method java/lang/StringBuilder.append:(Ljava/lang/String;)Ljava/lang/StringBuilder;
    1228: aload         25
    1230: invokevirtual #30                 // Method java/lang/StringBuilder.append:(Ljava/lang/String;)Ljava/lang/StringBuilder;
    1233: ldc           #88                 // String (item);_visitables.get(\"
    1235: invokevirtual #30                 // Method java/lang/StringBuilder.append:(Ljava/lang/String;)Ljava/lang/StringBuilder;
    1238: aload         17
    1240: invokevirtual #30                 // Method java/lang/StringBuilder.append:(Ljava/lang/String;)Ljava/lang/StringBuilder;
    1243: ldc           #93                 // String \").add(index >= 0 ? index : _visitables.get(\"
    1245: invokevirtual #30                 // Method java/lang/StringBuilder.append:(Ljava/lang/String;)Ljava/lang/StringBuilder;
    1248: aload         17
    1250: invokevirtual #30                 // Method java/lang/StringBuilder.append:(Ljava/lang/String;)Ljava/lang/StringBuilder;
    1253: ldc           #94                 // String \").size(), builder);this.
    1255: invokevirtual #30                 // Method java/lang/StringBuilder.append:(Ljava/lang/String;)Ljava/lang/StringBuilder;
    1258: aload         17
    1260: invokevirtual #30                 // Method java/lang/StringBuilder.append:(Ljava/lang/String;)Ljava/lang/StringBuilder;
    1263: ldc           #95                 // String .add(index >= 0 ? index :
    1265: invokevirtual #30                 // Method java/lang/StringBuilder.append:(Ljava/lang/String;)Ljava/lang/StringBuilder;
    1268: aload         17
    1270: invokevirtual #30                 // Method java/lang/StringBuilder.append:(Ljava/lang/String;)Ljava/lang/StringBuilder;
    1273: ldc           #96                 // String .size(), builder); return (
    1275: invokevirtual #30                 // Method java/lang/StringBuilder.append:(Ljava/lang/String;)Ljava/lang/StringBuilder;
    1278: aload         7
    1280: invokevirtual #65                 // Method java/lang/StringBuilder.append:(Ljava/lang/Object;)Ljava/lang/StringBuilder;
    1283: ldc           #66                 // String )this;
    1285: invokevirtual #30                 // Method java/lang/StringBuilder.append:(Ljava/lang/String;)Ljava/lang/StringBuilder;
    1288: invokevirtual #32                 // Method java/lang/StringBuilder.toString:()Ljava/lang/String;
    1291: invokespecial #61                 // Method io/sundr/codegen/model/StringStatement."<init>":(Ljava/lang/String;)V
    1294: aastore
    1295: invokeinterface #67,  2           // InterfaceMethod io/sundr/codegen/model/MethodFluent$BlockNested.withStatements:([Lio/sundr/codegen/model/Statement;)Lio/sundr/codegen/model/BlockFluent;
    1300: checkcast     #68                 // class io/sundr/codegen/model/MethodFluent$BlockNested
    1303: invokeinterface #69,  1           // InterfaceMethod io/sundr/codegen/model/MethodFluent$BlockNested.endBlock:()Ljava/lang/Object;
    1308: checkcast     #41                 // class io/sundr/codegen/model/MethodBuilder
    1311: invokevirtual #72                 // Method io/sundr/codegen/model/MethodBuilder.build:()Lio/sundr/codegen/model/EditableMethod;
    1314: astore        18
    1316: new           #41                 // class io/sundr/codegen/model/MethodBuilder
    1319: dup
    1320: aload         19
    1322: invokespecial #91                 // Method io/sundr/codegen/model/MethodBuilder."<init>":(Lio/sundr/codegen/model/Method;)V
    1325: aload         12
    1327: invokevirtual #47                 // Method io/sundr/codegen/model/MethodBuilder.withParameters:(Ljava/util/List;)Lio/sundr/codegen/model/MethodFluent;
    1330: checkcast     #41                 // class io/sundr/codegen/model/MethodBuilder
    1333: invokevirtual #92                 // Method io/sundr/codegen/model/MethodBuilder.editBlock:()Lio/sundr/codegen/model/MethodFluent$BlockNested;
    1336: iconst_5
    1337: anewarray     #53                 // class io/sundr/codegen/model/Statement
    1340: dup
    1341: iconst_0
    1342: new           #54                 // class io/sundr/codegen/model/StringStatement
    1345: dup
    1346: new           #27                 // class java/lang/StringBuilder
    1349: dup
    1350: invokespecial #28                 // Method java/lang/StringBuilder."<init>":()V
    1353: ldc           #55                 // String if (this.
    1355: invokevirtual #30                 // Method java/lang/StringBuilder.append:(Ljava/lang/String;)Ljava/lang/StringBuilder;
    1358: aload         17
    1360: invokevirtual #30                 // Method java/lang/StringBuilder.append:(Ljava/lang/String;)Ljava/lang/StringBuilder;
    1363: ldc           #56                 // String  == null) {this.
    1365: invokevirtual #30                 // Method java/lang/StringBuilder.append:(Ljava/lang/String;)Ljava/lang/StringBuilder;
    1368: aload         17
    1370: invokevirtual #30                 // Method java/lang/StringBuilder.append:(Ljava/lang/String;)Ljava/lang/StringBuilder;
    1373: ldc           #57                 // String  =
    1375: invokevirtual #30                 // Method java/lang/StringBuilder.append:(Ljava/lang/String;)Ljava/lang/StringBuilder;
    1378: aload_1
    1379: getstatic     #58                 // Field io/sundr/codegen/model/Attributeable.LAZY_INIT:Lio/sundr/codegen/model/AttributeKey;
    1382: invokevirtual #16                 // Method io/sundr/codegen/model/Property.getAttribute:(Lio/sundr/codegen/model/AttributeKey;)Ljava/lang/Object;
    1385: checkcast     #59                 // class java/lang/String
    1388: invokevirtual #30                 // Method java/lang/StringBuilder.append:(Ljava/lang/String;)Ljava/lang/StringBuilder;
    1391: ldc           #60                 // String ;}
    1393: invokevirtual #30                 // Method java/lang/StringBuilder.append:(Ljava/lang/String;)Ljava/lang/StringBuilder;
    1396: invokevirtual #32                 // Method java/lang/StringBuilder.toString:()Ljava/lang/String;
    1399: invokespecial #61                 // Method io/sundr/codegen/model/StringStatement."<init>":(Ljava/lang/String;)V
    1402: aastore
    1403: dup
    1404: iconst_1
    1405: new           #54                 // class io/sundr/codegen/model/StringStatement
    1408: dup
    1409: new           #27                 // class java/lang/StringBuilder
    1412: dup
    1413: invokespecial #28                 // Method java/lang/StringBuilder."<init>":()V
    1416: aload         25
    1418: invokevirtual #30                 // Method java/lang/StringBuilder.append:(Ljava/lang/String;)Ljava/lang/StringBuilder;
    1421: ldc           #87                 // String  builder = new
    1423: invokevirtual #30                 // Method java/lang/StringBuilder.append:(Ljava/lang/String;)Ljava/lang/StringBuilder;
    1426: aload         25
    1428: invokevirtual #30                 // Method java/lang/StringBuilder.append:(Ljava/lang/String;)Ljava/lang/StringBuilder;
    1431: ldc           #97                 // String (item);
    1433: invokevirtual #30                 // Method java/lang/StringBuilder.append:(Ljava/lang/String;)Ljava/lang/StringBuilder;
    1436: invokevirtual #32                 // Method java/lang/StringBuilder.toString:()Ljava/lang/String;
    1439: invokespecial #61                 // Method io/sundr/codegen/model/StringStatement."<init>":(Ljava/lang/String;)V
    1442: aastore
    1443: dup
    1444: iconst_2
    1445: new           #54                 // class io/sundr/codegen/model/StringStatement
    1448: dup
    1449: new           #27                 // class java/lang/StringBuilder
    1452: dup
    1453: invokespecial #28                 // Method java/lang/StringBuilder."<init>":()V
    1456: ldc           #98                 // String if (index < 0 || index >= _visitables.get(\"
    1458: invokevirtual #30                 // Method java/lang/StringBuilder.append:(Ljava/lang/String;)Ljava/lang/StringBuilder;
    1461: aload         17
    1463: invokevirtual #30                 // Method java/lang/StringBuilder.append:(Ljava/lang/String;)Ljava/lang/StringBuilder;
    1466: ldc           #99                 // String \").size()) { _visitables.get(\"
    1468: invokevirtual #30                 // Method java/lang/StringBuilder.append:(Ljava/lang/String;)Ljava/lang/StringBuilder;
    1471: aload         17
    1473: invokevirtual #30                 // Method java/lang/StringBuilder.append:(Ljava/lang/String;)Ljava/lang/StringBuilder;
    1476: ldc           #100                // String \").add(builder); } else { _visitables.get(\"
    1478: invokevirtual #30                 // Method java/lang/StringBuilder.append:(Ljava/lang/String;)Ljava/lang/StringBuilder;
    1481: aload         17
    1483: invokevirtual #30                 // Method java/lang/StringBuilder.append:(Ljava/lang/String;)Ljava/lang/StringBuilder;
    1486: ldc           #101                // String \").set(index, builder);}
    1488: invokevirtual #30                 // Method java/lang/StringBuilder.append:(Ljava/lang/String;)Ljava/lang/StringBuilder;
    1491: invokevirtual #32                 // Method java/lang/StringBuilder.toString:()Ljava/lang/String;
    1494: invokespecial #61                 // Method io/sundr/codegen/model/StringStatement."<init>":(Ljava/lang/String;)V
    1497: aastore
    1498: dup
    1499: iconst_3
    1500: new           #54                 // class io/sundr/codegen/model/StringStatement
    1503: dup
    1504: new           #27                 // class java/lang/StringBuilder
    1507: dup
    1508: invokespecial #28                 // Method java/lang/StringBuilder."<init>":()V
    1511: ldc           #102                // String if (index < 0 || index >=
    1513: invokevirtual #30                 // Method java/lang/StringBuilder.append:(Ljava/lang/String;)Ljava/lang/StringBuilder;
    1516: aload         17
    1518: invokevirtual #30                 // Method java/lang/StringBuilder.append:(Ljava/lang/String;)Ljava/lang/StringBuilder;
    1521: ldc           #103                // String .size()) {
    1523: invokevirtual #30                 // Method java/lang/StringBuilder.append:(Ljava/lang/String;)Ljava/lang/StringBuilder;
    1526: aload         17
    1528: invokevirtual #30                 // Method java/lang/StringBuilder.append:(Ljava/lang/String;)Ljava/lang/StringBuilder;
    1531: ldc           #104                // String .add(builder); } else {
    1533: invokevirtual #30                 // Method java/lang/StringBuilder.append:(Ljava/lang/String;)Ljava/lang/StringBuilder;
    1536: aload         17
    1538: invokevirtual #30                 // Method java/lang/StringBuilder.append:(Ljava/lang/String;)Ljava/lang/StringBuilder;
    1541: ldc           #105                // String .set(index, builder);}
    1543: invokevirtual #30                 // Method java/lang/StringBuilder.append:(Ljava/lang/String;)Ljava/lang/StringBuilder;
    1546: invokevirtual #32                 // Method java/lang/StringBuilder.toString:()Ljava/lang/String;
    1549: invokespecial #61                 // Method io/sundr/codegen/model/StringStatement."<init>":(Ljava/lang/String;)V
    1552: aastore
    1553: dup
    1554: iconst_4
    1555: new           #54                 // class io/sundr/codegen/model/StringStatement
    1558: dup
    1559: new           #27                 // class java/lang/StringBuilder
    1562: dup
    1563: invokespecial #28                 // Method java/lang/StringBuilder."<init>":()V
    1566: ldc           #106                // String  return (
    1568: invokevirtual #30                 // Method java/lang/StringBuilder.append:(Ljava/lang/String;)Ljava/lang/StringBuilder;
    1571: aload         7
    1573: invokevirtual #65                 // Method java/lang/StringBuilder.append:(Ljava/lang/Object;)Ljava/lang/StringBuilder;
    1576: ldc           #66                 // String )this;
    1578: invokevirtual #30                 // Method java/lang/StringBuilder.append:(Ljava/lang/String;)Ljava/lang/StringBuilder;
    1581: invokevirtual #32                 // Method java/lang/StringBuilder.toString:()Ljava/lang/String;
    1584: invokespecial #61                 // Method io/sundr/codegen/model/StringStatement."<init>":(Ljava/lang/String;)V
    1587: aastore
    1588: invokeinterface #67,  2           // InterfaceMethod io/sundr/codegen/model/MethodFluent$BlockNested.withStatements:([Lio/sundr/codegen/model/Statement;)Lio/sundr/codegen/model/BlockFluent;
    1593: checkcast     #68                 // class io/sundr/codegen/model/MethodFluent$BlockNested
    1596: invokeinterface #69,  1           // InterfaceMethod io/sundr/codegen/model/MethodFluent$BlockNested.endBlock:()Ljava/lang/Object;
    1601: checkcast     #41                 // class io/sundr/codegen/model/MethodBuilder
    1604: invokevirtual #72                 // Method io/sundr/codegen/model/MethodBuilder.build:()Lio/sundr/codegen/model/EditableMethod;
    1607: astore        19
    1609: goto          2642
    1612: aload         16
    1614: invokeinterface #107,  1          // InterfaceMethod java/util/Set.isEmpty:()Z
    1619: ifne          2509
    1622: aload         8
    1624: checkcast     #76                 // class io/sundr/codegen/model/ClassRef
    1627: astore        23
    1629: aload         12
    1631: aload         23
    1633: invokevirtual #78                 // Method io/sundr/codegen/model/ClassRef.getDefinition:()Lio/sundr/codegen/model/TypeDef;
    1636: invokevirtual #79                 // Method io/sundr/codegen/model/TypeDef.getParameters:()Ljava/util/List;
    1639: invokeinterface #80,  2           // InterfaceMethod java/util/List.addAll:(Ljava/util/Collection;)Z
    1644: pop
    1645: aload         21
    1647: new           #54                 // class io/sundr/codegen/model/StringStatement
    1650: dup
    1651: new           #27                 // class java/lang/StringBuilder
    1654: dup
    1655: invokespecial #28                 // Method java/lang/StringBuilder."<init>":()V
    1658: ldc           #108                // String  if (items != null && items.length > 0 && this.
    1660: invokevirtual #30                 // Method java/lang/StringBuilder.append:(Ljava/lang/String;)Ljava/lang/StringBuilder;
    1663: aload         17
    1665: invokevirtual #30                 // Method java/lang/StringBuilder.append:(Ljava/lang/String;)Ljava/lang/StringBuilder;
    1668: ldc           #109                // String == null) {this.
    1670: invokevirtual #30                 // Method java/lang/StringBuilder.append:(Ljava/lang/String;)Ljava/lang/StringBuilder;
    1673: aload         17
    1675: invokevirtual #30                 // Method java/lang/StringBuilder.append:(Ljava/lang/String;)Ljava/lang/StringBuilder;
    1678: ldc           #110                // String  = new ArrayList<VisitableBuilder<? extends
    1680: invokevirtual #30                 // Method java/lang/StringBuilder.append:(Ljava/lang/String;)Ljava/lang/StringBuilder;
    1683: aload         23
    1685: invokevirtual #65                 // Method java/lang/StringBuilder.append:(Ljava/lang/Object;)Ljava/lang/StringBuilder;
    1688: ldc           #111                // String ,?>>();}
    1690: invokevirtual #30                 // Method java/lang/StringBuilder.append:(Ljava/lang/String;)Ljava/lang/StringBuilder;
    1693: invokevirtual #32                 // Method java/lang/StringBuilder.toString:()Ljava/lang/String;
    1696: invokespecial #61                 // Method io/sundr/codegen/model/StringStatement."<init>":(Ljava/lang/String;)V
    1699: invokeinterface #84,  2           // InterfaceMethod java/util/List.add:(Ljava/lang/Object;)Z
    1704: pop
    1705: aload         22
    1707: new           #54                 // class io/sundr/codegen/model/StringStatement
    1710: dup
    1711: new           #27                 // class java/lang/StringBuilder
    1714: dup
    1715: invokespecial #28                 // Method java/lang/StringBuilder."<init>":()V
    1718: ldc           #112                // String  if (items != null && items.size() > 0 && this.
    1720: invokevirtual #30                 // Method java/lang/StringBuilder.append:(Ljava/lang/String;)Ljava/lang/StringBuilder;
    1723: aload         17
    1725: invokevirtual #30                 // Method java/lang/StringBuilder.append:(Ljava/lang/String;)Ljava/lang/StringBuilder;
    1728: ldc           #109                // String == null) {this.
    1730: invokevirtual #30                 // Method java/lang/StringBuilder.append:(Ljava/lang/String;)Ljava/lang/StringBuilder;
    1733: aload         17
    1735: invokevirtual #30                 // Method java/lang/StringBuilder.append:(Ljava/lang/String;)Ljava/lang/StringBuilder;
    1738: ldc           #110                // String  = new ArrayList<VisitableBuilder<? extends
    1740: invokevirtual #30                 // Method java/lang/StringBuilder.append:(Ljava/lang/String;)Ljava/lang/StringBuilder;
    1743: aload         23
    1745: invokevirtual #65                 // Method java/lang/StringBuilder.append:(Ljava/lang/Object;)Ljava/lang/StringBuilder;
    1748: ldc           #111                // String ,?>>();}
    1750: invokevirtual #30                 // Method java/lang/StringBuilder.append:(Ljava/lang/String;)Ljava/lang/StringBuilder;
    1753: invokevirtual #32                 // Method java/lang/StringBuilder.toString:()Ljava/lang/String;
    1756: invokespecial #61                 // Method io/sundr/codegen/model/StringStatement."<init>":(Ljava/lang/String;)V
    1759: invokeinterface #84,  2           // InterfaceMethod java/util/List.add:(Ljava/lang/Object;)Z
    1764: pop
    1765: aload         20
    1767: new           #54                 // class io/sundr/codegen/model/StringStatement
    1770: dup
    1771: new           #27                 // class java/lang/StringBuilder
    1774: dup
    1775: invokespecial #28                 // Method java/lang/StringBuilder."<init>":()V
    1778: ldc           #85                 // String for (
    1780: invokevirtual #30                 // Method java/lang/StringBuilder.append:(Ljava/lang/String;)Ljava/lang/StringBuilder;
    1783: aload         23
    1785: invokevirtual #113                // Method io/sundr/codegen/model/ClassRef.toString:()Ljava/lang/String;
    1788: invokevirtual #30                 // Method java/lang/StringBuilder.append:(Ljava/lang/String;)Ljava/lang/StringBuilder;
    1791: ldc           #114                // String  item : items) {
    1793: invokevirtual #30                 // Method java/lang/StringBuilder.append:(Ljava/lang/String;)Ljava/lang/StringBuilder;
    1796: invokevirtual #32                 // Method java/lang/StringBuilder.toString:()Ljava/lang/String;
    1799: invokespecial #61                 // Method io/sundr/codegen/model/StringStatement."<init>":(Ljava/lang/String;)V
    1802: invokeinterface #84,  2           // InterfaceMethod java/util/List.add:(Ljava/lang/Object;)Z
    1807: pop
    1808: aload         20
    1810: aload_0
    1811: ldc           #29                 // String addTo
    1813: aload         16
    1815: iconst_0
    1816: invokespecial #115                // Method createAddToDescendants:(Ljava/lang/String;Ljava/util/Set;Z)Lio/sundr/codegen/model/Statement;
    1819: invokeinterface #84,  2           // InterfaceMethod java/util/List.add:(Ljava/lang/Object;)Z
    1824: pop
    1825: aload         20
    1827: aload_0
    1828: aload         23
    1830: invokevirtual #77                 // Method io/sundr/codegen/model/ClassRef.getName:()Ljava/lang/String;
    1833: aload         17
    1835: invokespecial #116                // Method createAddToDescendantsFallback:(Ljava/lang/String;Ljava/lang/String;)Lio/sundr/codegen/model/Statement;
    1838: invokeinterface #84,  2           // InterfaceMethod java/util/List.add:(Ljava/lang/Object;)Z
    1843: pop
    1844: aload         20
    1846: new           #54                 // class io/sundr/codegen/model/StringStatement
    1849: dup
    1850: new           #27                 // class java/lang/StringBuilder
    1853: dup
    1854: invokespecial #28                 // Method java/lang/StringBuilder."<init>":()V
    1857: ldc           #117                // String } return (
    1859: invokevirtual #30                 // Method java/lang/StringBuilder.append:(Ljava/lang/String;)Ljava/lang/StringBuilder;
    1862: aload         7
    1864: invokevirtual #65                 // Method java/lang/StringBuilder.append:(Ljava/lang/Object;)Ljava/lang/StringBuilder;
    1867: ldc           #66                 // String )this;
    1869: invokevirtual #30                 // Method java/lang/StringBuilder.append:(Ljava/lang/String;)Ljava/lang/StringBuilder;
    1872: invokevirtual #32                 // Method java/lang/StringBuilder.toString:()Ljava/lang/String;
    1875: invokespecial #61                 // Method io/sundr/codegen/model/StringStatement."<init>":(Ljava/lang/String;)V
    1878: invokeinterface #84,  2           // InterfaceMethod java/util/List.add:(Ljava/lang/Object;)Z
    1883: pop
    1884: new           #41                 // class io/sundr/codegen/model/MethodBuilder
    1887: dup
    1888: aload         18
    1890: invokespecial #91                 // Method io/sundr/codegen/model/MethodBuilder."<init>":(Lio/sundr/codegen/model/Method;)V
    1893: aload         12
    1895: invokevirtual #47                 // Method io/sundr/codegen/model/MethodBuilder.withParameters:(Ljava/util/List;)Lio/sundr/codegen/model/MethodFluent;
    1898: checkcast     #41                 // class io/sundr/codegen/model/MethodBuilder
    1901: invokevirtual #92                 // Method io/sundr/codegen/model/MethodBuilder.editBlock:()Lio/sundr/codegen/model/MethodFluent$BlockNested;
    1904: iconst_2
    1905: anewarray     #53                 // class io/sundr/codegen/model/Statement
    1908: dup
    1909: iconst_0
    1910: aload_0
    1911: ldc           #29                 // String addTo
    1913: aload         16
    1915: iconst_1
    1916: invokespecial #115                // Method createAddToDescendants:(Ljava/lang/String;Ljava/util/Set;Z)Lio/sundr/codegen/model/Statement;
    1919: aastore
    1920: dup
    1921: iconst_1
    1922: new           #54                 // class io/sundr/codegen/model/StringStatement
    1925: dup
    1926: new           #27                 // class java/lang/StringBuilder
    1929: dup
    1930: invokespecial #28                 // Method java/lang/StringBuilder."<init>":()V
    1933: ldc           #64                 // String return (
    1935: invokevirtual #30                 // Method java/lang/StringBuilder.append:(Ljava/lang/String;)Ljava/lang/StringBuilder;
    1938: aload         7
    1940: invokevirtual #65                 // Method java/lang/StringBuilder.append:(Ljava/lang/Object;)Ljava/lang/StringBuilder;
    1943: ldc           #66                 // String )this;
    1945: invokevirtual #30                 // Method java/lang/StringBuilder.append:(Ljava/lang/String;)Ljava/lang/StringBuilder;
    1948: invokevirtual #32                 // Method java/lang/StringBuilder.toString:()Ljava/lang/String;
    1951: invokespecial #61                 // Method io/sundr/codegen/model/StringStatement."<init>":(Ljava/lang/String;)V
    1954: aastore
    1955: invokeinterface #67,  2           // InterfaceMethod io/sundr/codegen/model/MethodFluent$BlockNested.withStatements:([Lio/sundr/codegen/model/Statement;)Lio/sundr/codegen/model/BlockFluent;
    1960: checkcast     #68                 // class io/sundr/codegen/model/MethodFluent$BlockNested
    1963: invokeinterface #69,  1           // InterfaceMethod io/sundr/codegen/model/MethodFluent$BlockNested.endBlock:()Ljava/lang/Object;
    1968: checkcast     #41                 // class io/sundr/codegen/model/MethodBuilder
    1971: invokevirtual #72                 // Method io/sundr/codegen/model/MethodBuilder.build:()Lio/sundr/codegen/model/EditableMethod;
    1974: astore        18
    1976: new           #41                 // class io/sundr/codegen/model/MethodBuilder
    1979: dup
    1980: aload         19
    1982: invokespecial #91                 // Method io/sundr/codegen/model/MethodBuilder."<init>":(Lio/sundr/codegen/model/Method;)V
    1985: aload         12
    1987: invokevirtual #47                 // Method io/sundr/codegen/model/MethodBuilder.withParameters:(Ljava/util/List;)Lio/sundr/codegen/model/MethodFluent;
    1990: checkcast     #41                 // class io/sundr/codegen/model/MethodBuilder
    1993: invokevirtual #92                 // Method io/sundr/codegen/model/MethodBuilder.editBlock:()Lio/sundr/codegen/model/MethodFluent$BlockNested;
    1996: iconst_2
    1997: anewarray     #53                 // class io/sundr/codegen/model/Statement
    2000: dup
    2001: iconst_0
    2002: aload_0
    2003: ldc           #33                 // String setTo
    2005: aload         16
    2007: iconst_1
    2008: invokespecial #115                // Method createAddToDescendants:(Ljava/lang/String;Ljava/util/Set;Z)Lio/sundr/codegen/model/Statement;
    2011: aastore
    2012: dup
    2013: iconst_1
    2014: new           #54                 // class io/sundr/codegen/model/StringStatement
    2017: dup
    2018: new           #27                 // class java/lang/StringBuilder
    2021: dup
    2022: invokespecial #28                 // Method java/lang/StringBuilder."<init>":()V
    2025: ldc           #64                 // String return (
    2027: invokevirtual #30                 // Method java/lang/StringBuilder.append:(Ljava/lang/String;)Ljava/lang/StringBuilder;
    2030: aload         7
    2032: invokevirtual #65                 // Method java/lang/StringBuilder.append:(Ljava/lang/Object;)Ljava/lang/StringBuilder;
    2035: ldc           #66                 // String )this;
    2037: invokevirtual #30                 // Method java/lang/StringBuilder.append:(Ljava/lang/String;)Ljava/lang/StringBuilder;
    2040: invokevirtual #32                 // Method java/lang/StringBuilder.toString:()Ljava/lang/String;
    2043: invokespecial #61                 // Method io/sundr/codegen/model/StringStatement."<init>":(Ljava/lang/String;)V
    2046: aastore
    2047: invokeinterface #67,  2           // InterfaceMethod io/sundr/codegen/model/MethodFluent$BlockNested.withStatements:([Lio/sundr/codegen/model/Statement;)Lio/sundr/codegen/model/BlockFluent;
    2052: checkcast     #68                 // class io/sundr/codegen/model/MethodFluent$BlockNested
    2055: invokeinterface #69,  1           // InterfaceMethod io/sundr/codegen/model/MethodFluent$BlockNested.endBlock:()Ljava/lang/Object;
    2060: checkcast     #41                 // class io/sundr/codegen/model/MethodBuilder
    2063: invokevirtual #72                 // Method io/sundr/codegen/model/MethodBuilder.build:()Lio/sundr/codegen/model/EditableMethod;
    2066: astore        19
    2068: aload_2
    2069: new           #41                 // class io/sundr/codegen/model/MethodBuilder
    2072: dup
    2073: invokespecial #42                 // Method io/sundr/codegen/model/MethodBuilder."<init>":()V
    2076: iconst_1
    2077: anewarray     #43                 // class javax/lang/model/element/Modifier
    2080: dup
    2081: iconst_0
    2082: getstatic     #44                 // Field javax/lang/model/element/Modifier.PUBLIC:Ljavax/lang/model/element/Modifier;
    2085: aastore
    2086: invokestatic  #45                 // Method io/sundr/codegen/utils/TypeUtils.modifiersToInt:([Ljavax/lang/model/element/Modifier;)I
    2089: invokevirtual #46                 // Method io/sundr/codegen/model/MethodBuilder.withModifiers:(I)Lio/sundr/codegen/model/ModifierSupportFluent;
    2092: checkcast     #41                 // class io/sundr/codegen/model/MethodBuilder
    2095: aload         12
    2097: invokevirtual #47                 // Method io/sundr/codegen/model/MethodBuilder.withParameters:(Ljava/util/List;)Lio/sundr/codegen/model/MethodFluent;
    2100: checkcast     #41                 // class io/sundr/codegen/model/MethodBuilder
    2103: aload         13
    2105: invokevirtual #48                 // Method io/sundr/codegen/model/MethodBuilder.withName:(Ljava/lang/String;)Lio/sundr/codegen/model/MethodFluent;
    2108: checkcast     #41                 // class io/sundr/codegen/model/MethodBuilder
    2111: aload         7
    2113: invokevirtual #49                 // Method io/sundr/codegen/model/MethodBuilder.withReturnType:(Lio/sundr/codegen/model/TypeRef;)Lio/sundr/codegen/model/MethodFluent;
    2116: checkcast     #41                 // class io/sundr/codegen/model/MethodBuilder
    2119: iconst_1
    2120: anewarray     #40                 // class io/sundr/codegen/model/Property
    2123: dup
    2124: iconst_0
    2125: aload         5
    2127: aastore
    2128: invokevirtual #118                // Method io/sundr/codegen/model/MethodBuilder.withArguments:([Lio/sundr/codegen/model/Property;)Lio/sundr/codegen/model/MethodFluent;
    2131: checkcast     #41                 // class io/sundr/codegen/model/MethodBuilder
    2134: invokevirtual #52                 // Method io/sundr/codegen/model/MethodBuilder.withNewBlock:()Lio/sundr/codegen/model/MethodFluent$BlockNested;
    2137: iconst_2
    2138: anewarray     #53                 // class io/sundr/codegen/model/Statement
    2141: dup
    2142: iconst_0
    2143: new           #54                 // class io/sundr/codegen/model/StringStatement
    2146: dup
    2147: new           #27                 // class java/lang/StringBuilder
    2150: dup
    2151: invokespecial #28                 // Method java/lang/StringBuilder."<init>":()V
    2154: ldc           #55                 // String if (this.
    2156: invokevirtual #30                 // Method java/lang/StringBuilder.append:(Ljava/lang/String;)Ljava/lang/StringBuilder;
    2159: aload         17
    2161: invokevirtual #30                 // Method java/lang/StringBuilder.append:(Ljava/lang/String;)Ljava/lang/StringBuilder;
    2164: ldc           #56                 // String  == null) {this.
    2166: invokevirtual #30                 // Method java/lang/StringBuilder.append:(Ljava/lang/String;)Ljava/lang/StringBuilder;
    2169: aload         17
    2171: invokevirtual #30                 // Method java/lang/StringBuilder.append:(Ljava/lang/String;)Ljava/lang/StringBuilder;
    2174: ldc           #57                 // String  =
    2176: invokevirtual #30                 // Method java/lang/StringBuilder.append:(Ljava/lang/String;)Ljava/lang/StringBuilder;
    2179: aload_1
    2180: getstatic     #58                 // Field io/sundr/codegen/model/Attributeable.LAZY_INIT:Lio/sundr/codegen/model/AttributeKey;
    2183: invokevirtual #16                 // Method io/sundr/codegen/model/Property.getAttribute:(Lio/sundr/codegen/model/AttributeKey;)Ljava/lang/Object;
    2186: checkcast     #59                 // class java/lang/String
    2189: invokevirtual #30                 // Method java/lang/StringBuilder.append:(Ljava/lang/String;)Ljava/lang/StringBuilder;
    2192: ldc           #60                 // String ;}
    2194: invokevirtual #30                 // Method java/lang/StringBuilder.append:(Ljava/lang/String;)Ljava/lang/StringBuilder;
    2197: invokevirtual #32                 // Method java/lang/StringBuilder.toString:()Ljava/lang/String;
    2200: invokespecial #61                 // Method io/sundr/codegen/model/StringStatement."<init>":(Ljava/lang/String;)V
    2203: aastore
    2204: dup
    2205: iconst_1
    2206: new           #54                 // class io/sundr/codegen/model/StringStatement
    2209: dup
    2210: new           #27                 // class java/lang/StringBuilder
    2213: dup
    2214: invokespecial #28                 // Method java/lang/StringBuilder."<init>":()V
    2217: ldc           #119                // String _visitables.get(\"
    2219: invokevirtual #30                 // Method java/lang/StringBuilder.append:(Ljava/lang/String;)Ljava/lang/StringBuilder;
    2222: aload         17
    2224: invokevirtual #30                 // Method java/lang/StringBuilder.append:(Ljava/lang/String;)Ljava/lang/StringBuilder;
    2227: ldc           #89                 // String \").add(builder);this.
    2229: invokevirtual #30                 // Method java/lang/StringBuilder.append:(Ljava/lang/String;)Ljava/lang/StringBuilder;
    2232: aload         17
    2234: invokevirtual #30                 // Method java/lang/StringBuilder.append:(Ljava/lang/String;)Ljava/lang/StringBuilder;
    2237: ldc           #120                // String .add(builder); return (
    2239: invokevirtual #30                 // Method java/lang/StringBuilder.append:(Ljava/lang/String;)Ljava/lang/StringBuilder;
    2242: aload         7
    2244: invokevirtual #65                 // Method java/lang/StringBuilder.append:(Ljava/lang/Object;)Ljava/lang/StringBuilder;
    2247: ldc           #66                 // String )this;
    2249: invokevirtual #30                 // Method java/lang/StringBuilder.append:(Ljava/lang/String;)Ljava/lang/StringBuilder;
    2252: invokevirtual #32                 // Method java/lang/StringBuilder.toString:()Ljava/lang/String;
    2255: invokespecial #61                 // Method io/sundr/codegen/model/StringStatement."<init>":(Ljava/lang/String;)V
    2258: aastore
    2259: invokeinterface #121,  2          // InterfaceMethod io/sundr/codegen/model/MethodFluent$BlockNested.addToStatements:([Lio/sundr/codegen/model/Statement;)Lio/sundr/codegen/model/BlockFluent;
    2264: checkcast     #68                 // class io/sundr/codegen/model/MethodFluent$BlockNested
    2267: invokeinterface #69,  1           // InterfaceMethod io/sundr/codegen/model/MethodFluent$BlockNested.endBlock:()Ljava/lang/Object;
    2272: checkcast     #41                 // class io/sundr/codegen/model/MethodBuilder
    2275: invokevirtual #72                 // Method io/sundr/codegen/model/MethodBuilder.build:()Lio/sundr/codegen/model/EditableMethod;
    2278: invokeinterface #84,  2           // InterfaceMethod java/util/List.add:(Ljava/lang/Object;)Z
    2283: pop
    2284: aload_2
    2285: new           #41                 // class io/sundr/codegen/model/MethodBuilder
    2288: dup
    2289: invokespecial #42                 // Method io/sundr/codegen/model/MethodBuilder."<init>":()V
    2292: iconst_1
    2293: anewarray     #43                 // class javax/lang/model/element/Modifier
    2296: dup
    2297: iconst_0
    2298: getstatic     #44                 // Field javax/lang/model/element/Modifier.PUBLIC:Ljavax/lang/model/element/Modifier;
    2301: aastore
    2302: invokestatic  #45                 // Method io/sundr/codegen/utils/TypeUtils.modifiersToInt:([Ljavax/lang/model/element/Modifier;)I
    2305: invokevirtual #46                 // Method io/sundr/codegen/model/MethodBuilder.withModifiers:(I)Lio/sundr/codegen/model/ModifierSupportFluent;
    2308: checkcast     #41                 // class io/sundr/codegen/model/MethodBuilder
    2311: aload         12
    2313: invokevirtual #47                 // Method io/sundr/codegen/model/MethodBuilder.withParameters:(Ljava/util/List;)Lio/sundr/codegen/model/MethodFluent;
    2316: checkcast     #41                 // class io/sundr/codegen/model/MethodBuilder
    2319: aload         13
    2321: invokevirtual #48                 // Method io/sundr/codegen/model/MethodBuilder.withName:(Ljava/lang/String;)Lio/sundr/codegen/model/MethodFluent;
    2324: checkcast     #41                 // class io/sundr/codegen/model/MethodBuilder
    2327: aload         7
    2329: invokevirtual #49                 // Method io/sundr/codegen/model/MethodBuilder.withReturnType:(Lio/sundr/codegen/model/TypeRef;)Lio/sundr/codegen/model/MethodFluent;
    2332: checkcast     #41                 // class io/sundr/codegen/model/MethodBuilder
    2335: iconst_2
    2336: anewarray     #40                 // class io/sundr/codegen/model/Property
    2339: dup
    2340: iconst_0
    2341: getstatic     #50                 // Field io/sundr/builder/Constants.INDEX:Lio/sundr/codegen/model/Property;
    2344: aastore
    2345: dup
    2346: iconst_1
    2347: aload         5
    2349: aastore
    2350: invokevirtual #118                // Method io/sundr/codegen/model/MethodBuilder.withArguments:([Lio/sundr/codegen/model/Property;)Lio/sundr/codegen/model/MethodFluent;
    2353: checkcast     #41                 // class io/sundr/codegen/model/MethodBuilder
    2356: invokevirtual #52                 // Method io/sundr/codegen/model/MethodBuilder.withNewBlock:()Lio/sundr/codegen/model/MethodFluent$BlockNested;
    2359: iconst_2
    2360: anewarray     #53                 // class io/sundr/codegen/model/Statement
    2363: dup
    2364: iconst_0
    2365: new           #54                 // class io/sundr/codegen/model/StringStatement
    2368: dup
    2369: new           #27                 // class java/lang/StringBuilder
    2372: dup
    2373: invokespecial #28                 // Method java/lang/StringBuilder."<init>":()V
    2376: ldc           #55                 // String if (this.
    2378: invokevirtual #30                 // Method java/lang/StringBuilder.append:(Ljava/lang/String;)Ljava/lang/StringBuilder;
    2381: aload         17
    2383: invokevirtual #30                 // Method java/lang/StringBuilder.append:(Ljava/lang/String;)Ljava/lang/StringBuilder;
    2386: ldc           #56                 // String  == null) {this.
    2388: invokevirtual #30                 // Method java/lang/StringBuilder.append:(Ljava/lang/String;)Ljava/lang/StringBuilder;
    2391: aload         17
    2393: invokevirtual #30                 // Method java/lang/StringBuilder.append:(Ljava/lang/String;)Ljava/lang/StringBuilder;
    2396: ldc           #57                 // String  =
    2398: invokevirtual #30                 // Method java/lang/StringBuilder.append:(Ljava/lang/String;)Ljava/lang/StringBuilder;
    2401: aload_1
    2402: getstatic     #58                 // Field io/sundr/codegen/model/Attributeable.LAZY_INIT:Lio/sundr/codegen/model/AttributeKey;
    2405: invokevirtual #16                 // Method io/sundr/codegen/model/Property.getAttribute:(Lio/sundr/codegen/model/AttributeKey;)Ljava/lang/Object;
    2408: checkcast     #59                 // class java/lang/String
    2411: invokevirtual #30                 // Method java/lang/StringBuilder.append:(Ljava/lang/String;)Ljava/lang/StringBuilder;
    2414: ldc           #60                 // String ;}
    2416: invokevirtual #30                 // Method java/lang/StringBuilder.append:(Ljava/lang/String;)Ljava/lang/StringBuilder;
    2419: invokevirtual #32                 // Method java/lang/StringBuilder.toString:()Ljava/lang/String;
    2422: invokespecial #61                 // Method io/sundr/codegen/model/StringStatement."<init>":(Ljava/lang/String;)V
    2425: aastore
    2426: dup
    2427: iconst_1
    2428: new           #54                 // class io/sundr/codegen/model/StringStatement
    2431: dup
    2432: new           #27                 // class java/lang/StringBuilder
    2435: dup
    2436: invokespecial #28                 // Method java/lang/StringBuilder."<init>":()V
    2439: ldc           #119                // String _visitables.get(\"
    2441: invokevirtual #30                 // Method java/lang/StringBuilder.append:(Ljava/lang/String;)Ljava/lang/StringBuilder;
    2444: aload         17
    2446: invokevirtual #30                 // Method java/lang/StringBuilder.append:(Ljava/lang/String;)Ljava/lang/StringBuilder;
    2449: ldc           #122                // String \").add(index, builder);this.
    2451: invokevirtual #30                 // Method java/lang/StringBuilder.append:(Ljava/lang/String;)Ljava/lang/StringBuilder;
    2454: aload         17
    2456: invokevirtual #30                 // Method java/lang/StringBuilder.append:(Ljava/lang/String;)Ljava/lang/StringBuilder;
    2459: ldc           #123                // String .add(index, builder); return (
    2461: invokevirtual #30                 // Method java/lang/StringBuilder.append:(Ljava/lang/String;)Ljava/lang/StringBuilder;
    2464: aload         7
    2466: invokevirtual #65                 // Method java/lang/StringBuilder.append:(Ljava/lang/Object;)Ljava/lang/StringBuilder;
    2469: ldc           #66                 // String )this;
    2471: invokevirtual #30                 // Method java/lang/StringBuilder.append:(Ljava/lang/String;)Ljava/lang/StringBuilder;
    2474: invokevirtual #32                 // Method java/lang/StringBuilder.toString:()Ljava/lang/String;
    2477: invokespecial #61                 // Method io/sundr/codegen/model/StringStatement."<init>":(Ljava/lang/String;)V
    2480: aastore
    2481: invokeinterface #121,  2          // InterfaceMethod io/sundr/codegen/model/MethodFluent$BlockNested.addToStatements:([Lio/sundr/codegen/model/Statement;)Lio/sundr/codegen/model/BlockFluent;
    2486: checkcast     #68                 // class io/sundr/codegen/model/MethodFluent$BlockNested
    2489: invokeinterface #69,  1           // InterfaceMethod io/sundr/codegen/model/MethodFluent$BlockNested.endBlock:()Ljava/lang/Object;
    2494: checkcast     #41                 // class io/sundr/codegen/model/MethodBuilder
    2497: invokevirtual #72                 // Method io/sundr/codegen/model/MethodBuilder.build:()Lio/sundr/codegen/model/EditableMethod;
    2500: invokeinterface #84,  2           // InterfaceMethod java/util/List.add:(Ljava/lang/Object;)Z
    2505: pop
    2506: goto          2642
    2509: aload         20
    2511: new           #54                 // class io/sundr/codegen/model/StringStatement
    2514: dup
    2515: new           #27                 // class java/lang/StringBuilder
    2518: dup
    2519: invokespecial #28                 // Method java/lang/StringBuilder."<init>":()V
    2522: ldc           #55                 // String if (this.
    2524: invokevirtual #30                 // Method java/lang/StringBuilder.append:(Ljava/lang/String;)Ljava/lang/StringBuilder;
    2527: aload         17
    2529: invokevirtual #30                 // Method java/lang/StringBuilder.append:(Ljava/lang/String;)Ljava/lang/StringBuilder;
    2532: ldc           #56                 // String  == null) {this.
    2534: invokevirtual #30                 // Method java/lang/StringBuilder.append:(Ljava/lang/String;)Ljava/lang/StringBuilder;
    2537: aload         17
    2539: invokevirtual #30                 // Method java/lang/StringBuilder.append:(Ljava/lang/String;)Ljava/lang/StringBuilder;
    2542: ldc           #57                 // String  =
    2544: invokevirtual #30                 // Method java/lang/StringBuilder.append:(Ljava/lang/String;)Ljava/lang/StringBuilder;
    2547: aload_1
    2548: getstatic     #58                 // Field io/sundr/codegen/model/Attributeable.LAZY_INIT:Lio/sundr/codegen/model/AttributeKey;
    2551: invokevirtual #16                 // Method io/sundr/codegen/model/Property.getAttribute:(Lio/sundr/codegen/model/AttributeKey;)Ljava/lang/Object;
    2554: checkcast     #59                 // class java/lang/String
    2557: invokevirtual #30                 // Method java/lang/StringBuilder.append:(Ljava/lang/String;)Ljava/lang/StringBuilder;
    2560: ldc           #60                 // String ;}
    2562: invokevirtual #30                 // Method java/lang/StringBuilder.append:(Ljava/lang/String;)Ljava/lang/StringBuilder;
    2565: invokevirtual #32                 // Method java/lang/StringBuilder.toString:()Ljava/lang/String;
    2568: invokespecial #61                 // Method io/sundr/codegen/model/StringStatement."<init>":(Ljava/lang/String;)V
    2571: invokeinterface #84,  2           // InterfaceMethod java/util/List.add:(Ljava/lang/Object;)Z
    2576: pop
    2577: aload         20
    2579: new           #54                 // class io/sundr/codegen/model/StringStatement
    2582: dup
    2583: new           #27                 // class java/lang/StringBuilder
    2586: dup
    2587: invokespecial #28                 // Method java/lang/StringBuilder."<init>":()V
    2590: ldc           #85                 // String for (
    2592: invokevirtual #30                 // Method java/lang/StringBuilder.append:(Ljava/lang/String;)Ljava/lang/StringBuilder;
    2595: aload         8
    2597: invokevirtual #124                // Method java/lang/Object.toString:()Ljava/lang/String;
    2600: invokevirtual #30                 // Method java/lang/StringBuilder.append:(Ljava/lang/String;)Ljava/lang/StringBuilder;
    2603: ldc           #125                // String  item : items) {this.
    2605: invokevirtual #30                 // Method java/lang/StringBuilder.append:(Ljava/lang/String;)Ljava/lang/StringBuilder;
    2608: aload_1
    2609: invokevirtual #38                 // Method io/sundr/codegen/model/Property.getName:()Ljava/lang/String;
    2612: invokevirtual #30                 // Method java/lang/StringBuilder.append:(Ljava/lang/String;)Ljava/lang/StringBuilder;
    2615: ldc           #126                // String .add(item);} return (
    2617: invokevirtual #30                 // Method java/lang/StringBuilder.append:(Ljava/lang/String;)Ljava/lang/StringBuilder;
    2620: aload         7
    2622: invokevirtual #65                 // Method java/lang/StringBuilder.append:(Ljava/lang/Object;)Ljava/lang/StringBuilder;
    2625: ldc           #66                 // String )this;
    2627: invokevirtual #30                 // Method java/lang/StringBuilder.append:(Ljava/lang/String;)Ljava/lang/StringBuilder;
    2630: invokevirtual #32                 // Method java/lang/StringBuilder.toString:()Ljava/lang/String;
    2633: invokespecial #61                 // Method io/sundr/codegen/model/StringStatement."<init>":(Ljava/lang/String;)V
    2636: invokeinterface #84,  2           // InterfaceMethod java/util/List.add:(Ljava/lang/Object;)Z
    2641: pop
    2642: new           #41                 // class io/sundr/codegen/model/MethodBuilder
    2645: dup
    2646: invokespecial #42                 // Method io/sundr/codegen/model/MethodBuilder."<init>":()V
    2649: iconst_1
    2650: anewarray     #43                 // class javax/lang/model/element/Modifier
    2653: dup
    2654: iconst_0
    2655: getstatic     #44                 // Field javax/lang/model/element/Modifier.PUBLIC:Ljavax/lang/model/element/Modifier;
    2658: aastore
    2659: invokestatic  #45                 // Method io/sundr/codegen/utils/TypeUtils.modifiersToInt:([Ljavax/lang/model/element/Modifier;)I
    2662: invokevirtual #46                 // Method io/sundr/codegen/model/MethodBuilder.withModifiers:(I)Lio/sundr/codegen/model/ModifierSupportFluent;
    2665: checkcast     #41                 // class io/sundr/codegen/model/MethodBuilder
    2668: aload         12
    2670: invokevirtual #47                 // Method io/sundr/codegen/model/MethodBuilder.withParameters:(Ljava/util/List;)Lio/sundr/codegen/model/MethodFluent;
    2673: checkcast     #41                 // class io/sundr/codegen/model/MethodBuilder
    2676: aload         13
    2678: invokevirtual #48                 // Method io/sundr/codegen/model/MethodBuilder.withName:(Ljava/lang/String;)Lio/sundr/codegen/model/MethodFluent;
    2681: checkcast     #41                 // class io/sundr/codegen/model/MethodBuilder
    2684: aload         7
    2686: invokevirtual #49                 // Method io/sundr/codegen/model/MethodBuilder.withReturnType:(Lio/sundr/codegen/model/TypeRef;)Lio/sundr/codegen/model/MethodFluent;
    2689: checkcast     #41                 // class io/sundr/codegen/model/MethodBuilder
    2692: iconst_1
    2693: anewarray     #40                 // class io/sundr/codegen/model/Property
    2696: dup
    2697: iconst_0
    2698: aload         10
    2700: aastore
    2701: invokevirtual #118                // Method io/sundr/codegen/model/MethodBuilder.withArguments:([Lio/sundr/codegen/model/Property;)Lio/sundr/codegen/model/MethodFluent;
    2704: checkcast     #41                 // class io/sundr/codegen/model/MethodBuilder
    2707: iconst_1
    2708: invokevirtual #127                // Method io/sundr/codegen/model/MethodBuilder.withVarArgPreferred:(Z)Lio/sundr/codegen/model/MethodFluent;
    2711: checkcast     #41                 // class io/sundr/codegen/model/MethodBuilder
    2714: invokevirtual #52                 // Method io/sundr/codegen/model/MethodBuilder.withNewBlock:()Lio/sundr/codegen/model/MethodFluent$BlockNested;
    2717: aload         21
    2719: invokeinterface #128,  2          // InterfaceMethod io/sundr/codegen/model/MethodFluent$BlockNested.addAllToStatements:(Ljava/util/Collection;)Lio/sundr/codegen/model/BlockFluent;
    2724: checkcast     #68                 // class io/sundr/codegen/model/MethodFluent$BlockNested
    2727: aload         20
    2729: invokeinterface #128,  2          // InterfaceMethod io/sundr/codegen/model/MethodFluent$BlockNested.addAllToStatements:(Ljava/util/Collection;)Lio/sundr/codegen/model/BlockFluent;
    2734: checkcast     #68                 // class io/sundr/codegen/model/MethodFluent$BlockNested
    2737: invokeinterface #69,  1           // InterfaceMethod io/sundr/codegen/model/MethodFluent$BlockNested.endBlock:()Ljava/lang/Object;
    2742: checkcast     #41                 // class io/sundr/codegen/model/MethodBuilder
    2745: getstatic     #70                 // Field io/sundr/codegen/model/Attributeable.ALSO_IMPORT:Lio/sundr/codegen/model/AttributeKey;
    2748: aload         9
    2750: invokevirtual #71                 // Method io/sundr/codegen/model/MethodBuilder.addToAttributes:(Lio/sundr/codegen/model/AttributeKey;Ljava/lang/Object;)Lio/sundr/codegen/model/AttributeSupportFluent;
    2753: checkcast     #41                 // class io/sundr/codegen/model/MethodBuilder
    2756: invokevirtual #72                 // Method io/sundr/codegen/model/MethodBuilder.build:()Lio/sundr/codegen/model/EditableMethod;
    2759: astore        23
    2761: new           #41                 // class io/sundr/codegen/model/MethodBuilder
    2764: dup
    2765: invokespecial #42                 // Method io/sundr/codegen/model/MethodBuilder."<init>":()V
    2768: iconst_1
    2769: anewarray     #43                 // class javax/lang/model/element/Modifier
    2772: dup
    2773: iconst_0
    2774: getstatic     #44                 // Field javax/lang/model/element/Modifier.PUBLIC:Ljavax/lang/model/element/Modifier;
    2777: aastore
    2778: invokestatic  #45                 // Method io/sundr/codegen/utils/TypeUtils.modifiersToInt:([Ljavax/lang/model/element/Modifier;)I
    2781: invokevirtual #46                 // Method io/sundr/codegen/model/MethodBuilder.withModifiers:(I)Lio/sundr/codegen/model/ModifierSupportFluent;
    2784: checkcast     #41                 // class io/sundr/codegen/model/MethodBuilder
    2787: aload         12
    2789: invokevirtual #47                 // Method io/sundr/codegen/model/MethodBuilder.withParameters:(Ljava/util/List;)Lio/sundr/codegen/model/MethodFluent;
    2792: checkcast     #41                 // class io/sundr/codegen/model/MethodBuilder
    2795: aload         15
    2797: invokevirtual #48                 // Method io/sundr/codegen/model/MethodBuilder.withName:(Ljava/lang/String;)Lio/sundr/codegen/model/MethodFluent;
    2800: checkcast     #41                 // class io/sundr/codegen/model/MethodBuilder
    2803: aload         7
    2805: invokevirtual #49                 // Method io/sundr/codegen/model/MethodBuilder.withReturnType:(Lio/sundr/codegen/model/TypeRef;)Lio/sundr/codegen/model/MethodFluent;
    2808: checkcast     #41                 // class io/sundr/codegen/model/MethodBuilder
    2811: iconst_1
    2812: anewarray     #40                 // class io/sundr/codegen/model/Property
    2815: dup
    2816: iconst_0
    2817: new           #9                  // class io/sundr/codegen/model/PropertyBuilder
    2820: dup
    2821: aload         10
    2823: invokespecial #10                 // Method io/sundr/codegen/model/PropertyBuilder."<init>":(Lio/sundr/codegen/model/Property;)V
    2826: getstatic     #129                // Field io/sundr/codegen/functions/Collections.COLLECTION:Lio/sundr/codegen/model/TypeDef;
    2829: iconst_1
    2830: anewarray     #7                  // class io/sundr/codegen/model/TypeRef
    2833: dup
    2834: iconst_0
    2835: aload         8
    2837: aastore
    2838: invokevirtual #130                // Method io/sundr/codegen/model/TypeDef.toReference:([Lio/sundr/codegen/model/TypeRef;)Lio/sundr/codegen/model/ClassRef;
    2841: invokevirtual #13                 // Method io/sundr/codegen/model/PropertyBuilder.withTypeRef:(Lio/sundr/codegen/model/TypeRef;)Lio/sundr/codegen/model/PropertyFluent;
    2844: checkcast     #9                  // class io/sundr/codegen/model/PropertyBuilder
    2847: invokevirtual #14                 // Method io/sundr/codegen/model/PropertyBuilder.build:()Lio/sundr/codegen/model/EditableProperty;
    2850: aastore
    2851: invokevirtual #118                // Method io/sundr/codegen/model/MethodBuilder.withArguments:([Lio/sundr/codegen/model/Property;)Lio/sundr/codegen/model/MethodFluent;
    2854: checkcast     #41                 // class io/sundr/codegen/model/MethodBuilder
    2857: invokevirtual #52                 // Method io/sundr/codegen/model/MethodBuilder.withNewBlock:()Lio/sundr/codegen/model/MethodFluent$BlockNested;
    2860: aload         22
    2862: invokeinterface #128,  2          // InterfaceMethod io/sundr/codegen/model/MethodFluent$BlockNested.addAllToStatements:(Ljava/util/Collection;)Lio/sundr/codegen/model/BlockFluent;
    2867: checkcast     #68                 // class io/sundr/codegen/model/MethodFluent$BlockNested
    2870: aload         20
    2872: invokeinterface #128,  2          // InterfaceMethod io/sundr/codegen/model/MethodFluent$BlockNested.addAllToStatements:(Ljava/util/Collection;)Lio/sundr/codegen/model/BlockFluent;
    2877: checkcast     #68                 // class io/sundr/codegen/model/MethodFluent$BlockNested
    2880: invokeinterface #69,  1           // InterfaceMethod io/sundr/codegen/model/MethodFluent$BlockNested.endBlock:()Ljava/lang/Object;
    2885: checkcast     #41                 // class io/sundr/codegen/model/MethodBuilder
    2888: getstatic     #70                 // Field io/sundr/codegen/model/Attributeable.ALSO_IMPORT:Lio/sundr/codegen/model/AttributeKey;
    2891: aload         9
    2893: invokevirtual #71                 // Method io/sundr/codegen/model/MethodBuilder.addToAttributes:(Lio/sundr/codegen/model/AttributeKey;Ljava/lang/Object;)Lio/sundr/codegen/model/AttributeSupportFluent;
    2896: checkcast     #41                 // class io/sundr/codegen/model/MethodBuilder
    2899: invokevirtual #72                 // Method io/sundr/codegen/model/MethodBuilder.build:()Lio/sundr/codegen/model/EditableMethod;
    2902: astore        24
    2904: aload_2
    2905: aload         18
    2907: invokeinterface #84,  2           // InterfaceMethod java/util/List.add:(Ljava/lang/Object;)Z
    2912: pop
    2913: aload_2
    2914: aload         19
    2916: invokeinterface #84,  2           // InterfaceMethod java/util/List.add:(Ljava/lang/Object;)Z
    2921: pop
    2922: aload_2
    2923: aload         23
    2925: invokeinterface #84,  2           // InterfaceMethod java/util/List.add:(Ljava/lang/Object;)Z
    2930: pop
    2931: aload_2
    2932: aload         24
    2934: invokeinterface #84,  2           // InterfaceMethod java/util/List.add:(Ljava/lang/Object;)Z
    2939: pop
    2940: aload_2
    2941: areturn

  private io.sundr.codegen.model.Statement createAddToDescendants(java.lang.String, java.util.Set<io.sundr.codegen.model.Property>, boolean);
    Code:
       0: new           #54                 // class io/sundr/codegen/model/StringStatement
       3: dup
       4: aload_2
       5: aload_1
       6: iload_3
       7: invokedynamic #131,  0            // InvokeDynamic #0:apply:(Ljava/lang/String;Z)Lio/sundr/Function;
      12: ldc           #132                // String  else
      14: invokestatic  #133                // Method io/sundr/codegen/utils/StringUtils.join:(Ljava/lang/Iterable;Lio/sundr/Function;Ljava/lang/String;)Ljava/lang/String;
      17: invokespecial #61                 // Method io/sundr/codegen/model/StringStatement."<init>":(Ljava/lang/String;)V
      20: areturn

  private io.sundr.codegen.model.Statement createAddToDescendantsFallback(java.lang.String, java.lang.String);
    Code:
       0: new           #54                 // class io/sundr/codegen/model/StringStatement
       3: dup
       4: new           #27                 // class java/lang/StringBuilder
       7: dup
       8: invokespecial #28                 // Method java/lang/StringBuilder."<init>":()V
      11: ldc           #134                // String else {  VisitableBuilder<? extends
      13: invokevirtual #30                 // Method java/lang/StringBuilder.append:(Ljava/lang/String;)Ljava/lang/StringBuilder;
      16: aload_1
      17: invokevirtual #30                 // Method java/lang/StringBuilder.append:(Ljava/lang/String;)Ljava/lang/StringBuilder;
      20: ldc           #135                // String ,?> builder = builderOf(item); _visitables.get(\"
      22: invokevirtual #30                 // Method java/lang/StringBuilder.append:(Ljava/lang/String;)Ljava/lang/StringBuilder;
      25: aload_2
      26: invokevirtual #30                 // Method java/lang/StringBuilder.append:(Ljava/lang/String;)Ljava/lang/StringBuilder;
      29: ldc           #89                 // String \").add(builder);this.
      31: invokevirtual #30                 // Method java/lang/StringBuilder.append:(Ljava/lang/String;)Ljava/lang/StringBuilder;
      34: aload_2
      35: invokevirtual #30                 // Method java/lang/StringBuilder.append:(Ljava/lang/String;)Ljava/lang/StringBuilder;
      38: ldc           #136                // String .add(builder); }
      40: invokevirtual #30                 // Method java/lang/StringBuilder.append:(Ljava/lang/String;)Ljava/lang/StringBuilder;
      43: invokevirtual #32                 // Method java/lang/StringBuilder.toString:()Ljava/lang/String;
      46: invokespecial #61                 // Method io/sundr/codegen/model/StringStatement."<init>":(Ljava/lang/String;)V
      49: areturn

  public java.lang.Object apply(java.lang.Object);
    Code:
       0: aload_0
       1: aload_1
       2: checkcast     #40                 // class io/sundr/codegen/model/Property
       5: invokevirtual #137                // Method apply:(Lio/sundr/codegen/model/Property;)Ljava/util/List;
       8: areturn

  private static java.lang.String lambda$createAddToDescendants$0(java.lang.String, boolean, io.sundr.codegen.model.Property);
    Code:
       0: iconst_3
       1: anewarray     #22                 // class io/sundr/Function
       4: dup
       5: iconst_0
       6: getstatic     #4                  // Field io/sundr/builder/internal/functions/TypeAs.UNWRAP_COLLECTION_OF:Lio/sundr/Function;
       9: aastore
      10: dup
      11: iconst_1
      12: getstatic     #138                // Field io/sundr/builder/internal/functions/TypeAs.ARRAY_OF:Lio/sundr/Function;
      15: aastore
      16: dup
      17: iconst_2
      18: getstatic     #139                // Field io/sundr/builder/internal/functions/TypeAs.UNWRAP_OPTIONAL_OF:Lio/sundr/Function;
      21: aastore
      22: invokestatic  #23                 // Method io/sundr/builder/internal/functions/TypeAs.combine:([Lio/sundr/Function;)Lio/sundr/Function;
      25: aload_2
      26: invokevirtual #5                  // Method io/sundr/codegen/model/Property.getTypeRef:()Lio/sundr/codegen/model/TypeRef;
      29: invokeinterface #6,  2            // InterfaceMethod io/sundr/Function.apply:(Ljava/lang/Object;)Ljava/lang/Object;
      34: checkcast     #7                  // class io/sundr/codegen/model/TypeRef
      37: astore_3
      38: aload_3
      39: checkcast     #76                 // class io/sundr/codegen/model/ClassRef
      42: invokevirtual #77                 // Method io/sundr/codegen/model/ClassRef.getName:()Ljava/lang/String;
      45: astore        4
      47: new           #27                 // class java/lang/StringBuilder
      50: dup
      51: invokespecial #28                 // Method java/lang/StringBuilder."<init>":()V
      54: aload_0
      55: invokevirtual #30                 // Method java/lang/StringBuilder.append:(Ljava/lang/String;)Ljava/lang/StringBuilder;
      58: aload_2
      59: invokevirtual #31                 // Method io/sundr/codegen/model/Property.getNameCapitalized:()Ljava/lang/String;
      62: invokevirtual #30                 // Method java/lang/StringBuilder.append:(Ljava/lang/String;)Ljava/lang/StringBuilder;
      65: invokevirtual #32                 // Method java/lang/StringBuilder.toString:()Ljava/lang/String;
      68: astore        5
      70: new           #27                 // class java/lang/StringBuilder
      73: dup
      74: invokespecial #28                 // Method java/lang/StringBuilder."<init>":()V
      77: ldc           #140                // String if (item instanceof
      79: invokevirtual #30                 // Method java/lang/StringBuilder.append:(Ljava/lang/String;)Ljava/lang/StringBuilder;
      82: aload         4
      84: invokevirtual #30                 // Method java/lang/StringBuilder.append:(Ljava/lang/String;)Ljava/lang/StringBuilder;
      87: ldc           #141                // String ){
      89: invokevirtual #30                 // Method java/lang/StringBuilder.append:(Ljava/lang/String;)Ljava/lang/StringBuilder;
      92: aload         5
      94: invokevirtual #30                 // Method java/lang/StringBuilder.append:(Ljava/lang/String;)Ljava/lang/StringBuilder;
      97: ldc           #142                // String (
      99: invokevirtual #30                 // Method java/lang/StringBuilder.append:(Ljava/lang/String;)Ljava/lang/StringBuilder;
     102: iload_1
     103: ifeq          111
     106: ldc           #143                // String index,
     108: goto          113
     111: ldc           #144                // String
     113: invokevirtual #30                 // Method java/lang/StringBuilder.append:(Ljava/lang/String;)Ljava/lang/StringBuilder;
     116: ldc           #142                // String (
     118: invokevirtual #30                 // Method java/lang/StringBuilder.append:(Ljava/lang/String;)Ljava/lang/StringBuilder;
     121: aload         4
     123: invokevirtual #30                 // Method java/lang/StringBuilder.append:(Ljava/lang/String;)Ljava/lang/StringBuilder;
     126: ldc           #145                // String )item);}\n
     128: invokevirtual #30                 // Method java/lang/StringBuilder.append:(Ljava/lang/String;)Ljava/lang/StringBuilder;
     131: invokevirtual #32                 // Method java/lang/StringBuilder.toString:()Ljava/lang/String;
     134: areturn
}
