Compiled from "GetEnvironmentResponse.java"
final class software.amazon.awssdk.services.m2.model.GetEnvironmentResponse$BuilderImpl extends software.amazon.awssdk.services.m2.model.M2Response$BuilderImpl implements software.amazon.awssdk.services.m2.model.GetEnvironmentResponse$Builder {
  private java.lang.Integer actualCapacity;

  private java.time.Instant creationTime;

  private java.lang.String description;

  private java.lang.String engineType;

  private java.lang.String engineVersion;

  private java.lang.String environmentArn;

  private java.lang.String environmentId;

  private software.amazon.awssdk.services.m2.model.HighAvailabilityConfig highAvailabilityConfig;

  private java.lang.String instanceType;

  private java.lang.String kmsKeyId;

  private java.lang.String loadBalancerArn;

  private java.lang.String name;

  private software.amazon.awssdk.services.m2.model.PendingMaintenance pendingMaintenance;

  private java.lang.String preferredMaintenanceWindow;

  private java.lang.Boolean publiclyAccessible;

  private java.util.List<java.lang.String> securityGroupIds;

  private java.lang.String status;

  private java.lang.String statusReason;

  private java.util.List<software.amazon.awssdk.services.m2.model.StorageConfiguration> storageConfigurations;

  private java.util.List<java.lang.String> subnetIds;

  private java.util.Map<java.lang.String, java.lang.String> tags;

  private java.lang.String vpcId;

  private software.amazon.awssdk.services.m2.model.GetEnvironmentResponse$BuilderImpl();
    Code:
       0: aload_0
       1: invokespecial #25                 // Method software/amazon/awssdk/services/m2/model/M2Response$BuilderImpl."<init>":()V
       4: aload_0
       5: invokestatic  #26                 // Method software/amazon/awssdk/core/util/DefaultSdkAutoConstructList.getInstance:()Lsoftware/amazon/awssdk/core/util/DefaultSdkAutoConstructList;
       8: putfield      #9                  // Field securityGroupIds:Ljava/util/List;
      11: aload_0
      12: invokestatic  #26                 // Method software/amazon/awssdk/core/util/DefaultSdkAutoConstructList.getInstance:()Lsoftware/amazon/awssdk/core/util/DefaultSdkAutoConstructList;
      15: putfield      #6                  // Field storageConfigurations:Ljava/util/List;
      18: aload_0
      19: invokestatic  #26                 // Method software/amazon/awssdk/core/util/DefaultSdkAutoConstructList.getInstance:()Lsoftware/amazon/awssdk/core/util/DefaultSdkAutoConstructList;
      22: putfield      #5                  // Field subnetIds:Ljava/util/List;
      25: aload_0
      26: invokestatic  #27                 // Method software/amazon/awssdk/core/util/DefaultSdkAutoConstructMap.getInstance:()Lsoftware/amazon/awssdk/core/util/DefaultSdkAutoConstructMap;
      29: putfield      #4                  // Field tags:Ljava/util/Map;
      32: return

  private software.amazon.awssdk.services.m2.model.GetEnvironmentResponse$BuilderImpl(software.amazon.awssdk.services.m2.model.GetEnvironmentResponse);
    Code:
       0: aload_0
       1: aload_1
       2: invokespecial #28                 // Method software/amazon/awssdk/services/m2/model/M2Response$BuilderImpl."<init>":(Lsoftware/amazon/awssdk/services/m2/model/M2Response;)V
       5: aload_0
       6: invokestatic  #26                 // Method software/amazon/awssdk/core/util/DefaultSdkAutoConstructList.getInstance:()Lsoftware/amazon/awssdk/core/util/DefaultSdkAutoConstructList;
       9: putfield      #9                  // Field securityGroupIds:Ljava/util/List;
      12: aload_0
      13: invokestatic  #26                 // Method software/amazon/awssdk/core/util/DefaultSdkAutoConstructList.getInstance:()Lsoftware/amazon/awssdk/core/util/DefaultSdkAutoConstructList;
      16: putfield      #6                  // Field storageConfigurations:Ljava/util/List;
      19: aload_0
      20: invokestatic  #26                 // Method software/amazon/awssdk/core/util/DefaultSdkAutoConstructList.getInstance:()Lsoftware/amazon/awssdk/core/util/DefaultSdkAutoConstructList;
      23: putfield      #5                  // Field subnetIds:Ljava/util/List;
      26: aload_0
      27: invokestatic  #27                 // Method software/amazon/awssdk/core/util/DefaultSdkAutoConstructMap.getInstance:()Lsoftware/amazon/awssdk/core/util/DefaultSdkAutoConstructMap;
      30: putfield      #4                  // Field tags:Ljava/util/Map;
      33: aload_0
      34: aload_1
      35: invokestatic  #29                 // Method software/amazon/awssdk/services/m2/model/GetEnvironmentResponse.access$2400:(Lsoftware/amazon/awssdk/services/m2/model/GetEnvironmentResponse;)Ljava/lang/Integer;
      38: invokevirtual #30                 // Method actualCapacity:(Ljava/lang/Integer;)Lsoftware/amazon/awssdk/services/m2/model/GetEnvironmentResponse$Builder;
      41: pop
      42: aload_0
      43: aload_1
      44: invokestatic  #31                 // Method software/amazon/awssdk/services/m2/model/GetEnvironmentResponse.access$2500:(Lsoftware/amazon/awssdk/services/m2/model/GetEnvironmentResponse;)Ljava/time/Instant;
      47: invokevirtual #32                 // Method creationTime:(Ljava/time/Instant;)Lsoftware/amazon/awssdk/services/m2/model/GetEnvironmentResponse$Builder;
      50: pop
      51: aload_0
      52: aload_1
      53: invokestatic  #33                 // Method software/amazon/awssdk/services/m2/model/GetEnvironmentResponse.access$2600:(Lsoftware/amazon/awssdk/services/m2/model/GetEnvironmentResponse;)Ljava/lang/String;
      56: invokevirtual #34                 // Method description:(Ljava/lang/String;)Lsoftware/amazon/awssdk/services/m2/model/GetEnvironmentResponse$Builder;
      59: pop
      60: aload_0
      61: aload_1
      62: invokestatic  #35                 // Method software/amazon/awssdk/services/m2/model/GetEnvironmentResponse.access$2700:(Lsoftware/amazon/awssdk/services/m2/model/GetEnvironmentResponse;)Ljava/lang/String;
      65: invokevirtual #36                 // Method engineType:(Ljava/lang/String;)Lsoftware/amazon/awssdk/services/m2/model/GetEnvironmentResponse$Builder;
      68: pop
      69: aload_0
      70: aload_1
      71: invokestatic  #37                 // Method software/amazon/awssdk/services/m2/model/GetEnvironmentResponse.access$2800:(Lsoftware/amazon/awssdk/services/m2/model/GetEnvironmentResponse;)Ljava/lang/String;
      74: invokevirtual #38                 // Method engineVersion:(Ljava/lang/String;)Lsoftware/amazon/awssdk/services/m2/model/GetEnvironmentResponse$Builder;
      77: pop
      78: aload_0
      79: aload_1
      80: invokestatic  #39                 // Method software/amazon/awssdk/services/m2/model/GetEnvironmentResponse.access$2900:(Lsoftware/amazon/awssdk/services/m2/model/GetEnvironmentResponse;)Ljava/lang/String;
      83: invokevirtual #40                 // Method environmentArn:(Ljava/lang/String;)Lsoftware/amazon/awssdk/services/m2/model/GetEnvironmentResponse$Builder;
      86: pop
      87: aload_0
      88: aload_1
      89: invokestatic  #41                 // Method software/amazon/awssdk/services/m2/model/GetEnvironmentResponse.access$3000:(Lsoftware/amazon/awssdk/services/m2/model/GetEnvironmentResponse;)Ljava/lang/String;
      92: invokevirtual #42                 // Method environmentId:(Ljava/lang/String;)Lsoftware/amazon/awssdk/services/m2/model/GetEnvironmentResponse$Builder;
      95: pop
      96: aload_0
      97: aload_1
      98: invokestatic  #43                 // Method software/amazon/awssdk/services/m2/model/GetEnvironmentResponse.access$3100:(Lsoftware/amazon/awssdk/services/m2/model/GetEnvironmentResponse;)Lsoftware/amazon/awssdk/services/m2/model/HighAvailabilityConfig;
     101: invokevirtual #44                 // Method highAvailabilityConfig:(Lsoftware/amazon/awssdk/services/m2/model/HighAvailabilityConfig;)Lsoftware/amazon/awssdk/services/m2/model/GetEnvironmentResponse$Builder;
     104: pop
     105: aload_0
     106: aload_1
     107: invokestatic  #45                 // Method software/amazon/awssdk/services/m2/model/GetEnvironmentResponse.access$3200:(Lsoftware/amazon/awssdk/services/m2/model/GetEnvironmentResponse;)Ljava/lang/String;
     110: invokevirtual #46                 // Method instanceType:(Ljava/lang/String;)Lsoftware/amazon/awssdk/services/m2/model/GetEnvironmentResponse$Builder;
     113: pop
     114: aload_0
     115: aload_1
     116: invokestatic  #47                 // Method software/amazon/awssdk/services/m2/model/GetEnvironmentResponse.access$3300:(Lsoftware/amazon/awssdk/services/m2/model/GetEnvironmentResponse;)Ljava/lang/String;
     119: invokevirtual #48                 // Method kmsKeyId:(Ljava/lang/String;)Lsoftware/amazon/awssdk/services/m2/model/GetEnvironmentResponse$Builder;
     122: pop
     123: aload_0
     124: aload_1
     125: invokestatic  #49                 // Method software/amazon/awssdk/services/m2/model/GetEnvironmentResponse.access$3400:(Lsoftware/amazon/awssdk/services/m2/model/GetEnvironmentResponse;)Ljava/lang/String;
     128: invokevirtual #50                 // Method loadBalancerArn:(Ljava/lang/String;)Lsoftware/amazon/awssdk/services/m2/model/GetEnvironmentResponse$Builder;
     131: pop
     132: aload_0
     133: aload_1
     134: invokestatic  #51                 // Method software/amazon/awssdk/services/m2/model/GetEnvironmentResponse.access$3500:(Lsoftware/amazon/awssdk/services/m2/model/GetEnvironmentResponse;)Ljava/lang/String;
     137: invokevirtual #52                 // Method name:(Ljava/lang/String;)Lsoftware/amazon/awssdk/services/m2/model/GetEnvironmentResponse$Builder;
     140: pop
     141: aload_0
     142: aload_1
     143: invokestatic  #53                 // Method software/amazon/awssdk/services/m2/model/GetEnvironmentResponse.access$3600:(Lsoftware/amazon/awssdk/services/m2/model/GetEnvironmentResponse;)Lsoftware/amazon/awssdk/services/m2/model/PendingMaintenance;
     146: invokevirtual #54                 // Method pendingMaintenance:(Lsoftware/amazon/awssdk/services/m2/model/PendingMaintenance;)Lsoftware/amazon/awssdk/services/m2/model/GetEnvironmentResponse$Builder;
     149: pop
     150: aload_0
     151: aload_1
     152: invokestatic  #55                 // Method software/amazon/awssdk/services/m2/model/GetEnvironmentResponse.access$3700:(Lsoftware/amazon/awssdk/services/m2/model/GetEnvironmentResponse;)Ljava/lang/String;
     155: invokevirtual #56                 // Method preferredMaintenanceWindow:(Ljava/lang/String;)Lsoftware/amazon/awssdk/services/m2/model/GetEnvironmentResponse$Builder;
     158: pop
     159: aload_0
     160: aload_1
     161: invokestatic  #57                 // Method software/amazon/awssdk/services/m2/model/GetEnvironmentResponse.access$3800:(Lsoftware/amazon/awssdk/services/m2/model/GetEnvironmentResponse;)Ljava/lang/Boolean;
     164: invokevirtual #58                 // Method publiclyAccessible:(Ljava/lang/Boolean;)Lsoftware/amazon/awssdk/services/m2/model/GetEnvironmentResponse$Builder;
     167: pop
     168: aload_0
     169: aload_1
     170: invokestatic  #59                 // Method software/amazon/awssdk/services/m2/model/GetEnvironmentResponse.access$3900:(Lsoftware/amazon/awssdk/services/m2/model/GetEnvironmentResponse;)Ljava/util/List;
     173: invokevirtual #60                 // Method securityGroupIds:(Ljava/util/Collection;)Lsoftware/amazon/awssdk/services/m2/model/GetEnvironmentResponse$Builder;
     176: pop
     177: aload_0
     178: aload_1
     179: invokestatic  #61                 // Method software/amazon/awssdk/services/m2/model/GetEnvironmentResponse.access$4000:(Lsoftware/amazon/awssdk/services/m2/model/GetEnvironmentResponse;)Ljava/lang/String;
     182: invokevirtual #62                 // Method status:(Ljava/lang/String;)Lsoftware/amazon/awssdk/services/m2/model/GetEnvironmentResponse$Builder;
     185: pop
     186: aload_0
     187: aload_1
     188: invokestatic  #63                 // Method software/amazon/awssdk/services/m2/model/GetEnvironmentResponse.access$4100:(Lsoftware/amazon/awssdk/services/m2/model/GetEnvironmentResponse;)Ljava/lang/String;
     191: invokevirtual #64                 // Method statusReason:(Ljava/lang/String;)Lsoftware/amazon/awssdk/services/m2/model/GetEnvironmentResponse$Builder;
     194: pop
     195: aload_0
     196: aload_1
     197: invokestatic  #65                 // Method software/amazon/awssdk/services/m2/model/GetEnvironmentResponse.access$4200:(Lsoftware/amazon/awssdk/services/m2/model/GetEnvironmentResponse;)Ljava/util/List;
     200: invokevirtual #66                 // Method storageConfigurations:(Ljava/util/Collection;)Lsoftware/amazon/awssdk/services/m2/model/GetEnvironmentResponse$Builder;
     203: pop
     204: aload_0
     205: aload_1
     206: invokestatic  #67                 // Method software/amazon/awssdk/services/m2/model/GetEnvironmentResponse.access$4300:(Lsoftware/amazon/awssdk/services/m2/model/GetEnvironmentResponse;)Ljava/util/List;
     209: invokevirtual #68                 // Method subnetIds:(Ljava/util/Collection;)Lsoftware/amazon/awssdk/services/m2/model/GetEnvironmentResponse$Builder;
     212: pop
     213: aload_0
     214: aload_1
     215: invokestatic  #69                 // Method software/amazon/awssdk/services/m2/model/GetEnvironmentResponse.access$4400:(Lsoftware/amazon/awssdk/services/m2/model/GetEnvironmentResponse;)Ljava/util/Map;
     218: invokevirtual #70                 // Method tags:(Ljava/util/Map;)Lsoftware/amazon/awssdk/services/m2/model/GetEnvironmentResponse$Builder;
     221: pop
     222: aload_0
     223: aload_1
     224: invokestatic  #71                 // Method software/amazon/awssdk/services/m2/model/GetEnvironmentResponse.access$4500:(Lsoftware/amazon/awssdk/services/m2/model/GetEnvironmentResponse;)Ljava/lang/String;
     227: invokevirtual #72                 // Method vpcId:(Ljava/lang/String;)Lsoftware/amazon/awssdk/services/m2/model/GetEnvironmentResponse$Builder;
     230: pop
     231: return

  public final java.lang.Integer getActualCapacity();
    Code:
       0: aload_0
       1: getfield      #24                 // Field actualCapacity:Ljava/lang/Integer;
       4: areturn

  public final void setActualCapacity(java.lang.Integer);
    Code:
       0: aload_0
       1: aload_1
       2: putfield      #24                 // Field actualCapacity:Ljava/lang/Integer;
       5: return

  public final software.amazon.awssdk.services.m2.model.GetEnvironmentResponse$Builder actualCapacity(java.lang.Integer);
    Code:
       0: aload_0
       1: aload_1
       2: putfield      #24                 // Field actualCapacity:Ljava/lang/Integer;
       5: aload_0
       6: areturn

  public final java.time.Instant getCreationTime();
    Code:
       0: aload_0
       1: getfield      #23                 // Field creationTime:Ljava/time/Instant;
       4: areturn

  public final void setCreationTime(java.time.Instant);
    Code:
       0: aload_0
       1: aload_1
       2: putfield      #23                 // Field creationTime:Ljava/time/Instant;
       5: return

  public final software.amazon.awssdk.services.m2.model.GetEnvironmentResponse$Builder creationTime(java.time.Instant);
    Code:
       0: aload_0
       1: aload_1
       2: putfield      #23                 // Field creationTime:Ljava/time/Instant;
       5: aload_0
       6: areturn

  public final java.lang.String getDescription();
    Code:
       0: aload_0
       1: getfield      #22                 // Field description:Ljava/lang/String;
       4: areturn

  public final void setDescription(java.lang.String);
    Code:
       0: aload_0
       1: aload_1
       2: putfield      #22                 // Field description:Ljava/lang/String;
       5: return

  public final software.amazon.awssdk.services.m2.model.GetEnvironmentResponse$Builder description(java.lang.String);
    Code:
       0: aload_0
       1: aload_1
       2: putfield      #22                 // Field description:Ljava/lang/String;
       5: aload_0
       6: areturn

  public final java.lang.String getEngineType();
    Code:
       0: aload_0
       1: getfield      #21                 // Field engineType:Ljava/lang/String;
       4: areturn

  public final void setEngineType(java.lang.String);
    Code:
       0: aload_0
       1: aload_1
       2: putfield      #21                 // Field engineType:Ljava/lang/String;
       5: return

  public final software.amazon.awssdk.services.m2.model.GetEnvironmentResponse$Builder engineType(java.lang.String);
    Code:
       0: aload_0
       1: aload_1
       2: putfield      #21                 // Field engineType:Ljava/lang/String;
       5: aload_0
       6: areturn

  public final software.amazon.awssdk.services.m2.model.GetEnvironmentResponse$Builder engineType(software.amazon.awssdk.services.m2.model.EngineType);
    Code:
       0: aload_0
       1: aload_1
       2: ifnonnull     9
       5: aconst_null
       6: goto          13
       9: aload_1
      10: invokevirtual #73                 // Method software/amazon/awssdk/services/m2/model/EngineType.toString:()Ljava/lang/String;
      13: invokevirtual #36                 // Method engineType:(Ljava/lang/String;)Lsoftware/amazon/awssdk/services/m2/model/GetEnvironmentResponse$Builder;
      16: pop
      17: aload_0
      18: areturn

  public final java.lang.String getEngineVersion();
    Code:
       0: aload_0
       1: getfield      #20                 // Field engineVersion:Ljava/lang/String;
       4: areturn

  public final void setEngineVersion(java.lang.String);
    Code:
       0: aload_0
       1: aload_1
       2: putfield      #20                 // Field engineVersion:Ljava/lang/String;
       5: return

  public final software.amazon.awssdk.services.m2.model.GetEnvironmentResponse$Builder engineVersion(java.lang.String);
    Code:
       0: aload_0
       1: aload_1
       2: putfield      #20                 // Field engineVersion:Ljava/lang/String;
       5: aload_0
       6: areturn

  public final java.lang.String getEnvironmentArn();
    Code:
       0: aload_0
       1: getfield      #19                 // Field environmentArn:Ljava/lang/String;
       4: areturn

  public final void setEnvironmentArn(java.lang.String);
    Code:
       0: aload_0
       1: aload_1
       2: putfield      #19                 // Field environmentArn:Ljava/lang/String;
       5: return

  public final software.amazon.awssdk.services.m2.model.GetEnvironmentResponse$Builder environmentArn(java.lang.String);
    Code:
       0: aload_0
       1: aload_1
       2: putfield      #19                 // Field environmentArn:Ljava/lang/String;
       5: aload_0
       6: areturn

  public final java.lang.String getEnvironmentId();
    Code:
       0: aload_0
       1: getfield      #18                 // Field environmentId:Ljava/lang/String;
       4: areturn

  public final void setEnvironmentId(java.lang.String);
    Code:
       0: aload_0
       1: aload_1
       2: putfield      #18                 // Field environmentId:Ljava/lang/String;
       5: return

  public final software.amazon.awssdk.services.m2.model.GetEnvironmentResponse$Builder environmentId(java.lang.String);
    Code:
       0: aload_0
       1: aload_1
       2: putfield      #18                 // Field environmentId:Ljava/lang/String;
       5: aload_0
       6: areturn

  public final software.amazon.awssdk.services.m2.model.HighAvailabilityConfig$Builder getHighAvailabilityConfig();
    Code:
       0: aload_0
       1: getfield      #17                 // Field highAvailabilityConfig:Lsoftware/amazon/awssdk/services/m2/model/HighAvailabilityConfig;
       4: ifnull        17
       7: aload_0
       8: getfield      #17                 // Field highAvailabilityConfig:Lsoftware/amazon/awssdk/services/m2/model/HighAvailabilityConfig;
      11: invokevirtual #74                 // Method software/amazon/awssdk/services/m2/model/HighAvailabilityConfig.toBuilder:()Lsoftware/amazon/awssdk/services/m2/model/HighAvailabilityConfig$Builder;
      14: goto          18
      17: aconst_null
      18: areturn

  public final void setHighAvailabilityConfig(software.amazon.awssdk.services.m2.model.HighAvailabilityConfig$BuilderImpl);
    Code:
       0: aload_0
       1: aload_1
       2: ifnull        12
       5: aload_1
       6: invokevirtual #75                 // Method software/amazon/awssdk/services/m2/model/HighAvailabilityConfig$BuilderImpl.build:()Lsoftware/amazon/awssdk/services/m2/model/HighAvailabilityConfig;
       9: goto          13
      12: aconst_null
      13: putfield      #17                 // Field highAvailabilityConfig:Lsoftware/amazon/awssdk/services/m2/model/HighAvailabilityConfig;
      16: return

  public final software.amazon.awssdk.services.m2.model.GetEnvironmentResponse$Builder highAvailabilityConfig(software.amazon.awssdk.services.m2.model.HighAvailabilityConfig);
    Code:
       0: aload_0
       1: aload_1
       2: putfield      #17                 // Field highAvailabilityConfig:Lsoftware/amazon/awssdk/services/m2/model/HighAvailabilityConfig;
       5: aload_0
       6: areturn

  public final java.lang.String getInstanceType();
    Code:
       0: aload_0
       1: getfield      #16                 // Field instanceType:Ljava/lang/String;
       4: areturn

  public final void setInstanceType(java.lang.String);
    Code:
       0: aload_0
       1: aload_1
       2: putfield      #16                 // Field instanceType:Ljava/lang/String;
       5: return

  public final software.amazon.awssdk.services.m2.model.GetEnvironmentResponse$Builder instanceType(java.lang.String);
    Code:
       0: aload_0
       1: aload_1
       2: putfield      #16                 // Field instanceType:Ljava/lang/String;
       5: aload_0
       6: areturn

  public final java.lang.String getKmsKeyId();
    Code:
       0: aload_0
       1: getfield      #15                 // Field kmsKeyId:Ljava/lang/String;
       4: areturn

  public final void setKmsKeyId(java.lang.String);
    Code:
       0: aload_0
       1: aload_1
       2: putfield      #15                 // Field kmsKeyId:Ljava/lang/String;
       5: return

  public final software.amazon.awssdk.services.m2.model.GetEnvironmentResponse$Builder kmsKeyId(java.lang.String);
    Code:
       0: aload_0
       1: aload_1
       2: putfield      #15                 // Field kmsKeyId:Ljava/lang/String;
       5: aload_0
       6: areturn

  public final java.lang.String getLoadBalancerArn();
    Code:
       0: aload_0
       1: getfield      #14                 // Field loadBalancerArn:Ljava/lang/String;
       4: areturn

  public final void setLoadBalancerArn(java.lang.String);
    Code:
       0: aload_0
       1: aload_1
       2: putfield      #14                 // Field loadBalancerArn:Ljava/lang/String;
       5: return

  public final software.amazon.awssdk.services.m2.model.GetEnvironmentResponse$Builder loadBalancerArn(java.lang.String);
    Code:
       0: aload_0
       1: aload_1
       2: putfield      #14                 // Field loadBalancerArn:Ljava/lang/String;
       5: aload_0
       6: areturn

  public final java.lang.String getName();
    Code:
       0: aload_0
       1: getfield      #13                 // Field name:Ljava/lang/String;
       4: areturn

  public final void setName(java.lang.String);
    Code:
       0: aload_0
       1: aload_1
       2: putfield      #13                 // Field name:Ljava/lang/String;
       5: return

  public final software.amazon.awssdk.services.m2.model.GetEnvironmentResponse$Builder name(java.lang.String);
    Code:
       0: aload_0
       1: aload_1
       2: putfield      #13                 // Field name:Ljava/lang/String;
       5: aload_0
       6: areturn

  public final software.amazon.awssdk.services.m2.model.PendingMaintenance$Builder getPendingMaintenance();
    Code:
       0: aload_0
       1: getfield      #12                 // Field pendingMaintenance:Lsoftware/amazon/awssdk/services/m2/model/PendingMaintenance;
       4: ifnull        17
       7: aload_0
       8: getfield      #12                 // Field pendingMaintenance:Lsoftware/amazon/awssdk/services/m2/model/PendingMaintenance;
      11: invokevirtual #76                 // Method software/amazon/awssdk/services/m2/model/PendingMaintenance.toBuilder:()Lsoftware/amazon/awssdk/services/m2/model/PendingMaintenance$Builder;
      14: goto          18
      17: aconst_null
      18: areturn

  public final void setPendingMaintenance(software.amazon.awssdk.services.m2.model.PendingMaintenance$BuilderImpl);
    Code:
       0: aload_0
       1: aload_1
       2: ifnull        12
       5: aload_1
       6: invokevirtual #77                 // Method software/amazon/awssdk/services/m2/model/PendingMaintenance$BuilderImpl.build:()Lsoftware/amazon/awssdk/services/m2/model/PendingMaintenance;
       9: goto          13
      12: aconst_null
      13: putfield      #12                 // Field pendingMaintenance:Lsoftware/amazon/awssdk/services/m2/model/PendingMaintenance;
      16: return

  public final software.amazon.awssdk.services.m2.model.GetEnvironmentResponse$Builder pendingMaintenance(software.amazon.awssdk.services.m2.model.PendingMaintenance);
    Code:
       0: aload_0
       1: aload_1
       2: putfield      #12                 // Field pendingMaintenance:Lsoftware/amazon/awssdk/services/m2/model/PendingMaintenance;
       5: aload_0
       6: areturn

  public final java.lang.String getPreferredMaintenanceWindow();
    Code:
       0: aload_0
       1: getfield      #11                 // Field preferredMaintenanceWindow:Ljava/lang/String;
       4: areturn

  public final void setPreferredMaintenanceWindow(java.lang.String);
    Code:
       0: aload_0
       1: aload_1
       2: putfield      #11                 // Field preferredMaintenanceWindow:Ljava/lang/String;
       5: return

  public final software.amazon.awssdk.services.m2.model.GetEnvironmentResponse$Builder preferredMaintenanceWindow(java.lang.String);
    Code:
       0: aload_0
       1: aload_1
       2: putfield      #11                 // Field preferredMaintenanceWindow:Ljava/lang/String;
       5: aload_0
       6: areturn

  public final java.lang.Boolean getPubliclyAccessible();
    Code:
       0: aload_0
       1: getfield      #10                 // Field publiclyAccessible:Ljava/lang/Boolean;
       4: areturn

  public final void setPubliclyAccessible(java.lang.Boolean);
    Code:
       0: aload_0
       1: aload_1
       2: putfield      #10                 // Field publiclyAccessible:Ljava/lang/Boolean;
       5: return

  public final software.amazon.awssdk.services.m2.model.GetEnvironmentResponse$Builder publiclyAccessible(java.lang.Boolean);
    Code:
       0: aload_0
       1: aload_1
       2: putfield      #10                 // Field publiclyAccessible:Ljava/lang/Boolean;
       5: aload_0
       6: areturn

  public final java.util.Collection<java.lang.String> getSecurityGroupIds();
    Code:
       0: aload_0
       1: getfield      #9                  // Field securityGroupIds:Ljava/util/List;
       4: instanceof    #78                 // class software/amazon/awssdk/core/util/SdkAutoConstructList
       7: ifeq          12
      10: aconst_null
      11: areturn
      12: aload_0
      13: getfield      #9                  // Field securityGroupIds:Ljava/util/List;
      16: areturn

  public final void setSecurityGroupIds(java.util.Collection<java.lang.String>);
    Code:
       0: aload_0
       1: aload_1
       2: invokestatic  #79                 // Method software/amazon/awssdk/services/m2/model/String50ListCopier.copy:(Ljava/util/Collection;)Ljava/util/List;
       5: putfield      #9                  // Field securityGroupIds:Ljava/util/List;
       8: return

  public final software.amazon.awssdk.services.m2.model.GetEnvironmentResponse$Builder securityGroupIds(java.util.Collection<java.lang.String>);
    Code:
       0: aload_0
       1: aload_1
       2: invokestatic  #79                 // Method software/amazon/awssdk/services/m2/model/String50ListCopier.copy:(Ljava/util/Collection;)Ljava/util/List;
       5: putfield      #9                  // Field securityGroupIds:Ljava/util/List;
       8: aload_0
       9: areturn

  public final software.amazon.awssdk.services.m2.model.GetEnvironmentResponse$Builder securityGroupIds(java.lang.String...);
    Code:
       0: aload_0
       1: aload_1
       2: invokestatic  #80                 // Method java/util/Arrays.asList:([Ljava/lang/Object;)Ljava/util/List;
       5: invokevirtual #60                 // Method securityGroupIds:(Ljava/util/Collection;)Lsoftware/amazon/awssdk/services/m2/model/GetEnvironmentResponse$Builder;
       8: pop
       9: aload_0
      10: areturn

  public final java.lang.String getStatus();
    Code:
       0: aload_0
       1: getfield      #8                  // Field status:Ljava/lang/String;
       4: areturn

  public final void setStatus(java.lang.String);
    Code:
       0: aload_0
       1: aload_1
       2: putfield      #8                  // Field status:Ljava/lang/String;
       5: return

  public final software.amazon.awssdk.services.m2.model.GetEnvironmentResponse$Builder status(java.lang.String);
    Code:
       0: aload_0
       1: aload_1
       2: putfield      #8                  // Field status:Ljava/lang/String;
       5: aload_0
       6: areturn

  public final software.amazon.awssdk.services.m2.model.GetEnvironmentResponse$Builder status(software.amazon.awssdk.services.m2.model.EnvironmentLifecycle);
    Code:
       0: aload_0
       1: aload_1
       2: ifnonnull     9
       5: aconst_null
       6: goto          13
       9: aload_1
      10: invokevirtual #81                 // Method software/amazon/awssdk/services/m2/model/EnvironmentLifecycle.toString:()Ljava/lang/String;
      13: invokevirtual #62                 // Method status:(Ljava/lang/String;)Lsoftware/amazon/awssdk/services/m2/model/GetEnvironmentResponse$Builder;
      16: pop
      17: aload_0
      18: areturn

  public final java.lang.String getStatusReason();
    Code:
       0: aload_0
       1: getfield      #7                  // Field statusReason:Ljava/lang/String;
       4: areturn

  public final void setStatusReason(java.lang.String);
    Code:
       0: aload_0
       1: aload_1
       2: putfield      #7                  // Field statusReason:Ljava/lang/String;
       5: return

  public final software.amazon.awssdk.services.m2.model.GetEnvironmentResponse$Builder statusReason(java.lang.String);
    Code:
       0: aload_0
       1: aload_1
       2: putfield      #7                  // Field statusReason:Ljava/lang/String;
       5: aload_0
       6: areturn

  public final java.util.List<software.amazon.awssdk.services.m2.model.StorageConfiguration$Builder> getStorageConfigurations();
    Code:
       0: aload_0
       1: getfield      #6                  // Field storageConfigurations:Ljava/util/List;
       4: invokestatic  #82                 // Method software/amazon/awssdk/services/m2/model/StorageConfigurationListCopier.copyToBuilder:(Ljava/util/Collection;)Ljava/util/List;
       7: astore_1
       8: aload_1
       9: instanceof    #78                 // class software/amazon/awssdk/core/util/SdkAutoConstructList
      12: ifeq          17
      15: aconst_null
      16: areturn
      17: aload_1
      18: areturn

  public final void setStorageConfigurations(java.util.Collection<software.amazon.awssdk.services.m2.model.StorageConfiguration$BuilderImpl>);
    Code:
       0: aload_0
       1: aload_1
       2: invokestatic  #83                 // Method software/amazon/awssdk/services/m2/model/StorageConfigurationListCopier.copyFromBuilder:(Ljava/util/Collection;)Ljava/util/List;
       5: putfield      #6                  // Field storageConfigurations:Ljava/util/List;
       8: return

  public final software.amazon.awssdk.services.m2.model.GetEnvironmentResponse$Builder storageConfigurations(java.util.Collection<software.amazon.awssdk.services.m2.model.StorageConfiguration>);
    Code:
       0: aload_0
       1: aload_1
       2: invokestatic  #84                 // Method software/amazon/awssdk/services/m2/model/StorageConfigurationListCopier.copy:(Ljava/util/Collection;)Ljava/util/List;
       5: putfield      #6                  // Field storageConfigurations:Ljava/util/List;
       8: aload_0
       9: areturn

  public final software.amazon.awssdk.services.m2.model.GetEnvironmentResponse$Builder storageConfigurations(software.amazon.awssdk.services.m2.model.StorageConfiguration...);
    Code:
       0: aload_0
       1: aload_1
       2: invokestatic  #80                 // Method java/util/Arrays.asList:([Ljava/lang/Object;)Ljava/util/List;
       5: invokevirtual #66                 // Method storageConfigurations:(Ljava/util/Collection;)Lsoftware/amazon/awssdk/services/m2/model/GetEnvironmentResponse$Builder;
       8: pop
       9: aload_0
      10: areturn

  public final software.amazon.awssdk.services.m2.model.GetEnvironmentResponse$Builder storageConfigurations(java.util.function.Consumer<software.amazon.awssdk.services.m2.model.StorageConfiguration$Builder>...);
    Code:
       0: aload_0
       1: aload_1
       2: invokestatic  #85                 // InterfaceMethod java/util/stream/Stream.of:([Ljava/lang/Object;)Ljava/util/stream/Stream;
       5: invokedynamic #86,  0             // InvokeDynamic #0:apply:()Ljava/util/function/Function;
      10: invokeinterface #87,  2           // InterfaceMethod java/util/stream/Stream.map:(Ljava/util/function/Function;)Ljava/util/stream/Stream;
      15: invokestatic  #88                 // Method java/util/stream/Collectors.toList:()Ljava/util/stream/Collector;
      18: invokeinterface #89,  2           // InterfaceMethod java/util/stream/Stream.collect:(Ljava/util/stream/Collector;)Ljava/lang/Object;
      23: checkcast     #90                 // class java/util/Collection
      26: invokevirtual #66                 // Method storageConfigurations:(Ljava/util/Collection;)Lsoftware/amazon/awssdk/services/m2/model/GetEnvironmentResponse$Builder;
      29: pop
      30: aload_0
      31: areturn

  public final java.util.Collection<java.lang.String> getSubnetIds();
    Code:
       0: aload_0
       1: getfield      #5                  // Field subnetIds:Ljava/util/List;
       4: instanceof    #78                 // class software/amazon/awssdk/core/util/SdkAutoConstructList
       7: ifeq          12
      10: aconst_null
      11: areturn
      12: aload_0
      13: getfield      #5                  // Field subnetIds:Ljava/util/List;
      16: areturn

  public final void setSubnetIds(java.util.Collection<java.lang.String>);
    Code:
       0: aload_0
       1: aload_1
       2: invokestatic  #79                 // Method software/amazon/awssdk/services/m2/model/String50ListCopier.copy:(Ljava/util/Collection;)Ljava/util/List;
       5: putfield      #5                  // Field subnetIds:Ljava/util/List;
       8: return

  public final software.amazon.awssdk.services.m2.model.GetEnvironmentResponse$Builder subnetIds(java.util.Collection<java.lang.String>);
    Code:
       0: aload_0
       1: aload_1
       2: invokestatic  #79                 // Method software/amazon/awssdk/services/m2/model/String50ListCopier.copy:(Ljava/util/Collection;)Ljava/util/List;
       5: putfield      #5                  // Field subnetIds:Ljava/util/List;
       8: aload_0
       9: areturn

  public final software.amazon.awssdk.services.m2.model.GetEnvironmentResponse$Builder subnetIds(java.lang.String...);
    Code:
       0: aload_0
       1: aload_1
       2: invokestatic  #80                 // Method java/util/Arrays.asList:([Ljava/lang/Object;)Ljava/util/List;
       5: invokevirtual #68                 // Method subnetIds:(Ljava/util/Collection;)Lsoftware/amazon/awssdk/services/m2/model/GetEnvironmentResponse$Builder;
       8: pop
       9: aload_0
      10: areturn

  public final java.util.Map<java.lang.String, java.lang.String> getTags();
    Code:
       0: aload_0
       1: getfield      #4                  // Field tags:Ljava/util/Map;
       4: instanceof    #91                 // class software/amazon/awssdk/core/util/SdkAutoConstructMap
       7: ifeq          12
      10: aconst_null
      11: areturn
      12: aload_0
      13: getfield      #4                  // Field tags:Ljava/util/Map;
      16: areturn

  public final void setTags(java.util.Map<java.lang.String, java.lang.String>);
    Code:
       0: aload_0
       1: aload_1
       2: invokestatic  #92                 // Method software/amazon/awssdk/services/m2/model/TagMapCopier.copy:(Ljava/util/Map;)Ljava/util/Map;
       5: putfield      #4                  // Field tags:Ljava/util/Map;
       8: return

  public final software.amazon.awssdk.services.m2.model.GetEnvironmentResponse$Builder tags(java.util.Map<java.lang.String, java.lang.String>);
    Code:
       0: aload_0
       1: aload_1
       2: invokestatic  #92                 // Method software/amazon/awssdk/services/m2/model/TagMapCopier.copy:(Ljava/util/Map;)Ljava/util/Map;
       5: putfield      #4                  // Field tags:Ljava/util/Map;
       8: aload_0
       9: areturn

  public final java.lang.String getVpcId();
    Code:
       0: aload_0
       1: getfield      #3                  // Field vpcId:Ljava/lang/String;
       4: areturn

  public final void setVpcId(java.lang.String);
    Code:
       0: aload_0
       1: aload_1
       2: putfield      #3                  // Field vpcId:Ljava/lang/String;
       5: return

  public final software.amazon.awssdk.services.m2.model.GetEnvironmentResponse$Builder vpcId(java.lang.String);
    Code:
       0: aload_0
       1: aload_1
       2: putfield      #3                  // Field vpcId:Ljava/lang/String;
       5: aload_0
       6: areturn

  public software.amazon.awssdk.services.m2.model.GetEnvironmentResponse build();
    Code:
       0: new           #93                 // class software/amazon/awssdk/services/m2/model/GetEnvironmentResponse
       3: dup
       4: aload_0
       5: aconst_null
       6: invokespecial #94                 // Method software/amazon/awssdk/services/m2/model/GetEnvironmentResponse."<init>":(Lsoftware/amazon/awssdk/services/m2/model/GetEnvironmentResponse$BuilderImpl;Lsoftware/amazon/awssdk/services/m2/model/GetEnvironmentResponse$1;)V
       9: areturn

  public java.util.List<software.amazon.awssdk.core.SdkField<?>> sdkFields();
    Code:
       0: invokestatic  #95                 // Method software/amazon/awssdk/services/m2/model/GetEnvironmentResponse.access$4700:()Ljava/util/List;
       3: areturn

  public software.amazon.awssdk.services.m2.model.M2Response build();
    Code:
       0: aload_0
       1: invokevirtual #96                 // Method build:()Lsoftware/amazon/awssdk/services/m2/model/GetEnvironmentResponse;
       4: areturn

  public software.amazon.awssdk.awscore.AwsResponse build();
    Code:
       0: aload_0
       1: invokevirtual #96                 // Method build:()Lsoftware/amazon/awssdk/services/m2/model/GetEnvironmentResponse;
       4: areturn

  public software.amazon.awssdk.core.SdkResponse build();
    Code:
       0: aload_0
       1: invokevirtual #96                 // Method build:()Lsoftware/amazon/awssdk/services/m2/model/GetEnvironmentResponse;
       4: areturn

  public java.lang.Object build();
    Code:
       0: aload_0
       1: invokevirtual #96                 // Method build:()Lsoftware/amazon/awssdk/services/m2/model/GetEnvironmentResponse;
       4: areturn

  private static software.amazon.awssdk.services.m2.model.StorageConfiguration lambda$storageConfigurations$0(java.util.function.Consumer);
    Code:
       0: invokestatic  #97                 // Method software/amazon/awssdk/services/m2/model/StorageConfiguration.builder:()Lsoftware/amazon/awssdk/services/m2/model/StorageConfiguration$Builder;
       3: aload_0
       4: invokeinterface #98,  2           // InterfaceMethod software/amazon/awssdk/services/m2/model/StorageConfiguration$Builder.applyMutation:(Ljava/util/function/Consumer;)Lsoftware/amazon/awssdk/utils/builder/SdkBuilder;
       9: checkcast     #99                 // class software/amazon/awssdk/services/m2/model/StorageConfiguration$Builder
      12: invokeinterface #100,  1          // InterfaceMethod software/amazon/awssdk/services/m2/model/StorageConfiguration$Builder.build:()Ljava/lang/Object;
      17: checkcast     #101                // class software/amazon/awssdk/services/m2/model/StorageConfiguration
      20: areturn

  static java.lang.Integer access$000(software.amazon.awssdk.services.m2.model.GetEnvironmentResponse$BuilderImpl);
    Code:
       0: aload_0
       1: getfield      #24                 // Field actualCapacity:Ljava/lang/Integer;
       4: areturn

  static java.time.Instant access$100(software.amazon.awssdk.services.m2.model.GetEnvironmentResponse$BuilderImpl);
    Code:
       0: aload_0
       1: getfield      #23                 // Field creationTime:Ljava/time/Instant;
       4: areturn

  static java.lang.String access$200(software.amazon.awssdk.services.m2.model.GetEnvironmentResponse$BuilderImpl);
    Code:
       0: aload_0
       1: getfield      #22                 // Field description:Ljava/lang/String;
       4: areturn

  static java.lang.String access$300(software.amazon.awssdk.services.m2.model.GetEnvironmentResponse$BuilderImpl);
    Code:
       0: aload_0
       1: getfield      #21                 // Field engineType:Ljava/lang/String;
       4: areturn

  static java.lang.String access$400(software.amazon.awssdk.services.m2.model.GetEnvironmentResponse$BuilderImpl);
    Code:
       0: aload_0
       1: getfield      #20                 // Field engineVersion:Ljava/lang/String;
       4: areturn

  static java.lang.String access$500(software.amazon.awssdk.services.m2.model.GetEnvironmentResponse$BuilderImpl);
    Code:
       0: aload_0
       1: getfield      #19                 // Field environmentArn:Ljava/lang/String;
       4: areturn

  static java.lang.String access$600(software.amazon.awssdk.services.m2.model.GetEnvironmentResponse$BuilderImpl);
    Code:
       0: aload_0
       1: getfield      #18                 // Field environmentId:Ljava/lang/String;
       4: areturn

  static software.amazon.awssdk.services.m2.model.HighAvailabilityConfig access$700(software.amazon.awssdk.services.m2.model.GetEnvironmentResponse$BuilderImpl);
    Code:
       0: aload_0
       1: getfield      #17                 // Field highAvailabilityConfig:Lsoftware/amazon/awssdk/services/m2/model/HighAvailabilityConfig;
       4: areturn

  static java.lang.String access$800(software.amazon.awssdk.services.m2.model.GetEnvironmentResponse$BuilderImpl);
    Code:
       0: aload_0
       1: getfield      #16                 // Field instanceType:Ljava/lang/String;
       4: areturn

  static java.lang.String access$900(software.amazon.awssdk.services.m2.model.GetEnvironmentResponse$BuilderImpl);
    Code:
       0: aload_0
       1: getfield      #15                 // Field kmsKeyId:Ljava/lang/String;
       4: areturn

  static java.lang.String access$1000(software.amazon.awssdk.services.m2.model.GetEnvironmentResponse$BuilderImpl);
    Code:
       0: aload_0
       1: getfield      #14                 // Field loadBalancerArn:Ljava/lang/String;
       4: areturn

  static java.lang.String access$1100(software.amazon.awssdk.services.m2.model.GetEnvironmentResponse$BuilderImpl);
    Code:
       0: aload_0
       1: getfield      #13                 // Field name:Ljava/lang/String;
       4: areturn

  static software.amazon.awssdk.services.m2.model.PendingMaintenance access$1200(software.amazon.awssdk.services.m2.model.GetEnvironmentResponse$BuilderImpl);
    Code:
       0: aload_0
       1: getfield      #12                 // Field pendingMaintenance:Lsoftware/amazon/awssdk/services/m2/model/PendingMaintenance;
       4: areturn

  static java.lang.String access$1300(software.amazon.awssdk.services.m2.model.GetEnvironmentResponse$BuilderImpl);
    Code:
       0: aload_0
       1: getfield      #11                 // Field preferredMaintenanceWindow:Ljava/lang/String;
       4: areturn

  static java.lang.Boolean access$1400(software.amazon.awssdk.services.m2.model.GetEnvironmentResponse$BuilderImpl);
    Code:
       0: aload_0
       1: getfield      #10                 // Field publiclyAccessible:Ljava/lang/Boolean;
       4: areturn

  static java.util.List access$1500(software.amazon.awssdk.services.m2.model.GetEnvironmentResponse$BuilderImpl);
    Code:
       0: aload_0
       1: getfield      #9                  // Field securityGroupIds:Ljava/util/List;
       4: areturn

  static java.lang.String access$1600(software.amazon.awssdk.services.m2.model.GetEnvironmentResponse$BuilderImpl);
    Code:
       0: aload_0
       1: getfield      #8                  // Field status:Ljava/lang/String;
       4: areturn

  static java.lang.String access$1700(software.amazon.awssdk.services.m2.model.GetEnvironmentResponse$BuilderImpl);
    Code:
       0: aload_0
       1: getfield      #7                  // Field statusReason:Ljava/lang/String;
       4: areturn

  static java.util.List access$1800(software.amazon.awssdk.services.m2.model.GetEnvironmentResponse$BuilderImpl);
    Code:
       0: aload_0
       1: getfield      #6                  // Field storageConfigurations:Ljava/util/List;
       4: areturn

  static java.util.List access$1900(software.amazon.awssdk.services.m2.model.GetEnvironmentResponse$BuilderImpl);
    Code:
       0: aload_0
       1: getfield      #5                  // Field subnetIds:Ljava/util/List;
       4: areturn

  static java.util.Map access$2000(software.amazon.awssdk.services.m2.model.GetEnvironmentResponse$BuilderImpl);
    Code:
       0: aload_0
       1: getfield      #4                  // Field tags:Ljava/util/Map;
       4: areturn

  static java.lang.String access$2100(software.amazon.awssdk.services.m2.model.GetEnvironmentResponse$BuilderImpl);
    Code:
       0: aload_0
       1: getfield      #3                  // Field vpcId:Ljava/lang/String;
       4: areturn

  software.amazon.awssdk.services.m2.model.GetEnvironmentResponse$BuilderImpl(software.amazon.awssdk.services.m2.model.GetEnvironmentResponse, software.amazon.awssdk.services.m2.model.GetEnvironmentResponse$1);
    Code:
       0: aload_0
       1: aload_1
       2: invokespecial #2                  // Method "<init>":(Lsoftware/amazon/awssdk/services/m2/model/GetEnvironmentResponse;)V
       5: return

  software.amazon.awssdk.services.m2.model.GetEnvironmentResponse$BuilderImpl(software.amazon.awssdk.services.m2.model.GetEnvironmentResponse$1);
    Code:
       0: aload_0
       1: invokespecial #1                  // Method "<init>":()V
       4: return
}
