Compiled from "StartBatchJobRequest.java"
final class software.amazon.awssdk.services.m2.model.StartBatchJobRequest$BuilderImpl extends software.amazon.awssdk.services.m2.model.M2Request$BuilderImpl implements software.amazon.awssdk.services.m2.model.StartBatchJobRequest$Builder {
  private java.lang.String applicationId;

  private software.amazon.awssdk.services.m2.model.BatchJobIdentifier batchJobIdentifier;

  private java.util.Map<java.lang.String, java.lang.String> jobParams;

  private software.amazon.awssdk.services.m2.model.StartBatchJobRequest$BuilderImpl();
    Code:
       0: aload_0
       1: invokespecial #6                  // Method software/amazon/awssdk/services/m2/model/M2Request$BuilderImpl."<init>":()V
       4: aload_0
       5: invokestatic  #7                  // Method software/amazon/awssdk/core/util/DefaultSdkAutoConstructMap.getInstance:()Lsoftware/amazon/awssdk/core/util/DefaultSdkAutoConstructMap;
       8: putfield      #3                  // Field jobParams:Ljava/util/Map;
      11: return

  private software.amazon.awssdk.services.m2.model.StartBatchJobRequest$BuilderImpl(software.amazon.awssdk.services.m2.model.StartBatchJobRequest);
    Code:
       0: aload_0
       1: aload_1
       2: invokespecial #8                  // Method software/amazon/awssdk/services/m2/model/M2Request$BuilderImpl."<init>":(Lsoftware/amazon/awssdk/services/m2/model/M2Request;)V
       5: aload_0
       6: invokestatic  #7                  // Method software/amazon/awssdk/core/util/DefaultSdkAutoConstructMap.getInstance:()Lsoftware/amazon/awssdk/core/util/DefaultSdkAutoConstructMap;
       9: putfield      #3                  // Field jobParams:Ljava/util/Map;
      12: aload_0
      13: aload_1
      14: invokestatic  #9                  // Method software/amazon/awssdk/services/m2/model/StartBatchJobRequest.access$500:(Lsoftware/amazon/awssdk/services/m2/model/StartBatchJobRequest;)Ljava/lang/String;
      17: invokevirtual #10                 // Method applicationId:(Ljava/lang/String;)Lsoftware/amazon/awssdk/services/m2/model/StartBatchJobRequest$Builder;
      20: pop
      21: aload_0
      22: aload_1
      23: invokestatic  #11                 // Method software/amazon/awssdk/services/m2/model/StartBatchJobRequest.access$600:(Lsoftware/amazon/awssdk/services/m2/model/StartBatchJobRequest;)Lsoftware/amazon/awssdk/services/m2/model/BatchJobIdentifier;
      26: invokevirtual #12                 // Method batchJobIdentifier:(Lsoftware/amazon/awssdk/services/m2/model/BatchJobIdentifier;)Lsoftware/amazon/awssdk/services/m2/model/StartBatchJobRequest$Builder;
      29: pop
      30: aload_0
      31: aload_1
      32: invokestatic  #13                 // Method software/amazon/awssdk/services/m2/model/StartBatchJobRequest.access$700:(Lsoftware/amazon/awssdk/services/m2/model/StartBatchJobRequest;)Ljava/util/Map;
      35: invokevirtual #14                 // Method jobParams:(Ljava/util/Map;)Lsoftware/amazon/awssdk/services/m2/model/StartBatchJobRequest$Builder;
      38: pop
      39: return

  public final java.lang.String getApplicationId();
    Code:
       0: aload_0
       1: getfield      #5                  // Field applicationId:Ljava/lang/String;
       4: areturn

  public final void setApplicationId(java.lang.String);
    Code:
       0: aload_0
       1: aload_1
       2: putfield      #5                  // Field applicationId:Ljava/lang/String;
       5: return

  public final software.amazon.awssdk.services.m2.model.StartBatchJobRequest$Builder applicationId(java.lang.String);
    Code:
       0: aload_0
       1: aload_1
       2: putfield      #5                  // Field applicationId:Ljava/lang/String;
       5: aload_0
       6: areturn

  public final software.amazon.awssdk.services.m2.model.BatchJobIdentifier$Builder getBatchJobIdentifier();
    Code:
       0: aload_0
       1: getfield      #4                  // Field batchJobIdentifier:Lsoftware/amazon/awssdk/services/m2/model/BatchJobIdentifier;
       4: ifnull        17
       7: aload_0
       8: getfield      #4                  // Field batchJobIdentifier:Lsoftware/amazon/awssdk/services/m2/model/BatchJobIdentifier;
      11: invokevirtual #15                 // Method software/amazon/awssdk/services/m2/model/BatchJobIdentifier.toBuilder:()Lsoftware/amazon/awssdk/services/m2/model/BatchJobIdentifier$Builder;
      14: goto          18
      17: aconst_null
      18: areturn

  public final void setBatchJobIdentifier(software.amazon.awssdk.services.m2.model.BatchJobIdentifier$BuilderImpl);
    Code:
       0: aload_0
       1: aload_1
       2: ifnull        12
       5: aload_1
       6: invokevirtual #16                 // Method software/amazon/awssdk/services/m2/model/BatchJobIdentifier$BuilderImpl.build:()Lsoftware/amazon/awssdk/services/m2/model/BatchJobIdentifier;
       9: goto          13
      12: aconst_null
      13: putfield      #4                  // Field batchJobIdentifier:Lsoftware/amazon/awssdk/services/m2/model/BatchJobIdentifier;
      16: return

  public final software.amazon.awssdk.services.m2.model.StartBatchJobRequest$Builder batchJobIdentifier(software.amazon.awssdk.services.m2.model.BatchJobIdentifier);
    Code:
       0: aload_0
       1: aload_1
       2: putfield      #4                  // Field batchJobIdentifier:Lsoftware/amazon/awssdk/services/m2/model/BatchJobIdentifier;
       5: aload_0
       6: areturn

  public final java.util.Map<java.lang.String, java.lang.String> getJobParams();
    Code:
       0: aload_0
       1: getfield      #3                  // Field jobParams:Ljava/util/Map;
       4: instanceof    #17                 // class software/amazon/awssdk/core/util/SdkAutoConstructMap
       7: ifeq          12
      10: aconst_null
      11: areturn
      12: aload_0
      13: getfield      #3                  // Field jobParams:Ljava/util/Map;
      16: areturn

  public final void setJobParams(java.util.Map<java.lang.String, java.lang.String>);
    Code:
       0: aload_0
       1: aload_1
       2: invokestatic  #18                 // Method software/amazon/awssdk/services/m2/model/BatchJobParametersMapCopier.copy:(Ljava/util/Map;)Ljava/util/Map;
       5: putfield      #3                  // Field jobParams:Ljava/util/Map;
       8: return

  public final software.amazon.awssdk.services.m2.model.StartBatchJobRequest$Builder jobParams(java.util.Map<java.lang.String, java.lang.String>);
    Code:
       0: aload_0
       1: aload_1
       2: invokestatic  #18                 // Method software/amazon/awssdk/services/m2/model/BatchJobParametersMapCopier.copy:(Ljava/util/Map;)Ljava/util/Map;
       5: putfield      #3                  // Field jobParams:Ljava/util/Map;
       8: aload_0
       9: areturn

  public software.amazon.awssdk.services.m2.model.StartBatchJobRequest$Builder overrideConfiguration(software.amazon.awssdk.awscore.AwsRequestOverrideConfiguration);
    Code:
       0: aload_0
       1: aload_1
       2: invokespecial #19                 // Method software/amazon/awssdk/services/m2/model/M2Request$BuilderImpl.overrideConfiguration:(Lsoftware/amazon/awssdk/awscore/AwsRequestOverrideConfiguration;)Lsoftware/amazon/awssdk/awscore/AwsRequest$Builder;
       5: pop
       6: aload_0
       7: areturn

  public software.amazon.awssdk.services.m2.model.StartBatchJobRequest$Builder overrideConfiguration(java.util.function.Consumer<software.amazon.awssdk.awscore.AwsRequestOverrideConfiguration$Builder>);
    Code:
       0: aload_0
       1: aload_1
       2: invokespecial #20                 // Method software/amazon/awssdk/services/m2/model/M2Request$BuilderImpl.overrideConfiguration:(Ljava/util/function/Consumer;)Lsoftware/amazon/awssdk/awscore/AwsRequest$Builder;
       5: pop
       6: aload_0
       7: areturn

  public software.amazon.awssdk.services.m2.model.StartBatchJobRequest build();
    Code:
       0: new           #21                 // class software/amazon/awssdk/services/m2/model/StartBatchJobRequest
       3: dup
       4: aload_0
       5: aconst_null
       6: invokespecial #22                 // Method software/amazon/awssdk/services/m2/model/StartBatchJobRequest."<init>":(Lsoftware/amazon/awssdk/services/m2/model/StartBatchJobRequest$BuilderImpl;Lsoftware/amazon/awssdk/services/m2/model/StartBatchJobRequest$1;)V
       9: areturn

  public java.util.List<software.amazon.awssdk.core.SdkField<?>> sdkFields();
    Code:
       0: invokestatic  #23                 // Method software/amazon/awssdk/services/m2/model/StartBatchJobRequest.access$900:()Ljava/util/List;
       3: areturn

  public software.amazon.awssdk.services.m2.model.M2Request build();
    Code:
       0: aload_0
       1: invokevirtual #24                 // Method build:()Lsoftware/amazon/awssdk/services/m2/model/StartBatchJobRequest;
       4: areturn

  public software.amazon.awssdk.awscore.AwsRequest build();
    Code:
       0: aload_0
       1: invokevirtual #24                 // Method build:()Lsoftware/amazon/awssdk/services/m2/model/StartBatchJobRequest;
       4: areturn

  public software.amazon.awssdk.awscore.AwsRequest$Builder overrideConfiguration(java.util.function.Consumer);
    Code:
       0: aload_0
       1: aload_1
       2: invokevirtual #25                 // Method overrideConfiguration:(Ljava/util/function/Consumer;)Lsoftware/amazon/awssdk/services/m2/model/StartBatchJobRequest$Builder;
       5: areturn

  public software.amazon.awssdk.awscore.AwsRequest$Builder overrideConfiguration(software.amazon.awssdk.awscore.AwsRequestOverrideConfiguration);
    Code:
       0: aload_0
       1: aload_1
       2: invokevirtual #26                 // Method overrideConfiguration:(Lsoftware/amazon/awssdk/awscore/AwsRequestOverrideConfiguration;)Lsoftware/amazon/awssdk/services/m2/model/StartBatchJobRequest$Builder;
       5: areturn

  public software.amazon.awssdk.core.SdkRequest build();
    Code:
       0: aload_0
       1: invokevirtual #24                 // Method build:()Lsoftware/amazon/awssdk/services/m2/model/StartBatchJobRequest;
       4: areturn

  public java.lang.Object build();
    Code:
       0: aload_0
       1: invokevirtual #24                 // Method build:()Lsoftware/amazon/awssdk/services/m2/model/StartBatchJobRequest;
       4: areturn

  static java.lang.String access$000(software.amazon.awssdk.services.m2.model.StartBatchJobRequest$BuilderImpl);
    Code:
       0: aload_0
       1: getfield      #5                  // Field applicationId:Ljava/lang/String;
       4: areturn

  static software.amazon.awssdk.services.m2.model.BatchJobIdentifier access$100(software.amazon.awssdk.services.m2.model.StartBatchJobRequest$BuilderImpl);
    Code:
       0: aload_0
       1: getfield      #4                  // Field batchJobIdentifier:Lsoftware/amazon/awssdk/services/m2/model/BatchJobIdentifier;
       4: areturn

  static java.util.Map access$200(software.amazon.awssdk.services.m2.model.StartBatchJobRequest$BuilderImpl);
    Code:
       0: aload_0
       1: getfield      #3                  // Field jobParams:Ljava/util/Map;
       4: areturn

  software.amazon.awssdk.services.m2.model.StartBatchJobRequest$BuilderImpl(software.amazon.awssdk.services.m2.model.StartBatchJobRequest, software.amazon.awssdk.services.m2.model.StartBatchJobRequest$1);
    Code:
       0: aload_0
       1: aload_1
       2: invokespecial #2                  // Method "<init>":(Lsoftware/amazon/awssdk/services/m2/model/StartBatchJobRequest;)V
       5: return

  software.amazon.awssdk.services.m2.model.StartBatchJobRequest$BuilderImpl(software.amazon.awssdk.services.m2.model.StartBatchJobRequest$1);
    Code:
       0: aload_0
       1: invokespecial #1                  // Method "<init>":()V
       4: return
}
