Compiled from "ScalaVersionSpecificCollectionsConverter.scala"
public class scala.util.ScalaJavaConversions$IteratorOps<T> {
  private final java.util.Iterator<T> iterator;

  public scala.collection.Iterator<T> toScala();
    Code:
       0: getstatic     #26                 // Field scala/jdk/CollectionConverters$.MODULE$:Lscala/jdk/CollectionConverters$;
       3: aload_0
       4: getfield      #28                 // Field iterator:Ljava/util/Iterator;
       7: invokevirtual #31                 // Method scala/jdk/CollectionConverters$.IteratorHasAsScala:(Ljava/util/Iterator;)Lscala/collection/convert/AsScalaExtensions$IteratorHasAsScala;
      10: invokevirtual #34                 // Method scala/collection/convert/AsScalaExtensions$IteratorHasAsScala.asScala:()Lscala/collection/Iterator;
      13: areturn

  public scala.util.ScalaJavaConversions$IteratorOps(java.util.Iterator<T>);
    Code:
       0: aload_0
       1: aload_1
       2: putfield      #28                 // Field iterator:Ljava/util/Iterator;
       5: aload_0
       6: invokespecial #42                 // Method java/lang/Object."<init>":()V
       9: return
}
