Compiled from "AbstractClient.java"
class me.hekr.iotos.softgateway.network.common.client.AbstractClient$1 extends io.netty.channel.ChannelInitializer<io.netty.channel.Channel> {
  final me.hekr.iotos.softgateway.network.common.client.AbstractClient this$0;

  me.hekr.iotos.softgateway.network.common.client.AbstractClient$1(me.hekr.iotos.softgateway.network.common.client.AbstractClient);
    Code:
       0: aload_0
       1: aload_1
       2: putfield      #1                  // Field this$0:Lme/hekr/iotos/softgateway/network/common/client/AbstractClient;
       5: aload_0
       6: invokespecial #2                  // Method io/netty/channel/ChannelInitializer."<init>":()V
       9: return

  protected void initChannel(io.netty.channel.Channel);
    Code:
       0: aload_0
       1: getfield      #1                  // Field this$0:Lme/hekr/iotos/softgateway/network/common/client/AbstractClient;
       4: getfield      #3                  // Field me/hekr/iotos/softgateway/network/common/client/AbstractClient.enableNetLog:Z
       7: ifeq          36
      10: aload_1
      11: invokeinterface #4,  1            // InterfaceMethod io/netty/channel/Channel.pipeline:()Lio/netty/channel/ChannelPipeline;
      16: iconst_1
      17: anewarray     #5                  // class io/netty/channel/ChannelHandler
      20: dup
      21: iconst_0
      22: new           #6                  // class io/netty/handler/logging/LoggingHandler
      25: dup
      26: invokespecial #7                  // Method io/netty/handler/logging/LoggingHandler."<init>":()V
      29: aastore
      30: invokeinterface #8,  2            // InterfaceMethod io/netty/channel/ChannelPipeline.addLast:([Lio/netty/channel/ChannelHandler;)Lio/netty/channel/ChannelPipeline;
      35: pop
      36: aload_1
      37: invokeinterface #4,  1            // InterfaceMethod io/netty/channel/Channel.pipeline:()Lio/netty/channel/ChannelPipeline;
      42: iconst_1
      43: anewarray     #5                  // class io/netty/channel/ChannelHandler
      46: dup
      47: iconst_0
      48: aload_0
      49: getfield      #1                  // Field this$0:Lme/hekr/iotos/softgateway/network/common/client/AbstractClient;
      52: getfield      #9                  // Field me/hekr/iotos/softgateway/network/common/client/AbstractClient.packetCoderHandlerFactory:Lme/hekr/iotos/softgateway/network/common/client/PacketCoderHandlerFactory;
      55: invokeinterface #10,  1           // InterfaceMethod me/hekr/iotos/softgateway/network/common/client/PacketCoderHandlerFactory.getPacketCoderHandler:()Lio/netty/channel/ChannelHandler;
      60: aastore
      61: invokeinterface #8,  2            // InterfaceMethod io/netty/channel/ChannelPipeline.addLast:([Lio/netty/channel/ChannelHandler;)Lio/netty/channel/ChannelPipeline;
      66: iconst_1
      67: anewarray     #5                  // class io/netty/channel/ChannelHandler
      70: dup
      71: iconst_0
      72: aload_0
      73: getfield      #1                  // Field this$0:Lme/hekr/iotos/softgateway/network/common/client/AbstractClient;
      76: getfield      #11                 // Field me/hekr/iotos/softgateway/network/common/client/AbstractClient.clientMessageHandler:Lme/hekr/iotos/softgateway/network/common/client/ClientMessageHandler;
      79: aastore
      80: invokeinterface #8,  2            // InterfaceMethod io/netty/channel/ChannelPipeline.addLast:([Lio/netty/channel/ChannelHandler;)Lio/netty/channel/ChannelPipeline;
      85: pop
      86: return
}
