Compiled from "EventListenerAdapter.java"
public class me.hekr.iotos.softgateway.network.common.client.EventListenerAdapter<T> implements me.hekr.iotos.softgateway.network.common.client.EventListener<T> {
  private static final org.slf4j.Logger log;

  public me.hekr.iotos.softgateway.network.common.client.EventListenerAdapter();
    Code:
       0: aload_0
       1: invokespecial #1                  // Method java/lang/Object."<init>":()V
       4: return

  public void onConnect(me.hekr.iotos.softgateway.network.common.ConnectionContext<T>);
    Code:
       0: getstatic     #2                  // Field log:Lorg/slf4j/Logger;
       3: ldc           #3                  // String onConnect, remote: {}
       5: aload_1
       6: invokevirtual #4                  // Method me/hekr/iotos/softgateway/network/common/ConnectionContext.getAddress:()Ljava/net/InetSocketAddress;
       9: invokeinterface #5,  3            // InterfaceMethod org/slf4j/Logger.info:(Ljava/lang/String;Ljava/lang/Object;)V
      14: return

  public void onDisconnect(me.hekr.iotos.softgateway.network.common.ConnectionContext<T>, me.hekr.iotos.softgateway.network.common.CloseReason);
    Code:
       0: getstatic     #2                  // Field log:Lorg/slf4j/Logger;
       3: ldc           #6                  // String onDisconnect, remote: {}, reason: {}
       5: aload_1
       6: invokevirtual #4                  // Method me/hekr/iotos/softgateway/network/common/ConnectionContext.getAddress:()Ljava/net/InetSocketAddress;
       9: aload_2
      10: invokeinterface #7,  4            // InterfaceMethod org/slf4j/Logger.info:(Ljava/lang/String;Ljava/lang/Object;Ljava/lang/Object;)V
      15: return

  public void onHeartbeatTimeout(me.hekr.iotos.softgateway.network.common.ConnectionContext<T>, java.time.LocalDateTime, int);
    Code:
       0: return

  public void exceptionCaught(me.hekr.iotos.softgateway.network.common.ConnectionContext<T>, java.lang.Throwable);
    Code:
       0: getstatic     #2                  // Field log:Lorg/slf4j/Logger;
       3: new           #8                  // class java/lang/StringBuilder
       6: dup
       7: invokespecial #9                  // Method java/lang/StringBuilder."<init>":()V
      10: ldc           #10                 // String exceptionCaught, remote:
      12: invokevirtual #11                 // Method java/lang/StringBuilder.append:(Ljava/lang/String;)Ljava/lang/StringBuilder;
      15: aload_1
      16: invokevirtual #4                  // Method me/hekr/iotos/softgateway/network/common/ConnectionContext.getAddress:()Ljava/net/InetSocketAddress;
      19: invokevirtual #12                 // Method java/lang/StringBuilder.append:(Ljava/lang/Object;)Ljava/lang/StringBuilder;
      22: ldc           #13                 // String , error:
      24: invokevirtual #11                 // Method java/lang/StringBuilder.append:(Ljava/lang/String;)Ljava/lang/StringBuilder;
      27: aload_2
      28: invokevirtual #14                 // Method java/lang/Throwable.getMessage:()Ljava/lang/String;
      31: invokevirtual #11                 // Method java/lang/StringBuilder.append:(Ljava/lang/String;)Ljava/lang/StringBuilder;
      34: invokevirtual #15                 // Method java/lang/StringBuilder.toString:()Ljava/lang/String;
      37: aload_2
      38: invokeinterface #16,  3           // InterfaceMethod org/slf4j/Logger.error:(Ljava/lang/String;Ljava/lang/Throwable;)V
      43: return

  static {};
    Code:
       0: ldc           #17                 // class me/hekr/iotos/softgateway/network/common/client/EventListenerAdapter
       2: invokestatic  #18                 // Method org/slf4j/LoggerFactory.getLogger:(Ljava/lang/Class;)Lorg/slf4j/Logger;
       5: putstatic     #2                  // Field log:Lorg/slf4j/Logger;
       8: return
}
