Compiled from "WeldExpressionFactory.java"
public class org.jboss.weld.el.WeldExpressionFactory extends org.jboss.weld.util.el.ForwardingExpressionFactory {
  private final javax.el.ExpressionFactory delegate;

  public org.jboss.weld.el.WeldExpressionFactory(javax.el.ExpressionFactory);
    Code:
       0: aload_0
       1: invokespecial #1                  // Method org/jboss/weld/util/el/ForwardingExpressionFactory."<init>":()V
       4: aload_1
       5: ifnonnull     17
       8: getstatic     #2                  // Field org/jboss/weld/logging/ElLogger.LOG:Lorg/jboss/weld/logging/ElLogger;
      11: invokeinterface #3,  1            // InterfaceMethod org/jboss/weld/logging/ElLogger.nullExpressionFactory:()Ljava/lang/IllegalArgumentException;
      16: athrow
      17: aload_0
      18: aload_1
      19: putfield      #4                  // Field delegate:Ljavax/el/ExpressionFactory;
      22: return

  protected javax.el.ExpressionFactory delegate();
    Code:
       0: aload_0
       1: getfield      #4                  // Field delegate:Ljavax/el/ExpressionFactory;
       4: areturn

  public javax.el.ValueExpression createValueExpression(javax.el.ELContext, java.lang.String, java.lang.Class);
    Code:
       0: new           #5                  // class org/jboss/weld/el/WeldValueExpression
       3: dup
       4: aload_0
       5: aload_1
       6: aload_2
       7: aload_3
       8: invokespecial #6                  // Method org/jboss/weld/util/el/ForwardingExpressionFactory.createValueExpression:(Ljavax/el/ELContext;Ljava/lang/String;Ljava/lang/Class;)Ljavax/el/ValueExpression;
      11: invokespecial #7                  // Method org/jboss/weld/el/WeldValueExpression."<init>":(Ljavax/el/ValueExpression;)V
      14: areturn

  public javax.el.MethodExpression createMethodExpression(javax.el.ELContext, java.lang.String, java.lang.Class, java.lang.Class[]);
    Code:
       0: new           #8                  // class org/jboss/weld/el/WeldMethodExpression
       3: dup
       4: aload_0
       5: aload_1
       6: aload_2
       7: aload_3
       8: aload         4
      10: invokespecial #9                  // Method org/jboss/weld/util/el/ForwardingExpressionFactory.createMethodExpression:(Ljavax/el/ELContext;Ljava/lang/String;Ljava/lang/Class;[Ljava/lang/Class;)Ljavax/el/MethodExpression;
      13: invokespecial #10                 // Method org/jboss/weld/el/WeldMethodExpression."<init>":(Ljavax/el/MethodExpression;)V
      16: areturn
}
