Compiled from "FaultyServiceData.java"
public class org.apache.axis2.util.FaultyServiceData {
  private java.lang.String serviceGroupName;

  private org.apache.axis2.description.AxisServiceGroup serviceGroup;

  private java.util.ArrayList<org.apache.axis2.description.AxisService> serviceList;

  private org.apache.axis2.deployment.repository.util.DeploymentFileData currentDeploymentFile;

  private java.net.URL serviceLocation;

  public org.apache.axis2.util.FaultyServiceData(org.apache.axis2.description.AxisServiceGroup, java.util.ArrayList<org.apache.axis2.description.AxisService>, java.net.URL, org.apache.axis2.deployment.repository.util.DeploymentFileData);
    Code:
       0: aload_0
       1: invokespecial #1                  // Method java/lang/Object."<init>":()V
       4: aload_0
       5: aload_1
       6: invokevirtual #2                  // Method org/apache/axis2/description/AxisServiceGroup.getServiceGroupName:()Ljava/lang/String;
       9: putfield      #3                  // Field serviceGroupName:Ljava/lang/String;
      12: aload_0
      13: aload_1
      14: putfield      #4                  // Field serviceGroup:Lorg/apache/axis2/description/AxisServiceGroup;
      17: aload_0
      18: aload_2
      19: putfield      #5                  // Field serviceList:Ljava/util/ArrayList;
      22: aload_0
      23: aload         4
      25: putfield      #6                  // Field currentDeploymentFile:Lorg/apache/axis2/deployment/repository/util/DeploymentFileData;
      28: aload_0
      29: aload_3
      30: putfield      #7                  // Field serviceLocation:Ljava/net/URL;
      33: return

  public org.apache.axis2.description.AxisServiceGroup getServiceGroup();
    Code:
       0: aload_0
       1: getfield      #4                  // Field serviceGroup:Lorg/apache/axis2/description/AxisServiceGroup;
       4: areturn

  public org.apache.axis2.deployment.repository.util.DeploymentFileData getCurrentDeploymentFile();
    Code:
       0: aload_0
       1: getfield      #6                  // Field currentDeploymentFile:Lorg/apache/axis2/deployment/repository/util/DeploymentFileData;
       4: areturn

  public java.util.ArrayList<org.apache.axis2.description.AxisService> getServiceList();
    Code:
       0: aload_0
       1: getfield      #5                  // Field serviceList:Ljava/util/ArrayList;
       4: areturn

  public java.net.URL getServiceLocation();
    Code:
       0: aload_0
       1: getfield      #7                  // Field serviceLocation:Ljava/net/URL;
       4: areturn

  public java.lang.String getServiceGroupName();
    Code:
       0: aload_0
       1: getfield      #3                  // Field serviceGroupName:Ljava/lang/String;
       4: areturn
}
