Compiled from "LoggingControl.java"
public class org.apache.axis2.util.LoggingControl {
  public static final boolean debugLoggingAllowed;

  public org.apache.axis2.util.LoggingControl();
    Code:
       0: aload_0
       1: invokespecial #1                  // Method java/lang/Object."<init>":()V
       4: return

  static {};
    Code:
       0: aconst_null
       1: astore_0
       2: new           #2                  // class org/apache/axis2/util/LoggingControl$1
       5: dup
       6: invokespecial #3                  // Method org/apache/axis2/util/LoggingControl$1."<init>":()V
       9: invokestatic  #4                  // Method org/apache/axis2/java/security/AccessController.doPrivileged:(Ljava/security/PrivilegedAction;)Ljava/lang/Object;
      12: checkcast     #5                  // class java/lang/String
      15: astore_0
      16: goto          20
      19: astore_1
      20: aload_0
      21: ifnonnull     28
      24: iconst_1
      25: goto          29
      28: iconst_0
      29: putstatic     #7                  // Field debugLoggingAllowed:Z
      32: return
    Exception table:
       from    to  target type
           2    16    19   Class java/lang/SecurityException
}
