Compiled from "FieldDescriptionComposite.java"
public class org.apache.axis2.jaxws.description.builder.FieldDescriptionComposite implements org.apache.axis2.jaxws.description.builder.TMFAnnotationComposite {
  private java.lang.String fieldName;

  private java.lang.String modifierType;

  private java.lang.String fieldClassName;

  private boolean isListType;

  private org.apache.axis2.jaxws.description.builder.HandlerChainAnnot handlerChainAnnot;

  private org.apache.axis2.jaxws.description.builder.WebServiceRefAnnot webServiceRefAnnot;

  public org.apache.axis2.jaxws.description.builder.FieldDescriptionComposite();
    Code:
       0: aload_0
       1: invokespecial #1                  // Method java/lang/Object."<init>":()V
       4: aload_0
       5: iconst_0
       6: putfield      #2                  // Field isListType:Z
       9: return

  public org.apache.axis2.jaxws.description.builder.FieldDescriptionComposite(java.lang.String, java.lang.String, org.apache.axis2.jaxws.description.builder.HandlerChainAnnot, org.apache.axis2.jaxws.description.builder.WebServiceRefAnnot);
    Code:
       0: aload_0
       1: invokespecial #1                  // Method java/lang/Object."<init>":()V
       4: aload_0
       5: iconst_0
       6: putfield      #2                  // Field isListType:Z
       9: aload_0
      10: aload_1
      11: putfield      #3                  // Field fieldName:Ljava/lang/String;
      14: aload_0
      15: aload_2
      16: putfield      #4                  // Field modifierType:Ljava/lang/String;
      19: aload_0
      20: aload_3
      21: putfield      #5                  // Field handlerChainAnnot:Lorg/apache/axis2/jaxws/description/builder/HandlerChainAnnot;
      24: aload_0
      25: aload         4
      27: putfield      #6                  // Field webServiceRefAnnot:Lorg/apache/axis2/jaxws/description/builder/WebServiceRefAnnot;
      30: return

  public java.lang.String getFieldName();
    Code:
       0: aload_0
       1: getfield      #3                  // Field fieldName:Ljava/lang/String;
       4: areturn

  public org.apache.axis2.jaxws.description.builder.HandlerChainAnnot getHandlerChainAnnot();
    Code:
       0: aload_0
       1: getfield      #5                  // Field handlerChainAnnot:Lorg/apache/axis2/jaxws/description/builder/HandlerChainAnnot;
       4: areturn

  public java.lang.String getModifierType();
    Code:
       0: aload_0
       1: getfield      #4                  // Field modifierType:Ljava/lang/String;
       4: areturn

  public java.lang.String getFieldClassName();
    Code:
       0: aload_0
       1: getfield      #7                  // Field fieldClassName:Ljava/lang/String;
       4: areturn

  public org.apache.axis2.jaxws.description.builder.WebServiceRefAnnot getWebServiceRefAnnot();
    Code:
       0: aload_0
       1: getfield      #6                  // Field webServiceRefAnnot:Lorg/apache/axis2/jaxws/description/builder/WebServiceRefAnnot;
       4: areturn

  public void setFieldName(java.lang.String);
    Code:
       0: aload_0
       1: aload_1
       2: putfield      #3                  // Field fieldName:Ljava/lang/String;
       5: return

  public void setHandlerChainAnnot(org.apache.axis2.jaxws.description.builder.HandlerChainAnnot);
    Code:
       0: aload_0
       1: aload_1
       2: putfield      #5                  // Field handlerChainAnnot:Lorg/apache/axis2/jaxws/description/builder/HandlerChainAnnot;
       5: return

  public void setModifierType(java.lang.String);
    Code:
       0: aload_0
       1: aload_1
       2: putfield      #4                  // Field modifierType:Ljava/lang/String;
       5: return

  public void setWebServiceRefAnnot(org.apache.axis2.jaxws.description.builder.WebServiceRefAnnot);
    Code:
       0: aload_0
       1: aload_1
       2: putfield      #6                  // Field webServiceRefAnnot:Lorg/apache/axis2/jaxws/description/builder/WebServiceRefAnnot;
       5: return

  public void setIsListType(boolean);
    Code:
       0: aload_0
       1: iload_1
       2: putfield      #2                  // Field isListType:Z
       5: return

  public boolean isListType();
    Code:
       0: aload_0
       1: getfield      #2                  // Field isListType:Z
       4: ireturn

  public void setFieldClassName(java.lang.String);
    Code:
       0: aload_0
       1: aload_1
       2: putfield      #7                  // Field fieldClassName:Ljava/lang/String;
       5: return

  public java.lang.String toString();
    Code:
       0: new           #8                  // class java/lang/StringBuffer
       3: dup
       4: invokespecial #9                  // Method java/lang/StringBuffer."<init>":()V
       7: astore_1
       8: ldc           #10                 // String \n
      10: astore_2
      11: aload_1
      12: ldc           #11                 // String ***** BEGIN FieldDescriptionComposite *****
      14: invokevirtual #12                 // Method java/lang/StringBuffer.append:(Ljava/lang/String;)Ljava/lang/StringBuffer;
      17: pop
      18: aload_1
      19: new           #13                 // class java/lang/StringBuilder
      22: dup
      23: invokespecial #14                 // Method java/lang/StringBuilder."<init>":()V
      26: ldc           #15                 // String FDC.fieldName=
      28: invokevirtual #16                 // Method java/lang/StringBuilder.append:(Ljava/lang/String;)Ljava/lang/StringBuilder;
      31: aload_0
      32: getfield      #3                  // Field fieldName:Ljava/lang/String;
      35: invokevirtual #16                 // Method java/lang/StringBuilder.append:(Ljava/lang/String;)Ljava/lang/StringBuilder;
      38: invokevirtual #17                 // Method java/lang/StringBuilder.toString:()Ljava/lang/String;
      41: invokevirtual #12                 // Method java/lang/StringBuffer.append:(Ljava/lang/String;)Ljava/lang/StringBuffer;
      44: pop
      45: aload_1
      46: aload_2
      47: invokevirtual #12                 // Method java/lang/StringBuffer.append:(Ljava/lang/String;)Ljava/lang/StringBuffer;
      50: pop
      51: aload_0
      52: getfield      #5                  // Field handlerChainAnnot:Lorg/apache/axis2/jaxws/description/builder/HandlerChainAnnot;
      55: ifnull        101
      58: aload_1
      59: ldc           #18                 // String \t @HandlerChain
      61: invokevirtual #12                 // Method java/lang/StringBuffer.append:(Ljava/lang/String;)Ljava/lang/StringBuffer;
      64: pop
      65: aload_1
      66: aload_2
      67: invokevirtual #12                 // Method java/lang/StringBuffer.append:(Ljava/lang/String;)Ljava/lang/StringBuffer;
      70: pop
      71: aload_1
      72: new           #13                 // class java/lang/StringBuilder
      75: dup
      76: invokespecial #14                 // Method java/lang/StringBuilder."<init>":()V
      79: ldc           #19                 // String \t
      81: invokevirtual #16                 // Method java/lang/StringBuilder.append:(Ljava/lang/String;)Ljava/lang/StringBuilder;
      84: aload_0
      85: getfield      #5                  // Field handlerChainAnnot:Lorg/apache/axis2/jaxws/description/builder/HandlerChainAnnot;
      88: invokevirtual #20                 // Method org/apache/axis2/jaxws/description/builder/HandlerChainAnnot.toString:()Ljava/lang/String;
      91: invokevirtual #16                 // Method java/lang/StringBuilder.append:(Ljava/lang/String;)Ljava/lang/StringBuilder;
      94: invokevirtual #17                 // Method java/lang/StringBuilder.toString:()Ljava/lang/String;
      97: invokevirtual #12                 // Method java/lang/StringBuffer.append:(Ljava/lang/String;)Ljava/lang/StringBuffer;
     100: pop
     101: aload_1
     102: aload_2
     103: invokevirtual #12                 // Method java/lang/StringBuffer.append:(Ljava/lang/String;)Ljava/lang/StringBuffer;
     106: pop
     107: aload_0
     108: getfield      #6                  // Field webServiceRefAnnot:Lorg/apache/axis2/jaxws/description/builder/WebServiceRefAnnot;
     111: ifnull        157
     114: aload_1
     115: ldc           #21                 // String \t @WebServiceRef
     117: invokevirtual #12                 // Method java/lang/StringBuffer.append:(Ljava/lang/String;)Ljava/lang/StringBuffer;
     120: pop
     121: aload_1
     122: aload_2
     123: invokevirtual #12                 // Method java/lang/StringBuffer.append:(Ljava/lang/String;)Ljava/lang/StringBuffer;
     126: pop
     127: aload_1
     128: new           #13                 // class java/lang/StringBuilder
     131: dup
     132: invokespecial #14                 // Method java/lang/StringBuilder."<init>":()V
     135: ldc           #19                 // String \t
     137: invokevirtual #16                 // Method java/lang/StringBuilder.append:(Ljava/lang/String;)Ljava/lang/StringBuilder;
     140: aload_0
     141: getfield      #6                  // Field webServiceRefAnnot:Lorg/apache/axis2/jaxws/description/builder/WebServiceRefAnnot;
     144: invokevirtual #22                 // Method org/apache/axis2/jaxws/description/builder/WebServiceRefAnnot.toString:()Ljava/lang/String;
     147: invokevirtual #16                 // Method java/lang/StringBuilder.append:(Ljava/lang/String;)Ljava/lang/StringBuilder;
     150: invokevirtual #17                 // Method java/lang/StringBuilder.toString:()Ljava/lang/String;
     153: invokevirtual #12                 // Method java/lang/StringBuffer.append:(Ljava/lang/String;)Ljava/lang/StringBuffer;
     156: pop
     157: aload_1
     158: ldc           #23                 // String ***** END FieldDescriptionComposite
     160: invokevirtual #12                 // Method java/lang/StringBuffer.append:(Ljava/lang/String;)Ljava/lang/StringBuffer;
     163: pop
     164: aload_1
     165: invokevirtual #24                 // Method java/lang/StringBuffer.toString:()Ljava/lang/String;
     168: areturn
}
