Compiled from "BaseConfigurationBuilderProvider.java"
public class org.apache.commons.configuration2.builder.combined.BaseConfigurationBuilderProvider implements org.apache.commons.configuration2.builder.combined.ConfigurationBuilderProvider {
  private static final java.lang.Class<?>[] CTOR_PARAM_TYPES;

  private final java.lang.String builderClass;

  private final java.lang.String reloadingBuilderClass;

  private final java.lang.String configurationClass;

  private final java.util.Collection<java.lang.String> parameterClasses;

  public org.apache.commons.configuration2.builder.combined.BaseConfigurationBuilderProvider(java.lang.String, java.lang.String, java.lang.String, java.util.Collection<java.lang.String>);
    Code:
       0: aload_0
       1: invokespecial #1                  // Method java/lang/Object."<init>":()V
       4: aload_1
       5: ifnonnull     18
       8: new           #2                  // class java/lang/IllegalArgumentException
      11: dup
      12: ldc           #3                  // String Builder class must not be null!
      14: invokespecial #4                  // Method java/lang/IllegalArgumentException."<init>":(Ljava/lang/String;)V
      17: athrow
      18: aload_3
      19: ifnonnull     32
      22: new           #2                  // class java/lang/IllegalArgumentException
      25: dup
      26: ldc           #5                  // String Configuration class must not be null!
      28: invokespecial #4                  // Method java/lang/IllegalArgumentException."<init>":(Ljava/lang/String;)V
      31: athrow
      32: aload_0
      33: aload_1
      34: putfield      #6                  // Field builderClass:Ljava/lang/String;
      37: aload_0
      38: aload_2
      39: putfield      #7                  // Field reloadingBuilderClass:Ljava/lang/String;
      42: aload_0
      43: aload_3
      44: putfield      #8                  // Field configurationClass:Ljava/lang/String;
      47: aload_0
      48: aload         4
      50: invokestatic  #9                  // Method initParameterClasses:(Ljava/util/Collection;)Ljava/util/Collection;
      53: putfield      #10                 // Field parameterClasses:Ljava/util/Collection;
      56: return

  public java.lang.String getBuilderClass();
    Code:
       0: aload_0
       1: getfield      #6                  // Field builderClass:Ljava/lang/String;
       4: areturn

  public java.lang.String getReloadingBuilderClass();
    Code:
       0: aload_0
       1: getfield      #7                  // Field reloadingBuilderClass:Ljava/lang/String;
       4: areturn

  public java.lang.String getConfigurationClass();
    Code:
       0: aload_0
       1: getfield      #8                  // Field configurationClass:Ljava/lang/String;
       4: areturn

  public java.util.Collection<java.lang.String> getParameterClasses();
    Code:
       0: aload_0
       1: getfield      #10                 // Field parameterClasses:Ljava/util/Collection;
       4: areturn

  public org.apache.commons.configuration2.builder.ConfigurationBuilder<? extends org.apache.commons.configuration2.Configuration> getConfigurationBuilder(org.apache.commons.configuration2.builder.combined.ConfigurationDeclaration) throws org.apache.commons.configuration2.ex.ConfigurationException;
    Code:
       0: aload_0
       1: invokevirtual #11                 // Method createParameterObjects:()Ljava/util/Collection;
       4: astore_2
       5: aload_0
       6: aload_1
       7: aload_2
       8: invokevirtual #12                 // Method initializeParameterObjects:(Lorg/apache/commons/configuration2/builder/combined/ConfigurationDeclaration;Ljava/util/Collection;)V
      11: aload_0
      12: aload_1
      13: aload_2
      14: invokevirtual #13                 // Method createBuilder:(Lorg/apache/commons/configuration2/builder/combined/ConfigurationDeclaration;Ljava/util/Collection;)Lorg/apache/commons/configuration2/builder/BasicConfigurationBuilder;
      17: astore_3
      18: aload_0
      19: aload_3
      20: aload_1
      21: aload_2
      22: invokevirtual #14                 // Method configureBuilder:(Lorg/apache/commons/configuration2/builder/BasicConfigurationBuilder;Lorg/apache/commons/configuration2/builder/combined/ConfigurationDeclaration;Ljava/util/Collection;)V
      25: aload_3
      26: areturn
      27: astore_2
      28: aload_2
      29: athrow
      30: astore_2
      31: new           #15                 // class org/apache/commons/configuration2/ex/ConfigurationException
      34: dup
      35: aload_2
      36: invokespecial #17                 // Method org/apache/commons/configuration2/ex/ConfigurationException."<init>":(Ljava/lang/Throwable;)V
      39: athrow
    Exception table:
       from    to  target type
           0    26    27   Class org/apache/commons/configuration2/ex/ConfigurationException
           0    26    30   Class java/lang/Exception

  protected boolean isAllowFailOnInit(org.apache.commons.configuration2.builder.combined.ConfigurationDeclaration);
    Code:
       0: aload_1
       1: invokevirtual #18                 // Method org/apache/commons/configuration2/builder/combined/ConfigurationDeclaration.isOptional:()Z
       4: ifeq          18
       7: aload_1
       8: invokevirtual #19                 // Method org/apache/commons/configuration2/builder/combined/ConfigurationDeclaration.isForceCreate:()Z
      11: ifeq          18
      14: iconst_1
      15: goto          19
      18: iconst_0
      19: ireturn

  protected java.util.Collection<org.apache.commons.configuration2.builder.BuilderParameters> createParameterObjects() throws java.lang.Exception;
    Code:
       0: new           #20                 // class java/util/ArrayList
       3: dup
       4: aload_0
       5: invokevirtual #21                 // Method getParameterClasses:()Ljava/util/Collection;
       8: invokeinterface #22,  1           // InterfaceMethod java/util/Collection.size:()I
      13: invokespecial #23                 // Method java/util/ArrayList."<init>":(I)V
      16: astore_1
      17: aload_0
      18: invokevirtual #21                 // Method getParameterClasses:()Ljava/util/Collection;
      21: invokeinterface #24,  1           // InterfaceMethod java/util/Collection.iterator:()Ljava/util/Iterator;
      26: astore_2
      27: aload_2
      28: invokeinterface #25,  1           // InterfaceMethod java/util/Iterator.hasNext:()Z
      33: ifeq          60
      36: aload_2
      37: invokeinterface #26,  1           // InterfaceMethod java/util/Iterator.next:()Ljava/lang/Object;
      42: checkcast     #27                 // class java/lang/String
      45: astore_3
      46: aload_1
      47: aload_3
      48: invokestatic  #28                 // Method createParameterObject:(Ljava/lang/String;)Lorg/apache/commons/configuration2/builder/BuilderParameters;
      51: invokeinterface #29,  2           // InterfaceMethod java/util/Collection.add:(Ljava/lang/Object;)Z
      56: pop
      57: goto          27
      60: aload_1
      61: areturn

  protected void initializeParameterObjects(org.apache.commons.configuration2.builder.combined.ConfigurationDeclaration, java.util.Collection<org.apache.commons.configuration2.builder.BuilderParameters>) throws java.lang.Exception;
    Code:
       0: aload_0
       1: aload_1
       2: aload_2
       3: invokevirtual #30                 // Method inheritParentBuilderProperties:(Lorg/apache/commons/configuration2/builder/combined/ConfigurationDeclaration;Ljava/util/Collection;)V
       6: new           #31                 // class org/apache/commons/configuration2/builder/combined/MultiWrapDynaBean
       9: dup
      10: aload_2
      11: invokespecial #32                 // Method org/apache/commons/configuration2/builder/combined/MultiWrapDynaBean."<init>":(Ljava/util/Collection;)V
      14: astore_3
      15: aload_1
      16: invokevirtual #33                 // Method org/apache/commons/configuration2/builder/combined/ConfigurationDeclaration.getConfigurationBuilder:()Lorg/apache/commons/configuration2/builder/combined/CombinedConfigurationBuilder;
      19: aload_3
      20: aload_1
      21: invokevirtual #34                 // Method org/apache/commons/configuration2/builder/combined/CombinedConfigurationBuilder.initBean:(Ljava/lang/Object;Lorg/apache/commons/configuration2/beanutils/BeanDeclaration;)V
      24: return

  protected void inheritParentBuilderProperties(org.apache.commons.configuration2.builder.combined.ConfigurationDeclaration, java.util.Collection<org.apache.commons.configuration2.builder.BuilderParameters>);
    Code:
       0: aload_2
       1: invokeinterface #24,  1           // InterfaceMethod java/util/Collection.iterator:()Ljava/util/Iterator;
       6: astore_3
       7: aload_3
       8: invokeinterface #25,  1           // InterfaceMethod java/util/Iterator.hasNext:()Z
      13: ifeq          39
      16: aload_3
      17: invokeinterface #26,  1           // InterfaceMethod java/util/Iterator.next:()Ljava/lang/Object;
      22: checkcast     #35                 // class org/apache/commons/configuration2/builder/BuilderParameters
      25: astore        4
      27: aload_1
      28: invokevirtual #33                 // Method org/apache/commons/configuration2/builder/combined/ConfigurationDeclaration.getConfigurationBuilder:()Lorg/apache/commons/configuration2/builder/combined/CombinedConfigurationBuilder;
      31: aload         4
      33: invokevirtual #36                 // Method org/apache/commons/configuration2/builder/combined/CombinedConfigurationBuilder.initChildBuilderParameters:(Lorg/apache/commons/configuration2/builder/BuilderParameters;)V
      36: goto          7
      39: return

  protected org.apache.commons.configuration2.builder.BasicConfigurationBuilder<? extends org.apache.commons.configuration2.Configuration> createBuilder(org.apache.commons.configuration2.builder.combined.ConfigurationDeclaration, java.util.Collection<org.apache.commons.configuration2.builder.BuilderParameters>) throws java.lang.Exception;
    Code:
       0: aload_0
       1: aload_1
       2: invokevirtual #37                 // Method determineBuilderClass:(Lorg/apache/commons/configuration2/builder/combined/ConfigurationDeclaration;)Ljava/lang/String;
       5: invokestatic  #38                 // Method org/apache/commons/configuration2/ConfigurationUtils.loadClass:(Ljava/lang/String;)Ljava/lang/Class;
       8: astore_3
       9: aload_0
      10: aload_1
      11: aload_2
      12: invokevirtual #39                 // Method determineConfigurationClass:(Lorg/apache/commons/configuration2/builder/combined/ConfigurationDeclaration;Ljava/util/Collection;)Ljava/lang/String;
      15: invokestatic  #38                 // Method org/apache/commons/configuration2/ConfigurationUtils.loadClass:(Ljava/lang/String;)Ljava/lang/Class;
      18: astore        4
      20: aload_3
      21: getstatic     #40                 // Field CTOR_PARAM_TYPES:[Ljava/lang/Class;
      24: invokevirtual #41                 // Method java/lang/Class.getConstructor:([Ljava/lang/Class;)Ljava/lang/reflect/Constructor;
      27: astore        5
      29: aload         5
      31: iconst_3
      32: anewarray     #42                 // class java/lang/Object
      35: dup
      36: iconst_0
      37: aload         4
      39: aastore
      40: dup
      41: iconst_1
      42: aconst_null
      43: aastore
      44: dup
      45: iconst_2
      46: aload_0
      47: aload_1
      48: invokevirtual #43                 // Method isAllowFailOnInit:(Lorg/apache/commons/configuration2/builder/combined/ConfigurationDeclaration;)Z
      51: invokestatic  #44                 // Method java/lang/Boolean.valueOf:(Z)Ljava/lang/Boolean;
      54: aastore
      55: invokevirtual #45                 // Method java/lang/reflect/Constructor.newInstance:([Ljava/lang/Object;)Ljava/lang/Object;
      58: checkcast     #46                 // class org/apache/commons/configuration2/builder/BasicConfigurationBuilder
      61: astore        6
      63: aload         6
      65: areturn

  protected void configureBuilder(org.apache.commons.configuration2.builder.BasicConfigurationBuilder<? extends org.apache.commons.configuration2.Configuration>, org.apache.commons.configuration2.builder.combined.ConfigurationDeclaration, java.util.Collection<org.apache.commons.configuration2.builder.BuilderParameters>) throws java.lang.Exception;
    Code:
       0: aload_1
       1: aload_3
       2: aload_3
       3: invokeinterface #22,  1           // InterfaceMethod java/util/Collection.size:()I
       8: anewarray     #35                 // class org/apache/commons/configuration2/builder/BuilderParameters
      11: invokeinterface #47,  2           // InterfaceMethod java/util/Collection.toArray:([Ljava/lang/Object;)[Ljava/lang/Object;
      16: checkcast     #48                 // class "[Lorg/apache/commons/configuration2/builder/BuilderParameters;"
      19: invokevirtual #49                 // Method org/apache/commons/configuration2/builder/BasicConfigurationBuilder.configure:([Lorg/apache/commons/configuration2/builder/BuilderParameters;)Lorg/apache/commons/configuration2/builder/BasicConfigurationBuilder;
      22: pop
      23: return

  protected java.lang.String determineBuilderClass(org.apache.commons.configuration2.builder.combined.ConfigurationDeclaration) throws org.apache.commons.configuration2.ex.ConfigurationException;
    Code:
       0: aload_1
       1: invokevirtual #50                 // Method org/apache/commons/configuration2/builder/combined/ConfigurationDeclaration.isReload:()Z
       4: ifeq          49
       7: aload_0
       8: invokevirtual #51                 // Method getReloadingBuilderClass:()Ljava/lang/String;
      11: ifnonnull     44
      14: new           #15                 // class org/apache/commons/configuration2/ex/ConfigurationException
      17: dup
      18: new           #52                 // class java/lang/StringBuilder
      21: dup
      22: invokespecial #53                 // Method java/lang/StringBuilder."<init>":()V
      25: ldc           #54                 // String No support for reloading for builder class
      27: invokevirtual #55                 // Method java/lang/StringBuilder.append:(Ljava/lang/String;)Ljava/lang/StringBuilder;
      30: aload_0
      31: invokevirtual #56                 // Method getBuilderClass:()Ljava/lang/String;
      34: invokevirtual #55                 // Method java/lang/StringBuilder.append:(Ljava/lang/String;)Ljava/lang/StringBuilder;
      37: invokevirtual #57                 // Method java/lang/StringBuilder.toString:()Ljava/lang/String;
      40: invokespecial #58                 // Method org/apache/commons/configuration2/ex/ConfigurationException."<init>":(Ljava/lang/String;)V
      43: athrow
      44: aload_0
      45: invokevirtual #51                 // Method getReloadingBuilderClass:()Ljava/lang/String;
      48: areturn
      49: aload_0
      50: invokevirtual #56                 // Method getBuilderClass:()Ljava/lang/String;
      53: areturn

  protected java.lang.String determineConfigurationClass(org.apache.commons.configuration2.builder.combined.ConfigurationDeclaration, java.util.Collection<org.apache.commons.configuration2.builder.BuilderParameters>) throws org.apache.commons.configuration2.ex.ConfigurationException;
    Code:
       0: aload_0
       1: invokevirtual #59                 // Method getConfigurationClass:()Ljava/lang/String;
       4: areturn

  private static org.apache.commons.configuration2.builder.BuilderParameters createParameterObject(java.lang.String) throws java.lang.Exception;
    Code:
       0: aload_0
       1: invokestatic  #38                 // Method org/apache/commons/configuration2/ConfigurationUtils.loadClass:(Ljava/lang/String;)Ljava/lang/Class;
       4: astore_1
       5: aload_1
       6: invokevirtual #60                 // Method java/lang/Class.newInstance:()Ljava/lang/Object;
       9: checkcast     #35                 // class org/apache/commons/configuration2/builder/BuilderParameters
      12: astore_2
      13: aload_2
      14: areturn

  private static java.util.Collection<java.lang.String> initParameterClasses(java.util.Collection<java.lang.String>);
    Code:
       0: aload_0
       1: ifnonnull     8
       4: invokestatic  #61                 // Method java/util/Collections.emptySet:()Ljava/util/Set;
       7: areturn
       8: new           #20                 // class java/util/ArrayList
      11: dup
      12: aload_0
      13: invokespecial #62                 // Method java/util/ArrayList."<init>":(Ljava/util/Collection;)V
      16: invokestatic  #63                 // Method java/util/Collections.unmodifiableCollection:(Ljava/util/Collection;)Ljava/util/Collection;
      19: areturn

  static {};
    Code:
       0: iconst_3
       1: anewarray     #64                 // class java/lang/Class
       4: dup
       5: iconst_0
       6: ldc           #64                 // class java/lang/Class
       8: aastore
       9: dup
      10: iconst_1
      11: ldc           #65                 // class java/util/Map
      13: aastore
      14: dup
      15: iconst_2
      16: getstatic     #66                 // Field java/lang/Boolean.TYPE:Ljava/lang/Class;
      19: aastore
      20: putstatic     #40                 // Field CTOR_PARAM_TYPES:[Ljava/lang/Class;
      23: return
}
