Compiled from "MultiFileConfigurationBuilder.java"
public class org.apache.commons.configuration2.builder.combined.MultiFileConfigurationBuilder<T extends org.apache.commons.configuration2.FileBasedConfiguration> extends org.apache.commons.configuration2.builder.BasicConfigurationBuilder<T> {
  private static final java.lang.String KEY_INTERPOLATOR;

  private final java.util.concurrent.ConcurrentMap<java.lang.String, org.apache.commons.configuration2.builder.FileBasedConfigurationBuilder<T>> managedBuilders;

  private final java.util.concurrent.atomic.AtomicReference<org.apache.commons.configuration2.interpol.ConfigurationInterpolator> interpolator;

  private final java.lang.ThreadLocal<java.lang.Boolean> inInterpolation;

  private final org.apache.commons.configuration2.event.EventListenerList configurationListeners;

  private final org.apache.commons.configuration2.event.EventListener<org.apache.commons.configuration2.builder.ConfigurationBuilderEvent> managedBuilderDelegationListener;

  public org.apache.commons.configuration2.builder.combined.MultiFileConfigurationBuilder(java.lang.Class<? extends T>, java.util.Map<java.lang.String, java.lang.Object>, boolean);
    Code:
       0: aload_0
       1: aload_1
       2: aload_2
       3: iload_3
       4: invokespecial #2                  // Method org/apache/commons/configuration2/builder/BasicConfigurationBuilder."<init>":(Ljava/lang/Class;Ljava/util/Map;Z)V
       7: aload_0
       8: new           #3                  // class java/util/concurrent/ConcurrentHashMap
      11: dup
      12: invokespecial #4                  // Method java/util/concurrent/ConcurrentHashMap."<init>":()V
      15: putfield      #5                  // Field managedBuilders:Ljava/util/concurrent/ConcurrentMap;
      18: aload_0
      19: new           #6                  // class java/util/concurrent/atomic/AtomicReference
      22: dup
      23: invokespecial #7                  // Method java/util/concurrent/atomic/AtomicReference."<init>":()V
      26: putfield      #8                  // Field interpolator:Ljava/util/concurrent/atomic/AtomicReference;
      29: aload_0
      30: new           #9                  // class java/lang/ThreadLocal
      33: dup
      34: invokespecial #10                 // Method java/lang/ThreadLocal."<init>":()V
      37: putfield      #11                 // Field inInterpolation:Ljava/lang/ThreadLocal;
      40: aload_0
      41: new           #12                 // class org/apache/commons/configuration2/event/EventListenerList
      44: dup
      45: invokespecial #13                 // Method org/apache/commons/configuration2/event/EventListenerList."<init>":()V
      48: putfield      #14                 // Field configurationListeners:Lorg/apache/commons/configuration2/event/EventListenerList;
      51: aload_0
      52: new           #15                 // class org/apache/commons/configuration2/builder/combined/MultiFileConfigurationBuilder$1
      55: dup
      56: aload_0
      57: invokespecial #16                 // Method org/apache/commons/configuration2/builder/combined/MultiFileConfigurationBuilder$1."<init>":(Lorg/apache/commons/configuration2/builder/combined/MultiFileConfigurationBuilder;)V
      60: putfield      #17                 // Field managedBuilderDelegationListener:Lorg/apache/commons/configuration2/event/EventListener;
      63: return

  public org.apache.commons.configuration2.builder.combined.MultiFileConfigurationBuilder(java.lang.Class<? extends T>, java.util.Map<java.lang.String, java.lang.Object>);
    Code:
       0: aload_0
       1: aload_1
       2: aload_2
       3: invokespecial #18                 // Method org/apache/commons/configuration2/builder/BasicConfigurationBuilder."<init>":(Ljava/lang/Class;Ljava/util/Map;)V
       6: aload_0
       7: new           #3                  // class java/util/concurrent/ConcurrentHashMap
      10: dup
      11: invokespecial #4                  // Method java/util/concurrent/ConcurrentHashMap."<init>":()V
      14: putfield      #5                  // Field managedBuilders:Ljava/util/concurrent/ConcurrentMap;
      17: aload_0
      18: new           #6                  // class java/util/concurrent/atomic/AtomicReference
      21: dup
      22: invokespecial #7                  // Method java/util/concurrent/atomic/AtomicReference."<init>":()V
      25: putfield      #8                  // Field interpolator:Ljava/util/concurrent/atomic/AtomicReference;
      28: aload_0
      29: new           #9                  // class java/lang/ThreadLocal
      32: dup
      33: invokespecial #10                 // Method java/lang/ThreadLocal."<init>":()V
      36: putfield      #11                 // Field inInterpolation:Ljava/lang/ThreadLocal;
      39: aload_0
      40: new           #12                 // class org/apache/commons/configuration2/event/EventListenerList
      43: dup
      44: invokespecial #13                 // Method org/apache/commons/configuration2/event/EventListenerList."<init>":()V
      47: putfield      #14                 // Field configurationListeners:Lorg/apache/commons/configuration2/event/EventListenerList;
      50: aload_0
      51: new           #15                 // class org/apache/commons/configuration2/builder/combined/MultiFileConfigurationBuilder$1
      54: dup
      55: aload_0
      56: invokespecial #16                 // Method org/apache/commons/configuration2/builder/combined/MultiFileConfigurationBuilder$1."<init>":(Lorg/apache/commons/configuration2/builder/combined/MultiFileConfigurationBuilder;)V
      59: putfield      #17                 // Field managedBuilderDelegationListener:Lorg/apache/commons/configuration2/event/EventListener;
      62: return

  public org.apache.commons.configuration2.builder.combined.MultiFileConfigurationBuilder(java.lang.Class<? extends T>);
    Code:
       0: aload_0
       1: aload_1
       2: invokespecial #19                 // Method org/apache/commons/configuration2/builder/BasicConfigurationBuilder."<init>":(Ljava/lang/Class;)V
       5: aload_0
       6: new           #3                  // class java/util/concurrent/ConcurrentHashMap
       9: dup
      10: invokespecial #4                  // Method java/util/concurrent/ConcurrentHashMap."<init>":()V
      13: putfield      #5                  // Field managedBuilders:Ljava/util/concurrent/ConcurrentMap;
      16: aload_0
      17: new           #6                  // class java/util/concurrent/atomic/AtomicReference
      20: dup
      21: invokespecial #7                  // Method java/util/concurrent/atomic/AtomicReference."<init>":()V
      24: putfield      #8                  // Field interpolator:Ljava/util/concurrent/atomic/AtomicReference;
      27: aload_0
      28: new           #9                  // class java/lang/ThreadLocal
      31: dup
      32: invokespecial #10                 // Method java/lang/ThreadLocal."<init>":()V
      35: putfield      #11                 // Field inInterpolation:Ljava/lang/ThreadLocal;
      38: aload_0
      39: new           #12                 // class org/apache/commons/configuration2/event/EventListenerList
      42: dup
      43: invokespecial #13                 // Method org/apache/commons/configuration2/event/EventListenerList."<init>":()V
      46: putfield      #14                 // Field configurationListeners:Lorg/apache/commons/configuration2/event/EventListenerList;
      49: aload_0
      50: new           #15                 // class org/apache/commons/configuration2/builder/combined/MultiFileConfigurationBuilder$1
      53: dup
      54: aload_0
      55: invokespecial #16                 // Method org/apache/commons/configuration2/builder/combined/MultiFileConfigurationBuilder$1."<init>":(Lorg/apache/commons/configuration2/builder/combined/MultiFileConfigurationBuilder;)V
      58: putfield      #17                 // Field managedBuilderDelegationListener:Lorg/apache/commons/configuration2/event/EventListener;
      61: return

  public org.apache.commons.configuration2.builder.combined.MultiFileConfigurationBuilder<T> configure(org.apache.commons.configuration2.builder.BuilderParameters...);
    Code:
       0: aload_0
       1: aload_1
       2: invokespecial #20                 // Method org/apache/commons/configuration2/builder/BasicConfigurationBuilder.configure:([Lorg/apache/commons/configuration2/builder/BuilderParameters;)Lorg/apache/commons/configuration2/builder/BasicConfigurationBuilder;
       5: pop
       6: aload_0
       7: areturn

  public T getConfiguration() throws org.apache.commons.configuration2.ex.ConfigurationException;
    Code:
       0: aload_0
       1: invokevirtual #21                 // Method getManagedBuilder:()Lorg/apache/commons/configuration2/builder/FileBasedConfigurationBuilder;
       4: invokevirtual #22                 // Method org/apache/commons/configuration2/builder/FileBasedConfigurationBuilder.getConfiguration:()Lorg/apache/commons/configuration2/ImmutableConfiguration;
       7: checkcast     #23                 // class org/apache/commons/configuration2/FileBasedConfiguration
      10: areturn

  public org.apache.commons.configuration2.builder.FileBasedConfigurationBuilder<T> getManagedBuilder() throws org.apache.commons.configuration2.ex.ConfigurationException;
    Code:
       0: aload_0
       1: invokevirtual #24                 // Method getParameters:()Ljava/util/Map;
       4: astore_1
       5: aload_1
       6: iconst_1
       7: invokestatic  #25                 // Method org/apache/commons/configuration2/builder/combined/MultiFileBuilderParametersImpl.fromParameters:(Ljava/util/Map;Z)Lorg/apache/commons/configuration2/builder/combined/MultiFileBuilderParametersImpl;
      10: astore_2
      11: aload_2
      12: invokevirtual #26                 // Method org/apache/commons/configuration2/builder/combined/MultiFileBuilderParametersImpl.getFilePattern:()Ljava/lang/String;
      15: ifnonnull     28
      18: new           #27                 // class org/apache/commons/configuration2/ex/ConfigurationException
      21: dup
      22: ldc           #28                 // String No file name pattern is set!
      24: invokespecial #29                 // Method org/apache/commons/configuration2/ex/ConfigurationException."<init>":(Ljava/lang/String;)V
      27: athrow
      28: aload_0
      29: aload_2
      30: invokespecial #30                 // Method fetchFileName:(Lorg/apache/commons/configuration2/builder/combined/MultiFileBuilderParametersImpl;)Ljava/lang/String;
      33: astore_3
      34: aload_0
      35: invokevirtual #31                 // Method getManagedBuilders:()Ljava/util/concurrent/ConcurrentMap;
      38: aload_3
      39: invokeinterface #32,  2           // InterfaceMethod java/util/concurrent/ConcurrentMap.get:(Ljava/lang/Object;)Ljava/lang/Object;
      44: checkcast     #33                 // class org/apache/commons/configuration2/builder/FileBasedConfigurationBuilder
      47: astore        4
      49: aload         4
      51: ifnonnull     101
      54: aload_0
      55: aload_3
      56: aload_1
      57: aload_2
      58: invokestatic  #34                 // Method createManagedBuilderParameters:(Ljava/util/Map;Lorg/apache/commons/configuration2/builder/combined/MultiFileBuilderParametersImpl;)Ljava/util/Map;
      61: invokevirtual #35                 // Method createInitializedManagedBuilder:(Ljava/lang/String;Ljava/util/Map;)Lorg/apache/commons/configuration2/builder/FileBasedConfigurationBuilder;
      64: astore        4
      66: aload_0
      67: invokevirtual #31                 // Method getManagedBuilders:()Ljava/util/concurrent/ConcurrentMap;
      70: aload_3
      71: aload         4
      73: invokestatic  #36                 // Method org/apache/commons/lang3/concurrent/ConcurrentUtils.putIfAbsent:(Ljava/util/concurrent/ConcurrentMap;Ljava/lang/Object;Ljava/lang/Object;)Ljava/lang/Object;
      76: checkcast     #33                 // class org/apache/commons/configuration2/builder/FileBasedConfigurationBuilder
      79: astore        5
      81: aload         5
      83: aload         4
      85: if_acmpne     97
      88: aload_0
      89: aload         5
      91: invokespecial #37                 // Method initListeners:(Lorg/apache/commons/configuration2/builder/FileBasedConfigurationBuilder;)V
      94: goto          101
      97: aload         5
      99: astore        4
     101: aload         4
     103: areturn

  public synchronized <E extends org.apache.commons.configuration2.event.Event> void addEventListener(org.apache.commons.configuration2.event.EventType<E>, org.apache.commons.configuration2.event.EventListener<? super E>);
    Code:
       0: aload_0
       1: aload_1
       2: aload_2
       3: invokespecial #38                 // Method org/apache/commons/configuration2/builder/BasicConfigurationBuilder.addEventListener:(Lorg/apache/commons/configuration2/event/EventType;Lorg/apache/commons/configuration2/event/EventListener;)V
       6: aload_1
       7: invokestatic  #39                 // Method isEventTypeForManagedBuilders:(Lorg/apache/commons/configuration2/event/EventType;)Z
      10: ifeq          67
      13: aload_0
      14: invokevirtual #31                 // Method getManagedBuilders:()Ljava/util/concurrent/ConcurrentMap;
      17: invokeinterface #40,  1           // InterfaceMethod java/util/concurrent/ConcurrentMap.values:()Ljava/util/Collection;
      22: invokeinterface #41,  1           // InterfaceMethod java/util/Collection.iterator:()Ljava/util/Iterator;
      27: astore_3
      28: aload_3
      29: invokeinterface #42,  1           // InterfaceMethod java/util/Iterator.hasNext:()Z
      34: ifeq          58
      37: aload_3
      38: invokeinterface #43,  1           // InterfaceMethod java/util/Iterator.next:()Ljava/lang/Object;
      43: checkcast     #33                 // class org/apache/commons/configuration2/builder/FileBasedConfigurationBuilder
      46: astore        4
      48: aload         4
      50: aload_1
      51: aload_2
      52: invokevirtual #44                 // Method org/apache/commons/configuration2/builder/FileBasedConfigurationBuilder.addEventListener:(Lorg/apache/commons/configuration2/event/EventType;Lorg/apache/commons/configuration2/event/EventListener;)V
      55: goto          28
      58: aload_0
      59: getfield      #14                 // Field configurationListeners:Lorg/apache/commons/configuration2/event/EventListenerList;
      62: aload_1
      63: aload_2
      64: invokevirtual #45                 // Method org/apache/commons/configuration2/event/EventListenerList.addEventListener:(Lorg/apache/commons/configuration2/event/EventType;Lorg/apache/commons/configuration2/event/EventListener;)V
      67: return

  public synchronized <E extends org.apache.commons.configuration2.event.Event> boolean removeEventListener(org.apache.commons.configuration2.event.EventType<E>, org.apache.commons.configuration2.event.EventListener<? super E>);
    Code:
       0: aload_0
       1: aload_1
       2: aload_2
       3: invokespecial #46                 // Method org/apache/commons/configuration2/builder/BasicConfigurationBuilder.removeEventListener:(Lorg/apache/commons/configuration2/event/EventType;Lorg/apache/commons/configuration2/event/EventListener;)Z
       6: istore_3
       7: aload_1
       8: invokestatic  #39                 // Method isEventTypeForManagedBuilders:(Lorg/apache/commons/configuration2/event/EventType;)Z
      11: ifeq          73
      14: aload_0
      15: invokevirtual #31                 // Method getManagedBuilders:()Ljava/util/concurrent/ConcurrentMap;
      18: invokeinterface #40,  1           // InterfaceMethod java/util/concurrent/ConcurrentMap.values:()Ljava/util/Collection;
      23: invokeinterface #41,  1           // InterfaceMethod java/util/Collection.iterator:()Ljava/util/Iterator;
      28: astore        4
      30: aload         4
      32: invokeinterface #42,  1           // InterfaceMethod java/util/Iterator.hasNext:()Z
      37: ifeq          63
      40: aload         4
      42: invokeinterface #43,  1           // InterfaceMethod java/util/Iterator.next:()Ljava/lang/Object;
      47: checkcast     #33                 // class org/apache/commons/configuration2/builder/FileBasedConfigurationBuilder
      50: astore        5
      52: aload         5
      54: aload_1
      55: aload_2
      56: invokevirtual #47                 // Method org/apache/commons/configuration2/builder/FileBasedConfigurationBuilder.removeEventListener:(Lorg/apache/commons/configuration2/event/EventType;Lorg/apache/commons/configuration2/event/EventListener;)Z
      59: pop
      60: goto          30
      63: aload_0
      64: getfield      #14                 // Field configurationListeners:Lorg/apache/commons/configuration2/event/EventListenerList;
      67: aload_1
      68: aload_2
      69: invokevirtual #48                 // Method org/apache/commons/configuration2/event/EventListenerList.removeEventListener:(Lorg/apache/commons/configuration2/event/EventType;Lorg/apache/commons/configuration2/event/EventListener;)Z
      72: pop
      73: iload_3
      74: ireturn

  public synchronized void resetParameters();
    Code:
       0: aload_0
       1: invokevirtual #31                 // Method getManagedBuilders:()Ljava/util/concurrent/ConcurrentMap;
       4: invokeinterface #40,  1           // InterfaceMethod java/util/concurrent/ConcurrentMap.values:()Ljava/util/Collection;
       9: invokeinterface #41,  1           // InterfaceMethod java/util/Collection.iterator:()Ljava/util/Iterator;
      14: astore_1
      15: aload_1
      16: invokeinterface #42,  1           // InterfaceMethod java/util/Iterator.hasNext:()Z
      21: ifeq          49
      24: aload_1
      25: invokeinterface #43,  1           // InterfaceMethod java/util/Iterator.next:()Ljava/lang/Object;
      30: checkcast     #33                 // class org/apache/commons/configuration2/builder/FileBasedConfigurationBuilder
      33: astore_2
      34: aload_2
      35: getstatic     #49                 // Field org/apache/commons/configuration2/builder/ConfigurationBuilderEvent.ANY:Lorg/apache/commons/configuration2/event/EventType;
      38: aload_0
      39: getfield      #17                 // Field managedBuilderDelegationListener:Lorg/apache/commons/configuration2/event/EventListener;
      42: invokevirtual #47                 // Method org/apache/commons/configuration2/builder/FileBasedConfigurationBuilder.removeEventListener:(Lorg/apache/commons/configuration2/event/EventType;Lorg/apache/commons/configuration2/event/EventListener;)Z
      45: pop
      46: goto          15
      49: aload_0
      50: invokevirtual #31                 // Method getManagedBuilders:()Ljava/util/concurrent/ConcurrentMap;
      53: invokeinterface #50,  1           // InterfaceMethod java/util/concurrent/ConcurrentMap.clear:()V
      58: aload_0
      59: getfield      #8                  // Field interpolator:Ljava/util/concurrent/atomic/AtomicReference;
      62: aconst_null
      63: invokevirtual #51                 // Method java/util/concurrent/atomic/AtomicReference.set:(Ljava/lang/Object;)V
      66: aload_0
      67: invokespecial #52                 // Method org/apache/commons/configuration2/builder/BasicConfigurationBuilder.resetParameters:()V
      70: return

  protected org.apache.commons.configuration2.interpol.ConfigurationInterpolator getInterpolator();
    Code:
       0: aload_0
       1: getfield      #8                  // Field interpolator:Ljava/util/concurrent/atomic/AtomicReference;
       4: invokevirtual #53                 // Method java/util/concurrent/atomic/AtomicReference.get:()Ljava/lang/Object;
       7: checkcast     #54                 // class org/apache/commons/configuration2/interpol/ConfigurationInterpolator
      10: astore_1
      11: aload_1
      12: ifnull        20
      15: iconst_1
      16: istore_2
      17: goto          35
      20: aload_0
      21: invokevirtual #55                 // Method createInterpolator:()Lorg/apache/commons/configuration2/interpol/ConfigurationInterpolator;
      24: astore_1
      25: aload_0
      26: getfield      #8                  // Field interpolator:Ljava/util/concurrent/atomic/AtomicReference;
      29: aconst_null
      30: aload_1
      31: invokevirtual #56                 // Method java/util/concurrent/atomic/AtomicReference.compareAndSet:(Ljava/lang/Object;Ljava/lang/Object;)Z
      34: istore_2
      35: iload_2
      36: ifeq          0
      39: aload_1
      40: areturn

  protected org.apache.commons.configuration2.interpol.ConfigurationInterpolator createInterpolator();
    Code:
       0: aload_0
       1: invokevirtual #24                 // Method getParameters:()Ljava/util/Map;
       4: invokestatic  #57                 // Method org/apache/commons/configuration2/builder/BasicBuilderParameters.fetchInterpolatorSpecification:(Ljava/util/Map;)Lorg/apache/commons/configuration2/interpol/InterpolatorSpecification;
       7: astore_1
       8: aload_1
       9: invokestatic  #58                 // Method org/apache/commons/configuration2/interpol/ConfigurationInterpolator.fromSpecification:(Lorg/apache/commons/configuration2/interpol/InterpolatorSpecification;)Lorg/apache/commons/configuration2/interpol/ConfigurationInterpolator;
      12: areturn

  protected java.lang.String constructFileName(org.apache.commons.configuration2.builder.combined.MultiFileBuilderParametersImpl);
    Code:
       0: aload_0
       1: invokevirtual #59                 // Method getInterpolator:()Lorg/apache/commons/configuration2/interpol/ConfigurationInterpolator;
       4: astore_2
       5: aload_2
       6: aload_1
       7: invokevirtual #26                 // Method org/apache/commons/configuration2/builder/combined/MultiFileBuilderParametersImpl.getFilePattern:()Ljava/lang/String;
      10: invokevirtual #60                 // Method org/apache/commons/configuration2/interpol/ConfigurationInterpolator.interpolate:(Ljava/lang/Object;)Ljava/lang/Object;
      13: invokestatic  #61                 // Method java/lang/String.valueOf:(Ljava/lang/Object;)Ljava/lang/String;
      16: areturn

  protected org.apache.commons.configuration2.builder.FileBasedConfigurationBuilder<T> createManagedBuilder(java.lang.String, java.util.Map<java.lang.String, java.lang.Object>) throws org.apache.commons.configuration2.ex.ConfigurationException;
    Code:
       0: new           #33                 // class org/apache/commons/configuration2/builder/FileBasedConfigurationBuilder
       3: dup
       4: aload_0
       5: invokevirtual #62                 // Method getResultClass:()Ljava/lang/Class;
       8: aload_2
       9: aload_0
      10: invokevirtual #63                 // Method isAllowFailOnInit:()Z
      13: invokespecial #64                 // Method org/apache/commons/configuration2/builder/FileBasedConfigurationBuilder."<init>":(Ljava/lang/Class;Ljava/util/Map;Z)V
      16: areturn

  protected org.apache.commons.configuration2.builder.FileBasedConfigurationBuilder<T> createInitializedManagedBuilder(java.lang.String, java.util.Map<java.lang.String, java.lang.Object>) throws org.apache.commons.configuration2.ex.ConfigurationException;
    Code:
       0: aload_0
       1: aload_1
       2: aload_2
       3: invokevirtual #65                 // Method createManagedBuilder:(Ljava/lang/String;Ljava/util/Map;)Lorg/apache/commons/configuration2/builder/FileBasedConfigurationBuilder;
       6: astore_3
       7: aload_3
       8: invokevirtual #66                 // Method org/apache/commons/configuration2/builder/FileBasedConfigurationBuilder.getFileHandler:()Lorg/apache/commons/configuration2/io/FileHandler;
      11: aload_1
      12: invokevirtual #67                 // Method org/apache/commons/configuration2/io/FileHandler.setFileName:(Ljava/lang/String;)V
      15: aload_3
      16: areturn

  protected java.util.concurrent.ConcurrentMap<java.lang.String, org.apache.commons.configuration2.builder.FileBasedConfigurationBuilder<T>> getManagedBuilders();
    Code:
       0: aload_0
       1: getfield      #5                  // Field managedBuilders:Ljava/util/concurrent/ConcurrentMap;
       4: areturn

  private void initListeners(org.apache.commons.configuration2.builder.FileBasedConfigurationBuilder<T>);
    Code:
       0: aload_0
       1: aload_1
       2: aload_0
       3: getfield      #14                 // Field configurationListeners:Lorg/apache/commons/configuration2/event/EventListenerList;
       6: invokevirtual #68                 // Method copyEventListeners:(Lorg/apache/commons/configuration2/builder/BasicConfigurationBuilder;Lorg/apache/commons/configuration2/event/EventListenerList;)V
       9: aload_1
      10: getstatic     #49                 // Field org/apache/commons/configuration2/builder/ConfigurationBuilderEvent.ANY:Lorg/apache/commons/configuration2/event/EventType;
      13: aload_0
      14: getfield      #17                 // Field managedBuilderDelegationListener:Lorg/apache/commons/configuration2/event/EventListener;
      17: invokevirtual #44                 // Method org/apache/commons/configuration2/builder/FileBasedConfigurationBuilder.addEventListener:(Lorg/apache/commons/configuration2/event/EventType;Lorg/apache/commons/configuration2/event/EventListener;)V
      20: return

  private java.lang.String fetchFileName(org.apache.commons.configuration2.builder.combined.MultiFileBuilderParametersImpl);
    Code:
       0: aload_0
       1: getfield      #11                 // Field inInterpolation:Ljava/lang/ThreadLocal;
       4: invokevirtual #69                 // Method java/lang/ThreadLocal.get:()Ljava/lang/Object;
       7: checkcast     #70                 // class java/lang/Boolean
      10: astore_3
      11: aload_3
      12: ifnull        30
      15: aload_3
      16: invokevirtual #71                 // Method java/lang/Boolean.booleanValue:()Z
      19: ifeq          30
      22: aload_1
      23: invokevirtual #26                 // Method org/apache/commons/configuration2/builder/combined/MultiFileBuilderParametersImpl.getFilePattern:()Ljava/lang/String;
      26: astore_2
      27: goto          74
      30: aload_0
      31: getfield      #11                 // Field inInterpolation:Ljava/lang/ThreadLocal;
      34: getstatic     #72                 // Field java/lang/Boolean.TRUE:Ljava/lang/Boolean;
      37: invokevirtual #73                 // Method java/lang/ThreadLocal.set:(Ljava/lang/Object;)V
      40: aload_0
      41: aload_1
      42: invokevirtual #74                 // Method constructFileName:(Lorg/apache/commons/configuration2/builder/combined/MultiFileBuilderParametersImpl;)Ljava/lang/String;
      45: astore_2
      46: aload_0
      47: getfield      #11                 // Field inInterpolation:Ljava/lang/ThreadLocal;
      50: getstatic     #75                 // Field java/lang/Boolean.FALSE:Ljava/lang/Boolean;
      53: invokevirtual #73                 // Method java/lang/ThreadLocal.set:(Ljava/lang/Object;)V
      56: goto          74
      59: astore        4
      61: aload_0
      62: getfield      #11                 // Field inInterpolation:Ljava/lang/ThreadLocal;
      65: getstatic     #75                 // Field java/lang/Boolean.FALSE:Ljava/lang/Boolean;
      68: invokevirtual #73                 // Method java/lang/ThreadLocal.set:(Ljava/lang/Object;)V
      71: aload         4
      73: athrow
      74: aload_2
      75: areturn
    Exception table:
       from    to  target type
          40    46    59   any
          59    61    59   any

  private void handleManagedBuilderEvent(org.apache.commons.configuration2.builder.ConfigurationBuilderEvent);
    Code:
       0: getstatic     #76                 // Field org/apache/commons/configuration2/builder/ConfigurationBuilderEvent.RESET:Lorg/apache/commons/configuration2/event/EventType;
       3: aload_1
       4: invokevirtual #77                 // Method org/apache/commons/configuration2/builder/ConfigurationBuilderEvent.getEventType:()Lorg/apache/commons/configuration2/event/EventType;
       7: invokevirtual #78                 // Method java/lang/Object.equals:(Ljava/lang/Object;)Z
      10: ifeq          20
      13: aload_0
      14: invokevirtual #79                 // Method resetResult:()V
      17: goto          29
      20: aload_0
      21: aload_0
      22: aload_1
      23: invokespecial #80                 // Method createEventWithChangedSource:(Lorg/apache/commons/configuration2/builder/ConfigurationBuilderEvent;)Lorg/apache/commons/configuration2/builder/ConfigurationBuilderEvent;
      26: invokevirtual #81                 // Method fireBuilderEvent:(Lorg/apache/commons/configuration2/builder/ConfigurationBuilderEvent;)V
      29: return

  private org.apache.commons.configuration2.builder.ConfigurationBuilderEvent createEventWithChangedSource(org.apache.commons.configuration2.builder.ConfigurationBuilderEvent);
    Code:
       0: getstatic     #82                 // Field org/apache/commons/configuration2/builder/ConfigurationBuilderResultCreatedEvent.RESULT_CREATED:Lorg/apache/commons/configuration2/event/EventType;
       3: aload_1
       4: invokevirtual #77                 // Method org/apache/commons/configuration2/builder/ConfigurationBuilderEvent.getEventType:()Lorg/apache/commons/configuration2/event/EventType;
       7: invokevirtual #78                 // Method java/lang/Object.equals:(Ljava/lang/Object;)Z
      10: ifeq          32
      13: new           #83                 // class org/apache/commons/configuration2/builder/ConfigurationBuilderResultCreatedEvent
      16: dup
      17: aload_0
      18: getstatic     #82                 // Field org/apache/commons/configuration2/builder/ConfigurationBuilderResultCreatedEvent.RESULT_CREATED:Lorg/apache/commons/configuration2/event/EventType;
      21: aload_1
      22: checkcast     #83                 // class org/apache/commons/configuration2/builder/ConfigurationBuilderResultCreatedEvent
      25: invokevirtual #84                 // Method org/apache/commons/configuration2/builder/ConfigurationBuilderResultCreatedEvent.getConfiguration:()Lorg/apache/commons/configuration2/ImmutableConfiguration;
      28: invokespecial #85                 // Method org/apache/commons/configuration2/builder/ConfigurationBuilderResultCreatedEvent."<init>":(Lorg/apache/commons/configuration2/builder/ConfigurationBuilder;Lorg/apache/commons/configuration2/event/EventType;Lorg/apache/commons/configuration2/ImmutableConfiguration;)V
      31: areturn
      32: aload_1
      33: invokevirtual #77                 // Method org/apache/commons/configuration2/builder/ConfigurationBuilderEvent.getEventType:()Lorg/apache/commons/configuration2/event/EventType;
      36: astore_2
      37: new           #86                 // class org/apache/commons/configuration2/builder/ConfigurationBuilderEvent
      40: dup
      41: aload_0
      42: aload_2
      43: invokespecial #87                 // Method org/apache/commons/configuration2/builder/ConfigurationBuilderEvent."<init>":(Lorg/apache/commons/configuration2/builder/ConfigurationBuilder;Lorg/apache/commons/configuration2/event/EventType;)V
      46: areturn

  private static java.util.Map<java.lang.String, java.lang.Object> createManagedBuilderParameters(java.util.Map<java.lang.String, java.lang.Object>, org.apache.commons.configuration2.builder.combined.MultiFileBuilderParametersImpl);
    Code:
       0: new           #88                 // class java/util/HashMap
       3: dup
       4: aload_0
       5: invokespecial #89                 // Method java/util/HashMap."<init>":(Ljava/util/Map;)V
       8: astore_2
       9: aload_2
      10: ldc           #91                 // String interpolator
      12: invokeinterface #92,  2           // InterfaceMethod java/util/Map.remove:(Ljava/lang/Object;)Ljava/lang/Object;
      17: pop
      18: aload_1
      19: invokevirtual #93                 // Method org/apache/commons/configuration2/builder/combined/MultiFileBuilderParametersImpl.getManagedBuilderParameters:()Lorg/apache/commons/configuration2/builder/BuilderParameters;
      22: astore_3
      23: aload_3
      24: ifnull        49
      27: aload_3
      28: invokestatic  #94                 // Method org/apache/commons/configuration2/ConfigurationUtils.cloneIfPossible:(Ljava/lang/Object;)Ljava/lang/Object;
      31: checkcast     #95                 // class org/apache/commons/configuration2/builder/BuilderParameters
      34: astore        4
      36: aload_2
      37: aload         4
      39: invokeinterface #96,  1           // InterfaceMethod org/apache/commons/configuration2/builder/BuilderParameters.getParameters:()Ljava/util/Map;
      44: invokeinterface #97,  2           // InterfaceMethod java/util/Map.putAll:(Ljava/util/Map;)V
      49: aload_2
      50: areturn

  private static boolean isEventTypeForManagedBuilders(org.apache.commons.configuration2.event.EventType<?>);
    Code:
       0: aload_0
       1: getstatic     #49                 // Field org/apache/commons/configuration2/builder/ConfigurationBuilderEvent.ANY:Lorg/apache/commons/configuration2/event/EventType;
       4: invokestatic  #98                 // Method org/apache/commons/configuration2/event/EventType.isInstanceOf:(Lorg/apache/commons/configuration2/event/EventType;Lorg/apache/commons/configuration2/event/EventType;)Z
       7: ifne          14
      10: iconst_1
      11: goto          15
      14: iconst_0
      15: ireturn

  public org.apache.commons.configuration2.ImmutableConfiguration getConfiguration() throws org.apache.commons.configuration2.ex.ConfigurationException;
    Code:
       0: aload_0
       1: invokevirtual #99                 // Method getConfiguration:()Lorg/apache/commons/configuration2/FileBasedConfiguration;
       4: areturn

  public org.apache.commons.configuration2.builder.BasicConfigurationBuilder configure(org.apache.commons.configuration2.builder.BuilderParameters[]);
    Code:
       0: aload_0
       1: aload_1
       2: invokevirtual #100                // Method configure:([Lorg/apache/commons/configuration2/builder/BuilderParameters;)Lorg/apache/commons/configuration2/builder/combined/MultiFileConfigurationBuilder;
       5: areturn

  static void access$000(org.apache.commons.configuration2.builder.combined.MultiFileConfigurationBuilder, org.apache.commons.configuration2.builder.ConfigurationBuilderEvent);
    Code:
       0: aload_0
       1: aload_1
       2: invokespecial #1                  // Method handleManagedBuilderEvent:(Lorg/apache/commons/configuration2/builder/ConfigurationBuilderEvent;)V
       5: return
}
