Compiled from "Filters.java"
public final class org.jdom2.filter.Filters {
  private static final org.jdom2.filter.Filter<org.jdom2.Content> fcontent;

  private static final org.jdom2.filter.Filter<org.jdom2.Attribute> fattribute;

  private static final org.jdom2.filter.Filter<org.jdom2.Comment> fcomment;

  private static final org.jdom2.filter.Filter<org.jdom2.CDATA> fcdata;

  private static final org.jdom2.filter.Filter<org.jdom2.DocType> fdoctype;

  private static final org.jdom2.filter.Filter<org.jdom2.EntityRef> fentityref;

  private static final org.jdom2.filter.Filter<org.jdom2.ProcessingInstruction> fpi;

  private static final org.jdom2.filter.Filter<org.jdom2.Text> ftext;

  private static final org.jdom2.filter.Filter<org.jdom2.Text> ftextonly;

  private static final org.jdom2.filter.Filter<org.jdom2.Element> felement;

  private static final org.jdom2.filter.Filter<org.jdom2.Document> fdocument;

  private static final org.jdom2.filter.Filter<java.lang.Double> fdouble;

  private static final org.jdom2.filter.Filter<java.lang.Boolean> fboolean;

  private static final org.jdom2.filter.Filter<java.lang.String> fstring;

  private static final org.jdom2.filter.Filter<java.lang.Object> fpassthrough;

  private org.jdom2.filter.Filters();
    Code:
       0: aload_0
       1: invokespecial #1                  // Method java/lang/Object."<init>":()V
       4: return

  public static final org.jdom2.filter.Filter<org.jdom2.Content> content();
    Code:
       0: getstatic     #2                  // Field fcontent:Lorg/jdom2/filter/Filter;
       3: areturn

  public static final org.jdom2.filter.Filter<org.jdom2.Attribute> attribute();
    Code:
       0: getstatic     #3                  // Field fattribute:Lorg/jdom2/filter/Filter;
       3: areturn

  public static final org.jdom2.filter.Filter<org.jdom2.Attribute> attribute(java.lang.String);
    Code:
       0: new           #4                  // class org/jdom2/filter/AttributeFilter
       3: dup
       4: aload_0
       5: invokespecial #5                  // Method org/jdom2/filter/AttributeFilter."<init>":(Ljava/lang/String;)V
       8: areturn

  public static final org.jdom2.filter.Filter<org.jdom2.Attribute> attribute(java.lang.String, org.jdom2.Namespace);
    Code:
       0: new           #4                  // class org/jdom2/filter/AttributeFilter
       3: dup
       4: aload_0
       5: aload_1
       6: invokespecial #6                  // Method org/jdom2/filter/AttributeFilter."<init>":(Ljava/lang/String;Lorg/jdom2/Namespace;)V
       9: areturn

  public static final org.jdom2.filter.Filter<org.jdom2.Attribute> attribute(org.jdom2.Namespace);
    Code:
       0: new           #4                  // class org/jdom2/filter/AttributeFilter
       3: dup
       4: aload_0
       5: invokespecial #7                  // Method org/jdom2/filter/AttributeFilter."<init>":(Lorg/jdom2/Namespace;)V
       8: areturn

  public static final org.jdom2.filter.Filter<org.jdom2.Comment> comment();
    Code:
       0: getstatic     #8                  // Field fcomment:Lorg/jdom2/filter/Filter;
       3: areturn

  public static final org.jdom2.filter.Filter<org.jdom2.CDATA> cdata();
    Code:
       0: getstatic     #9                  // Field fcdata:Lorg/jdom2/filter/Filter;
       3: areturn

  public static final org.jdom2.filter.Filter<org.jdom2.DocType> doctype();
    Code:
       0: getstatic     #10                 // Field fdoctype:Lorg/jdom2/filter/Filter;
       3: areturn

  public static final org.jdom2.filter.Filter<org.jdom2.EntityRef> entityref();
    Code:
       0: getstatic     #11                 // Field fentityref:Lorg/jdom2/filter/Filter;
       3: areturn

  public static final org.jdom2.filter.Filter<org.jdom2.Element> element();
    Code:
       0: getstatic     #12                 // Field felement:Lorg/jdom2/filter/Filter;
       3: areturn

  public static final org.jdom2.filter.Filter<org.jdom2.Document> document();
    Code:
       0: getstatic     #13                 // Field fdocument:Lorg/jdom2/filter/Filter;
       3: areturn

  public static final org.jdom2.filter.Filter<org.jdom2.Element> element(java.lang.String);
    Code:
       0: new           #14                 // class org/jdom2/filter/ElementFilter
       3: dup
       4: aload_0
       5: getstatic     #15                 // Field org/jdom2/Namespace.NO_NAMESPACE:Lorg/jdom2/Namespace;
       8: invokespecial #16                 // Method org/jdom2/filter/ElementFilter."<init>":(Ljava/lang/String;Lorg/jdom2/Namespace;)V
      11: areturn

  public static final org.jdom2.filter.Filter<org.jdom2.Element> element(java.lang.String, org.jdom2.Namespace);
    Code:
       0: new           #14                 // class org/jdom2/filter/ElementFilter
       3: dup
       4: aload_0
       5: aload_1
       6: invokespecial #16                 // Method org/jdom2/filter/ElementFilter."<init>":(Ljava/lang/String;Lorg/jdom2/Namespace;)V
       9: areturn

  public static final org.jdom2.filter.Filter<org.jdom2.Element> element(org.jdom2.Namespace);
    Code:
       0: new           #14                 // class org/jdom2/filter/ElementFilter
       3: dup
       4: aconst_null
       5: aload_0
       6: invokespecial #16                 // Method org/jdom2/filter/ElementFilter."<init>":(Ljava/lang/String;Lorg/jdom2/Namespace;)V
       9: areturn

  public static final org.jdom2.filter.Filter<org.jdom2.ProcessingInstruction> processinginstruction();
    Code:
       0: getstatic     #17                 // Field fpi:Lorg/jdom2/filter/Filter;
       3: areturn

  public static final org.jdom2.filter.Filter<org.jdom2.Text> text();
    Code:
       0: getstatic     #18                 // Field ftext:Lorg/jdom2/filter/Filter;
       3: areturn

  public static final org.jdom2.filter.Filter<org.jdom2.Text> textOnly();
    Code:
       0: getstatic     #19                 // Field ftextonly:Lorg/jdom2/filter/Filter;
       3: areturn

  public static final org.jdom2.filter.Filter<java.lang.Boolean> fboolean();
    Code:
       0: getstatic     #20                 // Field fboolean:Lorg/jdom2/filter/Filter;
       3: areturn

  public static final org.jdom2.filter.Filter<java.lang.String> fstring();
    Code:
       0: getstatic     #21                 // Field fstring:Lorg/jdom2/filter/Filter;
       3: areturn

  public static final org.jdom2.filter.Filter<java.lang.Double> fdouble();
    Code:
       0: getstatic     #22                 // Field fdouble:Lorg/jdom2/filter/Filter;
       3: areturn

  public static final <F> org.jdom2.filter.Filter<F> fclass(java.lang.Class<F>);
    Code:
       0: new           #23                 // class org/jdom2/filter/ClassFilter
       3: dup
       4: aload_0
       5: invokespecial #24                 // Method org/jdom2/filter/ClassFilter."<init>":(Ljava/lang/Class;)V
       8: areturn

  public static final org.jdom2.filter.Filter<java.lang.Object> fpassthrough();
    Code:
       0: getstatic     #25                 // Field fpassthrough:Lorg/jdom2/filter/Filter;
       3: areturn

  static {};
    Code:
       0: new           #23                 // class org/jdom2/filter/ClassFilter
       3: dup
       4: ldc_w         #26                 // class org/jdom2/Content
       7: invokespecial #24                 // Method org/jdom2/filter/ClassFilter."<init>":(Ljava/lang/Class;)V
      10: putstatic     #2                  // Field fcontent:Lorg/jdom2/filter/Filter;
      13: new           #4                  // class org/jdom2/filter/AttributeFilter
      16: dup
      17: invokespecial #27                 // Method org/jdom2/filter/AttributeFilter."<init>":()V
      20: putstatic     #3                  // Field fattribute:Lorg/jdom2/filter/Filter;
      23: new           #23                 // class org/jdom2/filter/ClassFilter
      26: dup
      27: ldc_w         #28                 // class org/jdom2/Comment
      30: invokespecial #24                 // Method org/jdom2/filter/ClassFilter."<init>":(Ljava/lang/Class;)V
      33: putstatic     #8                  // Field fcomment:Lorg/jdom2/filter/Filter;
      36: new           #23                 // class org/jdom2/filter/ClassFilter
      39: dup
      40: ldc_w         #29                 // class org/jdom2/CDATA
      43: invokespecial #24                 // Method org/jdom2/filter/ClassFilter."<init>":(Ljava/lang/Class;)V
      46: putstatic     #9                  // Field fcdata:Lorg/jdom2/filter/Filter;
      49: new           #23                 // class org/jdom2/filter/ClassFilter
      52: dup
      53: ldc_w         #30                 // class org/jdom2/DocType
      56: invokespecial #24                 // Method org/jdom2/filter/ClassFilter."<init>":(Ljava/lang/Class;)V
      59: putstatic     #10                 // Field fdoctype:Lorg/jdom2/filter/Filter;
      62: new           #23                 // class org/jdom2/filter/ClassFilter
      65: dup
      66: ldc_w         #31                 // class org/jdom2/EntityRef
      69: invokespecial #24                 // Method org/jdom2/filter/ClassFilter."<init>":(Ljava/lang/Class;)V
      72: putstatic     #11                 // Field fentityref:Lorg/jdom2/filter/Filter;
      75: new           #23                 // class org/jdom2/filter/ClassFilter
      78: dup
      79: ldc_w         #32                 // class org/jdom2/ProcessingInstruction
      82: invokespecial #24                 // Method org/jdom2/filter/ClassFilter."<init>":(Ljava/lang/Class;)V
      85: putstatic     #17                 // Field fpi:Lorg/jdom2/filter/Filter;
      88: new           #23                 // class org/jdom2/filter/ClassFilter
      91: dup
      92: ldc_w         #33                 // class org/jdom2/Text
      95: invokespecial #24                 // Method org/jdom2/filter/ClassFilter."<init>":(Ljava/lang/Class;)V
      98: putstatic     #18                 // Field ftext:Lorg/jdom2/filter/Filter;
     101: new           #34                 // class org/jdom2/filter/TextOnlyFilter
     104: dup
     105: invokespecial #35                 // Method org/jdom2/filter/TextOnlyFilter."<init>":()V
     108: putstatic     #19                 // Field ftextonly:Lorg/jdom2/filter/Filter;
     111: new           #23                 // class org/jdom2/filter/ClassFilter
     114: dup
     115: ldc_w         #36                 // class org/jdom2/Element
     118: invokespecial #24                 // Method org/jdom2/filter/ClassFilter."<init>":(Ljava/lang/Class;)V
     121: putstatic     #12                 // Field felement:Lorg/jdom2/filter/Filter;
     124: new           #23                 // class org/jdom2/filter/ClassFilter
     127: dup
     128: ldc_w         #37                 // class org/jdom2/Document
     131: invokespecial #24                 // Method org/jdom2/filter/ClassFilter."<init>":(Ljava/lang/Class;)V
     134: putstatic     #13                 // Field fdocument:Lorg/jdom2/filter/Filter;
     137: new           #23                 // class org/jdom2/filter/ClassFilter
     140: dup
     141: ldc_w         #38                 // class java/lang/Double
     144: invokespecial #24                 // Method org/jdom2/filter/ClassFilter."<init>":(Ljava/lang/Class;)V
     147: putstatic     #22                 // Field fdouble:Lorg/jdom2/filter/Filter;
     150: new           #23                 // class org/jdom2/filter/ClassFilter
     153: dup
     154: ldc_w         #39                 // class java/lang/Boolean
     157: invokespecial #24                 // Method org/jdom2/filter/ClassFilter."<init>":(Ljava/lang/Class;)V
     160: putstatic     #20                 // Field fboolean:Lorg/jdom2/filter/Filter;
     163: new           #23                 // class org/jdom2/filter/ClassFilter
     166: dup
     167: ldc_w         #40                 // class java/lang/String
     170: invokespecial #24                 // Method org/jdom2/filter/ClassFilter."<init>":(Ljava/lang/Class;)V
     173: putstatic     #21                 // Field fstring:Lorg/jdom2/filter/Filter;
     176: new           #41                 // class org/jdom2/filter/PassThroughFilter
     179: dup
     180: invokespecial #42                 // Method org/jdom2/filter/PassThroughFilter."<init>":()V
     183: putstatic     #25                 // Field fpassthrough:Lorg/jdom2/filter/Filter;
     186: return
}
