Compiled from "ReplParser.java"
public final class org.aya.repl.ReplParser$ReplParsedLine extends java.lang.Record implements org.jline.reader.CompletingParsedLine {
  private final int wordCursor;

  private final java.util.List<java.lang.String> words;

  private final java.lang.String word;

  private final int wordIndex;

  private final java.lang.String line;

  private final int cursor;

  public org.aya.repl.ReplParser$ReplParsedLine(int, java.util.List<java.lang.String>, java.lang.String, int, java.lang.String, int);
    Code:
       0: aload_0
       1: invokespecial #1                  // Method java/lang/Record."<init>":()V
       4: aload_0
       5: iload_1
       6: putfield      #7                  // Field wordCursor:I
       9: aload_0
      10: aload_2
      11: putfield      #13                 // Field words:Ljava/util/List;
      14: aload_0
      15: aload_3
      16: putfield      #17                 // Field word:Ljava/lang/String;
      19: aload_0
      20: iload         4
      22: putfield      #21                 // Field wordIndex:I
      25: aload_0
      26: aload         5
      28: putfield      #24                 // Field line:Ljava/lang/String;
      31: aload_0
      32: iload         6
      34: putfield      #27                 // Field cursor:I
      37: return

  public java.lang.CharSequence escape(java.lang.CharSequence, boolean);
    Code:
       0: aload_1
       1: areturn

  public int rawWordCursor();
    Code:
       0: aload_0
       1: getfield      #7                  // Field wordCursor:I
       4: ireturn

  public int rawWordLength();
    Code:
       0: aload_0
       1: getfield      #17                 // Field word:Ljava/lang/String;
       4: invokevirtual #30                 // Method java/lang/String.length:()I
       7: ireturn

  public final java.lang.String toString();
    Code:
       0: aload_0
       1: invokedynamic #36,  0             // InvokeDynamic #0:toString:(Lorg/aya/repl/ReplParser$ReplParsedLine;)Ljava/lang/String;
       6: areturn

  public final int hashCode();
    Code:
       0: aload_0
       1: invokedynamic #40,  0             // InvokeDynamic #0:hashCode:(Lorg/aya/repl/ReplParser$ReplParsedLine;)I
       6: ireturn

  public final boolean equals(java.lang.Object);
    Code:
       0: aload_0
       1: aload_1
       2: invokedynamic #44,  0             // InvokeDynamic #0:equals:(Lorg/aya/repl/ReplParser$ReplParsedLine;Ljava/lang/Object;)Z
       7: ireturn

  public int wordCursor();
    Code:
       0: aload_0
       1: getfield      #7                  // Field wordCursor:I
       4: ireturn

  public java.util.List<java.lang.String> words();
    Code:
       0: aload_0
       1: getfield      #13                 // Field words:Ljava/util/List;
       4: areturn

  public java.lang.String word();
    Code:
       0: aload_0
       1: getfield      #17                 // Field word:Ljava/lang/String;
       4: areturn

  public int wordIndex();
    Code:
       0: aload_0
       1: getfield      #21                 // Field wordIndex:I
       4: ireturn

  public java.lang.String line();
    Code:
       0: aload_0
       1: getfield      #24                 // Field line:Ljava/lang/String;
       4: areturn

  public int cursor();
    Code:
       0: aload_0
       1: getfield      #27                 // Field cursor:I
       4: ireturn
}
