Compiled from "MatcherApplicationStrategy.java"
final class org.mockito.internal.invocation.MatcherApplicationStrategy$MatcherApplicationType extends java.lang.Enum<org.mockito.internal.invocation.MatcherApplicationStrategy$MatcherApplicationType> {
  public static final org.mockito.internal.invocation.MatcherApplicationStrategy$MatcherApplicationType ONE_MATCHER_PER_ARGUMENT;

  public static final org.mockito.internal.invocation.MatcherApplicationStrategy$MatcherApplicationType MATCH_EACH_VARARGS_WITH_LAST_MATCHER;

  public static final org.mockito.internal.invocation.MatcherApplicationStrategy$MatcherApplicationType ERROR_UNSUPPORTED_NUMBER_OF_MATCHERS;

  private static final org.mockito.internal.invocation.MatcherApplicationStrategy$MatcherApplicationType[] $VALUES;

  public static org.mockito.internal.invocation.MatcherApplicationStrategy$MatcherApplicationType[] values();
    Code:
       0: getstatic     #1                  // Field $VALUES:[Lorg/mockito/internal/invocation/MatcherApplicationStrategy$MatcherApplicationType;
       3: invokevirtual #2                  // Method "[Lorg/mockito/internal/invocation/MatcherApplicationStrategy$MatcherApplicationType;".clone:()Ljava/lang/Object;
       6: checkcast     #3                  // class "[Lorg/mockito/internal/invocation/MatcherApplicationStrategy$MatcherApplicationType;"
       9: areturn

  public static org.mockito.internal.invocation.MatcherApplicationStrategy$MatcherApplicationType valueOf(java.lang.String);
    Code:
       0: ldc_w         #4                  // class org/mockito/internal/invocation/MatcherApplicationStrategy$MatcherApplicationType
       3: aload_0
       4: invokestatic  #5                  // Method java/lang/Enum.valueOf:(Ljava/lang/Class;Ljava/lang/String;)Ljava/lang/Enum;
       7: checkcast     #4                  // class org/mockito/internal/invocation/MatcherApplicationStrategy$MatcherApplicationType
      10: areturn

  private org.mockito.internal.invocation.MatcherApplicationStrategy$MatcherApplicationType();
    Code:
       0: aload_0
       1: aload_1
       2: iload_2
       3: invokespecial #6                  // Method java/lang/Enum."<init>":(Ljava/lang/String;I)V
       6: return

  static {};
    Code:
       0: new           #4                  // class org/mockito/internal/invocation/MatcherApplicationStrategy$MatcherApplicationType
       3: dup
       4: ldc           #7                  // String ONE_MATCHER_PER_ARGUMENT
       6: iconst_0
       7: invokespecial #8                  // Method "<init>":(Ljava/lang/String;I)V
      10: putstatic     #9                  // Field ONE_MATCHER_PER_ARGUMENT:Lorg/mockito/internal/invocation/MatcherApplicationStrategy$MatcherApplicationType;
      13: new           #4                  // class org/mockito/internal/invocation/MatcherApplicationStrategy$MatcherApplicationType
      16: dup
      17: ldc           #10                 // String MATCH_EACH_VARARGS_WITH_LAST_MATCHER
      19: iconst_1
      20: invokespecial #8                  // Method "<init>":(Ljava/lang/String;I)V
      23: putstatic     #11                 // Field MATCH_EACH_VARARGS_WITH_LAST_MATCHER:Lorg/mockito/internal/invocation/MatcherApplicationStrategy$MatcherApplicationType;
      26: new           #4                  // class org/mockito/internal/invocation/MatcherApplicationStrategy$MatcherApplicationType
      29: dup
      30: ldc           #12                 // String ERROR_UNSUPPORTED_NUMBER_OF_MATCHERS
      32: iconst_2
      33: invokespecial #8                  // Method "<init>":(Ljava/lang/String;I)V
      36: putstatic     #13                 // Field ERROR_UNSUPPORTED_NUMBER_OF_MATCHERS:Lorg/mockito/internal/invocation/MatcherApplicationStrategy$MatcherApplicationType;
      39: iconst_3
      40: anewarray     #4                  // class org/mockito/internal/invocation/MatcherApplicationStrategy$MatcherApplicationType
      43: dup
      44: iconst_0
      45: getstatic     #9                  // Field ONE_MATCHER_PER_ARGUMENT:Lorg/mockito/internal/invocation/MatcherApplicationStrategy$MatcherApplicationType;
      48: aastore
      49: dup
      50: iconst_1
      51: getstatic     #11                 // Field MATCH_EACH_VARARGS_WITH_LAST_MATCHER:Lorg/mockito/internal/invocation/MatcherApplicationStrategy$MatcherApplicationType;
      54: aastore
      55: dup
      56: iconst_2
      57: getstatic     #13                 // Field ERROR_UNSUPPORTED_NUMBER_OF_MATCHERS:Lorg/mockito/internal/invocation/MatcherApplicationStrategy$MatcherApplicationType;
      60: aastore
      61: putstatic     #1                  // Field $VALUES:[Lorg/mockito/internal/invocation/MatcherApplicationStrategy$MatcherApplicationType;
      64: return
}
