Compiled from "SAXEventRecorder.java"
public class org.dom4j.io.SAXEventRecorder extends org.xml.sax.helpers.DefaultHandler implements org.xml.sax.ext.LexicalHandler,org.xml.sax.ext.DeclHandler,org.xml.sax.DTDHandler,java.io.Externalizable {
  public static final long serialVersionUID;

  private static final byte STRING;

  private static final byte OBJECT;

  private static final byte NULL;

  private java.util.List<org.dom4j.io.SAXEventRecorder$SAXEvent> events;

  private java.util.Map<org.dom4j.QName, java.util.List<java.lang.String>> prefixMappings;

  private static final java.lang.String XMLNS;

  private static final java.lang.String EMPTY_STRING;

  public org.dom4j.io.SAXEventRecorder();
    Code:
       0: aload_0
       1: invokespecial #1                  // Method org/xml/sax/helpers/DefaultHandler."<init>":()V
       4: aload_0
       5: new           #2                  // class java/util/ArrayList
       8: dup
       9: invokespecial #3                  // Method java/util/ArrayList."<init>":()V
      12: putfield      #4                  // Field events:Ljava/util/List;
      15: aload_0
      16: new           #5                  // class java/util/HashMap
      19: dup
      20: invokespecial #6                  // Method java/util/HashMap."<init>":()V
      23: putfield      #7                  // Field prefixMappings:Ljava/util/Map;
      26: return

  public void replay(org.xml.sax.ContentHandler) throws org.xml.sax.SAXException;
    Code:
       0: aload_0
       1: getfield      #4                  // Field events:Ljava/util/List;
       4: invokeinterface #8,  1            // InterfaceMethod java/util/List.iterator:()Ljava/util/Iterator;
       9: astore_2
      10: aload_2
      11: invokeinterface #9,  1            // InterfaceMethod java/util/Iterator.hasNext:()Z
      16: ifeq          754
      19: aload_2
      20: invokeinterface #10,  1           // InterfaceMethod java/util/Iterator.next:()Ljava/lang/Object;
      25: checkcast     #11                 // class org/dom4j/io/SAXEventRecorder$SAXEvent
      28: astore_3
      29: aload_3
      30: getfield      #12                 // Field org/dom4j/io/SAXEventRecorder$SAXEvent.event:B
      33: tableswitch   { // 1 to 19
                     1: 124
                     2: 149
                     3: 174
                     4: 191
                     5: 200
                     6: 209
                     7: 327
                     8: 360
                     9: 411
                    10: 447
                    11: 459
                    12: 479
                    13: 499
                    14: 511
                    15: 523
                    16: 577
                    17: 605
                    18: 657
                    19: 685
               default: 721
          }
     124: aload_1
     125: aload_3
     126: iconst_0
     127: invokevirtual #13                 // Method org/dom4j/io/SAXEventRecorder$SAXEvent.getParm:(I)Ljava/lang/Object;
     130: checkcast     #14                 // class java/lang/String
     133: aload_3
     134: iconst_1
     135: invokevirtual #13                 // Method org/dom4j/io/SAXEventRecorder$SAXEvent.getParm:(I)Ljava/lang/Object;
     138: checkcast     #14                 // class java/lang/String
     141: invokeinterface #15,  3           // InterfaceMethod org/xml/sax/ContentHandler.processingInstruction:(Ljava/lang/String;Ljava/lang/String;)V
     146: goto          751
     149: aload_1
     150: aload_3
     151: iconst_0
     152: invokevirtual #13                 // Method org/dom4j/io/SAXEventRecorder$SAXEvent.getParm:(I)Ljava/lang/Object;
     155: checkcast     #14                 // class java/lang/String
     158: aload_3
     159: iconst_1
     160: invokevirtual #13                 // Method org/dom4j/io/SAXEventRecorder$SAXEvent.getParm:(I)Ljava/lang/Object;
     163: checkcast     #14                 // class java/lang/String
     166: invokeinterface #16,  3           // InterfaceMethod org/xml/sax/ContentHandler.startPrefixMapping:(Ljava/lang/String;Ljava/lang/String;)V
     171: goto          751
     174: aload_1
     175: aload_3
     176: iconst_0
     177: invokevirtual #13                 // Method org/dom4j/io/SAXEventRecorder$SAXEvent.getParm:(I)Ljava/lang/Object;
     180: checkcast     #14                 // class java/lang/String
     183: invokeinterface #17,  2           // InterfaceMethod org/xml/sax/ContentHandler.endPrefixMapping:(Ljava/lang/String;)V
     188: goto          751
     191: aload_1
     192: invokeinterface #18,  1           // InterfaceMethod org/xml/sax/ContentHandler.startDocument:()V
     197: goto          751
     200: aload_1
     201: invokeinterface #19,  1           // InterfaceMethod org/xml/sax/ContentHandler.endDocument:()V
     206: goto          751
     209: new           #20                 // class org/xml/sax/helpers/AttributesImpl
     212: dup
     213: invokespecial #21                 // Method org/xml/sax/helpers/AttributesImpl."<init>":()V
     216: astore        4
     218: aload_3
     219: iconst_3
     220: invokevirtual #13                 // Method org/dom4j/io/SAXEventRecorder$SAXEvent.getParm:(I)Ljava/lang/Object;
     223: checkcast     #22                 // class java/util/List
     226: astore        5
     228: aload         5
     230: ifnull        292
     233: aload         5
     235: invokeinterface #8,  1            // InterfaceMethod java/util/List.iterator:()Ljava/util/Iterator;
     240: astore        6
     242: aload         6
     244: invokeinterface #9,  1            // InterfaceMethod java/util/Iterator.hasNext:()Z
     249: ifeq          292
     252: aload         6
     254: invokeinterface #10,  1           // InterfaceMethod java/util/Iterator.next:()Ljava/lang/Object;
     259: checkcast     #23                 // class "[Ljava/lang/String;"
     262: astore        7
     264: aload         4
     266: aload         7
     268: iconst_0
     269: aaload
     270: aload         7
     272: iconst_1
     273: aaload
     274: aload         7
     276: iconst_2
     277: aaload
     278: aload         7
     280: iconst_3
     281: aaload
     282: aload         7
     284: iconst_4
     285: aaload
     286: invokevirtual #24                 // Method org/xml/sax/helpers/AttributesImpl.addAttribute:(Ljava/lang/String;Ljava/lang/String;Ljava/lang/String;Ljava/lang/String;Ljava/lang/String;)V
     289: goto          242
     292: aload_1
     293: aload_3
     294: iconst_0
     295: invokevirtual #13                 // Method org/dom4j/io/SAXEventRecorder$SAXEvent.getParm:(I)Ljava/lang/Object;
     298: checkcast     #14                 // class java/lang/String
     301: aload_3
     302: iconst_1
     303: invokevirtual #13                 // Method org/dom4j/io/SAXEventRecorder$SAXEvent.getParm:(I)Ljava/lang/Object;
     306: checkcast     #14                 // class java/lang/String
     309: aload_3
     310: iconst_2
     311: invokevirtual #13                 // Method org/dom4j/io/SAXEventRecorder$SAXEvent.getParm:(I)Ljava/lang/Object;
     314: checkcast     #14                 // class java/lang/String
     317: aload         4
     319: invokeinterface #25,  5           // InterfaceMethod org/xml/sax/ContentHandler.startElement:(Ljava/lang/String;Ljava/lang/String;Ljava/lang/String;Lorg/xml/sax/Attributes;)V
     324: goto          751
     327: aload_1
     328: aload_3
     329: iconst_0
     330: invokevirtual #13                 // Method org/dom4j/io/SAXEventRecorder$SAXEvent.getParm:(I)Ljava/lang/Object;
     333: checkcast     #14                 // class java/lang/String
     336: aload_3
     337: iconst_1
     338: invokevirtual #13                 // Method org/dom4j/io/SAXEventRecorder$SAXEvent.getParm:(I)Ljava/lang/Object;
     341: checkcast     #14                 // class java/lang/String
     344: aload_3
     345: iconst_2
     346: invokevirtual #13                 // Method org/dom4j/io/SAXEventRecorder$SAXEvent.getParm:(I)Ljava/lang/Object;
     349: checkcast     #14                 // class java/lang/String
     352: invokeinterface #26,  4           // InterfaceMethod org/xml/sax/ContentHandler.endElement:(Ljava/lang/String;Ljava/lang/String;Ljava/lang/String;)V
     357: goto          751
     360: aload_3
     361: iconst_0
     362: invokevirtual #13                 // Method org/dom4j/io/SAXEventRecorder$SAXEvent.getParm:(I)Ljava/lang/Object;
     365: checkcast     #27                 // class "[C"
     368: astore        6
     370: aload_3
     371: iconst_1
     372: invokevirtual #13                 // Method org/dom4j/io/SAXEventRecorder$SAXEvent.getParm:(I)Ljava/lang/Object;
     375: checkcast     #28                 // class java/lang/Integer
     378: invokevirtual #29                 // Method java/lang/Integer.intValue:()I
     381: istore        7
     383: aload_3
     384: iconst_2
     385: invokevirtual #13                 // Method org/dom4j/io/SAXEventRecorder$SAXEvent.getParm:(I)Ljava/lang/Object;
     388: checkcast     #28                 // class java/lang/Integer
     391: invokevirtual #29                 // Method java/lang/Integer.intValue:()I
     394: istore        8
     396: aload_1
     397: aload         6
     399: iload         7
     401: iload         8
     403: invokeinterface #30,  4           // InterfaceMethod org/xml/sax/ContentHandler.characters:([CII)V
     408: goto          751
     411: aload_1
     412: checkcast     #31                 // class org/xml/sax/ext/LexicalHandler
     415: aload_3
     416: iconst_0
     417: invokevirtual #13                 // Method org/dom4j/io/SAXEventRecorder$SAXEvent.getParm:(I)Ljava/lang/Object;
     420: checkcast     #14                 // class java/lang/String
     423: aload_3
     424: iconst_1
     425: invokevirtual #13                 // Method org/dom4j/io/SAXEventRecorder$SAXEvent.getParm:(I)Ljava/lang/Object;
     428: checkcast     #14                 // class java/lang/String
     431: aload_3
     432: iconst_2
     433: invokevirtual #13                 // Method org/dom4j/io/SAXEventRecorder$SAXEvent.getParm:(I)Ljava/lang/Object;
     436: checkcast     #14                 // class java/lang/String
     439: invokeinterface #32,  4           // InterfaceMethod org/xml/sax/ext/LexicalHandler.startDTD:(Ljava/lang/String;Ljava/lang/String;Ljava/lang/String;)V
     444: goto          751
     447: aload_1
     448: checkcast     #31                 // class org/xml/sax/ext/LexicalHandler
     451: invokeinterface #33,  1           // InterfaceMethod org/xml/sax/ext/LexicalHandler.endDTD:()V
     456: goto          751
     459: aload_1
     460: checkcast     #31                 // class org/xml/sax/ext/LexicalHandler
     463: aload_3
     464: iconst_0
     465: invokevirtual #13                 // Method org/dom4j/io/SAXEventRecorder$SAXEvent.getParm:(I)Ljava/lang/Object;
     468: checkcast     #14                 // class java/lang/String
     471: invokeinterface #34,  2           // InterfaceMethod org/xml/sax/ext/LexicalHandler.startEntity:(Ljava/lang/String;)V
     476: goto          751
     479: aload_1
     480: checkcast     #31                 // class org/xml/sax/ext/LexicalHandler
     483: aload_3
     484: iconst_0
     485: invokevirtual #13                 // Method org/dom4j/io/SAXEventRecorder$SAXEvent.getParm:(I)Ljava/lang/Object;
     488: checkcast     #14                 // class java/lang/String
     491: invokeinterface #35,  2           // InterfaceMethod org/xml/sax/ext/LexicalHandler.endEntity:(Ljava/lang/String;)V
     496: goto          751
     499: aload_1
     500: checkcast     #31                 // class org/xml/sax/ext/LexicalHandler
     503: invokeinterface #36,  1           // InterfaceMethod org/xml/sax/ext/LexicalHandler.startCDATA:()V
     508: goto          751
     511: aload_1
     512: checkcast     #31                 // class org/xml/sax/ext/LexicalHandler
     515: invokeinterface #37,  1           // InterfaceMethod org/xml/sax/ext/LexicalHandler.endCDATA:()V
     520: goto          751
     523: aload_3
     524: iconst_0
     525: invokevirtual #13                 // Method org/dom4j/io/SAXEventRecorder$SAXEvent.getParm:(I)Ljava/lang/Object;
     528: checkcast     #27                 // class "[C"
     531: astore        9
     533: aload_3
     534: iconst_1
     535: invokevirtual #13                 // Method org/dom4j/io/SAXEventRecorder$SAXEvent.getParm:(I)Ljava/lang/Object;
     538: checkcast     #28                 // class java/lang/Integer
     541: invokevirtual #29                 // Method java/lang/Integer.intValue:()I
     544: istore        10
     546: aload_3
     547: iconst_2
     548: invokevirtual #13                 // Method org/dom4j/io/SAXEventRecorder$SAXEvent.getParm:(I)Ljava/lang/Object;
     551: checkcast     #28                 // class java/lang/Integer
     554: invokevirtual #29                 // Method java/lang/Integer.intValue:()I
     557: istore        11
     559: aload_1
     560: checkcast     #31                 // class org/xml/sax/ext/LexicalHandler
     563: aload         9
     565: iload         10
     567: iload         11
     569: invokeinterface #38,  4           // InterfaceMethod org/xml/sax/ext/LexicalHandler.comment:([CII)V
     574: goto          751
     577: aload_1
     578: checkcast     #39                 // class org/xml/sax/ext/DeclHandler
     581: aload_3
     582: iconst_0
     583: invokevirtual #13                 // Method org/dom4j/io/SAXEventRecorder$SAXEvent.getParm:(I)Ljava/lang/Object;
     586: checkcast     #14                 // class java/lang/String
     589: aload_3
     590: iconst_1
     591: invokevirtual #13                 // Method org/dom4j/io/SAXEventRecorder$SAXEvent.getParm:(I)Ljava/lang/Object;
     594: checkcast     #14                 // class java/lang/String
     597: invokeinterface #40,  3           // InterfaceMethod org/xml/sax/ext/DeclHandler.elementDecl:(Ljava/lang/String;Ljava/lang/String;)V
     602: goto          751
     605: aload_1
     606: checkcast     #39                 // class org/xml/sax/ext/DeclHandler
     609: aload_3
     610: iconst_0
     611: invokevirtual #13                 // Method org/dom4j/io/SAXEventRecorder$SAXEvent.getParm:(I)Ljava/lang/Object;
     614: checkcast     #14                 // class java/lang/String
     617: aload_3
     618: iconst_1
     619: invokevirtual #13                 // Method org/dom4j/io/SAXEventRecorder$SAXEvent.getParm:(I)Ljava/lang/Object;
     622: checkcast     #14                 // class java/lang/String
     625: aload_3
     626: iconst_2
     627: invokevirtual #13                 // Method org/dom4j/io/SAXEventRecorder$SAXEvent.getParm:(I)Ljava/lang/Object;
     630: checkcast     #14                 // class java/lang/String
     633: aload_3
     634: iconst_3
     635: invokevirtual #13                 // Method org/dom4j/io/SAXEventRecorder$SAXEvent.getParm:(I)Ljava/lang/Object;
     638: checkcast     #14                 // class java/lang/String
     641: aload_3
     642: iconst_4
     643: invokevirtual #13                 // Method org/dom4j/io/SAXEventRecorder$SAXEvent.getParm:(I)Ljava/lang/Object;
     646: checkcast     #14                 // class java/lang/String
     649: invokeinterface #41,  6           // InterfaceMethod org/xml/sax/ext/DeclHandler.attributeDecl:(Ljava/lang/String;Ljava/lang/String;Ljava/lang/String;Ljava/lang/String;Ljava/lang/String;)V
     654: goto          751
     657: aload_1
     658: checkcast     #39                 // class org/xml/sax/ext/DeclHandler
     661: aload_3
     662: iconst_0
     663: invokevirtual #13                 // Method org/dom4j/io/SAXEventRecorder$SAXEvent.getParm:(I)Ljava/lang/Object;
     666: checkcast     #14                 // class java/lang/String
     669: aload_3
     670: iconst_1
     671: invokevirtual #13                 // Method org/dom4j/io/SAXEventRecorder$SAXEvent.getParm:(I)Ljava/lang/Object;
     674: checkcast     #14                 // class java/lang/String
     677: invokeinterface #42,  3           // InterfaceMethod org/xml/sax/ext/DeclHandler.internalEntityDecl:(Ljava/lang/String;Ljava/lang/String;)V
     682: goto          751
     685: aload_1
     686: checkcast     #39                 // class org/xml/sax/ext/DeclHandler
     689: aload_3
     690: iconst_0
     691: invokevirtual #13                 // Method org/dom4j/io/SAXEventRecorder$SAXEvent.getParm:(I)Ljava/lang/Object;
     694: checkcast     #14                 // class java/lang/String
     697: aload_3
     698: iconst_1
     699: invokevirtual #13                 // Method org/dom4j/io/SAXEventRecorder$SAXEvent.getParm:(I)Ljava/lang/Object;
     702: checkcast     #14                 // class java/lang/String
     705: aload_3
     706: iconst_2
     707: invokevirtual #13                 // Method org/dom4j/io/SAXEventRecorder$SAXEvent.getParm:(I)Ljava/lang/Object;
     710: checkcast     #14                 // class java/lang/String
     713: invokeinterface #43,  4           // InterfaceMethod org/xml/sax/ext/DeclHandler.externalEntityDecl:(Ljava/lang/String;Ljava/lang/String;Ljava/lang/String;)V
     718: goto          751
     721: new           #44                 // class org/xml/sax/SAXException
     724: dup
     725: new           #45                 // class java/lang/StringBuilder
     728: dup
     729: invokespecial #46                 // Method java/lang/StringBuilder."<init>":()V
     732: ldc           #47                 // String Unrecognized event:
     734: invokevirtual #48                 // Method java/lang/StringBuilder.append:(Ljava/lang/String;)Ljava/lang/StringBuilder;
     737: aload_3
     738: getfield      #12                 // Field org/dom4j/io/SAXEventRecorder$SAXEvent.event:B
     741: invokevirtual #49                 // Method java/lang/StringBuilder.append:(I)Ljava/lang/StringBuilder;
     744: invokevirtual #50                 // Method java/lang/StringBuilder.toString:()Ljava/lang/String;
     747: invokespecial #51                 // Method org/xml/sax/SAXException."<init>":(Ljava/lang/String;)V
     750: athrow
     751: goto          10
     754: return

  public void processingInstruction(java.lang.String, java.lang.String) throws org.xml.sax.SAXException;
    Code:
       0: new           #11                 // class org/dom4j/io/SAXEventRecorder$SAXEvent
       3: dup
       4: iconst_1
       5: invokespecial #52                 // Method org/dom4j/io/SAXEventRecorder$SAXEvent."<init>":(B)V
       8: astore_3
       9: aload_3
      10: aload_1
      11: invokevirtual #53                 // Method org/dom4j/io/SAXEventRecorder$SAXEvent.addParm:(Ljava/lang/Object;)V
      14: aload_3
      15: aload_2
      16: invokevirtual #53                 // Method org/dom4j/io/SAXEventRecorder$SAXEvent.addParm:(Ljava/lang/Object;)V
      19: aload_0
      20: getfield      #4                  // Field events:Ljava/util/List;
      23: aload_3
      24: invokeinterface #54,  2           // InterfaceMethod java/util/List.add:(Ljava/lang/Object;)Z
      29: pop
      30: return

  public void startPrefixMapping(java.lang.String, java.lang.String) throws org.xml.sax.SAXException;
    Code:
       0: new           #11                 // class org/dom4j/io/SAXEventRecorder$SAXEvent
       3: dup
       4: iconst_2
       5: invokespecial #52                 // Method org/dom4j/io/SAXEventRecorder$SAXEvent."<init>":(B)V
       8: astore_3
       9: aload_3
      10: aload_1
      11: invokevirtual #53                 // Method org/dom4j/io/SAXEventRecorder$SAXEvent.addParm:(Ljava/lang/Object;)V
      14: aload_3
      15: aload_2
      16: invokevirtual #53                 // Method org/dom4j/io/SAXEventRecorder$SAXEvent.addParm:(Ljava/lang/Object;)V
      19: aload_0
      20: getfield      #4                  // Field events:Ljava/util/List;
      23: aload_3
      24: invokeinterface #54,  2           // InterfaceMethod java/util/List.add:(Ljava/lang/Object;)Z
      29: pop
      30: return

  public void endPrefixMapping(java.lang.String) throws org.xml.sax.SAXException;
    Code:
       0: new           #11                 // class org/dom4j/io/SAXEventRecorder$SAXEvent
       3: dup
       4: iconst_3
       5: invokespecial #52                 // Method org/dom4j/io/SAXEventRecorder$SAXEvent."<init>":(B)V
       8: astore_2
       9: aload_2
      10: aload_1
      11: invokevirtual #53                 // Method org/dom4j/io/SAXEventRecorder$SAXEvent.addParm:(Ljava/lang/Object;)V
      14: aload_0
      15: getfield      #4                  // Field events:Ljava/util/List;
      18: aload_2
      19: invokeinterface #54,  2           // InterfaceMethod java/util/List.add:(Ljava/lang/Object;)Z
      24: pop
      25: return

  public void startDocument() throws org.xml.sax.SAXException;
    Code:
       0: new           #11                 // class org/dom4j/io/SAXEventRecorder$SAXEvent
       3: dup
       4: iconst_4
       5: invokespecial #52                 // Method org/dom4j/io/SAXEventRecorder$SAXEvent."<init>":(B)V
       8: astore_1
       9: aload_0
      10: getfield      #4                  // Field events:Ljava/util/List;
      13: aload_1
      14: invokeinterface #54,  2           // InterfaceMethod java/util/List.add:(Ljava/lang/Object;)Z
      19: pop
      20: return

  public void endDocument() throws org.xml.sax.SAXException;
    Code:
       0: new           #11                 // class org/dom4j/io/SAXEventRecorder$SAXEvent
       3: dup
       4: iconst_5
       5: invokespecial #52                 // Method org/dom4j/io/SAXEventRecorder$SAXEvent."<init>":(B)V
       8: astore_1
       9: aload_0
      10: getfield      #4                  // Field events:Ljava/util/List;
      13: aload_1
      14: invokeinterface #54,  2           // InterfaceMethod java/util/List.add:(Ljava/lang/Object;)Z
      19: pop
      20: return

  public void startElement(java.lang.String, java.lang.String, java.lang.String, org.xml.sax.Attributes) throws org.xml.sax.SAXException;
    Code:
       0: new           #11                 // class org/dom4j/io/SAXEventRecorder$SAXEvent
       3: dup
       4: bipush        6
       6: invokespecial #52                 // Method org/dom4j/io/SAXEventRecorder$SAXEvent."<init>":(B)V
       9: astore        5
      11: aload         5
      13: aload_1
      14: invokevirtual #53                 // Method org/dom4j/io/SAXEventRecorder$SAXEvent.addParm:(Ljava/lang/Object;)V
      17: aload         5
      19: aload_2
      20: invokevirtual #53                 // Method org/dom4j/io/SAXEventRecorder$SAXEvent.addParm:(Ljava/lang/Object;)V
      23: aload         5
      25: aload_3
      26: invokevirtual #53                 // Method org/dom4j/io/SAXEventRecorder$SAXEvent.addParm:(Ljava/lang/Object;)V
      29: aload_1
      30: ifnull        50
      33: new           #55                 // class org/dom4j/QName
      36: dup
      37: aload_2
      38: aload_1
      39: invokestatic  #56                 // Method org/dom4j/Namespace.get:(Ljava/lang/String;)Lorg/dom4j/Namespace;
      42: invokespecial #57                 // Method org/dom4j/QName."<init>":(Ljava/lang/String;Lorg/dom4j/Namespace;)V
      45: astore        6
      47: goto          60
      50: new           #55                 // class org/dom4j/QName
      53: dup
      54: aload_2
      55: invokespecial #58                 // Method org/dom4j/QName."<init>":(Ljava/lang/String;)V
      58: astore        6
      60: aload         4
      62: ifnull        339
      65: aload         4
      67: invokeinterface #59,  1           // InterfaceMethod org/xml/sax/Attributes.getLength:()I
      72: ifle          339
      75: new           #2                  // class java/util/ArrayList
      78: dup
      79: aload         4
      81: invokeinterface #59,  1           // InterfaceMethod org/xml/sax/Attributes.getLength:()I
      86: invokespecial #60                 // Method java/util/ArrayList."<init>":(I)V
      89: astore        7
      91: iconst_0
      92: istore        9
      94: iload         9
      96: aload         4
      98: invokeinterface #59,  1           // InterfaceMethod org/xml/sax/Attributes.getLength:()I
     103: if_icmpge     332
     106: aload         4
     108: iload         9
     110: invokeinterface #61,  2           // InterfaceMethod org/xml/sax/Attributes.getLocalName:(I)Ljava/lang/String;
     115: astore        10
     117: aload         10
     119: ldc           #63                 // String xmlns
     121: invokevirtual #64                 // Method java/lang/String.startsWith:(Ljava/lang/String;)Z
     124: ifeq          252
     127: aload         10
     129: invokevirtual #65                 // Method java/lang/String.length:()I
     132: iconst_5
     133: if_icmple     148
     136: aload         10
     138: bipush        6
     140: invokevirtual #66                 // Method java/lang/String.substring:(I)Ljava/lang/String;
     143: astore        11
     145: goto          152
     148: ldc           #67                 // String
     150: astore        11
     152: new           #11                 // class org/dom4j/io/SAXEventRecorder$SAXEvent
     155: dup
     156: iconst_2
     157: invokespecial #52                 // Method org/dom4j/io/SAXEventRecorder$SAXEvent."<init>":(B)V
     160: astore        12
     162: aload         12
     164: aload         11
     166: invokevirtual #53                 // Method org/dom4j/io/SAXEventRecorder$SAXEvent.addParm:(Ljava/lang/Object;)V
     169: aload         12
     171: aload         4
     173: iload         9
     175: invokeinterface #68,  2           // InterfaceMethod org/xml/sax/Attributes.getValue:(I)Ljava/lang/String;
     180: invokevirtual #53                 // Method org/dom4j/io/SAXEventRecorder$SAXEvent.addParm:(Ljava/lang/Object;)V
     183: aload_0
     184: getfield      #4                  // Field events:Ljava/util/List;
     187: aload         12
     189: invokeinterface #54,  2           // InterfaceMethod java/util/List.add:(Ljava/lang/Object;)Z
     194: pop
     195: aload_0
     196: getfield      #7                  // Field prefixMappings:Ljava/util/Map;
     199: aload         6
     201: invokeinterface #69,  2           // InterfaceMethod java/util/Map.get:(Ljava/lang/Object;)Ljava/lang/Object;
     206: checkcast     #22                 // class java/util/List
     209: astore        13
     211: aload         13
     213: ifnonnull     239
     216: new           #2                  // class java/util/ArrayList
     219: dup
     220: invokespecial #3                  // Method java/util/ArrayList."<init>":()V
     223: astore        13
     225: aload_0
     226: getfield      #7                  // Field prefixMappings:Ljava/util/Map;
     229: aload         6
     231: aload         13
     233: invokeinterface #70,  3           // InterfaceMethod java/util/Map.put:(Ljava/lang/Object;Ljava/lang/Object;)Ljava/lang/Object;
     238: pop
     239: aload         13
     241: aload         11
     243: invokeinterface #54,  2           // InterfaceMethod java/util/List.add:(Ljava/lang/Object;)Z
     248: pop
     249: goto          326
     252: iconst_5
     253: anewarray     #14                 // class java/lang/String
     256: astore        8
     258: aload         8
     260: iconst_0
     261: aload         4
     263: iload         9
     265: invokeinterface #71,  2           // InterfaceMethod org/xml/sax/Attributes.getURI:(I)Ljava/lang/String;
     270: aastore
     271: aload         8
     273: iconst_1
     274: aload         10
     276: aastore
     277: aload         8
     279: iconst_2
     280: aload         4
     282: iload         9
     284: invokeinterface #72,  2           // InterfaceMethod org/xml/sax/Attributes.getQName:(I)Ljava/lang/String;
     289: aastore
     290: aload         8
     292: iconst_3
     293: aload         4
     295: iload         9
     297: invokeinterface #73,  2           // InterfaceMethod org/xml/sax/Attributes.getType:(I)Ljava/lang/String;
     302: aastore
     303: aload         8
     305: iconst_4
     306: aload         4
     308: iload         9
     310: invokeinterface #68,  2           // InterfaceMethod org/xml/sax/Attributes.getValue:(I)Ljava/lang/String;
     315: aastore
     316: aload         7
     318: aload         8
     320: invokeinterface #54,  2           // InterfaceMethod java/util/List.add:(Ljava/lang/Object;)Z
     325: pop
     326: iinc          9, 1
     329: goto          94
     332: aload         5
     334: aload         7
     336: invokevirtual #53                 // Method org/dom4j/io/SAXEventRecorder$SAXEvent.addParm:(Ljava/lang/Object;)V
     339: aload_0
     340: getfield      #4                  // Field events:Ljava/util/List;
     343: aload         5
     345: invokeinterface #54,  2           // InterfaceMethod java/util/List.add:(Ljava/lang/Object;)Z
     350: pop
     351: return

  public void endElement(java.lang.String, java.lang.String, java.lang.String) throws org.xml.sax.SAXException;
    Code:
       0: new           #11                 // class org/dom4j/io/SAXEventRecorder$SAXEvent
       3: dup
       4: bipush        7
       6: invokespecial #52                 // Method org/dom4j/io/SAXEventRecorder$SAXEvent."<init>":(B)V
       9: astore        4
      11: aload         4
      13: aload_1
      14: invokevirtual #53                 // Method org/dom4j/io/SAXEventRecorder$SAXEvent.addParm:(Ljava/lang/Object;)V
      17: aload         4
      19: aload_2
      20: invokevirtual #53                 // Method org/dom4j/io/SAXEventRecorder$SAXEvent.addParm:(Ljava/lang/Object;)V
      23: aload         4
      25: aload_3
      26: invokevirtual #53                 // Method org/dom4j/io/SAXEventRecorder$SAXEvent.addParm:(Ljava/lang/Object;)V
      29: aload_0
      30: getfield      #4                  // Field events:Ljava/util/List;
      33: aload         4
      35: invokeinterface #54,  2           // InterfaceMethod java/util/List.add:(Ljava/lang/Object;)Z
      40: pop
      41: aload_1
      42: ifnull        62
      45: new           #55                 // class org/dom4j/QName
      48: dup
      49: aload_2
      50: aload_1
      51: invokestatic  #56                 // Method org/dom4j/Namespace.get:(Ljava/lang/String;)Lorg/dom4j/Namespace;
      54: invokespecial #57                 // Method org/dom4j/QName."<init>":(Ljava/lang/String;Lorg/dom4j/Namespace;)V
      57: astore        5
      59: goto          72
      62: new           #55                 // class org/dom4j/QName
      65: dup
      66: aload_2
      67: invokespecial #58                 // Method org/dom4j/QName."<init>":(Ljava/lang/String;)V
      70: astore        5
      72: aload_0
      73: getfield      #7                  // Field prefixMappings:Ljava/util/Map;
      76: aload         5
      78: invokeinterface #69,  2           // InterfaceMethod java/util/Map.get:(Ljava/lang/Object;)Ljava/lang/Object;
      83: checkcast     #22                 // class java/util/List
      86: astore        6
      88: aload         6
      90: ifnull        156
      93: aload         6
      95: invokeinterface #8,  1            // InterfaceMethod java/util/List.iterator:()Ljava/util/Iterator;
     100: astore        7
     102: aload         7
     104: invokeinterface #9,  1            // InterfaceMethod java/util/Iterator.hasNext:()Z
     109: ifeq          156
     112: aload         7
     114: invokeinterface #10,  1           // InterfaceMethod java/util/Iterator.next:()Ljava/lang/Object;
     119: checkcast     #14                 // class java/lang/String
     122: astore        8
     124: new           #11                 // class org/dom4j/io/SAXEventRecorder$SAXEvent
     127: dup
     128: iconst_3
     129: invokespecial #52                 // Method org/dom4j/io/SAXEventRecorder$SAXEvent."<init>":(B)V
     132: astore        9
     134: aload         9
     136: aload         8
     138: invokevirtual #53                 // Method org/dom4j/io/SAXEventRecorder$SAXEvent.addParm:(Ljava/lang/Object;)V
     141: aload_0
     142: getfield      #4                  // Field events:Ljava/util/List;
     145: aload         9
     147: invokeinterface #54,  2           // InterfaceMethod java/util/List.add:(Ljava/lang/Object;)Z
     152: pop
     153: goto          102
     156: return

  public void characters(char[], int, int) throws org.xml.sax.SAXException;
    Code:
       0: new           #11                 // class org/dom4j/io/SAXEventRecorder$SAXEvent
       3: dup
       4: bipush        8
       6: invokespecial #52                 // Method org/dom4j/io/SAXEventRecorder$SAXEvent."<init>":(B)V
       9: astore        4
      11: aload         4
      13: aload_1
      14: invokevirtual #53                 // Method org/dom4j/io/SAXEventRecorder$SAXEvent.addParm:(Ljava/lang/Object;)V
      17: aload         4
      19: iload_2
      20: invokestatic  #74                 // Method java/lang/Integer.valueOf:(I)Ljava/lang/Integer;
      23: invokevirtual #53                 // Method org/dom4j/io/SAXEventRecorder$SAXEvent.addParm:(Ljava/lang/Object;)V
      26: aload         4
      28: iload_3
      29: invokestatic  #74                 // Method java/lang/Integer.valueOf:(I)Ljava/lang/Integer;
      32: invokevirtual #53                 // Method org/dom4j/io/SAXEventRecorder$SAXEvent.addParm:(Ljava/lang/Object;)V
      35: aload_0
      36: getfield      #4                  // Field events:Ljava/util/List;
      39: aload         4
      41: invokeinterface #54,  2           // InterfaceMethod java/util/List.add:(Ljava/lang/Object;)Z
      46: pop
      47: return

  public void startDTD(java.lang.String, java.lang.String, java.lang.String) throws org.xml.sax.SAXException;
    Code:
       0: new           #11                 // class org/dom4j/io/SAXEventRecorder$SAXEvent
       3: dup
       4: bipush        9
       6: invokespecial #52                 // Method org/dom4j/io/SAXEventRecorder$SAXEvent."<init>":(B)V
       9: astore        4
      11: aload         4
      13: aload_1
      14: invokevirtual #53                 // Method org/dom4j/io/SAXEventRecorder$SAXEvent.addParm:(Ljava/lang/Object;)V
      17: aload         4
      19: aload_2
      20: invokevirtual #53                 // Method org/dom4j/io/SAXEventRecorder$SAXEvent.addParm:(Ljava/lang/Object;)V
      23: aload         4
      25: aload_3
      26: invokevirtual #53                 // Method org/dom4j/io/SAXEventRecorder$SAXEvent.addParm:(Ljava/lang/Object;)V
      29: aload_0
      30: getfield      #4                  // Field events:Ljava/util/List;
      33: aload         4
      35: invokeinterface #54,  2           // InterfaceMethod java/util/List.add:(Ljava/lang/Object;)Z
      40: pop
      41: return

  public void endDTD() throws org.xml.sax.SAXException;
    Code:
       0: new           #11                 // class org/dom4j/io/SAXEventRecorder$SAXEvent
       3: dup
       4: bipush        10
       6: invokespecial #52                 // Method org/dom4j/io/SAXEventRecorder$SAXEvent."<init>":(B)V
       9: astore_1
      10: aload_0
      11: getfield      #4                  // Field events:Ljava/util/List;
      14: aload_1
      15: invokeinterface #54,  2           // InterfaceMethod java/util/List.add:(Ljava/lang/Object;)Z
      20: pop
      21: return

  public void startEntity(java.lang.String) throws org.xml.sax.SAXException;
    Code:
       0: new           #11                 // class org/dom4j/io/SAXEventRecorder$SAXEvent
       3: dup
       4: bipush        11
       6: invokespecial #52                 // Method org/dom4j/io/SAXEventRecorder$SAXEvent."<init>":(B)V
       9: astore_2
      10: aload_2
      11: aload_1
      12: invokevirtual #53                 // Method org/dom4j/io/SAXEventRecorder$SAXEvent.addParm:(Ljava/lang/Object;)V
      15: aload_0
      16: getfield      #4                  // Field events:Ljava/util/List;
      19: aload_2
      20: invokeinterface #54,  2           // InterfaceMethod java/util/List.add:(Ljava/lang/Object;)Z
      25: pop
      26: return

  public void endEntity(java.lang.String) throws org.xml.sax.SAXException;
    Code:
       0: new           #11                 // class org/dom4j/io/SAXEventRecorder$SAXEvent
       3: dup
       4: bipush        12
       6: invokespecial #52                 // Method org/dom4j/io/SAXEventRecorder$SAXEvent."<init>":(B)V
       9: astore_2
      10: aload_2
      11: aload_1
      12: invokevirtual #53                 // Method org/dom4j/io/SAXEventRecorder$SAXEvent.addParm:(Ljava/lang/Object;)V
      15: aload_0
      16: getfield      #4                  // Field events:Ljava/util/List;
      19: aload_2
      20: invokeinterface #54,  2           // InterfaceMethod java/util/List.add:(Ljava/lang/Object;)Z
      25: pop
      26: return

  public void startCDATA() throws org.xml.sax.SAXException;
    Code:
       0: new           #11                 // class org/dom4j/io/SAXEventRecorder$SAXEvent
       3: dup
       4: bipush        13
       6: invokespecial #52                 // Method org/dom4j/io/SAXEventRecorder$SAXEvent."<init>":(B)V
       9: astore_1
      10: aload_0
      11: getfield      #4                  // Field events:Ljava/util/List;
      14: aload_1
      15: invokeinterface #54,  2           // InterfaceMethod java/util/List.add:(Ljava/lang/Object;)Z
      20: pop
      21: return

  public void endCDATA() throws org.xml.sax.SAXException;
    Code:
       0: new           #11                 // class org/dom4j/io/SAXEventRecorder$SAXEvent
       3: dup
       4: bipush        14
       6: invokespecial #52                 // Method org/dom4j/io/SAXEventRecorder$SAXEvent."<init>":(B)V
       9: astore_1
      10: aload_0
      11: getfield      #4                  // Field events:Ljava/util/List;
      14: aload_1
      15: invokeinterface #54,  2           // InterfaceMethod java/util/List.add:(Ljava/lang/Object;)Z
      20: pop
      21: return

  public void comment(char[], int, int) throws org.xml.sax.SAXException;
    Code:
       0: new           #11                 // class org/dom4j/io/SAXEventRecorder$SAXEvent
       3: dup
       4: bipush        15
       6: invokespecial #52                 // Method org/dom4j/io/SAXEventRecorder$SAXEvent."<init>":(B)V
       9: astore        4
      11: aload         4
      13: aload_1
      14: invokevirtual #53                 // Method org/dom4j/io/SAXEventRecorder$SAXEvent.addParm:(Ljava/lang/Object;)V
      17: aload         4
      19: iload_2
      20: invokestatic  #74                 // Method java/lang/Integer.valueOf:(I)Ljava/lang/Integer;
      23: invokevirtual #53                 // Method org/dom4j/io/SAXEventRecorder$SAXEvent.addParm:(Ljava/lang/Object;)V
      26: aload         4
      28: iload_3
      29: invokestatic  #74                 // Method java/lang/Integer.valueOf:(I)Ljava/lang/Integer;
      32: invokevirtual #53                 // Method org/dom4j/io/SAXEventRecorder$SAXEvent.addParm:(Ljava/lang/Object;)V
      35: aload_0
      36: getfield      #4                  // Field events:Ljava/util/List;
      39: aload         4
      41: invokeinterface #54,  2           // InterfaceMethod java/util/List.add:(Ljava/lang/Object;)Z
      46: pop
      47: return

  public void elementDecl(java.lang.String, java.lang.String) throws org.xml.sax.SAXException;
    Code:
       0: new           #11                 // class org/dom4j/io/SAXEventRecorder$SAXEvent
       3: dup
       4: bipush        16
       6: invokespecial #52                 // Method org/dom4j/io/SAXEventRecorder$SAXEvent."<init>":(B)V
       9: astore_3
      10: aload_3
      11: aload_1
      12: invokevirtual #53                 // Method org/dom4j/io/SAXEventRecorder$SAXEvent.addParm:(Ljava/lang/Object;)V
      15: aload_3
      16: aload_2
      17: invokevirtual #53                 // Method org/dom4j/io/SAXEventRecorder$SAXEvent.addParm:(Ljava/lang/Object;)V
      20: aload_0
      21: getfield      #4                  // Field events:Ljava/util/List;
      24: aload_3
      25: invokeinterface #54,  2           // InterfaceMethod java/util/List.add:(Ljava/lang/Object;)Z
      30: pop
      31: return

  public void attributeDecl(java.lang.String, java.lang.String, java.lang.String, java.lang.String, java.lang.String) throws org.xml.sax.SAXException;
    Code:
       0: new           #11                 // class org/dom4j/io/SAXEventRecorder$SAXEvent
       3: dup
       4: bipush        17
       6: invokespecial #52                 // Method org/dom4j/io/SAXEventRecorder$SAXEvent."<init>":(B)V
       9: astore        6
      11: aload         6
      13: aload_1
      14: invokevirtual #53                 // Method org/dom4j/io/SAXEventRecorder$SAXEvent.addParm:(Ljava/lang/Object;)V
      17: aload         6
      19: aload_2
      20: invokevirtual #53                 // Method org/dom4j/io/SAXEventRecorder$SAXEvent.addParm:(Ljava/lang/Object;)V
      23: aload         6
      25: aload_3
      26: invokevirtual #53                 // Method org/dom4j/io/SAXEventRecorder$SAXEvent.addParm:(Ljava/lang/Object;)V
      29: aload         6
      31: aload         4
      33: invokevirtual #53                 // Method org/dom4j/io/SAXEventRecorder$SAXEvent.addParm:(Ljava/lang/Object;)V
      36: aload         6
      38: aload         5
      40: invokevirtual #53                 // Method org/dom4j/io/SAXEventRecorder$SAXEvent.addParm:(Ljava/lang/Object;)V
      43: aload_0
      44: getfield      #4                  // Field events:Ljava/util/List;
      47: aload         6
      49: invokeinterface #54,  2           // InterfaceMethod java/util/List.add:(Ljava/lang/Object;)Z
      54: pop
      55: return

  public void internalEntityDecl(java.lang.String, java.lang.String) throws org.xml.sax.SAXException;
    Code:
       0: new           #11                 // class org/dom4j/io/SAXEventRecorder$SAXEvent
       3: dup
       4: bipush        18
       6: invokespecial #52                 // Method org/dom4j/io/SAXEventRecorder$SAXEvent."<init>":(B)V
       9: astore_3
      10: aload_3
      11: aload_1
      12: invokevirtual #53                 // Method org/dom4j/io/SAXEventRecorder$SAXEvent.addParm:(Ljava/lang/Object;)V
      15: aload_3
      16: aload_2
      17: invokevirtual #53                 // Method org/dom4j/io/SAXEventRecorder$SAXEvent.addParm:(Ljava/lang/Object;)V
      20: aload_0
      21: getfield      #4                  // Field events:Ljava/util/List;
      24: aload_3
      25: invokeinterface #54,  2           // InterfaceMethod java/util/List.add:(Ljava/lang/Object;)Z
      30: pop
      31: return

  public void externalEntityDecl(java.lang.String, java.lang.String, java.lang.String) throws org.xml.sax.SAXException;
    Code:
       0: new           #11                 // class org/dom4j/io/SAXEventRecorder$SAXEvent
       3: dup
       4: bipush        19
       6: invokespecial #52                 // Method org/dom4j/io/SAXEventRecorder$SAXEvent."<init>":(B)V
       9: astore        4
      11: aload         4
      13: aload_1
      14: invokevirtual #53                 // Method org/dom4j/io/SAXEventRecorder$SAXEvent.addParm:(Ljava/lang/Object;)V
      17: aload         4
      19: aload_2
      20: invokevirtual #53                 // Method org/dom4j/io/SAXEventRecorder$SAXEvent.addParm:(Ljava/lang/Object;)V
      23: aload         4
      25: aload_3
      26: invokevirtual #53                 // Method org/dom4j/io/SAXEventRecorder$SAXEvent.addParm:(Ljava/lang/Object;)V
      29: aload_0
      30: getfield      #4                  // Field events:Ljava/util/List;
      33: aload         4
      35: invokeinterface #54,  2           // InterfaceMethod java/util/List.add:(Ljava/lang/Object;)Z
      40: pop
      41: return

  public void writeExternal(java.io.ObjectOutput) throws java.io.IOException;
    Code:
       0: aload_0
       1: getfield      #4                  // Field events:Ljava/util/List;
       4: ifnonnull     17
       7: aload_1
       8: iconst_2
       9: invokeinterface #75,  2           // InterfaceMethod java/io/ObjectOutput.writeByte:(I)V
      14: goto          34
      17: aload_1
      18: iconst_1
      19: invokeinterface #75,  2           // InterfaceMethod java/io/ObjectOutput.writeByte:(I)V
      24: aload_1
      25: aload_0
      26: getfield      #4                  // Field events:Ljava/util/List;
      29: invokeinterface #76,  2           // InterfaceMethod java/io/ObjectOutput.writeObject:(Ljava/lang/Object;)V
      34: return

  public void readExternal(java.io.ObjectInput) throws java.lang.ClassNotFoundException, java.io.IOException;
    Code:
       0: aload_1
       1: invokeinterface #77,  1           // InterfaceMethod java/io/ObjectInput.readByte:()B
       6: iconst_2
       7: if_icmpeq     23
      10: aload_0
      11: aload_1
      12: invokeinterface #78,  1           // InterfaceMethod java/io/ObjectInput.readObject:()Ljava/lang/Object;
      17: checkcast     #22                 // class java/util/List
      20: putfield      #4                  // Field events:Ljava/util/List;
      23: return
}
