Compiled from "STAXEventWriter.java"
class org.dom4j.io.STAXEventWriter$AttributeIterator implements java.util.Iterator<javax.xml.stream.events.Attribute> {
  private java.util.Iterator<org.dom4j.Attribute> iter;

  final org.dom4j.io.STAXEventWriter this$0;

  public org.dom4j.io.STAXEventWriter$AttributeIterator(java.util.Iterator<org.dom4j.Attribute>);
    Code:
       0: aload_0
       1: aload_1
       2: putfield      #1                  // Field this$0:Lorg/dom4j/io/STAXEventWriter;
       5: aload_0
       6: invokespecial #2                  // Method java/lang/Object."<init>":()V
       9: aload_0
      10: aload_2
      11: putfield      #3                  // Field iter:Ljava/util/Iterator;
      14: return

  public boolean hasNext();
    Code:
       0: aload_0
       1: getfield      #3                  // Field iter:Ljava/util/Iterator;
       4: invokeinterface #4,  1            // InterfaceMethod java/util/Iterator.hasNext:()Z
       9: ireturn

  public javax.xml.stream.events.Attribute next();
    Code:
       0: aload_0
       1: getfield      #3                  // Field iter:Ljava/util/Iterator;
       4: invokeinterface #5,  1            // InterfaceMethod java/util/Iterator.next:()Ljava/lang/Object;
       9: checkcast     #6                  // class org/dom4j/Attribute
      12: astore_1
      13: aload_0
      14: getfield      #1                  // Field this$0:Lorg/dom4j/io/STAXEventWriter;
      17: aload_1
      18: invokeinterface #7,  1            // InterfaceMethod org/dom4j/Attribute.getQName:()Lorg/dom4j/QName;
      23: invokevirtual #8                  // Method org/dom4j/io/STAXEventWriter.createQName:(Lorg/dom4j/QName;)Ljavax/xml/namespace/QName;
      26: astore_2
      27: aload_1
      28: invokeinterface #9,  1            // InterfaceMethod org/dom4j/Attribute.getValue:()Ljava/lang/String;
      33: astore_3
      34: aload_0
      35: getfield      #1                  // Field this$0:Lorg/dom4j/io/STAXEventWriter;
      38: invokestatic  #10                 // Method org/dom4j/io/STAXEventWriter.access$000:(Lorg/dom4j/io/STAXEventWriter;)Ljavax/xml/stream/XMLEventFactory;
      41: aload_2
      42: aload_3
      43: invokevirtual #11                 // Method javax/xml/stream/XMLEventFactory.createAttribute:(Ljavax/xml/namespace/QName;Ljava/lang/String;)Ljavax/xml/stream/events/Attribute;
      46: areturn

  public void remove();
    Code:
       0: new           #12                 // class java/lang/UnsupportedOperationException
       3: dup
       4: invokespecial #13                 // Method java/lang/UnsupportedOperationException."<init>":()V
       7: athrow

  public java.lang.Object next();
    Code:
       0: aload_0
       1: invokevirtual #14                 // Method next:()Ljavax/xml/stream/events/Attribute;
       4: areturn
}
