Compiled from "XPPReader.java"
public class org.dom4j.io.XPPReader {
  private org.dom4j.DocumentFactory factory;

  private org.gjt.xpp.XmlPullParser xppParser;

  private org.gjt.xpp.XmlPullParserFactory xppFactory;

  private org.dom4j.io.DispatchHandler dispatchHandler;

  public org.dom4j.io.XPPReader();
    Code:
       0: aload_0
       1: invokespecial #1                  // Method java/lang/Object."<init>":()V
       4: return

  public org.dom4j.io.XPPReader(org.dom4j.DocumentFactory);
    Code:
       0: aload_0
       1: invokespecial #1                  // Method java/lang/Object."<init>":()V
       4: aload_0
       5: aload_1
       6: putfield      #2                  // Field factory:Lorg/dom4j/DocumentFactory;
       9: return

  public org.dom4j.Document read(java.io.File) throws org.dom4j.DocumentException, java.io.IOException, org.gjt.xpp.XmlPullParserException;
    Code:
       0: aload_1
       1: invokevirtual #3                  // Method java/io/File.getAbsolutePath:()Ljava/lang/String;
       4: astore_2
       5: aload_0
       6: new           #4                  // class java/io/BufferedReader
       9: dup
      10: new           #5                  // class java/io/FileReader
      13: dup
      14: aload_1
      15: invokespecial #6                  // Method java/io/FileReader."<init>":(Ljava/io/File;)V
      18: invokespecial #7                  // Method java/io/BufferedReader."<init>":(Ljava/io/Reader;)V
      21: aload_2
      22: invokevirtual #8                  // Method read:(Ljava/io/Reader;Ljava/lang/String;)Lorg/dom4j/Document;
      25: areturn

  public org.dom4j.Document read(java.net.URL) throws org.dom4j.DocumentException, java.io.IOException, org.gjt.xpp.XmlPullParserException;
    Code:
       0: aload_1
       1: invokevirtual #9                  // Method java/net/URL.toExternalForm:()Ljava/lang/String;
       4: astore_2
       5: aload_0
       6: aload_0
       7: aload_1
       8: invokevirtual #10                 // Method java/net/URL.openStream:()Ljava/io/InputStream;
      11: invokevirtual #11                 // Method createReader:(Ljava/io/InputStream;)Ljava/io/Reader;
      14: aload_2
      15: invokevirtual #8                  // Method read:(Ljava/io/Reader;Ljava/lang/String;)Lorg/dom4j/Document;
      18: areturn

  public org.dom4j.Document read(java.lang.String) throws org.dom4j.DocumentException, java.io.IOException, org.gjt.xpp.XmlPullParserException;
    Code:
       0: aload_1
       1: bipush        58
       3: invokevirtual #12                 // Method java/lang/String.indexOf:(I)I
       6: iflt          22
       9: aload_0
      10: new           #13                 // class java/net/URL
      13: dup
      14: aload_1
      15: invokespecial #14                 // Method java/net/URL."<init>":(Ljava/lang/String;)V
      18: invokevirtual #15                 // Method read:(Ljava/net/URL;)Lorg/dom4j/Document;
      21: areturn
      22: aload_0
      23: new           #16                 // class java/io/File
      26: dup
      27: aload_1
      28: invokespecial #17                 // Method java/io/File."<init>":(Ljava/lang/String;)V
      31: invokevirtual #18                 // Method read:(Ljava/io/File;)Lorg/dom4j/Document;
      34: areturn

  public org.dom4j.Document read(java.io.InputStream) throws org.dom4j.DocumentException, java.io.IOException, org.gjt.xpp.XmlPullParserException;
    Code:
       0: aload_0
       1: aload_0
       2: aload_1
       3: invokevirtual #11                 // Method createReader:(Ljava/io/InputStream;)Ljava/io/Reader;
       6: invokevirtual #19                 // Method read:(Ljava/io/Reader;)Lorg/dom4j/Document;
       9: areturn

  public org.dom4j.Document read(java.io.Reader) throws org.dom4j.DocumentException, java.io.IOException, org.gjt.xpp.XmlPullParserException;
    Code:
       0: aload_0
       1: invokevirtual #20                 // Method getXPPParser:()Lorg/gjt/xpp/XmlPullParser;
       4: aload_1
       5: invokeinterface #21,  2           // InterfaceMethod org/gjt/xpp/XmlPullParser.setInput:(Ljava/io/Reader;)V
      10: aload_0
      11: invokevirtual #22                 // Method parseDocument:()Lorg/dom4j/Document;
      14: areturn

  public org.dom4j.Document read(char[]) throws org.dom4j.DocumentException, java.io.IOException, org.gjt.xpp.XmlPullParserException;
    Code:
       0: aload_0
       1: invokevirtual #20                 // Method getXPPParser:()Lorg/gjt/xpp/XmlPullParser;
       4: aload_1
       5: invokeinterface #23,  2           // InterfaceMethod org/gjt/xpp/XmlPullParser.setInput:([C)V
      10: aload_0
      11: invokevirtual #22                 // Method parseDocument:()Lorg/dom4j/Document;
      14: areturn

  public org.dom4j.Document read(java.io.InputStream, java.lang.String) throws org.dom4j.DocumentException, java.io.IOException, org.gjt.xpp.XmlPullParserException;
    Code:
       0: aload_0
       1: aload_0
       2: aload_1
       3: invokevirtual #11                 // Method createReader:(Ljava/io/InputStream;)Ljava/io/Reader;
       6: aload_2
       7: invokevirtual #8                  // Method read:(Ljava/io/Reader;Ljava/lang/String;)Lorg/dom4j/Document;
      10: areturn

  public org.dom4j.Document read(java.io.Reader, java.lang.String) throws org.dom4j.DocumentException, java.io.IOException, org.gjt.xpp.XmlPullParserException;
    Code:
       0: aload_0
       1: aload_1
       2: invokevirtual #19                 // Method read:(Ljava/io/Reader;)Lorg/dom4j/Document;
       5: astore_3
       6: aload_3
       7: aload_2
       8: invokeinterface #24,  2           // InterfaceMethod org/dom4j/Document.setName:(Ljava/lang/String;)V
      13: aload_3
      14: areturn

  public org.gjt.xpp.XmlPullParser getXPPParser() throws org.gjt.xpp.XmlPullParserException;
    Code:
       0: aload_0
       1: getfield      #25                 // Field xppParser:Lorg/gjt/xpp/XmlPullParser;
       4: ifnonnull     18
       7: aload_0
       8: aload_0
       9: invokevirtual #26                 // Method getXPPFactory:()Lorg/gjt/xpp/XmlPullParserFactory;
      12: invokevirtual #27                 // Method org/gjt/xpp/XmlPullParserFactory.newPullParser:()Lorg/gjt/xpp/XmlPullParser;
      15: putfield      #25                 // Field xppParser:Lorg/gjt/xpp/XmlPullParser;
      18: aload_0
      19: getfield      #25                 // Field xppParser:Lorg/gjt/xpp/XmlPullParser;
      22: areturn

  public org.gjt.xpp.XmlPullParserFactory getXPPFactory() throws org.gjt.xpp.XmlPullParserException;
    Code:
       0: aload_0
       1: getfield      #28                 // Field xppFactory:Lorg/gjt/xpp/XmlPullParserFactory;
       4: ifnonnull     14
       7: aload_0
       8: invokestatic  #29                 // Method org/gjt/xpp/XmlPullParserFactory.newInstance:()Lorg/gjt/xpp/XmlPullParserFactory;
      11: putfield      #28                 // Field xppFactory:Lorg/gjt/xpp/XmlPullParserFactory;
      14: aload_0
      15: getfield      #28                 // Field xppFactory:Lorg/gjt/xpp/XmlPullParserFactory;
      18: areturn

  public void setXPPFactory(org.gjt.xpp.XmlPullParserFactory);
    Code:
       0: aload_0
       1: aload_1
       2: putfield      #28                 // Field xppFactory:Lorg/gjt/xpp/XmlPullParserFactory;
       5: return

  public org.dom4j.DocumentFactory getDocumentFactory();
    Code:
       0: aload_0
       1: getfield      #2                  // Field factory:Lorg/dom4j/DocumentFactory;
       4: ifnonnull     14
       7: aload_0
       8: invokestatic  #30                 // Method org/dom4j/DocumentFactory.getInstance:()Lorg/dom4j/DocumentFactory;
      11: putfield      #2                  // Field factory:Lorg/dom4j/DocumentFactory;
      14: aload_0
      15: getfield      #2                  // Field factory:Lorg/dom4j/DocumentFactory;
      18: areturn

  public void setDocumentFactory(org.dom4j.DocumentFactory);
    Code:
       0: aload_0
       1: aload_1
       2: putfield      #2                  // Field factory:Lorg/dom4j/DocumentFactory;
       5: return

  public void addHandler(java.lang.String, org.dom4j.ElementHandler);
    Code:
       0: aload_0
       1: invokevirtual #31                 // Method getDispatchHandler:()Lorg/dom4j/io/DispatchHandler;
       4: aload_1
       5: aload_2
       6: invokevirtual #32                 // Method org/dom4j/io/DispatchHandler.addHandler:(Ljava/lang/String;Lorg/dom4j/ElementHandler;)V
       9: return

  public void removeHandler(java.lang.String);
    Code:
       0: aload_0
       1: invokevirtual #31                 // Method getDispatchHandler:()Lorg/dom4j/io/DispatchHandler;
       4: aload_1
       5: invokevirtual #33                 // Method org/dom4j/io/DispatchHandler.removeHandler:(Ljava/lang/String;)Lorg/dom4j/ElementHandler;
       8: pop
       9: return

  public void setDefaultHandler(org.dom4j.ElementHandler);
    Code:
       0: aload_0
       1: invokevirtual #31                 // Method getDispatchHandler:()Lorg/dom4j/io/DispatchHandler;
       4: aload_1
       5: invokevirtual #34                 // Method org/dom4j/io/DispatchHandler.setDefaultHandler:(Lorg/dom4j/ElementHandler;)V
       8: return

  protected org.dom4j.Document parseDocument() throws org.dom4j.DocumentException, java.io.IOException, org.gjt.xpp.XmlPullParserException;
    Code:
       0: aload_0
       1: invokevirtual #35                 // Method getDocumentFactory:()Lorg/dom4j/DocumentFactory;
       4: invokevirtual #36                 // Method org/dom4j/DocumentFactory.createDocument:()Lorg/dom4j/Document;
       7: astore_1
       8: aconst_null
       9: astore_2
      10: aload_0
      11: invokevirtual #20                 // Method getXPPParser:()Lorg/gjt/xpp/XmlPullParser;
      14: astore_3
      15: aload_3
      16: iconst_1
      17: invokeinterface #37,  2           // InterfaceMethod org/gjt/xpp/XmlPullParser.setNamespaceAware:(Z)V
      22: new           #38                 // class org/dom4j/xpp/ProxyXmlStartTag
      25: dup
      26: invokespecial #39                 // Method org/dom4j/xpp/ProxyXmlStartTag."<init>":()V
      29: astore        4
      31: aload_0
      32: getfield      #28                 // Field xppFactory:Lorg/gjt/xpp/XmlPullParserFactory;
      35: invokevirtual #40                 // Method org/gjt/xpp/XmlPullParserFactory.newEndTag:()Lorg/gjt/xpp/XmlEndTag;
      38: astore        5
      40: aload_3
      41: invokeinterface #41,  1           // InterfaceMethod org/gjt/xpp/XmlPullParser.next:()B
      46: istore        6
      48: iload         6
      50: tableswitch   { // 1 to 4
                     1: 80
                     2: 82
                     3: 126
                     4: 148
               default: 186
          }
      80: aload_1
      81: areturn
      82: aload_3
      83: aload         4
      85: invokeinterface #42,  2           // InterfaceMethod org/gjt/xpp/XmlPullParser.readStartTag:(Lorg/gjt/xpp/XmlStartTag;)V
      90: aload         4
      92: invokevirtual #43                 // Method org/dom4j/xpp/ProxyXmlStartTag.getElement:()Lorg/dom4j/Element;
      95: astore        7
      97: aload_2
      98: ifnull        112
     101: aload_2
     102: aload         7
     104: invokeinterface #44,  2           // InterfaceMethod org/dom4j/Element.add:(Lorg/dom4j/Element;)V
     109: goto          120
     112: aload_1
     113: aload         7
     115: invokeinterface #45,  2           // InterfaceMethod org/dom4j/Document.add:(Lorg/dom4j/Element;)V
     120: aload         7
     122: astore_2
     123: goto          214
     126: aload_3
     127: aload         5
     129: invokeinterface #46,  2           // InterfaceMethod org/gjt/xpp/XmlPullParser.readEndTag:(Lorg/gjt/xpp/XmlEndTag;)V
     134: aload_2
     135: ifnull        214
     138: aload_2
     139: invokeinterface #47,  1           // InterfaceMethod org/dom4j/Element.getParent:()Lorg/dom4j/Element;
     144: astore_2
     145: goto          214
     148: aload_3
     149: invokeinterface #48,  1           // InterfaceMethod org/gjt/xpp/XmlPullParser.readContent:()Ljava/lang/String;
     154: astore        7
     156: aload_2
     157: ifnull        172
     160: aload_2
     161: aload         7
     163: invokeinterface #49,  2           // InterfaceMethod org/dom4j/Element.addText:(Ljava/lang/String;)Lorg/dom4j/Element;
     168: pop
     169: goto          214
     172: ldc           #50                 // String Cannot have text content outside of the root document
     174: astore        8
     176: new           #51                 // class org/dom4j/DocumentException
     179: dup
     180: aload         8
     182: invokespecial #52                 // Method org/dom4j/DocumentException."<init>":(Ljava/lang/String;)V
     185: athrow
     186: new           #51                 // class org/dom4j/DocumentException
     189: dup
     190: new           #53                 // class java/lang/StringBuilder
     193: dup
     194: invokespecial #54                 // Method java/lang/StringBuilder."<init>":()V
     197: ldc           #55                 // String Error: unknown type:
     199: invokevirtual #56                 // Method java/lang/StringBuilder.append:(Ljava/lang/String;)Ljava/lang/StringBuilder;
     202: iload         6
     204: invokevirtual #57                 // Method java/lang/StringBuilder.append:(I)Ljava/lang/StringBuilder;
     207: invokevirtual #58                 // Method java/lang/StringBuilder.toString:()Ljava/lang/String;
     210: invokespecial #52                 // Method org/dom4j/DocumentException."<init>":(Ljava/lang/String;)V
     213: athrow
     214: goto          40

  protected org.dom4j.io.DispatchHandler getDispatchHandler();
    Code:
       0: aload_0
       1: getfield      #59                 // Field dispatchHandler:Lorg/dom4j/io/DispatchHandler;
       4: ifnonnull     18
       7: aload_0
       8: new           #60                 // class org/dom4j/io/DispatchHandler
      11: dup
      12: invokespecial #61                 // Method org/dom4j/io/DispatchHandler."<init>":()V
      15: putfield      #59                 // Field dispatchHandler:Lorg/dom4j/io/DispatchHandler;
      18: aload_0
      19: getfield      #59                 // Field dispatchHandler:Lorg/dom4j/io/DispatchHandler;
      22: areturn

  protected void setDispatchHandler(org.dom4j.io.DispatchHandler);
    Code:
       0: aload_0
       1: aload_1
       2: putfield      #59                 // Field dispatchHandler:Lorg/dom4j/io/DispatchHandler;
       5: return

  protected java.io.Reader createReader(java.io.InputStream) throws java.io.IOException;
    Code:
       0: new           #4                  // class java/io/BufferedReader
       3: dup
       4: new           #62                 // class java/io/InputStreamReader
       7: dup
       8: aload_1
       9: invokespecial #63                 // Method java/io/InputStreamReader."<init>":(Ljava/io/InputStream;)V
      12: invokespecial #7                  // Method java/io/BufferedReader."<init>":(Ljava/io/Reader;)V
      15: areturn
}
