Compiled from "GlassFishServ30WebSocketSupport.java"
public class org.atmosphere.container.GlassFishServ30WebSocketSupport extends org.atmosphere.container.Servlet30CometSupport {
  private static final org.slf4j.Logger LOGGER;

  private org.atmosphere.container.GlassFishServ30WebSocketSupport$Grizzly2WebSocketApplication application;

  public org.atmosphere.container.GlassFishServ30WebSocketSupport(org.atmosphere.cpr.AtmosphereConfig);
    Code:
       0: aload_0
       1: aload_1
       2: invokespecial #2                  // Method org/atmosphere/container/Servlet30CometSupport."<init>":(Lorg/atmosphere/cpr/AtmosphereConfig;)V
       5: aload_0
       6: new           #3                  // class org/atmosphere/container/GlassFishServ30WebSocketSupport$Grizzly2WebSocketApplication
       9: dup
      10: aload_1
      11: invokespecial #4                  // Method org/atmosphere/container/GlassFishServ30WebSocketSupport$Grizzly2WebSocketApplication."<init>":(Lorg/atmosphere/cpr/AtmosphereConfig;)V
      14: putfield      #5                  // Field application:Lorg/atmosphere/container/GlassFishServ30WebSocketSupport$Grizzly2WebSocketApplication;
      17: invokestatic  #6                  // Method org/glassfish/grizzly/websockets/WebSocketEngine.getEngine:()Lorg/glassfish/grizzly/websockets/WebSocketEngine;
      20: aload_1
      21: invokevirtual #7                  // Method org/atmosphere/cpr/AtmosphereConfig.getServletContext:()Ljavax/servlet/ServletContext;
      24: invokeinterface #8,  1            // InterfaceMethod javax/servlet/ServletContext.getContextPath:()Ljava/lang/String;
      29: aload_1
      30: invokestatic  #9                  // Method org/atmosphere/util/IOUtils.guestRawServletPath:(Lorg/atmosphere/cpr/AtmosphereConfig;)Ljava/lang/String;
      33: aload_0
      34: getfield      #5                  // Field application:Lorg/atmosphere/container/GlassFishServ30WebSocketSupport$Grizzly2WebSocketApplication;
      37: invokevirtual #10                 // Method org/glassfish/grizzly/websockets/WebSocketEngine.register:(Ljava/lang/String;Ljava/lang/String;Lorg/glassfish/grizzly/websockets/WebSocketApplication;)V
      40: return

  public org.atmosphere.container.GlassFishServ30WebSocketSupport(org.atmosphere.cpr.AtmosphereConfig, javax.servlet.ServletContext);
    Code:
       0: aload_0
       1: aload_1
       2: invokespecial #2                  // Method org/atmosphere/container/Servlet30CometSupport."<init>":(Lorg/atmosphere/cpr/AtmosphereConfig;)V
       5: aload_0
       6: new           #3                  // class org/atmosphere/container/GlassFishServ30WebSocketSupport$Grizzly2WebSocketApplication
       9: dup
      10: aload_1
      11: invokespecial #4                  // Method org/atmosphere/container/GlassFishServ30WebSocketSupport$Grizzly2WebSocketApplication."<init>":(Lorg/atmosphere/cpr/AtmosphereConfig;)V
      14: putfield      #5                  // Field application:Lorg/atmosphere/container/GlassFishServ30WebSocketSupport$Grizzly2WebSocketApplication;
      17: invokestatic  #6                  // Method org/glassfish/grizzly/websockets/WebSocketEngine.getEngine:()Lorg/glassfish/grizzly/websockets/WebSocketEngine;
      20: aload_2
      21: invokeinterface #8,  1            // InterfaceMethod javax/servlet/ServletContext.getContextPath:()Ljava/lang/String;
      26: aload_1
      27: invokestatic  #9                  // Method org/atmosphere/util/IOUtils.guestRawServletPath:(Lorg/atmosphere/cpr/AtmosphereConfig;)Ljava/lang/String;
      30: aload_0
      31: getfield      #5                  // Field application:Lorg/atmosphere/container/GlassFishServ30WebSocketSupport$Grizzly2WebSocketApplication;
      34: invokevirtual #10                 // Method org/glassfish/grizzly/websockets/WebSocketEngine.register:(Ljava/lang/String;Ljava/lang/String;Lorg/glassfish/grizzly/websockets/WebSocketApplication;)V
      37: return

  public org.atmosphere.cpr.Action service(org.atmosphere.cpr.AtmosphereRequest, org.atmosphere.cpr.AtmosphereResponse) throws java.io.IOException, javax.servlet.ServletException;
    Code:
       0: aload_1
       1: invokestatic  #11                 // Method org/atmosphere/util/Utils.webSocketEnabled:(Ljavax/servlet/http/HttpServletRequest;)Z
       4: ifeq          14
       7: aload_0
       8: aload_1
       9: aload_2
      10: invokevirtual #12                 // Method suspended:(Lorg/atmosphere/cpr/AtmosphereRequest;Lorg/atmosphere/cpr/AtmosphereResponse;)Lorg/atmosphere/cpr/Action;
      13: areturn
      14: aload_0
      15: aload_1
      16: aload_2
      17: invokespecial #13                 // Method org/atmosphere/container/Servlet30CometSupport.service:(Lorg/atmosphere/cpr/AtmosphereRequest;Lorg/atmosphere/cpr/AtmosphereResponse;)Lorg/atmosphere/cpr/Action;
      20: areturn

  public java.lang.String getContainerName();
    Code:
       0: new           #14                 // class java/lang/StringBuilder
       3: dup
       4: invokespecial #15                 // Method java/lang/StringBuilder."<init>":()V
       7: aload_0
       8: getfield      #16                 // Field config:Lorg/atmosphere/cpr/AtmosphereConfig;
      11: invokevirtual #17                 // Method org/atmosphere/cpr/AtmosphereConfig.getServletConfig:()Ljavax/servlet/ServletConfig;
      14: invokeinterface #18,  1           // InterfaceMethod javax/servlet/ServletConfig.getServletContext:()Ljavax/servlet/ServletContext;
      19: invokeinterface #19,  1           // InterfaceMethod javax/servlet/ServletContext.getServerInfo:()Ljava/lang/String;
      24: invokevirtual #20                 // Method java/lang/StringBuilder.append:(Ljava/lang/String;)Ljava/lang/StringBuilder;
      27: ldc           #21                 // String  with WebSocket enabled.
      29: invokevirtual #20                 // Method java/lang/StringBuilder.append:(Ljava/lang/String;)Ljava/lang/StringBuilder;
      32: invokevirtual #22                 // Method java/lang/StringBuilder.toString:()Ljava/lang/String;
      35: areturn

  public boolean supportWebSocket();
    Code:
       0: iconst_1
       1: ireturn

  public void shutdown();
    Code:
       0: aload_0
       1: invokespecial #23                 // Method org/atmosphere/container/Servlet30CometSupport.shutdown:()V
       4: invokestatic  #6                  // Method org/glassfish/grizzly/websockets/WebSocketEngine.getEngine:()Lorg/glassfish/grizzly/websockets/WebSocketEngine;
       7: aload_0
       8: getfield      #5                  // Field application:Lorg/atmosphere/container/GlassFishServ30WebSocketSupport$Grizzly2WebSocketApplication;
      11: invokevirtual #24                 // Method org/glassfish/grizzly/websockets/WebSocketEngine.unregister:(Lorg/glassfish/grizzly/websockets/WebSocketApplication;)V
      14: aload_0
      15: invokespecial #23                 // Method org/atmosphere/container/Servlet30CometSupport.shutdown:()V
      18: return

  static org.slf4j.Logger access$000();
    Code:
       0: getstatic     #1                  // Field LOGGER:Lorg/slf4j/Logger;
       3: areturn

  static {};
    Code:
       0: ldc           #25                 // class org/atmosphere/container/GlassFishServ30WebSocketSupport
       2: invokestatic  #26                 // Method org/slf4j/LoggerFactory.getLogger:(Ljava/lang/Class;)Lorg/slf4j/Logger;
       5: putstatic     #1                  // Field LOGGER:Lorg/slf4j/Logger;
       8: return
}
