Compiled from "Grizzly2CometSupport.java"
class org.atmosphere.container.Grizzly2CometSupport$VoidCometHandler implements org.glassfish.grizzly.comet.CometHandler {
  org.atmosphere.cpr.AtmosphereRequest req;

  org.atmosphere.cpr.AtmosphereResponse res;

  private org.glassfish.grizzly.http.server.Response grizzlyResponse;

  org.glassfish.grizzly.comet.CometContext cometContext;

  final org.atmosphere.container.Grizzly2CometSupport this$0;

  public org.atmosphere.container.Grizzly2CometSupport$VoidCometHandler(org.atmosphere.container.Grizzly2CometSupport, org.atmosphere.cpr.AtmosphereRequest, org.atmosphere.cpr.AtmosphereResponse);
    Code:
       0: aload_0
       1: aload_1
       2: putfield      #1                  // Field this$0:Lorg/atmosphere/container/Grizzly2CometSupport;
       5: aload_0
       6: invokespecial #2                  // Method java/lang/Object."<init>":()V
       9: aload_0
      10: aload_2
      11: putfield      #3                  // Field req:Lorg/atmosphere/cpr/AtmosphereRequest;
      14: aload_0
      15: aload_3
      16: putfield      #4                  // Field res:Lorg/atmosphere/cpr/AtmosphereResponse;
      19: return

  public void attach(java.lang.Object);
    Code:
       0: return

  public void onEvent(org.glassfish.grizzly.comet.CometEvent) throws java.io.IOException;
    Code:
       0: return

  public void onInitialize(org.glassfish.grizzly.comet.CometEvent) throws java.io.IOException;
    Code:
       0: return

  public void onTerminate(org.glassfish.grizzly.comet.CometEvent) throws java.io.IOException;
    Code:
       0: return

  public synchronized void onInterrupt(org.glassfish.grizzly.comet.CometEvent) throws java.io.IOException;
    Code:
       0: aload_1
       1: invokevirtual #5                  // Method org/glassfish/grizzly/comet/CometEvent.getCometContext:()Lorg/glassfish/grizzly/comet/CometContext;
       4: ldc           #6                  // String Time
       6: invokevirtual #7                  // Method org/glassfish/grizzly/comet/CometContext.getAttribute:(Ljava/lang/Object;)Ljava/lang/Object;
       9: checkcast     #8                  // class java/lang/Long
      12: invokevirtual #9                  // Method java/lang/Long.longValue:()J
      15: lstore_2
      16: aload_1
      17: invokevirtual #5                  // Method org/glassfish/grizzly/comet/CometEvent.getCometContext:()Lorg/glassfish/grizzly/comet/CometContext;
      20: invokevirtual #10                 // Method org/glassfish/grizzly/comet/CometContext.getExpirationDelay:()J
      23: lconst_0
      24: lcmp
      25: ifle          70
      28: invokestatic  #11                 // Method java/lang/System.currentTimeMillis:()J
      31: lload_2
      32: lsub
      33: aload_1
      34: invokevirtual #5                  // Method org/glassfish/grizzly/comet/CometEvent.getCometContext:()Lorg/glassfish/grizzly/comet/CometContext;
      37: invokevirtual #10                 // Method org/glassfish/grizzly/comet/CometContext.getExpirationDelay:()J
      40: lcmp
      41: iflt          70
      44: aload_0
      45: getfield      #1                  // Field this$0:Lorg/atmosphere/container/Grizzly2CometSupport;
      48: aload_0
      49: getfield      #3                  // Field req:Lorg/atmosphere/cpr/AtmosphereRequest;
      52: aload_0
      53: getfield      #4                  // Field res:Lorg/atmosphere/cpr/AtmosphereResponse;
      56: invokevirtual #12                 // Method org/atmosphere/container/Grizzly2CometSupport.timedout:(Lorg/atmosphere/cpr/AtmosphereRequest;Lorg/atmosphere/cpr/AtmosphereResponse;)Lorg/atmosphere/cpr/Action;
      59: pop
      60: aload_0
      61: getfield      #13                 // Field grizzlyResponse:Lorg/glassfish/grizzly/http/server/Response;
      64: invokevirtual #14                 // Method org/glassfish/grizzly/http/server/Response.finish:()V
      67: goto          86
      70: aload_0
      71: getfield      #1                  // Field this$0:Lorg/atmosphere/container/Grizzly2CometSupport;
      74: aload_0
      75: getfield      #3                  // Field req:Lorg/atmosphere/cpr/AtmosphereRequest;
      78: aload_0
      79: getfield      #4                  // Field res:Lorg/atmosphere/cpr/AtmosphereResponse;
      82: invokevirtual #15                 // Method org/atmosphere/container/Grizzly2CometSupport.cancelled:(Lorg/atmosphere/cpr/AtmosphereRequest;Lorg/atmosphere/cpr/AtmosphereResponse;)Lorg/atmosphere/cpr/Action;
      85: pop
      86: goto          103
      89: astore        4
      91: invokestatic  #17                 // Method org/atmosphere/container/Grizzly2CometSupport.access$000:()Lorg/slf4j/Logger;
      94: ldc           #18                 // String onInterrupt() encountered exception
      96: aload         4
      98: invokeinterface #19,  3           // InterfaceMethod org/slf4j/Logger.warn:(Ljava/lang/String;Ljava/lang/Throwable;)V
     103: return
    Exception table:
       from    to  target type
          16    86    89   Class javax/servlet/ServletException

  public org.glassfish.grizzly.http.server.Response getResponse();
    Code:
       0: aload_0
       1: getfield      #13                 // Field grizzlyResponse:Lorg/glassfish/grizzly/http/server/Response;
       4: areturn

  public void setResponse(org.glassfish.grizzly.http.server.Response);
    Code:
       0: aload_0
       1: aload_1
       2: putfield      #13                 // Field grizzlyResponse:Lorg/glassfish/grizzly/http/server/Response;
       5: return

  public org.glassfish.grizzly.comet.CometContext getCometContext();
    Code:
       0: aload_0
       1: getfield      #20                 // Field cometContext:Lorg/glassfish/grizzly/comet/CometContext;
       4: areturn

  public void setCometContext(org.glassfish.grizzly.comet.CometContext);
    Code:
       0: aload_0
       1: aload_1
       2: putfield      #20                 // Field cometContext:Lorg/glassfish/grizzly/comet/CometContext;
       5: return
}
