Compiled from "Jetty93AsyncSupportWithWebSocket.java"
public class org.atmosphere.container.Jetty93AsyncSupportWithWebSocket extends org.atmosphere.container.AbstractJetty9AsyncSupportWithWebSocket {
  private static final org.slf4j.Logger logger;

  private final org.eclipse.jetty.websocket.server.WebSocketServerFactory webSocketFactory;

  public org.atmosphere.container.Jetty93AsyncSupportWithWebSocket(org.atmosphere.cpr.AtmosphereConfig);
    Code:
       0: aload_0
       1: aload_1
       2: getstatic     #1                  // Field logger:Lorg/slf4j/Logger;
       5: invokespecial #2                  // Method org/atmosphere/container/AbstractJetty9AsyncSupportWithWebSocket."<init>":(Lorg/atmosphere/cpr/AtmosphereConfig;Lorg/slf4j/Logger;)V
       8: aload_1
       9: invokestatic  #3                  // Method GetPolicy:(Lorg/atmosphere/cpr/AtmosphereConfig;)Lorg/eclipse/jetty/websocket/api/WebSocketPolicy;
      12: astore_2
      13: invokestatic  #4                  // Method org/atmosphere/cpr/WebSocketProcessorFactory.getDefault:()Lorg/atmosphere/cpr/WebSocketProcessorFactory;
      16: aload_1
      17: invokevirtual #5                  // Method org/atmosphere/cpr/AtmosphereConfig.framework:()Lorg/atmosphere/cpr/AtmosphereFramework;
      20: invokevirtual #6                  // Method org/atmosphere/cpr/WebSocketProcessorFactory.getWebSocketProcessor:(Lorg/atmosphere/cpr/AtmosphereFramework;)Lorg/atmosphere/websocket/WebSocketProcessor;
      23: astore_3
      24: aload_0
      25: new           #7                  // class org/atmosphere/container/Jetty93AsyncSupportWithWebSocket$1
      28: dup
      29: aload_0
      30: aload_1
      31: invokevirtual #8                  // Method org/atmosphere/cpr/AtmosphereConfig.getServletContext:()Ljavax/servlet/ServletContext;
      34: aload_2
      35: aload_3
      36: invokespecial #9                  // Method org/atmosphere/container/Jetty93AsyncSupportWithWebSocket$1."<init>":(Lorg/atmosphere/container/Jetty93AsyncSupportWithWebSocket;Ljavax/servlet/ServletContext;Lorg/eclipse/jetty/websocket/api/WebSocketPolicy;Lorg/atmosphere/websocket/WebSocketProcessor;)V
      39: putfield      #10                 // Field webSocketFactory:Lorg/eclipse/jetty/websocket/server/WebSocketServerFactory;
      42: aload_0
      43: getfield      #10                 // Field webSocketFactory:Lorg/eclipse/jetty/websocket/server/WebSocketServerFactory;
      46: invokevirtual #11                 // Method org/eclipse/jetty/websocket/server/WebSocketServerFactory.start:()V
      49: goto          66
      52: astore        4
      54: getstatic     #1                  // Field logger:Lorg/slf4j/Logger;
      57: ldc           #13                 // String
      59: aload         4
      61: invokeinterface #14,  3           // InterfaceMethod org/slf4j/Logger.error:(Ljava/lang/String;Ljava/lang/Throwable;)V
      66: return
    Exception table:
       from    to  target type
          42    49    52   Class java/lang/Exception

  org.eclipse.jetty.websocket.server.WebSocketServerFactory getWebSocketFactory();
    Code:
       0: aload_0
       1: getfield      #10                 // Field webSocketFactory:Lorg/eclipse/jetty/websocket/server/WebSocketServerFactory;
       4: areturn

  public boolean supportWebSocket();
    Code:
       0: aload_0
       1: invokespecial #15                 // Method org/atmosphere/container/AbstractJetty9AsyncSupportWithWebSocket.supportWebSocket:()Z
       4: ireturn

  public java.lang.String getContainerName();
    Code:
       0: aload_0
       1: invokespecial #16                 // Method org/atmosphere/container/AbstractJetty9AsyncSupportWithWebSocket.getContainerName:()Ljava/lang/String;
       4: areturn

  public org.atmosphere.cpr.Action service(org.atmosphere.cpr.AtmosphereRequest, org.atmosphere.cpr.AtmosphereResponse) throws java.io.IOException, javax.servlet.ServletException;
    Code:
       0: aload_0
       1: aload_1
       2: aload_2
       3: invokespecial #17                 // Method org/atmosphere/container/AbstractJetty9AsyncSupportWithWebSocket.service:(Lorg/atmosphere/cpr/AtmosphereRequest;Lorg/atmosphere/cpr/AtmosphereResponse;)Lorg/atmosphere/cpr/Action;
       6: areturn

  static {};
    Code:
       0: ldc           #18                 // class org/atmosphere/container/Jetty93AsyncSupportWithWebSocket
       2: invokestatic  #19                 // Method org/slf4j/LoggerFactory.getLogger:(Ljava/lang/Class;)Lorg/slf4j/Logger;
       5: putstatic     #1                  // Field logger:Lorg/slf4j/Logger;
       8: return
}
