Compiled from "DefaultAccessorNamingStrategy.java"
public class com.fasterxml.jackson.databind.introspect.DefaultAccessorNamingStrategy$RecordNaming extends com.fasterxml.jackson.databind.introspect.DefaultAccessorNamingStrategy {
  protected final java.util.Set<java.lang.String> _fieldNames;

  public com.fasterxml.jackson.databind.introspect.DefaultAccessorNamingStrategy$RecordNaming(com.fasterxml.jackson.databind.cfg.MapperConfig<?>, com.fasterxml.jackson.databind.introspect.AnnotatedClass);
    Code:
       0: aload_0
       1: aload_1
       2: aload_2
       3: aconst_null
       4: ldc           #1                  // String get
       6: ldc           #2                  // String is
       8: aconst_null
       9: invokespecial #3                  // Method com/fasterxml/jackson/databind/introspect/DefaultAccessorNamingStrategy."<init>":(Lcom/fasterxml/jackson/databind/cfg/MapperConfig;Lcom/fasterxml/jackson/databind/introspect/AnnotatedClass;Ljava/lang/String;Ljava/lang/String;Ljava/lang/String;Lcom/fasterxml/jackson/databind/introspect/DefaultAccessorNamingStrategy$BaseNameValidator;)V
      12: aload_0
      13: new           #4                  // class java/util/HashSet
      16: dup
      17: invokespecial #5                  // Method java/util/HashSet."<init>":()V
      20: putfield      #6                  // Field _fieldNames:Ljava/util/Set;
      23: aload_2
      24: invokevirtual #7                  // Method com/fasterxml/jackson/databind/introspect/AnnotatedClass.getRawType:()Ljava/lang/Class;
      27: invokestatic  #8                  // Method com/fasterxml/jackson/databind/jdk14/JDK14Util.getRecordFieldNames:(Ljava/lang/Class;)[Ljava/lang/String;
      30: astore_3
      31: aload_3
      32: arraylength
      33: istore        4
      35: iconst_0
      36: istore        5
      38: iload         5
      40: iload         4
      42: if_icmpge     69
      45: aload_3
      46: iload         5
      48: aaload
      49: astore        6
      51: aload_0
      52: getfield      #6                  // Field _fieldNames:Ljava/util/Set;
      55: aload         6
      57: invokeinterface #9,  2            // InterfaceMethod java/util/Set.add:(Ljava/lang/Object;)Z
      62: pop
      63: iinc          5, 1
      66: goto          38
      69: return

  public java.lang.String findNameForRegularGetter(com.fasterxml.jackson.databind.introspect.AnnotatedMethod, java.lang.String);
    Code:
       0: aload_0
       1: getfield      #6                  // Field _fieldNames:Ljava/util/Set;
       4: aload_2
       5: invokeinterface #10,  2           // InterfaceMethod java/util/Set.contains:(Ljava/lang/Object;)Z
      10: ifeq          15
      13: aload_2
      14: areturn
      15: aload_0
      16: aload_1
      17: aload_2
      18: invokespecial #11                 // Method com/fasterxml/jackson/databind/introspect/DefaultAccessorNamingStrategy.findNameForRegularGetter:(Lcom/fasterxml/jackson/databind/introspect/AnnotatedMethod;Ljava/lang/String;)Ljava/lang/String;
      21: areturn
}
