Compiled from "RoleResource.java"
public class org.sonatype.security.rest.model.RoleResource implements java.io.Serializable {
  private java.lang.String resourceURI;

  private java.lang.String id;

  private java.lang.String name;

  private java.lang.String description;

  private int sessionTimeout;

  private java.util.List<java.lang.String> roles;

  private java.util.List<java.lang.String> privileges;

  private boolean userManaged;

  public org.sonatype.security.rest.model.RoleResource();
    Code:
       0: aload_0
       1: invokespecial #1                  // Method java/lang/Object."<init>":()V
       4: aload_0
       5: iconst_0
       6: putfield      #2                  // Field sessionTimeout:I
       9: aload_0
      10: iconst_0
      11: putfield      #3                  // Field userManaged:Z
      14: return

  public void addPrivilege(java.lang.String);
    Code:
       0: aload_0
       1: invokevirtual #4                  // Method getPrivileges:()Ljava/util/List;
       4: aload_1
       5: invokeinterface #5,  2            // InterfaceMethod java/util/List.add:(Ljava/lang/Object;)Z
      10: pop
      11: return

  public void addRole(java.lang.String);
    Code:
       0: aload_0
       1: invokevirtual #6                  // Method getRoles:()Ljava/util/List;
       4: aload_1
       5: invokeinterface #5,  2            // InterfaceMethod java/util/List.add:(Ljava/lang/Object;)Z
      10: pop
      11: return

  public java.lang.String getDescription();
    Code:
       0: aload_0
       1: getfield      #7                  // Field description:Ljava/lang/String;
       4: areturn

  public java.lang.String getId();
    Code:
       0: aload_0
       1: getfield      #8                  // Field id:Ljava/lang/String;
       4: areturn

  public java.lang.String getName();
    Code:
       0: aload_0
       1: getfield      #9                  // Field name:Ljava/lang/String;
       4: areturn

  public java.util.List<java.lang.String> getPrivileges();
    Code:
       0: aload_0
       1: getfield      #10                 // Field privileges:Ljava/util/List;
       4: ifnonnull     18
       7: aload_0
       8: new           #11                 // class java/util/ArrayList
      11: dup
      12: invokespecial #12                 // Method java/util/ArrayList."<init>":()V
      15: putfield      #10                 // Field privileges:Ljava/util/List;
      18: aload_0
      19: getfield      #10                 // Field privileges:Ljava/util/List;
      22: areturn

  public java.lang.String getResourceURI();
    Code:
       0: aload_0
       1: getfield      #13                 // Field resourceURI:Ljava/lang/String;
       4: areturn

  public java.util.List<java.lang.String> getRoles();
    Code:
       0: aload_0
       1: getfield      #14                 // Field roles:Ljava/util/List;
       4: ifnonnull     18
       7: aload_0
       8: new           #11                 // class java/util/ArrayList
      11: dup
      12: invokespecial #12                 // Method java/util/ArrayList."<init>":()V
      15: putfield      #14                 // Field roles:Ljava/util/List;
      18: aload_0
      19: getfield      #14                 // Field roles:Ljava/util/List;
      22: areturn

  public int getSessionTimeout();
    Code:
       0: aload_0
       1: getfield      #2                  // Field sessionTimeout:I
       4: ireturn

  public boolean isUserManaged();
    Code:
       0: aload_0
       1: getfield      #3                  // Field userManaged:Z
       4: ireturn

  public void removePrivilege(java.lang.String);
    Code:
       0: aload_0
       1: invokevirtual #4                  // Method getPrivileges:()Ljava/util/List;
       4: aload_1
       5: invokeinterface #15,  2           // InterfaceMethod java/util/List.remove:(Ljava/lang/Object;)Z
      10: pop
      11: return

  public void removeRole(java.lang.String);
    Code:
       0: aload_0
       1: invokevirtual #6                  // Method getRoles:()Ljava/util/List;
       4: aload_1
       5: invokeinterface #15,  2           // InterfaceMethod java/util/List.remove:(Ljava/lang/Object;)Z
      10: pop
      11: return

  public void setDescription(java.lang.String);
    Code:
       0: aload_0
       1: aload_1
       2: putfield      #7                  // Field description:Ljava/lang/String;
       5: return

  public void setId(java.lang.String);
    Code:
       0: aload_0
       1: aload_1
       2: putfield      #8                  // Field id:Ljava/lang/String;
       5: return

  public void setName(java.lang.String);
    Code:
       0: aload_0
       1: aload_1
       2: putfield      #9                  // Field name:Ljava/lang/String;
       5: return

  public void setPrivileges(java.util.List<java.lang.String>);
    Code:
       0: aload_0
       1: aload_1
       2: putfield      #10                 // Field privileges:Ljava/util/List;
       5: return

  public void setResourceURI(java.lang.String);
    Code:
       0: aload_0
       1: aload_1
       2: putfield      #13                 // Field resourceURI:Ljava/lang/String;
       5: return

  public void setRoles(java.util.List<java.lang.String>);
    Code:
       0: aload_0
       1: aload_1
       2: putfield      #14                 // Field roles:Ljava/util/List;
       5: return

  public void setSessionTimeout(int);
    Code:
       0: aload_0
       1: iload_1
       2: putfield      #2                  // Field sessionTimeout:I
       5: return

  public void setUserManaged(boolean);
    Code:
       0: aload_0
       1: iload_1
       2: putfield      #3                  // Field userManaged:Z
       5: return
}
