Compiled from "UserForgotPasswordResource.java"
public class org.sonatype.security.rest.model.UserForgotPasswordResource implements java.io.Serializable {
  private java.lang.String email;

  private java.lang.String userId;

  public org.sonatype.security.rest.model.UserForgotPasswordResource();
    Code:
       0: aload_0
       1: invokespecial #1                  // Method java/lang/Object."<init>":()V
       4: return

  public java.lang.String getEmail();
    Code:
       0: aload_0
       1: getfield      #2                  // Field email:Ljava/lang/String;
       4: areturn

  public java.lang.String getUserId();
    Code:
       0: aload_0
       1: getfield      #3                  // Field userId:Ljava/lang/String;
       4: areturn

  public void setEmail(java.lang.String);
    Code:
       0: aload_0
       1: aload_1
       2: putfield      #2                  // Field email:Ljava/lang/String;
       5: return

  public void setUserId(java.lang.String);
    Code:
       0: aload_0
       1: aload_1
       2: putfield      #3                  // Field userId:Ljava/lang/String;
       5: return
}
