Compiled from "ExtraFieldPropagation.java"
final class brave.propagation.ExtraFieldPropagation$Extra extends brave.internal.PredefinedPropagationFields {
  brave.propagation.ExtraFieldPropagation$Extra(java.lang.String...);
    Code:
       0: aload_0
       1: aload_1
       2: invokespecial #12                 // Method brave/internal/PredefinedPropagationFields."<init>":([Ljava/lang/String;)V
       5: return

  brave.propagation.ExtraFieldPropagation$Extra(brave.propagation.ExtraFieldPropagation$Extra, java.lang.String...);
    Code:
       0: aload_0
       1: aload_1
       2: aload_2
       3: invokespecial #20                 // Method brave/internal/PredefinedPropagationFields."<init>":(Lbrave/internal/PredefinedPropagationFields;[Ljava/lang/String;)V
       6: return
}
