Compiled from "Propagation.java"
public abstract class brave.propagation.Propagation$Factory {
  public brave.propagation.Propagation$Factory();
    Code:
       0: aload_0
       1: invokespecial #15                 // Method java/lang/Object."<init>":()V
       4: return

  public boolean supportsJoin();
    Code:
       0: iconst_0
       1: ireturn

  public boolean requires128BitTraceId();
    Code:
       0: iconst_0
       1: ireturn

  public abstract <K> brave.propagation.Propagation<K> create(brave.propagation.Propagation$KeyFactory<K>);

  public brave.propagation.TraceContext decorate(brave.propagation.TraceContext);
    Code:
       0: aload_1
       1: areturn
}
