Compiled from "CustomResourceDefinitionSpecBuilder.java"
public class io.dekorate.deps.kubernetes.api.model.apiextensions.CustomResourceDefinitionSpecBuilder extends io.dekorate.deps.kubernetes.api.model.apiextensions.CustomResourceDefinitionSpecFluentImpl<io.dekorate.deps.kubernetes.api.model.apiextensions.CustomResourceDefinitionSpecBuilder> implements io.dekorate.deps.kubernetes.api.builder.VisitableBuilder<io.dekorate.deps.kubernetes.api.model.apiextensions.CustomResourceDefinitionSpec, io.dekorate.deps.kubernetes.api.model.apiextensions.CustomResourceDefinitionSpecBuilder> {
  io.dekorate.deps.kubernetes.api.model.apiextensions.CustomResourceDefinitionSpecFluent<?> fluent;

  java.lang.Boolean validationEnabled;

  public io.dekorate.deps.kubernetes.api.model.apiextensions.CustomResourceDefinitionSpecBuilder();
    Code:
       0: aload_0
       1: iconst_1
       2: invokestatic  #21                 // Method java/lang/Boolean.valueOf:(Z)Ljava/lang/Boolean;
       5: invokespecial #24                 // Method "<init>":(Ljava/lang/Boolean;)V
       8: return

  public io.dekorate.deps.kubernetes.api.model.apiextensions.CustomResourceDefinitionSpecBuilder(java.lang.Boolean);
    Code:
       0: aload_0
       1: new           #28                 // class io/dekorate/deps/kubernetes/api/model/apiextensions/CustomResourceDefinitionSpec
       4: dup
       5: invokespecial #30                 // Method io/dekorate/deps/kubernetes/api/model/apiextensions/CustomResourceDefinitionSpec."<init>":()V
       8: aload_1
       9: invokespecial #33                 // Method "<init>":(Lio/dekorate/deps/kubernetes/api/model/apiextensions/CustomResourceDefinitionSpec;Ljava/lang/Boolean;)V
      12: return

  public io.dekorate.deps.kubernetes.api.model.apiextensions.CustomResourceDefinitionSpecBuilder(io.dekorate.deps.kubernetes.api.model.apiextensions.CustomResourceDefinitionSpecFluent<?>);
    Code:
       0: aload_0
       1: aload_1
       2: iconst_1
       3: invokestatic  #21                 // Method java/lang/Boolean.valueOf:(Z)Ljava/lang/Boolean;
       6: invokespecial #38                 // Method "<init>":(Lio/dekorate/deps/kubernetes/api/model/apiextensions/CustomResourceDefinitionSpecFluent;Ljava/lang/Boolean;)V
       9: return

  public io.dekorate.deps.kubernetes.api.model.apiextensions.CustomResourceDefinitionSpecBuilder(io.dekorate.deps.kubernetes.api.model.apiextensions.CustomResourceDefinitionSpecFluent<?>, java.lang.Boolean);
    Code:
       0: aload_0
       1: aload_1
       2: new           #28                 // class io/dekorate/deps/kubernetes/api/model/apiextensions/CustomResourceDefinitionSpec
       5: dup
       6: invokespecial #30                 // Method io/dekorate/deps/kubernetes/api/model/apiextensions/CustomResourceDefinitionSpec."<init>":()V
       9: aload_2
      10: invokespecial #42                 // Method "<init>":(Lio/dekorate/deps/kubernetes/api/model/apiextensions/CustomResourceDefinitionSpecFluent;Lio/dekorate/deps/kubernetes/api/model/apiextensions/CustomResourceDefinitionSpec;Ljava/lang/Boolean;)V
      13: return

  public io.dekorate.deps.kubernetes.api.model.apiextensions.CustomResourceDefinitionSpecBuilder(io.dekorate.deps.kubernetes.api.model.apiextensions.CustomResourceDefinitionSpecFluent<?>, io.dekorate.deps.kubernetes.api.model.apiextensions.CustomResourceDefinitionSpec);
    Code:
       0: aload_0
       1: aload_1
       2: aload_2
       3: iconst_1
       4: invokestatic  #21                 // Method java/lang/Boolean.valueOf:(Z)Ljava/lang/Boolean;
       7: invokespecial #42                 // Method "<init>":(Lio/dekorate/deps/kubernetes/api/model/apiextensions/CustomResourceDefinitionSpecFluent;Lio/dekorate/deps/kubernetes/api/model/apiextensions/CustomResourceDefinitionSpec;Ljava/lang/Boolean;)V
      10: return

  public io.dekorate.deps.kubernetes.api.model.apiextensions.CustomResourceDefinitionSpecBuilder(io.dekorate.deps.kubernetes.api.model.apiextensions.CustomResourceDefinitionSpecFluent<?>, io.dekorate.deps.kubernetes.api.model.apiextensions.CustomResourceDefinitionSpec, java.lang.Boolean);
    Code:
       0: aload_0
       1: invokespecial #48                 // Method io/dekorate/deps/kubernetes/api/model/apiextensions/CustomResourceDefinitionSpecFluentImpl."<init>":()V
       4: aload_0
       5: aload_1
       6: putfield      #50                 // Field fluent:Lio/dekorate/deps/kubernetes/api/model/apiextensions/CustomResourceDefinitionSpecFluent;
       9: aload_1
      10: aload_2
      11: invokevirtual #54                 // Method io/dekorate/deps/kubernetes/api/model/apiextensions/CustomResourceDefinitionSpec.getAdditionalPrinterColumns:()Ljava/util/List;
      14: invokeinterface #60,  2           // InterfaceMethod io/dekorate/deps/kubernetes/api/model/apiextensions/CustomResourceDefinitionSpecFluent.withAdditionalPrinterColumns:(Ljava/util/List;)Lio/dekorate/deps/kubernetes/api/model/apiextensions/CustomResourceDefinitionSpecFluent;
      19: pop
      20: aload_1
      21: aload_2
      22: invokevirtual #64                 // Method io/dekorate/deps/kubernetes/api/model/apiextensions/CustomResourceDefinitionSpec.getConversion:()Lio/dekorate/deps/kubernetes/api/model/apiextensions/CustomResourceConversion;
      25: invokeinterface #68,  2           // InterfaceMethod io/dekorate/deps/kubernetes/api/model/apiextensions/CustomResourceDefinitionSpecFluent.withConversion:(Lio/dekorate/deps/kubernetes/api/model/apiextensions/CustomResourceConversion;)Lio/dekorate/deps/kubernetes/api/model/apiextensions/CustomResourceDefinitionSpecFluent;
      30: pop
      31: aload_1
      32: aload_2
      33: invokevirtual #72                 // Method io/dekorate/deps/kubernetes/api/model/apiextensions/CustomResourceDefinitionSpec.getGroup:()Ljava/lang/String;
      36: invokeinterface #76,  2           // InterfaceMethod io/dekorate/deps/kubernetes/api/model/apiextensions/CustomResourceDefinitionSpecFluent.withGroup:(Ljava/lang/String;)Lio/dekorate/deps/kubernetes/api/model/apiextensions/CustomResourceDefinitionSpecFluent;
      41: pop
      42: aload_1
      43: aload_2
      44: invokevirtual #80                 // Method io/dekorate/deps/kubernetes/api/model/apiextensions/CustomResourceDefinitionSpec.getNames:()Lio/dekorate/deps/kubernetes/api/model/apiextensions/CustomResourceDefinitionNames;
      47: invokeinterface #84,  2           // InterfaceMethod io/dekorate/deps/kubernetes/api/model/apiextensions/CustomResourceDefinitionSpecFluent.withNames:(Lio/dekorate/deps/kubernetes/api/model/apiextensions/CustomResourceDefinitionNames;)Lio/dekorate/deps/kubernetes/api/model/apiextensions/CustomResourceDefinitionSpecFluent;
      52: pop
      53: aload_1
      54: aload_2
      55: invokevirtual #88                 // Method io/dekorate/deps/kubernetes/api/model/apiextensions/CustomResourceDefinitionSpec.getPreserveUnknownFields:()Ljava/lang/Boolean;
      58: invokeinterface #92,  2           // InterfaceMethod io/dekorate/deps/kubernetes/api/model/apiextensions/CustomResourceDefinitionSpecFluent.withPreserveUnknownFields:(Ljava/lang/Boolean;)Lio/dekorate/deps/kubernetes/api/model/apiextensions/CustomResourceDefinitionSpecFluent;
      63: pop
      64: aload_1
      65: aload_2
      66: invokevirtual #95                 // Method io/dekorate/deps/kubernetes/api/model/apiextensions/CustomResourceDefinitionSpec.getScope:()Ljava/lang/String;
      69: invokeinterface #98,  2           // InterfaceMethod io/dekorate/deps/kubernetes/api/model/apiextensions/CustomResourceDefinitionSpecFluent.withScope:(Ljava/lang/String;)Lio/dekorate/deps/kubernetes/api/model/apiextensions/CustomResourceDefinitionSpecFluent;
      74: pop
      75: aload_1
      76: aload_2
      77: invokevirtual #102                // Method io/dekorate/deps/kubernetes/api/model/apiextensions/CustomResourceDefinitionSpec.getSubresources:()Lio/dekorate/deps/kubernetes/api/model/apiextensions/CustomResourceSubresources;
      80: invokeinterface #106,  2          // InterfaceMethod io/dekorate/deps/kubernetes/api/model/apiextensions/CustomResourceDefinitionSpecFluent.withSubresources:(Lio/dekorate/deps/kubernetes/api/model/apiextensions/CustomResourceSubresources;)Lio/dekorate/deps/kubernetes/api/model/apiextensions/CustomResourceDefinitionSpecFluent;
      85: pop
      86: aload_1
      87: aload_2
      88: invokevirtual #110                // Method io/dekorate/deps/kubernetes/api/model/apiextensions/CustomResourceDefinitionSpec.getValidation:()Lio/dekorate/deps/kubernetes/api/model/apiextensions/CustomResourceValidation;
      91: invokeinterface #114,  2          // InterfaceMethod io/dekorate/deps/kubernetes/api/model/apiextensions/CustomResourceDefinitionSpecFluent.withValidation:(Lio/dekorate/deps/kubernetes/api/model/apiextensions/CustomResourceValidation;)Lio/dekorate/deps/kubernetes/api/model/apiextensions/CustomResourceDefinitionSpecFluent;
      96: pop
      97: aload_1
      98: aload_2
      99: invokevirtual #117                // Method io/dekorate/deps/kubernetes/api/model/apiextensions/CustomResourceDefinitionSpec.getVersion:()Ljava/lang/String;
     102: invokeinterface #120,  2          // InterfaceMethod io/dekorate/deps/kubernetes/api/model/apiextensions/CustomResourceDefinitionSpecFluent.withVersion:(Ljava/lang/String;)Lio/dekorate/deps/kubernetes/api/model/apiextensions/CustomResourceDefinitionSpecFluent;
     107: pop
     108: aload_1
     109: aload_2
     110: invokevirtual #123                // Method io/dekorate/deps/kubernetes/api/model/apiextensions/CustomResourceDefinitionSpec.getVersions:()Ljava/util/List;
     113: invokeinterface #126,  2          // InterfaceMethod io/dekorate/deps/kubernetes/api/model/apiextensions/CustomResourceDefinitionSpecFluent.withVersions:(Ljava/util/List;)Lio/dekorate/deps/kubernetes/api/model/apiextensions/CustomResourceDefinitionSpecFluent;
     118: pop
     119: aload_0
     120: aload_3
     121: putfield      #128                // Field validationEnabled:Ljava/lang/Boolean;
     124: return

  public io.dekorate.deps.kubernetes.api.model.apiextensions.CustomResourceDefinitionSpecBuilder(io.dekorate.deps.kubernetes.api.model.apiextensions.CustomResourceDefinitionSpec);
    Code:
       0: aload_0
       1: aload_1
       2: iconst_1
       3: invokestatic  #21                 // Method java/lang/Boolean.valueOf:(Z)Ljava/lang/Boolean;
       6: invokespecial #33                 // Method "<init>":(Lio/dekorate/deps/kubernetes/api/model/apiextensions/CustomResourceDefinitionSpec;Ljava/lang/Boolean;)V
       9: return

  public io.dekorate.deps.kubernetes.api.model.apiextensions.CustomResourceDefinitionSpecBuilder(io.dekorate.deps.kubernetes.api.model.apiextensions.CustomResourceDefinitionSpec, java.lang.Boolean);
    Code:
       0: aload_0
       1: invokespecial #48                 // Method io/dekorate/deps/kubernetes/api/model/apiextensions/CustomResourceDefinitionSpecFluentImpl."<init>":()V
       4: aload_0
       5: aload_0
       6: putfield      #50                 // Field fluent:Lio/dekorate/deps/kubernetes/api/model/apiextensions/CustomResourceDefinitionSpecFluent;
       9: aload_0
      10: aload_1
      11: invokevirtual #54                 // Method io/dekorate/deps/kubernetes/api/model/apiextensions/CustomResourceDefinitionSpec.getAdditionalPrinterColumns:()Ljava/util/List;
      14: invokevirtual #130                // Method withAdditionalPrinterColumns:(Ljava/util/List;)Lio/dekorate/deps/kubernetes/api/model/apiextensions/CustomResourceDefinitionSpecFluent;
      17: pop
      18: aload_0
      19: aload_1
      20: invokevirtual #64                 // Method io/dekorate/deps/kubernetes/api/model/apiextensions/CustomResourceDefinitionSpec.getConversion:()Lio/dekorate/deps/kubernetes/api/model/apiextensions/CustomResourceConversion;
      23: invokevirtual #131                // Method withConversion:(Lio/dekorate/deps/kubernetes/api/model/apiextensions/CustomResourceConversion;)Lio/dekorate/deps/kubernetes/api/model/apiextensions/CustomResourceDefinitionSpecFluent;
      26: pop
      27: aload_0
      28: aload_1
      29: invokevirtual #72                 // Method io/dekorate/deps/kubernetes/api/model/apiextensions/CustomResourceDefinitionSpec.getGroup:()Ljava/lang/String;
      32: invokevirtual #132                // Method withGroup:(Ljava/lang/String;)Lio/dekorate/deps/kubernetes/api/model/apiextensions/CustomResourceDefinitionSpecFluent;
      35: pop
      36: aload_0
      37: aload_1
      38: invokevirtual #80                 // Method io/dekorate/deps/kubernetes/api/model/apiextensions/CustomResourceDefinitionSpec.getNames:()Lio/dekorate/deps/kubernetes/api/model/apiextensions/CustomResourceDefinitionNames;
      41: invokevirtual #133                // Method withNames:(Lio/dekorate/deps/kubernetes/api/model/apiextensions/CustomResourceDefinitionNames;)Lio/dekorate/deps/kubernetes/api/model/apiextensions/CustomResourceDefinitionSpecFluent;
      44: pop
      45: aload_0
      46: aload_1
      47: invokevirtual #88                 // Method io/dekorate/deps/kubernetes/api/model/apiextensions/CustomResourceDefinitionSpec.getPreserveUnknownFields:()Ljava/lang/Boolean;
      50: invokevirtual #134                // Method withPreserveUnknownFields:(Ljava/lang/Boolean;)Lio/dekorate/deps/kubernetes/api/model/apiextensions/CustomResourceDefinitionSpecFluent;
      53: pop
      54: aload_0
      55: aload_1
      56: invokevirtual #95                 // Method io/dekorate/deps/kubernetes/api/model/apiextensions/CustomResourceDefinitionSpec.getScope:()Ljava/lang/String;
      59: invokevirtual #135                // Method withScope:(Ljava/lang/String;)Lio/dekorate/deps/kubernetes/api/model/apiextensions/CustomResourceDefinitionSpecFluent;
      62: pop
      63: aload_0
      64: aload_1
      65: invokevirtual #102                // Method io/dekorate/deps/kubernetes/api/model/apiextensions/CustomResourceDefinitionSpec.getSubresources:()Lio/dekorate/deps/kubernetes/api/model/apiextensions/CustomResourceSubresources;
      68: invokevirtual #136                // Method withSubresources:(Lio/dekorate/deps/kubernetes/api/model/apiextensions/CustomResourceSubresources;)Lio/dekorate/deps/kubernetes/api/model/apiextensions/CustomResourceDefinitionSpecFluent;
      71: pop
      72: aload_0
      73: aload_1
      74: invokevirtual #110                // Method io/dekorate/deps/kubernetes/api/model/apiextensions/CustomResourceDefinitionSpec.getValidation:()Lio/dekorate/deps/kubernetes/api/model/apiextensions/CustomResourceValidation;
      77: invokevirtual #137                // Method withValidation:(Lio/dekorate/deps/kubernetes/api/model/apiextensions/CustomResourceValidation;)Lio/dekorate/deps/kubernetes/api/model/apiextensions/CustomResourceDefinitionSpecFluent;
      80: pop
      81: aload_0
      82: aload_1
      83: invokevirtual #117                // Method io/dekorate/deps/kubernetes/api/model/apiextensions/CustomResourceDefinitionSpec.getVersion:()Ljava/lang/String;
      86: invokevirtual #138                // Method withVersion:(Ljava/lang/String;)Lio/dekorate/deps/kubernetes/api/model/apiextensions/CustomResourceDefinitionSpecFluent;
      89: pop
      90: aload_0
      91: aload_1
      92: invokevirtual #123                // Method io/dekorate/deps/kubernetes/api/model/apiextensions/CustomResourceDefinitionSpec.getVersions:()Ljava/util/List;
      95: invokevirtual #139                // Method withVersions:(Ljava/util/List;)Lio/dekorate/deps/kubernetes/api/model/apiextensions/CustomResourceDefinitionSpecFluent;
      98: pop
      99: aload_0
     100: aload_2
     101: putfield      #128                // Field validationEnabled:Ljava/lang/Boolean;
     104: return

  public io.dekorate.deps.kubernetes.api.model.apiextensions.CustomResourceDefinitionSpec build();
    Code:
       0: new           #28                 // class io/dekorate/deps/kubernetes/api/model/apiextensions/CustomResourceDefinitionSpec
       3: dup
       4: aload_0
       5: getfield      #50                 // Field fluent:Lio/dekorate/deps/kubernetes/api/model/apiextensions/CustomResourceDefinitionSpecFluent;
       8: invokeinterface #142,  1          // InterfaceMethod io/dekorate/deps/kubernetes/api/model/apiextensions/CustomResourceDefinitionSpecFluent.getAdditionalPrinterColumns:()Ljava/util/List;
      13: aload_0
      14: getfield      #50                 // Field fluent:Lio/dekorate/deps/kubernetes/api/model/apiextensions/CustomResourceDefinitionSpecFluent;
      17: invokeinterface #143,  1          // InterfaceMethod io/dekorate/deps/kubernetes/api/model/apiextensions/CustomResourceDefinitionSpecFluent.getConversion:()Lio/dekorate/deps/kubernetes/api/model/apiextensions/CustomResourceConversion;
      22: aload_0
      23: getfield      #50                 // Field fluent:Lio/dekorate/deps/kubernetes/api/model/apiextensions/CustomResourceDefinitionSpecFluent;
      26: invokeinterface #144,  1          // InterfaceMethod io/dekorate/deps/kubernetes/api/model/apiextensions/CustomResourceDefinitionSpecFluent.getGroup:()Ljava/lang/String;
      31: aload_0
      32: getfield      #50                 // Field fluent:Lio/dekorate/deps/kubernetes/api/model/apiextensions/CustomResourceDefinitionSpecFluent;
      35: invokeinterface #145,  1          // InterfaceMethod io/dekorate/deps/kubernetes/api/model/apiextensions/CustomResourceDefinitionSpecFluent.getNames:()Lio/dekorate/deps/kubernetes/api/model/apiextensions/CustomResourceDefinitionNames;
      40: aload_0
      41: getfield      #50                 // Field fluent:Lio/dekorate/deps/kubernetes/api/model/apiextensions/CustomResourceDefinitionSpecFluent;
      44: invokeinterface #148,  1          // InterfaceMethod io/dekorate/deps/kubernetes/api/model/apiextensions/CustomResourceDefinitionSpecFluent.isPreserveUnknownFields:()Ljava/lang/Boolean;
      49: aload_0
      50: getfield      #50                 // Field fluent:Lio/dekorate/deps/kubernetes/api/model/apiextensions/CustomResourceDefinitionSpecFluent;
      53: invokeinterface #149,  1          // InterfaceMethod io/dekorate/deps/kubernetes/api/model/apiextensions/CustomResourceDefinitionSpecFluent.getScope:()Ljava/lang/String;
      58: aload_0
      59: getfield      #50                 // Field fluent:Lio/dekorate/deps/kubernetes/api/model/apiextensions/CustomResourceDefinitionSpecFluent;
      62: invokeinterface #150,  1          // InterfaceMethod io/dekorate/deps/kubernetes/api/model/apiextensions/CustomResourceDefinitionSpecFluent.getSubresources:()Lio/dekorate/deps/kubernetes/api/model/apiextensions/CustomResourceSubresources;
      67: aload_0
      68: getfield      #50                 // Field fluent:Lio/dekorate/deps/kubernetes/api/model/apiextensions/CustomResourceDefinitionSpecFluent;
      71: invokeinterface #151,  1          // InterfaceMethod io/dekorate/deps/kubernetes/api/model/apiextensions/CustomResourceDefinitionSpecFluent.getValidation:()Lio/dekorate/deps/kubernetes/api/model/apiextensions/CustomResourceValidation;
      76: aload_0
      77: getfield      #50                 // Field fluent:Lio/dekorate/deps/kubernetes/api/model/apiextensions/CustomResourceDefinitionSpecFluent;
      80: invokeinterface #152,  1          // InterfaceMethod io/dekorate/deps/kubernetes/api/model/apiextensions/CustomResourceDefinitionSpecFluent.getVersion:()Ljava/lang/String;
      85: aload_0
      86: getfield      #50                 // Field fluent:Lio/dekorate/deps/kubernetes/api/model/apiextensions/CustomResourceDefinitionSpecFluent;
      89: invokeinterface #153,  1          // InterfaceMethod io/dekorate/deps/kubernetes/api/model/apiextensions/CustomResourceDefinitionSpecFluent.getVersions:()Ljava/util/List;
      94: invokespecial #156                // Method io/dekorate/deps/kubernetes/api/model/apiextensions/CustomResourceDefinitionSpec."<init>":(Ljava/util/List;Lio/dekorate/deps/kubernetes/api/model/apiextensions/CustomResourceConversion;Ljava/lang/String;Lio/dekorate/deps/kubernetes/api/model/apiextensions/CustomResourceDefinitionNames;Ljava/lang/Boolean;Ljava/lang/String;Lio/dekorate/deps/kubernetes/api/model/apiextensions/CustomResourceSubresources;Lio/dekorate/deps/kubernetes/api/model/apiextensions/CustomResourceValidation;Ljava/lang/String;Ljava/util/List;)V
      97: astore_1
      98: aload_1
      99: areturn

  public boolean equals(java.lang.Object);
    Code:
       0: aload_0
       1: aload_1
       2: if_acmpne     7
       5: iconst_1
       6: ireturn
       7: aload_1
       8: ifnull        22
      11: aload_0
      12: invokevirtual #165                // Method java/lang/Object.getClass:()Ljava/lang/Class;
      15: aload_1
      16: invokevirtual #165                // Method java/lang/Object.getClass:()Ljava/lang/Class;
      19: if_acmpeq     24
      22: iconst_0
      23: ireturn
      24: aload_0
      25: aload_1
      26: invokespecial #167                // Method io/dekorate/deps/kubernetes/api/model/apiextensions/CustomResourceDefinitionSpecFluentImpl.equals:(Ljava/lang/Object;)Z
      29: ifne          34
      32: iconst_0
      33: ireturn
      34: aload_1
      35: checkcast     #2                  // class io/dekorate/deps/kubernetes/api/model/apiextensions/CustomResourceDefinitionSpecBuilder
      38: astore_2
      39: aload_0
      40: getfield      #50                 // Field fluent:Lio/dekorate/deps/kubernetes/api/model/apiextensions/CustomResourceDefinitionSpecFluent;
      43: ifnull        71
      46: aload_0
      47: getfield      #50                 // Field fluent:Lio/dekorate/deps/kubernetes/api/model/apiextensions/CustomResourceDefinitionSpecFluent;
      50: aload_0
      51: if_acmpeq     71
      54: aload_0
      55: getfield      #50                 // Field fluent:Lio/dekorate/deps/kubernetes/api/model/apiextensions/CustomResourceDefinitionSpecFluent;
      58: aload_2
      59: getfield      #50                 // Field fluent:Lio/dekorate/deps/kubernetes/api/model/apiextensions/CustomResourceDefinitionSpecFluent;
      62: invokevirtual #168                // Method java/lang/Object.equals:(Ljava/lang/Object;)Z
      65: ifne          88
      68: goto          86
      71: aload_2
      72: getfield      #50                 // Field fluent:Lio/dekorate/deps/kubernetes/api/model/apiextensions/CustomResourceDefinitionSpecFluent;
      75: ifnull        88
      78: aload_0
      79: getfield      #50                 // Field fluent:Lio/dekorate/deps/kubernetes/api/model/apiextensions/CustomResourceDefinitionSpecFluent;
      82: aload_0
      83: if_acmpeq     88
      86: iconst_0
      87: ireturn
      88: aload_0
      89: getfield      #128                // Field validationEnabled:Ljava/lang/Boolean;
      92: ifnull        112
      95: aload_0
      96: getfield      #128                // Field validationEnabled:Ljava/lang/Boolean;
      99: aload_2
     100: getfield      #128                // Field validationEnabled:Ljava/lang/Boolean;
     103: invokevirtual #169                // Method java/lang/Boolean.equals:(Ljava/lang/Object;)Z
     106: ifne          121
     109: goto          119
     112: aload_2
     113: getfield      #128                // Field validationEnabled:Ljava/lang/Boolean;
     116: ifnull        121
     119: iconst_0
     120: ireturn
     121: iconst_1
     122: ireturn

  public java.lang.Object build();
    Code:
       0: aload_0
       1: invokevirtual #175                // Method build:()Lio/dekorate/deps/kubernetes/api/model/apiextensions/CustomResourceDefinitionSpec;
       4: areturn
}
