Compiled from "DoneableCustomResourceDefinitionNames.java"
public class io.dekorate.deps.kubernetes.api.model.apiextensions.DoneableCustomResourceDefinitionNames extends io.dekorate.deps.kubernetes.api.model.apiextensions.CustomResourceDefinitionNamesFluentImpl<io.dekorate.deps.kubernetes.api.model.apiextensions.DoneableCustomResourceDefinitionNames> implements io.dekorate.deps.kubernetes.api.model.Doneable<io.dekorate.deps.kubernetes.api.model.apiextensions.CustomResourceDefinitionNames> {
  private final io.dekorate.deps.kubernetes.api.model.apiextensions.CustomResourceDefinitionNamesBuilder builder;

  private final io.dekorate.deps.kubernetes.api.builder.Function<io.dekorate.deps.kubernetes.api.model.apiextensions.CustomResourceDefinitionNames, io.dekorate.deps.kubernetes.api.model.apiextensions.CustomResourceDefinitionNames> function;

  public io.dekorate.deps.kubernetes.api.model.apiextensions.DoneableCustomResourceDefinitionNames(io.dekorate.deps.kubernetes.api.builder.Function<io.dekorate.deps.kubernetes.api.model.apiextensions.CustomResourceDefinitionNames, io.dekorate.deps.kubernetes.api.model.apiextensions.CustomResourceDefinitionNames>);
    Code:
       0: aload_0
       1: invokespecial #21                 // Method io/dekorate/deps/kubernetes/api/model/apiextensions/CustomResourceDefinitionNamesFluentImpl."<init>":()V
       4: aload_0
       5: new           #23                 // class io/dekorate/deps/kubernetes/api/model/apiextensions/CustomResourceDefinitionNamesBuilder
       8: dup
       9: aload_0
      10: invokespecial #26                 // Method io/dekorate/deps/kubernetes/api/model/apiextensions/CustomResourceDefinitionNamesBuilder."<init>":(Lio/dekorate/deps/kubernetes/api/model/apiextensions/CustomResourceDefinitionNamesFluent;)V
      13: putfield      #28                 // Field builder:Lio/dekorate/deps/kubernetes/api/model/apiextensions/CustomResourceDefinitionNamesBuilder;
      16: aload_0
      17: aload_1
      18: putfield      #30                 // Field function:Lio/dekorate/deps/kubernetes/api/builder/Function;
      21: return

  public io.dekorate.deps.kubernetes.api.model.apiextensions.DoneableCustomResourceDefinitionNames(io.dekorate.deps.kubernetes.api.model.apiextensions.CustomResourceDefinitionNames, io.dekorate.deps.kubernetes.api.builder.Function<io.dekorate.deps.kubernetes.api.model.apiextensions.CustomResourceDefinitionNames, io.dekorate.deps.kubernetes.api.model.apiextensions.CustomResourceDefinitionNames>);
    Code:
       0: aload_0
       1: aload_1
       2: invokespecial #37                 // Method io/dekorate/deps/kubernetes/api/model/apiextensions/CustomResourceDefinitionNamesFluentImpl."<init>":(Lio/dekorate/deps/kubernetes/api/model/apiextensions/CustomResourceDefinitionNames;)V
       5: aload_0
       6: new           #23                 // class io/dekorate/deps/kubernetes/api/model/apiextensions/CustomResourceDefinitionNamesBuilder
       9: dup
      10: aload_0
      11: aload_1
      12: invokespecial #40                 // Method io/dekorate/deps/kubernetes/api/model/apiextensions/CustomResourceDefinitionNamesBuilder."<init>":(Lio/dekorate/deps/kubernetes/api/model/apiextensions/CustomResourceDefinitionNamesFluent;Lio/dekorate/deps/kubernetes/api/model/apiextensions/CustomResourceDefinitionNames;)V
      15: putfield      #28                 // Field builder:Lio/dekorate/deps/kubernetes/api/model/apiextensions/CustomResourceDefinitionNamesBuilder;
      18: aload_0
      19: aload_2
      20: putfield      #30                 // Field function:Lio/dekorate/deps/kubernetes/api/builder/Function;
      23: return

  public io.dekorate.deps.kubernetes.api.model.apiextensions.DoneableCustomResourceDefinitionNames(io.dekorate.deps.kubernetes.api.model.apiextensions.CustomResourceDefinitionNames);
    Code:
       0: aload_0
       1: aload_1
       2: invokespecial #37                 // Method io/dekorate/deps/kubernetes/api/model/apiextensions/CustomResourceDefinitionNamesFluentImpl."<init>":(Lio/dekorate/deps/kubernetes/api/model/apiextensions/CustomResourceDefinitionNames;)V
       5: aload_0
       6: new           #23                 // class io/dekorate/deps/kubernetes/api/model/apiextensions/CustomResourceDefinitionNamesBuilder
       9: dup
      10: aload_0
      11: aload_1
      12: invokespecial #40                 // Method io/dekorate/deps/kubernetes/api/model/apiextensions/CustomResourceDefinitionNamesBuilder."<init>":(Lio/dekorate/deps/kubernetes/api/model/apiextensions/CustomResourceDefinitionNamesFluent;Lio/dekorate/deps/kubernetes/api/model/apiextensions/CustomResourceDefinitionNames;)V
      15: putfield      #28                 // Field builder:Lio/dekorate/deps/kubernetes/api/model/apiextensions/CustomResourceDefinitionNamesBuilder;
      18: aload_0
      19: new           #10                 // class io/dekorate/deps/kubernetes/api/model/apiextensions/DoneableCustomResourceDefinitionNames$1
      22: dup
      23: aload_0
      24: invokespecial #45                 // Method io/dekorate/deps/kubernetes/api/model/apiextensions/DoneableCustomResourceDefinitionNames$1."<init>":(Lio/dekorate/deps/kubernetes/api/model/apiextensions/DoneableCustomResourceDefinitionNames;)V
      27: putfield      #30                 // Field function:Lio/dekorate/deps/kubernetes/api/builder/Function;
      30: return

  public io.dekorate.deps.kubernetes.api.model.apiextensions.CustomResourceDefinitionNames done();
    Code:
       0: aload_0
       1: getfield      #30                 // Field function:Lio/dekorate/deps/kubernetes/api/builder/Function;
       4: aload_0
       5: getfield      #28                 // Field builder:Lio/dekorate/deps/kubernetes/api/model/apiextensions/CustomResourceDefinitionNamesBuilder;
       8: invokevirtual #50                 // Method io/dekorate/deps/kubernetes/api/model/apiextensions/CustomResourceDefinitionNamesBuilder.build:()Lio/dekorate/deps/kubernetes/api/model/apiextensions/CustomResourceDefinitionNames;
      11: invokeinterface #56,  2           // InterfaceMethod io/dekorate/deps/kubernetes/api/builder/Function.apply:(Ljava/lang/Object;)Ljava/lang/Object;
      16: checkcast     #58                 // class io/dekorate/deps/kubernetes/api/model/apiextensions/CustomResourceDefinitionNames
      19: areturn

  public java.lang.Object done();
    Code:
       0: aload_0
       1: invokevirtual #61                 // Method done:()Lio/dekorate/deps/kubernetes/api/model/apiextensions/CustomResourceDefinitionNames;
       4: areturn
}
