Compiled from "JSONSchemaPropsOrBoolFluentImpl.java"
public class io.dekorate.deps.kubernetes.api.model.apiextensions.JSONSchemaPropsOrBoolFluentImpl$SchemaNestedImpl<N> extends io.dekorate.deps.kubernetes.api.model.apiextensions.JSONSchemaPropsFluentImpl<io.dekorate.deps.kubernetes.api.model.apiextensions.JSONSchemaPropsOrBoolFluent$SchemaNested<N>> implements io.dekorate.deps.kubernetes.api.model.apiextensions.JSONSchemaPropsOrBoolFluent$SchemaNested<N>, io.dekorate.deps.kubernetes.api.builder.Nested<N> {
  private final io.dekorate.deps.kubernetes.api.model.apiextensions.JSONSchemaPropsBuilder builder;

  final io.dekorate.deps.kubernetes.api.model.apiextensions.JSONSchemaPropsOrBoolFluentImpl this$0;

  io.dekorate.deps.kubernetes.api.model.apiextensions.JSONSchemaPropsOrBoolFluentImpl$SchemaNestedImpl(io.dekorate.deps.kubernetes.api.model.apiextensions.JSONSchemaPropsOrBoolFluentImpl, io.dekorate.deps.kubernetes.api.model.apiextensions.JSONSchemaProps);
    Code:
       0: aload_0
       1: aload_1
       2: putfield      #24                 // Field this$0:Lio/dekorate/deps/kubernetes/api/model/apiextensions/JSONSchemaPropsOrBoolFluentImpl;
       5: aload_0
       6: invokespecial #27                 // Method io/dekorate/deps/kubernetes/api/model/apiextensions/JSONSchemaPropsFluentImpl."<init>":()V
       9: aload_0
      10: new           #29                 // class io/dekorate/deps/kubernetes/api/model/apiextensions/JSONSchemaPropsBuilder
      13: dup
      14: aload_0
      15: aload_2
      16: invokespecial #32                 // Method io/dekorate/deps/kubernetes/api/model/apiextensions/JSONSchemaPropsBuilder."<init>":(Lio/dekorate/deps/kubernetes/api/model/apiextensions/JSONSchemaPropsFluent;Lio/dekorate/deps/kubernetes/api/model/apiextensions/JSONSchemaProps;)V
      19: putfield      #34                 // Field builder:Lio/dekorate/deps/kubernetes/api/model/apiextensions/JSONSchemaPropsBuilder;
      22: return

  io.dekorate.deps.kubernetes.api.model.apiextensions.JSONSchemaPropsOrBoolFluentImpl$SchemaNestedImpl(io.dekorate.deps.kubernetes.api.model.apiextensions.JSONSchemaPropsOrBoolFluentImpl);
    Code:
       0: aload_0
       1: aload_1
       2: putfield      #24                 // Field this$0:Lio/dekorate/deps/kubernetes/api/model/apiextensions/JSONSchemaPropsOrBoolFluentImpl;
       5: aload_0
       6: invokespecial #27                 // Method io/dekorate/deps/kubernetes/api/model/apiextensions/JSONSchemaPropsFluentImpl."<init>":()V
       9: aload_0
      10: new           #29                 // class io/dekorate/deps/kubernetes/api/model/apiextensions/JSONSchemaPropsBuilder
      13: dup
      14: aload_0
      15: invokespecial #43                 // Method io/dekorate/deps/kubernetes/api/model/apiextensions/JSONSchemaPropsBuilder."<init>":(Lio/dekorate/deps/kubernetes/api/model/apiextensions/JSONSchemaPropsFluent;)V
      18: putfield      #34                 // Field builder:Lio/dekorate/deps/kubernetes/api/model/apiextensions/JSONSchemaPropsBuilder;
      21: return

  public N and();
    Code:
       0: aload_0
       1: getfield      #24                 // Field this$0:Lio/dekorate/deps/kubernetes/api/model/apiextensions/JSONSchemaPropsOrBoolFluentImpl;
       4: aload_0
       5: getfield      #34                 // Field builder:Lio/dekorate/deps/kubernetes/api/model/apiextensions/JSONSchemaPropsBuilder;
       8: invokevirtual #50                 // Method io/dekorate/deps/kubernetes/api/model/apiextensions/JSONSchemaPropsBuilder.build:()Lio/dekorate/deps/kubernetes/api/model/apiextensions/JSONSchemaProps;
      11: invokevirtual #54                 // Method io/dekorate/deps/kubernetes/api/model/apiextensions/JSONSchemaPropsOrBoolFluentImpl.withSchema:(Lio/dekorate/deps/kubernetes/api/model/apiextensions/JSONSchemaProps;)Lio/dekorate/deps/kubernetes/api/model/apiextensions/JSONSchemaPropsOrBoolFluent;
      14: areturn

  public N endSchema();
    Code:
       0: aload_0
       1: invokevirtual #57                 // Method and:()Ljava/lang/Object;
       4: areturn
}
