Compiled from "Mappe.java"
public class no.nav.tjeneste.virksomhet.oppgave.v3.informasjon.oppgave.Mappe {
  protected java.lang.String fagomradeKode;

  protected java.lang.String mappeId;

  protected java.lang.String mappeNavn;

  protected java.lang.String enhetId;

  protected java.lang.Integer versjon;

  protected no.nav.tjeneste.virksomhet.oppgave.v3.informasjon.oppgave.MappeUtvidelse1 utvidelse;

  public no.nav.tjeneste.virksomhet.oppgave.v3.informasjon.oppgave.Mappe();
    Code:
       0: aload_0
       1: invokespecial #1                  // Method java/lang/Object."<init>":()V
       4: return

  public java.lang.String getFagomradeKode();
    Code:
       0: aload_0
       1: getfield      #2                  // Field fagomradeKode:Ljava/lang/String;
       4: areturn

  public void setFagomradeKode(java.lang.String);
    Code:
       0: aload_0
       1: aload_1
       2: putfield      #2                  // Field fagomradeKode:Ljava/lang/String;
       5: return

  public java.lang.String getMappeId();
    Code:
       0: aload_0
       1: getfield      #3                  // Field mappeId:Ljava/lang/String;
       4: areturn

  public void setMappeId(java.lang.String);
    Code:
       0: aload_0
       1: aload_1
       2: putfield      #3                  // Field mappeId:Ljava/lang/String;
       5: return

  public java.lang.String getMappeNavn();
    Code:
       0: aload_0
       1: getfield      #4                  // Field mappeNavn:Ljava/lang/String;
       4: areturn

  public void setMappeNavn(java.lang.String);
    Code:
       0: aload_0
       1: aload_1
       2: putfield      #4                  // Field mappeNavn:Ljava/lang/String;
       5: return

  public java.lang.String getEnhetId();
    Code:
       0: aload_0
       1: getfield      #5                  // Field enhetId:Ljava/lang/String;
       4: areturn

  public void setEnhetId(java.lang.String);
    Code:
       0: aload_0
       1: aload_1
       2: putfield      #5                  // Field enhetId:Ljava/lang/String;
       5: return

  public java.lang.Integer getVersjon();
    Code:
       0: aload_0
       1: getfield      #6                  // Field versjon:Ljava/lang/Integer;
       4: areturn

  public void setVersjon(java.lang.Integer);
    Code:
       0: aload_0
       1: aload_1
       2: putfield      #6                  // Field versjon:Ljava/lang/Integer;
       5: return

  public no.nav.tjeneste.virksomhet.oppgave.v3.informasjon.oppgave.MappeUtvidelse1 getUtvidelse();
    Code:
       0: aload_0
       1: getfield      #7                  // Field utvidelse:Lno/nav/tjeneste/virksomhet/oppgave/v3/informasjon/oppgave/MappeUtvidelse1;
       4: areturn

  public void setUtvidelse(no.nav.tjeneste.virksomhet.oppgave.v3.informasjon.oppgave.MappeUtvidelse1);
    Code:
       0: aload_0
       1: aload_1
       2: putfield      #7                  // Field utvidelse:Lno/nav/tjeneste/virksomhet/oppgave/v3/informasjon/oppgave/MappeUtvidelse1;
       5: return
}
