Compiled from "ServletContextAttribute.java"
public class org.jboss.as.web.common.ServletContextAttribute {
  public static final org.jboss.as.server.deployment.AttachmentKey<org.jboss.as.server.deployment.AttachmentList<org.jboss.as.web.common.ServletContextAttribute>> ATTACHMENT_KEY;

  private final java.lang.String name;

  private final java.lang.Object value;

  public org.jboss.as.web.common.ServletContextAttribute(java.lang.String, java.lang.Object);
    Code:
       0: aload_0
       1: invokespecial #1                  // Method java/lang/Object."<init>":()V
       4: aload_0
       5: aload_1
       6: putfield      #2                  // Field name:Ljava/lang/String;
       9: aload_0
      10: aload_2
      11: putfield      #3                  // Field value:Ljava/lang/Object;
      14: return

  public java.lang.String getName();
    Code:
       0: aload_0
       1: getfield      #2                  // Field name:Ljava/lang/String;
       4: areturn

  public java.lang.Object getValue();
    Code:
       0: aload_0
       1: getfield      #3                  // Field value:Ljava/lang/Object;
       4: areturn

  static {};
    Code:
       0: ldc           #4                  // class org/jboss/as/web/common/ServletContextAttribute
       2: invokestatic  #5                  // Method org/jboss/as/server/deployment/AttachmentKey.createList:(Ljava/lang/Class;)Lorg/jboss/as/server/deployment/AttachmentKey;
       5: putstatic     #6                  // Field ATTACHMENT_KEY:Lorg/jboss/as/server/deployment/AttachmentKey;
       8: return
}
