Compiled from "BaseConfigFluentImpl.java"
public class io.dekorate.kubernetes.config.BaseConfigFluentImpl$GitRepoVolumesNestedImpl<N> extends io.dekorate.kubernetes.config.GitRepoVolumeFluentImpl<io.dekorate.kubernetes.config.BaseConfigFluent$GitRepoVolumesNested<N>> implements io.dekorate.kubernetes.config.BaseConfigFluent$GitRepoVolumesNested<N>, io.dekorate.deps.kubernetes.api.builder.Nested<N> {
  private final io.dekorate.kubernetes.config.GitRepoVolumeBuilder builder;

  private final int index;

  final io.dekorate.kubernetes.config.BaseConfigFluentImpl this$0;

  io.dekorate.kubernetes.config.BaseConfigFluentImpl$GitRepoVolumesNestedImpl(io.dekorate.kubernetes.config.BaseConfigFluentImpl, int, io.dekorate.kubernetes.config.GitRepoVolume);
    Code:
       0: aload_0
       1: aload_1
       2: putfield      #1                  // Field this$0:Lio/dekorate/kubernetes/config/BaseConfigFluentImpl;
       5: aload_0
       6: invokespecial #2                  // Method io/dekorate/kubernetes/config/GitRepoVolumeFluentImpl."<init>":()V
       9: aload_0
      10: iload_2
      11: putfield      #3                  // Field index:I
      14: aload_0
      15: new           #4                  // class io/dekorate/kubernetes/config/GitRepoVolumeBuilder
      18: dup
      19: aload_0
      20: aload_3
      21: invokespecial #5                  // Method io/dekorate/kubernetes/config/GitRepoVolumeBuilder."<init>":(Lio/dekorate/kubernetes/config/GitRepoVolumeFluent;Lio/dekorate/kubernetes/config/GitRepoVolume;)V
      24: putfield      #6                  // Field builder:Lio/dekorate/kubernetes/config/GitRepoVolumeBuilder;
      27: return

  io.dekorate.kubernetes.config.BaseConfigFluentImpl$GitRepoVolumesNestedImpl(io.dekorate.kubernetes.config.BaseConfigFluentImpl);
    Code:
       0: aload_0
       1: aload_1
       2: putfield      #1                  // Field this$0:Lio/dekorate/kubernetes/config/BaseConfigFluentImpl;
       5: aload_0
       6: invokespecial #2                  // Method io/dekorate/kubernetes/config/GitRepoVolumeFluentImpl."<init>":()V
       9: aload_0
      10: iconst_m1
      11: putfield      #3                  // Field index:I
      14: aload_0
      15: new           #4                  // class io/dekorate/kubernetes/config/GitRepoVolumeBuilder
      18: dup
      19: aload_0
      20: invokespecial #7                  // Method io/dekorate/kubernetes/config/GitRepoVolumeBuilder."<init>":(Lio/dekorate/kubernetes/config/GitRepoVolumeFluent;)V
      23: putfield      #6                  // Field builder:Lio/dekorate/kubernetes/config/GitRepoVolumeBuilder;
      26: return

  public N and();
    Code:
       0: aload_0
       1: getfield      #1                  // Field this$0:Lio/dekorate/kubernetes/config/BaseConfigFluentImpl;
       4: aload_0
       5: getfield      #3                  // Field index:I
       8: aload_0
       9: getfield      #6                  // Field builder:Lio/dekorate/kubernetes/config/GitRepoVolumeBuilder;
      12: invokevirtual #8                  // Method io/dekorate/kubernetes/config/GitRepoVolumeBuilder.build:()Lio/dekorate/kubernetes/config/EditableGitRepoVolume;
      15: invokevirtual #9                  // Method io/dekorate/kubernetes/config/BaseConfigFluentImpl.setToGitRepoVolumes:(ILio/dekorate/kubernetes/config/GitRepoVolume;)Lio/dekorate/kubernetes/config/BaseConfigFluent;
      18: areturn

  public N endGitRepoVolume();
    Code:
       0: aload_0
       1: invokevirtual #10                 // Method and:()Ljava/lang/Object;
       4: areturn
}
