Compiled from "GitRepoVolumeBuilder.java"
public class io.dekorate.kubernetes.config.GitRepoVolumeBuilder extends io.dekorate.kubernetes.config.GitRepoVolumeFluentImpl<io.dekorate.kubernetes.config.GitRepoVolumeBuilder> implements io.dekorate.deps.kubernetes.api.builder.VisitableBuilder<io.dekorate.kubernetes.config.GitRepoVolume, io.dekorate.kubernetes.config.GitRepoVolumeBuilder> {
  io.dekorate.kubernetes.config.GitRepoVolumeFluent<?> fluent;

  java.lang.Boolean validationEnabled;

  public io.dekorate.kubernetes.config.GitRepoVolumeBuilder();
    Code:
       0: aload_0
       1: iconst_1
       2: invokestatic  #1                  // Method java/lang/Boolean.valueOf:(Z)Ljava/lang/Boolean;
       5: invokespecial #2                  // Method "<init>":(Ljava/lang/Boolean;)V
       8: return

  public io.dekorate.kubernetes.config.GitRepoVolumeBuilder(java.lang.Boolean);
    Code:
       0: aload_0
       1: new           #3                  // class io/dekorate/kubernetes/config/GitRepoVolume
       4: dup
       5: invokespecial #4                  // Method io/dekorate/kubernetes/config/GitRepoVolume."<init>":()V
       8: aload_1
       9: invokespecial #5                  // Method "<init>":(Lio/dekorate/kubernetes/config/GitRepoVolume;Ljava/lang/Boolean;)V
      12: return

  public io.dekorate.kubernetes.config.GitRepoVolumeBuilder(io.dekorate.kubernetes.config.GitRepoVolumeFluent<?>);
    Code:
       0: aload_0
       1: aload_1
       2: iconst_1
       3: invokestatic  #1                  // Method java/lang/Boolean.valueOf:(Z)Ljava/lang/Boolean;
       6: invokespecial #6                  // Method "<init>":(Lio/dekorate/kubernetes/config/GitRepoVolumeFluent;Ljava/lang/Boolean;)V
       9: return

  public io.dekorate.kubernetes.config.GitRepoVolumeBuilder(io.dekorate.kubernetes.config.GitRepoVolumeFluent<?>, java.lang.Boolean);
    Code:
       0: aload_0
       1: aload_1
       2: new           #3                  // class io/dekorate/kubernetes/config/GitRepoVolume
       5: dup
       6: invokespecial #4                  // Method io/dekorate/kubernetes/config/GitRepoVolume."<init>":()V
       9: aload_2
      10: invokespecial #7                  // Method "<init>":(Lio/dekorate/kubernetes/config/GitRepoVolumeFluent;Lio/dekorate/kubernetes/config/GitRepoVolume;Ljava/lang/Boolean;)V
      13: return

  public io.dekorate.kubernetes.config.GitRepoVolumeBuilder(io.dekorate.kubernetes.config.GitRepoVolumeFluent<?>, io.dekorate.kubernetes.config.GitRepoVolume);
    Code:
       0: aload_0
       1: aload_1
       2: aload_2
       3: iconst_1
       4: invokestatic  #1                  // Method java/lang/Boolean.valueOf:(Z)Ljava/lang/Boolean;
       7: invokespecial #7                  // Method "<init>":(Lio/dekorate/kubernetes/config/GitRepoVolumeFluent;Lio/dekorate/kubernetes/config/GitRepoVolume;Ljava/lang/Boolean;)V
      10: return

  public io.dekorate.kubernetes.config.GitRepoVolumeBuilder(io.dekorate.kubernetes.config.GitRepoVolumeFluent<?>, io.dekorate.kubernetes.config.GitRepoVolume, java.lang.Boolean);
    Code:
       0: aload_0
       1: invokespecial #8                  // Method io/dekorate/kubernetes/config/GitRepoVolumeFluentImpl."<init>":()V
       4: aload_0
       5: aload_1
       6: putfield      #9                  // Field fluent:Lio/dekorate/kubernetes/config/GitRepoVolumeFluent;
       9: aload_1
      10: aload_2
      11: invokevirtual #10                 // Method io/dekorate/kubernetes/config/GitRepoVolume.getVolumeName:()Ljava/lang/String;
      14: invokeinterface #11,  2           // InterfaceMethod io/dekorate/kubernetes/config/GitRepoVolumeFluent.withVolumeName:(Ljava/lang/String;)Lio/dekorate/kubernetes/config/GitRepoVolumeFluent;
      19: pop
      20: aload_1
      21: aload_2
      22: invokevirtual #12                 // Method io/dekorate/kubernetes/config/GitRepoVolume.getRepository:()Ljava/lang/String;
      25: invokeinterface #13,  2           // InterfaceMethod io/dekorate/kubernetes/config/GitRepoVolumeFluent.withRepository:(Ljava/lang/String;)Lio/dekorate/kubernetes/config/GitRepoVolumeFluent;
      30: pop
      31: aload_1
      32: aload_2
      33: invokevirtual #14                 // Method io/dekorate/kubernetes/config/GitRepoVolume.getDirectory:()Ljava/lang/String;
      36: invokeinterface #15,  2           // InterfaceMethod io/dekorate/kubernetes/config/GitRepoVolumeFluent.withDirectory:(Ljava/lang/String;)Lio/dekorate/kubernetes/config/GitRepoVolumeFluent;
      41: pop
      42: aload_1
      43: aload_2
      44: invokevirtual #16                 // Method io/dekorate/kubernetes/config/GitRepoVolume.getRevision:()Ljava/lang/String;
      47: invokeinterface #17,  2           // InterfaceMethod io/dekorate/kubernetes/config/GitRepoVolumeFluent.withRevision:(Ljava/lang/String;)Lio/dekorate/kubernetes/config/GitRepoVolumeFluent;
      52: pop
      53: aload_0
      54: aload_3
      55: putfield      #18                 // Field validationEnabled:Ljava/lang/Boolean;
      58: return

  public io.dekorate.kubernetes.config.GitRepoVolumeBuilder(io.dekorate.kubernetes.config.GitRepoVolume);
    Code:
       0: aload_0
       1: aload_1
       2: iconst_1
       3: invokestatic  #1                  // Method java/lang/Boolean.valueOf:(Z)Ljava/lang/Boolean;
       6: invokespecial #5                  // Method "<init>":(Lio/dekorate/kubernetes/config/GitRepoVolume;Ljava/lang/Boolean;)V
       9: return

  public io.dekorate.kubernetes.config.GitRepoVolumeBuilder(io.dekorate.kubernetes.config.GitRepoVolume, java.lang.Boolean);
    Code:
       0: aload_0
       1: invokespecial #8                  // Method io/dekorate/kubernetes/config/GitRepoVolumeFluentImpl."<init>":()V
       4: aload_0
       5: aload_0
       6: putfield      #9                  // Field fluent:Lio/dekorate/kubernetes/config/GitRepoVolumeFluent;
       9: aload_0
      10: aload_1
      11: invokevirtual #10                 // Method io/dekorate/kubernetes/config/GitRepoVolume.getVolumeName:()Ljava/lang/String;
      14: invokevirtual #19                 // Method withVolumeName:(Ljava/lang/String;)Lio/dekorate/kubernetes/config/GitRepoVolumeFluent;
      17: pop
      18: aload_0
      19: aload_1
      20: invokevirtual #12                 // Method io/dekorate/kubernetes/config/GitRepoVolume.getRepository:()Ljava/lang/String;
      23: invokevirtual #20                 // Method withRepository:(Ljava/lang/String;)Lio/dekorate/kubernetes/config/GitRepoVolumeFluent;
      26: pop
      27: aload_0
      28: aload_1
      29: invokevirtual #14                 // Method io/dekorate/kubernetes/config/GitRepoVolume.getDirectory:()Ljava/lang/String;
      32: invokevirtual #21                 // Method withDirectory:(Ljava/lang/String;)Lio/dekorate/kubernetes/config/GitRepoVolumeFluent;
      35: pop
      36: aload_0
      37: aload_1
      38: invokevirtual #16                 // Method io/dekorate/kubernetes/config/GitRepoVolume.getRevision:()Ljava/lang/String;
      41: invokevirtual #22                 // Method withRevision:(Ljava/lang/String;)Lio/dekorate/kubernetes/config/GitRepoVolumeFluent;
      44: pop
      45: aload_0
      46: aload_2
      47: putfield      #18                 // Field validationEnabled:Ljava/lang/Boolean;
      50: return

  public io.dekorate.kubernetes.config.EditableGitRepoVolume build();
    Code:
       0: new           #23                 // class io/dekorate/kubernetes/config/EditableGitRepoVolume
       3: dup
       4: aload_0
       5: getfield      #9                  // Field fluent:Lio/dekorate/kubernetes/config/GitRepoVolumeFluent;
       8: invokeinterface #24,  1           // InterfaceMethod io/dekorate/kubernetes/config/GitRepoVolumeFluent.getVolumeName:()Ljava/lang/String;
      13: aload_0
      14: getfield      #9                  // Field fluent:Lio/dekorate/kubernetes/config/GitRepoVolumeFluent;
      17: invokeinterface #25,  1           // InterfaceMethod io/dekorate/kubernetes/config/GitRepoVolumeFluent.getRepository:()Ljava/lang/String;
      22: aload_0
      23: getfield      #9                  // Field fluent:Lio/dekorate/kubernetes/config/GitRepoVolumeFluent;
      26: invokeinterface #26,  1           // InterfaceMethod io/dekorate/kubernetes/config/GitRepoVolumeFluent.getDirectory:()Ljava/lang/String;
      31: aload_0
      32: getfield      #9                  // Field fluent:Lio/dekorate/kubernetes/config/GitRepoVolumeFluent;
      35: invokeinterface #27,  1           // InterfaceMethod io/dekorate/kubernetes/config/GitRepoVolumeFluent.getRevision:()Ljava/lang/String;
      40: invokespecial #28                 // Method io/dekorate/kubernetes/config/EditableGitRepoVolume."<init>":(Ljava/lang/String;Ljava/lang/String;Ljava/lang/String;Ljava/lang/String;)V
      43: astore_1
      44: aload_1
      45: areturn

  public boolean equals(java.lang.Object);
    Code:
       0: aload_0
       1: aload_1
       2: if_acmpne     7
       5: iconst_1
       6: ireturn
       7: aload_1
       8: ifnull        22
      11: aload_0
      12: invokevirtual #29                 // Method java/lang/Object.getClass:()Ljava/lang/Class;
      15: aload_1
      16: invokevirtual #29                 // Method java/lang/Object.getClass:()Ljava/lang/Class;
      19: if_acmpeq     24
      22: iconst_0
      23: ireturn
      24: aload_0
      25: aload_1
      26: invokespecial #30                 // Method io/dekorate/kubernetes/config/GitRepoVolumeFluentImpl.equals:(Ljava/lang/Object;)Z
      29: ifne          34
      32: iconst_0
      33: ireturn
      34: aload_1
      35: checkcast     #31                 // class io/dekorate/kubernetes/config/GitRepoVolumeBuilder
      38: astore_2
      39: aload_0
      40: getfield      #9                  // Field fluent:Lio/dekorate/kubernetes/config/GitRepoVolumeFluent;
      43: ifnull        71
      46: aload_0
      47: getfield      #9                  // Field fluent:Lio/dekorate/kubernetes/config/GitRepoVolumeFluent;
      50: aload_0
      51: if_acmpeq     71
      54: aload_0
      55: getfield      #9                  // Field fluent:Lio/dekorate/kubernetes/config/GitRepoVolumeFluent;
      58: aload_2
      59: getfield      #9                  // Field fluent:Lio/dekorate/kubernetes/config/GitRepoVolumeFluent;
      62: invokevirtual #32                 // Method java/lang/Object.equals:(Ljava/lang/Object;)Z
      65: ifne          88
      68: goto          86
      71: aload_2
      72: getfield      #9                  // Field fluent:Lio/dekorate/kubernetes/config/GitRepoVolumeFluent;
      75: ifnull        88
      78: aload_0
      79: getfield      #9                  // Field fluent:Lio/dekorate/kubernetes/config/GitRepoVolumeFluent;
      82: aload_0
      83: if_acmpeq     88
      86: iconst_0
      87: ireturn
      88: aload_0
      89: getfield      #18                 // Field validationEnabled:Ljava/lang/Boolean;
      92: ifnull        112
      95: aload_0
      96: getfield      #18                 // Field validationEnabled:Ljava/lang/Boolean;
      99: aload_2
     100: getfield      #18                 // Field validationEnabled:Ljava/lang/Boolean;
     103: invokevirtual #33                 // Method java/lang/Boolean.equals:(Ljava/lang/Object;)Z
     106: ifne          121
     109: goto          119
     112: aload_2
     113: getfield      #18                 // Field validationEnabled:Ljava/lang/Boolean;
     116: ifnull        121
     119: iconst_0
     120: ireturn
     121: iconst_1
     122: ireturn

  public java.lang.Object build();
    Code:
       0: aload_0
       1: invokevirtual #34                 // Method build:()Lio/dekorate/kubernetes/config/EditableGitRepoVolume;
       4: areturn
}
