Compiled from "LabelBuilder.java"
public class io.dekorate.kubernetes.config.LabelBuilder extends io.dekorate.kubernetes.config.LabelFluentImpl<io.dekorate.kubernetes.config.LabelBuilder> implements io.dekorate.deps.kubernetes.api.builder.VisitableBuilder<io.dekorate.kubernetes.config.Label, io.dekorate.kubernetes.config.LabelBuilder> {
  io.dekorate.kubernetes.config.LabelFluent<?> fluent;

  java.lang.Boolean validationEnabled;

  public io.dekorate.kubernetes.config.LabelBuilder();
    Code:
       0: aload_0
       1: iconst_1
       2: invokestatic  #1                  // Method java/lang/Boolean.valueOf:(Z)Ljava/lang/Boolean;
       5: invokespecial #2                  // Method "<init>":(Ljava/lang/Boolean;)V
       8: return

  public io.dekorate.kubernetes.config.LabelBuilder(java.lang.Boolean);
    Code:
       0: aload_0
       1: new           #3                  // class io/dekorate/kubernetes/config/Label
       4: dup
       5: invokespecial #4                  // Method io/dekorate/kubernetes/config/Label."<init>":()V
       8: aload_1
       9: invokespecial #5                  // Method "<init>":(Lio/dekorate/kubernetes/config/Label;Ljava/lang/Boolean;)V
      12: return

  public io.dekorate.kubernetes.config.LabelBuilder(io.dekorate.kubernetes.config.LabelFluent<?>);
    Code:
       0: aload_0
       1: aload_1
       2: iconst_1
       3: invokestatic  #1                  // Method java/lang/Boolean.valueOf:(Z)Ljava/lang/Boolean;
       6: invokespecial #6                  // Method "<init>":(Lio/dekorate/kubernetes/config/LabelFluent;Ljava/lang/Boolean;)V
       9: return

  public io.dekorate.kubernetes.config.LabelBuilder(io.dekorate.kubernetes.config.LabelFluent<?>, java.lang.Boolean);
    Code:
       0: aload_0
       1: aload_1
       2: new           #3                  // class io/dekorate/kubernetes/config/Label
       5: dup
       6: invokespecial #4                  // Method io/dekorate/kubernetes/config/Label."<init>":()V
       9: aload_2
      10: invokespecial #7                  // Method "<init>":(Lio/dekorate/kubernetes/config/LabelFluent;Lio/dekorate/kubernetes/config/Label;Ljava/lang/Boolean;)V
      13: return

  public io.dekorate.kubernetes.config.LabelBuilder(io.dekorate.kubernetes.config.LabelFluent<?>, io.dekorate.kubernetes.config.Label);
    Code:
       0: aload_0
       1: aload_1
       2: aload_2
       3: iconst_1
       4: invokestatic  #1                  // Method java/lang/Boolean.valueOf:(Z)Ljava/lang/Boolean;
       7: invokespecial #7                  // Method "<init>":(Lio/dekorate/kubernetes/config/LabelFluent;Lio/dekorate/kubernetes/config/Label;Ljava/lang/Boolean;)V
      10: return

  public io.dekorate.kubernetes.config.LabelBuilder(io.dekorate.kubernetes.config.LabelFluent<?>, io.dekorate.kubernetes.config.Label, java.lang.Boolean);
    Code:
       0: aload_0
       1: invokespecial #8                  // Method io/dekorate/kubernetes/config/LabelFluentImpl."<init>":()V
       4: aload_0
       5: aload_1
       6: putfield      #9                  // Field fluent:Lio/dekorate/kubernetes/config/LabelFluent;
       9: aload_1
      10: aload_2
      11: invokevirtual #10                 // Method io/dekorate/kubernetes/config/Label.getKey:()Ljava/lang/String;
      14: invokeinterface #11,  2           // InterfaceMethod io/dekorate/kubernetes/config/LabelFluent.withKey:(Ljava/lang/String;)Lio/dekorate/kubernetes/config/LabelFluent;
      19: pop
      20: aload_1
      21: aload_2
      22: invokevirtual #12                 // Method io/dekorate/kubernetes/config/Label.getValue:()Ljava/lang/String;
      25: invokeinterface #13,  2           // InterfaceMethod io/dekorate/kubernetes/config/LabelFluent.withValue:(Ljava/lang/String;)Lio/dekorate/kubernetes/config/LabelFluent;
      30: pop
      31: aload_0
      32: aload_3
      33: putfield      #14                 // Field validationEnabled:Ljava/lang/Boolean;
      36: return

  public io.dekorate.kubernetes.config.LabelBuilder(io.dekorate.kubernetes.config.Label);
    Code:
       0: aload_0
       1: aload_1
       2: iconst_1
       3: invokestatic  #1                  // Method java/lang/Boolean.valueOf:(Z)Ljava/lang/Boolean;
       6: invokespecial #5                  // Method "<init>":(Lio/dekorate/kubernetes/config/Label;Ljava/lang/Boolean;)V
       9: return

  public io.dekorate.kubernetes.config.LabelBuilder(io.dekorate.kubernetes.config.Label, java.lang.Boolean);
    Code:
       0: aload_0
       1: invokespecial #8                  // Method io/dekorate/kubernetes/config/LabelFluentImpl."<init>":()V
       4: aload_0
       5: aload_0
       6: putfield      #9                  // Field fluent:Lio/dekorate/kubernetes/config/LabelFluent;
       9: aload_0
      10: aload_1
      11: invokevirtual #10                 // Method io/dekorate/kubernetes/config/Label.getKey:()Ljava/lang/String;
      14: invokevirtual #15                 // Method withKey:(Ljava/lang/String;)Lio/dekorate/kubernetes/config/LabelFluent;
      17: pop
      18: aload_0
      19: aload_1
      20: invokevirtual #12                 // Method io/dekorate/kubernetes/config/Label.getValue:()Ljava/lang/String;
      23: invokevirtual #16                 // Method withValue:(Ljava/lang/String;)Lio/dekorate/kubernetes/config/LabelFluent;
      26: pop
      27: aload_0
      28: aload_2
      29: putfield      #14                 // Field validationEnabled:Ljava/lang/Boolean;
      32: return

  public io.dekorate.kubernetes.config.EditableLabel build();
    Code:
       0: new           #17                 // class io/dekorate/kubernetes/config/EditableLabel
       3: dup
       4: aload_0
       5: getfield      #9                  // Field fluent:Lio/dekorate/kubernetes/config/LabelFluent;
       8: invokeinterface #18,  1           // InterfaceMethod io/dekorate/kubernetes/config/LabelFluent.getKey:()Ljava/lang/String;
      13: aload_0
      14: getfield      #9                  // Field fluent:Lio/dekorate/kubernetes/config/LabelFluent;
      17: invokeinterface #19,  1           // InterfaceMethod io/dekorate/kubernetes/config/LabelFluent.getValue:()Ljava/lang/String;
      22: invokespecial #20                 // Method io/dekorate/kubernetes/config/EditableLabel."<init>":(Ljava/lang/String;Ljava/lang/String;)V
      25: astore_1
      26: aload_1
      27: areturn

  public boolean equals(java.lang.Object);
    Code:
       0: aload_0
       1: aload_1
       2: if_acmpne     7
       5: iconst_1
       6: ireturn
       7: aload_1
       8: ifnull        22
      11: aload_0
      12: invokevirtual #21                 // Method java/lang/Object.getClass:()Ljava/lang/Class;
      15: aload_1
      16: invokevirtual #21                 // Method java/lang/Object.getClass:()Ljava/lang/Class;
      19: if_acmpeq     24
      22: iconst_0
      23: ireturn
      24: aload_0
      25: aload_1
      26: invokespecial #22                 // Method io/dekorate/kubernetes/config/LabelFluentImpl.equals:(Ljava/lang/Object;)Z
      29: ifne          34
      32: iconst_0
      33: ireturn
      34: aload_1
      35: checkcast     #23                 // class io/dekorate/kubernetes/config/LabelBuilder
      38: astore_2
      39: aload_0
      40: getfield      #9                  // Field fluent:Lio/dekorate/kubernetes/config/LabelFluent;
      43: ifnull        71
      46: aload_0
      47: getfield      #9                  // Field fluent:Lio/dekorate/kubernetes/config/LabelFluent;
      50: aload_0
      51: if_acmpeq     71
      54: aload_0
      55: getfield      #9                  // Field fluent:Lio/dekorate/kubernetes/config/LabelFluent;
      58: aload_2
      59: getfield      #9                  // Field fluent:Lio/dekorate/kubernetes/config/LabelFluent;
      62: invokevirtual #24                 // Method java/lang/Object.equals:(Ljava/lang/Object;)Z
      65: ifne          88
      68: goto          86
      71: aload_2
      72: getfield      #9                  // Field fluent:Lio/dekorate/kubernetes/config/LabelFluent;
      75: ifnull        88
      78: aload_0
      79: getfield      #9                  // Field fluent:Lio/dekorate/kubernetes/config/LabelFluent;
      82: aload_0
      83: if_acmpeq     88
      86: iconst_0
      87: ireturn
      88: aload_0
      89: getfield      #14                 // Field validationEnabled:Ljava/lang/Boolean;
      92: ifnull        112
      95: aload_0
      96: getfield      #14                 // Field validationEnabled:Ljava/lang/Boolean;
      99: aload_2
     100: getfield      #14                 // Field validationEnabled:Ljava/lang/Boolean;
     103: invokevirtual #25                 // Method java/lang/Boolean.equals:(Ljava/lang/Object;)Z
     106: ifne          121
     109: goto          119
     112: aload_2
     113: getfield      #14                 // Field validationEnabled:Ljava/lang/Boolean;
     116: ifnull        121
     119: iconst_0
     120: ireturn
     121: iconst_1
     122: ireturn

  public java.lang.Object build();
    Code:
       0: aload_0
       1: invokevirtual #26                 // Method build:()Lio/dekorate/kubernetes/config/EditableLabel;
       4: areturn
}
