Compiled from "ReplicationManager.java"
final class org.apache.activemq.artemis.core.replication.ReplicationManager$ADD_OPERATION_TYPE$1 extends org.apache.activemq.artemis.core.replication.ReplicationManager$ADD_OPERATION_TYPE {
  org.apache.activemq.artemis.core.replication.ReplicationManager$ADD_OPERATION_TYPE$1(java.lang.String, int);
    Code:
       0: aload_0
       1: aload_1
       2: iload_2
       3: aconst_null
       4: invokespecial #1                  // Method org/apache/activemq/artemis/core/replication/ReplicationManager$ADD_OPERATION_TYPE."<init>":(Ljava/lang/String;ILorg/apache/activemq/artemis/core/replication/ReplicationManager$1;)V
       7: return

  public boolean toBoolean();
    Code:
       0: iconst_1
       1: ireturn
}
