Compiled from "DCTypes.java"
public class org.apache.jena.vocabulary.DCTypes {
  private static final org.apache.jena.rdf.model.Model m_model;

  public static final java.lang.String NS;

  public static final org.apache.jena.rdf.model.Resource NAMESPACE;

  public static final org.apache.jena.rdf.model.Resource Collection;

  public static final org.apache.jena.rdf.model.Resource Dataset;

  public static final org.apache.jena.rdf.model.Resource Event;

  public static final org.apache.jena.rdf.model.Resource Image;

  public static final org.apache.jena.rdf.model.Resource InteractiveResource;

  public static final org.apache.jena.rdf.model.Resource MovingImage;

  public static final org.apache.jena.rdf.model.Resource PhysicalObject;

  public static final org.apache.jena.rdf.model.Resource Service;

  public static final org.apache.jena.rdf.model.Resource Software;

  public static final org.apache.jena.rdf.model.Resource Sound;

  public static final org.apache.jena.rdf.model.Resource StillImage;

  public static final org.apache.jena.rdf.model.Resource Text;

  public org.apache.jena.vocabulary.DCTypes();
    Code:
       0: aload_0
       1: invokespecial #1                  // Method java/lang/Object."<init>":()V
       4: return

  public static java.lang.String getURI();
    Code:
       0: ldc           #3                  // String http://purl.org/dc/dcmitype/
       2: areturn

  static {};
    Code:
       0: invokestatic  #4                  // Method org/apache/jena/rdf/model/ModelFactory.createDefaultModel:()Lorg/apache/jena/rdf/model/Model;
       3: putstatic     #5                  // Field m_model:Lorg/apache/jena/rdf/model/Model;
       6: getstatic     #5                  // Field m_model:Lorg/apache/jena/rdf/model/Model;
       9: ldc           #3                  // String http://purl.org/dc/dcmitype/
      11: invokeinterface #6,  2            // InterfaceMethod org/apache/jena/rdf/model/Model.createResource:(Ljava/lang/String;)Lorg/apache/jena/rdf/model/Resource;
      16: putstatic     #7                  // Field NAMESPACE:Lorg/apache/jena/rdf/model/Resource;
      19: getstatic     #5                  // Field m_model:Lorg/apache/jena/rdf/model/Model;
      22: ldc           #8                  // String http://purl.org/dc/dcmitype/Collection
      24: invokeinterface #6,  2            // InterfaceMethod org/apache/jena/rdf/model/Model.createResource:(Ljava/lang/String;)Lorg/apache/jena/rdf/model/Resource;
      29: putstatic     #9                  // Field Collection:Lorg/apache/jena/rdf/model/Resource;
      32: getstatic     #5                  // Field m_model:Lorg/apache/jena/rdf/model/Model;
      35: ldc           #10                 // String http://purl.org/dc/dcmitype/Dataset
      37: invokeinterface #6,  2            // InterfaceMethod org/apache/jena/rdf/model/Model.createResource:(Ljava/lang/String;)Lorg/apache/jena/rdf/model/Resource;
      42: putstatic     #11                 // Field Dataset:Lorg/apache/jena/rdf/model/Resource;
      45: getstatic     #5                  // Field m_model:Lorg/apache/jena/rdf/model/Model;
      48: ldc           #12                 // String http://purl.org/dc/dcmitype/Event
      50: invokeinterface #6,  2            // InterfaceMethod org/apache/jena/rdf/model/Model.createResource:(Ljava/lang/String;)Lorg/apache/jena/rdf/model/Resource;
      55: putstatic     #13                 // Field Event:Lorg/apache/jena/rdf/model/Resource;
      58: getstatic     #5                  // Field m_model:Lorg/apache/jena/rdf/model/Model;
      61: ldc           #14                 // String http://purl.org/dc/dcmitype/Image
      63: invokeinterface #6,  2            // InterfaceMethod org/apache/jena/rdf/model/Model.createResource:(Ljava/lang/String;)Lorg/apache/jena/rdf/model/Resource;
      68: putstatic     #15                 // Field Image:Lorg/apache/jena/rdf/model/Resource;
      71: getstatic     #5                  // Field m_model:Lorg/apache/jena/rdf/model/Model;
      74: ldc           #16                 // String http://purl.org/dc/dcmitype/InteractiveResource
      76: invokeinterface #6,  2            // InterfaceMethod org/apache/jena/rdf/model/Model.createResource:(Ljava/lang/String;)Lorg/apache/jena/rdf/model/Resource;
      81: putstatic     #17                 // Field InteractiveResource:Lorg/apache/jena/rdf/model/Resource;
      84: getstatic     #5                  // Field m_model:Lorg/apache/jena/rdf/model/Model;
      87: ldc           #18                 // String http://purl.org/dc/dcmitype/MovingImage
      89: invokeinterface #6,  2            // InterfaceMethod org/apache/jena/rdf/model/Model.createResource:(Ljava/lang/String;)Lorg/apache/jena/rdf/model/Resource;
      94: putstatic     #19                 // Field MovingImage:Lorg/apache/jena/rdf/model/Resource;
      97: getstatic     #5                  // Field m_model:Lorg/apache/jena/rdf/model/Model;
     100: ldc           #20                 // String http://purl.org/dc/dcmitype/PhysicalObject
     102: invokeinterface #6,  2            // InterfaceMethod org/apache/jena/rdf/model/Model.createResource:(Ljava/lang/String;)Lorg/apache/jena/rdf/model/Resource;
     107: putstatic     #21                 // Field PhysicalObject:Lorg/apache/jena/rdf/model/Resource;
     110: getstatic     #5                  // Field m_model:Lorg/apache/jena/rdf/model/Model;
     113: ldc           #22                 // String http://purl.org/dc/dcmitype/Service
     115: invokeinterface #6,  2            // InterfaceMethod org/apache/jena/rdf/model/Model.createResource:(Ljava/lang/String;)Lorg/apache/jena/rdf/model/Resource;
     120: putstatic     #23                 // Field Service:Lorg/apache/jena/rdf/model/Resource;
     123: getstatic     #5                  // Field m_model:Lorg/apache/jena/rdf/model/Model;
     126: ldc           #24                 // String http://purl.org/dc/dcmitype/Software
     128: invokeinterface #6,  2            // InterfaceMethod org/apache/jena/rdf/model/Model.createResource:(Ljava/lang/String;)Lorg/apache/jena/rdf/model/Resource;
     133: putstatic     #25                 // Field Software:Lorg/apache/jena/rdf/model/Resource;
     136: getstatic     #5                  // Field m_model:Lorg/apache/jena/rdf/model/Model;
     139: ldc           #26                 // String http://purl.org/dc/dcmitype/Sound
     141: invokeinterface #6,  2            // InterfaceMethod org/apache/jena/rdf/model/Model.createResource:(Ljava/lang/String;)Lorg/apache/jena/rdf/model/Resource;
     146: putstatic     #27                 // Field Sound:Lorg/apache/jena/rdf/model/Resource;
     149: getstatic     #5                  // Field m_model:Lorg/apache/jena/rdf/model/Model;
     152: ldc           #28                 // String http://purl.org/dc/dcmitype/StillImage
     154: invokeinterface #6,  2            // InterfaceMethod org/apache/jena/rdf/model/Model.createResource:(Ljava/lang/String;)Lorg/apache/jena/rdf/model/Resource;
     159: putstatic     #29                 // Field StillImage:Lorg/apache/jena/rdf/model/Resource;
     162: getstatic     #5                  // Field m_model:Lorg/apache/jena/rdf/model/Model;
     165: ldc           #30                 // String http://purl.org/dc/dcmitype/Text
     167: invokeinterface #6,  2            // InterfaceMethod org/apache/jena/rdf/model/Model.createResource:(Ljava/lang/String;)Lorg/apache/jena/rdf/model/Resource;
     172: putstatic     #31                 // Field Text:Lorg/apache/jena/rdf/model/Resource;
     175: return
}
