Compiled from "RDF.java"
public class org.apache.jena.vocabulary.RDF {
  public static final java.lang.String uri;

  public static final org.apache.jena.rdf.model.Resource Alt;

  public static final org.apache.jena.rdf.model.Resource Bag;

  public static final org.apache.jena.rdf.model.Resource Property;

  public static final org.apache.jena.rdf.model.Resource Seq;

  public static final org.apache.jena.rdf.model.Resource Statement;

  public static final org.apache.jena.rdf.model.Resource List;

  public static final org.apache.jena.rdf.model.Resource nil;

  public static final org.apache.jena.rdf.model.Property first;

  public static final org.apache.jena.rdf.model.Property rest;

  public static final org.apache.jena.rdf.model.Property subject;

  public static final org.apache.jena.rdf.model.Property predicate;

  public static final org.apache.jena.rdf.model.Property object;

  public static final org.apache.jena.rdf.model.Property type;

  public static final org.apache.jena.rdf.model.Property value;

  public static final org.apache.jena.rdf.model.Resource langString;

  public static final org.apache.jena.rdf.model.Resource HTML;

  public static final org.apache.jena.rdf.model.Resource xmlLiteral;

  public static final org.apache.jena.datatypes.RDFDatatype dtRDFHTML;

  public static final org.apache.jena.datatypes.RDFDatatype dtLangString;

  public static final org.apache.jena.datatypes.RDFDatatype dtXMLLiteral;

  public org.apache.jena.vocabulary.RDF();
    Code:
       0: aload_0
       1: invokespecial #1                  // Method java/lang/Object."<init>":()V
       4: return

  public static java.lang.String getURI();
    Code:
       0: ldc           #3                  // String http://www.w3.org/1999/02/22-rdf-syntax-ns#
       2: areturn

  protected static final org.apache.jena.rdf.model.Resource resource(java.lang.String);
    Code:
       0: new           #4                  // class java/lang/StringBuilder
       3: dup
       4: invokespecial #5                  // Method java/lang/StringBuilder."<init>":()V
       7: ldc           #3                  // String http://www.w3.org/1999/02/22-rdf-syntax-ns#
       9: invokevirtual #6                  // Method java/lang/StringBuilder.append:(Ljava/lang/String;)Ljava/lang/StringBuilder;
      12: aload_0
      13: invokevirtual #6                  // Method java/lang/StringBuilder.append:(Ljava/lang/String;)Ljava/lang/StringBuilder;
      16: invokevirtual #7                  // Method java/lang/StringBuilder.toString:()Ljava/lang/String;
      19: invokestatic  #8                  // Method org/apache/jena/rdf/model/ResourceFactory.createResource:(Ljava/lang/String;)Lorg/apache/jena/rdf/model/Resource;
      22: areturn

  protected static final org.apache.jena.rdf.model.Property property(java.lang.String);
    Code:
       0: ldc           #3                  // String http://www.w3.org/1999/02/22-rdf-syntax-ns#
       2: aload_0
       3: invokestatic  #9                  // Method org/apache/jena/rdf/model/ResourceFactory.createProperty:(Ljava/lang/String;Ljava/lang/String;)Lorg/apache/jena/rdf/model/Property;
       6: areturn

  public static org.apache.jena.rdf.model.Property li(int);
    Code:
       0: new           #4                  // class java/lang/StringBuilder
       3: dup
       4: invokespecial #5                  // Method java/lang/StringBuilder."<init>":()V
       7: ldc           #10                 // String _
       9: invokevirtual #6                  // Method java/lang/StringBuilder.append:(Ljava/lang/String;)Ljava/lang/StringBuilder;
      12: iload_0
      13: invokevirtual #11                 // Method java/lang/StringBuilder.append:(I)Ljava/lang/StringBuilder;
      16: invokevirtual #7                  // Method java/lang/StringBuilder.toString:()Ljava/lang/String;
      19: invokestatic  #12                 // Method property:(Ljava/lang/String;)Lorg/apache/jena/rdf/model/Property;
      22: areturn

  static {};
    Code:
       0: invokestatic  #13                 // Method org/apache/jena/vocabulary/RDF$Init.Alt:()Lorg/apache/jena/rdf/model/Resource;
       3: putstatic     #14                 // Field Alt:Lorg/apache/jena/rdf/model/Resource;
       6: invokestatic  #15                 // Method org/apache/jena/vocabulary/RDF$Init.Bag:()Lorg/apache/jena/rdf/model/Resource;
       9: putstatic     #16                 // Field Bag:Lorg/apache/jena/rdf/model/Resource;
      12: invokestatic  #17                 // Method org/apache/jena/vocabulary/RDF$Init._Property:()Lorg/apache/jena/rdf/model/Resource;
      15: putstatic     #18                 // Field Property:Lorg/apache/jena/rdf/model/Resource;
      18: invokestatic  #19                 // Method org/apache/jena/vocabulary/RDF$Init.Seq:()Lorg/apache/jena/rdf/model/Resource;
      21: putstatic     #20                 // Field Seq:Lorg/apache/jena/rdf/model/Resource;
      24: invokestatic  #21                 // Method org/apache/jena/vocabulary/RDF$Init.Statement:()Lorg/apache/jena/rdf/model/Resource;
      27: putstatic     #22                 // Field Statement:Lorg/apache/jena/rdf/model/Resource;
      30: invokestatic  #23                 // Method org/apache/jena/vocabulary/RDF$Init.List:()Lorg/apache/jena/rdf/model/Resource;
      33: putstatic     #24                 // Field List:Lorg/apache/jena/rdf/model/Resource;
      36: invokestatic  #25                 // Method org/apache/jena/vocabulary/RDF$Init.nil:()Lorg/apache/jena/rdf/model/Resource;
      39: putstatic     #26                 // Field nil:Lorg/apache/jena/rdf/model/Resource;
      42: invokestatic  #27                 // Method org/apache/jena/vocabulary/RDF$Init.first:()Lorg/apache/jena/rdf/model/Property;
      45: putstatic     #28                 // Field first:Lorg/apache/jena/rdf/model/Property;
      48: invokestatic  #29                 // Method org/apache/jena/vocabulary/RDF$Init.rest:()Lorg/apache/jena/rdf/model/Property;
      51: putstatic     #30                 // Field rest:Lorg/apache/jena/rdf/model/Property;
      54: invokestatic  #31                 // Method org/apache/jena/vocabulary/RDF$Init.subject:()Lorg/apache/jena/rdf/model/Property;
      57: putstatic     #32                 // Field subject:Lorg/apache/jena/rdf/model/Property;
      60: invokestatic  #33                 // Method org/apache/jena/vocabulary/RDF$Init.predicate:()Lorg/apache/jena/rdf/model/Property;
      63: putstatic     #34                 // Field predicate:Lorg/apache/jena/rdf/model/Property;
      66: invokestatic  #35                 // Method org/apache/jena/vocabulary/RDF$Init.object:()Lorg/apache/jena/rdf/model/Property;
      69: putstatic     #36                 // Field object:Lorg/apache/jena/rdf/model/Property;
      72: invokestatic  #37                 // Method org/apache/jena/vocabulary/RDF$Init.type:()Lorg/apache/jena/rdf/model/Property;
      75: putstatic     #38                 // Field type:Lorg/apache/jena/rdf/model/Property;
      78: invokestatic  #39                 // Method org/apache/jena/vocabulary/RDF$Init.value:()Lorg/apache/jena/rdf/model/Property;
      81: putstatic     #40                 // Field value:Lorg/apache/jena/rdf/model/Property;
      84: invokestatic  #41                 // Method org/apache/jena/vocabulary/RDF$Init.langString:()Lorg/apache/jena/rdf/model/Resource;
      87: putstatic     #42                 // Field langString:Lorg/apache/jena/rdf/model/Resource;
      90: invokestatic  #43                 // Method org/apache/jena/vocabulary/RDF$Init.HTML:()Lorg/apache/jena/rdf/model/Resource;
      93: putstatic     #44                 // Field HTML:Lorg/apache/jena/rdf/model/Resource;
      96: invokestatic  #45                 // Method org/apache/jena/vocabulary/RDF$Init.xmlLiteral:()Lorg/apache/jena/rdf/model/Resource;
      99: putstatic     #46                 // Field xmlLiteral:Lorg/apache/jena/rdf/model/Resource;
     102: invokestatic  #47                 // Method org/apache/jena/vocabulary/RDF$Init.dtRDFHTML:()Lorg/apache/jena/datatypes/RDFDatatype;
     105: putstatic     #48                 // Field dtRDFHTML:Lorg/apache/jena/datatypes/RDFDatatype;
     108: invokestatic  #49                 // Method org/apache/jena/vocabulary/RDF$Init.dtLangString:()Lorg/apache/jena/datatypes/RDFDatatype;
     111: putstatic     #50                 // Field dtLangString:Lorg/apache/jena/datatypes/RDFDatatype;
     114: invokestatic  #51                 // Method org/apache/jena/vocabulary/RDF$Init.dtXMLLiteral:()Lorg/apache/jena/datatypes/RDFDatatype;
     117: putstatic     #52                 // Field dtXMLLiteral:Lorg/apache/jena/datatypes/RDFDatatype;
     120: return
}
