Compiled from "GaussianCurveFitter.java"
final class org.apache.commons.math3.fitting.GaussianCurveFitter$1 extends org.apache.commons.math3.analysis.function.Gaussian$Parametric {
  org.apache.commons.math3.fitting.GaussianCurveFitter$1();
    Code:
       0: aload_0
       1: invokespecial #1                  // Method org/apache/commons/math3/analysis/function/Gaussian$Parametric."<init>":()V
       4: return

  public double value(double, double...);
    Code:
       0: ldc2_w        #2                  // double Infinityd
       3: dstore        4
       5: aload_0
       6: dload_1
       7: aload_3
       8: invokespecial #4                  // Method org/apache/commons/math3/analysis/function/Gaussian$Parametric.value:(D[D)D
      11: dstore        4
      13: goto          18
      16: astore        6
      18: dload         4
      20: dreturn
    Exception table:
       from    to  target type
           5    13    16   Class org/apache/commons/math3/exception/NotStrictlyPositiveException

  public double[] gradient(double, double...);
    Code:
       0: iconst_3
       1: newarray       double
       3: dup
       4: iconst_0
       5: ldc2_w        #2                  // double Infinityd
       8: dastore
       9: dup
      10: iconst_1
      11: ldc2_w        #2                  // double Infinityd
      14: dastore
      15: dup
      16: iconst_2
      17: ldc2_w        #2                  // double Infinityd
      20: dastore
      21: astore        4
      23: aload_0
      24: dload_1
      25: aload_3
      26: invokespecial #6                  // Method org/apache/commons/math3/analysis/function/Gaussian$Parametric.gradient:(D[D)[D
      29: astore        4
      31: goto          36
      34: astore        5
      36: aload         4
      38: areturn
    Exception table:
       from    to  target type
          23    31    34   Class org/apache/commons/math3/exception/NotStrictlyPositiveException
}
