Compiled from "NioEventLoop.java"
class io.netty.channel.nio.NioEventLoop$4 implements java.security.PrivilegedAction<java.lang.Object> {
  final java.lang.Class val$selectorImplClass;

  final java.nio.channels.Selector val$unwrappedSelector;

  final io.netty.channel.nio.SelectedSelectionKeySet val$selectedKeySet;

  final io.netty.channel.nio.NioEventLoop this$0;

  io.netty.channel.nio.NioEventLoop$4(io.netty.channel.nio.NioEventLoop, java.lang.Class, java.nio.channels.Selector, io.netty.channel.nio.SelectedSelectionKeySet);
    Code:
       0: aload_0
       1: aload_1
       2: putfield      #1                  // Field this$0:Lio/netty/channel/nio/NioEventLoop;
       5: aload_0
       6: aload_2
       7: putfield      #2                  // Field val$selectorImplClass:Ljava/lang/Class;
      10: aload_0
      11: aload_3
      12: putfield      #3                  // Field val$unwrappedSelector:Ljava/nio/channels/Selector;
      15: aload_0
      16: aload         4
      18: putfield      #4                  // Field val$selectedKeySet:Lio/netty/channel/nio/SelectedSelectionKeySet;
      21: aload_0
      22: invokespecial #5                  // Method java/lang/Object."<init>":()V
      25: return

  public java.lang.Object run();
    Code:
       0: aload_0
       1: getfield      #2                  // Field val$selectorImplClass:Ljava/lang/Class;
       4: ldc           #6                  // String selectedKeys
       6: invokevirtual #7                  // Method java/lang/Class.getDeclaredField:(Ljava/lang/String;)Ljava/lang/reflect/Field;
       9: astore_1
      10: aload_0
      11: getfield      #2                  // Field val$selectorImplClass:Ljava/lang/Class;
      14: ldc           #8                  // String publicSelectedKeys
      16: invokevirtual #7                  // Method java/lang/Class.getDeclaredField:(Ljava/lang/String;)Ljava/lang/reflect/Field;
      19: astore_2
      20: invokestatic  #9                  // Method io/netty/util/internal/PlatformDependent.javaVersion:()I
      23: bipush        9
      25: if_icmplt     89
      28: invokestatic  #10                 // Method io/netty/util/internal/PlatformDependent.hasUnsafe:()Z
      31: ifeq          89
      34: aload_1
      35: invokestatic  #11                 // Method io/netty/util/internal/PlatformDependent.objectFieldOffset:(Ljava/lang/reflect/Field;)J
      38: lstore_3
      39: aload_2
      40: invokestatic  #11                 // Method io/netty/util/internal/PlatformDependent.objectFieldOffset:(Ljava/lang/reflect/Field;)J
      43: lstore        5
      45: lload_3
      46: ldc2_w        #12                 // long -1l
      49: lcmp
      50: ifeq          89
      53: lload         5
      55: ldc2_w        #12                 // long -1l
      58: lcmp
      59: ifeq          89
      62: aload_0
      63: getfield      #3                  // Field val$unwrappedSelector:Ljava/nio/channels/Selector;
      66: lload_3
      67: aload_0
      68: getfield      #4                  // Field val$selectedKeySet:Lio/netty/channel/nio/SelectedSelectionKeySet;
      71: invokestatic  #14                 // Method io/netty/util/internal/PlatformDependent.putObject:(Ljava/lang/Object;JLjava/lang/Object;)V
      74: aload_0
      75: getfield      #3                  // Field val$unwrappedSelector:Ljava/nio/channels/Selector;
      78: lload         5
      80: aload_0
      81: getfield      #4                  // Field val$selectedKeySet:Lio/netty/channel/nio/SelectedSelectionKeySet;
      84: invokestatic  #14                 // Method io/netty/util/internal/PlatformDependent.putObject:(Ljava/lang/Object;JLjava/lang/Object;)V
      87: aconst_null
      88: areturn
      89: aload_1
      90: iconst_1
      91: invokestatic  #15                 // Method io/netty/util/internal/ReflectionUtil.trySetAccessible:(Ljava/lang/reflect/AccessibleObject;Z)Ljava/lang/Throwable;
      94: astore_3
      95: aload_3
      96: ifnull        101
      99: aload_3
     100: areturn
     101: aload_2
     102: iconst_1
     103: invokestatic  #15                 // Method io/netty/util/internal/ReflectionUtil.trySetAccessible:(Ljava/lang/reflect/AccessibleObject;Z)Ljava/lang/Throwable;
     106: astore_3
     107: aload_3
     108: ifnull        113
     111: aload_3
     112: areturn
     113: aload_1
     114: aload_0
     115: getfield      #3                  // Field val$unwrappedSelector:Ljava/nio/channels/Selector;
     118: aload_0
     119: getfield      #4                  // Field val$selectedKeySet:Lio/netty/channel/nio/SelectedSelectionKeySet;
     122: invokevirtual #16                 // Method java/lang/reflect/Field.set:(Ljava/lang/Object;Ljava/lang/Object;)V
     125: aload_2
     126: aload_0
     127: getfield      #3                  // Field val$unwrappedSelector:Ljava/nio/channels/Selector;
     130: aload_0
     131: getfield      #4                  // Field val$selectedKeySet:Lio/netty/channel/nio/SelectedSelectionKeySet;
     134: invokevirtual #16                 // Method java/lang/reflect/Field.set:(Ljava/lang/Object;Ljava/lang/Object;)V
     137: aconst_null
     138: areturn
     139: astore_1
     140: aload_1
     141: areturn
     142: astore_1
     143: aload_1
     144: areturn
    Exception table:
       from    to  target type
           0    88   139   Class java/lang/NoSuchFieldException
          89   100   139   Class java/lang/NoSuchFieldException
         101   112   139   Class java/lang/NoSuchFieldException
         113   138   139   Class java/lang/NoSuchFieldException
           0    88   142   Class java/lang/IllegalAccessException
          89   100   142   Class java/lang/IllegalAccessException
         101   112   142   Class java/lang/IllegalAccessException
         113   138   142   Class java/lang/IllegalAccessException
}
