Compiled from "DocumentStartEvent.java"
public final class org.yaml.snakeyaml.events.DocumentStartEvent extends org.yaml.snakeyaml.events.Event {
  private final boolean explicit;

  private final org.yaml.snakeyaml.DumperOptions$Version version;

  private final java.util.Map<java.lang.String, java.lang.String> tags;

  public org.yaml.snakeyaml.events.DocumentStartEvent(org.yaml.snakeyaml.error.Mark, org.yaml.snakeyaml.error.Mark, boolean, org.yaml.snakeyaml.DumperOptions$Version, java.util.Map<java.lang.String, java.lang.String>);
    Code:
       0: aload_0
       1: aload_1
       2: aload_2
       3: invokespecial #1                  // Method org/yaml/snakeyaml/events/Event."<init>":(Lorg/yaml/snakeyaml/error/Mark;Lorg/yaml/snakeyaml/error/Mark;)V
       6: aload_0
       7: iload_3
       8: putfield      #2                  // Field explicit:Z
      11: aload_0
      12: aload         4
      14: putfield      #3                  // Field version:Lorg/yaml/snakeyaml/DumperOptions$Version;
      17: aload_0
      18: aload         5
      20: putfield      #4                  // Field tags:Ljava/util/Map;
      23: return

  public boolean getExplicit();
    Code:
       0: aload_0
       1: getfield      #2                  // Field explicit:Z
       4: ireturn

  public org.yaml.snakeyaml.DumperOptions$Version getVersion();
    Code:
       0: aload_0
       1: getfield      #3                  // Field version:Lorg/yaml/snakeyaml/DumperOptions$Version;
       4: areturn

  public java.util.Map<java.lang.String, java.lang.String> getTags();
    Code:
       0: aload_0
       1: getfield      #4                  // Field tags:Ljava/util/Map;
       4: areturn

  public org.yaml.snakeyaml.events.Event$ID getEventId();
    Code:
       0: getstatic     #5                  // Field org/yaml/snakeyaml/events/Event$ID.DocumentStart:Lorg/yaml/snakeyaml/events/Event$ID;
       3: areturn
}
