Compiled from "PersistenceUnitImpl.java"
public class org.jboss.shrinkwrap.descriptor.impl.persistence20.PersistenceUnitImpl<T> implements org.jboss.shrinkwrap.descriptor.api.Child<T>, org.jboss.shrinkwrap.descriptor.api.persistence20.PersistenceUnit<T> {
  private T t;

  private org.jboss.shrinkwrap.descriptor.spi.node.Node childNode;

  public org.jboss.shrinkwrap.descriptor.impl.persistence20.PersistenceUnitImpl(T, java.lang.String, org.jboss.shrinkwrap.descriptor.spi.node.Node);
    Code:
       0: aload_0
       1: invokespecial #1                  // Method java/lang/Object."<init>":()V
       4: aload_0
       5: aload_1
       6: putfield      #2                  // Field t:Ljava/lang/Object;
       9: aload_0
      10: aload_3
      11: aload_2
      12: invokevirtual #3                  // Method org/jboss/shrinkwrap/descriptor/spi/node/Node.createChild:(Ljava/lang/String;)Lorg/jboss/shrinkwrap/descriptor/spi/node/Node;
      15: putfield      #4                  // Field childNode:Lorg/jboss/shrinkwrap/descriptor/spi/node/Node;
      18: return

  public org.jboss.shrinkwrap.descriptor.impl.persistence20.PersistenceUnitImpl(T, java.lang.String, org.jboss.shrinkwrap.descriptor.spi.node.Node, org.jboss.shrinkwrap.descriptor.spi.node.Node);
    Code:
       0: aload_0
       1: invokespecial #1                  // Method java/lang/Object."<init>":()V
       4: aload_0
       5: aload_1
       6: putfield      #2                  // Field t:Ljava/lang/Object;
       9: aload_0
      10: aload         4
      12: putfield      #4                  // Field childNode:Lorg/jboss/shrinkwrap/descriptor/spi/node/Node;
      15: return

  public T up();
    Code:
       0: aload_0
       1: getfield      #2                  // Field t:Ljava/lang/Object;
       4: areturn

  public org.jboss.shrinkwrap.descriptor.api.persistence20.PersistenceUnit<T> description(java.lang.String);
    Code:
       0: aload_0
       1: getfield      #4                  // Field childNode:Lorg/jboss/shrinkwrap/descriptor/spi/node/Node;
       4: ldc           #5                  // String description
       6: invokevirtual #6                  // Method org/jboss/shrinkwrap/descriptor/spi/node/Node.getOrCreate:(Ljava/lang/String;)Lorg/jboss/shrinkwrap/descriptor/spi/node/Node;
       9: aload_1
      10: invokevirtual #7                  // Method org/jboss/shrinkwrap/descriptor/spi/node/Node.text:(Ljava/lang/String;)Lorg/jboss/shrinkwrap/descriptor/spi/node/Node;
      13: pop
      14: aload_0
      15: areturn

  public java.lang.String getDescription();
    Code:
       0: aload_0
       1: getfield      #4                  // Field childNode:Lorg/jboss/shrinkwrap/descriptor/spi/node/Node;
       4: ldc           #5                  // String description
       6: invokevirtual #8                  // Method org/jboss/shrinkwrap/descriptor/spi/node/Node.getTextValueForPatternName:(Ljava/lang/String;)Ljava/lang/String;
       9: areturn

  public org.jboss.shrinkwrap.descriptor.api.persistence20.PersistenceUnit<T> removeDescription();
    Code:
       0: aload_0
       1: getfield      #4                  // Field childNode:Lorg/jboss/shrinkwrap/descriptor/spi/node/Node;
       4: ldc           #5                  // String description
       6: invokevirtual #9                  // Method org/jboss/shrinkwrap/descriptor/spi/node/Node.removeChildren:(Ljava/lang/String;)Ljava/util/List;
       9: pop
      10: aload_0
      11: areturn

  public org.jboss.shrinkwrap.descriptor.api.persistence20.PersistenceUnit<T> provider(java.lang.String);
    Code:
       0: aload_0
       1: getfield      #4                  // Field childNode:Lorg/jboss/shrinkwrap/descriptor/spi/node/Node;
       4: ldc           #10                 // String provider
       6: invokevirtual #6                  // Method org/jboss/shrinkwrap/descriptor/spi/node/Node.getOrCreate:(Ljava/lang/String;)Lorg/jboss/shrinkwrap/descriptor/spi/node/Node;
       9: aload_1
      10: invokevirtual #7                  // Method org/jboss/shrinkwrap/descriptor/spi/node/Node.text:(Ljava/lang/String;)Lorg/jboss/shrinkwrap/descriptor/spi/node/Node;
      13: pop
      14: aload_0
      15: areturn

  public java.lang.String getProvider();
    Code:
       0: aload_0
       1: getfield      #4                  // Field childNode:Lorg/jboss/shrinkwrap/descriptor/spi/node/Node;
       4: ldc           #10                 // String provider
       6: invokevirtual #8                  // Method org/jboss/shrinkwrap/descriptor/spi/node/Node.getTextValueForPatternName:(Ljava/lang/String;)Ljava/lang/String;
       9: areturn

  public org.jboss.shrinkwrap.descriptor.api.persistence20.PersistenceUnit<T> removeProvider();
    Code:
       0: aload_0
       1: getfield      #4                  // Field childNode:Lorg/jboss/shrinkwrap/descriptor/spi/node/Node;
       4: ldc           #10                 // String provider
       6: invokevirtual #9                  // Method org/jboss/shrinkwrap/descriptor/spi/node/Node.removeChildren:(Ljava/lang/String;)Ljava/util/List;
       9: pop
      10: aload_0
      11: areturn

  public org.jboss.shrinkwrap.descriptor.api.persistence20.PersistenceUnit<T> jtaDataSource(java.lang.String);
    Code:
       0: aload_0
       1: getfield      #4                  // Field childNode:Lorg/jboss/shrinkwrap/descriptor/spi/node/Node;
       4: ldc           #11                 // String jta-data-source
       6: invokevirtual #6                  // Method org/jboss/shrinkwrap/descriptor/spi/node/Node.getOrCreate:(Ljava/lang/String;)Lorg/jboss/shrinkwrap/descriptor/spi/node/Node;
       9: aload_1
      10: invokevirtual #7                  // Method org/jboss/shrinkwrap/descriptor/spi/node/Node.text:(Ljava/lang/String;)Lorg/jboss/shrinkwrap/descriptor/spi/node/Node;
      13: pop
      14: aload_0
      15: areturn

  public java.lang.String getJtaDataSource();
    Code:
       0: aload_0
       1: getfield      #4                  // Field childNode:Lorg/jboss/shrinkwrap/descriptor/spi/node/Node;
       4: ldc           #11                 // String jta-data-source
       6: invokevirtual #8                  // Method org/jboss/shrinkwrap/descriptor/spi/node/Node.getTextValueForPatternName:(Ljava/lang/String;)Ljava/lang/String;
       9: areturn

  public org.jboss.shrinkwrap.descriptor.api.persistence20.PersistenceUnit<T> removeJtaDataSource();
    Code:
       0: aload_0
       1: getfield      #4                  // Field childNode:Lorg/jboss/shrinkwrap/descriptor/spi/node/Node;
       4: ldc           #11                 // String jta-data-source
       6: invokevirtual #9                  // Method org/jboss/shrinkwrap/descriptor/spi/node/Node.removeChildren:(Ljava/lang/String;)Ljava/util/List;
       9: pop
      10: aload_0
      11: areturn

  public org.jboss.shrinkwrap.descriptor.api.persistence20.PersistenceUnit<T> nonJtaDataSource(java.lang.String);
    Code:
       0: aload_0
       1: getfield      #4                  // Field childNode:Lorg/jboss/shrinkwrap/descriptor/spi/node/Node;
       4: ldc           #12                 // String non-jta-data-source
       6: invokevirtual #6                  // Method org/jboss/shrinkwrap/descriptor/spi/node/Node.getOrCreate:(Ljava/lang/String;)Lorg/jboss/shrinkwrap/descriptor/spi/node/Node;
       9: aload_1
      10: invokevirtual #7                  // Method org/jboss/shrinkwrap/descriptor/spi/node/Node.text:(Ljava/lang/String;)Lorg/jboss/shrinkwrap/descriptor/spi/node/Node;
      13: pop
      14: aload_0
      15: areturn

  public java.lang.String getNonJtaDataSource();
    Code:
       0: aload_0
       1: getfield      #4                  // Field childNode:Lorg/jboss/shrinkwrap/descriptor/spi/node/Node;
       4: ldc           #12                 // String non-jta-data-source
       6: invokevirtual #8                  // Method org/jboss/shrinkwrap/descriptor/spi/node/Node.getTextValueForPatternName:(Ljava/lang/String;)Ljava/lang/String;
       9: areturn

  public org.jboss.shrinkwrap.descriptor.api.persistence20.PersistenceUnit<T> removeNonJtaDataSource();
    Code:
       0: aload_0
       1: getfield      #4                  // Field childNode:Lorg/jboss/shrinkwrap/descriptor/spi/node/Node;
       4: ldc           #12                 // String non-jta-data-source
       6: invokevirtual #9                  // Method org/jboss/shrinkwrap/descriptor/spi/node/Node.removeChildren:(Ljava/lang/String;)Ljava/util/List;
       9: pop
      10: aload_0
      11: areturn

  public org.jboss.shrinkwrap.descriptor.api.persistence20.PersistenceUnit<T> mappingFile(java.lang.String...);
    Code:
       0: aload_1
       1: ifnull        45
       4: aload_1
       5: astore_2
       6: aload_2
       7: arraylength
       8: istore_3
       9: iconst_0
      10: istore        4
      12: iload         4
      14: iload_3
      15: if_icmpge     45
      18: aload_2
      19: iload         4
      21: aaload
      22: astore        5
      24: aload_0
      25: getfield      #4                  // Field childNode:Lorg/jboss/shrinkwrap/descriptor/spi/node/Node;
      28: ldc           #13                 // String mapping-file
      30: invokevirtual #3                  // Method org/jboss/shrinkwrap/descriptor/spi/node/Node.createChild:(Ljava/lang/String;)Lorg/jboss/shrinkwrap/descriptor/spi/node/Node;
      33: aload         5
      35: invokevirtual #7                  // Method org/jboss/shrinkwrap/descriptor/spi/node/Node.text:(Ljava/lang/String;)Lorg/jboss/shrinkwrap/descriptor/spi/node/Node;
      38: pop
      39: iinc          4, 1
      42: goto          12
      45: aload_0
      46: areturn

  public java.util.List<java.lang.String> getAllMappingFile();
    Code:
       0: new           #14                 // class java/util/ArrayList
       3: dup
       4: invokespecial #15                 // Method java/util/ArrayList."<init>":()V
       7: astore_1
       8: aload_0
       9: getfield      #4                  // Field childNode:Lorg/jboss/shrinkwrap/descriptor/spi/node/Node;
      12: ldc           #13                 // String mapping-file
      14: invokevirtual #16                 // Method org/jboss/shrinkwrap/descriptor/spi/node/Node.get:(Ljava/lang/String;)Ljava/util/List;
      17: astore_2
      18: aload_2
      19: invokeinterface #17,  1           // InterfaceMethod java/util/List.iterator:()Ljava/util/Iterator;
      24: astore_3
      25: aload_3
      26: invokeinterface #18,  1           // InterfaceMethod java/util/Iterator.hasNext:()Z
      31: ifeq          60
      34: aload_3
      35: invokeinterface #19,  1           // InterfaceMethod java/util/Iterator.next:()Ljava/lang/Object;
      40: checkcast     #20                 // class org/jboss/shrinkwrap/descriptor/spi/node/Node
      43: astore        4
      45: aload_1
      46: aload         4
      48: invokevirtual #21                 // Method org/jboss/shrinkwrap/descriptor/spi/node/Node.getText:()Ljava/lang/String;
      51: invokeinterface #22,  2           // InterfaceMethod java/util/List.add:(Ljava/lang/Object;)Z
      56: pop
      57: goto          25
      60: aload_1
      61: areturn

  public org.jboss.shrinkwrap.descriptor.api.persistence20.PersistenceUnit<T> removeAllMappingFile();
    Code:
       0: aload_0
       1: getfield      #4                  // Field childNode:Lorg/jboss/shrinkwrap/descriptor/spi/node/Node;
       4: ldc           #13                 // String mapping-file
       6: invokevirtual #9                  // Method org/jboss/shrinkwrap/descriptor/spi/node/Node.removeChildren:(Ljava/lang/String;)Ljava/util/List;
       9: pop
      10: aload_0
      11: areturn

  public org.jboss.shrinkwrap.descriptor.api.persistence20.PersistenceUnit<T> jarFile(java.lang.String...);
    Code:
       0: aload_1
       1: ifnull        45
       4: aload_1
       5: astore_2
       6: aload_2
       7: arraylength
       8: istore_3
       9: iconst_0
      10: istore        4
      12: iload         4
      14: iload_3
      15: if_icmpge     45
      18: aload_2
      19: iload         4
      21: aaload
      22: astore        5
      24: aload_0
      25: getfield      #4                  // Field childNode:Lorg/jboss/shrinkwrap/descriptor/spi/node/Node;
      28: ldc           #23                 // String jar-file
      30: invokevirtual #3                  // Method org/jboss/shrinkwrap/descriptor/spi/node/Node.createChild:(Ljava/lang/String;)Lorg/jboss/shrinkwrap/descriptor/spi/node/Node;
      33: aload         5
      35: invokevirtual #7                  // Method org/jboss/shrinkwrap/descriptor/spi/node/Node.text:(Ljava/lang/String;)Lorg/jboss/shrinkwrap/descriptor/spi/node/Node;
      38: pop
      39: iinc          4, 1
      42: goto          12
      45: aload_0
      46: areturn

  public java.util.List<java.lang.String> getAllJarFile();
    Code:
       0: new           #14                 // class java/util/ArrayList
       3: dup
       4: invokespecial #15                 // Method java/util/ArrayList."<init>":()V
       7: astore_1
       8: aload_0
       9: getfield      #4                  // Field childNode:Lorg/jboss/shrinkwrap/descriptor/spi/node/Node;
      12: ldc           #23                 // String jar-file
      14: invokevirtual #16                 // Method org/jboss/shrinkwrap/descriptor/spi/node/Node.get:(Ljava/lang/String;)Ljava/util/List;
      17: astore_2
      18: aload_2
      19: invokeinterface #17,  1           // InterfaceMethod java/util/List.iterator:()Ljava/util/Iterator;
      24: astore_3
      25: aload_3
      26: invokeinterface #18,  1           // InterfaceMethod java/util/Iterator.hasNext:()Z
      31: ifeq          60
      34: aload_3
      35: invokeinterface #19,  1           // InterfaceMethod java/util/Iterator.next:()Ljava/lang/Object;
      40: checkcast     #20                 // class org/jboss/shrinkwrap/descriptor/spi/node/Node
      43: astore        4
      45: aload_1
      46: aload         4
      48: invokevirtual #21                 // Method org/jboss/shrinkwrap/descriptor/spi/node/Node.getText:()Ljava/lang/String;
      51: invokeinterface #22,  2           // InterfaceMethod java/util/List.add:(Ljava/lang/Object;)Z
      56: pop
      57: goto          25
      60: aload_1
      61: areturn

  public org.jboss.shrinkwrap.descriptor.api.persistence20.PersistenceUnit<T> removeAllJarFile();
    Code:
       0: aload_0
       1: getfield      #4                  // Field childNode:Lorg/jboss/shrinkwrap/descriptor/spi/node/Node;
       4: ldc           #23                 // String jar-file
       6: invokevirtual #9                  // Method org/jboss/shrinkwrap/descriptor/spi/node/Node.removeChildren:(Ljava/lang/String;)Ljava/util/List;
       9: pop
      10: aload_0
      11: areturn

  public org.jboss.shrinkwrap.descriptor.api.persistence20.PersistenceUnit<T> clazz(java.lang.String...);
    Code:
       0: aload_1
       1: ifnull        45
       4: aload_1
       5: astore_2
       6: aload_2
       7: arraylength
       8: istore_3
       9: iconst_0
      10: istore        4
      12: iload         4
      14: iload_3
      15: if_icmpge     45
      18: aload_2
      19: iload         4
      21: aaload
      22: astore        5
      24: aload_0
      25: getfield      #4                  // Field childNode:Lorg/jboss/shrinkwrap/descriptor/spi/node/Node;
      28: ldc           #24                 // String class
      30: invokevirtual #3                  // Method org/jboss/shrinkwrap/descriptor/spi/node/Node.createChild:(Ljava/lang/String;)Lorg/jboss/shrinkwrap/descriptor/spi/node/Node;
      33: aload         5
      35: invokevirtual #7                  // Method org/jboss/shrinkwrap/descriptor/spi/node/Node.text:(Ljava/lang/String;)Lorg/jboss/shrinkwrap/descriptor/spi/node/Node;
      38: pop
      39: iinc          4, 1
      42: goto          12
      45: aload_0
      46: areturn

  public java.util.List<java.lang.String> getAllClazz();
    Code:
       0: new           #14                 // class java/util/ArrayList
       3: dup
       4: invokespecial #15                 // Method java/util/ArrayList."<init>":()V
       7: astore_1
       8: aload_0
       9: getfield      #4                  // Field childNode:Lorg/jboss/shrinkwrap/descriptor/spi/node/Node;
      12: ldc           #24                 // String class
      14: invokevirtual #16                 // Method org/jboss/shrinkwrap/descriptor/spi/node/Node.get:(Ljava/lang/String;)Ljava/util/List;
      17: astore_2
      18: aload_2
      19: invokeinterface #17,  1           // InterfaceMethod java/util/List.iterator:()Ljava/util/Iterator;
      24: astore_3
      25: aload_3
      26: invokeinterface #18,  1           // InterfaceMethod java/util/Iterator.hasNext:()Z
      31: ifeq          60
      34: aload_3
      35: invokeinterface #19,  1           // InterfaceMethod java/util/Iterator.next:()Ljava/lang/Object;
      40: checkcast     #20                 // class org/jboss/shrinkwrap/descriptor/spi/node/Node
      43: astore        4
      45: aload_1
      46: aload         4
      48: invokevirtual #21                 // Method org/jboss/shrinkwrap/descriptor/spi/node/Node.getText:()Ljava/lang/String;
      51: invokeinterface #22,  2           // InterfaceMethod java/util/List.add:(Ljava/lang/Object;)Z
      56: pop
      57: goto          25
      60: aload_1
      61: areturn

  public org.jboss.shrinkwrap.descriptor.api.persistence20.PersistenceUnit<T> removeAllClazz();
    Code:
       0: aload_0
       1: getfield      #4                  // Field childNode:Lorg/jboss/shrinkwrap/descriptor/spi/node/Node;
       4: ldc           #24                 // String class
       6: invokevirtual #9                  // Method org/jboss/shrinkwrap/descriptor/spi/node/Node.removeChildren:(Ljava/lang/String;)Ljava/util/List;
       9: pop
      10: aload_0
      11: areturn

  public org.jboss.shrinkwrap.descriptor.api.persistence20.PersistenceUnit<T> excludeUnlistedClasses(java.lang.Boolean);
    Code:
       0: aload_0
       1: getfield      #4                  // Field childNode:Lorg/jboss/shrinkwrap/descriptor/spi/node/Node;
       4: ldc           #25                 // String exclude-unlisted-classes
       6: invokevirtual #6                  // Method org/jboss/shrinkwrap/descriptor/spi/node/Node.getOrCreate:(Ljava/lang/String;)Lorg/jboss/shrinkwrap/descriptor/spi/node/Node;
       9: aload_1
      10: invokevirtual #26                 // Method org/jboss/shrinkwrap/descriptor/spi/node/Node.text:(Ljava/lang/Object;)Lorg/jboss/shrinkwrap/descriptor/spi/node/Node;
      13: pop
      14: aload_0
      15: areturn

  public java.lang.Boolean isExcludeUnlistedClasses();
    Code:
       0: aload_0
       1: getfield      #4                  // Field childNode:Lorg/jboss/shrinkwrap/descriptor/spi/node/Node;
       4: ldc           #25                 // String exclude-unlisted-classes
       6: invokevirtual #8                  // Method org/jboss/shrinkwrap/descriptor/spi/node/Node.getTextValueForPatternName:(Ljava/lang/String;)Ljava/lang/String;
       9: invokestatic  #27                 // Method org/jboss/shrinkwrap/descriptor/impl/base/Strings.isTrue:(Ljava/lang/String;)Z
      12: invokestatic  #28                 // Method java/lang/Boolean.valueOf:(Z)Ljava/lang/Boolean;
      15: areturn

  public org.jboss.shrinkwrap.descriptor.api.persistence20.PersistenceUnit<T> removeExcludeUnlistedClasses();
    Code:
       0: aload_0
       1: getfield      #4                  // Field childNode:Lorg/jboss/shrinkwrap/descriptor/spi/node/Node;
       4: ldc           #25                 // String exclude-unlisted-classes
       6: invokevirtual #9                  // Method org/jboss/shrinkwrap/descriptor/spi/node/Node.removeChildren:(Ljava/lang/String;)Ljava/util/List;
       9: pop
      10: aload_0
      11: areturn

  public org.jboss.shrinkwrap.descriptor.api.persistence20.PersistenceUnit<T> sharedCacheMode(org.jboss.shrinkwrap.descriptor.api.persistence20.PersistenceUnitCachingType);
    Code:
       0: aload_0
       1: getfield      #4                  // Field childNode:Lorg/jboss/shrinkwrap/descriptor/spi/node/Node;
       4: ldc           #29                 // String shared-cache-mode
       6: invokevirtual #6                  // Method org/jboss/shrinkwrap/descriptor/spi/node/Node.getOrCreate:(Ljava/lang/String;)Lorg/jboss/shrinkwrap/descriptor/spi/node/Node;
       9: aload_1
      10: invokevirtual #26                 // Method org/jboss/shrinkwrap/descriptor/spi/node/Node.text:(Ljava/lang/Object;)Lorg/jboss/shrinkwrap/descriptor/spi/node/Node;
      13: pop
      14: aload_0
      15: areturn

  public org.jboss.shrinkwrap.descriptor.api.persistence20.PersistenceUnit<T> sharedCacheMode(java.lang.String);
    Code:
       0: aload_0
       1: getfield      #4                  // Field childNode:Lorg/jboss/shrinkwrap/descriptor/spi/node/Node;
       4: ldc           #29                 // String shared-cache-mode
       6: invokevirtual #6                  // Method org/jboss/shrinkwrap/descriptor/spi/node/Node.getOrCreate:(Ljava/lang/String;)Lorg/jboss/shrinkwrap/descriptor/spi/node/Node;
       9: aload_1
      10: invokevirtual #7                  // Method org/jboss/shrinkwrap/descriptor/spi/node/Node.text:(Ljava/lang/String;)Lorg/jboss/shrinkwrap/descriptor/spi/node/Node;
      13: pop
      14: aload_0
      15: areturn

  public org.jboss.shrinkwrap.descriptor.api.persistence20.PersistenceUnitCachingType getSharedCacheMode();
    Code:
       0: aload_0
       1: getfield      #4                  // Field childNode:Lorg/jboss/shrinkwrap/descriptor/spi/node/Node;
       4: ldc           #29                 // String shared-cache-mode
       6: invokevirtual #8                  // Method org/jboss/shrinkwrap/descriptor/spi/node/Node.getTextValueForPatternName:(Ljava/lang/String;)Ljava/lang/String;
       9: invokestatic  #30                 // Method org/jboss/shrinkwrap/descriptor/api/persistence20/PersistenceUnitCachingType.getFromStringValue:(Ljava/lang/String;)Lorg/jboss/shrinkwrap/descriptor/api/persistence20/PersistenceUnitCachingType;
      12: areturn

  public java.lang.String getSharedCacheModeAsString();
    Code:
       0: aload_0
       1: getfield      #4                  // Field childNode:Lorg/jboss/shrinkwrap/descriptor/spi/node/Node;
       4: ldc           #29                 // String shared-cache-mode
       6: invokevirtual #8                  // Method org/jboss/shrinkwrap/descriptor/spi/node/Node.getTextValueForPatternName:(Ljava/lang/String;)Ljava/lang/String;
       9: areturn

  public org.jboss.shrinkwrap.descriptor.api.persistence20.PersistenceUnit<T> removeSharedCacheMode();
    Code:
       0: aload_0
       1: getfield      #4                  // Field childNode:Lorg/jboss/shrinkwrap/descriptor/spi/node/Node;
       4: ldc           #29                 // String shared-cache-mode
       6: invokevirtual #31                 // Method org/jboss/shrinkwrap/descriptor/spi/node/Node.removeAttribute:(Ljava/lang/String;)Ljava/lang/String;
       9: pop
      10: aload_0
      11: areturn

  public org.jboss.shrinkwrap.descriptor.api.persistence20.PersistenceUnit<T> validationMode(org.jboss.shrinkwrap.descriptor.api.persistence20.PersistenceUnitValidationModeType);
    Code:
       0: aload_0
       1: getfield      #4                  // Field childNode:Lorg/jboss/shrinkwrap/descriptor/spi/node/Node;
       4: ldc           #32                 // String validation-mode
       6: invokevirtual #6                  // Method org/jboss/shrinkwrap/descriptor/spi/node/Node.getOrCreate:(Ljava/lang/String;)Lorg/jboss/shrinkwrap/descriptor/spi/node/Node;
       9: aload_1
      10: invokevirtual #26                 // Method org/jboss/shrinkwrap/descriptor/spi/node/Node.text:(Ljava/lang/Object;)Lorg/jboss/shrinkwrap/descriptor/spi/node/Node;
      13: pop
      14: aload_0
      15: areturn

  public org.jboss.shrinkwrap.descriptor.api.persistence20.PersistenceUnit<T> validationMode(java.lang.String);
    Code:
       0: aload_0
       1: getfield      #4                  // Field childNode:Lorg/jboss/shrinkwrap/descriptor/spi/node/Node;
       4: ldc           #32                 // String validation-mode
       6: invokevirtual #6                  // Method org/jboss/shrinkwrap/descriptor/spi/node/Node.getOrCreate:(Ljava/lang/String;)Lorg/jboss/shrinkwrap/descriptor/spi/node/Node;
       9: aload_1
      10: invokevirtual #7                  // Method org/jboss/shrinkwrap/descriptor/spi/node/Node.text:(Ljava/lang/String;)Lorg/jboss/shrinkwrap/descriptor/spi/node/Node;
      13: pop
      14: aload_0
      15: areturn

  public org.jboss.shrinkwrap.descriptor.api.persistence20.PersistenceUnitValidationModeType getValidationMode();
    Code:
       0: aload_0
       1: getfield      #4                  // Field childNode:Lorg/jboss/shrinkwrap/descriptor/spi/node/Node;
       4: ldc           #32                 // String validation-mode
       6: invokevirtual #8                  // Method org/jboss/shrinkwrap/descriptor/spi/node/Node.getTextValueForPatternName:(Ljava/lang/String;)Ljava/lang/String;
       9: invokestatic  #33                 // Method org/jboss/shrinkwrap/descriptor/api/persistence20/PersistenceUnitValidationModeType.getFromStringValue:(Ljava/lang/String;)Lorg/jboss/shrinkwrap/descriptor/api/persistence20/PersistenceUnitValidationModeType;
      12: areturn

  public java.lang.String getValidationModeAsString();
    Code:
       0: aload_0
       1: getfield      #4                  // Field childNode:Lorg/jboss/shrinkwrap/descriptor/spi/node/Node;
       4: ldc           #32                 // String validation-mode
       6: invokevirtual #8                  // Method org/jboss/shrinkwrap/descriptor/spi/node/Node.getTextValueForPatternName:(Ljava/lang/String;)Ljava/lang/String;
       9: areturn

  public org.jboss.shrinkwrap.descriptor.api.persistence20.PersistenceUnit<T> removeValidationMode();
    Code:
       0: aload_0
       1: getfield      #4                  // Field childNode:Lorg/jboss/shrinkwrap/descriptor/spi/node/Node;
       4: ldc           #32                 // String validation-mode
       6: invokevirtual #31                 // Method org/jboss/shrinkwrap/descriptor/spi/node/Node.removeAttribute:(Ljava/lang/String;)Ljava/lang/String;
       9: pop
      10: aload_0
      11: areturn

  public org.jboss.shrinkwrap.descriptor.api.persistence20.Properties<org.jboss.shrinkwrap.descriptor.api.persistence20.PersistenceUnit<T>> getOrCreateProperties();
    Code:
       0: aload_0
       1: getfield      #4                  // Field childNode:Lorg/jboss/shrinkwrap/descriptor/spi/node/Node;
       4: ldc           #34                 // String properties
       6: invokevirtual #6                  // Method org/jboss/shrinkwrap/descriptor/spi/node/Node.getOrCreate:(Ljava/lang/String;)Lorg/jboss/shrinkwrap/descriptor/spi/node/Node;
       9: astore_1
      10: new           #35                 // class org/jboss/shrinkwrap/descriptor/impl/persistence20/PropertiesImpl
      13: dup
      14: aload_0
      15: ldc           #34                 // String properties
      17: aload_0
      18: getfield      #4                  // Field childNode:Lorg/jboss/shrinkwrap/descriptor/spi/node/Node;
      21: aload_1
      22: invokespecial #36                 // Method org/jboss/shrinkwrap/descriptor/impl/persistence20/PropertiesImpl."<init>":(Ljava/lang/Object;Ljava/lang/String;Lorg/jboss/shrinkwrap/descriptor/spi/node/Node;Lorg/jboss/shrinkwrap/descriptor/spi/node/Node;)V
      25: astore_2
      26: aload_2
      27: areturn

  public org.jboss.shrinkwrap.descriptor.api.persistence20.PersistenceUnit<T> removeProperties();
    Code:
       0: aload_0
       1: getfield      #4                  // Field childNode:Lorg/jboss/shrinkwrap/descriptor/spi/node/Node;
       4: ldc           #34                 // String properties
       6: invokevirtual #9                  // Method org/jboss/shrinkwrap/descriptor/spi/node/Node.removeChildren:(Ljava/lang/String;)Ljava/util/List;
       9: pop
      10: aload_0
      11: areturn

  public org.jboss.shrinkwrap.descriptor.api.persistence20.PersistenceUnit<T> name(java.lang.String);
    Code:
       0: aload_0
       1: getfield      #4                  // Field childNode:Lorg/jboss/shrinkwrap/descriptor/spi/node/Node;
       4: ldc           #37                 // String name
       6: aload_1
       7: invokevirtual #38                 // Method org/jboss/shrinkwrap/descriptor/spi/node/Node.attribute:(Ljava/lang/String;Ljava/lang/String;)Lorg/jboss/shrinkwrap/descriptor/spi/node/Node;
      10: pop
      11: aload_0
      12: areturn

  public java.lang.String getName();
    Code:
       0: aload_0
       1: getfield      #4                  // Field childNode:Lorg/jboss/shrinkwrap/descriptor/spi/node/Node;
       4: ldc           #37                 // String name
       6: invokevirtual #39                 // Method org/jboss/shrinkwrap/descriptor/spi/node/Node.getAttribute:(Ljava/lang/String;)Ljava/lang/String;
       9: areturn

  public org.jboss.shrinkwrap.descriptor.api.persistence20.PersistenceUnit<T> removeName();
    Code:
       0: aload_0
       1: getfield      #4                  // Field childNode:Lorg/jboss/shrinkwrap/descriptor/spi/node/Node;
       4: ldc           #37                 // String name
       6: invokevirtual #31                 // Method org/jboss/shrinkwrap/descriptor/spi/node/Node.removeAttribute:(Ljava/lang/String;)Ljava/lang/String;
       9: pop
      10: aload_0
      11: areturn

  public org.jboss.shrinkwrap.descriptor.api.persistence20.PersistenceUnit<T> transactionType(org.jboss.shrinkwrap.descriptor.api.persistence20.PersistenceUnitTransactionType);
    Code:
       0: aload_0
       1: getfield      #4                  // Field childNode:Lorg/jboss/shrinkwrap/descriptor/spi/node/Node;
       4: ldc           #40                 // String transaction-type
       6: aload_1
       7: invokevirtual #41                 // Method org/jboss/shrinkwrap/descriptor/spi/node/Node.attribute:(Ljava/lang/String;Ljava/lang/Object;)Lorg/jboss/shrinkwrap/descriptor/spi/node/Node;
      10: pop
      11: aload_0
      12: areturn

  public org.jboss.shrinkwrap.descriptor.api.persistence20.PersistenceUnit<T> transactionType(java.lang.String);
    Code:
       0: aload_0
       1: getfield      #4                  // Field childNode:Lorg/jboss/shrinkwrap/descriptor/spi/node/Node;
       4: ldc           #40                 // String transaction-type
       6: aload_1
       7: invokevirtual #38                 // Method org/jboss/shrinkwrap/descriptor/spi/node/Node.attribute:(Ljava/lang/String;Ljava/lang/String;)Lorg/jboss/shrinkwrap/descriptor/spi/node/Node;
      10: pop
      11: aload_0
      12: areturn

  public org.jboss.shrinkwrap.descriptor.api.persistence20.PersistenceUnitTransactionType getTransactionType();
    Code:
       0: aload_0
       1: getfield      #4                  // Field childNode:Lorg/jboss/shrinkwrap/descriptor/spi/node/Node;
       4: ldc           #40                 // String transaction-type
       6: invokevirtual #39                 // Method org/jboss/shrinkwrap/descriptor/spi/node/Node.getAttribute:(Ljava/lang/String;)Ljava/lang/String;
       9: invokestatic  #42                 // Method org/jboss/shrinkwrap/descriptor/api/persistence20/PersistenceUnitTransactionType.getFromStringValue:(Ljava/lang/String;)Lorg/jboss/shrinkwrap/descriptor/api/persistence20/PersistenceUnitTransactionType;
      12: areturn

  public java.lang.String getTransactionTypeAsString();
    Code:
       0: aload_0
       1: getfield      #4                  // Field childNode:Lorg/jboss/shrinkwrap/descriptor/spi/node/Node;
       4: ldc           #40                 // String transaction-type
       6: invokevirtual #39                 // Method org/jboss/shrinkwrap/descriptor/spi/node/Node.getAttribute:(Ljava/lang/String;)Ljava/lang/String;
       9: areturn

  public org.jboss.shrinkwrap.descriptor.api.persistence20.PersistenceUnit<T> removeTransactionType();
    Code:
       0: aload_0
       1: getfield      #4                  // Field childNode:Lorg/jboss/shrinkwrap/descriptor/spi/node/Node;
       4: ldc           #40                 // String transaction-type
       6: invokevirtual #31                 // Method org/jboss/shrinkwrap/descriptor/spi/node/Node.removeAttribute:(Ljava/lang/String;)Ljava/lang/String;
       9: pop
      10: aload_0
      11: areturn
}
