Compiled from "AbstractMonitoringInterceptor.java"
public abstract class org.springframework.aop.interceptor.AbstractMonitoringInterceptor extends org.springframework.aop.interceptor.AbstractTraceInterceptor {
  private java.lang.String prefix;

  private java.lang.String suffix;

  private boolean logTargetClassInvocation;

  public org.springframework.aop.interceptor.AbstractMonitoringInterceptor();
    Code:
       0: aload_0
       1: invokespecial #1                  // Method org/springframework/aop/interceptor/AbstractTraceInterceptor."<init>":()V
       4: aload_0
       5: ldc           #2                  // String
       7: putfield      #3                  // Field prefix:Ljava/lang/String;
      10: aload_0
      11: ldc           #2                  // String
      13: putfield      #4                  // Field suffix:Ljava/lang/String;
      16: aload_0
      17: iconst_0
      18: putfield      #5                  // Field logTargetClassInvocation:Z
      21: return

  public void setPrefix(java.lang.String);
    Code:
       0: aload_0
       1: aload_1
       2: ifnull        9
       5: aload_1
       6: goto          11
       9: ldc           #2                  // String
      11: putfield      #3                  // Field prefix:Ljava/lang/String;
      14: return

  protected java.lang.String getPrefix();
    Code:
       0: aload_0
       1: getfield      #3                  // Field prefix:Ljava/lang/String;
       4: areturn

  public void setSuffix(java.lang.String);
    Code:
       0: aload_0
       1: aload_1
       2: ifnull        9
       5: aload_1
       6: goto          11
       9: ldc           #2                  // String
      11: putfield      #4                  // Field suffix:Ljava/lang/String;
      14: return

  protected java.lang.String getSuffix();
    Code:
       0: aload_0
       1: getfield      #4                  // Field suffix:Ljava/lang/String;
       4: areturn

  public void setLogTargetClassInvocation(boolean);
    Code:
       0: aload_0
       1: iload_1
       2: putfield      #5                  // Field logTargetClassInvocation:Z
       5: return

  protected java.lang.String createInvocationTraceName(org.aopalliance.intercept.MethodInvocation);
    Code:
       0: aload_1
       1: invokeinterface #6,  1            // InterfaceMethod org/aopalliance/intercept/MethodInvocation.getMethod:()Ljava/lang/reflect/Method;
       6: astore_2
       7: aload_2
       8: invokevirtual #7                  // Method java/lang/reflect/Method.getDeclaringClass:()Ljava/lang/Class;
      11: astore_3
      12: aload_0
      13: getfield      #5                  // Field logTargetClassInvocation:Z
      16: ifeq          42
      19: aload_3
      20: aload_1
      21: invokeinterface #8,  1            // InterfaceMethod org/aopalliance/intercept/MethodInvocation.getThis:()Ljava/lang/Object;
      26: invokevirtual #9                  // Method java/lang/Class.isInstance:(Ljava/lang/Object;)Z
      29: ifeq          42
      32: aload_1
      33: invokeinterface #8,  1            // InterfaceMethod org/aopalliance/intercept/MethodInvocation.getThis:()Ljava/lang/Object;
      38: invokevirtual #10                 // Method java/lang/Object.getClass:()Ljava/lang/Class;
      41: astore_3
      42: aload_3
      43: invokevirtual #11                 // Method java/lang/Class.getName:()Ljava/lang/String;
      46: astore        4
      48: new           #12                 // class java/lang/StringBuilder
      51: dup
      52: invokespecial #13                 // Method java/lang/StringBuilder."<init>":()V
      55: aload_0
      56: invokevirtual #14                 // Method getPrefix:()Ljava/lang/String;
      59: invokevirtual #15                 // Method java/lang/StringBuilder.append:(Ljava/lang/String;)Ljava/lang/StringBuilder;
      62: aload         4
      64: invokevirtual #15                 // Method java/lang/StringBuilder.append:(Ljava/lang/String;)Ljava/lang/StringBuilder;
      67: bipush        46
      69: invokevirtual #16                 // Method java/lang/StringBuilder.append:(C)Ljava/lang/StringBuilder;
      72: aload_2
      73: invokevirtual #17                 // Method java/lang/reflect/Method.getName:()Ljava/lang/String;
      76: invokevirtual #15                 // Method java/lang/StringBuilder.append:(Ljava/lang/String;)Ljava/lang/StringBuilder;
      79: aload_0
      80: invokevirtual #18                 // Method getSuffix:()Ljava/lang/String;
      83: invokevirtual #15                 // Method java/lang/StringBuilder.append:(Ljava/lang/String;)Ljava/lang/StringBuilder;
      86: invokevirtual #19                 // Method java/lang/StringBuilder.toString:()Ljava/lang/String;
      89: areturn
}
