Compiled from "MonitoringServerCallListener.java"
class org.apache.bookkeeper.common.grpc.stats.MonitoringServerCallListener<RespT> extends io.grpc.ForwardingServerCallListener<RespT> {
  private final io.grpc.ServerCall$Listener<RespT> delegate;

  private final org.apache.bookkeeper.common.grpc.stats.ServerStats stats;

  org.apache.bookkeeper.common.grpc.stats.MonitoringServerCallListener(io.grpc.ServerCall$Listener<RespT>, org.apache.bookkeeper.common.grpc.stats.ServerStats);
    Code:
       0: aload_0
       1: invokespecial #1                  // Method io/grpc/ForwardingServerCallListener."<init>":()V
       4: aload_0
       5: aload_1
       6: putfield      #2                  // Field delegate:Lio/grpc/ServerCall$Listener;
       9: aload_0
      10: aload_2
      11: putfield      #3                  // Field stats:Lorg/apache/bookkeeper/common/grpc/stats/ServerStats;
      14: return

  protected io.grpc.ServerCall$Listener<RespT> delegate();
    Code:
       0: aload_0
       1: getfield      #2                  // Field delegate:Lio/grpc/ServerCall$Listener;
       4: areturn

  public void onMessage(RespT);
    Code:
       0: aload_0
       1: getfield      #3                  // Field stats:Lorg/apache/bookkeeper/common/grpc/stats/ServerStats;
       4: invokevirtual #4                  // Method org/apache/bookkeeper/common/grpc/stats/ServerStats.recordStreamMessageReceived:()V
       7: aload_0
       8: aload_1
       9: invokespecial #5                  // Method io/grpc/ForwardingServerCallListener.onMessage:(Ljava/lang/Object;)V
      12: return

  public java.lang.String toString();
    Code:
       0: aload_0
       1: getfield      #2                  // Field delegate:Lio/grpc/ServerCall$Listener;
       4: invokevirtual #6                  // Method java/lang/Object.toString:()Ljava/lang/String;
       7: areturn
}
