Compiled from "NexusConnectionException.java"
public class org.sonatype.nexus.client.NexusConnectionException extends java.lang.Exception {
  private java.util.List<org.sonatype.nexus.rest.model.NexusError> errors;

  private static final long serialVersionUID;

  public org.sonatype.nexus.client.NexusConnectionException();
    Code:
       0: aload_0
       1: invokespecial #1                  // Method java/lang/Exception."<init>":()V
       4: aload_0
       5: new           #2                  // class java/util/ArrayList
       8: dup
       9: invokespecial #3                  // Method java/util/ArrayList."<init>":()V
      12: putfield      #4                  // Field errors:Ljava/util/List;
      15: return

  public org.sonatype.nexus.client.NexusConnectionException(java.util.List<org.sonatype.nexus.rest.model.NexusError>);
    Code:
       0: aload_0
       1: invokespecial #1                  // Method java/lang/Exception."<init>":()V
       4: aload_0
       5: new           #2                  // class java/util/ArrayList
       8: dup
       9: invokespecial #3                  // Method java/util/ArrayList."<init>":()V
      12: putfield      #4                  // Field errors:Ljava/util/List;
      15: aload_0
      16: aload_1
      17: putfield      #4                  // Field errors:Ljava/util/List;
      20: return

  public org.sonatype.nexus.client.NexusConnectionException(java.lang.String, java.lang.Throwable);
    Code:
       0: aload_0
       1: aload_1
       2: aload_2
       3: invokespecial #5                  // Method java/lang/Exception."<init>":(Ljava/lang/String;Ljava/lang/Throwable;)V
       6: aload_0
       7: new           #2                  // class java/util/ArrayList
      10: dup
      11: invokespecial #3                  // Method java/util/ArrayList."<init>":()V
      14: putfield      #4                  // Field errors:Ljava/util/List;
      17: return

  public org.sonatype.nexus.client.NexusConnectionException(java.lang.String, java.lang.Throwable, java.util.List<org.sonatype.nexus.rest.model.NexusError>);
    Code:
       0: aload_0
       1: aload_1
       2: aload_2
       3: invokespecial #5                  // Method java/lang/Exception."<init>":(Ljava/lang/String;Ljava/lang/Throwable;)V
       6: aload_0
       7: new           #2                  // class java/util/ArrayList
      10: dup
      11: invokespecial #3                  // Method java/util/ArrayList."<init>":()V
      14: putfield      #4                  // Field errors:Ljava/util/List;
      17: aload_0
      18: aload_3
      19: putfield      #4                  // Field errors:Ljava/util/List;
      22: return

  public org.sonatype.nexus.client.NexusConnectionException(java.lang.String);
    Code:
       0: aload_0
       1: aload_1
       2: invokespecial #6                  // Method java/lang/Exception."<init>":(Ljava/lang/String;)V
       5: aload_0
       6: new           #2                  // class java/util/ArrayList
       9: dup
      10: invokespecial #3                  // Method java/util/ArrayList."<init>":()V
      13: putfield      #4                  // Field errors:Ljava/util/List;
      16: return

  public org.sonatype.nexus.client.NexusConnectionException(java.lang.String, java.util.List<org.sonatype.nexus.rest.model.NexusError>);
    Code:
       0: aload_0
       1: aload_1
       2: invokespecial #6                  // Method java/lang/Exception."<init>":(Ljava/lang/String;)V
       5: aload_0
       6: new           #2                  // class java/util/ArrayList
       9: dup
      10: invokespecial #3                  // Method java/util/ArrayList."<init>":()V
      13: putfield      #4                  // Field errors:Ljava/util/List;
      16: aload_0
      17: aload_2
      18: putfield      #4                  // Field errors:Ljava/util/List;
      21: return

  public org.sonatype.nexus.client.NexusConnectionException(java.lang.Throwable);
    Code:
       0: aload_0
       1: aload_1
       2: invokespecial #7                  // Method java/lang/Exception."<init>":(Ljava/lang/Throwable;)V
       5: aload_0
       6: new           #2                  // class java/util/ArrayList
       9: dup
      10: invokespecial #3                  // Method java/util/ArrayList."<init>":()V
      13: putfield      #4                  // Field errors:Ljava/util/List;
      16: return

  public org.sonatype.nexus.client.NexusConnectionException(java.lang.Throwable, java.util.List<org.sonatype.nexus.rest.model.NexusError>);
    Code:
       0: aload_0
       1: aload_1
       2: invokespecial #7                  // Method java/lang/Exception."<init>":(Ljava/lang/Throwable;)V
       5: aload_0
       6: new           #2                  // class java/util/ArrayList
       9: dup
      10: invokespecial #3                  // Method java/util/ArrayList."<init>":()V
      13: putfield      #4                  // Field errors:Ljava/util/List;
      16: aload_0
      17: aload_2
      18: putfield      #4                  // Field errors:Ljava/util/List;
      21: return

  public java.util.List<org.sonatype.nexus.rest.model.NexusError> getErrors();
    Code:
       0: aload_0
       1: getfield      #4                  // Field errors:Ljava/util/List;
       4: areturn

  public java.lang.String getMessage();
    Code:
       0: new           #8                  // class java/lang/StringBuffer
       3: dup
       4: aload_0
       5: invokespecial #9                  // Method java/lang/Exception.getMessage:()Ljava/lang/String;
       8: invokespecial #10                 // Method java/lang/StringBuffer."<init>":(Ljava/lang/String;)V
      11: astore_1
      12: aload_0
      13: invokevirtual #11                 // Method getErrors:()Ljava/util/List;
      16: ifnull        65
      19: aload_0
      20: invokevirtual #11                 // Method getErrors:()Ljava/util/List;
      23: invokeinterface #12,  1           // InterfaceMethod java/util/List.iterator:()Ljava/util/Iterator;
      28: astore_2
      29: aload_2
      30: invokeinterface #13,  1           // InterfaceMethod java/util/Iterator.hasNext:()Z
      35: ifeq          65
      38: aload_2
      39: invokeinterface #14,  1           // InterfaceMethod java/util/Iterator.next:()Ljava/lang/Object;
      44: checkcast     #15                 // class org/sonatype/nexus/rest/model/NexusError
      47: astore_3
      48: aload_1
      49: ldc           #16                 // String \n
      51: invokevirtual #17                 // Method java/lang/StringBuffer.append:(Ljava/lang/String;)Ljava/lang/StringBuffer;
      54: aload_3
      55: invokevirtual #18                 // Method org/sonatype/nexus/rest/model/NexusError.getMsg:()Ljava/lang/String;
      58: invokevirtual #17                 // Method java/lang/StringBuffer.append:(Ljava/lang/String;)Ljava/lang/StringBuffer;
      61: pop
      62: goto          29
      65: aload_1
      66: invokevirtual #19                 // Method java/lang/StringBuffer.toString:()Ljava/lang/String;
      69: areturn
}
