Compiled from "StdSerializer.java"
public abstract class com.fasterxml.jackson.databind.ser.std.StdSerializer<T> extends com.fasterxml.jackson.databind.JsonSerializer<T> implements com.fasterxml.jackson.databind.jsonFormatVisitors.JsonFormatVisitable, com.fasterxml.jackson.databind.jsonschema.SchemaAware, java.io.Serializable {
  private static final java.lang.Object CONVERTING_CONTENT_CONVERTER_LOCK;

  private static final long serialVersionUID;

  protected final java.lang.Class<T> _handledType;

  protected com.fasterxml.jackson.databind.ser.std.StdSerializer(java.lang.Class<T>);
    Code:
       0: aload_0
       1: invokespecial #1                  // Method com/fasterxml/jackson/databind/JsonSerializer."<init>":()V
       4: aload_0
       5: aload_1
       6: putfield      #2                  // Field _handledType:Ljava/lang/Class;
       9: return

  protected com.fasterxml.jackson.databind.ser.std.StdSerializer(com.fasterxml.jackson.databind.JavaType);
    Code:
       0: aload_0
       1: invokespecial #1                  // Method com/fasterxml/jackson/databind/JsonSerializer."<init>":()V
       4: aload_0
       5: aload_1
       6: invokevirtual #3                  // Method com/fasterxml/jackson/databind/JavaType.getRawClass:()Ljava/lang/Class;
       9: putfield      #2                  // Field _handledType:Ljava/lang/Class;
      12: return

  protected com.fasterxml.jackson.databind.ser.std.StdSerializer(java.lang.Class<?>, boolean);
    Code:
       0: aload_0
       1: invokespecial #1                  // Method com/fasterxml/jackson/databind/JsonSerializer."<init>":()V
       4: aload_0
       5: aload_1
       6: putfield      #2                  // Field _handledType:Ljava/lang/Class;
       9: return

  protected com.fasterxml.jackson.databind.ser.std.StdSerializer(com.fasterxml.jackson.databind.ser.std.StdSerializer<?>);
    Code:
       0: aload_0
       1: invokespecial #1                  // Method com/fasterxml/jackson/databind/JsonSerializer."<init>":()V
       4: aload_0
       5: aload_1
       6: getfield      #2                  // Field _handledType:Ljava/lang/Class;
       9: putfield      #2                  // Field _handledType:Ljava/lang/Class;
      12: return

  public java.lang.Class<T> handledType();
    Code:
       0: aload_0
       1: getfield      #2                  // Field _handledType:Ljava/lang/Class;
       4: areturn

  public abstract void serialize(T, com.fasterxml.jackson.core.JsonGenerator, com.fasterxml.jackson.databind.SerializerProvider) throws java.io.IOException;

  public void acceptJsonFormatVisitor(com.fasterxml.jackson.databind.jsonFormatVisitors.JsonFormatVisitorWrapper, com.fasterxml.jackson.databind.JavaType) throws com.fasterxml.jackson.databind.JsonMappingException;
    Code:
       0: aload_1
       1: aload_2
       2: invokeinterface #4,  2            // InterfaceMethod com/fasterxml/jackson/databind/jsonFormatVisitors/JsonFormatVisitorWrapper.expectAnyFormat:(Lcom/fasterxml/jackson/databind/JavaType;)Lcom/fasterxml/jackson/databind/jsonFormatVisitors/JsonAnyFormatVisitor;
       7: pop
       8: return

  public com.fasterxml.jackson.databind.JsonNode getSchema(com.fasterxml.jackson.databind.SerializerProvider, java.lang.reflect.Type) throws com.fasterxml.jackson.databind.JsonMappingException;
    Code:
       0: aload_0
       1: ldc           #5                  // String string
       3: invokevirtual #6                  // Method createSchemaNode:(Ljava/lang/String;)Lcom/fasterxml/jackson/databind/node/ObjectNode;
       6: areturn

  public com.fasterxml.jackson.databind.JsonNode getSchema(com.fasterxml.jackson.databind.SerializerProvider, java.lang.reflect.Type, boolean) throws com.fasterxml.jackson.databind.JsonMappingException;
    Code:
       0: aload_0
       1: aload_1
       2: aload_2
       3: invokevirtual #7                  // Method getSchema:(Lcom/fasterxml/jackson/databind/SerializerProvider;Ljava/lang/reflect/Type;)Lcom/fasterxml/jackson/databind/JsonNode;
       6: checkcast     #8                  // class com/fasterxml/jackson/databind/node/ObjectNode
       9: astore        4
      11: iload_3
      12: ifne          32
      15: aload         4
      17: ldc           #9                  // String required
      19: iload_3
      20: ifne          27
      23: iconst_1
      24: goto          28
      27: iconst_0
      28: invokevirtual #10                 // Method com/fasterxml/jackson/databind/node/ObjectNode.put:(Ljava/lang/String;Z)Lcom/fasterxml/jackson/databind/node/ObjectNode;
      31: pop
      32: aload         4
      34: areturn

  protected com.fasterxml.jackson.databind.node.ObjectNode createObjectNode();
    Code:
       0: getstatic     #11                 // Field com/fasterxml/jackson/databind/node/JsonNodeFactory.instance:Lcom/fasterxml/jackson/databind/node/JsonNodeFactory;
       3: invokevirtual #12                 // Method com/fasterxml/jackson/databind/node/JsonNodeFactory.objectNode:()Lcom/fasterxml/jackson/databind/node/ObjectNode;
       6: areturn

  protected com.fasterxml.jackson.databind.node.ObjectNode createSchemaNode(java.lang.String);
    Code:
       0: aload_0
       1: invokevirtual #13                 // Method createObjectNode:()Lcom/fasterxml/jackson/databind/node/ObjectNode;
       4: astore_2
       5: aload_2
       6: ldc           #14                 // String type
       8: aload_1
       9: invokevirtual #15                 // Method com/fasterxml/jackson/databind/node/ObjectNode.put:(Ljava/lang/String;Ljava/lang/String;)Lcom/fasterxml/jackson/databind/node/ObjectNode;
      12: pop
      13: aload_2
      14: areturn

  protected com.fasterxml.jackson.databind.node.ObjectNode createSchemaNode(java.lang.String, boolean);
    Code:
       0: aload_0
       1: aload_1
       2: invokevirtual #6                  // Method createSchemaNode:(Ljava/lang/String;)Lcom/fasterxml/jackson/databind/node/ObjectNode;
       5: astore_3
       6: iload_2
       7: ifne          26
      10: aload_3
      11: ldc           #9                  // String required
      13: iload_2
      14: ifne          21
      17: iconst_1
      18: goto          22
      21: iconst_0
      22: invokevirtual #10                 // Method com/fasterxml/jackson/databind/node/ObjectNode.put:(Ljava/lang/String;Z)Lcom/fasterxml/jackson/databind/node/ObjectNode;
      25: pop
      26: aload_3
      27: areturn

  protected void visitStringFormat(com.fasterxml.jackson.databind.jsonFormatVisitors.JsonFormatVisitorWrapper, com.fasterxml.jackson.databind.JavaType) throws com.fasterxml.jackson.databind.JsonMappingException;
    Code:
       0: aload_1
       1: ifnull        12
       4: aload_1
       5: aload_2
       6: invokeinterface #16,  2           // InterfaceMethod com/fasterxml/jackson/databind/jsonFormatVisitors/JsonFormatVisitorWrapper.expectStringFormat:(Lcom/fasterxml/jackson/databind/JavaType;)Lcom/fasterxml/jackson/databind/jsonFormatVisitors/JsonStringFormatVisitor;
      11: pop
      12: return

  protected void visitStringFormat(com.fasterxml.jackson.databind.jsonFormatVisitors.JsonFormatVisitorWrapper, com.fasterxml.jackson.databind.JavaType, com.fasterxml.jackson.databind.jsonFormatVisitors.JsonValueFormat) throws com.fasterxml.jackson.databind.JsonMappingException;
    Code:
       0: aload_1
       1: ifnull        26
       4: aload_1
       5: aload_2
       6: invokeinterface #16,  2           // InterfaceMethod com/fasterxml/jackson/databind/jsonFormatVisitors/JsonFormatVisitorWrapper.expectStringFormat:(Lcom/fasterxml/jackson/databind/JavaType;)Lcom/fasterxml/jackson/databind/jsonFormatVisitors/JsonStringFormatVisitor;
      11: astore        4
      13: aload         4
      15: ifnull        26
      18: aload         4
      20: aload_3
      21: invokeinterface #17,  2           // InterfaceMethod com/fasterxml/jackson/databind/jsonFormatVisitors/JsonStringFormatVisitor.format:(Lcom/fasterxml/jackson/databind/jsonFormatVisitors/JsonValueFormat;)V
      26: return

  protected void visitIntFormat(com.fasterxml.jackson.databind.jsonFormatVisitors.JsonFormatVisitorWrapper, com.fasterxml.jackson.databind.JavaType, com.fasterxml.jackson.core.JsonParser$NumberType) throws com.fasterxml.jackson.databind.JsonMappingException;
    Code:
       0: aload_1
       1: ifnull        30
       4: aload_1
       5: aload_2
       6: invokeinterface #18,  2           // InterfaceMethod com/fasterxml/jackson/databind/jsonFormatVisitors/JsonFormatVisitorWrapper.expectIntegerFormat:(Lcom/fasterxml/jackson/databind/JavaType;)Lcom/fasterxml/jackson/databind/jsonFormatVisitors/JsonIntegerFormatVisitor;
      11: astore        4
      13: aload         4
      15: ifnull        30
      18: aload_3
      19: ifnull        30
      22: aload         4
      24: aload_3
      25: invokeinterface #19,  2           // InterfaceMethod com/fasterxml/jackson/databind/jsonFormatVisitors/JsonIntegerFormatVisitor.numberType:(Lcom/fasterxml/jackson/core/JsonParser$NumberType;)V
      30: return

  protected void visitIntFormat(com.fasterxml.jackson.databind.jsonFormatVisitors.JsonFormatVisitorWrapper, com.fasterxml.jackson.databind.JavaType, com.fasterxml.jackson.core.JsonParser$NumberType, com.fasterxml.jackson.databind.jsonFormatVisitors.JsonValueFormat) throws com.fasterxml.jackson.databind.JsonMappingException;
    Code:
       0: aload_1
       1: ifnull        44
       4: aload_1
       5: aload_2
       6: invokeinterface #18,  2           // InterfaceMethod com/fasterxml/jackson/databind/jsonFormatVisitors/JsonFormatVisitorWrapper.expectIntegerFormat:(Lcom/fasterxml/jackson/databind/JavaType;)Lcom/fasterxml/jackson/databind/jsonFormatVisitors/JsonIntegerFormatVisitor;
      11: astore        5
      13: aload         5
      15: ifnull        44
      18: aload_3
      19: ifnull        30
      22: aload         5
      24: aload_3
      25: invokeinterface #19,  2           // InterfaceMethod com/fasterxml/jackson/databind/jsonFormatVisitors/JsonIntegerFormatVisitor.numberType:(Lcom/fasterxml/jackson/core/JsonParser$NumberType;)V
      30: aload         4
      32: ifnull        44
      35: aload         5
      37: aload         4
      39: invokeinterface #20,  2           // InterfaceMethod com/fasterxml/jackson/databind/jsonFormatVisitors/JsonIntegerFormatVisitor.format:(Lcom/fasterxml/jackson/databind/jsonFormatVisitors/JsonValueFormat;)V
      44: return

  protected void visitFloatFormat(com.fasterxml.jackson.databind.jsonFormatVisitors.JsonFormatVisitorWrapper, com.fasterxml.jackson.databind.JavaType, com.fasterxml.jackson.core.JsonParser$NumberType) throws com.fasterxml.jackson.databind.JsonMappingException;
    Code:
       0: aload_1
       1: ifnull        26
       4: aload_1
       5: aload_2
       6: invokeinterface #21,  2           // InterfaceMethod com/fasterxml/jackson/databind/jsonFormatVisitors/JsonFormatVisitorWrapper.expectNumberFormat:(Lcom/fasterxml/jackson/databind/JavaType;)Lcom/fasterxml/jackson/databind/jsonFormatVisitors/JsonNumberFormatVisitor;
      11: astore        4
      13: aload         4
      15: ifnull        26
      18: aload         4
      20: aload_3
      21: invokeinterface #22,  2           // InterfaceMethod com/fasterxml/jackson/databind/jsonFormatVisitors/JsonNumberFormatVisitor.numberType:(Lcom/fasterxml/jackson/core/JsonParser$NumberType;)V
      26: return

  protected void visitArrayFormat(com.fasterxml.jackson.databind.jsonFormatVisitors.JsonFormatVisitorWrapper, com.fasterxml.jackson.databind.JavaType, com.fasterxml.jackson.databind.JsonSerializer<?>, com.fasterxml.jackson.databind.JavaType) throws com.fasterxml.jackson.databind.JsonMappingException;
    Code:
       0: aload_1
       1: ifnull        32
       4: aload_1
       5: aload_2
       6: invokeinterface #23,  2           // InterfaceMethod com/fasterxml/jackson/databind/jsonFormatVisitors/JsonFormatVisitorWrapper.expectArrayFormat:(Lcom/fasterxml/jackson/databind/JavaType;)Lcom/fasterxml/jackson/databind/jsonFormatVisitors/JsonArrayFormatVisitor;
      11: astore        5
      13: aload         5
      15: ifnull        32
      18: aload_3
      19: ifnull        32
      22: aload         5
      24: aload_3
      25: aload         4
      27: invokeinterface #24,  3           // InterfaceMethod com/fasterxml/jackson/databind/jsonFormatVisitors/JsonArrayFormatVisitor.itemsFormat:(Lcom/fasterxml/jackson/databind/jsonFormatVisitors/JsonFormatVisitable;Lcom/fasterxml/jackson/databind/JavaType;)V
      32: return

  protected void visitArrayFormat(com.fasterxml.jackson.databind.jsonFormatVisitors.JsonFormatVisitorWrapper, com.fasterxml.jackson.databind.JavaType, com.fasterxml.jackson.databind.jsonFormatVisitors.JsonFormatTypes) throws com.fasterxml.jackson.databind.JsonMappingException;
    Code:
       0: aload_1
       1: ifnull        26
       4: aload_1
       5: aload_2
       6: invokeinterface #23,  2           // InterfaceMethod com/fasterxml/jackson/databind/jsonFormatVisitors/JsonFormatVisitorWrapper.expectArrayFormat:(Lcom/fasterxml/jackson/databind/JavaType;)Lcom/fasterxml/jackson/databind/jsonFormatVisitors/JsonArrayFormatVisitor;
      11: astore        4
      13: aload         4
      15: ifnull        26
      18: aload         4
      20: aload_3
      21: invokeinterface #25,  2           // InterfaceMethod com/fasterxml/jackson/databind/jsonFormatVisitors/JsonArrayFormatVisitor.itemsFormat:(Lcom/fasterxml/jackson/databind/jsonFormatVisitors/JsonFormatTypes;)V
      26: return

  public void wrapAndThrow(com.fasterxml.jackson.databind.SerializerProvider, java.lang.Throwable, java.lang.Object, java.lang.String) throws java.io.IOException;
    Code:
       0: aload_2
       1: instanceof    #26                 // class java/lang/reflect/InvocationTargetException
       4: ifeq          22
       7: aload_2
       8: invokevirtual #27                 // Method java/lang/Throwable.getCause:()Ljava/lang/Throwable;
      11: ifnull        22
      14: aload_2
      15: invokevirtual #27                 // Method java/lang/Throwable.getCause:()Ljava/lang/Throwable;
      18: astore_2
      19: goto          0
      22: aload_2
      23: instanceof    #28                 // class java/lang/Error
      26: ifeq          34
      29: aload_2
      30: checkcast     #28                 // class java/lang/Error
      33: athrow
      34: aload_1
      35: ifnull        48
      38: aload_1
      39: getstatic     #29                 // Field com/fasterxml/jackson/databind/SerializationFeature.WRAP_EXCEPTIONS:Lcom/fasterxml/jackson/databind/SerializationFeature;
      42: invokevirtual #30                 // Method com/fasterxml/jackson/databind/SerializerProvider.isEnabled:(Lcom/fasterxml/jackson/databind/SerializationFeature;)Z
      45: ifeq          52
      48: iconst_1
      49: goto          53
      52: iconst_0
      53: istore        5
      55: aload_2
      56: instanceof    #31                 // class java/io/IOException
      59: ifeq          79
      62: iload         5
      64: ifeq          74
      67: aload_2
      68: instanceof    #32                 // class com/fasterxml/jackson/databind/JsonMappingException
      71: ifne          96
      74: aload_2
      75: checkcast     #31                 // class java/io/IOException
      78: athrow
      79: iload         5
      81: ifne          96
      84: aload_2
      85: instanceof    #33                 // class java/lang/RuntimeException
      88: ifeq          96
      91: aload_2
      92: checkcast     #33                 // class java/lang/RuntimeException
      95: athrow
      96: aload_2
      97: aload_3
      98: aload         4
     100: invokestatic  #34                 // Method com/fasterxml/jackson/databind/JsonMappingException.wrapWithPath:(Ljava/lang/Throwable;Ljava/lang/Object;Ljava/lang/String;)Lcom/fasterxml/jackson/databind/JsonMappingException;
     103: athrow

  public void wrapAndThrow(com.fasterxml.jackson.databind.SerializerProvider, java.lang.Throwable, java.lang.Object, int) throws java.io.IOException;
    Code:
       0: aload_2
       1: instanceof    #26                 // class java/lang/reflect/InvocationTargetException
       4: ifeq          22
       7: aload_2
       8: invokevirtual #27                 // Method java/lang/Throwable.getCause:()Ljava/lang/Throwable;
      11: ifnull        22
      14: aload_2
      15: invokevirtual #27                 // Method java/lang/Throwable.getCause:()Ljava/lang/Throwable;
      18: astore_2
      19: goto          0
      22: aload_2
      23: instanceof    #28                 // class java/lang/Error
      26: ifeq          34
      29: aload_2
      30: checkcast     #28                 // class java/lang/Error
      33: athrow
      34: aload_1
      35: ifnull        48
      38: aload_1
      39: getstatic     #29                 // Field com/fasterxml/jackson/databind/SerializationFeature.WRAP_EXCEPTIONS:Lcom/fasterxml/jackson/databind/SerializationFeature;
      42: invokevirtual #30                 // Method com/fasterxml/jackson/databind/SerializerProvider.isEnabled:(Lcom/fasterxml/jackson/databind/SerializationFeature;)Z
      45: ifeq          52
      48: iconst_1
      49: goto          53
      52: iconst_0
      53: istore        5
      55: aload_2
      56: instanceof    #31                 // class java/io/IOException
      59: ifeq          79
      62: iload         5
      64: ifeq          74
      67: aload_2
      68: instanceof    #32                 // class com/fasterxml/jackson/databind/JsonMappingException
      71: ifne          96
      74: aload_2
      75: checkcast     #31                 // class java/io/IOException
      78: athrow
      79: iload         5
      81: ifne          96
      84: aload_2
      85: instanceof    #33                 // class java/lang/RuntimeException
      88: ifeq          96
      91: aload_2
      92: checkcast     #33                 // class java/lang/RuntimeException
      95: athrow
      96: aload_2
      97: aload_3
      98: iload         4
     100: invokestatic  #35                 // Method com/fasterxml/jackson/databind/JsonMappingException.wrapWithPath:(Ljava/lang/Throwable;Ljava/lang/Object;I)Lcom/fasterxml/jackson/databind/JsonMappingException;
     103: athrow

  protected com.fasterxml.jackson.databind.JsonSerializer<?> findConvertingContentSerializer(com.fasterxml.jackson.databind.SerializerProvider, com.fasterxml.jackson.databind.BeanProperty, com.fasterxml.jackson.databind.JsonSerializer<?>) throws com.fasterxml.jackson.databind.JsonMappingException;
    Code:
       0: aload_1
       1: getstatic     #36                 // Field CONVERTING_CONTENT_CONVERTER_LOCK:Ljava/lang/Object;
       4: invokevirtual #37                 // Method com/fasterxml/jackson/databind/SerializerProvider.getAttribute:(Ljava/lang/Object;)Ljava/lang/Object;
       7: astore        4
       9: aload         4
      11: ifnull        24
      14: aload         4
      16: getstatic     #38                 // Field java/lang/Boolean.TRUE:Ljava/lang/Boolean;
      19: if_acmpne     24
      22: aload_3
      23: areturn
      24: aload_1
      25: invokevirtual #39                 // Method com/fasterxml/jackson/databind/SerializerProvider.getAnnotationIntrospector:()Lcom/fasterxml/jackson/databind/AnnotationIntrospector;
      28: astore        5
      30: aload         5
      32: ifnull        162
      35: aload_2
      36: ifnull        162
      39: aload_2
      40: invokeinterface #40,  1           // InterfaceMethod com/fasterxml/jackson/databind/BeanProperty.getMember:()Lcom/fasterxml/jackson/databind/introspect/AnnotatedMember;
      45: astore        6
      47: aload         6
      49: ifnull        162
      52: aload_1
      53: getstatic     #36                 // Field CONVERTING_CONTENT_CONVERTER_LOCK:Ljava/lang/Object;
      56: getstatic     #38                 // Field java/lang/Boolean.TRUE:Ljava/lang/Boolean;
      59: invokevirtual #41                 // Method com/fasterxml/jackson/databind/SerializerProvider.setAttribute:(Ljava/lang/Object;Ljava/lang/Object;)Lcom/fasterxml/jackson/databind/SerializerProvider;
      62: pop
      63: aload         5
      65: aload         6
      67: invokevirtual #42                 // Method com/fasterxml/jackson/databind/AnnotationIntrospector.findSerializationContentConverter:(Lcom/fasterxml/jackson/databind/introspect/AnnotatedMember;)Ljava/lang/Object;
      70: astore        7
      72: aload_1
      73: getstatic     #36                 // Field CONVERTING_CONTENT_CONVERTER_LOCK:Ljava/lang/Object;
      76: aconst_null
      77: invokevirtual #41                 // Method com/fasterxml/jackson/databind/SerializerProvider.setAttribute:(Ljava/lang/Object;Ljava/lang/Object;)Lcom/fasterxml/jackson/databind/SerializerProvider;
      80: pop
      81: goto          98
      84: astore        8
      86: aload_1
      87: getstatic     #36                 // Field CONVERTING_CONTENT_CONVERTER_LOCK:Ljava/lang/Object;
      90: aconst_null
      91: invokevirtual #41                 // Method com/fasterxml/jackson/databind/SerializerProvider.setAttribute:(Ljava/lang/Object;Ljava/lang/Object;)Lcom/fasterxml/jackson/databind/SerializerProvider;
      94: pop
      95: aload         8
      97: athrow
      98: aload         7
     100: ifnull        162
     103: aload_1
     104: aload_2
     105: invokeinterface #40,  1           // InterfaceMethod com/fasterxml/jackson/databind/BeanProperty.getMember:()Lcom/fasterxml/jackson/databind/introspect/AnnotatedMember;
     110: aload         7
     112: invokevirtual #43                 // Method com/fasterxml/jackson/databind/SerializerProvider.converterInstance:(Lcom/fasterxml/jackson/databind/introspect/Annotated;Ljava/lang/Object;)Lcom/fasterxml/jackson/databind/util/Converter;
     115: astore        8
     117: aload         8
     119: aload_1
     120: invokevirtual #44                 // Method com/fasterxml/jackson/databind/SerializerProvider.getTypeFactory:()Lcom/fasterxml/jackson/databind/type/TypeFactory;
     123: invokeinterface #45,  2           // InterfaceMethod com/fasterxml/jackson/databind/util/Converter.getOutputType:(Lcom/fasterxml/jackson/databind/type/TypeFactory;)Lcom/fasterxml/jackson/databind/JavaType;
     128: astore        9
     130: aload_3
     131: ifnonnull     149
     134: aload         9
     136: invokevirtual #46                 // Method com/fasterxml/jackson/databind/JavaType.isJavaLangObject:()Z
     139: ifne          149
     142: aload_1
     143: aload         9
     145: invokevirtual #47                 // Method com/fasterxml/jackson/databind/SerializerProvider.findValueSerializer:(Lcom/fasterxml/jackson/databind/JavaType;)Lcom/fasterxml/jackson/databind/JsonSerializer;
     148: astore_3
     149: new           #48                 // class com/fasterxml/jackson/databind/ser/std/StdDelegatingSerializer
     152: dup
     153: aload         8
     155: aload         9
     157: aload_3
     158: invokespecial #49                 // Method com/fasterxml/jackson/databind/ser/std/StdDelegatingSerializer."<init>":(Lcom/fasterxml/jackson/databind/util/Converter;Lcom/fasterxml/jackson/databind/JavaType;Lcom/fasterxml/jackson/databind/JsonSerializer;)V
     161: areturn
     162: aload_3
     163: areturn
    Exception table:
       from    to  target type
          63    72    84   any
          84    86    84   any

  protected com.fasterxml.jackson.databind.ser.PropertyFilter findPropertyFilter(com.fasterxml.jackson.databind.SerializerProvider, java.lang.Object, java.lang.Object) throws com.fasterxml.jackson.databind.JsonMappingException;
    Code:
       0: aload_1
       1: invokevirtual #50                 // Method com/fasterxml/jackson/databind/SerializerProvider.getFilterProvider:()Lcom/fasterxml/jackson/databind/ser/FilterProvider;
       4: astore        4
       6: aload         4
       8: ifnonnull     40
      11: aload_1
      12: new           #51                 // class java/lang/StringBuilder
      15: dup
      16: invokespecial #52                 // Method java/lang/StringBuilder."<init>":()V
      19: ldc           #53                 // String Can not resolve PropertyFilter with id \'
      21: invokevirtual #54                 // Method java/lang/StringBuilder.append:(Ljava/lang/String;)Ljava/lang/StringBuilder;
      24: aload_2
      25: invokevirtual #55                 // Method java/lang/StringBuilder.append:(Ljava/lang/Object;)Ljava/lang/StringBuilder;
      28: ldc           #56                 // String \'; no FilterProvider configured
      30: invokevirtual #54                 // Method java/lang/StringBuilder.append:(Ljava/lang/String;)Ljava/lang/StringBuilder;
      33: invokevirtual #57                 // Method java/lang/StringBuilder.toString:()Ljava/lang/String;
      36: invokestatic  #58                 // Method com/fasterxml/jackson/databind/JsonMappingException.from:(Lcom/fasterxml/jackson/databind/SerializerProvider;Ljava/lang/String;)Lcom/fasterxml/jackson/databind/JsonMappingException;
      39: athrow
      40: aload         4
      42: aload_2
      43: aload_3
      44: invokevirtual #59                 // Method com/fasterxml/jackson/databind/ser/FilterProvider.findPropertyFilter:(Ljava/lang/Object;Ljava/lang/Object;)Lcom/fasterxml/jackson/databind/ser/PropertyFilter;
      47: areturn

  protected com.fasterxml.jackson.annotation.JsonFormat$Value findFormatOverrides(com.fasterxml.jackson.databind.SerializerProvider, com.fasterxml.jackson.databind.BeanProperty, java.lang.Class<?>);
    Code:
       0: aload_2
       1: ifnull        16
       4: aload_2
       5: aload_1
       6: invokevirtual #60                 // Method com/fasterxml/jackson/databind/SerializerProvider.getConfig:()Lcom/fasterxml/jackson/databind/SerializationConfig;
       9: aload_3
      10: invokeinterface #61,  3           // InterfaceMethod com/fasterxml/jackson/databind/BeanProperty.findPropertyFormat:(Lcom/fasterxml/jackson/databind/cfg/MapperConfig;Ljava/lang/Class;)Lcom/fasterxml/jackson/annotation/JsonFormat$Value;
      15: areturn
      16: aload_1
      17: aload_3
      18: invokevirtual #62                 // Method com/fasterxml/jackson/databind/SerializerProvider.getDefaultPropertyFormat:(Ljava/lang/Class;)Lcom/fasterxml/jackson/annotation/JsonFormat$Value;
      21: areturn

  protected java.lang.Boolean findFormatFeature(com.fasterxml.jackson.databind.SerializerProvider, com.fasterxml.jackson.databind.BeanProperty, java.lang.Class<?>, com.fasterxml.jackson.annotation.JsonFormat$Feature);
    Code:
       0: aload_0
       1: aload_1
       2: aload_2
       3: aload_3
       4: invokevirtual #63                 // Method findFormatOverrides:(Lcom/fasterxml/jackson/databind/SerializerProvider;Lcom/fasterxml/jackson/databind/BeanProperty;Ljava/lang/Class;)Lcom/fasterxml/jackson/annotation/JsonFormat$Value;
       7: astore        5
       9: aload         5
      11: ifnull        22
      14: aload         5
      16: aload         4
      18: invokevirtual #64                 // Method com/fasterxml/jackson/annotation/JsonFormat$Value.getFeature:(Lcom/fasterxml/jackson/annotation/JsonFormat$Feature;)Ljava/lang/Boolean;
      21: areturn
      22: aconst_null
      23: areturn

  protected com.fasterxml.jackson.annotation.JsonInclude$Value findIncludeOverrides(com.fasterxml.jackson.databind.SerializerProvider, com.fasterxml.jackson.databind.BeanProperty, java.lang.Class<?>);
    Code:
       0: aload_2
       1: ifnull        16
       4: aload_2
       5: aload_1
       6: invokevirtual #60                 // Method com/fasterxml/jackson/databind/SerializerProvider.getConfig:()Lcom/fasterxml/jackson/databind/SerializationConfig;
       9: aload_3
      10: invokeinterface #65,  3           // InterfaceMethod com/fasterxml/jackson/databind/BeanProperty.findPropertyInclusion:(Lcom/fasterxml/jackson/databind/cfg/MapperConfig;Ljava/lang/Class;)Lcom/fasterxml/jackson/annotation/JsonInclude$Value;
      15: areturn
      16: aload_1
      17: aload_3
      18: invokevirtual #66                 // Method com/fasterxml/jackson/databind/SerializerProvider.getDefaultPropertyInclusion:(Ljava/lang/Class;)Lcom/fasterxml/jackson/annotation/JsonInclude$Value;
      21: areturn

  protected com.fasterxml.jackson.databind.JsonSerializer<?> findAnnotatedContentSerializer(com.fasterxml.jackson.databind.SerializerProvider, com.fasterxml.jackson.databind.BeanProperty) throws com.fasterxml.jackson.databind.JsonMappingException;
    Code:
       0: aload_2
       1: ifnull        42
       4: aload_2
       5: invokeinterface #40,  1           // InterfaceMethod com/fasterxml/jackson/databind/BeanProperty.getMember:()Lcom/fasterxml/jackson/databind/introspect/AnnotatedMember;
      10: astore_3
      11: aload_1
      12: invokevirtual #39                 // Method com/fasterxml/jackson/databind/SerializerProvider.getAnnotationIntrospector:()Lcom/fasterxml/jackson/databind/AnnotationIntrospector;
      15: astore        4
      17: aload_3
      18: ifnull        42
      21: aload         4
      23: aload_3
      24: invokevirtual #67                 // Method com/fasterxml/jackson/databind/AnnotationIntrospector.findContentSerializer:(Lcom/fasterxml/jackson/databind/introspect/Annotated;)Ljava/lang/Object;
      27: astore        5
      29: aload         5
      31: ifnull        42
      34: aload_1
      35: aload_3
      36: aload         5
      38: invokevirtual #68                 // Method com/fasterxml/jackson/databind/SerializerProvider.serializerInstance:(Lcom/fasterxml/jackson/databind/introspect/Annotated;Ljava/lang/Object;)Lcom/fasterxml/jackson/databind/JsonSerializer;
      41: areturn
      42: aconst_null
      43: areturn

  protected boolean isDefaultSerializer(com.fasterxml.jackson.databind.JsonSerializer<?>);
    Code:
       0: aload_1
       1: invokestatic  #69                 // Method com/fasterxml/jackson/databind/util/ClassUtil.isJacksonStdImpl:(Ljava/lang/Object;)Z
       4: ireturn

  static {};
    Code:
       0: new           #70                 // class java/lang/Object
       3: dup
       4: invokespecial #71                 // Method java/lang/Object."<init>":()V
       7: putstatic     #36                 // Field CONVERTING_CONTENT_CONVERTER_LOCK:Ljava/lang/Object;
      10: return
}
