Compiled from "EnhancerImpl.java"
class org.hibernate.bytecode.enhance.internal.bytebuddy.EnhancerImpl$EnhancerClassFileLocator extends net.bytebuddy.dynamic.ClassFileLocator$ForClassLoader {
  private java.lang.String className;

  private net.bytebuddy.dynamic.ClassFileLocator$Resolution resolution;

  static final boolean $assertionsDisabled;

  final org.hibernate.bytecode.enhance.internal.bytebuddy.EnhancerImpl this$0;

  protected org.hibernate.bytecode.enhance.internal.bytebuddy.EnhancerImpl$EnhancerClassFileLocator(org.hibernate.bytecode.enhance.internal.bytebuddy.EnhancerImpl, java.lang.ClassLoader);
    Code:
       0: aload_0
       1: aload_1
       2: putfield      #1                  // Field this$0:Lorg/hibernate/bytecode/enhance/internal/bytebuddy/EnhancerImpl;
       5: aload_0
       6: aload_2
       7: invokespecial #2                  // Method net/bytebuddy/dynamic/ClassFileLocator$ForClassLoader."<init>":(Ljava/lang/ClassLoader;)V
      10: return

  public net.bytebuddy.dynamic.ClassFileLocator$Resolution locate(java.lang.String) throws java.io.IOException;
    Code:
       0: getstatic     #3                  // Field $assertionsDisabled:Z
       3: ifne          18
       6: aload_1
       7: ifnonnull     18
      10: new           #4                  // class java/lang/AssertionError
      13: dup
      14: invokespecial #5                  // Method java/lang/AssertionError."<init>":()V
      17: athrow
      18: aload_1
      19: aload_0
      20: getfield      #6                  // Field className:Ljava/lang/String;
      23: invokevirtual #7                  // Method java/lang/String.equals:(Ljava/lang/Object;)Z
      26: ifeq          34
      29: aload_0
      30: getfield      #8                  // Field resolution:Lnet/bytebuddy/dynamic/ClassFileLocator$Resolution;
      33: areturn
      34: aload_0
      35: aload_1
      36: invokespecial #9                  // Method net/bytebuddy/dynamic/ClassFileLocator$ForClassLoader.locate:(Ljava/lang/String;)Lnet/bytebuddy/dynamic/ClassFileLocator$Resolution;
      39: areturn

  void setClassNameAndBytes(java.lang.String, byte[]);
    Code:
       0: getstatic     #3                  // Field $assertionsDisabled:Z
       3: ifne          18
       6: aload_1
       7: ifnonnull     18
      10: new           #4                  // class java/lang/AssertionError
      13: dup
      14: invokespecial #5                  // Method java/lang/AssertionError."<init>":()V
      17: athrow
      18: getstatic     #3                  // Field $assertionsDisabled:Z
      21: ifne          36
      24: aload_2
      25: ifnonnull     36
      28: new           #4                  // class java/lang/AssertionError
      31: dup
      32: invokespecial #5                  // Method java/lang/AssertionError."<init>":()V
      35: athrow
      36: aload_0
      37: aload_1
      38: putfield      #6                  // Field className:Ljava/lang/String;
      41: aload_0
      42: new           #10                 // class net/bytebuddy/dynamic/ClassFileLocator$Resolution$Explicit
      45: dup
      46: aload_2
      47: invokespecial #11                 // Method net/bytebuddy/dynamic/ClassFileLocator$Resolution$Explicit."<init>":([B)V
      50: putfield      #8                  // Field resolution:Lnet/bytebuddy/dynamic/ClassFileLocator$Resolution;
      53: return

  static {};
    Code:
       0: ldc           #12                 // class org/hibernate/bytecode/enhance/internal/bytebuddy/EnhancerImpl
       2: invokevirtual #13                 // Method java/lang/Class.desiredAssertionStatus:()Z
       5: ifne          12
       8: iconst_1
       9: goto          13
      12: iconst_0
      13: putstatic     #3                  // Field $assertionsDisabled:Z
      16: return
}
