Compiled from "EnhancerImpl.java"
public class org.hibernate.bytecode.enhance.internal.bytebuddy.EnhancerImpl implements org.hibernate.bytecode.enhance.spi.Enhancer {
  private static final org.hibernate.internal.CoreMessageLogger log;

  protected final org.hibernate.bytecode.enhance.internal.bytebuddy.ByteBuddyEnhancementContext enhancementContext;

  private final org.hibernate.bytecode.internal.bytebuddy.ByteBuddyState byteBuddyState;

  private final org.hibernate.bytecode.enhance.internal.bytebuddy.EnhancerImpl$EnhancerClassFileLocator classFileLocator;

  private final net.bytebuddy.pool.TypePool typePool;

  private final net.bytebuddy.dynamic.ClassFileLocator adviceLocator;

  private final net.bytebuddy.implementation.Implementation implementationTrackChange;

  private final net.bytebuddy.implementation.Implementation implementationGetDirtyAttributesWithoutCollections;

  private final net.bytebuddy.implementation.Implementation implementationAreFieldsDirtyWithoutCollections;

  private final net.bytebuddy.implementation.Implementation implementationClearDirtyAttributesWithoutCollections;

  private final net.bytebuddy.implementation.Implementation implementationSuspendDirtyTracking;

  private final net.bytebuddy.implementation.Implementation implementationGetDirtyAttributes;

  private final net.bytebuddy.implementation.Implementation implementationAreFieldsDirty;

  private final net.bytebuddy.implementation.Implementation implementationGetCollectionTrackerWithoutCollections;

  private final net.bytebuddy.implementation.Implementation implementationClearDirtyAttributes;

  private final net.bytebuddy.asm.Advice adviceInitializeLazyAttributeLoadingInterceptor;

  private final net.bytebuddy.implementation.Implementation implementationSetOwner;

  private final net.bytebuddy.implementation.Implementation implementationClearOwner;

  public org.hibernate.bytecode.enhance.internal.bytebuddy.EnhancerImpl(org.hibernate.bytecode.enhance.spi.EnhancementContext, org.hibernate.bytecode.internal.bytebuddy.ByteBuddyState);
    Code:
       0: aload_0
       1: invokespecial #1                  // Method java/lang/Object."<init>":()V
       4: aload_0
       5: ldc           #2                  // class org/hibernate/bytecode/enhance/internal/bytebuddy/CodeTemplates
       7: invokevirtual #3                  // Method java/lang/Class.getClassLoader:()Ljava/lang/ClassLoader;
      10: invokestatic  #4                  // Method net/bytebuddy/dynamic/ClassFileLocator$ForClassLoader.of:(Ljava/lang/ClassLoader;)Lnet/bytebuddy/dynamic/ClassFileLocator;
      13: putfield      #5                  // Field adviceLocator:Lnet/bytebuddy/dynamic/ClassFileLocator;
      16: aload_0
      17: ldc           #6                  // class org/hibernate/bytecode/enhance/internal/bytebuddy/CodeTemplates$TrackChange
      19: aload_0
      20: getfield      #5                  // Field adviceLocator:Lnet/bytebuddy/dynamic/ClassFileLocator;
      23: invokestatic  #7                  // Method net/bytebuddy/asm/Advice.to:(Ljava/lang/Class;Lnet/bytebuddy/dynamic/ClassFileLocator;)Lnet/bytebuddy/asm/Advice;
      26: getstatic     #8                  // Field net/bytebuddy/implementation/StubMethod.INSTANCE:Lnet/bytebuddy/implementation/StubMethod;
      29: invokevirtual #9                  // Method net/bytebuddy/asm/Advice.wrap:(Lnet/bytebuddy/implementation/Implementation;)Lnet/bytebuddy/implementation/Implementation;
      32: putfield      #10                 // Field implementationTrackChange:Lnet/bytebuddy/implementation/Implementation;
      35: aload_0
      36: ldc           #11                 // class org/hibernate/bytecode/enhance/internal/bytebuddy/CodeTemplates$GetDirtyAttributesWithoutCollections
      38: aload_0
      39: getfield      #5                  // Field adviceLocator:Lnet/bytebuddy/dynamic/ClassFileLocator;
      42: invokestatic  #7                  // Method net/bytebuddy/asm/Advice.to:(Ljava/lang/Class;Lnet/bytebuddy/dynamic/ClassFileLocator;)Lnet/bytebuddy/asm/Advice;
      45: getstatic     #8                  // Field net/bytebuddy/implementation/StubMethod.INSTANCE:Lnet/bytebuddy/implementation/StubMethod;
      48: invokevirtual #9                  // Method net/bytebuddy/asm/Advice.wrap:(Lnet/bytebuddy/implementation/Implementation;)Lnet/bytebuddy/implementation/Implementation;
      51: putfield      #12                 // Field implementationGetDirtyAttributesWithoutCollections:Lnet/bytebuddy/implementation/Implementation;
      54: aload_0
      55: ldc           #13                 // class org/hibernate/bytecode/enhance/internal/bytebuddy/CodeTemplates$AreFieldsDirtyWithoutCollections
      57: aload_0
      58: getfield      #5                  // Field adviceLocator:Lnet/bytebuddy/dynamic/ClassFileLocator;
      61: invokestatic  #7                  // Method net/bytebuddy/asm/Advice.to:(Ljava/lang/Class;Lnet/bytebuddy/dynamic/ClassFileLocator;)Lnet/bytebuddy/asm/Advice;
      64: getstatic     #8                  // Field net/bytebuddy/implementation/StubMethod.INSTANCE:Lnet/bytebuddy/implementation/StubMethod;
      67: invokevirtual #9                  // Method net/bytebuddy/asm/Advice.wrap:(Lnet/bytebuddy/implementation/Implementation;)Lnet/bytebuddy/implementation/Implementation;
      70: putfield      #14                 // Field implementationAreFieldsDirtyWithoutCollections:Lnet/bytebuddy/implementation/Implementation;
      73: aload_0
      74: ldc           #15                 // class org/hibernate/bytecode/enhance/internal/bytebuddy/CodeTemplates$ClearDirtyAttributesWithoutCollections
      76: aload_0
      77: getfield      #5                  // Field adviceLocator:Lnet/bytebuddy/dynamic/ClassFileLocator;
      80: invokestatic  #7                  // Method net/bytebuddy/asm/Advice.to:(Ljava/lang/Class;Lnet/bytebuddy/dynamic/ClassFileLocator;)Lnet/bytebuddy/asm/Advice;
      83: getstatic     #8                  // Field net/bytebuddy/implementation/StubMethod.INSTANCE:Lnet/bytebuddy/implementation/StubMethod;
      86: invokevirtual #9                  // Method net/bytebuddy/asm/Advice.wrap:(Lnet/bytebuddy/implementation/Implementation;)Lnet/bytebuddy/implementation/Implementation;
      89: putfield      #16                 // Field implementationClearDirtyAttributesWithoutCollections:Lnet/bytebuddy/implementation/Implementation;
      92: aload_0
      93: ldc           #17                 // class org/hibernate/bytecode/enhance/internal/bytebuddy/CodeTemplates$SuspendDirtyTracking
      95: aload_0
      96: getfield      #5                  // Field adviceLocator:Lnet/bytebuddy/dynamic/ClassFileLocator;
      99: invokestatic  #7                  // Method net/bytebuddy/asm/Advice.to:(Ljava/lang/Class;Lnet/bytebuddy/dynamic/ClassFileLocator;)Lnet/bytebuddy/asm/Advice;
     102: getstatic     #8                  // Field net/bytebuddy/implementation/StubMethod.INSTANCE:Lnet/bytebuddy/implementation/StubMethod;
     105: invokevirtual #9                  // Method net/bytebuddy/asm/Advice.wrap:(Lnet/bytebuddy/implementation/Implementation;)Lnet/bytebuddy/implementation/Implementation;
     108: putfield      #18                 // Field implementationSuspendDirtyTracking:Lnet/bytebuddy/implementation/Implementation;
     111: aload_0
     112: ldc           #19                 // class org/hibernate/bytecode/enhance/internal/bytebuddy/CodeTemplates$GetDirtyAttributes
     114: aload_0
     115: getfield      #5                  // Field adviceLocator:Lnet/bytebuddy/dynamic/ClassFileLocator;
     118: invokestatic  #7                  // Method net/bytebuddy/asm/Advice.to:(Ljava/lang/Class;Lnet/bytebuddy/dynamic/ClassFileLocator;)Lnet/bytebuddy/asm/Advice;
     121: getstatic     #8                  // Field net/bytebuddy/implementation/StubMethod.INSTANCE:Lnet/bytebuddy/implementation/StubMethod;
     124: invokevirtual #9                  // Method net/bytebuddy/asm/Advice.wrap:(Lnet/bytebuddy/implementation/Implementation;)Lnet/bytebuddy/implementation/Implementation;
     127: putfield      #20                 // Field implementationGetDirtyAttributes:Lnet/bytebuddy/implementation/Implementation;
     130: aload_0
     131: ldc           #21                 // class org/hibernate/bytecode/enhance/internal/bytebuddy/CodeTemplates$AreFieldsDirty
     133: aload_0
     134: getfield      #5                  // Field adviceLocator:Lnet/bytebuddy/dynamic/ClassFileLocator;
     137: invokestatic  #7                  // Method net/bytebuddy/asm/Advice.to:(Ljava/lang/Class;Lnet/bytebuddy/dynamic/ClassFileLocator;)Lnet/bytebuddy/asm/Advice;
     140: getstatic     #8                  // Field net/bytebuddy/implementation/StubMethod.INSTANCE:Lnet/bytebuddy/implementation/StubMethod;
     143: invokevirtual #9                  // Method net/bytebuddy/asm/Advice.wrap:(Lnet/bytebuddy/implementation/Implementation;)Lnet/bytebuddy/implementation/Implementation;
     146: putfield      #22                 // Field implementationAreFieldsDirty:Lnet/bytebuddy/implementation/Implementation;
     149: aload_0
     150: ldc           #23                 // class org/hibernate/bytecode/enhance/internal/bytebuddy/CodeTemplates$GetCollectionTrackerWithoutCollections
     152: aload_0
     153: getfield      #5                  // Field adviceLocator:Lnet/bytebuddy/dynamic/ClassFileLocator;
     156: invokestatic  #7                  // Method net/bytebuddy/asm/Advice.to:(Ljava/lang/Class;Lnet/bytebuddy/dynamic/ClassFileLocator;)Lnet/bytebuddy/asm/Advice;
     159: getstatic     #8                  // Field net/bytebuddy/implementation/StubMethod.INSTANCE:Lnet/bytebuddy/implementation/StubMethod;
     162: invokevirtual #9                  // Method net/bytebuddy/asm/Advice.wrap:(Lnet/bytebuddy/implementation/Implementation;)Lnet/bytebuddy/implementation/Implementation;
     165: putfield      #24                 // Field implementationGetCollectionTrackerWithoutCollections:Lnet/bytebuddy/implementation/Implementation;
     168: aload_0
     169: ldc           #25                 // class org/hibernate/bytecode/enhance/internal/bytebuddy/CodeTemplates$ClearDirtyAttributes
     171: aload_0
     172: getfield      #5                  // Field adviceLocator:Lnet/bytebuddy/dynamic/ClassFileLocator;
     175: invokestatic  #7                  // Method net/bytebuddy/asm/Advice.to:(Ljava/lang/Class;Lnet/bytebuddy/dynamic/ClassFileLocator;)Lnet/bytebuddy/asm/Advice;
     178: getstatic     #8                  // Field net/bytebuddy/implementation/StubMethod.INSTANCE:Lnet/bytebuddy/implementation/StubMethod;
     181: invokevirtual #9                  // Method net/bytebuddy/asm/Advice.wrap:(Lnet/bytebuddy/implementation/Implementation;)Lnet/bytebuddy/implementation/Implementation;
     184: putfield      #26                 // Field implementationClearDirtyAttributes:Lnet/bytebuddy/implementation/Implementation;
     187: aload_0
     188: ldc           #27                 // class org/hibernate/bytecode/enhance/internal/bytebuddy/CodeTemplates$InitializeLazyAttributeLoadingInterceptor
     190: aload_0
     191: getfield      #5                  // Field adviceLocator:Lnet/bytebuddy/dynamic/ClassFileLocator;
     194: invokestatic  #7                  // Method net/bytebuddy/asm/Advice.to:(Ljava/lang/Class;Lnet/bytebuddy/dynamic/ClassFileLocator;)Lnet/bytebuddy/asm/Advice;
     197: putfield      #28                 // Field adviceInitializeLazyAttributeLoadingInterceptor:Lnet/bytebuddy/asm/Advice;
     200: aload_0
     201: ldc           #29                 // class org/hibernate/bytecode/enhance/internal/bytebuddy/CodeTemplates$SetOwner
     203: aload_0
     204: getfield      #5                  // Field adviceLocator:Lnet/bytebuddy/dynamic/ClassFileLocator;
     207: invokestatic  #7                  // Method net/bytebuddy/asm/Advice.to:(Ljava/lang/Class;Lnet/bytebuddy/dynamic/ClassFileLocator;)Lnet/bytebuddy/asm/Advice;
     210: getstatic     #8                  // Field net/bytebuddy/implementation/StubMethod.INSTANCE:Lnet/bytebuddy/implementation/StubMethod;
     213: invokevirtual #9                  // Method net/bytebuddy/asm/Advice.wrap:(Lnet/bytebuddy/implementation/Implementation;)Lnet/bytebuddy/implementation/Implementation;
     216: putfield      #30                 // Field implementationSetOwner:Lnet/bytebuddy/implementation/Implementation;
     219: aload_0
     220: ldc           #31                 // class org/hibernate/bytecode/enhance/internal/bytebuddy/CodeTemplates$ClearOwner
     222: aload_0
     223: getfield      #5                  // Field adviceLocator:Lnet/bytebuddy/dynamic/ClassFileLocator;
     226: invokestatic  #7                  // Method net/bytebuddy/asm/Advice.to:(Ljava/lang/Class;Lnet/bytebuddy/dynamic/ClassFileLocator;)Lnet/bytebuddy/asm/Advice;
     229: getstatic     #8                  // Field net/bytebuddy/implementation/StubMethod.INSTANCE:Lnet/bytebuddy/implementation/StubMethod;
     232: invokevirtual #9                  // Method net/bytebuddy/asm/Advice.wrap:(Lnet/bytebuddy/implementation/Implementation;)Lnet/bytebuddy/implementation/Implementation;
     235: putfield      #32                 // Field implementationClearOwner:Lnet/bytebuddy/implementation/Implementation;
     238: aload_0
     239: new           #33                 // class org/hibernate/bytecode/enhance/internal/bytebuddy/ByteBuddyEnhancementContext
     242: dup
     243: aload_1
     244: invokespecial #34                 // Method org/hibernate/bytecode/enhance/internal/bytebuddy/ByteBuddyEnhancementContext."<init>":(Lorg/hibernate/bytecode/enhance/spi/EnhancementContext;)V
     247: putfield      #35                 // Field enhancementContext:Lorg/hibernate/bytecode/enhance/internal/bytebuddy/ByteBuddyEnhancementContext;
     250: aload_0
     251: aload_2
     252: putfield      #36                 // Field byteBuddyState:Lorg/hibernate/bytecode/internal/bytebuddy/ByteBuddyState;
     255: aload_0
     256: new           #37                 // class org/hibernate/bytecode/enhance/internal/bytebuddy/EnhancerImpl$EnhancerClassFileLocator
     259: dup
     260: aload_0
     261: aload_1
     262: invokeinterface #38,  1           // InterfaceMethod org/hibernate/bytecode/enhance/spi/EnhancementContext.getLoadingClassLoader:()Ljava/lang/ClassLoader;
     267: invokespecial #39                 // Method org/hibernate/bytecode/enhance/internal/bytebuddy/EnhancerImpl$EnhancerClassFileLocator."<init>":(Lorg/hibernate/bytecode/enhance/internal/bytebuddy/EnhancerImpl;Ljava/lang/ClassLoader;)V
     270: putfield      #40                 // Field classFileLocator:Lorg/hibernate/bytecode/enhance/internal/bytebuddy/EnhancerImpl$EnhancerClassFileLocator;
     273: aload_0
     274: aload_0
     275: aload_0
     276: getfield      #40                 // Field classFileLocator:Lorg/hibernate/bytecode/enhance/internal/bytebuddy/EnhancerImpl$EnhancerClassFileLocator;
     279: invokespecial #41                 // Method buildTypePool:(Lnet/bytebuddy/dynamic/ClassFileLocator;)Lnet/bytebuddy/pool/TypePool;
     282: putfield      #42                 // Field typePool:Lnet/bytebuddy/pool/TypePool;
     285: return

  public synchronized byte[] enhance(java.lang.String, byte[]) throws org.hibernate.bytecode.enhance.spi.EnhancementException;
    Code:
       0: aload_1
       1: bipush        47
       3: bipush        46
       5: invokevirtual #43                 // Method java/lang/String.replace:(CC)Ljava/lang/String;
       8: astore_3
       9: aload_0
      10: getfield      #40                 // Field classFileLocator:Lorg/hibernate/bytecode/enhance/internal/bytebuddy/EnhancerImpl$EnhancerClassFileLocator;
      13: aload_3
      14: aload_2
      15: invokevirtual #44                 // Method org/hibernate/bytecode/enhance/internal/bytebuddy/EnhancerImpl$EnhancerClassFileLocator.setClassNameAndBytes:(Ljava/lang/String;[B)V
      18: aload_0
      19: getfield      #42                 // Field typePool:Lnet/bytebuddy/pool/TypePool;
      22: aload_3
      23: invokeinterface #45,  2           // InterfaceMethod net/bytebuddy/pool/TypePool.describe:(Ljava/lang/String;)Lnet/bytebuddy/pool/TypePool$Resolution;
      28: invokeinterface #46,  1           // InterfaceMethod net/bytebuddy/pool/TypePool$Resolution.resolve:()Lnet/bytebuddy/description/type/TypeDescription;
      33: astore        4
      35: aload_0
      36: getfield      #36                 // Field byteBuddyState:Lorg/hibernate/bytecode/internal/bytebuddy/ByteBuddyState;
      39: aload_0
      40: getfield      #42                 // Field typePool:Lnet/bytebuddy/pool/TypePool;
      43: aload_3
      44: aload_0
      45: aload         4
      47: aload_3
      48: aload_2
      49: invokedynamic #47,  0             // InvokeDynamic #0:apply:(Lorg/hibernate/bytecode/enhance/internal/bytebuddy/EnhancerImpl;Lnet/bytebuddy/description/type/TypeDescription;Ljava/lang/String;[B)Ljava/util/function/Function;
      54: invokevirtual #48                 // Method org/hibernate/bytecode/internal/bytebuddy/ByteBuddyState.rewrite:(Lnet/bytebuddy/pool/TypePool;Ljava/lang/String;Ljava/util/function/Function;)[B
      57: areturn
      58: astore        4
      60: new           #50                 // class org/hibernate/bytecode/enhance/spi/EnhancementException
      63: dup
      64: new           #51                 // class java/lang/StringBuilder
      67: dup
      68: invokespecial #52                 // Method java/lang/StringBuilder."<init>":()V
      71: ldc           #53                 // String Failed to enhance class
      73: invokevirtual #54                 // Method java/lang/StringBuilder.append:(Ljava/lang/String;)Ljava/lang/StringBuilder;
      76: aload_1
      77: invokevirtual #54                 // Method java/lang/StringBuilder.append:(Ljava/lang/String;)Ljava/lang/StringBuilder;
      80: invokevirtual #55                 // Method java/lang/StringBuilder.toString:()Ljava/lang/String;
      83: aload         4
      85: invokespecial #56                 // Method org/hibernate/bytecode/enhance/spi/EnhancementException."<init>":(Ljava/lang/String;Ljava/lang/Throwable;)V
      88: athrow
    Exception table:
       from    to  target type
          18    57    58   Class java/lang/RuntimeException

  private net.bytebuddy.pool.TypePool buildTypePool(net.bytebuddy.dynamic.ClassFileLocator);
    Code:
       0: aload_1
       1: invokestatic  #57                 // Method net/bytebuddy/pool/TypePool$Default$WithLazyResolution.of:(Lnet/bytebuddy/dynamic/ClassFileLocator;)Lnet/bytebuddy/pool/TypePool;
       4: areturn

  private net.bytebuddy.dynamic.DynamicType$Builder<?> doEnhance(net.bytebuddy.dynamic.DynamicType$Builder<?>, net.bytebuddy.description.type.TypeDescription);
    Code:
       0: aload_2
       1: invokeinterface #58,  1           // InterfaceMethod net/bytebuddy/description/type/TypeDescription.isInterface:()Z
       6: ifeq          27
       9: getstatic     #59                 // Field log:Lorg/hibernate/internal/CoreMessageLogger;
      12: ldc           #60                 // String Skipping enhancement of [%s]: it\'s an interface!
      14: aload_2
      15: invokeinterface #61,  1           // InterfaceMethod net/bytebuddy/description/type/TypeDescription.getName:()Ljava/lang/String;
      20: invokeinterface #62,  3           // InterfaceMethod org/hibernate/internal/CoreMessageLogger.debugf:(Ljava/lang/String;Ljava/lang/Object;)V
      25: aconst_null
      26: areturn
      27: aload_0
      28: aload_2
      29: invokespecial #63                 // Method alreadyEnhanced:(Lnet/bytebuddy/description/type/TypeDescription;)Z
      32: ifeq          53
      35: getstatic     #59                 // Field log:Lorg/hibernate/internal/CoreMessageLogger;
      38: ldc           #64                 // String Skipping enhancement of [%s]: already enhanced
      40: aload_2
      41: invokeinterface #61,  1           // InterfaceMethod net/bytebuddy/description/type/TypeDescription.getName:()Ljava/lang/String;
      46: invokeinterface #62,  3           // InterfaceMethod org/hibernate/internal/CoreMessageLogger.debugf:(Ljava/lang/String;Ljava/lang/Object;)V
      51: aconst_null
      52: areturn
      53: aload_0
      54: getfield      #35                 // Field enhancementContext:Lorg/hibernate/bytecode/enhance/internal/bytebuddy/ByteBuddyEnhancementContext;
      57: aload_2
      58: invokevirtual #65                 // Method org/hibernate/bytecode/enhance/internal/bytebuddy/ByteBuddyEnhancementContext.isEntityClass:(Lnet/bytebuddy/description/type/TypeDescription;)Z
      61: ifeq          1260
      64: getstatic     #59                 // Field log:Lorg/hibernate/internal/CoreMessageLogger;
      67: ldc           #66                 // String Enhancing [%s] as Entity
      69: aload_2
      70: invokeinterface #61,  1           // InterfaceMethod net/bytebuddy/description/type/TypeDescription.getName:()Ljava/lang/String;
      75: invokeinterface #67,  3           // InterfaceMethod org/hibernate/internal/CoreMessageLogger.infof:(Ljava/lang/String;Ljava/lang/Object;)V
      80: aload_1
      81: iconst_1
      82: anewarray     #68                 // class java/lang/reflect/Type
      85: dup
      86: iconst_0
      87: ldc           #69                 // class org/hibernate/engine/spi/ManagedEntity
      89: aastore
      90: invokeinterface #70,  2           // InterfaceMethod net/bytebuddy/dynamic/DynamicType$Builder.implement:([Ljava/lang/reflect/Type;)Lnet/bytebuddy/dynamic/DynamicType$Builder$MethodDefinition$ImplementationDefinition$Optional;
      95: ldc           #72                 // String $$_hibernate_getEntityInstance
      97: ldc           #73                 // class java/lang/Object
      99: iconst_1
     100: anewarray     #74                 // class net/bytebuddy/description/modifier/ModifierContributor$ForMethod
     103: dup
     104: iconst_0
     105: getstatic     #75                 // Field net/bytebuddy/description/modifier/Visibility.PUBLIC:Lnet/bytebuddy/description/modifier/Visibility;
     108: aastore
     109: invokeinterface #76,  4           // InterfaceMethod net/bytebuddy/dynamic/DynamicType$Builder$MethodDefinition$ImplementationDefinition$Optional.defineMethod:(Ljava/lang/String;Ljava/lang/reflect/Type;[Lnet/bytebuddy/description/modifier/ModifierContributor$ForMethod;)Lnet/bytebuddy/dynamic/DynamicType$Builder$MethodDefinition$ParameterDefinition$Initial;
     114: invokestatic  #77                 // Method net/bytebuddy/implementation/FixedValue.self:()Lnet/bytebuddy/implementation/FixedValue$AssignerConfigurable;
     117: invokeinterface #78,  2           // InterfaceMethod net/bytebuddy/dynamic/DynamicType$Builder$MethodDefinition$ParameterDefinition$Initial.intercept:(Lnet/bytebuddy/implementation/Implementation;)Lnet/bytebuddy/dynamic/DynamicType$Builder$MethodDefinition$ReceiverTypeDefinition;
     122: astore_1
     123: aload_1
     124: ldc           #79                 // class org/hibernate/engine/spi/EntityEntry
     126: ldc           #80                 // String $$_hibernate_entityEntryHolder
     128: ldc           #81                 // String $$_hibernate_getEntityEntry
     130: ldc           #82                 // String $$_hibernate_setEntityEntry
     132: invokestatic  #83                 // Method addFieldWithGetterAndSetter:(Lnet/bytebuddy/dynamic/DynamicType$Builder;Ljava/lang/Class;Ljava/lang/String;Ljava/lang/String;Ljava/lang/String;)Lnet/bytebuddy/dynamic/DynamicType$Builder;
     135: astore_1
     136: aload_1
     137: ldc           #69                 // class org/hibernate/engine/spi/ManagedEntity
     139: ldc           #84                 // String $$_hibernate_previousManagedEntity
     141: ldc           #85                 // String $$_hibernate_getPreviousManagedEntity
     143: ldc           #86                 // String $$_hibernate_setPreviousManagedEntity
     145: invokestatic  #83                 // Method addFieldWithGetterAndSetter:(Lnet/bytebuddy/dynamic/DynamicType$Builder;Ljava/lang/Class;Ljava/lang/String;Ljava/lang/String;Ljava/lang/String;)Lnet/bytebuddy/dynamic/DynamicType$Builder;
     148: astore_1
     149: aload_1
     150: ldc           #69                 // class org/hibernate/engine/spi/ManagedEntity
     152: ldc           #87                 // String $$_hibernate_nextManagedEntity
     154: ldc           #88                 // String $$_hibernate_getNextManagedEntity
     156: ldc           #89                 // String $$_hibernate_setNextManagedEntity
     158: invokestatic  #83                 // Method addFieldWithGetterAndSetter:(Lnet/bytebuddy/dynamic/DynamicType$Builder;Ljava/lang/Class;Ljava/lang/String;Ljava/lang/String;Ljava/lang/String;)Lnet/bytebuddy/dynamic/DynamicType$Builder;
     161: astore_1
     162: aload_0
     163: aload_1
     164: aload_2
     165: invokespecial #90                 // Method addInterceptorHandling:(Lnet/bytebuddy/dynamic/DynamicType$Builder;Lnet/bytebuddy/description/type/TypeDescription;)Lnet/bytebuddy/dynamic/DynamicType$Builder;
     168: astore_1
     169: aload_0
     170: getfield      #35                 // Field enhancementContext:Lorg/hibernate/bytecode/enhance/internal/bytebuddy/ByteBuddyEnhancementContext;
     173: aload_2
     174: invokevirtual #91                 // Method org/hibernate/bytecode/enhance/internal/bytebuddy/ByteBuddyEnhancementContext.doDirtyCheckingInline:(Lnet/bytebuddy/description/type/TypeDescription;)Z
     177: ifeq          1249
     180: aload_0
     181: aload_2
     182: invokespecial #92                 // Method collectCollectionFields:(Lnet/bytebuddy/description/type/TypeDescription;)Ljava/util/List;
     185: astore_3
     186: aload_3
     187: invokeinterface #93,  1           // InterfaceMethod java/util/List.isEmpty:()Z
     192: ifeq          460
     195: aload_1
     196: iconst_1
     197: anewarray     #68                 // class java/lang/reflect/Type
     200: dup
     201: iconst_0
     202: ldc           #94                 // class org/hibernate/engine/spi/SelfDirtinessTracker
     204: aastore
     205: invokeinterface #70,  2           // InterfaceMethod net/bytebuddy/dynamic/DynamicType$Builder.implement:([Ljava/lang/reflect/Type;)Lnet/bytebuddy/dynamic/DynamicType$Builder$MethodDefinition$ImplementationDefinition$Optional;
     210: ldc           #95                 // String $$_hibernate_tracker
     212: ldc           #96                 // class org/hibernate/bytecode/enhance/internal/tracker/DirtyTracker
     214: iconst_2
     215: anewarray     #97                 // class net/bytebuddy/description/modifier/ModifierContributor$ForField
     218: dup
     219: iconst_0
     220: getstatic     #98                 // Field net/bytebuddy/description/modifier/FieldPersistence.TRANSIENT:Lnet/bytebuddy/description/modifier/FieldPersistence;
     223: aastore
     224: dup
     225: iconst_1
     226: getstatic     #99                 // Field net/bytebuddy/description/modifier/Visibility.PRIVATE:Lnet/bytebuddy/description/modifier/Visibility;
     229: aastore
     230: invokeinterface #100,  4          // InterfaceMethod net/bytebuddy/dynamic/DynamicType$Builder$MethodDefinition$ImplementationDefinition$Optional.defineField:(Ljava/lang/String;Ljava/lang/reflect/Type;[Lnet/bytebuddy/description/modifier/ModifierContributor$ForField;)Lnet/bytebuddy/dynamic/DynamicType$Builder$FieldDefinition$Optional$Valuable;
     235: iconst_1
     236: anewarray     #101                // class net/bytebuddy/description/annotation/AnnotationDescription
     239: dup
     240: iconst_0
     241: ldc           #102                // class javax/persistence/Transient
     243: invokestatic  #103                // Method net/bytebuddy/description/annotation/AnnotationDescription$Builder.ofType:(Ljava/lang/Class;)Lnet/bytebuddy/description/annotation/AnnotationDescription$Builder;
     246: invokevirtual #104                // Method net/bytebuddy/description/annotation/AnnotationDescription$Builder.build:()Lnet/bytebuddy/description/annotation/AnnotationDescription;
     249: aastore
     250: invokeinterface #105,  2          // InterfaceMethod net/bytebuddy/dynamic/DynamicType$Builder$FieldDefinition$Optional$Valuable.annotateField:([Lnet/bytebuddy/description/annotation/AnnotationDescription;)Lnet/bytebuddy/dynamic/DynamicType$Builder$FieldDefinition$Optional;
     255: ldc           #106                // String $$_hibernate_trackChange
     257: getstatic     #107                // Field java/lang/Void.TYPE:Ljava/lang/Class;
     260: iconst_1
     261: anewarray     #74                 // class net/bytebuddy/description/modifier/ModifierContributor$ForMethod
     264: dup
     265: iconst_0
     266: getstatic     #75                 // Field net/bytebuddy/description/modifier/Visibility.PUBLIC:Lnet/bytebuddy/description/modifier/Visibility;
     269: aastore
     270: invokeinterface #108,  4          // InterfaceMethod net/bytebuddy/dynamic/DynamicType$Builder$FieldDefinition$Optional.defineMethod:(Ljava/lang/String;Ljava/lang/reflect/Type;[Lnet/bytebuddy/description/modifier/ModifierContributor$ForMethod;)Lnet/bytebuddy/dynamic/DynamicType$Builder$MethodDefinition$ParameterDefinition$Initial;
     275: iconst_1
     276: anewarray     #68                 // class java/lang/reflect/Type
     279: dup
     280: iconst_0
     281: ldc           #109                // class java/lang/String
     283: aastore
     284: invokeinterface #110,  2          // InterfaceMethod net/bytebuddy/dynamic/DynamicType$Builder$MethodDefinition$ParameterDefinition$Initial.withParameters:([Ljava/lang/reflect/Type;)Lnet/bytebuddy/dynamic/DynamicType$Builder$MethodDefinition$ExceptionDefinition;
     289: aload_0
     290: getfield      #10                 // Field implementationTrackChange:Lnet/bytebuddy/implementation/Implementation;
     293: invokeinterface #111,  2          // InterfaceMethod net/bytebuddy/dynamic/DynamicType$Builder$MethodDefinition$ExceptionDefinition.intercept:(Lnet/bytebuddy/implementation/Implementation;)Lnet/bytebuddy/dynamic/DynamicType$Builder$MethodDefinition$ReceiverTypeDefinition;
     298: ldc           #112                // String $$_hibernate_getDirtyAttributes
     300: ldc           #113                // class "[Ljava/lang/String;"
     302: iconst_1
     303: anewarray     #74                 // class net/bytebuddy/description/modifier/ModifierContributor$ForMethod
     306: dup
     307: iconst_0
     308: getstatic     #75                 // Field net/bytebuddy/description/modifier/Visibility.PUBLIC:Lnet/bytebuddy/description/modifier/Visibility;
     311: aastore
     312: invokeinterface #114,  4          // InterfaceMethod net/bytebuddy/dynamic/DynamicType$Builder$MethodDefinition$ReceiverTypeDefinition.defineMethod:(Ljava/lang/String;Ljava/lang/reflect/Type;[Lnet/bytebuddy/description/modifier/ModifierContributor$ForMethod;)Lnet/bytebuddy/dynamic/DynamicType$Builder$MethodDefinition$ParameterDefinition$Initial;
     317: aload_0
     318: getfield      #12                 // Field implementationGetDirtyAttributesWithoutCollections:Lnet/bytebuddy/implementation/Implementation;
     321: invokeinterface #78,  2           // InterfaceMethod net/bytebuddy/dynamic/DynamicType$Builder$MethodDefinition$ParameterDefinition$Initial.intercept:(Lnet/bytebuddy/implementation/Implementation;)Lnet/bytebuddy/dynamic/DynamicType$Builder$MethodDefinition$ReceiverTypeDefinition;
     326: ldc           #115                // String $$_hibernate_hasDirtyAttributes
     328: getstatic     #116                // Field java/lang/Boolean.TYPE:Ljava/lang/Class;
     331: iconst_1
     332: anewarray     #74                 // class net/bytebuddy/description/modifier/ModifierContributor$ForMethod
     335: dup
     336: iconst_0
     337: getstatic     #75                 // Field net/bytebuddy/description/modifier/Visibility.PUBLIC:Lnet/bytebuddy/description/modifier/Visibility;
     340: aastore
     341: invokeinterface #114,  4          // InterfaceMethod net/bytebuddy/dynamic/DynamicType$Builder$MethodDefinition$ReceiverTypeDefinition.defineMethod:(Ljava/lang/String;Ljava/lang/reflect/Type;[Lnet/bytebuddy/description/modifier/ModifierContributor$ForMethod;)Lnet/bytebuddy/dynamic/DynamicType$Builder$MethodDefinition$ParameterDefinition$Initial;
     346: aload_0
     347: getfield      #14                 // Field implementationAreFieldsDirtyWithoutCollections:Lnet/bytebuddy/implementation/Implementation;
     350: invokeinterface #78,  2           // InterfaceMethod net/bytebuddy/dynamic/DynamicType$Builder$MethodDefinition$ParameterDefinition$Initial.intercept:(Lnet/bytebuddy/implementation/Implementation;)Lnet/bytebuddy/dynamic/DynamicType$Builder$MethodDefinition$ReceiverTypeDefinition;
     355: ldc           #117                // String $$_hibernate_clearDirtyAttributes
     357: getstatic     #107                // Field java/lang/Void.TYPE:Ljava/lang/Class;
     360: iconst_1
     361: anewarray     #74                 // class net/bytebuddy/description/modifier/ModifierContributor$ForMethod
     364: dup
     365: iconst_0
     366: getstatic     #75                 // Field net/bytebuddy/description/modifier/Visibility.PUBLIC:Lnet/bytebuddy/description/modifier/Visibility;
     369: aastore
     370: invokeinterface #114,  4          // InterfaceMethod net/bytebuddy/dynamic/DynamicType$Builder$MethodDefinition$ReceiverTypeDefinition.defineMethod:(Ljava/lang/String;Ljava/lang/reflect/Type;[Lnet/bytebuddy/description/modifier/ModifierContributor$ForMethod;)Lnet/bytebuddy/dynamic/DynamicType$Builder$MethodDefinition$ParameterDefinition$Initial;
     375: aload_0
     376: getfield      #16                 // Field implementationClearDirtyAttributesWithoutCollections:Lnet/bytebuddy/implementation/Implementation;
     379: invokeinterface #78,  2           // InterfaceMethod net/bytebuddy/dynamic/DynamicType$Builder$MethodDefinition$ParameterDefinition$Initial.intercept:(Lnet/bytebuddy/implementation/Implementation;)Lnet/bytebuddy/dynamic/DynamicType$Builder$MethodDefinition$ReceiverTypeDefinition;
     384: ldc           #118                // String $$_hibernate_suspendDirtyTracking
     386: getstatic     #107                // Field java/lang/Void.TYPE:Ljava/lang/Class;
     389: iconst_1
     390: anewarray     #74                 // class net/bytebuddy/description/modifier/ModifierContributor$ForMethod
     393: dup
     394: iconst_0
     395: getstatic     #75                 // Field net/bytebuddy/description/modifier/Visibility.PUBLIC:Lnet/bytebuddy/description/modifier/Visibility;
     398: aastore
     399: invokeinterface #114,  4          // InterfaceMethod net/bytebuddy/dynamic/DynamicType$Builder$MethodDefinition$ReceiverTypeDefinition.defineMethod:(Ljava/lang/String;Ljava/lang/reflect/Type;[Lnet/bytebuddy/description/modifier/ModifierContributor$ForMethod;)Lnet/bytebuddy/dynamic/DynamicType$Builder$MethodDefinition$ParameterDefinition$Initial;
     404: iconst_1
     405: anewarray     #68                 // class java/lang/reflect/Type
     408: dup
     409: iconst_0
     410: getstatic     #116                // Field java/lang/Boolean.TYPE:Ljava/lang/Class;
     413: aastore
     414: invokeinterface #110,  2          // InterfaceMethod net/bytebuddy/dynamic/DynamicType$Builder$MethodDefinition$ParameterDefinition$Initial.withParameters:([Ljava/lang/reflect/Type;)Lnet/bytebuddy/dynamic/DynamicType$Builder$MethodDefinition$ExceptionDefinition;
     419: aload_0
     420: getfield      #18                 // Field implementationSuspendDirtyTracking:Lnet/bytebuddy/implementation/Implementation;
     423: invokeinterface #111,  2          // InterfaceMethod net/bytebuddy/dynamic/DynamicType$Builder$MethodDefinition$ExceptionDefinition.intercept:(Lnet/bytebuddy/implementation/Implementation;)Lnet/bytebuddy/dynamic/DynamicType$Builder$MethodDefinition$ReceiverTypeDefinition;
     428: ldc           #119                // String $$_hibernate_getCollectionTracker
     430: ldc           #120                // class org/hibernate/bytecode/enhance/spi/CollectionTracker
     432: iconst_1
     433: anewarray     #74                 // class net/bytebuddy/description/modifier/ModifierContributor$ForMethod
     436: dup
     437: iconst_0
     438: getstatic     #75                 // Field net/bytebuddy/description/modifier/Visibility.PUBLIC:Lnet/bytebuddy/description/modifier/Visibility;
     441: aastore
     442: invokeinterface #114,  4          // InterfaceMethod net/bytebuddy/dynamic/DynamicType$Builder$MethodDefinition$ReceiverTypeDefinition.defineMethod:(Ljava/lang/String;Ljava/lang/reflect/Type;[Lnet/bytebuddy/description/modifier/ModifierContributor$ForMethod;)Lnet/bytebuddy/dynamic/DynamicType$Builder$MethodDefinition$ParameterDefinition$Initial;
     447: aload_0
     448: getfield      #24                 // Field implementationGetCollectionTrackerWithoutCollections:Lnet/bytebuddy/implementation/Implementation;
     451: invokeinterface #78,  2           // InterfaceMethod net/bytebuddy/dynamic/DynamicType$Builder$MethodDefinition$ParameterDefinition$Initial.intercept:(Lnet/bytebuddy/implementation/Implementation;)Lnet/bytebuddy/dynamic/DynamicType$Builder$MethodDefinition$ReceiverTypeDefinition;
     456: astore_1
     457: goto          1249
     460: aload_1
     461: iconst_1
     462: anewarray     #68                 // class java/lang/reflect/Type
     465: dup
     466: iconst_0
     467: ldc           #121                // class org/hibernate/engine/spi/ExtendedSelfDirtinessTracker
     469: aastore
     470: invokeinterface #70,  2           // InterfaceMethod net/bytebuddy/dynamic/DynamicType$Builder.implement:([Ljava/lang/reflect/Type;)Lnet/bytebuddy/dynamic/DynamicType$Builder$MethodDefinition$ImplementationDefinition$Optional;
     475: ldc           #95                 // String $$_hibernate_tracker
     477: ldc           #96                 // class org/hibernate/bytecode/enhance/internal/tracker/DirtyTracker
     479: iconst_2
     480: anewarray     #97                 // class net/bytebuddy/description/modifier/ModifierContributor$ForField
     483: dup
     484: iconst_0
     485: getstatic     #98                 // Field net/bytebuddy/description/modifier/FieldPersistence.TRANSIENT:Lnet/bytebuddy/description/modifier/FieldPersistence;
     488: aastore
     489: dup
     490: iconst_1
     491: getstatic     #99                 // Field net/bytebuddy/description/modifier/Visibility.PRIVATE:Lnet/bytebuddy/description/modifier/Visibility;
     494: aastore
     495: invokeinterface #100,  4          // InterfaceMethod net/bytebuddy/dynamic/DynamicType$Builder$MethodDefinition$ImplementationDefinition$Optional.defineField:(Ljava/lang/String;Ljava/lang/reflect/Type;[Lnet/bytebuddy/description/modifier/ModifierContributor$ForField;)Lnet/bytebuddy/dynamic/DynamicType$Builder$FieldDefinition$Optional$Valuable;
     500: iconst_1
     501: anewarray     #101                // class net/bytebuddy/description/annotation/AnnotationDescription
     504: dup
     505: iconst_0
     506: ldc           #102                // class javax/persistence/Transient
     508: invokestatic  #103                // Method net/bytebuddy/description/annotation/AnnotationDescription$Builder.ofType:(Ljava/lang/Class;)Lnet/bytebuddy/description/annotation/AnnotationDescription$Builder;
     511: invokevirtual #104                // Method net/bytebuddy/description/annotation/AnnotationDescription$Builder.build:()Lnet/bytebuddy/description/annotation/AnnotationDescription;
     514: aastore
     515: invokeinterface #105,  2          // InterfaceMethod net/bytebuddy/dynamic/DynamicType$Builder$FieldDefinition$Optional$Valuable.annotateField:([Lnet/bytebuddy/description/annotation/AnnotationDescription;)Lnet/bytebuddy/dynamic/DynamicType$Builder$FieldDefinition$Optional;
     520: ldc           #122                // String $$_hibernate_collectionTracker
     522: ldc           #120                // class org/hibernate/bytecode/enhance/spi/CollectionTracker
     524: iconst_2
     525: anewarray     #97                 // class net/bytebuddy/description/modifier/ModifierContributor$ForField
     528: dup
     529: iconst_0
     530: getstatic     #98                 // Field net/bytebuddy/description/modifier/FieldPersistence.TRANSIENT:Lnet/bytebuddy/description/modifier/FieldPersistence;
     533: aastore
     534: dup
     535: iconst_1
     536: getstatic     #99                 // Field net/bytebuddy/description/modifier/Visibility.PRIVATE:Lnet/bytebuddy/description/modifier/Visibility;
     539: aastore
     540: invokeinterface #123,  4          // InterfaceMethod net/bytebuddy/dynamic/DynamicType$Builder$FieldDefinition$Optional.defineField:(Ljava/lang/String;Ljava/lang/reflect/Type;[Lnet/bytebuddy/description/modifier/ModifierContributor$ForField;)Lnet/bytebuddy/dynamic/DynamicType$Builder$FieldDefinition$Optional$Valuable;
     545: iconst_1
     546: anewarray     #101                // class net/bytebuddy/description/annotation/AnnotationDescription
     549: dup
     550: iconst_0
     551: ldc           #102                // class javax/persistence/Transient
     553: invokestatic  #103                // Method net/bytebuddy/description/annotation/AnnotationDescription$Builder.ofType:(Ljava/lang/Class;)Lnet/bytebuddy/description/annotation/AnnotationDescription$Builder;
     556: invokevirtual #104                // Method net/bytebuddy/description/annotation/AnnotationDescription$Builder.build:()Lnet/bytebuddy/description/annotation/AnnotationDescription;
     559: aastore
     560: invokeinterface #105,  2          // InterfaceMethod net/bytebuddy/dynamic/DynamicType$Builder$FieldDefinition$Optional$Valuable.annotateField:([Lnet/bytebuddy/description/annotation/AnnotationDescription;)Lnet/bytebuddy/dynamic/DynamicType$Builder$FieldDefinition$Optional;
     565: ldc           #106                // String $$_hibernate_trackChange
     567: getstatic     #107                // Field java/lang/Void.TYPE:Ljava/lang/Class;
     570: iconst_1
     571: anewarray     #74                 // class net/bytebuddy/description/modifier/ModifierContributor$ForMethod
     574: dup
     575: iconst_0
     576: getstatic     #75                 // Field net/bytebuddy/description/modifier/Visibility.PUBLIC:Lnet/bytebuddy/description/modifier/Visibility;
     579: aastore
     580: invokeinterface #108,  4          // InterfaceMethod net/bytebuddy/dynamic/DynamicType$Builder$FieldDefinition$Optional.defineMethod:(Ljava/lang/String;Ljava/lang/reflect/Type;[Lnet/bytebuddy/description/modifier/ModifierContributor$ForMethod;)Lnet/bytebuddy/dynamic/DynamicType$Builder$MethodDefinition$ParameterDefinition$Initial;
     585: iconst_1
     586: anewarray     #68                 // class java/lang/reflect/Type
     589: dup
     590: iconst_0
     591: ldc           #109                // class java/lang/String
     593: aastore
     594: invokeinterface #110,  2          // InterfaceMethod net/bytebuddy/dynamic/DynamicType$Builder$MethodDefinition$ParameterDefinition$Initial.withParameters:([Ljava/lang/reflect/Type;)Lnet/bytebuddy/dynamic/DynamicType$Builder$MethodDefinition$ExceptionDefinition;
     599: aload_0
     600: getfield      #10                 // Field implementationTrackChange:Lnet/bytebuddy/implementation/Implementation;
     603: invokeinterface #111,  2          // InterfaceMethod net/bytebuddy/dynamic/DynamicType$Builder$MethodDefinition$ExceptionDefinition.intercept:(Lnet/bytebuddy/implementation/Implementation;)Lnet/bytebuddy/dynamic/DynamicType$Builder$MethodDefinition$ReceiverTypeDefinition;
     608: ldc           #112                // String $$_hibernate_getDirtyAttributes
     610: ldc           #113                // class "[Ljava/lang/String;"
     612: iconst_1
     613: anewarray     #74                 // class net/bytebuddy/description/modifier/ModifierContributor$ForMethod
     616: dup
     617: iconst_0
     618: getstatic     #75                 // Field net/bytebuddy/description/modifier/Visibility.PUBLIC:Lnet/bytebuddy/description/modifier/Visibility;
     621: aastore
     622: invokeinterface #114,  4          // InterfaceMethod net/bytebuddy/dynamic/DynamicType$Builder$MethodDefinition$ReceiverTypeDefinition.defineMethod:(Ljava/lang/String;Ljava/lang/reflect/Type;[Lnet/bytebuddy/description/modifier/ModifierContributor$ForMethod;)Lnet/bytebuddy/dynamic/DynamicType$Builder$MethodDefinition$ParameterDefinition$Initial;
     627: aload_0
     628: getfield      #20                 // Field implementationGetDirtyAttributes:Lnet/bytebuddy/implementation/Implementation;
     631: invokeinterface #78,  2           // InterfaceMethod net/bytebuddy/dynamic/DynamicType$Builder$MethodDefinition$ParameterDefinition$Initial.intercept:(Lnet/bytebuddy/implementation/Implementation;)Lnet/bytebuddy/dynamic/DynamicType$Builder$MethodDefinition$ReceiverTypeDefinition;
     636: ldc           #115                // String $$_hibernate_hasDirtyAttributes
     638: getstatic     #116                // Field java/lang/Boolean.TYPE:Ljava/lang/Class;
     641: iconst_1
     642: anewarray     #74                 // class net/bytebuddy/description/modifier/ModifierContributor$ForMethod
     645: dup
     646: iconst_0
     647: getstatic     #75                 // Field net/bytebuddy/description/modifier/Visibility.PUBLIC:Lnet/bytebuddy/description/modifier/Visibility;
     650: aastore
     651: invokeinterface #114,  4          // InterfaceMethod net/bytebuddy/dynamic/DynamicType$Builder$MethodDefinition$ReceiverTypeDefinition.defineMethod:(Ljava/lang/String;Ljava/lang/reflect/Type;[Lnet/bytebuddy/description/modifier/ModifierContributor$ForMethod;)Lnet/bytebuddy/dynamic/DynamicType$Builder$MethodDefinition$ParameterDefinition$Initial;
     656: aload_0
     657: getfield      #22                 // Field implementationAreFieldsDirty:Lnet/bytebuddy/implementation/Implementation;
     660: invokeinterface #78,  2           // InterfaceMethod net/bytebuddy/dynamic/DynamicType$Builder$MethodDefinition$ParameterDefinition$Initial.intercept:(Lnet/bytebuddy/implementation/Implementation;)Lnet/bytebuddy/dynamic/DynamicType$Builder$MethodDefinition$ReceiverTypeDefinition;
     665: ldc           #117                // String $$_hibernate_clearDirtyAttributes
     667: getstatic     #107                // Field java/lang/Void.TYPE:Ljava/lang/Class;
     670: iconst_1
     671: anewarray     #74                 // class net/bytebuddy/description/modifier/ModifierContributor$ForMethod
     674: dup
     675: iconst_0
     676: getstatic     #75                 // Field net/bytebuddy/description/modifier/Visibility.PUBLIC:Lnet/bytebuddy/description/modifier/Visibility;
     679: aastore
     680: invokeinterface #114,  4          // InterfaceMethod net/bytebuddy/dynamic/DynamicType$Builder$MethodDefinition$ReceiverTypeDefinition.defineMethod:(Ljava/lang/String;Ljava/lang/reflect/Type;[Lnet/bytebuddy/description/modifier/ModifierContributor$ForMethod;)Lnet/bytebuddy/dynamic/DynamicType$Builder$MethodDefinition$ParameterDefinition$Initial;
     685: aload_0
     686: getfield      #26                 // Field implementationClearDirtyAttributes:Lnet/bytebuddy/implementation/Implementation;
     689: invokeinterface #78,  2           // InterfaceMethod net/bytebuddy/dynamic/DynamicType$Builder$MethodDefinition$ParameterDefinition$Initial.intercept:(Lnet/bytebuddy/implementation/Implementation;)Lnet/bytebuddy/dynamic/DynamicType$Builder$MethodDefinition$ReceiverTypeDefinition;
     694: ldc           #118                // String $$_hibernate_suspendDirtyTracking
     696: getstatic     #107                // Field java/lang/Void.TYPE:Ljava/lang/Class;
     699: iconst_1
     700: anewarray     #74                 // class net/bytebuddy/description/modifier/ModifierContributor$ForMethod
     703: dup
     704: iconst_0
     705: getstatic     #75                 // Field net/bytebuddy/description/modifier/Visibility.PUBLIC:Lnet/bytebuddy/description/modifier/Visibility;
     708: aastore
     709: invokeinterface #114,  4          // InterfaceMethod net/bytebuddy/dynamic/DynamicType$Builder$MethodDefinition$ReceiverTypeDefinition.defineMethod:(Ljava/lang/String;Ljava/lang/reflect/Type;[Lnet/bytebuddy/description/modifier/ModifierContributor$ForMethod;)Lnet/bytebuddy/dynamic/DynamicType$Builder$MethodDefinition$ParameterDefinition$Initial;
     714: iconst_1
     715: anewarray     #68                 // class java/lang/reflect/Type
     718: dup
     719: iconst_0
     720: getstatic     #116                // Field java/lang/Boolean.TYPE:Ljava/lang/Class;
     723: aastore
     724: invokeinterface #110,  2          // InterfaceMethod net/bytebuddy/dynamic/DynamicType$Builder$MethodDefinition$ParameterDefinition$Initial.withParameters:([Ljava/lang/reflect/Type;)Lnet/bytebuddy/dynamic/DynamicType$Builder$MethodDefinition$ExceptionDefinition;
     729: aload_0
     730: getfield      #18                 // Field implementationSuspendDirtyTracking:Lnet/bytebuddy/implementation/Implementation;
     733: invokeinterface #111,  2          // InterfaceMethod net/bytebuddy/dynamic/DynamicType$Builder$MethodDefinition$ExceptionDefinition.intercept:(Lnet/bytebuddy/implementation/Implementation;)Lnet/bytebuddy/dynamic/DynamicType$Builder$MethodDefinition$ReceiverTypeDefinition;
     738: ldc           #119                // String $$_hibernate_getCollectionTracker
     740: ldc           #120                // class org/hibernate/bytecode/enhance/spi/CollectionTracker
     742: iconst_1
     743: anewarray     #74                 // class net/bytebuddy/description/modifier/ModifierContributor$ForMethod
     746: dup
     747: iconst_0
     748: getstatic     #75                 // Field net/bytebuddy/description/modifier/Visibility.PUBLIC:Lnet/bytebuddy/description/modifier/Visibility;
     751: aastore
     752: invokeinterface #114,  4          // InterfaceMethod net/bytebuddy/dynamic/DynamicType$Builder$MethodDefinition$ReceiverTypeDefinition.defineMethod:(Ljava/lang/String;Ljava/lang/reflect/Type;[Lnet/bytebuddy/description/modifier/ModifierContributor$ForMethod;)Lnet/bytebuddy/dynamic/DynamicType$Builder$MethodDefinition$ParameterDefinition$Initial;
     757: ldc           #122                // String $$_hibernate_collectionTracker
     759: invokestatic  #124                // Method net/bytebuddy/implementation/FieldAccessor.ofField:(Ljava/lang/String;)Lnet/bytebuddy/implementation/FieldAccessor$OwnerTypeLocatable;
     762: invokeinterface #78,  2           // InterfaceMethod net/bytebuddy/dynamic/DynamicType$Builder$MethodDefinition$ParameterDefinition$Initial.intercept:(Lnet/bytebuddy/implementation/Implementation;)Lnet/bytebuddy/dynamic/DynamicType$Builder$MethodDefinition$ReceiverTypeDefinition;
     767: astore_1
     768: getstatic     #8                  // Field net/bytebuddy/implementation/StubMethod.INSTANCE:Lnet/bytebuddy/implementation/StubMethod;
     771: astore        4
     773: getstatic     #8                  // Field net/bytebuddy/implementation/StubMethod.INSTANCE:Lnet/bytebuddy/implementation/StubMethod;
     776: astore        5
     778: getstatic     #8                  // Field net/bytebuddy/implementation/StubMethod.INSTANCE:Lnet/bytebuddy/implementation/StubMethod;
     781: astore        6
     783: aload_3
     784: invokeinterface #125,  1          // InterfaceMethod java/util/List.iterator:()Ljava/util/Iterator;
     789: astore        7
     791: aload         7
     793: invokeinterface #126,  1          // InterfaceMethod java/util/Iterator.hasNext:()Z
     798: ifeq          1073
     801: aload         7
     803: invokeinterface #127,  1          // InterfaceMethod java/util/Iterator.next:()Ljava/lang/Object;
     808: checkcast     #128                // class org/hibernate/bytecode/enhance/internal/bytebuddy/EnhancerImpl$AnnotatedFieldDescription
     811: astore        8
     813: aload         8
     815: invokevirtual #129                // Method org/hibernate/bytecode/enhance/internal/bytebuddy/EnhancerImpl$AnnotatedFieldDescription.getType:()Lnet/bytebuddy/description/type/TypeDescription$Generic;
     818: invokeinterface #130,  1          // InterfaceMethod net/bytebuddy/description/type/TypeDescription$Generic.asErasure:()Lnet/bytebuddy/description/type/TypeDescription;
     823: ldc           #131                // class java/util/Map
     825: invokeinterface #132,  2          // InterfaceMethod net/bytebuddy/description/type/TypeDescription.isAssignableTo:(Ljava/lang/Class;)Z
     830: ifeq          953
     833: invokestatic  #133                // Method net/bytebuddy/asm/Advice.withCustomMapping:()Lnet/bytebuddy/asm/Advice$WithCustomMapping;
     836: ldc           #134                // class org/hibernate/bytecode/enhance/internal/bytebuddy/CodeTemplates$FieldName
     838: aload         8
     840: invokevirtual #135                // Method org/hibernate/bytecode/enhance/internal/bytebuddy/EnhancerImpl$AnnotatedFieldDescription.getName:()Ljava/lang/String;
     843: invokevirtual #136                // Method net/bytebuddy/asm/Advice$WithCustomMapping.bind:(Ljava/lang/Class;Ljava/lang/Object;)Lnet/bytebuddy/asm/Advice$WithCustomMapping;
     846: ldc           #137                // class org/hibernate/bytecode/enhance/internal/bytebuddy/CodeTemplates$FieldValue
     848: aload         8
     850: invokevirtual #138                // Method org/hibernate/bytecode/enhance/internal/bytebuddy/EnhancerImpl$AnnotatedFieldDescription.getFieldDescription:()Lnet/bytebuddy/description/field/FieldDescription;
     853: invokevirtual #139                // Method net/bytebuddy/asm/Advice$WithCustomMapping.bind:(Ljava/lang/Class;Lnet/bytebuddy/description/field/FieldDescription;)Lnet/bytebuddy/asm/Advice$WithCustomMapping;
     856: ldc           #140                // class org/hibernate/bytecode/enhance/internal/bytebuddy/CodeTemplates$MapAreCollectionFieldsDirty
     858: aload_0
     859: getfield      #5                  // Field adviceLocator:Lnet/bytebuddy/dynamic/ClassFileLocator;
     862: invokevirtual #141                // Method net/bytebuddy/asm/Advice$WithCustomMapping.to:(Ljava/lang/Class;Lnet/bytebuddy/dynamic/ClassFileLocator;)Lnet/bytebuddy/asm/Advice;
     865: aload         4
     867: invokevirtual #9                  // Method net/bytebuddy/asm/Advice.wrap:(Lnet/bytebuddy/implementation/Implementation;)Lnet/bytebuddy/implementation/Implementation;
     870: astore        4
     872: invokestatic  #133                // Method net/bytebuddy/asm/Advice.withCustomMapping:()Lnet/bytebuddy/asm/Advice$WithCustomMapping;
     875: ldc           #134                // class org/hibernate/bytecode/enhance/internal/bytebuddy/CodeTemplates$FieldName
     877: aload         8
     879: invokevirtual #135                // Method org/hibernate/bytecode/enhance/internal/bytebuddy/EnhancerImpl$AnnotatedFieldDescription.getName:()Ljava/lang/String;
     882: invokevirtual #136                // Method net/bytebuddy/asm/Advice$WithCustomMapping.bind:(Ljava/lang/Class;Ljava/lang/Object;)Lnet/bytebuddy/asm/Advice$WithCustomMapping;
     885: ldc           #137                // class org/hibernate/bytecode/enhance/internal/bytebuddy/CodeTemplates$FieldValue
     887: aload         8
     889: invokevirtual #138                // Method org/hibernate/bytecode/enhance/internal/bytebuddy/EnhancerImpl$AnnotatedFieldDescription.getFieldDescription:()Lnet/bytebuddy/description/field/FieldDescription;
     892: invokevirtual #139                // Method net/bytebuddy/asm/Advice$WithCustomMapping.bind:(Ljava/lang/Class;Lnet/bytebuddy/description/field/FieldDescription;)Lnet/bytebuddy/asm/Advice$WithCustomMapping;
     895: ldc           #142                // class org/hibernate/bytecode/enhance/internal/bytebuddy/CodeTemplates$MapGetCollectionFieldDirtyNames
     897: aload_0
     898: getfield      #5                  // Field adviceLocator:Lnet/bytebuddy/dynamic/ClassFileLocator;
     901: invokevirtual #141                // Method net/bytebuddy/asm/Advice$WithCustomMapping.to:(Ljava/lang/Class;Lnet/bytebuddy/dynamic/ClassFileLocator;)Lnet/bytebuddy/asm/Advice;
     904: aload         5
     906: invokevirtual #9                  // Method net/bytebuddy/asm/Advice.wrap:(Lnet/bytebuddy/implementation/Implementation;)Lnet/bytebuddy/implementation/Implementation;
     909: astore        5
     911: invokestatic  #133                // Method net/bytebuddy/asm/Advice.withCustomMapping:()Lnet/bytebuddy/asm/Advice$WithCustomMapping;
     914: ldc           #134                // class org/hibernate/bytecode/enhance/internal/bytebuddy/CodeTemplates$FieldName
     916: aload         8
     918: invokevirtual #135                // Method org/hibernate/bytecode/enhance/internal/bytebuddy/EnhancerImpl$AnnotatedFieldDescription.getName:()Ljava/lang/String;
     921: invokevirtual #136                // Method net/bytebuddy/asm/Advice$WithCustomMapping.bind:(Ljava/lang/Class;Ljava/lang/Object;)Lnet/bytebuddy/asm/Advice$WithCustomMapping;
     924: ldc           #137                // class org/hibernate/bytecode/enhance/internal/bytebuddy/CodeTemplates$FieldValue
     926: aload         8
     928: invokevirtual #138                // Method org/hibernate/bytecode/enhance/internal/bytebuddy/EnhancerImpl$AnnotatedFieldDescription.getFieldDescription:()Lnet/bytebuddy/description/field/FieldDescription;
     931: invokevirtual #139                // Method net/bytebuddy/asm/Advice$WithCustomMapping.bind:(Ljava/lang/Class;Lnet/bytebuddy/description/field/FieldDescription;)Lnet/bytebuddy/asm/Advice$WithCustomMapping;
     934: ldc           #143                // class org/hibernate/bytecode/enhance/internal/bytebuddy/CodeTemplates$MapGetCollectionClearDirtyNames
     936: aload_0
     937: getfield      #5                  // Field adviceLocator:Lnet/bytebuddy/dynamic/ClassFileLocator;
     940: invokevirtual #141                // Method net/bytebuddy/asm/Advice$WithCustomMapping.to:(Ljava/lang/Class;Lnet/bytebuddy/dynamic/ClassFileLocator;)Lnet/bytebuddy/asm/Advice;
     943: aload         6
     945: invokevirtual #9                  // Method net/bytebuddy/asm/Advice.wrap:(Lnet/bytebuddy/implementation/Implementation;)Lnet/bytebuddy/implementation/Implementation;
     948: astore        6
     950: goto          1070
     953: invokestatic  #133                // Method net/bytebuddy/asm/Advice.withCustomMapping:()Lnet/bytebuddy/asm/Advice$WithCustomMapping;
     956: ldc           #134                // class org/hibernate/bytecode/enhance/internal/bytebuddy/CodeTemplates$FieldName
     958: aload         8
     960: invokevirtual #135                // Method org/hibernate/bytecode/enhance/internal/bytebuddy/EnhancerImpl$AnnotatedFieldDescription.getName:()Ljava/lang/String;
     963: invokevirtual #136                // Method net/bytebuddy/asm/Advice$WithCustomMapping.bind:(Ljava/lang/Class;Ljava/lang/Object;)Lnet/bytebuddy/asm/Advice$WithCustomMapping;
     966: ldc           #137                // class org/hibernate/bytecode/enhance/internal/bytebuddy/CodeTemplates$FieldValue
     968: aload         8
     970: invokevirtual #138                // Method org/hibernate/bytecode/enhance/internal/bytebuddy/EnhancerImpl$AnnotatedFieldDescription.getFieldDescription:()Lnet/bytebuddy/description/field/FieldDescription;
     973: invokevirtual #139                // Method net/bytebuddy/asm/Advice$WithCustomMapping.bind:(Ljava/lang/Class;Lnet/bytebuddy/description/field/FieldDescription;)Lnet/bytebuddy/asm/Advice$WithCustomMapping;
     976: ldc           #144                // class org/hibernate/bytecode/enhance/internal/bytebuddy/CodeTemplates$CollectionAreCollectionFieldsDirty
     978: aload_0
     979: getfield      #5                  // Field adviceLocator:Lnet/bytebuddy/dynamic/ClassFileLocator;
     982: invokevirtual #141                // Method net/bytebuddy/asm/Advice$WithCustomMapping.to:(Ljava/lang/Class;Lnet/bytebuddy/dynamic/ClassFileLocator;)Lnet/bytebuddy/asm/Advice;
     985: aload         4
     987: invokevirtual #9                  // Method net/bytebuddy/asm/Advice.wrap:(Lnet/bytebuddy/implementation/Implementation;)Lnet/bytebuddy/implementation/Implementation;
     990: astore        4
     992: invokestatic  #133                // Method net/bytebuddy/asm/Advice.withCustomMapping:()Lnet/bytebuddy/asm/Advice$WithCustomMapping;
     995: ldc           #134                // class org/hibernate/bytecode/enhance/internal/bytebuddy/CodeTemplates$FieldName
     997: aload         8
     999: invokevirtual #135                // Method org/hibernate/bytecode/enhance/internal/bytebuddy/EnhancerImpl$AnnotatedFieldDescription.getName:()Ljava/lang/String;
    1002: invokevirtual #136                // Method net/bytebuddy/asm/Advice$WithCustomMapping.bind:(Ljava/lang/Class;Ljava/lang/Object;)Lnet/bytebuddy/asm/Advice$WithCustomMapping;
    1005: ldc           #137                // class org/hibernate/bytecode/enhance/internal/bytebuddy/CodeTemplates$FieldValue
    1007: aload         8
    1009: invokevirtual #138                // Method org/hibernate/bytecode/enhance/internal/bytebuddy/EnhancerImpl$AnnotatedFieldDescription.getFieldDescription:()Lnet/bytebuddy/description/field/FieldDescription;
    1012: invokevirtual #139                // Method net/bytebuddy/asm/Advice$WithCustomMapping.bind:(Ljava/lang/Class;Lnet/bytebuddy/description/field/FieldDescription;)Lnet/bytebuddy/asm/Advice$WithCustomMapping;
    1015: ldc           #145                // class org/hibernate/bytecode/enhance/internal/bytebuddy/CodeTemplates$CollectionGetCollectionFieldDirtyNames
    1017: aload_0
    1018: getfield      #5                  // Field adviceLocator:Lnet/bytebuddy/dynamic/ClassFileLocator;
    1021: invokevirtual #141                // Method net/bytebuddy/asm/Advice$WithCustomMapping.to:(Ljava/lang/Class;Lnet/bytebuddy/dynamic/ClassFileLocator;)Lnet/bytebuddy/asm/Advice;
    1024: aload         5
    1026: invokevirtual #9                  // Method net/bytebuddy/asm/Advice.wrap:(Lnet/bytebuddy/implementation/Implementation;)Lnet/bytebuddy/implementation/Implementation;
    1029: astore        5
    1031: invokestatic  #133                // Method net/bytebuddy/asm/Advice.withCustomMapping:()Lnet/bytebuddy/asm/Advice$WithCustomMapping;
    1034: ldc           #134                // class org/hibernate/bytecode/enhance/internal/bytebuddy/CodeTemplates$FieldName
    1036: aload         8
    1038: invokevirtual #135                // Method org/hibernate/bytecode/enhance/internal/bytebuddy/EnhancerImpl$AnnotatedFieldDescription.getName:()Ljava/lang/String;
    1041: invokevirtual #136                // Method net/bytebuddy/asm/Advice$WithCustomMapping.bind:(Ljava/lang/Class;Ljava/lang/Object;)Lnet/bytebuddy/asm/Advice$WithCustomMapping;
    1044: ldc           #137                // class org/hibernate/bytecode/enhance/internal/bytebuddy/CodeTemplates$FieldValue
    1046: aload         8
    1048: invokevirtual #138                // Method org/hibernate/bytecode/enhance/internal/bytebuddy/EnhancerImpl$AnnotatedFieldDescription.getFieldDescription:()Lnet/bytebuddy/description/field/FieldDescription;
    1051: invokevirtual #139                // Method net/bytebuddy/asm/Advice$WithCustomMapping.bind:(Ljava/lang/Class;Lnet/bytebuddy/description/field/FieldDescription;)Lnet/bytebuddy/asm/Advice$WithCustomMapping;
    1054: ldc           #146                // class org/hibernate/bytecode/enhance/internal/bytebuddy/CodeTemplates$CollectionGetCollectionClearDirtyNames
    1056: aload_0
    1057: getfield      #5                  // Field adviceLocator:Lnet/bytebuddy/dynamic/ClassFileLocator;
    1060: invokevirtual #141                // Method net/bytebuddy/asm/Advice$WithCustomMapping.to:(Ljava/lang/Class;Lnet/bytebuddy/dynamic/ClassFileLocator;)Lnet/bytebuddy/asm/Advice;
    1063: aload         6
    1065: invokevirtual #9                  // Method net/bytebuddy/asm/Advice.wrap:(Lnet/bytebuddy/implementation/Implementation;)Lnet/bytebuddy/implementation/Implementation;
    1068: astore        6
    1070: goto          791
    1073: aload_0
    1074: getfield      #35                 // Field enhancementContext:Lorg/hibernate/bytecode/enhance/internal/bytebuddy/ByteBuddyEnhancementContext;
    1077: aload_2
    1078: invokevirtual #147                // Method org/hibernate/bytecode/enhance/internal/bytebuddy/ByteBuddyEnhancementContext.hasLazyLoadableAttributes:(Lnet/bytebuddy/description/type/TypeDescription;)Z
    1081: ifeq          1095
    1084: aload_0
    1085: getfield      #28                 // Field adviceInitializeLazyAttributeLoadingInterceptor:Lnet/bytebuddy/asm/Advice;
    1088: aload         6
    1090: invokevirtual #9                  // Method net/bytebuddy/asm/Advice.wrap:(Lnet/bytebuddy/implementation/Implementation;)Lnet/bytebuddy/implementation/Implementation;
    1093: astore        6
    1095: aload_1
    1096: ldc           #148                // String $$_hibernate_areCollectionFieldsDirty
    1098: getstatic     #116                // Field java/lang/Boolean.TYPE:Ljava/lang/Class;
    1101: iconst_1
    1102: anewarray     #74                 // class net/bytebuddy/description/modifier/ModifierContributor$ForMethod
    1105: dup
    1106: iconst_0
    1107: getstatic     #75                 // Field net/bytebuddy/description/modifier/Visibility.PUBLIC:Lnet/bytebuddy/description/modifier/Visibility;
    1110: aastore
    1111: invokeinterface #149,  4          // InterfaceMethod net/bytebuddy/dynamic/DynamicType$Builder.defineMethod:(Ljava/lang/String;Ljava/lang/reflect/Type;[Lnet/bytebuddy/description/modifier/ModifierContributor$ForMethod;)Lnet/bytebuddy/dynamic/DynamicType$Builder$MethodDefinition$ParameterDefinition$Initial;
    1116: aload         4
    1118: invokeinterface #78,  2           // InterfaceMethod net/bytebuddy/dynamic/DynamicType$Builder$MethodDefinition$ParameterDefinition$Initial.intercept:(Lnet/bytebuddy/implementation/Implementation;)Lnet/bytebuddy/dynamic/DynamicType$Builder$MethodDefinition$ReceiverTypeDefinition;
    1123: ldc           #150                // String $$_hibernate_getCollectionFieldDirtyNames
    1125: getstatic     #107                // Field java/lang/Void.TYPE:Ljava/lang/Class;
    1128: iconst_1
    1129: anewarray     #74                 // class net/bytebuddy/description/modifier/ModifierContributor$ForMethod
    1132: dup
    1133: iconst_0
    1134: getstatic     #75                 // Field net/bytebuddy/description/modifier/Visibility.PUBLIC:Lnet/bytebuddy/description/modifier/Visibility;
    1137: aastore
    1138: invokeinterface #114,  4          // InterfaceMethod net/bytebuddy/dynamic/DynamicType$Builder$MethodDefinition$ReceiverTypeDefinition.defineMethod:(Ljava/lang/String;Ljava/lang/reflect/Type;[Lnet/bytebuddy/description/modifier/ModifierContributor$ForMethod;)Lnet/bytebuddy/dynamic/DynamicType$Builder$MethodDefinition$ParameterDefinition$Initial;
    1143: iconst_1
    1144: anewarray     #68                 // class java/lang/reflect/Type
    1147: dup
    1148: iconst_0
    1149: ldc           #96                 // class org/hibernate/bytecode/enhance/internal/tracker/DirtyTracker
    1151: aastore
    1152: invokeinterface #110,  2          // InterfaceMethod net/bytebuddy/dynamic/DynamicType$Builder$MethodDefinition$ParameterDefinition$Initial.withParameters:([Ljava/lang/reflect/Type;)Lnet/bytebuddy/dynamic/DynamicType$Builder$MethodDefinition$ExceptionDefinition;
    1157: aload         5
    1159: invokeinterface #111,  2          // InterfaceMethod net/bytebuddy/dynamic/DynamicType$Builder$MethodDefinition$ExceptionDefinition.intercept:(Lnet/bytebuddy/implementation/Implementation;)Lnet/bytebuddy/dynamic/DynamicType$Builder$MethodDefinition$ReceiverTypeDefinition;
    1164: ldc           #151                // String $$_hibernate_clearDirtyCollectionNames
    1166: getstatic     #107                // Field java/lang/Void.TYPE:Ljava/lang/Class;
    1169: iconst_1
    1170: anewarray     #74                 // class net/bytebuddy/description/modifier/ModifierContributor$ForMethod
    1173: dup
    1174: iconst_0
    1175: getstatic     #75                 // Field net/bytebuddy/description/modifier/Visibility.PUBLIC:Lnet/bytebuddy/description/modifier/Visibility;
    1178: aastore
    1179: invokeinterface #114,  4          // InterfaceMethod net/bytebuddy/dynamic/DynamicType$Builder$MethodDefinition$ReceiverTypeDefinition.defineMethod:(Ljava/lang/String;Ljava/lang/reflect/Type;[Lnet/bytebuddy/description/modifier/ModifierContributor$ForMethod;)Lnet/bytebuddy/dynamic/DynamicType$Builder$MethodDefinition$ParameterDefinition$Initial;
    1184: invokestatic  #133                // Method net/bytebuddy/asm/Advice.withCustomMapping:()Lnet/bytebuddy/asm/Advice$WithCustomMapping;
    1187: ldc           #152                // class org/hibernate/bytecode/enhance/internal/bytebuddy/CodeTemplates$ClearDirtyCollectionNames
    1189: aload_0
    1190: getfield      #5                  // Field adviceLocator:Lnet/bytebuddy/dynamic/ClassFileLocator;
    1193: invokevirtual #141                // Method net/bytebuddy/asm/Advice$WithCustomMapping.to:(Ljava/lang/Class;Lnet/bytebuddy/dynamic/ClassFileLocator;)Lnet/bytebuddy/asm/Advice;
    1196: getstatic     #8                  // Field net/bytebuddy/implementation/StubMethod.INSTANCE:Lnet/bytebuddy/implementation/StubMethod;
    1199: invokevirtual #9                  // Method net/bytebuddy/asm/Advice.wrap:(Lnet/bytebuddy/implementation/Implementation;)Lnet/bytebuddy/implementation/Implementation;
    1202: invokeinterface #78,  2           // InterfaceMethod net/bytebuddy/dynamic/DynamicType$Builder$MethodDefinition$ParameterDefinition$Initial.intercept:(Lnet/bytebuddy/implementation/Implementation;)Lnet/bytebuddy/dynamic/DynamicType$Builder$MethodDefinition$ReceiverTypeDefinition;
    1207: ldc           #153                // String $$_hibernate_removeDirtyFields
    1209: getstatic     #107                // Field java/lang/Void.TYPE:Ljava/lang/Class;
    1212: iconst_1
    1213: anewarray     #74                 // class net/bytebuddy/description/modifier/ModifierContributor$ForMethod
    1216: dup
    1217: iconst_0
    1218: getstatic     #75                 // Field net/bytebuddy/description/modifier/Visibility.PUBLIC:Lnet/bytebuddy/description/modifier/Visibility;
    1221: aastore
    1222: invokeinterface #114,  4          // InterfaceMethod net/bytebuddy/dynamic/DynamicType$Builder$MethodDefinition$ReceiverTypeDefinition.defineMethod:(Ljava/lang/String;Ljava/lang/reflect/Type;[Lnet/bytebuddy/description/modifier/ModifierContributor$ForMethod;)Lnet/bytebuddy/dynamic/DynamicType$Builder$MethodDefinition$ParameterDefinition$Initial;
    1227: iconst_1
    1228: anewarray     #68                 // class java/lang/reflect/Type
    1231: dup
    1232: iconst_0
    1233: ldc           #154                // class org/hibernate/bytecode/enhance/spi/interceptor/LazyAttributeLoadingInterceptor
    1235: aastore
    1236: invokeinterface #110,  2          // InterfaceMethod net/bytebuddy/dynamic/DynamicType$Builder$MethodDefinition$ParameterDefinition$Initial.withParameters:([Ljava/lang/reflect/Type;)Lnet/bytebuddy/dynamic/DynamicType$Builder$MethodDefinition$ExceptionDefinition;
    1241: aload         6
    1243: invokeinterface #111,  2          // InterfaceMethod net/bytebuddy/dynamic/DynamicType$Builder$MethodDefinition$ExceptionDefinition.intercept:(Lnet/bytebuddy/implementation/Implementation;)Lnet/bytebuddy/dynamic/DynamicType$Builder$MethodDefinition$ReceiverTypeDefinition;
    1248: astore_1
    1249: aload_0
    1250: aload_2
    1251: invokespecial #155                // Method createTransformer:(Lnet/bytebuddy/description/type/TypeDescription;)Lorg/hibernate/bytecode/enhance/internal/bytebuddy/PersistentAttributeTransformer;
    1254: aload_1
    1255: iconst_0
    1256: invokevirtual #156                // Method org/hibernate/bytecode/enhance/internal/bytebuddy/PersistentAttributeTransformer.applyTo:(Lnet/bytebuddy/dynamic/DynamicType$Builder;Z)Lnet/bytebuddy/dynamic/DynamicType$Builder;
    1259: areturn
    1260: aload_0
    1261: getfield      #35                 // Field enhancementContext:Lorg/hibernate/bytecode/enhance/internal/bytebuddy/ByteBuddyEnhancementContext;
    1264: aload_2
    1265: invokevirtual #157                // Method org/hibernate/bytecode/enhance/internal/bytebuddy/ByteBuddyEnhancementContext.isCompositeClass:(Lnet/bytebuddy/description/type/TypeDescription;)Z
    1268: ifeq          1484
    1271: getstatic     #59                 // Field log:Lorg/hibernate/internal/CoreMessageLogger;
    1274: ldc           #158                // String Enhancing [%s] as Composite
    1276: aload_2
    1277: invokeinterface #61,  1           // InterfaceMethod net/bytebuddy/description/type/TypeDescription.getName:()Ljava/lang/String;
    1282: invokeinterface #67,  3           // InterfaceMethod org/hibernate/internal/CoreMessageLogger.infof:(Ljava/lang/String;Ljava/lang/Object;)V
    1287: aload_1
    1288: iconst_1
    1289: anewarray     #68                 // class java/lang/reflect/Type
    1292: dup
    1293: iconst_0
    1294: ldc           #159                // class org/hibernate/engine/spi/ManagedComposite
    1296: aastore
    1297: invokeinterface #70,  2           // InterfaceMethod net/bytebuddy/dynamic/DynamicType$Builder.implement:([Ljava/lang/reflect/Type;)Lnet/bytebuddy/dynamic/DynamicType$Builder$MethodDefinition$ImplementationDefinition$Optional;
    1302: astore_1
    1303: aload_0
    1304: aload_1
    1305: aload_2
    1306: invokespecial #90                 // Method addInterceptorHandling:(Lnet/bytebuddy/dynamic/DynamicType$Builder;Lnet/bytebuddy/description/type/TypeDescription;)Lnet/bytebuddy/dynamic/DynamicType$Builder;
    1309: astore_1
    1310: aload_0
    1311: getfield      #35                 // Field enhancementContext:Lorg/hibernate/bytecode/enhance/internal/bytebuddy/ByteBuddyEnhancementContext;
    1314: aload_2
    1315: invokevirtual #91                 // Method org/hibernate/bytecode/enhance/internal/bytebuddy/ByteBuddyEnhancementContext.doDirtyCheckingInline:(Lnet/bytebuddy/description/type/TypeDescription;)Z
    1318: ifeq          1473
    1321: aload_1
    1322: iconst_1
    1323: anewarray     #68                 // class java/lang/reflect/Type
    1326: dup
    1327: iconst_0
    1328: ldc           #160                // class org/hibernate/engine/spi/CompositeTracker
    1330: aastore
    1331: invokeinterface #70,  2           // InterfaceMethod net/bytebuddy/dynamic/DynamicType$Builder.implement:([Ljava/lang/reflect/Type;)Lnet/bytebuddy/dynamic/DynamicType$Builder$MethodDefinition$ImplementationDefinition$Optional;
    1336: ldc           #161                // String $$_hibernate_compositeOwners
    1338: ldc           #162                // class org/hibernate/bytecode/enhance/internal/tracker/CompositeOwnerTracker
    1340: iconst_2
    1341: anewarray     #97                 // class net/bytebuddy/description/modifier/ModifierContributor$ForField
    1344: dup
    1345: iconst_0
    1346: getstatic     #98                 // Field net/bytebuddy/description/modifier/FieldPersistence.TRANSIENT:Lnet/bytebuddy/description/modifier/FieldPersistence;
    1349: aastore
    1350: dup
    1351: iconst_1
    1352: getstatic     #99                 // Field net/bytebuddy/description/modifier/Visibility.PRIVATE:Lnet/bytebuddy/description/modifier/Visibility;
    1355: aastore
    1356: invokeinterface #100,  4          // InterfaceMethod net/bytebuddy/dynamic/DynamicType$Builder$MethodDefinition$ImplementationDefinition$Optional.defineField:(Ljava/lang/String;Ljava/lang/reflect/Type;[Lnet/bytebuddy/description/modifier/ModifierContributor$ForField;)Lnet/bytebuddy/dynamic/DynamicType$Builder$FieldDefinition$Optional$Valuable;
    1361: iconst_1
    1362: anewarray     #101                // class net/bytebuddy/description/annotation/AnnotationDescription
    1365: dup
    1366: iconst_0
    1367: ldc           #102                // class javax/persistence/Transient
    1369: invokestatic  #103                // Method net/bytebuddy/description/annotation/AnnotationDescription$Builder.ofType:(Ljava/lang/Class;)Lnet/bytebuddy/description/annotation/AnnotationDescription$Builder;
    1372: invokevirtual #104                // Method net/bytebuddy/description/annotation/AnnotationDescription$Builder.build:()Lnet/bytebuddy/description/annotation/AnnotationDescription;
    1375: aastore
    1376: invokeinterface #105,  2          // InterfaceMethod net/bytebuddy/dynamic/DynamicType$Builder$FieldDefinition$Optional$Valuable.annotateField:([Lnet/bytebuddy/description/annotation/AnnotationDescription;)Lnet/bytebuddy/dynamic/DynamicType$Builder$FieldDefinition$Optional;
    1381: ldc           #163                // String $$_hibernate_setOwner
    1383: getstatic     #107                // Field java/lang/Void.TYPE:Ljava/lang/Class;
    1386: iconst_1
    1387: anewarray     #74                 // class net/bytebuddy/description/modifier/ModifierContributor$ForMethod
    1390: dup
    1391: iconst_0
    1392: getstatic     #75                 // Field net/bytebuddy/description/modifier/Visibility.PUBLIC:Lnet/bytebuddy/description/modifier/Visibility;
    1395: aastore
    1396: invokeinterface #108,  4          // InterfaceMethod net/bytebuddy/dynamic/DynamicType$Builder$FieldDefinition$Optional.defineMethod:(Ljava/lang/String;Ljava/lang/reflect/Type;[Lnet/bytebuddy/description/modifier/ModifierContributor$ForMethod;)Lnet/bytebuddy/dynamic/DynamicType$Builder$MethodDefinition$ParameterDefinition$Initial;
    1401: iconst_2
    1402: anewarray     #68                 // class java/lang/reflect/Type
    1405: dup
    1406: iconst_0
    1407: ldc           #109                // class java/lang/String
    1409: aastore
    1410: dup
    1411: iconst_1
    1412: ldc           #164                // class org/hibernate/engine/spi/CompositeOwner
    1414: aastore
    1415: invokeinterface #110,  2          // InterfaceMethod net/bytebuddy/dynamic/DynamicType$Builder$MethodDefinition$ParameterDefinition$Initial.withParameters:([Ljava/lang/reflect/Type;)Lnet/bytebuddy/dynamic/DynamicType$Builder$MethodDefinition$ExceptionDefinition;
    1420: aload_0
    1421: getfield      #30                 // Field implementationSetOwner:Lnet/bytebuddy/implementation/Implementation;
    1424: invokeinterface #111,  2          // InterfaceMethod net/bytebuddy/dynamic/DynamicType$Builder$MethodDefinition$ExceptionDefinition.intercept:(Lnet/bytebuddy/implementation/Implementation;)Lnet/bytebuddy/dynamic/DynamicType$Builder$MethodDefinition$ReceiverTypeDefinition;
    1429: ldc           #165                // String $$_hibernate_clearOwner
    1431: getstatic     #107                // Field java/lang/Void.TYPE:Ljava/lang/Class;
    1434: iconst_1
    1435: anewarray     #74                 // class net/bytebuddy/description/modifier/ModifierContributor$ForMethod
    1438: dup
    1439: iconst_0
    1440: getstatic     #75                 // Field net/bytebuddy/description/modifier/Visibility.PUBLIC:Lnet/bytebuddy/description/modifier/Visibility;
    1443: aastore
    1444: invokeinterface #114,  4          // InterfaceMethod net/bytebuddy/dynamic/DynamicType$Builder$MethodDefinition$ReceiverTypeDefinition.defineMethod:(Ljava/lang/String;Ljava/lang/reflect/Type;[Lnet/bytebuddy/description/modifier/ModifierContributor$ForMethod;)Lnet/bytebuddy/dynamic/DynamicType$Builder$MethodDefinition$ParameterDefinition$Initial;
    1449: iconst_1
    1450: anewarray     #68                 // class java/lang/reflect/Type
    1453: dup
    1454: iconst_0
    1455: ldc           #109                // class java/lang/String
    1457: aastore
    1458: invokeinterface #110,  2          // InterfaceMethod net/bytebuddy/dynamic/DynamicType$Builder$MethodDefinition$ParameterDefinition$Initial.withParameters:([Ljava/lang/reflect/Type;)Lnet/bytebuddy/dynamic/DynamicType$Builder$MethodDefinition$ExceptionDefinition;
    1463: aload_0
    1464: getfield      #32                 // Field implementationClearOwner:Lnet/bytebuddy/implementation/Implementation;
    1467: invokeinterface #111,  2          // InterfaceMethod net/bytebuddy/dynamic/DynamicType$Builder$MethodDefinition$ExceptionDefinition.intercept:(Lnet/bytebuddy/implementation/Implementation;)Lnet/bytebuddy/dynamic/DynamicType$Builder$MethodDefinition$ReceiverTypeDefinition;
    1472: astore_1
    1473: aload_0
    1474: aload_2
    1475: invokespecial #155                // Method createTransformer:(Lnet/bytebuddy/description/type/TypeDescription;)Lorg/hibernate/bytecode/enhance/internal/bytebuddy/PersistentAttributeTransformer;
    1478: aload_1
    1479: iconst_0
    1480: invokevirtual #156                // Method org/hibernate/bytecode/enhance/internal/bytebuddy/PersistentAttributeTransformer.applyTo:(Lnet/bytebuddy/dynamic/DynamicType$Builder;Z)Lnet/bytebuddy/dynamic/DynamicType$Builder;
    1483: areturn
    1484: aload_0
    1485: getfield      #35                 // Field enhancementContext:Lorg/hibernate/bytecode/enhance/internal/bytebuddy/ByteBuddyEnhancementContext;
    1488: aload_2
    1489: invokevirtual #166                // Method org/hibernate/bytecode/enhance/internal/bytebuddy/ByteBuddyEnhancementContext.isMappedSuperclassClass:(Lnet/bytebuddy/description/type/TypeDescription;)Z
    1492: ifeq          1538
    1495: getstatic     #59                 // Field log:Lorg/hibernate/internal/CoreMessageLogger;
    1498: ldc           #167                // String Enhancing [%s] as MappedSuperclass
    1500: aload_2
    1501: invokeinterface #61,  1           // InterfaceMethod net/bytebuddy/description/type/TypeDescription.getName:()Ljava/lang/String;
    1506: invokeinterface #67,  3           // InterfaceMethod org/hibernate/internal/CoreMessageLogger.infof:(Ljava/lang/String;Ljava/lang/Object;)V
    1511: aload_1
    1512: iconst_1
    1513: anewarray     #68                 // class java/lang/reflect/Type
    1516: dup
    1517: iconst_0
    1518: ldc           #168                // class org/hibernate/engine/spi/ManagedMappedSuperclass
    1520: aastore
    1521: invokeinterface #70,  2           // InterfaceMethod net/bytebuddy/dynamic/DynamicType$Builder.implement:([Ljava/lang/reflect/Type;)Lnet/bytebuddy/dynamic/DynamicType$Builder$MethodDefinition$ImplementationDefinition$Optional;
    1526: astore_1
    1527: aload_0
    1528: aload_2
    1529: invokespecial #155                // Method createTransformer:(Lnet/bytebuddy/description/type/TypeDescription;)Lorg/hibernate/bytecode/enhance/internal/bytebuddy/PersistentAttributeTransformer;
    1532: aload_1
    1533: iconst_1
    1534: invokevirtual #156                // Method org/hibernate/bytecode/enhance/internal/bytebuddy/PersistentAttributeTransformer.applyTo:(Lnet/bytebuddy/dynamic/DynamicType$Builder;Z)Lnet/bytebuddy/dynamic/DynamicType$Builder;
    1537: areturn
    1538: aload_0
    1539: getfield      #35                 // Field enhancementContext:Lorg/hibernate/bytecode/enhance/internal/bytebuddy/ByteBuddyEnhancementContext;
    1542: aload_2
    1543: invokevirtual #169                // Method org/hibernate/bytecode/enhance/internal/bytebuddy/ByteBuddyEnhancementContext.doExtendedEnhancement:(Lnet/bytebuddy/description/type/TypeDescription;)Z
    1546: ifeq          1575
    1549: getstatic     #59                 // Field log:Lorg/hibernate/internal/CoreMessageLogger;
    1552: ldc           #170                // String Extended enhancement of [%s]
    1554: aload_2
    1555: invokeinterface #61,  1           // InterfaceMethod net/bytebuddy/description/type/TypeDescription.getName:()Ljava/lang/String;
    1560: invokeinterface #67,  3           // InterfaceMethod org/hibernate/internal/CoreMessageLogger.infof:(Ljava/lang/String;Ljava/lang/Object;)V
    1565: aload_0
    1566: aload_2
    1567: invokespecial #155                // Method createTransformer:(Lnet/bytebuddy/description/type/TypeDescription;)Lorg/hibernate/bytecode/enhance/internal/bytebuddy/PersistentAttributeTransformer;
    1570: aload_1
    1571: invokevirtual #171                // Method org/hibernate/bytecode/enhance/internal/bytebuddy/PersistentAttributeTransformer.applyExtended:(Lnet/bytebuddy/dynamic/DynamicType$Builder;)Lnet/bytebuddy/dynamic/DynamicType$Builder;
    1574: areturn
    1575: getstatic     #59                 // Field log:Lorg/hibernate/internal/CoreMessageLogger;
    1578: ldc           #172                // String Skipping enhancement of [%s]: not entity or composite
    1580: aload_2
    1581: invokeinterface #61,  1           // InterfaceMethod net/bytebuddy/description/type/TypeDescription.getName:()Ljava/lang/String;
    1586: invokeinterface #62,  3           // InterfaceMethod org/hibernate/internal/CoreMessageLogger.debugf:(Ljava/lang/String;Ljava/lang/Object;)V
    1591: aconst_null
    1592: areturn

  private org.hibernate.bytecode.enhance.internal.bytebuddy.PersistentAttributeTransformer createTransformer(net.bytebuddy.description.type.TypeDescription);
    Code:
       0: aload_1
       1: aload_0
       2: getfield      #35                 // Field enhancementContext:Lorg/hibernate/bytecode/enhance/internal/bytebuddy/ByteBuddyEnhancementContext;
       5: aload_0
       6: getfield      #42                 // Field typePool:Lnet/bytebuddy/pool/TypePool;
       9: invokestatic  #173                // Method org/hibernate/bytecode/enhance/internal/bytebuddy/PersistentAttributeTransformer.collectPersistentFields:(Lnet/bytebuddy/description/type/TypeDescription;Lorg/hibernate/bytecode/enhance/internal/bytebuddy/ByteBuddyEnhancementContext;Lnet/bytebuddy/pool/TypePool;)Lorg/hibernate/bytecode/enhance/internal/bytebuddy/PersistentAttributeTransformer;
      12: areturn

  private boolean alreadyEnhanced(net.bytebuddy.description.type.TypeDescription);
    Code:
       0: aload_1
       1: invokeinterface #174,  1          // InterfaceMethod net/bytebuddy/description/type/TypeDescription.getInterfaces:()Lnet/bytebuddy/description/type/TypeList$Generic;
       6: invokeinterface #175,  1          // InterfaceMethod net/bytebuddy/description/type/TypeList$Generic.iterator:()Ljava/util/Iterator;
      11: astore_2
      12: aload_2
      13: invokeinterface #126,  1          // InterfaceMethod java/util/Iterator.hasNext:()Z
      18: ifeq          52
      21: aload_2
      22: invokeinterface #127,  1          // InterfaceMethod java/util/Iterator.next:()Ljava/lang/Object;
      27: checkcast     #176                // class net/bytebuddy/description/type/TypeDescription$Generic
      30: astore_3
      31: aload_3
      32: invokeinterface #130,  1          // InterfaceMethod net/bytebuddy/description/type/TypeDescription$Generic.asErasure:()Lnet/bytebuddy/description/type/TypeDescription;
      37: ldc           #177                // class org/hibernate/engine/spi/Managed
      39: invokeinterface #132,  2          // InterfaceMethod net/bytebuddy/description/type/TypeDescription.isAssignableTo:(Ljava/lang/Class;)Z
      44: ifeq          49
      47: iconst_1
      48: ireturn
      49: goto          12
      52: iconst_0
      53: ireturn

  private net.bytebuddy.dynamic.DynamicType$Builder<?> addInterceptorHandling(net.bytebuddy.dynamic.DynamicType$Builder<?>, net.bytebuddy.description.type.TypeDescription);
    Code:
       0: aload_0
       1: getfield      #35                 // Field enhancementContext:Lorg/hibernate/bytecode/enhance/internal/bytebuddy/ByteBuddyEnhancementContext;
       4: aload_2
       5: invokevirtual #147                // Method org/hibernate/bytecode/enhance/internal/bytebuddy/ByteBuddyEnhancementContext.hasLazyLoadableAttributes:(Lnet/bytebuddy/description/type/TypeDescription;)Z
       8: ifeq          56
      11: getstatic     #59                 // Field log:Lorg/hibernate/internal/CoreMessageLogger;
      14: ldc           #178                // String Weaving in PersistentAttributeInterceptable implementation on [%s]
      16: aload_2
      17: invokeinterface #61,  1           // InterfaceMethod net/bytebuddy/description/type/TypeDescription.getName:()Ljava/lang/String;
      22: invokeinterface #62,  3           // InterfaceMethod org/hibernate/internal/CoreMessageLogger.debugf:(Ljava/lang/String;Ljava/lang/Object;)V
      27: aload_1
      28: iconst_1
      29: anewarray     #68                 // class java/lang/reflect/Type
      32: dup
      33: iconst_0
      34: ldc           #179                // class org/hibernate/engine/spi/PersistentAttributeInterceptable
      36: aastore
      37: invokeinterface #70,  2           // InterfaceMethod net/bytebuddy/dynamic/DynamicType$Builder.implement:([Ljava/lang/reflect/Type;)Lnet/bytebuddy/dynamic/DynamicType$Builder$MethodDefinition$ImplementationDefinition$Optional;
      42: astore_1
      43: aload_1
      44: ldc           #180                // class org/hibernate/engine/spi/PersistentAttributeInterceptor
      46: ldc           #181                // String $$_hibernate_attributeInterceptor
      48: ldc           #182                // String $$_hibernate_getInterceptor
      50: ldc           #183                // String $$_hibernate_setInterceptor
      52: invokestatic  #83                 // Method addFieldWithGetterAndSetter:(Lnet/bytebuddy/dynamic/DynamicType$Builder;Ljava/lang/Class;Ljava/lang/String;Ljava/lang/String;Ljava/lang/String;)Lnet/bytebuddy/dynamic/DynamicType$Builder;
      55: astore_1
      56: aload_1
      57: areturn

  private static net.bytebuddy.dynamic.DynamicType$Builder<?> addFieldWithGetterAndSetter(net.bytebuddy.dynamic.DynamicType$Builder<?>, java.lang.Class<?>, java.lang.String, java.lang.String, java.lang.String);
    Code:
       0: aload_0
       1: aload_2
       2: aload_1
       3: iconst_2
       4: anewarray     #97                 // class net/bytebuddy/description/modifier/ModifierContributor$ForField
       7: dup
       8: iconst_0
       9: getstatic     #99                 // Field net/bytebuddy/description/modifier/Visibility.PRIVATE:Lnet/bytebuddy/description/modifier/Visibility;
      12: aastore
      13: dup
      14: iconst_1
      15: getstatic     #98                 // Field net/bytebuddy/description/modifier/FieldPersistence.TRANSIENT:Lnet/bytebuddy/description/modifier/FieldPersistence;
      18: aastore
      19: invokeinterface #184,  4          // InterfaceMethod net/bytebuddy/dynamic/DynamicType$Builder.defineField:(Ljava/lang/String;Ljava/lang/reflect/Type;[Lnet/bytebuddy/description/modifier/ModifierContributor$ForField;)Lnet/bytebuddy/dynamic/DynamicType$Builder$FieldDefinition$Optional$Valuable;
      24: iconst_1
      25: anewarray     #101                // class net/bytebuddy/description/annotation/AnnotationDescription
      28: dup
      29: iconst_0
      30: ldc           #102                // class javax/persistence/Transient
      32: invokestatic  #103                // Method net/bytebuddy/description/annotation/AnnotationDescription$Builder.ofType:(Ljava/lang/Class;)Lnet/bytebuddy/description/annotation/AnnotationDescription$Builder;
      35: invokevirtual #104                // Method net/bytebuddy/description/annotation/AnnotationDescription$Builder.build:()Lnet/bytebuddy/description/annotation/AnnotationDescription;
      38: aastore
      39: invokeinterface #105,  2          // InterfaceMethod net/bytebuddy/dynamic/DynamicType$Builder$FieldDefinition$Optional$Valuable.annotateField:([Lnet/bytebuddy/description/annotation/AnnotationDescription;)Lnet/bytebuddy/dynamic/DynamicType$Builder$FieldDefinition$Optional;
      44: aload_3
      45: aload_1
      46: iconst_1
      47: anewarray     #74                 // class net/bytebuddy/description/modifier/ModifierContributor$ForMethod
      50: dup
      51: iconst_0
      52: getstatic     #75                 // Field net/bytebuddy/description/modifier/Visibility.PUBLIC:Lnet/bytebuddy/description/modifier/Visibility;
      55: aastore
      56: invokeinterface #108,  4          // InterfaceMethod net/bytebuddy/dynamic/DynamicType$Builder$FieldDefinition$Optional.defineMethod:(Ljava/lang/String;Ljava/lang/reflect/Type;[Lnet/bytebuddy/description/modifier/ModifierContributor$ForMethod;)Lnet/bytebuddy/dynamic/DynamicType$Builder$MethodDefinition$ParameterDefinition$Initial;
      61: aload_2
      62: invokestatic  #124                // Method net/bytebuddy/implementation/FieldAccessor.ofField:(Ljava/lang/String;)Lnet/bytebuddy/implementation/FieldAccessor$OwnerTypeLocatable;
      65: invokeinterface #78,  2           // InterfaceMethod net/bytebuddy/dynamic/DynamicType$Builder$MethodDefinition$ParameterDefinition$Initial.intercept:(Lnet/bytebuddy/implementation/Implementation;)Lnet/bytebuddy/dynamic/DynamicType$Builder$MethodDefinition$ReceiverTypeDefinition;
      70: aload         4
      72: getstatic     #107                // Field java/lang/Void.TYPE:Ljava/lang/Class;
      75: iconst_1
      76: anewarray     #74                 // class net/bytebuddy/description/modifier/ModifierContributor$ForMethod
      79: dup
      80: iconst_0
      81: getstatic     #75                 // Field net/bytebuddy/description/modifier/Visibility.PUBLIC:Lnet/bytebuddy/description/modifier/Visibility;
      84: aastore
      85: invokeinterface #114,  4          // InterfaceMethod net/bytebuddy/dynamic/DynamicType$Builder$MethodDefinition$ReceiverTypeDefinition.defineMethod:(Ljava/lang/String;Ljava/lang/reflect/Type;[Lnet/bytebuddy/description/modifier/ModifierContributor$ForMethod;)Lnet/bytebuddy/dynamic/DynamicType$Builder$MethodDefinition$ParameterDefinition$Initial;
      90: iconst_1
      91: anewarray     #68                 // class java/lang/reflect/Type
      94: dup
      95: iconst_0
      96: aload_1
      97: aastore
      98: invokeinterface #110,  2          // InterfaceMethod net/bytebuddy/dynamic/DynamicType$Builder$MethodDefinition$ParameterDefinition$Initial.withParameters:([Ljava/lang/reflect/Type;)Lnet/bytebuddy/dynamic/DynamicType$Builder$MethodDefinition$ExceptionDefinition;
     103: aload_2
     104: invokestatic  #124                // Method net/bytebuddy/implementation/FieldAccessor.ofField:(Ljava/lang/String;)Lnet/bytebuddy/implementation/FieldAccessor$OwnerTypeLocatable;
     107: invokeinterface #111,  2          // InterfaceMethod net/bytebuddy/dynamic/DynamicType$Builder$MethodDefinition$ExceptionDefinition.intercept:(Lnet/bytebuddy/implementation/Implementation;)Lnet/bytebuddy/dynamic/DynamicType$Builder$MethodDefinition$ReceiverTypeDefinition;
     112: areturn

  private java.util.List<org.hibernate.bytecode.enhance.internal.bytebuddy.EnhancerImpl$AnnotatedFieldDescription> collectCollectionFields(net.bytebuddy.description.type.TypeDescription);
    Code:
       0: new           #185                // class java/util/ArrayList
       3: dup
       4: invokespecial #186                // Method java/util/ArrayList."<init>":()V
       7: astore_2
       8: aload_1
       9: invokeinterface #187,  1          // InterfaceMethod net/bytebuddy/description/type/TypeDescription.getDeclaredFields:()Lnet/bytebuddy/description/field/FieldList;
      14: invokeinterface #188,  1          // InterfaceMethod net/bytebuddy/description/field/FieldList.iterator:()Ljava/util/Iterator;
      19: astore_3
      20: aload_3
      21: invokeinterface #126,  1          // InterfaceMethod java/util/Iterator.hasNext:()Z
      26: ifeq          166
      29: aload_3
      30: invokeinterface #127,  1          // InterfaceMethod java/util/Iterator.next:()Ljava/lang/Object;
      35: checkcast     #189                // class net/bytebuddy/description/field/FieldDescription
      38: astore        4
      40: aload         4
      42: invokeinterface #190,  1          // InterfaceMethod net/bytebuddy/description/field/FieldDescription.getModifiers:()I
      47: invokestatic  #191                // Method java/lang/reflect/Modifier.isStatic:(I)Z
      50: ifne          20
      53: aload         4
      55: invokeinterface #192,  1          // InterfaceMethod net/bytebuddy/description/field/FieldDescription.getName:()Ljava/lang/String;
      60: ldc           #193                // String $$_hibernate_
      62: invokevirtual #194                // Method java/lang/String.startsWith:(Ljava/lang/String;)Z
      65: ifeq          71
      68: goto          20
      71: new           #128                // class org/hibernate/bytecode/enhance/internal/bytebuddy/EnhancerImpl$AnnotatedFieldDescription
      74: dup
      75: aload_0
      76: getfield      #35                 // Field enhancementContext:Lorg/hibernate/bytecode/enhance/internal/bytebuddy/ByteBuddyEnhancementContext;
      79: aload         4
      81: invokespecial #195                // Method org/hibernate/bytecode/enhance/internal/bytebuddy/EnhancerImpl$AnnotatedFieldDescription."<init>":(Lorg/hibernate/bytecode/enhance/internal/bytebuddy/ByteBuddyEnhancementContext;Lnet/bytebuddy/description/field/FieldDescription;)V
      84: astore        5
      86: aload_0
      87: getfield      #35                 // Field enhancementContext:Lorg/hibernate/bytecode/enhance/internal/bytebuddy/ByteBuddyEnhancementContext;
      90: aload         5
      92: invokevirtual #196                // Method org/hibernate/bytecode/enhance/internal/bytebuddy/ByteBuddyEnhancementContext.isPersistentField:(Lorg/hibernate/bytecode/enhance/internal/bytebuddy/EnhancerImpl$AnnotatedFieldDescription;)Z
      95: ifeq          163
      98: aload_0
      99: getfield      #35                 // Field enhancementContext:Lorg/hibernate/bytecode/enhance/internal/bytebuddy/ByteBuddyEnhancementContext;
     102: aload         5
     104: invokevirtual #197                // Method org/hibernate/bytecode/enhance/internal/bytebuddy/ByteBuddyEnhancementContext.isMappedCollection:(Lorg/hibernate/bytecode/enhance/internal/bytebuddy/EnhancerImpl$AnnotatedFieldDescription;)Z
     107: ifne          163
     110: aload         4
     112: invokeinterface #198,  1          // InterfaceMethod net/bytebuddy/description/field/FieldDescription.getType:()Lnet/bytebuddy/description/type/TypeDescription$Generic;
     117: invokeinterface #130,  1          // InterfaceMethod net/bytebuddy/description/type/TypeDescription$Generic.asErasure:()Lnet/bytebuddy/description/type/TypeDescription;
     122: ldc           #199                // class java/util/Collection
     124: invokeinterface #132,  2          // InterfaceMethod net/bytebuddy/description/type/TypeDescription.isAssignableTo:(Ljava/lang/Class;)Z
     129: ifne          154
     132: aload         4
     134: invokeinterface #198,  1          // InterfaceMethod net/bytebuddy/description/field/FieldDescription.getType:()Lnet/bytebuddy/description/type/TypeDescription$Generic;
     139: invokeinterface #130,  1          // InterfaceMethod net/bytebuddy/description/type/TypeDescription$Generic.asErasure:()Lnet/bytebuddy/description/type/TypeDescription;
     144: ldc           #131                // class java/util/Map
     146: invokeinterface #132,  2          // InterfaceMethod net/bytebuddy/description/type/TypeDescription.isAssignableTo:(Ljava/lang/Class;)Z
     151: ifeq          163
     154: aload_2
     155: aload         5
     157: invokeinterface #200,  2          // InterfaceMethod java/util/List.add:(Ljava/lang/Object;)Z
     162: pop
     163: goto          20
     166: aload_0
     167: getfield      #35                 // Field enhancementContext:Lorg/hibernate/bytecode/enhance/internal/bytebuddy/ByteBuddyEnhancementContext;
     170: aload_1
     171: invokevirtual #166                // Method org/hibernate/bytecode/enhance/internal/bytebuddy/ByteBuddyEnhancementContext.isMappedSuperclassClass:(Lnet/bytebuddy/description/type/TypeDescription;)Z
     174: ifne          189
     177: aload_2
     178: aload_0
     179: aload_1
     180: invokespecial #201                // Method collectInheritCollectionFields:(Lnet/bytebuddy/description/type/TypeDefinition;)Ljava/util/Collection;
     183: invokeinterface #202,  2          // InterfaceMethod java/util/List.addAll:(Ljava/util/Collection;)Z
     188: pop
     189: aload_2
     190: areturn

  private java.util.Collection<org.hibernate.bytecode.enhance.internal.bytebuddy.EnhancerImpl$AnnotatedFieldDescription> collectInheritCollectionFields(net.bytebuddy.description.type.TypeDefinition);
    Code:
       0: aload_1
       1: invokeinterface #203,  1          // InterfaceMethod net/bytebuddy/description/type/TypeDefinition.getSuperClass:()Lnet/bytebuddy/description/type/TypeDescription$Generic;
       6: astore_2
       7: aload_2
       8: ifnull        22
      11: aload_2
      12: ldc           #73                 // class java/lang/Object
      14: invokeinterface #204,  2          // InterfaceMethod net/bytebuddy/description/type/TypeDefinition.represents:(Ljava/lang/reflect/Type;)Z
      19: ifeq          26
      22: invokestatic  #205                // Method java/util/Collections.emptyList:()Ljava/util/List;
      25: areturn
      26: aload_0
      27: getfield      #35                 // Field enhancementContext:Lorg/hibernate/bytecode/enhance/internal/bytebuddy/ByteBuddyEnhancementContext;
      30: aload_2
      31: invokeinterface #206,  1          // InterfaceMethod net/bytebuddy/description/type/TypeDefinition.asErasure:()Lnet/bytebuddy/description/type/TypeDescription;
      36: invokevirtual #166                // Method org/hibernate/bytecode/enhance/internal/bytebuddy/ByteBuddyEnhancementContext.isMappedSuperclassClass:(Lnet/bytebuddy/description/type/TypeDescription;)Z
      39: ifne          53
      42: aload_0
      43: aload_2
      44: invokeinterface #206,  1          // InterfaceMethod net/bytebuddy/description/type/TypeDefinition.asErasure:()Lnet/bytebuddy/description/type/TypeDescription;
      49: invokespecial #201                // Method collectInheritCollectionFields:(Lnet/bytebuddy/description/type/TypeDefinition;)Ljava/util/Collection;
      52: areturn
      53: new           #185                // class java/util/ArrayList
      56: dup
      57: invokespecial #186                // Method java/util/ArrayList."<init>":()V
      60: astore_3
      61: aload_2
      62: invokeinterface #207,  1          // InterfaceMethod net/bytebuddy/description/type/TypeDefinition.getDeclaredFields:()Lnet/bytebuddy/description/field/FieldList;
      67: invokeinterface #188,  1          // InterfaceMethod net/bytebuddy/description/field/FieldList.iterator:()Ljava/util/Iterator;
      72: astore        4
      74: aload         4
      76: invokeinterface #126,  1          // InterfaceMethod java/util/Iterator.hasNext:()Z
      81: ifeq          204
      84: aload         4
      86: invokeinterface #127,  1          // InterfaceMethod java/util/Iterator.next:()Ljava/lang/Object;
      91: checkcast     #189                // class net/bytebuddy/description/field/FieldDescription
      94: astore        5
      96: aload         5
      98: invokeinterface #190,  1          // InterfaceMethod net/bytebuddy/description/field/FieldDescription.getModifiers:()I
     103: invokestatic  #191                // Method java/lang/reflect/Modifier.isStatic:(I)Z
     106: ifne          201
     109: new           #128                // class org/hibernate/bytecode/enhance/internal/bytebuddy/EnhancerImpl$AnnotatedFieldDescription
     112: dup
     113: aload_0
     114: getfield      #35                 // Field enhancementContext:Lorg/hibernate/bytecode/enhance/internal/bytebuddy/ByteBuddyEnhancementContext;
     117: aload         5
     119: invokespecial #195                // Method org/hibernate/bytecode/enhance/internal/bytebuddy/EnhancerImpl$AnnotatedFieldDescription."<init>":(Lorg/hibernate/bytecode/enhance/internal/bytebuddy/ByteBuddyEnhancementContext;Lnet/bytebuddy/description/field/FieldDescription;)V
     122: astore        6
     124: aload_0
     125: getfield      #35                 // Field enhancementContext:Lorg/hibernate/bytecode/enhance/internal/bytebuddy/ByteBuddyEnhancementContext;
     128: aload         6
     130: invokevirtual #196                // Method org/hibernate/bytecode/enhance/internal/bytebuddy/ByteBuddyEnhancementContext.isPersistentField:(Lorg/hibernate/bytecode/enhance/internal/bytebuddy/EnhancerImpl$AnnotatedFieldDescription;)Z
     133: ifeq          201
     136: aload_0
     137: getfield      #35                 // Field enhancementContext:Lorg/hibernate/bytecode/enhance/internal/bytebuddy/ByteBuddyEnhancementContext;
     140: aload         6
     142: invokevirtual #197                // Method org/hibernate/bytecode/enhance/internal/bytebuddy/ByteBuddyEnhancementContext.isMappedCollection:(Lorg/hibernate/bytecode/enhance/internal/bytebuddy/EnhancerImpl$AnnotatedFieldDescription;)Z
     145: ifne          201
     148: aload         5
     150: invokeinterface #198,  1          // InterfaceMethod net/bytebuddy/description/field/FieldDescription.getType:()Lnet/bytebuddy/description/type/TypeDescription$Generic;
     155: invokeinterface #130,  1          // InterfaceMethod net/bytebuddy/description/type/TypeDescription$Generic.asErasure:()Lnet/bytebuddy/description/type/TypeDescription;
     160: ldc           #199                // class java/util/Collection
     162: invokeinterface #132,  2          // InterfaceMethod net/bytebuddy/description/type/TypeDescription.isAssignableTo:(Ljava/lang/Class;)Z
     167: ifne          192
     170: aload         5
     172: invokeinterface #198,  1          // InterfaceMethod net/bytebuddy/description/field/FieldDescription.getType:()Lnet/bytebuddy/description/type/TypeDescription$Generic;
     177: invokeinterface #130,  1          // InterfaceMethod net/bytebuddy/description/type/TypeDescription$Generic.asErasure:()Lnet/bytebuddy/description/type/TypeDescription;
     182: ldc           #131                // class java/util/Map
     184: invokeinterface #132,  2          // InterfaceMethod net/bytebuddy/description/type/TypeDescription.isAssignableTo:(Ljava/lang/Class;)Z
     189: ifeq          201
     192: aload_3
     193: aload         6
     195: invokeinterface #200,  2          // InterfaceMethod java/util/List.add:(Ljava/lang/Object;)Z
     200: pop
     201: goto          74
     204: aload_3
     205: aload_0
     206: aload_2
     207: invokespecial #201                // Method collectInheritCollectionFields:(Lnet/bytebuddy/description/type/TypeDefinition;)Ljava/util/Collection;
     210: invokeinterface #202,  2          // InterfaceMethod java/util/List.addAll:(Ljava/util/Collection;)Z
     215: pop
     216: aload_3
     217: areturn

  static java.lang.String capitalize(java.lang.String);
    Code:
       0: new           #51                 // class java/lang/StringBuilder
       3: dup
       4: invokespecial #52                 // Method java/lang/StringBuilder."<init>":()V
       7: aload_0
       8: iconst_0
       9: invokevirtual #208                // Method java/lang/String.charAt:(I)C
      12: invokestatic  #209                // Method java/lang/Character.toUpperCase:(C)C
      15: invokevirtual #210                // Method java/lang/StringBuilder.append:(C)Ljava/lang/StringBuilder;
      18: aload_0
      19: iconst_1
      20: invokevirtual #211                // Method java/lang/String.substring:(I)Ljava/lang/String;
      23: invokevirtual #54                 // Method java/lang/StringBuilder.append:(Ljava/lang/String;)Ljava/lang/StringBuilder;
      26: invokevirtual #55                 // Method java/lang/StringBuilder.toString:()Ljava/lang/String;
      29: areturn

  private net.bytebuddy.dynamic.DynamicType$Builder lambda$enhance$0(net.bytebuddy.description.type.TypeDescription, java.lang.String, byte[], net.bytebuddy.ByteBuddy);
    Code:
       0: aload_0
       1: aload         4
       3: invokestatic  #212                // Method net/bytebuddy/matcher/ElementMatchers.isDefaultFinalizer:()Lnet/bytebuddy/matcher/ElementMatcher$Junction;
       6: invokevirtual #213                // Method net/bytebuddy/ByteBuddy.ignore:(Lnet/bytebuddy/matcher/ElementMatcher;)Lnet/bytebuddy/ByteBuddy;
       9: aload_1
      10: aload_2
      11: aload_3
      12: invokestatic  #214                // Method net/bytebuddy/dynamic/ClassFileLocator$Simple.of:(Ljava/lang/String;[B)Lnet/bytebuddy/dynamic/ClassFileLocator;
      15: invokevirtual #215                // Method net/bytebuddy/ByteBuddy.redefine:(Lnet/bytebuddy/description/type/TypeDescription;Lnet/bytebuddy/dynamic/ClassFileLocator;)Lnet/bytebuddy/dynamic/DynamicType$Builder;
      18: aload_1
      19: invokespecial #216                // Method doEnhance:(Lnet/bytebuddy/dynamic/DynamicType$Builder;Lnet/bytebuddy/description/type/TypeDescription;)Lnet/bytebuddy/dynamic/DynamicType$Builder;
      22: areturn

  static {};
    Code:
       0: ldc           #217                // class org/hibernate/bytecode/enhance/spi/Enhancer
       2: invokestatic  #218                // Method org/hibernate/internal/CoreLogging.messageLogger:(Ljava/lang/Class;)Lorg/hibernate/internal/CoreMessageLogger;
       5: putstatic     #59                 // Field log:Lorg/hibernate/internal/CoreMessageLogger;
       8: return
}
