Compiled from "FieldReaderAppender.java"
class org.hibernate.bytecode.enhance.internal.bytebuddy.FieldReaderAppender$FieldWriting extends org.hibernate.bytecode.enhance.internal.bytebuddy.FieldReaderAppender {
  private org.hibernate.bytecode.enhance.internal.bytebuddy.FieldReaderAppender$FieldWriting(net.bytebuddy.description.type.TypeDescription, org.hibernate.bytecode.enhance.internal.bytebuddy.EnhancerImpl$AnnotatedFieldDescription);
    Code:
       0: aload_0
       1: aload_1
       2: aload_2
       3: aconst_null
       4: invokespecial #2                  // Method org/hibernate/bytecode/enhance/internal/bytebuddy/FieldReaderAppender."<init>":(Lnet/bytebuddy/description/type/TypeDescription;Lorg/hibernate/bytecode/enhance/internal/bytebuddy/EnhancerImpl$AnnotatedFieldDescription;Lorg/hibernate/bytecode/enhance/internal/bytebuddy/FieldReaderAppender$1;)V
       7: return

  protected void fieldRead(net.bytebuddy.jar.asm.MethodVisitor);
    Code:
       0: aload_1
       1: sipush        180
       4: aload_0
       5: getfield      #4                  // Field persistentFieldAsDefined:Lnet/bytebuddy/description/field/FieldDescription$InDefinedShape;
       8: invokeinterface #5,  1            // InterfaceMethod net/bytebuddy/description/field/FieldDescription$InDefinedShape.getDeclaringType:()Lnet/bytebuddy/description/type/TypeDescription;
      13: invokeinterface #6,  1            // InterfaceMethod net/bytebuddy/description/type/TypeDescription.asErasure:()Lnet/bytebuddy/description/type/TypeDescription;
      18: invokeinterface #7,  1            // InterfaceMethod net/bytebuddy/description/type/TypeDescription.getInternalName:()Ljava/lang/String;
      23: aload_0
      24: getfield      #4                  // Field persistentFieldAsDefined:Lnet/bytebuddy/description/field/FieldDescription$InDefinedShape;
      27: invokeinterface #8,  1            // InterfaceMethod net/bytebuddy/description/field/FieldDescription$InDefinedShape.getInternalName:()Ljava/lang/String;
      32: aload_0
      33: getfield      #4                  // Field persistentFieldAsDefined:Lnet/bytebuddy/description/field/FieldDescription$InDefinedShape;
      36: invokeinterface #9,  1            // InterfaceMethod net/bytebuddy/description/field/FieldDescription$InDefinedShape.getDescriptor:()Ljava/lang/String;
      41: invokevirtual #10                 // Method net/bytebuddy/jar/asm/MethodVisitor.visitFieldInsn:(ILjava/lang/String;Ljava/lang/String;Ljava/lang/String;)V
      44: return

  protected void fieldWrite(net.bytebuddy.jar.asm.MethodVisitor);
    Code:
       0: aload_1
       1: sipush        181
       4: aload_0
       5: getfield      #4                  // Field persistentFieldAsDefined:Lnet/bytebuddy/description/field/FieldDescription$InDefinedShape;
       8: invokeinterface #5,  1            // InterfaceMethod net/bytebuddy/description/field/FieldDescription$InDefinedShape.getDeclaringType:()Lnet/bytebuddy/description/type/TypeDescription;
      13: invokeinterface #6,  1            // InterfaceMethod net/bytebuddy/description/type/TypeDescription.asErasure:()Lnet/bytebuddy/description/type/TypeDescription;
      18: invokeinterface #7,  1            // InterfaceMethod net/bytebuddy/description/type/TypeDescription.getInternalName:()Ljava/lang/String;
      23: aload_0
      24: getfield      #4                  // Field persistentFieldAsDefined:Lnet/bytebuddy/description/field/FieldDescription$InDefinedShape;
      27: invokeinterface #8,  1            // InterfaceMethod net/bytebuddy/description/field/FieldDescription$InDefinedShape.getInternalName:()Ljava/lang/String;
      32: aload_0
      33: getfield      #4                  // Field persistentFieldAsDefined:Lnet/bytebuddy/description/field/FieldDescription$InDefinedShape;
      36: invokeinterface #9,  1            // InterfaceMethod net/bytebuddy/description/field/FieldDescription$InDefinedShape.getDescriptor:()Ljava/lang/String;
      41: invokevirtual #10                 // Method net/bytebuddy/jar/asm/MethodVisitor.visitFieldInsn:(ILjava/lang/String;Ljava/lang/String;Ljava/lang/String;)V
      44: return

  org.hibernate.bytecode.enhance.internal.bytebuddy.FieldReaderAppender$FieldWriting(net.bytebuddy.description.type.TypeDescription, org.hibernate.bytecode.enhance.internal.bytebuddy.EnhancerImpl$AnnotatedFieldDescription, org.hibernate.bytecode.enhance.internal.bytebuddy.FieldReaderAppender$1);
    Code:
       0: aload_0
       1: aload_1
       2: aload_2
       3: invokespecial #1                  // Method "<init>":(Lnet/bytebuddy/description/type/TypeDescription;Lorg/hibernate/bytecode/enhance/internal/bytebuddy/EnhancerImpl$AnnotatedFieldDescription;)V
       6: return
}
