Compiled from "Cache.java"
class net.sf.ehcache.Cache$4 extends java.util.concurrent.AbstractExecutorService {
  final net.sf.ehcache.Cache this$0;

  net.sf.ehcache.Cache$4(net.sf.ehcache.Cache);
    Code:
       0: aload_0
       1: aload_1
       2: putfield      #1                  // Field this$0:Lnet/sf/ehcache/Cache;
       5: aload_0
       6: invokespecial #2                  // Method java/util/concurrent/AbstractExecutorService."<init>":()V
       9: return

  public void execute(java.lang.Runnable);
    Code:
       0: aload_1
       1: invokeinterface #3,  1            // InterfaceMethod java/lang/Runnable.run:()V
       6: return

  public java.util.List<java.lang.Runnable> shutdownNow();
    Code:
       0: invokestatic  #4                  // Method java/util/Collections.emptyList:()Ljava/util/List;
       3: areturn

  public void shutdown();
    Code:
       0: return

  public boolean isTerminated();
    Code:
       0: aload_0
       1: invokevirtual #5                  // Method isShutdown:()Z
       4: ireturn

  public boolean isShutdown();
    Code:
       0: iconst_0
       1: ireturn

  public boolean awaitTermination(long, java.util.concurrent.TimeUnit) throws java.lang.InterruptedException;
    Code:
       0: iconst_1
       1: ireturn
}
