Compiled from "Status.java"
public final class net.sf.ehcache.Status implements java.io.Serializable {
  public static final net.sf.ehcache.Status STATUS_UNINITIALISED;

  public static final net.sf.ehcache.Status STATUS_ALIVE;

  public static final net.sf.ehcache.Status STATUS_SHUTDOWN;

  private static final long serialVersionUID;

  private static final net.sf.ehcache.Status[] STATUSES;

  private final java.lang.String name;

  private final int intValue;

  private net.sf.ehcache.Status(int, java.lang.String);
    Code:
       0: aload_0
       1: invokespecial #1                  // Method java/lang/Object."<init>":()V
       4: aload_0
       5: iload_1
       6: putfield      #2                  // Field intValue:I
       9: aload_0
      10: aload_2
      11: putfield      #3                  // Field name:Ljava/lang/String;
      14: return

  public java.lang.String toString();
    Code:
       0: aload_0
       1: getfield      #3                  // Field name:Ljava/lang/String;
       4: areturn

  public static net.sf.ehcache.Status convertIntToStatus(int) throws java.lang.IllegalArgumentException;
    Code:
       0: iload_0
       1: getstatic     #4                  // Field STATUS_UNINITIALISED:Lnet/sf/ehcache/Status;
       4: getfield      #2                  // Field intValue:I
       7: if_icmplt     20
      10: iload_0
      11: getstatic     #5                  // Field STATUS_SHUTDOWN:Lnet/sf/ehcache/Status;
      14: getfield      #2                  // Field intValue:I
      17: if_icmple     30
      20: new           #6                  // class java/lang/IllegalArgumentException
      23: dup
      24: ldc           #7                  // String int value of statuses must be between 1 and three
      26: invokespecial #8                  // Method java/lang/IllegalArgumentException."<init>":(Ljava/lang/String;)V
      29: athrow
      30: getstatic     #9                  // Field STATUSES:[Lnet/sf/ehcache/Status;
      33: iload_0
      34: aaload
      35: areturn

  public int intValue();
    Code:
       0: aload_0
       1: getfield      #2                  // Field intValue:I
       4: ireturn

  public boolean equals(java.lang.Object);
    Code:
       0: aload_1
       1: instanceof    #10                 // class net/sf/ehcache/Status
       4: ifne          9
       7: iconst_0
       8: ireturn
       9: aload_1
      10: checkcast     #10                 // class net/sf/ehcache/Status
      13: getfield      #2                  // Field intValue:I
      16: aload_0
      17: getfield      #2                  // Field intValue:I
      20: if_icmpne     27
      23: iconst_1
      24: goto          28
      27: iconst_0
      28: ireturn

  public boolean equals(net.sf.ehcache.Status);
    Code:
       0: aload_1
       1: ifnonnull     6
       4: iconst_0
       5: ireturn
       6: aload_0
       7: getfield      #2                  // Field intValue:I
      10: aload_1
      11: getfield      #2                  // Field intValue:I
      14: if_icmpne     21
      17: iconst_1
      18: goto          22
      21: iconst_0
      22: ireturn

  public int hashCode();
    Code:
       0: aload_0
       1: getfield      #2                  // Field intValue:I
       4: ireturn

  static {};
    Code:
       0: new           #10                 // class net/sf/ehcache/Status
       3: dup
       4: iconst_0
       5: ldc           #11                 // String STATUS_UNINITIALISED
       7: invokespecial #12                 // Method "<init>":(ILjava/lang/String;)V
      10: putstatic     #4                  // Field STATUS_UNINITIALISED:Lnet/sf/ehcache/Status;
      13: new           #10                 // class net/sf/ehcache/Status
      16: dup
      17: iconst_1
      18: ldc           #13                 // String STATUS_ALIVE
      20: invokespecial #12                 // Method "<init>":(ILjava/lang/String;)V
      23: putstatic     #14                 // Field STATUS_ALIVE:Lnet/sf/ehcache/Status;
      26: new           #10                 // class net/sf/ehcache/Status
      29: dup
      30: iconst_2
      31: ldc           #15                 // String STATUS_SHUTDOWN
      33: invokespecial #12                 // Method "<init>":(ILjava/lang/String;)V
      36: putstatic     #5                  // Field STATUS_SHUTDOWN:Lnet/sf/ehcache/Status;
      39: iconst_3
      40: anewarray     #10                 // class net/sf/ehcache/Status
      43: dup
      44: iconst_0
      45: getstatic     #4                  // Field STATUS_UNINITIALISED:Lnet/sf/ehcache/Status;
      48: aastore
      49: dup
      50: iconst_1
      51: getstatic     #14                 // Field STATUS_ALIVE:Lnet/sf/ehcache/Status;
      54: aastore
      55: dup
      56: iconst_2
      57: getstatic     #5                  // Field STATUS_SHUTDOWN:Lnet/sf/ehcache/Status;
      60: aastore
      61: putstatic     #9                  // Field STATUSES:[Lnet/sf/ehcache/Status;
      64: return
}
