Compiled from "ArgMatchers.java"
public class pro.javacard.gp.ArgMatchers$KeySetMatcher implements joptsimple.ValueConverter<pro.javacard.gp.PlaintextKeys> {
  public pro.javacard.gp.ArgMatchers$KeySetMatcher();
    Code:
       0: aload_0
       1: invokespecial #1                  // Method java/lang/Object."<init>":()V
       4: return

  public java.lang.Class<pro.javacard.gp.PlaintextKeys> valueType();
    Code:
       0: ldc           #2                  // class pro/javacard/gp/PlaintextKeys
       2: areturn

  public java.lang.String valuePattern();
    Code:
       0: aconst_null
       1: areturn

  public pro.javacard.gp.PlaintextKeys convert(java.lang.String);
    Code:
       0: aconst_null
       1: astore_2
       2: getstatic     #3                  // Field pro/javacard/gp/GPKeySet$Diversification.NONE:Lpro/javacard/gp/GPKeySet$Diversification;
       5: astore_3
       6: aload_1
       7: invokevirtual #4                  // Method java/lang/String.trim:()Ljava/lang/String;
      10: invokevirtual #5                  // Method java/lang/String.toLowerCase:()Ljava/lang/String;
      13: astore        4
      15: aload         4
      17: ldc           #6                  // String emv:
      19: invokevirtual #7                  // Method java/lang/String.startsWith:(Ljava/lang/String;)Z
      22: ifeq          56
      25: new           #8                  // class pro/javacard/gp/GPKeySet$GPKey
      28: dup
      29: aload         4
      31: ldc           #6                  // String emv:
      33: invokevirtual #9                  // Method java/lang/String.length:()I
      36: invokevirtual #10                 // Method java/lang/String.substring:(I)Ljava/lang/String;
      39: invokestatic  #11                 // Method apdu4j/HexUtils.hex2bin:(Ljava/lang/String;)[B
      42: getstatic     #12                 // Field pro/javacard/gp/GPKeySet$GPKey$Type.DES3:Lpro/javacard/gp/GPKeySet$GPKey$Type;
      45: invokespecial #13                 // Method pro/javacard/gp/GPKeySet$GPKey."<init>":([BLpro/javacard/gp/GPKeySet$GPKey$Type;)V
      48: astore_2
      49: getstatic     #14                 // Field pro/javacard/gp/GPKeySet$Diversification.EMV:Lpro/javacard/gp/GPKeySet$Diversification;
      52: astore_3
      53: goto          150
      56: aload         4
      58: ldc           #15                 // String visa2:
      60: invokevirtual #7                  // Method java/lang/String.startsWith:(Ljava/lang/String;)Z
      63: ifeq          97
      66: new           #8                  // class pro/javacard/gp/GPKeySet$GPKey
      69: dup
      70: aload         4
      72: ldc           #15                 // String visa2:
      74: invokevirtual #9                  // Method java/lang/String.length:()I
      77: invokevirtual #10                 // Method java/lang/String.substring:(I)Ljava/lang/String;
      80: invokestatic  #11                 // Method apdu4j/HexUtils.hex2bin:(Ljava/lang/String;)[B
      83: getstatic     #12                 // Field pro/javacard/gp/GPKeySet$GPKey$Type.DES3:Lpro/javacard/gp/GPKeySet$GPKey$Type;
      86: invokespecial #13                 // Method pro/javacard/gp/GPKeySet$GPKey."<init>":([BLpro/javacard/gp/GPKeySet$GPKey$Type;)V
      89: astore_2
      90: getstatic     #16                 // Field pro/javacard/gp/GPKeySet$Diversification.VISA2:Lpro/javacard/gp/GPKeySet$Diversification;
      93: astore_3
      94: goto          150
      97: aload         4
      99: ldc           #17                 // String aes:
     101: invokevirtual #7                  // Method java/lang/String.startsWith:(Ljava/lang/String;)Z
     104: ifeq          134
     107: new           #8                  // class pro/javacard/gp/GPKeySet$GPKey
     110: dup
     111: aload         4
     113: ldc           #17                 // String aes:
     115: invokevirtual #9                  // Method java/lang/String.length:()I
     118: invokevirtual #10                 // Method java/lang/String.substring:(I)Ljava/lang/String;
     121: invokestatic  #11                 // Method apdu4j/HexUtils.hex2bin:(Ljava/lang/String;)[B
     124: getstatic     #18                 // Field pro/javacard/gp/GPKeySet$GPKey$Type.AES:Lpro/javacard/gp/GPKeySet$GPKey$Type;
     127: invokespecial #13                 // Method pro/javacard/gp/GPKeySet$GPKey."<init>":([BLpro/javacard/gp/GPKeySet$GPKey$Type;)V
     130: astore_2
     131: goto          150
     134: new           #8                  // class pro/javacard/gp/GPKeySet$GPKey
     137: dup
     138: aload         4
     140: invokestatic  #11                 // Method apdu4j/HexUtils.hex2bin:(Ljava/lang/String;)[B
     143: getstatic     #12                 // Field pro/javacard/gp/GPKeySet$GPKey$Type.DES3:Lpro/javacard/gp/GPKeySet$GPKey$Type;
     146: invokespecial #13                 // Method pro/javacard/gp/GPKeySet$GPKey."<init>":([BLpro/javacard/gp/GPKeySet$GPKey$Type;)V
     149: astore_2
     150: aload_2
     151: aload_3
     152: invokestatic  #19                 // Method pro/javacard/gp/PlaintextKeys.fromMasterKey:(Lpro/javacard/gp/GPKeySet$GPKey;Lpro/javacard/gp/GPKeySet$Diversification;)Lpro/javacard/gp/PlaintextKeys;
     155: areturn
     156: astore_2
     157: new           #21                 // class joptsimple/ValueConversionException
     160: dup
     161: new           #22                 // class java/lang/StringBuilder
     164: dup
     165: invokespecial #23                 // Method java/lang/StringBuilder."<init>":()V
     168: aload_1
     169: invokevirtual #24                 // Method java/lang/StringBuilder.append:(Ljava/lang/String;)Ljava/lang/StringBuilder;
     172: ldc           #25                 // String  is not a valid master key indicator!
     174: invokevirtual #24                 // Method java/lang/StringBuilder.append:(Ljava/lang/String;)Ljava/lang/StringBuilder;
     177: invokevirtual #26                 // Method java/lang/StringBuilder.toString:()Ljava/lang/String;
     180: invokespecial #27                 // Method joptsimple/ValueConversionException."<init>":(Ljava/lang/String;)V
     183: athrow
    Exception table:
       from    to  target type
           0   155   156   Class java/lang/IllegalArgumentException

  public java.lang.Object convert(java.lang.String);
    Code:
       0: aload_0
       1: aload_1
       2: invokevirtual #28                 // Method convert:(Ljava/lang/String;)Lpro/javacard/gp/PlaintextKeys;
       5: areturn
}
