Compiled from "GPRegistryEntry.java"
public final class pro.javacard.gp.GPRegistryEntry$Kind extends java.lang.Enum<pro.javacard.gp.GPRegistryEntry$Kind> {
  public static final pro.javacard.gp.GPRegistryEntry$Kind IssuerSecurityDomain;

  public static final pro.javacard.gp.GPRegistryEntry$Kind Application;

  public static final pro.javacard.gp.GPRegistryEntry$Kind SecurityDomain;

  public static final pro.javacard.gp.GPRegistryEntry$Kind ExecutableLoadFile;

  private static final pro.javacard.gp.GPRegistryEntry$Kind[] $VALUES;

  public static pro.javacard.gp.GPRegistryEntry$Kind[] values();
    Code:
       0: getstatic     #1                  // Field $VALUES:[Lpro/javacard/gp/GPRegistryEntry$Kind;
       3: invokevirtual #2                  // Method "[Lpro/javacard/gp/GPRegistryEntry$Kind;".clone:()Ljava/lang/Object;
       6: checkcast     #3                  // class "[Lpro/javacard/gp/GPRegistryEntry$Kind;"
       9: areturn

  public static pro.javacard.gp.GPRegistryEntry$Kind valueOf(java.lang.String);
    Code:
       0: ldc           #4                  // class pro/javacard/gp/GPRegistryEntry$Kind
       2: aload_0
       3: invokestatic  #5                  // Method java/lang/Enum.valueOf:(Ljava/lang/Class;Ljava/lang/String;)Ljava/lang/Enum;
       6: checkcast     #4                  // class pro/javacard/gp/GPRegistryEntry$Kind
       9: areturn

  private pro.javacard.gp.GPRegistryEntry$Kind();
    Code:
       0: aload_0
       1: aload_1
       2: iload_2
       3: invokespecial #6                  // Method java/lang/Enum."<init>":(Ljava/lang/String;I)V
       6: return

  public java.lang.String toShortString();
    Code:
       0: getstatic     #7                  // Field pro/javacard/gp/GPRegistryEntry$1.$SwitchMap$pro$javacard$gp$GPRegistryEntry$Kind:[I
       3: aload_0
       4: invokevirtual #8                  // Method ordinal:()I
       7: iaload
       8: tableswitch   { // 1 to 4
                     1: 40
                     2: 43
                     3: 46
                     4: 49
               default: 52
          }
      40: ldc           #9                  // String ISD
      42: areturn
      43: ldc           #10                 // String APP
      45: areturn
      46: ldc           #11                 // String DOM
      48: areturn
      49: ldc           #12                 // String PKG
      51: areturn
      52: new           #13                 // class java/lang/IllegalStateException
      55: dup
      56: ldc           #14                 // String Unknown entry type
      58: invokespecial #15                 // Method java/lang/IllegalStateException."<init>":(Ljava/lang/String;)V
      61: athrow

  static {};
    Code:
       0: new           #4                  // class pro/javacard/gp/GPRegistryEntry$Kind
       3: dup
       4: ldc           #16                 // String IssuerSecurityDomain
       6: iconst_0
       7: invokespecial #17                 // Method "<init>":(Ljava/lang/String;I)V
      10: putstatic     #18                 // Field IssuerSecurityDomain:Lpro/javacard/gp/GPRegistryEntry$Kind;
      13: new           #4                  // class pro/javacard/gp/GPRegistryEntry$Kind
      16: dup
      17: ldc           #19                 // String Application
      19: iconst_1
      20: invokespecial #17                 // Method "<init>":(Ljava/lang/String;I)V
      23: putstatic     #20                 // Field Application:Lpro/javacard/gp/GPRegistryEntry$Kind;
      26: new           #4                  // class pro/javacard/gp/GPRegistryEntry$Kind
      29: dup
      30: ldc           #21                 // String SecurityDomain
      32: iconst_2
      33: invokespecial #17                 // Method "<init>":(Ljava/lang/String;I)V
      36: putstatic     #22                 // Field SecurityDomain:Lpro/javacard/gp/GPRegistryEntry$Kind;
      39: new           #4                  // class pro/javacard/gp/GPRegistryEntry$Kind
      42: dup
      43: ldc           #23                 // String ExecutableLoadFile
      45: iconst_3
      46: invokespecial #17                 // Method "<init>":(Ljava/lang/String;I)V
      49: putstatic     #24                 // Field ExecutableLoadFile:Lpro/javacard/gp/GPRegistryEntry$Kind;
      52: iconst_4
      53: anewarray     #4                  // class pro/javacard/gp/GPRegistryEntry$Kind
      56: dup
      57: iconst_0
      58: getstatic     #18                 // Field IssuerSecurityDomain:Lpro/javacard/gp/GPRegistryEntry$Kind;
      61: aastore
      62: dup
      63: iconst_1
      64: getstatic     #20                 // Field Application:Lpro/javacard/gp/GPRegistryEntry$Kind;
      67: aastore
      68: dup
      69: iconst_2
      70: getstatic     #22                 // Field SecurityDomain:Lpro/javacard/gp/GPRegistryEntry$Kind;
      73: aastore
      74: dup
      75: iconst_3
      76: getstatic     #24                 // Field ExecutableLoadFile:Lpro/javacard/gp/GPRegistryEntry$Kind;
      79: aastore
      80: putstatic     #1                  // Field $VALUES:[Lpro/javacard/gp/GPRegistryEntry$Kind;
      83: return
}
