Compiled from "GPUtils.java"
public class pro.javacard.gp.GPUtils {
  public pro.javacard.gp.GPUtils();
    Code:
       0: aload_0
       1: invokespecial #1                  // Method java/lang/Object."<init>":()V
       4: return

  public static java.lang.String byteArrayToReadableString(byte[]);
    Code:
       0: aload_0
       1: ifnonnull     7
       4: ldc           #2                  // String (null)
       6: areturn
       7: new           #3                  // class java/lang/StringBuffer
      10: dup
      11: invokespecial #4                  // Method java/lang/StringBuffer."<init>":()V
      14: astore_1
      15: iconst_0
      16: istore_2
      17: iload_2
      18: aload_0
      19: arraylength
      20: if_icmpge     60
      23: aload_0
      24: iload_2
      25: baload
      26: i2c
      27: istore_3
      28: aload_1
      29: iload_3
      30: bipush        32
      32: if_icmplt     48
      35: iload_3
      36: bipush        127
      38: if_icmpge     48
      41: iload_3
      42: invokestatic  #5                  // Method java/lang/Character.valueOf:(C)Ljava/lang/Character;
      45: goto          50
      48: ldc           #6                  // String .
      50: invokevirtual #7                  // Method java/lang/StringBuffer.append:(Ljava/lang/Object;)Ljava/lang/StringBuffer;
      53: pop
      54: iinc          2, 1
      57: goto          17
      60: new           #8                  // class java/lang/StringBuilder
      63: dup
      64: invokespecial #9                  // Method java/lang/StringBuilder."<init>":()V
      67: ldc           #10                 // String |
      69: invokevirtual #11                 // Method java/lang/StringBuilder.append:(Ljava/lang/String;)Ljava/lang/StringBuilder;
      72: aload_1
      73: invokevirtual #12                 // Method java/lang/StringBuffer.toString:()Ljava/lang/String;
      76: invokevirtual #11                 // Method java/lang/StringBuilder.append:(Ljava/lang/String;)Ljava/lang/StringBuilder;
      79: ldc           #10                 // String |
      81: invokevirtual #11                 // Method java/lang/StringBuilder.append:(Ljava/lang/String;)Ljava/lang/StringBuilder;
      84: invokevirtual #13                 // Method java/lang/StringBuilder.toString:()Ljava/lang/String;
      87: areturn

  public static java.lang.String swToString(int);
    Code:
       0: ldc           #14                 // String %04X
       2: iconst_1
       3: anewarray     #15                 // class java/lang/Object
       6: dup
       7: iconst_0
       8: iload_0
       9: invokestatic  #16                 // Method java/lang/Integer.valueOf:(I)Ljava/lang/Integer;
      12: aastore
      13: invokestatic  #17                 // Method java/lang/String.format:(Ljava/lang/String;[Ljava/lang/Object;)Ljava/lang/String;
      16: areturn

  public static byte[] concatenate(byte[]...);
    Code:
       0: iconst_0
       1: istore_1
       2: iconst_0
       3: istore_2
       4: aload_0
       5: astore_3
       6: aload_3
       7: arraylength
       8: istore        4
      10: iconst_0
      11: istore        5
      13: iload         5
      15: iload         4
      17: if_icmpge     38
      20: aload_3
      21: iload         5
      23: aaload
      24: astore        6
      26: iload_1
      27: aload         6
      29: arraylength
      30: iadd
      31: istore_1
      32: iinc          5, 1
      35: goto          13
      38: iload_1
      39: newarray       byte
      41: astore_3
      42: aload_0
      43: astore        4
      45: aload         4
      47: arraylength
      48: istore        5
      50: iconst_0
      51: istore        6
      53: iload         6
      55: iload         5
      57: if_icmpge     90
      60: aload         4
      62: iload         6
      64: aaload
      65: astore        7
      67: aload         7
      69: iconst_0
      70: aload_3
      71: iload_2
      72: aload         7
      74: arraylength
      75: invokestatic  #18                 // Method java/lang/System.arraycopy:(Ljava/lang/Object;ILjava/lang/Object;II)V
      78: iload_2
      79: aload         7
      81: arraylength
      82: iadd
      83: istore_2
      84: iinc          6, 1
      87: goto          53
      90: aload_3
      91: areturn

  public static java.util.List<byte[]> splitArray(byte[], int);
    Code:
       0: new           #19                 // class java/util/ArrayList
       3: dup
       4: invokespecial #20                 // Method java/util/ArrayList."<init>":()V
       7: astore_2
       8: aload_0
       9: arraylength
      10: istore_3
      11: iconst_0
      12: istore        4
      14: iload_3
      15: iload         4
      17: isub
      18: istore        5
      20: iload         5
      22: ifle          87
      25: iconst_0
      26: istore        6
      28: iload         5
      30: iload_1
      31: if_icmplt     40
      34: iload_1
      35: istore        6
      37: goto          44
      40: iload         5
      42: istore        6
      44: iload         6
      46: newarray       byte
      48: astore        7
      50: aload_0
      51: iload         4
      53: aload         7
      55: iconst_0
      56: iload         6
      58: invokestatic  #18                 // Method java/lang/System.arraycopy:(Ljava/lang/Object;ILjava/lang/Object;II)V
      61: aload_2
      62: aload         7
      64: invokeinterface #21,  2           // InterfaceMethod java/util/List.add:(Ljava/lang/Object;)Z
      69: pop
      70: iload         5
      72: iload         6
      74: isub
      75: istore        5
      77: iload         4
      79: iload         6
      81: iadd
      82: istore        4
      84: goto          20
      87: aload_2
      88: areturn
}
