Compiled from "ColumnName.java"
public final class ch.qos.logback.classic.db.names.ColumnName extends java.lang.Enum<ch.qos.logback.classic.db.names.ColumnName> {
  public static final ch.qos.logback.classic.db.names.ColumnName EVENT_ID;

  public static final ch.qos.logback.classic.db.names.ColumnName TIMESTMP;

  public static final ch.qos.logback.classic.db.names.ColumnName FORMATTED_MESSAGE;

  public static final ch.qos.logback.classic.db.names.ColumnName LOGGER_NAME;

  public static final ch.qos.logback.classic.db.names.ColumnName LEVEL_STRING;

  public static final ch.qos.logback.classic.db.names.ColumnName THREAD_NAME;

  public static final ch.qos.logback.classic.db.names.ColumnName REFERENCE_FLAG;

  public static final ch.qos.logback.classic.db.names.ColumnName ARG0;

  public static final ch.qos.logback.classic.db.names.ColumnName ARG1;

  public static final ch.qos.logback.classic.db.names.ColumnName ARG2;

  public static final ch.qos.logback.classic.db.names.ColumnName ARG3;

  public static final ch.qos.logback.classic.db.names.ColumnName CALLER_FILENAME;

  public static final ch.qos.logback.classic.db.names.ColumnName CALLER_CLASS;

  public static final ch.qos.logback.classic.db.names.ColumnName CALLER_METHOD;

  public static final ch.qos.logback.classic.db.names.ColumnName CALLER_LINE;

  public static final ch.qos.logback.classic.db.names.ColumnName MAPPED_KEY;

  public static final ch.qos.logback.classic.db.names.ColumnName MAPPED_VALUE;

  public static final ch.qos.logback.classic.db.names.ColumnName I;

  public static final ch.qos.logback.classic.db.names.ColumnName TRACE_LINE;

  private static final ch.qos.logback.classic.db.names.ColumnName[] $VALUES;

  public static ch.qos.logback.classic.db.names.ColumnName[] values();
    Code:
       0: getstatic     #1                  // Field $VALUES:[Lch/qos/logback/classic/db/names/ColumnName;
       3: invokevirtual #2                  // Method "[Lch/qos/logback/classic/db/names/ColumnName;".clone:()Ljava/lang/Object;
       6: checkcast     #3                  // class "[Lch/qos/logback/classic/db/names/ColumnName;"
       9: areturn

  public static ch.qos.logback.classic.db.names.ColumnName valueOf(java.lang.String);
    Code:
       0: ldc_w         #4                  // class ch/qos/logback/classic/db/names/ColumnName
       3: aload_0
       4: invokestatic  #5                  // Method java/lang/Enum.valueOf:(Ljava/lang/Class;Ljava/lang/String;)Ljava/lang/Enum;
       7: checkcast     #4                  // class ch/qos/logback/classic/db/names/ColumnName
      10: areturn

  private ch.qos.logback.classic.db.names.ColumnName();
    Code:
       0: aload_0
       1: aload_1
       2: iload_2
       3: invokespecial #6                  // Method java/lang/Enum."<init>":(Ljava/lang/String;I)V
       6: return

  static {};
    Code:
       0: new           #4                  // class ch/qos/logback/classic/db/names/ColumnName
       3: dup
       4: ldc           #7                  // String EVENT_ID
       6: iconst_0
       7: invokespecial #8                  // Method "<init>":(Ljava/lang/String;I)V
      10: putstatic     #9                  // Field EVENT_ID:Lch/qos/logback/classic/db/names/ColumnName;
      13: new           #4                  // class ch/qos/logback/classic/db/names/ColumnName
      16: dup
      17: ldc           #10                 // String TIMESTMP
      19: iconst_1
      20: invokespecial #8                  // Method "<init>":(Ljava/lang/String;I)V
      23: putstatic     #11                 // Field TIMESTMP:Lch/qos/logback/classic/db/names/ColumnName;
      26: new           #4                  // class ch/qos/logback/classic/db/names/ColumnName
      29: dup
      30: ldc           #12                 // String FORMATTED_MESSAGE
      32: iconst_2
      33: invokespecial #8                  // Method "<init>":(Ljava/lang/String;I)V
      36: putstatic     #13                 // Field FORMATTED_MESSAGE:Lch/qos/logback/classic/db/names/ColumnName;
      39: new           #4                  // class ch/qos/logback/classic/db/names/ColumnName
      42: dup
      43: ldc           #14                 // String LOGGER_NAME
      45: iconst_3
      46: invokespecial #8                  // Method "<init>":(Ljava/lang/String;I)V
      49: putstatic     #15                 // Field LOGGER_NAME:Lch/qos/logback/classic/db/names/ColumnName;
      52: new           #4                  // class ch/qos/logback/classic/db/names/ColumnName
      55: dup
      56: ldc           #16                 // String LEVEL_STRING
      58: iconst_4
      59: invokespecial #8                  // Method "<init>":(Ljava/lang/String;I)V
      62: putstatic     #17                 // Field LEVEL_STRING:Lch/qos/logback/classic/db/names/ColumnName;
      65: new           #4                  // class ch/qos/logback/classic/db/names/ColumnName
      68: dup
      69: ldc           #18                 // String THREAD_NAME
      71: iconst_5
      72: invokespecial #8                  // Method "<init>":(Ljava/lang/String;I)V
      75: putstatic     #19                 // Field THREAD_NAME:Lch/qos/logback/classic/db/names/ColumnName;
      78: new           #4                  // class ch/qos/logback/classic/db/names/ColumnName
      81: dup
      82: ldc           #20                 // String REFERENCE_FLAG
      84: bipush        6
      86: invokespecial #8                  // Method "<init>":(Ljava/lang/String;I)V
      89: putstatic     #21                 // Field REFERENCE_FLAG:Lch/qos/logback/classic/db/names/ColumnName;
      92: new           #4                  // class ch/qos/logback/classic/db/names/ColumnName
      95: dup
      96: ldc           #22                 // String ARG0
      98: bipush        7
     100: invokespecial #8                  // Method "<init>":(Ljava/lang/String;I)V
     103: putstatic     #23                 // Field ARG0:Lch/qos/logback/classic/db/names/ColumnName;
     106: new           #4                  // class ch/qos/logback/classic/db/names/ColumnName
     109: dup
     110: ldc           #24                 // String ARG1
     112: bipush        8
     114: invokespecial #8                  // Method "<init>":(Ljava/lang/String;I)V
     117: putstatic     #25                 // Field ARG1:Lch/qos/logback/classic/db/names/ColumnName;
     120: new           #4                  // class ch/qos/logback/classic/db/names/ColumnName
     123: dup
     124: ldc           #26                 // String ARG2
     126: bipush        9
     128: invokespecial #8                  // Method "<init>":(Ljava/lang/String;I)V
     131: putstatic     #27                 // Field ARG2:Lch/qos/logback/classic/db/names/ColumnName;
     134: new           #4                  // class ch/qos/logback/classic/db/names/ColumnName
     137: dup
     138: ldc           #28                 // String ARG3
     140: bipush        10
     142: invokespecial #8                  // Method "<init>":(Ljava/lang/String;I)V
     145: putstatic     #29                 // Field ARG3:Lch/qos/logback/classic/db/names/ColumnName;
     148: new           #4                  // class ch/qos/logback/classic/db/names/ColumnName
     151: dup
     152: ldc           #30                 // String CALLER_FILENAME
     154: bipush        11
     156: invokespecial #8                  // Method "<init>":(Ljava/lang/String;I)V
     159: putstatic     #31                 // Field CALLER_FILENAME:Lch/qos/logback/classic/db/names/ColumnName;
     162: new           #4                  // class ch/qos/logback/classic/db/names/ColumnName
     165: dup
     166: ldc           #32                 // String CALLER_CLASS
     168: bipush        12
     170: invokespecial #8                  // Method "<init>":(Ljava/lang/String;I)V
     173: putstatic     #33                 // Field CALLER_CLASS:Lch/qos/logback/classic/db/names/ColumnName;
     176: new           #4                  // class ch/qos/logback/classic/db/names/ColumnName
     179: dup
     180: ldc           #34                 // String CALLER_METHOD
     182: bipush        13
     184: invokespecial #8                  // Method "<init>":(Ljava/lang/String;I)V
     187: putstatic     #35                 // Field CALLER_METHOD:Lch/qos/logback/classic/db/names/ColumnName;
     190: new           #4                  // class ch/qos/logback/classic/db/names/ColumnName
     193: dup
     194: ldc           #36                 // String CALLER_LINE
     196: bipush        14
     198: invokespecial #8                  // Method "<init>":(Ljava/lang/String;I)V
     201: putstatic     #37                 // Field CALLER_LINE:Lch/qos/logback/classic/db/names/ColumnName;
     204: new           #4                  // class ch/qos/logback/classic/db/names/ColumnName
     207: dup
     208: ldc           #38                 // String MAPPED_KEY
     210: bipush        15
     212: invokespecial #8                  // Method "<init>":(Ljava/lang/String;I)V
     215: putstatic     #39                 // Field MAPPED_KEY:Lch/qos/logback/classic/db/names/ColumnName;
     218: new           #4                  // class ch/qos/logback/classic/db/names/ColumnName
     221: dup
     222: ldc           #40                 // String MAPPED_VALUE
     224: bipush        16
     226: invokespecial #8                  // Method "<init>":(Ljava/lang/String;I)V
     229: putstatic     #41                 // Field MAPPED_VALUE:Lch/qos/logback/classic/db/names/ColumnName;
     232: new           #4                  // class ch/qos/logback/classic/db/names/ColumnName
     235: dup
     236: ldc           #42                 // String I
     238: bipush        17
     240: invokespecial #8                  // Method "<init>":(Ljava/lang/String;I)V
     243: putstatic     #43                 // Field I:Lch/qos/logback/classic/db/names/ColumnName;
     246: new           #4                  // class ch/qos/logback/classic/db/names/ColumnName
     249: dup
     250: ldc           #44                 // String TRACE_LINE
     252: bipush        18
     254: invokespecial #8                  // Method "<init>":(Ljava/lang/String;I)V
     257: putstatic     #45                 // Field TRACE_LINE:Lch/qos/logback/classic/db/names/ColumnName;
     260: bipush        19
     262: anewarray     #4                  // class ch/qos/logback/classic/db/names/ColumnName
     265: dup
     266: iconst_0
     267: getstatic     #9                  // Field EVENT_ID:Lch/qos/logback/classic/db/names/ColumnName;
     270: aastore
     271: dup
     272: iconst_1
     273: getstatic     #11                 // Field TIMESTMP:Lch/qos/logback/classic/db/names/ColumnName;
     276: aastore
     277: dup
     278: iconst_2
     279: getstatic     #13                 // Field FORMATTED_MESSAGE:Lch/qos/logback/classic/db/names/ColumnName;
     282: aastore
     283: dup
     284: iconst_3
     285: getstatic     #15                 // Field LOGGER_NAME:Lch/qos/logback/classic/db/names/ColumnName;
     288: aastore
     289: dup
     290: iconst_4
     291: getstatic     #17                 // Field LEVEL_STRING:Lch/qos/logback/classic/db/names/ColumnName;
     294: aastore
     295: dup
     296: iconst_5
     297: getstatic     #19                 // Field THREAD_NAME:Lch/qos/logback/classic/db/names/ColumnName;
     300: aastore
     301: dup
     302: bipush        6
     304: getstatic     #21                 // Field REFERENCE_FLAG:Lch/qos/logback/classic/db/names/ColumnName;
     307: aastore
     308: dup
     309: bipush        7
     311: getstatic     #23                 // Field ARG0:Lch/qos/logback/classic/db/names/ColumnName;
     314: aastore
     315: dup
     316: bipush        8
     318: getstatic     #25                 // Field ARG1:Lch/qos/logback/classic/db/names/ColumnName;
     321: aastore
     322: dup
     323: bipush        9
     325: getstatic     #27                 // Field ARG2:Lch/qos/logback/classic/db/names/ColumnName;
     328: aastore
     329: dup
     330: bipush        10
     332: getstatic     #29                 // Field ARG3:Lch/qos/logback/classic/db/names/ColumnName;
     335: aastore
     336: dup
     337: bipush        11
     339: getstatic     #31                 // Field CALLER_FILENAME:Lch/qos/logback/classic/db/names/ColumnName;
     342: aastore
     343: dup
     344: bipush        12
     346: getstatic     #33                 // Field CALLER_CLASS:Lch/qos/logback/classic/db/names/ColumnName;
     349: aastore
     350: dup
     351: bipush        13
     353: getstatic     #35                 // Field CALLER_METHOD:Lch/qos/logback/classic/db/names/ColumnName;
     356: aastore
     357: dup
     358: bipush        14
     360: getstatic     #37                 // Field CALLER_LINE:Lch/qos/logback/classic/db/names/ColumnName;
     363: aastore
     364: dup
     365: bipush        15
     367: getstatic     #39                 // Field MAPPED_KEY:Lch/qos/logback/classic/db/names/ColumnName;
     370: aastore
     371: dup
     372: bipush        16
     374: getstatic     #41                 // Field MAPPED_VALUE:Lch/qos/logback/classic/db/names/ColumnName;
     377: aastore
     378: dup
     379: bipush        17
     381: getstatic     #43                 // Field I:Lch/qos/logback/classic/db/names/ColumnName;
     384: aastore
     385: dup
     386: bipush        18
     388: getstatic     #45                 // Field TRACE_LINE:Lch/qos/logback/classic/db/names/ColumnName;
     391: aastore
     392: putstatic     #1                  // Field $VALUES:[Lch/qos/logback/classic/db/names/ColumnName;
     395: return
}
