Compiled from "HttpRequestWrapper.java"
public class org.apache.http.client.methods.HttpRequestWrapper extends org.apache.http.message.AbstractHttpMessage implements org.apache.http.client.methods.HttpUriRequest {
  private final org.apache.http.HttpRequest original;

  private final org.apache.http.HttpHost target;

  private final java.lang.String method;

  private org.apache.http.RequestLine requestLine;

  private org.apache.http.ProtocolVersion version;

  private java.net.URI uri;

  private org.apache.http.client.methods.HttpRequestWrapper(org.apache.http.HttpRequest, org.apache.http.HttpHost);
    Code:
       0: aload_0
       1: invokespecial #2                  // Method org/apache/http/message/AbstractHttpMessage."<init>":()V
       4: aload_0
       5: aload_1
       6: ldc           #3                  // String HTTP request
       8: invokestatic  #4                  // Method org/apache/http/util/Args.notNull:(Ljava/lang/Object;Ljava/lang/String;)Ljava/lang/Object;
      11: checkcast     #5                  // class org/apache/http/HttpRequest
      14: putfield      #6                  // Field original:Lorg/apache/http/HttpRequest;
      17: aload_0
      18: aload_2
      19: putfield      #7                  // Field target:Lorg/apache/http/HttpHost;
      22: aload_0
      23: aload_0
      24: getfield      #6                  // Field original:Lorg/apache/http/HttpRequest;
      27: invokeinterface #8,  1            // InterfaceMethod org/apache/http/HttpRequest.getRequestLine:()Lorg/apache/http/RequestLine;
      32: invokeinterface #9,  1            // InterfaceMethod org/apache/http/RequestLine.getProtocolVersion:()Lorg/apache/http/ProtocolVersion;
      37: putfield      #10                 // Field version:Lorg/apache/http/ProtocolVersion;
      40: aload_0
      41: aload_0
      42: getfield      #6                  // Field original:Lorg/apache/http/HttpRequest;
      45: invokeinterface #8,  1            // InterfaceMethod org/apache/http/HttpRequest.getRequestLine:()Lorg/apache/http/RequestLine;
      50: invokeinterface #11,  1           // InterfaceMethod org/apache/http/RequestLine.getMethod:()Ljava/lang/String;
      55: putfield      #12                 // Field method:Ljava/lang/String;
      58: aload_1
      59: instanceof    #13                 // class org/apache/http/client/methods/HttpUriRequest
      62: ifeq          81
      65: aload_0
      66: aload_1
      67: checkcast     #13                 // class org/apache/http/client/methods/HttpUriRequest
      70: invokeinterface #14,  1           // InterfaceMethod org/apache/http/client/methods/HttpUriRequest.getURI:()Ljava/net/URI;
      75: putfield      #15                 // Field uri:Ljava/net/URI;
      78: goto          86
      81: aload_0
      82: aconst_null
      83: putfield      #15                 // Field uri:Ljava/net/URI;
      86: aload_0
      87: aload_1
      88: invokeinterface #16,  1           // InterfaceMethod org/apache/http/HttpRequest.getAllHeaders:()[Lorg/apache/http/Header;
      93: invokevirtual #17                 // Method setHeaders:([Lorg/apache/http/Header;)V
      96: return

  public org.apache.http.ProtocolVersion getProtocolVersion();
    Code:
       0: aload_0
       1: getfield      #10                 // Field version:Lorg/apache/http/ProtocolVersion;
       4: ifnull        14
       7: aload_0
       8: getfield      #10                 // Field version:Lorg/apache/http/ProtocolVersion;
      11: goto          23
      14: aload_0
      15: getfield      #6                  // Field original:Lorg/apache/http/HttpRequest;
      18: invokeinterface #18,  1           // InterfaceMethod org/apache/http/HttpRequest.getProtocolVersion:()Lorg/apache/http/ProtocolVersion;
      23: areturn

  public void setProtocolVersion(org.apache.http.ProtocolVersion);
    Code:
       0: aload_0
       1: aload_1
       2: putfield      #10                 // Field version:Lorg/apache/http/ProtocolVersion;
       5: aload_0
       6: aconst_null
       7: putfield      #19                 // Field requestLine:Lorg/apache/http/RequestLine;
      10: return

  public java.net.URI getURI();
    Code:
       0: aload_0
       1: getfield      #15                 // Field uri:Ljava/net/URI;
       4: areturn

  public void setURI(java.net.URI);
    Code:
       0: aload_0
       1: aload_1
       2: putfield      #15                 // Field uri:Ljava/net/URI;
       5: aload_0
       6: aconst_null
       7: putfield      #19                 // Field requestLine:Lorg/apache/http/RequestLine;
      10: return

  public java.lang.String getMethod();
    Code:
       0: aload_0
       1: getfield      #12                 // Field method:Ljava/lang/String;
       4: areturn

  public void abort() throws java.lang.UnsupportedOperationException;
    Code:
       0: new           #20                 // class java/lang/UnsupportedOperationException
       3: dup
       4: invokespecial #21                 // Method java/lang/UnsupportedOperationException."<init>":()V
       7: athrow

  public boolean isAborted();
    Code:
       0: iconst_0
       1: ireturn

  public org.apache.http.RequestLine getRequestLine();
    Code:
       0: aload_0
       1: getfield      #19                 // Field requestLine:Lorg/apache/http/RequestLine;
       4: ifnonnull     74
       7: aload_0
       8: getfield      #15                 // Field uri:Ljava/net/URI;
      11: ifnull        25
      14: aload_0
      15: getfield      #15                 // Field uri:Ljava/net/URI;
      18: invokevirtual #22                 // Method java/net/URI.toASCIIString:()Ljava/lang/String;
      21: astore_1
      22: goto          40
      25: aload_0
      26: getfield      #6                  // Field original:Lorg/apache/http/HttpRequest;
      29: invokeinterface #8,  1            // InterfaceMethod org/apache/http/HttpRequest.getRequestLine:()Lorg/apache/http/RequestLine;
      34: invokeinterface #23,  1           // InterfaceMethod org/apache/http/RequestLine.getUri:()Ljava/lang/String;
      39: astore_1
      40: aload_1
      41: ifnull        51
      44: aload_1
      45: invokevirtual #24                 // Method java/lang/String.isEmpty:()Z
      48: ifeq          54
      51: ldc           #25                 // String /
      53: astore_1
      54: aload_0
      55: new           #26                 // class org/apache/http/message/BasicRequestLine
      58: dup
      59: aload_0
      60: getfield      #12                 // Field method:Ljava/lang/String;
      63: aload_1
      64: aload_0
      65: invokevirtual #27                 // Method getProtocolVersion:()Lorg/apache/http/ProtocolVersion;
      68: invokespecial #28                 // Method org/apache/http/message/BasicRequestLine."<init>":(Ljava/lang/String;Ljava/lang/String;Lorg/apache/http/ProtocolVersion;)V
      71: putfield      #19                 // Field requestLine:Lorg/apache/http/RequestLine;
      74: aload_0
      75: getfield      #19                 // Field requestLine:Lorg/apache/http/RequestLine;
      78: areturn

  public org.apache.http.HttpRequest getOriginal();
    Code:
       0: aload_0
       1: getfield      #6                  // Field original:Lorg/apache/http/HttpRequest;
       4: areturn

  public org.apache.http.HttpHost getTarget();
    Code:
       0: aload_0
       1: getfield      #7                  // Field target:Lorg/apache/http/HttpHost;
       4: areturn

  public java.lang.String toString();
    Code:
       0: new           #29                 // class java/lang/StringBuilder
       3: dup
       4: invokespecial #30                 // Method java/lang/StringBuilder."<init>":()V
       7: aload_0
       8: invokevirtual #31                 // Method getRequestLine:()Lorg/apache/http/RequestLine;
      11: invokevirtual #32                 // Method java/lang/StringBuilder.append:(Ljava/lang/Object;)Ljava/lang/StringBuilder;
      14: ldc           #33                 // String
      16: invokevirtual #34                 // Method java/lang/StringBuilder.append:(Ljava/lang/String;)Ljava/lang/StringBuilder;
      19: aload_0
      20: getfield      #35                 // Field headergroup:Lorg/apache/http/message/HeaderGroup;
      23: invokevirtual #32                 // Method java/lang/StringBuilder.append:(Ljava/lang/Object;)Ljava/lang/StringBuilder;
      26: invokevirtual #36                 // Method java/lang/StringBuilder.toString:()Ljava/lang/String;
      29: areturn

  public static org.apache.http.client.methods.HttpRequestWrapper wrap(org.apache.http.HttpRequest);
    Code:
       0: aload_0
       1: aconst_null
       2: invokestatic  #37                 // Method wrap:(Lorg/apache/http/HttpRequest;Lorg/apache/http/HttpHost;)Lorg/apache/http/client/methods/HttpRequestWrapper;
       5: areturn

  public static org.apache.http.client.methods.HttpRequestWrapper wrap(org.apache.http.HttpRequest, org.apache.http.HttpHost);
    Code:
       0: aload_0
       1: ldc           #3                  // String HTTP request
       3: invokestatic  #4                  // Method org/apache/http/util/Args.notNull:(Ljava/lang/Object;Ljava/lang/String;)Ljava/lang/Object;
       6: pop
       7: aload_0
       8: instanceof    #38                 // class org/apache/http/HttpEntityEnclosingRequest
      11: ifeq          29
      14: new           #39                 // class org/apache/http/client/methods/HttpRequestWrapper$HttpEntityEnclosingRequestWrapper
      17: dup
      18: aload_0
      19: checkcast     #38                 // class org/apache/http/HttpEntityEnclosingRequest
      22: aload_1
      23: invokespecial #40                 // Method org/apache/http/client/methods/HttpRequestWrapper$HttpEntityEnclosingRequestWrapper."<init>":(Lorg/apache/http/HttpEntityEnclosingRequest;Lorg/apache/http/HttpHost;)V
      26: goto          38
      29: new           #41                 // class org/apache/http/client/methods/HttpRequestWrapper
      32: dup
      33: aload_0
      34: aload_1
      35: invokespecial #1                  // Method "<init>":(Lorg/apache/http/HttpRequest;Lorg/apache/http/HttpHost;)V
      38: areturn

  public org.apache.http.params.HttpParams getParams();
    Code:
       0: aload_0
       1: getfield      #42                 // Field params:Lorg/apache/http/params/HttpParams;
       4: ifnonnull     25
       7: aload_0
       8: aload_0
       9: getfield      #6                  // Field original:Lorg/apache/http/HttpRequest;
      12: invokeinterface #43,  1           // InterfaceMethod org/apache/http/HttpRequest.getParams:()Lorg/apache/http/params/HttpParams;
      17: invokeinterface #44,  1           // InterfaceMethod org/apache/http/params/HttpParams.copy:()Lorg/apache/http/params/HttpParams;
      22: putfield      #42                 // Field params:Lorg/apache/http/params/HttpParams;
      25: aload_0
      26: getfield      #42                 // Field params:Lorg/apache/http/params/HttpParams;
      29: areturn

  org.apache.http.client.methods.HttpRequestWrapper(org.apache.http.HttpRequest, org.apache.http.HttpHost, org.apache.http.client.methods.HttpRequestWrapper$1);
    Code:
       0: aload_0
       1: aload_1
       2: aload_2
       3: invokespecial #1                  // Method "<init>":(Lorg/apache/http/HttpRequest;Lorg/apache/http/HttpHost;)V
       6: return
}
