Compiled from "DefaultElementInfo.java"
public class org.codehaus.staxmate.in.DefaultElementInfo extends org.codehaus.staxmate.in.SMElementInfo {
  final org.codehaus.staxmate.in.SMElementInfo mParentElem;

  final org.codehaus.staxmate.in.SMElementInfo mPrevSiblingElem;

  final java.lang.String mNsURI;

  final java.lang.String mLocalName;

  final java.lang.String mPrefix;

  final int mNodeIndex;

  final int mElemIndex;

  final int mDepth;

  public org.codehaus.staxmate.in.DefaultElementInfo(org.codehaus.staxmate.in.SMElementInfo, org.codehaus.staxmate.in.SMElementInfo, java.lang.String, java.lang.String, java.lang.String, int, int, int) throws javax.xml.stream.XMLStreamException;
    Code:
       0: aload_0
       1: invokespecial #1                  // Method org/codehaus/staxmate/in/SMElementInfo."<init>":()V
       4: aload_0
       5: aload_1
       6: putfield      #2                  // Field mParentElem:Lorg/codehaus/staxmate/in/SMElementInfo;
       9: aload_0
      10: aload_2
      11: putfield      #3                  // Field mPrevSiblingElem:Lorg/codehaus/staxmate/in/SMElementInfo;
      14: aload_0
      15: aload_3
      16: putfield      #4                  // Field mPrefix:Ljava/lang/String;
      19: aload_0
      20: aload         4
      22: putfield      #5                  // Field mNsURI:Ljava/lang/String;
      25: aload_0
      26: aload         5
      28: putfield      #6                  // Field mLocalName:Ljava/lang/String;
      31: aload_0
      32: iload         6
      34: putfield      #7                  // Field mNodeIndex:I
      37: aload_0
      38: iload         7
      40: putfield      #8                  // Field mElemIndex:I
      43: aload_0
      44: iload         8
      46: putfield      #9                  // Field mDepth:I
      49: return

  public org.codehaus.staxmate.in.SMElementInfo getParent();
    Code:
       0: aload_0
       1: getfield      #2                  // Field mParentElem:Lorg/codehaus/staxmate/in/SMElementInfo;
       4: areturn

  public org.codehaus.staxmate.in.SMElementInfo getPreviousSibling();
    Code:
       0: aload_0
       1: getfield      #3                  // Field mPrevSiblingElem:Lorg/codehaus/staxmate/in/SMElementInfo;
       4: areturn

  public int getNodeIndex();
    Code:
       0: aload_0
       1: getfield      #7                  // Field mNodeIndex:I
       4: ireturn

  public int getElementIndex();
    Code:
       0: aload_0
       1: getfield      #8                  // Field mElemIndex:I
       4: ireturn

  public int getDepth();
    Code:
       0: aload_0
       1: getfield      #9                  // Field mDepth:I
       4: ireturn

  public java.lang.String getNamespaceURI();
    Code:
       0: aload_0
       1: getfield      #5                  // Field mNsURI:Ljava/lang/String;
       4: areturn

  public java.lang.String getLocalName();
    Code:
       0: aload_0
       1: getfield      #6                  // Field mLocalName:Ljava/lang/String;
       4: areturn

  public java.lang.String getPrefix();
    Code:
       0: aload_0
       1: getfield      #4                  // Field mPrefix:Ljava/lang/String;
       4: areturn
}
