Compiled from "SMFlatteningCursor.java"
public class org.codehaus.staxmate.in.SMFlatteningCursor extends org.codehaus.staxmate.in.SMInputCursor {
  public org.codehaus.staxmate.in.SMFlatteningCursor(org.codehaus.staxmate.in.SMInputContext, org.codehaus.staxmate.in.SMInputCursor, org.codehaus.staxmate.in.SMFilter);
    Code:
       0: aload_0
       1: aload_1
       2: aload_2
       3: aload_3
       4: invokespecial #1                  // Method org/codehaus/staxmate/in/SMInputCursor."<init>":(Lorg/codehaus/staxmate/in/SMInputContext;Lorg/codehaus/staxmate/in/SMInputCursor;Lorg/codehaus/staxmate/in/SMFilter;)V
       7: return

  public int getParentCount();
    Code:
       0: aload_0
       1: getfield      #2                  // Field _childCursor:Lorg/codehaus/staxmate/in/SMInputCursor;
       4: ifnull        15
       7: aload_0
       8: getfield      #2                  // Field _childCursor:Lorg/codehaus/staxmate/in/SMInputCursor;
      11: invokevirtual #3                  // Method org/codehaus/staxmate/in/SMInputCursor.getBaseParentCount:()I
      14: ireturn
      15: aload_0
      16: getfield      #4                  // Field _currEvent:Lorg/codehaus/staxmate/in/SMEvent;
      19: ifnonnull     27
      22: aload_0
      23: getfield      #5                  // Field _baseDepth:I
      26: ireturn
      27: aload_0
      28: getfield      #6                  // Field _streamReader:Lorg/codehaus/stax2/XMLStreamReader2;
      31: invokeinterface #7,  1            // InterfaceMethod org/codehaus/stax2/XMLStreamReader2.getDepth:()I
      36: istore_1
      37: aload_0
      38: getfield      #4                  // Field _currEvent:Lorg/codehaus/staxmate/in/SMEvent;
      41: getstatic     #8                  // Field org/codehaus/staxmate/in/SMEvent.START_ELEMENT:Lorg/codehaus/staxmate/in/SMEvent;
      44: if_acmpeq     57
      47: aload_0
      48: getfield      #4                  // Field _currEvent:Lorg/codehaus/staxmate/in/SMEvent;
      51: getstatic     #9                  // Field org/codehaus/staxmate/in/SMEvent.END_ELEMENT:Lorg/codehaus/staxmate/in/SMEvent;
      54: if_acmpne     60
      57: iinc          1, -1
      60: iload_1
      61: ireturn

  public org.codehaus.staxmate.in.SMEvent getNext() throws javax.xml.stream.XMLStreamException;
    Code:
       0: aload_0
       1: getfield      #10                 // Field _state:Lorg/codehaus/staxmate/in/CursorBase$State;
       4: getstatic     #11                 // Field org/codehaus/staxmate/in/CursorBase$State.CLOSED:Lorg/codehaus/staxmate/in/CursorBase$State;
       7: if_acmpne     12
      10: aconst_null
      11: areturn
      12: aload_0
      13: getfield      #10                 // Field _state:Lorg/codehaus/staxmate/in/CursorBase$State;
      16: getstatic     #12                 // Field org/codehaus/staxmate/in/CursorBase$State.HAS_CHILD:Lorg/codehaus/staxmate/in/CursorBase$State;
      19: if_acmpne     36
      22: aload_0
      23: invokevirtual #13                 // Method rewindPastChild:()V
      26: aload_0
      27: getstatic     #14                 // Field org/codehaus/staxmate/in/CursorBase$State.ACTIVE:Lorg/codehaus/staxmate/in/CursorBase$State;
      30: putfield      #10                 // Field _state:Lorg/codehaus/staxmate/in/CursorBase$State;
      33: goto          53
      36: aload_0
      37: getfield      #10                 // Field _state:Lorg/codehaus/staxmate/in/CursorBase$State;
      40: getstatic     #15                 // Field org/codehaus/staxmate/in/CursorBase$State.INITIAL:Lorg/codehaus/staxmate/in/CursorBase$State;
      43: if_acmpne     53
      46: aload_0
      47: getstatic     #14                 // Field org/codehaus/staxmate/in/CursorBase$State.ACTIVE:Lorg/codehaus/staxmate/in/CursorBase$State;
      50: putfield      #10                 // Field _state:Lorg/codehaus/staxmate/in/CursorBase$State;
      53: aload_0
      54: invokevirtual #16                 // Method isRootCursor:()Z
      57: ifeq          94
      60: aload_0
      61: getfield      #6                  // Field _streamReader:Lorg/codehaus/stax2/XMLStreamReader2;
      64: invokeinterface #17,  1           // InterfaceMethod org/codehaus/stax2/XMLStreamReader2.hasNext:()Z
      69: ifne          75
      72: goto          331
      75: aload_0
      76: getfield      #6                  // Field _streamReader:Lorg/codehaus/stax2/XMLStreamReader2;
      79: invokeinterface #18,  1           // InterfaceMethod org/codehaus/stax2/XMLStreamReader2.next:()I
      84: istore_1
      85: iload_1
      86: bipush        8
      88: if_icmpne     104
      91: goto          331
      94: aload_0
      95: getfield      #6                  // Field _streamReader:Lorg/codehaus/stax2/XMLStreamReader2;
      98: invokeinterface #18,  1           // InterfaceMethod org/codehaus/stax2/XMLStreamReader2.next:()I
     103: istore_1
     104: aload_0
     105: dup
     106: getfield      #19                 // Field _nodeCount:I
     109: iconst_1
     110: iadd
     111: putfield      #19                 // Field _nodeCount:I
     114: iload_1
     115: iconst_2
     116: if_icmpne     160
     119: aload_0
     120: getfield      #6                  // Field _streamReader:Lorg/codehaus/stax2/XMLStreamReader2;
     123: invokeinterface #7,  1            // InterfaceMethod org/codehaus/stax2/XMLStreamReader2.getDepth:()I
     128: istore_2
     129: iload_2
     130: aload_0
     131: getfield      #5                  // Field _baseDepth:I
     134: if_icmpgt     157
     137: iload_2
     138: aload_0
     139: getfield      #5                  // Field _baseDepth:I
     142: if_icmpeq     331
     145: aload_0
     146: aload_0
     147: getfield      #5                  // Field _baseDepth:I
     150: iload_2
     151: invokevirtual #20                 // Method _throwWrongEndElem:(II)V
     154: goto          331
     157: goto          219
     160: iload_1
     161: iconst_1
     162: if_icmpne     178
     165: aload_0
     166: dup
     167: getfield      #21                 // Field _elemCount:I
     170: iconst_1
     171: iadd
     172: putfield      #21                 // Field _elemCount:I
     175: goto          219
     178: iload_1
     179: bipush        8
     181: if_icmpne     219
     184: new           #22                 // class java/lang/IllegalStateException
     187: dup
     188: new           #23                 // class java/lang/StringBuilder
     191: dup
     192: invokespecial #24                 // Method java/lang/StringBuilder."<init>":()V
     195: ldc           #25                 // String Unexpected END_DOCUMENT encountered (root =
     197: invokevirtual #26                 // Method java/lang/StringBuilder.append:(Ljava/lang/String;)Ljava/lang/StringBuilder;
     200: aload_0
     201: invokevirtual #16                 // Method isRootCursor:()Z
     204: invokevirtual #27                 // Method java/lang/StringBuilder.append:(Z)Ljava/lang/StringBuilder;
     207: ldc           #28                 // String )
     209: invokevirtual #26                 // Method java/lang/StringBuilder.append:(Ljava/lang/String;)Ljava/lang/StringBuilder;
     212: invokevirtual #29                 // Method java/lang/StringBuilder.toString:()Ljava/lang/String;
     215: invokespecial #30                 // Method java/lang/IllegalStateException."<init>":(Ljava/lang/String;)V
     218: athrow
     219: iload_1
     220: invokestatic  #31                 // Method eventObjectByEventId:(I)Lorg/codehaus/staxmate/in/SMEvent;
     223: astore_2
     224: aload_0
     225: aload_2
     226: putfield      #4                  // Field _currEvent:Lorg/codehaus/staxmate/in/SMEvent;
     229: aload_0
     230: getfield      #32                 // Field mFilter:Lorg/codehaus/staxmate/in/SMFilter;
     233: ifnull        282
     236: aload_0
     237: getfield      #32                 // Field mFilter:Lorg/codehaus/staxmate/in/SMFilter;
     240: aload_2
     241: aload_0
     242: invokevirtual #33                 // Method org/codehaus/staxmate/in/SMFilter.accept:(Lorg/codehaus/staxmate/in/SMEvent;Lorg/codehaus/staxmate/in/SMInputCursor;)Z
     245: ifne          282
     248: iload_1
     249: iconst_1
     250: if_icmpne     53
     253: aload_0
     254: getfield      #34                 // Field mElemTracking:Lorg/codehaus/staxmate/in/SMInputCursor$Tracking;
     257: getstatic     #35                 // Field org/codehaus/staxmate/in/SMInputCursor$Tracking.ALL_SIBLINGS:Lorg/codehaus/staxmate/in/SMInputCursor$Tracking;
     260: if_acmpne     53
     263: aload_0
     264: aload_0
     265: aload_0
     266: getfield      #36                 // Field _parentTrackedElement:Lorg/codehaus/staxmate/in/SMElementInfo;
     269: aload_0
     270: getfield      #37                 // Field _trackedElement:Lorg/codehaus/staxmate/in/SMElementInfo;
     273: invokevirtual #38                 // Method constructElementInfo:(Lorg/codehaus/staxmate/in/SMElementInfo;Lorg/codehaus/staxmate/in/SMElementInfo;)Lorg/codehaus/staxmate/in/SMElementInfo;
     276: putfield      #37                 // Field _trackedElement:Lorg/codehaus/staxmate/in/SMElementInfo;
     279: goto          53
     282: iload_1
     283: iconst_1
     284: if_icmpne     329
     287: aload_0
     288: getfield      #34                 // Field mElemTracking:Lorg/codehaus/staxmate/in/SMInputCursor$Tracking;
     291: getstatic     #39                 // Field org/codehaus/staxmate/in/SMInputCursor$Tracking.NONE:Lorg/codehaus/staxmate/in/SMInputCursor$Tracking;
     294: if_acmpeq     329
     297: aload_0
     298: getfield      #34                 // Field mElemTracking:Lorg/codehaus/staxmate/in/SMInputCursor$Tracking;
     301: getstatic     #40                 // Field org/codehaus/staxmate/in/SMInputCursor$Tracking.PARENTS:Lorg/codehaus/staxmate/in/SMInputCursor$Tracking;
     304: if_acmpne     311
     307: aconst_null
     308: goto          315
     311: aload_0
     312: getfield      #37                 // Field _trackedElement:Lorg/codehaus/staxmate/in/SMElementInfo;
     315: astore_3
     316: aload_0
     317: aload_0
     318: aload_0
     319: getfield      #36                 // Field _parentTrackedElement:Lorg/codehaus/staxmate/in/SMElementInfo;
     322: aload_3
     323: invokevirtual #38                 // Method constructElementInfo:(Lorg/codehaus/staxmate/in/SMElementInfo;Lorg/codehaus/staxmate/in/SMElementInfo;)Lorg/codehaus/staxmate/in/SMElementInfo;
     326: putfield      #37                 // Field _trackedElement:Lorg/codehaus/staxmate/in/SMElementInfo;
     329: aload_2
     330: areturn
     331: aload_0
     332: getstatic     #11                 // Field org/codehaus/staxmate/in/CursorBase$State.CLOSED:Lorg/codehaus/staxmate/in/CursorBase$State;
     335: putfield      #10                 // Field _state:Lorg/codehaus/staxmate/in/CursorBase$State;
     338: aload_0
     339: aconst_null
     340: putfield      #4                  // Field _currEvent:Lorg/codehaus/staxmate/in/SMEvent;
     343: aconst_null
     344: areturn

  public org.codehaus.staxmate.in.SMInputCursor constructChildCursor(org.codehaus.staxmate.in.SMFilter);
    Code:
       0: new           #41                 // class org/codehaus/staxmate/in/SMHierarchicCursor
       3: dup
       4: aload_0
       5: getfield      #42                 // Field _context:Lorg/codehaus/staxmate/in/SMInputContext;
       8: aload_0
       9: aload_1
      10: invokespecial #43                 // Method org/codehaus/staxmate/in/SMHierarchicCursor."<init>":(Lorg/codehaus/staxmate/in/SMInputContext;Lorg/codehaus/staxmate/in/SMInputCursor;Lorg/codehaus/staxmate/in/SMFilter;)V
      13: areturn

  public org.codehaus.staxmate.in.SMInputCursor constructDescendantCursor(org.codehaus.staxmate.in.SMFilter);
    Code:
       0: new           #44                 // class org/codehaus/staxmate/in/SMFlatteningCursor
       3: dup
       4: aload_0
       5: getfield      #42                 // Field _context:Lorg/codehaus/staxmate/in/SMInputContext;
       8: aload_0
       9: aload_1
      10: invokespecial #45                 // Method "<init>":(Lorg/codehaus/staxmate/in/SMInputContext;Lorg/codehaus/staxmate/in/SMInputCursor;Lorg/codehaus/staxmate/in/SMFilter;)V
      13: areturn
}
