Compiled from "LocalJaxWsServiceFactory.java"
public class org.springframework.remoting.jaxws.LocalJaxWsServiceFactory {
  private java.net.URL wsdlDocumentUrl;

  private java.lang.String namespaceUri;

  private java.lang.String serviceName;

  private javax.xml.ws.WebServiceFeature[] serviceFeatures;

  private java.util.concurrent.Executor executor;

  private javax.xml.ws.handler.HandlerResolver handlerResolver;

  public org.springframework.remoting.jaxws.LocalJaxWsServiceFactory();
    Code:
       0: aload_0
       1: invokespecial #1                  // Method java/lang/Object."<init>":()V
       4: return

  public void setWsdlDocumentUrl(java.net.URL);
    Code:
       0: aload_0
       1: aload_1
       2: putfield      #2                  // Field wsdlDocumentUrl:Ljava/net/URL;
       5: return

  public void setWsdlDocumentResource(org.springframework.core.io.Resource) throws java.io.IOException;
    Code:
       0: aload_1
       1: ldc           #3                  // String WSDL Resource must not be null.
       3: invokestatic  #4                  // Method org/springframework/util/Assert.notNull:(Ljava/lang/Object;Ljava/lang/String;)V
       6: aload_0
       7: aload_1
       8: invokeinterface #5,  1            // InterfaceMethod org/springframework/core/io/Resource.getURL:()Ljava/net/URL;
      13: putfield      #2                  // Field wsdlDocumentUrl:Ljava/net/URL;
      16: return

  public java.net.URL getWsdlDocumentUrl();
    Code:
       0: aload_0
       1: getfield      #2                  // Field wsdlDocumentUrl:Ljava/net/URL;
       4: areturn

  public void setNamespaceUri(java.lang.String);
    Code:
       0: aload_0
       1: aload_1
       2: ifnull        12
       5: aload_1
       6: invokevirtual #6                  // Method java/lang/String.trim:()Ljava/lang/String;
       9: goto          13
      12: aconst_null
      13: putfield      #7                  // Field namespaceUri:Ljava/lang/String;
      16: return

  public java.lang.String getNamespaceUri();
    Code:
       0: aload_0
       1: getfield      #7                  // Field namespaceUri:Ljava/lang/String;
       4: areturn

  public void setServiceName(java.lang.String);
    Code:
       0: aload_0
       1: aload_1
       2: putfield      #8                  // Field serviceName:Ljava/lang/String;
       5: return

  public java.lang.String getServiceName();
    Code:
       0: aload_0
       1: getfield      #8                  // Field serviceName:Ljava/lang/String;
       4: areturn

  public void setServiceFeatures(javax.xml.ws.WebServiceFeature...);
    Code:
       0: aload_0
       1: aload_1
       2: putfield      #9                  // Field serviceFeatures:[Ljavax/xml/ws/WebServiceFeature;
       5: return

  public void setExecutor(java.util.concurrent.Executor);
    Code:
       0: aload_0
       1: aload_1
       2: putfield      #10                 // Field executor:Ljava/util/concurrent/Executor;
       5: return

  public void setHandlerResolver(javax.xml.ws.handler.HandlerResolver);
    Code:
       0: aload_0
       1: aload_1
       2: putfield      #11                 // Field handlerResolver:Ljavax/xml/ws/handler/HandlerResolver;
       5: return

  public javax.xml.ws.Service createJaxWsService();
    Code:
       0: aload_0
       1: getfield      #8                  // Field serviceName:Ljava/lang/String;
       4: ldc           #12                 // String No service name specified
       6: invokestatic  #4                  // Method org/springframework/util/Assert.notNull:(Ljava/lang/Object;Ljava/lang/String;)V
       9: aload_0
      10: getfield      #9                  // Field serviceFeatures:[Ljavax/xml/ws/WebServiceFeature;
      13: ifnull        64
      16: aload_0
      17: getfield      #2                  // Field wsdlDocumentUrl:Ljava/net/URL;
      20: ifnull        45
      23: aload_0
      24: getfield      #2                  // Field wsdlDocumentUrl:Ljava/net/URL;
      27: aload_0
      28: aload_0
      29: getfield      #8                  // Field serviceName:Ljava/lang/String;
      32: invokevirtual #13                 // Method getQName:(Ljava/lang/String;)Ljavax/xml/namespace/QName;
      35: aload_0
      36: getfield      #9                  // Field serviceFeatures:[Ljavax/xml/ws/WebServiceFeature;
      39: invokestatic  #14                 // Method javax/xml/ws/Service.create:(Ljava/net/URL;Ljavax/xml/namespace/QName;[Ljavax/xml/ws/WebServiceFeature;)Ljavax/xml/ws/Service;
      42: goto          60
      45: aload_0
      46: aload_0
      47: getfield      #8                  // Field serviceName:Ljava/lang/String;
      50: invokevirtual #13                 // Method getQName:(Ljava/lang/String;)Ljavax/xml/namespace/QName;
      53: aload_0
      54: getfield      #9                  // Field serviceFeatures:[Ljavax/xml/ws/WebServiceFeature;
      57: invokestatic  #15                 // Method javax/xml/ws/Service.create:(Ljavax/xml/namespace/QName;[Ljavax/xml/ws/WebServiceFeature;)Ljavax/xml/ws/Service;
      60: astore_1
      61: goto          101
      64: aload_0
      65: getfield      #2                  // Field wsdlDocumentUrl:Ljava/net/URL;
      68: ifnull        89
      71: aload_0
      72: getfield      #2                  // Field wsdlDocumentUrl:Ljava/net/URL;
      75: aload_0
      76: aload_0
      77: getfield      #8                  // Field serviceName:Ljava/lang/String;
      80: invokevirtual #13                 // Method getQName:(Ljava/lang/String;)Ljavax/xml/namespace/QName;
      83: invokestatic  #16                 // Method javax/xml/ws/Service.create:(Ljava/net/URL;Ljavax/xml/namespace/QName;)Ljavax/xml/ws/Service;
      86: goto          100
      89: aload_0
      90: aload_0
      91: getfield      #8                  // Field serviceName:Ljava/lang/String;
      94: invokevirtual #13                 // Method getQName:(Ljava/lang/String;)Ljavax/xml/namespace/QName;
      97: invokestatic  #17                 // Method javax/xml/ws/Service.create:(Ljavax/xml/namespace/QName;)Ljavax/xml/ws/Service;
     100: astore_1
     101: aload_0
     102: getfield      #10                 // Field executor:Ljava/util/concurrent/Executor;
     105: ifnull        116
     108: aload_1
     109: aload_0
     110: getfield      #10                 // Field executor:Ljava/util/concurrent/Executor;
     113: invokevirtual #18                 // Method javax/xml/ws/Service.setExecutor:(Ljava/util/concurrent/Executor;)V
     116: aload_0
     117: getfield      #11                 // Field handlerResolver:Ljavax/xml/ws/handler/HandlerResolver;
     120: ifnull        131
     123: aload_1
     124: aload_0
     125: getfield      #11                 // Field handlerResolver:Ljavax/xml/ws/handler/HandlerResolver;
     128: invokevirtual #19                 // Method javax/xml/ws/Service.setHandlerResolver:(Ljavax/xml/ws/handler/HandlerResolver;)V
     131: aload_1
     132: areturn

  protected javax.xml.namespace.QName getQName(java.lang.String);
    Code:
       0: aload_0
       1: invokevirtual #20                 // Method getNamespaceUri:()Ljava/lang/String;
       4: ifnull        22
       7: new           #21                 // class javax/xml/namespace/QName
      10: dup
      11: aload_0
      12: invokevirtual #20                 // Method getNamespaceUri:()Ljava/lang/String;
      15: aload_1
      16: invokespecial #22                 // Method javax/xml/namespace/QName."<init>":(Ljava/lang/String;Ljava/lang/String;)V
      19: goto          30
      22: new           #21                 // class javax/xml/namespace/QName
      25: dup
      26: aload_1
      27: invokespecial #23                 // Method javax/xml/namespace/QName."<init>":(Ljava/lang/String;)V
      30: areturn
}
