Compiled from "CamelEndpointLoader.java"
class org.apache.activemq.camel.component.CamelEndpointLoader$1 implements org.apache.activemq.advisory.DestinationListener {
  final org.apache.activemq.camel.component.CamelEndpointLoader this$0;

  org.apache.activemq.camel.component.CamelEndpointLoader$1(org.apache.activemq.camel.component.CamelEndpointLoader);
    Code:
       0: aload_0
       1: aload_1
       2: putfield      #1                  // Field this$0:Lorg/apache/activemq/camel/component/CamelEndpointLoader;
       5: aload_0
       6: invokespecial #2                  // Method java/lang/Object."<init>":()V
       9: return

  public void onDestinationEvent(org.apache.activemq.advisory.DestinationEvent);
    Code:
       0: aload_1
       1: invokevirtual #3                  // Method org/apache/activemq/advisory/DestinationEvent.getDestination:()Lorg/apache/activemq/command/ActiveMQDestination;
       4: astore_2
       5: aload_2
       6: instanceof    #4                  // class org/apache/activemq/command/ActiveMQQueue
       9: ifeq          46
      12: aload_2
      13: checkcast     #4                  // class org/apache/activemq/command/ActiveMQQueue
      16: astore_3
      17: aload_1
      18: invokevirtual #5                  // Method org/apache/activemq/advisory/DestinationEvent.isAddOperation:()Z
      21: ifeq          35
      24: aload_0
      25: getfield      #1                  // Field this$0:Lorg/apache/activemq/camel/component/CamelEndpointLoader;
      28: aload_3
      29: invokevirtual #6                  // Method org/apache/activemq/camel/component/CamelEndpointLoader.addQueue:(Lorg/apache/activemq/command/ActiveMQQueue;)V
      32: goto          43
      35: aload_0
      36: getfield      #1                  // Field this$0:Lorg/apache/activemq/camel/component/CamelEndpointLoader;
      39: aload_3
      40: invokevirtual #7                  // Method org/apache/activemq/camel/component/CamelEndpointLoader.removeQueue:(Lorg/apache/activemq/command/ActiveMQQueue;)V
      43: goto          84
      46: aload_2
      47: instanceof    #8                  // class org/apache/activemq/command/ActiveMQTopic
      50: ifeq          84
      53: aload_2
      54: checkcast     #8                  // class org/apache/activemq/command/ActiveMQTopic
      57: astore_3
      58: aload_1
      59: invokevirtual #5                  // Method org/apache/activemq/advisory/DestinationEvent.isAddOperation:()Z
      62: ifeq          76
      65: aload_0
      66: getfield      #1                  // Field this$0:Lorg/apache/activemq/camel/component/CamelEndpointLoader;
      69: aload_3
      70: invokevirtual #9                  // Method org/apache/activemq/camel/component/CamelEndpointLoader.addTopic:(Lorg/apache/activemq/command/ActiveMQTopic;)V
      73: goto          84
      76: aload_0
      77: getfield      #1                  // Field this$0:Lorg/apache/activemq/camel/component/CamelEndpointLoader;
      80: aload_3
      81: invokevirtual #10                 // Method org/apache/activemq/camel/component/CamelEndpointLoader.removeTopic:(Lorg/apache/activemq/command/ActiveMQTopic;)V
      84: goto          116
      87: astore_2
      88: invokestatic  #12                 // Method org/apache/activemq/camel/component/CamelEndpointLoader.access$000:()Lorg/slf4j/Logger;
      91: new           #13                 // class java/lang/StringBuilder
      94: dup
      95: invokespecial #14                 // Method java/lang/StringBuilder."<init>":()V
      98: ldc           #15                 // String Caught:
     100: invokevirtual #16                 // Method java/lang/StringBuilder.append:(Ljava/lang/String;)Ljava/lang/StringBuilder;
     103: aload_2
     104: invokevirtual #17                 // Method java/lang/StringBuilder.append:(Ljava/lang/Object;)Ljava/lang/StringBuilder;
     107: invokevirtual #18                 // Method java/lang/StringBuilder.toString:()Ljava/lang/String;
     110: aload_2
     111: invokeinterface #19,  3           // InterfaceMethod org/slf4j/Logger.warn:(Ljava/lang/String;Ljava/lang/Throwable;)V
     116: return
    Exception table:
       from    to  target type
           0    84    87   Class java/lang/Exception
}
