Compiled from "AbstractService.java"
final class org.apache.curator.shaded.com.google.common.util.concurrent.AbstractService$StateSnapshot {
  final org.apache.curator.shaded.com.google.common.util.concurrent.Service$State state;

  final boolean shutdownWhenStartupFinishes;

  final java.lang.Throwable failure;

  org.apache.curator.shaded.com.google.common.util.concurrent.AbstractService$StateSnapshot(org.apache.curator.shaded.com.google.common.util.concurrent.Service$State);
    Code:
       0: aload_0
       1: aload_1
       2: iconst_0
       3: aconst_null
       4: invokespecial #26                 // Method "<init>":(Lorg/apache/curator/shaded/com/google/common/util/concurrent/Service$State;ZLjava/lang/Throwable;)V
       7: return

  org.apache.curator.shaded.com.google.common.util.concurrent.AbstractService$StateSnapshot(org.apache.curator.shaded.com.google.common.util.concurrent.Service$State, boolean, java.lang.Throwable);
    Code:
       0: aload_0
       1: invokespecial #32                 // Method java/lang/Object."<init>":()V
       4: iload_2
       5: ifeq          15
       8: aload_1
       9: getstatic     #35                 // Field org/apache/curator/shaded/com/google/common/util/concurrent/Service$State.STARTING:Lorg/apache/curator/shaded/com/google/common/util/concurrent/Service$State;
      12: if_acmpne     19
      15: iconst_1
      16: goto          20
      19: iconst_0
      20: ldc           #39                 // String shudownWhenStartupFinishes can only be set if state is STARTING. Got %s instead.
      22: iconst_1
      23: anewarray     #4                  // class java/lang/Object
      26: dup
      27: iconst_0
      28: aload_1
      29: aastore
      30: invokestatic  #45                 // Method org/apache/curator/shaded/com/google/common/base/Preconditions.checkArgument:(ZLjava/lang/String;[Ljava/lang/Object;)V
      33: aload_3
      34: ifnull        41
      37: iconst_1
      38: goto          42
      41: iconst_0
      42: aload_1
      43: getstatic     #48                 // Field org/apache/curator/shaded/com/google/common/util/concurrent/Service$State.FAILED:Lorg/apache/curator/shaded/com/google/common/util/concurrent/Service$State;
      46: if_acmpne     53
      49: iconst_1
      50: goto          54
      53: iconst_0
      54: ixor
      55: ifne          62
      58: iconst_1
      59: goto          63
      62: iconst_0
      63: ldc           #50                 // String A failure cause should be set if and only if the state is failed.  Got %s and %s instead.
      65: iconst_2
      66: anewarray     #4                  // class java/lang/Object
      69: dup
      70: iconst_0
      71: aload_1
      72: aastore
      73: dup
      74: iconst_1
      75: aload_3
      76: aastore
      77: invokestatic  #45                 // Method org/apache/curator/shaded/com/google/common/base/Preconditions.checkArgument:(ZLjava/lang/String;[Ljava/lang/Object;)V
      80: aload_0
      81: aload_1
      82: putfield      #52                 // Field state:Lorg/apache/curator/shaded/com/google/common/util/concurrent/Service$State;
      85: aload_0
      86: iload_2
      87: putfield      #54                 // Field shutdownWhenStartupFinishes:Z
      90: aload_0
      91: aload_3
      92: putfield      #56                 // Field failure:Ljava/lang/Throwable;
      95: return

  org.apache.curator.shaded.com.google.common.util.concurrent.Service$State externalState();
    Code:
       0: aload_0
       1: getfield      #54                 // Field shutdownWhenStartupFinishes:Z
       4: ifeq          21
       7: aload_0
       8: getfield      #52                 // Field state:Lorg/apache/curator/shaded/com/google/common/util/concurrent/Service$State;
      11: getstatic     #35                 // Field org/apache/curator/shaded/com/google/common/util/concurrent/Service$State.STARTING:Lorg/apache/curator/shaded/com/google/common/util/concurrent/Service$State;
      14: if_acmpne     21
      17: getstatic     #61                 // Field org/apache/curator/shaded/com/google/common/util/concurrent/Service$State.STOPPING:Lorg/apache/curator/shaded/com/google/common/util/concurrent/Service$State;
      20: areturn
      21: aload_0
      22: getfield      #52                 // Field state:Lorg/apache/curator/shaded/com/google/common/util/concurrent/Service$State;
      25: areturn

  java.lang.Throwable failureCause();
    Code:
       0: aload_0
       1: getfield      #52                 // Field state:Lorg/apache/curator/shaded/com/google/common/util/concurrent/Service$State;
       4: getstatic     #48                 // Field org/apache/curator/shaded/com/google/common/util/concurrent/Service$State.FAILED:Lorg/apache/curator/shaded/com/google/common/util/concurrent/Service$State;
       7: if_acmpne     14
      10: iconst_1
      11: goto          15
      14: iconst_0
      15: ldc           #65                 // String failureCause() is only valid if the service has failed, service is %s
      17: iconst_1
      18: anewarray     #4                  // class java/lang/Object
      21: dup
      22: iconst_0
      23: aload_0
      24: getfield      #52                 // Field state:Lorg/apache/curator/shaded/com/google/common/util/concurrent/Service$State;
      27: aastore
      28: invokestatic  #68                 // Method org/apache/curator/shaded/com/google/common/base/Preconditions.checkState:(ZLjava/lang/String;[Ljava/lang/Object;)V
      31: aload_0
      32: getfield      #56                 // Field failure:Ljava/lang/Throwable;
      35: areturn
}
