Compiled from "Futures.java"
class org.apache.curator.shaded.com.google.common.util.concurrent.Futures$FallbackFuture<V> extends org.apache.curator.shaded.com.google.common.util.concurrent.AbstractFuture<V> {
  private volatile org.apache.curator.shaded.com.google.common.util.concurrent.ListenableFuture<? extends V> running;

  org.apache.curator.shaded.com.google.common.util.concurrent.Futures$FallbackFuture(org.apache.curator.shaded.com.google.common.util.concurrent.ListenableFuture<? extends V>, org.apache.curator.shaded.com.google.common.util.concurrent.FutureFallback<? extends V>, java.util.concurrent.Executor);
    Code:
       0: aload_0
       1: invokespecial #19                 // Method org/apache/curator/shaded/com/google/common/util/concurrent/AbstractFuture."<init>":()V
       4: aload_0
       5: aload_1
       6: putfield      #21                 // Field running:Lorg/apache/curator/shaded/com/google/common/util/concurrent/ListenableFuture;
       9: aload_0
      10: getfield      #21                 // Field running:Lorg/apache/curator/shaded/com/google/common/util/concurrent/ListenableFuture;
      13: new           #11                 // class org/apache/curator/shaded/com/google/common/util/concurrent/Futures$FallbackFuture$1
      16: dup
      17: aload_0
      18: aload_2
      19: invokespecial #24                 // Method org/apache/curator/shaded/com/google/common/util/concurrent/Futures$FallbackFuture$1."<init>":(Lorg/apache/curator/shaded/com/google/common/util/concurrent/Futures$FallbackFuture;Lorg/apache/curator/shaded/com/google/common/util/concurrent/FutureFallback;)V
      22: aload_3
      23: invokestatic  #28                 // Method org/apache/curator/shaded/com/google/common/util/concurrent/Futures.addCallback:(Lorg/apache/curator/shaded/com/google/common/util/concurrent/ListenableFuture;Lorg/apache/curator/shaded/com/google/common/util/concurrent/FutureCallback;Ljava/util/concurrent/Executor;)V
      26: return

  public boolean cancel(boolean);
    Code:
       0: aload_0
       1: iload_1
       2: invokespecial #41                 // Method org/apache/curator/shaded/com/google/common/util/concurrent/AbstractFuture.cancel:(Z)Z
       5: ifeq          21
       8: aload_0
       9: getfield      #21                 // Field running:Lorg/apache/curator/shaded/com/google/common/util/concurrent/ListenableFuture;
      12: iload_1
      13: invokeinterface #44,  2           // InterfaceMethod org/apache/curator/shaded/com/google/common/util/concurrent/ListenableFuture.cancel:(Z)Z
      18: pop
      19: iconst_1
      20: ireturn
      21: iconst_0
      22: ireturn

  static org.apache.curator.shaded.com.google.common.util.concurrent.ListenableFuture access$102(org.apache.curator.shaded.com.google.common.util.concurrent.Futures$FallbackFuture, org.apache.curator.shaded.com.google.common.util.concurrent.ListenableFuture);
    Code:
       0: aload_0
       1: aload_1
       2: dup_x1
       3: putfield      #21                 // Field running:Lorg/apache/curator/shaded/com/google/common/util/concurrent/ListenableFuture;
       6: areturn

  static org.apache.curator.shaded.com.google.common.util.concurrent.ListenableFuture access$100(org.apache.curator.shaded.com.google.common.util.concurrent.Futures$FallbackFuture);
    Code:
       0: aload_0
       1: getfield      #21                 // Field running:Lorg/apache/curator/shaded/com/google/common/util/concurrent/ListenableFuture;
       4: areturn
}
