Compiled from "ServiceManager.java"
class org.apache.curator.shaded.com.google.common.util.concurrent.ServiceManager$ServiceManagerState$7 implements java.lang.Runnable {
  final org.apache.curator.shaded.com.google.common.util.concurrent.ServiceManager$ListenerExecutorPair val$pair;

  final org.apache.curator.shaded.com.google.common.util.concurrent.Service val$service;

  final org.apache.curator.shaded.com.google.common.util.concurrent.ServiceManager$ServiceManagerState this$0;

  org.apache.curator.shaded.com.google.common.util.concurrent.ServiceManager$ServiceManagerState$7(org.apache.curator.shaded.com.google.common.util.concurrent.ServiceManager$ServiceManagerState, org.apache.curator.shaded.com.google.common.util.concurrent.ServiceManager$ListenerExecutorPair, org.apache.curator.shaded.com.google.common.util.concurrent.Service);
    Code:
       0: aload_0
       1: aload_1
       2: putfield      #31                 // Field this$0:Lorg/apache/curator/shaded/com/google/common/util/concurrent/ServiceManager$ServiceManagerState;
       5: aload_0
       6: aload_2
       7: putfield      #33                 // Field val$pair:Lorg/apache/curator/shaded/com/google/common/util/concurrent/ServiceManager$ListenerExecutorPair;
      10: aload_0
      11: aload_3
      12: putfield      #35                 // Field val$service:Lorg/apache/curator/shaded/com/google/common/util/concurrent/Service;
      15: aload_0
      16: invokespecial #38                 // Method java/lang/Object."<init>":()V
      19: return

  public void run();
    Code:
       0: aload_0
       1: getfield      #33                 // Field val$pair:Lorg/apache/curator/shaded/com/google/common/util/concurrent/ServiceManager$ListenerExecutorPair;
       4: getfield      #45                 // Field org/apache/curator/shaded/com/google/common/util/concurrent/ServiceManager$ListenerExecutorPair.listener:Lorg/apache/curator/shaded/com/google/common/util/concurrent/ServiceManager$Listener;
       7: aload_0
       8: getfield      #35                 // Field val$service:Lorg/apache/curator/shaded/com/google/common/util/concurrent/Service;
      11: invokevirtual #48                 // Method org/apache/curator/shaded/com/google/common/util/concurrent/ServiceManager$Listener.failure:(Lorg/apache/curator/shaded/com/google/common/util/concurrent/Service;)V
      14: return
}
