Compiled from "AllDefaultPossibilitiesBuilder.java"
public class org.junit.internal.builders.AllDefaultPossibilitiesBuilder extends org.junit.runners.model.RunnerBuilder {
  private final boolean canUseSuiteMethod;

  public org.junit.internal.builders.AllDefaultPossibilitiesBuilder();
    Code:
       0: aload_0
       1: invokespecial #1                  // Method org/junit/runners/model/RunnerBuilder."<init>":()V
       4: aload_0
       5: iconst_1
       6: putfield      #2                  // Field canUseSuiteMethod:Z
       9: return

  public org.junit.internal.builders.AllDefaultPossibilitiesBuilder(boolean);
    Code:
       0: aload_0
       1: invokespecial #1                  // Method org/junit/runners/model/RunnerBuilder."<init>":()V
       4: aload_0
       5: iload_1
       6: putfield      #2                  // Field canUseSuiteMethod:Z
       9: return

  public org.junit.runner.Runner runnerForClass(java.lang.Class<?>) throws java.lang.Throwable;
    Code:
       0: iconst_5
       1: anewarray     #3                  // class org/junit/runners/model/RunnerBuilder
       4: dup
       5: iconst_0
       6: aload_0
       7: invokevirtual #4                  // Method ignoredBuilder:()Lorg/junit/internal/builders/IgnoredBuilder;
      10: aastore
      11: dup
      12: iconst_1
      13: aload_0
      14: invokevirtual #5                  // Method annotatedBuilder:()Lorg/junit/internal/builders/AnnotatedBuilder;
      17: aastore
      18: dup
      19: iconst_2
      20: aload_0
      21: invokevirtual #6                  // Method suiteMethodBuilder:()Lorg/junit/runners/model/RunnerBuilder;
      24: aastore
      25: dup
      26: iconst_3
      27: aload_0
      28: invokevirtual #7                  // Method junit3Builder:()Lorg/junit/internal/builders/JUnit3Builder;
      31: aastore
      32: dup
      33: iconst_4
      34: aload_0
      35: invokevirtual #8                  // Method junit4Builder:()Lorg/junit/internal/builders/JUnit4Builder;
      38: aastore
      39: invokestatic  #9                  // Method java/util/Arrays.asList:([Ljava/lang/Object;)Ljava/util/List;
      42: astore_2
      43: aload_2
      44: invokeinterface #10,  1           // InterfaceMethod java/util/List.iterator:()Ljava/util/Iterator;
      49: astore_3
      50: aload_3
      51: invokeinterface #11,  1           // InterfaceMethod java/util/Iterator.hasNext:()Z
      56: ifeq          89
      59: aload_3
      60: invokeinterface #12,  1           // InterfaceMethod java/util/Iterator.next:()Ljava/lang/Object;
      65: checkcast     #3                  // class org/junit/runners/model/RunnerBuilder
      68: astore        4
      70: aload         4
      72: aload_1
      73: invokevirtual #13                 // Method org/junit/runners/model/RunnerBuilder.safeRunnerForClass:(Ljava/lang/Class;)Lorg/junit/runner/Runner;
      76: astore        5
      78: aload         5
      80: ifnull        86
      83: aload         5
      85: areturn
      86: goto          50
      89: aconst_null
      90: areturn

  protected org.junit.internal.builders.JUnit4Builder junit4Builder();
    Code:
       0: new           #14                 // class org/junit/internal/builders/JUnit4Builder
       3: dup
       4: invokespecial #15                 // Method org/junit/internal/builders/JUnit4Builder."<init>":()V
       7: areturn

  protected org.junit.internal.builders.JUnit3Builder junit3Builder();
    Code:
       0: new           #16                 // class org/junit/internal/builders/JUnit3Builder
       3: dup
       4: invokespecial #17                 // Method org/junit/internal/builders/JUnit3Builder."<init>":()V
       7: areturn

  protected org.junit.internal.builders.AnnotatedBuilder annotatedBuilder();
    Code:
       0: new           #18                 // class org/junit/internal/builders/AnnotatedBuilder
       3: dup
       4: aload_0
       5: invokespecial #19                 // Method org/junit/internal/builders/AnnotatedBuilder."<init>":(Lorg/junit/runners/model/RunnerBuilder;)V
       8: areturn

  protected org.junit.internal.builders.IgnoredBuilder ignoredBuilder();
    Code:
       0: new           #20                 // class org/junit/internal/builders/IgnoredBuilder
       3: dup
       4: invokespecial #21                 // Method org/junit/internal/builders/IgnoredBuilder."<init>":()V
       7: areturn

  protected org.junit.runners.model.RunnerBuilder suiteMethodBuilder();
    Code:
       0: aload_0
       1: getfield      #2                  // Field canUseSuiteMethod:Z
       4: ifeq          15
       7: new           #22                 // class org/junit/internal/builders/SuiteMethodBuilder
      10: dup
      11: invokespecial #23                 // Method org/junit/internal/builders/SuiteMethodBuilder."<init>":()V
      14: areturn
      15: new           #24                 // class org/junit/internal/builders/NullBuilder
      18: dup
      19: invokespecial #25                 // Method org/junit/internal/builders/NullBuilder."<init>":()V
      22: areturn
}
