Compiled from "CamelConverter.java"
final class org.apache.camel.converter.CamelConverter$1 implements org.apache.camel.Processor {
  final org.apache.camel.Predicate val$predicate;

  org.apache.camel.converter.CamelConverter$1(org.apache.camel.Predicate);
    Code:
       0: aload_0
       1: aload_1
       2: putfield      #18                 // Field val$predicate:Lorg/apache/camel/Predicate;
       5: aload_0
       6: invokespecial #21                 // Method java/lang/Object."<init>":()V
       9: return

  public void process(org.apache.camel.Exchange) throws java.lang.Exception;
    Code:
       0: aload_0
       1: getfield      #18                 // Field val$predicate:Lorg/apache/camel/Predicate;
       4: aload_1
       5: invokeinterface #33,  2           // InterfaceMethod org/apache/camel/Predicate.matches:(Lorg/apache/camel/Exchange;)Z
      10: istore_2
      11: aload_1
      12: invokeinterface #39,  1           // InterfaceMethod org/apache/camel/Exchange.getOut:()Lorg/apache/camel/Message;
      17: astore_3
      18: aload_3
      19: aload_1
      20: invokeinterface #42,  1           // InterfaceMethod org/apache/camel/Exchange.getIn:()Lorg/apache/camel/Message;
      25: invokeinterface #48,  2           // InterfaceMethod org/apache/camel/Message.copyFrom:(Lorg/apache/camel/Message;)V
      30: aload_3
      31: iload_2
      32: invokestatic  #54                 // Method java/lang/Boolean.valueOf:(Z)Ljava/lang/Boolean;
      35: invokeinterface #58,  2           // InterfaceMethod org/apache/camel/Message.setBody:(Ljava/lang/Object;)V
      40: return
}
