Compiled from "TypeEnvironmentFactory.java"
class org.hibernate.annotations.common.reflection.java.generics.TypeEnvironmentFactory$1 extends org.hibernate.annotations.common.reflection.java.generics.TypeSwitch<org.hibernate.annotations.common.reflection.java.generics.TypeEnvironment> {
  final org.hibernate.annotations.common.reflection.java.generics.TypeEnvironmentFactory this$0;

  org.hibernate.annotations.common.reflection.java.generics.TypeEnvironmentFactory$1(org.hibernate.annotations.common.reflection.java.generics.TypeEnvironmentFactory);
    Code:
       0: aload_0
       1: aload_1
       2: putfield      #1                  // Field this$0:Lorg/hibernate/annotations/common/reflection/java/generics/TypeEnvironmentFactory;
       5: aload_0
       6: invokespecial #2                  // Method org/hibernate/annotations/common/reflection/java/generics/TypeSwitch."<init>":()V
       9: return

  public org.hibernate.annotations.common.reflection.java.generics.TypeEnvironment caseClass(java.lang.Class);
    Code:
       0: aload_0
       1: getfield      #1                  // Field this$0:Lorg/hibernate/annotations/common/reflection/java/generics/TypeEnvironmentFactory;
       4: aload_1
       5: invokestatic  #3                  // Method org/hibernate/annotations/common/reflection/java/generics/TypeEnvironmentFactory.access$000:(Lorg/hibernate/annotations/common/reflection/java/generics/TypeEnvironmentFactory;Ljava/lang/Class;)Lorg/hibernate/annotations/common/reflection/java/generics/TypeEnvironment;
       8: aload_0
       9: getfield      #1                  // Field this$0:Lorg/hibernate/annotations/common/reflection/java/generics/TypeEnvironmentFactory;
      12: aload_1
      13: invokevirtual #4                  // Method java/lang/Class.getSuperclass:()Ljava/lang/Class;
      16: invokevirtual #5                  // Method org/hibernate/annotations/common/reflection/java/generics/TypeEnvironmentFactory.getEnvironment:(Ljava/lang/Class;)Lorg/hibernate/annotations/common/reflection/java/generics/TypeEnvironment;
      19: invokestatic  #6                  // Method org/hibernate/annotations/common/reflection/java/generics/CompoundTypeEnvironment.create:(Lorg/hibernate/annotations/common/reflection/java/generics/TypeEnvironment;Lorg/hibernate/annotations/common/reflection/java/generics/TypeEnvironment;)Lorg/hibernate/annotations/common/reflection/java/generics/TypeEnvironment;
      22: areturn

  public org.hibernate.annotations.common.reflection.java.generics.TypeEnvironment caseParameterizedType(java.lang.reflect.ParameterizedType);
    Code:
       0: aload_0
       1: getfield      #1                  // Field this$0:Lorg/hibernate/annotations/common/reflection/java/generics/TypeEnvironmentFactory;
       4: aload_1
       5: invokestatic  #7                  // Method org/hibernate/annotations/common/reflection/java/generics/TypeEnvironmentFactory.access$100:(Lorg/hibernate/annotations/common/reflection/java/generics/TypeEnvironmentFactory;Ljava/lang/reflect/ParameterizedType;)Lorg/hibernate/annotations/common/reflection/java/generics/TypeEnvironment;
       8: areturn

  public org.hibernate.annotations.common.reflection.java.generics.TypeEnvironment defaultCase(java.lang.reflect.Type);
    Code:
       0: new           #8                  // class java/lang/IllegalArgumentException
       3: dup
       4: new           #9                  // class java/lang/StringBuilder
       7: dup
       8: invokespecial #10                 // Method java/lang/StringBuilder."<init>":()V
      11: ldc           #11                 // String Invalid type for generating environment:
      13: invokevirtual #12                 // Method java/lang/StringBuilder.append:(Ljava/lang/String;)Ljava/lang/StringBuilder;
      16: aload_1
      17: invokevirtual #13                 // Method java/lang/StringBuilder.append:(Ljava/lang/Object;)Ljava/lang/StringBuilder;
      20: invokevirtual #14                 // Method java/lang/StringBuilder.toString:()Ljava/lang/String;
      23: invokespecial #15                 // Method java/lang/IllegalArgumentException."<init>":(Ljava/lang/String;)V
      26: athrow

  public java.lang.Object defaultCase(java.lang.reflect.Type);
    Code:
       0: aload_0
       1: aload_1
       2: invokevirtual #16                 // Method defaultCase:(Ljava/lang/reflect/Type;)Lorg/hibernate/annotations/common/reflection/java/generics/TypeEnvironment;
       5: areturn

  public java.lang.Object caseParameterizedType(java.lang.reflect.ParameterizedType);
    Code:
       0: aload_0
       1: aload_1
       2: invokevirtual #17                 // Method caseParameterizedType:(Ljava/lang/reflect/ParameterizedType;)Lorg/hibernate/annotations/common/reflection/java/generics/TypeEnvironment;
       5: areturn

  public java.lang.Object caseClass(java.lang.Class);
    Code:
       0: aload_0
       1: aload_1
       2: invokevirtual #18                 // Method caseClass:(Ljava/lang/Class;)Lorg/hibernate/annotations/common/reflection/java/generics/TypeEnvironment;
       5: areturn
}
