Compiled from "BioApiErrorConstant.java"
public final class io.mosip.kernel.core.bioapi.constant.BioApiErrorConstant extends java.lang.Enum<io.mosip.kernel.core.bioapi.constant.BioApiErrorConstant> {
  public static final io.mosip.kernel.core.bioapi.constant.BioApiErrorConstant INVALID_INPUT_PARAMETER;

  public static final io.mosip.kernel.core.bioapi.constant.BioApiErrorConstant MISSING_INPUT_PARAMETER;

  public static final io.mosip.kernel.core.bioapi.constant.BioApiErrorConstant QUALITY_CHECK_FAILED;

  public static final io.mosip.kernel.core.bioapi.constant.BioApiErrorConstant MATCHING_FAILED;

  public static final io.mosip.kernel.core.bioapi.constant.BioApiErrorConstant UNKNOWN_ERROR;

  private final java.lang.String errorCode;

  private final java.lang.String message;

  private static final io.mosip.kernel.core.bioapi.constant.BioApiErrorConstant[] $VALUES;

  public static io.mosip.kernel.core.bioapi.constant.BioApiErrorConstant[] values();
    Code:
       0: getstatic     #1                  // Field $VALUES:[Lio/mosip/kernel/core/bioapi/constant/BioApiErrorConstant;
       3: invokevirtual #2                  // Method "[Lio/mosip/kernel/core/bioapi/constant/BioApiErrorConstant;".clone:()Ljava/lang/Object;
       6: checkcast     #3                  // class "[Lio/mosip/kernel/core/bioapi/constant/BioApiErrorConstant;"
       9: areturn

  public static io.mosip.kernel.core.bioapi.constant.BioApiErrorConstant valueOf(java.lang.String);
    Code:
       0: ldc           #4                  // class io/mosip/kernel/core/bioapi/constant/BioApiErrorConstant
       2: aload_0
       3: invokestatic  #5                  // Method java/lang/Enum.valueOf:(Ljava/lang/Class;Ljava/lang/String;)Ljava/lang/Enum;
       6: checkcast     #4                  // class io/mosip/kernel/core/bioapi/constant/BioApiErrorConstant
       9: areturn

  private io.mosip.kernel.core.bioapi.constant.BioApiErrorConstant(java.lang.String, java.lang.String);
    Code:
       0: aload_0
       1: aload_1
       2: iload_2
       3: invokespecial #6                  // Method java/lang/Enum."<init>":(Ljava/lang/String;I)V
       6: aload_0
       7: aload_3
       8: putfield      #7                  // Field errorCode:Ljava/lang/String;
      11: aload_0
      12: aload         4
      14: putfield      #8                  // Field message:Ljava/lang/String;
      17: return

  public java.lang.String getErrorCode();
    Code:
       0: aload_0
       1: getfield      #7                  // Field errorCode:Ljava/lang/String;
       4: areturn

  public java.lang.String getMessage();
    Code:
       0: aload_0
       1: getfield      #8                  // Field message:Ljava/lang/String;
       4: areturn

  static {};
    Code:
       0: new           #4                  // class io/mosip/kernel/core/bioapi/constant/BioApiErrorConstant
       3: dup
       4: ldc           #9                  // String INVALID_INPUT_PARAMETER
       6: iconst_0
       7: ldc           #10                 // String KER-BIO-001
       9: ldc           #11                 // String Invalid Input Parameter - %s
      11: invokespecial #12                 // Method "<init>":(Ljava/lang/String;ILjava/lang/String;Ljava/lang/String;)V
      14: putstatic     #13                 // Field INVALID_INPUT_PARAMETER:Lio/mosip/kernel/core/bioapi/constant/BioApiErrorConstant;
      17: new           #4                  // class io/mosip/kernel/core/bioapi/constant/BioApiErrorConstant
      20: dup
      21: ldc           #14                 // String MISSING_INPUT_PARAMETER
      23: iconst_1
      24: ldc           #15                 // String KER-BIO-002
      26: ldc           #16                 // String Missing Input Parameter - %s
      28: invokespecial #12                 // Method "<init>":(Ljava/lang/String;ILjava/lang/String;Ljava/lang/String;)V
      31: putstatic     #17                 // Field MISSING_INPUT_PARAMETER:Lio/mosip/kernel/core/bioapi/constant/BioApiErrorConstant;
      34: new           #4                  // class io/mosip/kernel/core/bioapi/constant/BioApiErrorConstant
      37: dup
      38: ldc           #18                 // String QUALITY_CHECK_FAILED
      40: iconst_2
      41: ldc           #19                 // String KER-BIO-003
      43: ldc           #20                 // String Quality check of Biometric data failed
      45: invokespecial #12                 // Method "<init>":(Ljava/lang/String;ILjava/lang/String;Ljava/lang/String;)V
      48: putstatic     #21                 // Field QUALITY_CHECK_FAILED:Lio/mosip/kernel/core/bioapi/constant/BioApiErrorConstant;
      51: new           #4                  // class io/mosip/kernel/core/bioapi/constant/BioApiErrorConstant
      54: dup
      55: ldc           #22                 // String MATCHING_FAILED
      57: iconst_3
      58: ldc           #23                 // String KER-BIO-004
      60: ldc           #24                 // String Matching of Biometric data failed
      62: invokespecial #12                 // Method "<init>":(Ljava/lang/String;ILjava/lang/String;Ljava/lang/String;)V
      65: putstatic     #25                 // Field MATCHING_FAILED:Lio/mosip/kernel/core/bioapi/constant/BioApiErrorConstant;
      68: new           #4                  // class io/mosip/kernel/core/bioapi/constant/BioApiErrorConstant
      71: dup
      72: ldc           #26                 // String UNKNOWN_ERROR
      74: iconst_4
      75: ldc           #27                 // String KER-BIO-005
      77: ldc           #28                 // String Unknown error occurred
      79: invokespecial #12                 // Method "<init>":(Ljava/lang/String;ILjava/lang/String;Ljava/lang/String;)V
      82: putstatic     #29                 // Field UNKNOWN_ERROR:Lio/mosip/kernel/core/bioapi/constant/BioApiErrorConstant;
      85: iconst_5
      86: anewarray     #4                  // class io/mosip/kernel/core/bioapi/constant/BioApiErrorConstant
      89: dup
      90: iconst_0
      91: getstatic     #13                 // Field INVALID_INPUT_PARAMETER:Lio/mosip/kernel/core/bioapi/constant/BioApiErrorConstant;
      94: aastore
      95: dup
      96: iconst_1
      97: getstatic     #17                 // Field MISSING_INPUT_PARAMETER:Lio/mosip/kernel/core/bioapi/constant/BioApiErrorConstant;
     100: aastore
     101: dup
     102: iconst_2
     103: getstatic     #21                 // Field QUALITY_CHECK_FAILED:Lio/mosip/kernel/core/bioapi/constant/BioApiErrorConstant;
     106: aastore
     107: dup
     108: iconst_3
     109: getstatic     #25                 // Field MATCHING_FAILED:Lio/mosip/kernel/core/bioapi/constant/BioApiErrorConstant;
     112: aastore
     113: dup
     114: iconst_4
     115: getstatic     #29                 // Field UNKNOWN_ERROR:Lio/mosip/kernel/core/bioapi/constant/BioApiErrorConstant;
     118: aastore
     119: putstatic     #1                  // Field $VALUES:[Lio/mosip/kernel/core/bioapi/constant/BioApiErrorConstant;
     122: return
}
