Compiled from "GwtRpcClientSerializer.java"
public abstract class org.atmosphere.gwt20.client.GwtRpcClientSerializer implements org.atmosphere.gwt20.client.ClientSerializer {
  private static final java.util.logging.Logger logger;

  private java.lang.StringBuffer buffer;

  public org.atmosphere.gwt20.client.GwtRpcClientSerializer();
    Code:
       0: aload_0
       1: invokespecial #1                  // Method java/lang/Object."<init>":()V
       4: aload_0
       5: new           #2                  // class java/lang/StringBuffer
       8: dup
       9: sipush        16100
      12: invokespecial #3                  // Method java/lang/StringBuffer."<init>":(I)V
      15: putfield      #4                  // Field buffer:Ljava/lang/StringBuffer;
      18: return

  public java.lang.Object deserialize(java.lang.String) throws com.google.gwt.user.client.rpc.SerializationException;
    Code:
       0: new           #5                  // class java/util/ArrayList
       3: dup
       4: invokespecial #6                  // Method java/util/ArrayList."<init>":()V
       7: astore_2
       8: aload_2
       9: aload_1
      10: invokeinterface #7,  2            // InterfaceMethod java/util/List.add:(Ljava/lang/Object;)Z
      15: pop
      16: new           #5                  // class java/util/ArrayList
      19: dup
      20: aload_2
      21: invokeinterface #8,  1            // InterfaceMethod java/util/List.size:()I
      26: invokespecial #9                  // Method java/util/ArrayList."<init>":(I)V
      29: astore_3
      30: aload_2
      31: invokeinterface #10,  1           // InterfaceMethod java/util/List.iterator:()Ljava/util/Iterator;
      36: astore        4
      38: aload         4
      40: invokeinterface #11,  1           // InterfaceMethod java/util/Iterator.hasNext:()Z
      45: ifeq          114
      48: aload         4
      50: invokeinterface #12,  1           // InterfaceMethod java/util/Iterator.next:()Ljava/lang/Object;
      55: checkcast     #13                 // class java/lang/String
      58: astore        5
      60: aload_0
      61: invokevirtual #14                 // Method getRPCSerializer:()Lcom/google/gwt/user/client/rpc/impl/Serializer;
      64: astore        6
      66: new           #15                 // class com/google/gwt/user/client/rpc/impl/ClientSerializationStreamReader
      69: dup
      70: aload         6
      72: invokespecial #16                 // Method com/google/gwt/user/client/rpc/impl/ClientSerializationStreamReader."<init>":(Lcom/google/gwt/user/client/rpc/impl/Serializer;)V
      75: astore        7
      77: aload         7
      79: aload         5
      81: invokevirtual #17                 // Method com/google/gwt/user/client/rpc/impl/ClientSerializationStreamReader.prepareToRead:(Ljava/lang/String;)V
      84: aload_3
      85: aload         7
      87: invokevirtual #18                 // Method com/google/gwt/user/client/rpc/impl/ClientSerializationStreamReader.readObject:()Ljava/lang/Object;
      90: invokeinterface #7,  2            // InterfaceMethod java/util/List.add:(Ljava/lang/Object;)Z
      95: pop
      96: goto          111
      99: astore        6
     101: new           #20                 // class com/google/gwt/user/client/rpc/SerializationException
     104: dup
     105: aload         6
     107: invokespecial #21                 // Method com/google/gwt/user/client/rpc/SerializationException."<init>":(Ljava/lang/Throwable;)V
     110: athrow
     111: goto          38
     114: aload_3
     115: areturn
    Exception table:
       from    to  target type
          60    96    99   Class java/lang/RuntimeException

  public java.lang.String serialize(java.lang.Object) throws com.google.gwt.user.client.rpc.SerializationException;
    Code:
       0: aload_0
       1: invokevirtual #14                 // Method getRPCSerializer:()Lcom/google/gwt/user/client/rpc/impl/Serializer;
       4: astore_2
       5: new           #22                 // class com/google/gwt/user/client/rpc/impl/ClientSerializationStreamWriter
       8: dup
       9: aload_2
      10: invokestatic  #23                 // Method com/google/gwt/core/client/GWT.getModuleBaseURL:()Ljava/lang/String;
      13: invokestatic  #24                 // Method com/google/gwt/core/client/GWT.getPermutationStrongName:()Ljava/lang/String;
      16: invokespecial #25                 // Method com/google/gwt/user/client/rpc/impl/ClientSerializationStreamWriter."<init>":(Lcom/google/gwt/user/client/rpc/impl/Serializer;Ljava/lang/String;Ljava/lang/String;)V
      19: astore_3
      20: aload_3
      21: invokevirtual #26                 // Method com/google/gwt/user/client/rpc/impl/ClientSerializationStreamWriter.prepareToWrite:()V
      24: aload_3
      25: aload_1
      26: invokevirtual #27                 // Method com/google/gwt/user/client/rpc/impl/ClientSerializationStreamWriter.writeObject:(Ljava/lang/Object;)V
      29: aload_3
      30: invokevirtual #28                 // Method com/google/gwt/user/client/rpc/impl/ClientSerializationStreamWriter.toString:()Ljava/lang/String;
      33: areturn
      34: astore_2
      35: new           #20                 // class com/google/gwt/user/client/rpc/SerializationException
      38: dup
      39: aload_2
      40: invokespecial #21                 // Method com/google/gwt/user/client/rpc/SerializationException."<init>":(Ljava/lang/Throwable;)V
      43: athrow
    Exception table:
       from    to  target type
           0    33    34   Class java/lang/RuntimeException

  protected abstract com.google.gwt.user.client.rpc.impl.Serializer getRPCSerializer();

  static {};
    Code:
       0: ldc           #29                 // class org/atmosphere/gwt20/client/GwtRpcClientSerializer
       2: invokevirtual #30                 // Method java/lang/Class.getName:()Ljava/lang/String;
       5: invokestatic  #31                 // Method java/util/logging/Logger.getLogger:(Ljava/lang/String;)Ljava/util/logging/Logger;
       8: putstatic     #32                 // Field logger:Ljava/util/logging/Logger;
      11: return
}
