Compiled from "ShutdownFallbackExecutor.java"
final class io.undertow.server.protocol.framed.ShutdownFallbackExecutor$ShutdownFallbackThreadFactory implements java.util.concurrent.ThreadFactory {
  private final java.util.concurrent.atomic.AtomicLong count;

  private final java.util.concurrent.ThreadFactory threadFactory;

  io.undertow.server.protocol.framed.ShutdownFallbackExecutor$ShutdownFallbackThreadFactory();
    Code:
       0: aload_0
       1: invokespecial #1                  // Method java/lang/Object."<init>":()V
       4: aload_0
       5: new           #2                  // class java/util/concurrent/atomic/AtomicLong
       8: dup
       9: invokespecial #3                  // Method java/util/concurrent/atomic/AtomicLong."<init>":()V
      12: putfield      #4                  // Field count:Ljava/util/concurrent/atomic/AtomicLong;
      15: aload_0
      16: invokestatic  #5                  // Method java/util/concurrent/Executors.defaultThreadFactory:()Ljava/util/concurrent/ThreadFactory;
      19: putfield      #6                  // Field threadFactory:Ljava/util/concurrent/ThreadFactory;
      22: return

  public java.lang.Thread newThread(java.lang.Runnable);
    Code:
       0: aload_0
       1: getfield      #6                  // Field threadFactory:Ljava/util/concurrent/ThreadFactory;
       4: aload_1
       5: invokeinterface #7,  2            // InterfaceMethod java/util/concurrent/ThreadFactory.newThread:(Ljava/lang/Runnable;)Ljava/lang/Thread;
      10: astore_2
      11: aload_2
      12: aload_0
      13: getfield      #4                  // Field count:Ljava/util/concurrent/atomic/AtomicLong;
      16: invokevirtual #8                  // Method java/util/concurrent/atomic/AtomicLong.getAndIncrement:()J
      19: invokedynamic #9,  0              // InvokeDynamic #0:makeConcatWithConstants:(J)Ljava/lang/String;
      24: invokevirtual #10                 // Method java/lang/Thread.setName:(Ljava/lang/String;)V
      27: aload_2
      28: iconst_1
      29: invokevirtual #11                 // Method java/lang/Thread.setDaemon:(Z)V
      32: aload_2
      33: areturn
}
