Compiled from "EspExceptionWrapper.java"
public class org.hpccsystems.ws.client.wrappers.gen.wssmc.EspExceptionWrapper {
  protected java.lang.String local_code;

  protected java.lang.String local_audience;

  protected java.lang.String local_source;

  protected java.lang.String local_message;

  public org.hpccsystems.ws.client.wrappers.gen.wssmc.EspExceptionWrapper();
    Code:
       0: aload_0
       1: invokespecial #1                  // Method java/lang/Object."<init>":()V
       4: return

  public org.hpccsystems.ws.client.wrappers.gen.wssmc.EspExceptionWrapper(org.hpccsystems.ws.client.gen.axis2.wssmc.v1_23.EspException);
    Code:
       0: aload_0
       1: invokespecial #1                  // Method java/lang/Object."<init>":()V
       4: aload_0
       5: aload_1
       6: invokespecial #2                  // Method copy:(Lorg/hpccsystems/ws/client/gen/axis2/wssmc/v1_23/EspException;)V
       9: return

  public org.hpccsystems.ws.client.wrappers.gen.wssmc.EspExceptionWrapper(java.lang.String, java.lang.String, java.lang.String, java.lang.String);
    Code:
       0: aload_0
       1: invokespecial #1                  // Method java/lang/Object."<init>":()V
       4: aload_0
       5: aload_1
       6: putfield      #3                  // Field local_code:Ljava/lang/String;
       9: aload_0
      10: aload_2
      11: putfield      #4                  // Field local_audience:Ljava/lang/String;
      14: aload_0
      15: aload_3
      16: putfield      #5                  // Field local_source:Ljava/lang/String;
      19: aload_0
      20: aload         4
      22: putfield      #6                  // Field local_message:Ljava/lang/String;
      25: return

  private void copy(org.hpccsystems.ws.client.gen.axis2.wssmc.v1_23.EspException);
    Code:
       0: aload_1
       1: ifnonnull     5
       4: return
       5: aload_0
       6: aload_1
       7: invokevirtual #7                  // Method org/hpccsystems/ws/client/gen/axis2/wssmc/v1_23/EspException.getCode:()Ljava/lang/String;
      10: putfield      #3                  // Field local_code:Ljava/lang/String;
      13: aload_0
      14: aload_1
      15: invokevirtual #8                  // Method org/hpccsystems/ws/client/gen/axis2/wssmc/v1_23/EspException.getAudience:()Ljava/lang/String;
      18: putfield      #4                  // Field local_audience:Ljava/lang/String;
      21: aload_0
      22: aload_1
      23: invokevirtual #9                  // Method org/hpccsystems/ws/client/gen/axis2/wssmc/v1_23/EspException.getSource:()Ljava/lang/String;
      26: putfield      #5                  // Field local_source:Ljava/lang/String;
      29: aload_0
      30: aload_1
      31: invokevirtual #10                 // Method org/hpccsystems/ws/client/gen/axis2/wssmc/v1_23/EspException.getMessage:()Ljava/lang/String;
      34: putfield      #6                  // Field local_message:Ljava/lang/String;
      37: return

  public java.lang.String toString();
    Code:
       0: new           #11                 // class java/lang/StringBuilder
       3: dup
       4: invokespecial #12                 // Method java/lang/StringBuilder."<init>":()V
       7: ldc           #13                 // String EspExceptionWrapper [code =
       9: invokevirtual #14                 // Method java/lang/StringBuilder.append:(Ljava/lang/String;)Ljava/lang/StringBuilder;
      12: aload_0
      13: getfield      #3                  // Field local_code:Ljava/lang/String;
      16: invokevirtual #14                 // Method java/lang/StringBuilder.append:(Ljava/lang/String;)Ljava/lang/StringBuilder;
      19: ldc           #15                 // String , audience =
      21: invokevirtual #14                 // Method java/lang/StringBuilder.append:(Ljava/lang/String;)Ljava/lang/StringBuilder;
      24: aload_0
      25: getfield      #4                  // Field local_audience:Ljava/lang/String;
      28: invokevirtual #14                 // Method java/lang/StringBuilder.append:(Ljava/lang/String;)Ljava/lang/StringBuilder;
      31: ldc           #16                 // String , source =
      33: invokevirtual #14                 // Method java/lang/StringBuilder.append:(Ljava/lang/String;)Ljava/lang/StringBuilder;
      36: aload_0
      37: getfield      #5                  // Field local_source:Ljava/lang/String;
      40: invokevirtual #14                 // Method java/lang/StringBuilder.append:(Ljava/lang/String;)Ljava/lang/StringBuilder;
      43: ldc           #17                 // String , message =
      45: invokevirtual #14                 // Method java/lang/StringBuilder.append:(Ljava/lang/String;)Ljava/lang/StringBuilder;
      48: aload_0
      49: getfield      #6                  // Field local_message:Ljava/lang/String;
      52: invokevirtual #14                 // Method java/lang/StringBuilder.append:(Ljava/lang/String;)Ljava/lang/StringBuilder;
      55: ldc           #18                 // String ]
      57: invokevirtual #14                 // Method java/lang/StringBuilder.append:(Ljava/lang/String;)Ljava/lang/StringBuilder;
      60: invokevirtual #19                 // Method java/lang/StringBuilder.toString:()Ljava/lang/String;
      63: areturn

  public org.hpccsystems.ws.client.gen.axis2.wssmc.v1_23.EspException getRaw();
    Code:
       0: new           #20                 // class org/hpccsystems/ws/client/gen/axis2/wssmc/v1_23/EspException
       3: dup
       4: invokespecial #21                 // Method org/hpccsystems/ws/client/gen/axis2/wssmc/v1_23/EspException."<init>":()V
       7: astore_1
       8: aload_1
       9: aload_0
      10: getfield      #3                  // Field local_code:Ljava/lang/String;
      13: invokevirtual #22                 // Method org/hpccsystems/ws/client/gen/axis2/wssmc/v1_23/EspException.setCode:(Ljava/lang/String;)V
      16: aload_1
      17: aload_0
      18: getfield      #4                  // Field local_audience:Ljava/lang/String;
      21: invokevirtual #23                 // Method org/hpccsystems/ws/client/gen/axis2/wssmc/v1_23/EspException.setAudience:(Ljava/lang/String;)V
      24: aload_1
      25: aload_0
      26: getfield      #5                  // Field local_source:Ljava/lang/String;
      29: invokevirtual #24                 // Method org/hpccsystems/ws/client/gen/axis2/wssmc/v1_23/EspException.setSource:(Ljava/lang/String;)V
      32: aload_1
      33: aload_0
      34: getfield      #6                  // Field local_message:Ljava/lang/String;
      37: invokevirtual #25                 // Method org/hpccsystems/ws/client/gen/axis2/wssmc/v1_23/EspException.setMessage:(Ljava/lang/String;)V
      40: aload_1
      41: areturn

  public void setCode(java.lang.String);
    Code:
       0: aload_0
       1: aload_1
       2: putfield      #3                  // Field local_code:Ljava/lang/String;
       5: return

  public java.lang.String getCode();
    Code:
       0: aload_0
       1: getfield      #3                  // Field local_code:Ljava/lang/String;
       4: areturn

  public void setAudience(java.lang.String);
    Code:
       0: aload_0
       1: aload_1
       2: putfield      #4                  // Field local_audience:Ljava/lang/String;
       5: return

  public java.lang.String getAudience();
    Code:
       0: aload_0
       1: getfield      #4                  // Field local_audience:Ljava/lang/String;
       4: areturn

  public void setSource(java.lang.String);
    Code:
       0: aload_0
       1: aload_1
       2: putfield      #5                  // Field local_source:Ljava/lang/String;
       5: return

  public java.lang.String getSource();
    Code:
       0: aload_0
       1: getfield      #5                  // Field local_source:Ljava/lang/String;
       4: areturn

  public void setMessage(java.lang.String);
    Code:
       0: aload_0
       1: aload_1
       2: putfield      #6                  // Field local_message:Ljava/lang/String;
       5: return

  public java.lang.String getMessage();
    Code:
       0: aload_0
       1: getfield      #6                  // Field local_message:Ljava/lang/String;
       4: areturn
}
