Compiled from "SMCJobWrapper.java"
public class org.hpccsystems.ws.client.wrappers.gen.wssmc.SMCJobWrapper {
  protected java.lang.String local_wuid;

  protected java.lang.String local_queueName;

  public org.hpccsystems.ws.client.wrappers.gen.wssmc.SMCJobWrapper();
    Code:
       0: aload_0
       1: invokespecial #1                  // Method java/lang/Object."<init>":()V
       4: return

  public org.hpccsystems.ws.client.wrappers.gen.wssmc.SMCJobWrapper(org.hpccsystems.ws.client.gen.axis2.wssmc.v1_23.SMCJob);
    Code:
       0: aload_0
       1: invokespecial #1                  // Method java/lang/Object."<init>":()V
       4: aload_0
       5: aload_1
       6: invokespecial #2                  // Method copy:(Lorg/hpccsystems/ws/client/gen/axis2/wssmc/v1_23/SMCJob;)V
       9: return

  public org.hpccsystems.ws.client.wrappers.gen.wssmc.SMCJobWrapper(java.lang.String, java.lang.String);
    Code:
       0: aload_0
       1: invokespecial #1                  // Method java/lang/Object."<init>":()V
       4: aload_0
       5: aload_1
       6: putfield      #3                  // Field local_wuid:Ljava/lang/String;
       9: aload_0
      10: aload_2
      11: putfield      #4                  // Field local_queueName:Ljava/lang/String;
      14: return

  private void copy(org.hpccsystems.ws.client.gen.axis2.wssmc.v1_23.SMCJob);
    Code:
       0: aload_1
       1: ifnonnull     5
       4: return
       5: aload_0
       6: aload_1
       7: invokevirtual #5                  // Method org/hpccsystems/ws/client/gen/axis2/wssmc/v1_23/SMCJob.getWuid:()Ljava/lang/String;
      10: putfield      #3                  // Field local_wuid:Ljava/lang/String;
      13: aload_0
      14: aload_1
      15: invokevirtual #6                  // Method org/hpccsystems/ws/client/gen/axis2/wssmc/v1_23/SMCJob.getQueueName:()Ljava/lang/String;
      18: putfield      #4                  // Field local_queueName:Ljava/lang/String;
      21: return

  public java.lang.String toString();
    Code:
       0: new           #7                  // class java/lang/StringBuilder
       3: dup
       4: invokespecial #8                  // Method java/lang/StringBuilder."<init>":()V
       7: ldc           #9                  // String SMCJobWrapper [wuid =
       9: invokevirtual #10                 // Method java/lang/StringBuilder.append:(Ljava/lang/String;)Ljava/lang/StringBuilder;
      12: aload_0
      13: getfield      #3                  // Field local_wuid:Ljava/lang/String;
      16: invokevirtual #10                 // Method java/lang/StringBuilder.append:(Ljava/lang/String;)Ljava/lang/StringBuilder;
      19: ldc           #11                 // String , queueName =
      21: invokevirtual #10                 // Method java/lang/StringBuilder.append:(Ljava/lang/String;)Ljava/lang/StringBuilder;
      24: aload_0
      25: getfield      #4                  // Field local_queueName:Ljava/lang/String;
      28: invokevirtual #10                 // Method java/lang/StringBuilder.append:(Ljava/lang/String;)Ljava/lang/StringBuilder;
      31: ldc           #12                 // String ]
      33: invokevirtual #10                 // Method java/lang/StringBuilder.append:(Ljava/lang/String;)Ljava/lang/StringBuilder;
      36: invokevirtual #13                 // Method java/lang/StringBuilder.toString:()Ljava/lang/String;
      39: areturn

  public org.hpccsystems.ws.client.gen.axis2.wssmc.v1_23.SMCJob getRaw();
    Code:
       0: new           #14                 // class org/hpccsystems/ws/client/gen/axis2/wssmc/v1_23/SMCJob
       3: dup
       4: invokespecial #15                 // Method org/hpccsystems/ws/client/gen/axis2/wssmc/v1_23/SMCJob."<init>":()V
       7: astore_1
       8: aload_1
       9: aload_0
      10: getfield      #3                  // Field local_wuid:Ljava/lang/String;
      13: invokevirtual #16                 // Method org/hpccsystems/ws/client/gen/axis2/wssmc/v1_23/SMCJob.setWuid:(Ljava/lang/String;)V
      16: aload_1
      17: aload_0
      18: getfield      #4                  // Field local_queueName:Ljava/lang/String;
      21: invokevirtual #17                 // Method org/hpccsystems/ws/client/gen/axis2/wssmc/v1_23/SMCJob.setQueueName:(Ljava/lang/String;)V
      24: aload_1
      25: areturn

  public void setWuid(java.lang.String);
    Code:
       0: aload_0
       1: aload_1
       2: putfield      #3                  // Field local_wuid:Ljava/lang/String;
       5: return

  public java.lang.String getWuid();
    Code:
       0: aload_0
       1: getfield      #3                  // Field local_wuid:Ljava/lang/String;
       4: areturn

  public void setQueueName(java.lang.String);
    Code:
       0: aload_0
       1: aload_1
       2: putfield      #4                  // Field local_queueName:Ljava/lang/String;
       5: return

  public java.lang.String getQueueName();
    Code:
       0: aload_0
       1: getfield      #4                  // Field local_queueName:Ljava/lang/String;
       4: areturn
}
