Compiled from "StatefulSessionComponent.java"
class org.jboss.as.ejb3.component.stateful.StatefulSessionComponent$1 implements java.security.PrivilegedAction<javax.ejb.EJBObject> {
  final org.jboss.as.ee.component.ComponentView val$view;

  final java.lang.String val$locatorAppName;

  final org.jboss.invocation.InterceptorContext val$ctx;

  final org.jboss.as.ejb3.component.stateful.StatefulSessionComponent this$0;

  org.jboss.as.ejb3.component.stateful.StatefulSessionComponent$1(org.jboss.as.ejb3.component.stateful.StatefulSessionComponent, org.jboss.as.ee.component.ComponentView, java.lang.String, org.jboss.invocation.InterceptorContext);
    Code:
       0: aload_0
       1: aload_1
       2: putfield      #1                  // Field this$0:Lorg/jboss/as/ejb3/component/stateful/StatefulSessionComponent;
       5: aload_0
       6: aload_2
       7: putfield      #2                  // Field val$view:Lorg/jboss/as/ee/component/ComponentView;
      10: aload_0
      11: aload_3
      12: putfield      #3                  // Field val$locatorAppName:Ljava/lang/String;
      15: aload_0
      16: aload         4
      18: putfield      #4                  // Field val$ctx:Lorg/jboss/invocation/InterceptorContext;
      21: aload_0
      22: invokespecial #5                  // Method java/lang/Object."<init>":()V
      25: return

  public javax.ejb.EJBObject run();
    Code:
       0: new           #6                  // class org/jboss/ejb/client/StatefulEJBLocator
       3: dup
       4: aload_0
       5: getfield      #2                  // Field val$view:Lorg/jboss/as/ee/component/ComponentView;
       8: invokeinterface #7,  1            // InterfaceMethod org/jboss/as/ee/component/ComponentView.getViewClass:()Ljava/lang/Class;
      13: aload_0
      14: getfield      #3                  // Field val$locatorAppName:Ljava/lang/String;
      17: aload_0
      18: getfield      #1                  // Field this$0:Lorg/jboss/as/ejb3/component/stateful/StatefulSessionComponent;
      21: invokevirtual #8                  // Method org/jboss/as/ejb3/component/stateful/StatefulSessionComponent.getModuleName:()Ljava/lang/String;
      24: aload_0
      25: getfield      #1                  // Field this$0:Lorg/jboss/as/ejb3/component/stateful/StatefulSessionComponent;
      28: invokevirtual #9                  // Method org/jboss/as/ejb3/component/stateful/StatefulSessionComponent.getComponentName:()Ljava/lang/String;
      31: aload_0
      32: getfield      #1                  // Field this$0:Lorg/jboss/as/ejb3/component/stateful/StatefulSessionComponent;
      35: invokevirtual #10                 // Method org/jboss/as/ejb3/component/stateful/StatefulSessionComponent.getDistinctName:()Ljava/lang/String;
      38: aload_0
      39: getfield      #1                  // Field this$0:Lorg/jboss/as/ejb3/component/stateful/StatefulSessionComponent;
      42: aload_0
      43: getfield      #4                  // Field val$ctx:Lorg/jboss/invocation/InterceptorContext;
      46: invokevirtual #11                 // Method org/jboss/as/ejb3/component/stateful/StatefulSessionComponent.getSessionIdOf:(Lorg/jboss/invocation/InterceptorContext;)Lorg/jboss/ejb/client/SessionID;
      49: aload_0
      50: getfield      #1                  // Field this$0:Lorg/jboss/as/ejb3/component/stateful/StatefulSessionComponent;
      53: invokevirtual #12                 // Method org/jboss/as/ejb3/component/stateful/StatefulSessionComponent.getCache:()Lorg/jboss/as/ejb3/cache/Cache;
      56: invokeinterface #13,  1           // InterfaceMethod org/jboss/as/ejb3/cache/Cache.getStrictAffinity:()Lorg/jboss/ejb/client/Affinity;
      61: ldc           #15                 // String jboss.node.name
      63: aconst_null
      64: invokestatic  #16                 // Method org/wildfly/security/manager/WildFlySecurityManager.getPropertyPrivileged:(Ljava/lang/String;Ljava/lang/String;)Ljava/lang/String;
      67: invokespecial #17                 // Method org/jboss/ejb/client/StatefulEJBLocator."<init>":(Ljava/lang/Class;Ljava/lang/String;Ljava/lang/String;Ljava/lang/String;Ljava/lang/String;Lorg/jboss/ejb/client/SessionID;Lorg/jboss/ejb/client/Affinity;Ljava/lang/String;)V
      70: invokestatic  #18                 // Method org/jboss/ejb/client/EJBClient.createProxy:(Lorg/jboss/ejb/client/EJBLocator;)Ljava/lang/Object;
      73: checkcast     #19                 // class javax/ejb/EJBObject
      76: areturn

  public java.lang.Object run();
    Code:
       0: aload_0
       1: invokevirtual #20                 // Method run:()Ljavax/ejb/EJBObject;
       4: areturn
}
