Compiled from "CreateClusterRequest.java"
public interface software.amazon.awssdk.services.eks.model.CreateClusterRequest$Builder extends software.amazon.awssdk.services.eks.model.EksRequest$Builder, software.amazon.awssdk.core.SdkPojo, software.amazon.awssdk.utils.builder.CopyableBuilder<software.amazon.awssdk.services.eks.model.CreateClusterRequest$Builder, software.amazon.awssdk.services.eks.model.CreateClusterRequest> {
  public abstract software.amazon.awssdk.services.eks.model.CreateClusterRequest$Builder name(java.lang.String);

  public abstract software.amazon.awssdk.services.eks.model.CreateClusterRequest$Builder version(java.lang.String);

  public abstract software.amazon.awssdk.services.eks.model.CreateClusterRequest$Builder roleArn(java.lang.String);

  public abstract software.amazon.awssdk.services.eks.model.CreateClusterRequest$Builder resourcesVpcConfig(software.amazon.awssdk.services.eks.model.VpcConfigRequest);

  public default software.amazon.awssdk.services.eks.model.CreateClusterRequest$Builder resourcesVpcConfig(java.util.function.Consumer<software.amazon.awssdk.services.eks.model.VpcConfigRequest$Builder>);
    Code:
       0: aload_0
       1: invokestatic  #1                  // Method software/amazon/awssdk/services/eks/model/VpcConfigRequest.builder:()Lsoftware/amazon/awssdk/services/eks/model/VpcConfigRequest$Builder;
       4: aload_1
       5: invokeinterface #2,  2            // InterfaceMethod software/amazon/awssdk/services/eks/model/VpcConfigRequest$Builder.applyMutation:(Ljava/util/function/Consumer;)Lsoftware/amazon/awssdk/utils/builder/SdkBuilder;
      10: checkcast     #3                  // class software/amazon/awssdk/services/eks/model/VpcConfigRequest$Builder
      13: invokeinterface #4,  1            // InterfaceMethod software/amazon/awssdk/services/eks/model/VpcConfigRequest$Builder.build:()Ljava/lang/Object;
      18: checkcast     #5                  // class software/amazon/awssdk/services/eks/model/VpcConfigRequest
      21: invokeinterface #6,  2            // InterfaceMethod resourcesVpcConfig:(Lsoftware/amazon/awssdk/services/eks/model/VpcConfigRequest;)Lsoftware/amazon/awssdk/services/eks/model/CreateClusterRequest$Builder;
      26: areturn

  public abstract software.amazon.awssdk.services.eks.model.CreateClusterRequest$Builder kubernetesNetworkConfig(software.amazon.awssdk.services.eks.model.KubernetesNetworkConfigRequest);

  public default software.amazon.awssdk.services.eks.model.CreateClusterRequest$Builder kubernetesNetworkConfig(java.util.function.Consumer<software.amazon.awssdk.services.eks.model.KubernetesNetworkConfigRequest$Builder>);
    Code:
       0: aload_0
       1: invokestatic  #7                  // Method software/amazon/awssdk/services/eks/model/KubernetesNetworkConfigRequest.builder:()Lsoftware/amazon/awssdk/services/eks/model/KubernetesNetworkConfigRequest$Builder;
       4: aload_1
       5: invokeinterface #8,  2            // InterfaceMethod software/amazon/awssdk/services/eks/model/KubernetesNetworkConfigRequest$Builder.applyMutation:(Ljava/util/function/Consumer;)Lsoftware/amazon/awssdk/utils/builder/SdkBuilder;
      10: checkcast     #9                  // class software/amazon/awssdk/services/eks/model/KubernetesNetworkConfigRequest$Builder
      13: invokeinterface #10,  1           // InterfaceMethod software/amazon/awssdk/services/eks/model/KubernetesNetworkConfigRequest$Builder.build:()Ljava/lang/Object;
      18: checkcast     #11                 // class software/amazon/awssdk/services/eks/model/KubernetesNetworkConfigRequest
      21: invokeinterface #12,  2           // InterfaceMethod kubernetesNetworkConfig:(Lsoftware/amazon/awssdk/services/eks/model/KubernetesNetworkConfigRequest;)Lsoftware/amazon/awssdk/services/eks/model/CreateClusterRequest$Builder;
      26: areturn

  public abstract software.amazon.awssdk.services.eks.model.CreateClusterRequest$Builder logging(software.amazon.awssdk.services.eks.model.Logging);

  public default software.amazon.awssdk.services.eks.model.CreateClusterRequest$Builder logging(java.util.function.Consumer<software.amazon.awssdk.services.eks.model.Logging$Builder>);
    Code:
       0: aload_0
       1: invokestatic  #13                 // Method software/amazon/awssdk/services/eks/model/Logging.builder:()Lsoftware/amazon/awssdk/services/eks/model/Logging$Builder;
       4: aload_1
       5: invokeinterface #14,  2           // InterfaceMethod software/amazon/awssdk/services/eks/model/Logging$Builder.applyMutation:(Ljava/util/function/Consumer;)Lsoftware/amazon/awssdk/utils/builder/SdkBuilder;
      10: checkcast     #15                 // class software/amazon/awssdk/services/eks/model/Logging$Builder
      13: invokeinterface #16,  1           // InterfaceMethod software/amazon/awssdk/services/eks/model/Logging$Builder.build:()Ljava/lang/Object;
      18: checkcast     #17                 // class software/amazon/awssdk/services/eks/model/Logging
      21: invokeinterface #18,  2           // InterfaceMethod logging:(Lsoftware/amazon/awssdk/services/eks/model/Logging;)Lsoftware/amazon/awssdk/services/eks/model/CreateClusterRequest$Builder;
      26: areturn

  public abstract software.amazon.awssdk.services.eks.model.CreateClusterRequest$Builder clientRequestToken(java.lang.String);

  public abstract software.amazon.awssdk.services.eks.model.CreateClusterRequest$Builder tags(java.util.Map<java.lang.String, java.lang.String>);

  public abstract software.amazon.awssdk.services.eks.model.CreateClusterRequest$Builder encryptionConfig(java.util.Collection<software.amazon.awssdk.services.eks.model.EncryptionConfig>);

  public abstract software.amazon.awssdk.services.eks.model.CreateClusterRequest$Builder encryptionConfig(software.amazon.awssdk.services.eks.model.EncryptionConfig...);

  public abstract software.amazon.awssdk.services.eks.model.CreateClusterRequest$Builder encryptionConfig(java.util.function.Consumer<software.amazon.awssdk.services.eks.model.EncryptionConfig$Builder>...);

  public abstract software.amazon.awssdk.services.eks.model.CreateClusterRequest$Builder overrideConfiguration(software.amazon.awssdk.awscore.AwsRequestOverrideConfiguration);

  public abstract software.amazon.awssdk.services.eks.model.CreateClusterRequest$Builder overrideConfiguration(java.util.function.Consumer<software.amazon.awssdk.awscore.AwsRequestOverrideConfiguration$Builder>);

  public default software.amazon.awssdk.awscore.AwsRequest$Builder overrideConfiguration(java.util.function.Consumer);
    Code:
       0: aload_0
       1: aload_1
       2: invokeinterface #19,  2           // InterfaceMethod overrideConfiguration:(Ljava/util/function/Consumer;)Lsoftware/amazon/awssdk/services/eks/model/CreateClusterRequest$Builder;
       7: areturn

  public default software.amazon.awssdk.awscore.AwsRequest$Builder overrideConfiguration(software.amazon.awssdk.awscore.AwsRequestOverrideConfiguration);
    Code:
       0: aload_0
       1: aload_1
       2: invokeinterface #20,  2           // InterfaceMethod overrideConfiguration:(Lsoftware/amazon/awssdk/awscore/AwsRequestOverrideConfiguration;)Lsoftware/amazon/awssdk/services/eks/model/CreateClusterRequest$Builder;
       7: areturn
}
