Compiled from "DisassociateIdentityProviderConfigResponse.java"
public interface software.amazon.awssdk.services.eks.model.DisassociateIdentityProviderConfigResponse$Builder extends software.amazon.awssdk.services.eks.model.EksResponse$Builder, software.amazon.awssdk.core.SdkPojo, software.amazon.awssdk.utils.builder.CopyableBuilder<software.amazon.awssdk.services.eks.model.DisassociateIdentityProviderConfigResponse$Builder, software.amazon.awssdk.services.eks.model.DisassociateIdentityProviderConfigResponse> {
  public abstract software.amazon.awssdk.services.eks.model.DisassociateIdentityProviderConfigResponse$Builder update(software.amazon.awssdk.services.eks.model.Update);

  public default software.amazon.awssdk.services.eks.model.DisassociateIdentityProviderConfigResponse$Builder update(java.util.function.Consumer<software.amazon.awssdk.services.eks.model.Update$Builder>);
    Code:
       0: aload_0
       1: invokestatic  #1                  // Method software/amazon/awssdk/services/eks/model/Update.builder:()Lsoftware/amazon/awssdk/services/eks/model/Update$Builder;
       4: aload_1
       5: invokeinterface #2,  2            // InterfaceMethod software/amazon/awssdk/services/eks/model/Update$Builder.applyMutation:(Ljava/util/function/Consumer;)Lsoftware/amazon/awssdk/utils/builder/SdkBuilder;
      10: checkcast     #3                  // class software/amazon/awssdk/services/eks/model/Update$Builder
      13: invokeinterface #4,  1            // InterfaceMethod software/amazon/awssdk/services/eks/model/Update$Builder.build:()Ljava/lang/Object;
      18: checkcast     #5                  // class software/amazon/awssdk/services/eks/model/Update
      21: invokeinterface #6,  2            // InterfaceMethod update:(Lsoftware/amazon/awssdk/services/eks/model/Update;)Lsoftware/amazon/awssdk/services/eks/model/DisassociateIdentityProviderConfigResponse$Builder;
      26: areturn
}
