Compiled from "FargateProfileSelector.java"
final class software.amazon.awssdk.services.eks.model.FargateProfileSelector$BuilderImpl implements software.amazon.awssdk.services.eks.model.FargateProfileSelector$Builder {
  private java.lang.String namespace;

  private java.util.Map<java.lang.String, java.lang.String> labels;

  private software.amazon.awssdk.services.eks.model.FargateProfileSelector$BuilderImpl();
    Code:
       0: aload_0
       1: invokespecial #5                  // Method java/lang/Object."<init>":()V
       4: aload_0
       5: invokestatic  #6                  // Method software/amazon/awssdk/core/util/DefaultSdkAutoConstructMap.getInstance:()Lsoftware/amazon/awssdk/core/util/DefaultSdkAutoConstructMap;
       8: putfield      #3                  // Field labels:Ljava/util/Map;
      11: return

  private software.amazon.awssdk.services.eks.model.FargateProfileSelector$BuilderImpl(software.amazon.awssdk.services.eks.model.FargateProfileSelector);
    Code:
       0: aload_0
       1: invokespecial #5                  // Method java/lang/Object."<init>":()V
       4: aload_0
       5: invokestatic  #6                  // Method software/amazon/awssdk/core/util/DefaultSdkAutoConstructMap.getInstance:()Lsoftware/amazon/awssdk/core/util/DefaultSdkAutoConstructMap;
       8: putfield      #3                  // Field labels:Ljava/util/Map;
      11: aload_0
      12: aload_1
      13: invokestatic  #7                  // Method software/amazon/awssdk/services/eks/model/FargateProfileSelector.access$400:(Lsoftware/amazon/awssdk/services/eks/model/FargateProfileSelector;)Ljava/lang/String;
      16: invokevirtual #8                  // Method namespace:(Ljava/lang/String;)Lsoftware/amazon/awssdk/services/eks/model/FargateProfileSelector$Builder;
      19: pop
      20: aload_0
      21: aload_1
      22: invokestatic  #9                  // Method software/amazon/awssdk/services/eks/model/FargateProfileSelector.access$500:(Lsoftware/amazon/awssdk/services/eks/model/FargateProfileSelector;)Ljava/util/Map;
      25: invokevirtual #10                 // Method labels:(Ljava/util/Map;)Lsoftware/amazon/awssdk/services/eks/model/FargateProfileSelector$Builder;
      28: pop
      29: return

  public final java.lang.String getNamespace();
    Code:
       0: aload_0
       1: getfield      #4                  // Field namespace:Ljava/lang/String;
       4: areturn

  public final void setNamespace(java.lang.String);
    Code:
       0: aload_0
       1: aload_1
       2: putfield      #4                  // Field namespace:Ljava/lang/String;
       5: return

  public final software.amazon.awssdk.services.eks.model.FargateProfileSelector$Builder namespace(java.lang.String);
    Code:
       0: aload_0
       1: aload_1
       2: putfield      #4                  // Field namespace:Ljava/lang/String;
       5: aload_0
       6: areturn

  public final java.util.Map<java.lang.String, java.lang.String> getLabels();
    Code:
       0: aload_0
       1: getfield      #3                  // Field labels:Ljava/util/Map;
       4: instanceof    #11                 // class software/amazon/awssdk/core/util/SdkAutoConstructMap
       7: ifeq          12
      10: aconst_null
      11: areturn
      12: aload_0
      13: getfield      #3                  // Field labels:Ljava/util/Map;
      16: areturn

  public final void setLabels(java.util.Map<java.lang.String, java.lang.String>);
    Code:
       0: aload_0
       1: aload_1
       2: invokestatic  #12                 // Method software/amazon/awssdk/services/eks/model/FargateProfileLabelCopier.copy:(Ljava/util/Map;)Ljava/util/Map;
       5: putfield      #3                  // Field labels:Ljava/util/Map;
       8: return

  public final software.amazon.awssdk.services.eks.model.FargateProfileSelector$Builder labels(java.util.Map<java.lang.String, java.lang.String>);
    Code:
       0: aload_0
       1: aload_1
       2: invokestatic  #12                 // Method software/amazon/awssdk/services/eks/model/FargateProfileLabelCopier.copy:(Ljava/util/Map;)Ljava/util/Map;
       5: putfield      #3                  // Field labels:Ljava/util/Map;
       8: aload_0
       9: areturn

  public software.amazon.awssdk.services.eks.model.FargateProfileSelector build();
    Code:
       0: new           #13                 // class software/amazon/awssdk/services/eks/model/FargateProfileSelector
       3: dup
       4: aload_0
       5: aconst_null
       6: invokespecial #14                 // Method software/amazon/awssdk/services/eks/model/FargateProfileSelector."<init>":(Lsoftware/amazon/awssdk/services/eks/model/FargateProfileSelector$BuilderImpl;Lsoftware/amazon/awssdk/services/eks/model/FargateProfileSelector$1;)V
       9: areturn

  public java.util.List<software.amazon.awssdk.core.SdkField<?>> sdkFields();
    Code:
       0: invokestatic  #15                 // Method software/amazon/awssdk/services/eks/model/FargateProfileSelector.access$700:()Ljava/util/List;
       3: areturn

  public java.lang.Object build();
    Code:
       0: aload_0
       1: invokevirtual #16                 // Method build:()Lsoftware/amazon/awssdk/services/eks/model/FargateProfileSelector;
       4: areturn

  static java.lang.String access$000(software.amazon.awssdk.services.eks.model.FargateProfileSelector$BuilderImpl);
    Code:
       0: aload_0
       1: getfield      #4                  // Field namespace:Ljava/lang/String;
       4: areturn

  static java.util.Map access$100(software.amazon.awssdk.services.eks.model.FargateProfileSelector$BuilderImpl);
    Code:
       0: aload_0
       1: getfield      #3                  // Field labels:Ljava/util/Map;
       4: areturn

  software.amazon.awssdk.services.eks.model.FargateProfileSelector$BuilderImpl(software.amazon.awssdk.services.eks.model.FargateProfileSelector, software.amazon.awssdk.services.eks.model.FargateProfileSelector$1);
    Code:
       0: aload_0
       1: aload_1
       2: invokespecial #2                  // Method "<init>":(Lsoftware/amazon/awssdk/services/eks/model/FargateProfileSelector;)V
       5: return

  software.amazon.awssdk.services.eks.model.FargateProfileSelector$BuilderImpl(software.amazon.awssdk.services.eks.model.FargateProfileSelector$1);
    Code:
       0: aload_0
       1: invokespecial #1                  // Method "<init>":()V
       4: return
}
