Compiled from "Taint.java"
final class software.amazon.awssdk.services.eks.model.Taint$BuilderImpl implements software.amazon.awssdk.services.eks.model.Taint$Builder {
  private java.lang.String key;

  private java.lang.String value;

  private java.lang.String effect;

  private software.amazon.awssdk.services.eks.model.Taint$BuilderImpl();
    Code:
       0: aload_0
       1: invokespecial #6                  // Method java/lang/Object."<init>":()V
       4: return

  private software.amazon.awssdk.services.eks.model.Taint$BuilderImpl(software.amazon.awssdk.services.eks.model.Taint);
    Code:
       0: aload_0
       1: invokespecial #6                  // Method java/lang/Object."<init>":()V
       4: aload_0
       5: aload_1
       6: invokestatic  #7                  // Method software/amazon/awssdk/services/eks/model/Taint.access$500:(Lsoftware/amazon/awssdk/services/eks/model/Taint;)Ljava/lang/String;
       9: invokevirtual #8                  // Method key:(Ljava/lang/String;)Lsoftware/amazon/awssdk/services/eks/model/Taint$Builder;
      12: pop
      13: aload_0
      14: aload_1
      15: invokestatic  #9                  // Method software/amazon/awssdk/services/eks/model/Taint.access$600:(Lsoftware/amazon/awssdk/services/eks/model/Taint;)Ljava/lang/String;
      18: invokevirtual #10                 // Method value:(Ljava/lang/String;)Lsoftware/amazon/awssdk/services/eks/model/Taint$Builder;
      21: pop
      22: aload_0
      23: aload_1
      24: invokestatic  #11                 // Method software/amazon/awssdk/services/eks/model/Taint.access$700:(Lsoftware/amazon/awssdk/services/eks/model/Taint;)Ljava/lang/String;
      27: invokevirtual #12                 // Method effect:(Ljava/lang/String;)Lsoftware/amazon/awssdk/services/eks/model/Taint$Builder;
      30: pop
      31: return

  public final java.lang.String getKey();
    Code:
       0: aload_0
       1: getfield      #5                  // Field key:Ljava/lang/String;
       4: areturn

  public final void setKey(java.lang.String);
    Code:
       0: aload_0
       1: aload_1
       2: putfield      #5                  // Field key:Ljava/lang/String;
       5: return

  public final software.amazon.awssdk.services.eks.model.Taint$Builder key(java.lang.String);
    Code:
       0: aload_0
       1: aload_1
       2: putfield      #5                  // Field key:Ljava/lang/String;
       5: aload_0
       6: areturn

  public final java.lang.String getValue();
    Code:
       0: aload_0
       1: getfield      #4                  // Field value:Ljava/lang/String;
       4: areturn

  public final void setValue(java.lang.String);
    Code:
       0: aload_0
       1: aload_1
       2: putfield      #4                  // Field value:Ljava/lang/String;
       5: return

  public final software.amazon.awssdk.services.eks.model.Taint$Builder value(java.lang.String);
    Code:
       0: aload_0
       1: aload_1
       2: putfield      #4                  // Field value:Ljava/lang/String;
       5: aload_0
       6: areturn

  public final java.lang.String getEffect();
    Code:
       0: aload_0
       1: getfield      #3                  // Field effect:Ljava/lang/String;
       4: areturn

  public final void setEffect(java.lang.String);
    Code:
       0: aload_0
       1: aload_1
       2: putfield      #3                  // Field effect:Ljava/lang/String;
       5: return

  public final software.amazon.awssdk.services.eks.model.Taint$Builder effect(java.lang.String);
    Code:
       0: aload_0
       1: aload_1
       2: putfield      #3                  // Field effect:Ljava/lang/String;
       5: aload_0
       6: areturn

  public final software.amazon.awssdk.services.eks.model.Taint$Builder effect(software.amazon.awssdk.services.eks.model.TaintEffect);
    Code:
       0: aload_0
       1: aload_1
       2: ifnonnull     9
       5: aconst_null
       6: goto          13
       9: aload_1
      10: invokevirtual #13                 // Method software/amazon/awssdk/services/eks/model/TaintEffect.toString:()Ljava/lang/String;
      13: invokevirtual #12                 // Method effect:(Ljava/lang/String;)Lsoftware/amazon/awssdk/services/eks/model/Taint$Builder;
      16: pop
      17: aload_0
      18: areturn

  public software.amazon.awssdk.services.eks.model.Taint build();
    Code:
       0: new           #14                 // class software/amazon/awssdk/services/eks/model/Taint
       3: dup
       4: aload_0
       5: aconst_null
       6: invokespecial #15                 // Method software/amazon/awssdk/services/eks/model/Taint."<init>":(Lsoftware/amazon/awssdk/services/eks/model/Taint$BuilderImpl;Lsoftware/amazon/awssdk/services/eks/model/Taint$1;)V
       9: areturn

  public java.util.List<software.amazon.awssdk.core.SdkField<?>> sdkFields();
    Code:
       0: invokestatic  #16                 // Method software/amazon/awssdk/services/eks/model/Taint.access$900:()Ljava/util/List;
       3: areturn

  public java.lang.Object build();
    Code:
       0: aload_0
       1: invokevirtual #17                 // Method build:()Lsoftware/amazon/awssdk/services/eks/model/Taint;
       4: areturn

  static java.lang.String access$000(software.amazon.awssdk.services.eks.model.Taint$BuilderImpl);
    Code:
       0: aload_0
       1: getfield      #5                  // Field key:Ljava/lang/String;
       4: areturn

  static java.lang.String access$100(software.amazon.awssdk.services.eks.model.Taint$BuilderImpl);
    Code:
       0: aload_0
       1: getfield      #4                  // Field value:Ljava/lang/String;
       4: areturn

  static java.lang.String access$200(software.amazon.awssdk.services.eks.model.Taint$BuilderImpl);
    Code:
       0: aload_0
       1: getfield      #3                  // Field effect:Ljava/lang/String;
       4: areturn

  software.amazon.awssdk.services.eks.model.Taint$BuilderImpl(software.amazon.awssdk.services.eks.model.Taint, software.amazon.awssdk.services.eks.model.Taint$1);
    Code:
       0: aload_0
       1: aload_1
       2: invokespecial #2                  // Method "<init>":(Lsoftware/amazon/awssdk/services/eks/model/Taint;)V
       5: return

  software.amazon.awssdk.services.eks.model.Taint$BuilderImpl(software.amazon.awssdk.services.eks.model.Taint$1);
    Code:
       0: aload_0
       1: invokespecial #1                  // Method "<init>":()V
       4: return
}
