Compiled from "LogBrokerMonitor.java"
class org.apache.log4j.lf5.viewer.LogBrokerMonitor$29 implements java.awt.event.ActionListener {
  private final org.apache.log4j.lf5.viewer.LogBrokerMonitor this$0;

  org.apache.log4j.lf5.viewer.LogBrokerMonitor$29(org.apache.log4j.lf5.viewer.LogBrokerMonitor);
    Code:
       0: aload_0
       1: invokespecial #1                  // Method java/lang/Object."<init>":()V
       4: aload_0
       5: aload_1
       6: putfield      #2                  // Field this$0:Lorg/apache/log4j/lf5/viewer/LogBrokerMonitor;
       9: return

  public void actionPerformed(java.awt.event.ActionEvent);
    Code:
       0: aload_0
       1: getfield      #2                  // Field this$0:Lorg/apache/log4j/lf5/viewer/LogBrokerMonitor;
       4: getfield      #3                  // Field org/apache/log4j/lf5/viewer/LogBrokerMonitor._table:Lorg/apache/log4j/lf5/viewer/LogTable;
       7: invokevirtual #4                  // Method org/apache/log4j/lf5/viewer/LogTable.clearLogRecords:()V
      10: aload_0
      11: getfield      #2                  // Field this$0:Lorg/apache/log4j/lf5/viewer/LogBrokerMonitor;
      14: getfield      #5                  // Field org/apache/log4j/lf5/viewer/LogBrokerMonitor._categoryExplorerTree:Lorg/apache/log4j/lf5/viewer/categoryexplorer/CategoryExplorerTree;
      17: invokevirtual #6                  // Method org/apache/log4j/lf5/viewer/categoryexplorer/CategoryExplorerTree.getExplorerModel:()Lorg/apache/log4j/lf5/viewer/categoryexplorer/CategoryExplorerModel;
      20: invokevirtual #7                  // Method org/apache/log4j/lf5/viewer/categoryexplorer/CategoryExplorerModel.resetAllNodeCounts:()V
      23: aload_0
      24: getfield      #2                  // Field this$0:Lorg/apache/log4j/lf5/viewer/LogBrokerMonitor;
      27: invokevirtual #8                  // Method org/apache/log4j/lf5/viewer/LogBrokerMonitor.updateStatusLabel:()V
      30: aload_0
      31: getfield      #2                  // Field this$0:Lorg/apache/log4j/lf5/viewer/LogBrokerMonitor;
      34: invokevirtual #9                  // Method org/apache/log4j/lf5/viewer/LogBrokerMonitor.clearDetailTextArea:()V
      37: invokestatic  #10                 // Method org/apache/log4j/lf5/LogRecord.resetSequenceNumber:()V
      40: return
}
