Compiled from "ArchiveModelAspect.scala"
public interface net.java.truevfs.kernel.impl.ArchiveModelAspect<E extends net.java.truevfs.kernel.spec.FsArchiveEntry> extends net.java.truevfs.kernel.impl.ReentrantReadWriteLockAspect {
  public static java.util.concurrent.locks.ReentrantReadWriteLock lock$(net.java.truevfs.kernel.impl.ArchiveModelAspect);
    Code:
       0: aload_0
       1: invokespecial #18                 // InterfaceMethod lock:()Ljava/util/concurrent/locks/ReentrantReadWriteLock;
       4: areturn

  public default java.util.concurrent.locks.ReentrantReadWriteLock lock();
    Code:
       0: aload_0
       1: invokeinterface #23,  1           // InterfaceMethod model:()Lnet/java/truevfs/kernel/impl/ArchiveModel;
       6: invokevirtual #26                 // Method net/java/truevfs/kernel/impl/ArchiveModel.lock:()Ljava/util/concurrent/locks/ReentrantReadWriteLock;
       9: areturn

  public abstract net.java.truevfs.kernel.impl.ArchiveModel<E> model();

  public static net.java.truevfs.kernel.spec.FsMountPoint mountPoint$(net.java.truevfs.kernel.impl.ArchiveModelAspect);
    Code:
       0: aload_0
       1: invokespecial #33                 // InterfaceMethod mountPoint:()Lnet/java/truevfs/kernel/spec/FsMountPoint;
       4: areturn

  public default net.java.truevfs.kernel.spec.FsMountPoint mountPoint();
    Code:
       0: aload_0
       1: invokeinterface #23,  1           // InterfaceMethod model:()Lnet/java/truevfs/kernel/impl/ArchiveModel;
       6: invokevirtual #36                 // Method net/java/truevfs/kernel/impl/ArchiveModel.getMountPoint:()Lnet/java/truevfs/kernel/spec/FsMountPoint;
       9: areturn

  public static boolean mounted$(net.java.truevfs.kernel.impl.ArchiveModelAspect);
    Code:
       0: aload_0
       1: invokespecial #42                 // InterfaceMethod mounted:()Z
       4: ireturn

  public default boolean mounted();
    Code:
       0: aload_0
       1: invokeinterface #23,  1           // InterfaceMethod model:()Lnet/java/truevfs/kernel/impl/ArchiveModel;
       6: invokevirtual #45                 // Method net/java/truevfs/kernel/impl/ArchiveModel.isMounted:()Z
       9: ireturn

  public static void mounted_$eq$(net.java.truevfs.kernel.impl.ArchiveModelAspect, boolean);
    Code:
       0: aload_0
       1: iload_1
       2: invokespecial #51                 // InterfaceMethod mounted_$eq:(Z)V
       5: return

  public default void mounted_$eq(boolean);
    Code:
       0: aload_0
       1: invokeinterface #23,  1           // InterfaceMethod model:()Lnet/java/truevfs/kernel/impl/ArchiveModel;
       6: iload_1
       7: invokevirtual #55                 // Method net/java/truevfs/kernel/impl/ArchiveModel.setMounted:(Z)V
      10: return

  public static net.java.truevfs.kernel.spec.FsArchiveDriver driver$(net.java.truevfs.kernel.impl.ArchiveModelAspect);
    Code:
       0: aload_0
       1: invokespecial #61                 // InterfaceMethod driver:()Lnet/java/truevfs/kernel/spec/FsArchiveDriver;
       4: areturn

  public default net.java.truevfs.kernel.spec.FsArchiveDriver<E> driver();
    Code:
       0: aload_0
       1: invokeinterface #23,  1           // InterfaceMethod model:()Lnet/java/truevfs/kernel/impl/ArchiveModel;
       6: invokevirtual #62                 // Method net/java/truevfs/kernel/impl/ArchiveModel.driver:()Lnet/java/truevfs/kernel/spec/FsArchiveDriver;
       9: areturn

  public static net.java.truevfs.kernel.spec.FsNodePath path$(net.java.truevfs.kernel.impl.ArchiveModelAspect, net.java.truevfs.kernel.spec.FsNodeName);
    Code:
       0: aload_0
       1: aload_1
       2: invokespecial #69                 // InterfaceMethod path:(Lnet/java/truevfs/kernel/spec/FsNodeName;)Lnet/java/truevfs/kernel/spec/FsNodePath;
       5: areturn

  public default net.java.truevfs.kernel.spec.FsNodePath path(net.java.truevfs.kernel.spec.FsNodeName);
    Code:
       0: aload_0
       1: invokeinterface #23,  1           // InterfaceMethod model:()Lnet/java/truevfs/kernel/impl/ArchiveModel;
       6: aload_1
       7: invokevirtual #71                 // Method net/java/truevfs/kernel/impl/ArchiveModel.path:(Lnet/java/truevfs/kernel/spec/FsNodeName;)Lnet/java/truevfs/kernel/spec/FsNodePath;
      10: areturn

  public static void touch$(net.java.truevfs.kernel.impl.ArchiveModelAspect, net.java.truecommons.shed.BitField);
    Code:
       0: aload_0
       1: aload_1
       2: invokespecial #78                 // InterfaceMethod touch:(Lnet/java/truecommons/shed/BitField;)V
       5: return

  public default void touch(net.java.truecommons.shed.BitField<net.java.truevfs.kernel.spec.FsAccessOption>);
    Code:
       0: aload_0
       1: invokeinterface #23,  1           // InterfaceMethod model:()Lnet/java/truevfs/kernel/impl/ArchiveModel;
       6: aload_1
       7: invokevirtual #80                 // Method net/java/truevfs/kernel/impl/ArchiveModel.touch:(Lnet/java/truecommons/shed/BitField;)V
      10: return

  public static void $init$(net.java.truevfs.kernel.impl.ArchiveModelAspect);
    Code:
       0: return
}
