Compiled from "DefaultModel.scala"
public final class net.java.truevfs.kernel.impl.DefaultModel extends net.java.truevfs.kernel.spec.FsAbstractModel {
  private volatile boolean mounted;

  private boolean mounted();
    Code:
       0: aload_0
       1: getfield      #14                 // Field mounted:Z
       4: ireturn

  private void mounted_$eq(boolean);
    Code:
       0: aload_0
       1: iload_1
       2: putfield      #14                 // Field mounted:Z
       5: return

  public boolean isMounted();
    Code:
       0: aload_0
       1: invokespecial #22                 // Method mounted:()Z
       4: ireturn

  public void setMounted(boolean);
    Code:
       0: aload_0
       1: iload_1
       2: invokespecial #25                 // Method mounted_$eq:(Z)V
       5: return

  public net.java.truevfs.kernel.impl.DefaultModel(net.java.truevfs.kernel.spec.FsMountPoint, net.java.truevfs.kernel.spec.FsModel);
    Code:
       0: aload_0
       1: aload_1
       2: aload_2
       3: invokespecial #31                 // Method net/java/truevfs/kernel/spec/FsAbstractModel."<init>":(Lnet/java/truevfs/kernel/spec/FsMountPoint;Lnet/java/truevfs/kernel/spec/FsModel;)V
       6: return
}
