Compiled from "FalsePositiveArchiveController.scala"
public final class net.java.truevfs.kernel.impl.FalsePositiveArchiveController extends net.java.truevfs.kernel.spec.FsDecoratingController {
  private net.java.truevfs.kernel.spec.FsController getParent;

  private net.java.truevfs.kernel.spec.FsNodePath path;

  private volatile net.java.truevfs.kernel.impl.FalsePositiveArchiveController$TryChild$ TryChild$module;

  private volatile net.java.truevfs.kernel.impl.FalsePositiveArchiveController$UseParent$ UseParent$module;

  public final net.java.truevfs.kernel.spec.FsController net$java$truevfs$kernel$impl$FalsePositiveArchiveController$$controller;

  private volatile net.java.truevfs.kernel.impl.FalsePositiveArchiveController$State state;

  private volatile byte bitmap$0;

  private net.java.truevfs.kernel.impl.FalsePositiveArchiveController$TryChild$ TryChild();
    Code:
       0: aload_0
       1: getfield      #57                 // Field TryChild$module:Lnet/java/truevfs/kernel/impl/FalsePositiveArchiveController$TryChild$;
       4: ifnonnull     11
       7: aload_0
       8: invokespecial #61                 // Method TryChild$lzycompute$1:()V
      11: aload_0
      12: getfield      #57                 // Field TryChild$module:Lnet/java/truevfs/kernel/impl/FalsePositiveArchiveController$TryChild$;
      15: areturn

  private net.java.truevfs.kernel.impl.FalsePositiveArchiveController$UseParent$ UseParent();
    Code:
       0: aload_0
       1: getfield      #66                 // Field UseParent$module:Lnet/java/truevfs/kernel/impl/FalsePositiveArchiveController$UseParent$;
       4: ifnonnull     11
       7: aload_0
       8: invokespecial #69                 // Method UseParent$lzycompute$1:()V
      11: aload_0
      12: getfield      #66                 // Field UseParent$module:Lnet/java/truevfs/kernel/impl/FalsePositiveArchiveController$UseParent$;
      15: areturn

  private net.java.truevfs.kernel.spec.FsController getParent$lzycompute();
    Code:
       0: aload_0
       1: dup
       2: astore_1
       3: monitorenter
       4: aload_0
       5: getfield      #73                 // Field bitmap$0:B
       8: iconst_1
       9: iand
      10: i2b
      11: iconst_0
      12: if_icmpne     39
      15: aload_0
      16: aload_0
      17: getfield      #75                 // Field net$java$truevfs$kernel$impl$FalsePositiveArchiveController$$controller:Lnet/java/truevfs/kernel/spec/FsController;
      20: invokeinterface #79,  1           // InterfaceMethod net/java/truevfs/kernel/spec/FsController.getParent:()Lnet/java/truevfs/kernel/spec/FsController;
      25: putfield      #81                 // Field getParent:Lnet/java/truevfs/kernel/spec/FsController;
      28: aload_0
      29: aload_0
      30: getfield      #73                 // Field bitmap$0:B
      33: iconst_1
      34: ior
      35: i2b
      36: putfield      #73                 // Field bitmap$0:B
      39: aload_1
      40: monitorexit
      41: goto          47
      44: aload_1
      45: monitorexit
      46: athrow
      47: aload_0
      48: getfield      #81                 // Field getParent:Lnet/java/truevfs/kernel/spec/FsController;
      51: areturn
    Exception table:
       from    to  target type
           4    39    44   any

  public net.java.truevfs.kernel.spec.FsController getParent();
    Code:
       0: aload_0
       1: getfield      #73                 // Field bitmap$0:B
       4: iconst_1
       5: iand
       6: i2b
       7: iconst_0
       8: if_icmpne     18
      11: aload_0
      12: invokespecial #85                 // Method getParent$lzycompute:()Lnet/java/truevfs/kernel/spec/FsController;
      15: goto          22
      18: aload_0
      19: getfield      #81                 // Field getParent:Lnet/java/truevfs/kernel/spec/FsController;
      22: areturn

  private net.java.truevfs.kernel.spec.FsNodePath path$lzycompute();
    Code:
       0: aload_0
       1: dup
       2: astore_1
       3: monitorenter
       4: aload_0
       5: getfield      #73                 // Field bitmap$0:B
       8: iconst_2
       9: iand
      10: i2b
      11: iconst_0
      12: if_icmpne     37
      15: aload_0
      16: aload_0
      17: invokevirtual #91                 // Method getMountPoint:()Lnet/java/truevfs/kernel/spec/FsMountPoint;
      20: invokevirtual #96                 // Method net/java/truevfs/kernel/spec/FsMountPoint.getPath:()Lnet/java/truevfs/kernel/spec/FsNodePath;
      23: putfield      #98                 // Field path:Lnet/java/truevfs/kernel/spec/FsNodePath;
      26: aload_0
      27: aload_0
      28: getfield      #73                 // Field bitmap$0:B
      31: iconst_2
      32: ior
      33: i2b
      34: putfield      #73                 // Field bitmap$0:B
      37: aload_1
      38: monitorexit
      39: goto          45
      42: aload_1
      43: monitorexit
      44: athrow
      45: aload_0
      46: getfield      #98                 // Field path:Lnet/java/truevfs/kernel/spec/FsNodePath;
      49: areturn
    Exception table:
       from    to  target type
           4    37    42   any

  private net.java.truevfs.kernel.spec.FsNodePath path();
    Code:
       0: aload_0
       1: getfield      #73                 // Field bitmap$0:B
       4: iconst_2
       5: iand
       6: i2b
       7: iconst_0
       8: if_icmpne     18
      11: aload_0
      12: invokespecial #100                // Method path$lzycompute:()Lnet/java/truevfs/kernel/spec/FsNodePath;
      15: goto          22
      18: aload_0
      19: getfield      #98                 // Field path:Lnet/java/truevfs/kernel/spec/FsNodePath;
      22: areturn

  public net.java.truevfs.kernel.spec.FsNode node(net.java.truecommons.shed.BitField<net.java.truevfs.kernel.spec.FsAccessOption>, net.java.truevfs.kernel.spec.FsNodeName);
    Code:
       0: aload_0
       1: aload_2
       2: aload_1
       3: invokedynamic #130,  0            // InvokeDynamic #0:apply:(Lnet/java/truecommons/shed/BitField;)Lscala/Function2;
       8: invokevirtual #134                // Method net$java$truevfs$kernel$impl$FalsePositiveArchiveController$$apply:(Lnet/java/truevfs/kernel/spec/FsNodeName;Lscala/Function2;)Ljava/lang/Object;
      11: checkcast     #136                // class net/java/truevfs/kernel/spec/FsNode
      14: areturn

  public void checkAccess(net.java.truecommons.shed.BitField<net.java.truevfs.kernel.spec.FsAccessOption>, net.java.truevfs.kernel.spec.FsNodeName, net.java.truecommons.shed.BitField<net.java.truecommons.cio.Entry$Access>);
    Code:
       0: aload_0
       1: aload_2
       2: aload_1
       3: aload_3
       4: invokedynamic #151,  0            // InvokeDynamic #1:apply:(Lnet/java/truecommons/shed/BitField;Lnet/java/truecommons/shed/BitField;)Lscala/Function2;
       9: invokevirtual #134                // Method net$java$truevfs$kernel$impl$FalsePositiveArchiveController$$apply:(Lnet/java/truevfs/kernel/spec/FsNodeName;Lscala/Function2;)Ljava/lang/Object;
      12: pop
      13: return

  public void setReadOnly(net.java.truecommons.shed.BitField<net.java.truevfs.kernel.spec.FsAccessOption>, net.java.truevfs.kernel.spec.FsNodeName);
    Code:
       0: aload_0
       1: aload_2
       2: aload_1
       3: invokedynamic #159,  0            // InvokeDynamic #2:apply:(Lnet/java/truecommons/shed/BitField;)Lscala/Function2;
       8: invokevirtual #134                // Method net$java$truevfs$kernel$impl$FalsePositiveArchiveController$$apply:(Lnet/java/truevfs/kernel/spec/FsNodeName;Lscala/Function2;)Ljava/lang/Object;
      11: pop
      12: return

  public boolean setTime(net.java.truecommons.shed.BitField<net.java.truevfs.kernel.spec.FsAccessOption>, net.java.truevfs.kernel.spec.FsNodeName, java.util.Map<net.java.truecommons.cio.Entry$Access, java.lang.Long>);
    Code:
       0: aload_0
       1: aload_2
       2: aload_1
       3: aload_3
       4: invokedynamic #170,  0            // InvokeDynamic #3:apply:(Lnet/java/truecommons/shed/BitField;Ljava/util/Map;)Lscala/Function2;
       9: invokevirtual #134                // Method net$java$truevfs$kernel$impl$FalsePositiveArchiveController$$apply:(Lnet/java/truevfs/kernel/spec/FsNodeName;Lscala/Function2;)Ljava/lang/Object;
      12: invokestatic  #176                // Method scala/runtime/BoxesRunTime.unboxToBoolean:(Ljava/lang/Object;)Z
      15: ireturn

  public boolean setTime(net.java.truecommons.shed.BitField<net.java.truevfs.kernel.spec.FsAccessOption>, net.java.truevfs.kernel.spec.FsNodeName, net.java.truecommons.shed.BitField<net.java.truecommons.cio.Entry$Access>, long);
    Code:
       0: aload_0
       1: aload_2
       2: aload_1
       3: aload_3
       4: lload         4
       6: invokedynamic #187,  0            // InvokeDynamic #4:apply:(Lnet/java/truecommons/shed/BitField;Lnet/java/truecommons/shed/BitField;J)Lscala/Function2;
      11: invokevirtual #134                // Method net$java$truevfs$kernel$impl$FalsePositiveArchiveController$$apply:(Lnet/java/truevfs/kernel/spec/FsNodeName;Lscala/Function2;)Ljava/lang/Object;
      14: invokestatic  #176                // Method scala/runtime/BoxesRunTime.unboxToBoolean:(Ljava/lang/Object;)Z
      17: ireturn

  public net.java.truecommons.cio.InputSocket<? extends net.java.truecommons.cio.Entry> input(net.java.truecommons.shed.BitField<net.java.truevfs.kernel.spec.FsAccessOption>, net.java.truevfs.kernel.spec.FsNodeName);
    Code:
       0: new           #24                 // class net/java/truevfs/kernel/impl/FalsePositiveArchiveController$Input$1
       3: dup
       4: aload_0
       5: aload_1
       6: aload_2
       7: invokespecial #194                // Method net/java/truevfs/kernel/impl/FalsePositiveArchiveController$Input$1."<init>":(Lnet/java/truevfs/kernel/impl/FalsePositiveArchiveController;Lnet/java/truecommons/shed/BitField;Lnet/java/truevfs/kernel/spec/FsNodeName;)V
      10: areturn

  public net.java.truecommons.cio.OutputSocket<? extends net.java.truecommons.cio.Entry> output(net.java.truecommons.shed.BitField<net.java.truevfs.kernel.spec.FsAccessOption>, net.java.truevfs.kernel.spec.FsNodeName, net.java.truecommons.cio.Entry);
    Code:
       0: new           #27                 // class net/java/truevfs/kernel/impl/FalsePositiveArchiveController$Output$1
       3: dup
       4: aload_0
       5: aload_1
       6: aload_2
       7: aload_3
       8: invokespecial #200                // Method net/java/truevfs/kernel/impl/FalsePositiveArchiveController$Output$1."<init>":(Lnet/java/truevfs/kernel/impl/FalsePositiveArchiveController;Lnet/java/truecommons/shed/BitField;Lnet/java/truevfs/kernel/spec/FsNodeName;Lnet/java/truecommons/cio/Entry;)V
      11: areturn

  public void make(net.java.truecommons.shed.BitField<net.java.truevfs.kernel.spec.FsAccessOption>, net.java.truevfs.kernel.spec.FsNodeName, net.java.truecommons.cio.Entry$Type, net.java.truecommons.cio.Entry);
    Code:
       0: aload_0
       1: aload_2
       2: aload_1
       3: aload_3
       4: aload         4
       6: invokedynamic #212,  0            // InvokeDynamic #5:apply:(Lnet/java/truecommons/shed/BitField;Lnet/java/truecommons/cio/Entry$Type;Lnet/java/truecommons/cio/Entry;)Lscala/Function2;
      11: invokevirtual #134                // Method net$java$truevfs$kernel$impl$FalsePositiveArchiveController$$apply:(Lnet/java/truevfs/kernel/spec/FsNodeName;Lscala/Function2;)Ljava/lang/Object;
      14: pop
      15: return

  public void unlink(net.java.truecommons.shed.BitField<net.java.truevfs.kernel.spec.FsAccessOption>, net.java.truevfs.kernel.spec.FsNodeName);
    Code:
       0: aload_0
       1: aload_1
       2: invokedynamic #224,  0            // InvokeDynamic #6:apply:(Lnet/java/truevfs/kernel/impl/FalsePositiveArchiveController;Lnet/java/truecommons/shed/BitField;)Lscala/Function2;
       7: astore_3
       8: aload_2
       9: invokevirtual #230                // Method net/java/truevfs/kernel/spec/FsNodeName.isRoot:()Z
      12: ifeq          63
      15: aload_0
      16: invokespecial #232                // Method TryChild:()Lnet/java/truevfs/kernel/impl/FalsePositiveArchiveController$TryChild$;
      19: getstatic     #235                // Field net/java/truevfs/kernel/spec/FsNodeName.ROOT:Lnet/java/truevfs/kernel/spec/FsNodeName;
      22: aload_3
      23: invokevirtual #237                // Method net/java/truevfs/kernel/impl/FalsePositiveArchiveController$TryChild$.apply:(Lnet/java/truevfs/kernel/spec/FsNodeName;Lscala/Function2;)Ljava/lang/Object;
      26: goto          51
      29: astore        4
      31: new           #36                 // class net/java/truevfs/kernel/impl/FalsePositiveArchiveController$UseParent
      34: dup
      35: aload_0
      36: aload         4
      38: invokespecial #240                // Method net/java/truevfs/kernel/impl/FalsePositiveArchiveController$UseParent."<init>":(Lnet/java/truevfs/kernel/impl/FalsePositiveArchiveController;Lnet/java/truevfs/kernel/impl/FalsePositiveArchiveException;)V
      41: getstatic     #235                // Field net/java/truevfs/kernel/spec/FsNodeName.ROOT:Lnet/java/truevfs/kernel/spec/FsNodeName;
      44: aload_3
      45: invokevirtual #241                // Method net/java/truevfs/kernel/impl/FalsePositiveArchiveController$UseParent.apply:(Lnet/java/truevfs/kernel/spec/FsNodeName;Lscala/Function2;)Ljava/lang/Object;
      48: goto          51
      51: pop
      52: aload_0
      53: aload_0
      54: invokespecial #232                // Method TryChild:()Lnet/java/truevfs/kernel/impl/FalsePositiveArchiveController$TryChild$;
      57: putfield      #243                // Field state:Lnet/java/truevfs/kernel/impl/FalsePositiveArchiveController$State;
      60: goto          70
      63: aload_0
      64: aload_2
      65: aload_3
      66: invokevirtual #134                // Method net$java$truevfs$kernel$impl$FalsePositiveArchiveController$$apply:(Lnet/java/truevfs/kernel/spec/FsNodeName;Lscala/Function2;)Ljava/lang/Object;
      69: pop
      70: return
    Exception table:
       from    to  target type
          15    26    29   Class net/java/truevfs/kernel/impl/FalsePositiveArchiveException

  public void sync(net.java.truecommons.shed.BitField<net.java.truevfs.kernel.spec.FsSyncOption>);
    Code:
       0: aload_0
       1: getfield      #75                 // Field net$java$truevfs$kernel$impl$FalsePositiveArchiveController$$controller:Lnet/java/truevfs/kernel/spec/FsController;
       4: aload_1
       5: invokeinterface #261,  2          // InterfaceMethod net/java/truevfs/kernel/spec/FsController.sync:(Lnet/java/truecommons/shed/BitField;)V
      10: goto          63
      13: astore_2
      14: getstatic     #267                // Field scala/Predef$.MODULE$:Lscala/Predef$;
      17: aload_0
      18: getfield      #243                // Field state:Lnet/java/truevfs/kernel/impl/FalsePositiveArchiveController$State;
      21: aload_0
      22: invokespecial #232                // Method TryChild:()Lnet/java/truevfs/kernel/impl/FalsePositiveArchiveController$TryChild$;
      25: if_acmpne     32
      28: iconst_1
      29: goto          33
      32: iconst_0
      33: invokevirtual #271                // Method scala/Predef$.assert:(Z)V
      36: aload_2
      37: athrow
      38: astore_3
      39: getstatic     #267                // Field scala/Predef$.MODULE$:Lscala/Predef$;
      42: aload_0
      43: getfield      #243                // Field state:Lnet/java/truevfs/kernel/impl/FalsePositiveArchiveController$State;
      46: aload_0
      47: invokespecial #232                // Method TryChild:()Lnet/java/truevfs/kernel/impl/FalsePositiveArchiveController$TryChild$;
      50: if_acmpne     57
      53: iconst_1
      54: goto          58
      57: iconst_0
      58: invokevirtual #271                // Method scala/Predef$.assert:(Z)V
      61: aload_3
      62: athrow
      63: aload_0
      64: aload_0
      65: invokespecial #232                // Method TryChild:()Lnet/java/truevfs/kernel/impl/FalsePositiveArchiveController$TryChild$;
      68: putfield      #243                // Field state:Lnet/java/truevfs/kernel/impl/FalsePositiveArchiveController$State;
      71: return
    Exception table:
       from    to  target type
           0    10    13   Class net/java/truevfs/kernel/spec/FsSyncException
           0    10    38   Class net/java/truecommons/shed/ControlFlowException

  public <V> V net$java$truevfs$kernel$impl$FalsePositiveArchiveController$$apply(net.java.truevfs.kernel.spec.FsNodeName, scala.Function2<net.java.truevfs.kernel.spec.FsController, net.java.truevfs.kernel.spec.FsNodeName, V>);
    Code:
       0: aload_0
       1: getfield      #243                // Field state:Lnet/java/truevfs/kernel/impl/FalsePositiveArchiveController$State;
       4: astore_3
       5: aload_3
       6: aload_1
       7: aload_2
       8: invokeinterface #276,  3          // InterfaceMethod net/java/truevfs/kernel/impl/FalsePositiveArchiveController$State.apply:(Lnet/java/truevfs/kernel/spec/FsNodeName;Lscala/Function2;)Ljava/lang/Object;
      13: goto          103
      16: astore        4
      18: getstatic     #267                // Field scala/Predef$.MODULE$:Lscala/Predef$;
      21: aload_3
      22: aload_0
      23: invokespecial #232                // Method TryChild:()Lnet/java/truevfs/kernel/impl/FalsePositiveArchiveController$TryChild$;
      26: if_acmpne     33
      29: iconst_1
      30: goto          34
      33: iconst_0
      34: invokevirtual #271                // Method scala/Predef$.assert:(Z)V
      37: new           #36                 // class net/java/truevfs/kernel/impl/FalsePositiveArchiveController$UseParent
      40: dup
      41: aload_0
      42: aload         4
      44: invokespecial #240                // Method net/java/truevfs/kernel/impl/FalsePositiveArchiveController$UseParent."<init>":(Lnet/java/truevfs/kernel/impl/FalsePositiveArchiveController;Lnet/java/truevfs/kernel/impl/FalsePositiveArchiveException;)V
      47: astore_3
      48: aload_0
      49: aload_3
      50: putfield      #243                // Field state:Lnet/java/truevfs/kernel/impl/FalsePositiveArchiveController$State;
      53: aload_3
      54: aload_1
      55: aload_2
      56: invokeinterface #276,  3          // InterfaceMethod net/java/truevfs/kernel/impl/FalsePositiveArchiveController$State.apply:(Lnet/java/truevfs/kernel/spec/FsNodeName;Lscala/Function2;)Ljava/lang/Object;
      61: goto          103
      64: astore        5
      66: getstatic     #267                // Field scala/Predef$.MODULE$:Lscala/Predef$;
      69: aload_3
      70: aload_0
      71: invokespecial #232                // Method TryChild:()Lnet/java/truevfs/kernel/impl/FalsePositiveArchiveController$TryChild$;
      74: if_acmpne     81
      77: iconst_1
      78: goto          82
      81: iconst_0
      82: invokevirtual #271                // Method scala/Predef$.assert:(Z)V
      85: new           #36                 // class net/java/truevfs/kernel/impl/FalsePositiveArchiveController$UseParent
      88: dup
      89: aload_0
      90: aload         5
      92: invokespecial #240                // Method net/java/truevfs/kernel/impl/FalsePositiveArchiveController$UseParent."<init>":(Lnet/java/truevfs/kernel/impl/FalsePositiveArchiveController;Lnet/java/truevfs/kernel/impl/FalsePositiveArchiveException;)V
      95: aload_1
      96: aload_2
      97: invokevirtual #241                // Method net/java/truevfs/kernel/impl/FalsePositiveArchiveController$UseParent.apply:(Lnet/java/truevfs/kernel/spec/FsNodeName;Lscala/Function2;)Ljava/lang/Object;
     100: goto          103
     103: areturn
    Exception table:
       from    to  target type
           5    13    16   Class net/java/truevfs/kernel/impl/PersistentFalsePositiveArchiveException
           5    13    64   Class net/java/truevfs/kernel/impl/FalsePositiveArchiveException

  public net.java.truevfs.kernel.spec.FsNodeName net$java$truevfs$kernel$impl$FalsePositiveArchiveController$$parent(net.java.truevfs.kernel.spec.FsNodeName);
    Code:
       0: aload_0
       1: invokespecial #281                // Method path:()Lnet/java/truevfs/kernel/spec/FsNodePath;
       4: aload_1
       5: invokevirtual #285                // Method net/java/truevfs/kernel/spec/FsNodePath.resolve:(Lnet/java/truevfs/kernel/spec/FsNodeName;)Lnet/java/truevfs/kernel/spec/FsNodePath;
       8: invokevirtual #289                // Method net/java/truevfs/kernel/spec/FsNodePath.getNodeName:()Lnet/java/truevfs/kernel/spec/FsNodeName;
      11: areturn

  private final void TryChild$lzycompute$1();
    Code:
       0: aload_0
       1: dup
       2: astore_1
       3: monitorenter
       4: aload_0
       5: getfield      #57                 // Field TryChild$module:Lnet/java/truevfs/kernel/impl/FalsePositiveArchiveController$TryChild$;
       8: ifnonnull     23
      11: aload_0
      12: new           #33                 // class net/java/truevfs/kernel/impl/FalsePositiveArchiveController$TryChild$
      15: dup
      16: aload_0
      17: invokespecial #292                // Method net/java/truevfs/kernel/impl/FalsePositiveArchiveController$TryChild$."<init>":(Lnet/java/truevfs/kernel/impl/FalsePositiveArchiveController;)V
      20: putfield      #57                 // Field TryChild$module:Lnet/java/truevfs/kernel/impl/FalsePositiveArchiveController$TryChild$;
      23: aload_1
      24: monitorexit
      25: goto          31
      28: aload_1
      29: monitorexit
      30: athrow
      31: return
    Exception table:
       from    to  target type
           4    23    28   any

  private final void UseParent$lzycompute$1();
    Code:
       0: aload_0
       1: dup
       2: astore_1
       3: monitorenter
       4: aload_0
       5: getfield      #66                 // Field UseParent$module:Lnet/java/truevfs/kernel/impl/FalsePositiveArchiveController$UseParent$;
       8: ifnonnull     23
      11: aload_0
      12: new           #39                 // class net/java/truevfs/kernel/impl/FalsePositiveArchiveController$UseParent$
      15: dup
      16: aload_0
      17: invokespecial #293                // Method net/java/truevfs/kernel/impl/FalsePositiveArchiveController$UseParent$."<init>":(Lnet/java/truevfs/kernel/impl/FalsePositiveArchiveController;)V
      20: putfield      #66                 // Field UseParent$module:Lnet/java/truevfs/kernel/impl/FalsePositiveArchiveController$UseParent$;
      23: aload_1
      24: monitorexit
      25: goto          31
      28: aload_1
      29: monitorexit
      30: athrow
      31: return
    Exception table:
       from    to  target type
           4    23    28   any

  public static final net.java.truevfs.kernel.spec.FsNode $anonfun$node$1(net.java.truecommons.shed.BitField, net.java.truevfs.kernel.spec.FsController, net.java.truevfs.kernel.spec.FsNodeName);
    Code:
       0: aload_1
       1: aload_0
       2: aload_2
       3: invokeinterface #298,  3          // InterfaceMethod net/java/truevfs/kernel/spec/FsController.node:(Lnet/java/truecommons/shed/BitField;Lnet/java/truevfs/kernel/spec/FsNodeName;)Lnet/java/truevfs/kernel/spec/FsNode;
       8: areturn

  public static final void $anonfun$checkAccess$1(net.java.truecommons.shed.BitField, net.java.truecommons.shed.BitField, net.java.truevfs.kernel.spec.FsController, net.java.truevfs.kernel.spec.FsNodeName);
    Code:
       0: aload_2
       1: aload_0
       2: aload_3
       3: aload_1
       4: invokeinterface #306,  4          // InterfaceMethod net/java/truevfs/kernel/spec/FsController.checkAccess:(Lnet/java/truecommons/shed/BitField;Lnet/java/truevfs/kernel/spec/FsNodeName;Lnet/java/truecommons/shed/BitField;)V
       9: return

  public static final void $anonfun$setReadOnly$1(net.java.truecommons.shed.BitField, net.java.truevfs.kernel.spec.FsController, net.java.truevfs.kernel.spec.FsNodeName);
    Code:
       0: aload_1
       1: aload_0
       2: aload_2
       3: invokeinterface #313,  3          // InterfaceMethod net/java/truevfs/kernel/spec/FsController.setReadOnly:(Lnet/java/truecommons/shed/BitField;Lnet/java/truevfs/kernel/spec/FsNodeName;)V
       8: return

  public static final boolean $anonfun$setTime$1(net.java.truecommons.shed.BitField, java.util.Map, net.java.truevfs.kernel.spec.FsController, net.java.truevfs.kernel.spec.FsNodeName);
    Code:
       0: aload_2
       1: aload_0
       2: aload_3
       3: aload_1
       4: invokeinterface #321,  4          // InterfaceMethod net/java/truevfs/kernel/spec/FsController.setTime:(Lnet/java/truecommons/shed/BitField;Lnet/java/truevfs/kernel/spec/FsNodeName;Ljava/util/Map;)Z
       9: ireturn

  public static final boolean $anonfun$setTime$2(net.java.truecommons.shed.BitField, net.java.truecommons.shed.BitField, long, net.java.truevfs.kernel.spec.FsController, net.java.truevfs.kernel.spec.FsNodeName);
    Code:
       0: aload         4
       2: aload_0
       3: aload         5
       5: aload_1
       6: lload_2
       7: invokeinterface #330,  6          // InterfaceMethod net/java/truevfs/kernel/spec/FsController.setTime:(Lnet/java/truecommons/shed/BitField;Lnet/java/truevfs/kernel/spec/FsNodeName;Lnet/java/truecommons/shed/BitField;J)Z
      12: ireturn

  public static final void $anonfun$make$1(net.java.truecommons.shed.BitField, net.java.truecommons.cio.Entry$Type, net.java.truecommons.cio.Entry, net.java.truevfs.kernel.spec.FsController, net.java.truevfs.kernel.spec.FsNodeName);
    Code:
       0: aload_3
       1: aload_0
       2: aload         4
       4: aload_1
       5: aload_2
       6: invokeinterface #339,  5          // InterfaceMethod net/java/truevfs/kernel/spec/FsController.make:(Lnet/java/truecommons/shed/BitField;Lnet/java/truevfs/kernel/spec/FsNodeName;Lnet/java/truecommons/cio/Entry$Type;Lnet/java/truecommons/cio/Entry;)V
      11: return

  public static final void $anonfun$unlink$1(net.java.truevfs.kernel.impl.FalsePositiveArchiveController, net.java.truecommons.shed.BitField, net.java.truevfs.kernel.spec.FsController, net.java.truevfs.kernel.spec.FsNodeName);
    Code:
       0: aload_2
       1: aload_1
       2: aload_3
       3: invokeinterface #347,  3          // InterfaceMethod net/java/truevfs/kernel/spec/FsController.unlink:(Lnet/java/truecommons/shed/BitField;Lnet/java/truevfs/kernel/spec/FsNodeName;)V
       8: aload_3
       9: invokevirtual #230                // Method net/java/truevfs/kernel/spec/FsNodeName.isRoot:()Z
      12: ifeq          52
      15: getstatic     #267                // Field scala/Predef$.MODULE$:Lscala/Predef$;
      18: aload_2
      19: aload_0
      20: getfield      #75                 // Field net$java$truevfs$kernel$impl$FalsePositiveArchiveController$$controller:Lnet/java/truevfs/kernel/spec/FsController;
      23: if_acmpne     30
      26: iconst_1
      27: goto          31
      30: iconst_0
      31: invokevirtual #271                // Method scala/Predef$.assert:(Z)V
      34: aload_0
      35: invokevirtual #348                // Method getParent:()Lnet/java/truevfs/kernel/spec/FsController;
      38: aload_1
      39: aload_0
      40: aload_3
      41: invokevirtual #350                // Method net$java$truevfs$kernel$impl$FalsePositiveArchiveController$$parent:(Lnet/java/truevfs/kernel/spec/FsNodeName;)Lnet/java/truevfs/kernel/spec/FsNodeName;
      44: invokeinterface #347,  3          // InterfaceMethod net/java/truevfs/kernel/spec/FsController.unlink:(Lnet/java/truecommons/shed/BitField;Lnet/java/truevfs/kernel/spec/FsNodeName;)V
      49: goto          52
      52: return

  public net.java.truevfs.kernel.impl.FalsePositiveArchiveController(net.java.truevfs.kernel.spec.FsController);
    Code:
       0: aload_0
       1: aload_1
       2: putfield      #75                 // Field net$java$truevfs$kernel$impl$FalsePositiveArchiveController$$controller:Lnet/java/truevfs/kernel/spec/FsController;
       5: aload_0
       6: aload_1
       7: invokespecial #354                // Method net/java/truevfs/kernel/spec/FsDecoratingController."<init>":(Lnet/java/truevfs/kernel/spec/FsController;)V
      10: aload_0
      11: aload_0
      12: invokespecial #232                // Method TryChild:()Lnet/java/truevfs/kernel/impl/FalsePositiveArchiveController$TryChild$;
      15: putfield      #243                // Field state:Lnet/java/truevfs/kernel/impl/FalsePositiveArchiveController$State;
      18: return

  public static final java.lang.Object $anonfun$checkAccess$1$adapted(net.java.truecommons.shed.BitField, net.java.truecommons.shed.BitField, net.java.truevfs.kernel.spec.FsController, net.java.truevfs.kernel.spec.FsNodeName);
    Code:
       0: aload_0
       1: aload_1
       2: aload_2
       3: aload_3
       4: invokestatic  #356                // Method $anonfun$checkAccess$1:(Lnet/java/truecommons/shed/BitField;Lnet/java/truecommons/shed/BitField;Lnet/java/truevfs/kernel/spec/FsController;Lnet/java/truevfs/kernel/spec/FsNodeName;)V
       7: getstatic     #362                // Field scala/runtime/BoxedUnit.UNIT:Lscala/runtime/BoxedUnit;
      10: areturn

  public static final java.lang.Object $anonfun$setReadOnly$1$adapted(net.java.truecommons.shed.BitField, net.java.truevfs.kernel.spec.FsController, net.java.truevfs.kernel.spec.FsNodeName);
    Code:
       0: aload_0
       1: aload_1
       2: aload_2
       3: invokestatic  #364                // Method $anonfun$setReadOnly$1:(Lnet/java/truecommons/shed/BitField;Lnet/java/truevfs/kernel/spec/FsController;Lnet/java/truevfs/kernel/spec/FsNodeName;)V
       6: getstatic     #362                // Field scala/runtime/BoxedUnit.UNIT:Lscala/runtime/BoxedUnit;
       9: areturn

  public static final java.lang.Object $anonfun$setTime$1$adapted(net.java.truecommons.shed.BitField, java.util.Map, net.java.truevfs.kernel.spec.FsController, net.java.truevfs.kernel.spec.FsNodeName);
    Code:
       0: aload_0
       1: aload_1
       2: aload_2
       3: aload_3
       4: invokestatic  #366                // Method $anonfun$setTime$1:(Lnet/java/truecommons/shed/BitField;Ljava/util/Map;Lnet/java/truevfs/kernel/spec/FsController;Lnet/java/truevfs/kernel/spec/FsNodeName;)Z
       7: invokestatic  #370                // Method scala/runtime/BoxesRunTime.boxToBoolean:(Z)Ljava/lang/Boolean;
      10: areturn

  public static final java.lang.Object $anonfun$setTime$2$adapted(net.java.truecommons.shed.BitField, net.java.truecommons.shed.BitField, long, net.java.truevfs.kernel.spec.FsController, net.java.truevfs.kernel.spec.FsNodeName);
    Code:
       0: aload_0
       1: aload_1
       2: lload_2
       3: aload         4
       5: aload         5
       7: invokestatic  #372                // Method $anonfun$setTime$2:(Lnet/java/truecommons/shed/BitField;Lnet/java/truecommons/shed/BitField;JLnet/java/truevfs/kernel/spec/FsController;Lnet/java/truevfs/kernel/spec/FsNodeName;)Z
      10: invokestatic  #370                // Method scala/runtime/BoxesRunTime.boxToBoolean:(Z)Ljava/lang/Boolean;
      13: areturn

  public static final java.lang.Object $anonfun$make$1$adapted(net.java.truecommons.shed.BitField, net.java.truecommons.cio.Entry$Type, net.java.truecommons.cio.Entry, net.java.truevfs.kernel.spec.FsController, net.java.truevfs.kernel.spec.FsNodeName);
    Code:
       0: aload_0
       1: aload_1
       2: aload_2
       3: aload_3
       4: aload         4
       6: invokestatic  #374                // Method $anonfun$make$1:(Lnet/java/truecommons/shed/BitField;Lnet/java/truecommons/cio/Entry$Type;Lnet/java/truecommons/cio/Entry;Lnet/java/truevfs/kernel/spec/FsController;Lnet/java/truevfs/kernel/spec/FsNodeName;)V
       9: getstatic     #362                // Field scala/runtime/BoxedUnit.UNIT:Lscala/runtime/BoxedUnit;
      12: areturn

  public static final java.lang.Object $anonfun$unlink$1$adapted(net.java.truevfs.kernel.impl.FalsePositiveArchiveController, net.java.truecommons.shed.BitField, net.java.truevfs.kernel.spec.FsController, net.java.truevfs.kernel.spec.FsNodeName);
    Code:
       0: aload_0
       1: aload_1
       2: aload_2
       3: aload_3
       4: invokestatic  #376                // Method $anonfun$unlink$1:(Lnet/java/truevfs/kernel/impl/FalsePositiveArchiveController;Lnet/java/truecommons/shed/BitField;Lnet/java/truevfs/kernel/spec/FsController;Lnet/java/truevfs/kernel/spec/FsNodeName;)V
       7: getstatic     #362                // Field scala/runtime/BoxedUnit.UNIT:Lscala/runtime/BoxedUnit;
      10: areturn

  private static java.lang.Object $deserializeLambda$(java.lang.invoke.SerializedLambda);
    Code:
       0: aload_0
       1: invokedynamic #388,  0            // InvokeDynamic #7:lambdaDeserialize:(Ljava/lang/invoke/SerializedLambda;)Ljava/lang/Object;
       6: areturn
}
