public class org.bouncycastle.crypto.prng.drbg.CTRSP800DRBG implements org.bouncycastle.crypto.prng.drbg.SP80090DRBG {
  private static final long TDEA_RESEED_MAX;

  private static final long AES_RESEED_MAX;

  private static final int TDEA_MAX_BITS_REQUEST;

  private static final int AES_MAX_BITS_REQUEST;

  private org.bouncycastle.crypto.prng.EntropySource _entropySource;

  private org.bouncycastle.crypto.BlockCipher _engine;

  private int _keySizeInBits;

  private int _seedLength;

  private int _securityStrength;

  private byte[] _Key;

  private byte[] _V;

  private long _reseedCounter;

  private boolean _isTDEA;

  private static final byte[] K_BITS;

  public org.bouncycastle.crypto.prng.drbg.CTRSP800DRBG(org.bouncycastle.crypto.BlockCipher, int, int, org.bouncycastle.crypto.prng.EntropySource, byte[], byte[]);
    Code:
       0: aload_0
       1: invokespecial #175                // Method java/lang/Object."<init>":()V
       4: aload_0
       5: lconst_0
       6: putfield      #166                // Field _reseedCounter:J
       9: aload_0
      10: iconst_0
      11: putfield      #167                // Field _isTDEA:Z
      14: aload_0
      15: aload         4
      17: putfield      #172                // Field _entropySource:Lorg/bouncycastle/crypto/prng/EntropySource;
      20: aload_0
      21: aload_1
      22: putfield      #171                // Field _engine:Lorg/bouncycastle/crypto/BlockCipher;
      25: aload_0
      26: iload_2
      27: putfield      #163                // Field _keySizeInBits:I
      30: aload_0
      31: iload_3
      32: putfield      #164                // Field _securityStrength:I
      35: aload_0
      36: iload_2
      37: aload_1
      38: invokeinterface #196,  1          // InterfaceMethod org/bouncycastle/crypto/BlockCipher.getBlockSize:()I
      43: bipush        8
      45: imul
      46: iadd
      47: putfield      #165                // Field _seedLength:I
      50: aload_0
      51: aload_0
      52: aload_1
      53: invokespecial #190                // Method isTDEA:(Lorg/bouncycastle/crypto/BlockCipher;)Z
      56: putfield      #167                // Field _isTDEA:Z
      59: iload_3
      60: sipush        256
      63: if_icmple     76
      66: new           #102                // class java/lang/IllegalArgumentException
      69: dup
      70: ldc           #10                 // String Requested security strength is not supported by the derivation function
      72: invokespecial #173                // Method java/lang/IllegalArgumentException."<init>":(Ljava/lang/String;)V
      75: athrow
      76: aload_0
      77: aload_1
      78: iload_2
      79: invokespecial #191                // Method getMaxSecurityStrength:(Lorg/bouncycastle/crypto/BlockCipher;I)I
      82: iload_3
      83: if_icmpge     96
      86: new           #102                // class java/lang/IllegalArgumentException
      89: dup
      90: ldc           #9                  // String Requested security strength is not supported by block cipher and key size
      92: invokespecial #173                // Method java/lang/IllegalArgumentException."<init>":(Ljava/lang/String;)V
      95: athrow
      96: aload         4
      98: invokeinterface #200,  1          // InterfaceMethod org/bouncycastle/crypto/prng/EntropySource.entropySize:()I
     103: iload_3
     104: if_icmpge     117
     107: new           #102                // class java/lang/IllegalArgumentException
     110: dup
     111: ldc           #6                  // String Not enough entropy for security strength required
     113: invokespecial #173                // Method java/lang/IllegalArgumentException."<init>":(Ljava/lang/String;)V
     116: athrow
     117: aload_0
     118: invokespecial #179                // Method getEntropy:()[B
     121: astore        7
     123: aload_0
     124: aload         7
     126: aload         6
     128: aload         5
     130: invokespecial #186                // Method CTR_DRBG_Instantiate_algorithm:([B[B[B)V
     133: return

  private void CTR_DRBG_Instantiate_algorithm(byte[], byte[], byte[]);
    Code:
       0: aload_1
       1: aload_2
       2: aload_3
       3: invokestatic  #194                // Method org/bouncycastle/util/Arrays.concatenate:([B[B[B)[B
       6: astore        4
       8: aload_0
       9: aload         4
      11: aload_0
      12: getfield      #165                // Field _seedLength:I
      15: invokespecial #183                // Method Block_Cipher_df:([BI)[B
      18: astore        5
      20: aload_0
      21: getfield      #171                // Field _engine:Lorg/bouncycastle/crypto/BlockCipher;
      24: invokeinterface #196,  1          // InterfaceMethod org/bouncycastle/crypto/BlockCipher.getBlockSize:()I
      29: istore        6
      31: aload_0
      32: aload_0
      33: getfield      #163                // Field _keySizeInBits:I
      36: bipush        7
      38: iadd
      39: bipush        8
      41: idiv
      42: newarray       byte
      44: putfield      #169                // Field _Key:[B
      47: aload_0
      48: iload         6
      50: newarray       byte
      52: putfield      #170                // Field _V:[B
      55: aload_0
      56: aload         5
      58: aload_0
      59: getfield      #169                // Field _Key:[B
      62: aload_0
      63: getfield      #170                // Field _V:[B
      66: invokespecial #187                // Method CTR_DRBG_Update:([B[B[B)V
      69: aload_0
      70: lconst_1
      71: putfield      #166                // Field _reseedCounter:J
      74: return

  private void CTR_DRBG_Update(byte[], byte[], byte[]);
    Code:
       0: aload_1
       1: arraylength
       2: newarray       byte
       4: astore        4
       6: aload_0
       7: getfield      #171                // Field _engine:Lorg/bouncycastle/crypto/BlockCipher;
      10: invokeinterface #196,  1          // InterfaceMethod org/bouncycastle/crypto/BlockCipher.getBlockSize:()I
      15: newarray       byte
      17: astore        5
      19: iconst_0
      20: istore        6
      22: aload_0
      23: getfield      #171                // Field _engine:Lorg/bouncycastle/crypto/BlockCipher;
      26: invokeinterface #196,  1          // InterfaceMethod org/bouncycastle/crypto/BlockCipher.getBlockSize:()I
      31: istore        7
      33: aload_0
      34: getfield      #171                // Field _engine:Lorg/bouncycastle/crypto/BlockCipher;
      37: iconst_1
      38: new           #108                // class org/bouncycastle/crypto/params/KeyParameter
      41: dup
      42: aload_0
      43: aload_2
      44: invokevirtual #182                // Method expandKey:([B)[B
      47: invokespecial #178                // Method org/bouncycastle/crypto/params/KeyParameter."<init>":([B)V
      50: invokeinterface #199,  3          // InterfaceMethod org/bouncycastle/crypto/BlockCipher.init:(ZLorg/bouncycastle/crypto/CipherParameters;)V
      55: iload         6
      57: iload         7
      59: imul
      60: aload_1
      61: arraylength
      62: if_icmpge     136
      65: aload_0
      66: aload_3
      67: invokespecial #181                // Method addOneTo:([B)V
      70: aload_0
      71: getfield      #171                // Field _engine:Lorg/bouncycastle/crypto/BlockCipher;
      74: aload_3
      75: iconst_0
      76: aload         5
      78: iconst_0
      79: invokeinterface #197,  5          // InterfaceMethod org/bouncycastle/crypto/BlockCipher.processBlock:([BI[BI)I
      84: pop
      85: aload         4
      87: arraylength
      88: iload         6
      90: iload         7
      92: imul
      93: isub
      94: iload         7
      96: if_icmple     104
      99: iload         7
     101: goto          113
     104: aload         4
     106: arraylength
     107: iload         6
     109: iload         7
     111: imul
     112: isub
     113: istore        8
     115: aload         5
     117: iconst_0
     118: aload         4
     120: iload         6
     122: iload         7
     124: imul
     125: iload         8
     127: invokestatic  #177                // Method java/lang/System.arraycopy:(Ljava/lang/Object;ILjava/lang/Object;II)V
     130: iinc          6, 1
     133: goto          55
     136: aload_0
     137: aload         4
     139: aload_1
     140: aload         4
     142: iconst_0
     143: invokespecial #188                // Method XOR:([B[B[BI)V
     146: aload         4
     148: iconst_0
     149: aload_2
     150: iconst_0
     151: aload_2
     152: arraylength
     153: invokestatic  #177                // Method java/lang/System.arraycopy:(Ljava/lang/Object;ILjava/lang/Object;II)V
     156: aload         4
     158: aload_2
     159: arraylength
     160: aload_3
     161: iconst_0
     162: aload_3
     163: arraylength
     164: invokestatic  #177                // Method java/lang/System.arraycopy:(Ljava/lang/Object;ILjava/lang/Object;II)V
     167: return

  private void CTR_DRBG_Reseed_algorithm(byte[]);
    Code:
       0: aload_0
       1: invokespecial #179                // Method getEntropy:()[B
       4: aload_1
       5: invokestatic  #193                // Method org/bouncycastle/util/Arrays.concatenate:([B[B)[B
       8: astore_2
       9: aload_0
      10: aload_2
      11: aload_0
      12: getfield      #165                // Field _seedLength:I
      15: invokespecial #183                // Method Block_Cipher_df:([BI)[B
      18: astore_2
      19: aload_0
      20: aload_2
      21: aload_0
      22: getfield      #169                // Field _Key:[B
      25: aload_0
      26: getfield      #170                // Field _V:[B
      29: invokespecial #187                // Method CTR_DRBG_Update:([B[B[B)V
      32: aload_0
      33: lconst_1
      34: putfield      #166                // Field _reseedCounter:J
      37: return

  private void XOR(byte[], byte[], byte[], int);
    Code:
       0: iconst_0
       1: istore        5
       3: iload         5
       5: aload_1
       6: arraylength
       7: if_icmpge     33
      10: aload_1
      11: iload         5
      13: aload_2
      14: iload         5
      16: baload
      17: aload_3
      18: iload         5
      20: iload         4
      22: iadd
      23: baload
      24: ixor
      25: i2b
      26: bastore
      27: iinc          5, 1
      30: goto          3
      33: return

  private void addOneTo(byte[]);
    Code:
       0: iconst_1
       1: istore_2
       2: iconst_1
       3: istore_3
       4: iload_3
       5: aload_1
       6: arraylength
       7: if_icmpgt     53
      10: aload_1
      11: aload_1
      12: arraylength
      13: iload_3
      14: isub
      15: baload
      16: sipush        255
      19: iand
      20: iload_2
      21: iadd
      22: istore        4
      24: iload         4
      26: sipush        255
      29: if_icmple     36
      32: iconst_1
      33: goto          37
      36: iconst_0
      37: istore_2
      38: aload_1
      39: aload_1
      40: arraylength
      41: iload_3
      42: isub
      43: iload         4
      45: i2b
      46: bastore
      47: iinc          3, 1
      50: goto          4
      53: return

  private byte[] getEntropy();
    Code:
       0: aload_0
       1: getfield      #172                // Field _entropySource:Lorg/bouncycastle/crypto/prng/EntropySource;
       4: invokeinterface #201,  1          // InterfaceMethod org/bouncycastle/crypto/prng/EntropySource.getEntropy:()[B
       9: astore_1
      10: aload_1
      11: arraylength
      12: aload_0
      13: getfield      #164                // Field _securityStrength:I
      16: bipush        7
      18: iadd
      19: bipush        8
      21: idiv
      22: if_icmpge     35
      25: new           #103                // class java/lang/IllegalStateException
      28: dup
      29: ldc           #5                  // String Insufficient entropy provided by entropy source
      31: invokespecial #174                // Method java/lang/IllegalStateException."<init>":(Ljava/lang/String;)V
      34: athrow
      35: aload_1
      36: areturn

  private byte[] Block_Cipher_df(byte[], int);
    Code:
       0: aload_0
       1: getfield      #171                // Field _engine:Lorg/bouncycastle/crypto/BlockCipher;
       4: invokeinterface #196,  1          // InterfaceMethod org/bouncycastle/crypto/BlockCipher.getBlockSize:()I
       9: istore_3
      10: aload_1
      11: arraylength
      12: istore        4
      14: iload_2
      15: bipush        8
      17: idiv
      18: istore        5
      20: bipush        8
      22: iload         4
      24: iadd
      25: iconst_1
      26: iadd
      27: istore        6
      29: iload         6
      31: iload_3
      32: iadd
      33: iconst_1
      34: isub
      35: iload_3
      36: idiv
      37: iload_3
      38: imul
      39: istore        7
      41: iload         7
      43: newarray       byte
      45: astore        8
      47: aload_0
      48: aload         8
      50: iload         4
      52: iconst_0
      53: invokespecial #184                // Method copyIntToByteArray:([BII)V
      56: aload_0
      57: aload         8
      59: iload         5
      61: iconst_4
      62: invokespecial #184                // Method copyIntToByteArray:([BII)V
      65: aload_1
      66: iconst_0
      67: aload         8
      69: bipush        8
      71: iload         4
      73: invokestatic  #177                // Method java/lang/System.arraycopy:(Ljava/lang/Object;ILjava/lang/Object;II)V
      76: aload         8
      78: bipush        8
      80: iload         4
      82: iadd
      83: bipush        -128
      85: bastore
      86: aload_0
      87: getfield      #163                // Field _keySizeInBits:I
      90: bipush        8
      92: idiv
      93: iload_3
      94: iadd
      95: newarray       byte
      97: astore        9
      99: iload_3
     100: newarray       byte
     102: astore        10
     104: iload_3
     105: newarray       byte
     107: astore        11
     109: iconst_0
     110: istore        12
     112: aload_0
     113: getfield      #163                // Field _keySizeInBits:I
     116: bipush        8
     118: idiv
     119: newarray       byte
     121: astore        13
     123: getstatic     #168                // Field K_BITS:[B
     126: iconst_0
     127: aload         13
     129: iconst_0
     130: aload         13
     132: arraylength
     133: invokestatic  #177                // Method java/lang/System.arraycopy:(Ljava/lang/Object;ILjava/lang/Object;II)V
     136: iload         12
     138: iload_3
     139: imul
     140: bipush        8
     142: imul
     143: aload_0
     144: getfield      #163                // Field _keySizeInBits:I
     147: iload_3
     148: bipush        8
     150: imul
     151: iadd
     152: if_icmpge     222
     155: aload_0
     156: aload         11
     158: iload         12
     160: iconst_0
     161: invokespecial #184                // Method copyIntToByteArray:([BII)V
     164: aload_0
     165: aload         10
     167: aload         13
     169: aload         11
     171: aload         8
     173: invokespecial #189                // Method BCC:([B[B[B[B)V
     176: aload         9
     178: arraylength
     179: iload         12
     181: iload_3
     182: imul
     183: isub
     184: iload_3
     185: if_icmple     192
     188: iload_3
     189: goto          200
     192: aload         9
     194: arraylength
     195: iload         12
     197: iload_3
     198: imul
     199: isub
     200: istore        14
     202: aload         10
     204: iconst_0
     205: aload         9
     207: iload         12
     209: iload_3
     210: imul
     211: iload         14
     213: invokestatic  #177                // Method java/lang/System.arraycopy:(Ljava/lang/Object;ILjava/lang/Object;II)V
     216: iinc          12, 1
     219: goto          136
     222: iload_3
     223: newarray       byte
     225: astore        14
     227: aload         9
     229: iconst_0
     230: aload         13
     232: iconst_0
     233: aload         13
     235: arraylength
     236: invokestatic  #177                // Method java/lang/System.arraycopy:(Ljava/lang/Object;ILjava/lang/Object;II)V
     239: aload         9
     241: aload         13
     243: arraylength
     244: aload         14
     246: iconst_0
     247: aload         14
     249: arraylength
     250: invokestatic  #177                // Method java/lang/System.arraycopy:(Ljava/lang/Object;ILjava/lang/Object;II)V
     253: iload_2
     254: iconst_2
     255: idiv
     256: newarray       byte
     258: astore        9
     260: iconst_0
     261: istore        12
     263: aload_0
     264: getfield      #171                // Field _engine:Lorg/bouncycastle/crypto/BlockCipher;
     267: iconst_1
     268: new           #108                // class org/bouncycastle/crypto/params/KeyParameter
     271: dup
     272: aload_0
     273: aload         13
     275: invokevirtual #182                // Method expandKey:([B)[B
     278: invokespecial #178                // Method org/bouncycastle/crypto/params/KeyParameter."<init>":([B)V
     281: invokeinterface #199,  3          // InterfaceMethod org/bouncycastle/crypto/BlockCipher.init:(ZLorg/bouncycastle/crypto/CipherParameters;)V
     286: iload         12
     288: iload_3
     289: imul
     290: aload         9
     292: arraylength
     293: if_icmpge     358
     296: aload_0
     297: getfield      #171                // Field _engine:Lorg/bouncycastle/crypto/BlockCipher;
     300: aload         14
     302: iconst_0
     303: aload         14
     305: iconst_0
     306: invokeinterface #197,  5          // InterfaceMethod org/bouncycastle/crypto/BlockCipher.processBlock:([BI[BI)I
     311: pop
     312: aload         9
     314: arraylength
     315: iload         12
     317: iload_3
     318: imul
     319: isub
     320: iload_3
     321: if_icmple     328
     324: iload_3
     325: goto          336
     328: aload         9
     330: arraylength
     331: iload         12
     333: iload_3
     334: imul
     335: isub
     336: istore        15
     338: aload         14
     340: iconst_0
     341: aload         9
     343: iload         12
     345: iload_3
     346: imul
     347: iload         15
     349: invokestatic  #177                // Method java/lang/System.arraycopy:(Ljava/lang/Object;ILjava/lang/Object;II)V
     352: iinc          12, 1
     355: goto          286
     358: aload         9
     360: areturn

  private void BCC(byte[], byte[], byte[], byte[]);
    Code:
       0: aload_0
       1: getfield      #171                // Field _engine:Lorg/bouncycastle/crypto/BlockCipher;
       4: invokeinterface #196,  1          // InterfaceMethod org/bouncycastle/crypto/BlockCipher.getBlockSize:()I
       9: istore        5
      11: iload         5
      13: newarray       byte
      15: astore        6
      17: aload         4
      19: arraylength
      20: iload         5
      22: idiv
      23: istore        7
      25: iload         5
      27: newarray       byte
      29: astore        8
      31: aload_0
      32: getfield      #171                // Field _engine:Lorg/bouncycastle/crypto/BlockCipher;
      35: iconst_1
      36: new           #108                // class org/bouncycastle/crypto/params/KeyParameter
      39: dup
      40: aload_0
      41: aload_2
      42: invokevirtual #182                // Method expandKey:([B)[B
      45: invokespecial #178                // Method org/bouncycastle/crypto/params/KeyParameter."<init>":([B)V
      48: invokeinterface #199,  3          // InterfaceMethod org/bouncycastle/crypto/BlockCipher.init:(ZLorg/bouncycastle/crypto/CipherParameters;)V
      53: aload_0
      54: getfield      #171                // Field _engine:Lorg/bouncycastle/crypto/BlockCipher;
      57: aload_3
      58: iconst_0
      59: aload         6
      61: iconst_0
      62: invokeinterface #197,  5          // InterfaceMethod org/bouncycastle/crypto/BlockCipher.processBlock:([BI[BI)I
      67: pop
      68: iconst_0
      69: istore        9
      71: iload         9
      73: iload         7
      75: if_icmpge     115
      78: aload_0
      79: aload         8
      81: aload         6
      83: aload         4
      85: iload         9
      87: iload         5
      89: imul
      90: invokespecial #188                // Method XOR:([B[B[BI)V
      93: aload_0
      94: getfield      #171                // Field _engine:Lorg/bouncycastle/crypto/BlockCipher;
      97: aload         8
      99: iconst_0
     100: aload         6
     102: iconst_0
     103: invokeinterface #197,  5          // InterfaceMethod org/bouncycastle/crypto/BlockCipher.processBlock:([BI[BI)I
     108: pop
     109: iinc          9, 1
     112: goto          71
     115: aload         6
     117: iconst_0
     118: aload_1
     119: iconst_0
     120: aload_1
     121: arraylength
     122: invokestatic  #177                // Method java/lang/System.arraycopy:(Ljava/lang/Object;ILjava/lang/Object;II)V
     125: return

  private void copyIntToByteArray(byte[], int, int);
    Code:
       0: aload_1
       1: iload_3
       2: iconst_0
       3: iadd
       4: iload_2
       5: bipush        24
       7: ishr
       8: i2b
       9: bastore
      10: aload_1
      11: iload_3
      12: iconst_1
      13: iadd
      14: iload_2
      15: bipush        16
      17: ishr
      18: i2b
      19: bastore
      20: aload_1
      21: iload_3
      22: iconst_2
      23: iadd
      24: iload_2
      25: bipush        8
      27: ishr
      28: i2b
      29: bastore
      30: aload_1
      31: iload_3
      32: iconst_3
      33: iadd
      34: iload_2
      35: i2b
      36: bastore
      37: return

  public int getBlockSize();
    Code:
       0: aload_0
       1: getfield      #170                // Field _V:[B
       4: arraylength
       5: bipush        8
       7: imul
       8: ireturn

  public int generate(byte[], byte[], boolean);
    Code:
       0: aload_0
       1: getfield      #167                // Field _isTDEA:Z
       4: ifeq          40
       7: aload_0
       8: getfield      #166                // Field _reseedCounter:J
      11: ldc2_w        #98                 // long 2147483648l
      14: lcmp
      15: ifle          20
      18: iconst_m1
      19: ireturn
      20: aload_1
      21: sipush        512
      24: invokestatic  #192                // Method org/bouncycastle/crypto/prng/drbg/Utils.isTooLarge:([BI)Z
      27: ifeq          72
      30: new           #102                // class java/lang/IllegalArgumentException
      33: dup
      34: ldc           #8                  // String Number of bits per request limited to 4096
      36: invokespecial #173                // Method java/lang/IllegalArgumentException."<init>":(Ljava/lang/String;)V
      39: athrow
      40: aload_0
      41: getfield      #166                // Field _reseedCounter:J
      44: ldc2_w        #100                // long 140737488355328l
      47: lcmp
      48: ifle          53
      51: iconst_m1
      52: ireturn
      53: aload_1
      54: ldc           #1                  // int 32768
      56: invokestatic  #192                // Method org/bouncycastle/crypto/prng/drbg/Utils.isTooLarge:([BI)Z
      59: ifeq          72
      62: new           #102                // class java/lang/IllegalArgumentException
      65: dup
      66: ldc           #7                  // String Number of bits per request limited to 262144
      68: invokespecial #173                // Method java/lang/IllegalArgumentException."<init>":(Ljava/lang/String;)V
      71: athrow
      72: iload_3
      73: ifeq          83
      76: aload_0
      77: aload_2
      78: invokespecial #180                // Method CTR_DRBG_Reseed_algorithm:([B)V
      81: aconst_null
      82: astore_2
      83: aload_2
      84: ifnull        113
      87: aload_0
      88: aload_2
      89: aload_0
      90: getfield      #165                // Field _seedLength:I
      93: invokespecial #183                // Method Block_Cipher_df:([BI)[B
      96: astore_2
      97: aload_0
      98: aload_2
      99: aload_0
     100: getfield      #169                // Field _Key:[B
     103: aload_0
     104: getfield      #170                // Field _V:[B
     107: invokespecial #187                // Method CTR_DRBG_Update:([B[B[B)V
     110: goto          120
     113: aload_0
     114: getfield      #165                // Field _seedLength:I
     117: newarray       byte
     119: astore_2
     120: aload_0
     121: getfield      #170                // Field _V:[B
     124: arraylength
     125: newarray       byte
     127: astore        4
     129: aload_0
     130: getfield      #171                // Field _engine:Lorg/bouncycastle/crypto/BlockCipher;
     133: iconst_1
     134: new           #108                // class org/bouncycastle/crypto/params/KeyParameter
     137: dup
     138: aload_0
     139: aload_0
     140: getfield      #169                // Field _Key:[B
     143: invokevirtual #182                // Method expandKey:([B)[B
     146: invokespecial #178                // Method org/bouncycastle/crypto/params/KeyParameter."<init>":([B)V
     149: invokeinterface #199,  3          // InterfaceMethod org/bouncycastle/crypto/BlockCipher.init:(ZLorg/bouncycastle/crypto/CipherParameters;)V
     154: iconst_0
     155: istore        5
     157: iload         5
     159: aload_1
     160: arraylength
     161: aload         4
     163: arraylength
     164: idiv
     165: if_icmpgt     254
     168: aload_1
     169: arraylength
     170: iload         5
     172: aload         4
     174: arraylength
     175: imul
     176: isub
     177: aload         4
     179: arraylength
     180: if_icmple     189
     183: aload         4
     185: arraylength
     186: goto          200
     189: aload_1
     190: arraylength
     191: iload         5
     193: aload_0
     194: getfield      #170                // Field _V:[B
     197: arraylength
     198: imul
     199: isub
     200: istore        6
     202: iload         6
     204: ifeq          248
     207: aload_0
     208: aload_0
     209: getfield      #170                // Field _V:[B
     212: invokespecial #181                // Method addOneTo:([B)V
     215: aload_0
     216: getfield      #171                // Field _engine:Lorg/bouncycastle/crypto/BlockCipher;
     219: aload_0
     220: getfield      #170                // Field _V:[B
     223: iconst_0
     224: aload         4
     226: iconst_0
     227: invokeinterface #197,  5          // InterfaceMethod org/bouncycastle/crypto/BlockCipher.processBlock:([BI[BI)I
     232: pop
     233: aload         4
     235: iconst_0
     236: aload_1
     237: iload         5
     239: aload         4
     241: arraylength
     242: imul
     243: iload         6
     245: invokestatic  #177                // Method java/lang/System.arraycopy:(Ljava/lang/Object;ILjava/lang/Object;II)V
     248: iinc          5, 1
     251: goto          157
     254: aload_0
     255: aload_2
     256: aload_0
     257: getfield      #169                // Field _Key:[B
     260: aload_0
     261: getfield      #170                // Field _V:[B
     264: invokespecial #187                // Method CTR_DRBG_Update:([B[B[B)V
     267: aload_0
     268: dup
     269: getfield      #166                // Field _reseedCounter:J
     272: lconst_1
     273: ladd
     274: putfield      #166                // Field _reseedCounter:J
     277: aload_1
     278: arraylength
     279: bipush        8
     281: imul
     282: ireturn

  public void reseed(byte[]);
    Code:
       0: aload_0
       1: aload_1
       2: invokespecial #180                // Method CTR_DRBG_Reseed_algorithm:([B)V
       5: return

  private boolean isTDEA(org.bouncycastle.crypto.BlockCipher);
    Code:
       0: aload_1
       1: invokeinterface #198,  1          // InterfaceMethod org/bouncycastle/crypto/BlockCipher.getAlgorithmName:()Ljava/lang/String;
       6: ldc           #4                  // String DESede
       8: invokevirtual #176                // Method java/lang/String.equals:(Ljava/lang/Object;)Z
      11: ifne          28
      14: aload_1
      15: invokeinterface #198,  1          // InterfaceMethod org/bouncycastle/crypto/BlockCipher.getAlgorithmName:()Ljava/lang/String;
      20: ldc           #11                 // String TDEA
      22: invokevirtual #176                // Method java/lang/String.equals:(Ljava/lang/Object;)Z
      25: ifeq          32
      28: iconst_1
      29: goto          33
      32: iconst_0
      33: ireturn

  private int getMaxSecurityStrength(org.bouncycastle.crypto.BlockCipher, int);
    Code:
       0: aload_0
       1: aload_1
       2: invokespecial #190                // Method isTDEA:(Lorg/bouncycastle/crypto/BlockCipher;)Z
       5: ifeq          18
       8: iload_2
       9: sipush        168
      12: if_icmpne     18
      15: bipush        112
      17: ireturn
      18: aload_1
      19: invokeinterface #198,  1          // InterfaceMethod org/bouncycastle/crypto/BlockCipher.getAlgorithmName:()Ljava/lang/String;
      24: ldc           #3                  // String AES
      26: invokevirtual #176                // Method java/lang/String.equals:(Ljava/lang/Object;)Z
      29: ifeq          34
      32: iload_2
      33: ireturn
      34: iconst_m1
      35: ireturn

  byte[] expandKey(byte[]);
    Code:
       0: aload_0
       1: getfield      #167                // Field _isTDEA:Z
       4: ifeq          42
       7: bipush        24
       9: newarray       byte
      11: astore_2
      12: aload_0
      13: aload_1
      14: iconst_0
      15: aload_2
      16: iconst_0
      17: invokespecial #185                // Method padKey:([BI[BI)V
      20: aload_0
      21: aload_1
      22: bipush        7
      24: aload_2
      25: bipush        8
      27: invokespecial #185                // Method padKey:([BI[BI)V
      30: aload_0
      31: aload_1
      32: bipush        14
      34: aload_2
      35: bipush        16
      37: invokespecial #185                // Method padKey:([BI[BI)V
      40: aload_2
      41: areturn
      42: aload_1
      43: areturn

  private void padKey(byte[], int, byte[], int);
    Code:
       0: aload_3
       1: iload         4
       3: iconst_0
       4: iadd
       5: aload_1
       6: iload_2
       7: iconst_0
       8: iadd
       9: baload
      10: sipush        254
      13: iand
      14: i2b
      15: bastore
      16: aload_3
      17: iload         4
      19: iconst_1
      20: iadd
      21: aload_1
      22: iload_2
      23: iconst_0
      24: iadd
      25: baload
      26: bipush        7
      28: ishl
      29: aload_1
      30: iload_2
      31: iconst_1
      32: iadd
      33: baload
      34: sipush        252
      37: iand
      38: iconst_1
      39: iushr
      40: ior
      41: i2b
      42: bastore
      43: aload_3
      44: iload         4
      46: iconst_2
      47: iadd
      48: aload_1
      49: iload_2
      50: iconst_1
      51: iadd
      52: baload
      53: bipush        6
      55: ishl
      56: aload_1
      57: iload_2
      58: iconst_2
      59: iadd
      60: baload
      61: sipush        248
      64: iand
      65: iconst_2
      66: iushr
      67: ior
      68: i2b
      69: bastore
      70: aload_3
      71: iload         4
      73: iconst_3
      74: iadd
      75: aload_1
      76: iload_2
      77: iconst_2
      78: iadd
      79: baload
      80: iconst_5
      81: ishl
      82: aload_1
      83: iload_2
      84: iconst_3
      85: iadd
      86: baload
      87: sipush        240
      90: iand
      91: iconst_3
      92: iushr
      93: ior
      94: i2b
      95: bastore
      96: aload_3
      97: iload         4
      99: iconst_4
     100: iadd
     101: aload_1
     102: iload_2
     103: iconst_3
     104: iadd
     105: baload
     106: iconst_4
     107: ishl
     108: aload_1
     109: iload_2
     110: iconst_4
     111: iadd
     112: baload
     113: sipush        224
     116: iand
     117: iconst_4
     118: iushr
     119: ior
     120: i2b
     121: bastore
     122: aload_3
     123: iload         4
     125: iconst_5
     126: iadd
     127: aload_1
     128: iload_2
     129: iconst_4
     130: iadd
     131: baload
     132: iconst_3
     133: ishl
     134: aload_1
     135: iload_2
     136: iconst_5
     137: iadd
     138: baload
     139: sipush        192
     142: iand
     143: iconst_5
     144: iushr
     145: ior
     146: i2b
     147: bastore
     148: aload_3
     149: iload         4
     151: bipush        6
     153: iadd
     154: aload_1
     155: iload_2
     156: iconst_5
     157: iadd
     158: baload
     159: iconst_2
     160: ishl
     161: aload_1
     162: iload_2
     163: bipush        6
     165: iadd
     166: baload
     167: sipush        128
     170: iand
     171: bipush        6
     173: iushr
     174: ior
     175: i2b
     176: bastore
     177: aload_3
     178: iload         4
     180: bipush        7
     182: iadd
     183: aload_1
     184: iload_2
     185: bipush        6
     187: iadd
     188: baload
     189: iconst_1
     190: ishl
     191: i2b
     192: bastore
     193: iload         4
     195: istore        5
     197: iload         5
     199: iload         4
     201: bipush        7
     203: iadd
     204: if_icmpgt     271
     207: aload_3
     208: iload         5
     210: baload
     211: istore        6
     213: aload_3
     214: iload         5
     216: iload         6
     218: sipush        254
     221: iand
     222: iload         6
     224: iconst_1
     225: ishr
     226: iload         6
     228: iconst_2
     229: ishr
     230: ixor
     231: iload         6
     233: iconst_3
     234: ishr
     235: ixor
     236: iload         6
     238: iconst_4
     239: ishr
     240: ixor
     241: iload         6
     243: iconst_5
     244: ishr
     245: ixor
     246: iload         6
     248: bipush        6
     250: ishr
     251: ixor
     252: iload         6
     254: bipush        7
     256: ishr
     257: ixor
     258: iconst_1
     259: ixor
     260: iconst_1
     261: iand
     262: ior
     263: i2b
     264: bastore
     265: iinc          5, 1
     268: goto          197
     271: return

  static {};
    Code:
       0: ldc           #2                  // String 000102030405060708090A0B0C0D0E0F101112131415161718191A1B1C1D1E1F
       2: invokestatic  #195                // Method org/bouncycastle/util/encoders/Hex.decode:(Ljava/lang/String;)[B
       5: putstatic     #168                // Field K_BITS:[B
       8: return
}
