Compiled from "IgnoreExtraResponsesValidityFilter.java"
public final class org.infinispan.remoting.responses.IgnoreExtraResponsesValidityFilter implements org.infinispan.remoting.rpc.ResponseFilter {
  private final java.util.Set<org.infinispan.remoting.transport.Address> targets;

  private int missingResponses;

  public org.infinispan.remoting.responses.IgnoreExtraResponsesValidityFilter(java.util.Collection<org.infinispan.remoting.transport.Address>, org.infinispan.remoting.transport.Address, boolean);
    Code:
       0: aload_0
       1: invokespecial #1                  // Method java/lang/Object."<init>":()V
       4: aload_0
       5: new           #2                  // class java/util/HashSet
       8: dup
       9: aload_1
      10: invokespecial #3                  // Method java/util/HashSet."<init>":(Ljava/util/Collection;)V
      13: putfield      #4                  // Field targets:Ljava/util/Set;
      16: aload_0
      17: aload_1
      18: invokeinterface #5,  1            // InterfaceMethod java/util/Collection.size:()I
      23: putfield      #6                  // Field missingResponses:I
      26: iload_3
      27: ifeq          53
      30: aload_0
      31: getfield      #4                  // Field targets:Ljava/util/Set;
      34: aload_2
      35: invokeinterface #7,  2            // InterfaceMethod java/util/Set.contains:(Ljava/lang/Object;)Z
      40: ifeq          53
      43: aload_0
      44: dup
      45: getfield      #6                  // Field missingResponses:I
      48: iconst_1
      49: isub
      50: putfield      #6                  // Field missingResponses:I
      53: return

  public boolean isAcceptable(org.infinispan.remoting.responses.Response, org.infinispan.remoting.transport.Address);
    Code:
       0: aload_0
       1: getfield      #4                  // Field targets:Ljava/util/Set;
       4: aload_2
       5: invokeinterface #7,  2            // InterfaceMethod java/util/Set.contains:(Ljava/lang/Object;)Z
      10: ifeq          23
      13: aload_0
      14: dup
      15: getfield      #6                  // Field missingResponses:I
      18: iconst_1
      19: isub
      20: putfield      #6                  // Field missingResponses:I
      23: iconst_1
      24: ireturn

  public boolean needMoreResponses();
    Code:
       0: aload_0
       1: getfield      #6                  // Field missingResponses:I
       4: ifle          11
       7: iconst_1
       8: goto          12
      11: iconst_0
      12: ireturn
}
