Compiled from "AbstractEndpointMvcAdapter.java"
public abstract class org.springframework.boot.actuate.endpoint.mvc.AbstractEndpointMvcAdapter<E extends org.springframework.boot.actuate.endpoint.Endpoint<?>> implements org.springframework.boot.actuate.endpoint.mvc.MvcEndpoint {
  private final E delegate;

  private java.lang.String path;

  public org.springframework.boot.actuate.endpoint.mvc.AbstractEndpointMvcAdapter(E);
    Code:
       0: aload_0
       1: invokespecial #1                  // Method java/lang/Object."<init>":()V
       4: aload_1
       5: ldc           #2                  // String Delegate must not be null
       7: invokestatic  #3                  // Method org/springframework/util/Assert.notNull:(Ljava/lang/Object;Ljava/lang/String;)V
      10: aload_0
      11: aload_1
      12: putfield      #4                  // Field delegate:Lorg/springframework/boot/actuate/endpoint/Endpoint;
      15: return

  protected java.lang.Object invoke();
    Code:
       0: aload_0
       1: getfield      #4                  // Field delegate:Lorg/springframework/boot/actuate/endpoint/Endpoint;
       4: invokeinterface #5,  1            // InterfaceMethod org/springframework/boot/actuate/endpoint/Endpoint.isEnabled:()Z
       9: ifne          17
      12: aload_0
      13: invokevirtual #6                  // Method getDisabledResponse:()Lorg/springframework/http/ResponseEntity;
      16: areturn
      17: aload_0
      18: getfield      #4                  // Field delegate:Lorg/springframework/boot/actuate/endpoint/Endpoint;
      21: invokeinterface #7,  1            // InterfaceMethod org/springframework/boot/actuate/endpoint/Endpoint.invoke:()Ljava/lang/Object;
      26: areturn

  public E getDelegate();
    Code:
       0: aload_0
       1: getfield      #4                  // Field delegate:Lorg/springframework/boot/actuate/endpoint/Endpoint;
       4: areturn

  public java.lang.String getPath();
    Code:
       0: aload_0
       1: getfield      #8                  // Field path:Ljava/lang/String;
       4: ifnull        14
       7: aload_0
       8: getfield      #8                  // Field path:Ljava/lang/String;
      11: goto          41
      14: new           #9                  // class java/lang/StringBuilder
      17: dup
      18: invokespecial #10                 // Method java/lang/StringBuilder."<init>":()V
      21: ldc           #11                 // String /
      23: invokevirtual #12                 // Method java/lang/StringBuilder.append:(Ljava/lang/String;)Ljava/lang/StringBuilder;
      26: aload_0
      27: getfield      #4                  // Field delegate:Lorg/springframework/boot/actuate/endpoint/Endpoint;
      30: invokeinterface #13,  1           // InterfaceMethod org/springframework/boot/actuate/endpoint/Endpoint.getId:()Ljava/lang/String;
      35: invokevirtual #12                 // Method java/lang/StringBuilder.append:(Ljava/lang/String;)Ljava/lang/StringBuilder;
      38: invokevirtual #14                 // Method java/lang/StringBuilder.toString:()Ljava/lang/String;
      41: areturn

  public void setPath(java.lang.String);
    Code:
       0: aload_1
       1: ldc           #11                 // String /
       3: invokevirtual #15                 // Method java/lang/String.endsWith:(Ljava/lang/String;)Z
       6: ifeq          24
       9: aload_1
      10: iconst_0
      11: aload_1
      12: invokevirtual #16                 // Method java/lang/String.length:()I
      15: iconst_1
      16: isub
      17: invokevirtual #17                 // Method java/lang/String.substring:(II)Ljava/lang/String;
      20: astore_1
      21: goto          0
      24: aload_1
      25: ldc           #11                 // String /
      27: invokevirtual #18                 // Method java/lang/String.startsWith:(Ljava/lang/String;)Z
      30: ifne          53
      33: new           #9                  // class java/lang/StringBuilder
      36: dup
      37: invokespecial #10                 // Method java/lang/StringBuilder."<init>":()V
      40: ldc           #11                 // String /
      42: invokevirtual #12                 // Method java/lang/StringBuilder.append:(Ljava/lang/String;)Ljava/lang/StringBuilder;
      45: aload_1
      46: invokevirtual #12                 // Method java/lang/StringBuilder.append:(Ljava/lang/String;)Ljava/lang/StringBuilder;
      49: invokevirtual #14                 // Method java/lang/StringBuilder.toString:()Ljava/lang/String;
      52: astore_1
      53: aload_0
      54: aload_1
      55: putfield      #8                  // Field path:Ljava/lang/String;
      58: return

  public boolean isSensitive();
    Code:
       0: aload_0
       1: getfield      #4                  // Field delegate:Lorg/springframework/boot/actuate/endpoint/Endpoint;
       4: invokeinterface #19,  1           // InterfaceMethod org/springframework/boot/actuate/endpoint/Endpoint.isSensitive:()Z
       9: ireturn

  public java.lang.Class<? extends org.springframework.boot.actuate.endpoint.Endpoint> getEndpointType();
    Code:
       0: aload_0
       1: getfield      #4                  // Field delegate:Lorg/springframework/boot/actuate/endpoint/Endpoint;
       4: invokevirtual #20                 // Method java/lang/Object.getClass:()Ljava/lang/Class;
       7: areturn

  protected org.springframework.http.ResponseEntity<?> getDisabledResponse();
    Code:
       0: getstatic     #21                 // Field org/springframework/boot/actuate/endpoint/mvc/MvcEndpoint.DISABLED_RESPONSE:Lorg/springframework/http/ResponseEntity;
       3: areturn
}
