Compiled from "EnvironmentMvcEndpoint.java"
class org.springframework.boot.actuate.endpoint.mvc.EnvironmentMvcEndpoint$NamePatternEnvironmentFilter extends org.springframework.boot.actuate.endpoint.mvc.NamePatternFilter<org.springframework.core.env.Environment> {
  final org.springframework.boot.actuate.endpoint.mvc.EnvironmentMvcEndpoint this$0;

  org.springframework.boot.actuate.endpoint.mvc.EnvironmentMvcEndpoint$NamePatternEnvironmentFilter(org.springframework.boot.actuate.endpoint.mvc.EnvironmentMvcEndpoint, org.springframework.core.env.Environment);
    Code:
       0: aload_0
       1: aload_1
       2: putfield      #1                  // Field this$0:Lorg/springframework/boot/actuate/endpoint/mvc/EnvironmentMvcEndpoint;
       5: aload_0
       6: aload_2
       7: invokespecial #2                  // Method org/springframework/boot/actuate/endpoint/mvc/NamePatternFilter."<init>":(Ljava/lang/Object;)V
      10: return

  protected void getNames(org.springframework.core.env.Environment, org.springframework.boot.actuate.endpoint.mvc.NamePatternFilter$NameCallback);
    Code:
       0: aload_1
       1: instanceof    #3                  // class org/springframework/core/env/ConfigurableEnvironment
       4: ifeq          21
       7: aload_0
       8: aload_1
       9: checkcast     #3                  // class org/springframework/core/env/ConfigurableEnvironment
      12: invokeinterface #4,  1            // InterfaceMethod org/springframework/core/env/ConfigurableEnvironment.getPropertySources:()Lorg/springframework/core/env/MutablePropertySources;
      17: aload_2
      18: invokespecial #5                  // Method getNames:(Lorg/springframework/core/env/PropertySources;Lorg/springframework/boot/actuate/endpoint/mvc/NamePatternFilter$NameCallback;)V
      21: return

  private void getNames(org.springframework.core.env.PropertySources, org.springframework.boot.actuate.endpoint.mvc.NamePatternFilter$NameCallback);
    Code:
       0: aload_1
       1: invokeinterface #6,  1            // InterfaceMethod org/springframework/core/env/PropertySources.iterator:()Ljava/util/Iterator;
       6: astore_3
       7: aload_3
       8: invokeinterface #7,  1            // InterfaceMethod java/util/Iterator.hasNext:()Z
      13: ifeq          88
      16: aload_3
      17: invokeinterface #8,  1            // InterfaceMethod java/util/Iterator.next:()Ljava/lang/Object;
      22: checkcast     #9                  // class org/springframework/core/env/PropertySource
      25: astore        4
      27: aload         4
      29: instanceof    #10                 // class org/springframework/core/env/EnumerablePropertySource
      32: ifeq          85
      35: aload         4
      37: checkcast     #10                 // class org/springframework/core/env/EnumerablePropertySource
      40: astore        5
      42: aload         5
      44: invokevirtual #11                 // Method org/springframework/core/env/EnumerablePropertySource.getPropertyNames:()[Ljava/lang/String;
      47: astore        6
      49: aload         6
      51: arraylength
      52: istore        7
      54: iconst_0
      55: istore        8
      57: iload         8
      59: iload         7
      61: if_icmpge     85
      64: aload         6
      66: iload         8
      68: aaload
      69: astore        9
      71: aload_2
      72: aload         9
      74: invokeinterface #12,  2           // InterfaceMethod org/springframework/boot/actuate/endpoint/mvc/NamePatternFilter$NameCallback.addName:(Ljava/lang/String;)V
      79: iinc          8, 1
      82: goto          57
      85: goto          7
      88: return

  protected java.lang.Object getOptionalValue(org.springframework.core.env.Environment, java.lang.String);
    Code:
       0: aload_1
       1: aload_2
       2: invokeinterface #13,  2           // InterfaceMethod org/springframework/core/env/Environment.getProperty:(Ljava/lang/String;)Ljava/lang/String;
       7: astore_3
       8: aload_3
       9: ifnull        28
      12: aload_0
      13: getfield      #1                  // Field this$0:Lorg/springframework/boot/actuate/endpoint/mvc/EnvironmentMvcEndpoint;
      16: invokevirtual #14                 // Method org/springframework/boot/actuate/endpoint/mvc/EnvironmentMvcEndpoint.getDelegate:()Lorg/springframework/boot/actuate/endpoint/Endpoint;
      19: checkcast     #15                 // class org/springframework/boot/actuate/endpoint/EnvironmentEndpoint
      22: aload_2
      23: aload_3
      24: invokevirtual #16                 // Method org/springframework/boot/actuate/endpoint/EnvironmentEndpoint.sanitize:(Ljava/lang/String;Ljava/lang/Object;)Ljava/lang/Object;
      27: astore_3
      28: aload_3
      29: areturn

  protected java.lang.Object getValue(org.springframework.core.env.Environment, java.lang.String);
    Code:
       0: aload_1
       1: aload_2
       2: invokeinterface #13,  2           // InterfaceMethod org/springframework/core/env/Environment.getProperty:(Ljava/lang/String;)Ljava/lang/String;
       7: astore_3
       8: aload_3
       9: ifnonnull     39
      12: new           #17                 // class org/springframework/boot/actuate/endpoint/mvc/EnvironmentMvcEndpoint$NoSuchPropertyException
      15: dup
      16: new           #18                 // class java/lang/StringBuilder
      19: dup
      20: invokespecial #19                 // Method java/lang/StringBuilder."<init>":()V
      23: ldc           #20                 // String No such property:
      25: invokevirtual #21                 // Method java/lang/StringBuilder.append:(Ljava/lang/String;)Ljava/lang/StringBuilder;
      28: aload_2
      29: invokevirtual #21                 // Method java/lang/StringBuilder.append:(Ljava/lang/String;)Ljava/lang/StringBuilder;
      32: invokevirtual #22                 // Method java/lang/StringBuilder.toString:()Ljava/lang/String;
      35: invokespecial #23                 // Method org/springframework/boot/actuate/endpoint/mvc/EnvironmentMvcEndpoint$NoSuchPropertyException."<init>":(Ljava/lang/String;)V
      38: athrow
      39: aload_0
      40: getfield      #1                  // Field this$0:Lorg/springframework/boot/actuate/endpoint/mvc/EnvironmentMvcEndpoint;
      43: invokevirtual #14                 // Method org/springframework/boot/actuate/endpoint/mvc/EnvironmentMvcEndpoint.getDelegate:()Lorg/springframework/boot/actuate/endpoint/Endpoint;
      46: checkcast     #15                 // class org/springframework/boot/actuate/endpoint/EnvironmentEndpoint
      49: aload_2
      50: aload_3
      51: invokevirtual #16                 // Method org/springframework/boot/actuate/endpoint/EnvironmentEndpoint.sanitize:(Ljava/lang/String;Ljava/lang/Object;)Ljava/lang/Object;
      54: areturn

  protected java.lang.Object getOptionalValue(java.lang.Object, java.lang.String);
    Code:
       0: aload_0
       1: aload_1
       2: checkcast     #24                 // class org/springframework/core/env/Environment
       5: aload_2
       6: invokevirtual #25                 // Method getOptionalValue:(Lorg/springframework/core/env/Environment;Ljava/lang/String;)Ljava/lang/Object;
       9: areturn

  protected java.lang.Object getValue(java.lang.Object, java.lang.String);
    Code:
       0: aload_0
       1: aload_1
       2: checkcast     #24                 // class org/springframework/core/env/Environment
       5: aload_2
       6: invokevirtual #26                 // Method getValue:(Lorg/springframework/core/env/Environment;Ljava/lang/String;)Ljava/lang/Object;
       9: areturn

  protected void getNames(java.lang.Object, org.springframework.boot.actuate.endpoint.mvc.NamePatternFilter$NameCallback);
    Code:
       0: aload_0
       1: aload_1
       2: checkcast     #24                 // class org/springframework/core/env/Environment
       5: aload_2
       6: invokevirtual #27                 // Method getNames:(Lorg/springframework/core/env/Environment;Lorg/springframework/boot/actuate/endpoint/mvc/NamePatternFilter$NameCallback;)V
       9: return
}
