Compiled from "JolokiaMvcEndpoint.java"
class org.springframework.boot.actuate.endpoint.mvc.JolokiaMvcEndpoint$PathStripper extends javax.servlet.http.HttpServletRequestWrapper {
  private final java.lang.String path;

  private final org.springframework.web.util.UrlPathHelper urlPathHelper;

  org.springframework.boot.actuate.endpoint.mvc.JolokiaMvcEndpoint$PathStripper(javax.servlet.http.HttpServletRequest, java.lang.String);
    Code:
       0: aload_0
       1: aload_1
       2: invokespecial #1                  // Method javax/servlet/http/HttpServletRequestWrapper."<init>":(Ljavax/servlet/http/HttpServletRequest;)V
       5: aload_0
       6: aload_2
       7: putfield      #2                  // Field path:Ljava/lang/String;
      10: aload_0
      11: new           #3                  // class org/springframework/web/util/UrlPathHelper
      14: dup
      15: invokespecial #4                  // Method org/springframework/web/util/UrlPathHelper."<init>":()V
      18: putfield      #5                  // Field urlPathHelper:Lorg/springframework/web/util/UrlPathHelper;
      21: return

  public java.lang.String getPathInfo();
    Code:
       0: aload_0
       1: getfield      #5                  // Field urlPathHelper:Lorg/springframework/web/util/UrlPathHelper;
       4: aload_0
       5: invokevirtual #6                  // Method getRequest:()Ljavax/servlet/ServletRequest;
       8: checkcast     #7                  // class javax/servlet/http/HttpServletRequest
      11: aload_0
      12: invokespecial #8                  // Method javax/servlet/http/HttpServletRequestWrapper.getRequestURI:()Ljava/lang/String;
      15: invokevirtual #9                  // Method org/springframework/web/util/UrlPathHelper.decodeRequestString:(Ljavax/servlet/http/HttpServletRequest;Ljava/lang/String;)Ljava/lang/String;
      18: astore_1
      19: aload_1
      20: aload_0
      21: getfield      #2                  // Field path:Ljava/lang/String;
      24: invokevirtual #10                 // Method java/lang/String.contains:(Ljava/lang/CharSequence;)Z
      27: ifeq          51
      30: aload_1
      31: aload_1
      32: aload_0
      33: getfield      #2                  // Field path:Ljava/lang/String;
      36: invokevirtual #11                 // Method java/lang/String.indexOf:(Ljava/lang/String;)I
      39: aload_0
      40: getfield      #2                  // Field path:Ljava/lang/String;
      43: invokevirtual #12                 // Method java/lang/String.length:()I
      46: iadd
      47: invokevirtual #13                 // Method java/lang/String.substring:(I)Ljava/lang/String;
      50: astore_1
      51: aload_1
      52: ldc           #14                 // String ?
      54: invokevirtual #11                 // Method java/lang/String.indexOf:(Ljava/lang/String;)I
      57: istore_2
      58: iload_2
      59: ifle          69
      62: aload_1
      63: iconst_0
      64: iload_2
      65: invokevirtual #15                 // Method java/lang/String.substring:(II)Ljava/lang/String;
      68: astore_1
      69: aload_1
      70: ldc           #16                 // String /
      72: invokevirtual #17                 // Method java/lang/String.startsWith:(Ljava/lang/String;)Z
      75: ifeq          87
      78: aload_1
      79: iconst_1
      80: invokevirtual #13                 // Method java/lang/String.substring:(I)Ljava/lang/String;
      83: astore_1
      84: goto          69
      87: aload_1
      88: areturn
}
