Compiled from "LogFactory.java"
public class org.apache.juli.logging.LogFactory {
  private static final org.apache.juli.logging.LogFactory singleton;

  private final java.lang.reflect.Constructor<? extends org.apache.juli.logging.Log> discoveredLogConstructor;

  private org.apache.juli.logging.LogFactory();
    Code:
       0: aload_0
       1: invokespecial #1                  // Method java/lang/Object."<init>":()V
       4: ldc_w         #2                  // class org/apache/juli/logging/Log
       7: invokestatic  #3                  // Method java/util/ServiceLoader.load:(Ljava/lang/Class;)Ljava/util/ServiceLoader;
      10: astore_1
      11: aconst_null
      12: astore_2
      13: aload_1
      14: invokevirtual #4                  // Method java/util/ServiceLoader.iterator:()Ljava/util/Iterator;
      17: astore_3
      18: aload_3
      19: invokeinterface #5,  1            // InterfaceMethod java/util/Iterator.hasNext:()Z
      24: ifeq          76
      27: aload_3
      28: invokeinterface #6,  1            // InterfaceMethod java/util/Iterator.next:()Ljava/lang/Object;
      33: checkcast     #2                  // class org/apache/juli/logging/Log
      36: astore        4
      38: aload         4
      40: invokevirtual #7                  // Method java/lang/Object.getClass:()Ljava/lang/Class;
      43: astore        5
      45: aload         5
      47: iconst_1
      48: anewarray     #8                  // class java/lang/Class
      51: dup
      52: iconst_0
      53: ldc_w         #9                  // class java/lang/String
      56: aastore
      57: invokevirtual #10                 // Method java/lang/Class.getConstructor:([Ljava/lang/Class;)Ljava/lang/reflect/Constructor;
      60: astore_2
      61: goto          76
      64: astore        6
      66: new           #13                 // class java/lang/Error
      69: dup
      70: aload         6
      72: invokespecial #14                 // Method java/lang/Error."<init>":(Ljava/lang/Throwable;)V
      75: athrow
      76: aload_0
      77: aload_2
      78: putfield      #15                 // Field discoveredLogConstructor:Ljava/lang/reflect/Constructor;
      81: return
    Exception table:
       from    to  target type
          45    61    64   Class java/lang/NoSuchMethodException
          45    61    64   Class java/lang/SecurityException

  public org.apache.juli.logging.Log getInstance(java.lang.String) throws org.apache.juli.logging.LogConfigurationException;
    Code:
       0: aload_0
       1: getfield      #15                 // Field discoveredLogConstructor:Ljava/lang/reflect/Constructor;
       4: ifnonnull     12
       7: aload_1
       8: invokestatic  #16                 // Method org/apache/juli/logging/DirectJDKLog.getInstance:(Ljava/lang/String;)Lorg/apache/juli/logging/Log;
      11: areturn
      12: aload_0
      13: getfield      #15                 // Field discoveredLogConstructor:Ljava/lang/reflect/Constructor;
      16: iconst_1
      17: anewarray     #17                 // class java/lang/Object
      20: dup
      21: iconst_0
      22: aload_1
      23: aastore
      24: invokevirtual #18                 // Method java/lang/reflect/Constructor.newInstance:([Ljava/lang/Object;)Ljava/lang/Object;
      27: checkcast     #2                  // class org/apache/juli/logging/Log
      30: areturn
      31: astore_2
      32: new           #23                 // class org/apache/juli/logging/LogConfigurationException
      35: dup
      36: aload_2
      37: invokespecial #24                 // Method org/apache/juli/logging/LogConfigurationException."<init>":(Ljava/lang/Throwable;)V
      40: athrow
    Exception table:
       from    to  target type
          12    30    31   Class java/lang/InstantiationException
          12    30    31   Class java/lang/IllegalAccessException
          12    30    31   Class java/lang/IllegalArgumentException
          12    30    31   Class java/lang/reflect/InvocationTargetException

  public org.apache.juli.logging.Log getInstance(java.lang.Class<?>) throws org.apache.juli.logging.LogConfigurationException;
    Code:
       0: aload_0
       1: aload_1
       2: invokevirtual #25                 // Method java/lang/Class.getName:()Ljava/lang/String;
       5: invokevirtual #26                 // Method getInstance:(Ljava/lang/String;)Lorg/apache/juli/logging/Log;
       8: areturn

  public static org.apache.juli.logging.LogFactory getFactory() throws org.apache.juli.logging.LogConfigurationException;
    Code:
       0: getstatic     #27                 // Field singleton:Lorg/apache/juli/logging/LogFactory;
       3: areturn

  public static org.apache.juli.logging.Log getLog(java.lang.Class<?>) throws org.apache.juli.logging.LogConfigurationException;
    Code:
       0: invokestatic  #28                 // Method getFactory:()Lorg/apache/juli/logging/LogFactory;
       3: aload_0
       4: invokevirtual #29                 // Method getInstance:(Ljava/lang/Class;)Lorg/apache/juli/logging/Log;
       7: areturn

  public static org.apache.juli.logging.Log getLog(java.lang.String) throws org.apache.juli.logging.LogConfigurationException;
    Code:
       0: invokestatic  #28                 // Method getFactory:()Lorg/apache/juli/logging/LogFactory;
       3: aload_0
       4: invokevirtual #26                 // Method getInstance:(Ljava/lang/String;)Lorg/apache/juli/logging/Log;
       7: areturn

  public static void release(java.lang.ClassLoader);
    Code:
       0: invokestatic  #30                 // Method java/util/logging/LogManager.getLogManager:()Ljava/util/logging/LogManager;
       3: invokevirtual #7                  // Method java/lang/Object.getClass:()Ljava/lang/Class;
       6: invokevirtual #25                 // Method java/lang/Class.getName:()Ljava/lang/String;
       9: ldc           #31                 // String java.util.logging.LogManager
      11: invokevirtual #32                 // Method java/lang/String.equals:(Ljava/lang/Object;)Z
      14: ifne          23
      17: invokestatic  #30                 // Method java/util/logging/LogManager.getLogManager:()Ljava/util/logging/LogManager;
      20: invokevirtual #33                 // Method java/util/logging/LogManager.reset:()V
      23: return

  static {};
    Code:
       0: new           #34                 // class org/apache/juli/logging/LogFactory
       3: dup
       4: invokespecial #35                 // Method "<init>":()V
       7: putstatic     #27                 // Field singleton:Lorg/apache/juli/logging/LogFactory;
      10: return
}
