Compiled from "CreateAliasRequest.kt"
public final class aws.sdk.kotlin.services.gamelift.model.CreateAliasRequest$Builder {
  private java.lang.String description;

  private java.lang.String name;

  private aws.sdk.kotlin.services.gamelift.model.RoutingStrategy routingStrategy;

  private java.util.List<aws.sdk.kotlin.services.gamelift.model.Tag> tags;

  public final java.lang.String getDescription();
    Code:
       0: aload_0
       1: getfield      #11                 // Field description:Ljava/lang/String;
       4: areturn

  public final void setDescription(java.lang.String);
    Code:
       0: aload_0
       1: aload_1
       2: putfield      #11                 // Field description:Ljava/lang/String;
       5: return

  public final java.lang.String getName();
    Code:
       0: aload_0
       1: getfield      #20                 // Field name:Ljava/lang/String;
       4: areturn

  public final void setName(java.lang.String);
    Code:
       0: aload_0
       1: aload_1
       2: putfield      #20                 // Field name:Ljava/lang/String;
       5: return

  public final aws.sdk.kotlin.services.gamelift.model.RoutingStrategy getRoutingStrategy();
    Code:
       0: aload_0
       1: getfield      #27                 // Field routingStrategy:Laws/sdk/kotlin/services/gamelift/model/RoutingStrategy;
       4: areturn

  public final void setRoutingStrategy(aws.sdk.kotlin.services.gamelift.model.RoutingStrategy);
    Code:
       0: aload_0
       1: aload_1
       2: putfield      #27                 // Field routingStrategy:Laws/sdk/kotlin/services/gamelift/model/RoutingStrategy;
       5: return

  public final java.util.List<aws.sdk.kotlin.services.gamelift.model.Tag> getTags();
    Code:
       0: aload_0
       1: getfield      #36                 // Field tags:Ljava/util/List;
       4: areturn

  public final void setTags(java.util.List<aws.sdk.kotlin.services.gamelift.model.Tag>);
    Code:
       0: aload_0
       1: aload_1
       2: putfield      #36                 // Field tags:Ljava/util/List;
       5: return

  public aws.sdk.kotlin.services.gamelift.model.CreateAliasRequest$Builder();
    Code:
       0: aload_0
       1: invokespecial #43                 // Method java/lang/Object."<init>":()V
       4: return

  public aws.sdk.kotlin.services.gamelift.model.CreateAliasRequest$Builder(aws.sdk.kotlin.services.gamelift.model.CreateAliasRequest);
    Code:
       0: aload_1
       1: ldc           #48                 // String x
       3: invokestatic  #54                 // Method kotlin/jvm/internal/Intrinsics.checkNotNullParameter:(Ljava/lang/Object;Ljava/lang/String;)V
       6: aload_0
       7: invokespecial #55                 // Method "<init>":()V
      10: aload_0
      11: aload_1
      12: invokevirtual #59                 // Method aws/sdk/kotlin/services/gamelift/model/CreateAliasRequest.getDescription:()Ljava/lang/String;
      15: putfield      #11                 // Field description:Ljava/lang/String;
      18: aload_0
      19: aload_1
      20: invokevirtual #61                 // Method aws/sdk/kotlin/services/gamelift/model/CreateAliasRequest.getName:()Ljava/lang/String;
      23: putfield      #20                 // Field name:Ljava/lang/String;
      26: aload_0
      27: aload_1
      28: invokevirtual #63                 // Method aws/sdk/kotlin/services/gamelift/model/CreateAliasRequest.getRoutingStrategy:()Laws/sdk/kotlin/services/gamelift/model/RoutingStrategy;
      31: putfield      #27                 // Field routingStrategy:Laws/sdk/kotlin/services/gamelift/model/RoutingStrategy;
      34: aload_0
      35: aload_1
      36: invokevirtual #65                 // Method aws/sdk/kotlin/services/gamelift/model/CreateAliasRequest.getTags:()Ljava/util/List;
      39: putfield      #36                 // Field tags:Ljava/util/List;
      42: return

  public final aws.sdk.kotlin.services.gamelift.model.CreateAliasRequest build();
    Code:
       0: new           #57                 // class aws/sdk/kotlin/services/gamelift/model/CreateAliasRequest
       3: dup
       4: aload_0
       5: aconst_null
       6: invokespecial #71                 // Method aws/sdk/kotlin/services/gamelift/model/CreateAliasRequest."<init>":(Laws/sdk/kotlin/services/gamelift/model/CreateAliasRequest$Builder;Lkotlin/jvm/internal/DefaultConstructorMarker;)V
       9: areturn

  public final void routingStrategy(kotlin.jvm.functions.Function1<? super aws.sdk.kotlin.services.gamelift.model.RoutingStrategy$Builder, kotlin.Unit>);
    Code:
       0: aload_1
       1: ldc           #75                 // String block
       3: invokestatic  #54                 // Method kotlin/jvm/internal/Intrinsics.checkNotNullParameter:(Ljava/lang/Object;Ljava/lang/String;)V
       6: aload_0
       7: getstatic     #81                 // Field aws/sdk/kotlin/services/gamelift/model/RoutingStrategy.Companion:Laws/sdk/kotlin/services/gamelift/model/RoutingStrategy$Companion;
      10: aload_1
      11: invokevirtual #87                 // Method aws/sdk/kotlin/services/gamelift/model/RoutingStrategy$Companion.invoke:(Lkotlin/jvm/functions/Function1;)Laws/sdk/kotlin/services/gamelift/model/RoutingStrategy;
      14: putfield      #27                 // Field routingStrategy:Laws/sdk/kotlin/services/gamelift/model/RoutingStrategy;
      17: return
}
