Compiled from "CreateMatchmakingConfigurationResponse.kt"
public final class aws.sdk.kotlin.services.gamelift.model.CreateMatchmakingConfigurationResponse$Builder {
  private aws.sdk.kotlin.services.gamelift.model.MatchmakingConfiguration configuration;

  public final aws.sdk.kotlin.services.gamelift.model.MatchmakingConfiguration getConfiguration();
    Code:
       0: aload_0
       1: getfield      #11                 // Field configuration:Laws/sdk/kotlin/services/gamelift/model/MatchmakingConfiguration;
       4: areturn

  public final void setConfiguration(aws.sdk.kotlin.services.gamelift.model.MatchmakingConfiguration);
    Code:
       0: aload_0
       1: aload_1
       2: putfield      #11                 // Field configuration:Laws/sdk/kotlin/services/gamelift/model/MatchmakingConfiguration;
       5: return

  public aws.sdk.kotlin.services.gamelift.model.CreateMatchmakingConfigurationResponse$Builder();
    Code:
       0: aload_0
       1: invokespecial #20                 // Method java/lang/Object."<init>":()V
       4: return

  public aws.sdk.kotlin.services.gamelift.model.CreateMatchmakingConfigurationResponse$Builder(aws.sdk.kotlin.services.gamelift.model.CreateMatchmakingConfigurationResponse);
    Code:
       0: aload_1
       1: ldc           #25                 // String x
       3: invokestatic  #31                 // Method kotlin/jvm/internal/Intrinsics.checkNotNullParameter:(Ljava/lang/Object;Ljava/lang/String;)V
       6: aload_0
       7: invokespecial #32                 // Method "<init>":()V
      10: aload_0
      11: aload_1
      12: invokevirtual #36                 // Method aws/sdk/kotlin/services/gamelift/model/CreateMatchmakingConfigurationResponse.getConfiguration:()Laws/sdk/kotlin/services/gamelift/model/MatchmakingConfiguration;
      15: putfield      #11                 // Field configuration:Laws/sdk/kotlin/services/gamelift/model/MatchmakingConfiguration;
      18: return

  public final aws.sdk.kotlin.services.gamelift.model.CreateMatchmakingConfigurationResponse build();
    Code:
       0: new           #34                 // class aws/sdk/kotlin/services/gamelift/model/CreateMatchmakingConfigurationResponse
       3: dup
       4: aload_0
       5: aconst_null
       6: invokespecial #42                 // Method aws/sdk/kotlin/services/gamelift/model/CreateMatchmakingConfigurationResponse."<init>":(Laws/sdk/kotlin/services/gamelift/model/CreateMatchmakingConfigurationResponse$Builder;Lkotlin/jvm/internal/DefaultConstructorMarker;)V
       9: areturn

  public final void configuration(kotlin.jvm.functions.Function1<? super aws.sdk.kotlin.services.gamelift.model.MatchmakingConfiguration$Builder, kotlin.Unit>);
    Code:
       0: aload_1
       1: ldc           #46                 // String block
       3: invokestatic  #31                 // Method kotlin/jvm/internal/Intrinsics.checkNotNullParameter:(Ljava/lang/Object;Ljava/lang/String;)V
       6: aload_0
       7: getstatic     #52                 // Field aws/sdk/kotlin/services/gamelift/model/MatchmakingConfiguration.Companion:Laws/sdk/kotlin/services/gamelift/model/MatchmakingConfiguration$Companion;
      10: aload_1
      11: invokevirtual #58                 // Method aws/sdk/kotlin/services/gamelift/model/MatchmakingConfiguration$Companion.invoke:(Lkotlin/jvm/functions/Function1;)Laws/sdk/kotlin/services/gamelift/model/MatchmakingConfiguration;
      14: putfield      #11                 // Field configuration:Laws/sdk/kotlin/services/gamelift/model/MatchmakingConfiguration;
      17: return
}
