Compiled from "DescribeAliasResponse.kt"
public final class aws.sdk.kotlin.services.gamelift.model.DescribeAliasResponse$Builder {
  private aws.sdk.kotlin.services.gamelift.model.Alias alias;

  public final aws.sdk.kotlin.services.gamelift.model.Alias getAlias();
    Code:
       0: aload_0
       1: getfield      #11                 // Field alias:Laws/sdk/kotlin/services/gamelift/model/Alias;
       4: areturn

  public final void setAlias(aws.sdk.kotlin.services.gamelift.model.Alias);
    Code:
       0: aload_0
       1: aload_1
       2: putfield      #11                 // Field alias:Laws/sdk/kotlin/services/gamelift/model/Alias;
       5: return

  public aws.sdk.kotlin.services.gamelift.model.DescribeAliasResponse$Builder();
    Code:
       0: aload_0
       1: invokespecial #20                 // Method java/lang/Object."<init>":()V
       4: return

  public aws.sdk.kotlin.services.gamelift.model.DescribeAliasResponse$Builder(aws.sdk.kotlin.services.gamelift.model.DescribeAliasResponse);
    Code:
       0: aload_1
       1: ldc           #25                 // String x
       3: invokestatic  #31                 // Method kotlin/jvm/internal/Intrinsics.checkNotNullParameter:(Ljava/lang/Object;Ljava/lang/String;)V
       6: aload_0
       7: invokespecial #32                 // Method "<init>":()V
      10: aload_0
      11: aload_1
      12: invokevirtual #36                 // Method aws/sdk/kotlin/services/gamelift/model/DescribeAliasResponse.getAlias:()Laws/sdk/kotlin/services/gamelift/model/Alias;
      15: putfield      #11                 // Field alias:Laws/sdk/kotlin/services/gamelift/model/Alias;
      18: return

  public final aws.sdk.kotlin.services.gamelift.model.DescribeAliasResponse build();
    Code:
       0: new           #34                 // class aws/sdk/kotlin/services/gamelift/model/DescribeAliasResponse
       3: dup
       4: aload_0
       5: aconst_null
       6: invokespecial #42                 // Method aws/sdk/kotlin/services/gamelift/model/DescribeAliasResponse."<init>":(Laws/sdk/kotlin/services/gamelift/model/DescribeAliasResponse$Builder;Lkotlin/jvm/internal/DefaultConstructorMarker;)V
       9: areturn

  public final void alias(kotlin.jvm.functions.Function1<? super aws.sdk.kotlin.services.gamelift.model.Alias$Builder, kotlin.Unit>);
    Code:
       0: aload_1
       1: ldc           #46                 // String block
       3: invokestatic  #31                 // Method kotlin/jvm/internal/Intrinsics.checkNotNullParameter:(Ljava/lang/Object;Ljava/lang/String;)V
       6: aload_0
       7: getstatic     #52                 // Field aws/sdk/kotlin/services/gamelift/model/Alias.Companion:Laws/sdk/kotlin/services/gamelift/model/Alias$Companion;
      10: aload_1
      11: invokevirtual #58                 // Method aws/sdk/kotlin/services/gamelift/model/Alias$Companion.invoke:(Lkotlin/jvm/functions/Function1;)Laws/sdk/kotlin/services/gamelift/model/Alias;
      14: putfield      #11                 // Field alias:Laws/sdk/kotlin/services/gamelift/model/Alias;
      17: return
}
