Compiled from "ListFleetsRequest.kt"
public final class aws.sdk.kotlin.services.gamelift.model.ListFleetsRequest$Builder {
  private java.lang.String buildId;

  private java.lang.Integer limit;

  private java.lang.String nextToken;

  private java.lang.String scriptId;

  public final java.lang.String getBuildId();
    Code:
       0: aload_0
       1: getfield      #11                 // Field buildId:Ljava/lang/String;
       4: areturn

  public final void setBuildId(java.lang.String);
    Code:
       0: aload_0
       1: aload_1
       2: putfield      #11                 // Field buildId:Ljava/lang/String;
       5: return

  public final java.lang.Integer getLimit();
    Code:
       0: aload_0
       1: getfield      #22                 // Field limit:Ljava/lang/Integer;
       4: areturn

  public final void setLimit(java.lang.Integer);
    Code:
       0: aload_0
       1: aload_1
       2: putfield      #22                 // Field limit:Ljava/lang/Integer;
       5: return

  public final java.lang.String getNextToken();
    Code:
       0: aload_0
       1: getfield      #28                 // Field nextToken:Ljava/lang/String;
       4: areturn

  public final void setNextToken(java.lang.String);
    Code:
       0: aload_0
       1: aload_1
       2: putfield      #28                 // Field nextToken:Ljava/lang/String;
       5: return

  public final java.lang.String getScriptId();
    Code:
       0: aload_0
       1: getfield      #33                 // Field scriptId:Ljava/lang/String;
       4: areturn

  public final void setScriptId(java.lang.String);
    Code:
       0: aload_0
       1: aload_1
       2: putfield      #33                 // Field scriptId:Ljava/lang/String;
       5: return

  public aws.sdk.kotlin.services.gamelift.model.ListFleetsRequest$Builder();
    Code:
       0: aload_0
       1: invokespecial #38                 // Method java/lang/Object."<init>":()V
       4: return

  public aws.sdk.kotlin.services.gamelift.model.ListFleetsRequest$Builder(aws.sdk.kotlin.services.gamelift.model.ListFleetsRequest);
    Code:
       0: aload_1
       1: ldc           #43                 // String x
       3: invokestatic  #49                 // Method kotlin/jvm/internal/Intrinsics.checkNotNullParameter:(Ljava/lang/Object;Ljava/lang/String;)V
       6: aload_0
       7: invokespecial #50                 // Method "<init>":()V
      10: aload_0
      11: aload_1
      12: invokevirtual #54                 // Method aws/sdk/kotlin/services/gamelift/model/ListFleetsRequest.getBuildId:()Ljava/lang/String;
      15: putfield      #11                 // Field buildId:Ljava/lang/String;
      18: aload_0
      19: aload_1
      20: invokevirtual #56                 // Method aws/sdk/kotlin/services/gamelift/model/ListFleetsRequest.getLimit:()Ljava/lang/Integer;
      23: putfield      #22                 // Field limit:Ljava/lang/Integer;
      26: aload_0
      27: aload_1
      28: invokevirtual #58                 // Method aws/sdk/kotlin/services/gamelift/model/ListFleetsRequest.getNextToken:()Ljava/lang/String;
      31: putfield      #28                 // Field nextToken:Ljava/lang/String;
      34: aload_0
      35: aload_1
      36: invokevirtual #60                 // Method aws/sdk/kotlin/services/gamelift/model/ListFleetsRequest.getScriptId:()Ljava/lang/String;
      39: putfield      #33                 // Field scriptId:Ljava/lang/String;
      42: return

  public final aws.sdk.kotlin.services.gamelift.model.ListFleetsRequest build();
    Code:
       0: new           #52                 // class aws/sdk/kotlin/services/gamelift/model/ListFleetsRequest
       3: dup
       4: aload_0
       5: aconst_null
       6: invokespecial #66                 // Method aws/sdk/kotlin/services/gamelift/model/ListFleetsRequest."<init>":(Laws/sdk/kotlin/services/gamelift/model/ListFleetsRequest$Builder;Lkotlin/jvm/internal/DefaultConstructorMarker;)V
       9: areturn
}
