Compiled from "S3Location.kt"
public final class aws.sdk.kotlin.services.gamelift.model.S3Location$Builder {
  private java.lang.String bucket;

  private java.lang.String key;

  private java.lang.String objectVersion;

  private java.lang.String roleArn;

  public final java.lang.String getBucket();
    Code:
       0: aload_0
       1: getfield      #11                 // Field bucket:Ljava/lang/String;
       4: areturn

  public final void setBucket(java.lang.String);
    Code:
       0: aload_0
       1: aload_1
       2: putfield      #11                 // Field bucket:Ljava/lang/String;
       5: return

  public final java.lang.String getKey();
    Code:
       0: aload_0
       1: getfield      #20                 // Field key:Ljava/lang/String;
       4: areturn

  public final void setKey(java.lang.String);
    Code:
       0: aload_0
       1: aload_1
       2: putfield      #20                 // Field key:Ljava/lang/String;
       5: return

  public final java.lang.String getObjectVersion();
    Code:
       0: aload_0
       1: getfield      #25                 // Field objectVersion:Ljava/lang/String;
       4: areturn

  public final void setObjectVersion(java.lang.String);
    Code:
       0: aload_0
       1: aload_1
       2: putfield      #25                 // Field objectVersion:Ljava/lang/String;
       5: return

  public final java.lang.String getRoleArn();
    Code:
       0: aload_0
       1: getfield      #30                 // Field roleArn:Ljava/lang/String;
       4: areturn

  public final void setRoleArn(java.lang.String);
    Code:
       0: aload_0
       1: aload_1
       2: putfield      #30                 // Field roleArn:Ljava/lang/String;
       5: return

  public aws.sdk.kotlin.services.gamelift.model.S3Location$Builder();
    Code:
       0: aload_0
       1: invokespecial #35                 // Method java/lang/Object."<init>":()V
       4: return

  public aws.sdk.kotlin.services.gamelift.model.S3Location$Builder(aws.sdk.kotlin.services.gamelift.model.S3Location);
    Code:
       0: aload_1
       1: ldc           #40                 // String x
       3: invokestatic  #46                 // Method kotlin/jvm/internal/Intrinsics.checkNotNullParameter:(Ljava/lang/Object;Ljava/lang/String;)V
       6: aload_0
       7: invokespecial #47                 // Method "<init>":()V
      10: aload_0
      11: aload_1
      12: invokevirtual #51                 // Method aws/sdk/kotlin/services/gamelift/model/S3Location.getBucket:()Ljava/lang/String;
      15: putfield      #11                 // Field bucket:Ljava/lang/String;
      18: aload_0
      19: aload_1
      20: invokevirtual #53                 // Method aws/sdk/kotlin/services/gamelift/model/S3Location.getKey:()Ljava/lang/String;
      23: putfield      #20                 // Field key:Ljava/lang/String;
      26: aload_0
      27: aload_1
      28: invokevirtual #55                 // Method aws/sdk/kotlin/services/gamelift/model/S3Location.getObjectVersion:()Ljava/lang/String;
      31: putfield      #25                 // Field objectVersion:Ljava/lang/String;
      34: aload_0
      35: aload_1
      36: invokevirtual #57                 // Method aws/sdk/kotlin/services/gamelift/model/S3Location.getRoleArn:()Ljava/lang/String;
      39: putfield      #30                 // Field roleArn:Ljava/lang/String;
      42: return

  public final aws.sdk.kotlin.services.gamelift.model.S3Location build();
    Code:
       0: new           #49                 // class aws/sdk/kotlin/services/gamelift/model/S3Location
       3: dup
       4: aload_0
       5: aconst_null
       6: invokespecial #63                 // Method aws/sdk/kotlin/services/gamelift/model/S3Location."<init>":(Laws/sdk/kotlin/services/gamelift/model/S3Location$Builder;Lkotlin/jvm/internal/DefaultConstructorMarker;)V
       9: areturn
}
