Compiled from "SuspendGameServerGroupRequest.kt"
public final class aws.sdk.kotlin.services.gamelift.model.SuspendGameServerGroupRequest$Builder {
  private java.lang.String gameServerGroupName;

  private java.util.List<? extends aws.sdk.kotlin.services.gamelift.model.GameServerGroupAction> suspendActions;

  public final java.lang.String getGameServerGroupName();
    Code:
       0: aload_0
       1: getfield      #11                 // Field gameServerGroupName:Ljava/lang/String;
       4: areturn

  public final void setGameServerGroupName(java.lang.String);
    Code:
       0: aload_0
       1: aload_1
       2: putfield      #11                 // Field gameServerGroupName:Ljava/lang/String;
       5: return

  public final java.util.List<aws.sdk.kotlin.services.gamelift.model.GameServerGroupAction> getSuspendActions();
    Code:
       0: aload_0
       1: getfield      #23                 // Field suspendActions:Ljava/util/List;
       4: areturn

  public final void setSuspendActions(java.util.List<? extends aws.sdk.kotlin.services.gamelift.model.GameServerGroupAction>);
    Code:
       0: aload_0
       1: aload_1
       2: putfield      #23                 // Field suspendActions:Ljava/util/List;
       5: return

  public aws.sdk.kotlin.services.gamelift.model.SuspendGameServerGroupRequest$Builder();
    Code:
       0: aload_0
       1: invokespecial #30                 // Method java/lang/Object."<init>":()V
       4: return

  public aws.sdk.kotlin.services.gamelift.model.SuspendGameServerGroupRequest$Builder(aws.sdk.kotlin.services.gamelift.model.SuspendGameServerGroupRequest);
    Code:
       0: aload_1
       1: ldc           #35                 // String x
       3: invokestatic  #41                 // Method kotlin/jvm/internal/Intrinsics.checkNotNullParameter:(Ljava/lang/Object;Ljava/lang/String;)V
       6: aload_0
       7: invokespecial #42                 // Method "<init>":()V
      10: aload_0
      11: aload_1
      12: invokevirtual #46                 // Method aws/sdk/kotlin/services/gamelift/model/SuspendGameServerGroupRequest.getGameServerGroupName:()Ljava/lang/String;
      15: putfield      #11                 // Field gameServerGroupName:Ljava/lang/String;
      18: aload_0
      19: aload_1
      20: invokevirtual #48                 // Method aws/sdk/kotlin/services/gamelift/model/SuspendGameServerGroupRequest.getSuspendActions:()Ljava/util/List;
      23: putfield      #23                 // Field suspendActions:Ljava/util/List;
      26: return

  public final aws.sdk.kotlin.services.gamelift.model.SuspendGameServerGroupRequest build();
    Code:
       0: new           #44                 // class aws/sdk/kotlin/services/gamelift/model/SuspendGameServerGroupRequest
       3: dup
       4: aload_0
       5: aconst_null
       6: invokespecial #54                 // Method aws/sdk/kotlin/services/gamelift/model/SuspendGameServerGroupRequest."<init>":(Laws/sdk/kotlin/services/gamelift/model/SuspendGameServerGroupRequest$Builder;Lkotlin/jvm/internal/DefaultConstructorMarker;)V
       9: areturn
}
