Compiled from "UpdateFleetPortSettingsRequest.kt"
public final class aws.sdk.kotlin.services.gamelift.model.UpdateFleetPortSettingsRequest$Builder {
  private java.lang.String fleetId;

  private java.util.List<aws.sdk.kotlin.services.gamelift.model.IpPermission> inboundPermissionAuthorizations;

  private java.util.List<aws.sdk.kotlin.services.gamelift.model.IpPermission> inboundPermissionRevocations;

  public final java.lang.String getFleetId();
    Code:
       0: aload_0
       1: getfield      #11                 // Field fleetId:Ljava/lang/String;
       4: areturn

  public final void setFleetId(java.lang.String);
    Code:
       0: aload_0
       1: aload_1
       2: putfield      #11                 // Field fleetId:Ljava/lang/String;
       5: return

  public final java.util.List<aws.sdk.kotlin.services.gamelift.model.IpPermission> getInboundPermissionAuthorizations();
    Code:
       0: aload_0
       1: getfield      #23                 // Field inboundPermissionAuthorizations:Ljava/util/List;
       4: areturn

  public final void setInboundPermissionAuthorizations(java.util.List<aws.sdk.kotlin.services.gamelift.model.IpPermission>);
    Code:
       0: aload_0
       1: aload_1
       2: putfield      #23                 // Field inboundPermissionAuthorizations:Ljava/util/List;
       5: return

  public final java.util.List<aws.sdk.kotlin.services.gamelift.model.IpPermission> getInboundPermissionRevocations();
    Code:
       0: aload_0
       1: getfield      #30                 // Field inboundPermissionRevocations:Ljava/util/List;
       4: areturn

  public final void setInboundPermissionRevocations(java.util.List<aws.sdk.kotlin.services.gamelift.model.IpPermission>);
    Code:
       0: aload_0
       1: aload_1
       2: putfield      #30                 // Field inboundPermissionRevocations:Ljava/util/List;
       5: return

  public aws.sdk.kotlin.services.gamelift.model.UpdateFleetPortSettingsRequest$Builder();
    Code:
       0: aload_0
       1: invokespecial #35                 // Method java/lang/Object."<init>":()V
       4: return

  public aws.sdk.kotlin.services.gamelift.model.UpdateFleetPortSettingsRequest$Builder(aws.sdk.kotlin.services.gamelift.model.UpdateFleetPortSettingsRequest);
    Code:
       0: aload_1
       1: ldc           #40                 // String x
       3: invokestatic  #46                 // Method kotlin/jvm/internal/Intrinsics.checkNotNullParameter:(Ljava/lang/Object;Ljava/lang/String;)V
       6: aload_0
       7: invokespecial #47                 // Method "<init>":()V
      10: aload_0
      11: aload_1
      12: invokevirtual #51                 // Method aws/sdk/kotlin/services/gamelift/model/UpdateFleetPortSettingsRequest.getFleetId:()Ljava/lang/String;
      15: putfield      #11                 // Field fleetId:Ljava/lang/String;
      18: aload_0
      19: aload_1
      20: invokevirtual #53                 // Method aws/sdk/kotlin/services/gamelift/model/UpdateFleetPortSettingsRequest.getInboundPermissionAuthorizations:()Ljava/util/List;
      23: putfield      #23                 // Field inboundPermissionAuthorizations:Ljava/util/List;
      26: aload_0
      27: aload_1
      28: invokevirtual #55                 // Method aws/sdk/kotlin/services/gamelift/model/UpdateFleetPortSettingsRequest.getInboundPermissionRevocations:()Ljava/util/List;
      31: putfield      #30                 // Field inboundPermissionRevocations:Ljava/util/List;
      34: return

  public final aws.sdk.kotlin.services.gamelift.model.UpdateFleetPortSettingsRequest build();
    Code:
       0: new           #49                 // class aws/sdk/kotlin/services/gamelift/model/UpdateFleetPortSettingsRequest
       3: dup
       4: aload_0
       5: aconst_null
       6: invokespecial #61                 // Method aws/sdk/kotlin/services/gamelift/model/UpdateFleetPortSettingsRequest."<init>":(Laws/sdk/kotlin/services/gamelift/model/UpdateFleetPortSettingsRequest$Builder;Lkotlin/jvm/internal/DefaultConstructorMarker;)V
       9: areturn
}
