Compiled from "FileConsumer.java"
public interface org.wildfly.swarm.config.undertow.configuration.FileConsumer<T extends org.wildfly.swarm.config.undertow.configuration.File<T>> {
  public abstract void accept(T);

  public default org.wildfly.swarm.config.undertow.configuration.FileConsumer<T> andThen(org.wildfly.swarm.config.undertow.configuration.FileConsumer<T>);
    Code:
       0: aload_0
       1: aload_1
       2: invokedynamic #1,  0              // InvokeDynamic #0:accept:(Lorg/wildfly/swarm/config/undertow/configuration/FileConsumer;Lorg/wildfly/swarm/config/undertow/configuration/FileConsumer;)Lorg/wildfly/swarm/config/undertow/configuration/FileConsumer;
       7: areturn

  private void lambda$andThen$27(org.wildfly.swarm.config.undertow.configuration.FileConsumer, org.wildfly.swarm.config.undertow.configuration.File);
    Code:
       0: aload_0
       1: aload_2
       2: invokeinterface #2,  2            // InterfaceMethod accept:(Lorg/wildfly/swarm/config/undertow/configuration/File;)V
       7: aload_1
       8: aload_2
       9: invokeinterface #2,  2            // InterfaceMethod accept:(Lorg/wildfly/swarm/config/undertow/configuration/File;)V
      14: return
}
