Compiled from "ModClusterConsumer.java"
public interface org.wildfly.swarm.config.undertow.configuration.ModClusterConsumer<T extends org.wildfly.swarm.config.undertow.configuration.ModCluster<T>> {
  public abstract void accept(T);

  public default org.wildfly.swarm.config.undertow.configuration.ModClusterConsumer<T> andThen(org.wildfly.swarm.config.undertow.configuration.ModClusterConsumer<T>);
    Code:
       0: aload_0
       1: aload_1
       2: invokedynamic #1,  0              // InvokeDynamic #0:accept:(Lorg/wildfly/swarm/config/undertow/configuration/ModClusterConsumer;Lorg/wildfly/swarm/config/undertow/configuration/ModClusterConsumer;)Lorg/wildfly/swarm/config/undertow/configuration/ModClusterConsumer;
       7: areturn

  private void lambda$andThen$330(org.wildfly.swarm.config.undertow.configuration.ModClusterConsumer, org.wildfly.swarm.config.undertow.configuration.ModCluster);
    Code:
       0: aload_0
       1: aload_2
       2: invokeinterface #2,  2            // InterfaceMethod accept:(Lorg/wildfly/swarm/config/undertow/configuration/ModCluster;)V
       7: aload_1
       8: aload_2
       9: invokeinterface #2,  2            // InterfaceMethod accept:(Lorg/wildfly/swarm/config/undertow/configuration/ModCluster;)V
      14: return
}
