Compiled from "YearFormatter.java"
class org.springframework.format.datetime.standard.YearFormatter implements org.springframework.format.Formatter<java.time.Year> {
  org.springframework.format.datetime.standard.YearFormatter();
    Code:
       0: aload_0
       1: invokespecial #1                  // Method java/lang/Object."<init>":()V
       4: return

  public java.time.Year parse(java.lang.String, java.util.Locale) throws java.text.ParseException;
    Code:
       0: aload_1
       1: invokestatic  #2                  // Method java/time/Year.parse:(Ljava/lang/CharSequence;)Ljava/time/Year;
       4: areturn

  public java.lang.String print(java.time.Year, java.util.Locale);
    Code:
       0: aload_1
       1: invokevirtual #3                  // Method java/time/Year.toString:()Ljava/lang/String;
       4: areturn

  public java.lang.String print(java.lang.Object, java.util.Locale);
    Code:
       0: aload_0
       1: aload_1
       2: checkcast     #4                  // class java/time/Year
       5: aload_2
       6: invokevirtual #5                  // Method print:(Ljava/time/Year;Ljava/util/Locale;)Ljava/lang/String;
       9: areturn

  public java.lang.Object parse(java.lang.String, java.util.Locale) throws java.text.ParseException;
    Code:
       0: aload_0
       1: aload_1
       2: aload_2
       3: invokevirtual #6                  // Method parse:(Ljava/lang/String;Ljava/util/Locale;)Ljava/time/Year;
       6: areturn
}
