Compiled from "CommandLine.java"
class org.apache.logging.log4j.core.tools.picocli.CommandLine$BuiltIn$ISO8601DateConverter implements org.apache.logging.log4j.core.tools.picocli.CommandLine$ITypeConverter<java.util.Date> {
  org.apache.logging.log4j.core.tools.picocli.CommandLine$BuiltIn$ISO8601DateConverter();
    Code:
       0: aload_0
       1: invokespecial #1                  // Method java/lang/Object."<init>":()V
       4: return

  public java.util.Date convert(java.lang.String);
    Code:
       0: new           #2                  // class java/text/SimpleDateFormat
       3: dup
       4: ldc           #3                  // String yyyy-MM-dd
       6: invokespecial #4                  // Method java/text/SimpleDateFormat."<init>":(Ljava/lang/String;)V
       9: aload_1
      10: invokevirtual #5                  // Method java/text/SimpleDateFormat.parse:(Ljava/lang/String;)Ljava/util/Date;
      13: areturn
      14: astore_2
      15: new           #7                  // class org/apache/logging/log4j/core/tools/picocli/CommandLine$TypeConversionException
      18: dup
      19: new           #8                  // class java/lang/StringBuilder
      22: dup
      23: invokespecial #9                  // Method java/lang/StringBuilder."<init>":()V
      26: ldc           #10                 // String \'
      28: invokevirtual #11                 // Method java/lang/StringBuilder.append:(Ljava/lang/String;)Ljava/lang/StringBuilder;
      31: aload_1
      32: invokevirtual #11                 // Method java/lang/StringBuilder.append:(Ljava/lang/String;)Ljava/lang/StringBuilder;
      35: ldc           #12                 // String \' is not a yyyy-MM-dd date
      37: invokevirtual #11                 // Method java/lang/StringBuilder.append:(Ljava/lang/String;)Ljava/lang/StringBuilder;
      40: invokevirtual #13                 // Method java/lang/StringBuilder.toString:()Ljava/lang/String;
      43: invokespecial #14                 // Method org/apache/logging/log4j/core/tools/picocli/CommandLine$TypeConversionException."<init>":(Ljava/lang/String;)V
      46: athrow
    Exception table:
       from    to  target type
           0    13    14   Class java/text/ParseException

  public java.lang.Object convert(java.lang.String) throws java.lang.Exception;
    Code:
       0: aload_0
       1: aload_1
       2: invokevirtual #15                 // Method convert:(Ljava/lang/String;)Ljava/util/Date;
       5: areturn
}
