Compiled from "Interceptors.java"
public final class io.etcd.jetcd.support.Interceptors {
  private io.etcd.jetcd.support.Interceptors();
    Code:
       0: aload_0
       1: invokespecial #1                  // Method java/lang/Object."<init>":()V
       4: return

  public static io.grpc.ClientInterceptor intercept(java.util.function.BiConsumer<io.grpc.ClientCall$Listener<?>, io.grpc.Metadata>);
    Code:
       0: new           #2                  // class io/etcd/jetcd/support/Interceptors$1
       3: dup
       4: aload_0
       5: invokespecial #3                  // Method io/etcd/jetcd/support/Interceptors$1."<init>":(Ljava/util/function/BiConsumer;)V
       8: areturn
}
